{
  "type": "Feature",
  "properties": {
    "iso:country":"US",
    "sg:address":"648 N 120 W",
    "sg:city":"Lehi",
    "sg:classifiers":[
        {
            "category":"Building & Trades",
            "subcategory":"Landscaping Services",
            "type":"Services"
        }
    ],
    "sg:phone":"+1 801 768 8140",
    "sg:postcode":"84043",
    "sg:province":"UT",
    "sg:tags":[
        "landscape",
        "contractor"
    ],
    "wof:name":"B & H Curbing",
    "wof:placetype":"venue"
},
  "geometry": {"coordinates":[-111.850994,40.395148],"type":"Point"}
}