{
  "type": "Feature",
  "properties": {
    "iso:country":"US",
    "sg:address":"47 E 200 N",
    "sg:city":"St George",
    "sg:classifiers":[
        {
            "category":"Arts & Performance",
            "subcategory":"Theater",
            "type":"Entertainment"
        }
    ],
    "sg:phone":"+1 435 634 5942",
    "sg:postcode":"84770",
    "sg:province":"UT",
    "sg:tags":[
        "theatrical",
        "executive"
    ],
    "wof:name":"Saint Gorge Pionr Ctr For Arts",
    "wof:placetype":"venue"
},
  "geometry": {"coordinates":[-113.58228,37.111659],"type":"Point"}
}