{
  "type": "Feature",
  "properties": {
    "iso:country":"US",
    "sg:address":"299 US Hwy 6",
    "sg:city":"Delta",
    "sg:classifiers":[
        {
            "category":"Shopping",
            "subcategory":"Bicycles & Sporting Goods",
            "type":"Retail Goods"
        }
    ],
    "sg:phone":"+1 435 864 3432",
    "sg:postcode":"84624",
    "sg:province":"UT",
    "sg:tags":[
        "motorcycle"
    ],
    "wof:name":"Delta Sports Kawasaki",
    "wof:placetype":"venue"
},
  "geometry": {"coordinates":[-112.56799599999999,39.352309],"type":"Point"}
}