{
  "type": "Feature",
  "properties": {
    "iso:country":"US",
    "sg:address":"7911 S 2250 E",
    "sg:city":"Ogden",
    "sg:classifiers":[
        {
            "category":"Retail",
            "subcategory":"Repair Shop",
            "type":"Services"
        }
    ],
    "sg:phone":"+1 801 479 8447",
    "sg:postcode":"84405",
    "sg:province":"UT",
    "wof:name":"Coops Golf Enterprises",
    "wof:placetype":"venue"
},
  "geometry": {"coordinates":[-111.92119599999999,41.123308],"type":"Point"}
}