{
  "type": "Feature",
  "properties": {
    "iso:country":"US",
    "sg:address":"707 W 700 S Ste 201",
    "sg:city":"Woods Cross",
    "sg:classifiers":[
        {
            "category":"Communications",
            "type":"Services"
        }
    ],
    "sg:phone":"+1 801 294 6400",
    "sg:postcode":"84087",
    "sg:province":"UT",
    "sg:tags":[
        "web",
        "design"
    ],
    "sg:website":"www.i4solutions.com",
    "wof:name":"I 4 Solutions",
    "wof:placetype":"venue"
},
  "geometry": {"coordinates":[-111.900053,40.882397],"type":"Point"}
}