{
  "type": "Feature",
  "properties": {
    "iso:country":"US",
    "sg:address":"296 S 750 W",
    "sg:city":"Vernal",
    "sg:classifiers":[
        {
            "category":"Freight",
            "type":"Transportation"
        }
    ],
    "sg:phone":"+1 435 789 1510",
    "sg:postcode":"84078",
    "sg:province":"UT",
    "sg:tags":[
        "trucking"
    ],
    "wof:name":"Shane Holmes Trucking",
    "wof:placetype":"venue"
},
  "geometry": {"coordinates":[-109.542384,40.450778],"type":"Point"}
}