{
  "type": "Feature",
  "properties": {
    "iso:country":"US",
    "sg:address":"8080 S Beaumont Dr",
    "sg:city":"Sandy",
    "sg:classifiers":[
        {
            "category":"Restaurant",
            "type":"Food & Drink"
        }
    ],
    "sg:phone":"+1 801 942 7850",
    "sg:postcode":"84093",
    "sg:province":"UT",
    "sg:tags":[
        "eating"
    ],
    "wof:name":"Pie Pizzeria Midvale Inc",
    "wof:placetype":"venue"
},
  "geometry": {"coordinates":[-111.841888,40.60373],"type":"Point"}
}