{
  "type": "Feature",
  "properties": {
    "iso:country":"US",
    "sg:address":"2829 Crestview Dr",
    "sg:city":"Salt Lake City",
    "sg:classifiers":[
        {
            "category":"Social Services",
            "subcategory":"Child Care",
            "type":"Services"
        }
    ],
    "sg:phone":"+1 801 583 8224",
    "sg:postcode":"84108",
    "sg:province":"UT",
    "sg:tags":[
        "day"
    ],
    "wof:name":"Wee Enterprises",
    "wof:placetype":"venue"
},
  "geometry": {"coordinates":[-111.80906400000001,40.746249],"type":"Point"}
}