{
  "type": "Feature",
  "properties": {
    "iso:country":"US",
    "sg:address":"2250 W 800 S",
    "sg:city":"Vernal",
    "sg:classifiers":[
        {
            "category":"Autos & Motor Vehicles",
            "subcategory":"Automobile Sales",
            "type":"Retail Goods"
        }
    ],
    "sg:phone":"+1 435 789 6656",
    "sg:postcode":"84078",
    "sg:province":"UT",
    "sg:tags":[
        "snowmobile"
    ],
    "wof:name":"Greg's Speed Shop",
    "wof:placetype":"venue"
},
  "geometry": {"coordinates":[-109.56930800000001,40.443457],"type":"Point"}
}