{
  "type": "Feature",
  "properties": {
    "iso:country":"US",
    "sg:address":"428 Topez Blvd",
    "sg:city":"Delta",
    "sg:classifiers":[
        {
            "category":"Personal",
            "subcategory":"Beauty Salon",
            "type":"Services"
        }
    ],
    "sg:phone":"+1 435 864 5998",
    "sg:postcode":"84624",
    "sg:province":"UT",
    "sg:tags":[
        "shop"
    ],
    "wof:name":"Plaza Shears",
    "wof:placetype":"venue"
},
  "geometry": {"coordinates":[-112.563182,39.354731],"type":"Point"}
}