{
  "type": "Feature",
  "properties": {
    "iso:country":"US",
    "sg:address":"2140 E Keller Ln",
    "sg:city":"Salt Lake City",
    "sg:classifiers":[
        {
            "category":"Building & Trades",
            "subcategory":"Construction",
            "type":"Services"
        }
    ],
    "sg:phone":"+1 801 266 2042",
    "sg:postcode":"84109",
    "sg:province":"UT",
    "sg:tags":[
        "line",
        "installation",
        "telephone"
    ],
    "wof:name":"Mc Gee Laraine Construction Co",
    "wof:placetype":"venue"
},
  "geometry": {"coordinates":[-111.833102,40.694267],"type":"Point"}
}