{
  "type": "Feature",
  "properties": {
    "iso:country":"US",
    "sg:address":"2766 E 3300 S",
    "sg:city":"Salt Lake City",
    "sg:classifiers":[
        {
            "category":"Social Services",
            "subcategory":"Adult Care",
            "type":"Services"
        }
    ],
    "sg:phone":"+1 801 467 5437",
    "sg:postcode":"84109",
    "sg:province":"UT",
    "sg:tags":[
        "foster"
    ],
    "wof:name":"Millcreek Child & Family Svc",
    "wof:placetype":"venue"
},
  "geometry": {"coordinates":[-111.81452299999999,40.699781],"type":"Point"}
}