{
  "type": "Feature",
  "properties": {
    "iso:country":"US",
    "sg:address":"2011 E 800 N",
    "sg:city":"St George",
    "sg:classifiers":[
        {
            "category":"Organizations",
            "subcategory":"Religious Organization",
            "type":"Services"
        }
    ],
    "sg:phone":"+1 435 986 0277",
    "sg:postcode":"84770",
    "sg:province":"UT",
    "wof:name":"Lighthouse - A Jesus Name Chu",
    "wof:placetype":"venue"
},
  "geometry": {"coordinates":[-113.543111,37.121911],"type":"Point"}
}