{
  "type": "Feature",
  "properties": {
    "iso:country":"US",
    "sg:address":"555 E 5300 S",
    "sg:city":"Ogden",
    "sg:classifiers":[
        {
            "category":"Health Services",
            "subcategory":"Doctor",
            "type":"Services"
        }
    ],
    "sg:phone":"+1 801 399 9693",
    "sg:postcode":"84405",
    "sg:province":"UT",
    "sg:tags":[
        "medical"
    ],
    "wof:name":"Lowell R Daines MD",
    "wof:placetype":"venue"
},
  "geometry": {"coordinates":[-111.966178,41.168861],"type":"Point"}
}