{
  "type": "Feature",
  "properties": {
    "iso:country":"US",
    "sg:address":"194 W 300 N",
    "sg:city":"Manti",
    "sg:classifiers":[
        {
            "category":"Home & Garden",
            "subcategory":"Garden Supply",
            "type":"Retail Goods"
        }
    ],
    "sg:phone":"+1 435 835 0401",
    "sg:postcode":"84642",
    "sg:province":"UT",
    "sg:tags":[
        "bulb",
        "seed"
    ],
    "wof:name":"Maughan Seed Co",
    "wof:placetype":"venue"
},
  "geometry": {"coordinates":[-111.63993499999999,39.269864],"type":"Point"}
}