{
  "type": "Feature",
  "properties": {
    "iso:country":"US",
    "sg:address":"3354 Brett Ave",
    "sg:city":"Salt Lake City",
    "sg:classifiers":[
        {
            "category":"Building & Trades",
            "subcategory":"Construction",
            "type":"Services"
        }
    ],
    "sg:phone":"+1 801 964 2370",
    "sg:postcode":"84119",
    "sg:province":"UT",
    "sg:tags":[
        "contractor"
    ],
    "wof:name":"New Age Plastering Inc",
    "wof:placetype":"venue"
},
  "geometry": {"coordinates":[-111.97152199999999,40.686162],"type":"Point"}
}