{
  "type": "Feature",
  "properties": {
    "iso:country":"US",
    "sg:address":"73 S Main St",
    "sg:city":"Smithfield",
    "sg:classifiers":[
        {
            "category":"Health Services",
            "subcategory":"Doctor",
            "type":"Services"
        }
    ],
    "sg:phone":"+1 435 563 3025",
    "sg:postcode":"84335",
    "sg:province":"UT",
    "sg:tags":[
        "dentist"
    ],
    "wof:name":"Smithfield Dental Care",
    "wof:placetype":"venue"
},
  "geometry": {"coordinates":[-111.83280000000001,41.835019],"type":"Point"}
}