{
  "type": "Feature",
  "properties": {
    "iso:country":"US",
    "sg:address":"631 W North Temple",
    "sg:city":"Salt Lake City",
    "sg:classifiers":[
        {
            "category":"Real Estate",
            "subcategory":"Real Estate Operator",
            "type":"Services"
        }
    ],
    "sg:phone":"+1 801 521 0640",
    "sg:postcode":"84116",
    "sg:province":"UT",
    "sg:tags":[
        "apartment"
    ],
    "wof:name":"City Front Apartments",
    "wof:placetype":"venue"
},
  "geometry": {"coordinates":[-111.909452,40.771465],"type":"Point"}
}