{
  "type": "Feature",
  "properties": {
    "iso:country":"US",
    "sg:address":"7035 S 400 W",
    "sg:city":"Midvale",
    "sg:classifiers":[
        {
            "category":"Manufacturing",
            "subcategory":"Paper Products",
            "type":"Manufacturing & Wholesale Goods"
        }
    ],
    "sg:phone":"+1 801 561 3517",
    "sg:postcode":"84047",
    "sg:province":"UT",
    "sg:tags":[
        "mfg"
    ],
    "wof:name":"Custom Design Label Mfg Inc",
    "wof:placetype":"venue"
},
  "geometry": {"coordinates":[-111.90158599999999,40.622955],"type":"Point"}
}