{
  "type": "Feature",
  "properties": {
    "iso:country":"US",
    "sg:address":"353 E 200 S",
    "sg:city":"Salt Lake City",
    "sg:classifiers":[
        {
            "category":"Professional",
            "subcategory":"Business Services",
            "type":"Services"
        }
    ],
    "sg:phone":"+1 801 364 7225",
    "sg:postcode":"84111",
    "sg:province":"UT",
    "sg:tags":[
        "packaging",
        "shipping",
        "custom"
    ],
    "wof:name":"Handle With Care Packaging Str",
    "wof:placetype":"venue"
},
  "geometry": {"coordinates":[-111.879698,40.765079],"type":"Point"}
}