{
  "type": "Feature",
  "properties": {
    "iso:country":"US",
    "sg:address":"858 S 3760 W",
    "sg:city":"Salt Lake City",
    "sg:classifiers":[
        {
            "category":"Freight",
            "type":"Transportation"
        }
    ],
    "sg:phone":"+1 801 954 0709",
    "sg:postcode":"84104",
    "sg:province":"UT",
    "sg:tags":[
        "trucking"
    ],
    "wof:name":"Con-Way Western Express",
    "wof:placetype":"venue"
},
  "geometry": {"coordinates":[-111.981315,40.750168],"type":"Point"}
}