{
  "type": "Feature",
  "properties": {
    "iso:country":"US",
    "sg:address":"5095 W 2100 S",
    "sg:city":"Salt Lake City",
    "sg:classifiers":[
        {
            "category":"Professional",
            "subcategory":"Detective & Security Services",
            "type":"Services"
        }
    ],
    "sg:phone":"+1 801 478 0652",
    "sg:postcode":"84120",
    "sg:province":"UT",
    "sg:tags":[
        "guard",
        "patrol"
    ],
    "wof:name":"Secure Alert",
    "wof:placetype":"venue"
},
  "geometry": {"coordinates":[-112.012636,40.72586],"type":"Point"}
}