{
  "type": "Feature",
  "properties": {
    "iso:country":"US",
    "sg:address":"3221 S Highway 89",
    "sg:city":"Bountiful",
    "sg:classifiers":[
        {
            "category":"Arts & Performance",
            "subcategory":"Arts Center",
            "type":"Entertainment"
        },
        {
            "category":"Education",
            "subcategory":"School",
            "type":"Public Place"
        }
    ],
    "sg:phone":"+1 801 992 3699",
    "sg:postcode":"84010",
    "sg:province":"UT",
    "sg:tags":[
        "performing"
    ],
    "wof:name":"Accent School of Dance",
    "wof:placetype":"venue"
},
  "geometry": {"coordinates":[-111.901838,40.854294],"type":"Point"}
}