{
  "type": "Feature",
  "properties": {
    "iso:country":"US",
    "sg:address":"554 W 40 S",
    "sg:city":"Lindon",
    "sg:classifiers":[
        {
            "category":"Shopping",
            "subcategory":"Computers & Home Electronics",
            "type":"Retail Goods"
        }
    ],
    "sg:phone":"+1 801 785 7034",
    "sg:postcode":"84042",
    "sg:province":"UT",
    "sg:tags":[
        "dish",
        "satellite",
        "install"
    ],
    "wof:name":"Perfect Dish Satellite",
    "wof:placetype":"venue"
},
  "geometry": {"coordinates":[-111.72824900000001,40.337653],"type":"Point"}
}