{
  "type": "Feature",
  "properties": {
    "iso:country":"US",
    "sg:address":"15216 Mountainside Dr",
    "sg:city":"Riverton",
    "sg:classifiers":[
        {
            "category":"Retail",
            "subcategory":"Repair Shop",
            "type":"Services"
        }
    ],
    "sg:phone":"+1 801 576 9817",
    "sg:postcode":"84065",
    "sg:province":"UT",
    "sg:tags":[
        "related"
    ],
    "wof:name":"Sorenson Brick Cleaning",
    "wof:placetype":"venue"
},
  "geometry": {"coordinates":[-111.950227,40.477139],"type":"Point"}
}