{
  "type": "Feature",
  "properties": {
    "iso:country":"US",
    "sg:address":"350 E 300 N",
    "sg:city":"American Fork",
    "sg:classifiers":[
        {
            "category":"Health Services",
            "subcategory":"Nursing And Care Facility",
            "type":"Services"
        }
    ],
    "sg:phone":"+1 801 756 5293",
    "sg:postcode":"84003",
    "sg:province":"UT",
    "sg:tags":[
        "skilled"
    ],
    "wof:name":"Heritage Convalescent Cntr",
    "wof:placetype":"venue"
},
  "geometry": {"coordinates":[-111.788071,40.382985],"type":"Point"}
}