{
  "type": "Feature",
  "properties": {
    "iso:country":"US",
    "sg:address":"9298 S 500 W",
    "sg:city":"Sandy",
    "sg:classifiers":[
        {
            "category":"Wholesale",
            "subcategory":"Durable Goods & Equipment",
            "type":"Manufacturing & Wholesale Goods"
        }
    ],
    "sg:phone":"+1 801 255 1991",
    "sg:postcode":"84070",
    "sg:province":"UT",
    "sg:tags":[
        "record",
        "book",
        "tape"
    ],
    "wof:name":"Sounds of Zion Inc",
    "wof:placetype":"venue"
},
  "geometry": {"coordinates":[-111.90553,40.586299],"type":"Point"}
}