{
  "type": "Feature",
  "properties": {
    "iso:country":"US",
    "sg:address":"375 S Carbon Ave",
    "sg:city":"Price",
    "sg:classifiers":[
        {
            "category":"Professional",
            "subcategory":"Engineering",
            "type":"Services"
        }
    ],
    "sg:phone":"+1 435 636 8269",
    "sg:postcode":"84501",
    "sg:province":"UT",
    "sg:tags":[
        "engineer"
    ],
    "wof:name":"Hansen Allen & Luce Consulting",
    "wof:placetype":"venue"
},
  "geometry": {"coordinates":[-110.811143,39.594032],"type":"Point"}
}