{
  "type": "Feature",
  "properties": {
    "iso:country":"US",
    "sg:address":"1093 S Main St",
    "sg:city":"Cedar City",
    "sg:classifiers":[
        {
            "category":"Retail",
            "subcategory":"Auto Repair",
            "type":"Services"
        }
    ],
    "sg:phone":"+1 435 867 1812",
    "sg:postcode":"84720",
    "sg:province":"UT",
    "sg:tags":[
        "general"
    ],
    "wof:name":"Above All Auto Repair",
    "wof:placetype":"venue"
},
  "geometry": {"coordinates":[-113.076466,37.656493],"type":"Point"}
}