{
  "type": "Feature",
  "properties": {
    "iso:country":"US",
    "sg:address":"5682 S Redwood Rd",
    "sg:city":"Salt Lake City",
    "sg:classifiers":[
        {
            "category":"Restaurant",
            "type":"Food & Drink"
        }
    ],
    "sg:menulink":"http://www.allmenus.com/ut/salt-lake-city/218164-burger-king/menu/",
    "sg:phone":"+1 801 966 7600",
    "sg:postcode":"84123",
    "sg:province":"UT",
    "sg:tags":[
        "american"
    ],
    "wof:name":"Burger King",
    "wof:placetype":"venue"
},
  "geometry": {"coordinates":[-111.939198,40.647566],"type":"Point"}
}