{
  "type": "Feature",
  "properties": {
    "iso:country":"US",
    "sg:address":"1255 Iron Horse Dr",
    "sg:city":"Park City",
    "sg:classifiers":[
        {
            "category":"Recreation",
            "type":"Entertainment"
        }
    ],
    "sg:phone":"+1 435 658 3483",
    "sg:postcode":"84060",
    "sg:province":"UT",
    "sg:tags":[
        "diving",
        "instruction"
    ],
    "wof:name":"Summit Dive Masters",
    "wof:placetype":"venue"
},
  "geometry": {"coordinates":[-111.505073,40.658552],"type":"Point"}
}