{
  "type": "Feature",
  "properties": {
    "iso:country":"US",
    "sg:address":"637 E 500 S",
    "sg:city":"Salt Lake City",
    "sg:classifiers":[
        {
            "category":"Recreation",
            "type":"Entertainment"
        }
    ],
    "sg:phone":"+1 801 328 9848",
    "sg:postcode":"84102",
    "sg:province":"UT",
    "wof:name":"Sego Gallery",
    "wof:placetype":"venue"
},
  "geometry": {"coordinates":[-111.873682,40.758561],"type":"Point"}
}