{
  "type": "Feature",
  "properties": {
    "iso:country":"US",
    "sg:address":"5277 Havenwood Ln",
    "sg:city":"Salt Lake City",
    "sg:classifiers":[
        {
            "category":"Shopping",
            "subcategory":"Used Merchandise",
            "type":"Retail Goods"
        }
    ],
    "sg:phone":"+1 801 277 1925",
    "sg:postcode":"84117",
    "sg:province":"UT",
    "wof:name":"Something Special",
    "wof:placetype":"venue"
},
  "geometry": {"coordinates":[-111.81856999999999,40.655103],"type":"Point"}
}