{
  "type": "Feature",
  "properties": {
    "iso:country":"US",
    "sg:address":"11132 S 200 W",
    "sg:city":"Salem",
    "sg:classifiers":[
        {
            "category":"Organizations",
            "subcategory":"Labor Organization",
            "type":"Services"
        }
    ],
    "sg:phone":"+1 801 423 2170",
    "sg:postcode":"84653",
    "sg:province":"UT",
    "wof:name":"Love Holdings Lc",
    "wof:placetype":"venue"
},
  "geometry": {"coordinates":[-111.658635,40.027481],"type":"Point"}
}