{
  "type": "Feature",
  "properties": {
    "iso:country":"US",
    "sg:address":"1754 S 1430 E C",
    "sg:city":"St George",
    "sg:classifiers":[
        {
            "category":"Personal",
            "subcategory":"Barber",
            "type":"Services"
        }
    ],
    "sg:phone":"+1 435 652 4594",
    "sg:postcode":"84790",
    "sg:province":"UT",
    "sg:tags":[
        "shop"
    ],
    "wof:name":"Razor Technologies Inc",
    "wof:placetype":"venue"
},
  "geometry": {"coordinates":[-113.55318800000001,37.078522],"type":"Point"}
}