{
  "type": "Feature",
  "properties": {
    "iso:country":"US",
    "sg:address":"145 Zion Park Blvd",
    "sg:city":"Springdale",
    "sg:classifiers":[
        {
            "category":"Restaurant",
            "type":"Food & Drink"
        }
    ],
    "sg:phone":"+1 435 772 0510",
    "sg:postcode":"84763",
    "sg:province":"UT",
    "wof:name":"Thai Sapa",
    "wof:placetype":"venue"
},
  "geometry": {"coordinates":[-113.04843200000001,37.160833],"type":"Point"}
}