{
  "type": "Feature",
  "properties": {
    "iso:country":"US",
    "sg:address":"226 W 9210 S",
    "sg:city":"Sandy",
    "sg:classifiers":[
        {
            "category":"Wholesale",
            "subcategory":"Metals & Minerals",
            "type":"Manufacturing & Wholesale Goods"
        }
    ],
    "sg:phone":"+1 801 566 3552",
    "sg:postcode":"84070",
    "sg:province":"UT",
    "wof:name":"Wasatch West Siding Distrs",
    "wof:placetype":"venue"
},
  "geometry": {"coordinates":[-111.897723,40.584146],"type":"Point"}
}