{
  "type": "Feature",
  "properties": {
    "iso:country":"US",
    "sg:address":"1369 Princeton Ave",
    "sg:city":"Salt Lake City",
    "sg:classifiers":[
        {
            "category":"Real Estate",
            "subcategory":"Real Estate Agent",
            "type":"Services"
        }
    ],
    "sg:phone":"+1 801 581 9379",
    "sg:postcode":"84105",
    "sg:province":"UT",
    "wof:name":"Royal Tribe",
    "wof:placetype":"venue"
},
  "geometry": {"coordinates":[-111.85202,40.743119],"type":"Point"}
}