{
  "type": "Feature",
  "properties": {
    "iso:country":"US",
    "sg:address":"3433 W 2400 S",
    "sg:city":"Salt Lake City",
    "sg:classifiers":[
        {
            "category":"Airline",
            "type":"Transportation"
        }
    ],
    "sg:phone":"+1 800 463 3339",
    "sg:postcode":"84119",
    "sg:province":"UT",
    "sg:tags":[
        "air",
        "courier",
        "ground"
    ],
    "wof:name":"Fedex",
    "wof:placetype":"venue"
},
  "geometry": {"coordinates":[-111.972329,40.718524],"type":"Point"}
}