{
  "type": "Feature",
  "properties": {
    "iso:country":"US",
    "sg:address":"3983 Wasatch Blvd",
    "sg:city":"Holladay",
    "sg:classifiers":[
        {
            "category":"Banks & Credit Unions",
            "subcategory":"Bank",
            "type":"Services"
        }
    ],
    "sg:phone":"+1 801 272 4438",
    "sg:postcode":"84124",
    "sg:province":"UT",
    "sg:tags":[
        "federal",
        "savings",
        "assoc",
        "loan",
        "association"
    ],
    "wof:name":"Washington Federal Savings",
    "wof:placetype":"venue"
},
  "geometry": {"coordinates":[-111.795914,40.685832],"type":"Point"}
}