{
  "type": "Feature",
  "properties": {
    "iso:country":"US",
    "sg:address":"872 E 900 S",
    "sg:city":"Salt Lake City",
    "sg:classifiers":[
        {
            "category":"Shopping",
            "subcategory":"Hobbies, Toys, & Games",
            "type":"Retail Goods"
        }
    ],
    "sg:phone":"+1 801 521 6026",
    "sg:postcode":"84105",
    "sg:province":"UT",
    "sg:tags":[
        "shop",
        "rock"
    ],
    "wof:name":"Vug Rocks & Gems",
    "wof:placetype":"venue"
},
  "geometry": {"coordinates":[-111.865995,40.749713],"type":"Point"}
}