{
  "type": "Feature",
  "properties": {
    "iso:country":"US",
    "sg:address":"965 Murray Holladay Rd",
    "sg:city":"Salt Lake City",
    "sg:classifiers":[
        {
            "category":"Insurance",
            "subcategory":"Insurance Agent",
            "type":"Services"
        }
    ],
    "sg:phone":"+1 801 262 9002",
    "sg:postcode":"84117",
    "sg:province":"UT",
    "wof:name":"Insurance Marketing Svc",
    "wof:placetype":"venue"
},
  "geometry": {"coordinates":[-111.862441,40.665785],"type":"Point"}
}