{
  "type": "Feature",
  "properties": {
    "iso:country":"US",
    "sg:address":"515 W 500 S",
    "sg:city":"Bountiful",
    "sg:classifiers":[
        {
            "category":"Banks & Credit Unions",
            "subcategory":"Bank",
            "type":"Services"
        }
    ],
    "sg:phone":"+1 801 294 8828",
    "sg:postcode":"84010",
    "sg:province":"UT",
    "sg:tags":[
        "loan"
    ],
    "wof:name":"American General Finance Inc",
    "wof:placetype":"venue"
},
  "geometry": {"coordinates":[-111.892661,40.884161],"type":"Point"}
}