{
  "type": "Feature",
  "properties": {
    "iso:country":"US",
    "sg:address":"6310 W 13900 S",
    "sg:city":"Riverton",
    "sg:classifiers":[
        {
            "category":"Professional",
            "subcategory":"Business Services",
            "type":"Services"
        }
    ],
    "sg:phone":"+1 801 302 1165",
    "sg:postcode":"84096",
    "sg:province":"UT",
    "wof:name":"Utah First Financial",
    "wof:placetype":"venue"
},
  "geometry": {"coordinates":[-112.041901,40.49875],"type":"Point"}
}