{
  "type": "Feature",
  "properties": {
    "iso:country":"US",
    "sg:address":"140 N 50 W",
    "sg:city":"North Salt Lake",
    "sg:classifiers":[
        {
            "category":"Shopping",
            "subcategory":"Optical Goods",
            "type":"Retail Goods"
        }
    ],
    "sg:phone":"+1 801 292 0479",
    "sg:postcode":"84054",
    "sg:province":"UT",
    "wof:name":"Standard Optical Company",
    "wof:placetype":"venue"
},
  "geometry": {"coordinates":[-111.91284,40.845532],"type":"Point"}
}