{
  "type": "Feature",
  "properties": {
    "iso:country":"US",
    "sg:address":"49 E Mutton Hollow Rd",
    "sg:city":"Kaysville",
    "sg:classifiers":[
        {
            "category":"Social Services",
            "subcategory":"Child Care",
            "type":"Services"
        }
    ],
    "sg:phone":"+1 801 544 1058",
    "sg:postcode":"84037",
    "sg:province":"UT",
    "sg:tags":[
        "day"
    ],
    "wof:name":"Forever Young Preschool",
    "wof:placetype":"venue"
},
  "geometry": {"coordinates":[-111.93941700000001,41.052916],"type":"Point"}
}