{
  "type": "Feature",
  "properties": {
    "iso:country":"US",
    "sg:address":"139 N 2050 E",
    "sg:city":"Layton",
    "sg:classifiers":[
        {
            "category":"Manufacturing",
            "subcategory":"Motor Vehicles & Parts",
            "type":"Manufacturing & Wholesale Goods"
        }
    ],
    "sg:phone":"+1 801 543 2599",
    "sg:postcode":"84040",
    "sg:province":"UT",
    "sg:tags":[
        "vintage",
        "mfg",
        "automobile",
        "panel"
    ],
    "wof:name":"Dream Factory Fabrication Inc",
    "wof:placetype":"venue"
},
  "geometry": {"coordinates":[-111.92747300000001,41.061847],"type":"Point"}
}