{
  "type": "Feature",
  "properties": {
    "iso:country":"US",
    "sg:address":"1665 E Sagewood Rd",
    "sg:city":"Price",
    "sg:classifiers":[
        {
            "category":"Real Estate",
            "subcategory":"Surveying",
            "type":"Services"
        }
    ],
    "sg:phone":"+1 435 637 5748",
    "sg:postcode":"84501",
    "sg:province":"UT",
    "wof:name":"Hansen Evan",
    "wof:placetype":"venue"
},
  "geometry": {"coordinates":[-110.786292,39.61037],"type":"Point"}
}