{
  "type": "Feature",
  "properties": {
    "iso:country":"US",
    "sg:address":"115 E 100 S",
    "sg:city":"Laketown",
    "sg:classifiers":[
        {
            "category":"Organizations",
            "subcategory":"Religious Organization",
            "type":"Services"
        }
    ],
    "sg:phone":"+1 435 946 3262",
    "sg:postcode":"84038",
    "sg:province":"UT",
    "sg:tags":[
        "mormon",
        "church"
    ],
    "wof:name":"Laketown Ward",
    "wof:placetype":"venue"
},
  "geometry": {"coordinates":[-111.319292,41.823446],"type":"Point"}
}