{
  "type": "Feature",
  "properties": {
    "iso:country":"US",
    "sg:address":"358 E 300 S",
    "sg:city":"Ephraim",
    "sg:classifiers":[
        {
            "category":"Social Services",
            "type":"Services"
        }
    ],
    "sg:phone":"+1 435 283 4389",
    "sg:postcode":"84627",
    "sg:province":"UT",
    "wof:name":"Unlimited Potential",
    "wof:placetype":"venue"
},
  "geometry": {"coordinates":[-111.578282,39.354389],"type":"Point"}
}