{
  "type": "Feature",
  "properties": {
    "iso:country":"US",
    "sg:address":"2478 E Barcelona Dr",
    "sg:city":"Sandy",
    "sg:classifiers":[
        {
            "category":"Professional",
            "subcategory":"Management & Consulting",
            "type":"Services"
        }
    ],
    "sg:phone":"+1 801 942 1823",
    "sg:postcode":"84093",
    "sg:province":"UT",
    "sg:tags":[
        "business"
    ],
    "wof:name":"Abba Consulting LLC",
    "wof:placetype":"venue"
},
  "geometry": {"coordinates":[-111.820622,40.598092],"type":"Point"}
}