{
  "type": "Feature",
  "properties": {
    "iso:country":"US",
    "sg:address":"2427 Woodland Dr",
    "sg:city":"Ogden",
    "sg:classifiers":[
        {
            "category":"Real Estate",
            "subcategory":"Real Estate Agent",
            "type":"Services"
        }
    ],
    "sg:phone":"+1 801 476 8027",
    "sg:postcode":"84403",
    "sg:province":"UT",
    "sg:tags":[
        "personal"
    ],
    "wof:name":"Franklin Institute Est Pl",
    "wof:placetype":"venue"
},
  "geometry": {"coordinates":[-111.91926599999999,41.161109],"type":"Point"}
}