{
  "type": "Feature",
  "properties": {
    "iso:country":"US",
    "sg:address":"8613 S Vaquero Dr",
    "sg:city":"Sandy",
    "sg:classifiers":[
        {
            "category":"Building & Trades",
            "subcategory":"Electrical",
            "type":"Services"
        }
    ],
    "sg:phone":"+1 801 565 0897",
    "sg:postcode":"84094",
    "sg:province":"UT",
    "sg:tags":[
        "electrical",
        "contractor"
    ],
    "wof:name":"Rocky Mountain Elec Contrs I",
    "wof:placetype":"venue"
},
  "geometry": {"coordinates":[-111.864093,40.592608],"type":"Point"}
}