{
  "type": "Feature",
  "properties": {
    "iso:country":"US",
    "sg:address":"1560 Summer Crest Dr",
    "sg:city":"Lehi",
    "sg:classifiers":[
        {
            "category":"Professional",
            "subcategory":"Business Services",
            "type":"Services"
        }
    ],
    "sg:phone":"+1 801 768 0603",
    "sg:postcode":"84043",
    "sg:province":"UT",
    "wof:name":"Easy Auction Services Inc",
    "wof:placetype":"venue"
},
  "geometry": {"coordinates":[-111.837025,40.40573],"type":"Point"}
}