{
  "type": "Feature",
  "properties": {
    "iso:country":"US",
    "sg:address":"283 E State Rd",
    "sg:city":"Pleasant Grove",
    "sg:classifiers":[
        {
            "category":"Health Services",
            "subcategory":"Doctor",
            "type":"Services"
        }
    ],
    "sg:phone":"+1 801 785 9521",
    "sg:postcode":"84062",
    "sg:province":"UT",
    "sg:tags":[
        "dentist"
    ],
    "wof:name":"Steven L Skanchy DDS",
    "wof:placetype":"venue"
},
  "geometry": {"coordinates":[-111.737359,40.357127],"type":"Point"}
}