{
  "type": "Feature",
  "properties": {
    "iso:country":"US",
    "sg:address":"6973 High Tech Dr",
    "sg:city":"Midvale",
    "sg:classifiers":[
        {
            "category":"Manufacturing",
            "subcategory":"Tools & Machinery",
            "type":"Manufacturing & Wholesale Goods"
        }
    ],
    "sg:phone":"+1 801 352 5100",
    "sg:postcode":"84047",
    "sg:province":"UT",
    "sg:tags":[
        "turbine"
    ],
    "wof:name":"Solar Turbines Inc",
    "wof:placetype":"venue"
},
  "geometry": {"coordinates":[-111.89651499999999,40.625518],"type":"Point"}
}