{
  "type": "Feature",
  "properties": {
    "iso:country":"US",
    "sg:address":"5009 W Woodburne Rd",
    "sg:city":"West Jordan",
    "sg:classifiers":[
        {
            "category":"Education",
            "subcategory":"Dance Studio",
            "type":"Public Place"
        }
    ],
    "sg:phone":"+1 801 260 1483",
    "sg:postcode":"84084",
    "sg:province":"UT",
    "wof:name":"Maximum Dance",
    "wof:placetype":"venue"
},
  "geometry": {"coordinates":[-112.00998,40.613132],"type":"Point"}
}