{
  "type": "Feature",
  "properties": {
    "iso:country":"US",
    "sg:address":"5184 W Rendezvous Rd",
    "sg:city":"Morgan",
    "sg:classifiers":[
        {
            "category":"Shopping",
            "subcategory":"Stationery & Office Supplies",
            "type":"Retail Goods"
        }
    ],
    "sg:phone":"+1 801 876 7802",
    "sg:postcode":"84050",
    "sg:province":"UT",
    "wof:name":"Sunshine Label Company",
    "wof:placetype":"venue"
},
  "geometry": {"coordinates":[-111.802353,41.158871],"type":"Point"}
}