{
  "type": "Feature",
  "properties": {
    "iso:country":"US",
    "sg:address":"7139 S 3080 E",
    "sg:city":"Salt Lake City",
    "sg:classifiers":[
        {
            "category":"Social Services",
            "subcategory":"Child Care",
            "type":"Services"
        }
    ],
    "sg:phone":"+1 801 943 5429",
    "sg:postcode":"84121",
    "sg:province":"UT",
    "sg:tags":[
        "day"
    ],
    "wof:name":"Gerdas Day Care",
    "wof:placetype":"venue"
},
  "geometry": {"coordinates":[-111.806102,40.621918],"type":"Point"}
}