{
  "type": "Feature",
  "properties": {
    "iso:country":"US",
    "sg:address":"486 Main St",
    "sg:city":"Greenville",
    "sg:classifiers":[
        {
            "category":"Organizations",
            "subcategory":"Religious Organization",
            "type":"Services"
        }
    ],
    "sg:phone":"+1 435 438 5524",
    "sg:postcode":"84731",
    "sg:province":"UT",
    "sg:tags":[
        "church"
    ],
    "wof:name":"Church Of Jesus Christ Of Lds",
    "wof:placetype":"venue"
},
  "geometry": {"coordinates":[-112.793581,38.258192],"type":"Point"}
}