{
  "type": "Feature",
  "properties": {
    "iso:country":"US",
    "sg:address":"435 N Main St",
    "sg:city":"Moab",
    "sg:classifiers":[
        {
            "category":"Food & Beverages",
            "subcategory":"Groceries & Convenience Stores",
            "type":"Retail Goods"
        },
        {
            "category":"Autos & Motor Vehicles",
            "subcategory":"Fuel & Gas Station",
            "type":"Retail Goods"
        }
    ],
    "sg:phone":"+1 435 259 8718",
    "sg:postcode":"84532",
    "sg:province":"UT",
    "sg:tags":[
        "gasoline"
    ],
    "wof:name":"Maverik Country Stores 238",
    "wof:placetype":"venue"
},
  "geometry": {"coordinates":[-109.55202300000001,38.581411],"type":"Point"}
}