{
  "type": "Feature",
  "properties": {
    "iso:country":"US",
    "sg:address":"1160 N 1000 W",
    "sg:city":"Tremonton",
    "sg:classifiers":[
        {
            "category":"Shopping",
            "subcategory":"Clothing, Apparel, & Fashions",
            "type":"Retail Goods"
        }
    ],
    "sg:phone":"+1 435 257 1652",
    "sg:postcode":"84337",
    "sg:province":"UT",
    "sg:tags":[
        "spec",
        "mfg"
    ],
    "wof:name":"Redeye Classic Design",
    "wof:placetype":"venue"
},
  "geometry": {"coordinates":[-112.181524,41.732681],"type":"Point"}
}