{
  "type": "Feature",
  "properties": {
    "iso:country":"US",
    "sg:address":"3015 Sweetgum Way",
    "sg:city":"St George",
    "sg:classifiers":[
        {
            "category":"Building & Trades",
            "subcategory":"Construction",
            "type":"Services"
        }
    ],
    "sg:phone":"+1 435 673 8981",
    "sg:postcode":"84790",
    "sg:province":"UT",
    "sg:tags":[
        "contractor"
    ],
    "wof:name":"Sola-Tube",
    "wof:placetype":"venue"
},
  "geometry": {"coordinates":[-113.55135900000001,37.058538],"type":"Point"}
}