{
  "type": "Feature",
  "properties": {
    "iso:country":"US",
    "sg:address":"399 W 1200 N",
    "sg:city":"Orem",
    "sg:classifiers":[
        {
            "category":"Manufacturing",
            "subcategory":"Signs",
            "type":"Manufacturing & Wholesale Goods"
        }
    ],
    "sg:phone":"+1 801 426 6533",
    "sg:postcode":"84057",
    "sg:province":"UT",
    "wof:name":"Summit Graphic & Design",
    "wof:placetype":"venue"
},
  "geometry": {"coordinates":[-111.70260500000001,40.319247],"type":"Point"}
}