{
  "type": "Feature",
  "properties": {
    "iso:country":"US",
    "sg:address":"610 E Saint George Blvd",
    "sg:city":"Saint George",
    "sg:classifiers":[
        {
            "category":"Restaurant",
            "type":"Food & Drink"
        }
    ],
    "sg:menulink":"http://www.allmenus.com/ut/st-george/205501-taco-bell/menu/",
    "sg:phone":"+1 435 673 4400",
    "sg:postcode":"84770",
    "sg:province":"UT",
    "sg:tags":[
        "mexican"
    ],
    "wof:name":"Taco Bell",
    "wof:placetype":"venue"
},
  "geometry": {"coordinates":[-113.570286,37.109869],"type":"Point"}
}