{
  "type": "Feature",
  "properties": {
    "iso:country":"US",
    "sg:address":"111 E 200 N",
    "sg:city":"Cedar City",
    "sg:classifiers":[
        {
            "category":"Organizations",
            "subcategory":"Community Association",
            "type":"Services"
        }
    ],
    "sg:phone":"+1 435 586 8332",
    "sg:postcode":"84720",
    "sg:province":"UT",
    "sg:tags":[
        "fraternal"
    ],
    "wof:name":"Elks Lodge",
    "wof:placetype":"venue"
},
  "geometry": {"coordinates":[-113.05928400000001,37.680976],"type":"Point"}
}