{
  "type": "Feature",
  "properties": {
    "iso:country":"US",
    "sg:address":"8576 Top of the World Cir",
    "sg:city":"Salt Lake City",
    "sg:classifiers":[
        {
            "category":"Communications",
            "subcategory":"Film & Video Production",
            "type":"Services"
        }
    ],
    "sg:phone":"+1 801 942 1614",
    "sg:postcode":"84121",
    "sg:province":"UT",
    "sg:tags":[
        "taping"
    ],
    "wof:name":"B G Media",
    "wof:placetype":"venue"
},
  "geometry": {"coordinates":[-111.791932,40.596476],"type":"Point"}
}