{
  "type": "Feature",
  "properties": {
    "iso:country":"US",
    "sg:address":"1662 Rutherford Ridge Rd",
    "sg:city":"Ogden",
    "sg:classifiers":[
        {
            "category":"Real Estate",
            "subcategory":"Real Estate Agent",
            "type":"Services"
        }
    ],
    "sg:phone":"+1 801 479 1219",
    "sg:postcode":"84403",
    "sg:province":"UT",
    "sg:tags":[
        "management"
    ],
    "wof:name":"Fnm & Assoc",
    "wof:placetype":"venue"
},
  "geometry": {"coordinates":[-111.936553,41.176171],"type":"Point"}
}