{
  "type": "Feature",
  "properties": {
    "iso:country":"US",
    "sg:address":"170 West Election Road  Suite 205",
    "sg:city":"Draper",
    "sg:classifiers":[
        {
            "category":"Professional",
            "subcategory":"Computer Services",
            "type":"Services"
        }
    ],
    "sg:phone":"+1 801 858 1000",
    "sg:postcode":"84020",
    "sg:province":"UT",
    "sg:website":"http://www.cogitoinc.com/",
    "wof:name":"Cogito",
    "wof:placetype":"venue"
},
  "geometry": {"coordinates":[-111.901279,40.535033],"type":"Point"}
}