{
  "type": "Feature",
  "properties": {
    "iso:country":"US",
    "sg:address":"35 Skyline Dr",
    "sg:city":"Brigham City",
    "sg:classifiers":[
        {
            "category":"Autos & Motor Vehicles",
            "subcategory":"Automobile Sales",
            "type":"Retail Goods"
        }
    ],
    "sg:phone":"+1 435 723 9596",
    "sg:postcode":"84302",
    "sg:province":"UT",
    "sg:tags":[
        "used"
    ],
    "wof:name":"Golden Spike Motors",
    "wof:placetype":"venue"
},
  "geometry": {"coordinates":[-112.01515999999999,41.485903],"type":"Point"}
}