{
  "type": "Feature",
  "properties": {
    "iso:country":"US",
    "sg:address":"14039 Minuteman Dr",
    "sg:city":"Draper",
    "sg:classifiers":[
        {
            "category":"Freight",
            "type":"Transportation"
        }
    ],
    "sg:phone":"+1 801 619 1999",
    "sg:postcode":"84020",
    "sg:province":"UT",
    "sg:tags":[
        "commercial",
        "storage"
    ],
    "wof:name":"King Arthur Self Storage",
    "wof:placetype":"venue"
},
  "geometry": {"coordinates":[-111.89067300000001,40.492501],"type":"Point"}
}