{
  "type": "Feature",
  "properties": {
    "iso:country":"US",
    "sg:address":"47 Orange St",
    "sg:city":"Salt Lake City",
    "sg:classifiers":[
        {
            "category":"Food & Beverages",
            "subcategory":"Candy",
            "type":"Retail Goods"
        }
    ],
    "sg:phone":"+1 801 466 0330",
    "sg:postcode":"84116",
    "sg:province":"UT",
    "sg:tags":[
        "popcorn",
        "supply"
    ],
    "wof:name":"Mad Popper",
    "wof:placetype":"venue"
},
  "geometry": {"coordinates":[-111.94393700000001,40.770616],"type":"Point"}
}