{
  "type": "Feature",
  "properties": {
    "iso:country":"US",
    "sg:address":"1325 W 5000 S",
    "sg:city":"Salt Lake City",
    "sg:classifiers":[
        {
            "category":"Professional",
            "subcategory":"Computer Services",
            "type":"Services"
        }
    ],
    "sg:phone":"+1 801 266 6666",
    "sg:postcode":"84123",
    "sg:province":"UT",
    "sg:tags":[
        "related"
    ],
    "wof:name":"Awerkamp Consulting Entps LLC",
    "wof:placetype":"venue"
},
  "geometry": {"coordinates":[-111.927831,40.659305],"type":"Point"}
}