{
  "type": "Feature",
  "properties": {
    "iso:country":"US",
    "sg:address":"1168 Raymond Rd",
    "sg:city":"Kaysville",
    "sg:classifiers":[
        {
            "category":"Professional",
            "subcategory":"Computer Services",
            "type":"Services"
        }
    ],
    "sg:phone":"+1 801 546 1923",
    "sg:postcode":"84037",
    "sg:province":"UT",
    "wof:name":"General Automation Inc",
    "wof:placetype":"venue"
},
  "geometry": {"coordinates":[-111.911973,41.035989],"type":"Point"}
}