{
  "type": "Feature",
  "properties": {
    "iso:country":"US",
    "sg:address":"4725 Wallace Ln",
    "sg:city":"Salt Lake City",
    "sg:classifiers":[
        {
            "category":"Real Estate",
            "subcategory":"Real Estate Operator",
            "type":"Services"
        }
    ],
    "sg:phone":"+1 801 278 3393",
    "sg:postcode":"84117",
    "sg:province":"UT",
    "sg:tags":[
        "owner",
        "rental"
    ],
    "wof:name":"Richard Welch",
    "wof:placetype":"venue"
},
  "geometry": {"coordinates":[-111.80710999999999,40.668576],"type":"Point"}
}