{
  "type": "Feature",
  "properties": {
    "iso:country":"US",
    "sg:address":"3336 W 8350 S",
    "sg:city":"West Jordan",
    "sg:classifiers":[
        {
            "category":"Building & Trades",
            "subcategory":"Construction",
            "type":"Services"
        }
    ],
    "sg:phone":"+1 801 256 9835",
    "sg:postcode":"84088",
    "sg:province":"UT",
    "sg:tags":[
        "contractor"
    ],
    "wof:name":"Roberts Brothers Siding",
    "wof:placetype":"venue"
},
  "geometry": {"coordinates":[-111.970952,40.600173],"type":"Point"}
}