{
  "type": "Feature",
  "properties": {
    "iso:country":"US",
    "sg:address":"239 E 800 S",
    "sg:city":"Salt Lake City",
    "sg:classifiers":[
        {
            "category":"Arts & Performance",
            "subcategory":"Theater",
            "type":"Entertainment"
        }
    ],
    "sg:phone":"+1 801 322 3648",
    "sg:postcode":"84111",
    "sg:province":"UT",
    "sg:tags":[
        "talent",
        "agency",
        "casting"
    ],
    "wof:name":"Studio Talent",
    "wof:placetype":"venue"
},
  "geometry": {"coordinates":[-111.885361,40.751954],"type":"Point"}
}