{
  "type": "Feature",
  "properties": {
    "iso:country":"US",
    "sg:address":"1417 W 3300 S",
    "sg:city":"Ogden",
    "sg:classifiers":[
        {
            "category":"Freight",
            "type":"Transportation"
        }
    ],
    "sg:phone":"+1 801 392 2888",
    "sg:postcode":"84401",
    "sg:province":"UT",
    "sg:tags":[
        "commercial",
        "storage"
    ],
    "wof:name":"U-Store-It",
    "wof:placetype":"venue"
},
  "geometry": {"coordinates":[-112.013372,41.205087],"type":"Point"}
}