{
  "type": "Feature",
  "properties": {
    "iso:country":"US",
    "sg:address":"1077 37th St",
    "sg:city":"Ogden",
    "sg:classifiers":[
        {
            "category":"Professional",
            "subcategory":"Business Services",
            "type":"Services"
        }
    ],
    "sg:phone":"+1 801 392 2677",
    "sg:postcode":"84403",
    "sg:province":"UT",
    "sg:tags":[
        "personal"
    ],
    "wof:name":"Pampered Bdy Thraputic Massage",
    "wof:placetype":"venue"
},
  "geometry": {"coordinates":[-111.952939,41.195854],"type":"Point"}
}