{
  "type": "Feature",
  "properties": {
    "iso:country":"US",
    "sg:address":"1290 Sun River Dr",
    "sg:city":"Riverton",
    "sg:classifiers":[
        {
            "category":"Professional",
            "subcategory":"Management & Consulting",
            "type":"Services"
        }
    ],
    "sg:phone":"+1 801 446 4663",
    "sg:postcode":"84065",
    "sg:province":"UT",
    "sg:tags":[
        "business"
    ],
    "wof:name":"Resource Mktg & Consultations",
    "wof:placetype":"venue"
},
  "geometry": {"coordinates":[-111.92772600000001,40.509906],"type":"Point"}
}