{
  "type": "Feature",
  "properties": {
    "iso:country":"US",
    "sg:address":"239 W 9000 S",
    "sg:city":"Sandy",
    "sg:classifiers":[
        {
            "category":"Home & Garden",
            "subcategory":"Furniture",
            "type":"Retail Goods"
        }
    ],
    "sg:phone":"+1 801 566 8400",
    "sg:postcode":"84070",
    "sg:province":"UT",
    "wof:name":"Mattress & Furniture Outlet",
    "wof:placetype":"venue"
},
  "geometry": {"coordinates":[-111.896028,40.588063],"type":"Point"}
}