{
  "type": "Feature",
  "properties": {
    "iso:country":"US",
    "sg:address":"7005 W 9600 N",
    "sg:city":"American Fork",
    "sg:classifiers":[
        {
            "category":"Retail",
            "subcategory":"Repair Shop",
            "type":"Services"
        }
    ],
    "sg:phone":"+1 801 768 8686",
    "sg:postcode":"84003",
    "sg:province":"UT",
    "wof:name":"A-1 Septic Tank Service",
    "wof:placetype":"venue"
},
  "geometry": {"coordinates":[-111.82480700000001,40.406114],"type":"Point"}
}