{
  "type": "Feature",
  "properties": {
    "iso:country":"US",
    "sg:address":"2261 Adams Ave",
    "sg:city":"Ogden",
    "sg:classifiers":[
        {
            "category":"Organizations",
            "subcategory":"Non-profit Organization",
            "type":"Services"
        }
    ],
    "sg:phone":"+1 801 394 9456",
    "sg:postcode":"84401",
    "sg:province":"UT",
    "sg:tags":[
        "charitable",
        "institution"
    ],
    "sg:website":"www.yccogden.org",
    "wof:name":"YCC Your Comm Connection",
    "wof:placetype":"venue"
},
  "geometry": {"coordinates":[-111.967506,41.226898],"type":"Point"}
}