{
  "type": "Feature",
  "properties": {
    "iso:country":"US",
    "sg:address":"160 E 6600 S",
    "sg:city":"Hyrum",
    "sg:classifiers":[
        {
            "category":"Building & Trades",
            "subcategory":"Cleaning & Sanitation",
            "type":"Services"
        }
    ],
    "sg:phone":"+1 435 245 6679",
    "sg:postcode":"84319",
    "sg:province":"UT",
    "sg:tags":[
        "window"
    ],
    "wof:name":"D B's Window Wash",
    "wof:placetype":"venue"
},
  "geometry": {"coordinates":[-111.828793,41.612331],"type":"Point"}
}