{
  "type": "Feature",
  "properties": {
    "iso:country":"US",
    "sg:address":"1145 N 1100 W",
    "sg:city":"St George",
    "sg:classifiers":[
        {
            "category":"Wholesale",
            "subcategory":"Groceries",
            "type":"Manufacturing & Wholesale Goods"
        }
    ],
    "sg:phone":"+1 435 634 0309",
    "sg:postcode":"84770",
    "sg:province":"UT",
    "sg:tags":[
        "food",
        "product",
        "health"
    ],
    "sg:website":"www.tjclark.com",
    "wof:name":"T J Clark & Co",
    "wof:placetype":"venue"
},
  "geometry": {"coordinates":[-113.607214,37.129778],"type":"Point"}
}