{
  "type": "Feature",
  "properties": {
    "iso:country":"US",
    "sg:address":"6965 Union Park Center",
    "sg:city":"Midvale",
    "sg:classifiers":[
        {
            "category":"Banks & Credit Unions",
            "subcategory":"Bank",
            "type":"Services"
        }
    ],
    "sg:phone":"+1 801 568 2886",
    "sg:postcode":"84047",
    "sg:province":"UT",
    "sg:tags":[
        "personal",
        "institution"
    ],
    "wof:name":"Deborah Leaman Cfp",
    "wof:placetype":"venue"
},
  "geometry": {"coordinates":[-111.860339,40.624986],"type":"Point"}
}