{
  "type": "Feature",
  "properties": {
    "iso:country":"US",
    "sg:address":"97 W Center St",
    "sg:city":"Kanab",
    "sg:classifiers":[
        {
            "category":"Restaurant",
            "type":"Food & Drink"
        }
    ],
    "sg:phone":"+1 435 644 8001",
    "sg:postcode":"84741",
    "sg:province":"UT",
    "sg:tags":[
        "eating"
    ],
    "wof:name":"Rocking V Cafe",
    "wof:placetype":"venue"
},
  "geometry": {"coordinates":[-112.52993600000001,37.048042],"type":"Point"}
}