{
  "type": "Feature",
  "properties": {
    "iso:country":"US",
    "sg:address":"4965 S Redwood Rd",
    "sg:city":"Salt Lake City",
    "sg:classifiers":[
        {
            "category":"Retail",
            "subcategory":"Auto Rental",
            "type":"Services"
        }
    ],
    "sg:phone":"+1 801 265 8469",
    "sg:postcode":"84123",
    "sg:province":"UT",
    "sg:tags":[
        "truck"
    ],
    "wof:name":"Ryder",
    "wof:placetype":"venue"
},
  "geometry": {"coordinates":[-111.938756,40.663237],"type":"Point"}
}