{
  "type": "Feature",
  "properties": {
    "iso:country":"US",
    "sg:address":"13268 Akagi Ln",
    "sg:city":"Draper",
    "sg:classifiers":[
        {
            "category":"Manufacturing",
            "subcategory":"Tools & Machinery",
            "type":"Manufacturing & Wholesale Goods"
        }
    ],
    "sg:phone":"+1 801 619 3520",
    "sg:postcode":"84020",
    "sg:province":"UT",
    "sg:tags":[
        "lamp",
        "electric",
        "mfg"
    ],
    "wof:name":"Healthy Wealthy Ways Inc",
    "wof:placetype":"venue"
},
  "geometry": {"coordinates":[-111.847239,40.510228],"type":"Point"}
}