{
  "type": "Feature",
  "properties": {
    "iso:country":"US",
    "sg:address":"390 W 100 S",
    "sg:city":"Heber City",
    "sg:classifiers":[
        {
            "category":"Home & Garden",
            "subcategory":"Building Materials",
            "type":"Retail Goods"
        }
    ],
    "sg:phone":"+1 435 654 4352",
    "sg:postcode":"84032",
    "sg:province":"UT",
    "sg:tags":[
        "windows"
    ],
    "wof:name":"Wasatch Window & Door LLC",
    "wof:placetype":"venue"
},
  "geometry": {"coordinates":[-111.418865,40.506501],"type":"Point"}
}