{
  "type": "Feature",
  "properties": {
    "iso:country":"US",
    "sg:address":"208 E State St",
    "sg:city":"Lehi",
    "sg:classifiers":[
        {
            "category":"Food & Beverages",
            "subcategory":"Groceries & Convenience Stores",
            "type":"Retail Goods"
        }
    ],
    "sg:phone":"+1 801 768 4555",
    "sg:postcode":"84043",
    "sg:province":"UT",
    "wof:name":"D Corner Mart",
    "wof:placetype":"venue"
},
  "geometry": {"coordinates":[-111.84477699999999,40.395838],"type":"Point"}
}