{
  "type": "Feature",
  "properties": {
    "iso:country":"US",
    "sg:address":"1471 Industrial Rd",
    "sg:city":"Salt Lake City",
    "sg:classifiers":[
        {
            "category":"Manufacturing",
            "subcategory":"Paper Products",
            "type":"Manufacturing & Wholesale Goods"
        }
    ],
    "sg:phone":"+1 801 973 0100",
    "sg:postcode":"84104",
    "sg:province":"UT",
    "sg:tags":[
        "corrugated",
        "solid",
        "fiber",
        "box"
    ],
    "sg:website":"www.tharco.com",
    "wof:name":"Tharco",
    "wof:placetype":"venue"
},
  "geometry": {"coordinates":[-111.944682,40.738166],"type":"Point"}
}