{
  "type": "Feature",
  "properties": {
    "iso:country":"US",
    "sg:address":"2575 Bridger Rd",
    "sg:city":"Salt Lake City",
    "sg:classifiers":[
        {
            "category":"Wholesale",
            "subcategory":"Electrical",
            "type":"Manufacturing & Wholesale Goods"
        }
    ],
    "sg:phone":"+1 801 973 4343",
    "sg:postcode":"84104",
    "sg:province":"UT",
    "sg:tags":[
        "household",
        "appliance"
    ],
    "wof:name":"Clark Wholesale Inc",
    "wof:placetype":"venue"
},
  "geometry": {"coordinates":[-111.95337499999999,40.7293],"type":"Point"}
}