{
  "type": "Feature",
  "properties": {
    "iso:country":"US",
    "sg:address":"1070 N 500 E",
    "sg:city":"Pleasant Grove",
    "sg:classifiers":[
        {
            "category":"Building & Trades",
            "subcategory":"Construction",
            "type":"Services"
        }
    ],
    "sg:phone":"+1 801 785 2262",
    "sg:postcode":"84062",
    "sg:province":"UT",
    "sg:tags":[
        "contractor"
    ],
    "wof:name":"Advanced Gutter Systems",
    "wof:placetype":"venue"
},
  "geometry": {"coordinates":[-111.73047800000001,40.374513],"type":"Point"}
}