{
  "type": "Feature",
  "properties": {
    "iso:country":"US",
    "sg:address":"7186 W Gates Ave",
    "sg:city":"Salt Lake City",
    "sg:classifiers":[
        {
            "category":"Manufacturing",
            "subcategory":"Metals",
            "type":"Manufacturing & Wholesale Goods"
        }
    ],
    "sg:phone":"+1 801 250 5919",
    "sg:postcode":"84128",
    "sg:province":"UT",
    "sg:tags":[
        "powdered",
        "titanium",
        "product",
        "primary",
        "mfg"
    ],
    "wof:name":"Micron Metals Inc",
    "wof:placetype":"venue"
},
  "geometry": {"coordinates":[-112.06174900000001,40.716958],"type":"Point"}
}