{
  "type": "Feature",
  "properties": {
    "iso:country":"US",
    "sg:address":"1892 W 800 N",
    "sg:city":"Pleasant Grove",
    "sg:classifiers":[
        {
            "category":"Health Services",
            "subcategory":"Medical Lab",
            "type":"Services"
        }
    ],
    "sg:phone":"+1 801 492 6949",
    "sg:postcode":"84062",
    "sg:province":"UT",
    "sg:tags":[
        "laboratory",
        "research",
        "noncommercial",
        "organization"
    ],
    "wof:name":"Advanced Clncal RES ACR Tri Cy",
    "wof:placetype":"venue"
},
  "geometry": {"coordinates":[-111.766858,40.372271],"type":"Point"}
}