{
  "type": "Feature",
  "properties": {
    "iso:country":"US",
    "sg:address":"263 Red Cliffs Dr",
    "sg:city":"Saint George",
    "sg:classifiers":[
        {
            "category":"Restaurant",
            "type":"Food & Drink"
        }
    ],
    "sg:menulink":"http://www.allmenus.com/ut/st-george/127973-red-lobster/menu/",
    "sg:phone":"+1 435 656 2811",
    "sg:postcode":"84790",
    "sg:province":"UT",
    "sg:tags":[
        "seafood",
        "american"
    ],
    "wof:name":"Red Lobster",
    "wof:placetype":"venue"
},
  "geometry": {"coordinates":[-113.552009,37.115576],"type":"Point"}
}