{
  "type": "Feature",
  "properties": {
    "iso:country":"US",
    "sg:address":"4665 Beechwood Rd",
    "sg:city":"Salt Lake City",
    "sg:classifiers":[
        {
            "category":"Building & Trades",
            "subcategory":"Construction",
            "type":"Services"
        }
    ],
    "sg:phone":"+1 801 264 8841",
    "sg:postcode":"84123",
    "sg:province":"UT",
    "sg:tags":[
        "hanging",
        "contractor"
    ],
    "wof:name":"Knight Painting",
    "wof:placetype":"venue"
},
  "geometry": {"coordinates":[-111.935067,40.667917],"type":"Point"}
}