{
  "type": "Feature",
  "properties": {
    "iso:country":"US",
    "sg:address":"10667 N Castle Pine Way",
    "sg:city":"Highland",
    "sg:classifiers":[
        {
            "category":"Travel",
            "subcategory":"Travel Agent",
            "type":"Entertainment"
        }
    ],
    "sg:phone":"+1 801 492 4637",
    "sg:postcode":"84003",
    "sg:province":"UT",
    "sg:tags":[
        "tournament",
        "golf",
        "booking"
    ],
    "wof:name":"Utah Junior Golf",
    "wof:placetype":"venue"
},
  "geometry": {"coordinates":[-111.785399,40.423854],"type":"Point"}
}