{
  "type": "Feature",
  "properties": {
    "iso:country":"US",
    "sg:address":"9829 S 1300 E",
    "sg:city":"Sandy",
    "sg:classifiers":[
        {
            "category":"Health Services",
            "subcategory":"Health Practitioner",
            "type":"Services"
        }
    ],
    "sg:phone":"+1 801 576 8855",
    "sg:postcode":"84094",
    "sg:province":"UT",
    "wof:name":"B Jack David MD",
    "wof:placetype":"venue"
},
  "geometry": {"coordinates":[-111.85304499999999,40.569633],"type":"Point"}
}