{
  "type": "Feature",
  "properties": {
    "iso:country":"US",
    "sg:address":"8586 Center St",
    "sg:city":"Sandy",
    "sg:classifiers":[
        {
            "category":"Travel",
            "subcategory":"Hotels & Motels",
            "type":"Entertainment"
        }
    ],
    "sg:phone":"+1 801 562 2198",
    "sg:postcode":"84070",
    "sg:province":"UT",
    "sg:tags":[
        "breakfast",
        "accommodation",
        "bed"
    ],
    "wof:name":"Hansen House 1887 B & B",
    "wof:placetype":"venue"
},
  "geometry": {"coordinates":[-111.886036,40.595186],"type":"Point"}
}