{
  "type": "Feature",
  "properties": {
    "iso:country":"US",
    "sg:address":"185 N Commercial St",
    "sg:city":"Morgan",
    "sg:classifiers":[
        {
            "category":"Restaurant",
            "type":"Food & Drink"
        }
    ],
    "sg:menulink":"http://www.allmenus.com/ut/morgan-north/132833-subway/menu/",
    "sg:phone":"+1 801 829 4035",
    "sg:postcode":"84050",
    "sg:province":"UT",
    "sg:tags":[
        "american",
        "sandwich"
    ],
    "wof:name":"Subway",
    "wof:placetype":"venue"
},
  "geometry": {"coordinates":[-111.670091,41.043173],"type":"Point"}
}