{
  "type": "Feature",
  "properties": {
    "iso:country":"US",
    "sg:address":"8786 S Oak Valley Dr",
    "sg:city":"Sandy",
    "sg:classifiers":[
        {
            "category":"Shopping",
            "subcategory":"Music",
            "type":"Retail Goods"
        }
    ],
    "sg:phone":"+1 801 942 8928",
    "sg:postcode":"84093",
    "sg:province":"UT",
    "wof:name":"Paul Kern",
    "wof:placetype":"venue"
},
  "geometry": {"coordinates":[-111.808533,40.591395],"type":"Point"}
}