{
  "type": "Feature",
  "properties": {
    "iso:country":"US",
    "sg:address":"7160 W 10400 N",
    "sg:city":"Tremonton",
    "sg:classifiers":[
        {
            "category":"Farming",
            "subcategory":"Livestock Farm",
            "type":"Manufacturing & Wholesale Goods"
        }
    ],
    "sg:phone":"+1 435 257 7400",
    "sg:postcode":"84337",
    "sg:province":"UT",
    "sg:tags":[
        "ranch"
    ],
    "wof:name":"Clint Judkins",
    "wof:placetype":"venue"
},
  "geometry": {"coordinates":[-112.182095,41.696683],"type":"Point"}
}