{
  "type": "Feature",
  "properties": {
    "iso:country":"US",
    "sg:address":"6768 S 2300 E",
    "sg:city":"Salt Lake City",
    "sg:classifiers":[
        {
            "category":"Building & Trades",
            "subcategory":"Construction",
            "type":"Services"
        }
    ],
    "sg:phone":"+1 801 943 8168",
    "sg:postcode":"84121",
    "sg:province":"UT",
    "sg:tags":[
        "residential",
        "commercial",
        "remodeling"
    ],
    "wof:name":"Carn Enterprise",
    "wof:placetype":"venue"
},
  "geometry": {"coordinates":[-111.824803,40.629164],"type":"Point"}
}