{
  "type": "Feature",
  "properties": {
    "iso:country":"US",
    "sg:address":"775 N Main St",
    "sg:city":"Springville",
    "sg:classifiers":[
        {
            "category":"Professional",
            "type":"Services"
        }
    ],
    "sg:phone":"+1 801 489 9415",
    "sg:postcode":"84663",
    "sg:province":"UT",
    "wof:name":"22k Inc",
    "wof:placetype":"venue"
},
  "geometry": {"coordinates":[-111.610676,40.176514],"type":"Point"}
}