{
  "type": "Feature",
  "properties": {
    "iso:country":"US",
    "sg:address":"7301 S 900 E",
    "sg:city":"Murray",
    "sg:classifiers":[
        {
            "category":"Restaurant",
            "type":"Food & Drink"
        }
    ],
    "sg:menulink":"http://www.allmenus.com/ut/salt-lake-city/38720-la-puente/menu/",
    "sg:phone":"+1 801 562 5992",
    "sg:postcode":"84047",
    "sg:province":"UT",
    "sg:tags":[
        "mexican"
    ],
    "wof:name":"La Puente",
    "wof:placetype":"venue"
},
  "geometry": {"coordinates":[-111.866039,40.618108],"type":"Point"}
}