{
  "type": "Feature",
  "properties": {
    "iso:country":"US",
    "sg:address":"1177 E 2650 N",
    "sg:city":"Ogden",
    "sg:classifiers":[
        {
            "category":"Personal",
            "subcategory":"Beauty Salon",
            "type":"Services"
        }
    ],
    "sg:phone":"+1 801 782 7559",
    "sg:postcode":"84414",
    "sg:province":"UT",
    "sg:tags":[
        "manicuring"
    ],
    "wof:name":"Sister Salon",
    "wof:placetype":"venue"
},
  "geometry": {"coordinates":[-111.940696,41.3074],"type":"Point"}
}