{
  "type": "Feature",
  "properties": {
    "iso:country":"US",
    "sg:address":"283 S 450 W",
    "sg:city":"Cedar City",
    "sg:classifiers":[
        {
            "category":"Organizations",
            "subcategory":"Religious Organization",
            "type":"Services"
        }
    ],
    "sg:phone":"+1 435 586 2288",
    "sg:postcode":"84720",
    "sg:province":"UT",
    "sg:tags":[
        "church"
    ],
    "wof:name":"Church Of Jesus Christ Of Lds",
    "wof:placetype":"venue"
},
  "geometry": {"coordinates":[-113.069092,37.671992],"type":"Point"}
}