{
  "type": "Feature",
  "properties": {
    "iso:country":"US",
    "sg:address":"1310 Airport Rd",
    "sg:city":"Price",
    "sg:classifiers":[
        {
            "category":"Banks & Credit Unions",
            "subcategory":"Investment Brokerage",
            "type":"Services"
        }
    ],
    "sg:phone":"+1 435 637 1478",
    "sg:postcode":"84501",
    "sg:province":"UT",
    "sg:tags":[
        "advisory"
    ],
    "wof:name":"Bruno Investments",
    "wof:placetype":"venue"
},
  "geometry": {"coordinates":[-110.78931900000001,39.598941],"type":"Point"}
}