{
  "type": "Feature",
  "properties": {
    "iso:country":"US",
    "sg:address":"239 E 800 S",
    "sg:city":"Salt Lake City",
    "sg:classifiers":[
        {
            "category":"Building & Trades",
            "subcategory":"Cleaning & Sanitation",
            "type":"Services"
        },
        {
            "category":"Retail",
            "subcategory":"Repair Shop",
            "type":"Services"
        }
    ],
    "sg:phone":"+1 801 978 9354",
    "sg:postcode":"84111",
    "sg:province":"UT",
    "sg:tags":[
        "janitor"
    ],
    "wof:name":"Cleaning Specialist Inc",
    "wof:placetype":"venue"
},
  "geometry": {"coordinates":[-111.885361,40.751954],"type":"Point"}
}