{
  "type": "Feature",
  "properties": {
    "iso:country":"US",
    "sg:address":"405 Main St",
    "sg:city":"Park City",
    "sg:classifiers":[
        {
            "category":"Shopping",
            "subcategory":"Clothing, Apparel, & Fashions",
            "type":"Retail Goods"
        }
    ],
    "sg:phone":"+1 435 649 4054",
    "sg:postcode":"84060",
    "sg:province":"UT",
    "sg:tags":[
        "t",
        "family"
    ],
    "wof:name":"Shirt Off My Back The",
    "wof:placetype":"venue"
},
  "geometry": {"coordinates":[-111.496165,40.644094],"type":"Point"}
}