{
  "type": "Feature",
  "properties": {
    "iso:country":"US",
    "sg:address":"1354 Foothill Dr",
    "sg:city":"Salt Lake City",
    "sg:classifiers":[
        {
            "category":"Shopping",
            "subcategory":"Clothing, Apparel, & Fashions",
            "type":"Retail Goods"
        }
    ],
    "sg:phone":"+1 801 581 0600",
    "sg:postcode":"84108",
    "sg:province":"UT",
    "sg:tags":[
        "furnishing"
    ],
    "wof:name":"C T Brock Co",
    "wof:placetype":"venue"
},
  "geometry": {"coordinates":[-111.825971,40.740164],"type":"Point"}
}