{
  "type": "Feature",
  "properties": {
    "iso:country":"US",
    "sg:address":"12032 Lampton Cove",
    "sg:city":"Riverton",
    "sg:classifiers":[
        {
            "category":"Organizations",
            "subcategory":"Labor Organization",
            "type":"Services"
        }
    ],
    "sg:phone":"+1 801 254 3287",
    "sg:postcode":"84065",
    "sg:province":"UT",
    "wof:name":"Wells Holdings Lc",
    "wof:placetype":"venue"
},
  "geometry": {"coordinates":[-111.922951,40.532656],"type":"Point"}
}