{
  "type": "Feature",
  "properties": {
    "iso:country":"US",
    "sg:address":"87 W 400 N",
    "sg:city":"Salem",
    "sg:classifiers":[
        {
            "category":"Wholesale",
            "subcategory":"Hardware",
            "type":"Manufacturing & Wholesale Goods"
        }
    ],
    "sg:phone":"+1 801 423 2551",
    "sg:postcode":"84653",
    "sg:province":"UT",
    "sg:tags":[
        "air",
        "parts",
        "conditioning",
        "supply"
    ],
    "wof:name":"Mc Quay Intl",
    "wof:placetype":"venue"
},
  "geometry": {"coordinates":[-111.676602,40.06063],"type":"Point"}
}