{
  "type": "Feature",
  "properties": {
    "iso:country":"US",
    "sg:address":"2329 W Spring Hollow Rd",
    "sg:city":"Morgan",
    "sg:classifiers":[
        {
            "category":"Professional",
            "subcategory":"Business Services",
            "type":"Services"
        }
    ],
    "sg:phone":"+1 801 876 3501",
    "sg:postcode":"84050",
    "sg:province":"UT",
    "wof:name":"Wm York Co",
    "wof:placetype":"venue"
},
  "geometry": {"coordinates":[-111.714324,41.108184],"type":"Point"}
}