{
  "type": "Feature",
  "properties": {
    "iso:country":"US",
    "sg:address":"1060 W 600 N",
    "sg:city":"Woods Cross",
    "sg:classifiers":[
        {
            "category":"Building & Trades",
            "subcategory":"Plumbing",
            "type":"Services"
        }
    ],
    "sg:phone":"+1 801 298 9063",
    "sg:postcode":"84087",
    "sg:province":"UT",
    "sg:tags":[
        "contractor"
    ],
    "wof:name":"Turley Heating & Air Condition",
    "wof:placetype":"venue"
},
  "geometry": {"coordinates":[-111.909509,40.895461],"type":"Point"}
}