{
  "type": "Feature",
  "properties": {
    "iso:country":"US",
    "sg:address":"1476 E 4200 S",
    "sg:city":"Salt Lake City",
    "sg:classifiers":[
        {
            "category":"Building & Trades",
            "subcategory":"Plumbing",
            "type":"Services"
        }
    ],
    "sg:phone":"+1 801 278 4041",
    "sg:postcode":"84124",
    "sg:province":"UT",
    "sg:tags":[
        "conditioning",
        "air",
        "system",
        "contractor"
    ],
    "wof:name":"A-ACCUAIRE Hvac",
    "wof:placetype":"venue"
},
  "geometry": {"coordinates":[-111.85023,40.680231],"type":"Point"}
}