{
  "type": "Feature",
  "properties": {
    "iso:country":"US",
    "sg:address":"209 E 300 N",
    "sg:city":"Smithfield",
    "sg:classifiers":[
        {
            "category":"Building & Trades",
            "subcategory":"Plumbing",
            "type":"Services"
        }
    ],
    "sg:phone":"+1 435 563 6786",
    "sg:postcode":"84335",
    "sg:province":"UT",
    "sg:tags":[
        "heating",
        "contractor"
    ],
    "wof:name":"Gardner Enterprises",
    "wof:placetype":"venue"
},
  "geometry": {"coordinates":[-111.82669300000001,41.842791],"type":"Point"}
}