{
  "type": "Feature",
  "properties": {
    "iso:country":"US",
    "sg:address":"375 W 1700 S",
    "sg:city":"Clearfield",
    "sg:classifiers":[
        {
            "category":"Freight",
            "type":"Transportation"
        }
    ],
    "sg:phone":"+1 801 543 9099",
    "sg:postcode":"84075",
    "sg:province":"UT",
    "sg:tags":[
        "commercial",
        "storage"
    ],
    "wof:name":"A A Access Storage",
    "wof:placetype":"venue"
},
  "geometry": {"coordinates":[-112.034447,41.089078],"type":"Point"}
}