{
  "type": "Feature",
  "properties": {
    "iso:country":"US",
    "sg:address":"547 N Main St",
    "sg:city":"Layton",
    "sg:classifiers":[
        {
            "category":"Shopping",
            "subcategory":"Clothing, Apparel, & Fashions",
            "type":"Retail Goods"
        }
    ],
    "sg:phone":"+1 801 546 1301",
    "sg:postcode":"84041",
    "sg:province":"UT",
    "sg:tags":[
        "repair",
        "shoes"
    ],
    "wof:name":"Diamond T Western Wear",
    "wof:placetype":"venue"
},
  "geometry": {"coordinates":[-111.97398099999999,41.067852],"type":"Point"}
}