{
  "type": "Feature",
  "properties": {
    "iso:country":"US",
    "sg:address":"5833 Pinion Ln",
    "sg:city":"Kamas",
    "sg:classifiers":[
        {
            "category":"Building & Trades",
            "subcategory":"Construction",
            "type":"Services"
        }
    ],
    "sg:phone":"+1 435 783 5764",
    "sg:postcode":"84036",
    "sg:province":"UT",
    "sg:tags":[
        "general",
        "contractor"
    ],
    "wof:name":"Double E Construction Inc",
    "wof:placetype":"venue"
},
  "geometry": {"coordinates":[-111.254549,40.73005],"type":"Point"}
}