{
  "type": "Feature",
  "properties": {
    "iso:country":"US",
    "sg:address":"149 S Main St",
    "sg:city":"Coalville",
    "sg:classifiers":[
        {
            "category":"Professional",
            "subcategory":"Lawyer & Legal Services",
            "type":"Services"
        }
    ],
    "sg:phone":"+1 435 336 1200",
    "sg:postcode":"84017",
    "sg:province":"UT",
    "sg:tags":[
        "attorney"
    ],
    "wof:name":"Sheldon A Smith & Assoc",
    "wof:placetype":"venue"
},
  "geometry": {"coordinates":[-111.395732,40.909716],"type":"Point"}
}