{
  "type": "Feature",
  "properties": {
    "iso:country":"US",
    "sg:address":"61 S 360 W",
    "sg:city":"Orem",
    "sg:classifiers":[
        {
            "category":"Professional",
            "subcategory":"Management & Consulting",
            "type":"Services"
        }
    ],
    "sg:phone":"+1 801 224 3156",
    "sg:postcode":"84058",
    "sg:province":"UT",
    "wof:name":"Delphi Management Inc",
    "wof:placetype":"venue"
},
  "geometry": {"coordinates":[-111.70412899999999,40.295578],"type":"Point"}
}