{
  "type": "Feature",
  "properties": {
    "iso:country":"US",
    "sg:address":"5090 W 6275 S",
    "sg:city":"West Jordan",
    "sg:classifiers":[
        {
            "category":"Building & Trades",
            "subcategory":"Cleaning & Sanitation",
            "type":"Services"
        }
    ],
    "sg:phone":"+1 801 957 1286",
    "sg:postcode":"84084",
    "sg:province":"UT",
    "sg:tags":[
        "janitor"
    ],
    "wof:name":"Stephanie's Cleaning Svc",
    "wof:placetype":"venue"
},
  "geometry": {"coordinates":[-112.012467,40.637306],"type":"Point"}
}