{
  "type": "Feature",
  "properties": {
    "iso:country":"US",
    "sg:address":"449 N 500 W",
    "sg:city":"Provo",
    "sg:classifiers":[
        {
            "category":"Education",
            "subcategory":"School",
            "type":"Public Place"
        }
    ],
    "sg:phone":"+1 801 374 4955",
    "sg:postcode":"84601",
    "sg:province":"UT",
    "sg:website":"www.provo.edu",
    "wof:name":"Timpanogos Elementary School",
    "wof:placetype":"venue"
},
  "geometry": {"coordinates":[-111.667509,40.239765],"type":"Point"}
}