{
  "type": "Feature",
  "properties": {
    "iso:country":"US",
    "sg:address":"11370 W 10400 N",
    "sg:city":"Tremonton",
    "sg:classifiers":[
        {
            "category":"Manufacturing",
            "subcategory":"Building Materials",
            "type":"Manufacturing & Wholesale Goods"
        }
    ],
    "sg:phone":"+1 435 854 7001",
    "sg:postcode":"84337",
    "sg:province":"UT",
    "sg:tags":[
        "mfg"
    ],
    "wof:name":"Troy Toone Custom Woodworking",
    "wof:placetype":"venue"
},
  "geometry": {"coordinates":[-112.285538,41.694623],"type":"Point"}
}