{
  "type": "Feature",
  "properties": {
    "iso:country":"US",
    "sg:address":"432 Lawndale Dr",
    "sg:city":"Salt Lake City",
    "sg:classifiers":[
        {
            "category":"Shopping",
            "subcategory":"Computers & Home Electronics",
            "type":"Retail Goods"
        }
    ],
    "sg:phone":"+1 801 485 8420",
    "sg:postcode":"84115",
    "sg:province":"UT",
    "sg:tags":[
        "software"
    ],
    "wof:name":"Computer Engineering Inc",
    "wof:placetype":"venue"
},
  "geometry": {"coordinates":[-111.90252599999999,40.715847],"type":"Point"}
}