{
  "type": "Feature",
  "properties": {
    "iso:country":"US",
    "sg:address":"716 W 300 S",
    "sg:city":"Salt Lake City",
    "sg:classifiers":[
        {
            "category":"Manufacturing",
            "subcategory":"Furniture",
            "type":"Manufacturing & Wholesale Goods"
        }
    ],
    "sg:phone":"+1 801 359 4764",
    "sg:postcode":"84104",
    "sg:province":"UT",
    "wof:name":"Hamblin's Custom Furniture",
    "wof:placetype":"venue"
},
  "geometry": {"coordinates":[-111.912592,40.762885],"type":"Point"}
}