{
  "type": "Feature",
  "properties": {
    "iso:country":"US",
    "sg:address":"1232 W 450 N",
    "sg:city":"Layton",
    "sg:classifiers":[
        {
            "category":"Building & Trades",
            "subcategory":"Construction",
            "type":"Services"
        }
    ],
    "sg:phone":"+1 801 593 6647",
    "sg:postcode":"84041",
    "sg:province":"UT",
    "sg:tags":[
        "steel",
        "fabrication",
        "welding"
    ],
    "wof:name":"Liberty Steel",
    "wof:placetype":"venue"
},
  "geometry": {"coordinates":[-111.988516,41.066608],"type":"Point"}
}