{
  "type": "Feature",
  "properties": {
    "iso:country":"US",
    "sg:address":"161 S 200 W",
    "sg:city":"Cedar City",
    "sg:classifiers":[
        {
            "category":"Travel",
            "subcategory":"Hotels & Motels",
            "type":"Entertainment"
        }
    ],
    "sg:phone":"+1 435 867 5280",
    "sg:postcode":"84720",
    "sg:province":"UT",
    "sg:tags":[
        "breakfast",
        "accommodation",
        "bed"
    ],
    "wof:name":"Stratford",
    "wof:placetype":"venue"
},
  "geometry": {"coordinates":[-113.065073,37.675438],"type":"Point"}
}