{
  "type": "Feature",
  "properties": {
    "iso:country":"US",
    "sg:address":"829 Three Fountains Dr",
    "sg:city":"Salt Lake City",
    "sg:classifiers":[
        {
            "category":"Travel",
            "subcategory":"Travel Agent",
            "type":"Entertainment"
        }
    ],
    "sg:phone":"+1 801 269 8244",
    "sg:postcode":"84107",
    "sg:province":"UT",
    "sg:tags":[
        "agency",
        "bureau"
    ],
    "wof:name":"Beverly Morris Cruise & Tours",
    "wof:placetype":"venue"
},
  "geometry": {"coordinates":[-111.868208,40.66232],"type":"Point"}
}