{
  "type": "Feature",
  "properties": {
    "iso:country":"US",
    "sg:address":"5438 Spinnaker Row",
    "sg:city":"Salt Lake City",
    "sg:classifiers":[
        {
            "category":"Organizations",
            "subcategory":"Community Association",
            "type":"Services"
        }
    ],
    "sg:phone":"+1 801 685 2661",
    "sg:postcode":"84123",
    "sg:province":"UT",
    "wof:name":"Healing Overtones",
    "wof:placetype":"venue"
},
  "geometry": {"coordinates":[-111.933455,40.65239],"type":"Point"}
}