{
  "type": "Feature",
  "properties": {
    "iso:country":"US",
    "sg:address":"336 N 200 E",
    "sg:city":"Washington",
    "sg:classifiers":[
        {
            "category":"Recreation",
            "type":"Entertainment"
        }
    ],
    "sg:phone":"+1 435 628 0717",
    "sg:postcode":"84780",
    "sg:province":"UT",
    "sg:tags":[
        "pool",
        "swimming"
    ],
    "wof:name":"Swimming Pool",
    "wof:placetype":"venue"
},
  "geometry": {"coordinates":[-113.50645400000001,37.136679],"type":"Point"}
}