{
  "type": "Feature",
  "properties": {
    "iso:country":"US",
    "sg:address":"1524 Logan Ave",
    "sg:city":"Salt Lake City",
    "sg:classifiers":[
        {
            "category":"Professional",
            "type":"Services"
        }
    ],
    "sg:phone":"+1 801 486 1238",
    "sg:postcode":"84105",
    "sg:province":"UT",
    "sg:tags":[
        "establishment"
    ],
    "wof:name":"Micron Inc",
    "wof:placetype":"venue"
},
  "geometry": {"coordinates":[-111.84577400000001,40.73433],"type":"Point"}
}