{
  "type": "Feature",
  "properties": {
    "iso:country":"US",
    "sg:address":"36 S State St",
    "sg:city":"Salt Lake City",
    "sg:classifiers":[
        {
            "category":"Deli",
            "type":"Food & Drink"
        }
    ],
    "sg:menulink":"http://www.allmenus.com/ut/salt-lake-city/126845-blimpie-subs--sandwiches/menu/",
    "sg:phone":"+1 801 355 0634",
    "sg:postcode":"84111",
    "sg:province":"UT",
    "sg:tags":[
        "wrap",
        "american",
        "sandwich"
    ],
    "wof:name":"Blimpie Subs & Sandwiches",
    "wof:placetype":"venue"
},
  "geometry": {"coordinates":[-111.88829699999999,40.768511],"type":"Point"}
}