{
  "type": "Feature",
  "properties": {
    "iso:country":"US",
    "sg:address":"2696 S 1900 E",
    "sg:city":"Salt Lake City",
    "sg:classifiers":[
        {
            "category":"Recreation",
            "type":"Entertainment"
        }
    ],
    "sg:phone":"+1 801 486 7732",
    "sg:postcode":"84106",
    "sg:province":"UT",
    "wof:name":"Yoga Space LLC",
    "wof:placetype":"venue"
},
  "geometry": {"coordinates":[-111.836737,40.715405],"type":"Point"}
}