{
  "type": "Feature",
  "properties": {
    "iso:country":"US",
    "sg:address":"196 E State Rd",
    "sg:city":"American Fork",
    "sg:classifiers":[
        {
            "category":"Banks & Credit Unions",
            "subcategory":"Bank",
            "type":"Services"
        }
    ],
    "sg:phone":"+1 801 492 1150",
    "sg:postcode":"84003",
    "sg:province":"UT",
    "wof:name":"Universal Campus Credit Union",
    "wof:placetype":"venue"
},
  "geometry": {"coordinates":[-111.793222,40.376286],"type":"Point"}
}