{
  "type": "Feature",
  "properties": {
    "iso:country":"US",
    "sg:address":"1004 S Main St",
    "sg:city":"Moab",
    "sg:classifiers":[
        {
            "category":"Home & Garden",
            "subcategory":"Furniture",
            "type":"Retail Goods"
        }
    ],
    "sg:phone":"+1 435 259 1585",
    "sg:postcode":"84532",
    "sg:province":"UT",
    "sg:tags":[
        "furnishing"
    ],
    "wof:name":"Knowles Home Furnishings Inc",
    "wof:placetype":"venue"
},
  "geometry": {"coordinates":[-109.547034,38.560369],"type":"Point"}
}