{
  "type": "Feature",
  "properties": {
    "iso:country":"US",
    "sg:address":"944 E Claremont Dr",
    "sg:city":"Bountiful",
    "sg:classifiers":[
        {
            "category":"Professional",
            "subcategory":"Lawyer & Legal Services",
            "type":"Services"
        },
        {
            "category":"Professional",
            "subcategory":"Accounting & Tax Preparation",
            "type":"Services"
        }
    ],
    "sg:phone":"+1 801 295 9807",
    "sg:postcode":"84010",
    "sg:province":"UT",
    "sg:tags":[
        "bookkeeping",
        "general"
    ],
    "wof:name":"P C Despain CPA Firm",
    "wof:placetype":"venue"
},
  "geometry": {"coordinates":[-111.85899499999999,40.868128],"type":"Point"}
}