{
  "type": "Feature",
  "properties": {
    "iso:country":"US",
    "sg:address":"680 W Lambert Ln",
    "sg:city":"Kamas",
    "sg:phone":"+1 435 783 4743",
    "sg:postcode":"84036",
    "sg:province":"UT",
    "sg:tags":[
        "beef",
        "farm",
        "crop",
        "field",
        "cattle",
        "feedlot"
    ],
    "wof:name":"Duane Lambert",
    "wof:placetype":"venue"
},
  "geometry": {"coordinates":[-111.29372600000001,40.625048],"type":"Point"}
}