{
  "type": "Feature",
  "properties": {
    "iso:country":"US",
    "sg:address":"2730 W 3500 S",
    "sg:city":"Salt Lake City",
    "sg:classifiers":[
        {
            "category":"Restaurant",
            "type":"Food & Drink"
        }
    ],
    "sg:menulink":"http://www.allmenus.com/ut/salt-lake-city/37262-pizza-hut/menu/",
    "sg:phone":"+1 801 964 9696",
    "sg:postcode":"84119",
    "sg:province":"UT",
    "sg:tags":[
        "american",
        "pizza"
    ],
    "wof:name":"Pizza Hut",
    "wof:placetype":"venue"
},
  "geometry": {"coordinates":[-111.958989,40.696875],"type":"Point"}
}