{
  "type": "Feature",
  "properties": {
    "iso:country":"US",
    "sg:address":"953 S 200 W",
    "sg:city":"Salt Lake City",
    "sg:classifiers":[
        {
            "category":"Building & Trades",
            "subcategory":"Construction",
            "type":"Services"
        }
    ],
    "sg:phone":"+1 801 359 2773",
    "sg:postcode":"84101",
    "sg:province":"UT",
    "sg:tags":[
        "heavy"
    ],
    "wof:name":"Stacy and Witbeck Inc",
    "wof:placetype":"venue"
},
  "geometry": {"coordinates":[-111.89672899999999,40.749242],"type":"Point"}
}