{
  "type": "Feature",
  "properties": {
    "iso:country":"US",
    "sg:address":"358 N 930 E",
    "sg:city":"Lindon",
    "sg:classifiers":[
        {
            "category":"Professional",
            "subcategory":"Business Services",
            "type":"Services"
        }
    ],
    "sg:phone":"+1 801 796 8711",
    "sg:postcode":"84042",
    "sg:province":"UT",
    "wof:name":"Designworks",
    "wof:placetype":"venue"
},
  "geometry": {"coordinates":[-111.693851,40.344155],"type":"Point"}
}