{
  "type": "Feature",
  "properties": {
    "iso:country":"US",
    "sg:address":"1267 State Hwy 193",
    "sg:city":"Layton",
    "sg:classifiers":[
        {
            "category":"Shopping",
            "subcategory":"Bicycles & Sporting Goods",
            "type":"Retail Goods"
        }
    ],
    "sg:phone":"+1 801 771 8780",
    "sg:postcode":"84040",
    "sg:province":"UT",
    "sg:tags":[
        "gun",
        "gunsmith"
    ],
    "wof:name":"B & A Guns",
    "wof:placetype":"venue"
},
  "geometry": {"coordinates":[-111.94015,41.101185],"type":"Point"}
}