{
  "type": "Feature",
  "properties": {
    "iso:country":"US",
    "sg:address":"50 N 100 E",
    "sg:city":"Kaysville",
    "sg:classifiers":[
        {
            "category":"Education",
            "subcategory":"School",
            "type":"Public Place"
        }
    ],
    "sg:phone":"+1 801 402 3400",
    "sg:postcode":"84037",
    "sg:province":"UT",
    "wof:name":"Kaysville Elementary School",
    "wof:placetype":"venue"
},
  "geometry": {"coordinates":[-111.936226,41.035663],"type":"Point"}
}