{
  "type": "Feature",
  "properties": {
    "iso:country":"US",
    "sg:address":"243 E 200 S",
    "sg:city":"Manti",
    "sg:classifiers":[
        {
            "category":"Restaurant",
            "type":"Food & Drink"
        }
    ],
    "sg:phone":"+1 435 835 8491",
    "sg:postcode":"84642",
    "sg:province":"UT",
    "sg:tags":[
        "machine",
        "eating",
        "vending",
        "operator"
    ],
    "wof:name":"Snack Co",
    "wof:placetype":"venue"
},
  "geometry": {"coordinates":[-111.632475,39.262561],"type":"Point"}
}