{
  "type": "Feature",
  "properties": {
    "iso:country":"US",
    "sg:address":"564 Spruce Glen Rd",
    "sg:city":"Salt Lake City",
    "sg:classifiers":[
        {
            "category":"Professional",
            "subcategory":"Business Services",
            "type":"Services"
        }
    ],
    "sg:phone":"+1 801 266 6991",
    "sg:postcode":"84107",
    "sg:province":"UT",
    "wof:name":"Chase Management Group LLC",
    "wof:placetype":"venue"
},
  "geometry": {"coordinates":[-111.873648,40.666194],"type":"Point"}
}