{
  "type": "Feature",
  "properties": {
    "iso:country":"US",
    "sg:address":"1664 N 1200 W",
    "sg:city":"Layton",
    "sg:classifiers":[
        {
            "category":"Restaurant",
            "type":"Food & Drink"
        }
    ],
    "sg:phone":"+1 801 779 9394",
    "sg:postcode":"84041",
    "sg:province":"UT",
    "sg:website":"www.outback.com",
    "wof:name":"Outback Steakhouse",
    "wof:placetype":"venue"
},
  "geometry": {"coordinates":[-111.98771600000001,41.081562],"type":"Point"}
}