{
  "type": "Feature",
  "properties": {
    "iso:country":"US",
    "sg:address":"37 W 10600 S",
    "sg:city":"Sandy",
    "sg:classifiers":[
        {
            "category":"Restaurant",
            "type":"Food & Drink"
        }
    ],
    "sg:menulink":"http://www.allmenus.com/ut/salt-lake-city/37324-simply-thai/menu/",
    "sg:phone":"+1 801 307 1221",
    "sg:postcode":"84070",
    "sg:province":"UT",
    "sg:tags":[
        "taiwanese",
        "asian"
    ],
    "wof:name":"Simply Thai",
    "wof:placetype":"venue"
},
  "geometry": {"coordinates":[-111.891892,40.558779],"type":"Point"}
}