{
  "type": "Feature",
  "properties": {
    "iso:country":"US",
    "sg:address":"675 W 5300 S",
    "sg:city":"Murray",
    "sg:classifiers":[
        {
            "category":"Personal",
            "subcategory":"Shoe Repair & Shine",
            "type":"Services"
        }
    ],
    "sg:phone":"+1 801 264 1831",
    "sg:postcode":"84123",
    "sg:province":"UT",
    "sg:tags":[
        "repairing",
        "parlor",
        "boot"
    ],
    "wof:name":"Ace Shoe Repair",
    "wof:placetype":"venue"
},
  "geometry": {"coordinates":[-111.908312,40.653936],"type":"Point"}
}