{
  "type": "Feature",
  "properties": {
    "iso:country":"US",
    "sg:address":"801 N 500 W",
    "sg:city":"Bountiful",
    "sg:classifiers":[
        {
            "category":"Banks & Credit Unions",
            "subcategory":"Bank",
            "type":"Services"
        }
    ],
    "sg:phone":"+1 801 397 0613",
    "sg:postcode":"84010",
    "sg:province":"UT",
    "wof:name":"Republic Bank",
    "wof:placetype":"venue"
},
  "geometry": {"coordinates":[-111.891998,40.897099],"type":"Point"}
}