{
  "type": "Feature",
  "properties": {
    "iso:country":"US",
    "sg:address":"1438 S State St",
    "sg:city":"Salt Lake City",
    "sg:classifiers":[
        {
            "category":"Restaurant",
            "type":"Food & Drink"
        }
    ],
    "sg:menulink":"http://www.allmenus.com/ut/salt-lake-city/164219-wienerschnitzel/menu/",
    "sg:phone":"+1 801 484 7674",
    "sg:postcode":"84115",
    "sg:province":"UT",
    "sg:tags":[
        "sandwich",
        "dog",
        "burger",
        "hot",
        "wrap",
        "american"
    ],
    "wof:name":"Wienerschnitzel",
    "wof:placetype":"venue"
},
  "geometry": {"coordinates":[-111.888364,40.738575],"type":"Point"}
}