{
  "type": "Feature",
  "properties": {
    "iso:country":"US",
    "sg:address":"1504 E 950 S",
    "sg:city":"Springville",
    "sg:classifiers":[
        {
            "category":"Building & Trades",
            "subcategory":"Construction",
            "type":"Services"
        }
    ],
    "sg:phone":"+1 801 491 8750",
    "sg:postcode":"84663",
    "sg:province":"UT",
    "sg:tags":[
        "nonresidential"
    ],
    "wof:name":"Ridgeline Development Inc",
    "wof:placetype":"venue"
},
  "geometry": {"coordinates":[-111.58497800000001,40.153336],"type":"Point"}
}