{
  "type": "Feature",
  "properties": {
    "iso:country":"US",
    "sg:address":"6871 N 2200 W",
    "sg:city":"Park City",
    "sg:classifiers":[
        {
            "category":"Professional",
            "type":"Services"
        }
    ],
    "sg:phone":"+1 435 655 8024",
    "sg:postcode":"84098",
    "sg:province":"UT",
    "sg:tags":[
        "consultant",
        "geological"
    ],
    "wof:name":"Aqua Ver Inc",
    "wof:placetype":"venue"
},
  "geometry": {"coordinates":[-111.552775,40.727571],"type":"Point"}
}