{
  "type": "Feature",
  "properties": {
    "iso:country":"US",
    "sg:address":"4290 W 5415 S",
    "sg:city":"Salt Lake City",
    "sg:classifiers":[
        {
            "category":"Organizations",
            "subcategory":"Religious Organization",
            "type":"Services"
        }
    ],
    "sg:phone":"+1 801 968 3509",
    "sg:postcode":"84118",
    "sg:province":"UT",
    "wof:name":"Trinity United Methdst Church",
    "wof:placetype":"venue"
},
  "geometry": {"coordinates":[-111.993318,40.65287],"type":"Point"}
}