{
  "type": "Feature",
  "properties": {
    "iso:country":"US",
    "sg:address":"751 N 900 W",
    "sg:city":"Orem",
    "sg:classifiers":[
        {
            "category":"Building & Trades",
            "subcategory":"Construction",
            "type":"Services"
        }
    ],
    "sg:phone":"+1 801 225 7501",
    "sg:postcode":"84057",
    "sg:province":"UT",
    "sg:tags":[
        "wallcoverings-installation",
        "wallpaper",
        "painting",
        "contractor"
    ],
    "wof:name":"Viewtec",
    "wof:placetype":"venue"
},
  "geometry": {"coordinates":[-111.717425,40.310948],"type":"Point"}
}