{
  "type": "Feature",
  "properties": {
    "iso:country":"US",
    "sg:address":"1301 S State St",
    "sg:city":"Salt Lake City",
    "sg:classifiers":[
        {
            "category":"Restaurant",
            "type":"Food & Drink"
        }
    ],
    "sg:phone":"+1 801 486 3579",
    "sg:postcode":"84115",
    "sg:province":"UT",
    "wof:name":"Coachmans Dinner & Pancake Hse",
    "wof:placetype":"venue"
},
  "geometry": {"coordinates":[-111.88821299999999,40.740338],"type":"Point"}
}