{
  "type": "Feature",
  "properties": {
    "iso:country":"US",
    "sg:address":"1380 S University Ave",
    "sg:city":"Provo",
    "sg:classifiers":[
        {
            "category":"Travel",
            "subcategory":"Hotels & Motels",
            "type":"Entertainment"
        }
    ],
    "sg:phone":"+1 801 374 6800",
    "sg:postcode":"84601",
    "sg:province":"UT",
    "sg:tags":[
        "operation"
    ],
    "wof:name":"National 9 Inn",
    "wof:placetype":"venue"
},
  "geometry": {"coordinates":[-111.65902699999999,40.217382],"type":"Point"}
}