{
  "type": "Feature",
  "properties": {
    "iso:country":"US",
    "sg:address":"14725 Majestic Oaks Ln",
    "sg:city":"Riverton",
    "sg:classifiers":[
        {
            "category":"Utilities",
            "subcategory":"Refuse",
            "type":"Services"
        }
    ],
    "sg:phone":"+1 801 446 0392",
    "sg:postcode":"84096",
    "sg:province":"UT",
    "sg:tags":[
        "system"
    ],
    "wof:name":"Haulin Trash Cnstr Cleanup",
    "wof:placetype":"venue"
},
  "geometry": {"coordinates":[-112.059656,40.479183],"type":"Point"}
}