{
  "type": "Feature",
  "properties": {
    "iso:country":"US",
    "sg:address":"608 S 520 W",
    "sg:city":"Orem",
    "sg:classifiers":[
        {
            "category":"Building & Trades",
            "subcategory":"Construction",
            "type":"Services"
        }
    ],
    "sg:phone":"+1 801 259 5862",
    "sg:postcode":"84058",
    "sg:province":"UT",
    "sg:tags":[
        "builder",
        "operative"
    ],
    "wof:name":"Kesslers Home & Office Repair",
    "wof:placetype":"venue"
},
  "geometry": {"coordinates":[-111.70795200000001,40.286266],"type":"Point"}
}