{
  "type": "Feature",
  "properties": {
    "iso:country":"US",
    "sg:address":"424 S Redwood Rd",
    "sg:city":"Salt Lake City",
    "sg:classifiers":[
        {
            "category":"Building & Trades",
            "subcategory":"Construction",
            "type":"Services"
        }
    ],
    "sg:phone":"+1 801 973 8001",
    "sg:postcode":"84104",
    "sg:province":"UT",
    "sg:tags":[
        "general",
        "commercial",
        "contractor"
    ],
    "sg:website":"www.petersoncc.net",
    "wof:name":"Peterson Construction Co",
    "wof:placetype":"venue"
},
  "geometry": {"coordinates":[-111.939094,40.759652],"type":"Point"}
}