{
  "type": "Feature",
  "properties": {
    "iso:country":"US",
    "sg:address":"60 S 700 E",
    "sg:city":"Price",
    "sg:classifiers":[
        {
            "category":"Shopping",
            "type":"Retail Goods"
        }
    ],
    "sg:phone":"+1 435 637 9500",
    "sg:postcode":"84501",
    "sg:province":"UT",
    "sg:tags":[
        "equipment",
        "care",
        "health",
        "home"
    ],
    "wof:name":"Praxair Healthcare Svc",
    "wof:placetype":"venue"
},
  "geometry": {"coordinates":[-110.797989,39.598692],"type":"Point"}
}