{
  "type": "Feature",
  "properties": {
    "iso:country":"US",
    "sg:address":"9308 Janet Way",
    "sg:city":"West Jordan",
    "sg:classifiers":[
        {
            "category":"Real Estate",
            "subcategory":"Real Estate Agent",
            "type":"Services"
        }
    ],
    "sg:phone":"+1 801 280 8179",
    "sg:postcode":"84088",
    "sg:province":"UT",
    "sg:tags":[
        "appraiser"
    ],
    "wof:name":"Brown Appraisal Svc",
    "wof:placetype":"venue"
},
  "geometry": {"coordinates":[-111.98401800000001,40.5819],"type":"Point"}
}