{
  "type": "Feature",
  "properties": {
    "iso:country":"US",
    "sg:address":"1376 N State St",
    "sg:city":"Orem",
    "sg:classifiers":[
        {
            "category":"Banks & Credit Unions",
            "subcategory":"Bank",
            "type":"Services"
        }
    ],
    "sg:phone":"+1 801 222 9006",
    "sg:postcode":"84057",
    "sg:province":"UT",
    "wof:name":"Western Community Bank",
    "wof:placetype":"venue"
},
  "geometry": {"coordinates":[-111.706292,40.322896],"type":"Point"}
}