{
  "type": "Feature",
  "properties": {
    "iso:country":"US",
    "sg:address":"35 E 1100 N",
    "sg:city":"Brigham City",
    "sg:classifiers":[
        {
            "category":"Manufacturing",
            "subcategory":"Tools & Machinery",
            "type":"Manufacturing & Wholesale Goods"
        }
    ],
    "sg:phone":"+1 435 734 2650",
    "sg:postcode":"84302",
    "sg:province":"UT",
    "sg:tags":[
        "machine",
        "shop",
        "industrial",
        "mfg"
    ],
    "wof:name":"J B Precision Machine",
    "wof:placetype":"venue"
},
  "geometry": {"coordinates":[-112.01444600000001,41.53216],"type":"Point"}
}