{
  "type": "Feature",
  "properties": {
    "iso:country":"US",
    "sg:address":"935 Rosewood Ln",
    "sg:city":"Layton",
    "sg:classifiers":[
        {
            "category":"Shopping",
            "subcategory":"Gifts & Souvenirs",
            "type":"Retail Goods"
        }
    ],
    "sg:phone":"+1 801 544 8740",
    "sg:postcode":"84041",
    "sg:province":"UT",
    "wof:name":"Bear Essential Collectibl",
    "wof:placetype":"venue"
},
  "geometry": {"coordinates":[-111.949707,41.05536],"type":"Point"}
}