{
  "type": "Feature",
  "properties": {
    "iso:country":"US",
    "sg:address":"483 N 600 W",
    "sg:city":"American Fork",
    "sg:classifiers":[
        {
            "category":"Retail",
            "subcategory":"Auto Repair",
            "type":"Services"
        }
    ],
    "sg:phone":"+1 801 444 1171",
    "sg:postcode":"84003",
    "sg:province":"UT",
    "sg:tags":[
        "transmission"
    ],
    "wof:name":"Craig's Transmission & Auto",
    "wof:placetype":"venue"
},
  "geometry": {"coordinates":[-111.814404,40.387141],"type":"Point"}
}