{
  "type": "Feature",
  "properties": {
    "iso:country":"US",
    "sg:address":"190 N Main St",
    "sg:city":"Hatch",
    "sg:classifiers":[
        {
            "category":"Government",
            "subcategory":"Post Office",
            "type":"Public Place"
        }
    ],
    "sg:phone":"+1 435 735 4317",
    "sg:postcode":"84735",
    "sg:province":"UT",
    "wof:name":"US Post Office",
    "wof:placetype":"venue"
},
  "geometry": {"coordinates":[-112.43431699999999,37.652805],"type":"Point"}
}