{
  "type": "Feature",
  "properties": {
    "iso:country":"US",
    "sg:address":"1227 E 3300 S",
    "sg:city":"Salt Lake City",
    "sg:classifiers":[
        {
            "category":"Retail",
            "subcategory":"Photofinishing",
            "type":"Services"
        }
    ],
    "sg:phone":"+1 801 466 1939",
    "sg:postcode":"84106",
    "sg:province":"UT",
    "sg:tags":[
        "laboratory"
    ],
    "wof:name":"Shutterbugz",
    "wof:placetype":"venue"
},
  "geometry": {"coordinates":[-111.857524,40.699988],"type":"Point"}
}