{
  "type": "Feature",
  "properties": {
    "iso:country":"US",
    "sg:address":"587 W 300 N",
    "sg:city":"Hyrum",
    "sg:classifiers":[
        {
            "category":"Professional",
            "subcategory":"Employment Agencies",
            "type":"Services"
        }
    ],
    "sg:phone":"+1 435 245 3443",
    "sg:postcode":"84319",
    "sg:province":"UT",
    "wof:name":"Nurses Needs LLC",
    "wof:placetype":"venue"
},
  "geometry": {"coordinates":[-111.871368,41.640592],"type":"Point"}
}