{
  "type": "Feature",
  "properties": {
    "iso:country":"US",
    "sg:address":"608 Main St",
    "sg:city":"Park City",
    "sg:classifiers":[
        {
            "category":"Professional",
            "type":"Services"
        }
    ],
    "sg:phone":"+1 435 649 9627",
    "sg:postcode":"84060",
    "sg:province":"UT",
    "sg:tags":[
        "establishment"
    ],
    "wof:name":"Slamdance",
    "wof:placetype":"venue"
},
  "geometry": {"coordinates":[-111.49714,40.646127],"type":"Point"}
}