{
  "type": "Feature",
  "properties": {
    "iso:country":"US",
    "sg:address":"280 S 400 E",
    "sg:city":"Salem",
    "sg:classifiers":[
        {
            "category":"Building & Trades",
            "subcategory":"Plumbing",
            "type":"Services"
        }
    ],
    "sg:phone":"+1 801 423 4153",
    "sg:postcode":"84653",
    "sg:province":"UT",
    "sg:tags":[
        "contractor"
    ],
    "wof:name":"Hanks Plumbing",
    "wof:placetype":"venue"
},
  "geometry": {"coordinates":[-111.665514,40.050199],"type":"Point"}
}