{
  "type": "Feature",
  "properties": {
    "iso:country":"US",
    "sg:address":"344 S 400 E",
    "sg:city":"Moab",
    "sg:classifiers":[
        {
            "category":"Shopping",
            "subcategory":"Hobbies, Toys, & Games",
            "type":"Retail Goods"
        }
    ],
    "sg:phone":"+1 435 259 2361",
    "sg:postcode":"84532",
    "sg:province":"UT",
    "sg:tags":[
        "model",
        "supply"
    ],
    "wof:name":"Wizards Of The Desert",
    "wof:placetype":"venue"
},
  "geometry": {"coordinates":[-109.542917,38.568039],"type":"Point"}
}