{
  "type": "Feature",
  "properties": {
    "iso:country":"US",
    "sg:address":"63 E 300 N",
    "sg:city":"North Salt Lake",
    "sg:classifiers":[
        {
            "category":"Social Services",
            "subcategory":"Child Care",
            "type":"Services"
        }
    ],
    "sg:phone":"+1 801 298 3921",
    "sg:postcode":"84054",
    "sg:province":"UT",
    "sg:tags":[
        "day"
    ],
    "wof:name":"Betty Day Care",
    "wof:placetype":"venue"
},
  "geometry": {"coordinates":[-111.91075499999999,40.847412],"type":"Point"}
}