{
  "type": "Feature",
  "properties": {
    "iso:country":"US",
    "sg:address":"1090 Pioneer Rd",
    "sg:city":"Salt Lake City",
    "sg:classifiers":[
        {
            "category":"Wholesale",
            "subcategory":"Home Furnishings",
            "type":"Manufacturing & Wholesale Goods"
        }
    ],
    "sg:phone":"+1 801 973 4441",
    "sg:postcode":"84104",
    "sg:province":"UT",
    "sg:tags":[
        "equipment",
        "fireplace"
    ],
    "wof:name":"Custom Fireplace Distributors",
    "wof:placetype":"venue"
},
  "geometry": {"coordinates":[-111.958136,40.741804],"type":"Point"}
}