{
  "type": "Feature",
  "properties": {
    "iso:country":"US",
    "sg:address":"800 S Lambert Ln",
    "sg:city":"Kamas",
    "sg:classifiers":[
        {
            "category":"Banks & Credit Unions",
            "subcategory":"Investment Brokerage",
            "type":"Services"
        }
    ],
    "sg:phone":"+1 435 783 4639",
    "sg:postcode":"84036",
    "sg:province":"UT",
    "sg:tags":[
        "security"
    ],
    "wof:name":"Washington Irrigation Co",
    "wof:placetype":"venue"
},
  "geometry": {"coordinates":[-111.318172,40.631024],"type":"Point"}
}