{
  "type": "Feature",
  "properties": {
    "iso:country":"US",
    "sg:address":"45 E Center St",
    "sg:city":"Spanish Fork",
    "sg:classifiers":[
        {
            "category":"Home & Garden",
            "subcategory":"Hardware",
            "type":"Retail Goods"
        },
        {
            "category":"Real Estate",
            "subcategory":"Real Estate Operator",
            "type":"Services"
        }
    ],
    "sg:phone":"+1 801 798 6195",
    "sg:postcode":"84660",
    "sg:province":"UT",
    "sg:tags":[
        "commercial",
        "property",
        "rental"
    ],
    "wof:name":"Spanish Fork Builders Supply",
    "wof:placetype":"venue"
},
  "geometry": {"coordinates":[-111.654166,40.109902],"type":"Point"}
}