{
  "type": "Feature",
  "properties": {
    "iso:country":"US",
    "sg:address":"78 W 2400 S",
    "sg:city":"South Salt Lake",
    "sg:classifiers":[
        {
            "category":"Professional",
            "subcategory":"Testing Lab",
            "type":"Services"
        },
        {
            "category":"Building & Trades",
            "subcategory":"Construction",
            "type":"Services"
        }
    ],
    "sg:phone":"+1 801 486 0800",
    "sg:postcode":"84115",
    "sg:province":"UT",
    "sg:tags":[
        "asbestos",
        "laboratory",
        "analysis"
    ],
    "wof:name":"Dixon Information Inc",
    "wof:placetype":"venue"
},
  "geometry": {"coordinates":[-111.892118,40.718749],"type":"Point"}
}