{
  "type": "Feature",
  "properties": {
    "iso:country":"US",
    "sg:address":"49 N Main St",
    "sg:city":"Tooele",
    "sg:classifiers":[
        {
            "category":"Shopping",
            "subcategory":"Clothing, Apparel, & Fashions",
            "type":"Retail Goods"
        }
    ],
    "sg:phone":"+1 435 843 3566",
    "sg:postcode":"84074",
    "sg:province":"UT",
    "sg:tags":[
        "infant",
        "wear"
    ],
    "wof:name":"Sweet Pea Boutique",
    "wof:placetype":"venue"
},
  "geometry": {"coordinates":[-112.29860600000001,40.530692],"type":"Point"}
}