{
  "type": "Feature",
  "properties": {
    "iso:country":"US",
    "sg:address":"1176 W 3300 S",
    "sg:city":"Ogden",
    "sg:classifiers":[
        {
            "category":"Social Services",
            "type":"Services"
        }
    ],
    "sg:phone":"+1 801 399 8392",
    "sg:postcode":"84401",
    "sg:province":"UT",
    "wof:name":"Meals On Wheels",
    "wof:placetype":"venue"
},
  "geometry": {"coordinates":[-112.007321,41.205455],"type":"Point"}
}