{
  "type": "Feature",
  "properties": {
    "iso:country":"US",
    "sg:address":"1766 W 5000 S",
    "sg:city":"Salt Lake City",
    "sg:classifiers":[
        {
            "category":"Restaurant",
            "type":"Food & Drink"
        }
    ],
    "sg:phone":"+1 801 967 4084",
    "sg:postcode":"84118",
    "sg:province":"UT",
    "wof:name":"Las Cazuelas",
    "wof:placetype":"venue"
},
  "geometry": {"coordinates":[-111.940134,40.660365],"type":"Point"}
}