{
  "type": "Feature",
  "properties": {
    "iso:country":"US",
    "sg:address":"57 S 600 E",
    "sg:city":"Salt Lake City",
    "sg:classifiers":[
        {
            "category":"Travel",
            "subcategory":"Hotels & Motels",
            "type":"Entertainment"
        }
    ],
    "sg:phone":"+1 801 363 8035",
    "sg:postcode":"84102",
    "sg:province":"UT",
    "sg:tags":[
        "breakfast",
        "accommodation",
        "bed"
    ],
    "wof:name":"Anton Boxrud Bed & Breakfast",
    "wof:placetype":"venue"
},
  "geometry": {"coordinates":[-111.87384400000001,40.76842],"type":"Point"}
}