{
  "type": "Feature",
  "properties": {
    "iso:country":"US",
    "sg:address":"1215 W 600 S",
    "sg:city":"Orem",
    "sg:classifiers":[
        {
            "category":"Building & Trades",
            "subcategory":"Landscaping Services",
            "type":"Services"
        }
    ],
    "sg:phone":"+1 801 222 9432",
    "sg:postcode":"84058",
    "sg:province":"UT",
    "sg:tags":[
        "tree"
    ],
    "wof:name":"River Mountain Tree Svc",
    "wof:placetype":"venue"
},
  "geometry": {"coordinates":[-111.723809,40.286302],"type":"Point"}
}