{
  "type": "Feature",
  "properties": {
    "iso:country":"US",
    "sg:address":"835 N Main St",
    "sg:city":"Bountiful",
    "sg:classifiers":[
        {
            "category":"Organizations",
            "subcategory":"Religious Organization",
            "type":"Services"
        }
    ],
    "sg:phone":"+1 801 298 5268",
    "sg:postcode":"84010",
    "sg:province":"UT",
    "wof:name":"Elca",
    "wof:placetype":"venue"
},
  "geometry": {"coordinates":[-111.87906599999999,40.898382],"type":"Point"}
}