{
  "type": "Feature",
  "properties": {
    "iso:country":"US",
    "sg:address":"2111 W 3300 S",
    "sg:city":"Ogden",
    "sg:classifiers":[
        {
            "category":"Building & Trades",
            "subcategory":"Construction",
            "type":"Services"
        }
    ],
    "sg:phone":"+1 801 731 4753",
    "sg:postcode":"84401",
    "sg:province":"UT",
    "sg:tags":[
        "concrete",
        "contractor"
    ],
    "wof:name":"R L Shaw & Co",
    "wof:placetype":"venue"
},
  "geometry": {"coordinates":[-112.033626,41.205018],"type":"Point"}
}