{
  "type": "Feature",
  "properties": {
    "iso:country":"US",
    "sg:address":"10448 Violet Dr",
    "sg:city":"Sandy",
    "sg:classifiers":[
        {
            "category":"Arts & Performance",
            "subcategory":"Theater",
            "type":"Entertainment"
        }
    ],
    "sg:phone":"+1 801 571 0371",
    "sg:postcode":"84094",
    "sg:province":"UT",
    "sg:tags":[
        "group"
    ],
    "wof:name":"Mona Etc",
    "wof:placetype":"venue"
},
  "geometry": {"coordinates":[-111.860902,40.56088],"type":"Point"}
}