{
  "type": "Feature",
  "properties": {
    "iso:country":"US",
    "sg:address":"136 Aaron Burr",
    "sg:city":"Big Water",
    "sg:classifiers":[
        {
            "category":"Real Estate",
            "subcategory":"Real Estate Agent",
            "type":"Services"
        }
    ],
    "sg:phone":"+1 435 675 9191",
    "sg:postcode":"84741",
    "sg:province":"UT",
    "sg:website":"www.lakepowellutah.com",
    "wof:name":"Palanquin Realty",
    "wof:placetype":"venue"
},
  "geometry": {"coordinates":[-111.664581,37.078986],"type":"Point"}
}