{
  "type": "Feature",
  "properties": {
    "iso:country":"US",
    "sg:address":"1134 N 500 W",
    "sg:city":"Provo",
    "sg:classifiers":[
        {
            "category":"Professional",
            "type":"Services"
        }
    ],
    "sg:phone":"+1 801 357 8179",
    "sg:postcode":"84601",
    "sg:province":"UT",
    "sg:tags":[
        "establishment"
    ],
    "wof:name":"Utah Valley Sports & Athletic",
    "wof:placetype":"venue"
},
  "geometry": {"coordinates":[-111.667342,40.246573],"type":"Point"}
}