{
  "type": "Feature",
  "properties": {
    "iso:country":"US",
    "sg:address":"177 W Center St",
    "sg:city":"Provo",
    "sg:classifiers":[
        {
            "category":"Organizations",
            "subcategory":"Community Association",
            "type":"Services"
        }
    ],
    "sg:phone":"+1 801 226 8647",
    "sg:postcode":"84601",
    "sg:province":"UT",
    "sg:tags":[
        "legal"
    ],
    "wof:name":"Save Our Scouts",
    "wof:placetype":"venue"
},
  "geometry": {"coordinates":[-111.661135,40.233579],"type":"Point"}
}