{
  "type": "Feature",
  "properties": {
    "iso:country":"US",
    "sg:address":"790 W 200 N",
    "sg:city":"Logan",
    "sg:classifiers":[
        {
            "category":"Building & Trades",
            "subcategory":"Construction",
            "type":"Services"
        }
    ],
    "sg:phone":"+1 435 752 5377",
    "sg:postcode":"84321",
    "sg:province":"UT",
    "sg:tags":[
        "road",
        "contractor"
    ],
    "wof:name":"Highway Dept Maintenance Shed",
    "wof:placetype":"venue"
},
  "geometry": {"coordinates":[-111.851202,41.735421],"type":"Point"}
}