{
  "type": "Feature",
  "properties": {
    "iso:country":"US",
    "sg:address":"4170 S 4850 W",
    "sg:city":"Salt Lake City",
    "sg:classifiers":[
        {
            "category":"Wholesale",
            "subcategory":"Apparel",
            "type":"Manufacturing & Wholesale Goods"
        }
    ],
    "sg:phone":"+1 801 969 0527",
    "sg:postcode":"84120",
    "sg:province":"UT",
    "sg:tags":[
        "clothing"
    ],
    "wof:name":"Golden Travel",
    "wof:placetype":"venue"
},
  "geometry": {"coordinates":[-112.006894,40.679241],"type":"Point"}
}