{
  "type": "Feature",
  "properties": {
    "iso:country":"US",
    "sg:address":"175 S Main St",
    "sg:city":"Salt Lake City",
    "sg:classifiers":[
        {
            "category":"Professional",
            "subcategory":"Lawyer & Legal Services",
            "type":"Services"
        }
    ],
    "sg:phone":"+1 801 532 6200",
    "sg:postcode":"84111",
    "sg:province":"UT",
    "sg:tags":[
        "attorney"
    ],
    "wof:name":"Boyack Ashton",
    "wof:placetype":"venue"
},
  "geometry": {"coordinates":[-111.891018,40.766641],"type":"Point"}
}