{
  "type": "Feature",
  "properties": {
    "iso:country":"US",
    "sg:address":"399 W 100 N",
    "sg:city":"Vernal",
    "sg:classifiers":[
        {
            "category":"Personal",
            "subcategory":"Beauty Salon",
            "type":"Services"
        }
    ],
    "sg:phone":"+1 435 789 5060",
    "sg:postcode":"84078",
    "sg:province":"UT",
    "sg:tags":[
        "shop"
    ],
    "wof:name":"Janet's Beauty Shop",
    "wof:placetype":"venue"
},
  "geometry": {"coordinates":[-109.53648800000001,40.457057],"type":"Point"}
}