{
  "type": "Feature",
  "properties": {
    "iso:country":"US",
    "sg:address":"4291 S 900 E",
    "sg:city":"Holladay",
    "sg:classifiers":[
        {
            "category":"Restaurant",
            "type":"Food & Drink"
        }
    ],
    "sg:phone":"+1 801 268 3374",
    "sg:postcode":"84124",
    "sg:province":"UT",
    "sg:website":"www.firehousebbq.com",
    "wof:name":"Firehouse Bbq Grill",
    "wof:placetype":"venue"
},
  "geometry": {"coordinates":[-111.865455,40.679849],"type":"Point"}
}