{
  "type": "Feature",
  "properties": {
    "iso:country":"US",
    "sg:address":"2033 Dan Dr",
    "sg:city":"Layton",
    "sg:classifiers":[
        {
            "category":"Real Estate",
            "subcategory":"Architect",
            "type":"Services"
        }
    ],
    "sg:phone":"+1 801 593 9338",
    "sg:postcode":"84040",
    "sg:province":"UT",
    "sg:tags":[
        "architectural"
    ],
    "wof:name":"KCB Architecture",
    "wof:placetype":"venue"
},
  "geometry": {"coordinates":[-111.92925099999999,41.085537],"type":"Point"}
}