{
  "type": "Feature",
  "properties": {
    "iso:country":"US",
    "sg:address":"821 E 12300 S",
    "sg:city":"Draper",
    "sg:classifiers":[
        {
            "category":"Retail",
            "subcategory":"Car Wash",
            "type":"Services"
        }
    ],
    "sg:phone":"+1 801 572 6110",
    "sg:postcode":"84020",
    "sg:province":"UT",
    "sg:tags":[
        "carwash"
    ],
    "wof:name":"Hidden Valley Car Wash",
    "wof:placetype":"venue"
},
  "geometry": {"coordinates":[-111.86676300000001,40.527003],"type":"Point"}
}