{
  "type": "Feature",
  "properties": {
    "iso:country":"US",
    "sg:address":"9672 Charleston Dr",
    "sg:city":"Pleasant Grove",
    "sg:classifiers":[
        {
            "category":"Organizations",
            "subcategory":"Labor Organization",
            "type":"Services"
        }
    ],
    "sg:phone":"+1 801 763 1757",
    "sg:postcode":"84062",
    "sg:province":"UT",
    "wof:name":"Bbk Enterprises Lc",
    "wof:placetype":"venue"
},
  "geometry": {"coordinates":[-111.761927,40.408693],"type":"Point"}
}