{
  "type": "Feature",
  "properties": {
    "iso:country":"US",
    "sg:address":"362 N Main St",
    "sg:city":"Heber City",
    "sg:classifiers":[
        {
            "category":"Home & Garden",
            "subcategory":"Furniture",
            "type":"Retail Goods"
        }
    ],
    "sg:phone":"+1 435 654 5555",
    "sg:postcode":"84032",
    "sg:province":"UT",
    "wof:name":"Pinto Pony Designs",
    "wof:placetype":"venue"
},
  "geometry": {"coordinates":[-111.41336200000001,40.512086],"type":"Point"}
}