{
  "type": "Feature",
  "properties": {
    "iso:country":"US",
    "sg:address":"10115 S 280 W",
    "sg:city":"Sandy",
    "sg:classifiers":[
        {
            "category":"Autos & Motor Vehicles",
            "subcategory":"Auto Supplies",
            "type":"Retail Goods"
        }
    ],
    "sg:phone":"+1 801 255 7244",
    "sg:postcode":"84070",
    "sg:province":"UT",
    "sg:tags":[
        "alternator",
        "generator"
    ],
    "wof:name":"Glade's Generator Svc",
    "wof:placetype":"venue"
},
  "geometry": {"coordinates":[-111.899051,40.567898],"type":"Point"}
}