{
  "type": "Feature",
  "properties": {
    "iso:country":"US",
    "sg:address":"2158 E Stone Canyon Cir",
    "sg:city":"St George",
    "sg:classifiers":[
        {
            "category":"Professional",
            "subcategory":"Management & Consulting",
            "type":"Services"
        }
    ],
    "sg:phone":"+1 435 656 2778",
    "sg:postcode":"84790",
    "sg:province":"UT",
    "wof:name":"Information Mgt Consulting",
    "wof:placetype":"venue"
},
  "geometry": {"coordinates":[-113.53994299999999,37.074162],"type":"Point"}
}