{
  "type": "Feature",
  "properties": {
    "iso:country":"US",
    "sg:address":"470 12th St",
    "sg:city":"Ogden",
    "sg:classifiers":[
        {
            "category":"Personal",
            "subcategory":"Beauty Salon",
            "type":"Services"
        }
    ],
    "sg:phone":"+1 801 621 2405",
    "sg:postcode":"84404",
    "sg:province":"UT",
    "sg:tags":[
        "shop"
    ],
    "wof:name":"Dollar Cuts Inc",
    "wof:placetype":"venue"
},
  "geometry": {"coordinates":[-111.968834,41.244353],"type":"Point"}
}