{
  "type": "Feature",
  "properties": {
    "iso:country":"US",
    "sg:address":"243 E Saint George Blvd",
    "sg:city":"St George",
    "sg:classifiers":[
        {
            "category":"Professional",
            "subcategory":"Employment Agencies",
            "type":"Services"
        }
    ],
    "sg:phone":"+1 435 652 0200",
    "sg:postcode":"84770",
    "sg:province":"UT",
    "sg:tags":[
        "employee",
        "leasing"
    ],
    "wof:name":"Resource Management Inc",
    "wof:placetype":"venue"
},
  "geometry": {"coordinates":[-113.578249,37.10995],"type":"Point"}
}