{
  "type": "Feature",
  "properties": {
    "iso:country":"US",
    "sg:address":"290 S Main St",
    "sg:city":"Bountiful",
    "sg:classifiers":[
        {
            "category":"Shopping",
            "subcategory":"Hobbies, Toys, & Games",
            "type":"Retail Goods"
        }
    ],
    "sg:phone":"+1 801 294 2900",
    "sg:postcode":"84010",
    "sg:province":"UT",
    "sg:tags":[
        "craft",
        "art",
        "supply"
    ],
    "wof:name":"Main Street Art Supply",
    "wof:placetype":"venue"
},
  "geometry": {"coordinates":[-111.88099699999999,40.8866],"type":"Point"}
}