{
  "type": "Feature",
  "properties": {
    "iso:country":"US",
    "sg:address":"3601 Constitution Blvd",
    "sg:city":"Salt Lake City",
    "sg:classifiers":[
        {
            "category":"Shopping",
            "subcategory":"Optical Goods",
            "type":"Retail Goods"
        }
    ],
    "sg:phone":"+1 801 840 0677",
    "sg:postcode":"84119",
    "sg:province":"UT",
    "sg:tags":[
        "sun",
        "goggles",
        "sunglasses"
    ],
    "wof:name":"Solar Shades",
    "wof:placetype":"venue"
},
  "geometry": {"coordinates":[-111.957919,40.69545],"type":"Point"}
}