{
  "type": "Feature",
  "properties": {
    "iso:country":"US",
    "sg:address":"702 S Main St",
    "sg:city":"Moab",
    "sg:classifiers":[
        {
            "category":"Shopping",
            "subcategory":"Department Store",
            "type":"Retail Goods"
        }
    ],
    "sg:phone":"+1 435 259 0491",
    "sg:postcode":"84532",
    "sg:province":"UT",
    "sg:tags":[
        "shop"
    ],
    "wof:name":"Family Dollar Store",
    "wof:placetype":"venue"
},
  "geometry": {"coordinates":[-109.55037900000001,38.565547],"type":"Point"}
}