{
  "type": "Feature",
  "properties": {
    "iso:country":"US",
    "sg:address":"3165 S State St",
    "sg:city":"Salt Lake City",
    "sg:classifiers":[
        {
            "category":"Retail",
            "subcategory":"Auto Repair",
            "type":"Services"
        }
    ],
    "sg:phone":"+1 801 486 6949",
    "sg:postcode":"84115",
    "sg:province":"UT",
    "sg:tags":[
        "automobile",
        "testing",
        "emission"
    ],
    "wof:name":"Super Emission",
    "wof:placetype":"venue"
},
  "geometry": {"coordinates":[-111.88819100000001,40.70241],"type":"Point"}
}