{
  "type": "Feature",
  "properties": {
    "iso:country":"US",
    "sg:address":"221 N Washington Blvd",
    "sg:city":"Ogden",
    "sg:classifiers":[
        {
            "category":"Government",
            "subcategory":"Post Office",
            "type":"Public Place"
        }
    ],
    "sg:phone":"+1 801 621 2180",
    "sg:postcode":"84404",
    "sg:province":"UT",
    "sg:tags":[
        "postal",
        "us"
    ],
    "wof:name":"US Post Office",
    "wof:placetype":"venue"
},
  "geometry": {"coordinates":[-111.96962499999999,41.26415],"type":"Point"}
}