{
  "type": "Feature",
  "properties": {
    "iso:country":"US",
    "sg:address":"400 High Bench Rd",
    "sg:city":"Alpine",
    "sg:classifiers":[
        {
            "category":"Farming",
            "subcategory":"Livestock Farm",
            "type":"Manufacturing & Wholesale Goods"
        }
    ],
    "sg:phone":"+1 801 756 8653",
    "sg:postcode":"84004",
    "sg:province":"UT",
    "sg:tags":[
        "ranch"
    ],
    "wof:name":"Gift Horse Ranch",
    "wof:placetype":"venue"
},
  "geometry": {"coordinates":[-111.762747,40.447883],"type":"Point"}
}