{
  "type": "Feature",
  "properties": {
    "iso:country":"US",
    "sg:address":"728 W 1425 N",
    "sg:city":"Layton",
    "sg:classifiers":[
        {
            "category":"Cinema",
            "subcategory":"Movie Theater",
            "type":"Entertainment"
        }
    ],
    "sg:phone":"+1 801 774 0800",
    "sg:postcode":"84041",
    "sg:province":"UT",
    "wof:name":"Cineplex Odeon",
    "wof:placetype":"venue"
},
  "geometry": {"coordinates":[-111.98171600000001,41.080723],"type":"Point"}
}