{
  "type": "Feature",
  "properties": {
    "iso:country":"US",
    "sg:address":"751 Main St",
    "sg:city":"Park City",
    "sg:classifiers":[
        {
            "category":"Shopping",
            "subcategory":"Clothing, Apparel, & Fashions",
            "type":"Retail Goods"
        }
    ],
    "sg:phone":"+1 435 649 3820",
    "sg:postcode":"84060",
    "sg:province":"UT",
    "sg:tags":[
        "wholesale",
        "fur",
        "furrier",
        "business"
    ],
    "wof:name":"Alaska Fur Gallery Inc",
    "wof:placetype":"venue"
},
  "geometry": {"coordinates":[-111.49764,40.646886],"type":"Point"}
}