{
  "type": "Feature",
  "properties": {
    "iso:country":"US",
    "sg:address":"360 S Main St",
    "sg:city":"Fillmore",
    "sg:classifiers":[
        {
            "category":"Real Estate",
            "subcategory":"Real Estate Agent",
            "type":"Services"
        }
    ],
    "sg:phone":"+1 435 743 6875",
    "sg:postcode":"84631",
    "sg:province":"UT",
    "sg:website":"www.daviesrealty.com",
    "wof:name":"Davies & Co Realty",
    "wof:placetype":"venue"
},
  "geometry": {"coordinates":[-112.323652,38.961028],"type":"Point"}
}