{
  "type": "Feature",
  "properties": {
    "iso:country":"US",
    "sg:address":"62 S Main St",
    "sg:city":"Alpine",
    "sg:classifiers":[
        {
            "category":"Real Estate",
            "subcategory":"Real Estate Agent",
            "type":"Services"
        }
    ],
    "sg:phone":"+1 801 756 2422",
    "sg:postcode":"84004",
    "sg:province":"UT",
    "wof:name":"Allpro Realty Group Inc",
    "wof:placetype":"venue"
},
  "geometry": {"coordinates":[-111.77790899999999,40.452451],"type":"Point"}
}