{
  "type": "Feature",
  "properties": {
    "iso:country":"US",
    "sg:address":"111 S 1200 E",
    "sg:city":"Lehi",
    "sg:classifiers":[
        {
            "category":"Professional",
            "subcategory":"Computer Services",
            "type":"Services"
        }
    ],
    "sg:phone":"+1 801 766 4191",
    "sg:postcode":"84043",
    "sg:province":"UT",
    "wof:name":"Northstar Computer Solutions",
    "wof:placetype":"venue"
},
  "geometry": {"coordinates":[-111.830635,40.38736],"type":"Point"}
}