{
  "type": "Feature",
  "properties": {
    "iso:country":"US",
    "sg:address":"270 N 200 W",
    "sg:city":"Cedar City",
    "sg:classifiers":[
        {
            "category":"Professional",
            "subcategory":"Business Services",
            "type":"Services"
        }
    ],
    "sg:phone":"+1 435 865 1238",
    "sg:postcode":"84720",
    "sg:province":"UT",
    "wof:name":"Deka Designs",
    "wof:placetype":"venue"
},
  "geometry": {"coordinates":[-113.065145,37.681567],"type":"Point"}
}