{
  "type": "Feature",
  "properties": {
    "iso:country":"US",
    "sg:address":"9253 S Redwood Rd",
    "sg:city":"West Jordan",
    "sg:classifiers":[
        {
            "category":"Social Services",
            "type":"Services"
        }
    ],
    "sg:phone":"+1 801 566 0749",
    "sg:postcode":"84088",
    "sg:province":"UT",
    "sg:tags":[
        "counselor",
        "marriage",
        "family"
    ],
    "wof:name":"Jordan West Family Counsel",
    "wof:placetype":"venue"
},
  "geometry": {"coordinates":[-111.937833,40.582509],"type":"Point"}
}