{
  "type": "Feature",
  "properties": {
    "iso:country":"US",
    "sg:address":"5002 Highland Dr",
    "sg:city":"Holladay",
    "sg:classifiers":[
        {
            "category":"Professional",
            "subcategory":"Accounting & Tax Preparation",
            "type":"Services"
        }
    ],
    "sg:phone":"+1 801 272 0412",
    "sg:postcode":"84117",
    "sg:province":"UT",
    "sg:tags":[
        "return",
        "filing"
    ],
    "wof:name":"H & R Block Tax Svc",
    "wof:placetype":"venue"
},
  "geometry": {"coordinates":[-111.836253,40.661286],"type":"Point"}
}