{
  "type": "Feature",
  "properties": {
    "iso:country":"US",
    "sg:address":"351 E 13800 S",
    "sg:city":"Draper",
    "sg:classifiers":[
        {
            "category":"Social Services",
            "subcategory":"Child Care",
            "type":"Services"
        }
    ],
    "sg:phone":"+1 801 571 4320",
    "sg:postcode":"84020",
    "sg:province":"UT",
    "sg:tags":[
        "day"
    ],
    "wof:name":"Jennys Daycare",
    "wof:placetype":"venue"
},
  "geometry": {"coordinates":[-111.878668,40.500749],"type":"Point"}
}