{
  "type": "Feature",
  "properties": {
    "iso:country":"US",
    "sg:address":"10006 Falcon Hurst Dr",
    "sg:city":"Sandy",
    "sg:classifiers":[
        {
            "category":"Building & Trades",
            "subcategory":"Construction",
            "type":"Services"
        }
    ],
    "sg:phone":"+1 801 571 7239",
    "sg:postcode":"84092",
    "sg:province":"UT",
    "sg:tags":[
        "contractor"
    ],
    "wof:name":"Sunset Plaster & Stucco",
    "wof:placetype":"venue"
},
  "geometry": {"coordinates":[-111.834794,40.569554],"type":"Point"}
}