{
  "type": "Feature",
  "properties": {
    "iso:country":"US",
    "sg:address":"389 S Main St",
    "sg:city":"Spanish Fork",
    "sg:classifiers":[
        {
            "category":"Home & Garden",
            "subcategory":"Home Furnishings",
            "type":"Retail Goods"
        }
    ],
    "sg:phone":"+1 801 798 8272",
    "sg:postcode":"84660",
    "sg:province":"UT",
    "sg:tags":[
        "quilting"
    ],
    "wof:name":"Quilted Memories",
    "wof:placetype":"venue"
},
  "geometry": {"coordinates":[-111.65488499999999,40.104734],"type":"Point"}
}