{
  "type": "Feature",
  "properties": {
    "iso:country":"US",
    "sg:address":"175 W 200 S",
    "sg:city":"Salt Lake City",
    "sg:classifiers":[
        {
            "category":"Professional",
            "subcategory":"Lawyer & Legal Services",
            "type":"Services"
        }
    ],
    "sg:phone":"+1 801 532 6996",
    "sg:postcode":"84101",
    "sg:province":"UT",
    "wof:name":"Laipis & Gray",
    "wof:placetype":"venue"
},
  "geometry": {"coordinates":[-111.895038,40.764923],"type":"Point"}
}