{
  "type": "Feature",
  "properties": {
    "iso:country":"US",
    "sg:address":"174 E Winchester St",
    "sg:city":"Murray",
    "sg:classifiers":[
        {
            "category":"Home & Garden",
            "subcategory":"Furniture",
            "type":"Retail Goods"
        }
    ],
    "sg:phone":"+1 801 892 3444",
    "sg:postcode":"84107",
    "sg:province":"UT",
    "sg:website":"www.drexelheritage.com",
    "wof:name":"Drexel Heritage Home Insprtns",
    "wof:placetype":"venue"
},
  "geometry": {"coordinates":[-111.88556800000001,40.632941],"type":"Point"}
}