{
  "type": "Feature",
  "properties": {
    "iso:country":"US",
    "sg:address":"244 W 300 S",
    "sg:city":"Provo",
    "sg:classifiers":[
        {
            "category":"Professional",
            "subcategory":"Accounting & Tax Preparation",
            "type":"Services"
        }
    ],
    "sg:phone":"+1 801 373 6920",
    "sg:postcode":"84601",
    "sg:province":"UT",
    "sg:tags":[
        "return",
        "filing"
    ],
    "wof:name":"Singleton's Tax Svc",
    "wof:placetype":"venue"
},
  "geometry": {"coordinates":[-111.663372,40.229776],"type":"Point"}
}