{
  "type": "Feature",
  "properties": {
    "iso:country":"US",
    "sg:address":"1245 E 8600 S",
    "sg:city":"Sandy",
    "sg:classifiers":[
        {
            "category":"Health Services",
            "subcategory":"Clinic",
            "type":"Services"
        }
    ],
    "sg:phone":"+1 801 566 0145",
    "sg:postcode":"84094",
    "sg:province":"UT",
    "sg:tags":[
        "center",
        "treatment",
        "outpatient",
        "rehabilitation"
    ],
    "wof:name":"HealthSouth",
    "wof:placetype":"venue"
},
  "geometry": {"coordinates":[-111.85327100000001,40.595122],"type":"Point"}
}