{
  "type": "Feature",
  "properties": {
    "iso:country":"US",
    "sg:address":"498 E 120 S",
    "sg:city":"Smithfield",
    "sg:classifiers":[
        {
            "category":"Wholesale",
            "subcategory":"Vending Machines",
            "type":"Manufacturing & Wholesale Goods"
        }
    ],
    "sg:phone":"+1 435 563 6945",
    "sg:postcode":"84335",
    "sg:province":"UT",
    "sg:tags":[
        "operator"
    ],
    "wof:name":"Dougs Vending",
    "wof:placetype":"venue"
},
  "geometry": {"coordinates":[-111.819154,41.833619],"type":"Point"}
}