{
  "type": "Feature",
  "properties": {
    "iso:country":"US",
    "sg:address":"46 N Broadway St",
    "sg:city":"Tooele",
    "sg:classifiers":[
        {
            "category":"Bars & Pubs",
            "type":"Food & Drink"
        }
    ],
    "sg:phone":"+1 435 882 7605",
    "sg:postcode":"84074",
    "sg:province":"UT",
    "sg:tags":[
        "lounge",
        "cocktail"
    ],
    "wof:name":"J & J Lounge A Private Club",
    "wof:placetype":"venue"
},
  "geometry": {"coordinates":[-112.287987,40.532241],"type":"Point"}
}