{
  "type": "Feature",
  "properties": {
    "iso:country":"US",
    "sg:address":"4084 W 5655 S",
    "sg:city":"Salt Lake City",
    "sg:classifiers":[
        {
            "category":"Building & Trades",
            "subcategory":"Construction",
            "type":"Services"
        }
    ],
    "sg:phone":"+1 801 964 8262",
    "sg:postcode":"84118",
    "sg:province":"UT",
    "sg:tags":[
        "carpentry",
        "contractor"
    ],
    "wof:name":"Pats Unfinished Woodcrafts",
    "wof:placetype":"venue"
},
  "geometry": {"coordinates":[-111.992446,40.648502],"type":"Point"}
}