{
  "type": "Feature",
  "properties": {
    "iso:country":"US",
    "sg:address":"2041 Sidewinder Dr",
    "sg:city":"Park City",
    "sg:classifiers":[
        {
            "category":"Professional",
            "subcategory":"Lawyer & Legal Services",
            "type":"Services"
        }
    ],
    "sg:phone":"+1 435 615 8792",
    "sg:postcode":"84060",
    "sg:province":"UT",
    "wof:name":"Mark A Kozak Atty",
    "wof:placetype":"venue"
},
  "geometry": {"coordinates":[-111.494998,40.664004],"type":"Point"}
}