{
  "type": "Feature",
  "properties": {
    "iso:country":"US",
    "sg:address":"722 W 100 S",
    "sg:city":"Heber City",
    "sg:classifiers":[
        {
            "category":"Professional",
            "subcategory":"Accounting & Tax Preparation",
            "type":"Services"
        }
    ],
    "sg:phone":"+1 435 654 3824",
    "sg:postcode":"84032",
    "sg:province":"UT",
    "sg:tags":[
        "accountant"
    ],
    "wof:name":"Brian L Winegar CPA",
    "wof:placetype":"venue"
},
  "geometry": {"coordinates":[-111.426171,40.506938],"type":"Point"}
}