{
  "type": "Feature",
  "properties": {
    "iso:country":"US",
    "sg:address":"810 E 4200 S",
    "sg:city":"Salt Lake City",
    "sg:classifiers":[
        {
            "category":"Building & Trades",
            "subcategory":"Construction",
            "type":"Services"
        }
    ],
    "sg:phone":"+1 801 266 6189",
    "sg:postcode":"84107",
    "sg:province":"UT",
    "sg:tags":[
        "contractor"
    ],
    "wof:name":"Guys Inc",
    "wof:placetype":"venue"
},
  "geometry": {"coordinates":[-111.869388,40.679926],"type":"Point"}
}