{
  "type": "Feature",
  "properties": {
    "iso:country":"US",
    "sg:address":"10469 S 1000 W",
    "sg:city":"South Jordan",
    "sg:classifiers":[
        {
            "category":"Professional",
            "subcategory":"Research",
            "type":"Services"
        },
        {
            "category":"Organizations",
            "subcategory":"Labor Organization",
            "type":"Services"
        }
    ],
    "sg:phone":"+1 801 254 9799",
    "sg:postcode":"84095",
    "sg:province":"UT",
    "sg:tags":[
        "environmental",
        "ecological"
    ],
    "wof:name":"Riding & Assoc Lc",
    "wof:placetype":"venue"
},
  "geometry": {"coordinates":[-111.91946799999999,40.562173],"type":"Point"}
}