{
  "type": "Feature",
  "properties": {
    "iso:country":"US",
    "sg:address":"1534 Santiago Ln",
    "sg:city":"Salt Lake City",
    "sg:classifiers":[
        {
            "category":"Building & Trades",
            "subcategory":"Plumbing",
            "type":"Services"
        }
    ],
    "sg:phone":"+1 801 944 5490",
    "sg:postcode":"84121",
    "sg:province":"UT",
    "sg:tags":[
        "excavation",
        "contractor"
    ],
    "wof:name":"D&G Excavating Inc",
    "wof:placetype":"venue"
},
  "geometry": {"coordinates":[-111.84934800000001,40.624866],"type":"Point"}
}