{
  "type": "Feature",
  "properties": {
    "iso:country":"US",
    "sg:address":"625 E Telegraph St",
    "sg:city":"Washington",
    "sg:classifiers":[
        {
            "category":"Personal",
            "subcategory":"Beauty Salon",
            "type":"Services"
        }
    ],
    "sg:phone":"+1 435 627 0899",
    "sg:postcode":"84780",
    "sg:province":"UT",
    "sg:tags":[
        "shop"
    ],
    "wof:name":"Regal Nail Salon",
    "wof:placetype":"venue"
},
  "geometry": {"coordinates":[-113.49755500000001,37.130354],"type":"Point"}
}