{
  "type": "Feature",
  "properties": {
    "iso:country":"US",
    "sg:address":"1904 Van Buren Ave",
    "sg:city":"Ogden",
    "sg:classifiers":[
        {
            "category":"Professional",
            "subcategory":"Computer Services",
            "type":"Services"
        }
    ],
    "sg:phone":"+1 801 399 5161",
    "sg:postcode":"84401",
    "sg:province":"UT",
    "sg:tags":[
        "consultant"
    ],
    "wof:name":"Edward Chemleski",
    "wof:placetype":"venue"
},
  "geometry": {"coordinates":[-111.950665,41.230942],"type":"Point"}
}