{
  "type": "Feature",
  "properties": {
    "iso:country":"US",
    "sg:address":"586 W 630 N",
    "sg:city":"American Fork",
    "sg:classifiers":[
        {
            "category":"Recreation",
            "type":"Entertainment"
        }
    ],
    "sg:phone":"+1 801 763 9905",
    "sg:postcode":"84003",
    "sg:province":"UT",
    "wof:name":"Memories Garden",
    "wof:placetype":"venue"
},
  "geometry": {"coordinates":[-111.814125,40.389262],"type":"Point"}
}