{
  "type": "Feature",
  "properties": {
    "iso:country":"US",
    "sg:address":"8920 S 1700 E",
    "sg:city":"Sandy",
    "sg:classifiers":[
        {
            "category":"Education",
            "subcategory":"School",
            "type":"Public Place"
        }
    ],
    "sg:phone":"+1 801 565 7492",
    "sg:postcode":"84093",
    "sg:province":"UT",
    "wof:name":"Silver Mesa Elementary School",
    "wof:placetype":"venue"
},
  "geometry": {"coordinates":[-111.84372999999999,40.589737],"type":"Point"}
}