{
  "type": "Feature",
  "properties": {
    "iso:country":"US",
    "sg:address":"136 E South Temple St",
    "sg:city":"Salt Lake City",
    "sg:classifiers":[
        {
            "category":"Professional",
            "subcategory":"Accounting & Tax Preparation",
            "type":"Services"
        }
    ],
    "sg:phone":"+1 801 363 3400",
    "sg:postcode":"84111",
    "sg:province":"UT",
    "wof:name":"Daines Goodwin & Co Cpas PC",
    "wof:placetype":"venue"
},
  "geometry": {"coordinates":[-111.886303,40.769274],"type":"Point"}
}