{
  "type": "Feature",
  "properties": {
    "iso:country":"US",
    "sg:address":"671 S 1000 E",
    "sg:city":"St George",
    "sg:classifiers":[
        {
            "category":"Personal",
            "subcategory":"Beauty Salon",
            "type":"Services"
        }
    ],
    "sg:phone":"+1 435 628 5419",
    "sg:postcode":"84790",
    "sg:province":"UT",
    "sg:tags":[
        "spa"
    ],
    "wof:name":"About Face Salon and Day Spa",
    "wof:placetype":"venue"
},
  "geometry": {"coordinates":[-113.562167,37.096754],"type":"Point"}
}