{
  "type": "Feature",
  "properties": {
    "iso:country":"US",
    "sg:address":"1220 E 7800 S",
    "sg:city":"Sandy",
    "sg:classifiers":[
        {
            "category":"Home & Garden",
            "subcategory":"Garden Supply",
            "type":"Retail Goods"
        }
    ],
    "sg:phone":"+1 801 561 9380",
    "sg:postcode":"84094",
    "sg:province":"UT",
    "wof:name":"Mitchells Nurs Gift & Floral",
    "wof:placetype":"venue"
},
  "geometry": {"coordinates":[-111.855377,40.609554],"type":"Point"}
}