{
  "type": "Feature",
  "properties": {
    "iso:country":"US",
    "sg:address":"580 S State St",
    "sg:city":"Orem",
    "sg:classifiers":[
        {
            "category":"Professional",
            "subcategory":"Detective & Security Services",
            "type":"Services"
        }
    ],
    "sg:phone":"+1 801 724 9913",
    "sg:postcode":"84058",
    "sg:province":"UT",
    "sg:tags":[
        "system"
    ],
    "sg:website":"www.billreminders.com",
    "wof:name":"Apex Training & Development",
    "wof:placetype":"venue"
},
  "geometry": {"coordinates":[-111.69098200000001,40.28803],"type":"Point"}
}