{
  "type": "Feature",
  "properties": {
    "iso:country":"US",
    "sg:address":"7260 S Racquet Club Dr",
    "sg:city":"Salt Lake City",
    "sg:classifiers":[
        {
            "category":"Wholesale",
            "subcategory":"Medical Equipment & Supplies",
            "type":"Manufacturing & Wholesale Goods"
        }
    ],
    "sg:phone":"+1 801 944 1590",
    "sg:postcode":"84121",
    "sg:province":"UT",
    "wof:name":"Framework Fabrications Inc",
    "wof:placetype":"venue"
},
  "geometry": {"coordinates":[-111.791849,40.618122],"type":"Point"}
}