{
  "type": "Feature",
  "properties": {
    "iso:country":"US",
    "sg:address":"4250 Harrison Blvd",
    "sg:city":"Ogden",
    "sg:classifiers":[
        {
            "category":"Restaurant",
            "type":"Food & Drink"
        }
    ],
    "sg:phone":"+1 801 621 3167",
    "sg:postcode":"84403",
    "sg:province":"UT",
    "wof:name":"Tasty's",
    "wof:placetype":"venue"
},
  "geometry": {"coordinates":[-111.948954,41.186063],"type":"Point"}
}