{
  "type": "Feature",
  "properties": {
    "iso:country":"US",
    "sg:address":"4643 S 4000 W",
    "sg:city":"West Valley",
    "sg:classifiers":[
        {
            "category":"Banks & Credit Unions",
            "subcategory":"Bank",
            "type":"Services"
        }
    ],
    "sg:phone":"+1 801 974 8800",
    "sg:postcode":"84120",
    "sg:province":"UT",
    "wof:name":"Zions First National Bank",
    "wof:placetype":"venue"
},
  "geometry": {"coordinates":[-111.98544699999999,40.670481],"type":"Point"}
}