{
  "type": "Feature",
  "properties": {
    "iso:country":"US",
    "sg:address":"2393 Sundown Ave",
    "sg:city":"Salt Lake City",
    "sg:classifiers":[
        {
            "category":"Banks & Credit Unions",
            "subcategory":"Financial Services",
            "type":"Services"
        }
    ],
    "sg:phone":"+1 801 942 5727",
    "sg:postcode":"84121",
    "sg:province":"UT",
    "sg:tags":[
        "company",
        "holding"
    ],
    "wof:name":"Fantastic Sams",
    "wof:placetype":"venue"
},
  "geometry": {"coordinates":[-111.824715,40.62706],"type":"Point"}
}