{
  "type": "Feature",
  "properties": {
    "iso:country":"US",
    "sg:address":"1639 W 6160 S",
    "sg:city":"Salt Lake City",
    "sg:classifiers":[
        {
            "category":"Manufacturing",
            "subcategory":"Apparel",
            "type":"Manufacturing & Wholesale Goods"
        }
    ],
    "sg:phone":"+1 801 261 4151",
    "sg:postcode":"84123",
    "sg:province":"UT",
    "sg:tags":[
        "bag",
        "mfg",
        "sleeping"
    ],
    "wof:name":"Storm Mountain Outdoor Pdts",
    "wof:placetype":"venue"
},
  "geometry": {"coordinates":[-111.93811100000001,40.639424],"type":"Point"}
}