{
  "type": "Feature",
  "properties": {
    "iso:country":"US",
    "sg:address":"580 N Redwood Rd",
    "sg:city":"North Salt Lake",
    "sg:classifiers":[
        {
            "category":"Home & Garden",
            "subcategory":"Furniture",
            "type":"Retail Goods"
        }
    ],
    "sg:phone":"+1 801 296 1698",
    "sg:postcode":"84054",
    "sg:province":"UT",
    "sg:tags":[
        "cabinet"
    ],
    "wof:name":"Client's Design",
    "wof:placetype":"venue"
},
  "geometry": {"coordinates":[-111.92968500000001,40.847114],"type":"Point"}
}