{
  "type": "Feature",
  "properties": {
    "iso:country":"US",
    "sg:address":"2024 Princeton Ave",
    "sg:city":"Salt Lake City",
    "sg:classifiers":[
        {
            "category":"Insurance",
            "subcategory":"Hazard Insurance",
            "type":"Services"
        }
    ],
    "sg:phone":"+1 801 581 1919",
    "sg:postcode":"84108",
    "sg:province":"UT",
    "sg:tags":[
        "profit",
        "sharing",
        "pension",
        "plan"
    ],
    "wof:name":"Dan Marriott & Co",
    "wof:placetype":"venue"
},
  "geometry": {"coordinates":[-111.832768,40.744417],"type":"Point"}
}