{
  "type": "Feature",
  "properties": {
    "iso:country":"US",
    "sg:address":"667 Country Club",
    "sg:city":"Tooele",
    "sg:classifiers":[
        {
            "category":"Wholesale",
            "subcategory":"Machinery & Supplies",
            "type":"Manufacturing & Wholesale Goods"
        }
    ],
    "sg:phone":"+1 435 843 4520",
    "sg:postcode":"84074",
    "sg:province":"UT",
    "sg:tags":[
        "equipment",
        "welding"
    ],
    "wof:name":"Harrell's Welding Supply",
    "wof:placetype":"venue"
},
  "geometry": {"coordinates":[-112.299423,40.637855],"type":"Point"}
}