{
  "type": "Feature",
  "properties": {
    "iso:country":"US",
    "sg:address":"625 S Redwood Rd",
    "sg:city":"Salt Lake City",
    "sg:classifiers":[
        {
            "category":"Real Estate",
            "subcategory":"Real Estate Operator",
            "type":"Services"
        }
    ],
    "sg:phone":"+1 801 973 2721",
    "sg:postcode":"84104",
    "sg:province":"UT",
    "sg:tags":[
        "building",
        "apartment"
    ],
    "wof:name":"Eagles Landing",
    "wof:placetype":"venue"
},
  "geometry": {"coordinates":[-111.938936,40.75556],"type":"Point"}
}