{
  "type": "Feature",
  "properties": {
    "iso:country":"US",
    "sg:address":"195 S 100 W",
    "sg:city":"Logan",
    "sg:classifiers":[
        {
            "category":"Recreation",
            "type":"Entertainment"
        }
    ],
    "sg:phone":"+1 435 716 9260",
    "sg:postcode":"84321",
    "sg:province":"UT",
    "sg:tags":[
        "parks"
    ],
    "sg:website":"www.loganutah.org",
    "wof:name":"Logan Parks Dept",
    "wof:placetype":"venue"
},
  "geometry": {"coordinates":[-111.837748,41.72786],"type":"Point"}
}