{
  "type": "Feature",
  "properties": {
    "iso:country":"US",
    "sg:address":"36 W Main St",
    "sg:city":"Ferron",
    "sg:classifiers":[
        {
            "category":"Food & Beverages",
            "subcategory":"Specialty",
            "type":"Retail Goods"
        }
    ],
    "sg:phone":"+1 435 384 2137",
    "sg:postcode":"84523",
    "sg:province":"UT",
    "sg:tags":[
        "vitamin"
    ],
    "wof:name":"Vital-Ex Distribution",
    "wof:placetype":"venue"
},
  "geometry": {"coordinates":[-111.132745,39.090086],"type":"Point"}
}