{
  "type": "Feature",
  "properties": {
    "iso:country":"US",
    "sg:address":"1136 Front St",
    "sg:city":"Evanston",
    "sg:classifiers":[
        {
            "category":"Local Transit",
            "type":"Transportation"
        }
    ],
    "sg:phone":"+1 307 789 8599",
    "sg:postcode":"82930",
    "sg:province":"UT",
    "sg:tags":[
        "passenger"
    ],
    "wof:name":"Uinta County Ambulance Service",
    "wof:placetype":"venue"
},
  "geometry": {"coordinates":[-110.96660900000001,41.269458],"type":"Point"}
}