{
  "type": "Feature",
  "properties": {
    "iso:country":"US",
    "sg:address":"1124 S 300 W",
    "sg:city":"Salt Lake City",
    "sg:classifiers":[
        {
            "category":"Manufacturing",
            "subcategory":"Tools & Machinery",
            "type":"Manufacturing & Wholesale Goods"
        },
        {
            "category":"Retail",
            "subcategory":"Auto Repair",
            "type":"Services"
        }
    ],
    "sg:phone":"+1 801 364 6427",
    "sg:postcode":"84101",
    "sg:province":"UT",
    "sg:tags":[
        "shop",
        "automobile",
        "machine",
        "industrial",
        "mfg"
    ],
    "wof:name":"Crankshaft Grind Metalizing Co",
    "wof:placetype":"venue"
},
  "geometry": {"coordinates":[-111.89973500000001,40.745207],"type":"Point"}
}