{
  "type": "Feature",
  "properties": {
    "iso:country":"US",
    "sg:address":"5236 Heather Ln",
    "sg:city":"Park City",
    "sg:classifiers":[
        {
            "category":"Building & Trades",
            "subcategory":"Construction",
            "type":"Services"
        }
    ],
    "sg:phone":"+1 435 615 6709",
    "sg:postcode":"84098",
    "sg:province":"UT",
    "sg:tags":[
        "contractor"
    ],
    "wof:name":"Antaya & Brownell Construction",
    "wof:placetype":"venue"
},
  "geometry": {"coordinates":[-111.54280799999999,40.708247],"type":"Point"}
}