{
  "type": "Feature",
  "properties": {
    "iso:country":"US",
    "sg:address":"5949 Blue Meadow Dr",
    "sg:city":"Kearns",
    "sg:classifiers":[
        {
            "category":"Building & Trades",
            "subcategory":"Cleaning & Sanitation",
            "type":"Services"
        }
    ],
    "sg:phone":"+1 801 963 6575",
    "sg:postcode":"84118",
    "sg:province":"UT",
    "sg:tags":[
        "janitor"
    ],
    "wof:name":"Metropolitan Building Mntnc",
    "wof:placetype":"venue"
},
  "geometry": {"coordinates":[-111.984478,40.644201],"type":"Point"}
}