{
  "type": "Feature",
  "properties": {
    "iso:country":"US",
    "sg:address":"750 N Main St",
    "sg:city":"Layton",
    "sg:classifiers":[
        {
            "category":"Home & Garden",
            "subcategory":"Home Furnishings",
            "type":"Retail Goods"
        }
    ],
    "sg:phone":"+1 801 544 2171",
    "sg:postcode":"84041",
    "sg:province":"UT",
    "sg:tags":[
        "housewares"
    ],
    "wof:name":"Bed Bath & Beyond",
    "wof:placetype":"venue"
},
  "geometry": {"coordinates":[-111.9772,41.071324],"type":"Point"}
}