{
  "type": "Feature",
  "properties": {
    "iso:country":"US",
    "sg:address":"1111 S Orem Blvd",
    "sg:city":"Orem",
    "sg:classifiers":[
        {
            "category":"Professional",
            "subcategory":"Advertising",
            "type":"Services"
        }
    ],
    "sg:phone":"+1 801 226 6201",
    "sg:postcode":"84058",
    "sg:province":"UT",
    "sg:tags":[
        "counselor"
    ],
    "sg:website":"www.tko.com",
    "wof:name":"TKO Advertising",
    "wof:placetype":"venue"
},
  "geometry": {"coordinates":[-111.688253,40.276311],"type":"Point"}
}