{
  "type": "Feature",
  "properties": {
    "iso:country":"US",
    "sg:address":"2450 Lucky John Dr",
    "sg:city":"Park City",
    "sg:classifiers":[
        {
            "category":"Arts & Performance",
            "subcategory":"Theater",
            "type":"Entertainment"
        }
    ],
    "sg:phone":"+1 435 649 5545",
    "sg:postcode":"84060",
    "sg:province":"UT",
    "sg:tags":[
        "theatrical"
    ],
    "wof:name":"Storybook Players & Theatre Co",
    "wof:placetype":"venue"
},
  "geometry": {"coordinates":[-111.50135,40.667394],"type":"Point"}
}