{
  "type": "Feature",
  "properties": {
    "iso:country":"US",
    "sg:address":"415 W 1200 North St",
    "sg:city":"Orem",
    "sg:classifiers":[
        {
            "category":"Shopping",
            "subcategory":"Clothing, Apparel, & Fashions",
            "type":"Retail Goods"
        }
    ],
    "sg:phone":"+1 801 434 5434",
    "sg:postcode":"84057",
    "sg:province":"UT",
    "sg:tags":[
        "dancing",
        "supply"
    ],
    "wof:name":"Marianne's Custom Sewing",
    "wof:placetype":"venue"
},
  "geometry": {"coordinates":[-111.705456,40.319172],"type":"Point"}
}