{
  "type": "Feature",
  "properties": {
    "iso:country":"US",
    "sg:address":"444 N 200 W",
    "sg:city":"American Fork",
    "sg:classifiers":[
        {
            "category":"Shopping",
            "subcategory":"Catalog Store",
            "type":"Retail Goods"
        }
    ],
    "sg:phone":"+1 801 756 2313",
    "sg:postcode":"84003",
    "sg:province":"UT",
    "sg:tags":[
        "mail",
        "house"
    ],
    "wof:name":"Grammas Creations",
    "wof:placetype":"venue"
},
  "geometry": {"coordinates":[-111.803658,40.386194],"type":"Point"}
}