{
  "type": "Feature",
  "properties": {
    "iso:country":"US",
    "sg:address":"425 N 700 W",
    "sg:city":"Salt Lake City",
    "sg:classifiers":[
        {
            "category":"Organizations",
            "subcategory":"Religious Organization",
            "type":"Services"
        }
    ],
    "sg:phone":"+1 801 534 0635",
    "sg:postcode":"84116",
    "sg:province":"UT",
    "wof:name":"Church Of God Of Prophecy",
    "wof:placetype":"venue"
},
  "geometry": {"coordinates":[-111.91097000000001,40.780145],"type":"Point"}
}