{
  "type": "Feature",
  "properties": {
    "iso:country":"US",
    "sg:address":"5809 S 3500 W",
    "sg:city":"Roy",
    "sg:classifiers":[
        {
            "category":"Professional",
            "subcategory":"Business Services",
            "type":"Services"
        }
    ],
    "sg:phone":"+1 801 776 8956",
    "sg:postcode":"84067",
    "sg:province":"UT",
    "wof:name":"Peakbiz Solutions LLC",
    "wof:placetype":"venue"
},
  "geometry": {"coordinates":[-112.064542,41.159003],"type":"Point"}
}