{
  "type": "Feature",
  "properties": {
    "iso:country":"US",
    "sg:address":"812 E 2100 S",
    "sg:city":"Salt Lake City",
    "sg:classifiers":[
        {
            "category":"Shopping",
            "subcategory":"Shoes",
            "type":"Retail Goods"
        }
    ],
    "sg:phone":"+1 801 487 2181",
    "sg:postcode":"84106",
    "sg:province":"UT",
    "wof:name":"Payless Shoesource",
    "wof:placetype":"venue"
},
  "geometry": {"coordinates":[-111.867103,40.725344],"type":"Point"}
}