{
  "type": "Feature",
  "properties": {
    "iso:country":"US",
    "sg:address":"1064 S 1950 W",
    "sg:city":"Delta",
    "sg:classifiers":[
        {
            "category":"Organizations",
            "subcategory":"Community Association",
            "type":"Services"
        }
    ],
    "sg:phone":"+1 435 864 3120",
    "sg:postcode":"84624",
    "sg:province":"UT",
    "wof:name":"Country Esttes Lot Owners Assn",
    "wof:placetype":"venue"
},
  "geometry": {"coordinates":[-112.612951,39.33438],"type":"Point"}
}