{
  "type": "Feature",
  "properties": {
    "iso:country":"US",
    "sg:address":"15024 Rose Creek Ln",
    "sg:city":"Riverton",
    "sg:classifiers":[
        {
            "category":"Professional",
            "subcategory":"Business Services",
            "type":"Services"
        }
    ],
    "sg:phone":"+1 801 253 7381",
    "sg:postcode":"84096",
    "sg:province":"UT",
    "wof:name":"Classic Fit Interiors",
    "wof:placetype":"venue"
},
  "geometry": {"coordinates":[-112.064955,40.480515],"type":"Point"}
}