{
  "type": "Feature",
  "properties": {
    "iso:country":"US",
    "sg:address":"230 W 170 N",
    "sg:city":"Orem",
    "sg:classifiers":[
        {
            "category":"Professional",
            "subcategory":"Management & Consulting",
            "type":"Services"
        }
    ],
    "sg:phone":"+1 801 235 1757",
    "sg:postcode":"84057",
    "sg:province":"UT",
    "sg:tags":[
        "business"
    ],
    "wof:name":"Zebra Consulting",
    "wof:placetype":"venue"
},
  "geometry": {"coordinates":[-111.70124300000001,40.300466],"type":"Point"}
}