{
  "type": "Feature",
  "properties": {
    "iso:country":"US",
    "sg:address":"350 North St",
    "sg:city":"Ogden",
    "sg:classifiers":[
        {
            "category":"Shopping",
            "subcategory":"Gifts & Souvenirs",
            "type":"Retail Goods"
        }
    ],
    "sg:phone":"+1 801 782 4057",
    "sg:postcode":"84404",
    "sg:province":"UT",
    "wof:name":"Dawns Rae Gifts LLC",
    "wof:placetype":"venue"
},
  "geometry": {"coordinates":[-111.9863,41.266715],"type":"Point"}
}