{
  "type": "Feature",
  "properties": {
    "iso:country":"US",
    "sg:address":"595 E 400 S",
    "sg:city":"Price",
    "sg:classifiers":[
        {
            "category":"Government",
            "subcategory":"Office",
            "type":"Public Place"
        }
    ],
    "sg:phone":"+1 435 636 3180",
    "sg:postcode":"84501",
    "sg:province":"UT",
    "sg:tags":[
        "village"
    ],
    "wof:name":"Price Cemetery",
    "wof:placetype":"venue"
},
  "geometry": {"coordinates":[-110.79996199999999,39.593818],"type":"Point"}
}