{
  "type": "Feature",
  "properties": {
    "iso:country":"US",
    "sg:address":"2278 Lexington Park Dr",
    "sg:city":"Salt Lake City",
    "sg:classifiers":[
        {
            "category":"Professional",
            "subcategory":"Computer Services",
            "type":"Services"
        }
    ],
    "sg:phone":"+1 801 956 2062",
    "sg:postcode":"84119",
    "sg:province":"UT",
    "wof:name":"Bytes & Pieces",
    "wof:placetype":"venue"
},
  "geometry": {"coordinates":[-111.948921,40.691795],"type":"Point"}
}