{
  "type": "Feature",
  "properties": {
    "iso:country":"US",
    "sg:address":"10 Exchange Pl",
    "sg:city":"Salt Lake City",
    "sg:classifiers":[
        {
            "category":"Real Estate",
            "subcategory":"Developer",
            "type":"Services"
        }
    ],
    "sg:phone":"+1 801 746 2888",
    "sg:postcode":"84111",
    "sg:province":"UT",
    "wof:name":"Hamilton Partners",
    "wof:placetype":"venue"
},
  "geometry": {"coordinates":[-111.88984000000001,40.761332],"type":"Point"}
}