{
  "type": "Feature",
  "properties": {
    "iso:country":"US",
    "sg:address":"92 N Main St",
    "sg:city":"Spanish Fork",
    "sg:classifiers":[
        {
            "category":"Real Estate",
            "subcategory":"Real Estate Agent",
            "type":"Services"
        }
    ],
    "sg:phone":"+1 801 798 9212",
    "sg:postcode":"84660",
    "sg:province":"UT",
    "sg:tags":[
        "cooperative"
    ],
    "wof:name":"Preston G Hughes Coop",
    "wof:placetype":"venue"
},
  "geometry": {"coordinates":[-111.654702,40.109915],"type":"Point"}
}