{
  "type": "Feature",
  "properties": {
    "iso:country":"US",
    "sg:address":"8510 W 10200 S",
    "sg:city":"Bingham Canyon",
    "sg:classifiers":[
        {
            "category":"Retail",
            "subcategory":"Auto Repair",
            "type":"Services"
        }
    ],
    "sg:phone":"+1 801 562 0605",
    "sg:postcode":"84006",
    "sg:province":"UT",
    "sg:tags":[
        "repairing",
        "automobile"
    ],
    "wof:name":"P & G Automotive",
    "wof:placetype":"venue"
},
  "geometry": {"coordinates":[-112.094086,40.56612],"type":"Point"}
}