{
  "type": "Feature",
  "properties": {
    "iso:country":"US",
    "sg:address":"2871 S 2870 E",
    "sg:city":"Salt Lake City",
    "sg:classifiers":[
        {
            "category":"Home & Garden",
            "subcategory":"Home Furnishings",
            "type":"Retail Goods"
        }
    ],
    "sg:phone":"+1 801 486 1900",
    "sg:postcode":"84109",
    "sg:province":"UT",
    "wof:name":"Window Quilt Of Utah",
    "wof:placetype":"venue"
},
  "geometry": {"coordinates":[-111.81088699999999,40.70918],"type":"Point"}
}