{
  "type": "Feature",
  "properties": {
    "iso:country":"US",
    "sg:address":"2253 W 13400 S",
    "sg:city":"Riverton",
    "sg:classifiers":[
        {
            "category":"Wholesale",
            "subcategory":"Computers",
            "type":"Manufacturing & Wholesale Goods"
        }
    ],
    "sg:phone":"+1 801 244 4159",
    "sg:postcode":"84065",
    "sg:province":"UT",
    "wof:name":"PM Concepts",
    "wof:placetype":"venue"
},
  "geometry": {"coordinates":[-111.949235,40.507697],"type":"Point"}
}