{
  "type": "Feature",
  "properties": {
    "iso:country":"US",
    "sg:address":"5 S Main St",
    "sg:city":"Ephraim",
    "sg:classifiers":[
        {
            "category":"Government",
            "subcategory":"Office",
            "type":"Public Place"
        }
    ],
    "sg:phone":"+1 435 283 4631",
    "sg:postcode":"84627",
    "sg:province":"UT",
    "sg:tags":[
        "executive"
    ],
    "wof:name":"City of Ephraim",
    "wof:placetype":"venue"
},
  "geometry": {"coordinates":[-111.586989,39.359714],"type":"Point"}
}