{
  "type": "Feature",
  "properties": {
    "iso:country":"US",
    "sg:address":"3065 W 5400 S",
    "sg:city":"Salt Lake City",
    "sg:classifiers":[
        {
            "category":"Banks & Credit Unions",
            "subcategory":"Bank",
            "type":"Services"
        }
    ],
    "sg:phone":"+1 801 486 7255",
    "sg:postcode":"84118",
    "sg:province":"UT",
    "wof:name":"Salt Lake City Credit Union",
    "wof:placetype":"venue"
},
  "geometry": {"coordinates":[-111.964731,40.653021],"type":"Point"}
}