{
  "type": "Feature",
  "properties": {
    "iso:country":"US",
    "sg:address":"166 W 2040 N",
    "sg:city":"Lehi",
    "sg:classifiers":[
        {
            "category":"Insurance",
            "subcategory":"Insurance Agent",
            "type":"Services"
        }
    ],
    "sg:phone":"+1 801 768 1206",
    "sg:postcode":"84043",
    "sg:province":"UT",
    "wof:name":"Horace Mann Insurance Co",
    "wof:placetype":"venue"
},
  "geometry": {"coordinates":[-111.852586,40.412916],"type":"Point"}
}