{
  "type": "Feature",
  "properties": {
    "iso:country":"US",
    "sg:address":"5283 Elk Horn Peak Dr",
    "sg:city":"Riverton",
    "sg:classifiers":[
        {
            "category":"Real Estate",
            "subcategory":"Real Estate Agent",
            "type":"Services"
        }
    ],
    "sg:phone":"+1 801 446 0401",
    "sg:postcode":"84065",
    "sg:province":"UT",
    "wof:name":"Don A Matthews 2 Real Estate",
    "wof:placetype":"venue"
},
  "geometry": {"coordinates":[-112.016113,40.493604],"type":"Point"}
}