{
  "type": "Feature",
  "properties": {
    "iso:country":"US",
    "sg:address":"175 S 350 E",
    "sg:city":"Farmington",
    "sg:classifiers":[
        {
            "category":"Retail",
            "subcategory":"Repair Shop",
            "type":"Services"
        }
    ],
    "sg:phone":"+1 801 451 7639",
    "sg:postcode":"84025",
    "sg:province":"UT",
    "wof:name":"OH Dolly My Dolly",
    "wof:placetype":"venue"
},
  "geometry": {"coordinates":[-111.879541,40.979974],"type":"Point"}
}