{
  "type": "Feature",
  "properties": {
    "iso:country":"US",
    "sg:address":"3898 S 900 E",
    "sg:city":"Salt Lake City",
    "sg:classifiers":[
        {
            "category":"Autos & Motor Vehicles",
            "subcategory":"Fuel & Gas Station",
            "type":"Retail Goods"
        }
    ],
    "sg:phone":"+1 801 264 8503",
    "sg:postcode":"84106",
    "sg:province":"UT",
    "sg:tags":[
        "oil"
    ],
    "wof:name":"Phillips 66",
    "wof:placetype":"venue"
},
  "geometry": {"coordinates":[-111.86550200000001,40.687675],"type":"Point"}
}