{
  "type": "Feature",
  "properties": {
    "iso:country":"US",
    "sg:address":"579 Heritage Park Blvd",
    "sg:city":"Layton",
    "sg:classifiers":[
        {
            "category":"Professional",
            "subcategory":"Business Services",
            "type":"Services"
        }
    ],
    "sg:phone":"+1 801 728 7000",
    "sg:postcode":"84041",
    "sg:province":"UT",
    "wof:name":"Park Place Suites",
    "wof:placetype":"venue"
},
  "geometry": {"coordinates":[-111.97761800000001,41.083035],"type":"Point"}
}