{
  "type": "Feature",
  "properties": {
    "iso:country":"US",
    "sg:address":"79 N 1020 W",
    "sg:city":"American Fork",
    "sg:classifiers":[
        {
            "category":"Manufacturing",
            "subcategory":"Electronics",
            "type":"Manufacturing & Wholesale Goods"
        },
        {
            "category":"Wholesale",
            "subcategory":"Electrical",
            "type":"Manufacturing & Wholesale Goods"
        }
    ],
    "sg:phone":"+1 801 763 5687",
    "sg:postcode":"84003",
    "sg:province":"UT",
    "sg:tags":[
        "control",
        "equipment",
        "security",
        "system"
    ],
    "wof:name":"Security Innovations Inc",
    "wof:placetype":"venue"
},
  "geometry": {"coordinates":[-111.824896,40.377235],"type":"Point"}
}