{
  "type": "Feature",
  "properties": {
    "iso:country":"US",
    "sg:address":"608 S Main St",
    "sg:city":"Layton",
    "sg:classifiers":[
        {
            "category":"Personal",
            "type":"Services"
        },
        {
            "category":"Retail",
            "subcategory":"Auto Rental",
            "type":"Services"
        },
        {
            "category":"Freight",
            "type":"Transportation"
        },
        {
            "category":"Retail",
            "subcategory":"Storage",
            "type":"Services"
        }
    ],
    "sg:phone":"+1 801 544 3843",
    "sg:postcode":"84041",
    "sg:province":"UT",
    "sg:tags":[
        "renting",
        "moving-self",
        "full",
        "leasing",
        "trucking",
        "truck",
        "mover",
        "local",
        "trailer"
    ],
    "sg:website":"http://www.uhaul.com/Locations/Rentals-near-Layton-UT-84041/031231",
    "wof:name":"U-Haul Neighborhood Dealer - Pool Pleasures",
    "wof:placetype":"venue"
},
  "geometry": {"coordinates":[-111.959125,41.051341],"type":"Point"}
}