{
  "type": "Feature",
  "properties": {
    "iso:country":"US",
    "sg:address":"7786 Prospector Dr",
    "sg:city":"Salt Lake City",
    "sg:classifiers":[
        {
            "category":"Building & Trades",
            "subcategory":"Construction",
            "type":"Services"
        }
    ],
    "sg:phone":"+1 801 272 6439",
    "sg:postcode":"84121",
    "sg:province":"UT",
    "wof:name":"D R D Paving",
    "wof:placetype":"venue"
},
  "geometry": {"coordinates":[-111.789581,40.609525],"type":"Point"}
}