{
  "type": "Feature",
  "properties": {
    "iso:country":"US",
    "sg:address":"2962 Wildflower Ct",
    "sg:city":"Park City",
    "sg:classifiers":[
        {
            "category":"Building & Trades",
            "subcategory":"Construction",
            "type":"Services"
        }
    ],
    "sg:phone":"+1 435 649 9185",
    "sg:postcode":"84098",
    "sg:province":"UT",
    "sg:tags":[
        "heavy"
    ],
    "wof:name":"Db Jones Construction",
    "wof:placetype":"venue"
},
  "geometry": {"coordinates":[-111.568817,40.748624],"type":"Point"}
}