{
  "type": "Feature",
  "properties": {
    "iso:country":"US",
    "sg:address":"2170 W North Temple",
    "sg:city":"Salt Lake City",
    "sg:classifiers":[
        {
            "category":"Travel",
            "subcategory":"Hotels & Motels",
            "type":"Entertainment"
        }
    ],
    "sg:phone":"+1 801 359 7500",
    "sg:postcode":"84116",
    "sg:province":"UT",
    "wof:name":"Candlewood Suites",
    "wof:placetype":"venue"
},
  "geometry": {"coordinates":[-111.95276699999999,40.771586],"type":"Point"}
}