{
  "type": "Feature",
  "properties": {
    "iso:country":"US",
    "sg:address":"1474 Harrop St",
    "sg:city":"Ogden",
    "sg:classifiers":[
        {
            "category":"Retail",
            "subcategory":"Laundry & Dry Cleaning",
            "type":"Services"
        }
    ],
    "sg:phone":"+1 801 399 1441",
    "sg:postcode":"84404",
    "sg:province":"UT",
    "sg:tags":[
        "upholstery",
        "carpet"
    ],
    "wof:name":"Shaws Carpet Service",
    "wof:placetype":"venue"
},
  "geometry": {"coordinates":[-111.94058200000001,41.256044],"type":"Point"}
}