{
  "type": "Feature",
  "properties": {
    "iso:country":"US",
    "sg:address":"491 E 400 S",
    "sg:city":"Kanab",
    "sg:classifiers":[
        {
            "category":"Wholesale",
            "subcategory":"Groceries",
            "type":"Manufacturing & Wholesale Goods"
        },
        {
            "category":"Wholesale",
            "subcategory":"Meat",
            "type":"Manufacturing & Wholesale Goods"
        }
    ],
    "sg:phone":"+1 435 644 2696",
    "sg:postcode":"84741",
    "sg:province":"UT",
    "sg:tags":[
        "food"
    ],
    "wof:name":"Kanab Custom Meats",
    "wof:placetype":"venue"
},
  "geometry": {"coordinates":[-112.518036,37.041338],"type":"Point"}
}