{
  "type": "Feature",
  "properties": {
    "iso:country":"US",
    "sg:address":"800 E Center St",
    "sg:city":"Midvale",
    "sg:classifiers":[
        {
            "category":"Government",
            "subcategory":"Post Office",
            "type":"Public Place"
        }
    ],
    "sg:phone":"+1 801 255 1711",
    "sg:postcode":"84047",
    "sg:province":"UT",
    "wof:name":"Midvale Postal Office",
    "wof:placetype":"venue"
},
  "geometry": {"coordinates":[-111.891988,40.610866],"type":"Point"}
}