{
  "type": "Feature",
  "properties": {
    "iso:country":"US",
    "sg:address":"500 S 200 W",
    "sg:city":"Smithfield",
    "sg:classifiers":[
        {
            "category":"Farming",
            "subcategory":"Dairy Farm",
            "type":"Manufacturing & Wholesale Goods"
        }
    ],
    "sg:phone":"+1 435 563 5512",
    "sg:postcode":"84335",
    "sg:province":"UT",
    "wof:name":"Chambers Cleon & Ch Dairy",
    "wof:placetype":"venue"
},
  "geometry": {"coordinates":[-111.83914900000001,41.825429],"type":"Point"}
}