{
  "type": "Feature",
  "properties": {
    "iso:country":"US",
    "sg:address":"231 Julie Ann Ct",
    "sg:city":"Tooele",
    "sg:classifiers":[
        {
            "category":"Building & Trades",
            "subcategory":"Construction",
            "type":"Services"
        }
    ],
    "sg:phone":"+1 435 850 4907",
    "sg:postcode":"84074",
    "sg:province":"UT",
    "sg:tags":[
        "handyman"
    ],
    "wof:name":"Handyman",
    "wof:placetype":"venue"
},
  "geometry": {"coordinates":[-112.305705,40.516976],"type":"Point"}
}