{
  "type": "Feature",
  "properties": {
    "iso:country":"US",
    "sg:address":"516 E 550 S",
    "sg:city":"Bountiful",
    "sg:classifiers":[
        {
            "category":"Building & Trades",
            "subcategory":"Construction",
            "type":"Services"
        }
    ],
    "sg:phone":"+1 801 298 3587",
    "sg:postcode":"84010",
    "sg:province":"UT",
    "sg:tags":[
        "house",
        "nonresidential"
    ],
    "wof:name":"General Finish Inc",
    "wof:placetype":"venue"
},
  "geometry": {"coordinates":[-111.872119,40.883244],"type":"Point"}
}