{
  "type": "Feature",
  "properties": {
    "iso:country":"US",
    "sg:address":"2785 W 9000 S",
    "sg:city":"West Jordan",
    "sg:classifiers":[
        {
            "category":"Building & Trades",
            "subcategory":"Electrical",
            "type":"Services"
        }
    ],
    "sg:phone":"+1 801 253 3265",
    "sg:postcode":"84088",
    "sg:province":"UT",
    "sg:tags":[
        "electric",
        "contractor"
    ],
    "wof:name":"Conelco Conrad Electric Co",
    "wof:placetype":"venue"
},
  "geometry": {"coordinates":[-111.959602,40.587678],"type":"Point"}
}