{
  "type": "Feature",
  "properties": {
    "iso:country":"US",
    "sg:address":"155 US Hwy 191",
    "sg:city":"Dutch John",
    "sg:classifiers":[
        {
            "category":"Travel",
            "subcategory":"Hotels & Motels",
            "type":"Entertainment"
        }
    ],
    "sg:phone":"+1 435 889 3773",
    "sg:postcode":"84023",
    "sg:province":"UT",
    "wof:name":"Flaming Gorge Lodge",
    "wof:placetype":"venue"
},
  "geometry": {"coordinates":[-109.432857,40.996345],"type":"Point"}
}