{
  "type": "Feature",
  "properties": {
    "iso:country":"US",
    "sg:address":"10 E 800 S",
    "sg:city":"Salt Lake City",
    "sg:classifiers":[
        {
            "category":"Professional",
            "subcategory":"Engineering",
            "type":"Services"
        }
    ],
    "sg:phone":"+1 801 521 2814",
    "sg:postcode":"84111",
    "sg:province":"UT",
    "sg:tags":[
        "engineer"
    ],
    "wof:name":"WBK Controls Inc",
    "wof:placetype":"venue"
},
  "geometry": {"coordinates":[-111.88839900000001,40.751878],"type":"Point"}
}