{
  "type": "Feature",
  "properties": {
    "iso:country":"US",
    "sg:address":"216 24th St",
    "sg:city":"Ogden",
    "sg:classifiers":[
        {
            "category":"Personal",
            "subcategory":"Beauty Salon",
            "type":"Services"
        }
    ],
    "sg:phone":"+1 801 621 0359",
    "sg:postcode":"84401",
    "sg:province":"UT",
    "wof:name":"Reflections Salon",
    "wof:placetype":"venue"
},
  "geometry": {"coordinates":[-111.973598,41.222868],"type":"Point"}
}