{
  "type": "Feature",
  "properties": {
    "iso:country":"US",
    "sg:address":"501 N 800 E",
    "sg:city":"Springville",
    "sg:classifiers":[
        {
            "category":"Professional",
            "type":"Services"
        }
    ],
    "sg:phone":"+1 801 489 5704",
    "sg:postcode":"84663",
    "sg:province":"UT",
    "wof:name":"Finleys LLC",
    "wof:placetype":"venue"
},
  "geometry": {"coordinates":[-111.596403,40.172545],"type":"Point"}
}