{
  "type": "Feature",
  "properties": {
    "iso:country":"US",
    "sg:address":"1655 White Pine Canyon Rd",
    "sg:city":"Park City",
    "sg:classifiers":[
        {
            "category":"Real Estate",
            "subcategory":"Real Estate Operator",
            "type":"Services"
        }
    ],
    "sg:phone":"+1 435 649 1497",
    "sg:postcode":"84060",
    "sg:province":"UT",
    "sg:tags":[
        "building",
        "nonresidential"
    ],
    "wof:name":"Ivers Land Partnr A Utah Ltd P",
    "wof:placetype":"venue"
},
  "geometry": {"coordinates":[-111.542412,40.683026],"type":"Point"}
}