{
  "type": "Feature",
  "properties": {
    "iso:country":"US",
    "sg:address":"100 S 50 E",
    "sg:city":"Duchesne",
    "sg:classifiers":[
        {
            "category":"Government",
            "subcategory":"Office",
            "type":"Public Place"
        }
    ],
    "sg:phone":"+1 435 738 1140",
    "sg:postcode":"84071",
    "sg:province":"UT",
    "wof:name":"Duchesne County Extension",
    "wof:placetype":"venue"
},
  "geometry": {"coordinates":[-112.361442,40.448817],"type":"Point"}
}