{
  "type": "Feature",
  "properties": {
    "iso:country":"US",
    "sg:address":"1343 Knollwood Dr",
    "sg:city":"Sandy",
    "sg:classifiers":[
        {
            "category":"Health Services",
            "subcategory":"Health Practitioner",
            "type":"Services"
        }
    ],
    "sg:phone":"+1 801 572 5516",
    "sg:postcode":"84092",
    "sg:province":"UT",
    "wof:name":"Sonography Inc",
    "wof:placetype":"venue"
},
  "geometry": {"coordinates":[-111.852154,40.545749],"type":"Point"}
}