{
  "type": "Feature",
  "properties": {
    "iso:country":"US",
    "sg:address":"5635 S 2200 W",
    "sg:city":"Kearns",
    "sg:classifiers":[
        {
            "category":"Organizations",
            "subcategory":"Religious Organization",
            "type":"Services"
        }
    ],
    "sg:phone":"+1 801 964 3056",
    "sg:postcode":"84118",
    "sg:province":"UT",
    "sg:tags":[
        "church"
    ],
    "wof:name":"Church Of Jesus Christ Of Lds",
    "wof:placetype":"venue"
},
  "geometry": {"coordinates":[-111.948275,40.648497],"type":"Point"}
}