{
  "type": "Feature",
  "properties": {
    "iso:country":"US",
    "sg:address":"257 N Main St",
    "sg:city":"Clearfield",
    "sg:classifiers":[
        {
            "category":"Professional",
            "subcategory":"Computer Services",
            "type":"Services"
        }
    ],
    "sg:phone":"+1 801 771 4199",
    "sg:postcode":"84015",
    "sg:province":"UT",
    "wof:name":"Oxide Network",
    "wof:placetype":"venue"
},
  "geometry": {"coordinates":[-112.026095,41.117948],"type":"Point"}
}