{
  "type": "Feature",
  "properties": {
    "iso:country":"US",
    "sg:address":"98 W 200 N",
    "sg:city":"Bountiful",
    "sg:classifiers":[
        {
            "category":"Insurance",
            "subcategory":"Insurance Agent",
            "type":"Services"
        }
    ],
    "sg:phone":"+1 801 292 7291",
    "sg:postcode":"84010",
    "sg:province":"UT",
    "wof:name":"State Farm Insurance",
    "wof:placetype":"venue"
},
  "geometry": {"coordinates":[-111.880724,40.891495],"type":"Point"}
}