{
  "type": "Feature",
  "properties": {
    "iso:country":"US",
    "sg:address":"6131 S 380 W",
    "sg:city":"Murray",
    "sg:classifiers":[
        {
            "category":"Home & Garden",
            "subcategory":"Furniture",
            "type":"Retail Goods"
        }
    ],
    "sg:phone":"+1 801 270 8001",
    "sg:postcode":"84107",
    "sg:province":"UT",
    "sg:tags":[
        "top",
        "counter"
    ],
    "wof:name":"Salt City Countertops",
    "wof:placetype":"venue"
},
  "geometry": {"coordinates":[-111.90168300000001,40.638327],"type":"Point"}
}