{
  "type": "Feature",
  "properties": {
    "iso:country":"US",
    "sg:address":"546 S State St",
    "sg:city":"Orem",
    "sg:classifiers":[
        {
            "category":"Shopping",
            "subcategory":"Bicycles & Sporting Goods",
            "type":"Retail Goods"
        }
    ],
    "sg:phone":"+1 801 224 3483",
    "sg:postcode":"84058",
    "sg:province":"UT",
    "wof:name":"Dive U",
    "wof:placetype":"venue"
},
  "geometry": {"coordinates":[-111.69077,40.287408],"type":"Point"}
}