{
  "type": "Feature",
  "properties": {
    "iso:country":"US",
    "sg:address":"24 S Country Ln",
    "sg:city":"Kaysville",
    "sg:classifiers":[
        {
            "category":"Organizations",
            "subcategory":"Religious Organization",
            "type":"Services"
        }
    ],
    "sg:phone":"+1 801 543 2805",
    "sg:postcode":"84037",
    "sg:province":"UT",
    "sg:tags":[
        "mormon",
        "church"
    ],
    "wof:name":"Fruit Heights Seventh Ward",
    "wof:placetype":"venue"
},
  "geometry": {"coordinates":[-111.913685,41.035227],"type":"Point"}
}