{
  "type": "Feature",
  "properties": {
    "iso:country":"US",
    "sg:address":"2883 N 725 W",
    "sg:city":"Layton",
    "sg:classifiers":[
        {
            "category":"Professional",
            "subcategory":"Management & Consulting",
            "type":"Services"
        }
    ],
    "sg:phone":"+1 801 825 7279",
    "sg:postcode":"84041",
    "sg:province":"UT",
    "sg:tags":[
        "business"
    ],
    "wof:name":"J C M Consulting",
    "wof:placetype":"venue"
},
  "geometry": {"coordinates":[-111.979196,41.101305],"type":"Point"}
}