{
  "type": "Feature",
  "properties": {
    "iso:country":"US",
    "sg:address":"55 E 3900 S",
    "sg:city":"Salt Lake City",
    "sg:classifiers":[
        {
            "category":"Retail",
            "subcategory":"Auto Rental",
            "type":"Services"
        }
    ],
    "sg:phone":"+1 801 265 0596",
    "sg:postcode":"84107",
    "sg:province":"UT",
    "sg:tags":[
        "truck",
        "rent",
        "trailer",
        "hitch"
    ],
    "wof:name":"U-Haul",
    "wof:placetype":"venue"
},
  "geometry": {"coordinates":[-111.889579,40.68708],"type":"Point"}
}