{
  "type": "Feature",
  "properties": {
    "iso:country":"US",
    "sg:address":"140 S 300 W",
    "sg:city":"Mount Pleasant",
    "sg:classifiers":[
        {
            "category":"Personal",
            "type":"Services"
        }
    ],
    "sg:phone":"+1 435 462 0042",
    "sg:postcode":"84647",
    "sg:province":"UT",
    "sg:tags":[
        "portable",
        "rest",
        "rooms"
    ],
    "wof:name":"A1 Rooter Service",
    "wof:placetype":"venue"
},
  "geometry": {"coordinates":[-111.461061,39.544706],"type":"Point"}
}