{
  "type": "Feature",
  "properties": {
    "iso:country":"US",
    "sg:address":"9844 S 1300 E",
    "sg:city":"Sandy",
    "sg:classifiers":[
        {
            "category":"Health Services",
            "subcategory":"Doctor",
            "type":"Services"
        },
        {
            "category":"Health Services",
            "subcategory":"Medical Lab",
            "type":"Services"
        }
    ],
    "sg:phone":"+1 801 576 1290",
    "sg:postcode":"84094",
    "sg:province":"UT",
    "sg:tags":[
        "physician",
        "surgeon",
        "laboratory"
    ],
    "wof:name":"Wasatch Imaging",
    "wof:placetype":"venue"
},
  "geometry": {"coordinates":[-111.85319800000001,40.569871],"type":"Point"}
}