{
  "type": "Feature",
  "properties": {
    "iso:country":"US",
    "sg:address":"118 N Main St",
    "sg:city":"Midvale",
    "sg:classifiers":[
        {
            "category":"Professional",
            "subcategory":"Accounting & Tax Preparation",
            "type":"Services"
        }
    ],
    "sg:phone":"+1 801 561 4311",
    "sg:postcode":"84047",
    "sg:province":"UT",
    "sg:tags":[
        "bookkeeping",
        "general"
    ],
    "wof:name":"Nebeker & Assoc Inc",
    "wof:placetype":"venue"
},
  "geometry": {"coordinates":[-111.91028900000001,40.613251],"type":"Point"}
}