{
  "type": "Feature",
  "properties": {
    "iso:country":"US",
    "sg:address":"117 E 12675 S",
    "sg:city":"Draper",
    "sg:classifiers":[
        {
            "category":"Professional",
            "subcategory":"Engineering",
            "type":"Services"
        }
    ],
    "sg:phone":"+1 801 576 0833",
    "sg:postcode":"84020",
    "sg:province":"UT",
    "wof:name":"Westbrook Construction",
    "wof:placetype":"venue"
},
  "geometry": {"coordinates":[-111.89042000000001,40.520459],"type":"Point"}
}