{
  "type": "Feature",
  "properties": {
    "iso:country":"US",
    "sg:address":"6069 Don Juan Dr",
    "sg:city":"Salt Lake City",
    "sg:classifiers":[
        {
            "category":"Building & Trades",
            "subcategory":"Landscaping Services",
            "type":"Services"
        }
    ],
    "sg:phone":"+1 801 955 4358",
    "sg:postcode":"84118",
    "sg:province":"UT",
    "wof:name":"Lawn Solutions",
    "wof:placetype":"venue"
},
  "geometry": {"coordinates":[-111.962422,40.640494],"type":"Point"}
}