{
  "type": "Feature",
  "properties": {
    "iso:country":"US",
    "sg:address":"23 Stone Mountain Dr",
    "sg:city":"St George",
    "sg:classifiers":[
        {
            "category":"Building & Trades",
            "subcategory":"Construction",
            "type":"Services"
        }
    ],
    "sg:phone":"+1 435 673 3182",
    "sg:postcode":"84770",
    "sg:province":"UT",
    "sg:tags":[
        "concrete",
        "contractor"
    ],
    "wof:name":"Jimerson Concrete",
    "wof:placetype":"venue"
},
  "geometry": {"coordinates":[-113.607837,37.108286],"type":"Point"}
}