{
  "type": "Feature",
  "properties": {
    "iso:country":"US",
    "sg:address":"30 N 1900 E",
    "sg:city":"Salt Lake City",
    "sg:classifiers":[
        {
            "category":"Health Services",
            "subcategory":"Doctor",
            "type":"Services"
        }
    ],
    "sg:phone":"+1 801 581 8812",
    "sg:postcode":"84112",
    "sg:province":"UT",
    "sg:tags":[
        "physician",
        "surgeon"
    ],
    "wof:name":"University Of Ut-Infectious",
    "wof:placetype":"venue"
},
  "geometry": {"coordinates":[-111.840705,40.772019],"type":"Point"}
}