{
  "type": "Feature",
  "properties": {
    "iso:country":"US",
    "sg:address":"45 N 490 W",
    "sg:city":"American Fork",
    "sg:classifiers":[
        {
            "category":"Professional",
            "subcategory":"Engineering",
            "type":"Services"
        }
    ],
    "sg:phone":"+1 801 492 1277",
    "sg:postcode":"84003",
    "sg:province":"UT",
    "wof:name":"Sowby and Berg Consultants",
    "wof:placetype":"venue"
},
  "geometry": {"coordinates":[-111.811791,40.377865],"type":"Point"}
}