{
  "type": "Feature",
  "properties": {
    "iso:country":"US",
    "sg:address":"405 Flaming Gorge Acres",
    "sg:city":"Dutch John",
    "sg:classifiers":[
        {
            "category":"Mining & Drilling",
            "type":"Manufacturing & Wholesale Goods"
        }
    ],
    "sg:phone":"+1 940 782 0109",
    "sg:postcode":"84023",
    "sg:province":"UT",
    "sg:tags":[
        "well"
    ],
    "wof:name":"Clevco Consulting",
    "wof:placetype":"venue"
},
  "geometry": {"coordinates":[-109.469668,40.877177],"type":"Point"}
}