{
  "type": "Feature",
  "properties": {
    "iso:country":"US",
    "sg:address":"1730 N Main St",
    "sg:city":"Logan",
    "sg:classifiers":[
        {
            "category":"Restaurant",
            "type":"Food & Drink"
        }
    ],
    "sg:menulink":"http://www.allmenus.com/ut/logan/116235-quiznos-sub/menu/",
    "sg:phone":"+1 435 755 8545",
    "sg:postcode":"84341",
    "sg:province":"UT",
    "sg:tags":[
        "wrap",
        "american",
        "sandwich"
    ],
    "wof:name":"Quiznos Sub",
    "wof:placetype":"venue"
},
  "geometry": {"coordinates":[-111.834222,41.763701],"type":"Point"}
}