{
  "type": "Feature",
  "properties": {
    "iso:country":"US",
    "sg:address":"2937 S 50 W",
    "sg:city":"Bountiful",
    "sg:classifiers":[
        {
            "category":"Banks & Credit Unions",
            "subcategory":"Financial Services",
            "type":"Services"
        }
    ],
    "sg:phone":"+1 801 397 2393",
    "sg:postcode":"84010",
    "sg:province":"UT",
    "sg:tags":[
        "investor"
    ],
    "wof:name":"Cjm Motion Picture Inv Corp",
    "wof:placetype":"venue"
},
  "geometry": {"coordinates":[-111.881152,40.85706],"type":"Point"}
}