{
  "type": "Feature",
  "properties": {
    "iso:country":"US",
    "sg:address":"573 E 650 N",
    "sg:city":"Centerville",
    "sg:classifiers":[
        {
            "category":"Real Estate",
            "subcategory":"Real Estate Agent",
            "type":"Services"
        }
    ],
    "sg:phone":"+1 801 298 0147",
    "sg:postcode":"84014",
    "sg:province":"UT",
    "wof:name":"Bangerter Wood Properties LLC",
    "wof:placetype":"venue"
},
  "geometry": {"coordinates":[-111.869136,40.924319],"type":"Point"}
}