{
  "type": "Feature",
  "properties": {
    "iso:country":"US",
    "sg:address":"35 S 500 E",
    "sg:city":"Heber City",
    "sg:classifiers":[
        {
            "category":"Health Services",
            "subcategory":"Doctor",
            "type":"Services"
        }
    ],
    "sg:phone":"+1 435 654 1501",
    "sg:postcode":"84032",
    "sg:province":"UT",
    "sg:tags":[
        "medical"
    ],
    "wof:name":"N J Burton MD PC",
    "wof:placetype":"venue"
},
  "geometry": {"coordinates":[-111.40468799999999,40.507087],"type":"Point"}
}