{
  "type": "Feature",
  "properties": {
    "iso:country":"US",
    "sg:address":"570 Research Park Way",
    "sg:city":"Logan",
    "sg:classifiers":[
        {
            "category":"Professional",
            "subcategory":"Management & Consulting",
            "type":"Services"
        }
    ],
    "sg:phone":"+1 435 787 1490",
    "sg:postcode":"84341",
    "sg:province":"UT",
    "sg:tags":[
        "environmental"
    ],
    "wof:name":"965 S 100 W Ste 200",
    "wof:placetype":"venue"
},
  "geometry": {"coordinates":[-111.820747,41.76313],"type":"Point"}
}