{
  "type": "Feature",
  "properties": {
    "iso:country":"US",
    "sg:address":"4530 Highland Dr",
    "sg:city":"Holladay",
    "sg:classifiers":[
        {
            "category":"Food & Beverages",
            "subcategory":"Groceries & Convenience Stores",
            "type":"Retail Goods"
        }
    ],
    "sg:phone":"+1 801 278 5390",
    "sg:postcode":"84117",
    "sg:province":"UT",
    "sg:tags":[
        "grocer"
    ],
    "sg:website":"www.albertsons.com",
    "wof:name":"Albertsons",
    "wof:placetype":"venue"
},
  "geometry": {"coordinates":[-111.840981,40.672521],"type":"Point"}
}