{
  "type": "Feature",
  "properties": {
    "iso:country":"US",
    "sg:address":"725 S Main St",
    "sg:city":"Spanish Fork",
    "sg:classifiers":[
        {
            "category":"Government",
            "subcategory":"Office",
            "type":"Public Place"
        }
    ],
    "sg:phone":"+1 801 798 6166",
    "sg:postcode":"84660",
    "sg:province":"UT",
    "sg:tags":[
        "state",
        "program"
    ],
    "wof:name":"Transportation-Maintenance Sta",
    "wof:placetype":"venue"
},
  "geometry": {"coordinates":[-111.655254,40.099282],"type":"Point"}
}