{
  "type": "Feature",
  "properties": {
    "iso:country":"US",
    "sg:address":"684 E Vine St",
    "sg:city":"Salt Lake City",
    "sg:classifiers":[
        {
            "category":"Insurance",
            "subcategory":"Insurance Agent",
            "type":"Services"
        }
    ],
    "sg:phone":"+1 801 269 0554",
    "sg:postcode":"84107",
    "sg:province":"UT",
    "wof:name":"Loyal American Life Insur Co",
    "wof:placetype":"venue"
},
  "geometry": {"coordinates":[-111.872773,40.655703],"type":"Point"}
}