{
  "type": "Feature",
  "properties": {
    "iso:country":"US",
    "sg:address":"1877 E 4800 S",
    "sg:city":"Holladay",
    "sg:classifiers":[
        {
            "category":"Restaurant",
            "type":"Food & Drink"
        }
    ],
    "sg:phone":"+1 801 272 9233",
    "sg:postcode":"84117",
    "sg:province":"UT",
    "wof:name":"M B Food Svc Inc",
    "wof:placetype":"venue"
},
  "geometry": {"coordinates":[-111.83550700000001,40.665941],"type":"Point"}
}