{
  "type": "Feature",
  "properties": {
    "iso:country":"US",
    "sg:address":"1787 Fort Union Blvd",
    "sg:city":"Salt Lake City",
    "sg:classifiers":[
        {
            "category":"Banks & Credit Unions",
            "subcategory":"Bank",
            "type":"Services"
        }
    ],
    "sg:phone":"+1 801 453 8030",
    "sg:postcode":"84121",
    "sg:province":"UT",
    "sg:tags":[
        "finance"
    ],
    "wof:name":"Nbf Capital LLC",
    "wof:placetype":"venue"
},
  "geometry": {"coordinates":[-111.84116899999999,40.624959],"type":"Point"}
}