{
  "type": "Feature",
  "properties": {
    "iso:country":"US",
    "sg:address":"2330 E 3300 S",
    "sg:city":"Salt Lake City",
    "sg:classifiers":[
        {
            "category":"Shopping",
            "subcategory":"Pharmacy",
            "type":"Retail Goods"
        }
    ],
    "sg:phone":"+1 801 487 7585",
    "sg:postcode":"84109",
    "sg:province":"UT",
    "wof:name":"Dan's Pharmacies",
    "wof:placetype":"venue"
},
  "geometry": {"coordinates":[-111.821325,40.699781],"type":"Point"}
}