{
  "type": "Feature",
  "properties": {
    "iso:country":"US",
    "sg:address":"510 S University Ave",
    "sg:city":"Provo",
    "sg:classifiers":[
        {
            "category":"Professional",
            "subcategory":"Computer Services",
            "type":"Services"
        }
    ],
    "sg:phone":"+1 801 379 0345",
    "sg:postcode":"84601",
    "sg:province":"UT",
    "sg:tags":[
        "datum"
    ],
    "wof:name":"E Prep Inc",
    "wof:placetype":"venue"
},
  "geometry": {"coordinates":[-111.658789,40.225877],"type":"Point"}
}