{
  "type": "Feature",
  "properties": {
    "iso:country":"US",
    "sg:address":"3909 S 8000 W",
    "sg:city":"Magna",
    "sg:classifiers":[
        {
            "category":"Manufacturing",
            "subcategory":"Building Materials",
            "type":"Manufacturing & Wholesale Goods"
        }
    ],
    "sg:phone":"+1 801 252 1130",
    "sg:postcode":"84044",
    "sg:province":"UT",
    "sg:tags":[
        "member",
        "wood",
        "structural"
    ],
    "wof:name":"G-L Industries Inc",
    "wof:placetype":"venue"
},
  "geometry": {"coordinates":[-112.082166,40.682584],"type":"Point"}
}