{
  "type": "Feature",
  "properties": {
    "iso:country":"US",
    "sg:address":"352 N State St",
    "sg:city":"Orem",
    "sg:classifiers":[
        {
            "category":"Shopping",
            "subcategory":"Bicycles & Sporting Goods",
            "type":"Retail Goods"
        }
    ],
    "sg:phone":"+1 801 222 9667",
    "sg:postcode":"84057",
    "sg:province":"UT",
    "wof:name":"Emergency Essentials Inc",
    "wof:placetype":"venue"
},
  "geometry": {"coordinates":[-111.697813,40.303561],"type":"Point"}
}