{
  "type": "Feature",
  "properties": {
    "iso:country":"US",
    "sg:address":"984 N 475 E",
    "sg:city":"Orem",
    "sg:classifiers":[
        {
            "category":"Wholesale",
            "subcategory":"Stationery",
            "type":"Manufacturing & Wholesale Goods"
        }
    ],
    "sg:phone":"+1 801 225 8056",
    "sg:postcode":"84097",
    "sg:province":"UT",
    "sg:tags":[
        "supply"
    ],
    "wof:name":"I Remember That",
    "wof:placetype":"venue"
},
  "geometry": {"coordinates":[-111.684347,40.315954],"type":"Point"}
}