{
  "type": "Feature",
  "properties": {
    "iso:country":"US",
    "sg:address":"4766 W 5100 S",
    "sg:city":"Salt Lake City",
    "sg:classifiers":[
        {
            "category":"Retail",
            "subcategory":"Repair Shop",
            "type":"Services"
        }
    ],
    "sg:phone":"+1 801 679 0808",
    "sg:postcode":"84118",
    "sg:province":"UT",
    "wof:name":"Ancy Company Corporation",
    "wof:placetype":"venue"
},
  "geometry": {"coordinates":[-112.00379599999999,40.658581],"type":"Point"}
}