{
  "type": "Feature",
  "properties": {
    "iso:country":"US",
    "sg:address":"4001 S 700 E",
    "sg:city":"Salt Lake City",
    "sg:classifiers":[
        {
            "category":"Banks & Credit Unions",
            "subcategory":"Bank",
            "type":"Services"
        }
    ],
    "sg:phone":"+1 801 571 8581",
    "sg:postcode":"84107",
    "sg:province":"UT",
    "sg:tags":[
        "loan",
        "real estate"
    ],
    "wof:name":"Russ Cottam",
    "wof:placetype":"venue"
},
  "geometry": {"coordinates":[-111.87129,40.683391],"type":"Point"}
}