{
  "type": "Feature",
  "properties": {
    "iso:country":"US",
    "sg:address":"1503 N 2100 W",
    "sg:city":"St George",
    "sg:classifiers":[
        {
            "category":"Real Estate",
            "subcategory":"Real Estate Operator",
            "type":"Services"
        }
    ],
    "sg:phone":"+1 435 674 9919",
    "sg:postcode":"84770",
    "sg:province":"UT",
    "sg:tags":[
        "building",
        "apartment"
    ],
    "wof:name":"Canyon Place Rock Creek",
    "wof:placetype":"venue"
},
  "geometry": {"coordinates":[-113.628435,37.133705],"type":"Point"}
}