{
  "type": "Feature",
  "properties": {
    "iso:country":"US",
    "sg:address":"8811 S 700 E",
    "sg:city":"Sandy",
    "sg:classifiers":[
        {
            "category":"Health Services",
            "subcategory":"Chiropractor",
            "type":"Services"
        }
    ],
    "sg:phone":"+1 801 984 2000",
    "sg:postcode":"84070",
    "sg:province":"UT",
    "wof:name":"Vance Chiropractic",
    "wof:placetype":"venue"
},
  "geometry": {"coordinates":[-111.87226,40.590023],"type":"Point"}
}