{
  "type": "Feature",
  "properties": {
    "iso:country":"US",
    "sg:address":"271 W 900 S",
    "sg:city":"Salt Lake City",
    "sg:classifiers":[
        {
            "category":"Restaurant",
            "type":"Food & Drink"
        }
    ],
    "sg:phone":"+1 801 359 4381",
    "sg:postcode":"84101",
    "sg:province":"UT",
    "sg:tags":[
        "eating"
    ],
    "wof:name":"El Taco Llama",
    "wof:placetype":"venue"
},
  "geometry": {"coordinates":[-111.899231,40.749692],"type":"Point"}
}