{
  "type": "Feature",
  "properties": {
    "iso:country":"US",
    "sg:address":"279 N Main St",
    "sg:city":"Spanish Fork",
    "sg:classifiers":[
        {
            "category":"Banks & Credit Unions",
            "subcategory":"Bank",
            "type":"Services"
        }
    ],
    "sg:phone":"+1 801 798 9333",
    "sg:postcode":"84660",
    "sg:province":"UT",
    "sg:tags":[
        "loan"
    ],
    "wof:name":"Raincheck",
    "wof:placetype":"venue"
},
  "geometry": {"coordinates":[-111.654848,40.112715],"type":"Point"}
}