{
  "type": "Feature",
  "properties": {
    "iso:country":"US",
    "sg:address":"3022 S 9050 W",
    "sg:city":"Magna",
    "sg:classifiers":[
        {
            "category":"Home & Garden",
            "subcategory":"Home Furnishings",
            "type":"Retail Goods"
        }
    ],
    "sg:phone":"+1 801 508 0169",
    "sg:postcode":"84044",
    "sg:province":"UT",
    "wof:name":"South Star SA Inc",
    "wof:placetype":"venue"
},
  "geometry": {"coordinates":[-112.107288,40.704223],"type":"Point"}
}