{
  "type": "Feature",
  "properties": {
    "iso:country":"US",
    "sg:address":"10101 S State St",
    "sg:city":"Sandy",
    "sg:classifiers":[
        {
            "category":"Organizations",
            "subcategory":"Professional Association",
            "type":"Services"
        }
    ],
    "sg:phone":"+1 801 255 4109",
    "sg:postcode":"84070",
    "sg:province":"UT",
    "sg:tags":[
        "engineering",
        "business"
    ],
    "wof:name":"Aisc",
    "wof:placetype":"venue"
},
  "geometry": {"coordinates":[-111.89071300000001,40.566137],"type":"Point"}
}