{
  "type": "Feature",
  "properties": {
    "iso:country":"US",
    "sg:address":"206 W 4860 S",
    "sg:city":"Salt Lake City",
    "sg:classifiers":[
        {
            "category":"Wholesale",
            "subcategory":"Non-durable Goods",
            "type":"Manufacturing & Wholesale Goods"
        }
    ],
    "sg:phone":"+1 801 263 8515",
    "sg:postcode":"84107",
    "sg:province":"UT",
    "sg:tags":[
        "advertising",
        "specialty"
    ],
    "wof:name":"High Image AP & Promotions",
    "wof:placetype":"venue"
},
  "geometry": {"coordinates":[-111.914342,40.663798],"type":"Point"}
}