{
  "type": "Feature",
  "properties": {
    "iso:country":"US",
    "sg:address":"287 E 100 S",
    "sg:city":"Vernal",
    "sg:classifiers":[
        {
            "category":"Manufacturing",
            "subcategory":"Signs",
            "type":"Manufacturing & Wholesale Goods"
        },
        {
            "category":"Professional",
            "subcategory":"Business Services",
            "type":"Services"
        }
    ],
    "sg:phone":"+1 435 789 5774",
    "sg:postcode":"84078",
    "sg:province":"UT",
    "sg:tags":[
        "specialty",
        "painter",
        "mfg"
    ],
    "wof:name":"Dinosigns",
    "wof:placetype":"venue"
},
  "geometry": {"coordinates":[-109.524551,40.45442],"type":"Point"}
}