{
  "type": "Feature",
  "properties": {
    "iso:country":"US",
    "sg:address":"4531 Country View Dr",
    "sg:city":"Ogden",
    "sg:classifiers":[
        {
            "category":"Manufacturing",
            "subcategory":"Printing",
            "type":"Manufacturing & Wholesale Goods"
        }
    ],
    "sg:phone":"+1 801 479 1153",
    "sg:postcode":"84403",
    "sg:province":"UT",
    "sg:tags":[
        "periodical"
    ],
    "wof:name":"Harmon Homes",
    "wof:placetype":"venue"
},
  "geometry": {"coordinates":[-111.96085600000001,41.180846],"type":"Point"}
}