{
  "type": "Feature",
  "properties": {
    "iso:country":"US",
    "sg:address":"3283 S Bluff Rd",
    "sg:city":"Syracuse",
    "sg:classifiers":[
        {
            "category":"Professional",
            "subcategory":"Business Services",
            "type":"Services"
        }
    ],
    "sg:phone":"+1 801 525 0603",
    "sg:postcode":"84075",
    "sg:province":"UT",
    "wof:name":"Huffs Tax Service LLC",
    "wof:placetype":"venue"
},
  "geometry": {"coordinates":[-112.05174,41.067549],"type":"Point"}
}