{
  "type": "Feature",
  "properties": {
    "iso:country":"US",
    "sg:address":"1377 E 1500 S",
    "sg:city":"Vernal",
    "sg:classifiers":[
        {
            "category":"Wholesale",
            "subcategory":"Machinery & Supplies",
            "type":"Manufacturing & Wholesale Goods"
        }
    ],
    "sg:phone":"+1 435 789 1833",
    "sg:postcode":"84078",
    "sg:province":"UT",
    "sg:tags":[
        "equipment",
        "oil",
        "well"
    ],
    "sg:website":"www.spidle.com",
    "wof:name":"Spidle Sales & Svc Inc",
    "wof:placetype":"venue"
},
  "geometry": {"coordinates":[-109.503119,40.434107],"type":"Point"}
}