{
  "type": "Feature",
  "properties": {
    "iso:country":"US",
    "sg:address":"12511 Bear Cub Cir",
    "sg:city":"Draper",
    "sg:classifiers":[
        {
            "category":"Professional",
            "subcategory":"Business Services",
            "type":"Services"
        }
    ],
    "sg:phone":"+1 801 523 9464",
    "sg:postcode":"84020",
    "sg:province":"UT",
    "wof:name":"Cdp Technologies",
    "wof:placetype":"venue"
},
  "geometry": {"coordinates":[-111.835092,40.523179],"type":"Point"}
}