{
  "type": "Feature",
  "properties": {
    "iso:country":"US",
    "sg:address":"55 E 200 N",
    "sg:city":"La Verkin",
    "sg:classifiers":[
        {
            "category":"Building & Trades",
            "subcategory":"Construction",
            "type":"Services"
        }
    ],
    "sg:phone":"+1 435 635 2975",
    "sg:postcode":"84745",
    "sg:province":"UT",
    "sg:tags":[
        "contractor"
    ],
    "wof:name":"Dannys Drywall",
    "wof:placetype":"venue"
},
  "geometry": {"coordinates":[-113.26870099999999,37.205243],"type":"Point"}
}