{
  "type": "Feature",
  "properties": {
    "iso:country":"US",
    "sg:address":"290 N 200 E",
    "sg:city":"Logan",
    "sg:classifiers":[
        {
            "category":"Health Services",
            "subcategory":"Doctor",
            "type":"Services"
        }
    ],
    "sg:phone":"+1 435 753 0506",
    "sg:postcode":"84321",
    "sg:province":"UT",
    "wof:name":"K N K Enterprises Inc",
    "wof:placetype":"venue"
},
  "geometry": {"coordinates":[-111.818119,41.684951],"type":"Point"}
}