{
  "type": "Feature",
  "properties": {
    "iso:country":"US",
    "sg:address":"1950 Washington Blvd",
    "sg:city":"Ogden",
    "sg:classifiers":[
        {
            "category":"Retail",
            "subcategory":"Auto Repair",
            "type":"Services"
        }
    ],
    "sg:phone":"+1 801 392 6546",
    "sg:postcode":"84401",
    "sg:province":"UT",
    "sg:tags":[
        "automotive",
        "glass",
        "replacement"
    ],
    "wof:name":"Nationwide Glass",
    "wof:placetype":"venue"
},
  "geometry": {"coordinates":[-111.970122,41.232352],"type":"Point"}
}