{
  "type": "Feature",
  "properties": {
    "iso:country":"US",
    "sg:address":"417 W University Pkwy",
    "sg:city":"Orem",
    "sg:classifiers":[
        {
            "category":"Bakery",
            "type":"Food & Drink"
        }
    ],
    "sg:menulink":"http://www.allmenus.com/ut/provo-orem/121412-krispy-kreme/menu/",
    "sg:phone":"+1 801 222 9995",
    "sg:postcode":"84058",
    "sg:province":"UT",
    "sg:tags":[
        "american",
        "pastry"
    ],
    "wof:name":"Krispy Kreme",
    "wof:placetype":"venue"
},
  "geometry": {"coordinates":[-111.70557700000001,40.273179],"type":"Point"}
}