{
  "type": "Feature",
  "properties": {
    "iso:country":"US",
    "sg:address":"26 N Main St",
    "sg:city":"Centerville",
    "sg:classifiers":[
        {
            "category":"Health Services",
            "subcategory":"Doctor",
            "type":"Services"
        }
    ],
    "sg:phone":"+1 801 295 2888",
    "sg:postcode":"84014",
    "sg:province":"UT",
    "sg:tags":[
        "medical"
    ],
    "wof:name":"Grow Up Great",
    "wof:placetype":"venue"
},
  "geometry": {"coordinates":[-111.87889199999999,40.917869],"type":"Point"}
}