{
  "type": "Feature",
  "properties": {
    "iso:country":"US",
    "sg:address":"141 W 2600 N",
    "sg:city":"Pleasant Grove",
    "sg:classifiers":[
        {
            "category":"Health Services",
            "subcategory":"Doctor",
            "type":"Services"
        }
    ],
    "sg:phone":"+1 801 785 9131",
    "sg:postcode":"84062",
    "sg:province":"UT",
    "wof:name":"C Ririe DDS",
    "wof:placetype":"venue"
},
  "geometry": {"coordinates":[-111.74463299999999,40.391974],"type":"Point"}
}