{
  "type": "Feature",
  "properties": {
    "iso:country":"US",
    "sg:address":"1464 N Main St",
    "sg:city":"Layton",
    "sg:classifiers":[
        {
            "category":"Autos & Motor Vehicles",
            "subcategory":"Automobile Sales",
            "type":"Retail Goods"
        }
    ],
    "sg:phone":"+1 801 544 9916",
    "sg:postcode":"84041",
    "sg:province":"UT",
    "sg:tags":[
        "car",
        "dealer"
    ],
    "wof:name":"Buy Rite Auto Inc",
    "wof:placetype":"venue"
},
  "geometry": {"coordinates":[-111.991625,41.081678],"type":"Point"}
}