{
  "type": "Feature",
  "properties": {
    "iso:country":"US",
    "sg:address":"327 E 1200 S",
    "sg:city":"Orem",
    "sg:classifiers":[
        {
            "category":"Health Services",
            "subcategory":"Chiropractor",
            "type":"Services"
        }
    ],
    "sg:phone":"+1 801 765 0389",
    "sg:postcode":"84097",
    "sg:province":"UT",
    "wof:name":"Norris Family Chiropractic",
    "wof:placetype":"venue"
},
  "geometry": {"coordinates":[-111.688301,40.275132],"type":"Point"}
}