{
  "type": "Feature",
  "properties": {
    "iso:country":"US",
    "sg:address":"9661 Winchester Dr",
    "sg:city":"Pleasant Grove",
    "sg:classifiers":[
        {
            "category":"Professional",
            "subcategory":"Business Services",
            "type":"Services"
        }
    ],
    "sg:phone":"+1 801 756 1905",
    "sg:postcode":"84062",
    "sg:province":"UT",
    "wof:name":"Derek Johnson",
    "wof:placetype":"venue"
},
  "geometry": {"coordinates":[-111.763237,40.407068],"type":"Point"}
}