{
  "type": "Feature",
  "properties": {
    "iso:country":"US",
    "sg:address":"220 Dorchester Dr",
    "sg:city":"Salt Lake City",
    "sg:classifiers":[
        {
            "category":"Banks & Credit Unions",
            "subcategory":"Financial Services",
            "type":"Services"
        }
    ],
    "sg:phone":"+1 801 328 3618",
    "sg:postcode":"84103",
    "sg:province":"UT",
    "sg:tags":[
        "trust",
        "nonprofit",
        "management"
    ],
    "wof:name":"Foundation of America",
    "wof:placetype":"venue"
},
  "geometry": {"coordinates":[-111.886179,40.789871],"type":"Point"}
}