{
  "type": "Feature",
  "properties": {
    "iso:country":"US",
    "sg:address":"2045 N 575 E",
    "sg:city":"Ogden",
    "sg:classifiers":[
        {
            "category":"Home & Garden",
            "subcategory":"Building Materials",
            "type":"Retail Goods"
        }
    ],
    "sg:phone":"+1 801 782 0322",
    "sg:postcode":"84414",
    "sg:province":"UT",
    "wof:name":"Tobys Glass",
    "wof:placetype":"venue"
},
  "geometry": {"coordinates":[-111.962383,41.29524],"type":"Point"}
}