{
  "type": "Feature",
  "properties": {
    "iso:country":"US",
    "sg:address":"1597 S 1100 E",
    "sg:city":"Salt Lake City",
    "sg:classifiers":[
        {
            "category":"Professional",
            "subcategory":"Business Services",
            "type":"Services"
        },
        {
            "category":"Building & Trades",
            "subcategory":"Equipment Rental",
            "type":"Services"
        }
    ],
    "sg:phone":"+1 801 582 3212",
    "sg:postcode":"84105",
    "sg:province":"UT",
    "sg:tags":[
        "plant",
        "design",
        "maintenance"
    ],
    "sg:website":"www.paradisepalm.com",
    "wof:name":"Paradise Palm Inc",
    "wof:placetype":"venue"
},
  "geometry": {"coordinates":[-111.859531,40.73503],"type":"Point"}
}