{
  "type": "Feature",
  "properties": {
    "iso:country":"US",
    "sg:address":"1306 Lakeview Dr",
    "sg:city":"Bountiful",
    "sg:classifiers":[
        {
            "category":"Professional",
            "subcategory":"Management & Consulting",
            "type":"Services"
        }
    ],
    "sg:phone":"+1 801 295 4191",
    "sg:postcode":"84010",
    "sg:province":"UT",
    "wof:name":"CDF Consulting LLC",
    "wof:placetype":"venue"
},
  "geometry": {"coordinates":[-111.85197100000001,40.878424],"type":"Point"}
}