{
  "type": "Feature",
  "properties": {
    "iso:country":"US",
    "sg:address":"45 E 400 N",
    "sg:city":"Spanish Fork",
    "sg:classifiers":[
        {
            "category":"Retail",
            "subcategory":"Repair Shop",
            "type":"Services"
        }
    ],
    "sg:phone":"+1 801 798 1738",
    "sg:postcode":"84660",
    "sg:province":"UT",
    "sg:tags":[
        "furniture"
    ],
    "wof:name":"A M-P M Keys",
    "wof:placetype":"venue"
},
  "geometry": {"coordinates":[-111.65412999999999,40.115088],"type":"Point"}
}