{
  "type": "Feature",
  "properties": {
    "iso:country":"US",
    "sg:address":"712 E 5600 S",
    "sg:city":"Salt Lake City",
    "sg:classifiers":[
        {
            "category":"Building & Trades",
            "subcategory":"Plumbing",
            "type":"Services"
        }
    ],
    "sg:phone":"+1 801 266 9685",
    "sg:postcode":"84107",
    "sg:province":"UT",
    "sg:tags":[
        "contractor"
    ],
    "wof:name":"Air Cndtning Htg By Dane Hnson",
    "wof:placetype":"venue"
},
  "geometry": {"coordinates":[-111.872798,40.649536],"type":"Point"}
}