{
  "type": "Feature",
  "properties": {
    "iso:country":"US",
    "sg:address":"750 N 700 E",
    "sg:city":"Spanish Fork",
    "sg:classifiers":[
        {
            "category":"Building & Trades",
            "subcategory":"Construction",
            "type":"Services"
        }
    ],
    "sg:phone":"+1 801 798 6881",
    "sg:postcode":"84660",
    "sg:province":"UT",
    "sg:tags":[
        "woodworker"
    ],
    "wof:name":"Jensen's Classic Woodworking",
    "wof:placetype":"venue"
},
  "geometry": {"coordinates":[-111.64266000000001,40.119447],"type":"Point"}
}