{
  "type": "Feature",
  "properties": {
    "iso:country":"US",
    "sg:address":"791 Coventry Ln",
    "sg:city":"Alpine",
    "sg:classifiers":[
        {
            "category":"Health Services",
            "subcategory":"Health Practitioner",
            "type":"Services"
        }
    ],
    "sg:phone":"+1 801 492 1772",
    "sg:postcode":"84004",
    "sg:province":"UT",
    "sg:tags":[
        "therapist",
        "physical"
    ],
    "wof:name":"B & K Physical Therapy Inc",
    "wof:placetype":"venue"
},
  "geometry": {"coordinates":[-111.764016,40.462986],"type":"Point"}
}