{
  "type": "Feature",
  "properties": {
    "iso:country":"US",
    "sg:address":"2375 E Middleton Dr",
    "sg:city":"St George",
    "sg:classifiers":[
        {
            "category":"Retail",
            "subcategory":"Auto Repair",
            "type":"Services"
        }
    ],
    "sg:phone":"+1 435 652 0702",
    "sg:postcode":"84770",
    "sg:province":"UT",
    "sg:tags":[
        "repairing",
        "automobile",
        "general"
    ],
    "wof:name":"Tri-City Auto & R V Repair",
    "wof:placetype":"venue"
},
  "geometry": {"coordinates":[-113.53515400000001,37.124562],"type":"Point"}
}