{
  "type": "Feature",
  "properties": {
    "iso:country":"US",
    "sg:address":"970 E 3300 S",
    "sg:city":"Salt Lake City",
    "sg:classifiers":[
        {
            "category":"Professional",
            "subcategory":"Accounting & Tax Preparation",
            "type":"Services"
        }
    ],
    "sg:phone":"+1 801 485 9003",
    "sg:postcode":"84106",
    "sg:province":"UT",
    "sg:tags":[
        "return",
        "filing"
    ],
    "wof:name":"Jackson Hewitt Tax Svc",
    "wof:placetype":"venue"
},
  "geometry": {"coordinates":[-111.863055,40.699814],"type":"Point"}
}