{
  "type": "Feature",
  "properties": {
    "iso:country":"US",
    "sg:address":"1207 Lost Eden Dr",
    "sg:city":"Sandy",
    "sg:classifiers":[
        {
            "category":"Retail",
            "subcategory":"Laundry & Dry Cleaning",
            "type":"Services"
        }
    ],
    "sg:phone":"+1 801 277 8152",
    "sg:postcode":"84094",
    "sg:province":"UT",
    "sg:tags":[
        "cleaners",
        "rug",
        "carpet"
    ],
    "wof:name":"Snow Carpet & Upholstery Clnrs",
    "wof:placetype":"venue"
},
  "geometry": {"coordinates":[-111.85857799999999,40.555258],"type":"Point"}
}