{
  "type": "Feature",
  "properties": {
    "iso:country":"US",
    "sg:address":"6159 S 2300 E",
    "sg:city":"Ogden",
    "sg:classifiers":[
        {
            "category":"Social Services",
            "subcategory":"Child Care",
            "type":"Services"
        }
    ],
    "sg:phone":"+1 801 479 3509",
    "sg:postcode":"84403",
    "sg:province":"UT",
    "sg:tags":[
        "day"
    ],
    "wof:name":"Critchlow Little Red Schl Hse",
    "wof:placetype":"venue"
},
  "geometry": {"coordinates":[-111.92331900000001,41.151114],"type":"Point"}
}