{
  "type": "Feature",
  "properties": {
    "iso:country":"US",
    "sg:address":"29 N 600 E",
    "sg:city":"Price",
    "sg:classifiers":[
        {
            "category":"Banks & Credit Unions",
            "subcategory":"Bank",
            "type":"Services"
        }
    ],
    "sg:phone":"+1 435 637 3305",
    "sg:postcode":"84501",
    "sg:province":"UT",
    "sg:tags":[
        "mortgage"
    ],
    "wof:name":"Bank Of Utah",
    "wof:placetype":"venue"
},
  "geometry": {"coordinates":[-110.79987300000001,39.600586],"type":"Point"}
}