{
  "type": "Feature",
  "properties": {
    "iso:country":"US",
    "sg:address":"5714 W 13400 S",
    "sg:city":"Riverton",
    "sg:classifiers":[
        {
            "category":"Retail",
            "subcategory":"Veterinary Services",
            "type":"Services"
        }
    ],
    "sg:phone":"+1 801 446 5194",
    "sg:postcode":"84065",
    "sg:province":"UT",
    "sg:tags":[
        "veterinarian"
    ],
    "wof:name":"Oquirrh Hills Veterinary Ctr",
    "wof:placetype":"venue"
},
  "geometry": {"coordinates":[-112.026511,40.507933],"type":"Point"}
}