{
  "type": "Feature",
  "properties": {
    "iso:country":"US",
    "sg:address":"363 N 970 E",
    "sg:city":"Logan",
    "sg:classifiers":[
        {
            "category":"Professional",
            "type":"Services"
        }
    ],
    "sg:phone":"+1 435 752 3941",
    "sg:postcode":"84321",
    "sg:province":"UT",
    "wof:name":"Lee Brilliant",
    "wof:placetype":"venue"
},
  "geometry": {"coordinates":[-111.810999,41.737682],"type":"Point"}
}