{
  "type": "Feature",
  "properties": {
    "iso:country":"US",
    "sg:address":"355 W 700 S",
    "sg:city":"Tooele",
    "sg:classifiers":[
        {
            "category":"Taxi",
            "type":"Transportation"
        }
    ],
    "sg:phone":"+1 435 882 8294",
    "sg:postcode":"84074",
    "sg:province":"UT",
    "sg:tags":[
        "taxicab"
    ],
    "wof:name":"Tooele Cab Co",
    "wof:placetype":"venue"
},
  "geometry": {"coordinates":[-112.309769,40.518257],"type":"Point"}
}