{
  "type": "Feature",
  "properties": {
    "iso:country":"US",
    "sg:address":"6000 W 5400 S",
    "sg:city":"Kearns",
    "sg:classifiers":[
        {
            "category":"Wholesale",
            "subcategory":"Construction Materials",
            "type":"Manufacturing & Wholesale Goods"
        }
    ],
    "sg:phone":"+1 801 969 1727",
    "sg:postcode":"84118",
    "sg:province":"UT",
    "sg:tags":[
        "sand",
        "gravel"
    ],
    "sg:website":"www.genevarock.com",
    "wof:name":"Geneva Rock Products Inc",
    "wof:placetype":"venue"
},
  "geometry": {"coordinates":[-112.033928,40.653146],"type":"Point"}
}