{
  "type": "Feature",
  "properties": {
    "iso:country":"US",
    "sg:address":"111 W 100 S",
    "sg:city":"Tremonton",
    "sg:classifiers":[
        {
            "category":"Personal",
            "subcategory":"Beauty Salon",
            "type":"Services"
        }
    ],
    "sg:phone":"+1 435 257 3227",
    "sg:postcode":"84337",
    "sg:province":"UT",
    "sg:tags":[
        "shop",
        "barber"
    ],
    "wof:name":"Hair Line",
    "wof:placetype":"venue"
},
  "geometry": {"coordinates":[-112.16880399999999,41.710423],"type":"Point"}
}