{
  "type": "Feature",
  "properties": {
    "iso:country":"US",
    "sg:address":"635 N 100 West St",
    "sg:city":"Orem",
    "sg:classifiers":[
        {
            "category":"Professional",
            "subcategory":"Business Services",
            "type":"Services"
        }
    ],
    "sg:phone":"+1 801 836 3966",
    "sg:postcode":"84057",
    "sg:province":"UT",
    "wof:name":"Digicom Enterprises",
    "wof:placetype":"venue"
},
  "geometry": {"coordinates":[-111.698211,40.308771],"type":"Point"}
}