{
  "type": "Feature",
  "properties": {
    "iso:country":"US",
    "sg:address":"170 E Shadowbrook Ln",
    "sg:city":"Kaysville",
    "sg:classifiers":[
        {
            "category":"Wholesale",
            "subcategory":"Vending Machines",
            "type":"Manufacturing & Wholesale Goods"
        }
    ],
    "sg:phone":"+1 801 544 9117",
    "sg:postcode":"84037",
    "sg:province":"UT",
    "sg:tags":[
        "operator"
    ],
    "wof:name":"Nova Vending Inc",
    "wof:placetype":"venue"
},
  "geometry": {"coordinates":[-111.933632,41.013724],"type":"Point"}
}