{
  "type": "Feature",
  "properties": {
    "iso:country":"US",
    "sg:address":"2821 S Hwy 10",
    "sg:city":"Price",
    "sg:classifiers":[
        {
            "category":"Organizations",
            "subcategory":"Religious Organization",
            "type":"Services"
        }
    ],
    "sg:phone":"+1 435 637 1162",
    "sg:postcode":"84501",
    "sg:province":"UT",
    "sg:tags":[
        "church"
    ],
    "wof:name":"Seventh-Day Adventist Church",
    "wof:placetype":"venue"
},
  "geometry": {"coordinates":[-110.815754,39.559899],"type":"Point"}
}