{
  "type": "Feature",
  "properties": {
    "iso:country":"US",
    "sg:address":"3463 W 1987 S",
    "sg:city":"Salt Lake City",
    "sg:classifiers":[
        {
            "category":"Building & Trades",
            "subcategory":"Equipment Rental",
            "type":"Services"
        }
    ],
    "sg:phone":"+1 801 972 6580",
    "sg:postcode":"84104",
    "sg:province":"UT",
    "sg:tags":[
        "commercial",
        "laundry",
        "t",
        "lease"
    ],
    "wof:name":"Evans Coin Meter",
    "wof:placetype":"venue"
},
  "geometry": {"coordinates":[-111.970348,40.728579],"type":"Point"}
}