{
  "type": "Feature",
  "properties": {
    "iso:country":"US",
    "sg:address":"7572 Grant St",
    "sg:city":"Midvale",
    "sg:classifiers":[
        {
            "category":"Wholesale",
            "subcategory":"Machinery & Supplies",
            "type":"Manufacturing & Wholesale Goods"
        }
    ],
    "sg:phone":"+1 801 561 5853",
    "sg:postcode":"84047",
    "sg:province":"UT",
    "sg:tags":[
        "spray",
        "booth"
    ],
    "wof:name":"Advanced Spray Booth Systems",
    "wof:placetype":"venue"
},
  "geometry": {"coordinates":[-111.896821,40.613182],"type":"Point"}
}