{
  "type": "Feature",
  "properties": {
    "iso:country":"US",
    "sg:address":"59 W 900 N",
    "sg:city":"Springville",
    "sg:classifiers":[
        {
            "category":"Banks & Credit Unions",
            "subcategory":"Bank",
            "type":"Services"
        }
    ],
    "sg:phone":"+1 801 491 0550",
    "sg:postcode":"84663",
    "sg:province":"UT",
    "wof:name":"Far West Bank",
    "wof:placetype":"venue"
},
  "geometry": {"coordinates":[-111.61538400000001,40.179447],"type":"Point"}
}