{
  "type": "Feature",
  "properties": {
    "iso:country":"US",
    "sg:address":"9072 S Sunrise Cir",
    "sg:city":"Sandy",
    "sg:classifiers":[
        {
            "category":"Wholesale",
            "subcategory":"Drugs",
            "type":"Manufacturing & Wholesale Goods"
        }
    ],
    "sg:phone":"+1 801 942 0067",
    "sg:postcode":"84093",
    "sg:province":"UT",
    "wof:name":"Wyeth",
    "wof:placetype":"venue"
},
  "geometry": {"coordinates":[-111.828987,40.585549],"type":"Point"}
}