{
  "type": "Feature",
  "properties": {
    "iso:country":"US",
    "sg:address":"363 N University Ave",
    "sg:city":"Provo",
    "sg:classifiers":[
        {
            "category":"Government",
            "subcategory":"Court House",
            "type":"Public Place"
        }
    ],
    "sg:phone":"+1 801 375 6839",
    "sg:postcode":"84601",
    "sg:province":"UT",
    "sg:tags":[
        "federal"
    ],
    "wof:name":"US District Court Probation",
    "wof:placetype":"venue"
},
  "geometry": {"coordinates":[-111.658728,40.238224],"type":"Point"}
}