{
  "type": "Feature",
  "properties": {
    "iso:country":"US",
    "sg:address":"1371 N 325 E",
    "sg:city":"Nephi",
    "sg:classifiers":[
        {
            "category":"Professional",
            "subcategory":"Management & Consulting",
            "type":"Services"
        }
    ],
    "sg:phone":"+1 435 623 3329",
    "sg:postcode":"84648",
    "sg:province":"UT",
    "sg:tags":[
        "ice",
        "cream"
    ],
    "wof:name":"Ice Cream Express",
    "wof:placetype":"venue"
},
  "geometry": {"coordinates":[-111.82977099999999,39.727919],"type":"Point"}
}