{
  "type": "Feature",
  "properties": {
    "iso:country":"US",
    "sg:address":"91 W Main St",
    "sg:city":"Vernal",
    "sg:classifiers":[
        {
            "category":"Personal",
            "subcategory":"Beauty Salon",
            "type":"Services"
        }
    ],
    "sg:phone":"+1 435 789 5451",
    "sg:postcode":"84078",
    "sg:province":"UT",
    "sg:tags":[
        "shop"
    ],
    "wof:name":"Salon 1210",
    "wof:placetype":"venue"
},
  "geometry": {"coordinates":[-109.530243,40.455622],"type":"Point"}
}