{
  "type": "Feature",
  "properties": {
    "iso:country":"US",
    "sg:address":"2400 S Hwy 191",
    "sg:city":"Moab",
    "sg:classifiers":[
        {
            "category":"Professional",
            "type":"Services"
        }
    ],
    "sg:phone":"+1 435 259 7250",
    "sg:postcode":"84532",
    "sg:province":"UT",
    "sg:tags":[
        "establishment"
    ],
    "wof:name":"Outward Bound West",
    "wof:placetype":"venue"
},
  "geometry": {"coordinates":[-109.512389,38.537266],"type":"Point"}
}