{
  "type": "Feature",
  "properties": {
    "iso:country":"US",
    "sg:address":"2105 S 2350 E",
    "sg:city":"Richfield",
    "sg:classifiers":[
        {
            "category":"Professional",
            "type":"Services"
        }
    ],
    "sg:phone":"+1 435 896 6947",
    "sg:postcode":"84790",
    "sg:province":"UT",
    "wof:name":"Snap-On Tools",
    "wof:placetype":"venue"
},
  "geometry": {"coordinates":[-113.53299,37.068732],"type":"Point"}
}