{
  "type": "Feature",
  "properties": {
    "iso:country":"US",
    "sg:address":"3676 S 1700 E",
    "sg:city":"St George",
    "sg:phone":"+1 435 656 0817",
    "sg:postcode":"84790",
    "sg:province":"UT",
    "sg:tags":[
        "gas"
    ],
    "wof:name":"Southern Utah Propane",
    "wof:placetype":"venue"
},
  "geometry": {"coordinates":[-113.54807099999999,37.068791],"type":"Point"}
}