{
  "type": "Feature",
  "properties": {
    "iso:country":"US",
    "sg:address":"4188 W 5415 S",
    "sg:city":"Salt Lake City",
    "sg:classifiers":[
        {
            "category":"Shopping",
            "subcategory":"Pharmacy",
            "type":"Retail Goods"
        }
    ],
    "sg:phone":"+1 801 969 1986",
    "sg:postcode":"84118",
    "sg:province":"UT",
    "wof:name":"Apothecary West United Drug",
    "wof:placetype":"venue"
},
  "geometry": {"coordinates":[-111.990332,40.652856],"type":"Point"}
}