{
  "type": "Feature",
  "properties": {
    "iso:country":"US",
    "sg:address":"2638 W 9435 S",
    "sg:city":"South Jordan",
    "sg:classifiers":[
        {
            "category":"Building & Trades",
            "subcategory":"Construction",
            "type":"Services"
        }
    ],
    "sg:phone":"+1 801 268 6232",
    "sg:postcode":"84095",
    "sg:province":"UT",
    "sg:tags":[
        "residential",
        "commercial"
    ],
    "wof:name":"Gustafson Construction Inc",
    "wof:placetype":"venue"
},
  "geometry": {"coordinates":[-111.95659499999999,40.57996],"type":"Point"}
}