{
  "type": "Feature",
  "properties": {
    "iso:country":"US",
    "sg:address":"3228 S 900 W",
    "sg:city":"Salt Lake City",
    "sg:classifiers":[
        {
            "category":"Wholesale",
            "subcategory":"Stationery",
            "type":"Manufacturing & Wholesale Goods"
        }
    ],
    "sg:phone":"+1 801 908 5225",
    "sg:postcode":"84119",
    "sg:province":"UT",
    "sg:tags":[
        "product",
        "paper"
    ],
    "wof:name":"Paper Plus",
    "wof:placetype":"venue"
},
  "geometry": {"coordinates":[-111.91701500000001,40.702769],"type":"Point"}
}