{
  "type": "Feature",
  "properties": {
    "iso:country":"US",
    "sg:address":"501 Chipeta Way",
    "sg:city":"Salt Lake City",
    "sg:classifiers":[
        {
            "category":"Health Services",
            "subcategory":"Health Practitioner",
            "type":"Services"
        }
    ],
    "sg:phone":"+1 801 587 3212",
    "sg:postcode":"84108",
    "sg:province":"UT",
    "sg:tags":[
        "psychologist"
    ],
    "wof:name":"John H Gill",
    "wof:placetype":"venue"
},
  "geometry": {"coordinates":[-111.82387,40.758908],"type":"Point"}
}