{
  "type": "Feature",
  "properties": {
    "iso:country":"US",
    "sg:address":"38 Uintah St",
    "sg:city":"Helper",
    "sg:classifiers":[
        {
            "category":"Bus Charters",
            "type":"Transportation"
        }
    ],
    "sg:phone":"+1 435 472 8269",
    "sg:postcode":"84526",
    "sg:province":"UT",
    "sg:tags":[
        "rental"
    ],
    "wof:name":"Smith Transit Inc",
    "wof:placetype":"venue"
},
  "geometry": {"coordinates":[-110.85967599999999,39.691922],"type":"Point"}
}