{
  "type": "Feature",
  "properties": {
    "iso:country":"US",
    "sg:address":"2415 S Morgan Valley Dr",
    "sg:city":"Morgan",
    "sg:classifiers":[
        {
            "category":"Building & Trades",
            "subcategory":"Construction",
            "type":"Services"
        }
    ],
    "sg:phone":"+1 801 829 6296",
    "sg:postcode":"84050",
    "sg:province":"UT",
    "sg:tags":[
        "house"
    ],
    "wof:name":"Unique Construction LLC",
    "wof:placetype":"venue"
},
  "geometry": {"coordinates":[-111.68462700000001,40.983234],"type":"Point"}
}