{
  "type": "Feature",
  "properties": {
    "iso:country":"US",
    "sg:address":"4362 S Hawarden Cir",
    "sg:city":"Salt Lake City",
    "sg:classifiers":[
        {
            "category":"Wholesale",
            "subcategory":"Construction Materials",
            "type":"Manufacturing & Wholesale Goods"
        }
    ],
    "sg:phone":"+1 801 968 4361",
    "sg:postcode":"84119",
    "sg:province":"UT",
    "sg:tags":[
        "concrete",
        "block",
        "filled",
        "styrene"
    ],
    "wof:name":"Janco Block",
    "wof:placetype":"venue"
},
  "geometry": {"coordinates":[-111.96864100000001,40.675998],"type":"Point"}
}