{
  "type": "Feature",
  "properties": {
    "iso:country":"US",
    "sg:address":"1011 Murray Holladay Rd",
    "sg:city":"Holladay",
    "sg:classifiers":[
        {
            "category":"Professional",
            "subcategory":"Computer Services",
            "type":"Services"
        }
    ],
    "sg:phone":"+1 801 262 2642",
    "sg:postcode":"84117",
    "sg:province":"UT",
    "wof:name":"Revinetix Inc",
    "wof:placetype":"venue"
},
  "geometry": {"coordinates":[-111.862922,40.665789],"type":"Point"}
}