{
  "type": "Feature",
  "properties": {
    "iso:country":"US",
    "sg:address":"2465 Doc Holiday Dr",
    "sg:city":"Park City",
    "sg:classifiers":[
        {
            "category":"Retail",
            "subcategory":"Animal Services",
            "type":"Services"
        }
    ],
    "sg:phone":"+1 435 649 4842",
    "sg:postcode":"84060",
    "sg:province":"UT",
    "sg:tags":[
        "mobile",
        "grooming"
    ],
    "wof:name":"Mobile Pet Grooming",
    "wof:placetype":"venue"
},
  "geometry": {"coordinates":[-111.49033,40.667474],"type":"Point"}
}