{
  "type": "Feature",
  "properties": {
    "iso:country":"US",
    "sg:address":"625 W 5300 S",
    "sg:city":"Salt Lake City",
    "sg:classifiers":[
        {
            "category":"Insurance",
            "subcategory":"Insurance Agent",
            "type":"Services"
        }
    ],
    "sg:phone":"+1 801 269 9703",
    "sg:postcode":"84123",
    "sg:province":"UT",
    "wof:name":"Farmers Insurance Group",
    "wof:placetype":"venue"
},
  "geometry": {"coordinates":[-111.909634,40.65379],"type":"Point"}
}