{
  "type": "Feature",
  "properties": {
    "iso:country":"US",
    "sg:address":"701 E 1950 N",
    "sg:city":"Orem",
    "sg:classifiers":[
        {
            "category":"Building & Trades",
            "subcategory":"Construction",
            "type":"Services"
        }
    ],
    "sg:phone":"+1 801 225 1867",
    "sg:postcode":"84097",
    "sg:province":"UT",
    "sg:tags":[
        "concrete",
        "contractor"
    ],
    "wof:name":"Bob Jensen Decorative Curbs",
    "wof:placetype":"venue"
},
  "geometry": {"coordinates":[-111.67917,40.332985],"type":"Point"}
}