{
  "type": "Feature",
  "properties": {
    "iso:country":"US",
    "sg:address":"4173 Sunrise Dr",
    "sg:city":"Park City",
    "sg:classifiers":[
        {
            "category":"Professional",
            "subcategory":"Accounting & Tax Preparation",
            "type":"Services"
        }
    ],
    "sg:phone":"+1 435 940 0775",
    "sg:postcode":"84098",
    "sg:province":"UT",
    "sg:tags":[
        "bookkeeping",
        "general"
    ],
    "wof:name":"Minding Your Business",
    "wof:placetype":"venue"
},
  "geometry": {"coordinates":[-111.590658,40.75588],"type":"Point"}
}