{
  "type": "Feature",
  "properties": {
    "iso:country":"US",
    "sg:address":"10 Exchange Pl",
    "sg:city":"Salt Lake City",
    "sg:classifiers":[
        {
            "category":"Manufacturing",
            "subcategory":"Tools & Machinery",
            "type":"Manufacturing & Wholesale Goods"
        }
    ],
    "sg:phone":"+1 801 366 4271",
    "sg:postcode":"84111",
    "sg:province":"UT",
    "sg:tags":[
        "mfg",
        "prepackaged",
        "storage",
        "devices",
        "computer",
        "software"
    ],
    "wof:name":"Emc2",
    "wof:placetype":"venue"
},
  "geometry": {"coordinates":[-111.88984000000001,40.761332],"type":"Point"}
}