{
  "type": "Feature",
  "properties": {
    "iso:country":"US",
    "sg:address":"5308 N 4200 W",
    "sg:city":"Cedar City",
    "sg:classifiers":[
        {
            "category":"Building & Trades",
            "subcategory":"Construction",
            "type":"Services"
        }
    ],
    "sg:phone":"+1 435 586 0112",
    "sg:postcode":"84720",
    "sg:province":"UT",
    "sg:tags":[
        "residential"
    ],
    "wof:name":"Atlas Development",
    "wof:placetype":"venue"
},
  "geometry": {"coordinates":[-113.135463,37.774258],"type":"Point"}
}