{
  "type": "Feature",
  "properties": {
    "iso:country":"US",
    "sg:address":"321 E 300 N",
    "sg:city":"American Fork",
    "sg:classifiers":[
        {
            "category":"Health Services",
            "subcategory":"Health Practitioner",
            "type":"Services"
        }
    ],
    "sg:phone":"+1 801 763 0724",
    "sg:postcode":"84003",
    "sg:province":"UT",
    "sg:tags":[
        "merchandise"
    ],
    "wof:name":"Timpanogos Audiology",
    "wof:placetype":"venue"
},
  "geometry": {"coordinates":[-111.789942,40.383105],"type":"Point"}
}