{
  "type": "Feature",
  "properties": {
    "iso:country":"US",
    "sg:address":"515 Bridlewalk Ln",
    "sg:city":"Salt Lake City",
    "sg:classifiers":[
        {
            "category":"Building & Trades",
            "subcategory":"Construction",
            "type":"Services"
        }
    ],
    "sg:phone":"+1 801 263 9377",
    "sg:postcode":"84107",
    "sg:province":"UT",
    "sg:tags":[
        "steel",
        "erection",
        "business",
        "structural"
    ],
    "wof:name":"Iverson Steel Erection Inc",
    "wof:placetype":"venue"
},
  "geometry": {"coordinates":[-111.876667,40.645272],"type":"Point"}
}