{
  "type": "Feature",
  "properties": {
    "iso:country":"US",
    "sg:address":"2740 California Ave",
    "sg:city":"Salt Lake City",
    "sg:classifiers":[
        {
            "category":"Retail",
            "subcategory":"Auto Rental",
            "type":"Services"
        }
    ],
    "sg:phone":"+1 801 977 9111",
    "sg:postcode":"84104",
    "sg:province":"UT",
    "sg:tags":[
        "renting",
        "automobile"
    ],
    "sg:website":"www.ruggedrental.com",
    "wof:name":"Fox Rent A Car",
    "wof:placetype":"venue"
},
  "geometry": {"coordinates":[-111.96216800000001,40.740489],"type":"Point"}
}