{
  "type": "Feature",
  "properties": {
    "iso:country":"US",
    "sg:address":"6525 S 1300 W",
    "sg:city":"Salt Lake City",
    "sg:classifiers":[
        {
            "category":"Shopping",
            "subcategory":"Computers & Home Electronics",
            "type":"Retail Goods"
        }
    ],
    "sg:phone":"+1 801 268 4805",
    "sg:postcode":"84123",
    "sg:province":"UT",
    "wof:name":"Hackerz Software",
    "wof:placetype":"venue"
},
  "geometry": {"coordinates":[-111.92917,40.632678],"type":"Point"}
}