{
  "type": "Feature",
  "properties": {
    "iso:country":"US",
    "sg:address":"1106 E 4500 S",
    "sg:city":"Murray",
    "sg:classifiers":[
        {
            "category":"Professional",
            "subcategory":"Art Services",
            "type":"Services"
        }
    ],
    "sg:phone":"+1 801 264 0082",
    "sg:postcode":"84117",
    "sg:province":"UT",
    "sg:tags":[
        "graphic",
        "designer"
    ],
    "wof:name":"Enspire Creative",
    "wof:placetype":"venue"
},
  "geometry": {"coordinates":[-111.859826,40.674222],"type":"Point"}
}