{
  "type": "Feature",
  "properties": {
    "iso:country":"US",
    "sg:address":"3031 N 975 E",
    "sg:city":"Ogden",
    "sg:classifiers":[
        {
            "category":"Wholesale",
            "subcategory":"Machinery & Supplies",
            "type":"Manufacturing & Wholesale Goods"
        }
    ],
    "sg:phone":"+1 801 782 1121",
    "sg:postcode":"84414",
    "sg:province":"UT",
    "sg:tags":[
        "shop",
        "equipment",
        "establishment",
        "beauty"
    ],
    "wof:name":"Creative Designs",
    "wof:placetype":"venue"
},
  "geometry": {"coordinates":[-111.94971099999999,41.316347],"type":"Point"}
}