{
  "type": "Feature",
  "properties": {
    "iso:country":"US",
    "sg:address":"172 S 300 E",
    "sg:city":"American Fork",
    "sg:classifiers":[
        {
            "category":"Retail",
            "subcategory":"Auto Repair",
            "type":"Services"
        }
    ],
    "sg:phone":"+1 801 756 5163",
    "sg:postcode":"84003",
    "sg:province":"UT",
    "sg:tags":[
        "automotive"
    ],
    "wof:name":"Edgar Automotive Punto Com",
    "wof:placetype":"venue"
},
  "geometry": {"coordinates":[-111.790745,40.374471],"type":"Point"}
}