{
  "type": "Feature",
  "properties": {
    "iso:country":"US",
    "sg:address":"155 W 300 S",
    "sg:city":"La Verkin",
    "sg:classifiers":[
        {
            "category":"Freight",
            "type":"Transportation"
        }
    ],
    "sg:phone":"+1 435 635 5848",
    "sg:postcode":"84745",
    "sg:province":"UT",
    "wof:name":"JB Macier Transportation Servi",
    "wof:placetype":"venue"
},
  "geometry": {"coordinates":[-113.27396400000001,37.19549],"type":"Point"}
}