{
  "type": "Feature",
  "properties": {
    "iso:country":"US",
    "sg:address":"5863 Jamiah Dr",
    "sg:city":"Salt Lake City",
    "sg:classifiers":[
        {
            "category":"Building & Trades",
            "subcategory":"Plumbing",
            "type":"Services"
        }
    ],
    "sg:phone":"+1 801 262 4709",
    "sg:postcode":"84123",
    "sg:province":"UT",
    "sg:tags":[
        "contractor"
    ],
    "wof:name":"Good Looking Daves Inc",
    "wof:placetype":"venue"
},
  "geometry": {"coordinates":[-111.90820600000001,40.643507],"type":"Point"}
}