{
  "type": "Feature",
  "properties": {
    "iso:country":"US",
    "sg:address":"55 W 500 S",
    "sg:city":"Provo",
    "sg:classifiers":[
        {
            "category":"Wholesale",
            "subcategory":"Farm Supplies",
            "type":"Manufacturing & Wholesale Goods"
        }
    ],
    "sg:phone":"+1 801 373 7680",
    "sg:postcode":"84601",
    "sg:province":"UT",
    "sg:tags":[
        "feed"
    ],
    "wof:name":"IFA Country Stores",
    "wof:placetype":"venue"
},
  "geometry": {"coordinates":[-111.65975299999999,40.226968],"type":"Point"}
}