{
  "type": "Feature",
  "properties": {
    "iso:country":"US",
    "sg:address":"1955 Wall Ave",
    "sg:city":"Ogden",
    "sg:classifiers":[
        {
            "category":"Bars & Pubs",
            "type":"Food & Drink"
        }
    ],
    "sg:phone":"+1 801 622 8667",
    "sg:postcode":"84401",
    "sg:province":"UT",
    "wof:name":"Tommy's Place",
    "wof:placetype":"venue"
},
  "geometry": {"coordinates":[-111.97866,41.232977],"type":"Point"}
}