{
  "type": "Feature",
  "properties": {
    "iso:country":"US",
    "sg:address":"2053 Sidewinder Dr",
    "sg:city":"Park City",
    "sg:classifiers":[
        {
            "category":"Building & Trades",
            "subcategory":"Construction",
            "type":"Services"
        }
    ],
    "sg:phone":"+1 435 615 8485",
    "sg:postcode":"84060",
    "sg:province":"UT",
    "sg:tags":[
        "general",
        "contractor"
    ],
    "wof:name":"W F Dator Constr Systems Inc",
    "wof:placetype":"venue"
},
  "geometry": {"coordinates":[-111.49491399999999,40.664003],"type":"Point"}
}