{
  "type": "Feature",
  "properties": {
    "iso:country":"US",
    "sg:address":"477 S Main St",
    "sg:city":"Brigham City",
    "sg:classifiers":[
        {
            "category":"Utilities",
            "subcategory":"Mobile Phone",
            "type":"Services"
        }
    ],
    "sg:phone":"+1 435 723 4111",
    "sg:postcode":"84302",
    "sg:province":"UT",
    "sg:tags":[
        "telephone",
        "cellular"
    ],
    "wof:name":"Lund Satellite",
    "wof:placetype":"venue"
},
  "geometry": {"coordinates":[-112.015805,41.502587],"type":"Point"}
}