{
  "type": "Feature",
  "properties": {
    "iso:country":"US",
    "sg:address":"155 W Commonwealth Ave",
    "sg:city":"South Salt Lake",
    "sg:classifiers":[
        {
            "category":"Shopping",
            "type":"Retail Goods"
        },
        {
            "category":"Building & Trades",
            "subcategory":"Construction",
            "type":"Services"
        }
    ],
    "sg:phone":"+1 801 466 1010",
    "sg:postcode":"84115",
    "sg:province":"UT",
    "sg:tags":[
        "contractor",
        "carpentry",
        "wood",
        "carving"
    ],
    "wof:name":"Architectural Wood Carving",
    "wof:placetype":"venue"
},
  "geometry": {"coordinates":[-111.895262,40.724517],"type":"Point"}
}