{
  "type": "Feature",
  "properties": {
    "iso:country":"US",
    "sg:address":"3060 S Redwood Rd",
    "sg:city":"Salt Lake City",
    "sg:classifiers":[
        {
            "category":"Health Services",
            "subcategory":"Doctor",
            "type":"Services"
        }
    ],
    "sg:phone":"+1 801 972 0555",
    "sg:postcode":"84119",
    "sg:province":"UT",
    "wof:name":"Ray E Dillman Jr DDS",
    "wof:placetype":"venue"
},
  "geometry": {"coordinates":[-111.93900600000001,40.704924],"type":"Point"}
}