{
  "type": "Feature",
  "properties": {
    "iso:country":"US",
    "sg:address":"1025 S Jordan Pkwy",
    "sg:city":"West Jordan",
    "sg:classifiers":[
        {
            "category":"Health Services",
            "subcategory":"Chiropractor",
            "type":"Services"
        }
    ],
    "sg:phone":"+1 801 523 3898",
    "sg:postcode":"84095",
    "sg:province":"UT",
    "wof:name":"Alta View Chiropractic",
    "wof:placetype":"venue"
},
  "geometry": {"coordinates":[-111.919954,40.560391],"type":"Point"}
}