{
  "type": "Feature",
  "properties": {
    "iso:country":"US",
    "sg:address":"341 N 840 E",
    "sg:city":"Tooele",
    "sg:classifiers":[
        {
            "category":"Professional",
            "subcategory":"Business Services",
            "type":"Services"
        }
    ],
    "sg:phone":"+1 435 833 9289",
    "sg:postcode":"84074",
    "sg:province":"UT",
    "wof:name":"Parmer Enterprises",
    "wof:placetype":"venue"
},
  "geometry": {"coordinates":[-112.275679,40.537897],"type":"Point"}
}