{
  "type": "Feature",
  "properties": {
    "iso:country":"US",
    "sg:address":"S. Parke Center Dr",
    "sg:city":"Midvale",
    "sg:classifiers":[
        {
            "category":"Cafe",
            "type":"Food & Drink"
        }
    ],
    "sg:menulink":"http://www.allmenus.com/ut/salt-lake-city/34826-cafe-rio/menu/",
    "sg:phone":"+1 801 562 4431",
    "sg:postcode":"84047",
    "sg:province":"UT",
    "sg:tags":[
        "mexican"
    ],
    "wof:name":"Cafe Rio",
    "wof:placetype":"venue"
},
  "geometry": {"coordinates":[-111.85090099999999,40.625567],"type":"Point"}
}