{
  "type": "Feature",
  "properties": {
    "iso:country":"US",
    "sg:address":"101 E 2000 N",
    "sg:city":"Ogden",
    "sg:classifiers":[
        {
            "category":"Building & Trades",
            "subcategory":"Construction",
            "type":"Services"
        }
    ],
    "sg:phone":"+1 801 725 6099",
    "sg:postcode":"84414",
    "sg:province":"UT",
    "sg:tags":[
        "excavation",
        "contractor"
    ],
    "wof:name":"Jack Kunz Construction",
    "wof:placetype":"venue"
},
  "geometry": {"coordinates":[-111.974433,41.294692],"type":"Point"}
}