{
  "type": "Feature",
  "properties": {
    "iso:country":"US",
    "sg:address":"1753 Pine Canyon Rd",
    "sg:city":"Tooele",
    "sg:classifiers":[
        {
            "category":"Government",
            "subcategory":"Fire Station",
            "type":"Public Place"
        }
    ],
    "sg:phone":"+1 435 882 8304",
    "sg:postcode":"84074",
    "sg:province":"UT",
    "sg:tags":[
        "department"
    ],
    "wof:name":"Pine Canyon Fire Station",
    "wof:placetype":"venue"
},
  "geometry": {"coordinates":[-112.262434,40.565963],"type":"Point"}
}