{
  "type": "Feature",
  "properties": {
    "iso:country":"US",
    "sg:address":"4710 Zimmerman Ln",
    "sg:city":"Moab",
    "sg:classifiers":[
        {
            "category":"Manufacturing",
            "subcategory":"Food",
            "type":"Manufacturing & Wholesale Goods"
        }
    ],
    "sg:phone":"+1 435 259 8134",
    "sg:postcode":"84532",
    "sg:province":"UT",
    "sg:tags":[
        "mfg"
    ],
    "wof:name":"Spanish Vly Vneyards Winery Lc",
    "wof:placetype":"venue"
},
  "geometry": {"coordinates":[-109.47141499999999,38.502013],"type":"Point"}
}