{
  "type": "Feature",
  "properties": {
    "iso:country":"US",
    "sg:address":"280 W 1000 N",
    "sg:city":"Logan",
    "sg:classifiers":[
        {
            "category":"Education",
            "subcategory":"Special Training",
            "type":"Public Place"
        }
    ],
    "sg:phone":"+1 435 752 6260",
    "sg:postcode":"84321",
    "sg:province":"UT",
    "sg:tags":[
        "instruction",
        "music"
    ],
    "wof:name":"Cache Children's Choir",
    "wof:placetype":"venue"
},
  "geometry": {"coordinates":[-111.840907,41.75018],"type":"Point"}
}