{
  "type": "Feature",
  "properties": {
    "iso:country":"US",
    "sg:address":"1172 US Hwy 6",
    "sg:city":"Payson",
    "sg:classifiers":[
        {
            "category":"Shopping",
            "subcategory":"Optical Goods",
            "type":"Retail Goods"
        }
    ],
    "sg:phone":"+1 801 465 0104",
    "sg:postcode":"84651",
    "sg:province":"UT",
    "wof:name":"Ogden Office",
    "wof:placetype":"venue"
},
  "geometry": {"coordinates":[-111.738381,40.028633],"type":"Point"}
}