{
  "type": "Feature",
  "properties": {
    "iso:country":"US",
    "sg:address":"329 W 3rd Ave",
    "sg:city":"Dugway",
    "sg:classifiers":[
        {
            "category":"Professional",
            "type":"Services"
        }
    ],
    "sg:phone":"+1 435 831 5282",
    "sg:postcode":"84022",
    "sg:province":"UT",
    "wof:name":"Michael Maughan",
    "wof:placetype":"venue"
},
  "geometry": {"coordinates":[-112.752014,40.223461],"type":"Point"}
}