{
  "type": "Feature",
  "properties": {
    "iso:country":"US",
    "sg:address":"2087 W Center St",
    "sg:city":"Provo",
    "sg:classifiers":[
        {
            "category":"Wholesale",
            "subcategory":"Home Furnishings",
            "type":"Manufacturing & Wholesale Goods"
        }
    ],
    "sg:phone":"+1 801 735 8100",
    "sg:postcode":"84601",
    "sg:province":"UT",
    "sg:tags":[
        "closet",
        "accessory"
    ],
    "wof:name":"First Class Closets",
    "wof:placetype":"venue"
},
  "geometry": {"coordinates":[-111.695593,40.233786],"type":"Point"}
}