{
  "type": "Feature",
  "properties": {
    "iso:country":"US",
    "sg:address":"644 N 800 W",
    "sg:city":"Cedar City",
    "sg:classifiers":[
        {
            "category":"Manufacturing",
            "subcategory":"Signs",
            "type":"Manufacturing & Wholesale Goods"
        }
    ],
    "sg:phone":"+1 435 586 7212",
    "sg:postcode":"84720",
    "sg:province":"UT",
    "wof:name":"Three Peaks Graphics",
    "wof:placetype":"venue"
},
  "geometry": {"coordinates":[-113.07386,37.68664],"type":"Point"}
}