{
  "type": "Feature",
  "properties": {
    "iso:country":"US",
    "sg:address":"1256 E Black Horse Dr",
    "sg:city":"Spanish Fork",
    "sg:classifiers":[
        {
            "category":"Building & Trades",
            "subcategory":"Construction",
            "type":"Services"
        }
    ],
    "sg:phone":"+1 801 794 9792",
    "sg:postcode":"84660",
    "sg:province":"UT",
    "sg:tags":[
        "general",
        "contractor"
    ],
    "wof:name":"L & T Construction",
    "wof:placetype":"venue"
},
  "geometry": {"coordinates":[-111.633093,40.118792],"type":"Point"}
}