{
  "type": "Feature",
  "properties": {
    "iso:country":"US",
    "sg:address":"6637 W 9850 N",
    "sg:city":"Highland",
    "sg:classifiers":[
        {
            "category":"Health Services",
            "subcategory":"Medical Lab",
            "type":"Services"
        }
    ],
    "sg:phone":"+1 801 572 5171",
    "sg:postcode":"84003",
    "sg:province":"UT",
    "sg:tags":[
        "laboratory"
    ],
    "wof:name":"Best Dental Lab",
    "wof:placetype":"venue"
},
  "geometry": {"coordinates":[-111.81726999999999,40.410725],"type":"Point"}
}