{
  "type": "Feature",
  "properties": {
    "iso:country":"US",
    "sg:address":"900 Bitner Rd",
    "sg:city":"Park City",
    "sg:classifiers":[
        {
            "category":"Building & Trades",
            "subcategory":"Construction",
            "type":"Services"
        }
    ],
    "sg:phone":"+1 435 647 5935",
    "sg:postcode":"84098",
    "sg:province":"UT",
    "sg:tags":[
        "concrete",
        "contractor"
    ],
    "wof:name":"American Concrete Pavement",
    "wof:placetype":"venue"
},
  "geometry": {"coordinates":[-111.529404,40.72354],"type":"Point"}
}