{
  "type": "Feature",
  "properties": {
    "iso:country":"US",
    "sg:address":"10170 Kalinda Dr",
    "sg:city":"Sandy",
    "sg:classifiers":[
        {
            "category":"Food & Beverages",
            "subcategory":"Bakery",
            "type":"Retail Goods"
        }
    ],
    "sg:phone":"+1 801 942 4434",
    "sg:postcode":"84092",
    "sg:province":"UT",
    "wof:name":"Bakers Korner Inc",
    "wof:placetype":"venue"
},
  "geometry": {"coordinates":[-111.828033,40.566859],"type":"Point"}
}