{
  "type": "Feature",
  "properties": {
    "iso:country":"US",
    "sg:address":"1195 S 1680 W",
    "sg:city":"Orem",
    "sg:classifiers":[
        {
            "category":"Manufacturing",
            "subcategory":"Building Materials",
            "type":"Manufacturing & Wholesale Goods"
        }
    ],
    "sg:phone":"+1 801 224 4069",
    "sg:postcode":"84058",
    "sg:province":"UT",
    "wof:name":"Woodcraft",
    "wof:placetype":"venue"
},
  "geometry": {"coordinates":[-111.735218,40.274756],"type":"Point"}
}