{
  "type": "Feature",
  "properties": {
    "iso:country":"US",
    "sg:address":"1082 E 8175 S",
    "sg:city":"Sandy",
    "sg:classifiers":[
        {
            "category":"Banks & Credit Unions",
            "subcategory":"Financial Services",
            "type":"Services"
        }
    ],
    "sg:phone":"+1 801 352 2936",
    "sg:postcode":"84094",
    "sg:province":"UT",
    "sg:tags":[
        "company",
        "holding"
    ],
    "wof:name":"Slauson Holdings Inc",
    "wof:placetype":"venue"
},
  "geometry": {"coordinates":[-111.85992,40.602645],"type":"Point"}
}