{
  "type": "Feature",
  "properties": {
    "iso:country":"US",
    "sg:address":"465 E 9800 S",
    "sg:city":"Sandy",
    "sg:classifiers":[
        {
            "category":"Health Services",
            "subcategory":"Clinic",
            "type":"Services"
        }
    ],
    "sg:phone":"+1 801 523 8777",
    "sg:postcode":"84070",
    "sg:province":"UT",
    "sg:tags":[
        "home",
        "care"
    ],
    "wof:name":"Country Care Homes",
    "wof:placetype":"venue"
},
  "geometry": {"coordinates":[-111.878512,40.573335],"type":"Point"}
}