{
  "type": "Feature",
  "properties": {
    "iso:country":"US",
    "sg:address":"1493 Riverside Dr",
    "sg:city":"Salt Lake City",
    "sg:classifiers":[
        {
            "category":"Home & Garden",
            "subcategory":"Building Materials",
            "type":"Retail Goods"
        }
    ],
    "sg:phone":"+1 801 972 3819",
    "sg:postcode":"84104",
    "sg:province":"UT",
    "wof:name":"Aim Windows",
    "wof:placetype":"venue"
},
  "geometry": {"coordinates":[-111.92226599999999,40.735926],"type":"Point"}
}