{
  "type": "Feature",
  "properties": {
    "iso:country":"US",
    "sg:address":"5764 W 4600 S",
    "sg:city":"Hooper",
    "sg:classifiers":[
        {
            "category":"Building & Trades",
            "subcategory":"Equipment Rental",
            "type":"Services"
        }
    ],
    "sg:phone":"+1 801 985 1009",
    "sg:postcode":"84315",
    "sg:province":"UT",
    "sg:tags":[
        "heavy",
        "construction"
    ],
    "wof:name":"Penrod Group",
    "wof:placetype":"venue"
},
  "geometry": {"coordinates":[-112.11620499999999,41.178943],"type":"Point"}
}