{
  "type": "Feature",
  "properties": {
    "iso:country":"US",
    "sg:address":"251 S 200 E",
    "sg:city":"American Fork",
    "sg:classifiers":[
        {
            "category":"Government",
            "subcategory":"Office",
            "type":"Public Place"
        }
    ],
    "sg:phone":"+1 801 763 6360",
    "sg:postcode":"84003",
    "sg:province":"UT",
    "sg:tags":[
        "national",
        "guard"
    ],
    "wof:name":"National Guard Utah",
    "wof:placetype":"venue"
},
  "geometry": {"coordinates":[-111.793083,40.369817],"type":"Point"}
}