{
  "type": "Feature",
  "properties": {
    "iso:country":"US",
    "sg:address":"1501 N Main St",
    "sg:city":"Layton",
    "sg:classifiers":[
        {
            "category":"Retail",
            "subcategory":"Auto Repair",
            "type":"Services"
        }
    ],
    "sg:phone":"+1 801 544 5983",
    "sg:postcode":"84041",
    "sg:province":"UT",
    "sg:tags":[
        "repairing",
        "automobile"
    ],
    "wof:name":"KWIK City Auto & Rpr Muffler",
    "wof:placetype":"venue"
},
  "geometry": {"coordinates":[-111.994342,41.083317],"type":"Point"}
}