{
  "type": "Feature",
  "properties": {
    "iso:country":"US",
    "sg:address":"663 Market Dr",
    "sg:city":"Centerville",
    "sg:classifiers":[
        {
            "category":"Restaurant",
            "type":"Food & Drink"
        }
    ],
    "sg:phone":"+1 801 298 7849",
    "sg:postcode":"84078",
    "sg:province":"UT",
    "sg:tags":[
        "delicatessen"
    ],
    "wof:name":"Quiznos Sub",
    "wof:placetype":"venue"
},
  "geometry": {"coordinates":[-109.547172,40.454581],"type":"Point"}
}