{
  "type": "Feature",
  "properties": {
    "iso:country":"US",
    "sg:address":"375 W 1600 N",
    "sg:city":"Mapleton",
    "sg:classifiers":[
        {
            "category":"Retail",
            "subcategory":"Repair Shop",
            "type":"Services"
        }
    ],
    "sg:phone":"+1 801 489 9694",
    "sg:postcode":"84664",
    "sg:province":"UT",
    "sg:tags":[
        "electrical"
    ],
    "wof:name":"Baker Audio Video Repair",
    "wof:placetype":"venue"
},
  "geometry": {"coordinates":[-111.58288,40.144788],"type":"Point"}
}