{
  "type": "Feature",
  "properties": {
    "iso:country":"US",
    "sg:address":"8538 S Bingham Vw",
    "sg:city":"West Jordan",
    "sg:classifiers":[
        {
            "category":"Home & Garden",
            "subcategory":"Home Furnishings",
            "type":"Retail Goods"
        }
    ],
    "sg:phone":"+1 801 282 1694",
    "sg:postcode":"84088",
    "sg:province":"UT",
    "wof:name":"Body Bliss",
    "wof:placetype":"venue"
},
  "geometry": {"coordinates":[-111.997749,40.595658],"type":"Point"}
}