{
  "type": "Feature",
  "properties": {
    "iso:country":"US",
    "sg:address":"315 E Broadway",
    "sg:city":"Salt Lake City",
    "sg:classifiers":[
        {
            "category":"Shopping",
            "type":"Retail Goods"
        }
    ],
    "sg:phone":"+1 801 363 1016",
    "sg:postcode":"84111",
    "sg:province":"UT",
    "sg:tags":[
        "art",
        "gallery",
        "dealer"
    ],
    "wof:name":"KAYO Gallery",
    "wof:placetype":"venue"
},
  "geometry": {"coordinates":[-111.879948,40.762904],"type":"Point"}
}