{
  "type": "Feature",
  "properties": {
    "iso:country":"US",
    "sg:address":"1712 Mueller Park Rd",
    "sg:city":"Bountiful",
    "sg:classifiers":[
        {
            "category":"Professional",
            "subcategory":"Management & Consulting",
            "type":"Services"
        }
    ],
    "sg:phone":"+1 801 299 9508",
    "sg:postcode":"84010",
    "sg:province":"UT",
    "sg:tags":[
        "construction"
    ],
    "wof:name":"Prows Development Inc",
    "wof:placetype":"venue"
},
  "geometry": {"coordinates":[-111.84488,40.867564],"type":"Point"}
}