{
  "type": "Feature",
  "properties": {
    "iso:country":"US",
    "sg:address":"7086 Highland Dr",
    "sg:city":"Salt Lake City",
    "sg:classifiers":[
        {
            "category":"Insurance",
            "subcategory":"Life Insurance",
            "type":"Services"
        }
    ],
    "sg:phone":"+1 801 733 4015",
    "sg:postcode":"84121",
    "sg:province":"UT",
    "sg:tags":[
        "carrier"
    ],
    "wof:name":"Ing America Insur Holdings Inc",
    "wof:placetype":"venue"
},
  "geometry": {"coordinates":[-111.83435799999999,40.622045],"type":"Point"}
}