{
  "type": "Feature",
  "properties": {
    "iso:country":"US",
    "sg:address":"376 Lawndale Dr",
    "sg:city":"South Salt Lake",
    "sg:classifiers":[
        {
            "category":"Shopping",
            "subcategory":"Pharmacy",
            "type":"Retail Goods"
        }
    ],
    "sg:phone":"+1 801 486 9555",
    "sg:postcode":"84115",
    "sg:province":"UT",
    "sg:website":"www.kindredhealthcare.com",
    "wof:name":"Kindred Pharmacy Svc",
    "wof:placetype":"venue"
},
  "geometry": {"coordinates":[-111.902721,40.715017],"type":"Point"}
}