{
  "type": "Feature",
  "properties": {
    "iso:country":"US",
    "sg:address":"6975 Union Park Center",
    "sg:city":"Midvale",
    "sg:classifiers":[
        {
            "category":"Social Services",
            "subcategory":"Job Training",
            "type":"Services"
        }
    ],
    "sg:phone":"+1 801 568 5980",
    "sg:postcode":"84047",
    "sg:province":"UT",
    "sg:tags":[
        "rehabilitation",
        "vocational"
    ],
    "wof:name":"GENEX Services Inc",
    "wof:placetype":"venue"
},
  "geometry": {"coordinates":[-111.86049800000001,40.62518],"type":"Point"}
}