{
  "type": "Feature",
  "properties": {
    "iso:country":"US",
    "sg:address":"596 Robin Rd",
    "sg:city":"Orem",
    "sg:classifiers":[
        {
            "category":"Professional",
            "subcategory":"Management & Consulting",
            "type":"Services"
        }
    ],
    "sg:phone":"+1 801 224 1411",
    "sg:postcode":"84097",
    "sg:province":"UT",
    "wof:name":"Professional Group",
    "wof:placetype":"venue"
},
  "geometry": {"coordinates":[-111.68221200000001,40.330385],"type":"Point"}
}