{
  "type": "Feature",
  "properties": {
    "iso:country":"US",
    "sg:address":"120 S 300 E",
    "sg:city":"Salt Lake City",
    "sg:classifiers":[
        {
            "category":"Real Estate",
            "subcategory":"Real Estate Operator",
            "type":"Services"
        }
    ],
    "sg:phone":"+1 801 364 2934",
    "sg:postcode":"84111",
    "sg:province":"UT",
    "sg:tags":[
        "building",
        "apartment"
    ],
    "wof:name":"Pauline Downs APT",
    "wof:placetype":"venue"
},
  "geometry": {"coordinates":[-111.88257900000001,40.766784],"type":"Point"}
}