{
  "type": "Feature",
  "properties": {
    "iso:country":"US",
    "sg:address":"150 S 700 E",
    "sg:city":"Salt Lake City",
    "sg:classifiers":[
        {
            "category":"Communications",
            "subcategory":"Film & Video Production",
            "type":"Services"
        }
    ],
    "sg:phone":"+1 801 350 8340",
    "sg:postcode":"84102",
    "sg:province":"UT",
    "sg:tags":[
        "motion"
    ],
    "wof:name":"Sullivan Presentations LLC",
    "wof:placetype":"venue"
},
  "geometry": {"coordinates":[-111.871134,40.765299],"type":"Point"}
}