{
  "type": "Feature",
  "properties": {
    "iso:country":"US",
    "sg:address":"723 Valley View Dr",
    "sg:city":"Tooele",
    "sg:classifiers":[
        {
            "category":"Arts & Performance",
            "subcategory":"Theater",
            "type":"Entertainment"
        }
    ],
    "sg:phone":"+1 435 882 6688",
    "sg:postcode":"84074",
    "sg:province":"UT",
    "sg:tags":[
        "group"
    ],
    "wof:name":"Fantasy Flavor Mobile Sound",
    "wof:placetype":"venue"
},
  "geometry": {"coordinates":[-112.279292,40.543753],"type":"Point"}
}