{
  "type": "Feature",
  "properties": {
    "iso:country":"US",
    "sg:address":"1552 Barcon Rd",
    "sg:city":"Salt Lake City",
    "sg:classifiers":[
        {
            "category":"Manufacturing",
            "subcategory":"Glass & Minerals",
            "type":"Manufacturing & Wholesale Goods"
        }
    ],
    "sg:phone":"+1 801 272 1490",
    "sg:postcode":"84117",
    "sg:province":"UT",
    "sg:tags":[
        "mfg"
    ],
    "wof:name":"Vitreous",
    "wof:placetype":"venue"
},
  "geometry": {"coordinates":[-111.846434,40.650204],"type":"Point"}
}