{
  "type": "Feature",
  "properties": {
    "iso:country":"US",
    "sg:address":"175 W 7065 S",
    "sg:city":"Midvale",
    "sg:classifiers":[
        {
            "category":"Home & Garden",
            "subcategory":"Building Materials",
            "type":"Retail Goods"
        },
        {
            "category":"Wholesale",
            "subcategory":"Auto Parts",
            "type":"Manufacturing & Wholesale Goods"
        }
    ],
    "sg:phone":"+1 801 255 2556",
    "sg:postcode":"84047",
    "sg:province":"UT",
    "sg:tags":[
        "glass",
        "window",
        "plate",
        "repair"
    ],
    "wof:name":"Diamond Glass Co",
    "wof:placetype":"venue"
},
  "geometry": {"coordinates":[-111.89035199999999,40.622992],"type":"Point"}
}