{
  "type": "Feature",
  "properties": {
    "iso:country":"US",
    "sg:address":"549 E 1860 S",
    "sg:city":"Provo",
    "sg:classifiers":[
        {
            "category":"Professional",
            "subcategory":"Computer Services",
            "type":"Services"
        }
    ],
    "sg:phone":"+1 801 229 2794",
    "sg:postcode":"84606",
    "sg:province":"UT",
    "sg:tags":[
        "internet"
    ],
    "wof:name":"Investor Tool Box",
    "wof:placetype":"venue"
},
  "geometry": {"coordinates":[-111.650678,40.208636],"type":"Point"}
}