{
  "type": "Feature",
  "properties": {
    "iso:country":"US",
    "sg:address":"1030 W 2610 S",
    "sg:city":"Salt Lake City",
    "sg:classifiers":[
        {
            "category":"Professional",
            "type":"Services"
        }
    ],
    "sg:phone":"+1 801 973 4653",
    "sg:postcode":"84119",
    "sg:province":"UT",
    "sg:tags":[
        "establishment"
    ],
    "wof:name":"Darol Wagstaff Enterprises",
    "wof:placetype":"venue"
},
  "geometry": {"coordinates":[-111.92112899999999,40.714814],"type":"Point"}
}