{
  "type": "Feature",
  "properties": {
    "iso:country":"US",
    "sg:address":"421 Main St",
    "sg:city":"Park City",
    "sg:classifiers":[
        {
            "category":"Shopping",
            "type":"Retail Goods"
        }
    ],
    "sg:phone":"+1 435 649 2155",
    "sg:postcode":"84060",
    "sg:province":"UT",
    "sg:tags":[
        "art",
        "gallery",
        "dealer"
    ],
    "wof:name":"Flat Rabbet Gallery & Framing",
    "wof:placetype":"venue"
},
  "geometry": {"coordinates":[-111.49606,40.643916],"type":"Point"}
}