{
  "type": "Feature",
  "properties": {
    "iso:country":"US",
    "sg:address":"425 E 150 S",
    "sg:city":"Venice",
    "sg:classifiers":[
        {
            "category":"Building & Trades",
            "subcategory":"Plumbing",
            "type":"Services"
        }
    ],
    "sg:phone":"+1 435 896 4021",
    "sg:postcode":"84711",
    "sg:province":"UT",
    "sg:tags":[
        "septic"
    ],
    "wof:name":"Valley Tank Svc",
    "wof:placetype":"venue"
},
  "geometry": {"coordinates":[-112.052328,38.706158],"type":"Point"}
}