{
  "type": "Feature",
  "properties": {
    "iso:country":"US",
    "sg:address":"50 S Main St",
    "sg:city":"Salt Lake City",
    "sg:classifiers":[
        {
            "category":"Personal",
            "subcategory":"Beauty Salon",
            "type":"Services"
        }
    ],
    "sg:phone":"+1 801 532 7583",
    "sg:postcode":"84101",
    "sg:province":"UT",
    "sg:tags":[
        "hair"
    ],
    "wof:name":"Bellezza Inc",
    "wof:placetype":"venue"
},
  "geometry": {"coordinates":[-111.89117,40.76826],"type":"Point"}
}