{
  "type": "Feature",
  "properties": {
    "iso:country":"US",
    "sg:address":"5316 S 4015 W",
    "sg:city":"Salt Lake City",
    "sg:classifiers":[
        {
            "category":"Building & Trades",
            "subcategory":"Equipment Rental",
            "type":"Services"
        }
    ],
    "sg:phone":"+1 801 966 6300",
    "sg:postcode":"84118",
    "sg:province":"UT",
    "wof:name":"Diamond Rental Inc",
    "wof:placetype":"venue"
},
  "geometry": {"coordinates":[-111.986981,40.653661],"type":"Point"}
}