{
  "type": "Feature",
  "properties": {
    "iso:country":"US",
    "sg:address":"2722 W 12600 S",
    "sg:city":"Riverton",
    "sg:classifiers":[
        {
            "category":"Cinema",
            "subcategory":"Movie Rental",
            "type":"Entertainment"
        }
    ],
    "sg:phone":"+1 801 253 0114",
    "sg:postcode":"84065",
    "sg:province":"UT",
    "sg:tags":[
        "leasing",
        "video",
        "disc",
        "tape"
    ],
    "wof:name":"Blockbuster Video",
    "wof:placetype":"venue"
},
  "geometry": {"coordinates":[-111.958017,40.52237],"type":"Point"}
}