{
  "type": "Feature",
  "properties": {
    "iso:country":"US",
    "sg:address":"151 W 200 N",
    "sg:city":"Vernal",
    "sg:classifiers":[
        {
            "category":"Professional",
            "type":"Services"
        }
    ],
    "sg:phone":"+1 435 789 6636",
    "sg:postcode":"84078",
    "sg:province":"UT",
    "sg:tags":[
        "establishment"
    ],
    "wof:name":"Avmc Womens Resource Ctr",
    "wof:placetype":"venue"
},
  "geometry": {"coordinates":[-109.531384,40.458446],"type":"Point"}
}