{
  "type": "Feature",
  "properties": {
    "iso:country":"US",
    "sg:address":"225 S Main St",
    "sg:city":"Randolph",
    "sg:classifiers":[
        {
            "category":"Retail",
            "subcategory":"Car Wash",
            "type":"Services"
        }
    ],
    "sg:phone":"+1 435 793 2176",
    "sg:postcode":"84064",
    "sg:province":"UT",
    "sg:tags":[
        "polishing",
        "washing"
    ],
    "wof:name":"Kings Kar Kare",
    "wof:placetype":"venue"
},
  "geometry": {"coordinates":[-111.18494800000001,41.660754],"type":"Point"}
}