{
  "type": "Feature",
  "properties": {
    "iso:country":"US",
    "sg:address":"440 N 500 E",
    "sg:city":"Heber City",
    "sg:classifiers":[
        {
            "category":"Organizations",
            "subcategory":"Membership Organization",
            "type":"Services"
        }
    ],
    "sg:phone":"+1 435 654 5095",
    "sg:postcode":"84032",
    "sg:province":"UT",
    "wof:name":"Freeway Watch",
    "wof:placetype":"venue"
},
  "geometry": {"coordinates":[-111.404584,40.513587],"type":"Point"}
}