{
  "type": "Feature",
  "properties": {
    "iso:country":"US",
    "sg:address":"1234 S Jordan Pkwy",
    "sg:city":"South Jordan",
    "sg:classifiers":[
        {
            "category":"Professional",
            "subcategory":"Computer Services",
            "type":"Services"
        }
    ],
    "sg:phone":"+1 801 446 6667",
    "sg:postcode":"84095",
    "sg:province":"UT",
    "sg:tags":[
        "datum"
    ],
    "wof:name":"Tough Lab",
    "wof:placetype":"venue"
},
  "geometry": {"coordinates":[-111.928991,40.562277],"type":"Point"}
}