{
  "type": "Feature",
  "properties": {
    "iso:country":"US",
    "sg:address":"3653 S 500 W",
    "sg:city":"Salt Lake City",
    "sg:classifiers":[
        {
            "category":"Manufacturing",
            "subcategory":"Chemicals & Compounds",
            "type":"Manufacturing & Wholesale Goods"
        }
    ],
    "sg:phone":"+1 801 261 3082",
    "sg:postcode":"84115",
    "sg:province":"UT",
    "sg:tags":[
        "composite"
    ],
    "wof:name":"Zoltek Corp Prepreg",
    "wof:placetype":"venue"
},
  "geometry": {"coordinates":[-111.905416,40.690029],"type":"Point"}
}