{
  "type": "Feature",
  "properties": {
    "iso:country":"US",
    "sg:address":"1155 Glendale Dr",
    "sg:city":"Salt Lake City",
    "sg:classifiers":[
        {
            "category":"Shopping",
            "subcategory":"Jewelry",
            "type":"Retail Goods"
        }
    ],
    "sg:phone":"+1 801 972 4141",
    "sg:postcode":"84104",
    "sg:province":"UT",
    "wof:name":"Blancas Jewelery",
    "wof:placetype":"venue"
},
  "geometry": {"coordinates":[-111.93253799999999,40.744471],"type":"Point"}
}