{
  "type": "Feature",
  "properties": {
    "iso:country":"US",
    "sg:address":"1550 W Gordon Ave",
    "sg:city":"Layton",
    "sg:classifiers":[
        {
            "category":"Social Services",
            "type":"Services"
        }
    ],
    "sg:phone":"+1 801 593 6343",
    "sg:postcode":"84041",
    "sg:province":"UT",
    "sg:tags":[
        "youth",
        "organization",
        "center"
    ],
    "wof:name":"Praxis Youth Quest",
    "wof:placetype":"venue"
},
  "geometry": {"coordinates":[-111.993095,41.07474],"type":"Point"}
}