{
  "type": "Feature",
  "properties": {
    "iso:country":"US",
    "sg:address":"7070 Union Park Ave",
    "sg:city":"Midvale",
    "sg:classifiers":[
        {
            "category":"Real Estate",
            "subcategory":"Real Estate Agent",
            "type":"Services"
        }
    ],
    "sg:phone":"+1 801 568 5240",
    "sg:postcode":"84047",
    "sg:province":"UT",
    "sg:tags":[
        "agency"
    ],
    "wof:name":"Joel Carson & Associates",
    "wof:placetype":"venue"
},
  "geometry": {"coordinates":[-111.85867500000001,40.623562],"type":"Point"}
}