{
  "type": "Feature",
  "properties": {
    "iso:country":"US",
    "sg:address":"3791 S 530 W",
    "sg:city":"Salt Lake City",
    "sg:classifiers":[
        {
            "category":"Building & Trades",
            "subcategory":"Landscaping Services",
            "type":"Services"
        }
    ],
    "sg:phone":"+1 801 261 8644",
    "sg:postcode":"84115",
    "sg:province":"UT",
    "sg:tags":[
        "lawn",
        "maintenance",
        "grounds"
    ],
    "wof:name":"Great Lawns",
    "wof:placetype":"venue"
},
  "geometry": {"coordinates":[-111.90641100000001,40.688322],"type":"Point"}
}