{
  "type": "Feature",
  "properties": {
    "iso:country":"US",
    "sg:address":"1974 Falcon View Dr",
    "sg:city":"Sandy",
    "sg:classifiers":[
        {
            "category":"Wholesale",
            "subcategory":"Machinery & Supplies",
            "type":"Manufacturing & Wholesale Goods"
        }
    ],
    "sg:phone":"+1 801 571 6554",
    "sg:postcode":"84092",
    "sg:province":"UT",
    "sg:tags":[
        "equipment",
        "industrial",
        "furniture"
    ],
    "wof:name":"American Interior Systems",
    "wof:placetype":"venue"
},
  "geometry": {"coordinates":[-111.836219,40.569892],"type":"Point"}
}