{
  "type": "Feature",
  "properties": {
    "iso:country":"US",
    "sg:address":"2731 E 1600 S",
    "sg:city":"Spanish Fork",
    "sg:classifiers":[
        {
            "category":"Building & Trades",
            "subcategory":"Construction",
            "type":"Services"
        }
    ],
    "sg:phone":"+1 801 794 1048",
    "sg:postcode":"84660",
    "sg:province":"UT",
    "sg:tags":[
        "restoration",
        "cleaning",
        "patio",
        "deck"
    ],
    "wof:name":"Kleanwash",
    "wof:placetype":"venue"
},
  "geometry": {"coordinates":[-111.60974400000001,40.089583],"type":"Point"}
}