{
  "type": "Feature",
  "properties": {
    "iso:country":"US",
    "sg:address":"351 S 100 W",
    "sg:city":"Delta",
    "sg:classifiers":[
        {
            "category":"Organizations",
            "subcategory":"Religious Organization",
            "type":"Services"
        }
    ],
    "sg:phone":"+1 435 864 3911",
    "sg:postcode":"84624",
    "sg:province":"UT",
    "wof:name":"Faith Christn Fellowship Delta",
    "wof:placetype":"venue"
},
  "geometry": {"coordinates":[-112.57701,39.346642],"type":"Point"}
}