{
  "type": "Feature",
  "properties": {
    "iso:country":"US",
    "sg:address":"540 S Main St",
    "sg:city":"Richfield",
    "sg:classifiers":[
        {
            "category":"Travel",
            "subcategory":"Hotels & Motels",
            "type":"Entertainment"
        }
    ],
    "sg:phone":"+1 435 896 5465",
    "sg:postcode":"84701",
    "sg:province":"UT",
    "wof:name":"Quality Inn",
    "wof:placetype":"venue"
},
  "geometry": {"coordinates":[-112.08477499999999,38.760569],"type":"Point"}
}