{
  "type": "Feature",
  "properties": {
    "iso:country":"US",
    "sg:address":"6699 Landmark Dr",
    "sg:city":"Park City",
    "sg:classifiers":[
        {
            "category":"Professional",
            "type":"Services"
        }
    ],
    "sg:phone":"+1 435 649 4401",
    "sg:postcode":"84098",
    "sg:province":"UT",
    "sg:tags":[
        "establishment"
    ],
    "wof:name":"GAP",
    "wof:placetype":"venue"
},
  "geometry": {"coordinates":[-111.550138,40.730212],"type":"Point"}
}