{
  "type": "Feature",
  "properties": {
    "iso:country":"US",
    "sg:address":"116 S 1250 E",
    "sg:city":"Hyrum",
    "sg:classifiers":[
        {
            "category":"Freight",
            "type":"Transportation"
        }
    ],
    "sg:phone":"+1 435 245 0174",
    "sg:postcode":"84321",
    "sg:province":"UT",
    "sg:tags":[
        "operator",
        "local",
        "trucking"
    ],
    "wof:name":"Sarmiento Trucking Inc",
    "wof:placetype":"venue"
},
  "geometry": {"coordinates":[-111.802981,41.729165],"type":"Point"}
}