{
  "type": "Feature",
  "properties": {
    "iso:country":"US",
    "sg:address":"2311 Santa Clara Dr",
    "sg:city":"Santa Clara",
    "sg:classifiers":[
        {
            "category":"Restaurant",
            "type":"Food & Drink"
        }
    ],
    "sg:menulink":"http://www.allmenus.com/ut/st-george/69612-dominos-pizza/menu/",
    "sg:phone":"+1 435 688 8885",
    "sg:postcode":"84765",
    "sg:province":"UT",
    "sg:tags":[
        "american",
        "wing",
        "pizza"
    ],
    "wof:name":"Domino's Pizza",
    "wof:placetype":"venue"
},
  "geometry": {"coordinates":[-113.63438600000001,37.125756],"type":"Point"}
}