{
  "type": "Feature",
  "properties": {
    "iso:country":"US",
    "sg:address":"217 Cottage Ave",
    "sg:city":"Sandy",
    "sg:classifiers":[
        {
            "category":"Professional",
            "subcategory":"Management & Consulting",
            "type":"Services"
        }
    ],
    "sg:phone":"+1 801 352 8700",
    "sg:postcode":"84070",
    "sg:province":"UT",
    "sg:tags":[
        "business",
        "merchandise"
    ],
    "sg:website":"www.western-com.com",
    "wof:name":"Western Communications",
    "wof:placetype":"venue"
},
  "geometry": {"coordinates":[-111.89814699999999,40.592141],"type":"Point"}
}