{
  "type": "Feature",
  "properties": {
    "iso:country":"US",
    "sg:address":"360 Culter Dr",
    "sg:city":"North Salt Lake",
    "sg:classifiers":[
        {
            "category":"Professional",
            "subcategory":"Lawyer & Legal Services",
            "type":"Services"
        }
    ],
    "sg:phone":"+1 801 297 2480",
    "sg:postcode":"84054",
    "sg:province":"UT",
    "sg:website":"www.lexingtonlaw.com",
    "wof:name":"Lexington Law Firm",
    "wof:placetype":"venue"
},
  "geometry": {"coordinates":[-111.931839,40.848972],"type":"Point"}
}