{
  "type": "Feature",
  "properties": {
    "iso:country":"US",
    "sg:address":"3668 W 9800 S",
    "sg:city":"South Jordan",
    "sg:classifiers":[
        {
            "category":"Health Services",
            "subcategory":"Doctor",
            "type":"Services"
        }
    ],
    "sg:phone":"+1 801 260 1515",
    "sg:postcode":"84095",
    "sg:province":"UT",
    "sg:tags":[
        "dentist"
    ],
    "wof:name":"Dana Orthodontics",
    "wof:placetype":"venue"
},
  "geometry": {"coordinates":[-111.977887,40.573356],"type":"Point"}
}