{
  "type": "Feature",
  "properties": {
    "iso:country":"US",
    "sg:address":"7041 Commerce Park Dr",
    "sg:city":"Midvale",
    "sg:classifiers":[
        {
            "category":"Shopping",
            "type":"Retail Goods"
        }
    ],
    "sg:phone":"+1 801 568 9697",
    "sg:postcode":"84047",
    "sg:province":"UT",
    "sg:tags":[
        "wheel",
        "chair",
        "scooter"
    ],
    "sg:website":"www.reshealthcare.com",
    "wof:name":"Rehabilitation Equipment Spec",
    "wof:placetype":"venue"
},
  "geometry": {"coordinates":[-111.908429,40.623209],"type":"Point"}
}