{
  "type": "Feature",
  "properties": {
    "iso:country":"US",
    "sg:address":"13106 S 2420 W",
    "sg:city":"Riverton",
    "sg:classifiers":[
        {
            "category":"Personal",
            "subcategory":"Beauty Salon",
            "type":"Services"
        }
    ],
    "sg:phone":"+1 801 253 3469",
    "sg:postcode":"84065",
    "sg:province":"UT",
    "sg:tags":[
        "shop"
    ],
    "wof:name":"Creative Nail Works",
    "wof:placetype":"venue"
},
  "geometry": {"coordinates":[-111.95244599999999,40.513526],"type":"Point"}
}