{
  "type": "Feature",
  "properties": {
    "iso:country":"US",
    "sg:address":"455 E 500 S",
    "sg:city":"Salt Lake City",
    "sg:classifiers":[
        {
            "category":"Banks & Credit Unions",
            "subcategory":"Investment Brokerage",
            "type":"Services"
        }
    ],
    "sg:phone":"+1 801 532 1742",
    "sg:postcode":"84111",
    "sg:province":"UT",
    "sg:tags":[
        "advisory"
    ],
    "wof:name":"Smith & Associates Inc",
    "wof:placetype":"venue"
},
  "geometry": {"coordinates":[-111.877099,40.758557],"type":"Point"}
}