{
  "type": "Feature",
  "properties": {
    "iso:country":"US",
    "sg:address":"5075 W 4700 S",
    "sg:city":"Kearns",
    "sg:classifiers":[
        {
            "category":"Real Estate",
            "subcategory":"Developer",
            "type":"Services"
        }
    ],
    "sg:phone":"+1 801 966 8830",
    "sg:postcode":"84118",
    "sg:province":"UT",
    "sg:tags":[
        "mobile",
        "home"
    ],
    "wof:name":"Shadow Ridge Estates",
    "wof:placetype":"venue"
},
  "geometry": {"coordinates":[-112.01325,40.667498],"type":"Point"}
}