{
  "type": "Feature",
  "properties": {
    "iso:country":"US",
    "sg:address":"3659 Pearblossom Cir",
    "sg:city":"Salt Lake City",
    "sg:classifiers":[
        {
            "category":"Communications",
            "subcategory":"Film & Video Production",
            "type":"Services"
        }
    ],
    "sg:phone":"+1 801 424 2103",
    "sg:postcode":"84109",
    "sg:province":"UT",
    "sg:tags":[
        "motion"
    ],
    "wof:name":"Productions Js Jon",
    "wof:placetype":"venue"
},
  "geometry": {"coordinates":[-111.79532399999999,40.691517],"type":"Point"}
}