{
  "type": "Feature",
  "properties": {
    "iso:country":"US",
    "sg:address":"188 W Main St",
    "sg:city":"Delta",
    "sg:classifiers":[
        {
            "category":"Organizations",
            "subcategory":"Religious Organization",
            "type":"Services"
        }
    ],
    "sg:phone":"+1 435 864 4311",
    "sg:postcode":"84624",
    "sg:province":"UT",
    "sg:tags":[
        "church"
    ],
    "wof:name":"Church Of Jesus Christ Of Lds",
    "wof:placetype":"venue"
},
  "geometry": {"coordinates":[-112.57728899999999,39.352442],"type":"Point"}
}