{
  "type": "Feature",
  "properties": {
    "iso:country":"US",
    "sg:address":"192 N Morgan Valley Dr",
    "sg:city":"Morgan",
    "sg:classifiers":[
        {
            "category":"Building & Trades",
            "subcategory":"Construction",
            "type":"Services"
        }
    ],
    "sg:phone":"+1 801 829 3236",
    "sg:postcode":"84050",
    "sg:province":"UT",
    "sg:tags":[
        "residential"
    ],
    "wof:name":"Stephens Sargent Construction",
    "wof:placetype":"venue"
},
  "geometry": {"coordinates":[-111.717833,41.039216],"type":"Point"}
}