{
  "type": "Feature",
  "properties": {
    "iso:country":"US",
    "sg:address":"846 S 400 W",
    "sg:city":"Hurricane",
    "sg:classifiers":[
        {
            "category":"Building & Trades",
            "subcategory":"Plumbing",
            "type":"Services"
        }
    ],
    "sg:phone":"+1 435 635 9121",
    "sg:postcode":"84737",
    "sg:province":"UT",
    "sg:tags":[
        "contractor"
    ],
    "wof:name":"Bucks Hvac Inc",
    "wof:placetype":"venue"
},
  "geometry": {"coordinates":[-113.29612400000001,37.167948],"type":"Point"}
}