{
  "type": "Feature",
  "properties": {
    "iso:country":"US",
    "sg:address":"102 W 500 S",
    "sg:city":"Salt Lake City",
    "sg:classifiers":[
        {
            "category":"Real Estate",
            "subcategory":"Real Estate Agent",
            "type":"Services"
        }
    ],
    "sg:phone":"+1 801 531 7011",
    "sg:postcode":"84101",
    "sg:province":"UT",
    "sg:tags":[
        "manager"
    ],
    "wof:name":"Affordable Hsing Partners Xii",
    "wof:placetype":"venue"
},
  "geometry": {"coordinates":[-111.896766,40.758548],"type":"Point"}
}