{
  "type": "Feature",
  "properties": {
    "iso:country":"US",
    "sg:address":"1615 W 2100 S",
    "sg:city":"Salt Lake City",
    "sg:classifiers":[
        {
            "category":"Professional",
            "subcategory":"Business Services",
            "type":"Services"
        }
    ],
    "sg:phone":"+1 801 975 1212",
    "sg:postcode":"84119",
    "sg:province":"UT",
    "wof:name":"Time & Temperature",
    "wof:placetype":"venue"
},
  "geometry": {"coordinates":[-111.929221,40.725835],"type":"Point"}
}