{
  "type": "Feature",
  "properties": {
    "iso:country":"US",
    "sg:address":"4231 N Hwy 91",
    "sg:city":"Cedar City",
    "sg:classifiers":[
        {
            "category":"Personal",
            "subcategory":"Beauty Salon",
            "type":"Services"
        }
    ],
    "sg:phone":"+1 435 867 1233",
    "sg:postcode":"84720",
    "sg:province":"UT",
    "sg:tags":[
        "shop"
    ],
    "wof:name":"Ann Marie's Hair Studio",
    "wof:placetype":"venue"
},
  "geometry": {"coordinates":[-113.027294,37.755258],"type":"Point"}
}