{
  "type": "Feature",
  "properties": {
    "iso:country":"US",
    "sg:address":"821 N 300 W",
    "sg:city":"Pleasant Grove",
    "sg:classifiers":[
        {
            "category":"Professional",
            "subcategory":"Computer Services",
            "type":"Services"
        }
    ],
    "sg:phone":"+1 801 796 7226",
    "sg:postcode":"84062",
    "sg:province":"UT",
    "sg:tags":[
        "scanning"
    ],
    "wof:name":"Infolink Scan Ctr",
    "wof:placetype":"venue"
},
  "geometry": {"coordinates":[-111.74515100000001,40.372915],"type":"Point"}
}