{
  "type": "Feature",
  "properties": {
    "iso:country":"US",
    "sg:address":"4471 Gordon Ln",
    "sg:city":"Salt Lake City",
    "sg:classifiers":[
        {
            "category":"Real Estate",
            "subcategory":"Real Estate Agent",
            "type":"Services"
        }
    ],
    "sg:phone":"+1 801 262 5553",
    "sg:postcode":"84107",
    "sg:province":"UT",
    "wof:name":"Style Realty Inc",
    "wof:placetype":"venue"
},
  "geometry": {"coordinates":[-111.87987200000001,40.67561],"type":"Point"}
}