{
  "type": "Feature",
  "properties": {
    "iso:country":"US",
    "sg:address":"418 E Main St",
    "sg:city":"Vernal",
    "sg:classifiers":[
        {
            "category":"Mining & Drilling",
            "type":"Manufacturing & Wholesale Goods"
        }
    ],
    "sg:phone":"+1 435 789 2766",
    "sg:postcode":"84078",
    "sg:province":"UT",
    "sg:tags":[
        "field",
        "oil"
    ],
    "wof:name":"Graco Fishing & Rental",
    "wof:placetype":"venue"
},
  "geometry": {"coordinates":[-109.519347,40.45576],"type":"Point"}
}