{
  "type": "Feature",
  "properties": {
    "iso:country":"US",
    "sg:address":"6707 S 1300 E",
    "sg:city":"Holladay",
    "sg:classifiers":[
        {
            "category":"Banks & Credit Unions",
            "subcategory":"Bank",
            "type":"Services"
        }
    ],
    "sg:phone":"+1 801 308 0132",
    "sg:postcode":"84121",
    "sg:province":"UT",
    "sg:tags":[
        "loan",
        "real estate"
    ],
    "wof:name":"Superior Lending Corp",
    "wof:placetype":"venue"
},
  "geometry": {"coordinates":[-111.854662,40.628998],"type":"Point"}
}