{
  "type": "Feature",
  "properties": {
    "iso:country":"US",
    "sg:address":"5792 S 900 E",
    "sg:city":"Salt Lake City",
    "sg:classifiers":[
        {
            "category":"Building & Trades",
            "subcategory":"Construction",
            "type":"Services"
        }
    ],
    "sg:phone":"+1 801 265 1405",
    "sg:postcode":"84121",
    "sg:province":"UT",
    "sg:tags":[
        "general",
        "contractor"
    ],
    "wof:name":"Wet Cor",
    "wof:placetype":"venue"
},
  "geometry": {"coordinates":[-111.866034,40.644661],"type":"Point"}
}