{
  "type": "Feature",
  "properties": {
    "iso:country":"US",
    "sg:address":"963 E 8600 S",
    "sg:city":"Sandy",
    "sg:classifiers":[
        {
            "category":"Real Estate",
            "subcategory":"Real Estate Operator",
            "type":"Services"
        }
    ],
    "sg:phone":"+1 801 255 0956",
    "sg:postcode":"84094",
    "sg:province":"UT",
    "sg:tags":[
        "building",
        "nonresidential"
    ],
    "wof:name":"Larson Properties 2 LLC",
    "wof:placetype":"venue"
},
  "geometry": {"coordinates":[-111.86342399999999,40.595045],"type":"Point"}
}