{
  "type": "Feature",
  "properties": {
    "iso:country":"US",
    "sg:address":"6687 S 1530 E",
    "sg:city":"Salt Lake City",
    "sg:classifiers":[
        {
            "category":"Cinema",
            "subcategory":"Movie Theater",
            "type":"Entertainment"
        }
    ],
    "sg:phone":"+1 801 943 4868",
    "sg:postcode":"84121",
    "sg:province":"UT",
    "wof:name":"Home Theater Dynamics",
    "wof:placetype":"venue"
},
  "geometry": {"coordinates":[-111.84833,40.627086],"type":"Point"}
}