{
  "type": "Feature",
  "properties": {
    "iso:country":"US",
    "sg:address":"959 S 700 E",
    "sg:city":"Orem",
    "sg:classifiers":[
        {
            "category":"Cinema",
            "subcategory":"Movie Theater",
            "type":"Entertainment"
        }
    ],
    "sg:phone":"+1 801 226 1770",
    "sg:postcode":"84097",
    "sg:province":"UT",
    "wof:name":"University Mall Cinema",
    "wof:placetype":"venue"
},
  "geometry": {"coordinates":[-111.678584,40.282031],"type":"Point"}
}