{
  "type": "Feature",
  "properties": {
    "iso:country":"US",
    "sg:address":"255 S State St",
    "sg:city":"Roosevelt",
    "sg:classifiers":[
        {
            "category":"Government",
            "subcategory":"Police Station",
            "type":"Public Place"
        }
    ],
    "sg:phone":"+1 435 722 0259",
    "sg:postcode":"84066",
    "sg:province":"UT",
    "sg:tags":[
        "state"
    ],
    "wof:name":"Highway Patrol",
    "wof:placetype":"venue"
},
  "geometry": {"coordinates":[-109.991732,40.296024],"type":"Point"}
}