{
  "type": "Feature",
  "properties": {
    "iso:country":"US",
    "sg:address":"675 E 100 N",
    "sg:city":"Price",
    "sg:classifiers":[
        {
            "category":"Banks & Credit Unions",
            "subcategory":"Bank",
            "type":"Services"
        }
    ],
    "sg:phone":"+1 435 637 2443",
    "sg:postcode":"84501",
    "sg:province":"UT",
    "sg:tags":[
        "state"
    ],
    "wof:name":"Carbon Credit Union",
    "wof:placetype":"venue"
},
  "geometry": {"coordinates":[-110.798621,39.601061],"type":"Point"}
}