{
  "type": "Feature",
  "properties": {
    "iso:country":"US",
    "sg:address":"1410 E 5875 S",
    "sg:city":"Ogden",
    "sg:classifiers":[
        {
            "category":"Manufacturing",
            "subcategory":"Apparel",
            "type":"Manufacturing & Wholesale Goods"
        }
    ],
    "sg:phone":"+1 801 479 8689",
    "sg:postcode":"84405",
    "sg:province":"UT",
    "wof:name":"Cain Mark",
    "wof:placetype":"venue"
},
  "geometry": {"coordinates":[-111.94447099999999,41.155832],"type":"Point"}
}