{
  "type": "Feature",
  "properties": {
    "iso:country":"US",
    "sg:address":"785 S 800 E",
    "sg:city":"Salt Lake City",
    "sg:classifiers":[
        {
            "category":"Shopping",
            "subcategory":"Clothing, Apparel, & Fashions",
            "type":"Retail Goods"
        }
    ],
    "sg:phone":"+1 801 363 1855",
    "sg:postcode":"84102",
    "sg:province":"UT",
    "wof:name":"Male 2 Male Screen Saver",
    "wof:placetype":"venue"
},
  "geometry": {"coordinates":[-111.868118,40.753827],"type":"Point"}
}