{
  "type": "Feature",
  "properties": {
    "iso:country":"US",
    "sg:address":"2730 Washington Blvd",
    "sg:city":"Ogden",
    "sg:classifiers":[
        {
            "category":"Government",
            "subcategory":"Post Office",
            "type":"Public Place"
        }
    ],
    "sg:phone":"+1 801 612 1815",
    "sg:postcode":"84401",
    "sg:province":"UT",
    "sg:tags":[
        "postal",
        "us"
    ],
    "wof:name":"US Post Office",
    "wof:placetype":"venue"
},
  "geometry": {"coordinates":[-111.97051999999999,41.21591],"type":"Point"}
}