{
  "type": "Feature",
  "properties": {
    "iso:country":"US",
    "sg:address":"5226 S 300 W",
    "sg:city":"Murray",
    "sg:classifiers":[
        {
            "category":"Building & Trades",
            "subcategory":"Electrical",
            "type":"Services"
        }
    ],
    "sg:phone":"+1 801 262 7021",
    "sg:postcode":"84107",
    "sg:province":"UT",
    "sg:tags":[
        "electric",
        "contractor"
    ],
    "wof:name":"Electro Arts",
    "wof:placetype":"venue"
},
  "geometry": {"coordinates":[-111.89871100000001,40.660431],"type":"Point"}
}