{
  "type": "Feature",
  "properties": {
    "iso:country":"US",
    "sg:address":"4015 W 5600 N",
    "sg:city":"Brigham City",
    "sg:classifiers":[
        {
            "category":"Shopping",
            "subcategory":"Hobbies, Toys, & Games",
            "type":"Retail Goods"
        }
    ],
    "sg:phone":"+1 435 279 8277",
    "sg:postcode":"84302",
    "sg:province":"UT",
    "sg:tags":[
        "wholesale",
        "craft",
        "art",
        "folk"
    ],
    "wof:name":"Bear River Folk Art Inc",
    "wof:placetype":"venue"
},
  "geometry": {"coordinates":[-112.11194399999999,41.611066],"type":"Point"}
}