{
  "type": "Feature",
  "properties": {
    "iso:country":"US",
    "sg:address":"1291 Wasatch Dr",
    "sg:city":"Provo",
    "sg:classifiers":[
        {
            "category":"Building & Trades",
            "subcategory":"Electrical",
            "type":"Services"
        }
    ],
    "sg:phone":"+1 801 374 9809",
    "sg:postcode":"84604",
    "sg:province":"UT",
    "sg:tags":[
        "electrical",
        "contractor"
    ],
    "wof:name":"Rycoe Electric LLC",
    "wof:placetype":"venue"
},
  "geometry": {"coordinates":[-111.689922,40.250445],"type":"Point"}
}