{
  "type": "Feature",
  "properties": {
    "iso:country":"US",
    "sg:address":"3366 S 875 W",
    "sg:city":"Syracuse",
    "sg:classifiers":[
        {
            "category":"Professional",
            "subcategory":"Computer Services",
            "type":"Services"
        }
    ],
    "sg:phone":"+1 801 774 9017",
    "sg:postcode":"84075",
    "sg:province":"UT",
    "sg:tags":[
        "prepackaged",
        "software"
    ],
    "wof:name":"Bate Software & Consulting",
    "wof:placetype":"venue"
},
  "geometry": {"coordinates":[-112.042558,41.064489],"type":"Point"}
}