{
  "type": "Feature",
  "properties": {
    "iso:country":"US",
    "sg:address":"1293 W 2200 S",
    "sg:city":"Salt Lake City",
    "sg:classifiers":[
        {
            "category":"Communications",
            "type":"Services"
        }
    ],
    "sg:phone":"+1 801 975 1000",
    "sg:postcode":"84119",
    "sg:province":"UT",
    "wof:name":"Vision Works Intl",
    "wof:placetype":"venue"
},
  "geometry": {"coordinates":[-111.926256,40.723838],"type":"Point"}
}