{
  "type": "Feature",
  "properties": {
    "iso:country":"US",
    "sg:address":"127 E 100 N",
    "sg:city":"Price",
    "sg:classifiers":[
        {
            "category":"Personal",
            "subcategory":"Barber",
            "type":"Services"
        }
    ],
    "sg:phone":"+1 435 637 2848",
    "sg:postcode":"84501",
    "sg:province":"UT",
    "wof:name":"Atwoods Beauty Shop",
    "wof:placetype":"venue"
},
  "geometry": {"coordinates":[-110.808723,39.601077],"type":"Point"}
}