{
  "type": "Feature",
  "properties": {
    "iso:country":"US",
    "sg:address":"400 E 1600 S",
    "sg:city":"Mapleton",
    "sg:classifiers":[
        {
            "category":"Real Estate",
            "subcategory":"Real Estate Operator",
            "type":"Services"
        }
    ],
    "sg:phone":"+1 801 489 3332",
    "sg:postcode":"84664",
    "sg:province":"UT",
    "sg:tags":[
        "building",
        "apartment"
    ],
    "wof:name":"Perry Apts",
    "wof:placetype":"venue"
},
  "geometry": {"coordinates":[-111.572591,40.115808],"type":"Point"}
}