{
  "type": "Feature",
  "properties": {
    "iso:country":"US",
    "sg:address":"1439 Owl Ln",
    "sg:city":"Lehi",
    "sg:classifiers":[
        {
            "category":"Building & Trades",
            "subcategory":"Plumbing",
            "type":"Services"
        }
    ],
    "sg:phone":"+1 801 789 5829",
    "sg:postcode":"84005",
    "sg:province":"UT",
    "sg:tags":[
        "contractor"
    ],
    "wof:name":"Cedar Valley Sprinkler & Maint",
    "wof:placetype":"venue"
},
  "geometry": {"coordinates":[-112.01912799999999,40.312759],"type":"Point"}
}