{
  "type": "Feature",
  "properties": {
    "iso:country":"US",
    "sg:address":"461 N 200 W",
    "sg:city":"Mount Pleasant",
    "sg:classifiers":[
        {
            "category":"Personal",
            "subcategory":"Beauty Salon",
            "type":"Services"
        }
    ],
    "sg:phone":"+1 435 462 2116",
    "sg:postcode":"84647",
    "sg:province":"UT",
    "sg:tags":[
        "shop"
    ],
    "wof:name":"Main Event Marketing Inc",
    "wof:placetype":"venue"
},
  "geometry": {"coordinates":[-111.459265,39.553271],"type":"Point"}
}