{
  "type": "Feature",
  "properties": {
    "iso:country":"US",
    "sg:address":"9847 Flint Dr",
    "sg:city":"Sandy",
    "sg:classifiers":[
        {
            "category":"Building & Trades",
            "subcategory":"Equipment Rental",
            "type":"Services"
        }
    ],
    "sg:phone":"+1 801 572 0976",
    "sg:postcode":"84094",
    "sg:province":"UT",
    "sg:tags":[
        "leasing"
    ],
    "wof:name":"C J Enterprises",
    "wof:placetype":"venue"
},
  "geometry": {"coordinates":[-111.85785,40.572761],"type":"Point"}
}