{
  "type": "Feature",
  "properties": {
    "iso:country":"US",
    "sg:address":"2652 E Capricorn Way",
    "sg:city":"Salt Lake City",
    "sg:classifiers":[
        {
            "category":"Professional",
            "subcategory":"Computer Services",
            "type":"Services"
        }
    ],
    "sg:phone":"+1 801 272 9776",
    "sg:postcode":"84124",
    "sg:province":"UT",
    "sg:tags":[
        "related"
    ],
    "wof:name":"Reiter Computing",
    "wof:placetype":"venue"
},
  "geometry": {"coordinates":[-111.81691499999999,40.682855],"type":"Point"}
}