{
  "type": "Feature",
  "properties": {
    "iso:country":"US",
    "sg:address":"7349 S 900 E",
    "sg:city":"Midvale",
    "sg:classifiers":[
        {
            "category":"Professional",
            "subcategory":"Accounting & Tax Preparation",
            "type":"Services"
        }
    ],
    "sg:phone":"+1 801 255 8922",
    "sg:postcode":"84047",
    "sg:province":"UT",
    "sg:tags":[
        "return",
        "filing"
    ],
    "wof:name":"Bennetts Tax Svc",
    "wof:placetype":"venue"
},
  "geometry": {"coordinates":[-111.865982,40.618754],"type":"Point"}
}