{
  "type": "Feature",
  "properties": {
    "iso:country":"US",
    "sg:address":"2154 Highland Dr",
    "sg:city":"Salt Lake City",
    "sg:classifiers":[
        {
            "category":"Shopping",
            "subcategory":"Musical Instruments",
            "type":"Retail Goods"
        }
    ],
    "sg:phone":"+1 801 467 7982",
    "sg:postcode":"84106",
    "sg:province":"UT",
    "wof:name":"Jack's Drum & Guitar Shop",
    "wof:placetype":"venue"
},
  "geometry": {"coordinates":[-111.859544,40.724197],"type":"Point"}
}