{
  "type": "Feature",
  "properties": {
    "iso:country":"US",
    "sg:address":"154 M St",
    "sg:city":"Salt Lake City",
    "sg:classifiers":[
        {
            "category":"Health Services",
            "subcategory":"Health Practitioner",
            "type":"Services"
        }
    ],
    "sg:phone":"+1 801 933 4761",
    "sg:postcode":"84103",
    "sg:province":"UT",
    "wof:name":"Richard Ingebretsen",
    "wof:placetype":"venue"
},
  "geometry": {"coordinates":[-111.865522,40.773918],"type":"Point"}
}