{
  "type": "Feature",
  "properties": {
    "iso:country":"US",
    "sg:address":"3122 W 12825 S",
    "sg:city":"Riverton",
    "sg:classifiers":[
        {
            "category":"Shopping",
            "subcategory":"Florist",
            "type":"Retail Goods"
        }
    ],
    "sg:phone":"+1 801 254 0888",
    "sg:postcode":"84065",
    "sg:province":"UT",
    "wof:name":"Suspended In Time Floral",
    "wof:placetype":"venue"
},
  "geometry": {"coordinates":[-111.964009,40.518275],"type":"Point"}
}