{
  "type": "Feature",
  "properties": {
    "iso:country":"US",
    "sg:address":"8464 S 4800 W",
    "sg:city":"West Jordan",
    "sg:classifiers":[
        {
            "category":"Building & Trades",
            "subcategory":"Construction",
            "type":"Services"
        }
    ],
    "sg:phone":"+1 801 280 7614",
    "sg:postcode":"84088",
    "sg:province":"UT",
    "sg:tags":[
        "heavy"
    ],
    "wof:name":"Ideal Homes & Developments",
    "wof:placetype":"venue"
},
  "geometry": {"coordinates":[-112.00530000000001,40.597826],"type":"Point"}
}