{
  "type": "Feature",
  "properties": {
    "iso:country":"US",
    "sg:address":"2230 E 40 N",
    "sg:city":"St George",
    "sg:classifiers":[
        {
            "category":"Retail",
            "subcategory":"Animal Services",
            "type":"Services"
        }
    ],
    "sg:phone":"+1 435 673 0239",
    "sg:postcode":"84790",
    "sg:province":"UT",
    "wof:name":"Brinkerhoff Racing Stable",
    "wof:placetype":"venue"
},
  "geometry": {"coordinates":[-113.535831,37.109038],"type":"Point"}
}