{
  "type": "Feature",
  "properties": {
    "iso:country":"US",
    "sg:address":"601 S 1100 W",
    "sg:city":"Woods Cross",
    "sg:classifiers":[
        {
            "category":"Building & Trades",
            "subcategory":"Construction",
            "type":"Services"
        }
    ],
    "sg:phone":"+1 801 295 0533",
    "sg:postcode":"84087",
    "sg:province":"UT",
    "sg:tags":[
        "paving",
        "contractor"
    ],
    "wof:name":"Christensen Paving",
    "wof:placetype":"venue"
},
  "geometry": {"coordinates":[-111.91171,40.882763],"type":"Point"}
}