{
  "type": "Feature",
  "properties": {
    "iso:country":"US",
    "sg:address":"13 Claim Jumper Ct",
    "sg:city":"Park City",
    "sg:classifiers":[
        {
            "category":"Real Estate",
            "subcategory":"Real Estate Agent",
            "type":"Services"
        }
    ],
    "sg:phone":"+1 435 649 6783",
    "sg:postcode":"84060",
    "sg:province":"UT",
    "sg:website":"www.harryreems.com",
    "wof:name":"Reems Real Estate Inc",
    "wof:placetype":"venue"
},
  "geometry": {"coordinates":[-111.520886,40.664186],"type":"Point"}
}