{
  "type": "Feature",
  "properties": {
    "iso:country":"US",
    "sg:address":"8492 S Fayeway Dr",
    "sg:city":"Sandy",
    "sg:classifiers":[
        {
            "category":"Retail",
            "subcategory":"Animal Services",
            "type":"Services"
        }
    ],
    "sg:phone":"+1 801 569 3760",
    "sg:postcode":"84094",
    "sg:province":"UT",
    "sg:tags":[
        "pet",
        "boarding",
        "sitting"
    ],
    "wof:name":"A Pets Best Friend",
    "wof:placetype":"venue"
},
  "geometry": {"coordinates":[-111.857427,40.595483],"type":"Point"}
}