{
  "type": "Feature",
  "properties": {
    "iso:country":"US",
    "sg:address":"11856 Aztec Rd",
    "sg:city":"Draper",
    "sg:classifiers":[
        {
            "category":"Professional",
            "subcategory":"Management & Consulting",
            "type":"Services"
        }
    ],
    "sg:phone":"+1 801 816 0440",
    "sg:postcode":"84020",
    "sg:province":"UT",
    "wof:name":"Embellish It",
    "wof:placetype":"venue"
},
  "geometry": {"coordinates":[-111.898872,40.536032],"type":"Point"}
}