{
  "type": "Feature",
  "properties": {
    "iso:country":"US",
    "sg:address":"7980 S State St",
    "sg:city":"Midvale",
    "sg:classifiers":[
        {
            "category":"Shopping",
            "subcategory":"Used Merchandise",
            "type":"Retail Goods"
        }
    ],
    "sg:phone":"+1 801 566 2780",
    "sg:postcode":"84047",
    "sg:province":"UT",
    "sg:tags":[
        "pawnbroker"
    ],
    "wof:name":"Ruru Pawn",
    "wof:placetype":"venue"
},
  "geometry": {"coordinates":[-111.890844,40.607981],"type":"Point"}
}