{
  "type": "Feature",
  "properties": {
    "iso:country":"US",
    "sg:address":"94 E Tabernacle St",
    "sg:city":"St George",
    "sg:classifiers":[
        {
            "category":"Professional",
            "subcategory":"Business Services",
            "type":"Services"
        }
    ],
    "sg:phone":"+1 435 674 5200",
    "sg:postcode":"84770",
    "sg:province":"UT",
    "sg:tags":[
        "bank"
    ],
    "wof:name":"Village Bank Inc",
    "wof:placetype":"venue"
},
  "geometry": {"coordinates":[-113.58130800000001,37.108115],"type":"Point"}
}