{
  "type": "Feature",
  "properties": {
    "iso:country":"US",
    "sg:address":"9933 Glendover Way",
    "sg:city":"Sandy",
    "sg:classifiers":[
        {
            "category":"Travel",
            "subcategory":"Hotels & Motels",
            "type":"Entertainment"
        }
    ],
    "sg:phone":"+1 801 572 0401",
    "sg:postcode":"84092",
    "sg:province":"UT",
    "wof:name":"Super 8 Motel",
    "wof:placetype":"venue"
},
  "geometry": {"coordinates":[-111.84585,40.571497],"type":"Point"}
}