{
  "type": "Feature",
  "properties": {
    "iso:country":"US",
    "sg:address":"2821 W 7420 S",
    "sg:city":"West Jordan",
    "sg:classifiers":[
        {
            "category":"Retail",
            "subcategory":"Auto Repair",
            "type":"Services"
        }
    ],
    "sg:phone":"+1 801 254 6896",
    "sg:postcode":"84084",
    "sg:province":"UT",
    "sg:tags":[
        "automobile",
        "electric"
    ],
    "wof:name":"Wilson & Sons All Electric",
    "wof:placetype":"venue"
},
  "geometry": {"coordinates":[-111.962441,40.615934],"type":"Point"}
}