{
  "type": "Feature",
  "properties": {
    "iso:country":"US",
    "sg:address":"4477 Balsam Ave",
    "sg:city":"Salt Lake City",
    "sg:classifiers":[
        {
            "category":"Building & Trades",
            "subcategory":"Construction",
            "type":"Services"
        }
    ],
    "sg:phone":"+1 801 281 2299",
    "sg:postcode":"84123",
    "sg:province":"UT",
    "sg:tags":[
        "concrete",
        "contractor"
    ],
    "wof:name":"Stone Touch",
    "wof:placetype":"venue"
},
  "geometry": {"coordinates":[-111.932299,40.673639],"type":"Point"}
}