{
  "type": "Feature",
  "properties": {
    "iso:country":"US",
    "sg:address":"4010 Highland Dr",
    "sg:city":"Holladay",
    "sg:classifiers":[
        {
            "category":"Personal",
            "subcategory":"Beauty Salon",
            "type":"Services"
        }
    ],
    "sg:phone":"+1 801 277 9185",
    "sg:postcode":"84124",
    "sg:province":"UT",
    "wof:name":"Enchante International Salon",
    "wof:placetype":"venue"
},
  "geometry": {"coordinates":[-111.84511000000001,40.687019],"type":"Point"}
}