{
  "type": "Feature",
  "properties": {
    "iso:country":"US",
    "sg:address":"1061 E Main St",
    "sg:city":"Delta",
    "sg:classifiers":[
        {
            "category":"Recreation",
            "type":"Entertainment"
        }
    ],
    "sg:phone":"+1 435 864 2627",
    "sg:postcode":"84624",
    "sg:province":"UT",
    "sg:tags":[
        "stable"
    ],
    "wof:name":"Horses Unlimited Inc",
    "wof:placetype":"venue"
},
  "geometry": {"coordinates":[-112.553338,39.352635],"type":"Point"}
}