{
  "type": "Feature",
  "properties": {
    "iso:country":"US",
    "sg:address":"6910 Highland Dr",
    "sg:city":"Salt Lake City",
    "sg:classifiers":[
        {
            "category":"Home & Garden",
            "subcategory":"Furniture",
            "type":"Retail Goods"
        }
    ],
    "sg:phone":"+1 801 947 0888",
    "sg:postcode":"84121",
    "sg:province":"UT",
    "wof:name":"Surroundings",
    "wof:placetype":"venue"
},
  "geometry": {"coordinates":[-111.834339,40.624483],"type":"Point"}
}