{
  "type": "Feature",
  "properties": {
    "iso:country":"US",
    "sg:address":"3401 S 1150 E",
    "sg:city":"Springville",
    "sg:classifiers":[
        {
            "category":"Building & Trades",
            "subcategory":"Construction",
            "type":"Services"
        }
    ],
    "sg:phone":"+1 801 489 3070",
    "sg:postcode":"84663",
    "sg:province":"UT",
    "sg:tags":[
        "general",
        "contractor"
    ],
    "wof:name":"Condie Construction Co",
    "wof:placetype":"venue"
},
  "geometry": {"coordinates":[-111.62784000000001,40.171088],"type":"Point"}
}