{
  "type": "Feature",
  "properties": {
    "iso:country":"US",
    "sg:address":"1625 S 1000 W",
    "sg:city":"Clearfield",
    "sg:classifiers":[
        {
            "category":"Food & Beverages",
            "subcategory":"Bakery",
            "type":"Retail Goods"
        }
    ],
    "sg:phone":"+1 801 728 3494",
    "sg:postcode":"84015",
    "sg:province":"UT",
    "sg:tags":[
        "baker"
    ],
    "wof:name":"Frankie Doodles Dandy Bakery",
    "wof:placetype":"venue"
},
  "geometry": {"coordinates":[-112.04533000000001,41.089151],"type":"Point"}
}