{
  "type": "Feature",
  "properties": {
    "iso:country":"US",
    "sg:address":"170 E Center St",
    "sg:city":"Logan",
    "sg:classifiers":[
        {
            "category":"Manufacturing",
            "subcategory":"Signs",
            "type":"Manufacturing & Wholesale Goods"
        }
    ],
    "sg:phone":"+1 435 787 1999",
    "sg:postcode":"84321",
    "sg:province":"UT",
    "sg:tags":[
        "specialty",
        "mfg"
    ],
    "wof:name":"Sign Source",
    "wof:placetype":"venue"
},
  "geometry": {"coordinates":[-111.83069399999999,41.731227],"type":"Point"}
}