{
  "type": "Feature",
  "properties": {
    "iso:country":"US",
    "sg:address":"7293 S Pecan Cir",
    "sg:city":"Salt Lake City",
    "sg:classifiers":[
        {
            "category":"Professional",
            "subcategory":"Business Services",
            "type":"Services"
        }
    ],
    "sg:phone":"+1 801 943 4593",
    "sg:postcode":"84121",
    "sg:province":"UT",
    "wof:name":"Dekko Design",
    "wof:placetype":"venue"
},
  "geometry": {"coordinates":[-111.80238199999999,40.61918],"type":"Point"}
}