{
  "type": "Feature",
  "properties": {
    "iso:country":"US",
    "sg:address":"5160 Highland Dr",
    "sg:city":"Holladay",
    "sg:classifiers":[
        {
            "category":"Personal",
            "type":"Services"
        }
    ],
    "sg:phone":"+1 801 277 8411",
    "sg:postcode":"84117",
    "sg:province":"UT",
    "sg:tags":[
        "wedding",
        "chapel"
    ],
    "wof:name":"Lane Walker Reception Ctr",
    "wof:placetype":"venue"
},
  "geometry": {"coordinates":[-111.834816,40.657993],"type":"Point"}
}