{
  "type": "Feature",
  "properties": {
    "iso:country":"US",
    "sg:address":"1447 N 400 W",
    "sg:city":"Centerville",
    "sg:classifiers":[
        {
            "category":"Building & Trades",
            "subcategory":"Landscaping Services",
            "type":"Services"
        }
    ],
    "sg:phone":"+1 801 298 3967",
    "sg:postcode":"84014",
    "sg:province":"UT",
    "sg:tags":[
        "landscape"
    ],
    "wof:name":"Country Garden Design",
    "wof:placetype":"venue"
},
  "geometry": {"coordinates":[-111.88558,40.933322],"type":"Point"}
}