{
  "type": "Feature",
  "properties": {
    "iso:country":"US",
    "sg:address":"4276 S 1670 W",
    "sg:city":"Salt Lake City",
    "sg:classifiers":[
        {
            "category":"Manufacturing",
            "subcategory":"Rubber & Plastics",
            "type":"Manufacturing & Wholesale Goods"
        }
    ],
    "sg:phone":"+1 801 266 8743",
    "sg:postcode":"84123",
    "sg:province":"UT",
    "sg:tags":[
        "product",
        "fabricated",
        "mfg"
    ],
    "wof:name":"Jrg Outdoor Products",
    "wof:placetype":"venue"
},
  "geometry": {"coordinates":[-111.93831299999999,40.677523],"type":"Point"}
}