{
  "type": "Feature",
  "properties": {
    "iso:country":"US",
    "sg:address":"1400 N Main St",
    "sg:city":"Cedar City",
    "sg:classifiers":[
        {
            "category":"Retail",
            "subcategory":"Repair Shop",
            "type":"Services"
        }
    ],
    "sg:phone":"+1 435 586 7496",
    "sg:postcode":"84720",
    "sg:province":"UT",
    "sg:tags":[
        "heat",
        "welding",
        "mfg"
    ],
    "wof:name":"Cylinder Stoves",
    "wof:placetype":"venue"
},
  "geometry": {"coordinates":[-113.063581,37.702124],"type":"Point"}
}