{
  "type": "Feature",
  "properties": {
    "iso:country":"US",
    "sg:address":"2501 Elm Ave",
    "sg:city":"Salt Lake City",
    "sg:classifiers":[
        {
            "category":"Banks & Credit Unions",
            "subcategory":"Investment Brokerage",
            "type":"Services"
        }
    ],
    "sg:phone":"+1 801 484 3012",
    "sg:postcode":"84109",
    "sg:province":"UT",
    "sg:tags":[
        "advisory",
        "financial"
    ],
    "wof:name":"Citadel Financial",
    "wof:placetype":"venue"
},
  "geometry": {"coordinates":[-111.816677,40.724568],"type":"Point"}
}