{
  "type": "Feature",
  "properties": {
    "iso:country":"US",
    "sg:address":"1974 N 2450 E",
    "sg:city":"Layton",
    "sg:classifiers":[
        {
            "category":"Professional",
            "subcategory":"Engineering",
            "type":"Services"
        }
    ],
    "sg:phone":"+1 801 546 5311",
    "sg:postcode":"84040",
    "sg:province":"UT",
    "sg:tags":[
        "engineer"
    ],
    "wof:name":"DDD Engineering Svc Inc",
    "wof:placetype":"venue"
},
  "geometry": {"coordinates":[-111.919011,41.088061],"type":"Point"}
}