{
  "type": "Feature",
  "properties": {
    "iso:country":"US",
    "sg:address":"168 N Main St",
    "sg:city":"Centerville",
    "sg:classifiers":[
        {
            "category":"Recreation",
            "type":"Entertainment"
        }
    ],
    "sg:phone":"+1 801 296 0950",
    "sg:postcode":"84014",
    "sg:province":"UT",
    "sg:tags":[
        "landmark",
        "building",
        "historical"
    ],
    "wof:name":"Centerville Historic Home",
    "wof:placetype":"venue"
},
  "geometry": {"coordinates":[-111.878345,40.91871],"type":"Point"}
}