{
  "type": "Feature",
  "properties": {
    "iso:country":"US",
    "sg:address":"5149 Silvertip Dr",
    "sg:city":"Salt Lake City",
    "sg:classifiers":[
        {
            "category":"Shopping",
            "type":"Retail Goods"
        }
    ],
    "sg:phone":"+1 801 967 5938",
    "sg:postcode":"84118",
    "sg:province":"UT",
    "sg:tags":[
        "merchandise"
    ],
    "wof:name":"Shiver Shack",
    "wof:placetype":"venue"
},
  "geometry": {"coordinates":[-112.01395599999999,40.652237],"type":"Point"}
}