{
  "type": "Feature",
  "properties": {
    "iso:country":"US",
    "sg:address":"1705 Fort Douglas Cir",
    "sg:city":"Salt Lake City",
    "sg:classifiers":[
        {
            "category":"Banks & Credit Unions",
            "subcategory":"Investment Brokerage",
            "type":"Services"
        }
    ],
    "sg:phone":"+1 801 322 4711",
    "sg:postcode":"84103",
    "sg:province":"UT",
    "sg:tags":[
        "security"
    ],
    "wof:name":"Saliomon Smith Barney",
    "wof:placetype":"venue"
},
  "geometry": {"coordinates":[-111.841629,40.773832],"type":"Point"}
}