{
  "type": "Feature",
  "properties": {
    "iso:country":"US",
    "sg:address":"2877 W Whitehall Dr",
    "sg:city":"Salt Lake City",
    "sg:classifiers":[
        {
            "category":"Retail",
            "subcategory":"Auto Repair",
            "type":"Services"
        }
    ],
    "sg:phone":"+1 801 580 9014",
    "sg:postcode":"84119",
    "sg:province":"UT",
    "sg:tags":[
        "automotive",
        "towing"
    ],
    "wof:name":"Buffalo Towing",
    "wof:placetype":"venue"
},
  "geometry": {"coordinates":[-111.959829,40.684627],"type":"Point"}
}