{
  "type": "Feature",
  "properties": {
    "iso:country":"US",
    "sg:address":"1175 E 135 S",
    "sg:city":"Vernal",
    "sg:classifiers":[
        {
            "category":"Wholesale",
            "subcategory":"Machinery & Supplies",
            "type":"Manufacturing & Wholesale Goods"
        }
    ],
    "sg:phone":"+1 435 789 3086",
    "sg:postcode":"84078",
    "sg:province":"UT",
    "sg:tags":[
        "equipment",
        "oil",
        "well"
    ],
    "wof:name":"Smith Services Inc",
    "wof:placetype":"venue"
},
  "geometry": {"coordinates":[-109.50286,40.454107],"type":"Point"}
}