{
  "type": "Feature",
  "properties": {
    "iso:country":"US",
    "sg:address":"495 N University Ave",
    "sg:city":"Provo",
    "sg:classifiers":[
        {
            "category":"Professional",
            "type":"Services"
        }
    ],
    "sg:phone":"+1 801 374 1162",
    "sg:postcode":"84601",
    "sg:province":"UT",
    "wof:name":"Deseret News Publishing Co",
    "wof:placetype":"venue"
},
  "geometry": {"coordinates":[-111.65872400000001,40.23911],"type":"Point"}
}