{
  "type": "Feature",
  "properties": {
    "iso:country":"US",
    "sg:address":"365 W 4050 N",
    "sg:city":"Ogden",
    "sg:classifiers":[
        {
            "category":"Building & Trades",
            "subcategory":"Construction",
            "type":"Services"
        }
    ],
    "sg:phone":"+1 801 782 9267",
    "sg:postcode":"84414",
    "sg:province":"UT",
    "sg:tags":[
        "heavy"
    ],
    "wof:name":"Arbon & Arbon LLC",
    "wof:placetype":"venue"
},
  "geometry": {"coordinates":[-111.98541400000001,41.330934],"type":"Point"}
}