{
  "type": "Feature",
  "properties": {
    "iso:country":"US",
    "sg:address":"6673 Castle View Dr",
    "sg:city":"Salt Lake City",
    "sg:classifiers":[
        {
            "category":"Retail",
            "subcategory":"Auto Rental",
            "type":"Services"
        }
    ],
    "sg:phone":"+1 801 250 9341",
    "sg:postcode":"84128",
    "sg:province":"UT",
    "sg:tags":[
        "renting",
        "leasing",
        "commercial",
        "truck",
        "hauling"
    ],
    "wof:name":"Steadman Enterprises Lc",
    "wof:placetype":"venue"
},
  "geometry": {"coordinates":[-112.04979,40.682698],"type":"Point"}
}