{
  "type": "Feature",
  "properties": {
    "iso:country":"US",
    "sg:address":"160 E Helm Ave",
    "sg:city":"Salt Lake City",
    "sg:classifiers":[
        {
            "category":"Building & Trades",
            "subcategory":"Plumbing",
            "type":"Services"
        }
    ],
    "sg:phone":"+1 801 261 8893",
    "sg:postcode":"84115",
    "sg:province":"UT",
    "sg:tags":[
        "repair",
        "rental",
        "equipment"
    ],
    "wof:name":"B & E Rooter Service",
    "wof:placetype":"venue"
},
  "geometry": {"coordinates":[-111.88693000000001,40.691912],"type":"Point"}
}