{
  "type": "Feature",
  "properties": {
    "iso:country":"US",
    "sg:address":"95 E 900 S",
    "sg:city":"Willard",
    "sg:classifiers":[
        {
            "category":"Real Estate",
            "subcategory":"Developer",
            "type":"Services"
        }
    ],
    "sg:phone":"+1 435 723 3771",
    "sg:postcode":"84340",
    "sg:province":"UT",
    "wof:name":"Parsons Distributing Company",
    "wof:placetype":"venue"
},
  "geometry": {"coordinates":[-112.031639,41.397624],"type":"Point"}
}