{
  "type": "Feature",
  "properties": {
    "iso:country":"US",
    "sg:address":"1726 N 600 W",
    "sg:city":"Pleasant Grove",
    "sg:classifiers":[
        {
            "category":"Education",
            "subcategory":"School",
            "type":"Public Place"
        }
    ],
    "sg:phone":"+1 801 785 8720",
    "sg:postcode":"84062",
    "sg:province":"UT",
    "wof:name":"Manila Elementary School",
    "wof:placetype":"venue"
},
  "geometry": {"coordinates":[-111.749443,40.380308],"type":"Point"}
}