{
  "type": "Feature",
  "properties": {
    "iso:country":"US",
    "sg:address":"294 E 1475 S",
    "sg:city":"Kaysville",
    "sg:classifiers":[
        {
            "category":"Building & Trades",
            "subcategory":"Landscaping Services",
            "type":"Services"
        }
    ],
    "sg:phone":"+1 801 451 7041",
    "sg:postcode":"84037",
    "sg:province":"UT",
    "sg:tags":[
        "landscape"
    ],
    "wof:name":"Horizon Landscaping",
    "wof:placetype":"venue"
},
  "geometry": {"coordinates":[-111.932771,41.011075],"type":"Point"}
}