{
  "type": "Feature",
  "properties": {
    "iso:country":"US",
    "sg:address":"3570 Timpview Dr",
    "sg:city":"Provo",
    "sg:classifiers":[
        {
            "category":"Education",
            "subcategory":"School",
            "type":"Public Place"
        }
    ],
    "sg:phone":"+1 801 221 9720",
    "sg:postcode":"84604",
    "sg:province":"UT",
    "sg:tags":[
        "secondary"
    ],
    "sg:website":"www.timpviewbasketball.net",
    "wof:name":"Timpview High School",
    "wof:placetype":"venue"
},
  "geometry": {"coordinates":[-111.647586,40.280515],"type":"Point"}
}