{
  "type": "Feature",
  "properties": {
    "iso:country":"US",
    "sg:address":"2244 Park Ave",
    "sg:city":"Park City",
    "sg:classifiers":[
        {
            "category":"Organizations",
            "subcategory":"Membership Organization",
            "type":"Services"
        }
    ],
    "sg:phone":"+1 435 647 9747",
    "sg:postcode":"84060",
    "sg:province":"UT",
    "wof:name":"Park Cy Smmit Cnty Arts Cuncil",
    "wof:placetype":"venue"
},
  "geometry": {"coordinates":[-111.51519399999999,40.66781],"type":"Point"}
}