{
  "type": "Feature",
  "properties": {
    "iso:country":"US",
    "sg:address":"318 Cranberry Hill Dr",
    "sg:city":"Draper",
    "sg:classifiers":[
        {
            "category":"Professional",
            "subcategory":"Employment Agencies",
            "type":"Services"
        }
    ],
    "sg:phone":"+1 801 545 8832",
    "sg:postcode":"84020",
    "sg:province":"UT",
    "sg:tags":[
        "help",
        "supply"
    ],
    "wof:name":"United Staffing of America",
    "wof:placetype":"venue"
},
  "geometry": {"coordinates":[-111.881736,40.542458],"type":"Point"}
}