{
  "type": "Feature",
  "properties": {
    "iso:country":"US",
    "sg:address":"101 Wasatch Dr",
    "sg:city":"Salt Lake City",
    "sg:classifiers":[
        {
            "category":"Communications",
            "subcategory":"Television Station",
            "type":"Services"
        }
    ],
    "sg:phone":"+1 801 581 7777",
    "sg:postcode":"84112",
    "sg:province":"UT",
    "sg:tags":[
        "broadcasting",
        "co"
    ],
    "sg:website":"www.kued.org",
    "wof:name":"KUED",
    "wof:placetype":"venue"
},
  "geometry": {"coordinates":[-111.838384,40.767173],"type":"Point"}
}