{
  "type": "Feature",
  "properties": {
    "iso:country":"US",
    "sg:address":"1021 N 500 W",
    "sg:city":"Provo",
    "sg:classifiers":[
        {
            "category":"Home & Garden",
            "subcategory":"Home Furnishings",
            "type":"Retail Goods"
        }
    ],
    "sg:phone":"+1 801 376 5000",
    "sg:postcode":"84604",
    "sg:province":"UT",
    "sg:tags":[
        "window",
        "covering"
    ],
    "wof:name":"Blinds By Pace Interior",
    "wof:placetype":"venue"
},
  "geometry": {"coordinates":[-111.667486,40.248208],"type":"Point"}
}