{
  "type": "Feature",
  "properties": {
    "iso:country":"US",
    "sg:address":"965 E 1200 N",
    "sg:city":"Orem",
    "sg:classifiers":[
        {
            "category":"Communications",
            "subcategory":"Film & Video Production",
            "type":"Services"
        }
    ],
    "sg:phone":"+1 801 221 4942",
    "sg:postcode":"84097",
    "sg:province":"UT",
    "sg:tags":[
        "taping"
    ],
    "wof:name":"Mountain West Video",
    "wof:placetype":"venue"
},
  "geometry": {"coordinates":[-111.67372899999999,40.319359],"type":"Point"}
}