{
  "type": "Feature",
  "properties": {
    "iso:country":"US",
    "sg:address":"203 E 1500 N",
    "sg:city":"Lehi",
    "sg:classifiers":[
        {
            "category":"Shopping",
            "subcategory":"Hobbies, Toys, & Games",
            "type":"Retail Goods"
        }
    ],
    "sg:phone":"+1 801 768 3734",
    "sg:postcode":"84043",
    "sg:province":"UT",
    "wof:name":"Dazzlebark Thicket Design",
    "wof:placetype":"venue"
},
  "geometry": {"coordinates":[-111.846636,40.406274],"type":"Point"}
}