{
  "type": "Feature",
  "properties": {
    "iso:country":"US",
    "sg:address":"10290 S State St",
    "sg:city":"Sandy",
    "sg:classifiers":[
        {
            "category":"Restaurant",
            "type":"Food & Drink"
        }
    ],
    "sg:menulink":"http://www.allmenus.com/ut/salt-lake-city/37347-black-angus-steakhouse/menu/",
    "sg:phone":"+1 801 569 1200",
    "sg:postcode":"84070",
    "sg:province":"UT",
    "sg:tags":[
        "american",
        "steakhouse"
    ],
    "wof:name":"Black Angus Steakhouse",
    "wof:placetype":"venue"
},
  "geometry": {"coordinates":[-111.89089199999999,40.564384],"type":"Point"}
}