{
  "type": "Feature",
  "properties": {
    "iso:country":"US",
    "sg:address":"272 Berger Ln",
    "sg:city":"Salt Lake City",
    "sg:classifiers":[
        {
            "category":"Retail",
            "subcategory":"Auto Repair",
            "type":"Services"
        }
    ],
    "sg:phone":"+1 801 747 1313",
    "sg:postcode":"84107",
    "sg:province":"UT",
    "sg:tags":[
        "exchanging",
        "engine"
    ],
    "wof:name":"Motion Motor Replacement",
    "wof:placetype":"venue"
},
  "geometry": {"coordinates":[-111.896663,40.664086],"type":"Point"}
}