{
  "type": "Feature",
  "properties": {
    "iso:country":"US",
    "sg:address":"2402 S 1100 W",
    "sg:city":"Woods Cross",
    "sg:classifiers":[
        {
            "category":"Manufacturing",
            "subcategory":"Tools & Machinery",
            "type":"Manufacturing & Wholesale Goods"
        }
    ],
    "sg:phone":"+1 801 298 7282",
    "sg:postcode":"84087",
    "sg:province":"UT",
    "sg:tags":[
        "mold"
    ],
    "wof:name":"Newman Mold",
    "wof:placetype":"venue"
},
  "geometry": {"coordinates":[-111.911928,40.867316],"type":"Point"}
}