{
  "type": "Feature",
  "properties": {
    "iso:country":"US",
    "sg:address":"3670 Quincy Ave",
    "sg:city":"Ogden",
    "sg:classifiers":[
        {
            "category":"Professional",
            "subcategory":"Research",
            "type":"Services"
        },
        {
            "category":"Professional",
            "subcategory":"Management & Consulting",
            "type":"Services"
        }
    ],
    "sg:phone":"+1 801 394 0013",
    "sg:postcode":"84403",
    "sg:province":"UT",
    "sg:tags":[
        "archaeologist",
        "business"
    ],
    "sg:website":"www.sagebrushconsultants.com",
    "wof:name":"Sagebrush Consultants LLC",
    "wof:placetype":"venue"
},
  "geometry": {"coordinates":[-111.956996,41.196256],"type":"Point"}
}