{
  "type": "Feature",
  "properties": {
    "iso:country":"US",
    "sg:address":"462 W Bearcat Dr",
    "sg:city":"Salt Lake City",
    "sg:classifiers":[
        {
            "category":"Food & Beverages",
            "subcategory":"Bakery",
            "type":"Retail Goods"
        }
    ],
    "sg:phone":"+1 801 474 3200",
    "sg:postcode":"84115",
    "sg:province":"UT",
    "sg:tags":[
        "cookie",
        "cracker"
    ],
    "wof:name":"Cookie Lee Inc",
    "wof:placetype":"venue"
},
  "geometry": {"coordinates":[-111.900526,40.719435],"type":"Point"}
}