{
  "type": "Feature",
  "properties": {
    "iso:country":"US",
    "sg:address":"1374 N 40 E",
    "sg:city":"Orem",
    "sg:classifiers":[
        {
            "category":"Food & Beverages",
            "subcategory":"Candy",
            "type":"Retail Goods"
        }
    ],
    "sg:phone":"+1 801 226 6009",
    "sg:postcode":"84057",
    "sg:province":"UT",
    "sg:tags":[
        "popcorn",
        "supply"
    ],
    "wof:name":"Rocky Mountain Kettle Corn",
    "wof:placetype":"venue"
},
  "geometry": {"coordinates":[-111.69501200000001,40.322106],"type":"Point"}
}