{
  "type": "Feature",
  "properties": {
    "iso:country":"US",
    "sg:address":"8501 S 1380 E",
    "sg:city":"Sandy",
    "sg:classifiers":[
        {
            "category":"Autos & Motor Vehicles",
            "subcategory":"Automobile Sales",
            "type":"Retail Goods"
        }
    ],
    "sg:phone":"+1 801 562 5119",
    "sg:postcode":"84093",
    "sg:province":"UT",
    "sg:tags":[
        "used"
    ],
    "wof:name":"Aaron Auto Sale",
    "wof:placetype":"venue"
},
  "geometry": {"coordinates":[-111.85131800000001,40.596809],"type":"Point"}
}