{
  "type": "Feature",
  "properties": {
    "iso:country":"US",
    "sg:address":"880 W Riverdale Rd",
    "sg:city":"Ogden",
    "sg:classifiers":[
        {
            "category":"Home & Garden",
            "subcategory":"Furniture",
            "type":"Retail Goods"
        }
    ],
    "sg:phone":"+1 801 621 5331",
    "sg:postcode":"84405",
    "sg:province":"UT",
    "wof:name":"Bedrooms Elite Inc",
    "wof:placetype":"venue"
},
  "geometry": {"coordinates":[-111.998266,41.179439],"type":"Point"}
}