{
  "type": "Feature",
  "properties": {
    "iso:country":"US",
    "sg:address":"3260 S West Temple",
    "sg:city":"South Salt Lake",
    "sg:classifiers":[
        {
            "category":"Home & Garden",
            "subcategory":"Furniture",
            "type":"Retail Goods"
        }
    ],
    "sg:phone":"+1 801 467 5336",
    "sg:postcode":"84115",
    "sg:province":"UT",
    "sg:tags":[
        "cabinet"
    ],
    "wof:name":"Heinz & Sons Inc",
    "wof:placetype":"venue"
},
  "geometry": {"coordinates":[-111.894063,40.700768],"type":"Point"}
}