{
  "type": "Feature",
  "properties": {
    "iso:country":"US",
    "sg:address":"1539 Roberta St",
    "sg:city":"Salt Lake City",
    "sg:classifiers":[
        {
            "category":"Government",
            "subcategory":"Office",
            "type":"Public Place"
        }
    ],
    "sg:phone":"+1 801 484 0502",
    "sg:postcode":"84115",
    "sg:province":"UT",
    "sg:website":"www.vmh.com",
    "wof:name":"Salt Lake County ARTEC",
    "wof:placetype":"venue"
},
  "geometry": {"coordinates":[-111.883872,40.736674],"type":"Point"}
}