{
  "type": "Feature",
  "properties": {
    "iso:country":"US",
    "sg:address":"1865 S State St",
    "sg:city":"Salt Lake City",
    "sg:classifiers":[
        {
            "category":"Manufacturing",
            "subcategory":"Furniture",
            "type":"Manufacturing & Wholesale Goods"
        }
    ],
    "sg:phone":"+1 801 485 6111",
    "sg:postcode":"84115",
    "sg:province":"UT",
    "wof:name":"Techline",
    "wof:placetype":"venue"
},
  "geometry": {"coordinates":[-111.88812900000001,40.72948],"type":"Point"}
}