{
  "type": "Feature",
  "properties": {
    "iso:country":"US",
    "sg:address":"4881 W 3850 S",
    "sg:city":"Salt Lake City",
    "sg:classifiers":[
        {
            "category":"Manufacturing",
            "subcategory":"Retail Goods",
            "type":"Manufacturing & Wholesale Goods"
        }
    ],
    "sg:phone":"+1 801 955 3459",
    "sg:postcode":"84120",
    "sg:province":"UT",
    "sg:tags":[
        "product",
        "mfg"
    ],
    "wof:name":"Dr Artists & Puppets Inc",
    "wof:placetype":"venue"
},
  "geometry": {"coordinates":[-112.00651999999999,40.688059],"type":"Point"}
}