{
  "type": "Feature",
  "properties": {
    "iso:country":"US",
    "sg:address":"410 W 100 N",
    "sg:city":"Price",
    "sg:classifiers":[
        {
            "category":"Building & Trades",
            "subcategory":"Electrical",
            "type":"Services"
        }
    ],
    "sg:phone":"+1 435 637 8596",
    "sg:postcode":"84501",
    "sg:province":"UT",
    "sg:tags":[
        "electric",
        "contractor"
    ],
    "wof:name":"Electric SAM",
    "wof:placetype":"venue"
},
  "geometry": {"coordinates":[-110.818169,39.601008],"type":"Point"}
}