{
  "type": "Feature",
  "properties": {
    "iso:country":"US",
    "sg:address":"325 S Orem Blvd",
    "sg:city":"Orem",
    "sg:classifiers":[
        {
            "category":"Retail",
            "subcategory":"Portrait Studio",
            "type":"Services"
        }
    ],
    "sg:phone":"+1 801 373 4911",
    "sg:postcode":"84058",
    "sg:province":"UT",
    "sg:tags":[
        "photo",
        "printing",
        "commercial"
    ],
    "wof:name":"Christensen Photography",
    "wof:placetype":"venue"
},
  "geometry": {"coordinates":[-111.694379,40.290298],"type":"Point"}
}