{
  "type": "Feature",
  "properties": {
    "iso:country":"US",
    "sg:address":"5280 Commerce Dr",
    "sg:city":"Salt Lake City",
    "sg:classifiers":[
        {
            "category":"Health Services",
            "subcategory":"Clinic",
            "type":"Services"
        }
    ],
    "sg:phone":"+1 801 281 0537",
    "sg:postcode":"84107",
    "sg:province":"UT",
    "sg:tags":[
        "home"
    ],
    "sg:website":"www.harmonyhomehealth.com",
    "wof:name":"Harmony Home Health",
    "wof:placetype":"venue"
},
  "geometry": {"coordinates":[-111.89934700000001,40.656254],"type":"Point"}
}