{
  "type": "Feature",
  "properties": {
    "iso:country":"US",
    "sg:address":"858 Fort Union Blvd",
    "sg:city":"Midvale",
    "sg:classifiers":[
        {
            "category":"Restaurant",
            "type":"Food & Drink"
        }
    ],
    "sg:phone":"+1 801 566 6067",
    "sg:postcode":"84047",
    "sg:province":"UT",
    "sg:website":"www.subway.com",
    "wof:name":"Subway Sandwiches & Salads",
    "wof:placetype":"venue"
},
  "geometry": {"coordinates":[-111.86722399999999,40.622051],"type":"Point"}
}