{
  "type": "Feature",
  "properties": {
    "iso:country":"US",
    "sg:address":"285 W 1250 N",
    "sg:city":"Clearfield",
    "sg:classifiers":[
        {
            "category":"Personal",
            "subcategory":"Beauty Salon",
            "type":"Services"
        }
    ],
    "sg:phone":"+1 801 825 4116",
    "sg:postcode":"84015",
    "sg:province":"UT",
    "sg:tags":[
        "shop"
    ],
    "wof:name":"Magic Fingers Style Salon",
    "wof:placetype":"venue"
},
  "geometry": {"coordinates":[-112.029228,41.131676],"type":"Point"}
}