{
  "type": "Feature",
  "properties": {
    "iso:country":"US",
    "sg:address":"235 S 800 W",
    "sg:city":"Lehi",
    "sg:classifiers":[
        {
            "category":"Shopping",
            "subcategory":"Hobbies, Toys, & Games",
            "type":"Retail Goods"
        }
    ],
    "sg:phone":"+1 801 768 0230",
    "sg:postcode":"84043",
    "sg:province":"UT",
    "wof:name":"Out On A Limb",
    "wof:placetype":"venue"
},
  "geometry": {"coordinates":[-111.863091,40.385898],"type":"Point"}
}