{
  "type": "Feature",
  "properties": {
    "iso:country":"US",
    "sg:address":"784 Staheli Dr",
    "sg:city":"Washington",
    "sg:classifiers":[
        {
            "category":"Building & Trades",
            "subcategory":"Construction",
            "type":"Services"
        }
    ],
    "sg:phone":"+1 435 656 1009",
    "sg:postcode":"84780",
    "sg:province":"UT",
    "sg:tags":[
        "residential"
    ],
    "wof:name":"B T Bills",
    "wof:placetype":"venue"
},
  "geometry": {"coordinates":[-113.50385,37.118514],"type":"Point"}
}