{
  "type": "Feature",
  "properties": {
    "iso:country":"US",
    "sg:address":"390 N 200 W",
    "sg:city":"Roosevelt",
    "sg:classifiers":[
        {
            "category":"Social Services",
            "subcategory":"Child Care",
            "type":"Services"
        }
    ],
    "sg:phone":"+1 435 722 6188",
    "sg:postcode":"84066",
    "sg:province":"UT",
    "sg:tags":[
        "day"
    ],
    "wof:name":"Child Care",
    "wof:placetype":"venue"
},
  "geometry": {"coordinates":[-109.995062,40.303513],"type":"Point"}
}