{
  "type": "Feature",
  "properties": {
    "iso:country":"US",
    "sg:address":"548 W 4500 S",
    "sg:city":"Salt Lake City",
    "sg:classifiers":[
        {
            "category":"Restaurant",
            "type":"Food & Drink"
        }
    ],
    "sg:phone":"+1 801 270 0188",
    "sg:postcode":"84123",
    "sg:province":"UT",
    "wof:name":"Teriyaki Time",
    "wof:placetype":"venue"
},
  "geometry": {"coordinates":[-111.906856,40.674785],"type":"Point"}
}