{
  "type": "Feature",
  "properties": {
    "iso:country":"US",
    "sg:address":"12894 Pony Express Rd",
    "sg:city":"Draper",
    "sg:classifiers":[
        {
            "category":"Banks & Credit Unions",
            "subcategory":"Bank",
            "type":"Services"
        }
    ],
    "sg:phone":"+1 801 838 9100",
    "sg:postcode":"84020",
    "sg:province":"UT",
    "sg:tags":[
        "loan",
        "real estate"
    ],
    "wof:name":"American Pioneer Financial Svc",
    "wof:placetype":"venue"
},
  "geometry": {"coordinates":[-111.891723,40.520212],"type":"Point"}
}