{
  "type": "Feature",
  "properties": {
    "iso:country":"US",
    "sg:address":"5724 S 590 W",
    "sg:city":"Murray",
    "sg:classifiers":[
        {
            "category":"Building & Trades",
            "subcategory":"Construction",
            "type":"Services"
        }
    ],
    "sg:phone":"+1 801 205 6100",
    "sg:postcode":"84123",
    "sg:province":"UT",
    "sg:tags":[
        "roofing",
        "contractor"
    ],
    "wof:name":"Fortress Roofing",
    "wof:placetype":"venue"
},
  "geometry": {"coordinates":[-111.905998,40.646879],"type":"Point"}
}