{
  "type": "Feature",
  "properties": {
    "iso:country":"US",
    "sg:address":"560 E 4500 S",
    "sg:city":"Delta",
    "sg:classifiers":[
        {
            "category":"Real Estate",
            "subcategory":"Real Estate Operator",
            "type":"Services"
        }
    ],
    "sg:phone":"+1 435 864 1842",
    "sg:postcode":"84624",
    "sg:province":"UT",
    "sg:tags":[
        "building",
        "nonresidential"
    ],
    "wof:name":"Evelyn England",
    "wof:placetype":"venue"
},
  "geometry": {"coordinates":[-112.57048,39.286747],"type":"Point"}
}