{
  "type": "Feature",
  "properties": {
    "iso:country":"US",
    "sg:address":"14852 Heritagecrest Way",
    "sg:city":"Riverton",
    "sg:classifiers":[
        {
            "category":"Building & Trades",
            "subcategory":"Construction",
            "type":"Services"
        }
    ],
    "sg:phone":"+1 801 253 1997",
    "sg:postcode":"84065",
    "sg:province":"UT",
    "sg:tags":[
        "painter"
    ],
    "wof:name":"Hegemann Paint Co",
    "wof:placetype":"venue"
},
  "geometry": {"coordinates":[-111.91160600000001,40.479781],"type":"Point"}
}