{
  "type": "Feature",
  "properties": {
    "iso:country":"US",
    "sg:address":"970 Emery St",
    "sg:city":"Salt Lake City",
    "sg:classifiers":[
        {
            "category":"Education",
            "subcategory":"School",
            "type":"Public Place"
        }
    ],
    "sg:phone":"+1 801 974 8304",
    "sg:postcode":"84104",
    "sg:province":"UT",
    "sg:tags":[
        "elementary"
    ],
    "wof:name":"Parkview Elementary School",
    "wof:placetype":"venue"
},
  "geometry": {"coordinates":[-111.924786,40.748842],"type":"Point"}
}