{
  "type": "Feature",
  "properties": {
    "iso:country":"US",
    "sg:address":"754 Utah Ave",
    "sg:city":"Provo",
    "sg:classifiers":[
        {
            "category":"Real Estate",
            "subcategory":"Real Estate Agent",
            "type":"Services"
        }
    ],
    "sg:phone":"+1 801 374 6308",
    "sg:postcode":"84606",
    "sg:province":"UT",
    "wof:name":"1076 East LLC",
    "wof:placetype":"venue"
},
  "geometry": {"coordinates":[-111.640479,40.224584],"type":"Point"}
}