{
  "type": "Feature",
  "properties": {
    "iso:country":"US",
    "sg:address":"837 S 500 W",
    "sg:city":"Brigham City",
    "sg:classifiers":[
        {
            "category":"Professional",
            "type":"Services"
        }
    ],
    "sg:phone":"+1 435 723 3682",
    "sg:postcode":"84302",
    "sg:province":"UT",
    "sg:tags":[
        "business"
    ],
    "wof:name":"Pillar To Post",
    "wof:placetype":"venue"
},
  "geometry": {"coordinates":[-112.023909,41.493866],"type":"Point"}
}