{
  "type": "Feature",
  "properties": {
    "iso:country":"US",
    "sg:address":"70 S State St",
    "sg:city":"Salt Lake City",
    "sg:classifiers":[
        {
            "category":"Professional",
            "subcategory":"Lawyer & Legal Services",
            "type":"Services"
        }
    ],
    "sg:phone":"+1 801 532 2266",
    "sg:postcode":"84111",
    "sg:province":"UT",
    "sg:tags":[
        "attorney"
    ],
    "wof:name":"Silvester & Conroy",
    "wof:placetype":"venue"
},
  "geometry": {"coordinates":[-111.88830299999999,40.767614],"type":"Point"}
}