{
  "type": "Feature",
  "properties": {
    "iso:country":"US",
    "sg:address":"47 E Jennies Ct N",
    "sg:city":"Kaysville",
    "sg:classifiers":[
        {
            "category":"Organizations",
            "subcategory":"Political Organization",
            "type":"Services"
        }
    ],
    "sg:phone":"+1 801 546 3959",
    "sg:postcode":"84037",
    "sg:province":"UT",
    "wof:name":"Utahwatchorg",
    "wof:placetype":"venue"
},
  "geometry": {"coordinates":[-111.93669199999999,41.048552],"type":"Point"}
}