{
  "type": "Feature",
  "properties": {
    "iso:country":"US",
    "sg:address":"1220 N 4000 W",
    "sg:city":"Delta",
    "sg:phone":"+1 435 864 2610",
    "sg:postcode":"84624",
    "sg:province":"UT",
    "sg:tags":[
        "farm",
        "corn",
        "cash",
        "crop",
        "field",
        "grain"
    ],
    "wof:name":"Howard R Bassett",
    "wof:placetype":"venue"
},
  "geometry": {"coordinates":[-112.652027,39.370594],"type":"Point"}
}