{
  "type": "Feature",
  "properties": {
    "iso:country":"US",
    "sg:address":"2029 Sidewinder Dr",
    "sg:city":"Park City",
    "sg:classifiers":[
        {
            "category":"Banks & Credit Unions",
            "subcategory":"Bank",
            "type":"Services"
        }
    ],
    "sg:phone":"+1 435 658 2787",
    "sg:postcode":"84060",
    "sg:province":"UT",
    "sg:tags":[
        "loan",
        "real estate"
    ],
    "wof:name":"Vesta Financial",
    "wof:placetype":"venue"
},
  "geometry": {"coordinates":[-111.495082,40.664005],"type":"Point"}
}