{
  "type": "Feature",
  "properties": {
    "iso:country":"US",
    "sg:address":"503 W 2600 S",
    "sg:city":"Bountiful",
    "sg:classifiers":[
        {
            "category":"Shopping",
            "subcategory":"Clothing, Apparel, & Fashions",
            "type":"Retail Goods"
        }
    ],
    "sg:phone":"+1 801 201 6910",
    "sg:postcode":"84010",
    "sg:province":"UT",
    "sg:tags":[
        "garment"
    ],
    "wof:name":"Specialty Apparel",
    "wof:placetype":"venue"
},
  "geometry": {"coordinates":[-111.892279,40.861667],"type":"Point"}
}