{
  "type": "Feature",
  "properties": {
    "iso:country":"US",
    "sg:address":"95 N 2125 W",
    "sg:city":"Cedar City",
    "sg:classifiers":[
        {
            "category":"Professional",
            "type":"Services"
        }
    ],
    "sg:phone":"+1 435 586 0432",
    "sg:postcode":"84720",
    "sg:province":"UT",
    "sg:tags":[
        "establishment"
    ],
    "wof:name":"North Stake Family History Ctr",
    "wof:placetype":"venue"
},
  "geometry": {"coordinates":[-113.088621,37.678002],"type":"Point"}
}