{
  "type": "Feature",
  "properties": {
    "iso:country":"US",
    "sg:address":"2964 W 4700 S",
    "sg:city":"Salt Lake City",
    "sg:classifiers":[
        {
            "category":"Food & Beverages",
            "subcategory":"Groceries & Convenience Stores",
            "type":"Retail Goods"
        }
    ],
    "sg:phone":"+1 801 967 7530",
    "sg:postcode":"84118",
    "sg:province":"UT",
    "sg:tags":[
        "product"
    ],
    "wof:name":"R & S Food Brokers",
    "wof:placetype":"venue"
},
  "geometry": {"coordinates":[-111.962611,40.66769],"type":"Point"}
}