{
  "type": "Feature",
  "properties": {
    "iso:country":"US",
    "sg:address":"721 W 1300 N",
    "sg:city":"Clearfield",
    "sg:classifiers":[
        {
            "category":"Social Services",
            "type":"Services"
        }
    ],
    "sg:phone":"+1 801 773 0946",
    "sg:postcode":"84015",
    "sg:province":"UT",
    "sg:tags":[
        "organization",
        "nonprofit",
        "religious"
    ],
    "wof:name":"Family Lgal Action Cuncil 216",
    "wof:placetype":"venue"
},
  "geometry": {"coordinates":[-112.040204,41.132539],"type":"Point"}
}