{
  "type": "Feature",
  "properties": {
    "iso:country":"US",
    "sg:address":"5666 W 4000 S",
    "sg:city":"Hooper",
    "sg:classifiers":[
        {
            "category":"Banks & Credit Unions",
            "subcategory":"Bank",
            "type":"Services"
        }
    ],
    "sg:phone":"+1 801 731 1645",
    "sg:postcode":"84315",
    "sg:province":"UT",
    "sg:tags":[
        "broker",
        "mortgage"
    ],
    "wof:name":"Granite Financial Group Inc",
    "wof:placetype":"venue"
},
  "geometry": {"coordinates":[-112.11902600000001,41.1908],"type":"Point"}
}