{
  "type": "Feature",
  "properties": {
    "iso:country":"US",
    "sg:address":"7478 Holden St",
    "sg:city":"Midvale",
    "sg:classifiers":[
        {
            "category":"Building & Trades",
            "subcategory":"Electrical",
            "type":"Services"
        }
    ],
    "sg:phone":"+1 801 568 0980",
    "sg:postcode":"84047",
    "sg:province":"UT",
    "sg:tags":[
        "electrical",
        "contractor"
    ],
    "wof:name":"Hofeling Electric Inc",
    "wof:placetype":"venue"
},
  "geometry": {"coordinates":[-111.911207,40.615329],"type":"Point"}
}