{
  "type": "Feature",
  "properties": {
    "iso:country":"US",
    "sg:address":"581 W 2600 S",
    "sg:city":"Bountiful",
    "sg:classifiers":[
        {
            "category":"Health Services",
            "subcategory":"Dentist",
            "type":"Services"
        }
    ],
    "sg:phone":"+1 801 295 4746",
    "sg:postcode":"84010",
    "sg:province":"UT",
    "wof:name":"Schmutz Paul A DDS",
    "wof:placetype":"venue"
},
  "geometry": {"coordinates":[-111.89451699999999,40.861473],"type":"Point"}
}