{
  "type": "Feature",
  "properties": {
    "iso:country":"US",
    "sg:address":"797 S Main St",
    "sg:city":"Cedar City",
    "sg:classifiers":[
        {
            "category":"Banks & Credit Unions",
            "subcategory":"Bank",
            "type":"Services"
        }
    ],
    "sg:phone":"+1 435 867 2605",
    "sg:postcode":"84720",
    "sg:province":"UT",
    "sg:website":"www.wellsfargo.com",
    "wof:name":"Wells Fargo Bank",
    "wof:placetype":"venue"
},
  "geometry": {"coordinates":[-113.06697699999999,37.663608],"type":"Point"}
}