{
  "type": "Feature",
  "properties": {
    "iso:country":"US",
    "sg:address":"455 W 1100 N",
    "sg:city":"North Salt Lake",
    "sg:classifiers":[
        {
            "category":"Freight",
            "type":"Transportation"
        }
    ],
    "sg:phone":"+1 801 292 7770",
    "sg:postcode":"84054",
    "sg:province":"UT",
    "sg:tags":[
        "trucking"
    ],
    "sg:website":"www.horseshoexp.com",
    "wof:name":"Horseshoe Express",
    "wof:placetype":"venue"
},
  "geometry": {"coordinates":[-111.92147,40.86156],"type":"Point"}
}