{
  "type": "Feature",
  "properties": {
    "iso:country":"US",
    "sg:address":"11624 Colchester Dr",
    "sg:city":"Sandy",
    "sg:classifiers":[
        {
            "category":"Food & Beverages",
            "subcategory":"Specialty",
            "type":"Retail Goods"
        }
    ],
    "sg:phone":"+1 801 571 8866",
    "sg:postcode":"84092",
    "sg:province":"UT",
    "sg:tags":[
        "tea",
        "coffee"
    ],
    "sg:website":"www.greatcoffee.com",
    "wof:name":"GREATCOFFEE.COM",
    "wof:placetype":"venue"
},
  "geometry": {"coordinates":[-111.84213800000001,40.540479],"type":"Point"}
}