{
  "type": "Feature",
  "properties": {
    "iso:country":"US",
    "sg:address":"1744 Oakcrest Dr",
    "sg:city":"Orem",
    "sg:classifiers":[
        {
            "category":"Real Estate",
            "subcategory":"Real Estate Agent",
            "type":"Services"
        },
        {
            "category":"Professional",
            "subcategory":"Business Services",
            "type":"Services"
        }
    ],
    "sg:phone":"+1 801 224 0488",
    "sg:postcode":"84097",
    "sg:province":"UT",
    "sg:tags":[
        "management"
    ],
    "wof:name":"Clifford Associates LLC",
    "wof:placetype":"venue"
},
  "geometry": {"coordinates":[-111.675488,40.329337],"type":"Point"}
}