{
  "type": "Feature",
  "properties": {
    "iso:country":"US",
    "sg:address":"2353 Fort Union Blvd",
    "sg:city":"Salt Lake City",
    "sg:classifiers":[
        {
            "category":"Bakery",
            "type":"Food & Drink"
        },
        {
            "category":"Bagels",
            "type":"Food & Drink"
        }
    ],
    "sg:menulink":"http://www.allmenus.com/ut/salt-lake-city/37300-einstein-bros/menu/",
    "sg:phone":"+1 801 944 5590",
    "sg:postcode":"84121",
    "sg:province":"UT",
    "sg:tags":[
        "sandwich",
        "salad",
        "soup",
        "american",
        "pastry",
        "wrap"
    ],
    "wof:name":"Einstein Bros",
    "wof:placetype":"venue"
},
  "geometry": {"coordinates":[-111.82370400000001,40.624469],"type":"Point"}
}