{
  "type": "Feature",
  "properties": {
    "iso:country":"US",
    "sg:address":"48 N 100 E",
    "sg:city":"Panguitch",
    "sg:classifiers":[
        {
            "category":"Government",
            "subcategory":"Office",
            "type":"Public Place"
        }
    ],
    "sg:phone":"+1 435 676 2662",
    "sg:postcode":"84759",
    "sg:province":"UT",
    "wof:name":"Garfield County Adm",
    "wof:placetype":"venue"
},
  "geometry": {"coordinates":[-112.433663,37.822756],"type":"Point"}
}