{
  "type": "Feature",
  "properties": {
    "iso:country":"US",
    "sg:address":"108 W 1650 N",
    "sg:city":"Centerville",
    "sg:classifiers":[
        {
            "category":"Organizations",
            "subcategory":"Labor Organization",
            "type":"Services"
        }
    ],
    "sg:phone":"+1 801 295 2228",
    "sg:postcode":"84014",
    "sg:province":"UT",
    "wof:name":"Jj Land Company Lc",
    "wof:placetype":"venue"
},
  "geometry": {"coordinates":[-111.881778,40.941227],"type":"Point"}
}