{
  "type": "Feature",
  "properties": {
    "iso:country":"US",
    "sg:address":"3404 W 4800 S",
    "sg:city":"Roy",
    "sg:classifiers":[
        {
            "category":"Restaurant",
            "type":"Food & Drink"
        }
    ],
    "sg:menulink":"http://www.allmenus.com/ut/ogden/81098-papa-johns-pizza/menu/",
    "sg:phone":"+1 801 776 6100",
    "sg:postcode":"84067",
    "sg:province":"UT",
    "sg:tags":[
        "american",
        "pizza"
    ],
    "wof:name":"Papa John's Pizza",
    "wof:placetype":"venue"
},
  "geometry": {"coordinates":[-112.06108399999999,41.176158],"type":"Point"}
}