{
  "type": "Feature",
  "properties": {
    "iso:country":"US",
    "sg:address":"4514 Parkview Dr",
    "sg:city":"Salt Lake City",
    "sg:classifiers":[
        {
            "category":"Banks & Credit Unions",
            "subcategory":"Financial Services",
            "type":"Services"
        }
    ],
    "sg:phone":"+1 801 272 3512",
    "sg:postcode":"84124",
    "sg:province":"UT",
    "sg:tags":[
        "investor"
    ],
    "wof:name":"Juanita Investment Co Ltd Part",
    "wof:placetype":"venue"
},
  "geometry": {"coordinates":[-111.786137,40.674047],"type":"Point"}
}