{
  "type": "Feature",
  "properties": {
    "iso:country":"US",
    "sg:address":"1611 W Grandview Ln",
    "sg:city":"Provo",
    "sg:classifiers":[
        {
            "category":"Health Services",
            "subcategory":"Doctor",
            "type":"Services"
        }
    ],
    "sg:phone":"+1 801 370 0093",
    "sg:postcode":"84604",
    "sg:province":"UT",
    "sg:tags":[
        "medical"
    ],
    "wof:name":"MD Producers Inc",
    "wof:placetype":"venue"
},
  "geometry": {"coordinates":[-111.673658,40.255012],"type":"Point"}
}