{
  "type": "Feature",
  "properties": {
    "iso:country":"US",
    "sg:address":"3140 Directors Row",
    "sg:city":"Salt Lake City",
    "sg:classifiers":[
        {
            "category":"Retail",
            "subcategory":"Auto Repair",
            "type":"Services"
        }
    ],
    "sg:phone":"+1 801 973 4433",
    "sg:postcode":"84104",
    "sg:province":"UT",
    "sg:tags":[
        "truck"
    ],
    "wof:name":"Salt Lake Truck & Trailor LLC",
    "wof:placetype":"venue"
},
  "geometry": {"coordinates":[-111.962806,40.745851],"type":"Point"}
}