{
  "type": "Feature",
  "properties": {
    "iso:country":"US",
    "sg:address":"514 N Bluff St",
    "sg:city":"St George",
    "sg:phone":"+1 435 656 2885",
    "sg:postcode":"84770",
    "sg:province":"UT",
    "sg:tags":[
        "gas"
    ],
    "wof:name":"Warren Energy Group Inc",
    "wof:placetype":"venue"
},
  "geometry": {"coordinates":[-113.597477,37.118226],"type":"Point"}
}