{
  "type": "Feature",
  "properties": {
    "iso:country":"US",
    "sg:address":"13408 Pony Express Rd",
    "sg:city":"Draper",
    "sg:classifiers":[
        {
            "category":"Banks & Credit Unions",
            "subcategory":"Bank",
            "type":"Services"
        }
    ],
    "sg:phone":"+1 801 571 3780",
    "sg:postcode":"84020",
    "sg:province":"UT",
    "sg:tags":[
        "broker",
        "mortgage"
    ],
    "wof:name":"Englewood Mortgage Co",
    "wof:placetype":"venue"
},
  "geometry": {"coordinates":[-111.892022,40.507081],"type":"Point"}
}