{
  "type": "Feature",
  "properties": {
    "iso:country":"US",
    "sg:address":"387 W 200 N",
    "sg:city":"Cedar City",
    "sg:classifiers":[
        {
            "category":"Personal",
            "subcategory":"Beauty Salon",
            "type":"Services"
        }
    ],
    "sg:phone":"+1 435 867 1993",
    "sg:postcode":"84720",
    "sg:province":"UT",
    "wof:name":"Hello Gorgeous",
    "wof:placetype":"venue"
},
  "geometry": {"coordinates":[-113.068386,37.680874],"type":"Point"}
}