{
  "type": "Feature",
  "properties": {
    "iso:country":"US",
    "sg:address":"1932 N Blue Mountain Rd",
    "sg:city":"Blanding",
    "sg:classifiers":[
        {
            "category":"Manufacturing",
            "subcategory":"Metals",
            "type":"Manufacturing & Wholesale Goods"
        }
    ],
    "sg:phone":"+1 435 678 2030",
    "sg:postcode":"84511",
    "sg:province":"UT",
    "wof:name":"Pauls Wood & Iron Company",
    "wof:placetype":"venue"
},
  "geometry": {"coordinates":[-109.473276,37.665319],"type":"Point"}
}