{
  "type": "Feature",
  "properties": {
    "iso:country":"US",
    "sg:address":"7332 Echo Ln",
    "sg:city":"Park City",
    "sg:classifiers":[
        {
            "category":"Banks & Credit Unions",
            "subcategory":"Financial Services",
            "type":"Services"
        }
    ],
    "sg:phone":"+1 435 649 4489",
    "sg:postcode":"84098",
    "sg:province":"UT",
    "sg:tags":[
        "investor"
    ],
    "wof:name":"Bacon Investments LLC",
    "wof:placetype":"venue"
},
  "geometry": {"coordinates":[-111.487313,40.739213],"type":"Point"}
}