{
  "type": "Feature",
  "properties": {
    "iso:country":"US",
    "sg:address":"867 Emeril Ave",
    "sg:city":"Salt Lake City",
    "sg:classifiers":[
        {
            "category":"Retail",
            "subcategory":"Auto Repair",
            "type":"Services"
        }
    ],
    "sg:phone":"+1 801 355 2246",
    "sg:postcode":"84116",
    "sg:province":"UT",
    "sg:tags":[
        "repairing",
        "automobile"
    ],
    "wof:name":"Santa Fe Auto Svc",
    "wof:placetype":"venue"
},
  "geometry": {"coordinates":[-111.915234,40.770134],"type":"Point"}
}