{
  "type": "Feature",
  "properties": {
    "iso:country":"US",
    "sg:address":"680 W 770 S",
    "sg:city":"Woods Cross",
    "sg:classifiers":[
        {
            "category":"Professional",
            "subcategory":"Accounting & Tax Preparation",
            "type":"Services"
        }
    ],
    "sg:phone":"+1 801 292 0873",
    "sg:postcode":"84087",
    "sg:province":"UT",
    "sg:tags":[
        "return",
        "filing"
    ],
    "wof:name":"C & M Tax & Bookeeping",
    "wof:placetype":"venue"
},
  "geometry": {"coordinates":[-111.898292,40.881621],"type":"Point"}
}