{
  "type": "Feature",
  "properties": {
    "iso:country":"US",
    "sg:address":"595 S Main St",
    "sg:city":"Manti",
    "sg:classifiers":[
        {
            "category":"Education",
            "subcategory":"Library",
            "type":"Public Place"
        }
    ],
    "sg:phone":"+1 435 835 8888",
    "sg:postcode":"84642",
    "sg:province":"UT",
    "wof:name":"Manti Family History Center",
    "wof:placetype":"venue"
},
  "geometry": {"coordinates":[-111.636944,39.256747],"type":"Point"}
}