{
  "type": "Feature",
  "properties": {
    "iso:country":"US",
    "sg:address":"7131 S 2740 E",
    "sg:city":"Salt Lake City",
    "sg:classifiers":[
        {
            "category":"Professional",
            "subcategory":"Business Services",
            "type":"Services"
        }
    ],
    "sg:phone":"+1 801 942 0176",
    "sg:postcode":"84121",
    "sg:province":"UT",
    "wof:name":"James A Lindsay & Associates",
    "wof:placetype":"venue"
},
  "geometry": {"coordinates":[-111.814205,40.619369],"type":"Point"}
}