{
  "type": "Feature",
  "properties": {
    "iso:country":"US",
    "sg:address":"1555 W 2200 S",
    "sg:city":"Salt Lake City",
    "sg:classifiers":[
        {
            "category":"Wholesale",
            "subcategory":"Medical Equipment & Supplies",
            "type":"Manufacturing & Wholesale Goods"
        }
    ],
    "sg:phone":"+1 801 972 5353",
    "sg:postcode":"84119",
    "sg:province":"UT",
    "sg:tags":[
        "physician",
        "surgeon"
    ],
    "wof:name":"Apria Healthcare Inc",
    "wof:placetype":"venue"
},
  "geometry": {"coordinates":[-111.93170600000001,40.723466],"type":"Point"}
}