{
  "type": "Feature",
  "properties": {
    "iso:country":"US",
    "sg:address":"7400 S 1000 E",
    "sg:city":"Midvale",
    "sg:classifiers":[
        {
            "category":"Organizations",
            "subcategory":"Religious Organization",
            "type":"Services"
        }
    ],
    "sg:phone":"+1 801 562 8087",
    "sg:postcode":"84047",
    "sg:province":"UT",
    "sg:tags":[
        "church"
    ],
    "wof:name":"Church Of Jesus Christ Of Lds",
    "wof:placetype":"venue"
},
  "geometry": {"coordinates":[-111.86254099999999,40.617682],"type":"Point"}
}