{
  "type": "Feature",
  "properties": {
    "iso:country":"US",
    "sg:address":"10577 Wasatch Blvd",
    "sg:city":"Sandy",
    "sg:classifiers":[
        {
            "category":"Banks & Credit Unions",
            "subcategory":"Financial Services",
            "type":"Services"
        }
    ],
    "sg:phone":"+1 801 942 1492",
    "sg:postcode":"84092",
    "sg:province":"UT",
    "sg:tags":[
        "investor"
    ],
    "wof:name":"Aotearoa Investments LLC",
    "wof:placetype":"venue"
},
  "geometry": {"coordinates":[-111.800281,40.559594],"type":"Point"}
}