{
  "type": "Feature",
  "properties": {
    "iso:country":"US",
    "sg:address":"753 Columbia Ln",
    "sg:city":"Provo",
    "sg:classifiers":[
        {
            "category":"Building & Trades",
            "subcategory":"Cleaning & Sanitation",
            "type":"Services"
        }
    ],
    "sg:phone":"+1 801 373 2424",
    "sg:postcode":"84604",
    "sg:province":"UT",
    "sg:tags":[
        "janitor"
    ],
    "wof:name":"RBM Svc",
    "wof:placetype":"venue"
},
  "geometry": {"coordinates":[-111.67183900000001,40.252576],"type":"Point"}
}