{
  "type": "Feature",
  "properties": {
    "iso:country":"US",
    "sg:address":"2879 Lancaster Dr",
    "sg:city":"Salt Lake City",
    "sg:classifiers":[
        {
            "category":"Banks & Credit Unions",
            "subcategory":"Financial Services",
            "type":"Services"
        }
    ],
    "sg:phone":"+1 801 582 6868",
    "sg:postcode":"84108",
    "sg:province":"UT",
    "sg:tags":[
        "company",
        "holding"
    ],
    "wof:name":"Pembroke Montana Properties LL",
    "wof:placetype":"venue"
},
  "geometry": {"coordinates":[-111.81032500000001,40.73723],"type":"Point"}
}