{
  "type": "Feature",
  "properties": {
    "iso:country":"US",
    "sg:address":"15 S 7th St",
    "sg:city":"Tooele",
    "sg:classifiers":[
        {
            "category":"Organizations",
            "subcategory":"Religious Organization",
            "type":"Services"
        }
    ],
    "sg:phone":"+1 435 882 0081",
    "sg:postcode":"84074",
    "sg:province":"UT",
    "sg:tags":[
        "church"
    ],
    "wof:name":"St Marguerite's",
    "wof:placetype":"venue"
},
  "geometry": {"coordinates":[-112.283456,40.530282],"type":"Point"}
}