{
  "type": "Feature",
  "properties": {
    "iso:country":"US",
    "sg:address":"331 S Rio Grande St",
    "sg:city":"Salt Lake City",
    "sg:classifiers":[
        {
            "category":"Organizations",
            "subcategory":"Non-profit Organization",
            "type":"Services"
        }
    ],
    "sg:phone":"+1 801 521 2035",
    "sg:postcode":"84101",
    "sg:province":"UT",
    "wof:name":"Utah Issues Information Prgrm",
    "wof:placetype":"venue"
},
  "geometry": {"coordinates":[-111.904015,40.761308],"type":"Point"}
}