{
  "type": "Feature",
  "properties": {
    "iso:country":"US",
    "sg:address":"4832 W 8800 S",
    "sg:city":"Payson",
    "sg:classifiers":[
        {
            "category":"Recreation",
            "type":"Entertainment"
        }
    ],
    "sg:phone":"+1 801 465 9173",
    "sg:postcode":"84651",
    "sg:province":"UT",
    "sg:tags":[
        "club",
        "membership"
    ],
    "wof:name":"Diamond Bar Ranch",
    "wof:placetype":"venue"
},
  "geometry": {"coordinates":[-111.771376,40.070651],"type":"Point"}
}