{
  "type": "Feature",
  "properties": {
    "iso:country":"US",
    "sg:address":"1928 Hill St",
    "sg:city":"Kaysville",
    "sg:classifiers":[
        {
            "category":"Building & Trades",
            "subcategory":"Construction",
            "type":"Services"
        }
    ],
    "sg:phone":"+1 801 546 4071",
    "sg:postcode":"84037",
    "sg:province":"UT",
    "sg:tags":[
        "painting",
        "contractor"
    ],
    "wof:name":"Rosewood Painting Inc",
    "wof:placetype":"venue"
},
  "geometry": {"coordinates":[-111.973855,41.03964],"type":"Point"}
}