{
  "type": "Feature",
  "properties": {
    "iso:country":"US",
    "sg:address":"1715 N State Rd 32",
    "sg:city":"Kamas",
    "sg:classifiers":[
        {
            "category":"Manufacturing",
            "subcategory":"Metals",
            "type":"Manufacturing & Wholesale Goods"
        }
    ],
    "sg:phone":"+1 435 783 4680",
    "sg:postcode":"84036",
    "sg:province":"UT",
    "sg:tags":[
        "plate",
        "work",
        "fabricated",
        "mfg"
    ],
    "wof:name":"A-Jacks",
    "wof:placetype":"venue"
},
  "geometry": {"coordinates":[-111.280733,40.66987],"type":"Point"}
}