{
  "type": "Feature",
  "properties": {
    "iso:country":"US",
    "sg:address":"154 N Main St",
    "sg:city":"Helper",
    "sg:classifiers":[
        {
            "category":"Restaurant",
            "type":"Food & Drink"
        }
    ],
    "sg:phone":"+1 435 472 5272",
    "sg:postcode":"84526",
    "sg:province":"UT",
    "sg:tags":[
        "eating"
    ],
    "wof:name":"Subway",
    "wof:placetype":"venue"
},
  "geometry": {"coordinates":[-110.86284000000001,39.693076],"type":"Point"}
}