{
  "type": "Feature",
  "properties": {
    "iso:country":"US",
    "sg:address":"781 Northview Dr",
    "sg:city":"Salt Lake City",
    "sg:classifiers":[
        {
            "category":"Professional",
            "type":"Services"
        }
    ],
    "sg:phone":"+1 801 364 8299",
    "sg:postcode":"84103",
    "sg:province":"UT",
    "wof:name":"Hanover Energy Management",
    "wof:placetype":"venue"
},
  "geometry": {"coordinates":[-111.85976599999999,40.785482],"type":"Point"}
}