{
  "type": "Feature",
  "properties": {
    "iso:country":"US",
    "sg:address":"5461 S State St",
    "sg:city":"Murray",
    "sg:classifiers":[
        {
            "category":"Shopping",
            "subcategory":"Clothing, Apparel, & Fashions",
            "type":"Retail Goods"
        }
    ],
    "sg:phone":"+1 801 261 4765",
    "sg:postcode":"84107",
    "sg:province":"UT",
    "sg:tags":[
        "furnishing"
    ],
    "sg:website":"www.dahles-bigandtall.com",
    "wof:name":"Large & Tall Fashions For Less",
    "wof:placetype":"venue"
},
  "geometry": {"coordinates":[-111.888357,40.651976],"type":"Point"}
}