{
  "type": "Feature",
  "properties": {
    "iso:country":"US",
    "sg:address":"110 W Center St",
    "sg:city":"Bountiful",
    "sg:classifiers":[
        {
            "category":"Real Estate",
            "subcategory":"Real Estate Services",
            "type":"Services"
        }
    ],
    "sg:phone":"+1 801 295 9469",
    "sg:postcode":"84010",
    "sg:province":"UT",
    "sg:tags":[
        "company",
        "abstract",
        "title"
    ],
    "wof:name":"Western States Title Davis",
    "wof:placetype":"venue"
},
  "geometry": {"coordinates":[-111.885434,40.88945],"type":"Point"}
}