{
  "type": "Feature",
  "properties": {
    "iso:country":"US",
    "sg:address":"2904 Preston St",
    "sg:city":"Salt Lake City",
    "sg:classifiers":[
        {
            "category":"Personal",
            "subcategory":"Beauty Salon",
            "type":"Services"
        }
    ],
    "sg:phone":"+1 801 466 4605",
    "sg:postcode":"84106",
    "sg:province":"UT",
    "sg:tags":[
        "shop"
    ],
    "wof:name":"Alice's Hair Fashions",
    "wof:placetype":"venue"
},
  "geometry": {"coordinates":[-111.83618800000001,40.70916],"type":"Point"}
}