{
  "type": "Feature",
  "properties": {
    "iso:country":"US",
    "sg:address":"180 N Main St",
    "sg:city":"Hyde Park",
    "sg:classifiers":[
        {
            "category":"Restaurant",
            "type":"Food & Drink"
        }
    ],
    "sg:menulink":"http://www.allmenus.com/ut/logan/212954-mcdonalds/menu/",
    "sg:phone":"+1 435 563 3477",
    "sg:postcode":"84318",
    "sg:province":"UT",
    "sg:tags":[
        "burger",
        "american"
    ],
    "wof:name":"McDonald's",
    "wof:placetype":"venue"
},
  "geometry": {"coordinates":[-111.819152,41.802678],"type":"Point"}
}