{
  "type": "Feature",
  "properties": {
    "iso:country":"US",
    "sg:address":"2985 S 300 W",
    "sg:city":"Salt Lake City",
    "sg:classifiers":[
        {
            "category":"Manufacturing",
            "subcategory":"Signs",
            "type":"Manufacturing & Wholesale Goods"
        }
    ],
    "sg:phone":"+1 801 463 6400",
    "sg:postcode":"84115",
    "sg:province":"UT",
    "sg:tags":[
        "mfg",
        "banner",
        "graphics"
    ],
    "wof:name":"Scribe Sign & Graphics Inc",
    "wof:placetype":"venue"
},
  "geometry": {"coordinates":[-111.899636,40.705908],"type":"Point"}
}