{
  "type": "Feature",
  "properties": {
    "iso:country":"US",
    "sg:address":"90 W 500 S",
    "sg:city":"Bountiful",
    "sg:classifiers":[
        {
            "category":"Professional",
            "subcategory":"Lawyer & Legal Services",
            "type":"Services"
        },
        {
            "category":"Professional",
            "subcategory":"Printing & Photocopies",
            "type":"Services"
        }
    ],
    "sg:phone":"+1 801 299 9995",
    "sg:postcode":"84010",
    "sg:province":"UT",
    "sg:tags":[
        "notary"
    ],
    "sg:website":"www.theupsstore.com",
    "wof:name":"Ups Store the",
    "wof:placetype":"venue"
},
  "geometry": {"coordinates":[-111.882004,40.884399],"type":"Point"}
}