{
  "type": "Feature",
  "properties": {
    "iso:country":"US",
    "sg:address":"3909 W 8700 S",
    "sg:city":"West Jordan",
    "sg:classifiers":[
        {
            "category":"Professional",
            "subcategory":"Engineering",
            "type":"Services"
        }
    ],
    "sg:phone":"+1 801 280 1953",
    "sg:postcode":"84088",
    "sg:province":"UT",
    "wof:name":"Anthon Engineering",
    "wof:placetype":"venue"
},
  "geometry": {"coordinates":[-111.984585,40.59337],"type":"Point"}
}