{
  "type": "Feature",
  "properties": {
    "iso:country":"US",
    "sg:address":"7684 S 4000 W",
    "sg:city":"Spanish Fork",
    "sg:classifiers":[
        {
            "category":"Freight",
            "type":"Transportation"
        }
    ],
    "sg:phone":"+1 801 798 1767",
    "sg:postcode":"84660",
    "sg:province":"UT",
    "sg:tags":[
        "trucking"
    ],
    "wof:name":"Penrod Custom Hauling",
    "wof:placetype":"venue"
},
  "geometry": {"coordinates":[-111.75044699999999,40.089506],"type":"Point"}
}