{
  "type": "Feature",
  "properties": {
    "iso:country":"US",
    "sg:address":"245 E Main St",
    "sg:city":"Elsinore",
    "sg:classifiers":[
        {
            "category":"Shopping",
            "type":"Retail Goods"
        }
    ],
    "sg:phone":"+1 435 527 3022",
    "sg:postcode":"84724",
    "sg:province":"UT",
    "sg:tags":[
        "ice"
    ],
    "wof:name":"Paradice Ice",
    "wof:placetype":"venue"
},
  "geometry": {"coordinates":[-112.14345,38.683193],"type":"Point"}
}