{
  "type": "Feature",
  "properties": {
    "iso:country":"US",
    "sg:address":"3646 S Redwood Rd",
    "sg:city":"Salt Lake City",
    "sg:classifiers":[
        {
            "category":"Organizations",
            "subcategory":"Non-profit Organization",
            "type":"Services"
        }
    ],
    "sg:phone":"+1 801 908 5600",
    "sg:postcode":"84119",
    "sg:province":"UT",
    "wof:name":"Fe Y Esperanza Grupo De",
    "wof:placetype":"venue"
},
  "geometry": {"coordinates":[-111.938976,40.696474],"type":"Point"}
}