{
  "type": "Feature",
  "properties": {
    "iso:country":"US",
    "sg:address":"510 E Main St",
    "sg:city":"Vernal",
    "sg:classifiers":[
        {
            "category":"Shopping",
            "subcategory":"Music",
            "type":"Retail Goods"
        }
    ],
    "sg:phone":"+1 435 789 4123",
    "sg:postcode":"84078",
    "sg:province":"UT",
    "wof:name":"Playback CD Exchange LLC",
    "wof:placetype":"venue"
},
  "geometry": {"coordinates":[-109.51890400000001,40.455766],"type":"Point"}
}