{
  "type": "Feature",
  "properties": {
    "iso:country":"US",
    "sg:address":"155 W 400 N",
    "sg:city":"Smithfield",
    "sg:classifiers":[
        {
            "category":"Organizations",
            "subcategory":"Religious Organization",
            "type":"Services"
        }
    ],
    "sg:phone":"+1 435 563 6044",
    "sg:postcode":"84335",
    "sg:province":"UT",
    "sg:tags":[
        "church"
    ],
    "wof:name":"Church Of Jesus Christ Of Lds",
    "wof:placetype":"venue"
},
  "geometry": {"coordinates":[-111.836789,41.845081],"type":"Point"}
}