{
  "type": "Feature",
  "properties": {
    "iso:country":"US",
    "sg:address":"151 W 2100 S",
    "sg:city":"Salt Lake City",
    "sg:classifiers":[
        {
            "category":"Wholesale",
            "subcategory":"Durable Goods & Equipment",
            "type":"Manufacturing & Wholesale Goods"
        }
    ],
    "sg:phone":"+1 801 483 2900",
    "sg:postcode":"84115",
    "sg:province":"UT",
    "sg:tags":[
        "importer"
    ],
    "wof:name":"Mae Jin Imports",
    "wof:placetype":"venue"
},
  "geometry": {"coordinates":[-111.89495599999999,40.725359],"type":"Point"}
}