{
  "type": "Feature",
  "properties": {
    "iso:country":"US",
    "sg:address":"3540 W 2600 N",
    "sg:city":"Smithfield",
    "sg:classifiers":[
        {
            "category":"Restaurant",
            "type":"Food & Drink"
        }
    ],
    "sg:phone":"+1 435 713 4738",
    "sg:postcode":"84335",
    "sg:province":"UT",
    "sg:tags":[
        "eating"
    ],
    "wof:name":"Ravenzis Italian Restaurant I",
    "wof:placetype":"venue"
},
  "geometry": {"coordinates":[-111.91318,41.780165],"type":"Point"}
}