{
  "type": "Feature",
  "properties": {
    "iso:country":"US",
    "sg:address":"4149 Riverdale Rd",
    "sg:city":"Ogden",
    "sg:classifiers":[
        {
            "category":"Manufacturing",
            "subcategory":"Printing",
            "type":"Manufacturing & Wholesale Goods"
        }
    ],
    "sg:phone":"+1 801 334 8663",
    "sg:postcode":"84405",
    "sg:province":"UT",
    "sg:tags":[
        "mfg"
    ],
    "wof:name":"Mind Your Memories Inc",
    "wof:placetype":"venue"
},
  "geometry": {"coordinates":[-111.984926,41.187167],"type":"Point"}
}