{
  "type": "Feature",
  "properties": {
    "iso:country":"US",
    "sg:address":"14 W 100 N",
    "sg:city":"Logan",
    "sg:classifiers":[
        {
            "category":"Professional",
            "subcategory":"Lawyer & Legal Services",
            "type":"Services"
        }
    ],
    "sg:phone":"+1 435 753 5933",
    "sg:postcode":"84321",
    "sg:province":"UT",
    "sg:tags":[
        "attorney"
    ],
    "wof:name":"Perry Malmberg & Perry",
    "wof:placetype":"venue"
},
  "geometry": {"coordinates":[-111.837288,41.733261],"type":"Point"}
}