{
  "type": "Feature",
  "properties": {
    "iso:country":"US",
    "sg:address":"4257 S 6115 W",
    "sg:city":"Salt Lake City",
    "sg:classifiers":[
        {
            "category":"Social Services",
            "subcategory":"Child Care",
            "type":"Services"
        }
    ],
    "sg:phone":"+1 801 969 7406",
    "sg:postcode":"84128",
    "sg:province":"UT",
    "sg:tags":[
        "day"
    ],
    "wof:name":"Catherine Wardle",
    "wof:placetype":"venue"
},
  "geometry": {"coordinates":[-112.03707199999999,40.678392],"type":"Point"}
}