{
  "type": "Feature",
  "properties": {
    "iso:country":"US",
    "sg:address":"1808 N 400 E",
    "sg:city":"Ogden",
    "sg:classifiers":[
        {
            "category":"Farming",
            "subcategory":"Farm",
            "type":"Manufacturing & Wholesale Goods"
        }
    ],
    "sg:phone":"+1 801 782 6350",
    "sg:postcode":"84414",
    "sg:province":"UT",
    "sg:tags":[
        "crop",
        "general"
    ],
    "wof:name":"Ned Woodfield",
    "wof:placetype":"venue"
},
  "geometry": {"coordinates":[-111.96891100000001,41.291041],"type":"Point"}
}