{
  "type": "Feature",
  "properties": {
    "iso:country":"US",
    "sg:address":"280 N 50 E",
    "sg:city":"Stockton",
    "sg:classifiers":[
        {
            "category":"Building & Trades",
            "subcategory":"Plumbing",
            "type":"Services"
        }
    ],
    "sg:phone":"+1 435 833 0185",
    "sg:postcode":"84071",
    "sg:province":"UT",
    "sg:tags":[
        "conditioning",
        "air",
        "system",
        "contractor"
    ],
    "wof:name":"Oly's Heating Air Conditioning",
    "wof:placetype":"venue"
},
  "geometry": {"coordinates":[-112.358408,40.455871],"type":"Point"}
}