{
  "type": "Feature",
  "properties": {
    "iso:country":"US",
    "sg:address":"421 W 900 N",
    "sg:city":"North Salt Lake",
    "sg:classifiers":[
        {
            "category":"Manufacturing",
            "subcategory":"Electronics",
            "type":"Manufacturing & Wholesale Goods"
        }
    ],
    "sg:phone":"+1 801 292 4999",
    "sg:postcode":"84054",
    "sg:province":"UT",
    "sg:tags":[
        "equipment",
        "electronic",
        "supply"
    ],
    "sg:website":"www.saltlakecable.com",
    "wof:name":"Salt Lake Cable & Harness",
    "wof:placetype":"venue"
},
  "geometry": {"coordinates":[-111.92087100000001,40.858312],"type":"Point"}
}