{
  "type": "Feature",
  "properties": {
    "iso:country":"US",
    "sg:address":"425 W 100 S",
    "sg:city":"Heber City",
    "sg:classifiers":[
        {
            "category":"Retail",
            "subcategory":"Auto Repair",
            "type":"Services"
        }
    ],
    "sg:phone":"+1 435 654 7009",
    "sg:postcode":"84032",
    "sg:province":"UT",
    "sg:tags":[
        "automotive"
    ],
    "wof:name":"G&S Automotive & Tow Service",
    "wof:placetype":"venue"
},
  "geometry": {"coordinates":[-111.42178199999999,40.506387],"type":"Point"}
}