{
  "type": "Feature",
  "properties": {
    "iso:country":"US",
    "sg:address":"55 N 200 W",
    "sg:city":"St George",
    "sg:classifiers":[
        {
            "category":"Professional",
            "subcategory":"Art Services",
            "type":"Services"
        }
    ],
    "sg:phone":"+1 435 688 9282",
    "sg:postcode":"84770",
    "sg:province":"UT",
    "sg:tags":[
        "commercial",
        "design"
    ],
    "wof:name":"Bright Ideas Graphic Design",
    "wof:placetype":"venue"
},
  "geometry": {"coordinates":[-113.58763500000001,37.108976],"type":"Point"}
}