{
  "type": "Feature",
  "properties": {
    "iso:country":"US",
    "sg:address":"1360 N 1000 W",
    "sg:city":"Tremonton",
    "sg:classifiers":[
        {
            "category":"Manufacturing",
            "subcategory":"Motor Vehicles & Parts",
            "type":"Manufacturing & Wholesale Goods"
        }
    ],
    "sg:phone":"+1 435 257 1000",
    "sg:postcode":"84337",
    "sg:province":"UT",
    "sg:tags":[
        "bag",
        "initiator",
        "mfg",
        "air"
    ],
    "wof:name":"Autoliv Tremonton Operations",
    "wof:placetype":"venue"
},
  "geometry": {"coordinates":[-112.18147999999999,41.728764],"type":"Point"}
}