{
  "type": "Feature",
  "properties": {
    "iso:country":"US",
    "sg:address":"700 W 800 N",
    "sg:city":"Orem",
    "sg:classifiers":[
        {
            "category":"Health Services",
            "subcategory":"Doctor",
            "type":"Services"
        }
    ],
    "sg:phone":"+1 801 431 0100",
    "sg:postcode":"84057",
    "sg:province":"UT",
    "sg:tags":[
        "physician",
        "surgeon"
    ],
    "wof:name":"Gordon George MD",
    "wof:placetype":"venue"
},
  "geometry": {"coordinates":[-111.715002,40.312018],"type":"Point"}
}