{
  "type": "Feature",
  "properties": {
    "iso:country":"US",
    "sg:address":"3226 S Main St",
    "sg:city":"Salt Lake City",
    "sg:classifiers":[
        {
            "category":"Banks & Credit Unions",
            "subcategory":"Bank",
            "type":"Services"
        }
    ],
    "sg:phone":"+1 801 487 0371",
    "sg:postcode":"84115",
    "sg:province":"UT",
    "wof:name":"Credit Union One",
    "wof:placetype":"venue"
},
  "geometry": {"coordinates":[-111.891199,40.700545],"type":"Point"}
}