{
  "type": "Feature",
  "properties": {
    "iso:country":"US",
    "sg:address":"8313 Van Buren St",
    "sg:city":"Midvale",
    "sg:classifiers":[
        {
            "category":"Professional",
            "subcategory":"Business Services",
            "type":"Services"
        }
    ],
    "sg:phone":"+1 801 565 4750",
    "sg:postcode":"84047",
    "sg:province":"UT",
    "sg:tags":[
        "photo",
        "studio",
        "portrait"
    ],
    "wof:name":"Suite Studio",
    "wof:placetype":"venue"
},
  "geometry": {"coordinates":[-111.897417,40.600176],"type":"Point"}
}