{
  "type": "Feature",
  "properties": {
    "iso:country":"US",
    "sg:address":"4180 S State St",
    "sg:city":"Murray",
    "sg:classifiers":[
        {
            "category":"Autos & Motor Vehicles",
            "subcategory":"Automobile Sales",
            "type":"Retail Goods"
        }
    ],
    "sg:phone":"+1 801 265 2609",
    "sg:postcode":"84107",
    "sg:province":"UT",
    "sg:tags":[
        "car",
        "used",
        "dealer"
    ],
    "wof:name":"Auto Image",
    "wof:placetype":"venue"
},
  "geometry": {"coordinates":[-111.88831999999999,40.680833],"type":"Point"}
}