{
  "type": "Feature",
  "properties": {
    "iso:country":"US",
    "sg:address":"1055 S Medical Dr",
    "sg:city":"Mount Pleasant",
    "sg:classifiers":[
        {
            "category":"Health Services",
            "subcategory":"Doctor",
            "type":"Services"
        }
    ],
    "sg:phone":"+1 435 462 3800",
    "sg:postcode":"84647",
    "sg:province":"UT",
    "wof:name":"Todd Lee DDS",
    "wof:placetype":"venue"
},
  "geometry": {"coordinates":[-111.461438,39.531487],"type":"Point"}
}