{
  "type": "Feature",
  "properties": {
    "iso:country":"US",
    "sg:address":"151 E 5600 S",
    "sg:city":"Murray",
    "sg:classifiers":[
        {
            "category":"Real Estate",
            "subcategory":"Real Estate Agent",
            "type":"Services"
        }
    ],
    "sg:phone":"+1 801 262 6654",
    "sg:postcode":"84107",
    "sg:province":"UT",
    "sg:tags":[
        "management"
    ],
    "wof:name":"PDT Management",
    "wof:placetype":"venue"
},
  "geometry": {"coordinates":[-111.885924,40.649262],"type":"Point"}
}