{
  "type": "Feature",
  "properties": {
    "iso:country":"US",
    "sg:address":"460 N State St",
    "sg:city":"La Verkin",
    "sg:classifiers":[
        {
            "category":"Autos & Motor Vehicles",
            "subcategory":"Fuel & Gas Station",
            "type":"Retail Goods"
        }
    ],
    "sg:phone":"+1 435 635 8544",
    "sg:postcode":"84745",
    "sg:province":"UT",
    "sg:tags":[
        "station",
        "gasoline"
    ],
    "wof:name":"Laverkin Chevron",
    "wof:placetype":"venue"
},
  "geometry": {"coordinates":[-113.27206200000001,37.209311],"type":"Point"}
}