{
  "type": "Feature",
  "properties": {
    "iso:country":"US",
    "sg:address":"4381 Highland Dr",
    "sg:city":"Salt Lake City",
    "sg:classifiers":[
        {
            "category":"Personal",
            "type":"Services"
        }
    ],
    "sg:phone":"+1 801 272 1643",
    "sg:postcode":"84124",
    "sg:province":"UT",
    "sg:tags":[
        "therapist",
        "massage"
    ],
    "wof:name":"Enchanted Oasis Therapeutic",
    "wof:placetype":"venue"
},
  "geometry": {"coordinates":[-111.84233399999999,40.676684],"type":"Point"}
}