{
  "type": "Feature",
  "properties": {
    "iso:country":"US",
    "sg:address":"307 N 300 W",
    "sg:city":"Kaysville",
    "sg:classifiers":[
        {
            "category":"Professional",
            "subcategory":"Management & Consulting",
            "type":"Services"
        }
    ],
    "sg:phone":"+1 801 547 0809",
    "sg:postcode":"84037",
    "sg:province":"UT",
    "sg:tags":[
        "consultant",
        "business"
    ],
    "wof:name":"AHACPA",
    "wof:placetype":"venue"
},
  "geometry": {"coordinates":[-111.944042,41.041006],"type":"Point"}
}