{
  "type": "Feature",
  "properties": {
    "iso:country":"US",
    "sg:address":"4635 W 2200 S",
    "sg:city":"Ogden",
    "sg:classifiers":[
        {
            "category":"Professional",
            "type":"Services"
        }
    ],
    "sg:phone":"+1 801 731 1684",
    "sg:postcode":"84401",
    "sg:province":"UT",
    "wof:name":"Gibson & Son Inc",
    "wof:placetype":"venue"
},
  "geometry": {"coordinates":[-112.088769,41.227223],"type":"Point"}
}