{
  "type": "Feature",
  "properties": {
    "iso:country":"US",
    "sg:address":"1230 N Mountain View Dr",
    "sg:city":"Dammeron Valley",
    "sg:classifiers":[
        {
            "category":"Wholesale",
            "subcategory":"Hardware",
            "type":"Manufacturing & Wholesale Goods"
        }
    ],
    "sg:phone":"+1 435 574 3561",
    "sg:postcode":"84783",
    "sg:province":"UT",
    "wof:name":"Toolrunner Inc",
    "wof:placetype":"venue"
},
  "geometry": {"coordinates":[-113.662183,37.306869],"type":"Point"}
}