{
  "type": "Feature",
  "properties": {
    "iso:country":"US",
    "sg:address":"629 E 1000 S",
    "sg:city":"American Fork",
    "sg:classifiers":[
        {
            "category":"Autos & Motor Vehicles",
            "subcategory":"Automobile Sales",
            "type":"Retail Goods"
        }
    ],
    "sg:phone":"+1 801 756 3533",
    "sg:postcode":"84003",
    "sg:province":"UT",
    "sg:tags":[
        "new",
        "used"
    ],
    "sg:website":"www.gregorypontiac.com",
    "wof:name":"Gregory Pontiac Buick GMC Trck",
    "wof:placetype":"venue"
},
  "geometry": {"coordinates":[-111.7851,40.357203],"type":"Point"}
}