{
  "type": "Feature",
  "properties": {
    "iso:country":"US",
    "sg:address":"920 Woodoak Ln",
    "sg:city":"Salt Lake City",
    "sg:classifiers":[
        {
            "category":"Banks & Credit Unions",
            "subcategory":"Bank",
            "type":"Services"
        }
    ],
    "sg:phone":"+1 801 262 1655",
    "sg:postcode":"84117",
    "sg:province":"UT",
    "sg:tags":[
        "mortgage",
        "personal",
        "loan",
        "real estate"
    ],
    "wof:name":"Lending Group",
    "wof:placetype":"venue"
},
  "geometry": {"coordinates":[-111.864521,40.653217],"type":"Point"}
}