{
  "type": "Feature",
  "properties": {
    "iso:country":"US",
    "sg:address":"446 Douglas St",
    "sg:city":"Salt Lake City",
    "sg:classifiers":[
        {
            "category":"Professional",
            "subcategory":"Business Services",
            "type":"Services"
        }
    ],
    "sg:phone":"+1 801 582 0777",
    "sg:postcode":"84102",
    "sg:province":"UT",
    "wof:name":"Bjr Design",
    "wof:placetype":"venue"
},
  "geometry": {"coordinates":[-111.85539,40.75951],"type":"Point"}
}