{
  "type": "Feature",
  "properties": {
    "iso:country":"US",
    "sg:address":"4091 W 3500 S",
    "sg:city":"West Valley",
    "sg:classifiers":[
        {
            "category":"Shopping",
            "subcategory":"Pharmacy",
            "type":"Retail Goods"
        }
    ],
    "sg:phone":"+1 801 957 7333",
    "sg:postcode":"84120",
    "sg:province":"UT",
    "wof:name":"Smith's Food & Drug Ctr",
    "wof:placetype":"venue"
},
  "geometry": {"coordinates":[-111.988553,40.696529],"type":"Point"}
}