{
  "type": "Feature",
  "properties": {
    "iso:country":"US",
    "sg:address":"1641 Binford St",
    "sg:city":"Ogden",
    "sg:classifiers":[
        {
            "category":"Organizations",
            "subcategory":"Labor Organization",
            "type":"Services"
        }
    ],
    "sg:phone":"+1 801 334 5663",
    "sg:postcode":"84401",
    "sg:province":"UT",
    "wof:name":"Apple Eye Lc",
    "wof:placetype":"venue"
},
  "geometry": {"coordinates":[-111.935627,41.216976],"type":"Point"}
}