{
  "type": "Feature",
  "properties": {
    "iso:country":"US",
    "sg:address":"7665 Main St",
    "sg:city":"Midvale",
    "sg:classifiers":[
        {
            "category":"Banks & Credit Unions",
            "subcategory":"Investment Brokerage",
            "type":"Services"
        }
    ],
    "sg:phone":"+1 801 208 5050",
    "sg:postcode":"84047",
    "sg:province":"UT",
    "sg:tags":[
        "merger",
        "acquisition"
    ],
    "sg:website":"www.cchi.net",
    "wof:name":"Clear Capital Holdings Inc",
    "wof:placetype":"venue"
},
  "geometry": {"coordinates":[-111.910222,40.611969],"type":"Point"}
}