{
  "type": "Feature",
  "properties": {
    "iso:country":"US",
    "sg:address":"852 W Hill Field Rd",
    "sg:city":"Layton",
    "sg:classifiers":[
        {
            "category":"Autos & Motor Vehicles",
            "subcategory":"Auto Supplies",
            "type":"Retail Goods"
        },
        {
            "category":"Wholesale",
            "subcategory":"Electrical",
            "type":"Manufacturing & Wholesale Goods"
        }
    ],
    "sg:phone":"+1 801 544 7111",
    "sg:postcode":"84041",
    "sg:province":"UT",
    "sg:tags":[
        "battery"
    ],
    "wof:name":"Batteries Plus",
    "wof:placetype":"venue"
},
  "geometry": {"coordinates":[-111.980909,41.103659],"type":"Point"}
}