{
  "type": "Feature",
  "properties": {
    "iso:country":"US",
    "sg:address":"1836 N 2500 W",
    "sg:city":"St George",
    "sg:classifiers":[
        {
            "category":"Freight",
            "type":"Transportation"
        }
    ],
    "sg:phone":"+1 435 628 4833",
    "sg:postcode":"84770",
    "sg:province":"UT",
    "sg:tags":[
        "operator",
        "local",
        "trucking"
    ],
    "wof:name":"Kelly Atkin Services LLC",
    "wof:placetype":"venue"
},
  "geometry": {"coordinates":[-113.63712599999999,37.140146],"type":"Point"}
}