{
  "type": "Feature",
  "properties": {
    "iso:country":"US",
    "sg:address":"1115 S 200 E",
    "sg:city":"Wellsville",
    "sg:classifiers":[
        {
            "category":"Social Services",
            "subcategory":"Child Care",
            "type":"Services"
        }
    ],
    "sg:phone":"+1 435 245 4200",
    "sg:postcode":"84339",
    "sg:province":"UT",
    "sg:tags":[
        "day"
    ],
    "wof:name":"Cooper Terri Day Care",
    "wof:placetype":"venue"
},
  "geometry": {"coordinates":[-111.92986399999999,41.615744],"type":"Point"}
}