{
  "type": "Feature",
  "properties": {
    "iso:country":"US",
    "sg:address":"4000 S Redwood Rd",
    "sg:city":"Salt Lake City",
    "sg:classifiers":[
        {
            "category":"Personal",
            "type":"Services"
        }
    ],
    "sg:phone":"+1 801 401 8601",
    "sg:postcode":"84123",
    "sg:province":"UT",
    "wof:name":"Arising Spirits Massage",
    "wof:placetype":"venue"
},
  "geometry": {"coordinates":[-111.93888,40.682121],"type":"Point"}
}