{
  "type": "Feature",
  "properties": {
    "iso:country":"US",
    "sg:address":"195 S Bluff St",
    "sg:city":"St George",
    "sg:classifiers":[
        {
            "category":"Restaurant",
            "type":"Food & Drink"
        }
    ],
    "sg:phone":"+1 435 673 0068",
    "sg:postcode":"84770",
    "sg:province":"UT",
    "sg:tags":[
        "eating"
    ],
    "wof:name":"China Palace",
    "wof:placetype":"venue"
},
  "geometry": {"coordinates":[-113.592856,37.104912],"type":"Point"}
}