{
  "type": "Feature",
  "properties": {
    "iso:country":"US",
    "sg:address":"1155 W Riverdale Rd",
    "sg:city":"Ogden",
    "sg:classifiers":[
        {
            "category":"Restaurant",
            "type":"Food & Drink"
        }
    ],
    "sg:menulink":"http://www.allmenus.com/ut/ogden/135954-jamba-juice/menu/",
    "sg:phone":"+1 801 399 4333",
    "sg:postcode":"84405",
    "sg:province":"UT",
    "sg:tags":[
        "smoothy",
        "juice",
        "american"
    ],
    "wof:name":"Jamba Juice",
    "wof:placetype":"venue"
},
  "geometry": {"coordinates":[-112.00797799999999,41.175513],"type":"Point"}
}