{
  "type": "Feature",
  "properties": {
    "iso:country":"US",
    "sg:address":"2504 W 14400 S",
    "sg:city":"Riverton",
    "sg:classifiers":[
        {
            "category":"Building & Trades",
            "subcategory":"Construction",
            "type":"Services"
        }
    ],
    "sg:phone":"+1 801 254 5290",
    "sg:postcode":"84065",
    "sg:province":"UT",
    "sg:tags":[
        "general",
        "contractor"
    ],
    "wof:name":"Shaw Homes Inc",
    "wof:placetype":"venue"
},
  "geometry": {"coordinates":[-111.95355000000001,40.489685],"type":"Point"}
}