{
  "type": "Feature",
  "properties": {
    "iso:country":"US",
    "sg:address":"1635 N 200 E",
    "sg:city":"Logan",
    "sg:classifiers":[
        {
            "category":"Personal",
            "subcategory":"Beauty Salon",
            "type":"Services"
        }
    ],
    "sg:phone":"+1 435 787 9477",
    "sg:postcode":"84341",
    "sg:province":"UT",
    "sg:tags":[
        "shop"
    ],
    "wof:name":"Swiss Renaissance Salon & Spa",
    "wof:placetype":"venue"
},
  "geometry": {"coordinates":[-111.82893199999999,41.763333],"type":"Point"}
}