{
  "type": "Feature",
  "properties": {
    "iso:country":"US",
    "sg:address":"1800 S 400 E",
    "sg:city":"Salt Lake City",
    "sg:classifiers":[
        {
            "category":"Building & Trades",
            "subcategory":"Construction",
            "type":"Services"
        }
    ],
    "sg:phone":"+1 801 733 6841",
    "sg:postcode":"84115",
    "sg:province":"UT",
    "sg:tags":[
        "house"
    ],
    "wof:name":"Pennington Construction Inc",
    "wof:placetype":"venue"
},
  "geometry": {"coordinates":[-111.879698,40.730928],"type":"Point"}
}