{
  "type": "Feature",
  "properties": {
    "iso:country":"US",
    "sg:address":"833 Coventry Ln",
    "sg:city":"Alpine",
    "sg:classifiers":[
        {
            "category":"Banks & Credit Unions",
            "subcategory":"Financial Services",
            "type":"Services"
        }
    ],
    "sg:phone":"+1 801 763 7990",
    "sg:postcode":"84004",
    "sg:province":"UT",
    "sg:tags":[
        "trust",
        "nonprofit",
        "management"
    ],
    "wof:name":"Roberts Family Foundation",
    "wof:placetype":"venue"
},
  "geometry": {"coordinates":[-111.76435600000001,40.463017],"type":"Point"}
}