{
  "type": "Feature",
  "properties": {
    "iso:country":"US",
    "sg:address":"2940 N 900 E",
    "sg:city":"Kamas",
    "sg:classifiers":[
        {
            "category":"Professional",
            "type":"Services"
        }
    ],
    "sg:phone":"+1 435 783 2334",
    "sg:postcode":"84036",
    "sg:province":"UT",
    "wof:name":"Weller Entps A Ltd Partnershi",
    "wof:placetype":"venue"
},
  "geometry": {"coordinates":[-111.26254400000001,40.687642],"type":"Point"}
}