{
  "type": "Feature",
  "properties": {
    "iso:country":"US",
    "sg:address":"252 S 900 E",
    "sg:city":"Payson",
    "sg:classifiers":[
        {
            "category":"Real Estate",
            "subcategory":"Real Estate Operator",
            "type":"Services"
        }
    ],
    "sg:phone":"+1 801 465 3885",
    "sg:postcode":"84651",
    "sg:province":"UT",
    "sg:tags":[
        "apartment"
    ],
    "wof:name":"Mountainview Apartments",
    "wof:placetype":"venue"
},
  "geometry": {"coordinates":[-111.717679,40.040822],"type":"Point"}
}