{
  "type": "Feature",
  "properties": {
    "iso:country":"US",
    "sg:address":"369 W 1300 N",
    "sg:city":"Clearfield",
    "sg:classifiers":[
        {
            "category":"Personal",
            "type":"Services"
        }
    ],
    "sg:phone":"+1 801 776 1900",
    "sg:postcode":"84015",
    "sg:province":"UT",
    "sg:tags":[
        "hair",
        "replacement"
    ],
    "sg:website":"www.symetrix.com",
    "wof:name":"Symetrix Hair Design",
    "wof:placetype":"venue"
},
  "geometry": {"coordinates":[-112.03368500000001,41.132524],"type":"Point"}
}