{
  "type": "Feature",
  "properties": {
    "iso:country":"US",
    "sg:address":"5965 Woodland Dr",
    "sg:city":"Ogden",
    "sg:classifiers":[
        {
            "category":"Professional",
            "subcategory":"Business Services",
            "type":"Services"
        }
    ],
    "sg:phone":"+1 801 476 6984",
    "sg:postcode":"84403",
    "sg:province":"UT",
    "wof:name":"Turfhead Landscape & Design In",
    "wof:placetype":"venue"
},
  "geometry": {"coordinates":[-111.91219100000001,41.154743],"type":"Point"}
}