{
  "type": "Feature",
  "properties": {
    "iso:country":"US",
    "sg:address":"449 E 1200 N",
    "sg:city":"Layton",
    "sg:classifiers":[
        {
            "category":"Personal",
            "type":"Services"
        }
    ],
    "sg:phone":"+1 801 546 2370",
    "sg:postcode":"84041",
    "sg:province":"UT",
    "wof:name":"Health Promoting Massage",
    "wof:placetype":"venue"
},
  "geometry": {"coordinates":[-111.958585,41.077531],"type":"Point"}
}