{
  "type": "Feature",
  "properties": {
    "iso:country":"US",
    "sg:address":"895 Raintree Cir",
    "sg:city":"Woods Cross",
    "sg:classifiers":[
        {
            "category":"Home & Garden",
            "subcategory":"Building Materials",
            "type":"Retail Goods"
        }
    ],
    "sg:phone":"+1 801 295 8550",
    "sg:postcode":"84087",
    "sg:province":"UT",
    "sg:tags":[
        "glass",
        "window",
        "plate"
    ],
    "wof:name":"Windshields Of Utah",
    "wof:placetype":"venue"
},
  "geometry": {"coordinates":[-111.904641,40.89924],"type":"Point"}
}