{
  "type": "Feature",
  "properties": {
    "iso:country":"US",
    "sg:address":"2430 W 5550 N",
    "sg:city":"Cedar City",
    "sg:classifiers":[
        {
            "category":"Freight",
            "type":"Transportation"
        }
    ],
    "sg:phone":"+1 435 586 4822",
    "sg:postcode":"84720",
    "sg:province":"UT",
    "sg:tags":[
        "car",
        "pilot"
    ],
    "wof:name":"Z Power Escort",
    "wof:placetype":"venue"
},
  "geometry": {"coordinates":[-113.095557,37.778874],"type":"Point"}
}