{
  "type": "Feature",
  "properties": {
    "iso:country":"US",
    "sg:address":"3185 N 675 E",
    "sg:city":"Layton",
    "sg:classifiers":[
        {
            "category":"Wholesale",
            "subcategory":"Machinery & Supplies",
            "type":"Manufacturing & Wholesale Goods"
        }
    ],
    "sg:phone":"+1 801 771 8075",
    "sg:postcode":"84041",
    "sg:province":"UT",
    "sg:tags":[
        "truck"
    ],
    "wof:name":"B & D Lift Trucks Inc",
    "wof:placetype":"venue"
},
  "geometry": {"coordinates":[-111.95401699999999,41.105353],"type":"Point"}
}