{
  "type": "Feature",
  "properties": {
    "iso:country":"US",
    "sg:address":"12930 S 300 E",
    "sg:city":"Draper",
    "sg:classifiers":[
        {
            "category":"Building & Trades",
            "subcategory":"Construction",
            "type":"Services"
        }
    ],
    "sg:phone":"+1 801 571 5545",
    "sg:postcode":"84020",
    "sg:province":"UT",
    "sg:tags":[
        "house"
    ],
    "wof:name":"P R Marketing",
    "wof:placetype":"venue"
},
  "geometry": {"coordinates":[-111.881753,40.517265],"type":"Point"}
}