{
  "type": "Feature",
  "properties": {
    "iso:country":"US",
    "sg:address":"3675 Driftwood Ln",
    "sg:city":"Cedar City",
    "sg:classifiers":[
        {
            "category":"Building & Trades",
            "subcategory":"Construction",
            "type":"Services"
        }
    ],
    "sg:phone":"+1 435 586 9160",
    "sg:postcode":"84720",
    "sg:province":"UT",
    "sg:tags":[
        "general",
        "contractor"
    ],
    "wof:name":"Didier Construction Inc",
    "wof:placetype":"venue"
},
  "geometry": {"coordinates":[-113.066338,37.744434],"type":"Point"}
}