{
  "type": "Feature",
  "properties": {
    "iso:country":"US",
    "sg:address":"1355 Foothill Dr",
    "sg:city":"Salt Lake City",
    "sg:classifiers":[
        {
            "category":"Insurance",
            "subcategory":"Insurance Agent",
            "type":"Services"
        }
    ],
    "sg:phone":"+1 801 582 5200",
    "sg:postcode":"84108",
    "sg:province":"UT",
    "wof:name":"State Farm Insurance",
    "wof:placetype":"venue"
},
  "geometry": {"coordinates":[-111.82602199999999,40.740511],"type":"Point"}
}