{
  "type": "Feature",
  "properties": {
    "iso:country":"US",
    "sg:address":"236 S 300 E",
    "sg:city":"Salt Lake City",
    "sg:classifiers":[
        {
            "category":"Manufacturing",
            "subcategory":"Printing",
            "type":"Manufacturing & Wholesale Goods"
        }
    ],
    "sg:phone":"+1 801 532 6267",
    "sg:postcode":"84111",
    "sg:province":"UT",
    "sg:tags":[
        "publisher"
    ],
    "sg:website":"www.thechristmasbox.com",
    "wof:name":"Richard P Evans Publishing Inc",
    "wof:placetype":"venue"
},
  "geometry": {"coordinates":[-111.882577,40.763625],"type":"Point"}
}