{
  "type": "Feature",
  "properties": {
    "iso:country":"US",
    "sg:address":"2108 Indiana Cir",
    "sg:city":"Salt Lake City",
    "sg:classifiers":[
        {
            "category":"Freight",
            "type":"Transportation"
        }
    ],
    "sg:phone":"+1 801 974 1982",
    "sg:postcode":"84104",
    "sg:province":"UT",
    "sg:tags":[
        "operator",
        "trucking"
    ],
    "wof:name":"Mel Flinders Trucking",
    "wof:placetype":"venue"
},
  "geometry": {"coordinates":[-111.949884,40.751286],"type":"Point"}
}