{
  "type": "Feature",
  "properties": {
    "iso:country":"US",
    "sg:address":"1500 W 1000 S",
    "sg:city":"Orem",
    "sg:classifiers":[
        {
            "category":"Government",
            "subcategory":"Office",
            "type":"Public Place"
        }
    ],
    "sg:phone":"+1 801 221 0192",
    "sg:postcode":"84058",
    "sg:province":"UT",
    "sg:tags":[
        "agency"
    ],
    "sg:website":"www.cuwcd.com",
    "wof:name":"Central Utah Water Conservancy",
    "wof:placetype":"venue"
},
  "geometry": {"coordinates":[-111.732527,40.279063],"type":"Point"}
}