{
  "type": "Feature",
  "properties": {
    "iso:country":"US",
    "sg:address":"2358 S 5600 W",
    "sg:city":"Salt Lake City",
    "sg:classifiers":[
        {
            "category":"Professional",
            "subcategory":"Business Services",
            "type":"Services"
        }
    ],
    "sg:phone":"+1 801 975 9828",
    "sg:postcode":"84120",
    "sg:province":"UT",
    "wof:name":"Wasatch Towing",
    "wof:placetype":"venue"
},
  "geometry": {"coordinates":[-112.024976,40.717594],"type":"Point"}
}