{
  "type": "Feature",
  "properties": {
    "iso:country":"US",
    "sg:address":"3098 Highland Dr",
    "sg:city":"Salt Lake City",
    "sg:classifiers":[
        {
            "category":"Social Services",
            "type":"Services"
        }
    ],
    "sg:phone":"+1 801 467 6255",
    "sg:postcode":"84106",
    "sg:province":"UT",
    "sg:tags":[
        "counselor",
        "marriage",
        "family"
    ],
    "wof:name":"Affiliated Pshchotherapists",
    "wof:placetype":"venue"
},
  "geometry": {"coordinates":[-111.85217299999999,40.703617],"type":"Point"}
}