{
  "type": "Feature",
  "properties": {
    "iso:country":"US",
    "sg:address":"2020 S Main St",
    "sg:city":"Salt Lake City",
    "sg:classifiers":[
        {
            "category":"Wholesale",
            "subcategory":"Hardware",
            "type":"Manufacturing & Wholesale Goods"
        }
    ],
    "sg:phone":"+1 801 474 1333",
    "sg:postcode":"84115",
    "sg:province":"UT",
    "sg:tags":[
        "plumbing",
        "merchandise"
    ],
    "wof:name":"Sharp Water Solutions",
    "wof:placetype":"venue"
},
  "geometry": {"coordinates":[-111.891159,40.725565],"type":"Point"}
}