{
  "type": "Feature",
  "properties": {
    "iso:country":"US",
    "sg:address":"5181 Amelia Earhart Dr",
    "sg:city":"Salt Lake City",
    "sg:classifiers":[
        {
            "category":"Communications",
            "subcategory":"Television Station",
            "type":"Services"
        }
    ],
    "sg:phone":"+1 801 537 1414",
    "sg:postcode":"84116",
    "sg:province":"UT",
    "sg:tags":[
        "broadcasting",
        "co"
    ],
    "sg:website":"www.kjzz.com",
    "wof:name":"KJZZ",
    "wof:placetype":"venue"
},
  "geometry": {"coordinates":[-112.016108,40.776317],"type":"Point"}
}