{
  "type": "Feature",
  "properties": {
    "iso:country":"US",
    "sg:address":"419 E 1790 N",
    "sg:city":"Pleasant Grove",
    "sg:classifiers":[
        {
            "category":"Wholesale",
            "subcategory":"Medical Equipment & Supplies",
            "type":"Manufacturing & Wholesale Goods"
        },
        {
            "category":"Health Services",
            "subcategory":"Clinic",
            "type":"Services"
        }
    ],
    "sg:phone":"+1 801 796 6229",
    "sg:postcode":"84062",
    "sg:province":"UT",
    "sg:tags":[
        "physician",
        "surgeon"
    ],
    "wof:name":"Crestline Medical LLC",
    "wof:placetype":"venue"
},
  "geometry": {"coordinates":[-111.732743,40.382874],"type":"Point"}
}