{
  "type": "Feature",
  "properties": {
    "iso:country":"US",
    "sg:address":"1787 W 5300 N",
    "sg:city":"St George",
    "sg:classifiers":[
        {
            "category":"Shopping",
            "subcategory":"Discount & Variety Stores",
            "type":"Retail Goods"
        }
    ],
    "sg:phone":"+1 435 986 3620",
    "sg:postcode":"84770",
    "sg:province":"UT",
    "sg:tags":[
        "merchandise",
        "general"
    ],
    "wof:name":"Kiosa",
    "wof:placetype":"venue"
},
  "geometry": {"coordinates":[-113.622192,37.200886],"type":"Point"}
}