{
  "type": "Feature",
  "properties": {
    "iso:country":"US",
    "sg:address":"50 E 500 N",
    "sg:city":"Provo",
    "sg:classifiers":[
        {
            "category":"Professional",
            "subcategory":"Art Services",
            "type":"Services"
        }
    ],
    "sg:phone":"+1 801 367 2828",
    "sg:postcode":"84606",
    "sg:province":"UT",
    "sg:tags":[
        "photography",
        "commercial"
    ],
    "wof:name":"Code Red Photography",
    "wof:placetype":"venue"
},
  "geometry": {"coordinates":[-111.657527,40.240303],"type":"Point"}
}