{
  "type": "Feature",
  "properties": {
    "iso:country":"US",
    "sg:address":"70 E State Rd",
    "sg:city":"Pleasant Grove",
    "sg:classifiers":[
        {
            "category":"Personal",
            "subcategory":"Beauty Salon",
            "type":"Services"
        }
    ],
    "sg:phone":"+1 801 785 2871",
    "sg:postcode":"84062",
    "sg:province":"UT",
    "wof:name":"Roberts Beauty Salon",
    "wof:placetype":"venue"
},
  "geometry": {"coordinates":[-111.739362,40.358243],"type":"Point"}
}