{
  "type": "Feature",
  "properties": {
    "iso:country":"US",
    "sg:address":"757 State Hwy 193",
    "sg:city":"Layton",
    "sg:classifiers":[
        {
            "category":"Building & Trades",
            "subcategory":"Construction",
            "type":"Services"
        }
    ],
    "sg:phone":"+1 801 771 0954",
    "sg:postcode":"84041",
    "sg:province":"UT",
    "sg:tags":[
        "repairing",
        "remodeling",
        "contractor"
    ],
    "wof:name":"Westcoast Construction",
    "wof:placetype":"venue"
},
  "geometry": {"coordinates":[-111.952444,41.102897],"type":"Point"}
}