{
  "type": "Feature",
  "properties": {
    "iso:country":"US",
    "sg:address":"11187 Wyngate Ln",
    "sg:city":"Sandy",
    "sg:classifiers":[
        {
            "category":"Building & Trades",
            "subcategory":"Construction",
            "type":"Services"
        }
    ],
    "sg:phone":"+1 801 571 9582",
    "sg:postcode":"84092",
    "sg:province":"UT",
    "sg:tags":[
        "house"
    ],
    "wof:name":"Eckman & Mitchell Cnstr LLC",
    "wof:placetype":"venue"
},
  "geometry": {"coordinates":[-111.834924,40.548273],"type":"Point"}
}