{
  "type": "Feature",
  "properties": {
    "iso:country":"US",
    "sg:address":"454 N Flint St",
    "sg:city":"Kaysville",
    "sg:classifiers":[
        {
            "category":"Building & Trades",
            "subcategory":"Cleaning & Sanitation",
            "type":"Services"
        }
    ],
    "sg:phone":"+1 801 543 1350",
    "sg:postcode":"84037",
    "sg:province":"UT",
    "sg:tags":[
        "maintenance"
    ],
    "wof:name":"Afterhours Maintenance",
    "wof:placetype":"venue"
},
  "geometry": {"coordinates":[-111.965526,41.042186],"type":"Point"}
}