{
  "type": "Feature",
  "properties": {
    "iso:country":"US",
    "sg:address":"8969 S 2700 W",
    "sg:city":"West Jordan",
    "sg:classifiers":[
        {
            "category":"Health Services",
            "subcategory":"Health Practitioner",
            "type":"Services"
        }
    ],
    "sg:phone":"+1 801 561 1061",
    "sg:postcode":"84088",
    "sg:province":"UT",
    "wof:name":"David L Wetzel",
    "wof:placetype":"venue"
},
  "geometry": {"coordinates":[-111.957763,40.589582],"type":"Point"}
}