{
  "type": "Feature",
  "properties": {
    "iso:country":"US",
    "sg:address":"707 W 700 S Ste 101",
    "sg:city":"Woods Cross",
    "sg:classifiers":[
        {
            "category":"Insurance",
            "subcategory":"Hazard Insurance",
            "type":"Services"
        }
    ],
    "sg:phone":"+1 801 292 4511",
    "sg:postcode":"84087",
    "sg:province":"UT",
    "sg:website":"insuranceaai.com",
    "wof:name":"American Affordable Insurance",
    "wof:placetype":"venue"
},
  "geometry": {"coordinates":[-111.900053,40.882397],"type":"Point"}
}