{
  "type": "Feature",
  "properties": {
    "iso:country":"US",
    "sg:address":"5899 S Sesame St",
    "sg:city":"Salt Lake City",
    "sg:classifiers":[
        {
            "category":"Building & Trades",
            "subcategory":"Construction",
            "type":"Services"
        }
    ],
    "sg:phone":"+1 801 256 0909",
    "sg:postcode":"84118",
    "sg:province":"UT",
    "sg:tags":[
        "television",
        "telephone",
        "cable",
        "contractor"
    ],
    "wof:name":"Westel",
    "wof:placetype":"venue"
},
  "geometry": {"coordinates":[-111.96068699999999,40.643561],"type":"Point"}
}