{
  "type": "Feature",
  "properties": {
    "iso:country":"US",
    "sg:address":"638 Wilmington Ave",
    "sg:city":"Salt Lake City",
    "sg:classifiers":[
        {
            "category":"Social Services",
            "type":"Services"
        }
    ],
    "sg:phone":"+1 801 486 3778",
    "sg:postcode":"84106",
    "sg:province":"UT",
    "sg:tags":[
        "development",
        "society",
        "state",
        "for",
        "welfare"
    ],
    "sg:website":"www.eastersealsutah.org",
    "wof:name":"Easter Seals Utah",
    "wof:placetype":"venue"
},
  "geometry": {"coordinates":[-111.873569,40.723242],"type":"Point"}
}