{
  "type": "Feature",
  "properties": {
    "iso:country":"US",
    "sg:address":"1702 S Main St",
    "sg:city":"Salt Lake City",
    "sg:classifiers":[
        {
            "category":"Restaurant",
            "type":"Food & Drink"
        }
    ],
    "sg:phone":"+1 801 466 9656",
    "sg:postcode":"84115",
    "sg:province":"UT",
    "wof:name":"Mr Sinaola's Restaurant",
    "wof:placetype":"venue"
},
  "geometry": {"coordinates":[-111.891139,40.731814],"type":"Point"}
}