{
  "type": "Feature",
  "properties": {
    "iso:country":"US",
    "sg:address":"102 W 500 S",
    "sg:city":"Manti",
    "sg:classifiers":[
        {
            "category":"Shopping",
            "subcategory":"Bicycles & Sporting Goods",
            "type":"Retail Goods"
        }
    ],
    "sg:phone":"+1 435 835 5332",
    "sg:postcode":"84642",
    "sg:province":"UT",
    "wof:name":"Skyline Stick Custom Bows",
    "wof:placetype":"venue"
},
  "geometry": {"coordinates":[-111.640748,39.258258],"type":"Point"}
}