{
  "type": "Feature",
  "properties": {
    "iso:country":"US",
    "sg:address":"325 Ash Cir",
    "sg:city":"Woodland Hills",
    "sg:classifiers":[
        {
            "category":"Professional",
            "subcategory":"Business Services",
            "type":"Services"
        }
    ],
    "sg:phone":"+1 801 423 2123",
    "sg:postcode":"84653",
    "sg:province":"UT",
    "sg:tags":[
        "interior",
        "consultant",
        "design",
        "decorator"
    ],
    "wof:name":"Design It Consultants",
    "wof:placetype":"venue"
},
  "geometry": {"coordinates":[-111.660449,40.028504],"type":"Point"}
}