{
  "type": "Feature",
  "properties": {
    "iso:country":"US",
    "sg:address":"900 N 400 W",
    "sg:city":"North Salt Lake",
    "sg:classifiers":[
        {
            "category":"Building & Trades",
            "subcategory":"Construction",
            "type":"Services"
        }
    ],
    "sg:phone":"+1 801 298 0406",
    "sg:postcode":"84054",
    "sg:province":"UT",
    "sg:tags":[
        "designer"
    ],
    "sg:website":"www.metropolisdesign.com",
    "wof:name":"Metropolis Design",
    "wof:placetype":"venue"
},
  "geometry": {"coordinates":[-111.920565,40.861635],"type":"Point"}
}