{
  "type": "Feature",
  "properties": {
    "iso:country":"US",
    "sg:address":"3340 S 300 W",
    "sg:city":"Salt Lake City",
    "sg:classifiers":[
        {
            "category":"Wholesale",
            "subcategory":"Computers",
            "type":"Manufacturing & Wholesale Goods"
        }
    ],
    "sg:phone":"+1 801 972 9464",
    "sg:postcode":"84115",
    "sg:province":"UT",
    "wof:name":"Micro Net Distribution",
    "wof:placetype":"venue"
},
  "geometry": {"coordinates":[-111.899805,40.699616],"type":"Point"}
}