{
  "type": "Feature",
  "properties": {
    "iso:country":"US",
    "sg:address":"514 E 1950 N",
    "sg:city":"Orem",
    "sg:classifiers":[
        {
            "category":"Organizations",
            "subcategory":"Labor Organization",
            "type":"Services"
        }
    ],
    "sg:phone":"+1 801 224 9298",
    "sg:postcode":"84097",
    "sg:province":"UT",
    "wof:name":"Red Cedar Properties LLC",
    "wof:placetype":"venue"
},
  "geometry": {"coordinates":[-111.68411399999999,40.33279],"type":"Point"}
}