{
  "type": "Feature",
  "properties": {
    "iso:country":"US",
    "sg:address":"2129 N 400 E",
    "sg:city":"Ogden",
    "sg:classifiers":[
        {
            "category":"Shopping",
            "subcategory":"Gifts & Souvenirs",
            "type":"Retail Goods"
        }
    ],
    "sg:phone":"+1 801 782 8648",
    "sg:postcode":"84414",
    "sg:province":"UT",
    "wof:name":"Heart of The Country",
    "wof:placetype":"venue"
},
  "geometry": {"coordinates":[-111.968936,41.29731],"type":"Point"}
}