{
  "type": "Feature",
  "properties": {
    "iso:country":"US",
    "sg:address":"634 S 1200 E",
    "sg:city":"Mapleton",
    "sg:classifiers":[
        {
            "category":"Professional",
            "subcategory":"Computer Services",
            "type":"Services"
        }
    ],
    "sg:phone":"+1 801 489 2520",
    "sg:postcode":"84664",
    "sg:province":"UT",
    "sg:tags":[
        "programing",
        "custom"
    ],
    "wof:name":"C Hart Enterprises",
    "wof:placetype":"venue"
},
  "geometry": {"coordinates":[-111.564615,40.12339],"type":"Point"}
}