{
  "type": "Feature",
  "properties": {
    "iso:country":"US",
    "sg:address":"795 N 800 E",
    "sg:city":"Logan",
    "sg:classifiers":[
        {
            "category":"Organizations",
            "subcategory":"Religious Organization",
            "type":"Services"
        }
    ],
    "sg:phone":"+1 435 752 1478",
    "sg:postcode":"84321",
    "sg:province":"UT",
    "sg:tags":[
        "church"
    ],
    "wof:name":"St Thomas Aquinas Catholic Chr",
    "wof:placetype":"venue"
},
  "geometry": {"coordinates":[-111.814126,41.74449],"type":"Point"}
}