{
  "type": "Feature",
  "properties": {
    "iso:country":"US",
    "sg:address":"643 Toronto Ln",
    "sg:city":"Spanish Fork",
    "sg:classifiers":[
        {
            "category":"Government",
            "subcategory":"Office",
            "type":"Public Place"
        }
    ],
    "sg:phone":"+1 801 798 3365",
    "sg:postcode":"84660",
    "sg:province":"UT",
    "sg:tags":[
        "field",
        "program",
        "for",
        "reader"
    ],
    "wof:name":"Olsen Leif",
    "wof:placetype":"venue"
},
  "geometry": {"coordinates":[-111.640353,40.100874],"type":"Point"}
}