{
  "type": "Feature",
  "properties": {
    "iso:country":"US",
    "sg:address":"1275 E Hwy 40",
    "sg:city":"Vernal",
    "sg:classifiers":[
        {
            "category":"Manufacturing",
            "subcategory":"Tools & Machinery",
            "type":"Manufacturing & Wholesale Goods"
        }
    ],
    "sg:phone":"+1 435 789 7001",
    "sg:postcode":"84078",
    "sg:province":"UT",
    "sg:tags":[
        "filter"
    ],
    "wof:name":"TPS Technical Process Solu",
    "wof:placetype":"venue"
},
  "geometry": {"coordinates":[-109.50323299999999,40.44973],"type":"Point"}
}