{
  "type": "Feature",
  "properties": {
    "iso:country":"US",
    "sg:address":"96 N Main St",
    "sg:city":"Helper",
    "sg:classifiers":[
        {
            "category":"Home & Garden",
            "subcategory":"Building Materials",
            "type":"Retail Goods"
        }
    ],
    "sg:phone":"+1 435 472 5579",
    "sg:postcode":"84526",
    "sg:province":"UT",
    "sg:tags":[
        "lumber"
    ],
    "wof:name":"Central Commission & Supply Co",
    "wof:placetype":"venue"
},
  "geometry": {"coordinates":[-110.85666000000001,39.691738],"type":"Point"}
}