{
  "type": "Feature",
  "properties": {
    "iso:country":"US",
    "sg:address":"4027 S 4520 W",
    "sg:city":"Salt Lake City",
    "sg:classifiers":[
        {
            "category":"Building & Trades",
            "subcategory":"Electrical",
            "type":"Services"
        }
    ],
    "sg:phone":"+1 801 967 2442",
    "sg:postcode":"84120",
    "sg:province":"UT",
    "sg:tags":[
        "electrical",
        "contractor"
    ],
    "wof:name":"BNG Electric Inc",
    "wof:placetype":"venue"
},
  "geometry": {"coordinates":[-111.999072,40.682719],"type":"Point"}
}