{
  "type": "Feature",
  "properties": {
    "iso:country":"US",
    "sg:address":"2277 Fort Union Blvd",
    "sg:city":"Salt Lake City",
    "sg:classifiers":[
        {
            "category":"Building & Trades",
            "subcategory":"Equipment Rental",
            "type":"Services"
        }
    ],
    "sg:phone":"+1 801 397 4011",
    "sg:postcode":"84121",
    "sg:province":"UT",
    "sg:tags":[
        "leasing"
    ],
    "wof:name":"Health Care Leasing",
    "wof:placetype":"venue"
},
  "geometry": {"coordinates":[-111.826222,40.624054],"type":"Point"}
}