{
  "type": "Feature",
  "properties": {
    "iso:country":"US",
    "sg:address":"4609 S 2300 East St",
    "sg:city":"Holladay",
    "sg:classifiers":[
        {
            "category":"Real Estate",
            "subcategory":"Real Estate Agent",
            "type":"Services"
        }
    ],
    "sg:phone":"+1 801 272 8636",
    "sg:postcode":"84117",
    "sg:province":"UT",
    "wof:name":"Sperling Realtors Inc",
    "wof:placetype":"venue"
},
  "geometry": {"coordinates":[-111.824443,40.672179],"type":"Point"}
}