{
  "type": "Feature",
  "properties": {
    "iso:country":"US",
    "sg:address":"1411 S Redwood Rd",
    "sg:city":"Salt Lake City",
    "sg:classifiers":[
        {
            "category":"Restaurant",
            "type":"Food & Drink"
        }
    ],
    "sg:menulink":"http://www.allmenus.com/ut/salt-lake-city/38790-soup-kitchen/menu/",
    "sg:phone":"+1 801 974 7910",
    "sg:postcode":"84104",
    "sg:province":"UT",
    "sg:tags":[
        "soup",
        "american",
        "salad"
    ],
    "wof:name":"Soup Kitchen",
    "wof:placetype":"venue"
},
  "geometry": {"coordinates":[-111.938964,40.738512],"type":"Point"}
}