{
  "type": "Feature",
  "properties": {
    "iso:country":"US",
    "sg:address":"7672 Center Sq",
    "sg:city":"Midvale",
    "sg:classifiers":[
        {
            "category":"Shopping",
            "subcategory":"Department Store",
            "type":"Retail Goods"
        }
    ],
    "sg:phone":"+1 801 566 1232",
    "sg:postcode":"84047",
    "sg:province":"UT",
    "sg:tags":[
        "shop"
    ],
    "wof:name":"Family Dollar Store",
    "wof:placetype":"venue"
},
  "geometry": {"coordinates":[-111.89532199999999,40.611539],"type":"Point"}
}