{
  "type": "Feature",
  "properties": {
    "iso:country":"US",
    "sg:address":"1820 S Main St",
    "sg:city":"Salt Lake City",
    "sg:classifiers":[
        {
            "category":"Retail",
            "subcategory":"Repair Shop",
            "type":"Services"
        }
    ],
    "sg:phone":"+1 801 474 2188",
    "sg:postcode":"84115",
    "sg:province":"UT",
    "wof:name":"J B Schild",
    "wof:placetype":"venue"
},
  "geometry": {"coordinates":[-111.891138,40.729946],"type":"Point"}
}