{
  "type": "Feature",
  "properties": {
    "iso:country":"US",
    "sg:address":"171 N 500 W",
    "sg:city":"Logan",
    "sg:classifiers":[
        {
            "category":"Social Services",
            "subcategory":"Child Care",
            "type":"Services"
        }
    ],
    "sg:phone":"+1 435 752 2147",
    "sg:postcode":"84321",
    "sg:province":"UT",
    "sg:tags":[
        "day"
    ],
    "wof:name":"T T Bear Day Care",
    "wof:placetype":"venue"
},
  "geometry": {"coordinates":[-111.84782199999999,41.734076],"type":"Point"}
}