{
  "type": "Feature",
  "properties": {
    "iso:country":"US",
    "sg:address":"1460 W 2950 S",
    "sg:city":"Brigham City",
    "sg:classifiers":[
        {
            "category":"Farming",
            "subcategory":"Farm",
            "type":"Manufacturing & Wholesale Goods"
        }
    ],
    "sg:phone":"+1 435 723 2529",
    "sg:postcode":"84302",
    "sg:province":"UT",
    "sg:tags":[
        "crop",
        "general"
    ],
    "wof:name":"Nelson Bros Farms LLC",
    "wof:placetype":"venue"
},
  "geometry": {"coordinates":[-112.04956900000001,41.456792],"type":"Point"}
}