{
  "type": "Feature",
  "properties": {
    "iso:country":"US",
    "sg:address":"449 E 3900 S",
    "sg:city":"Salt Lake City",
    "sg:classifiers":[
        {
            "category":"Wholesale",
            "subcategory":"Apparel",
            "type":"Manufacturing & Wholesale Goods"
        }
    ],
    "sg:phone":"+1 801 999 0120",
    "sg:postcode":"84107",
    "sg:province":"UT",
    "sg:tags":[
        "clothing",
        "shoes"
    ],
    "sg:website":"www.denim-connection.com",
    "wof:name":"Denim Connection",
    "wof:placetype":"venue"
},
  "geometry": {"coordinates":[-111.87702,40.687137],"type":"Point"}
}