{
  "type": "Feature",
  "properties": {
    "iso:country":"US",
    "sg:address":"2537 Lynwood Dr",
    "sg:city":"Salt Lake City",
    "sg:classifiers":[
        {
            "category":"Real Estate",
            "subcategory":"Real Estate Agent",
            "type":"Services"
        }
    ],
    "sg:phone":"+1 801 485 2295",
    "sg:postcode":"84109",
    "sg:province":"UT",
    "sg:tags":[
        "investment"
    ],
    "wof:name":"Knudson Investment LTD",
    "wof:placetype":"venue"
},
  "geometry": {"coordinates":[-111.817391,40.720127],"type":"Point"}
}