{
  "type": "Feature",
  "properties": {
    "iso:country":"US",
    "sg:address":"2240 Cottonwood Cove Ln",
    "sg:city":"Salt Lake City",
    "sg:classifiers":[
        {
            "category":"Building & Trades",
            "subcategory":"Construction",
            "type":"Services"
        }
    ],
    "sg:phone":"+1 801 943 8533",
    "sg:postcode":"84121",
    "sg:province":"UT",
    "sg:tags":[
        "general",
        "contractor"
    ],
    "wof:name":"Beuchert Builders Inc",
    "wof:placetype":"venue"
},
  "geometry": {"coordinates":[-111.829465,40.60723],"type":"Point"}
}