{
  "type": "Feature",
  "properties": {
    "iso:country":"US",
    "sg:address":"6672 Fargo Rd",
    "sg:city":"West Jordan",
    "sg:classifiers":[
        {
            "category":"Building & Trades",
            "subcategory":"Construction",
            "type":"Services"
        }
    ],
    "sg:phone":"+1 801 561 9234",
    "sg:postcode":"84084",
    "sg:province":"UT",
    "sg:tags":[
        "general",
        "contractor"
    ],
    "wof:name":"Fab-Rite Inc",
    "wof:placetype":"venue"
},
  "geometry": {"coordinates":[-111.95125899999999,40.628956],"type":"Point"}
}