{
  "type": "Feature",
  "properties": {
    "iso:country":"US",
    "sg:address":"424 F St",
    "sg:city":"Salt Lake City",
    "sg:classifiers":[
        {
            "category":"Communications",
            "type":"Services"
        }
    ],
    "sg:phone":"+1 801 363 4106",
    "sg:postcode":"84103",
    "sg:province":"UT",
    "sg:tags":[
        "communication"
    ],
    "wof:name":"Advocate Communications",
    "wof:placetype":"venue"
},
  "geometry": {"coordinates":[-111.87598,40.77907],"type":"Point"}
}