{
  "type": "Feature",
  "properties": {
    "iso:country":"US",
    "sg:address":"1071 E 100 S",
    "sg:city":"St George",
    "sg:classifiers":[
        {
            "category":"Building & Trades",
            "subcategory":"Construction",
            "type":"Services"
        }
    ],
    "sg:phone":"+1 435 628 0187",
    "sg:postcode":"84770",
    "sg:province":"UT",
    "sg:tags":[
        "general",
        "contractor"
    ],
    "wof:name":"West Land Construction",
    "wof:placetype":"venue"
},
  "geometry": {"coordinates":[-113.561144,37.106486],"type":"Point"}
}