{
  "type": "Feature",
  "properties": {
    "iso:country":"US",
    "sg:address":"3025 Spanish Trail Rd",
    "sg:city":"Moab",
    "sg:classifiers":[
        {
            "category":"Government",
            "subcategory":"Office",
            "type":"Public Place"
        }
    ],
    "sg:phone":"+1 435 259 8121",
    "sg:postcode":"84532",
    "sg:province":"UT",
    "sg:tags":[
        "county",
        "govt"
    ],
    "wof:name":"Grand Water & Sewer Svc Agency",
    "wof:placetype":"venue"
},
  "geometry": {"coordinates":[-109.498385,38.531425],"type":"Point"}
}