{
  "type": "Feature",
  "properties": {
    "iso:country":"US",
    "sg:address":"3452 W 6400 S",
    "sg:city":"Spanish Fork",
    "sg:classifiers":[
        {
            "category":"Shopping",
            "type":"Retail Goods"
        }
    ],
    "sg:phone":"+1 801 798 6862",
    "sg:postcode":"84660",
    "sg:province":"UT",
    "sg:tags":[
        "cosmetic",
        "perfume"
    ],
    "wof:name":"Mary Kay Cosmetics",
    "wof:placetype":"venue"
},
  "geometry": {"coordinates":[-111.734528,40.114696],"type":"Point"}
}