{
  "type": "Feature",
  "properties": {
    "iso:country":"US",
    "sg:address":"1215 E Pondoray Cir",
    "sg:city":"Salt Lake City",
    "sg:classifiers":[
        {
            "category":"Professional",
            "subcategory":"Engineering",
            "type":"Services"
        }
    ],
    "sg:phone":"+1 801 268 3033",
    "sg:postcode":"84117",
    "sg:province":"UT",
    "sg:tags":[
        "engineer"
    ],
    "wof:name":"Emmett Process Consulting LLC",
    "wof:placetype":"venue"
},
  "geometry": {"coordinates":[-111.854409,40.668985],"type":"Point"}
}