{
  "type": "Feature",
  "properties": {
    "iso:country":"US",
    "sg:address":"2875 S Main St",
    "sg:city":"Salt Lake City",
    "sg:classifiers":[
        {
            "category":"Building & Trades",
            "subcategory":"Construction",
            "type":"Services"
        }
    ],
    "sg:phone":"+1 801 531 1759",
    "sg:postcode":"84115",
    "sg:province":"UT",
    "sg:tags":[
        "general",
        "contractor"
    ],
    "wof:name":"Doneright Construction",
    "wof:placetype":"venue"
},
  "geometry": {"coordinates":[-111.89104500000001,40.708546],"type":"Point"}
}