{
  "type": "Feature",
  "properties": {
    "iso:country":"US",
    "sg:address":"2825 Cottonwood Pkwy",
    "sg:city":"Salt Lake City",
    "sg:classifiers":[
        {
            "category":"Banks & Credit Unions",
            "subcategory":"Bank",
            "type":"Services"
        }
    ],
    "sg:phone":"+1 801 973 2191",
    "sg:postcode":"84121",
    "sg:province":"UT",
    "sg:tags":[
        "loan",
        "real estate"
    ],
    "sg:website":"www.utahbest.net",
    "wof:name":"Utah Best Mortgage Co",
    "wof:placetype":"venue"
},
  "geometry": {"coordinates":[-111.811212,40.632768],"type":"Point"}
}