{
  "type": "Feature",
  "properties": {
    "iso:country":"US",
    "sg:address":"53 S Cliff Rose Dr",
    "sg:city":"Veyo",
    "sg:classifiers":[
        {
            "category":"Professional",
            "type":"Services"
        }
    ],
    "sg:phone":"+1 435 574 3625",
    "sg:postcode":"84782",
    "sg:province":"UT",
    "wof:name":"J Lynns Interiors",
    "wof:placetype":"venue"
},
  "geometry": {"coordinates":[-113.666358,37.360582],"type":"Point"}
}