{
  "type": "Feature",
  "properties": {
    "iso:country":"US",
    "sg:address":"3508 Winding Creek Cove",
    "sg:city":"Riverton",
    "sg:classifiers":[
        {
            "category":"Building & Trades",
            "subcategory":"Construction",
            "type":"Services"
        }
    ],
    "sg:phone":"+1 801 446 9200",
    "sg:postcode":"84065",
    "sg:province":"UT",
    "sg:tags":[
        "contracting",
        "general"
    ],
    "wof:name":"Cambridge Roofing",
    "wof:placetype":"venue"
},
  "geometry": {"coordinates":[-111.974638,40.533774],"type":"Point"}
}