{
  "type": "Feature",
  "properties": {
    "iso:country":"US",
    "sg:address":"4025 S Hwy 89/91",
    "sg:city":"Wellsville",
    "sg:classifiers":[
        {
            "category":"Education",
            "subcategory":"College",
            "type":"Public Place"
        }
    ],
    "sg:phone":"+1 435 245 4064",
    "sg:postcode":"84339",
    "sg:province":"UT",
    "wof:name":"RV Jnsen Lving Hstorical Frm",
    "wof:placetype":"venue"
},
  "geometry": {"coordinates":[-111.860992,41.696576],"type":"Point"}
}