{
  "type": "Feature",
  "properties": {
    "iso:country":"US",
    "sg:address":"1925 Indiana Ave",
    "sg:city":"Salt Lake City",
    "sg:classifiers":[
        {
            "category":"Manufacturing",
            "subcategory":"Motor Vehicles & Parts",
            "type":"Manufacturing & Wholesale Goods"
        }
    ],
    "sg:phone":"+1 801 973 9400",
    "sg:postcode":"84104",
    "sg:province":"UT",
    "sg:tags":[
        "body",
        "truck"
    ],
    "sg:website":"www.tescowilliamsen.com",
    "wof:name":"Tesco Williamsen",
    "wof:placetype":"venue"
},
  "geometry": {"coordinates":[-111.945222,40.75116],"type":"Point"}
}