{
  "type": "Feature",
  "properties": {
    "iso:country":"US",
    "sg:address":"1190 Pioneer Rd",
    "sg:city":"Salt Lake City",
    "sg:classifiers":[
        {
            "category":"Wholesale",
            "subcategory":"Electrical",
            "type":"Manufacturing & Wholesale Goods"
        }
    ],
    "sg:phone":"+1 801 972 0728",
    "sg:postcode":"84104",
    "sg:province":"UT",
    "sg:tags":[
        "electric",
        "motor"
    ],
    "wof:name":"Skyline Electric Motor Repair",
    "wof:placetype":"venue"
},
  "geometry": {"coordinates":[-111.958141,40.743347],"type":"Point"}
}