{
  "type": "Feature",
  "properties": {
    "iso:country":"US",
    "sg:address":"2122 W 5400 S",
    "sg:city":"Kearns",
    "sg:classifiers":[
        {
            "category":"Travel",
            "subcategory":"Travel Agent",
            "type":"Entertainment"
        }
    ],
    "sg:phone":"+1 801 966 4242",
    "sg:postcode":"84118",
    "sg:province":"UT",
    "sg:tags":[
        "operator",
        "tour",
        "tours",
        "promoter"
    ],
    "sg:website":"www.hydetour.com",
    "wof:name":"Hyde's Encore Tours & Travel",
    "wof:placetype":"venue"
},
  "geometry": {"coordinates":[-111.947461,40.653163],"type":"Point"}
}