{
  "type": "Feature",
  "properties": {
    "iso:country":"US",
    "sg:address":"452 N 970 E",
    "sg:city":"Springville",
    "sg:classifiers":[
        {
            "category":"Professional",
            "type":"Services"
        }
    ],
    "sg:phone":"+1 801 489 5133",
    "sg:postcode":"84663",
    "sg:province":"UT",
    "wof:name":"Hulce Paralegal Services Inc",
    "wof:placetype":"venue"
},
  "geometry": {"coordinates":[-111.592975,40.173454],"type":"Point"}
}