{
  "type": "Feature",
  "properties": {
    "iso:country":"US",
    "sg:address":"1610 N Dixie Downs Rd",
    "sg:city":"St George",
    "sg:classifiers":[
        {
            "category":"Professional",
            "subcategory":"Employment Agencies",
            "type":"Services"
        }
    ],
    "sg:phone":"+1 435 628 4751",
    "sg:postcode":"84770",
    "sg:province":"UT",
    "sg:tags":[
        "opportunity"
    ],
    "wof:name":"St George Stake Employment Ctr",
    "wof:placetype":"venue"
},
  "geometry": {"coordinates":[-113.623766,37.136957],"type":"Point"}
}