{
  "type": "Feature",
  "properties": {
    "iso:country":"US",
    "sg:address":"1000 S Main St",
    "sg:city":"Richfield",
    "sg:classifiers":[
        {
            "category":"Restaurant",
            "type":"Food & Drink"
        }
    ],
    "sg:phone":"+1 435 638 7409",
    "sg:postcode":"84701",
    "sg:province":"UT",
    "wof:name":"High Top Cafe",
    "wof:placetype":"venue"
},
  "geometry": {"coordinates":[-112.088775,38.753997],"type":"Point"}
}