{
  "type": "Feature",
  "properties": {
    "iso:country":"US",
    "sg:address":"925 E 900 S",
    "sg:city":"Salt Lake City",
    "sg:classifiers":[
        {
            "category":"Professional",
            "subcategory":"Lawyer & Legal Services",
            "type":"Services"
        }
    ],
    "sg:phone":"+1 801 359 2292",
    "sg:postcode":"84105",
    "sg:province":"UT",
    "wof:name":"Jeffrey J Noland",
    "wof:placetype":"venue"
},
  "geometry": {"coordinates":[-111.864683,40.749865],"type":"Point"}
}