{
  "type": "Feature",
  "properties": {
    "iso:country":"US",
    "sg:address":"2571 E Golden Eye Dr",
    "sg:city":"Sandy",
    "sg:classifiers":[
        {
            "category":"Shopping",
            "subcategory":"Computers & Home Electronics",
            "type":"Retail Goods"
        }
    ],
    "sg:phone":"+1 801 942 4727",
    "sg:postcode":"84093",
    "sg:province":"UT",
    "wof:name":"Crusader Systems",
    "wof:placetype":"venue"
},
  "geometry": {"coordinates":[-111.815667,40.584405],"type":"Point"}
}