{
  "type": "Feature",
  "properties": {
    "iso:country":"US",
    "sg:address":"2018 E 140 S",
    "sg:city":"St George",
    "sg:classifiers":[
        {
            "category":"Professional",
            "subcategory":"Computer Services",
            "type":"Services"
        }
    ],
    "sg:phone":"+1 435 628 4907",
    "sg:postcode":"84790",
    "sg:province":"UT",
    "sg:tags":[
        "design",
        "system"
    ],
    "wof:name":"Gifartcom",
    "wof:placetype":"venue"
},
  "geometry": {"coordinates":[-113.54011,37.105476],"type":"Point"}
}