{
  "type": "Feature",
  "properties": {
    "iso:country":"US",
    "sg:address":"9 Exchange Pl",
    "sg:city":"Salt Lake City",
    "sg:classifiers":[
        {
            "category":"Professional",
            "subcategory":"Lawyer & Legal Services",
            "type":"Services"
        }
    ],
    "sg:phone":"+1 801 359 1313",
    "sg:postcode":"84111",
    "sg:province":"UT",
    "wof:name":"Bankruptcy Firm",
    "wof:placetype":"venue"
},
  "geometry": {"coordinates":[-111.889832,40.761482],"type":"Point"}
}