{
  "type": "Feature",
  "properties": {
    "iso:country":"US",
    "sg:address":"5605 S 3300 W",
    "sg:city":"Wellsville",
    "sg:classifiers":[
        {
            "category":"Professional",
            "type":"Services"
        }
    ],
    "sg:phone":"+1 435 245 3183",
    "sg:postcode":"84339",
    "sg:province":"UT",
    "wof:name":"Jbba Ltd",
    "wof:placetype":"venue"
},
  "geometry": {"coordinates":[-111.910965,41.634961],"type":"Point"}
}