{
  "type": "Feature",
  "properties": {
    "iso:country":"US",
    "sg:address":"76 S 500 E",
    "sg:city":"Salt Lake City",
    "sg:classifiers":[
        {
            "category":"Social Services",
            "subcategory":"Adult Care",
            "type":"Services"
        }
    ],
    "sg:phone":"+1 801 359 0050",
    "sg:postcode":"84102",
    "sg:province":"UT",
    "sg:tags":[
        "home",
        "residential"
    ],
    "sg:website":"www.marriott.com",
    "wof:name":"Brighton Gardens-Salt Lake Cty",
    "wof:placetype":"venue"
},
  "geometry": {"coordinates":[-111.876859,40.769323],"type":"Point"}
}