{
  "type": "Feature",
  "properties": {
    "iso:country":"US",
    "sg:address":"2350 W 1500 S",
    "sg:city":"Salt Lake City",
    "sg:classifiers":[
        {
            "category":"Wholesale",
            "subcategory":"Machinery & Supplies",
            "type":"Manufacturing & Wholesale Goods"
        }
    ],
    "sg:phone":"+1 801 972 3660",
    "sg:postcode":"84104",
    "sg:province":"UT",
    "sg:tags":[
        "equipment",
        "excavating"
    ],
    "sg:website":"www.komatsueq.net",
    "wof:name":"Komatsu Equipment Co",
    "wof:placetype":"venue"
},
  "geometry": {"coordinates":[-111.953267,40.737846],"type":"Point"}
}