{
  "type": "Feature",
  "properties": {
    "iso:country":"US",
    "sg:address":"5761 S 2150 W",
    "sg:city":"Roy",
    "sg:classifiers":[
        {
            "category":"Wholesale",
            "subcategory":"Machinery & Supplies",
            "type":"Manufacturing & Wholesale Goods"
        }
    ],
    "sg:phone":"+1 801 825 2379",
    "sg:postcode":"84067",
    "sg:province":"UT",
    "sg:tags":[
        "equipment",
        "industrial"
    ],
    "wof:name":"Assoc Air Handling Inc",
    "wof:placetype":"venue"
},
  "geometry": {"coordinates":[-112.032387,41.158188],"type":"Point"}
}