{
  "type": "Feature",
  "properties": {
    "iso:country":"US",
    "sg:address":"333 W Center St",
    "sg:city":"North Salt Lake",
    "sg:classifiers":[
        {
            "category":"Banks & Credit Unions",
            "subcategory":"Bank",
            "type":"Services"
        }
    ],
    "sg:phone":"+1 801 296 7700",
    "sg:postcode":"84054",
    "sg:province":"UT",
    "wof:name":"Beeline Employees Federal Credit Union",
    "wof:placetype":"venue"
},
  "geometry": {"coordinates":[-111.919998,40.841801],"type":"Point"}
}