{
  "type": "Feature",
  "properties": {
    "iso:country":"US",
    "sg:address":"1224 W 1380 N",
    "sg:city":"Orem",
    "sg:classifiers":[
        {
            "category":"Building & Trades",
            "subcategory":"Construction",
            "type":"Services"
        }
    ],
    "sg:phone":"+1 801 762 0014",
    "sg:postcode":"84057",
    "sg:province":"UT",
    "sg:tags":[
        "acoustical",
        "contractor"
    ],
    "wof:name":"Valley Design Acoustics",
    "wof:placetype":"venue"
},
  "geometry": {"coordinates":[-111.72503500000001,40.322369],"type":"Point"}
}