{
  "type": "Feature",
  "properties": {
    "iso:country":"US",
    "sg:address":"7850 S 1300 E",
    "sg:city":"Sandy",
    "sg:classifiers":[
        {
            "category":"Banks & Credit Unions",
            "subcategory":"Bank",
            "type":"Services"
        }
    ],
    "sg:phone":"+1 801 307 0710",
    "sg:postcode":"84094",
    "sg:province":"UT",
    "wof:name":"Golden West Credit Union",
    "wof:placetype":"venue"
},
  "geometry": {"coordinates":[-111.853161,40.60736],"type":"Point"}
}