{
  "type": "Feature",
  "properties": {
    "iso:country":"US",
    "sg:address":"1971 S 1500 W",
    "sg:city":"Vernal",
    "sg:classifiers":[
        {
            "category":"Professional",
            "subcategory":"Accounting & Tax Preparation",
            "type":"Services"
        }
    ],
    "sg:phone":"+1 435 789 7378",
    "sg:postcode":"84078",
    "sg:province":"UT",
    "wof:name":"AAA Bokkeeping Secretarial Svc",
    "wof:placetype":"venue"
},
  "geometry": {"coordinates":[-109.55677799999999,40.426713],"type":"Point"}
}