{
  "type": "Feature",
  "properties": {
    "iso:country":"US",
    "sg:address":"550 N Main St",
    "sg:city":"Moab",
    "sg:classifiers":[
        {
            "category":"Banks & Credit Unions",
            "subcategory":"Bank",
            "type":"Services"
        }
    ],
    "sg:phone":"+1 435 259 4489",
    "sg:postcode":"84532",
    "sg:province":"UT",
    "sg:tags":[
        "loan",
        "mortgage"
    ],
    "wof:name":"Fidelity Mortgage Inc",
    "wof:placetype":"venue"
},
  "geometry": {"coordinates":[-109.552049,38.581597],"type":"Point"}
}