{
  "type": "Feature",
  "properties": {
    "iso:country":"US",
    "sg:address":"2445 Iron Canyon Dr",
    "sg:city":"Park City",
    "sg:classifiers":[
        {
            "category":"Real Estate",
            "subcategory":"Architect",
            "type":"Services"
        }
    ],
    "sg:phone":"+1 435 645 8188",
    "sg:postcode":"84068",
    "sg:province":"UT",
    "sg:tags":[
        "architectural"
    ],
    "wof:name":"Architecture & Planning",
    "wof:placetype":"venue"
},
  "geometry": {"coordinates":[-111.52480799999999,40.669202],"type":"Point"}
}