{
  "type": "Feature",
  "properties": {
    "iso:country":"US",
    "sg:address":"1748 US Hwy 40",
    "sg:city":"Vernal",
    "sg:classifiers":[
        {
            "category":"Freight",
            "type":"Transportation"
        }
    ],
    "sg:phone":"+1 435 781 1322",
    "sg:postcode":"84078",
    "sg:province":"UT",
    "sg:tags":[
        "hauling",
        "trucking"
    ],
    "wof:name":"Eight Ball Trucking",
    "wof:placetype":"venue"
},
  "geometry": {"coordinates":[-109.499471,40.43036],"type":"Point"}
}