{
  "type": "Feature",
  "properties": {
    "iso:country":"US",
    "sg:address":"38 W 300 S",
    "sg:city":"Moab",
    "sg:classifiers":[
        {
            "category":"Health Services",
            "subcategory":"Doctor",
            "type":"Services"
        }
    ],
    "sg:phone":"+1 435 259 7121",
    "sg:postcode":"84532",
    "sg:province":"UT",
    "sg:tags":[
        "physician",
        "surgeon"
    ],
    "wof:name":"Moab Medical Ctr",
    "wof:placetype":"venue"
},
  "geometry": {"coordinates":[-109.55162900000001,38.568756],"type":"Point"}
}