{
  "type": "Feature",
  "properties": {
    "iso:country":"US",
    "sg:address":"1 S Main St",
    "sg:city":"Brigham City",
    "sg:classifiers":[
        {
            "category":"Government",
            "subcategory":"Office",
            "type":"Public Place"
        }
    ],
    "sg:phone":"+1 435 734 3394",
    "sg:postcode":"84302",
    "sg:province":"UT",
    "sg:website":"www.boxeldercounty.org",
    "wof:name":"Box Elder County Agricultural",
    "wof:placetype":"venue"
},
  "geometry": {"coordinates":[-112.015737,41.51009],"type":"Point"}
}