{
  "type": "Feature",
  "properties": {
    "iso:country":"US",
    "sg:address":"80 E Center St",
    "sg:city":"Laketown",
    "sg:classifiers":[
        {
            "category":"Government",
            "subcategory":"Post Office",
            "type":"Public Place"
        }
    ],
    "sg:phone":"+1 435 946 8632",
    "sg:postcode":"84038",
    "sg:province":"UT",
    "wof:name":"US Post Office",
    "wof:placetype":"venue"
},
  "geometry": {"coordinates":[-111.32284,41.825525],"type":"Point"}
}