{
  "type": "Feature",
  "properties": {
    "iso:country":"US",
    "sg:address":"125 E 300 S",
    "sg:city":"Moab",
    "sg:classifiers":[
        {
            "category":"Retail",
            "subcategory":"Veterinary Services",
            "type":"Services"
        }
    ],
    "sg:phone":"+1 435 259 2733",
    "sg:postcode":"84532",
    "sg:province":"UT",
    "wof:name":"Dog & Cat Clinic of Moab",
    "wof:placetype":"venue"
},
  "geometry": {"coordinates":[-109.548197,38.568741],"type":"Point"}
}