{
  "type": "Feature",
  "properties": {
    "iso:country":"US",
    "sg:address":"1271 Cutter Ln",
    "sg:city":"Park City",
    "sg:classifiers":[
        {
            "category":"Professional",
            "subcategory":"Management & Consulting",
            "type":"Services"
        }
    ],
    "sg:phone":"+1 435 615 8247",
    "sg:postcode":"84098",
    "sg:province":"UT",
    "sg:tags":[
        "business"
    ],
    "wof:name":"Litmus Consulting Corp",
    "wof:placetype":"venue"
},
  "geometry": {"coordinates":[-111.533789,40.706557],"type":"Point"}
}