{
  "type": "Feature",
  "properties": {
    "iso:country":"US",
    "sg:address":"192 E 100 North St",
    "sg:city":"Fayette",
    "sg:classifiers":[
        {
            "category":"Manufacturing",
            "subcategory":"Tools & Machinery",
            "type":"Manufacturing & Wholesale Goods"
        }
    ],
    "sg:phone":"+1 435 528 7199",
    "sg:postcode":"84630",
    "sg:province":"UT",
    "sg:tags":[
        "limb",
        "artificial"
    ],
    "wof:name":"Applied Composite Technology",
    "wof:placetype":"venue"
},
  "geometry": {"coordinates":[-111.85231899999999,39.226731],"type":"Point"}
}