{
  "type": "Feature",
  "properties": {
    "iso:country":"US",
    "sg:address":"754 S State St",
    "sg:city":"Salt Lake City",
    "sg:classifiers":[
        {
            "category":"Shopping",
            "subcategory":"Optical Goods",
            "type":"Retail Goods"
        }
    ],
    "sg:phone":"+1 801 355 2644",
    "sg:postcode":"84111",
    "sg:province":"UT",
    "wof:name":"Cole",
    "wof:placetype":"venue"
},
  "geometry": {"coordinates":[-111.888294,40.752089],"type":"Point"}
}