{
  "type": "Feature",
  "properties": {
    "iso:country":"US",
    "sg:address":"1757 Seven Oaks Ln",
    "sg:city":"Ogden",
    "sg:classifiers":[
        {
            "category":"Real Estate",
            "subcategory":"Real Estate Agent",
            "type":"Services"
        }
    ],
    "sg:phone":"+1 801 479 0897",
    "sg:postcode":"84403",
    "sg:province":"UT",
    "wof:name":"Jensen Real Estate LLC",
    "wof:placetype":"venue"
},
  "geometry": {"coordinates":[-111.933744,41.178339],"type":"Point"}
}