{
  "type": "Feature",
  "properties": {
    "iso:country":"US",
    "sg:address":"5486 S 4220 W",
    "sg:city":"Kearns",
    "sg:classifiers":[
        {
            "category":"Professional",
            "type":"Services"
        }
    ],
    "sg:phone":"+1 801 969 3030",
    "sg:postcode":"84118",
    "sg:province":"UT",
    "sg:tags":[
        "establishment"
    ],
    "wof:name":"Discoteca Y Deportes Gdljr",
    "wof:placetype":"venue"
},
  "geometry": {"coordinates":[-111.99176799999999,40.652576],"type":"Point"}
}