{
  "type": "Feature",
  "properties": {
    "iso:country":"US",
    "sg:address":"3040 S 300 E",
    "sg:city":"South Salt Lake",
    "sg:classifiers":[
        {
            "category":"Retail",
            "subcategory":"Auto Repair",
            "type":"Services"
        }
    ],
    "sg:phone":"+1 801 466 3851",
    "sg:postcode":"84115",
    "sg:province":"UT",
    "sg:tags":[
        "body",
        "automobile",
        "painting",
        "general"
    ],
    "wof:name":"B & P Custom Body Works",
    "wof:placetype":"venue"
},
  "geometry": {"coordinates":[-111.882746,40.705453],"type":"Point"}
}