{
  "type": "Feature",
  "properties": {
    "iso:country":"US",
    "sg:address":"350 W 800 N",
    "sg:city":"Salt Lake City",
    "sg:classifiers":[
        {
            "category":"Banks & Credit Unions",
            "subcategory":"Investment Brokerage",
            "type":"Services"
        }
    ],
    "sg:phone":"+1 801 521 2560",
    "sg:postcode":"84103",
    "sg:province":"UT",
    "sg:tags":[
        "consultant",
        "planning",
        "financial"
    ],
    "wof:name":"Crossroads Investment Advisors",
    "wof:placetype":"venue"
},
  "geometry": {"coordinates":[-111.901301,40.786808],"type":"Point"}
}