{
  "type": "Feature",
  "properties": {
    "iso:country":"US",
    "sg:address":"15 N Main St",
    "sg:city":"Tooele",
    "sg:classifiers":[
        {
            "category":"Professional",
            "subcategory":"Advertising",
            "type":"Services"
        }
    ],
    "sg:phone":"+1 435 882 5494",
    "sg:postcode":"84074",
    "sg:province":"UT",
    "sg:website":"www.vision.com",
    "wof:name":"VISION.COM",
    "wof:placetype":"venue"
},
  "geometry": {"coordinates":[-112.29867400000001,40.531439],"type":"Point"}
}