{
  "type": "Feature",
  "properties": {
    "iso:country":"US",
    "sg:address":"1825 N University Pkwy",
    "sg:city":"Provo",
    "sg:classifiers":[
        {
            "category":"Autos & Motor Vehicles",
            "subcategory":"Automobile Sales",
            "type":"Retail Goods"
        }
    ],
    "sg:phone":"+1 801 224 1320",
    "sg:postcode":"84604",
    "sg:province":"UT",
    "sg:tags":[
        "car",
        "dealer"
    ],
    "wof:name":"Brent Brown Toyota",
    "wof:placetype":"venue"
},
  "geometry": {"coordinates":[-111.663067,40.258609],"type":"Point"}
}