{
  "type": "Feature",
  "properties": {
    "iso:country":"US",
    "sg:address":"5476 Wells Park Rd",
    "sg:city":"West Jordan",
    "sg:classifiers":[
        {
            "category":"Wholesale",
            "subcategory":"Construction Materials",
            "type":"Manufacturing & Wholesale Goods"
        }
    ],
    "sg:phone":"+1 801 560 9663",
    "sg:postcode":"84088",
    "sg:province":"UT",
    "sg:tags":[
        "fence"
    ],
    "wof:name":"Crown Vinyl Fence & Shed Inc",
    "wof:placetype":"venue"
},
  "geometry": {"coordinates":[-112.022322,40.577877],"type":"Point"}
}