{
  "type": "Feature",
  "properties": {
    "iso:country":"US",
    "sg:address":"1792 S Redwood Rd",
    "sg:city":"Salt Lake City",
    "sg:classifiers":[
        {
            "category":"Autos & Motor Vehicles",
            "subcategory":"Recreational Vehicle Sales",
            "type":"Retail Goods"
        }
    ],
    "sg:phone":"+1 801 973 0811",
    "sg:postcode":"84104",
    "sg:province":"UT",
    "sg:tags":[
        "canopy",
        "shell",
        "truck",
        "cap"
    ],
    "wof:name":"Fleet-Lite",
    "wof:placetype":"venue"
},
  "geometry": {"coordinates":[-111.939038,40.730527],"type":"Point"}
}