{
  "type": "Feature",
  "properties": {
    "iso:country":"US",
    "sg:address":"2770 S West Temple",
    "sg:city":"South Salt Lake",
    "sg:classifiers":[
        {
            "category":"Wholesale",
            "subcategory":"Hardware",
            "type":"Manufacturing & Wholesale Goods"
        }
    ],
    "sg:phone":"+1 801 486 4884",
    "sg:postcode":"84115",
    "sg:province":"UT",
    "sg:tags":[
        "builder"
    ],
    "wof:name":"Beacon Metals & Hardware Inc",
    "wof:placetype":"venue"
},
  "geometry": {"coordinates":[-111.894047,40.71068],"type":"Point"}
}