{
  "type": "Feature",
  "properties": {
    "iso:country":"US",
    "sg:address":"244 W 750 N",
    "sg:city":"Clearfield",
    "sg:classifiers":[
        {
            "category":"Personal",
            "type":"Services"
        }
    ],
    "sg:phone":"+1 801 773 7464",
    "sg:postcode":"84015",
    "sg:province":"UT",
    "sg:tags":[
        "electrolysis"
    ],
    "wof:name":"Affordable Electrolysis",
    "wof:placetype":"venue"
},
  "geometry": {"coordinates":[-112.03065700000001,41.124345],"type":"Point"}
}