{
  "type": "Feature",
  "properties": {
    "iso:country":"US",
    "sg:address":"61 N Main St",
    "sg:city":"Nephi",
    "sg:classifiers":[
        {
            "category":"Professional",
            "subcategory":"Business Services",
            "type":"Services"
        }
    ],
    "sg:phone":"+1 435 623 7033",
    "sg:postcode":"84648",
    "sg:province":"UT",
    "sg:tags":[
        "automotive"
    ],
    "wof:name":"Jones Lube & Wash",
    "wof:placetype":"venue"
},
  "geometry": {"coordinates":[-111.836226,39.709116],"type":"Point"}
}