{
  "type": "Feature",
  "properties": {
    "iso:country":"US",
    "sg:address":"115 N Main St",
    "sg:city":"Bountiful",
    "sg:classifiers":[
        {
            "category":"Shopping",
            "subcategory":"Hobbies, Toys, & Games",
            "type":"Retail Goods"
        }
    ],
    "sg:phone":"+1 801 292 6766",
    "sg:postcode":"84010",
    "sg:province":"UT",
    "wof:name":"Leisure Time Ceramics",
    "wof:placetype":"venue"
},
  "geometry": {"coordinates":[-111.880797,40.891338],"type":"Point"}
}