{
  "type": "Feature",
  "properties": {
    "iso:country":"US",
    "sg:address":"50 W Broadway",
    "sg:city":"Salt Lake City",
    "sg:classifiers":[
        {
            "category":"Real Estate",
            "subcategory":"Real Estate Operator",
            "type":"Services"
        }
    ],
    "sg:phone":"+1 801 481 5374",
    "sg:postcode":"84101",
    "sg:province":"UT",
    "sg:tags":[
        "building",
        "nonresidential"
    ],
    "wof:name":"Bank One Utah",
    "wof:placetype":"venue"
},
  "geometry": {"coordinates":[-111.89273,40.762898],"type":"Point"}
}