{
  "type": "Feature",
  "properties": {
    "iso:country":"US",
    "sg:address":"559 N 1060 E",
    "sg:city":"St George",
    "sg:classifiers":[
        {
            "category":"Health Services",
            "subcategory":"Clinic",
            "type":"Services"
        }
    ],
    "sg:phone":"+1 435 673 0608",
    "sg:postcode":"84770",
    "sg:province":"UT",
    "sg:tags":[
        "hospital",
        "specialty",
        "outpatient"
    ],
    "wof:name":"Alano Club Dixie",
    "wof:placetype":"venue"
},
  "geometry": {"coordinates":[-113.560669,37.118989],"type":"Point"}
}