{
  "type": "Feature",
  "properties": {
    "iso:country":"US",
    "sg:address":"1148 S Hwy 191",
    "sg:city":"Moab",
    "sg:classifiers":[
        {
            "category":"Retail",
            "subcategory":"Auto Repair",
            "type":"Services"
        }
    ],
    "sg:phone":"+1 435 259 6499",
    "sg:postcode":"84532",
    "sg:province":"UT",
    "sg:tags":[
        "repairing",
        "automobile"
    ],
    "wof:name":"Roy's Automotive",
    "wof:placetype":"venue"
},
  "geometry": {"coordinates":[-109.54132799999999,38.556775],"type":"Point"}
}