{
  "type": "Feature",
  "properties": {
    "iso:country":"US",
    "sg:address":"533 N Airport Rd",
    "sg:city":"Cedar City",
    "sg:classifiers":[
        {
            "category":"Retail",
            "subcategory":"Veterinary Services",
            "type":"Services"
        }
    ],
    "sg:phone":"+1 435 586 3400",
    "sg:postcode":"84720",
    "sg:province":"UT",
    "sg:tags":[
        "animal"
    ],
    "wof:name":"Cedar Veterinary Clinic",
    "wof:placetype":"venue"
},
  "geometry": {"coordinates":[-113.086949,37.686747],"type":"Point"}
}