{
  "type": "Feature",
  "properties": {
    "iso:country":"US",
    "sg:address":"50 E Broadway",
    "sg:city":"Salt Lake City",
    "sg:classifiers":[
        {
            "category":"Recreation",
            "type":"Entertainment"
        }
    ],
    "sg:phone":"+1 801 322 0376",
    "sg:postcode":"84111",
    "sg:province":"UT",
    "sg:tags":[
        "commercial",
        "art",
        "gallery"
    ],
    "wof:name":"Southam Gallery Inc",
    "wof:placetype":"venue"
},
  "geometry": {"coordinates":[-111.888822,40.762752],"type":"Point"}
}