{
  "type": "Feature",
  "properties": {
    "iso:country":"US",
    "sg:address":"844 E 6825 S",
    "sg:city":"Midvale",
    "sg:classifiers":[
        {
            "category":"Shopping",
            "subcategory":"Stationery & Office Supplies",
            "type":"Retail Goods"
        },
        {
            "category":"Shopping",
            "subcategory":"Hobbies, Toys, & Games",
            "type":"Retail Goods"
        }
    ],
    "sg:phone":"+1 801 565 0404",
    "sg:postcode":"84047",
    "sg:province":"UT",
    "sg:tags":[
        "album",
        "scrapbook"
    ],
    "wof:name":"Creative Memories",
    "wof:placetype":"venue"
},
  "geometry": {"coordinates":[-111.86653800000001,40.62748],"type":"Point"}
}