{
  "type": "Feature",
  "properties": {
    "iso:country":"US",
    "sg:address":"10757 S 1200 E",
    "sg:city":"Sandy",
    "sg:classifiers":[
        {
            "category":"Building & Trades",
            "subcategory":"Construction",
            "type":"Services"
        }
    ],
    "sg:phone":"+1 801 571 2699",
    "sg:postcode":"84094",
    "sg:province":"UT",
    "sg:tags":[
        "concrete",
        "contractor"
    ],
    "wof:name":"Stone Construction",
    "wof:placetype":"venue"
},
  "geometry": {"coordinates":[-111.85566799999999,40.556105],"type":"Point"}
}