{
  "type": "Feature",
  "properties": {
    "iso:country":"US",
    "sg:address":"4846 S 3750 W",
    "sg:city":"Roy",
    "sg:classifiers":[
        {
            "category":"Professional",
            "type":"Services"
        }
    ],
    "sg:phone":"+1 801 985 8963",
    "sg:postcode":"84067",
    "sg:province":"UT",
    "sg:tags":[
        "establishment"
    ],
    "wof:name":"Tilley & Tilley",
    "wof:placetype":"venue"
},
  "geometry": {"coordinates":[-112.070195,41.175863],"type":"Point"}
}