{
  "type": "Feature",
  "properties": {
    "iso:country":"US",
    "sg:address":"515 W 4770 N",
    "sg:city":"Provo",
    "sg:classifiers":[
        {
            "category":"Real Estate",
            "subcategory":"Real Estate Agent",
            "type":"Services"
        }
    ],
    "sg:phone":"+1 801 222 9272",
    "sg:postcode":"84604",
    "sg:province":"UT",
    "wof:name":"Steve Black Realty",
    "wof:placetype":"venue"
},
  "geometry": {"coordinates":[-111.665977,40.296265],"type":"Point"}
}