{
  "type": "Feature",
  "properties": {
    "iso:country":"US",
    "sg:address":"462 W 1st S",
    "sg:city":"Salt Lake City",
    "sg:classifiers":[
        {
            "category":"Health Services",
            "subcategory":"Optometrist",
            "type":"Services"
        }
    ],
    "sg:phone":"+1 801 532 5176",
    "sg:postcode":"84101",
    "sg:province":"UT",
    "wof:name":"Mortensen Spencer D Od A Prof",
    "wof:placetype":"venue"
},
  "geometry": {"coordinates":[-111.904402,40.767243],"type":"Point"}
}