{
  "type": "Feature",
  "properties": {
    "iso:country":"US",
    "sg:address":"975 E 120 S",
    "sg:city":"Spanish Fork",
    "sg:classifiers":[
        {
            "category":"Professional",
            "subcategory":"Management & Consulting",
            "type":"Services"
        }
    ],
    "sg:phone":"+1 801 798 1189",
    "sg:postcode":"84660",
    "sg:province":"UT",
    "wof:name":"Kennally Creek Marketing Inc",
    "wof:placetype":"venue"
},
  "geometry": {"coordinates":[-111.634889,40.108181],"type":"Point"}
}