{
  "type": "Feature",
  "properties": {
    "iso:country":"US",
    "sg:address":"3688 E Campus Drive, #240",
    "sg:city":"Eagle Mountain",
    "sg:classifiers":[
        {
            "category":"Professional",
            "subcategory":"Computer Services",
            "type":"Services"
        }
    ],
    "sg:phone":"+1 888 633 9269",
    "sg:postcode":"84005",
    "sg:province":"UT",
    "sg:website":"http://www.iapplicants.com/",
    "wof:name":"Iapplicants",
    "wof:placetype":"venue"
},
  "geometry": {"coordinates":[-111.68607799999999,40.301683],"type":"Point"}
}