{
  "type": "Feature",
  "properties": {
    "iso:country":"US",
    "sg:address":"16 W 800 S",
    "sg:city":"Salt Lake City",
    "sg:classifiers":[
        {
            "category":"Retail",
            "subcategory":"Auto Repair",
            "type":"Services"
        }
    ],
    "sg:phone":"+1 801 363 7289",
    "sg:postcode":"84101",
    "sg:province":"UT",
    "sg:tags":[
        "body",
        "automotive",
        "painting",
        "automobile"
    ],
    "wof:name":"L W Auto Body Shop Inc",
    "wof:placetype":"venue"
},
  "geometry": {"coordinates":[-111.89156199999999,40.752025],"type":"Point"}
}