{
  "type": "Feature",
  "properties": {
    "iso:country":"US",
    "sg:address":"1749 W 7800 S",
    "sg:city":"West Jordan",
    "sg:classifiers":[
        {
            "category":"Professional",
            "subcategory":"Employment Agencies",
            "type":"Services"
        }
    ],
    "sg:phone":"+1 801 561 9191",
    "sg:postcode":"84088",
    "sg:province":"UT",
    "wof:name":"Intermountain Employment Svcs",
    "wof:placetype":"venue"
},
  "geometry": {"coordinates":[-111.940375,40.609439],"type":"Point"}
}