{
  "type": "Feature",
  "properties": {
    "iso:country":"US",
    "sg:address":"2611 S 9080 W",
    "sg:city":"Magna",
    "sg:classifiers":[
        {
            "category":"Government",
            "subcategory":"Office",
            "type":"Public Place"
        }
    ],
    "sg:phone":"+1 801 250 7765",
    "sg:postcode":"84044",
    "sg:province":"UT",
    "wof:name":"Magna Mosquito Abatement",
    "wof:placetype":"venue"
},
  "geometry": {"coordinates":[-112.10795899999999,40.711164],"type":"Point"}
}