{
  "type": "Feature",
  "properties": {
    "iso:country":"US",
    "sg:address":"224 N Scenic Dr W",
    "sg:city":"Washington",
    "sg:classifiers":[
        {
            "category":"Professional",
            "subcategory":"Computer Services",
            "type":"Services"
        }
    ],
    "sg:phone":"+1 435 673 6332",
    "sg:postcode":"84780",
    "sg:province":"UT",
    "sg:tags":[
        "related"
    ],
    "wof:name":"Southern Utah Electronics",
    "wof:placetype":"venue"
},
  "geometry": {"coordinates":[-113.499359,37.135429],"type":"Point"}
}