{
  "type": "Feature",
  "properties": {
    "iso:country":"US",
    "sg:address":"2158 Buckboard Dr",
    "sg:city":"Cedar City",
    "sg:classifiers":[
        {
            "category":"Personal",
            "subcategory":"Beauty Salon",
            "type":"Services"
        }
    ],
    "sg:phone":"+1 435 586 1550",
    "sg:postcode":"84720",
    "sg:province":"UT",
    "sg:tags":[
        "shop"
    ],
    "wof:name":"Personal Touch Salon",
    "wof:placetype":"venue"
},
  "geometry": {"coordinates":[-113.051018,37.716219],"type":"Point"}
}