{
  "type": "Feature",
  "properties": {
    "iso:country":"US",
    "sg:address":"5580 Leo Park Rd",
    "sg:city":"West Jordan",
    "sg:classifiers":[
        {
            "category":"Real Estate",
            "subcategory":"Real Estate Operator",
            "type":"Services"
        }
    ],
    "sg:phone":"+1 801 280 3712",
    "sg:postcode":"84088",
    "sg:province":"UT",
    "sg:tags":[
        "building",
        "nonresidential"
    ],
    "wof:name":"Wsl Property Corporation",
    "wof:placetype":"venue"
},
  "geometry": {"coordinates":[-112.02349,40.579999],"type":"Point"}
}