{
  "type": "Feature",
  "properties": {
    "iso:country":"US",
    "sg:address":"1663 N 40 E",
    "sg:city":"Lehi",
    "sg:classifiers":[
        {
            "category":"Professional",
            "subcategory":"Computer Services",
            "type":"Services"
        }
    ],
    "sg:phone":"+1 801 768 3206",
    "sg:postcode":"84043",
    "sg:province":"UT",
    "sg:tags":[
        "related"
    ],
    "wof:name":"Xy Workshop LLC",
    "wof:placetype":"venue"
},
  "geometry": {"coordinates":[-111.848889,40.408046],"type":"Point"}
}