{
  "type": "Feature",
  "properties": {
    "iso:country":"US",
    "sg:address":"2821 W 880 N",
    "sg:city":"Provo",
    "sg:classifiers":[
        {
            "category":"Autos & Motor Vehicles",
            "subcategory":"Motorcycle Sales",
            "type":"Retail Goods"
        }
    ],
    "sg:phone":"+1 801 836 8280",
    "sg:postcode":"84601",
    "sg:province":"UT",
    "wof:name":"Sol Scooters LLC",
    "wof:placetype":"venue"
},
  "geometry": {"coordinates":[-111.71108,40.245437],"type":"Point"}
}