{
  "type": "Feature",
  "properties": {
    "iso:country":"US",
    "sg:address":"1945 Falcon Way",
    "sg:city":"Sandy",
    "sg:classifiers":[
        {
            "category":"Professional",
            "subcategory":"Business Services",
            "type":"Services"
        },
        {
            "category":"Manufacturing",
            "subcategory":"Apparel",
            "type":"Manufacturing & Wholesale Goods"
        }
    ],
    "sg:phone":"+1 801 572 2574",
    "sg:postcode":"84093",
    "sg:province":"UT",
    "sg:tags":[
        "embroidery"
    ],
    "wof:name":"Falcon Embroidery Inc",
    "wof:placetype":"venue"
},
  "geometry": {"coordinates":[-111.836201,40.584834],"type":"Point"}
}