{
  "type": "Feature",
  "properties": {
    "iso:country":"US",
    "sg:address":"123 S 1380 W",
    "sg:city":"Lindon",
    "sg:classifiers":[
        {
            "category":"Mining & Drilling",
            "type":"Manufacturing & Wholesale Goods"
        }
    ],
    "sg:phone":"+1 801 785 7051",
    "sg:postcode":"84042",
    "sg:province":"UT",
    "sg:tags":[
        "stone"
    ],
    "wof:name":"Terra Bella Inc",
    "wof:placetype":"venue"
},
  "geometry": {"coordinates":[-111.747767,40.3349],"type":"Point"}
}