{
  "type": "Feature",
  "properties": {
    "iso:country":"US",
    "sg:address":"4774 S State St",
    "sg:city":"Salt Lake City",
    "sg:classifiers":[
        {
            "category":"Retail",
            "subcategory":"Laundry & Dry Cleaning",
            "type":"Services"
        }
    ],
    "sg:phone":"+1 801 266 1851",
    "sg:postcode":"84107",
    "sg:province":"UT",
    "sg:tags":[
        "cleaners"
    ],
    "wof:name":"Prompt Drycleaners and Carwash",
    "wof:placetype":"venue"
},
  "geometry": {"coordinates":[-111.888352,40.668038],"type":"Point"}
}