{
  "type": "Feature",
  "properties": {
    "iso:country":"US",
    "sg:address":"4 Bonanza Ct",
    "sg:city":"Park City",
    "sg:classifiers":[
        {
            "category":"Real Estate",
            "subcategory":"Real Estate Operator",
            "type":"Services"
        }
    ],
    "sg:phone":"+1 435 649 3551",
    "sg:postcode":"84060",
    "sg:province":"UT",
    "sg:tags":[
        "condominium"
    ],
    "sg:website":"www.alpenhauslodging.com",
    "wof:name":"Alpenhaus Lodging",
    "wof:placetype":"venue"
},
  "geometry": {"coordinates":[-111.52013700000001,40.667804],"type":"Point"}
}