{
  "type": "Feature",
  "properties": {
    "iso:country":"US",
    "sg:address":"7755 N 4000 W",
    "sg:city":"Delta",
    "sg:phone":"+1 435 864 3280",
    "sg:postcode":"84624",
    "sg:province":"UT",
    "sg:tags":[
        "farm",
        "field",
        "crop"
    ],
    "wof:name":"June Losee",
    "wof:placetype":"venue"
},
  "geometry": {"coordinates":[-112.64963,39.469064],"type":"Point"}
}