{
  "type": "Feature",
  "properties": {
    "iso:country":"US",
    "sg:address":"909 Ranch Cir",
    "sg:city":"Draper",
    "sg:classifiers":[
        {
            "category":"Insurance",
            "subcategory":"Insurance Agent",
            "type":"Services"
        }
    ],
    "sg:phone":"+1 801 576 5648",
    "sg:postcode":"84020",
    "sg:province":"UT",
    "wof:name":"Berrick Insur & Inv Enterpr",
    "wof:placetype":"venue"
},
  "geometry": {"coordinates":[-111.867034,40.499712],"type":"Point"}
}