{
  "type": "Feature",
  "properties": {
    "iso:country":"US",
    "sg:address":"5376 S 1900 W",
    "sg:city":"Roy",
    "sg:classifiers":[
        {
            "category":"Shopping",
            "subcategory":"Pharmacy",
            "type":"Retail Goods"
        }
    ],
    "sg:phone":"+1 801 779 9675",
    "sg:postcode":"84067",
    "sg:province":"UT",
    "wof:name":"Wright Aid",
    "wof:placetype":"venue"
},
  "geometry": {"coordinates":[-112.025953,41.165945],"type":"Point"}
}