{
  "type": "Feature",
  "properties": {
    "iso:country":"US",
    "sg:address":"3403 Decker Lake Dr",
    "sg:city":"Salt Lake City",
    "sg:classifiers":[
        {
            "category":"Restaurant",
            "type":"Food & Drink"
        }
    ],
    "sg:menulink":"http://www.allmenus.com/ut/salt-lake-city/37053-chilis/menu/",
    "sg:phone":"+1 801 908 6006",
    "sg:postcode":"84119",
    "sg:province":"UT",
    "sg:tags":[
        "burger",
        "american",
        "sandwich",
        "tex-mex",
        "soup"
    ],
    "wof:name":"Chili's",
    "wof:placetype":"venue"
},
  "geometry": {"coordinates":[-111.94666700000001,40.698765],"type":"Point"}
}