{
  "type": "Feature",
  "properties": {
    "iso:country":"US",
    "sg:address":"1433 Granada Dr",
    "sg:city":"Sandy",
    "sg:classifiers":[
        {
            "category":"Real Estate",
            "subcategory":"Real Estate Agent",
            "type":"Services"
        }
    ],
    "sg:phone":"+1 801 561 9592",
    "sg:postcode":"84093",
    "sg:province":"UT",
    "wof:name":"Cross Roads Realty Inc",
    "wof:placetype":"venue"
},
  "geometry": {"coordinates":[-111.849997,40.588201],"type":"Point"}
}