{
  "type": "Feature",
  "properties": {
    "iso:country":"US",
    "sg:address":"877 E Saint George Blvd",
    "sg:city":"St George",
    "sg:classifiers":[
        {
            "category":"Restaurant",
            "type":"Food & Drink"
        }
    ],
    "sg:phone":"+1 435 656 1621",
    "sg:postcode":"84770",
    "sg:province":"UT",
    "sg:tags":[
        "eating"
    ],
    "wof:name":"Kentucky Fried Chicken/A & W",
    "wof:placetype":"venue"
},
  "geometry": {"coordinates":[-113.564927,37.109866],"type":"Point"}
}