{
  "type": "Feature",
  "properties": {
    "iso:country":"US",
    "sg:address":"272 E Center St",
    "sg:city":"Ivins",
    "sg:classifiers":[
        {
            "category":"Health Services",
            "subcategory":"Doctor",
            "type":"Services"
        }
    ],
    "sg:phone":"+1 435 656 5136",
    "sg:postcode":"84738",
    "sg:province":"UT",
    "sg:tags":[
        "physician",
        "surgeon"
    ],
    "wof:name":"Snow Canyon Cancer Clinic",
    "wof:placetype":"venue"
},
  "geometry": {"coordinates":[-113.67169699999999,37.168309],"type":"Point"}
}