{
  "type": "Feature",
  "properties": {
    "iso:country":"US",
    "sg:address":"1492 S State St",
    "sg:city":"Salt Lake City",
    "sg:classifiers":[
        {
            "category":"Bars & Pubs",
            "type":"Food & Drink"
        }
    ],
    "sg:phone":"+1 801 468 1492",
    "sg:postcode":"84115",
    "sg:province":"UT",
    "sg:tags":[
        "club",
        "night"
    ],
    "wof:name":"Piper Down & Olde World Pub",
    "wof:placetype":"venue"
},
  "geometry": {"coordinates":[-111.888285,40.738188],"type":"Point"}
}