{
  "type": "Feature",
  "properties": {
    "iso:country":"US",
    "sg:address":"236 S 1200 W",
    "sg:city":"Orem",
    "sg:classifiers":[
        {
            "category":"Banks & Credit Unions",
            "subcategory":"Investment Brokerage",
            "type":"Services"
        }
    ],
    "sg:phone":"+1 801 225 7214",
    "sg:postcode":"84058",
    "sg:province":"UT",
    "wof:name":"Deseret Investments",
    "wof:placetype":"venue"
},
  "geometry": {"coordinates":[-111.724288,40.293558],"type":"Point"}
}