{
  "type": "Feature",
  "properties": {
    "iso:country":"US",
    "sg:address":"2142 W Horse Aly",
    "sg:city":"Cedar City",
    "sg:classifiers":[
        {
            "category":"Autos & Motor Vehicles",
            "subcategory":"Automobile Sales",
            "type":"Retail Goods"
        }
    ],
    "sg:phone":"+1 435 867 9057",
    "sg:postcode":"84720",
    "sg:province":"UT",
    "sg:tags":[
        "car",
        "dealer"
    ],
    "wof:name":"Urie Auto",
    "wof:placetype":"venue"
},
  "geometry": {"coordinates":[-113.08773600000001,37.68514],"type":"Point"}
}