{
  "type": "Feature",
  "properties": {
    "iso:country":"US",
    "sg:address":"2899 N Indian Hills Dr",
    "sg:city":"Provo",
    "sg:classifiers":[
        {
            "category":"Shopping",
            "subcategory":"Florist",
            "type":"Retail Goods"
        }
    ],
    "sg:phone":"+1 801 375 8270",
    "sg:postcode":"84604",
    "sg:province":"UT",
    "wof:name":"Jeanies Flowers",
    "wof:placetype":"venue"
},
  "geometry": {"coordinates":[-111.641063,40.271646],"type":"Point"}
}