{
  "type": "Feature",
  "properties": {
    "iso:country":"US",
    "sg:address":"430 N 200 E",
    "sg:city":"Spanish Fork",
    "sg:classifiers":[
        {
            "category":"Professional",
            "subcategory":"Art Services",
            "type":"Services"
        }
    ],
    "sg:phone":"+1 801 798 2995",
    "sg:postcode":"84660",
    "sg:province":"UT",
    "sg:tags":[
        "photographer"
    ],
    "sg:website":"www.artinnature.com",
    "wof:name":"Elite Photography By John",
    "wof:placetype":"venue"
},
  "geometry": {"coordinates":[-111.651186,40.115896],"type":"Point"}
}