{
  "type": "Feature",
  "properties": {
    "iso:country":"US",
    "sg:address":"4541 Peach St",
    "sg:city":"Salt Lake City",
    "sg:classifiers":[
        {
            "category":"Manufacturing",
            "subcategory":"Food",
            "type":"Manufacturing & Wholesale Goods"
        }
    ],
    "sg:phone":"+1 435 731 0357",
    "sg:postcode":"84117",
    "sg:province":"UT",
    "sg:tags":[
        "vineyard"
    ],
    "wof:name":"Kiler Grove Winegrowers LLC",
    "wof:placetype":"venue"
},
  "geometry": {"coordinates":[-111.80944700000001,40.672044],"type":"Point"}
}