{
  "type": "Feature",
  "properties": {
    "iso:country":"US",
    "sg:address":"110 E 200 N",
    "sg:city":"Logan",
    "sg:classifiers":[
        {
            "category":"Health Services",
            "subcategory":"Doctor",
            "type":"Services"
        }
    ],
    "sg:phone":"+1 435 752 0300",
    "sg:postcode":"84321",
    "sg:province":"UT",
    "sg:tags":[
        "dentist"
    ],
    "wof:name":"Gary Foster DDS",
    "wof:placetype":"venue"
},
  "geometry": {"coordinates":[-111.83204600000001,41.735102],"type":"Point"}
}