{
  "type": "Feature",
  "properties": {
    "iso:country":"US",
    "sg:address":"1080 N Main St",
    "sg:city":"Brigham City",
    "sg:classifiers":[
        {
            "category":"Real Estate",
            "subcategory":"Real Estate Services",
            "type":"Services"
        }
    ],
    "sg:phone":"+1 801 393 6898",
    "sg:postcode":"84302",
    "sg:province":"UT",
    "sg:tags":[
        "abstract",
        "title"
    ],
    "wof:name":"American Secure Title",
    "wof:placetype":"venue"
},
  "geometry": {"coordinates":[-112.015368,41.530541],"type":"Point"}
}