{
  "type": "Feature",
  "properties": {
    "iso:country":"US",
    "sg:address":"209 N 775 E",
    "sg:city":"American Fork",
    "sg:classifiers":[
        {
            "category":"Manufacturing",
            "subcategory":"Printing",
            "type":"Manufacturing & Wholesale Goods"
        }
    ],
    "sg:phone":"+1 801 756 5171",
    "sg:postcode":"84003",
    "sg:province":"UT",
    "sg:tags":[
        "publishing"
    ],
    "wof:name":"Dymon Publications",
    "wof:placetype":"venue"
},
  "geometry": {"coordinates":[-111.777823,40.381415],"type":"Point"}
}