{
  "type": "Feature",
  "properties": {
    "iso:country":"US",
    "sg:address":"3693 S 300 W",
    "sg:city":"Salt Lake City",
    "sg:classifiers":[
        {
            "category":"Autos & Motor Vehicles",
            "subcategory":"Automobile Sales",
            "type":"Retail Goods"
        }
    ],
    "sg:phone":"+1 801 293 3349",
    "sg:postcode":"84115",
    "sg:province":"UT",
    "sg:tags":[
        "car",
        "dealer"
    ],
    "wof:name":"Singer Auto Sales LLC",
    "wof:placetype":"venue"
},
  "geometry": {"coordinates":[-111.89967,40.689929],"type":"Point"}
}