{
  "type": "Feature",
  "properties": {
    "iso:country":"US",
    "sg:address":"4574 W 1350 S",
    "sg:city":"Ogden",
    "sg:classifiers":[
        {
            "category":"Personal",
            "subcategory":"Beauty Salon",
            "type":"Services"
        }
    ],
    "sg:phone":"+1 801 732 8287",
    "sg:postcode":"84401",
    "sg:province":"UT",
    "sg:tags":[
        "shop"
    ],
    "wof:name":"Skj A Family Affair LLC",
    "wof:placetype":"venue"
},
  "geometry": {"coordinates":[-112.088796,41.243234],"type":"Point"}
}