{
  "type": "Feature",
  "properties": {
    "iso:country":"US",
    "sg:address":"2261 S State St",
    "sg:city":"Salt Lake City",
    "sg:classifiers":[
        {
            "category":"Building & Trades",
            "subcategory":"Equipment Rental",
            "type":"Services"
        }
    ],
    "sg:phone":"+1 801 485 7368",
    "sg:postcode":"84115",
    "sg:province":"UT",
    "wof:name":"Rent-A-Center",
    "wof:placetype":"venue"
},
  "geometry": {"coordinates":[-111.888158,40.721671],"type":"Point"}
}