{
  "type": "Feature",
  "properties": {
    "iso:country":"US",
    "sg:address":"3640 S 1550 W",
    "sg:city":"St George",
    "sg:classifiers":[
        {
            "category":"Real Estate",
            "subcategory":"Real Estate Operator",
            "type":"Services"
        }
    ],
    "sg:phone":"+1 812 853 7126",
    "sg:postcode":"84790",
    "sg:province":"UT",
    "sg:tags":[
        "building",
        "nonresidential"
    ],
    "wof:name":"Rbg Properties L L C",
    "wof:placetype":"venue"
},
  "geometry": {"coordinates":[-113.617126,37.046406],"type":"Point"}
}