{
  "type": "Feature",
  "properties": {
    "iso:country":"US",
    "sg:address":"1600 S 3600 E",
    "sg:city":"Heber City",
    "sg:classifiers":[
        {
            "category":"Building & Trades",
            "subcategory":"Construction",
            "type":"Services"
        }
    ],
    "sg:phone":"+1 435 654 4935",
    "sg:postcode":"84032",
    "sg:province":"UT",
    "sg:tags":[
        "excavation",
        "contractor"
    ],
    "wof:name":"Wall Trucking & Excavating",
    "wof:placetype":"venue"
},
  "geometry": {"coordinates":[-111.35727799999999,40.489179],"type":"Point"}
}