{
  "type": "Feature",
  "properties": {
    "iso:country":"US",
    "sg:address":"757 Country Club",
    "sg:city":"Tooele",
    "sg:classifiers":[
        {
            "category":"Building & Trades",
            "subcategory":"Construction",
            "type":"Services"
        }
    ],
    "sg:phone":"+1 435 833 0469",
    "sg:postcode":"84074",
    "sg:province":"UT",
    "sg:tags":[
        "contractor"
    ],
    "wof:name":"Design Build Operate Svcs LLC",
    "wof:placetype":"venue"
},
  "geometry": {"coordinates":[-112.29788499999999,40.635942],"type":"Point"}
}