{
  "type": "Feature",
  "properties": {
    "iso:country":"US",
    "sg:address":"558 W 1300 N",
    "sg:city":"Orem",
    "sg:classifiers":[
        {
            "category":"Professional",
            "subcategory":"Management & Consulting",
            "type":"Services"
        }
    ],
    "sg:phone":"+1 801 358 7411",
    "sg:postcode":"84057",
    "sg:province":"UT",
    "sg:tags":[
        "consultant",
        "business"
    ],
    "wof:name":"TSG",
    "wof:placetype":"venue"
},
  "geometry": {"coordinates":[-111.709452,40.321076],"type":"Point"}
}