{
  "type": "Feature",
  "properties": {
    "iso:country":"US",
    "sg:address":"91 S Sherwood Dr",
    "sg:city":"Providence",
    "sg:classifiers":[
        {
            "category":"Professional",
            "type":"Services"
        }
    ],
    "sg:phone":"+1 435 753 1023",
    "sg:postcode":"84332",
    "sg:province":"UT",
    "wof:name":"Dnr Enterprises",
    "wof:placetype":"venue"
},
  "geometry": {"coordinates":[-111.797383,41.703579],"type":"Point"}
}