{
  "type": "Feature",
  "properties": {
    "iso:country":"US",
    "sg:address":"922 W 1300 N",
    "sg:city":"Price",
    "sg:classifiers":[
        {
            "category":"Building & Trades",
            "subcategory":"Construction",
            "type":"Services"
        }
    ],
    "sg:phone":"+1 435 637 4383",
    "sg:postcode":"84501",
    "sg:province":"UT",
    "sg:tags":[
        "contractor"
    ],
    "wof:name":"Western Alloy Wldg Fabrication",
    "wof:placetype":"venue"
},
  "geometry": {"coordinates":[-110.83219,39.619738],"type":"Point"}
}