{
  "type": "Feature",
  "properties": {
    "iso:country":"US",
    "sg:address":"1876 N Concord Pl",
    "sg:city":"Lehi",
    "sg:classifiers":[
        {
            "category":"Retail",
            "subcategory":"Portrait Studio",
            "type":"Services"
        }
    ],
    "sg:phone":"+1 801 766 0624",
    "sg:postcode":"84043",
    "sg:province":"UT",
    "sg:tags":[
        "photo"
    ],
    "wof:name":"JW Photography",
    "wof:placetype":"venue"
},
  "geometry": {"coordinates":[-111.927153,40.397394],"type":"Point"}
}