{
  "type": "Feature",
  "properties": {
    "iso:country":"US",
    "sg:address":"1811 N 450 E",
    "sg:city":"Ogden",
    "sg:classifiers":[
        {
            "category":"Building & Trades",
            "subcategory":"Construction",
            "type":"Services"
        }
    ],
    "sg:phone":"+1 801 782 3271",
    "sg:postcode":"84414",
    "sg:province":"UT",
    "sg:tags":[
        "drywall",
        "contractor"
    ],
    "wof:name":"Drywall Subcontractor",
    "wof:placetype":"venue"
},
  "geometry": {"coordinates":[-111.966735,41.291484],"type":"Point"}
}