{
  "type": "Feature",
  "properties": {
    "iso:country":"US",
    "sg:address":"3251 S 2300 E",
    "sg:city":"Salt Lake City",
    "sg:classifiers":[
        {
            "category":"Retail",
            "subcategory":"Funeral Services",
            "type":"Services"
        }
    ],
    "sg:phone":"+1 801 484 2045",
    "sg:postcode":"84109",
    "sg:province":"UT",
    "sg:tags":[
        "director"
    ],
    "sg:website":"www.holbrookmortuary.com",
    "wof:name":"Holbrook Mortuary",
    "wof:placetype":"venue"
},
  "geometry": {"coordinates":[-111.824387,40.7002],"type":"Point"}
}