{
  "type": "Feature",
  "properties": {
    "iso:country":"US",
    "sg:address":"2020 S 700 E",
    "sg:city":"Salt Lake City",
    "sg:classifiers":[
        {
            "category":"Shopping",
            "subcategory":"Bicycles & Sporting Goods",
            "type":"Retail Goods"
        }
    ],
    "sg:phone":"+1 801 486 4449",
    "sg:postcode":"84105",
    "sg:province":"UT",
    "wof:name":"Soccer Plus",
    "wof:placetype":"venue"
},
  "geometry": {"coordinates":[-111.871089,40.726712],"type":"Point"}
}