{
  "type": "Feature",
  "properties": {
    "iso:country":"US",
    "sg:address":"1662 Transwest Dr",
    "sg:city":"Sandy",
    "sg:classifiers":[
        {
            "category":"Real Estate",
            "subcategory":"Real Estate Agent",
            "type":"Services"
        }
    ],
    "sg:phone":"+1 801 816 0729",
    "sg:postcode":"84092",
    "sg:province":"UT",
    "sg:tags":[
        "inspection"
    ],
    "wof:name":"A Complete Home Inspection Svc",
    "wof:placetype":"venue"
},
  "geometry": {"coordinates":[-111.84408999999999,40.548828],"type":"Point"}
}