{
  "type": "Feature",
  "properties": {
    "iso:country":"US",
    "sg:address":"520 N Redwood Rd",
    "sg:city":"North Salt Lake",
    "sg:classifiers":[
        {
            "category":"Wholesale",
            "subcategory":"Durable Goods & Equipment",
            "type":"Manufacturing & Wholesale Goods"
        }
    ],
    "sg:phone":"+1 801 292 0656",
    "sg:postcode":"84054",
    "sg:province":"UT",
    "sg:tags":[
        "importer"
    ],
    "sg:website":"www.crestware.com",
    "wof:name":"Crestware",
    "wof:placetype":"venue"
},
  "geometry": {"coordinates":[-111.929614,40.847891],"type":"Point"}
}