{
  "type": "Feature",
  "properties": {
    "iso:country":"US",
    "sg:address":"360 State St",
    "sg:city":"Clearfield",
    "sg:classifiers":[
        {
            "category":"Professional",
            "subcategory":"Management & Consulting",
            "type":"Services"
        },
        {
            "category":"Shopping",
            "subcategory":"Clothing, Apparel, & Fashions",
            "type":"Retail Goods"
        }
    ],
    "sg:phone":"+1 801 773 4552",
    "sg:postcode":"84015",
    "sg:province":"UT",
    "sg:tags":[
        "lingerie",
        "group",
        "sales",
        "direct"
    ],
    "sg:website":"www.ladydesiree.com",
    "wof:name":"Lady Desiree",
    "wof:placetype":"venue"
},
  "geometry": {"coordinates":[-112.02077300000001,41.108538],"type":"Point"}
}