{
  "type": "Feature",
  "properties": {
    "iso:country":"US",
    "sg:address":"8825 S 1095 W",
    "sg:city":"West Jordan",
    "sg:classifiers":[
        {
            "category":"Organizations",
            "subcategory":"Religious Organization",
            "type":"Services"
        }
    ],
    "sg:phone":"+1 801 562 8268",
    "sg:postcode":"84088",
    "sg:province":"UT",
    "sg:tags":[
        "mormon",
        "church"
    ],
    "wof:name":"Bingham Creek Eighth",
    "wof:placetype":"venue"
},
  "geometry": {"coordinates":[-111.922533,40.590914],"type":"Point"}
}