{
  "type": "Feature",
  "properties": {
    "iso:country":"US",
    "sg:address":"435 N 1680 E",
    "sg:city":"St George",
    "sg:classifiers":[
        {
            "category":"Professional",
            "subcategory":"Management & Consulting",
            "type":"Services"
        }
    ],
    "sg:phone":"+1 435 986 0016",
    "sg:postcode":"84790",
    "sg:province":"UT",
    "wof:name":"Inches-A-Weigh Inc",
    "wof:placetype":"venue"
},
  "geometry": {"coordinates":[-113.54758,37.116291],"type":"Point"}
}