{
  "type": "Feature",
  "properties": {
    "iso:country":"US",
    "sg:address":"8989 Schofield Cir",
    "sg:city":"Sandy",
    "sg:classifiers":[
        {
            "category":"Insurance",
            "subcategory":"Insurance Agent",
            "type":"Services"
        }
    ],
    "sg:phone":"+1 801 569 0828",
    "sg:postcode":"84093",
    "sg:province":"UT",
    "wof:name":"Joe & Mlnda Johnson Fmly Insur",
    "wof:placetype":"venue"
},
  "geometry": {"coordinates":[-111.819963,40.587808],"type":"Point"}
}