{
  "type": "Feature",
  "properties": {
    "iso:country":"US",
    "sg:address":"920 Heritage Park Blvd",
    "sg:city":"Layton",
    "sg:classifiers":[
        {
            "category":"Insurance",
            "subcategory":"Hazard Insurance",
            "type":"Services"
        }
    ],
    "sg:phone":"+1 801 825 9700",
    "sg:postcode":"84041",
    "sg:province":"UT",
    "sg:tags":[
        "warranty",
        "program"
    ],
    "wof:name":"Frontier Home Warranty",
    "wof:placetype":"venue"
},
  "geometry": {"coordinates":[-111.979471,41.083197],"type":"Point"}
}