{
  "type": "Feature",
  "properties": {
    "iso:country":"US",
    "sg:address":"426 S 1000 E",
    "sg:city":"Salt Lake City",
    "sg:classifiers":[
        {
            "category":"Professional",
            "type":"Services"
        }
    ],
    "sg:phone":"+1 801 973 2670",
    "sg:postcode":"84102",
    "sg:province":"UT",
    "sg:tags":[
        "establishment"
    ],
    "wof:name":"Mor Lite Inc",
    "wof:placetype":"venue"
},
  "geometry": {"coordinates":[-111.862533,40.76033],"type":"Point"}
}