{
  "type": "Feature",
  "properties": {
    "iso:country":"US",
    "sg:address":"275 E 100 S",
    "sg:city":"Morgan",
    "sg:classifiers":[
        {
            "category":"Real Estate",
            "subcategory":"Developer",
            "type":"Services"
        }
    ],
    "sg:phone":"+1 801 829 6681",
    "sg:postcode":"84050",
    "sg:province":"UT",
    "wof:name":"Kamelot Development Company",
    "wof:placetype":"venue"
},
  "geometry": {"coordinates":[-111.672764,41.035606],"type":"Point"}
}