{
  "type": "Feature",
  "properties": {
    "iso:country":"US",
    "sg:address":"373 N 300 E",
    "sg:city":"Bountiful",
    "sg:classifiers":[
        {
            "category":"Retail",
            "subcategory":"Portrait Studio",
            "type":"Services"
        }
    ],
    "sg:phone":"+1 801 292 8064",
    "sg:postcode":"84010",
    "sg:province":"UT",
    "sg:tags":[
        "photographer"
    ],
    "wof:name":"Morganarts",
    "wof:placetype":"venue"
},
  "geometry": {"coordinates":[-111.873999,40.892859],"type":"Point"}
}