{
  "type": "Feature",
  "properties": {
    "iso:country":"US",
    "sg:address":"2681 Parleys Way",
    "sg:city":"Salt Lake City",
    "sg:classifiers":[
        {
            "category":"Professional",
            "type":"Services"
        }
    ],
    "sg:phone":"+1 801 466 8944",
    "sg:postcode":"84109",
    "sg:province":"UT",
    "sg:tags":[
        "establishment"
    ],
    "wof:name":"Sound & Light",
    "wof:placetype":"venue"
},
  "geometry": {"coordinates":[-111.814187,40.718922],"type":"Point"}
}