{
  "type": "Feature",
  "properties": {
    "iso:country":"US",
    "sg:address":"1072 E Sleepy Hollow Ln",
    "sg:city":"Sandy",
    "sg:classifiers":[
        {
            "category":"Building & Trades",
            "subcategory":"Construction",
            "type":"Services"
        }
    ],
    "sg:phone":"+1 801 571 8170",
    "sg:postcode":"84094",
    "sg:province":"UT",
    "sg:tags":[
        "house"
    ],
    "wof:name":"Crystal Homes Inc",
    "wof:placetype":"venue"
},
  "geometry": {"coordinates":[-111.86087999999999,40.575588],"type":"Point"}
}