{
  "type": "Feature",
  "properties": {
    "iso:country":"US",
    "sg:address":"328 N Highway 89",
    "sg:city":"North Salt Lake",
    "sg:classifiers":[
        {
            "category":"Shopping",
            "subcategory":"Luggage & Leather Goods",
            "type":"Retail Goods"
        }
    ],
    "sg:phone":"+1 801 294 9303",
    "sg:postcode":"84054",
    "sg:province":"UT",
    "wof:name":"International Luggage Center",
    "wof:placetype":"venue"
},
  "geometry": {"coordinates":[-111.906998,40.848499],"type":"Point"}
}