{
  "type": "Feature",
  "properties": {
    "iso:country":"US",
    "sg:address":"3106 Homestead Rd",
    "sg:city":"Park City",
    "sg:classifiers":[
        {
            "category":"Professional",
            "subcategory":"Business Services",
            "type":"Services"
        }
    ],
    "sg:phone":"+1 435 647 3062",
    "sg:postcode":"84098",
    "sg:province":"UT",
    "wof:name":"Wangsgard & Associates LLC",
    "wof:placetype":"venue"
},
  "geometry": {"coordinates":[-111.57134499999999,40.760243],"type":"Point"}
}