{
  "type": "Feature",
  "properties": {
    "iso:country":"US",
    "sg:address":"3350 Wall Ave",
    "sg:city":"Ogden",
    "sg:classifiers":[
        {
            "category":"Building & Trades",
            "subcategory":"Construction",
            "type":"Services"
        }
    ],
    "sg:phone":"+1 801 399 9199",
    "sg:postcode":"84401",
    "sg:province":"UT",
    "sg:tags":[
        "carpentry",
        "contractor"
    ],
    "wof:name":"Atlas Autoglass LLC",
    "wof:placetype":"venue"
},
  "geometry": {"coordinates":[-111.979253,41.200762],"type":"Point"}
}