{
  "type": "Feature",
  "properties": {
    "iso:country":"US",
    "sg:address":"5209 S 300 W",
    "sg:city":"Salt Lake City",
    "sg:classifiers":[
        {
            "category":"Wholesale",
            "subcategory":"Home Furnishings",
            "type":"Manufacturing & Wholesale Goods"
        }
    ],
    "sg:phone":"+1 801 266 4323",
    "sg:postcode":"84107",
    "sg:province":"UT",
    "sg:tags":[
        "picture",
        "frame"
    ],
    "wof:name":"Warehouse Framing Supply",
    "wof:placetype":"venue"
},
  "geometry": {"coordinates":[-111.89849599999999,40.660029],"type":"Point"}
}