{
  "type": "Feature",
  "properties": {
    "iso:country":"US",
    "sg:address":"378 N Main St",
    "sg:city":"Layton",
    "sg:classifiers":[
        {
            "category":"Restaurant",
            "type":"Food & Drink"
        }
    ],
    "sg:phone":"+1 801 547 0775",
    "sg:postcode":"84041",
    "sg:province":"UT",
    "sg:tags":[
        "shop",
        "parlor",
        "ice",
        "cream"
    ],
    "wof:name":"Nielsen's Frozen Custard",
    "wof:placetype":"venue"
},
  "geometry": {"coordinates":[-111.971704,41.066237],"type":"Point"}
}