{
  "type": "Feature",
  "properties": {
    "iso:country":"US",
    "sg:address":"43 S Main St",
    "sg:city":"Logan",
    "sg:classifiers":[
        {
            "category":"Education",
            "subcategory":"Vocational School",
            "type":"Public Place"
        }
    ],
    "sg:phone":"+1 435 750 5066",
    "sg:postcode":"84321",
    "sg:province":"UT",
    "wof:name":"Paint Utah Art Schl & Gallery",
    "wof:placetype":"venue"
},
  "geometry": {"coordinates":[-111.835086,41.730844],"type":"Point"}
}