{
  "type": "Feature",
  "properties": {
    "iso:country":"US",
    "sg:address":"225 Amafille Ln",
    "sg:city":"Payson",
    "sg:classifiers":[
        {
            "category":"Wholesale",
            "subcategory":"Non-durable Goods",
            "type":"Manufacturing & Wholesale Goods"
        }
    ],
    "sg:phone":"+1 801 423 8511",
    "sg:postcode":"84651",
    "sg:province":"UT",
    "sg:tags":[
        "advertising",
        "specialty"
    ],
    "wof:name":"Novelty Press",
    "wof:placetype":"venue"
},
  "geometry": {"coordinates":[-111.678793,40.018287],"type":"Point"}
}