{
  "type": "Feature",
  "properties": {
    "iso:country":"US",
    "sg:address":"701 W 600 N",
    "sg:city":"Logan",
    "sg:classifiers":[
        {
            "category":"Wholesale",
            "subcategory":"Construction Materials",
            "type":"Manufacturing & Wholesale Goods"
        }
    ],
    "sg:phone":"+1 435 752 9999",
    "sg:postcode":"84321",
    "sg:province":"UT",
    "sg:tags":[
        "sand",
        "gravel"
    ],
    "wof:name":"Logan Landscape Products",
    "wof:placetype":"venue"
},
  "geometry": {"coordinates":[-111.852512,41.743062],"type":"Point"}
}