{
  "type": "Feature",
  "properties": {
    "iso:country":"US",
    "sg:address":"3580 W 3650 S",
    "sg:city":"Salt Lake City",
    "sg:classifiers":[
        {
            "category":"Organizations",
            "subcategory":"Religious Organization",
            "type":"Services"
        }
    ],
    "sg:phone":"+1 801 966 5119",
    "sg:postcode":"84170",
    "sg:province":"UT",
    "sg:tags":[
        "church"
    ],
    "wof:name":"Saints Peter & Paul Catholic",
    "wof:placetype":"venue"
},
  "geometry": {"coordinates":[-111.97364399999999,40.692919],"type":"Point"}
}