{
  "type": "Feature",
  "properties": {
    "iso:country":"US",
    "sg:address":"30 W 100 S",
    "sg:city":"Kanab",
    "sg:classifiers":[
        {
            "category":"Social Services",
            "subcategory":"Child Care",
            "type":"Services"
        }
    ],
    "sg:phone":"+1 435 644 8111",
    "sg:postcode":"84741",
    "sg:province":"UT",
    "sg:tags":[
        "day"
    ],
    "wof:name":"Kanab Head Start",
    "wof:placetype":"venue"
},
  "geometry": {"coordinates":[-112.53009400000001,37.046477],"type":"Point"}
}