{
  "type": "Feature",
  "properties": {
    "iso:country":"US",
    "sg:address":"1303 S 320 E",
    "sg:city":"St George",
    "sg:classifiers":[
        {
            "category":"Manufacturing",
            "subcategory":"Printing",
            "type":"Manufacturing & Wholesale Goods"
        }
    ],
    "sg:phone":"+1 435 673 9210",
    "sg:postcode":"84790",
    "sg:province":"UT",
    "sg:tags":[
        "printer"
    ],
    "wof:name":"Rocky Mountain Printing",
    "wof:placetype":"venue"
},
  "geometry": {"coordinates":[-113.57680499999999,37.084495],"type":"Point"}
}