{
  "type": "Feature",
  "properties": {
    "iso:country":"US",
    "sg:address":"872 W 850 N",
    "sg:city":"Pleasant Grove",
    "sg:classifiers":[
        {
            "category":"Manufacturing",
            "subcategory":"Metals",
            "type":"Manufacturing & Wholesale Goods"
        }
    ],
    "sg:phone":"+1 801 796 6837",
    "sg:postcode":"84062",
    "sg:province":"UT",
    "sg:tags":[
        "mfg",
        "metalwork",
        "sheet",
        "contractor"
    ],
    "wof:name":"Star Manufacturing Inc",
    "wof:placetype":"venue"
},
  "geometry": {"coordinates":[-111.75222599999999,40.372706],"type":"Point"}
}