{
  "type": "Feature",
  "properties": {
    "iso:country":"US",
    "sg:address":"715 Chalk Creek Rd",
    "sg:city":"Coalville",
    "sg:classifiers":[
        {
            "category":"Government",
            "subcategory":"Office",
            "type":"Public Place"
        }
    ],
    "sg:phone":"+1 435 336 2289",
    "sg:postcode":"84017",
    "sg:province":"UT",
    "sg:tags":[
        "management"
    ],
    "wof:name":"Chalk Creek Water Distrib",
    "wof:placetype":"venue"
},
  "geometry": {"coordinates":[-111.358901,40.92463],"type":"Point"}
}