{
  "type": "Feature",
  "properties": {
    "iso:country":"US",
    "sg:address":"2072 N Main St",
    "sg:city":"Logan",
    "sg:classifiers":[
        {
            "category":"Banks & Credit Unions",
            "subcategory":"Bank",
            "type":"Services"
        }
    ],
    "sg:phone":"+1 435 752 2146",
    "sg:postcode":"84341",
    "sg:province":"UT",
    "sg:tags":[
        "agricultural",
        "loan",
        "banking"
    ],
    "wof:name":"Western Ag Credit",
    "wof:placetype":"venue"
},
  "geometry": {"coordinates":[-111.834017,41.771337],"type":"Point"}
}