{
  "type": "Feature",
  "properties": {
    "iso:country":"US",
    "sg:address":"5454 Paulette Ave",
    "sg:city":"Salt Lake City",
    "sg:classifiers":[
        {
            "category":"Real Estate",
            "subcategory":"Real Estate Operator",
            "type":"Services"
        }
    ],
    "sg:phone":"+1 801 486 1124",
    "sg:postcode":"84120",
    "sg:province":"UT",
    "sg:tags":[
        "building",
        "nonresidential"
    ],
    "wof:name":"Bldg Blocks Mgmt",
    "wof:placetype":"venue"
},
  "geometry": {"coordinates":[-112.022854,40.688017],"type":"Point"}
}