{
  "type": "Feature",
  "properties": {
    "iso:country":"US",
    "sg:address":"2350 Parleys Way",
    "sg:city":"Salt Lake City",
    "sg:classifiers":[
        {
            "category":"Building & Trades",
            "subcategory":"Plumbing",
            "type":"Services"
        }
    ],
    "sg:phone":"+1 801 467 3951",
    "sg:postcode":"84109",
    "sg:province":"UT",
    "sg:tags":[
        "plumbing",
        "heating",
        "contractor"
    ],
    "sg:website":"www.neeringsplumbing.com",
    "wof:name":"Neerings Plumbing & Heating",
    "wof:placetype":"venue"
},
  "geometry": {"coordinates":[-111.823533,40.724639],"type":"Point"}
}