{
  "type": "Feature",
  "properties": {
    "iso:country":"US",
    "sg:address":"391 Wall St",
    "sg:city":"Salt Lake City",
    "sg:classifiers":[
        {
            "category":"Building & Trades",
            "subcategory":"Construction",
            "type":"Services"
        }
    ],
    "sg:phone":"+1 801 264 9373",
    "sg:postcode":"84103",
    "sg:province":"UT",
    "sg:tags":[
        "contractor"
    ],
    "wof:name":"Wsl Designs Inc",
    "wof:placetype":"venue"
},
  "geometry": {"coordinates":[-111.89072400000001,40.777515],"type":"Point"}
}