{
  "type": "Feature",
  "properties": {
    "iso:country":"US",
    "sg:address":"1751 S Vernal Ave",
    "sg:city":"Vernal",
    "sg:classifiers":[
        {
            "category":"Retail",
            "subcategory":"Veterinary Services",
            "type":"Services"
        }
    ],
    "sg:phone":"+1 435 789 6697",
    "sg:postcode":"84078",
    "sg:province":"UT",
    "wof:name":"Countryside Veterinary Clinic",
    "wof:placetype":"venue"
},
  "geometry": {"coordinates":[-109.528127,40.430159],"type":"Point"}
}