{
  "type": "Feature",
  "properties": {
    "iso:country":"US",
    "sg:address":"58 E Main St",
    "sg:city":"Delta",
    "sg:classifiers":[
        {
            "category":"Shopping",
            "subcategory":"Optical Goods",
            "type":"Retail Goods"
        }
    ],
    "sg:phone":"+1 435 864 4268",
    "sg:postcode":"84624",
    "sg:province":"UT",
    "wof:name":"Delta Eyecare",
    "wof:placetype":"venue"
},
  "geometry": {"coordinates":[-112.573393,39.352273],"type":"Point"}
}