{
  "type": "Feature",
  "properties": {
    "iso:country":"US",
    "sg:address":"599 N 800 W",
    "sg:city":"Cedar City",
    "sg:classifiers":[
        {
            "category":"Education",
            "subcategory":"Dance Studio",
            "type":"Public Place"
        }
    ],
    "sg:phone":"+1 435 586 8130",
    "sg:postcode":"84720",
    "sg:province":"UT",
    "wof:name":"On Stage Dance Studio",
    "wof:placetype":"venue"
},
  "geometry": {"coordinates":[-113.074009,37.686217],"type":"Point"}
}