{
  "type": "Feature",
  "properties": {
    "iso:country":"US",
    "sg:address":"2290 E 11620 S",
    "sg:city":"Sandy",
    "sg:classifiers":[
        {
            "category":"Real Estate",
            "subcategory":"Real Estate Agent",
            "type":"Services"
        }
    ],
    "sg:phone":"+1 801 571 5150",
    "sg:postcode":"84092",
    "sg:province":"UT",
    "sg:tags":[
        "investment"
    ],
    "wof:name":"Annbrooke",
    "wof:placetype":"venue"
},
  "geometry": {"coordinates":[-111.82708100000001,40.540144],"type":"Point"}
}