{
  "type": "Feature",
  "properties": {
    "iso:country":"US",
    "sg:address":"36 E 200 S",
    "sg:city":"Logan",
    "sg:classifiers":[
        {
            "category":"Shopping",
            "type":"Retail Goods"
        }
    ],
    "sg:phone":"+1 435 753 9771",
    "sg:postcode":"84321",
    "sg:province":"UT",
    "sg:tags":[
        "merchandise"
    ],
    "wof:name":"Pet Kingdom LLC",
    "wof:placetype":"venue"
},
  "geometry": {"coordinates":[-111.83425099999999,41.727648],"type":"Point"}
}