{
  "type": "Feature",
  "properties": {
    "iso:country":"US",
    "sg:address":"365 E Center St",
    "sg:city":"Salem",
    "sg:classifiers":[
        {
            "category":"Manufacturing",
            "subcategory":"Printing",
            "type":"Manufacturing & Wholesale Goods"
        }
    ],
    "sg:phone":"+1 801 423 2912",
    "sg:postcode":"84653",
    "sg:province":"UT",
    "sg:tags":[
        "lithographic",
        "commercial"
    ],
    "wof:name":"Wild Hare Printing Company",
    "wof:placetype":"venue"
},
  "geometry": {"coordinates":[-111.66638399999999,40.05463],"type":"Point"}
}