{
  "type": "Feature",
  "properties": {
    "iso:country":"US",
    "sg:address":"4507 S Royal Ann Cir",
    "sg:city":"Salt Lake City",
    "sg:classifiers":[
        {
            "category":"Wholesale",
            "subcategory":"Home Furnishings",
            "type":"Manufacturing & Wholesale Goods"
        }
    ],
    "sg:phone":"+1 801 968 6894",
    "sg:postcode":"84120",
    "sg:province":"UT",
    "wof:name":"Creative Impressions",
    "wof:placetype":"venue"
},
  "geometry": {"coordinates":[-112.007514,40.672492],"type":"Point"}
}