{
  "type": "Feature",
  "properties": {
    "iso:country":"US",
    "sg:address":"8339 Argenta Dr",
    "sg:city":"West Jordan",
    "sg:classifiers":[
        {
            "category":"Building & Trades",
            "subcategory":"Landscaping Services",
            "type":"Services"
        }
    ],
    "sg:phone":"+1 801 580 7899",
    "sg:postcode":"84088",
    "sg:province":"UT",
    "wof:name":"Lawn & Leaf Co",
    "wof:placetype":"venue"
},
  "geometry": {"coordinates":[-112.004323,40.600439],"type":"Point"}
}