{
  "type": "Feature",
  "properties": {
    "iso:country":"US",
    "sg:address":"547 Land Rush Dr",
    "sg:city":"Midvale",
    "sg:classifiers":[
        {
            "category":"Real Estate",
            "subcategory":"Real Estate Agent",
            "type":"Services"
        }
    ],
    "sg:phone":"+1 801 255 4115",
    "sg:postcode":"84047",
    "sg:province":"UT",
    "wof:name":"Premier Property MGT LLC",
    "wof:placetype":"venue"
},
  "geometry": {"coordinates":[-111.87253200000001,40.624487],"type":"Point"}
}