{
  "type": "Feature",
  "properties": {
    "iso:country":"US",
    "sg:address":"1553 Springwater Dr",
    "sg:city":"Orem",
    "sg:classifiers":[
        {
            "category":"Building & Trades",
            "subcategory":"Construction",
            "type":"Services"
        }
    ],
    "sg:phone":"+1 801 224 3035",
    "sg:postcode":"84058",
    "sg:province":"UT",
    "sg:tags":[
        "floor",
        "laying",
        "contractor"
    ],
    "wof:name":"Dons Installation",
    "wof:placetype":"venue"
},
  "geometry": {"coordinates":[-111.733338,40.282005],"type":"Point"}
}