{
  "type": "Feature",
  "properties": {
    "iso:country":"US",
    "sg:address":"1635 N Center St",
    "sg:city":"Park City",
    "sg:classifiers":[
        {
            "category":"Shopping",
            "subcategory":"Books",
            "type":"Retail Goods"
        }
    ],
    "sg:phone":"+1 435 575 2665",
    "sg:postcode":"84043",
    "sg:province":"UT",
    "sg:tags":[
        "dealer"
    ],
    "wof:name":"Spotted Frog",
    "wof:placetype":"venue"
},
  "geometry": {"coordinates":[-111.849423,40.406584],"type":"Point"}
}