{
  "type": "Feature",
  "properties": {
    "iso:country":"US",
    "sg:address":"5533 W 5505 S",
    "sg:city":"Kearns",
    "sg:classifiers":[
        {
            "category":"Manufacturing",
            "subcategory":"Chemicals & Compounds",
            "type":"Manufacturing & Wholesale Goods"
        }
    ],
    "sg:phone":"+1 801 955 6900",
    "sg:postcode":"84118",
    "sg:province":"UT",
    "sg:tags":[
        "material",
        "fireproofing"
    ],
    "wof:name":"No Burn Utah",
    "wof:placetype":"venue"
},
  "geometry": {"coordinates":[-112.022881,40.651122],"type":"Point"}
}