{
  "type": "Feature",
  "properties": {
    "iso:country":"US",
    "sg:address":"8498 S State St",
    "sg:city":"Midvale",
    "sg:classifiers":[
        {
            "category":"Autos & Motor Vehicles",
            "subcategory":"Automobile Sales",
            "type":"Retail Goods"
        }
    ],
    "sg:phone":"+1 801 561 2727",
    "sg:postcode":"84047",
    "sg:province":"UT",
    "sg:tags":[
        "car",
        "dealer"
    ],
    "sg:website":"www.petersonauto.com",
    "wof:name":"Peterson Auto Sales",
    "wof:placetype":"venue"
},
  "geometry": {"coordinates":[-111.890891,40.59713],"type":"Point"}
}