{
  "type": "Feature",
  "properties": {
    "iso:country":"US",
    "sg:address":"2665 Wall Ave",
    "sg:city":"Ogden",
    "sg:classifiers":[
        {
            "category":"Restaurant",
            "type":"Food & Drink"
        }
    ],
    "sg:phone":"+1 801 392 2892",
    "sg:postcode":"84401",
    "sg:province":"UT",
    "wof:name":"Taqueria El Paraiso",
    "wof:placetype":"venue"
},
  "geometry": {"coordinates":[-111.979027,41.216866],"type":"Point"}
}