{
  "type": "Feature",
  "properties": {
    "iso:country":"US",
    "sg:address":"541 W 9560 S",
    "sg:city":"Sandy",
    "sg:classifiers":[
        {
            "category":"Building & Trades",
            "subcategory":"Construction",
            "type":"Services"
        }
    ],
    "sg:phone":"+1 801 254 3603",
    "sg:postcode":"84070",
    "sg:province":"UT",
    "sg:tags":[
        "porch",
        "enclosure",
        "patio",
        "deck"
    ],
    "sg:website":"www.exteriorstructures.net",
    "wof:name":"Exterior Structures Inc",
    "wof:placetype":"venue"
},
  "geometry": {"coordinates":[-111.905829,40.577871],"type":"Point"}
}