{
  "type": "Feature",
  "properties": {
    "iso:country":"US",
    "sg:address":"6890 Trappers Cir",
    "sg:city":"Morgan",
    "sg:classifiers":[
        {
            "category":"Health Services",
            "subcategory":"Doctor",
            "type":"Services"
        }
    ],
    "sg:phone":"+1 801 876 3999",
    "sg:postcode":"84050",
    "sg:province":"UT",
    "sg:tags":[
        "physician",
        "surgeon"
    ],
    "wof:name":"Surgical Partners",
    "wof:placetype":"venue"
},
  "geometry": {"coordinates":[-111.80007999999999,41.160058],"type":"Point"}
}