{
  "type": "Feature",
  "properties": {
    "iso:country":"US",
    "sg:address":"1601 E 12700 S",
    "sg:city":"Draper",
    "sg:classifiers":[
        {
            "category":"Building & Trades",
            "subcategory":"Construction",
            "type":"Services"
        }
    ],
    "sg:phone":"+1 801 495 2130",
    "sg:postcode":"84020",
    "sg:province":"UT",
    "sg:tags":[
        "contractor"
    ],
    "wof:name":"Vawdrey Construction",
    "wof:placetype":"venue"
},
  "geometry": {"coordinates":[-111.846817,40.521104],"type":"Point"}
}