{
  "type": "Feature",
  "properties": {
    "iso:country":"US",
    "sg:address":"4851 S Atwood Blvd",
    "sg:city":"Salt Lake City",
    "sg:classifiers":[
        {
            "category":"Building & Trades",
            "subcategory":"Construction",
            "type":"Services"
        }
    ],
    "sg:phone":"+1 801 281 0376",
    "sg:postcode":"84107",
    "sg:province":"UT",
    "sg:tags":[
        "house"
    ],
    "wof:name":"N R G Plus Inc",
    "wof:placetype":"venue"
},
  "geometry": {"coordinates":[-111.88225799999999,40.666317],"type":"Point"}
}