{
  "type": "Feature",
  "properties": {
    "iso:country":"US",
    "sg:address":"55 S Main St",
    "sg:city":"Fillmore",
    "sg:classifiers":[
        {
            "category":"Health Services",
            "subcategory":"Doctor",
            "type":"Services"
        }
    ],
    "sg:phone":"+1 435 743 6178",
    "sg:postcode":"84631",
    "sg:province":"UT",
    "sg:tags":[
        "dentist"
    ],
    "wof:name":"An Apple A Day Dental Clinic",
    "wof:placetype":"venue"
},
  "geometry": {"coordinates":[-112.32355699999999,38.967705],"type":"Point"}
}