{
  "type": "Feature",
  "properties": {
    "iso:country":"US",
    "sg:address":"1296 E 2350 N",
    "sg:city":"Ogden",
    "sg:classifiers":[
        {
            "category":"Organizations",
            "subcategory":"Labor Organization",
            "type":"Services"
        }
    ],
    "sg:phone":"+1 801 782 0222",
    "sg:postcode":"84414",
    "sg:province":"UT",
    "wof:name":"Brotherhood of Locomotive",
    "wof:placetype":"venue"
},
  "geometry": {"coordinates":[-111.940478,41.300439],"type":"Point"}
}