{
  "type": "Feature",
  "properties": {
    "iso:country":"US",
    "sg:address":"2206 N 640 W",
    "sg:city":"Woods Cross",
    "sg:classifiers":[
        {
            "category":"Organizations",
            "subcategory":"Labor Organization",
            "type":"Services"
        }
    ],
    "sg:phone":"+1 801 298 1089",
    "sg:postcode":"84087",
    "sg:province":"UT",
    "wof:name":"Nelson Lc Specialties",
    "wof:placetype":"venue"
},
  "geometry": {"coordinates":[-111.896857,40.913324],"type":"Point"}
}