{
  "type": "Feature",
  "properties": {
    "iso:country":"US",
    "sg:address":"175 W 900 S",
    "sg:city":"St George",
    "sg:classifiers":[
        {
            "category":"Restaurant",
            "type":"Food & Drink"
        }
    ],
    "sg:phone":"+1 435 628 1822",
    "sg:postcode":"84770",
    "sg:province":"UT",
    "sg:tags":[
        "shop",
        "delicatessen",
        "sandwich"
    ],
    "wof:name":"Tom's Delicatessen Sandwiches",
    "wof:placetype":"venue"
},
  "geometry": {"coordinates":[-113.58709,37.092611],"type":"Point"}
}