{
  "type": "Feature",
  "properties": {
    "iso:country":"US",
    "sg:address":"1184 N 1270 E",
    "sg:city":"American Fork",
    "sg:classifiers":[
        {
            "category":"Building & Trades",
            "subcategory":"Construction",
            "type":"Services"
        }
    ],
    "sg:phone":"+1 801 763 1285",
    "sg:postcode":"84003",
    "sg:province":"UT",
    "sg:tags":[
        "house",
        "builder",
        "home"
    ],
    "wof:name":"Haven Homes Inc",
    "wof:placetype":"venue"
},
  "geometry": {"coordinates":[-111.764842,40.400171],"type":"Point"}
}