{
  "type": "Feature",
  "properties": {
    "iso:country":"US",
    "sg:address":"1135 N 200 E",
    "sg:city":"Bountiful",
    "sg:classifiers":[
        {
            "category":"Organizations",
            "subcategory":"Religious Organization",
            "type":"Services"
        }
    ],
    "sg:phone":"+1 801 299 4051",
    "sg:postcode":"84010",
    "sg:province":"UT",
    "sg:tags":[
        "church"
    ],
    "wof:name":"Church Of Jesus Christ Of Lds",
    "wof:placetype":"venue"
},
  "geometry": {"coordinates":[-111.87664100000001,40.901409],"type":"Point"}
}