{
  "type": "Feature",
  "properties": {
    "iso:country":"US",
    "sg:address":"1260 Vine St",
    "sg:city":"Salt Lake City",
    "sg:classifiers":[
        {
            "category":"Manufacturing",
            "subcategory":"Electronics",
            "type":"Manufacturing & Wholesale Goods"
        }
    ],
    "sg:phone":"+1 801 264 9347",
    "sg:postcode":"84121",
    "sg:province":"UT",
    "sg:tags":[
        "communications",
        "m",
        "mfg"
    ],
    "wof:name":"Chucks Dtctors Prspectors Sups",
    "wof:placetype":"venue"
},
  "geometry": {"coordinates":[-111.85567399999999,40.640562],"type":"Point"}
}