{
  "type": "Feature",
  "properties": {
    "iso:country":"US",
    "sg:address":"479 W 30 N",
    "sg:city":"American Fork",
    "sg:classifiers":[
        {
            "category":"Building & Trades",
            "subcategory":"Construction",
            "type":"Services"
        }
    ],
    "sg:phone":"+1 801 772 0890",
    "sg:postcode":"84003",
    "sg:province":"UT",
    "sg:tags":[
        "general",
        "contractor"
    ],
    "wof:name":"Pinacle Home & Development",
    "wof:placetype":"venue"
},
  "geometry": {"coordinates":[-111.811003,40.377546],"type":"Point"}
}