{
  "type": "Feature",
  "properties": {
    "iso:country":"US",
    "sg:address":"91 Allegiance Cir",
    "sg:city":"Evanston",
    "sg:classifiers":[
        {
            "category":"Home & Garden",
            "subcategory":"Furniture",
            "type":"Retail Goods"
        }
    ],
    "sg:phone":"+1 307 444 7057",
    "sg:postcode":"82930",
    "sg:province":"UT",
    "sg:tags":[
        "cabinet"
    ],
    "wof:name":"Wildwood Cabinet",
    "wof:placetype":"venue"
},
  "geometry": {"coordinates":[-110.994722,41.260061],"type":"Point"}
}