{
  "type": "Feature",
  "properties": {
    "iso:country":"US",
    "sg:address":"2060 Harrison Blvd",
    "sg:city":"Ogden",
    "sg:classifiers":[
        {
            "category":"Restaurant",
            "type":"Food & Drink"
        }
    ],
    "sg:menulink":"http://www.allmenus.com/ut/ogden/69597-dominos-pizza/menu/",
    "sg:phone":"+1 801 399 9999",
    "sg:postcode":"84401",
    "sg:province":"UT",
    "sg:tags":[
        "american",
        "wing",
        "pizza"
    ],
    "wof:name":"Domino's Pizza",
    "wof:placetype":"venue"
},
  "geometry": {"coordinates":[-111.94798299999999,41.229538],"type":"Point"}
}