{
  "type": "Feature",
  "properties": {
    "iso:country":"US",
    "sg:address":"3896 S 850 W",
    "sg:city":"Bountiful",
    "sg:classifiers":[
        {
            "category":"Building & Trades",
            "subcategory":"Landscaping Services",
            "type":"Services"
        }
    ],
    "sg:phone":"+1 801 292 9630",
    "sg:postcode":"84010",
    "sg:province":"UT",
    "wof:name":"Custom Ldscp & Grdn Designs",
    "wof:placetype":"venue"
},
  "geometry": {"coordinates":[-111.903893,40.848422],"type":"Point"}
}