{
  "type": "Feature",
  "properties": {
    "iso:country":"US",
    "sg:address":"230 Quirk St",
    "sg:city":"Grantsville",
    "sg:classifiers":[
        {
            "category":"Autos & Motor Vehicles",
            "subcategory":"Automobile Sales",
            "type":"Retail Goods"
        }
    ],
    "sg:phone":"+1 435 884 6722",
    "sg:postcode":"84029",
    "sg:province":"UT",
    "sg:tags":[
        "car",
        "dealer"
    ],
    "wof:name":"Quality Dodge",
    "wof:placetype":"venue"
},
  "geometry": {"coordinates":[-112.456762,40.594259],"type":"Point"}
}