{
  "type": "Feature",
  "properties": {
    "iso:country":"US",
    "sg:address":"1069 Loblolly Cir",
    "sg:city":"St George",
    "sg:classifiers":[
        {
            "category":"Farming",
            "subcategory":"Farm",
            "type":"Manufacturing & Wholesale Goods"
        }
    ],
    "sg:phone":"+1 435 628 2064",
    "sg:postcode":"84790",
    "sg:province":"UT",
    "sg:tags":[
        "crop",
        "general"
    ],
    "wof:name":"Jeff Esplin",
    "wof:placetype":"venue"
},
  "geometry": {"coordinates":[-113.56195,37.057836],"type":"Point"}
}