{
  "type": "Feature",
  "properties": {
    "iso:country":"US",
    "sg:address":"641 Southfork Dr",
    "sg:city":"Draper",
    "sg:classifiers":[
        {
            "category":"Building & Trades",
            "subcategory":"Construction",
            "type":"Services"
        }
    ],
    "sg:phone":"+1 801 572 1873",
    "sg:postcode":"84020",
    "sg:province":"UT",
    "sg:tags":[
        "house"
    ],
    "wof:name":"Thomas Construction",
    "wof:placetype":"venue"
},
  "geometry": {"coordinates":[-111.872275,40.49642],"type":"Point"}
}