{
  "type": "Feature",
  "properties": {
    "iso:country":"US",
    "sg:address":"776 N 1060 W",
    "sg:city":"Orem",
    "sg:classifiers":[
        {
            "category":"Manufacturing",
            "subcategory":"Retail Goods",
            "type":"Manufacturing & Wholesale Goods"
        }
    ],
    "sg:phone":"+1 801 229 1819",
    "sg:postcode":"84057",
    "sg:province":"UT",
    "sg:tags":[
        "product",
        "mfg"
    ],
    "wof:name":"Heidis Creations",
    "wof:placetype":"venue"
},
  "geometry": {"coordinates":[-111.721767,40.310601],"type":"Point"}
}