{
  "type": "Feature",
  "properties": {
    "iso:country":"US",
    "sg:address":"553 N Main St",
    "sg:city":"Tooele",
    "sg:classifiers":[
        {
            "category":"Insurance",
            "subcategory":"Insurance Agent",
            "type":"Services"
        }
    ],
    "sg:phone":"+1 435 882 1216",
    "sg:postcode":"84074",
    "sg:province":"UT",
    "wof:name":"Curry Insurance",
    "wof:placetype":"venue"
},
  "geometry": {"coordinates":[-112.29849,40.541482],"type":"Point"}
}