{
  "type": "Feature",
  "properties": {
    "iso:country":"US",
    "sg:address":"1739 Horizon Point Cir",
    "sg:city":"Draper",
    "sg:classifiers":[
        {
            "category":"Shopping",
            "subcategory":"Gifts & Souvenirs",
            "type":"Retail Goods"
        }
    ],
    "sg:phone":"+1 801 495 1077",
    "sg:postcode":"84020",
    "sg:province":"UT",
    "wof:name":"Rick and Lisa Evenson",
    "wof:placetype":"venue"
},
  "geometry": {"coordinates":[-111.842574,40.511941],"type":"Point"}
}