{
  "type": "Feature",
  "properties": {
    "iso:country":"US",
    "sg:address":"8111 Maio Dr",
    "sg:city":"Sandy",
    "sg:classifiers":[
        {
            "category":"Professional",
            "subcategory":"Management & Consulting",
            "type":"Services"
        }
    ],
    "sg:phone":"+1 801 942 1244",
    "sg:postcode":"84093",
    "sg:province":"UT",
    "wof:name":"Havenstrite Management Svcs",
    "wof:placetype":"venue"
},
  "geometry": {"coordinates":[-111.845674,40.604518],"type":"Point"}
}