{
  "type": "Feature",
  "properties": {
    "iso:country":"US",
    "sg:address":"4699 Harrison Blvd",
    "sg:city":"Ogden",
    "sg:classifiers":[
        {
            "category":"Insurance",
            "subcategory":"Title Insurance",
            "type":"Services"
        }
    ],
    "sg:phone":"+1 801 476 7400",
    "sg:postcode":"84403",
    "sg:province":"UT",
    "sg:tags":[
        "real estate"
    ],
    "wof:name":"Equity Title Insurance Agency",
    "wof:placetype":"venue"
},
  "geometry": {"coordinates":[-111.949208,41.178508],"type":"Point"}
}