{
  "type": "Feature",
  "properties": {
    "iso:country":"US",
    "sg:address":"549 Willow Springs Ln",
    "sg:city":"Draper",
    "sg:classifiers":[
        {
            "category":"Restaurant",
            "type":"Food & Drink"
        }
    ],
    "sg:phone":"+1 801 545 0598",
    "sg:postcode":"84020",
    "sg:province":"UT",
    "sg:tags":[
        "franchise",
        "fast"
    ],
    "wof:name":"Wienerschnitzel",
    "wof:placetype":"venue"
},
  "geometry": {"coordinates":[-111.876569,40.519973],"type":"Point"}
}