{
  "type": "Feature",
  "properties": {
    "iso:country":"US",
    "sg:address":"418 E Main St",
    "sg:city":"Vernal",
    "sg:classifiers":[
        {
            "category":"Real Estate",
            "subcategory":"Real Estate Agent",
            "type":"Services"
        }
    ],
    "sg:phone":"+1 435 789 1482",
    "sg:postcode":"84078",
    "sg:province":"UT",
    "sg:website":"www.c21dart.com",
    "wof:name":"Dart Realty",
    "wof:placetype":"venue"
},
  "geometry": {"coordinates":[-109.519347,40.45576],"type":"Point"}
}