{
  "type": "Feature",
  "properties": {
    "iso:country":"US",
    "sg:address":"3507 N University Ave",
    "sg:city":"Provo",
    "sg:classifiers":[
        {
            "category":"Professional",
            "subcategory":"Lawyer & Legal Services",
            "type":"Services"
        }
    ],
    "sg:phone":"+1 801 375 7680",
    "sg:postcode":"84604",
    "sg:province":"UT",
    "wof:name":"Zabriskie & Associates",
    "wof:placetype":"venue"
},
  "geometry": {"coordinates":[-111.657775,40.277386],"type":"Point"}
}