{
  "type": "Feature",
  "properties": {
    "iso:country":"US",
    "sg:address":"722 Rockwood Dr",
    "sg:city":"North Salt Lake",
    "sg:classifiers":[
        {
            "category":"Communications",
            "type":"Services"
        }
    ],
    "sg:phone":"+1 801 805 3895",
    "sg:postcode":"84054",
    "sg:province":"UT",
    "sg:tags":[
        "communication"
    ],
    "wof:name":"Multipoint Networks Inc",
    "wof:placetype":"venue"
},
  "geometry": {"coordinates":[-111.882687,40.827757],"type":"Point"}
}