{
  "type": "Feature",
  "properties": {
    "iso:country":"US",
    "sg:address":"4095 W 1975 N",
    "sg:city":"Ogden",
    "sg:phone":"+1 801 731 7752",
    "sg:postcode":"84404",
    "sg:province":"UT",
    "sg:tags":[
        "farm"
    ],
    "wof:name":"Panunzio Farm",
    "wof:placetype":"venue"
},
  "geometry": {"coordinates":[-112.074421,41.293886],"type":"Point"}
}