{
  "type": "Feature",
  "properties": {
    "iso:country":"US",
    "sg:address":"2646 W 800 N",
    "sg:city":"Clearfield",
    "sg:classifiers":[
        {
            "category":"Farming",
            "subcategory":"Livestock Farm",
            "type":"Manufacturing & Wholesale Goods"
        }
    ],
    "sg:phone":"+1 801 773 7108",
    "sg:postcode":"84015",
    "sg:province":"UT",
    "sg:tags":[
        "animal",
        "general"
    ],
    "wof:name":"Valley West Ranches Inc",
    "wof:placetype":"venue"
},
  "geometry": {"coordinates":[-112.07564499999999,41.125435],"type":"Point"}
}