{
  "type": "Feature",
  "properties": {
    "iso:country":"US",
    "sg:address":"437 Stephanie Cir",
    "sg:city":"Sandy",
    "sg:classifiers":[
        {
            "category":"Professional",
            "type":"Services"
        }
    ],
    "sg:phone":"+1 801 576 9078",
    "sg:postcode":"84070",
    "sg:province":"UT",
    "wof:name":"Stoddard G Art",
    "wof:placetype":"venue"
},
  "geometry": {"coordinates":[-111.878024,40.577326],"type":"Point"}
}