{
  "type": "Feature",
  "properties": {
    "iso:country":"US",
    "sg:address":"595 N 500 W",
    "sg:city":"Bountiful",
    "sg:classifiers":[
        {
            "category":"Social Services",
            "subcategory":"Child Care",
            "type":"Services"
        },
        {
            "category":"Education",
            "subcategory":"Preschool",
            "type":"Public Place"
        },
        {
            "category":"Education",
            "subcategory":"School",
            "type":"Public Place"
        }
    ],
    "sg:phone":"+1 801 397 0937",
    "sg:postcode":"84010",
    "sg:province":"UT",
    "sg:tags":[
        "elementary",
        "day"
    ],
    "wof:name":"Bryden Academy",
    "wof:placetype":"venue"
},
  "geometry": {"coordinates":[-111.892393,40.89534],"type":"Point"}
}