{
  "type": "Feature",
  "properties": {
    "iso:country":"US",
    "sg:address":"55 S State St",
    "sg:city":"Orem",
    "sg:classifiers":[
        {
            "category":"Cinema",
            "subcategory":"Movie Rental",
            "type":"Entertainment"
        }
    ],
    "sg:phone":"+1 801 229 1204",
    "sg:postcode":"84058",
    "sg:province":"UT",
    "sg:tags":[
        "leasing",
        "video",
        "disc",
        "tape"
    ],
    "wof:name":"Hollywood Video",
    "wof:placetype":"venue"
},
  "geometry": {"coordinates":[-111.69447,40.296273],"type":"Point"}
}