{
  "type": "Feature",
  "properties": {
    "iso:country":"US",
    "sg:address":"6924 Bear Spring Cir",
    "sg:city":"Morgan",
    "sg:classifiers":[
        {
            "category":"Organizations",
            "subcategory":"Religious Organization",
            "type":"Services"
        }
    ],
    "sg:phone":"+1 801 876 3531",
    "sg:postcode":"84050",
    "sg:province":"UT",
    "wof:name":"Covenant Carvings",
    "wof:placetype":"venue"
},
  "geometry": {"coordinates":[-111.79963600000001,41.161094],"type":"Point"}
}