{
  "type": "Feature",
  "properties": {
    "iso:country":"US",
    "sg:address":"7123 S 1300 E",
    "sg:city":"Midvale",
    "sg:classifiers":[
        {
            "category":"Shopping",
            "subcategory":"Clothing, Apparel, & Fashions",
            "type":"Retail Goods"
        }
    ],
    "sg:phone":"+1 801 567 9636",
    "sg:postcode":"84047",
    "sg:province":"UT",
    "sg:tags":[
        "family",
        "store"
    ],
    "wof:name":"Old Navy",
    "wof:placetype":"venue"
},
  "geometry": {"coordinates":[-111.855507,40.62122],"type":"Point"}
}