{
  "type": "Feature",
  "properties": {
    "iso:country":"US",
    "sg:address":"51 N 400 E",
    "sg:city":"Santaquin",
    "sg:classifiers":[
        {
            "category":"Professional",
            "type":"Services"
        },
        {
            "category":"Social Services",
            "subcategory":"Child Care",
            "type":"Services"
        }
    ],
    "sg:phone":"+1 801 754 5377",
    "sg:postcode":"84655",
    "sg:province":"UT",
    "sg:tags":[
        "establishment",
        "day"
    ],
    "wof:name":"Deb's Kiddie Korner",
    "wof:placetype":"venue"
},
  "geometry": {"coordinates":[-111.77697000000001,39.976377],"type":"Point"}
}