{
  "type": "Feature",
  "properties": {
    "iso:country":"US",
    "sg:address":"11796 Hidden Valley Rd",
    "sg:city":"Sandy",
    "sg:classifiers":[
        {
            "category":"Shopping",
            "subcategory":"Gifts & Souvenirs",
            "type":"Retail Goods"
        }
    ],
    "sg:phone":"+1 801 572 4032",
    "sg:postcode":"84092",
    "sg:province":"UT",
    "wof:name":"Basket Tree",
    "wof:placetype":"venue"
},
  "geometry": {"coordinates":[-111.851322,40.53656],"type":"Point"}
}