{
  "type": "Feature",
  "properties": {
    "iso:country":"US",
    "sg:address":"7273 S 245 E",
    "sg:city":"Midvale",
    "sg:classifiers":[
        {
            "category":"Manufacturing",
            "subcategory":"Metals",
            "type":"Manufacturing & Wholesale Goods"
        }
    ],
    "sg:phone":"+1 801 567 9553",
    "sg:postcode":"84047",
    "sg:province":"UT",
    "sg:tags":[
        "cutlery",
        "mfg"
    ],
    "wof:name":"Steven Rapp",
    "wof:placetype":"venue"
},
  "geometry": {"coordinates":[-111.883454,40.619665],"type":"Point"}
}