{
  "type": "Feature",
  "properties": {
    "iso:country":"US",
    "sg:address":"576 S 330 W",
    "sg:city":"Orem",
    "sg:classifiers":[
        {
            "category":"Education",
            "subcategory":"Special Training",
            "type":"Public Place"
        }
    ],
    "sg:phone":"+1 801 224 0140",
    "sg:postcode":"84058",
    "sg:province":"UT",
    "sg:tags":[
        "instruction",
        "music"
    ],
    "wof:name":"Play Right Publishing",
    "wof:placetype":"venue"
},
  "geometry": {"coordinates":[-111.703388,40.286453],"type":"Point"}
}