{
  "type": "Feature",
  "properties": {
    "iso:country":"US",
    "sg:address":"2104 S 700 E",
    "sg:city":"Salt Lake City",
    "sg:classifiers":[
        {
            "category":"Health Services",
            "subcategory":"Optometrist",
            "type":"Services"
        }
    ],
    "sg:phone":"+1 801 467 1315",
    "sg:postcode":"84106",
    "sg:province":"UT",
    "wof:name":"Knighton Optical",
    "wof:placetype":"venue"
},
  "geometry": {"coordinates":[-111.87117499999999,40.724406],"type":"Point"}
}