{
  "type": "Feature",
  "properties": {
    "iso:country":"US",
    "sg:address":"1939 S 300 E",
    "sg:city":"Salt Lake City",
    "sg:classifiers":[
        {
            "category":"Banks & Credit Unions",
            "subcategory":"Financial Services",
            "type":"Services"
        }
    ],
    "sg:phone":"+1 801 485 7797",
    "sg:postcode":"84115",
    "sg:province":"UT",
    "sg:tags":[
        "investor"
    ],
    "wof:name":"A-8 Group",
    "wof:placetype":"venue"
},
  "geometry": {"coordinates":[-111.88247200000001,40.728739],"type":"Point"}
}