{
  "type": "Feature",
  "properties": {
    "iso:country":"US",
    "sg:address":"12945 S 1615 W",
    "sg:city":"Riverton",
    "sg:classifiers":[
        {
            "category":"Building & Trades",
            "subcategory":"Construction",
            "type":"Services"
        }
    ],
    "sg:phone":"+1 801 254 1388",
    "sg:postcode":"84065",
    "sg:province":"UT",
    "sg:tags":[
        "nonresidential"
    ],
    "wof:name":"R B D Construction Inc",
    "wof:placetype":"venue"
},
  "geometry": {"coordinates":[-111.936657,40.517928],"type":"Point"}
}