{
  "type": "Feature",
  "properties": {
    "iso:country":"US",
    "sg:address":"2025 E 3100 N",
    "sg:city":"Layton",
    "sg:classifiers":[
        {
            "category":"Education",
            "subcategory":"School",
            "type":"Public Place"
        }
    ],
    "sg:phone":"+1 801 402 3700",
    "sg:postcode":"84040",
    "sg:province":"UT",
    "wof:name":"Mountain View Elem School",
    "wof:placetype":"venue"
},
  "geometry": {"coordinates":[-111.928262,41.104104],"type":"Point"}
}