{
  "type": "Feature",
  "properties": {
    "iso:country":"US",
    "sg:address":"148 S Main St",
    "sg:city":"Salt Lake City",
    "sg:classifiers":[
        {
            "category":"Restaurant",
            "type":"Food & Drink"
        }
    ],
    "sg:phone":"+1 435 472 0403",
    "sg:postcode":"84101",
    "sg:province":"UT",
    "sg:tags":[
        "eating"
    ],
    "wof:name":"Balance Rock Eatery & Pub",
    "wof:placetype":"venue"
},
  "geometry": {"coordinates":[-111.89116799999999,40.766064],"type":"Point"}
}