{
  "type": "Feature",
  "properties": {
    "iso:country":"US",
    "sg:address":"1900 N 280 W",
    "sg:city":"Orem",
    "sg:classifiers":[
        {
            "category":"Wholesale",
            "subcategory":"Non-durable Goods",
            "type":"Manufacturing & Wholesale Goods"
        }
    ],
    "sg:phone":"+1 801 224 6888",
    "sg:postcode":"84057",
    "sg:province":"UT",
    "wof:name":"By Ranata",
    "wof:placetype":"venue"
},
  "geometry": {"coordinates":[-111.702853,40.332182],"type":"Point"}
}