{
  "type": "Feature",
  "properties": {
    "iso:country":"US",
    "sg:address":"225 Queensland Ct",
    "sg:city":"Lindon",
    "sg:classifiers":[
        {
            "category":"Communications",
            "subcategory":"Film & Video Production",
            "type":"Services"
        }
    ],
    "sg:phone":"+1 801 796 7377",
    "sg:postcode":"84042",
    "sg:province":"UT",
    "sg:tags":[
        "motion"
    ],
    "wof:name":"Sonic Motion",
    "wof:placetype":"venue"
},
  "geometry": {"coordinates":[-111.69003499999999,40.344149],"type":"Point"}
}