{
  "type": "Feature",
  "properties": {
    "iso:country":"US",
    "sg:address":"425 S State St",
    "sg:city":"Orem",
    "sg:classifiers":[
        {
            "category":"Shopping",
            "subcategory":"Used Merchandise",
            "type":"Retail Goods"
        },
        {
            "category":"Shopping",
            "subcategory":"Books",
            "type":"Retail Goods"
        }
    ],
    "sg:phone":"+1 801 225 4088",
    "sg:postcode":"84058",
    "sg:province":"UT",
    "sg:tags":[
        "rare",
        "dealer"
    ],
    "wof:name":"Book Barons Cottage The",
    "wof:placetype":"venue"
},
  "geometry": {"coordinates":[-111.689644,40.285223],"type":"Point"}
}