{
  "type": "Feature",
  "properties": {
    "iso:country":"US",
    "sg:address":"1107 S State St",
    "sg:city":"Salt Lake City",
    "sg:phone":"+1 801 531 7625",
    "sg:postcode":"84111",
    "sg:province":"UT",
    "sg:tags":[
        "leather",
        "finish",
        "findings"
    ],
    "wof:name":"Leather Factory",
    "wof:placetype":"venue"
},
  "geometry": {"coordinates":[-111.88814000000001,40.745352],"type":"Point"}
}