{
  "type": "Feature",
  "properties": {
    "iso:country":"US",
    "sg:address":"20 Union Ave",
    "sg:city":"North Salt Lake",
    "sg:classifiers":[
        {
            "category":"Freight",
            "type":"Transportation"
        }
    ],
    "sg:phone":"+1 801 292 9045",
    "sg:postcode":"84054",
    "sg:province":"UT",
    "sg:tags":[
        "warehouse",
        "self",
        "storage"
    ],
    "wof:name":"Orbit Warehouse",
    "wof:placetype":"venue"
},
  "geometry": {"coordinates":[-111.909453,40.857979],"type":"Point"}
}