{
  "type": "Feature",
  "properties": {
    "iso:country":"US",
    "sg:address":"10411 Oak Cir",
    "sg:city":"American Fork",
    "sg:classifiers":[
        {
            "category":"Building & Trades",
            "subcategory":"Construction",
            "type":"Services"
        }
    ],
    "sg:phone":"+1 801 756 5644",
    "sg:postcode":"84003",
    "sg:province":"UT",
    "sg:tags":[
        "general",
        "contractor"
    ],
    "wof:name":"Mc Rae Construction Inc",
    "wof:placetype":"venue"
},
  "geometry": {"coordinates":[-111.780641,40.422086],"type":"Point"}
}