{
  "type": "Feature",
  "properties": {
    "iso:country":"US",
    "sg:address":"3216 E del Mar Dr",
    "sg:city":"Salt Lake City",
    "sg:classifiers":[
        {
            "category":"Shopping",
            "subcategory":"Bicycles & Sporting Goods",
            "type":"Retail Goods"
        }
    ],
    "sg:phone":"+1 801 272 2177",
    "sg:postcode":"84109",
    "sg:province":"UT",
    "wof:name":"Dolemite",
    "wof:placetype":"venue"
},
  "geometry": {"coordinates":[-111.804349,40.687758],"type":"Point"}
}