{
  "type": "Feature",
  "properties": {
    "iso:country":"US",
    "sg:address":"446 N Main St",
    "sg:city":"Logan",
    "sg:classifiers":[
        {
            "category":"Personal",
            "subcategory":"Beauty Salon",
            "type":"Services"
        }
    ],
    "sg:phone":"+1 435 755 0303",
    "sg:postcode":"84321",
    "sg:province":"UT",
    "wof:name":"Silver Clippers",
    "wof:placetype":"venue"
},
  "geometry": {"coordinates":[-111.834643,41.740168],"type":"Point"}
}