{
  "type": "Feature",
  "properties": {
    "iso:country":"US",
    "sg:address":"2208 W 300 N",
    "sg:city":"Clearfield",
    "sg:classifiers":[
        {
            "category":"Professional",
            "subcategory":"Business Services",
            "type":"Services"
        }
    ],
    "sg:phone":"+1 801 773 1352",
    "sg:postcode":"84015",
    "sg:province":"UT",
    "wof:name":"R Diamond Enterprises Inc",
    "wof:placetype":"venue"
},
  "geometry": {"coordinates":[-112.06775,41.118151],"type":"Point"}
}