{
  "type": "Feature",
  "properties": {
    "iso:country":"US",
    "sg:address":"58 E 100 S",
    "sg:city":"Roosevelt",
    "sg:classifiers":[
        {
            "category":"Building & Trades",
            "subcategory":"Construction",
            "type":"Services"
        }
    ],
    "sg:phone":"+1 435 722 3952",
    "sg:postcode":"84066",
    "sg:province":"UT",
    "sg:tags":[
        "house"
    ],
    "wof:name":"Uintah Bsin Assistance Council",
    "wof:placetype":"venue"
},
  "geometry": {"coordinates":[-109.990973,40.298048],"type":"Point"}
}