{
  "type": "Feature",
  "properties": {
    "iso:country":"US",
    "sg:address":"716 W 200 S",
    "sg:city":"Salt Lake City",
    "sg:classifiers":[
        {
            "category":"Autos & Motor Vehicles",
            "subcategory":"Boat Sales",
            "type":"Retail Goods"
        },
        {
            "category":"Shopping",
            "subcategory":"Clothing, Apparel, & Fashions",
            "type":"Retail Goods"
        }
    ],
    "sg:phone":"+1 801 359 1291",
    "sg:postcode":"84104",
    "sg:province":"UT",
    "sg:tags":[
        "top",
        "upholstery",
        "cover"
    ],
    "wof:name":"Louis Cohen Canvas Goods",
    "wof:placetype":"venue"
},
  "geometry": {"coordinates":[-111.91239899999999,40.765065],"type":"Point"}
}