{
  "type": "Feature",
  "properties": {
    "iso:country":"US",
    "sg:address":"188 S Main St",
    "sg:city":"Springville",
    "sg:classifiers":[
        {
            "category":"Cafe",
            "type":"Food & Drink"
        }
    ],
    "sg:menulink":"http://www.allmenus.com/ut/springville-mapleton/37038-gingers-garden-cafe/menu/",
    "sg:phone":"+1 801 489 4500",
    "sg:postcode":"84663",
    "sg:province":"UT",
    "sg:tags":[
        "new",
        "american"
    ],
    "wof:name":"Ginger's Garden Cafe",
    "wof:placetype":"venue"
},
  "geometry": {"coordinates":[-111.61059899999999,40.164138],"type":"Point"}
}