{
  "type": "Feature",
  "properties": {
    "iso:country":"US",
    "sg:address":"3328 Monte Verde Dr",
    "sg:city":"Salt Lake City",
    "sg:classifiers":[
        {
            "category":"Professional",
            "subcategory":"Management & Consulting",
            "type":"Services"
        }
    ],
    "sg:phone":"+1 801 274 7800",
    "sg:postcode":"84109",
    "sg:province":"UT",
    "wof:name":"Basix",
    "wof:placetype":"venue"
},
  "geometry": {"coordinates":[-111.791736,40.697965],"type":"Point"}
}