{
  "type": "Feature",
  "properties": {
    "iso:country":"US",
    "sg:address":"7960 S 1300 E",
    "sg:city":"Sandy",
    "sg:classifiers":[
        {
            "category":"Shopping",
            "subcategory":"Hobbies, Toys, & Games",
            "type":"Retail Goods"
        }
    ],
    "sg:phone":"+1 801 561 8481",
    "sg:postcode":"84094",
    "sg:province":"UT",
    "sg:tags":[
        "craft",
        "supply"
    ],
    "wof:name":"Reuel's Art & Frame",
    "wof:placetype":"venue"
},
  "geometry": {"coordinates":[-111.853161,40.606918],"type":"Point"}
}