{
  "type": "Feature",
  "properties": {
    "iso:country":"US",
    "sg:address":"160 N Main St",
    "sg:city":"Richfield",
    "sg:classifiers":[
        {
            "category":"Bars & Pubs",
            "type":"Food & Drink"
        }
    ],
    "sg:phone":"+1 435 896 9947",
    "sg:postcode":"84701",
    "sg:province":"UT",
    "wof:name":"Detour",
    "wof:placetype":"venue"
},
  "geometry": {"coordinates":[-112.0847,38.769456],"type":"Point"}
}