{
  "type": "Feature",
  "properties": {
    "iso:country":"US",
    "sg:address":"7200 W 3500 S",
    "sg:city":"Magna",
    "sg:classifiers":[
        {
            "category":"Food & Beverages",
            "subcategory":"Bakery",
            "type":"Retail Goods"
        }
    ],
    "sg:phone":"+1 801 250 5956",
    "sg:postcode":"84044",
    "sg:province":"UT",
    "sg:tags":[
        "product",
        "mfg"
    ],
    "wof:name":"Rogers Bakery",
    "wof:placetype":"venue"
},
  "geometry": {"coordinates":[-112.065539,40.69649],"type":"Point"}
}