{
  "type": "Feature",
  "properties": {
    "iso:country":"US",
    "sg:address":"6985 Union Park Center",
    "sg:city":"Midvale",
    "sg:classifiers":[
        {
            "category":"Real Estate",
            "subcategory":"Real Estate Agent",
            "type":"Services"
        }
    ],
    "sg:phone":"+1 801 273 8800",
    "sg:postcode":"84047",
    "sg:province":"UT",
    "sg:website":"www.rexut.com",
    "wof:name":"Realty Executives",
    "wof:placetype":"venue"
},
  "geometry": {"coordinates":[-111.86077400000001,40.625377],"type":"Point"}
}