{
  "type": "Feature",
  "properties": {
    "iso:country":"US",
    "sg:address":"175 S Rio Grande St",
    "sg:city":"Salt Lake City",
    "sg:classifiers":[
        {
            "category":"Restaurant",
            "type":"Food & Drink"
        }
    ],
    "sg:phone":"+1 801 456 0050",
    "sg:postcode":"84101",
    "sg:province":"UT",
    "sg:tags":[
        "eating"
    ],
    "wof:name":"Humphrey Yogurt",
    "wof:placetype":"venue"
},
  "geometry": {"coordinates":[-111.90401799999999,40.765399],"type":"Point"}
}