{
  "type": "Feature",
  "properties": {
    "iso:country":"US",
    "sg:address":"50 E 100 S",
    "sg:city":"Fairview",
    "sg:classifiers":[
        {
            "category":"Food & Beverages",
            "subcategory":"Specialty",
            "type":"Retail Goods"
        }
    ],
    "sg:phone":"+1 435 427 3245",
    "sg:postcode":"84629",
    "sg:province":"UT",
    "sg:tags":[
        "health",
        "diet"
    ],
    "sg:website":"www.utahwheatgrass.com",
    "wof:name":"Utah Wheatgrass",
    "wof:placetype":"venue"
},
  "geometry": {"coordinates":[-111.439145,39.626427],"type":"Point"}
}