{
  "type": "Feature",
  "properties": {
    "iso:country":"US",
    "sg:address":"715 W 500 S",
    "sg:city":"Woods Cross",
    "sg:classifiers":[
        {
            "category":"Retail",
            "subcategory":"Auto Repair",
            "type":"Services"
        }
    ],
    "sg:phone":"+1 801 292 4341",
    "sg:postcode":"84087",
    "sg:province":"UT",
    "sg:tags":[
        "repairing",
        "automobile"
    ],
    "wof:name":"Dave Roberts Auto Svc",
    "wof:placetype":"venue"
},
  "geometry": {"coordinates":[-111.89895799999999,40.88424],"type":"Point"}
}