{
  "type": "Feature",
  "properties": {
    "iso:country":"US",
    "sg:address":"450 S 50 E",
    "sg:city":"Ephraim",
    "sg:classifiers":[
        {
            "category":"Wholesale",
            "subcategory":"Farm Supplies",
            "type":"Manufacturing & Wholesale Goods"
        }
    ],
    "sg:phone":"+1 435 283 4701",
    "sg:postcode":"84627",
    "sg:province":"UT",
    "sg:tags":[
        "wholesaler",
        "seed"
    ],
    "wof:name":"Fremont Trading Company LLC",
    "wof:placetype":"venue"
},
  "geometry": {"coordinates":[-111.58574900000001,39.351959],"type":"Point"}
}