{
  "type": "Feature",
  "properties": {
    "iso:country":"US",
    "sg:address":"5085 Acoma St",
    "sg:city":"Salt Lake City",
    "sg:classifiers":[
        {
            "category":"Building & Trades",
            "subcategory":"Construction",
            "type":"Services"
        }
    ],
    "sg:phone":"+1 801 840 8647",
    "sg:postcode":"84120",
    "sg:province":"UT",
    "sg:tags":[
        "house"
    ],
    "wof:name":"Quality First Home Imprvs",
    "wof:placetype":"venue"
},
  "geometry": {"coordinates":[-112.012804,40.693673],"type":"Point"}
}