{
  "type": "Feature",
  "properties": {
    "iso:country":"US",
    "sg:address":"30 S 130 E",
    "sg:city":"North Salt Lake",
    "sg:classifiers":[
        {
            "category":"Professional",
            "subcategory":"Business Services",
            "type":"Services"
        }
    ],
    "sg:phone":"+1 801 936 8700",
    "sg:postcode":"84054",
    "sg:province":"UT",
    "sg:tags":[
        "bowling"
    ],
    "wof:name":"Orchard Lanes",
    "wof:placetype":"venue"
},
  "geometry": {"coordinates":[-111.908997,40.841202],"type":"Point"}
}