{
  "type": "Feature",
  "properties": {
    "iso:country":"US",
    "sg:address":"265 S 900 E",
    "sg:city":"Provo",
    "sg:classifiers":[
        {
            "category":"Retail",
            "subcategory":"Repair Shop",
            "type":"Services"
        }
    ],
    "sg:phone":"+1 801 830 0011",
    "sg:postcode":"84606",
    "sg:province":"UT",
    "wof:name":"Brighams Piano Service",
    "wof:placetype":"venue"
},
  "geometry": {"coordinates":[-111.642698,40.231348],"type":"Point"}
}