{
  "type": "Feature",
  "properties": {
    "iso:country":"US",
    "sg:address":"2084 S 700 W",
    "sg:city":"Hurricane",
    "sg:classifiers":[
        {
            "category":"Organizations",
            "subcategory":"Membership Organization",
            "type":"Services"
        }
    ],
    "sg:phone":"+1 435 635 8314",
    "sg:postcode":"84737",
    "sg:province":"UT",
    "wof:name":"Hurricane Animal Shelter",
    "wof:placetype":"venue"
},
  "geometry": {"coordinates":[-113.30105,37.141963],"type":"Point"}
}