{
  "type": "Feature",
  "properties": {
    "iso:country":"US",
    "sg:address":"273 W 500 S",
    "sg:city":"Bountiful",
    "sg:classifiers":[
        {
            "category":"Restaurant",
            "type":"Food & Drink"
        }
    ],
    "sg:phone":"+1 801 299 9944",
    "sg:postcode":"84010",
    "sg:province":"UT",
    "sg:tags":[
        "eating"
    ],
    "sg:website":"www.hogiyogi.com",
    "wof:name":"Hogi-Yogi of Bountiful",
    "wof:placetype":"venue"
},
  "geometry": {"coordinates":[-111.887001,40.8843],"type":"Point"}
}