{
  "type": "Feature",
  "properties": {
    "iso:country":"US",
    "sg:address":"175 S 200 W",
    "sg:city":"Richmond",
    "sg:classifiers":[
        {
            "category":"Retail",
            "subcategory":"Auto Repair",
            "type":"Services"
        }
    ],
    "sg:phone":"+1 435 258 4400",
    "sg:postcode":"84333",
    "sg:province":"UT",
    "sg:tags":[
        "trailer"
    ],
    "wof:name":"Cache Trailer & Repair",
    "wof:placetype":"venue"
},
  "geometry": {"coordinates":[-111.814358,41.919017],"type":"Point"}
}