{
  "type": "Feature",
  "properties": {
    "iso:country":"US",
    "sg:address":"4857 S 2500 W",
    "sg:city":"Roy",
    "sg:classifiers":[
        {
            "category":"Professional",
            "subcategory":"Management & Consulting",
            "type":"Services"
        }
    ],
    "sg:phone":"+1 801 774 9137",
    "sg:postcode":"84067",
    "sg:province":"UT",
    "wof:name":"Cashdirect LLC",
    "wof:placetype":"venue"
},
  "geometry": {"coordinates":[-112.04044500000001,41.175404],"type":"Point"}
}