{
  "type": "Feature",
  "properties": {
    "iso:country":"US",
    "sg:address":"266 W 100 N",
    "sg:city":"Vernal",
    "sg:classifiers":[
        {
            "category":"Education",
            "subcategory":"School",
            "type":"Public Place"
        }
    ],
    "sg:phone":"+1 435 789 1965",
    "sg:postcode":"84078",
    "sg:province":"UT",
    "wof:name":"Benjamin Franklin Academy",
    "wof:placetype":"venue"
},
  "geometry": {"coordinates":[-109.533749,40.45716],"type":"Point"}
}