{
  "type": "Feature",
  "properties": {
    "iso:country":"US",
    "sg:address":"60 W Main St",
    "sg:city":"Elsinore",
    "sg:classifiers":[
        {
            "category":"Manufacturing",
            "subcategory":"Furniture",
            "type":"Manufacturing & Wholesale Goods"
        }
    ],
    "sg:phone":"+1 435 527 1600",
    "sg:postcode":"84724",
    "sg:province":"UT",
    "wof:name":"Rustic Shop",
    "wof:placetype":"venue"
},
  "geometry": {"coordinates":[-112.14970099999999,38.683137],"type":"Point"}
}