{
  "type": "Feature",
  "properties": {
    "iso:country":"US",
    "sg:address":"433 N 2500 W",
    "sg:city":"Vernal",
    "sg:classifiers":[
        {
            "category":"Manufacturing",
            "subcategory":"Leather Goods",
            "type":"Manufacturing & Wholesale Goods"
        }
    ],
    "sg:phone":"+1 435 789 3900",
    "sg:postcode":"84078",
    "sg:province":"UT",
    "sg:tags":[
        "mfg"
    ],
    "wof:name":"Dry Fork Saddle Co",
    "wof:placetype":"venue"
},
  "geometry": {"coordinates":[-109.576622,40.456971],"type":"Point"}
}