{
  "type": "Feature",
  "properties": {
    "iso:country":"US",
    "sg:address":"178 W Parrish Ln",
    "sg:city":"Centerville",
    "sg:classifiers":[
        {
            "category":"Shopping",
            "subcategory":"Discount & Variety Stores",
            "type":"Retail Goods"
        }
    ],
    "sg:phone":"+1 801 296 0468",
    "sg:postcode":"84014",
    "sg:province":"UT",
    "wof:name":"Neighborhood Dollar",
    "wof:placetype":"venue"
},
  "geometry": {"coordinates":[-111.886651,40.921581],"type":"Point"}
}