{
  "type": "Feature",
  "properties": {
    "iso:country":"US",
    "sg:address":"1552 E 1260 N",
    "sg:city":"Logan",
    "sg:classifiers":[
        {
            "category":"Building & Trades",
            "subcategory":"Cleaning & Sanitation",
            "type":"Services"
        }
    ],
    "sg:phone":"+1 435 755 7802",
    "sg:postcode":"84341",
    "sg:province":"UT",
    "sg:tags":[
        "janitor"
    ],
    "wof:name":"Clean Team Of Logan",
    "wof:placetype":"venue"
},
  "geometry": {"coordinates":[-111.795677,41.754023],"type":"Point"}
}