{
  "type": "Feature",
  "properties": {
    "iso:country":"US",
    "sg:address":"836 S University Ave",
    "sg:city":"Provo",
    "sg:classifiers":[
        {
            "category":"Retail",
            "subcategory":"Auto Repair",
            "type":"Services"
        }
    ],
    "sg:phone":"+1 801 370 0303",
    "sg:postcode":"84601",
    "sg:province":"UT",
    "sg:tags":[
        "automotive"
    ],
    "sg:website":"www.jiffylube.com",
    "wof:name":"Jiffy Lube",
    "wof:placetype":"venue"
},
  "geometry": {"coordinates":[-111.658771,40.222855],"type":"Point"}
}