{
  "type": "Feature",
  "properties": {
    "iso:country":"US",
    "sg:address":"1006 E 12300 S",
    "sg:city":"Draper",
    "sg:classifiers":[
        {
            "category":"Wholesale",
            "subcategory":"Machinery & Supplies",
            "type":"Manufacturing & Wholesale Goods"
        },
        {
            "category":"Home & Garden",
            "subcategory":"Garden Supply",
            "type":"Retail Goods"
        }
    ],
    "sg:phone":"+1 801 553 9780",
    "sg:postcode":"84020",
    "sg:province":"UT",
    "sg:tags":[
        "sprinkler"
    ],
    "wof:name":"John Deere Landscapes Inc",
    "wof:placetype":"venue"
},
  "geometry": {"coordinates":[-111.856708,40.528314],"type":"Point"}
}