{
  "type": "Feature",
  "properties": {
    "iso:country":"US",
    "sg:address":"1123 E 2950 N",
    "sg:city":"Ogden",
    "sg:classifiers":[
        {
            "category":"Retail",
            "subcategory":"Repair Shop",
            "type":"Services"
        }
    ],
    "sg:phone":"+1 801 782 1448",
    "sg:postcode":"84414",
    "sg:province":"UT",
    "wof:name":"Altogether Clean Inc",
    "wof:placetype":"venue"
},
  "geometry": {"coordinates":[-111.94479699999999,41.315201],"type":"Point"}
}