{
  "type": "Feature",
  "properties": {
    "iso:country":"US",
    "sg:address":"280 Old Lincoln Hwy",
    "sg:city":"Grantsville",
    "sg:classifiers":[
        {
            "category":"Retail",
            "subcategory":"Auto Repair",
            "type":"Services"
        }
    ],
    "sg:phone":"+1 435 884 3390",
    "sg:postcode":"84029",
    "sg:province":"UT",
    "sg:tags":[
        "repairing",
        "automobile"
    ],
    "wof:name":"Grant Automotive",
    "wof:placetype":"venue"
},
  "geometry": {"coordinates":[-112.48421,40.604425],"type":"Point"}
}