{
  "type": "Feature",
  "properties": {
    "iso:country":"US",
    "sg:address":"452 W 1260 N",
    "sg:city":"Orem",
    "sg:classifiers":[
        {
            "category":"Manufacturing",
            "subcategory":"Tools & Machinery",
            "type":"Manufacturing & Wholesale Goods"
        }
    ],
    "sg:phone":"+1 801 225 0930",
    "sg:postcode":"84057",
    "sg:province":"UT",
    "sg:tags":[
        "analytical",
        "optical",
        "mfg"
    ],
    "wof:name":"Moxtek Inc",
    "wof:placetype":"venue"
},
  "geometry": {"coordinates":[-111.705698,40.320376],"type":"Point"}
}