{
  "type": "Feature",
  "properties": {
    "iso:country":"US",
    "sg:address":"25 E 100 S",
    "sg:city":"Clarkston",
    "sg:classifiers":[
        {
            "category":"Organizations",
            "subcategory":"Religious Organization",
            "type":"Services"
        }
    ],
    "sg:phone":"+1 435 563 5231",
    "sg:postcode":"84305",
    "sg:province":"UT",
    "sg:tags":[
        "church"
    ],
    "wof:name":"Church Of Jesus Christ Of Lds",
    "wof:placetype":"venue"
},
  "geometry": {"coordinates":[-112.049092,41.918081],"type":"Point"}
}