{
  "type": "Feature",
  "properties": {
    "iso:country":"US",
    "sg:address":"1506 N 600 W",
    "sg:city":"Woods Cross",
    "sg:classifiers":[
        {
            "category":"Social Services",
            "subcategory":"Child Care",
            "type":"Services"
        }
    ],
    "sg:phone":"+1 801 295 0971",
    "sg:postcode":"84087",
    "sg:province":"UT",
    "sg:tags":[
        "day"
    ],
    "wof:name":"Kaes Kids",
    "wof:placetype":"venue"
},
  "geometry": {"coordinates":[-111.895275,40.906573],"type":"Point"}
}