{
  "type": "Feature",
  "properties": {
    "iso:country":"US",
    "sg:address":"80 S Main St",
    "sg:city":"Kamas",
    "sg:classifiers":[
        {
            "category":"Restaurant",
            "type":"Food & Drink"
        }
    ],
    "sg:phone":"+1 435 783 4453",
    "sg:postcode":"84036",
    "sg:province":"UT",
    "wof:name":"Summit Inn Pizza & Ice Cream",
    "wof:placetype":"venue"
},
  "geometry": {"coordinates":[-111.280866,40.641833],"type":"Point"}
}