{
  "type": "Feature",
  "properties": {
    "iso:country":"US",
    "sg:address":"1240 S Hwy 191",
    "sg:city":"Moab",
    "sg:classifiers":[
        {
            "category":"Food & Beverages",
            "subcategory":"Meat & Fish",
            "type":"Retail Goods"
        },
        {
            "category":"Wholesale",
            "subcategory":"Meat",
            "type":"Manufacturing & Wholesale Goods"
        }
    ],
    "sg:phone":"+1 435 259 4378",
    "sg:postcode":"84532",
    "sg:province":"UT",
    "wof:name":"Ye'Ol Geezer Meat Shop",
    "wof:placetype":"venue"
},
  "geometry": {"coordinates":[-109.53642600000001,38.555032],"type":"Point"}
}