{
  "type": "Feature",
  "properties": {
    "iso:country":"US",
    "sg:address":"31 Acorn Dr",
    "sg:city":"North Salt Lake",
    "sg:classifiers":[
        {
            "category":"Wholesale",
            "subcategory":"Durable Goods & Equipment",
            "type":"Manufacturing & Wholesale Goods"
        }
    ],
    "sg:phone":"+1 801 936 1700",
    "sg:postcode":"84054",
    "sg:province":"UT",
    "sg:tags":[
        "laboratory",
        "supply"
    ],
    "wof:name":"C R Squared",
    "wof:placetype":"venue"
},
  "geometry": {"coordinates":[-111.894068,40.841919],"type":"Point"}
}