{
  "type": "Feature",
  "properties": {
    "iso:country":"US",
    "sg:address":"3736 W 7800 S",
    "sg:city":"West Jordan",
    "sg:classifiers":[
        {
            "category":"Restaurant",
            "type":"Food & Drink"
        }
    ],
    "sg:menulink":"http://www.allmenus.com/ut/salt-lake-city/34223-applebees/menu/",
    "sg:phone":"+1 801 280 6699",
    "sg:postcode":"84088",
    "sg:province":"UT",
    "sg:tags":[
        "burger",
        "american",
        "sandwich",
        "soup"
    ],
    "wof:name":"Applebee's",
    "wof:placetype":"venue"
},
  "geometry": {"coordinates":[-111.980181,40.609529],"type":"Point"}
}