{
  "type": "Feature",
  "properties": {
    "iso:country":"US",
    "sg:address":"4826 Tomahawk Dr",
    "sg:city":"Cedar City",
    "sg:classifiers":[
        {
            "category":"Professional",
            "subcategory":"Engineering",
            "type":"Services"
        }
    ],
    "sg:phone":"+1 435 586 3076",
    "sg:postcode":"84720",
    "sg:province":"UT",
    "sg:tags":[
        "construction",
        "contract"
    ],
    "wof:name":"High Gear Grading Inc",
    "wof:placetype":"venue"
},
  "geometry": {"coordinates":[-113.03149999999999,37.765126],"type":"Point"}
}