{
  "type": "Feature",
  "properties": {
    "iso:country":"US",
    "sg:address":"279 E 650 N",
    "sg:city":"Bountiful",
    "sg:classifiers":[
        {
            "category":"Professional",
            "subcategory":"Research",
            "type":"Services"
        }
    ],
    "sg:phone":"+1 801 296 0741",
    "sg:postcode":"84010",
    "sg:province":"UT",
    "sg:tags":[
        "development",
        "marketing",
        "product"
    ],
    "wof:name":"Eclectic Grey Mater Designs",
    "wof:placetype":"venue"
},
  "geometry": {"coordinates":[-111.875467,40.896435],"type":"Point"}
}