{
  "type": "Feature",
  "properties": {
    "iso:country":"US",
    "sg:address":"261 E 300 S",
    "sg:city":"Salt Lake City",
    "sg:classifiers":[
        {
            "category":"Insurance",
            "subcategory":"Insurance Agent",
            "type":"Services"
        }
    ],
    "sg:phone":"+1 801 363 1215",
    "sg:postcode":"84111",
    "sg:province":"UT",
    "sg:tags":[
        "broker"
    ],
    "wof:name":"Stone & Associates Inc",
    "wof:placetype":"venue"
},
  "geometry": {"coordinates":[-111.882846,40.762901],"type":"Point"}
}