{
  "type": "Feature",
  "properties": {
    "iso:country":"US",
    "sg:address":"510 Buckley Ave",
    "sg:city":"Springville",
    "sg:classifiers":[
        {
            "category":"Professional",
            "type":"Services"
        }
    ],
    "sg:phone":"+1 801 489 7734",
    "sg:postcode":"84663",
    "sg:province":"UT",
    "wof:name":"Bhc Land Co Inc",
    "wof:placetype":"venue"
},
  "geometry": {"coordinates":[-111.600827,40.161722],"type":"Point"}
}