{
  "type": "Feature",
  "properties": {
    "iso:country":"US",
    "sg:address":"153 S 200 E",
    "sg:city":"American Fork",
    "sg:classifiers":[
        {
            "category":"Food & Beverages",
            "subcategory":"Specialty",
            "type":"Retail Goods"
        }
    ],
    "sg:phone":"+1 801 492 1988",
    "sg:postcode":"84003",
    "sg:province":"UT",
    "wof:name":"Makin Distributing",
    "wof:placetype":"venue"
},
  "geometry": {"coordinates":[-111.79304,40.373721],"type":"Point"}
}