{
  "type": "Feature",
  "properties": {
    "iso:country":"US",
    "sg:address":"847 N 900 E",
    "sg:city":"American Fork",
    "sg:classifiers":[
        {
            "category":"Education",
            "subcategory":"School",
            "type":"Public Place"
        }
    ],
    "sg:phone":"+1 801 763 4110",
    "sg:postcode":"84003",
    "sg:province":"UT",
    "wof:name":"Education Program",
    "wof:placetype":"venue"
},
  "geometry": {"coordinates":[-111.773355,40.392614],"type":"Point"}
}