{
  "type": "Feature",
  "properties": {
    "iso:country":"US",
    "sg:address":"76 W Saint George Blvd",
    "sg:city":"St George",
    "sg:classifiers":[
        {
            "category":"Shopping",
            "subcategory":"Used Merchandise",
            "type":"Retail Goods"
        }
    ],
    "sg:phone":"+1 435 674 7522",
    "sg:postcode":"84770",
    "sg:province":"UT",
    "sg:tags":[
        "shop",
        "thrift"
    ],
    "wof:name":"Repeat Performance Economy Str",
    "wof:placetype":"venue"
},
  "geometry": {"coordinates":[-113.584025,37.109973],"type":"Point"}
}