{
  "type": "Feature",
  "properties": {
    "iso:country":"US",
    "sg:address":"1324 US Hwy 89",
    "sg:city":"Farmington",
    "sg:classifiers":[
        {
            "category":"Personal",
            "subcategory":"Beauty Salon",
            "type":"Services"
        }
    ],
    "sg:phone":"+1 801 451 2223",
    "sg:postcode":"84025",
    "sg:province":"UT",
    "sg:tags":[
        "manicuring"
    ],
    "wof:name":"Star Nails",
    "wof:placetype":"venue"
},
  "geometry": {"coordinates":[-111.908563,41.001758],"type":"Point"}
}