{
  "type": "Feature",
  "properties": {
    "iso:country":"US",
    "sg:address":"6877 Pineview Cir",
    "sg:city":"Salt Lake City",
    "sg:classifiers":[
        {
            "category":"Wholesale",
            "subcategory":"Auto Parts",
            "type":"Manufacturing & Wholesale Goods"
        }
    ],
    "sg:phone":"+1 801 942 1867",
    "sg:postcode":"84121",
    "sg:province":"UT",
    "sg:tags":[
        "body"
    ],
    "wof:name":"Rocky Mountain Auto Body Parts",
    "wof:placetype":"venue"
},
  "geometry": {"coordinates":[-111.808481,40.626256],"type":"Point"}
}