{
  "type": "Feature",
  "properties": {
    "iso:country":"US",
    "sg:address":"58 S 360 W",
    "sg:city":"Orem",
    "sg:classifiers":[
        {
            "category":"Building & Trades",
            "subcategory":"Construction",
            "type":"Services"
        }
    ],
    "sg:phone":"+1 801 226 3942",
    "sg:postcode":"84058",
    "sg:province":"UT",
    "sg:tags":[
        "house"
    ],
    "wof:name":"Mov Construction LLC",
    "wof:placetype":"venue"
},
  "geometry": {"coordinates":[-111.704279,40.295594],"type":"Point"}
}