{
  "type": "Feature",
  "properties": {
    "iso:country":"US",
    "sg:address":"48 E Vine St",
    "sg:city":"Tooele",
    "sg:classifiers":[
        {
            "category":"Bars & Pubs",
            "type":"Food & Drink"
        }
    ],
    "sg:phone":"+1 435 882 9802",
    "sg:postcode":"84074",
    "sg:province":"UT",
    "sg:tags":[
        "drinking"
    ],
    "wof:name":"48 Lounge",
    "wof:placetype":"venue"
},
  "geometry": {"coordinates":[-112.29860600000001,40.530604],"type":"Point"}
}