{
  "type": "Feature",
  "properties": {
    "iso:country":"US",
    "sg:address":"47 E 500 S",
    "sg:city":"Bountiful",
    "sg:classifiers":[
        {
            "category":"Shopping",
            "subcategory":"Pharmacy",
            "type":"Retail Goods"
        }
    ],
    "sg:phone":"+1 801 295 3463",
    "sg:postcode":"84010",
    "sg:province":"UT",
    "sg:tags":[
        "drugstore"
    ],
    "wof:name":"Medicare Claims Information Medicine Shoppe the",
    "wof:placetype":"venue"
},
  "geometry": {"coordinates":[-111.879997,40.884399],"type":"Point"}
}