{
  "type": "Feature",
  "properties": {
    "iso:country":"US",
    "sg:address":"477 S 600 E",
    "sg:city":"Provo",
    "sg:classifiers":[
        {
            "category":"Professional",
            "subcategory":"Computer Services",
            "type":"Services"
        }
    ],
    "sg:phone":"+1 801 356 9080",
    "sg:postcode":"84606",
    "sg:province":"UT",
    "sg:tags":[
        "related"
    ],
    "wof:name":"Linux Method",
    "wof:placetype":"venue"
},
  "geometry": {"coordinates":[-111.648202,40.22803],"type":"Point"}
}