{
  "type": "Feature",
  "properties": {
    "iso:country":"US",
    "sg:address":"298 S 800 E",
    "sg:city":"Bountiful",
    "sg:classifiers":[
        {
            "category":"Banks & Credit Unions",
            "subcategory":"Financial Services",
            "type":"Services"
        }
    ],
    "sg:phone":"+1 801 292 8924",
    "sg:postcode":"84010",
    "sg:province":"UT",
    "sg:tags":[
        "company",
        "holding"
    ],
    "wof:name":"Solace Holdings LLC",
    "wof:placetype":"venue"
},
  "geometry": {"coordinates":[-111.86472500000001,40.887114],"type":"Point"}
}