{
  "type": "Feature",
  "properties": {
    "iso:country":"US",
    "sg:address":"11942 Bluff View Dr",
    "sg:city":"Sandy",
    "sg:classifiers":[
        {
            "category":"Building & Trades",
            "subcategory":"Construction",
            "type":"Services"
        }
    ],
    "sg:phone":"+1 801 572 2217",
    "sg:postcode":"84092",
    "sg:province":"UT",
    "sg:tags":[
        "new",
        "commercial",
        "renovation"
    ],
    "wof:name":"U-Systems Inc",
    "wof:placetype":"venue"
},
  "geometry": {"coordinates":[-111.852011,40.533926],"type":"Point"}
}