{
  "type": "Feature",
  "properties": {
    "iso:country":"US",
    "sg:address":"690 S Hillside Oak Cir",
    "sg:city":"North Salt Lake",
    "sg:classifiers":[
        {
            "category":"Professional",
            "subcategory":"Management & Consulting",
            "type":"Services"
        }
    ],
    "sg:phone":"+1 801 298 5551",
    "sg:postcode":"84054",
    "sg:province":"UT",
    "sg:tags":[
        "marketing",
        "consultant"
    ],
    "wof:name":"Worldscan One",
    "wof:placetype":"venue"
},
  "geometry": {"coordinates":[-111.894104,40.841584],"type":"Point"}
}