{
  "type": "Feature",
  "properties": {
    "iso:country":"US",
    "sg:address":"1264 W 1700 N",
    "sg:city":"Clearfield",
    "sg:classifiers":[
        {
            "category":"Building & Trades",
            "subcategory":"Construction",
            "type":"Services"
        }
    ],
    "sg:phone":"+1 801 776 5465",
    "sg:postcode":"84015",
    "sg:province":"UT",
    "sg:tags":[
        "house"
    ],
    "wof:name":"Rohde Custom Building",
    "wof:placetype":"venue"
},
  "geometry": {"coordinates":[-112.050256,41.138371],"type":"Point"}
}