{
  "type": "Feature",
  "properties": {
    "iso:country":"US",
    "sg:address":"48 W Broadway",
    "sg:city":"Salt Lake City",
    "sg:classifiers":[
        {
            "category":"Real Estate",
            "subcategory":"Real Estate Agent",
            "type":"Services"
        }
    ],
    "sg:phone":"+1 801 364 6209",
    "sg:postcode":"84101",
    "sg:province":"UT",
    "sg:tags":[
        "manager"
    ],
    "wof:name":"City Life Properties",
    "wof:placetype":"venue"
},
  "geometry": {"coordinates":[-111.892775,40.762898],"type":"Point"}
}