{
  "type": "Feature",
  "properties": {
    "iso:country":"US",
    "sg:address":"1251 Grove Dr",
    "sg:city":"Alpine",
    "sg:classifiers":[
        {
            "category":"Professional",
            "type":"Services"
        }
    ],
    "sg:phone":"+1 801 756 1523",
    "sg:postcode":"84004",
    "sg:province":"UT",
    "wof:name":"Secret Escape Inc",
    "wof:placetype":"venue"
},
  "geometry": {"coordinates":[-111.76683199999999,40.468772],"type":"Point"}
}