{
  "type": "Feature",
  "properties": {
    "iso:country":"US",
    "sg:address":"548 W 100 N",
    "sg:city":"Hurricane",
    "sg:classifiers":[
        {
            "category":"Wholesale",
            "subcategory":"Hardware",
            "type":"Manufacturing & Wholesale Goods"
        }
    ],
    "sg:phone":"+1 435 635 4441",
    "sg:postcode":"84737",
    "sg:province":"UT",
    "sg:tags":[
        "nut",
        "bolt"
    ],
    "sg:website":"www.scholzenproducts.com",
    "wof:name":"Scholzen Products",
    "wof:placetype":"venue"
},
  "geometry": {"coordinates":[-113.298284,37.178043],"type":"Point"}
}