{
  "type": "Feature",
  "properties": {
    "iso:country":"US",
    "sg:address":"257 S 3200 W",
    "sg:city":"Layton",
    "sg:classifiers":[
        {
            "category":"Wholesale",
            "subcategory":"Plants",
            "type":"Manufacturing & Wholesale Goods"
        },
        {
            "category":"Farming",
            "subcategory":"Nursery",
            "type":"Manufacturing & Wholesale Goods"
        }
    ],
    "sg:phone":"+1 801 544 8049",
    "sg:postcode":"84041",
    "sg:province":"UT",
    "sg:tags":[
        "sell",
        "tree",
        "grows",
        "stock"
    ],
    "wof:name":"Perennial Favorite LLC",
    "wof:placetype":"venue"
},
  "geometry": {"coordinates":[-112.026214,41.057739],"type":"Point"}
}