{
  "type": "Feature",
  "properties": {
    "iso:country":"US",
    "sg:address":"2992 S Main St",
    "sg:city":"Salt Lake City",
    "sg:classifiers":[
        {
            "category":"Professional",
            "subcategory":"Art Services",
            "type":"Services"
        }
    ],
    "sg:phone":"+1 801 484 1673",
    "sg:postcode":"84115",
    "sg:province":"UT",
    "sg:tags":[
        "photographer"
    ],
    "sg:website":"www.tregeagle-photo.com",
    "wof:name":"Steve Tregeagle Photography",
    "wof:placetype":"venue"
},
  "geometry": {"coordinates":[-111.8912,40.705916],"type":"Point"}
}