{
  "type": "Feature",
  "properties": {
    "iso:country":"US",
    "sg:address":"1421 Carrie Dr",
    "sg:city":"Kaysville",
    "sg:classifiers":[
        {
            "category":"Personal",
            "subcategory":"Hair Removal",
            "type":"Services"
        }
    ],
    "sg:phone":"+1 801 547 8838",
    "sg:postcode":"84037",
    "sg:province":"UT",
    "wof:name":"Steven Summers Cfp",
    "wof:placetype":"venue"
},
  "geometry": {"coordinates":[-111.905107,41.034885],"type":"Point"}
}