{
  "type": "Feature",
  "properties": {
    "iso:country":"US",
    "sg:address":"1930 W Sunset Blvd",
    "sg:city":"St George",
    "sg:classifiers":[
        {
            "category":"Banks & Credit Unions",
            "subcategory":"Bank",
            "type":"Services"
        }
    ],
    "sg:phone":"+1 435 673 9692",
    "sg:postcode":"84770",
    "sg:province":"UT",
    "wof:name":"Zions Bank",
    "wof:placetype":"venue"
},
  "geometry": {"coordinates":[-113.62581299999999,37.12329],"type":"Point"}
}