{
  "type": "Feature",
  "properties": {
    "iso:country":"US",
    "sg:address":"1025 Hollywood Ave",
    "sg:city":"Salt Lake City",
    "sg:classifiers":[
        {
            "category":"Real Estate",
            "subcategory":"Architect",
            "type":"Services"
        },
        {
            "category":"Building & Trades",
            "subcategory":"Construction",
            "type":"Services"
        }
    ],
    "sg:phone":"+1 801 485 0708",
    "sg:postcode":"84105",
    "sg:province":"UT",
    "sg:tags":[
        "nonresidential"
    ],
    "wof:name":"Architect's Office",
    "wof:placetype":"venue"
},
  "geometry": {"coordinates":[-111.861951,40.727452],"type":"Point"}
}