{
  "type": "Feature",
  "properties": {
    "iso:country":"US",
    "sg:address":"1330 E Hwy 40",
    "sg:city":"Vernal",
    "sg:classifiers":[
        {
            "category":"Manufacturing",
            "subcategory":"Tools & Machinery",
            "type":"Manufacturing & Wholesale Goods"
        }
    ],
    "sg:phone":"+1 435 789 2031",
    "sg:postcode":"84078",
    "sg:province":"UT",
    "sg:tags":[
        "field",
        "oil",
        "equipment"
    ],
    "wof:name":"Production Control Svc",
    "wof:placetype":"venue"
},
  "geometry": {"coordinates":[-109.502307,40.44882],"type":"Point"}
}