{
  "type": "Feature",
  "properties": {
    "iso:country":"US",
    "sg:address":"932 S 6525 E",
    "sg:city":"Huntsville",
    "sg:classifiers":[
        {
            "category":"Real Estate",
            "subcategory":"Developer",
            "type":"Services"
        }
    ],
    "sg:phone":"+1 801 745 3004",
    "sg:postcode":"84317",
    "sg:province":"UT",
    "sg:website":"www.skilake.com",
    "wof:name":"Ski Lake Corp",
    "wof:placetype":"venue"
},
  "geometry": {"coordinates":[-111.791297,41.249104],"type":"Point"}
}