{
  "type": "Feature",
  "properties": {
    "iso:country":"US",
    "sg:address":"4883 S State St",
    "sg:city":"Murray",
    "sg:classifiers":[
        {
            "category":"Retail",
            "subcategory":"Portrait Studio",
            "type":"Services"
        }
    ],
    "sg:phone":"+1 801 262 2685",
    "sg:postcode":"84107",
    "sg:province":"UT",
    "sg:tags":[
        "photographer",
        "photo"
    ],
    "sg:website":"www.donblairphotography.com",
    "wof:name":"Don Blair Photography",
    "wof:placetype":"venue"
},
  "geometry": {"coordinates":[-111.888276,40.666943],"type":"Point"}
}