{
  "type": "Feature",
  "properties": {
    "iso:country":"US",
    "sg:address":"890 Summit Dr",
    "sg:city":"Smithfield",
    "sg:classifiers":[
        {
            "category":"Building & Trades",
            "subcategory":"Construction",
            "type":"Services"
        }
    ],
    "sg:phone":"+1 435 563 8334",
    "sg:postcode":"84335",
    "sg:province":"UT",
    "sg:tags":[
        "excavation",
        "soil",
        "preparation",
        "contractor"
    ],
    "wof:name":"Thompson Enterprises",
    "wof:placetype":"venue"
},
  "geometry": {"coordinates":[-111.80985,41.841688],"type":"Point"}
}