{
  "type": "Feature",
  "properties": {
    "iso:country":"US",
    "sg:address":"292 E 950 S",
    "sg:city":"Orem",
    "sg:classifiers":[
        {
            "category":"Retail",
            "subcategory":"Auto Repair",
            "type":"Services"
        }
    ],
    "sg:phone":"+1 801 226 7000",
    "sg:postcode":"84058",
    "sg:province":"UT",
    "sg:tags":[
        "machine",
        "automobile",
        "shop",
        "automotive"
    ],
    "wof:name":"Slightly Cranky Machine Inc",
    "wof:placetype":"venue"
},
  "geometry": {"coordinates":[-111.689422,40.279125],"type":"Point"}
}