{
  "type": "Feature",
  "properties": {
    "iso:country":"US",
    "sg:address":"17 W Main St",
    "sg:city":"Newton",
    "sg:classifiers":[
        {
            "category":"Organizations",
            "subcategory":"Non-profit Organization",
            "type":"Services"
        }
    ],
    "sg:phone":"+1 435 563 6105",
    "sg:postcode":"84327",
    "sg:province":"UT",
    "wof:name":"United Suffolk Sheep Assn",
    "wof:placetype":"venue"
},
  "geometry": {"coordinates":[-111.99075000000001,41.862545],"type":"Point"}
}