{
  "type": "Feature",
  "properties": {
    "iso:country":"US",
    "sg:address":"189 State St",
    "sg:city":"Clearfield",
    "sg:classifiers":[
        {
            "category":"Professional",
            "subcategory":"Employment Agencies",
            "type":"Services"
        }
    ],
    "sg:phone":"+1 801 825 0500",
    "sg:postcode":"84015",
    "sg:province":"UT",
    "sg:tags":[
        "help",
        "supply"
    ],
    "wof:name":"Adecco Staffing",
    "wof:placetype":"venue"
},
  "geometry": {"coordinates":[-112.02498199999999,41.112889],"type":"Point"}
}