{
  "type": "Feature",
  "properties": {
    "iso:country":"US",
    "sg:address":"530 N 2200 W",
    "sg:city":"Layton",
    "sg:classifiers":[
        {
            "category":"Government",
            "subcategory":"Fire Station",
            "type":"Public Place"
        }
    ],
    "sg:phone":"+1 801 546 8555",
    "sg:postcode":"84041",
    "sg:province":"UT",
    "sg:tags":[
        "department"
    ],
    "sg:website":"www.laytoncity.org",
    "wof:name":"Layton Fire Dept",
    "wof:placetype":"venue"
},
  "geometry": {"coordinates":[-112.00696499999999,41.061813],"type":"Point"}
}