{
  "type": "Feature",
  "properties": {
    "iso:country":"US",
    "sg:address":"1891 Spring Ln",
    "sg:city":"Salt Lake City",
    "sg:classifiers":[
        {
            "category":"Professional",
            "subcategory":"Business Services",
            "type":"Services"
        }
    ],
    "sg:phone":"+1 801 755 6399",
    "sg:postcode":"84117",
    "sg:province":"UT",
    "wof:name":"Baggaley Enterprises LLC",
    "wof:placetype":"venue"
},
  "geometry": {"coordinates":[-111.835308,40.656002],"type":"Point"}
}