{
  "type": "Feature",
  "properties": {
    "iso:country":"US",
    "sg:address":"2713 S State St",
    "sg:city":"Salt Lake City",
    "sg:classifiers":[
        {
            "category":"Personal",
            "subcategory":"Beauty Salon",
            "type":"Services"
        }
    ],
    "sg:phone":"+1 801 466 4142",
    "sg:postcode":"84115",
    "sg:province":"UT",
    "wof:name":"Jennife Beauty Salon",
    "wof:placetype":"venue"
},
  "geometry": {"coordinates":[-111.888186,40.712142],"type":"Point"}
}