{
  "type": "Feature",
  "properties": {
    "iso:country":"US",
    "sg:address":"733 E 380 N",
    "sg:city":"American Fork",
    "sg:classifiers":[
        {
            "category":"Retail",
            "subcategory":"Repair Shop",
            "type":"Services"
        }
    ],
    "sg:phone":"+1 801 787 9475",
    "sg:postcode":"84003",
    "sg:province":"UT",
    "wof:name":"Rollin Clean",
    "wof:placetype":"venue"
},
  "geometry": {"coordinates":[-111.77818000000001,40.384658],"type":"Point"}
}