{
  "type": "Feature",
  "properties": {
    "iso:country":"US",
    "sg:address":"2773 W 7550 S",
    "sg:city":"West Jordan",
    "sg:classifiers":[
        {
            "category":"Wholesale",
            "subcategory":"Construction Materials",
            "type":"Manufacturing & Wholesale Goods"
        }
    ],
    "sg:phone":"+1 801 259 6092",
    "sg:postcode":"84084",
    "sg:province":"UT",
    "sg:tags":[
        "pallet",
        "skid"
    ],
    "wof:name":"Mr Pallets Valle",
    "wof:placetype":"venue"
},
  "geometry": {"coordinates":[-111.959638,40.613329],"type":"Point"}
}