{
  "type": "Feature",
  "properties": {
    "iso:country":"US",
    "sg:address":"1493 S Geneva Rd",
    "sg:city":"Orem",
    "sg:classifiers":[
        {
            "category":"Wholesale",
            "subcategory":"Auto Parts",
            "type":"Manufacturing & Wholesale Goods"
        }
    ],
    "sg:phone":"+1 801 225 2963",
    "sg:postcode":"84058",
    "sg:province":"UT",
    "sg:tags":[
        "automotive",
        "supply"
    ],
    "wof:name":"Jim Clinger Sales",
    "wof:placetype":"venue"
},
  "geometry": {"coordinates":[-111.721863,40.268733],"type":"Point"}
}