{
  "type": "Feature",
  "properties": {
    "iso:country":"US",
    "sg:address":"1944 S 1100 E",
    "sg:city":"Salt Lake City",
    "sg:classifiers":[
        {
            "category":"Shopping",
            "subcategory":"Crafts & Fabrics",
            "type":"Retail Goods"
        }
    ],
    "sg:phone":"+1 801 484 5890",
    "sg:postcode":"84106",
    "sg:province":"UT",
    "sg:tags":[
        "material",
        "quilting",
        "sewing",
        "supply"
    ],
    "sg:website":"www.pipersquilts.com",
    "wof:name":"Piper's Quilts & Comforts",
    "wof:placetype":"venue"
},
  "geometry": {"coordinates":[-111.85968,40.727735],"type":"Point"}
}