{
  "type": "Feature",
  "properties": {
    "iso:country":"US",
    "sg:address":"2311 E 3300 S",
    "sg:city":"Salt Lake City",
    "sg:classifiers":[
        {
            "category":"Banks & Credit Unions",
            "subcategory":"Bank",
            "type":"Services"
        }
    ],
    "sg:phone":"+1 801 486 2020",
    "sg:postcode":"84109",
    "sg:province":"UT",
    "sg:tags":[
        "cashing",
        "check"
    ],
    "wof:name":"Check City",
    "wof:placetype":"venue"
},
  "geometry": {"coordinates":[-111.820961,40.699929],"type":"Point"}
}