{
  "type": "Feature",
  "properties": {
    "iso:country":"US",
    "sg:address":"54 N Main St",
    "sg:city":"Spanish Fork",
    "sg:classifiers":[
        {
            "category":"Personal",
            "subcategory":"Beauty Salon",
            "type":"Services"
        }
    ],
    "sg:phone":"+1 801 798 8988",
    "sg:postcode":"84660",
    "sg:province":"UT",
    "sg:tags":[
        "shop"
    ],
    "wof:name":"Hideaway Salon",
    "wof:placetype":"venue"
},
  "geometry": {"coordinates":[-111.654704,40.110445],"type":"Point"}
}