{
  "type": "Feature",
  "properties": {
    "iso:country":"US",
    "sg:address":"681 N 800 W",
    "sg:city":"Orem",
    "sg:classifiers":[
        {
            "category":"Arts & Performance",
            "subcategory":"Theater",
            "type":"Entertainment"
        }
    ],
    "sg:phone":"+1 801 229 1282",
    "sg:postcode":"84057",
    "sg:province":"UT",
    "sg:tags":[
        "group"
    ],
    "wof:name":"Idoneon",
    "wof:placetype":"venue"
},
  "geometry": {"coordinates":[-111.715024,40.309181],"type":"Point"}
}