{
  "type": "Feature",
  "properties": {
    "iso:country":"US",
    "sg:address":"5296 Commerce Dr",
    "sg:city":"Murray",
    "sg:classifiers":[
        {
            "category":"Professional",
            "subcategory":"Employment Agencies",
            "type":"Services"
        }
    ],
    "sg:phone":"+1 801 262 7300",
    "sg:postcode":"84107",
    "sg:province":"UT",
    "sg:tags":[
        "leasing"
    ],
    "wof:name":"AEG",
    "wof:placetype":"venue"
},
  "geometry": {"coordinates":[-111.898475,40.65691],"type":"Point"}
}