{
  "type": "Feature",
  "properties": {
    "iso:country":"US",
    "sg:address":"5058 W 4200 S",
    "sg:city":"West Valley",
    "sg:classifiers":[
        {
            "category":"Building & Trades",
            "subcategory":"Construction",
            "type":"Services"
        }
    ],
    "sg:phone":"+1 801 969 5180",
    "sg:postcode":"84120",
    "sg:province":"UT",
    "sg:tags":[
        "repairing",
        "remodeling",
        "contractor"
    ],
    "wof:name":"Roberts Brothers Siding Inc",
    "wof:placetype":"venue"
},
  "geometry": {"coordinates":[-112.01298199999999,40.67964],"type":"Point"}
}