{
  "type": "Feature",
  "properties": {
    "iso:country":"US",
    "sg:address":"2560 S Main St",
    "sg:city":"South Salt Lake",
    "sg:phone":"+1 801 485 5751",
    "sg:postcode":"84115",
    "sg:province":"UT",
    "sg:tags":[
        "equipment",
        "supply"
    ],
    "wof:name":"S & H Restaurant & Store Equip",
    "wof:placetype":"venue"
},
  "geometry": {"coordinates":[-111.891186,40.714411],"type":"Point"}
}