{
  "type": "Feature",
  "properties": {
    "iso:country":"US",
    "sg:address":"503 N 300 W",
    "sg:city":"Kanab",
    "sg:classifiers":[
        {
            "category":"Farming",
            "subcategory":"Livestock Farm",
            "type":"Manufacturing & Wholesale Goods"
        }
    ],
    "sg:phone":"+1 435 644 5017",
    "sg:postcode":"84741",
    "sg:province":"UT",
    "sg:tags":[
        "animal",
        "general"
    ],
    "wof:name":"Ej Cattle Ranches",
    "wof:placetype":"venue"
},
  "geometry": {"coordinates":[-112.535207,37.05461],"type":"Point"}
}