{
  "type": "Feature",
  "properties": {
    "iso:country":"US",
    "sg:address":"70 S State St",
    "sg:city":"Salt Lake City",
    "sg:classifiers":[
        {
            "category":"Utilities",
            "subcategory":"Telephone",
            "type":"Services"
        }
    ],
    "sg:phone":"+1 801 328 9865",
    "sg:postcode":"84111",
    "sg:province":"UT",
    "sg:tags":[
        "company"
    ],
    "wof:name":"A T & T",
    "wof:placetype":"venue"
},
  "geometry": {"coordinates":[-111.88830299999999,40.767614],"type":"Point"}
}