{
  "type": "Feature",
  "properties": {
    "iso:country":"US",
    "sg:address":"365 N Main St",
    "sg:city":"Spanish Fork",
    "sg:classifiers":[
        {
            "category":"Sports & Exercise",
            "subcategory":"Bowling",
            "type":"Entertainment"
        }
    ],
    "sg:phone":"+1 801 798 3885",
    "sg:postcode":"84660",
    "sg:province":"UT",
    "sg:tags":[
        "eating",
        "center"
    ],
    "wof:name":"Duke's Lanes",
    "wof:placetype":"venue"
},
  "geometry": {"coordinates":[-111.654832,40.114179],"type":"Point"}
}