{
  "type": "Feature",
  "properties": {
    "iso:country":"US",
    "sg:address":"206 Cottage Ave",
    "sg:city":"Sandy",
    "sg:classifiers":[
        {
            "category":"Manufacturing",
            "subcategory":"Printing",
            "type":"Manufacturing & Wholesale Goods"
        }
    ],
    "sg:phone":"+1 801 565 3658",
    "sg:postcode":"84070",
    "sg:province":"UT",
    "sg:tags":[
        "commercial"
    ],
    "wof:name":"Moore Graphic Services",
    "wof:placetype":"venue"
},
  "geometry": {"coordinates":[-111.897578,40.592272],"type":"Point"}
}