{
  "type": "Feature",
  "properties": {
    "iso:country":"US",
    "sg:address":"2448 Progress Dr",
    "sg:city":"Salt Lake City",
    "sg:classifiers":[
        {
            "category":"Manufacturing",
            "subcategory":"Tools & Machinery",
            "type":"Manufacturing & Wholesale Goods"
        }
    ],
    "sg:phone":"+1 801 487 0705",
    "sg:postcode":"84119",
    "sg:province":"UT",
    "sg:tags":[
        "equipment",
        "industrial",
        "mfg"
    ],
    "wof:name":"Schindler",
    "wof:placetype":"venue"
},
  "geometry": {"coordinates":[-111.94485,40.717823],"type":"Point"}
}