{
  "type": "Feature",
  "properties": {
    "iso:country":"US",
    "sg:address":"1612 E 3010 S",
    "sg:city":"Salt Lake City",
    "sg:classifiers":[
        {
            "category":"Building & Trades",
            "subcategory":"Construction",
            "type":"Services"
        }
    ],
    "sg:phone":"+1 801 486 6004",
    "sg:postcode":"84106",
    "sg:province":"UT",
    "sg:tags":[
        "floor",
        "laying",
        "contractor"
    ],
    "wof:name":"Denney Floor Service",
    "wof:placetype":"venue"
},
  "geometry": {"coordinates":[-111.847353,40.705499],"type":"Point"}
}