{
  "type": "Feature",
  "properties": {
    "iso:country":"US",
    "sg:address":"1598 Farr Dr",
    "sg:city":"Ogden",
    "sg:classifiers":[
        {
            "category":"Building & Trades",
            "subcategory":"Construction",
            "type":"Services"
        }
    ],
    "sg:phone":"+1 801 392 6630",
    "sg:postcode":"84404",
    "sg:province":"UT",
    "sg:tags":[
        "contractor"
    ],
    "wof:name":"Buckway Siding Co",
    "wof:placetype":"venue"
},
  "geometry": {"coordinates":[-111.946691,41.239432],"type":"Point"}
}