{
  "type": "Feature",
  "properties": {
    "iso:country":"US",
    "sg:address":"2740 Wilshire Dr",
    "sg:city":"Salt Lake City",
    "sg:classifiers":[
        {
            "category":"Banks & Credit Unions",
            "subcategory":"Financial Services",
            "type":"Services"
        }
    ],
    "sg:phone":"+1 801 484 5734",
    "sg:postcode":"84109",
    "sg:province":"UT",
    "sg:tags":[
        "investor"
    ],
    "wof:name":"Kurt Bernhisel LLC",
    "wof:placetype":"venue"
},
  "geometry": {"coordinates":[-111.81394400000001,40.717257],"type":"Point"}
}