{
  "type": "Feature",
  "properties": {
    "iso:country":"US",
    "sg:address":"347 N 400 E",
    "sg:city":"Orem",
    "sg:classifiers":[
        {
            "category":"Building & Trades",
            "subcategory":"Construction",
            "type":"Services"
        }
    ],
    "sg:phone":"+1 801 225 1180",
    "sg:postcode":"84097",
    "sg:province":"UT",
    "wof:name":"Ac-Csi Joint Venture",
    "wof:placetype":"venue"
},
  "geometry": {"coordinates":[-111.686173,40.304162],"type":"Point"}
}