{
  "type": "Feature",
  "properties": {
    "iso:country":"US",
    "sg:address":"7015 N 6800 W",
    "sg:city":"Tremonton",
    "sg:classifiers":[
        {
            "category":"Wholesale",
            "subcategory":"Farm Supplies",
            "type":"Manufacturing & Wholesale Goods"
        }
    ],
    "sg:phone":"+1 435 257 7972",
    "sg:postcode":"84337",
    "sg:province":"UT",
    "sg:tags":[
        "livestock"
    ],
    "wof:name":"Jensen Livestock",
    "wof:placetype":"venue"
},
  "geometry": {"coordinates":[-112.17854800000001,41.634618],"type":"Point"}
}