{
  "type": "Feature",
  "properties": {
    "iso:country":"US",
    "sg:address":"8471 Solar Way",
    "sg:city":"Sandy",
    "sg:classifiers":[
        {
            "category":"Autos & Motor Vehicles",
            "subcategory":"Recreational Vehicle Sales",
            "type":"Retail Goods"
        }
    ],
    "sg:phone":"+1 801 255 2229",
    "sg:postcode":"84070",
    "sg:province":"UT",
    "wof:name":"Sky View Rv & Mobile Home Park",
    "wof:placetype":"venue"
},
  "geometry": {"coordinates":[-111.88788700000001,40.596548],"type":"Point"}
}