{
  "type": "Feature",
  "properties": {
    "iso:country":"US",
    "sg:address":"400 E 300 N",
    "sg:city":"Alpine",
    "sg:classifiers":[
        {
            "category":"Education",
            "subcategory":"School",
            "type":"Public Place"
        }
    ],
    "sg:phone":"+1 801 756 8525",
    "sg:postcode":"84004",
    "sg:province":"UT",
    "wof:name":"Alpine Elementary School",
    "wof:placetype":"venue"
},
  "geometry": {"coordinates":[-111.770787,40.457015],"type":"Point"}
}