{
  "type": "Feature",
  "properties": {
    "iso:country":"US",
    "sg:address":"33 N Carbon Ave",
    "sg:city":"Price",
    "sg:classifiers":[
        {
            "category":"Autos & Motor Vehicles",
            "subcategory":"Auto Supplies",
            "type":"Retail Goods"
        }
    ],
    "sg:phone":"+1 435 637 4230",
    "sg:postcode":"84501",
    "sg:province":"UT",
    "sg:tags":[
        "automobile",
        "parts"
    ],
    "wof:name":"Price Trading Co-Parts Plus",
    "wof:placetype":"venue"
},
  "geometry": {"coordinates":[-110.81134400000001,39.600533],"type":"Point"}
}