{
  "type": "Feature",
  "properties": {
    "iso:country":"US",
    "sg:address":"25 N Main St",
    "sg:city":"Cedar City",
    "sg:classifiers":[
        {
            "category":"Shopping",
            "subcategory":"Gifts & Souvenirs",
            "type":"Retail Goods"
        }
    ],
    "sg:phone":"+1 435 586 2614",
    "sg:postcode":"84720",
    "sg:province":"UT",
    "wof:name":"Cottage Kids",
    "wof:placetype":"venue"
},
  "geometry": {"coordinates":[-113.061742,37.677767],"type":"Point"}
}