{
  "type": "Feature",
  "properties": {
    "iso:country":"US",
    "sg:address":"535 S Main St",
    "sg:city":"Richfield",
    "sg:classifiers":[
        {
            "category":"Retail",
            "subcategory":"Car Wash",
            "type":"Services"
        }
    ],
    "sg:phone":"+1 435 896 6004",
    "sg:postcode":"84701",
    "sg:province":"UT",
    "sg:tags":[
        "polishing",
        "washing"
    ],
    "wof:name":"Super Wash",
    "wof:placetype":"venue"
},
  "geometry": {"coordinates":[-112.084625,38.760652],"type":"Point"}
}