{
  "type": "Feature",
  "properties": {
    "iso:country":"US",
    "sg:address":"1428 Center St",
    "sg:city":"Evanston",
    "sg:classifiers":[
        {
            "category":"Professional",
            "type":"Services"
        }
    ],
    "sg:phone":"+1 307 789 3721",
    "sg:postcode":"82930",
    "sg:province":"UT",
    "sg:tags":[
        "establishment"
    ],
    "wof:name":"Bowen Inc",
    "wof:placetype":"venue"
},
  "geometry": {"coordinates":[-110.971474,41.270436],"type":"Point"}
}