{
  "type": "Feature",
  "properties": {
    "iso:country":"US",
    "sg:address":"6425 S 3000 E",
    "sg:city":"Salt Lake City",
    "sg:classifiers":[
        {
            "category":"Professional",
            "subcategory":"Engineering",
            "type":"Services"
        }
    ],
    "sg:phone":"+1 801 944 1280",
    "sg:postcode":"84121",
    "sg:province":"UT",
    "sg:tags":[
        "engineer"
    ],
    "wof:name":"Luscombe Engineering",
    "wof:placetype":"venue"
},
  "geometry": {"coordinates":[-111.805987,40.634134],"type":"Point"}
}