{
  "type": "Feature",
  "properties": {
    "iso:country":"US",
    "sg:address":"1675 Redstone Center Dr",
    "sg:city":"Park City",
    "sg:classifiers":[
        {
            "category":"Restaurant",
            "type":"Food & Drink"
        }
    ],
    "sg:menulink":"http://www.allmenus.com/ut/park-city/116244-quiznos-sub/menu/",
    "sg:phone":"+1 435 575 0213",
    "sg:postcode":"84098",
    "sg:province":"UT",
    "sg:tags":[
        "wrap",
        "american",
        "sandwich"
    ],
    "wof:name":"Quiznos Sub",
    "wof:placetype":"venue"
},
  "geometry": {"coordinates":[-111.542624,40.720355],"type":"Point"}
}