{
  "type": "Feature",
  "properties": {
    "iso:country":"US",
    "sg:address":"411 Hillside Dr",
    "sg:city":"Salt Lake City",
    "sg:classifiers":[
        {
            "category":"Health Services",
            "subcategory":"Chiropractor",
            "type":"Services"
        }
    ],
    "sg:phone":"+1 801 288 2332",
    "sg:postcode":"84107",
    "sg:province":"UT",
    "wof:name":"Physicians Medical Care",
    "wof:placetype":"venue"
},
  "geometry": {"coordinates":[-111.881905,40.651305],"type":"Point"}
}