{
  "type": "Feature",
  "properties": {
    "iso:country":"US",
    "sg:address":"180 E 100 S",
    "sg:city":"Salt Lake City",
    "sg:classifiers":[
        {
            "category":"Banks & Credit Unions",
            "subcategory":"Bank",
            "type":"Services"
        }
    ],
    "sg:phone":"+1 801 325 6228",
    "sg:postcode":"84111",
    "sg:province":"UT",
    "wof:name":"Mountain America Credit Union",
    "wof:placetype":"venue"
},
  "geometry": {"coordinates":[-111.887691,40.767099],"type":"Point"}
}