{
  "type": "Feature",
  "properties": {
    "iso:country":"US",
    "sg:address":"663 Church St",
    "sg:city":"Layton",
    "sg:classifiers":[
        {
            "category":"Education",
            "subcategory":"School",
            "type":"Public Place"
        }
    ],
    "sg:phone":"+1 801 402 7100",
    "sg:postcode":"84041",
    "sg:province":"UT",
    "wof:name":"Central Davis Junior High 408",
    "wof:placetype":"venue"
},
  "geometry": {"coordinates":[-111.963083,41.070249],"type":"Point"}
}