{
  "type": "Feature",
  "properties": {
    "iso:country":"US",
    "sg:address":"744 Sweet Meadow Ln",
    "sg:city":"Sandy",
    "sg:classifiers":[
        {
            "category":"Building & Trades",
            "subcategory":"Electrical",
            "type":"Services"
        }
    ],
    "sg:phone":"+1 801 233 8113",
    "sg:postcode":"84070",
    "sg:province":"UT",
    "sg:tags":[
        "electrical",
        "contractor"
    ],
    "wof:name":"Big Rock Electric LLC",
    "wof:placetype":"venue"
},
  "geometry": {"coordinates":[-111.91125,40.581448],"type":"Point"}
}