{
  "type": "Feature",
  "properties": {
    "iso:country":"US",
    "sg:address":"180 31st St",
    "sg:city":"Ogden",
    "sg:classifiers":[
        {
            "category":"Shopping",
            "subcategory":"Used Merchandise",
            "type":"Retail Goods"
        }
    ],
    "sg:phone":"+1 801 394 9035",
    "sg:postcode":"84401",
    "sg:province":"UT",
    "sg:tags":[
        "antique"
    ],
    "wof:name":"Abbys Estate Liquidators",
    "wof:placetype":"venue"
},
  "geometry": {"coordinates":[-111.978634,41.208294],"type":"Point"}
}