{
  "type": "Feature",
  "properties": {
    "iso:country":"US",
    "sg:address":"693 Main St",
    "sg:city":"Park City",
    "sg:classifiers":[
        {
            "category":"Shopping",
            "subcategory":"Jewelry",
            "type":"Retail Goods"
        }
    ],
    "sg:phone":"+1 435 649 1211",
    "sg:postcode":"84060",
    "sg:province":"UT",
    "sg:tags":[
        "designer"
    ],
    "wof:name":"Lido Gallery",
    "wof:placetype":"venue"
},
  "geometry": {"coordinates":[-111.497697,40.6467],"type":"Point"}
}