{
  "type": "Feature",
  "properties": {
    "iso:country":"US",
    "sg:address":"6830 Virginia Hills Dr",
    "sg:city":"Salt Lake City",
    "sg:classifiers":[
        {
            "category":"Building & Trades",
            "subcategory":"Construction",
            "type":"Services"
        }
    ],
    "sg:phone":"+1 801 944 4168",
    "sg:postcode":"84121",
    "sg:province":"UT",
    "sg:tags":[
        "contractor"
    ],
    "wof:name":"Discount Tile & Marble",
    "wof:placetype":"venue"
},
  "geometry": {"coordinates":[-111.814604,40.62641],"type":"Point"}
}