{
  "type": "Feature",
  "properties": {
    "iso:country":"US",
    "sg:address":"3671 W 1987 S",
    "sg:city":"Salt Lake City",
    "sg:classifiers":[
        {
            "category":"Professional",
            "subcategory":"Business Services",
            "type":"Services"
        },
        {
            "category":"Building & Trades",
            "subcategory":"Construction",
            "type":"Services"
        }
    ],
    "sg:phone":"+1 801 972 5050",
    "sg:postcode":"84104",
    "sg:province":"UT",
    "sg:tags":[
        "water",
        "remediation",
        "treatment"
    ],
    "wof:name":"Water Recovery Sciences Lc",
    "wof:placetype":"venue"
},
  "geometry": {"coordinates":[-111.978897,40.727657],"type":"Point"}
}