{
  "type": "Feature",
  "properties": {
    "iso:country":"US",
    "sg:address":"1927 W Hwy 40",
    "sg:city":"Vernal",
    "sg:classifiers":[
        {
            "category":"Building & Trades",
            "subcategory":"Construction",
            "type":"Services"
        }
    ],
    "sg:phone":"+1 435 789 6898",
    "sg:postcode":"84078",
    "sg:province":"UT",
    "sg:tags":[
        "roofing",
        "contractor"
    ],
    "wof:name":"Pitt Roofing & Construction",
    "wof:placetype":"venue"
},
  "geometry": {"coordinates":[-109.565037,40.439129],"type":"Point"}
}