{
  "type": "Feature",
  "properties": {
    "iso:country":"US",
    "sg:address":"4815 Kings Row Dr",
    "sg:city":"Salt Lake City",
    "sg:classifiers":[
        {
            "category":"Professional",
            "subcategory":"Management & Consulting",
            "type":"Services"
        }
    ],
    "sg:phone":"+1 801 274 0585",
    "sg:postcode":"84117",
    "sg:province":"UT",
    "sg:tags":[
        "business"
    ],
    "wof:name":"Jdb Consulting",
    "wof:placetype":"venue"
},
  "geometry": {"coordinates":[-111.844487,40.665916],"type":"Point"}
}