{
  "type": "Feature",
  "properties": {
    "iso:country":"US",
    "sg:address":"695 W 1100 N",
    "sg:city":"North Salt Lake",
    "sg:classifiers":[
        {
            "category":"Freight",
            "type":"Transportation"
        }
    ],
    "sg:phone":"+1 801 936 2221",
    "sg:postcode":"84054",
    "sg:province":"UT",
    "sg:tags":[
        "trucking"
    ],
    "wof:name":"Crete Carrier Corp",
    "wof:placetype":"venue"
},
  "geometry": {"coordinates":[-111.926439,40.86156],"type":"Point"}
}