{
  "type": "Feature",
  "properties": {
    "iso:country":"US",
    "sg:address":"110 W 300 S",
    "sg:city":"Salt Lake City",
    "sg:classifiers":[
        {
            "category":"Travel",
            "subcategory":"Hotels & Motels",
            "type":"Entertainment"
        }
    ],
    "sg:phone":"+1 801 521 4300",
    "sg:postcode":"84101",
    "sg:province":"UT",
    "sg:website":"www.peeryhotel.com",
    "wof:name":"Peery Hotel",
    "wof:placetype":"venue"
},
  "geometry": {"coordinates":[-111.89534500000001,40.762895],"type":"Point"}
}