{
  "type": "Feature",
  "properties": {
    "iso:country":"US",
    "sg:address":"3344 Olive Leaf Ln",
    "sg:city":"West Jordan",
    "sg:classifiers":[
        {
            "category":"Building & Trades",
            "subcategory":"Construction",
            "type":"Services"
        }
    ],
    "sg:phone":"+1 801 561 2223",
    "sg:postcode":"84088",
    "sg:province":"UT",
    "sg:tags":[
        "hanging",
        "contractor"
    ],
    "wof:name":"Bear Painting Inc",
    "wof:placetype":"venue"
},
  "geometry": {"coordinates":[-111.97091500000001,40.588847],"type":"Point"}
}