{
  "type": "Feature",
  "properties": {
    "iso:country":"US",
    "sg:address":"1114 N 600 W",
    "sg:city":"Orem",
    "sg:classifiers":[
        {
            "category":"Building & Trades",
            "subcategory":"Cleaning & Sanitation",
            "type":"Services"
        }
    ],
    "sg:phone":"+1 801 225 3598",
    "sg:postcode":"84057",
    "sg:province":"UT",
    "sg:tags":[
        "maintenance"
    ],
    "wof:name":"Practical Janitorial Systems",
    "wof:placetype":"venue"
},
  "geometry": {"coordinates":[-111.710232,40.317356],"type":"Point"}
}