{
  "type": "Feature",
  "properties": {
    "iso:country":"US",
    "sg:address":"9507 S 560 W",
    "sg:city":"Sandy",
    "sg:classifiers":[
        {
            "category":"Retail",
            "subcategory":"Auto Repair",
            "type":"Services"
        }
    ],
    "sg:phone":"+1 801 236 2521",
    "sg:postcode":"84070",
    "sg:province":"UT",
    "sg:tags":[
        "wrecker"
    ],
    "wof:name":"Speedy Towing",
    "wof:placetype":"venue"
},
  "geometry": {"coordinates":[-111.907399,40.578413],"type":"Point"}
}