{
  "type": "Feature",
  "properties": {
    "iso:country":"US",
    "sg:address":"44 W Broadway",
    "sg:city":"Salt Lake City",
    "sg:classifiers":[
        {
            "category":"Real Estate",
            "subcategory":"Real Estate Operator",
            "type":"Services"
        }
    ],
    "sg:phone":"+1 801 328 1943",
    "sg:postcode":"84101",
    "sg:province":"UT",
    "sg:tags":[
        "condominium"
    ],
    "wof:name":"American Towers Condos",
    "wof:placetype":"venue"
},
  "geometry": {"coordinates":[-111.892865,40.762898],"type":"Point"}
}