{
  "type": "Feature",
  "properties": {
    "iso:country":"US",
    "sg:address":"505 N State St",
    "sg:city":"Hurricane",
    "sg:classifiers":[
        {
            "category":"Autos & Motor Vehicles",
            "subcategory":"Automobile Sales",
            "type":"Retail Goods"
        }
    ],
    "sg:phone":"+1 435 635 9500",
    "sg:postcode":"84737",
    "sg:province":"UT",
    "sg:tags":[
        "used"
    ],
    "wof:name":"Better Buggies Auto Sales",
    "wof:placetype":"venue"
},
  "geometry": {"coordinates":[-113.282387,37.183446],"type":"Point"}
}