{
  "type": "Feature",
  "properties": {
    "iso:country":"US",
    "sg:address":"1867 S 3230 W",
    "sg:city":"Salt Lake City",
    "sg:classifiers":[
        {
            "category":"Wholesale",
            "subcategory":"Electrical",
            "type":"Manufacturing & Wholesale Goods"
        }
    ],
    "sg:phone":"+1 801 973 6987",
    "sg:postcode":"84104",
    "sg:province":"UT",
    "sg:tags":[
        "battery",
        "auto"
    ],
    "wof:name":"Exide Technologies",
    "wof:placetype":"venue"
},
  "geometry": {"coordinates":[-111.968112,40.72937],"type":"Point"}
}