{
  "type": "Feature",
  "properties": {
    "iso:country":"US",
    "sg:address":"1000 Jewell Ave",
    "sg:city":"Salt Lake City",
    "sg:classifiers":[
        {
            "category":"Wholesale",
            "subcategory":"Auto Parts",
            "type":"Manufacturing & Wholesale Goods"
        }
    ],
    "sg:phone":"+1 801 973 7283",
    "sg:postcode":"84104",
    "sg:province":"UT",
    "sg:tags":[
        "truck",
        "refrigeration",
        "equipment"
    ],
    "wof:name":"Quality Transport",
    "wof:placetype":"venue"
},
  "geometry": {"coordinates":[-111.91863499999999,40.728907],"type":"Point"}
}