{
  "type": "Feature",
  "properties": {
    "iso:country":"US",
    "sg:address":"145 N 1000 W",
    "sg:city":"Logan",
    "sg:classifiers":[
        {
            "category":"Wholesale",
            "subcategory":"Scrap",
            "type":"Manufacturing & Wholesale Goods"
        }
    ],
    "sg:phone":"+1 435 752 0571",
    "sg:postcode":"84321",
    "sg:province":"UT",
    "sg:tags":[
        "metal"
    ],
    "wof:name":"Valley Metals Inc",
    "wof:placetype":"venue"
},
  "geometry": {"coordinates":[-111.85971600000001,41.732848],"type":"Point"}
}