{
  "type": "Feature",
  "properties": {
    "iso:country":"US",
    "sg:address":"1031 Sullivan Rd",
    "sg:city":"Ogden",
    "sg:classifiers":[
        {
            "category":"Travel",
            "subcategory":"Hotels & Motels",
            "type":"Entertainment"
        },
        {
            "category":"Personal",
            "type":"Services"
        }
    ],
    "sg:phone":"+1 801 603 3318",
    "sg:postcode":"84403",
    "sg:province":"UT",
    "sg:tags":[
        "concierge",
        "assistant"
    ],
    "wof:name":"New World Energy",
    "wof:placetype":"venue"
},
  "geometry": {"coordinates":[-111.953217,41.206293],"type":"Point"}
}