{
  "type": "Feature",
  "properties": {
    "iso:country":"US",
    "sg:address":"130 N Main St",
    "sg:city":"Hurricane",
    "sg:classifiers":[
        {
            "category":"Real Estate",
            "subcategory":"Real Estate Agent",
            "type":"Services"
        }
    ],
    "sg:phone":"+1 435 635 3722",
    "sg:postcode":"84737",
    "sg:province":"UT",
    "wof:name":"Simpson Charles Real Estate",
    "wof:placetype":"venue"
},
  "geometry": {"coordinates":[-113.288056,37.179095],"type":"Point"}
}