{
  "type": "Feature",
  "properties": {
    "iso:country":"US",
    "sg:address":"4134 W 6400 S",
    "sg:city":"Spanish Fork",
    "sg:classifiers":[
        {
            "category":"Food & Beverages",
            "subcategory":"Bakery",
            "type":"Retail Goods"
        }
    ],
    "sg:phone":"+1 801 798 9289",
    "sg:postcode":"84660",
    "sg:province":"UT",
    "wof:name":"Greater Wasatch Dutch Oven Soc",
    "wof:placetype":"venue"
},
  "geometry": {"coordinates":[-111.752414,40.114621],"type":"Point"}
}