{
  "type": "Feature",
  "properties": {
    "iso:country":"US",
    "sg:address":"335 Pierpont Ave",
    "sg:city":"Salt Lake City",
    "sg:classifiers":[
        {
            "category":"Professional",
            "type":"Services"
        }
    ],
    "sg:phone":"+1 801 355 2715",
    "sg:postcode":"84101",
    "sg:province":"UT",
    "sg:tags":[
        "art",
        "restoring"
    ],
    "wof:name":"Chad Smith",
    "wof:placetype":"venue"
},
  "geometry": {"coordinates":[-111.90164,40.763758],"type":"Point"}
}