{
  "type": "Feature",
  "properties": {
    "iso:country":"US",
    "sg:address":"3785 S 700 E",
    "sg:city":"Salt Lake City",
    "sg:classifiers":[
        {
            "category":"Insurance",
            "subcategory":"Insurance Agent",
            "type":"Services"
        }
    ],
    "sg:phone":"+1 801 268 2600",
    "sg:postcode":"84106",
    "sg:province":"UT",
    "wof:name":"Poulton Associates Inc",
    "wof:placetype":"venue"
},
  "geometry": {"coordinates":[-111.87129400000001,40.689969],"type":"Point"}
}