{
  "type": "Feature",
  "properties": {
    "iso:country":"US",
    "sg:address":"1487 E State St",
    "sg:city":"Lehi",
    "sg:classifiers":[
        {
            "category":"Building & Trades",
            "subcategory":"Construction",
            "type":"Services"
        }
    ],
    "sg:phone":"+1 801 492 0204",
    "sg:postcode":"84043",
    "sg:province":"UT",
    "sg:tags":[
        "excavating",
        "contractor"
    ],
    "wof:name":"Coyote Construction",
    "wof:placetype":"venue"
},
  "geometry": {"coordinates":[-111.82684500000001,40.388921],"type":"Point"}
}