{
  "type": "Feature",
  "properties": {
    "iso:country":"US",
    "sg:address":"75 E 400 S",
    "sg:city":"Price",
    "sg:classifiers":[
        {
            "category":"Social Services",
            "type":"Services"
        }
    ],
    "sg:phone":"+1 435 637 9232",
    "sg:postcode":"84501",
    "sg:province":"UT",
    "sg:tags":[
        "food",
        "banks"
    ],
    "wof:name":"Carbon County Food Bank",
    "wof:placetype":"venue"
},
  "geometry": {"coordinates":[-110.809516,39.593823],"type":"Point"}
}