{
  "type": "Feature",
  "properties": {
    "iso:country":"US",
    "sg:address":"258 E 200 N",
    "sg:city":"Roosevelt",
    "sg:classifiers":[
        {
            "category":"Retail",
            "subcategory":"Auto Repair",
            "type":"Services"
        }
    ],
    "sg:phone":"+1 435 722 5832",
    "sg:postcode":"84066",
    "sg:province":"UT",
    "sg:tags":[
        "general"
    ],
    "wof:name":"Steves Automotive",
    "wof:placetype":"venue"
},
  "geometry": {"coordinates":[-109.988196,40.302062],"type":"Point"}
}