{
  "type": "Feature",
  "properties": {
    "iso:country":"US",
    "sg:address":"2340 E 4500 S",
    "sg:city":"Holladay",
    "sg:classifiers":[
        {
            "category":"Retail",
            "subcategory":"Laundry & Dry Cleaning",
            "type":"Services"
        }
    ],
    "sg:phone":"+1 801 278 4972",
    "sg:postcode":"84117",
    "sg:province":"UT",
    "sg:tags":[
        "cleaners"
    ],
    "wof:name":"Red Hanger Cleaners",
    "wof:placetype":"venue"
},
  "geometry": {"coordinates":[-111.82557,40.674142],"type":"Point"}
}