{
  "type": "Feature",
  "properties": {
    "iso:country":"US",
    "sg:address":"2109 W 12974 S",
    "sg:city":"Riverton",
    "sg:classifiers":[
        {
            "category":"Building & Trades",
            "subcategory":"Construction",
            "type":"Services"
        }
    ],
    "sg:phone":"+1 801 254 4386",
    "sg:postcode":"84065",
    "sg:province":"UT",
    "sg:tags":[
        "house"
    ],
    "wof:name":"Upright Homes Inc",
    "wof:placetype":"venue"
},
  "geometry": {"coordinates":[-111.946326,40.515427],"type":"Point"}
}