{
  "type": "Feature",
  "properties": {
    "iso:country":"US",
    "sg:address":"3905 Harrison Blvd",
    "sg:city":"Ogden",
    "sg:classifiers":[
        {
            "category":"Health Services",
            "subcategory":"Doctor",
            "type":"Services"
        }
    ],
    "sg:phone":"+1 801 399 3404",
    "sg:postcode":"84403",
    "sg:province":"UT",
    "sg:tags":[
        "medical"
    ],
    "wof:name":"Childrens Evening Clinic",
    "wof:placetype":"venue"
},
  "geometry": {"coordinates":[-111.948925,41.190593],"type":"Point"}
}