{
  "type": "Feature",
  "properties": {
    "iso:country":"US",
    "sg:address":"4679 W 11000 N",
    "sg:city":"Highland",
    "sg:classifiers":[
        {
            "category":"Organizations",
            "subcategory":"Religious Organization",
            "type":"Services"
        }
    ],
    "sg:phone":"+1 801 763 2082",
    "sg:postcode":"84003",
    "sg:province":"UT",
    "sg:tags":[
        "church"
    ],
    "wof:name":"Church Of Jesus Christ Of Lds",
    "wof:placetype":"venue"
},
  "geometry": {"coordinates":[-111.770624,40.431959],"type":"Point"}
}