{
  "type": "Feature",
  "properties": {
    "iso:country":"US",
    "sg:address":"4896 S 1900 W",
    "sg:city":"Roy",
    "sg:classifiers":[
        {
            "category":"Health Services",
            "subcategory":"Doctor",
            "type":"Services"
        }
    ],
    "sg:phone":"+1 801 825 3898",
    "sg:postcode":"84067",
    "sg:province":"UT",
    "wof:name":"Peter R Christensen",
    "wof:placetype":"venue"
},
  "geometry": {"coordinates":[-112.025904,41.176164],"type":"Point"}
}