{
  "type": "Feature",
  "properties": {
    "iso:country":"US",
    "sg:address":"785 E 200 S",
    "sg:city":"Lehi",
    "sg:classifiers":[
        {
            "category":"Communications",
            "type":"Services"
        }
    ],
    "sg:phone":"+1 801 768 9564",
    "sg:postcode":"84043",
    "sg:province":"UT",
    "sg:website":"www.focuscompanies.com",
    "wof:name":"Focus Communications",
    "wof:placetype":"venue"
},
  "geometry": {"coordinates":[-111.835751,40.385986],"type":"Point"}
}