{
  "type": "Feature",
  "properties": {
    "iso:country":"US",
    "sg:address":"1095 W 100 South St",
    "sg:city":"Provo",
    "sg:classifiers":[
        {
            "category":"Building & Trades",
            "subcategory":"Construction",
            "type":"Services"
        }
    ],
    "sg:phone":"+1 801 818 0639",
    "sg:postcode":"84601",
    "sg:province":"UT",
    "sg:tags":[
        "contractor"
    ],
    "wof:name":"Ackely Masonry Inc",
    "wof:placetype":"venue"
},
  "geometry": {"coordinates":[-111.676625,40.232331],"type":"Point"}
}