{
  "type": "Feature",
  "properties": {
    "iso:country":"US",
    "sg:address":"6029 S 900 E",
    "sg:city":"Salt Lake City",
    "sg:classifiers":[
        {
            "category":"Shopping",
            "subcategory":"Florist",
            "type":"Retail Goods"
        }
    ],
    "sg:phone":"+1 801 264 9497",
    "sg:postcode":"84121",
    "sg:province":"UT",
    "wof:name":"Flowers On Vine",
    "wof:placetype":"venue"
},
  "geometry": {"coordinates":[-111.8659,40.640414],"type":"Point"}
}