{
  "type": "Feature",
  "properties": {
    "iso:country":"US",
    "sg:address":"1560 N 1900 W",
    "sg:city":"Springville",
    "sg:classifiers":[
        {
            "category":"Professional",
            "type":"Services"
        }
    ],
    "sg:phone":"+1 801 491 0352",
    "sg:postcode":"84663",
    "sg:province":"UT",
    "wof:name":"Ton Services",
    "wof:placetype":"venue"
},
  "geometry": {"coordinates":[-111.642239,40.182128],"type":"Point"}
}