{
  "type": "Feature",
  "properties": {
    "iso:country":"US",
    "sg:address":"23 W 100 S",
    "sg:city":"Payson",
    "sg:classifiers":[
        {
            "category":"Personal",
            "subcategory":"Beauty Salon",
            "type":"Services"
        }
    ],
    "sg:phone":"+1 801 465 0996",
    "sg:postcode":"84651",
    "sg:province":"UT",
    "sg:tags":[
        "shop"
    ],
    "wof:name":"Bliss Beauty Bar",
    "wof:placetype":"venue"
},
  "geometry": {"coordinates":[-111.73247600000001,40.042442],"type":"Point"}
}