{
  "type": "Feature",
  "properties": {
    "iso:country":"US",
    "sg:address":"367 W 1450 N",
    "sg:city":"American Fork",
    "sg:classifiers":[
        {
            "category":"Manufacturing",
            "subcategory":"Printing",
            "type":"Manufacturing & Wholesale Goods"
        }
    ],
    "sg:phone":"+1 801 763 0575",
    "sg:postcode":"84003",
    "sg:province":"UT",
    "sg:tags":[
        "publishing"
    ],
    "wof:name":"Gatehouse Publishing",
    "wof:placetype":"venue"
},
  "geometry": {"coordinates":[-111.80654800000001,40.405568],"type":"Point"}
}