{
  "type": "Feature",
  "properties": {
    "iso:country":"US",
    "sg:address":"1645 Fernleaf St",
    "sg:city":"Salt Lake City",
    "sg:classifiers":[
        {
            "category":"Building & Trades",
            "subcategory":"Landscaping Services",
            "type":"Services"
        }
    ],
    "sg:phone":"+1 801 364 1754",
    "sg:postcode":"84116",
    "sg:province":"UT",
    "wof:name":"Green Side Up Lawncare LLC",
    "wof:placetype":"venue"
},
  "geometry": {"coordinates":[-111.941064,40.803406],"type":"Point"}
}