{
  "type": "Feature",
  "properties": {
    "iso:country":"US",
    "sg:address":"3070 Rasmussen Rd",
    "sg:city":"Park City",
    "sg:classifiers":[
        {
            "category":"Home & Garden",
            "subcategory":"Building Materials",
            "type":"Retail Goods"
        }
    ],
    "sg:phone":"+1 435 615 7580",
    "sg:postcode":"84098",
    "sg:province":"UT",
    "sg:tags":[
        "windows"
    ],
    "wof:name":"Sierra Pacific Windows",
    "wof:placetype":"venue"
},
  "geometry": {"coordinates":[-111.566525,40.749561],"type":"Point"}
}