{
  "type": "Feature",
  "properties": {
    "iso:country":"US",
    "sg:address":"4052 S 685 E",
    "sg:city":"Salt Lake City",
    "sg:classifiers":[
        {
            "category":"Professional",
            "subcategory":"Business Services",
            "type":"Services"
        }
    ],
    "sg:phone":"+1 801 266 6750",
    "sg:postcode":"84107",
    "sg:province":"UT",
    "wof:name":"Douglas Sales and Marketing",
    "wof:placetype":"venue"
},
  "geometry": {"coordinates":[-111.87188500000001,40.683589],"type":"Point"}
}