{
  "type": "Feature",
  "properties": {
    "iso:country":"US",
    "sg:address":"201 W Center St",
    "sg:city":"Provo",
    "sg:classifiers":[
        {
            "category":"Shopping",
            "type":"Retail Goods"
        }
    ],
    "sg:phone":"+1 801 375 1150",
    "sg:postcode":"84601",
    "sg:province":"UT",
    "sg:tags":[
        "picture",
        "frame",
        "art",
        "mfg"
    ],
    "wof:name":"Provo Art & Frame Inc",
    "wof:placetype":"venue"
},
  "geometry": {"coordinates":[-111.66393600000001,40.233728],"type":"Point"}
}