{
  "type": "Feature",
  "properties": {
    "iso:country":"US",
    "sg:address":"9055 S 1300 E",
    "sg:city":"Sandy",
    "sg:classifiers":[
        {
            "category":"Banks & Credit Unions",
            "subcategory":"Investment Brokerage",
            "type":"Services"
        },
        {
            "category":"Professional",
            "subcategory":"Management & Consulting",
            "type":"Services"
        }
    ],
    "sg:phone":"+1 801 562 1011",
    "sg:postcode":"84094",
    "sg:province":"UT",
    "sg:tags":[
        "retirement",
        "planning"
    ],
    "sg:website":"www.heritagefinancialplace.com",
    "wof:name":"Heritage Financial Place",
    "wof:placetype":"venue"
},
  "geometry": {"coordinates":[-111.853121,40.586],"type":"Point"}
}