{
  "type": "Feature",
  "properties": {
    "iso:country":"US",
    "sg:address":"1120 Russel Rd",
    "sg:city":"Lehi",
    "sg:classifiers":[
        {
            "category":"Professional",
            "type":"Services"
        }
    ],
    "sg:phone":"+1 801 789 5087",
    "sg:postcode":"84043",
    "sg:province":"UT",
    "sg:tags":[
        "establishment"
    ],
    "wof:name":"Global Fraud Solutions",
    "wof:placetype":"venue"
},
  "geometry": {"coordinates":[-112.02032699999999,40.306509],"type":"Point"}
}