{
  "type": "Feature",
  "properties": {
    "iso:country":"US",
    "sg:address":"8759 Highland Dr",
    "sg:city":"Sandy",
    "sg:classifiers":[
        {
            "category":"Professional",
            "subcategory":"Accounting & Tax Preparation",
            "type":"Services"
        }
    ],
    "sg:phone":"+1 801 944 5749",
    "sg:postcode":"84093",
    "sg:province":"UT",
    "sg:tags":[
        "return"
    ],
    "wof:name":"Sage Financial Strategies",
    "wof:placetype":"venue"
},
  "geometry": {"coordinates":[-111.83332900000001,40.592111],"type":"Point"}
}