{
  "type": "Feature",
  "properties": {
    "iso:country":"US",
    "sg:address":"33 N 800 W",
    "sg:city":"Provo",
    "sg:classifiers":[
        {
            "category":"Retail",
            "subcategory":"Auto Repair",
            "type":"Services"
        }
    ],
    "sg:phone":"+1 801 373 3253",
    "sg:postcode":"84601",
    "sg:province":"UT",
    "sg:tags":[
        "general"
    ],
    "wof:name":"Mitchell Garage",
    "wof:placetype":"venue"
},
  "geometry": {"coordinates":[-111.672788,40.234701],"type":"Point"}
}