{
  "type": "Feature",
  "properties": {
    "iso:country":"US",
    "sg:address":"3 N State St",
    "sg:city":"Hurricane",
    "sg:classifiers":[
        {
            "category":"Farming",
            "subcategory":"Nursery",
            "type":"Manufacturing & Wholesale Goods"
        }
    ],
    "sg:phone":"+1 435 635 5522",
    "sg:postcode":"84737",
    "sg:province":"UT",
    "sg:tags":[
        "ornamental"
    ],
    "wof:name":"3-H Landscape Products",
    "wof:placetype":"venue"
},
  "geometry": {"coordinates":[-113.284351,37.177654],"type":"Point"}
}