{
  "type": "Feature",
  "properties": {
    "iso:country":"US",
    "sg:address":"810 River Heights Blvd",
    "sg:city":"Logan",
    "sg:classifiers":[
        {
            "category":"Building & Trades",
            "subcategory":"Landscaping Services",
            "type":"Services"
        }
    ],
    "sg:phone":"+1 435 512 2723",
    "sg:postcode":"84321",
    "sg:province":"UT",
    "sg:tags":[
        "lawn",
        "maintenance",
        "grounds"
    ],
    "wof:name":"A Plus Lawn Care",
    "wof:placetype":"venue"
},
  "geometry": {"coordinates":[-111.81509200000001,41.724837],"type":"Point"}
}