{
  "type": "Feature",
  "properties": {
    "iso:country":"US",
    "sg:address":"1325 W 2375 S",
    "sg:city":"Syracuse",
    "sg:classifiers":[
        {
            "category":"Real Estate",
            "subcategory":"Developer",
            "type":"Services"
        }
    ],
    "sg:phone":"+1 801 525 0227",
    "sg:postcode":"84075",
    "sg:province":"UT",
    "wof:name":"Olsen Construction",
    "wof:placetype":"venue"
},
  "geometry": {"coordinates":[-112.051834,41.079081],"type":"Point"}
}