{
  "type": "Feature",
  "properties": {
    "iso:country":"US",
    "sg:address":"485 S Main St",
    "sg:city":"Springville",
    "sg:classifiers":[
        {
            "category":"Professional",
            "subcategory":"Accounting & Tax Preparation",
            "type":"Services"
        }
    ],
    "sg:phone":"+1 801 489 5015",
    "sg:postcode":"84663",
    "sg:province":"UT",
    "sg:tags":[
        "accountant"
    ],
    "wof:name":"J Niel Strong CPA",
    "wof:placetype":"venue"
},
  "geometry": {"coordinates":[-111.61058199999999,40.160889],"type":"Point"}
}