{
  "type": "Feature",
  "properties": {
    "iso:country":"US",
    "sg:address":"307 W 200 S",
    "sg:city":"Salt Lake City",
    "sg:classifiers":[
        {
            "category":"Social Services",
            "type":"Services"
        }
    ],
    "sg:phone":"+1 801 363 3837",
    "sg:postcode":"84101",
    "sg:province":"UT",
    "sg:tags":[
        "support",
        "group"
    ],
    "sg:website":"www.evergreen-intl.org",
    "wof:name":"Evergreen International",
    "wof:placetype":"venue"
},
  "geometry": {"coordinates":[-111.902399,40.764921],"type":"Point"}
}