{
  "type": "Feature",
  "properties": {
    "iso:country":"US",
    "sg:address":"4746 S 900 East St",
    "sg:city":"Salt Lake City",
    "sg:classifiers":[
        {
            "category":"Personal",
            "type":"Services"
        },
        {
            "category":"Professional",
            "subcategory":"Management & Consulting",
            "type":"Services"
        }
    ],
    "sg:phone":"+1 801 547 1333",
    "sg:postcode":"84117",
    "sg:province":"UT",
    "sg:tags":[
        "credit",
        "debt",
        "counseling"
    ],
    "wof:name":"Consumer Credit Advocates",
    "wof:placetype":"venue"
},
  "geometry": {"coordinates":[-111.86508499999999,40.667248],"type":"Point"}
}