{
  "type": "Feature",
  "properties": {
    "iso:country":"US",
    "sg:address":"14760 N 6000 W",
    "sg:city":"Garland",
    "sg:classifiers":[
        {
            "category":"Home & Garden",
            "subcategory":"Building Materials",
            "type":"Retail Goods"
        }
    ],
    "sg:phone":"+1 435 257 6833",
    "sg:postcode":"84312",
    "sg:province":"UT",
    "sg:tags":[
        "mixed",
        "concrete"
    ],
    "wof:name":"Circle C Ready-Mix",
    "wof:placetype":"venue"
},
  "geometry": {"coordinates":[-112.16350199999999,41.774003],"type":"Point"}
}