{
  "type": "Feature",
  "properties": {
    "iso:country":"US",
    "sg:address":"50 W Broadway",
    "sg:city":"Salt Lake City",
    "sg:classifiers":[
        {
            "category":"Professional",
            "subcategory":"Lawyer & Legal Services",
            "type":"Services"
        }
    ],
    "sg:phone":"+1 801 531 7090",
    "sg:postcode":"84101",
    "sg:province":"UT",
    "sg:tags":[
        "attorney"
    ],
    "sg:website":"www.klmlaw.com",
    "wof:name":"Kruse Landa Maycock & Ricks",
    "wof:placetype":"venue"
},
  "geometry": {"coordinates":[-111.89273,40.762898],"type":"Point"}
}