{
  "type": "Feature",
  "properties": {
    "iso:country":"US",
    "sg:address":"1650 Heather Dr",
    "sg:city":"Layton",
    "sg:classifiers":[
        {
            "category":"Wholesale",
            "subcategory":"Groceries",
            "type":"Manufacturing & Wholesale Goods"
        }
    ],
    "sg:phone":"+1 801 546 9428",
    "sg:postcode":"84040",
    "sg:province":"UT",
    "wof:name":"Grasshopper Creek Gourmet",
    "wof:placetype":"venue"
},
  "geometry": {"coordinates":[-111.93672100000001,41.081901],"type":"Point"}
}