{
  "type": "Feature",
  "properties": {
    "iso:country":"US",
    "sg:address":"1105 S 1680 W",
    "sg:city":"Orem",
    "sg:classifiers":[
        {
            "category":"Communications",
            "subcategory":"Film & Video Production",
            "type":"Services"
        }
    ],
    "sg:phone":"+1 801 226 0608",
    "sg:postcode":"84058",
    "sg:province":"UT",
    "sg:tags":[
        "taping"
    ],
    "sg:website":"www.jtvproductions.com",
    "wof:name":"JTV Productions",
    "wof:placetype":"venue"
},
  "geometry": {"coordinates":[-111.735224,40.275188],"type":"Point"}
}