{
  "type": "Feature",
  "properties": {
    "iso:country":"US",
    "sg:address":"159 W Center St",
    "sg:city":"Kanab",
    "sg:classifiers":[
        {
            "category":"Banks & Credit Unions",
            "subcategory":"Bank",
            "type":"Services"
        }
    ],
    "sg:phone":"+1 435 644 8989",
    "sg:postcode":"84741",
    "sg:province":"UT",
    "sg:tags":[
        "loan",
        "real estate"
    ],
    "wof:name":"Red Rock Mortgage & Financial",
    "wof:placetype":"venue"
},
  "geometry": {"coordinates":[-112.53267200000001,37.048032],"type":"Point"}
}