{
  "type": "Feature",
  "properties": {
    "iso:country":"US",
    "sg:address":"605 W 6300 S",
    "sg:city":"Murray",
    "sg:classifiers":[
        {
            "category":"Building & Trades",
            "subcategory":"Construction",
            "type":"Services"
        }
    ],
    "sg:phone":"+1 801 699 8530",
    "sg:postcode":"84123",
    "sg:province":"UT",
    "sg:tags":[
        "concrete",
        "cutting",
        "breaking",
        "sawing"
    ],
    "wof:name":"Asphalt Concrete Etc Cutting",
    "wof:placetype":"venue"
},
  "geometry": {"coordinates":[-111.909251,40.633823],"type":"Point"}
}