{
  "type": "Feature",
  "properties": {
    "iso:country":"US",
    "sg:address":"646 S 150 E",
    "sg:city":"Kaysville",
    "sg:classifiers":[
        {
            "category":"Manufacturing",
            "subcategory":"Jewelry",
            "type":"Manufacturing & Wholesale Goods"
        }
    ],
    "sg:phone":"+1 801 544 1027",
    "sg:postcode":"84037",
    "sg:province":"UT",
    "sg:tags":[
        "costume",
        "mfg"
    ],
    "wof:name":"Isnt That Cute",
    "wof:placetype":"venue"
},
  "geometry": {"coordinates":[-111.935106,41.023661],"type":"Point"}
}