{
  "type": "Feature",
  "properties": {
    "iso:country":"US",
    "sg:address":"105 S Main St",
    "sg:city":"Richfield",
    "sg:classifiers":[
        {
            "category":"Autos & Motor Vehicles",
            "subcategory":"Fuel & Gas Station",
            "type":"Retail Goods"
        }
    ],
    "sg:phone":"+1 435 896 6270",
    "sg:postcode":"84701",
    "sg:province":"UT",
    "sg:tags":[
        "oil"
    ],
    "wof:name":"Nowers' Chevron",
    "wof:placetype":"venue"
},
  "geometry": {"coordinates":[-112.08462400000001,38.766627],"type":"Point"}
}