{
  "type": "Feature",
  "properties": {
    "iso:country":"US",
    "sg:address":"835 S University Ave",
    "sg:city":"Provo",
    "sg:classifiers":[
        {
            "category":"Retail",
            "subcategory":"Auto Repair",
            "type":"Services"
        }
    ],
    "sg:phone":"+1 801 374 1191",
    "sg:postcode":"84601",
    "sg:province":"UT",
    "sg:tags":[
        "muffler",
        "exhaust",
        "system"
    ],
    "wof:name":"Master Muffler & Brake",
    "wof:placetype":"venue"
},
  "geometry": {"coordinates":[-111.65862199999999,40.222818],"type":"Point"}
}