{
  "type": "Feature",
  "properties": {
    "iso:country":"US",
    "sg:address":"711 N Main St",
    "sg:city":"Layton",
    "sg:classifiers":[
        {
            "category":"Banks & Credit Unions",
            "subcategory":"Bank",
            "type":"Services"
        }
    ],
    "sg:phone":"+1 801 544 9566",
    "sg:postcode":"84041",
    "sg:province":"UT",
    "sg:tags":[
        "personal",
        "institution"
    ],
    "wof:name":"Wells Fargo",
    "wof:placetype":"venue"
},
  "geometry": {"coordinates":[-111.97651,41.070219],"type":"Point"}
}