{
  "type": "Feature",
  "properties": {
    "iso:country":"US",
    "sg:address":"1315 E 550 N",
    "sg:city":"Orem",
    "sg:classifiers":[
        {
            "category":"Organizations",
            "subcategory":"Labor Organization",
            "type":"Services"
        }
    ],
    "sg:phone":"+1 801 225 8937",
    "sg:postcode":"84097",
    "sg:province":"UT",
    "wof:name":"G & C Zamboni Investments Lc",
    "wof:placetype":"venue"
},
  "geometry": {"coordinates":[-111.66474599999999,40.307617],"type":"Point"}
}