{
  "type": "Feature",
  "properties": {
    "iso:country":"US",
    "sg:address":"3885 Browns Canyon Rd",
    "sg:city":"Peoa",
    "sg:classifiers":[
        {
            "category":"Building & Trades",
            "subcategory":"Construction",
            "type":"Services"
        }
    ],
    "sg:phone":"+1 435 783 5925",
    "sg:postcode":"84061",
    "sg:province":"UT",
    "sg:tags":[
        "contractor"
    ],
    "wof:name":"Mountain Desert Builders Inc",
    "wof:placetype":"venue"
},
  "geometry": {"coordinates":[-111.35798,40.7373],"type":"Point"}
}