{
  "type": "Feature",
  "properties": {
    "iso:country":"US",
    "sg:address":"6300 S 300 E",
    "sg:city":"Murray",
    "sg:classifiers":[
        {
            "category":"Organizations",
            "subcategory":"Religious Organization",
            "type":"Services"
        }
    ],
    "sg:phone":"+1 801 264 4037",
    "sg:postcode":"84107",
    "sg:province":"UT",
    "sg:tags":[
        "church"
    ],
    "wof:name":"Church Of Jesus Christ Of Lds",
    "wof:placetype":"venue"
},
  "geometry": {"coordinates":[-111.89838899999999,40.634126],"type":"Point"}
}