{
  "type": "Feature",
  "properties": {
    "iso:country":"US",
    "sg:address":"5940 W Copper City Cir",
    "sg:city":"Kearns",
    "sg:classifiers":[
        {
            "category":"Building & Trades",
            "subcategory":"Plumbing",
            "type":"Services"
        }
    ],
    "sg:phone":"+1 801 968 2255",
    "sg:postcode":"84118",
    "sg:province":"UT",
    "sg:tags":[
        "conditioning",
        "air",
        "system",
        "contractor"
    ],
    "wof:name":"Tod R Packer Heating Air Cond",
    "wof:placetype":"venue"
},
  "geometry": {"coordinates":[-112.032641,40.650477],"type":"Point"}
}