{
  "type": "Feature",
  "properties": {
    "iso:country":"US",
    "sg:address":"6328 S State St",
    "sg:city":"Murray",
    "sg:classifiers":[
        {
            "category":"Home & Garden",
            "subcategory":"Furniture",
            "type":"Retail Goods"
        }
    ],
    "sg:phone":"+1 801 293 3476",
    "sg:postcode":"84107",
    "sg:province":"UT",
    "sg:tags":[
        "mattress"
    ],
    "wof:name":"Mattress Firm",
    "wof:placetype":"venue"
},
  "geometry": {"coordinates":[-111.889399,40.634995],"type":"Point"}
}