{
  "type": "Feature",
  "properties": {
    "iso:country":"US",
    "sg:address":"230 S 1000 E",
    "sg:city":"Salt Lake City",
    "sg:classifiers":[
        {
            "category":"Organizations",
            "subcategory":"Membership Organization",
            "type":"Services"
        }
    ],
    "sg:phone":"+1 801 364 6764",
    "sg:postcode":"84102",
    "sg:province":"UT",
    "sg:website":"www.polygamy.org",
    "wof:name":"Tapestry Of Polygamy",
    "wof:placetype":"venue"
},
  "geometry": {"coordinates":[-111.862532,40.763499],"type":"Point"}
}