{
  "type": "Feature",
  "properties": {
    "iso:country":"US",
    "sg:address":"1231 E 520 S",
    "sg:city":"Provo",
    "sg:classifiers":[
        {
            "category":"Social Services",
            "subcategory":"Child Care",
            "type":"Services"
        }
    ],
    "sg:phone":"+1 801 377 4570",
    "sg:postcode":"84606",
    "sg:province":"UT",
    "sg:tags":[
        "day"
    ],
    "wof:name":"Grandmas We Care",
    "wof:placetype":"venue"
},
  "geometry": {"coordinates":[-111.637173,40.226708],"type":"Point"}
}