{
  "type": "Feature",
  "properties": {
    "iso:country":"US",
    "sg:address":"223 S 700 E",
    "sg:city":"Salt Lake City",
    "sg:classifiers":[
        {
            "category":"Health Services",
            "subcategory":"Chiropractor",
            "type":"Services"
        },
        {
            "category":"Health Services",
            "subcategory":"Health Practitioner",
            "type":"Services"
        }
    ],
    "sg:phone":"+1 801 359 3617",
    "sg:postcode":"84102",
    "sg:province":"UT",
    "wof:name":"Great Basin Chiropractic",
    "wof:placetype":"venue"
},
  "geometry": {"coordinates":[-111.870985,40.764246],"type":"Point"}
}