{
  "type": "Feature",
  "properties": {
    "iso:country":"US",
    "sg:address":"58 S 450 W",
    "sg:city":"Springville",
    "sg:classifiers":[
        {
            "category":"Personal",
            "subcategory":"Beauty Salon",
            "type":"Services"
        }
    ],
    "sg:phone":"+1 801 491 8735",
    "sg:postcode":"84663",
    "sg:province":"UT",
    "sg:tags":[
        "shop"
    ],
    "wof:name":"Hairquest Salon",
    "wof:placetype":"venue"
},
  "geometry": {"coordinates":[-111.619001,40.166709],"type":"Point"}
}