{
  "type": "Feature",
  "properties": {
    "iso:country":"US",
    "sg:address":"9194 S 110 E",
    "sg:city":"Sandy",
    "sg:classifiers":[
        {
            "category":"Social Services",
            "subcategory":"Child Care",
            "type":"Services"
        }
    ],
    "sg:phone":"+1 801 561 8568",
    "sg:postcode":"84070",
    "sg:province":"UT",
    "sg:tags":[
        "day"
    ],
    "wof:name":"Kellys Daycare",
    "wof:placetype":"venue"
},
  "geometry": {"coordinates":[-111.886989,40.584666],"type":"Point"}
}