{
  "type": "Feature",
  "properties": {
    "iso:country":"US",
    "sg:address":"57 N 100 E",
    "sg:city":"Roosevelt",
    "sg:classifiers":[
        {
            "category":"Professional",
            "subcategory":"Engineering",
            "type":"Services"
        }
    ],
    "sg:phone":"+1 435 722 0968",
    "sg:postcode":"84066",
    "sg:province":"UT",
    "sg:tags":[
        "engineer"
    ],
    "wof:name":"Horrocks Engineers",
    "wof:placetype":"venue"
},
  "geometry": {"coordinates":[-109.990346,40.300841],"type":"Point"}
}