{
  "type": "Feature",
  "properties": {
    "iso:country":"US",
    "sg:address":"30 W 700 N",
    "sg:city":"Logan",
    "sg:classifiers":[
        {
            "category":"Manufacturing",
            "subcategory":"Signs",
            "type":"Manufacturing & Wholesale Goods"
        }
    ],
    "sg:phone":"+1 435 755 5812",
    "sg:postcode":"84321",
    "sg:province":"UT",
    "wof:name":"Signthis",
    "wof:placetype":"venue"
},
  "geometry": {"coordinates":[-111.835257,41.744517],"type":"Point"}
}