{
  "type": "Feature",
  "properties": {
    "iso:country":"US",
    "sg:address":"3226 W 8350 S",
    "sg:city":"West Jordan",
    "sg:classifiers":[
        {
            "category":"Education",
            "subcategory":"Dance Studio",
            "type":"Public Place"
        }
    ],
    "sg:phone":"+1 801 565 9499",
    "sg:postcode":"84088",
    "sg:province":"UT",
    "sg:tags":[
        "instruction",
        "dancing"
    ],
    "wof:name":"C & C Dance Factory",
    "wof:placetype":"venue"
},
  "geometry": {"coordinates":[-111.968862,40.600125],"type":"Point"}
}