{
  "type": "Feature",
  "properties": {
    "iso:country":"US",
    "sg:address":"102 W South Temple",
    "sg:city":"Salt Lake City",
    "sg:classifiers":[
        {
            "category":"Restaurant",
            "type":"Food & Drink"
        }
    ],
    "sg:menulink":"http://www.allmenus.com/ut/salt-lake-city/35257-jbs-family/menu/",
    "sg:phone":"+1 801 328 8344",
    "sg:postcode":"84101",
    "sg:province":"UT",
    "sg:tags":[
        "american"
    ],
    "wof:name":"JB's Family",
    "wof:placetype":"venue"
},
  "geometry": {"coordinates":[-111.894218,40.769406],"type":"Point"}
}