{
  "type": "Feature",
  "properties": {
    "iso:country":"US",
    "sg:address":"175 S 1300 W",
    "sg:city":"Pleasant Grove",
    "sg:classifiers":[
        {
            "category":"Building & Trades",
            "subcategory":"Plumbing",
            "type":"Services"
        }
    ],
    "sg:phone":"+1 801 785 6367",
    "sg:postcode":"84062",
    "sg:province":"UT",
    "sg:tags":[
        "plumbing",
        "contractor"
    ],
    "wof:name":"Kelley Plumbing Inc",
    "wof:placetype":"venue"
},
  "geometry": {"coordinates":[-111.759827,40.359229],"type":"Point"}
}