{
  "type": "Feature",
  "properties": {
    "iso:country":"US",
    "sg:address":"435 S Main St",
    "sg:city":"Smithfield",
    "sg:classifiers":[
        {
            "category":"Autos & Motor Vehicles",
            "subcategory":"Fuel & Gas Station",
            "type":"Retail Goods"
        }
    ],
    "sg:phone":"+1 435 563 5128",
    "sg:postcode":"84335",
    "sg:province":"UT",
    "sg:tags":[
        "station"
    ],
    "wof:name":"Flying J Travel Plaza",
    "wof:placetype":"venue"
},
  "geometry": {"coordinates":[-111.83299700000001,41.827473],"type":"Point"}
}