{
  "type": "Feature",
  "properties": {
    "iso:country":"US",
    "sg:address":"853 E Arrowhead Ln",
    "sg:city":"Murray",
    "sg:classifiers":[
        {
            "category":"Home & Garden",
            "subcategory":"Garden Supply",
            "type":"Retail Goods"
        }
    ],
    "sg:phone":"+1 801 266 7777",
    "sg:postcode":"84107",
    "sg:province":"UT",
    "sg:tags":[
        "lawn",
        "mower"
    ],
    "wof:name":"Al's/The Chain Saw King",
    "wof:placetype":"venue"
},
  "geometry": {"coordinates":[-111.867508,40.659499],"type":"Point"}
}