{
  "type": "Feature",
  "properties": {
    "iso:country":"US",
    "sg:address":"140 W University Pkwy",
    "sg:city":"Orem",
    "sg:classifiers":[
        {
            "category":"Home & Garden",
            "subcategory":"Building Materials",
            "type":"Retail Goods"
        }
    ],
    "sg:phone":"+1 801 229 1485",
    "sg:postcode":"84058",
    "sg:province":"UT",
    "sg:tags":[
        "center"
    ],
    "sg:website":"www.lowes.com",
    "wof:name":"Lowe's",
    "wof:placetype":"venue"
},
  "geometry": {"coordinates":[-111.702129,40.273654],"type":"Point"}
}