{
  "type": "Feature",
  "properties": {
    "iso:country":"US",
    "sg:address":"344 S 500 W Ste 3",
    "sg:city":"Bountiful",
    "sg:classifiers":[
        {
            "category":"Shopping",
            "subcategory":"Mobile Phones",
            "type":"Retail Goods"
        }
    ],
    "sg:phone":"+1 801 298 4290",
    "sg:postcode":"84010",
    "sg:province":"UT",
    "wof:name":"Freedom Wireless",
    "wof:placetype":"venue"
},
  "geometry": {"coordinates":[-111.892372,40.885763],"type":"Point"}
}