{
  "type": "Feature",
  "properties": {
    "iso:country":"US",
    "sg:address":"580 W 500 N",
    "sg:city":"Salt Lake City",
    "sg:classifiers":[
        {
            "category":"Wholesale",
            "subcategory":"Groceries",
            "type":"Manufacturing & Wholesale Goods"
        }
    ],
    "sg:phone":"+1 801 328 0188",
    "sg:postcode":"84116",
    "sg:province":"UT",
    "wof:name":"Quetzal Import",
    "wof:placetype":"venue"
},
  "geometry": {"coordinates":[-111.907898,40.780286],"type":"Point"}
}