{
  "type": "Feature",
  "properties": {
    "iso:country":"US",
    "sg:address":"1810 Fortune Rd",
    "sg:city":"Salt Lake City",
    "sg:classifiers":[
        {
            "category":"Building & Trades",
            "subcategory":"Landscaping Services",
            "type":"Services"
        }
    ],
    "sg:phone":"+1 801 977 0778",
    "sg:postcode":"84104",
    "sg:province":"UT",
    "sg:tags":[
        "lawn",
        "maintenance",
        "grounds"
    ],
    "wof:name":"Tru Green Chem Lawn",
    "wof:placetype":"venue"
},
  "geometry": {"coordinates":[-111.939151,40.738682],"type":"Point"}
}