{
  "type": "Feature",
  "properties": {
    "iso:country":"US",
    "sg:address":"480 W 900 N",
    "sg:city":"North Salt Lake",
    "sg:classifiers":[
        {
            "category":"Freight",
            "type":"Transportation"
        }
    ],
    "sg:phone":"+1 801 298 9337",
    "sg:postcode":"84054",
    "sg:province":"UT",
    "wof:name":"Basin Western Inc",
    "wof:placetype":"venue"
},
  "geometry": {"coordinates":[-111.92171999999999,40.858463],"type":"Point"}
}