{
  "type": "Feature",
  "properties": {
    "iso:country":"US",
    "sg:address":"390 S Main St",
    "sg:city":"Nephi",
    "sg:classifiers":[
        {
            "category":"Restaurant",
            "type":"Food & Drink"
        }
    ],
    "sg:menulink":"http://www.allmenus.com/ut/nephi/35732-mi-racherito/menu/",
    "sg:phone":"+1 435 623 4391",
    "sg:postcode":"84648",
    "sg:province":"UT",
    "sg:tags":[
        "mexican"
    ],
    "wof:name":"Mi Racherito",
    "wof:placetype":"venue"
},
  "geometry": {"coordinates":[-111.836108,39.702951],"type":"Point"}
}