{
  "type": "Feature",
  "properties": {
    "iso:country":"US",
    "sg:address":"1202 W 150 S",
    "sg:city":"Clearfield",
    "sg:classifiers":[
        {
            "category":"Building & Trades",
            "subcategory":"Plumbing",
            "type":"Services"
        }
    ],
    "sg:phone":"+1 801 779 2301",
    "sg:postcode":"84015",
    "sg:province":"UT",
    "sg:tags":[
        "plumbing",
        "contractor"
    ],
    "wof:name":"Intermountain Mechanical Svc",
    "wof:placetype":"venue"
},
  "geometry": {"coordinates":[-112.048196,41.111829],"type":"Point"}
}