{
  "type": "Feature",
  "properties": {
    "iso:country":"US",
    "sg:address":"39 Wanderwood Way",
    "sg:city":"Sandy",
    "sg:classifiers":[
        {
            "category":"Banks & Credit Unions",
            "subcategory":"Financial Services",
            "type":"Services"
        }
    ],
    "sg:phone":"+1 801 619 4855",
    "sg:postcode":"84092",
    "sg:province":"UT",
    "sg:tags":[
        "investor"
    ],
    "wof:name":"Mleynek Investments Ltd",
    "wof:placetype":"venue"
},
  "geometry": {"coordinates":[-111.818456,40.551432],"type":"Point"}
}