{
  "type": "Feature",
  "properties": {
    "iso:country":"US",
    "sg:address":"4575 Silver Springs Dr",
    "sg:city":"Park City",
    "sg:classifiers":[
        {
            "category":"Shopping",
            "subcategory":"Gifts & Souvenirs",
            "type":"Retail Goods"
        }
    ],
    "sg:phone":"+1 435 649 3877",
    "sg:postcode":"84098",
    "sg:province":"UT",
    "wof:name":"Alaskan",
    "wof:placetype":"venue"
},
  "geometry": {"coordinates":[-111.542998,40.697093],"type":"Point"}
}