{
  "type": "Feature",
  "properties": {
    "iso:country":"US",
    "sg:address":"19 W 4750 N",
    "sg:city":"Provo",
    "sg:classifiers":[
        {
            "category":"Arts & Performance",
            "subcategory":"Theater",
            "type":"Entertainment"
        }
    ],
    "sg:phone":"+1 801 765 9052",
    "sg:postcode":"84604",
    "sg:province":"UT",
    "wof:name":"ROC Entertainment Inc",
    "wof:placetype":"venue"
},
  "geometry": {"coordinates":[-111.657498,40.296325],"type":"Point"}
}