{
  "type": "Feature",
  "properties": {
    "iso:country":"US",
    "sg:address":"25 N 840 E",
    "sg:city":"Pleasant Grove",
    "sg:classifiers":[
        {
            "category":"Wholesale",
            "subcategory":"Office Equipment",
            "type":"Manufacturing & Wholesale Goods"
        }
    ],
    "sg:phone":"+1 801 796 9423",
    "sg:postcode":"84062",
    "sg:province":"UT",
    "wof:name":"Professional Office Solutions",
    "wof:placetype":"venue"
},
  "geometry": {"coordinates":[-111.722156,40.364768],"type":"Point"}
}