{
  "type": "Feature",
  "properties": {
    "iso:country":"US",
    "sg:address":"3975 Highland Dr",
    "sg:city":"Holladay",
    "sg:classifiers":[
        {
            "category":"Personal",
            "subcategory":"Beauty Salon",
            "type":"Services"
        }
    ],
    "sg:phone":"+1 801 272 8801",
    "sg:postcode":"84124",
    "sg:province":"UT",
    "sg:tags":[
        "shop"
    ],
    "wof:name":"Profiles Hair Studio",
    "wof:placetype":"venue"
},
  "geometry": {"coordinates":[-111.844336,40.68515],"type":"Point"}
}