{
  "type": "Feature",
  "properties": {
    "iso:country":"US",
    "sg:address":"4915 Silver Springs Rd",
    "sg:city":"Park City",
    "sg:classifiers":[
        {
            "category":"Building & Trades",
            "subcategory":"Landscaping Services",
            "type":"Services"
        }
    ],
    "sg:phone":"+1 435 647 6776",
    "sg:postcode":"84098",
    "sg:province":"UT",
    "sg:tags":[
        "tree"
    ],
    "wof:name":"Greenleaf Spraying & Tree Care",
    "wof:placetype":"venue"
},
  "geometry": {"coordinates":[-111.539587,40.703545],"type":"Point"}
}