{
  "type": "Feature",
  "properties": {
    "iso:country":"US",
    "sg:address":"1042 Fort Union Blvd",
    "sg:city":"Midvale",
    "sg:classifiers":[
        {
            "category":"Professional",
            "type":"Services"
        }
    ],
    "sg:phone":"+1 801 572 3461",
    "sg:postcode":"84047",
    "sg:province":"UT",
    "sg:tags":[
        "establishment"
    ],
    "wof:name":"Lippincott Co",
    "wof:placetype":"venue"
},
  "geometry": {"coordinates":[-111.863208,40.62267],"type":"Point"}
}