{
  "type": "Feature",
  "properties": {
    "iso:country":"US",
    "sg:address":"1156 N 150 W",
    "sg:city":"Orem",
    "sg:classifiers":[
        {
            "category":"Professional",
            "subcategory":"Business Services",
            "type":"Services"
        }
    ],
    "sg:phone":"+1 801 226 1035",
    "sg:postcode":"84057",
    "sg:province":"UT",
    "wof:name":"Greenerprises Inc",
    "wof:placetype":"venue"
},
  "geometry": {"coordinates":[-111.69919400000001,40.317724],"type":"Point"}
}