{
  "type": "Feature",
  "properties": {
    "iso:country":"US",
    "sg:address":"345 E 3300 S",
    "sg:city":"Salt Lake City",
    "sg:classifiers":[
        {
            "category":"Insurance",
            "subcategory":"Insurance Agent",
            "type":"Services"
        }
    ],
    "sg:phone":"+1 801 463 7140",
    "sg:postcode":"84115",
    "sg:province":"UT",
    "wof:name":"Hansen Insurance",
    "wof:placetype":"venue"
},
  "geometry": {"coordinates":[-111.880934,40.699943],"type":"Point"}
}