{
  "type": "Feature",
  "properties": {
    "iso:country":"US",
    "sg:address":"3207 S 75 E",
    "sg:city":"Bountiful",
    "sg:classifiers":[
        {
            "category":"Professional",
            "subcategory":"Engineering",
            "type":"Services"
        }
    ],
    "sg:phone":"+1 801 292 2079",
    "sg:postcode":"84010",
    "sg:province":"UT",
    "wof:name":"Bestech LLC",
    "wof:placetype":"venue"
},
  "geometry": {"coordinates":[-111.878035,40.854092],"type":"Point"}
}