{
  "type": "Feature",
  "properties": {
    "iso:country":"US",
    "sg:address":"92 W 500 S",
    "sg:city":"Provo",
    "sg:classifiers":[
        {
            "category":"Wholesale",
            "subcategory":"Machinery & Supplies",
            "type":"Manufacturing & Wholesale Goods"
        }
    ],
    "sg:phone":"+1 801 812 1866",
    "sg:postcode":"84601",
    "sg:province":"UT",
    "sg:tags":[
        "mining"
    ],
    "wof:name":"C H T Industrial Supply Co",
    "wof:placetype":"venue"
},
  "geometry": {"coordinates":[-111.659221,40.227116],"type":"Point"}
}