{
  "type": "Feature",
  "properties": {
    "iso:country":"US",
    "sg:address":"1605 Allegheny Dr",
    "sg:city":"Murray",
    "sg:classifiers":[
        {
            "category":"Building & Trades",
            "subcategory":"Landscaping Services",
            "type":"Services"
        }
    ],
    "sg:phone":"+1 801 270 8797",
    "sg:postcode":"84123",
    "sg:province":"UT",
    "sg:tags":[
        "tree"
    ],
    "wof:name":"Art Of Pruning Plant Care Svc",
    "wof:placetype":"venue"
},
  "geometry": {"coordinates":[-111.93719299999999,40.634549],"type":"Point"}
}