{
  "type": "Feature",
  "properties": {
    "iso:country":"US",
    "sg:address":"1074 W Hill Field Rd",
    "sg:city":"Layton",
    "sg:classifiers":[
        {
            "category":"Restaurant",
            "type":"Food & Drink"
        }
    ],
    "sg:phone":"+1 801 543 3322",
    "sg:postcode":"84041",
    "sg:province":"UT",
    "sg:tags":[
        "eating"
    ],
    "wof:name":"Hungry Bear Pizza",
    "wof:placetype":"venue"
},
  "geometry": {"coordinates":[-111.985596,41.103659],"type":"Point"}
}