{
  "type": "Feature",
  "properties": {
    "iso:country":"US",
    "sg:address":"1284 Empire Ave",
    "sg:city":"Park City",
    "sg:classifiers":[
        {
            "category":"Restaurant",
            "type":"Food & Drink"
        }
    ],
    "sg:menulink":"http://www.allmenus.com/ut/park-city/15242-baja-cantina/menu/",
    "sg:phone":"+1 435 649 2252",
    "sg:postcode":"84060",
    "sg:province":"UT",
    "sg:tags":[
        "mexican"
    ],
    "wof:name":"Baja Cantina",
    "wof:placetype":"venue"
},
  "geometry": {"coordinates":[-111.504857,40.651183],"type":"Point"}
}