{
  "type": "Feature",
  "properties": {
    "iso:country":"US",
    "sg:address":"291 W 400 N",
    "sg:city":"Lindon",
    "sg:classifiers":[
        {
            "category":"Restaurant",
            "type":"Food & Drink"
        }
    ],
    "sg:menulink":"http://www.allmenus.com/ut/american-fork-pleasant-grove/35377-the-pizza-factory/menu/",
    "sg:phone":"+1 801 785 4464",
    "sg:postcode":"84042",
    "sg:province":"UT",
    "sg:tags":[
        "italian"
    ],
    "wof:name":"The Pizza Factory",
    "wof:placetype":"venue"
},
  "geometry": {"coordinates":[-111.72124100000001,40.344769],"type":"Point"}
}