{
  "type": "Feature",
  "properties": {
    "iso:country":"US",
    "sg:address":"3355 S Bluff Dr",
    "sg:city":"Syracuse",
    "sg:classifiers":[
        {
            "category":"Manufacturing",
            "subcategory":"Paper Products",
            "type":"Manufacturing & Wholesale Goods"
        }
    ],
    "sg:phone":"+1 801 776 3023",
    "sg:postcode":"84075",
    "sg:province":"UT",
    "sg:tags":[
        "bag",
        "mfg"
    ],
    "wof:name":"Kathy S Foods & Filters",
    "wof:placetype":"venue"
},
  "geometry": {"coordinates":[-112.050309,41.06648],"type":"Point"}
}