{
  "type": "Feature",
  "properties": {
    "iso:country":"US",
    "sg:address":"879 Gladiola St",
    "sg:city":"Salt Lake City",
    "sg:classifiers":[
        {
            "category":"Autos & Motor Vehicles",
            "subcategory":"Automobile Sales",
            "type":"Retail Goods"
        }
    ],
    "sg:phone":"+1 801 973 9402",
    "sg:postcode":"84104",
    "sg:province":"UT",
    "sg:tags":[
        "car",
        "dealer"
    ],
    "wof:name":"Kaiser Saw Mill",
    "wof:placetype":"venue"
},
  "geometry": {"coordinates":[-111.97202900000001,40.750502],"type":"Point"}
}