{
  "type": "Feature",
  "properties": {
    "iso:country":"US",
    "sg:address":"1291 W Center St",
    "sg:city":"Lindon",
    "sg:classifiers":[
        {
            "category":"Freight",
            "type":"Transportation"
        }
    ],
    "sg:phone":"+1 801 785 9966",
    "sg:postcode":"84042",
    "sg:province":"UT",
    "sg:tags":[
        "dry",
        "facility",
        "trucking",
        "bulk",
        "motor",
        "fixed"
    ],
    "wof:name":"Harrison Transportation Co",
    "wof:placetype":"venue"
},
  "geometry": {"coordinates":[-111.74620400000001,40.337245],"type":"Point"}
}