{
  "type": "Feature",
  "properties": {
    "iso:country":"US",
    "sg:address":"4777 S 4720 W",
    "sg:city":"Salt Lake City",
    "sg:classifiers":[
        {
            "category":"Retail",
            "subcategory":"Repair Shop",
            "type":"Services"
        }
    ],
    "sg:phone":"+1 801 969 2410",
    "sg:postcode":"84118",
    "sg:province":"UT",
    "wof:name":"Pjs Service & Repair Inc",
    "wof:placetype":"venue"
},
  "geometry": {"coordinates":[-112.003455,40.665078],"type":"Point"}
}