{
  "type": "Feature",
  "properties": {
    "iso:country":"US",
    "sg:address":"540 Topez Blvd",
    "sg:city":"Delta",
    "sg:classifiers":[
        {
            "category":"Restaurant",
            "type":"Food & Drink"
        }
    ],
    "sg:phone":"+1 435 864 4245",
    "sg:postcode":"84624",
    "sg:province":"UT",
    "wof:name":"Mi Rancherito Mexican Rstrnt",
    "wof:placetype":"venue"
},
  "geometry": {"coordinates":[-112.564774,39.355069],"type":"Point"}
}