{
  "type": "Feature",
  "properties": {
    "iso:country":"US",
    "sg:address":"272 W 500 N",
    "sg:city":"American Fork",
    "sg:classifiers":[
        {
            "category":"Social Services",
            "subcategory":"Adult Care",
            "type":"Services"
        }
    ],
    "sg:phone":"+1 801 763 9377",
    "sg:postcode":"84003",
    "sg:province":"UT",
    "sg:tags":[
        "residential"
    ],
    "wof:name":"Beehive Homes Of American Fork",
    "wof:placetype":"venue"
},
  "geometry": {"coordinates":[-111.806031,40.387182],"type":"Point"}
}