{
  "type": "Feature",
  "properties": {
    "iso:country":"US",
    "sg:address":"272 S 1550 E",
    "sg:city":"Bountiful",
    "sg:classifiers":[
        {
            "category":"Professional",
            "type":"Services"
        }
    ],
    "sg:phone":"+1 801 294 0739",
    "sg:postcode":"84010",
    "sg:province":"UT",
    "sg:tags":[
        "establishment"
    ],
    "wof:name":"RMH",
    "wof:placetype":"venue"
},
  "geometry": {"coordinates":[-111.848184,40.886259],"type":"Point"}
}