{
  "type": "Feature",
  "properties": {
    "iso:country":"US",
    "sg:address":"2825 E Cottonwood Parkway, Suite 500",
    "sg:city":"Salt Lake City",
    "sg:classifiers":[
        {
            "category":"Professional",
            "subcategory":"Computer Services",
            "type":"Services"
        }
    ],
    "sg:phone":"+1 801 657 5402",
    "sg:postcode":"84124 ",
    "sg:province":"UT",
    "sg:tags":[
        "web-apps",
        "web-applications",
        "web-application",
        "web-app",
        "web-app-content",
        "web-application-content",
        "web-app-capabilities",
        "web-application-capabilities",
        "web-page",
        "web-site",
        "microsoft-word",
        "pdf",
        "paper-scanning",
        "templates",
        "reports",
        "reporting",
        "forms",
        "pdf-forms",
        "m"
    ],
    "sg:website":"http://www.WebTotality.com",
    "wof:name":"WebTotality",
    "wof:placetype":"venue"
},
  "geometry": {"coordinates":[-111.82730599999999,40.68342],"type":"Point"}
}