{
  "type": "Feature",
  "properties": {
    "iso:country":"US",
    "sg:address":"60 S Main St",
    "sg:city":"Tooele",
    "sg:classifiers":[
        {
            "category":"Professional",
            "subcategory":"Accounting & Tax Preparation",
            "type":"Services"
        }
    ],
    "sg:phone":"+1 435 882 8297",
    "sg:postcode":"84074",
    "sg:province":"UT",
    "sg:tags":[
        "return",
        "filing"
    ],
    "wof:name":"Tax Specialist",
    "wof:placetype":"venue"
},
  "geometry": {"coordinates":[-112.29867299999999,40.529358],"type":"Point"}
}