{
  "type": "Feature",
  "properties": {
    "iso:country":"US",
    "sg:address":"895 N 900 E",
    "sg:city":"American Fork",
    "sg:classifiers":[
        {
            "category":"Organizations",
            "subcategory":"Non-profit Organization",
            "type":"Services"
        },
        {
            "category":"Social Services",
            "subcategory":"Job Training",
            "type":"Services"
        }
    ],
    "sg:phone":"+1 801 763 4008",
    "sg:postcode":"84003",
    "sg:province":"UT",
    "sg:tags":[
        "retardation",
        "disabled",
        "mental",
        "dev"
    ],
    "wof:name":"Mental Retardation Assn Utah",
    "wof:placetype":"venue"
},
  "geometry": {"coordinates":[-111.773296,40.39718],"type":"Point"}
}