{
  "type": "Feature",
  "properties": {
    "iso:country":"US",
    "sg:address":"1079 Murray Holladay Rd",
    "sg:city":"Holladay",
    "sg:classifiers":[
        {
            "category":"Real Estate",
            "subcategory":"Architect",
            "type":"Services"
        }
    ],
    "sg:phone":"+1 801 270 8606",
    "sg:postcode":"84117",
    "sg:province":"UT",
    "sg:tags":[
        "architectural"
    ],
    "wof:name":"Craig Kitterman & Associates",
    "wof:placetype":"venue"
},
  "geometry": {"coordinates":[-111.86372799999999,40.665798],"type":"Point"}
}