{
  "type": "Feature",
  "properties": {
    "iso:country":"US",
    "sg:address":"12 Red Pine Dr",
    "sg:city":"Alpine",
    "sg:classifiers":[
        {
            "category":"Health Services",
            "subcategory":"Chiropractor",
            "type":"Services"
        }
    ],
    "sg:phone":"+1 801 763 5991",
    "sg:postcode":"84004",
    "sg:province":"UT",
    "wof:name":"Hayes Chiropractic",
    "wof:placetype":"venue"
},
  "geometry": {"coordinates":[-111.77641300000001,40.449069],"type":"Point"}
}