{
  "type": "Feature",
  "properties": {
    "iso:country":"US",
    "sg:address":"8418 Rams Horn Dr",
    "sg:city":"West Jordan",
    "sg:classifiers":[
        {
            "category":"Home & Garden",
            "subcategory":"Mobile Homes",
            "type":"Retail Goods"
        }
    ],
    "sg:phone":"+1 801 280 1205",
    "sg:postcode":"84088",
    "sg:province":"UT",
    "sg:tags":[
        "house",
        "factory",
        "built"
    ],
    "wof:name":"V W Modular LLC",
    "wof:placetype":"venue"
},
  "geometry": {"coordinates":[-112.000535,40.59827],"type":"Point"}
}