{
  "type": "Feature",
  "properties": {
    "iso:country":"US",
    "sg:address":"170 N State St",
    "sg:city":"La Verkin",
    "sg:classifiers":[
        {
            "category":"Social Services",
            "subcategory":"Adult Care",
            "type":"Services"
        }
    ],
    "sg:phone":"+1 435 635 4660",
    "sg:postcode":"84745",
    "sg:province":"UT",
    "sg:tags":[
        "residential",
        "training"
    ],
    "wof:name":"Browning Academy",
    "wof:placetype":"venue"
},
  "geometry": {"coordinates":[-113.272026,37.204814],"type":"Point"}
}