{
  "type": "Feature",
  "properties": {
    "iso:country":"US",
    "sg:address":"12261 Cypress Point Way",
    "sg:city":"Draper",
    "sg:classifiers":[
        {
            "category":"Banks & Credit Unions",
            "subcategory":"Investment Brokerage",
            "type":"Services"
        }
    ],
    "sg:phone":"+1 801 571 3071",
    "sg:postcode":"84020",
    "sg:province":"UT",
    "sg:tags":[
        "advisory"
    ],
    "wof:name":"Martan Financial Inc",
    "wof:placetype":"venue"
},
  "geometry": {"coordinates":[-111.844909,40.527317],"type":"Point"}
}