{
  "type": "Feature",
  "properties": {
    "iso:country":"US",
    "sg:address":"50 S Main St",
    "sg:city":"Springville",
    "sg:classifiers":[
        {
            "category":"Organizations",
            "subcategory":"Professional Association",
            "type":"Services"
        }
    ],
    "sg:phone":"+1 801 489 4681",
    "sg:postcode":"84663",
    "sg:province":"UT",
    "sg:tags":[
        "business"
    ],
    "wof:name":"Springville Area Chamber",
    "wof:placetype":"venue"
},
  "geometry": {"coordinates":[-111.610705,40.165968],"type":"Point"}
}