{
  "type": "Feature",
  "properties": {
    "iso:country":"US",
    "sg:address":"2780 Directors Row",
    "sg:city":"Salt Lake City",
    "sg:classifiers":[
        {
            "category":"Wholesale",
            "subcategory":"Machinery & Supplies",
            "type":"Manufacturing & Wholesale Goods"
        }
    ],
    "sg:phone":"+1 801 972 3182",
    "sg:postcode":"84104",
    "sg:province":"UT",
    "sg:tags":[
        "equipment",
        "industrial"
    ],
    "sg:website":"www.atsindustrial.com",
    "wof:name":"ATS Industrial Supply Co",
    "wof:placetype":"venue"
},
  "geometry": {"coordinates":[-111.961687,40.745854],"type":"Point"}
}