{
  "type": "Feature",
  "properties": {
    "iso:country":"US",
    "sg:address":"1449 N 1600 E",
    "sg:city":"Logan",
    "sg:classifiers":[
        {
            "category":"Insurance",
            "subcategory":"Insurance Agent",
            "type":"Services"
        }
    ],
    "sg:phone":"+1 435 787 1119",
    "sg:postcode":"84341",
    "sg:province":"UT",
    "wof:name":"SM Communications Inc",
    "wof:placetype":"venue"
},
  "geometry": {"coordinates":[-111.794709,41.757979],"type":"Point"}
}