{
  "type": "Feature",
  "properties": {
    "iso:country":"US",
    "sg:address":"580 N 800 E",
    "sg:city":"Nephi",
    "sg:classifiers":[
        {
            "category":"Building & Trades",
            "subcategory":"Pest Control",
            "type":"Services"
        }
    ],
    "sg:phone":"+1 435 623 0603",
    "sg:postcode":"84648",
    "sg:province":"UT",
    "wof:name":"Mount Nebo Lawn Pest Ctrl Svc",
    "wof:placetype":"venue"
},
  "geometry": {"coordinates":[-111.820898,39.717001],"type":"Point"}
}