{
  "type": "Feature",
  "properties": {
    "iso:country":"US",
    "sg:address":"7231 S 900 E",
    "sg:city":"Midvale",
    "sg:classifiers":[
        {
            "category":"Home & Garden",
            "subcategory":"Mobile Homes",
            "type":"Retail Goods"
        }
    ],
    "sg:phone":"+1 801 304 0882",
    "sg:postcode":"84047",
    "sg:province":"UT",
    "wof:name":"Paradyme Homes LLC",
    "wof:placetype":"venue"
},
  "geometry": {"coordinates":[-111.865954,40.619736],"type":"Point"}
}