{
  "type": "Feature",
  "properties": {
    "iso:country":"US",
    "sg:address":"357 W 910 S",
    "sg:city":"Heber City",
    "sg:classifiers":[
        {
            "category":"Manufacturing",
            "subcategory":"Food",
            "type":"Manufacturing & Wholesale Goods"
        }
    ],
    "sg:phone":"+1 435 654 0771",
    "sg:postcode":"84032",
    "sg:province":"UT",
    "sg:tags":[
        "cookie",
        "mfg"
    ],
    "wof:name":"Go Cookie Inc",
    "wof:placetype":"venue"
},
  "geometry": {"coordinates":[-111.420203,40.495951],"type":"Point"}
}