{
  "type": "Feature",
  "properties": {
    "iso:country":"US",
    "sg:address":"1953 California Ave",
    "sg:city":"Salt Lake City",
    "sg:classifiers":[
        {
            "category":"Restaurant",
            "type":"Food & Drink"
        }
    ],
    "sg:menulink":"http://www.allmenus.com/ut/salt-lake-city/218170-burger-king/menu/",
    "sg:phone":"+1 801 977 3900",
    "sg:postcode":"84104",
    "sg:province":"UT",
    "sg:tags":[
        "american"
    ],
    "wof:name":"Burger King",
    "wof:placetype":"venue"
},
  "geometry": {"coordinates":[-111.946701,40.740457],"type":"Point"}
}