{
  "type": "Feature",
  "properties": {
    "iso:country":"US",
    "sg:address":"4228 Westlake Ave",
    "sg:city":"Salt Lake City",
    "sg:classifiers":[
        {
            "category":"Building & Trades",
            "subcategory":"Construction",
            "type":"Services"
        }
    ],
    "sg:phone":"+1 801 969 5041",
    "sg:postcode":"84120",
    "sg:province":"UT",
    "sg:tags":[
        "contractor"
    ],
    "wof:name":"George Hanna Roofing Inc",
    "wof:placetype":"venue"
},
  "geometry": {"coordinates":[-111.992217,40.673551],"type":"Point"}
}