{
  "type": "Feature",
  "properties": {
    "iso:country":"US",
    "sg:address":"376 E 400 S",
    "sg:city":"Salt Lake City",
    "sg:classifiers":[
        {
            "category":"Retail",
            "subcategory":"Repair Shop",
            "type":"Services"
        }
    ],
    "sg:phone":"+1 801 969 9348",
    "sg:postcode":"84111",
    "sg:province":"UT",
    "sg:tags":[
        "welding"
    ],
    "wof:name":"J & J Welding Inc",
    "wof:placetype":"venue"
},
  "geometry": {"coordinates":[-111.880236,40.760579],"type":"Point"}
}