{
  "type": "Feature",
  "properties": {
    "iso:country":"US",
    "sg:address":"668 E 3500 S",
    "sg:city":"Vernal",
    "sg:classifiers":[
        {
            "category":"Professional",
            "type":"Services"
        }
    ],
    "sg:phone":"+1 435 789 6531",
    "sg:postcode":"84078",
    "sg:province":"UT",
    "wof:name":"Circle D Svc",
    "wof:placetype":"venue"
},
  "geometry": {"coordinates":[-109.511737,40.404617],"type":"Point"}
}