{
  "type": "Feature",
  "properties": {
    "iso:country":"US",
    "sg:address":"1512 E 4500 S",
    "sg:city":"Holladay",
    "sg:classifiers":[
        {
            "category":"Social Services",
            "type":"Services"
        }
    ],
    "sg:phone":"+1 801 274 1786",
    "sg:postcode":"84117",
    "sg:province":"UT",
    "sg:tags":[
        "counselor",
        "marriage",
        "family"
    ],
    "wof:name":"Sierra Health Assoc",
    "wof:placetype":"venue"
},
  "geometry": {"coordinates":[-111.847505,40.674201],"type":"Point"}
}