{
  "type": "Feature",
  "properties": {
    "iso:country":"US",
    "sg:address":"40 E Center St",
    "sg:city":"Cedar Valley",
    "sg:classifiers":[
        {
            "category":"Education",
            "subcategory":"School",
            "type":"Public Place"
        }
    ],
    "sg:phone":"+1 801 768 3542",
    "sg:postcode":"84013",
    "sg:province":"UT",
    "wof:name":"Cedar Valley Elementary School",
    "wof:placetype":"venue"
},
  "geometry": {"coordinates":[-112.105378,40.327309],"type":"Point"}
}