{
  "type": "Feature",
  "properties": {
    "iso:country":"US",
    "sg:address":"336 S Cooley St",
    "sg:city":"Grantsville",
    "sg:classifiers":[
        {
            "category":"Retail",
            "subcategory":"Repair Shop",
            "type":"Services"
        }
    ],
    "sg:phone":"+1 435 884 6374",
    "sg:postcode":"84029",
    "sg:province":"UT",
    "wof:name":"Faye Mower",
    "wof:placetype":"venue"
},
  "geometry": {"coordinates":[-112.473708,40.591634],"type":"Point"}
}