{
  "type": "Feature",
  "properties": {
    "iso:country":"US",
    "sg:address":"895 37th St",
    "sg:city":"Ogden",
    "sg:classifiers":[
        {
            "category":"Food & Beverages",
            "subcategory":"Meat & Fish",
            "type":"Retail Goods"
        }
    ],
    "sg:phone":"+1 801 392 5416",
    "sg:postcode":"84403",
    "sg:province":"UT",
    "wof:name":"Cut-N-Cold Food Lockers",
    "wof:placetype":"venue"
},
  "geometry": {"coordinates":[-111.958883,41.195826],"type":"Point"}
}