{
  "type": "Feature",
  "properties": {
    "iso:country":"US",
    "sg:address":"850 N 535 E",
    "sg:city":"Pleasant Grove",
    "sg:classifiers":[
        {
            "category":"Building & Trades",
            "subcategory":"Equipment Rental",
            "type":"Services"
        }
    ],
    "sg:phone":"+1 801 785 7189",
    "sg:postcode":"84062",
    "sg:province":"UT",
    "wof:name":"Accent Furniture Inc",
    "wof:placetype":"venue"
},
  "geometry": {"coordinates":[-111.72954,40.37235],"type":"Point"}
}