{
  "type": "Feature",
  "properties": {
    "iso:country":"US",
    "sg:address":"1050 Chapel Hill Dr",
    "sg:city":"Midvale",
    "sg:classifiers":[
        {
            "category":"Organizations",
            "subcategory":"Religious Organization",
            "type":"Services"
        }
    ],
    "sg:phone":"+1 801 562 8042",
    "sg:postcode":"84047",
    "sg:province":"UT",
    "sg:tags":[
        "church"
    ],
    "wof:name":"Church Of Jesus Christ Of Lds",
    "wof:placetype":"venue"
},
  "geometry": {"coordinates":[-111.86055,40.616558],"type":"Point"}
}