{
  "type": "Feature",
  "properties": {
    "iso:country":"US",
    "sg:address":"2350 E 1300 S",
    "sg:city":"Salt Lake City",
    "sg:classifiers":[
        {
            "category":"Retail",
            "subcategory":"Funeral Services",
            "type":"Services"
        }
    ],
    "sg:phone":"+1 801 582 1582",
    "sg:postcode":"84108",
    "sg:province":"UT",
    "sg:tags":[
        "mortuary"
    ],
    "wof:name":"Larking Sunset Lawn Mortuary",
    "wof:placetype":"venue"
},
  "geometry": {"coordinates":[-111.822684,40.742198],"type":"Point"}
}