{
  "type": "Feature",
  "properties": {
    "iso:country":"US",
    "sg:address":"151 N 500 W",
    "sg:city":"Payson",
    "sg:classifiers":[
        {
            "category":"Building & Trades",
            "subcategory":"Cleaning & Sanitation",
            "type":"Services"
        }
    ],
    "sg:phone":"+1 801 379 3302",
    "sg:postcode":"84651",
    "sg:province":"UT",
    "sg:tags":[
        "janitor"
    ],
    "wof:name":"Intermountain Janitorial",
    "wof:placetype":"venue"
},
  "geometry": {"coordinates":[-111.73979300000001,40.045167],"type":"Point"}
}