{
  "type": "Feature",
  "properties": {
    "iso:country":"US",
    "sg:address":"429 E 600 N",
    "sg:city":"Provo",
    "sg:classifiers":[
        {
            "category":"Real Estate",
            "subcategory":"Real Estate Agent",
            "type":"Services"
        }
    ],
    "sg:phone":"+1 801 375 3325",
    "sg:postcode":"84606",
    "sg:province":"UT",
    "sg:tags":[
        "property",
        "lessor"
    ],
    "wof:name":"Cutler Management",
    "wof:placetype":"venue"
},
  "geometry": {"coordinates":[-111.65031500000001,40.241758],"type":"Point"}
}