{
  "type": "Feature",
  "properties": {
    "iso:country":"US",
    "sg:address":"1009 N 1200 W",
    "sg:city":"Orem",
    "sg:classifiers":[
        {
            "category":"Home & Garden",
            "subcategory":"Carpets & Floor Coverings",
            "type":"Retail Goods"
        }
    ],
    "sg:phone":"+1 801 221 9086",
    "sg:postcode":"84057",
    "sg:province":"UT",
    "sg:tags":[
        "dealer",
        "rug"
    ],
    "wof:name":"Marathon Triad Carpet Mill",
    "wof:placetype":"venue"
},
  "geometry": {"coordinates":[-111.72462899999999,40.315353],"type":"Point"}
}