{
  "type": "Feature",
  "properties": {
    "iso:country":"US",
    "sg:address":"767 E 600 N",
    "sg:city":"Heber City",
    "sg:classifiers":[
        {
            "category":"Professional",
            "subcategory":"Business Services",
            "type":"Services"
        }
    ],
    "sg:phone":"+1 435 654 1432",
    "sg:postcode":"84032",
    "sg:province":"UT",
    "wof:name":"Ed Diamond & Assoc Inc",
    "wof:placetype":"venue"
},
  "geometry": {"coordinates":[-111.398533,40.515718],"type":"Point"}
}