{
  "type": "Feature",
  "properties": {
    "iso:country":"US",
    "sg:address":"6526 S State St",
    "sg:city":"Salt Lake City",
    "sg:classifiers":[
        {
            "category":"Shopping",
            "subcategory":"Optical Goods",
            "type":"Retail Goods"
        }
    ],
    "sg:phone":"+1 801 685 7989",
    "sg:postcode":"84107",
    "sg:province":"UT",
    "wof:name":"Brad Rice",
    "wof:placetype":"venue"
},
  "geometry": {"coordinates":[-111.889645,40.631581],"type":"Point"}
}