{
  "type": "Feature",
  "properties": {
    "iso:country":"US",
    "sg:address":"766 E 930 N",
    "sg:city":"Pleasant Grove",
    "sg:classifiers":[
        {
            "category":"Professional",
            "subcategory":"Business Services",
            "type":"Services"
        }
    ],
    "sg:phone":"+1 801 796 8100",
    "sg:postcode":"84062",
    "sg:province":"UT",
    "wof:name":"Duplication Station LLC",
    "wof:placetype":"venue"
},
  "geometry": {"coordinates":[-111.721745,40.373311],"type":"Point"}
}