{
  "type": "Feature",
  "properties": {
    "iso:country":"US",
    "sg:address":"1275 Fort Union Blvd",
    "sg:city":"Midvale",
    "sg:classifiers":[
        {
            "category":"Health Services",
            "subcategory":"Clinic",
            "type":"Services"
        }
    ],
    "sg:phone":"+1 801 568 0240",
    "sg:postcode":"84047",
    "sg:province":"UT",
    "sg:tags":[
        "specialty",
        "outpatient"
    ],
    "wof:name":"HealthSouth",
    "wof:placetype":"venue"
},
  "geometry": {"coordinates":[-111.855698,40.626172],"type":"Point"}
}