{
  "type": "Feature",
  "properties": {
    "iso:country":"US",
    "sg:address":"7355 S 900 East St",
    "sg:city":"Midvale",
    "sg:classifiers":[
        {
            "category":"Health Services",
            "subcategory":"Doctor",
            "type":"Services"
        }
    ],
    "sg:phone":"+1 801 255 4269",
    "sg:postcode":"84047",
    "sg:province":"UT",
    "sg:tags":[
        "dentist"
    ],
    "wof:name":"John L Alder DDS",
    "wof:placetype":"venue"
},
  "geometry": {"coordinates":[-111.865981,40.618821],"type":"Point"}
}