{
  "type": "Feature",
  "properties": {
    "iso:country":"US",
    "sg:address":"410 W State St",
    "sg:city":"Hurricane",
    "sg:classifiers":[
        {
            "category":"Restaurant",
            "type":"Food & Drink"
        }
    ],
    "sg:menulink":"http://www.allmenus.com/ut/hurricane/69603-dominos-pizza/menu/",
    "sg:phone":"+1 435 635 3322",
    "sg:postcode":"84737",
    "sg:province":"UT",
    "sg:tags":[
        "american",
        "wing",
        "pizza"
    ],
    "wof:name":"Domino's Pizza",
    "wof:placetype":"venue"
},
  "geometry": {"coordinates":[-113.295896,37.176486],"type":"Point"}
}