{
  "type": "Feature",
  "properties": {
    "iso:country":"US",
    "sg:address":"36 E Tabernacle St",
    "sg:city":"St George",
    "sg:classifiers":[
        {
            "category":"Shopping",
            "subcategory":"Books",
            "type":"Retail Goods"
        }
    ],
    "sg:phone":"+1 435 673 5478",
    "sg:postcode":"84770",
    "sg:province":"UT",
    "wof:name":"R& KS Bookstore",
    "wof:placetype":"venue"
},
  "geometry": {"coordinates":[-113.582678,37.10811],"type":"Point"}
}