{
  "type": "Feature",
  "properties": {
    "iso:country":"US",
    "sg:address":"3815 S West Temple",
    "sg:city":"Salt Lake City",
    "sg:classifiers":[
        {
            "category":"Mining & Drilling",
            "type":"Manufacturing & Wholesale Goods"
        }
    ],
    "sg:phone":"+1 801 293 2586",
    "sg:postcode":"84115",
    "sg:province":"UT",
    "sg:tags":[
        "field"
    ],
    "wof:name":"Loan Servicing Center",
    "wof:placetype":"venue"
},
  "geometry": {"coordinates":[-111.893896,40.689229],"type":"Point"}
}