{
  "type": "Feature",
  "properties": {
    "iso:country":"US",
    "sg:address":"2909 Washington Blvd",
    "sg:city":"Ogden",
    "sg:classifiers":[
        {
            "category":"Home & Garden",
            "subcategory":"Furniture",
            "type":"Retail Goods"
        }
    ],
    "sg:phone":"+1 801 621 4781",
    "sg:postcode":"84401",
    "sg:province":"UT",
    "sg:tags":[
        "building",
        "fixture",
        "supply"
    ],
    "wof:name":"Cornerstone Supply Inc",
    "wof:placetype":"venue"
},
  "geometry": {"coordinates":[-111.970783,41.21037],"type":"Point"}
}