{
  "type": "Feature",
  "properties": {
    "iso:country":"US",
    "sg:address":"1938 Oakshire Ln",
    "sg:city":"Sandy",
    "sg:classifiers":[
        {
            "category":"Professional",
            "subcategory":"Management & Consulting",
            "type":"Services"
        }
    ],
    "sg:phone":"+1 801 576 8064",
    "sg:postcode":"84092",
    "sg:province":"UT",
    "sg:tags":[
        "consultant",
        "business"
    ],
    "wof:name":"Spencer Shenk Capers & Assoc",
    "wof:placetype":"venue"
},
  "geometry": {"coordinates":[-111.835387,40.540577],"type":"Point"}
}