{
  "type": "Feature",
  "properties": {
    "iso:country":"US",
    "sg:address":"805 S 500 W",
    "sg:city":"Payson",
    "sg:classifiers":[
        {
            "category":"Health Services",
            "subcategory":"Medical Lab",
            "type":"Services"
        }
    ],
    "sg:phone":"+1 801 465 1296",
    "sg:postcode":"84651",
    "sg:province":"UT",
    "sg:tags":[
        "laboratory"
    ],
    "wof:name":"Tempus Laboratory",
    "wof:placetype":"venue"
},
  "geometry": {"coordinates":[-111.739694,40.031308],"type":"Point"}
}