{
  "type": "Feature",
  "properties": {
    "iso:country":"US",
    "sg:address":"385 N 75 W",
    "sg:city":"Clearfield",
    "sg:classifiers":[
        {
            "category":"Social Services",
            "subcategory":"Adult Care",
            "type":"Services"
        }
    ],
    "sg:phone":"+1 801 825 3280",
    "sg:postcode":"84015",
    "sg:province":"UT",
    "sg:tags":[
        "residential"
    ],
    "wof:name":"Jody Roper",
    "wof:placetype":"venue"
},
  "geometry": {"coordinates":[-112.02737999999999,41.119384],"type":"Point"}
}