{
  "type": "Feature",
  "properties": {
    "iso:country":"US",
    "sg:address":"2230 N University Pkwy",
    "sg:city":"Provo",
    "sg:classifiers":[
        {
            "category":"Travel",
            "subcategory":"Hotels & Motels",
            "type":"Entertainment"
        }
    ],
    "sg:phone":"+1 801 373 7044",
    "sg:postcode":"84604",
    "sg:province":"UT",
    "sg:website":"www.cottontree.net",
    "wof:name":"Best Western Inn",
    "wof:placetype":"venue"
},
  "geometry": {"coordinates":[-111.668554,40.263999],"type":"Point"}
}