{
  "type": "Feature",
  "properties": {
    "iso:country":"US",
    "sg:address":"974 E 2100 S",
    "sg:city":"Salt Lake City",
    "sg:classifiers":[
        {
            "category":"Restaurant",
            "type":"Food & Drink"
        }
    ],
    "sg:phone":"+1 801 485 8658",
    "sg:postcode":"84106",
    "sg:province":"UT",
    "wof:name":"Subway Sandwiches & Salads",
    "wof:placetype":"venue"
},
  "geometry": {"coordinates":[-111.86273,40.725344],"type":"Point"}
}