{
  "type": "Feature",
  "properties": {
    "iso:country":"US",
    "sg:address":"1433 N Main St",
    "sg:city":"Logan",
    "sg:classifiers":[
        {
            "category":"Shopping",
            "type":"Retail Goods"
        }
    ],
    "sg:phone":"+1 435 755 0575",
    "sg:postcode":"84341",
    "sg:province":"UT",
    "sg:tags":[
        "merchandise"
    ],
    "wof:name":"T-Mobile USA Inc",
    "wof:placetype":"venue"
},
  "geometry": {"coordinates":[-111.83442100000001,41.759163],"type":"Point"}
}