{
  "type": "Feature",
  "properties": {
    "iso:country":"US",
    "sg:address":"56 E Fireclay Ave",
    "sg:city":"Salt Lake City",
    "sg:classifiers":[
        {
            "category":"Retail",
            "subcategory":"Auto Repair",
            "type":"Services"
        }
    ],
    "sg:phone":"+1 801 268 9963",
    "sg:postcode":"84107",
    "sg:province":"UT",
    "sg:tags":[
        "general"
    ],
    "wof:name":"Tri Auto",
    "wof:placetype":"venue"
},
  "geometry": {"coordinates":[-111.88968,40.677911],"type":"Point"}
}