{
  "type": "Feature",
  "properties": {
    "iso:country":"US",
    "sg:address":"1135 S West Temple",
    "sg:city":"Salt Lake City",
    "sg:classifiers":[
        {
            "category":"Organizations",
            "subcategory":"Professional Association",
            "type":"Services"
        }
    ],
    "sg:phone":"+1 801 363 2753",
    "sg:postcode":"84101",
    "sg:province":"UT",
    "sg:website":"www.agc-utah.org",
    "wof:name":"Associated General Contractors",
    "wof:placetype":"venue"
},
  "geometry": {"coordinates":[-111.893868,40.744217],"type":"Point"}
}