{
  "type": "Feature",
  "properties": {
    "iso:country":"US",
    "sg:address":"115 N Main St",
    "sg:city":"Beaver",
    "sg:classifiers":[
        {
            "category":"Retail",
            "subcategory":"Auto Repair",
            "type":"Services"
        }
    ],
    "sg:phone":"+1 435 438 5409",
    "sg:postcode":"84751",
    "sg:province":"UT",
    "sg:tags":[
        "body",
        "general"
    ],
    "wof:name":"Tonys & Daves Auto Center",
    "wof:placetype":"venue"
},
  "geometry": {"coordinates":[-113.010341,38.399038],"type":"Point"}
}