{
  "type": "Feature",
  "properties": {
    "iso:country":"US",
    "sg:address":"628 State St",
    "sg:city":"Clearfield",
    "sg:classifiers":[
        {
            "category":"Personal",
            "subcategory":"Beauty Salon",
            "type":"Services"
        }
    ],
    "sg:phone":"+1 801 525 0113",
    "sg:postcode":"84015",
    "sg:province":"UT",
    "wof:name":"Fantastic Sam's",
    "wof:placetype":"venue"
},
  "geometry": {"coordinates":[-112.01654499999999,41.104712],"type":"Point"}
}