{
  "type": "Feature",
  "properties": {
    "iso:country":"US",
    "sg:address":"12233 S Spring Lake Rd",
    "sg:city":"Payson",
    "sg:classifiers":[
        {
            "category":"Wholesale",
            "subcategory":"Computers",
            "type":"Manufacturing & Wholesale Goods"
        }
    ],
    "sg:phone":"+1 801 465 4301",
    "sg:postcode":"84651",
    "sg:province":"UT",
    "sg:tags":[
        "software",
        "package"
    ],
    "wof:name":"Qualtech Systems Inc",
    "wof:placetype":"venue"
},
  "geometry": {"coordinates":[-111.746439,40.007635],"type":"Point"}
}