{
  "type": "Feature",
  "properties": {
    "iso:country":"US",
    "sg:address":"2 Longwood Ln",
    "sg:city":"Sandy",
    "sg:classifiers":[
        {
            "category":"Restaurant",
            "type":"Food & Drink"
        }
    ],
    "sg:phone":"+1 801 566 5016",
    "sg:postcode":"84092",
    "sg:province":"UT",
    "sg:tags":[
        "eating"
    ],
    "wof:name":"Black Forest Bakery & Cafe",
    "wof:placetype":"venue"
},
  "geometry": {"coordinates":[-111.821881,40.55373],"type":"Point"}
}