{
  "type": "Feature",
  "properties": {
    "iso:country":"US",
    "sg:address":"160 N Main St",
    "sg:city":"Nephi",
    "sg:classifiers":[
        {
            "category":"Professional",
            "subcategory":"Accounting & Tax Preparation",
            "type":"Services"
        }
    ],
    "sg:phone":"+1 435 623 3460",
    "sg:postcode":"84648",
    "sg:province":"UT",
    "sg:tags":[
        "billing",
        "ambulance"
    ],
    "wof:name":"Ambulance Billing",
    "wof:placetype":"venue"
},
  "geometry": {"coordinates":[-111.83607000000001,39.710572],"type":"Point"}
}