{
  "type": "Feature",
  "properties": {
    "iso:country":"US",
    "sg:address":"163 N Main St",
    "sg:city":"Huntington",
    "sg:classifiers":[
        {
            "category":"Cinema",
            "subcategory":"Movie Theater",
            "type":"Entertainment"
        }
    ],
    "sg:phone":"+1 435 687 7827",
    "sg:postcode":"84528",
    "sg:province":"UT",
    "sg:tags":[
        "motion",
        "picture"
    ],
    "wof:name":"Star Theatrer",
    "wof:placetype":"venue"
},
  "geometry": {"coordinates":[-110.964686,39.328917],"type":"Point"}
}