{
  "type": "Feature",
  "properties": {
    "iso:country":"US",
    "sg:address":"2195 E Evergreen Ave",
    "sg:city":"Salt Lake City",
    "sg:classifiers":[
        {
            "category":"Manufacturing",
            "subcategory":"Metals",
            "type":"Manufacturing & Wholesale Goods"
        }
    ],
    "sg:phone":"+1 801 466 0444",
    "sg:postcode":"84109",
    "sg:province":"UT",
    "sg:tags":[
        "equipment",
        "fireplace"
    ],
    "wof:name":"E Z Fire Products",
    "wof:placetype":"venue"
},
  "geometry": {"coordinates":[-111.827511,40.696792],"type":"Point"}
}