{
  "type": "Feature",
  "properties": {
    "iso:country":"US",
    "sg:address":"3549 N University Ave",
    "sg:city":"Provo",
    "sg:classifiers":[
        {
            "category":"Professional",
            "subcategory":"Management & Consulting",
            "type":"Services"
        }
    ],
    "sg:phone":"+1 801 374 5244",
    "sg:postcode":"84604",
    "sg:province":"UT",
    "wof:name":"Wealthcare",
    "wof:placetype":"venue"
},
  "geometry": {"coordinates":[-111.65859,40.282309],"type":"Point"}
}