{
  "type": "Feature",
  "properties": {
    "iso:country":"US",
    "sg:address":"747 S Paradise Canyon Rd",
    "sg:city":"Cedar City",
    "sg:classifiers":[
        {
            "category":"Government",
            "subcategory":"Office",
            "type":"Public Place"
        }
    ],
    "sg:phone":"+1 435 586 2162",
    "sg:postcode":"84720",
    "sg:province":"UT",
    "sg:tags":[
        "station",
        "recruiting",
        "naval"
    ],
    "wof:name":"Navy Recruiting Station",
    "wof:placetype":"venue"
},
  "geometry": {"coordinates":[-113.06498499999999,37.664319],"type":"Point"}
}