{
  "type": "Feature",
  "properties": {
    "iso:country":"US",
    "sg:address":"546 Willow Springs Ln",
    "sg:city":"Draper",
    "sg:classifiers":[
        {
            "category":"Professional",
            "subcategory":"Business Services",
            "type":"Services"
        }
    ],
    "sg:phone":"+1 801 571 5187",
    "sg:postcode":"84020",
    "sg:province":"UT",
    "wof:name":"Business Solutions",
    "wof:placetype":"venue"
},
  "geometry": {"coordinates":[-111.87649399999999,40.519793],"type":"Point"}
}