{
  "type": "Feature",
  "properties": {
    "iso:country":"US",
    "sg:address":"520 E 9000 S",
    "sg:city":"Sandy",
    "sg:classifiers":[
        {
            "category":"Professional",
            "subcategory":"Business Services",
            "type":"Services"
        }
    ],
    "sg:phone":"+1 801 561 7188",
    "sg:postcode":"84070",
    "sg:province":"UT",
    "wof:name":"R B Services",
    "wof:placetype":"venue"
},
  "geometry": {"coordinates":[-111.87687699999999,40.588073],"type":"Point"}
}