{
  "type": "Feature",
  "properties": {
    "iso:country":"US",
    "sg:address":"5042 Three Fountains Cir",
    "sg:city":"Salt Lake City",
    "sg:classifiers":[
        {
            "category":"Organizations",
            "subcategory":"Non-profit Organization",
            "type":"Services"
        }
    ],
    "sg:phone":"+1 801 261 2121",
    "sg:postcode":"84107",
    "sg:province":"UT",
    "sg:tags":[
        "social"
    ],
    "wof:name":"George Q Morris Foundation",
    "wof:placetype":"venue"
},
  "geometry": {"coordinates":[-111.865872,40.661594],"type":"Point"}
}