{
  "type": "Feature",
  "properties": {
    "iso:country":"US",
    "sg:address":"1574 N Dixie Downs Rd",
    "sg:city":"St George",
    "sg:classifiers":[
        {
            "category":"Building & Trades",
            "subcategory":"Landscaping Services",
            "type":"Services"
        }
    ],
    "sg:phone":"+1 435 673 0492",
    "sg:postcode":"84770",
    "sg:province":"UT",
    "wof:name":"Jerald Sandberg Yard Care",
    "wof:placetype":"venue"
},
  "geometry": {"coordinates":[-113.623859,37.136213],"type":"Point"}
}