{
  "type": "Feature",
  "properties": {
    "iso:country":"US",
    "sg:address":"1454 S University Ave",
    "sg:city":"Provo",
    "sg:classifiers":[
        {
            "category":"Restaurant",
            "type":"Food & Drink"
        }
    ],
    "sg:menulink":"http://www.allmenus.com/ut/provo-orem/40227-ruby-river/menu/",
    "sg:phone":"+1 801 371 0648",
    "sg:postcode":"84601",
    "sg:province":"UT",
    "sg:tags":[
        "american",
        "steakhouse"
    ],
    "wof:name":"Ruby River",
    "wof:placetype":"venue"
},
  "geometry": {"coordinates":[-111.65916199999999,40.214287],"type":"Point"}
}