{
  "type": "Feature",
  "properties": {
    "iso:country":"US",
    "sg:address":"544 Lindon Pkwy",
    "sg:city":"Lindon",
    "sg:classifiers":[
        {
            "category":"Autos & Motor Vehicles",
            "subcategory":"Automobile Sales",
            "type":"Retail Goods"
        }
    ],
    "sg:phone":"+1 801 227 3200",
    "sg:postcode":"84042",
    "sg:province":"UT",
    "sg:tags":[
        "car",
        "dealer"
    ],
    "sg:website":"www.lexusoflindon.com",
    "wof:name":"Larry H Miller Lexus Of Lindon",
    "wof:placetype":"venue"
},
  "geometry": {"coordinates":[-111.730833,40.330063],"type":"Point"}
}