{
  "type": "Feature",
  "properties": {
    "iso:country":"US",
    "sg:address":"687 W 6960 S",
    "sg:city":"Midvale",
    "sg:classifiers":[
        {
            "category":"Manufacturing",
            "subcategory":"Tools & Machinery",
            "type":"Manufacturing & Wholesale Goods"
        }
    ],
    "sg:phone":"+1 801 718 3742",
    "sg:postcode":"84047",
    "sg:province":"UT",
    "sg:tags":[
        "industrial",
        "mfg"
    ],
    "wof:name":"Braggs Machining Inc",
    "wof:placetype":"venue"
},
  "geometry": {"coordinates":[-111.909897,40.62494],"type":"Point"}
}