{
  "type": "Feature",
  "properties": {
    "iso:country":"US",
    "sg:address":"61 S 600 W",
    "sg:city":"Kaysville",
    "sg:classifiers":[
        {
            "category":"Freight",
            "type":"Transportation"
        }
    ],
    "sg:phone":"+1 801 544 5227",
    "sg:postcode":"84037",
    "sg:province":"UT",
    "sg:tags":[
        "grain",
        "elevator"
    ],
    "wof:name":"Deseret Grain-Kaysville",
    "wof:placetype":"venue"
},
  "geometry": {"coordinates":[-111.949451,41.034334],"type":"Point"}
}