{
  "type": "Feature",
  "properties": {
    "iso:country":"US",
    "sg:address":"10814 Meadow River Dr",
    "sg:city":"Sandy",
    "sg:classifiers":[
        {
            "category":"Professional",
            "type":"Services"
        }
    ],
    "sg:phone":"+1 801 572 1960",
    "sg:postcode":"84070",
    "sg:province":"UT",
    "wof:name":"Realize Incorporated",
    "wof:placetype":"venue"
},
  "geometry": {"coordinates":[-111.883101,40.554829],"type":"Point"}
}