{
  "type": "Feature",
  "properties": {
    "iso:country":"US",
    "sg:address":"2459 S Main St",
    "sg:city":"Woods Cross",
    "sg:classifiers":[
        {
            "category":"Insurance",
            "subcategory":"Insurance Agent",
            "type":"Services"
        }
    ],
    "sg:phone":"+1 801 294 5502",
    "sg:postcode":"84010",
    "sg:province":"UT",
    "wof:name":"Allstate Insurance",
    "wof:placetype":"venue"
},
  "geometry": {"coordinates":[-111.894594,40.86332],"type":"Point"}
}