{
  "type": "Feature",
  "properties": {
    "iso:country":"US",
    "sg:address":"315 E 200 S",
    "sg:city":"Salt Lake City",
    "sg:classifiers":[
        {
            "category":"Organizations",
            "subcategory":"Community Association",
            "type":"Services"
        }
    ],
    "sg:phone":"+1 801 799 3440",
    "sg:postcode":"84111",
    "sg:province":"UT",
    "wof:name":"Salt Lake Cy Police Derartment",
    "wof:placetype":"venue"
},
  "geometry": {"coordinates":[-111.881759,40.765079],"type":"Point"}
}