{
  "type": "Feature",
  "properties": {
    "iso:country":"US",
    "sg:address":"226 W 1060 S",
    "sg:city":"Orem",
    "sg:classifiers":[
        {
            "category":"Recreation",
            "type":"Entertainment"
        }
    ],
    "sg:phone":"+1 801 226 0367",
    "sg:postcode":"84058",
    "sg:province":"UT",
    "wof:name":"Kids FAD (fighting AGA",
    "wof:placetype":"venue"
},
  "geometry": {"coordinates":[-111.70202999999999,40.27797],"type":"Point"}
}