{
  "type": "Feature",
  "properties": {
    "iso:country":"US",
    "sg:address":"1024 E 5275 S",
    "sg:city":"Ogden",
    "sg:classifiers":[
        {
            "category":"Utilities",
            "subcategory":"Telephone",
            "type":"Services"
        }
    ],
    "sg:phone":"+1 801 773 1680",
    "sg:postcode":"84403",
    "sg:province":"UT",
    "sg:tags":[
        "web",
        "consulting",
        "financial",
        "it",
        "solution",
        "advising",
        "internet"
    ],
    "wof:name":"Pay-Yourselfcom Inc",
    "wof:placetype":"venue"
},
  "geometry": {"coordinates":[-111.94927,41.166745],"type":"Point"}
}