{
  "type": "Feature",
  "properties": {
    "iso:country":"US",
    "sg:address":"1492 Haight Creek Dr",
    "sg:city":"Kaysville",
    "sg:classifiers":[
        {
            "category":"Building & Trades",
            "subcategory":"Electrical",
            "type":"Services"
        }
    ],
    "sg:phone":"+1 801 451 7873",
    "sg:postcode":"84037",
    "sg:province":"UT",
    "sg:tags":[
        "lighting",
        "contractor"
    ],
    "wof:name":"K & S Lighting Lc",
    "wof:placetype":"venue"
},
  "geometry": {"coordinates":[-111.92131000000001,41.010843],"type":"Point"}
}