{
  "type": "Feature",
  "properties": {
    "iso:country":"US",
    "sg:address":"243 E 500 N",
    "sg:city":"Provo",
    "sg:classifiers":[
        {
            "category":"Real Estate",
            "subcategory":"Real Estate Operator",
            "type":"Services"
        }
    ],
    "sg:phone":"+1 801 374 9788",
    "sg:postcode":"84606",
    "sg:province":"UT",
    "wof:name":"Par Management",
    "wof:placetype":"venue"
},
  "geometry": {"coordinates":[-111.653953,40.240438],"type":"Point"}
}