{
  "type": "Feature",
  "properties": {
    "iso:country":"US",
    "sg:address":"8692 S 4000 W",
    "sg:city":"West Jordan",
    "sg:classifiers":[
        {
            "category":"Insurance",
            "subcategory":"Hazard Insurance",
            "type":"Services"
        }
    ],
    "sg:phone":"+1 801 578 5788",
    "sg:postcode":"84088",
    "sg:province":"UT",
    "sg:tags":[
        "funds",
        "administrator"
    ],
    "wof:name":"Deseret Mutl Bneft Admnstrtors",
    "wof:placetype":"venue"
},
  "geometry": {"coordinates":[-111.98649899999999,40.593242],"type":"Point"}
}