{
  "type": "Feature",
  "properties": {
    "iso:country":"US",
    "sg:address":"742 W 800 N",
    "sg:city":"Orem",
    "sg:classifiers":[
        {
            "category":"Health Services",
            "subcategory":"Doctor",
            "type":"Services"
        }
    ],
    "sg:phone":"+1 801 802 0120",
    "sg:postcode":"84057",
    "sg:province":"UT",
    "sg:tags":[
        "surgeon",
        "plastic"
    ],
    "wof:name":"John B Bishop MD PC",
    "wof:placetype":"venue"
},
  "geometry": {"coordinates":[-111.71344999999999,40.312109],"type":"Point"}
}