{
  "type": "Feature",
  "properties": {
    "iso:country":"US",
    "sg:address":"151 W 200 N",
    "sg:city":"Salt Lake City",
    "sg:classifiers":[
        {
            "category":"Building & Trades",
            "subcategory":"Construction",
            "type":"Services"
        }
    ],
    "sg:phone":"+1 435 781 8310",
    "sg:postcode":"84103",
    "sg:province":"UT",
    "sg:tags":[
        "contractor"
    ],
    "wof:name":"Big D Construction",
    "wof:placetype":"venue"
},
  "geometry": {"coordinates":[-111.89492799999999,40.773617],"type":"Point"}
}