{
  "type": "Feature",
  "properties": {
    "iso:country":"US",
    "sg:address":"196 N 200 W",
    "sg:city":"Kaysville",
    "sg:classifiers":[
        {
            "category":"Shopping",
            "subcategory":"Clothing, Apparel, & Fashions",
            "type":"Retail Goods"
        }
    ],
    "sg:phone":"+1 801 547 0061",
    "sg:postcode":"84037",
    "sg:province":"UT",
    "sg:tags":[
        "shop",
        "bridal"
    ],
    "sg:website":"www.kathleensbridal.com",
    "wof:name":"Kathleen's Career & Formal Wr",
    "wof:placetype":"venue"
},
  "geometry": {"coordinates":[-111.941892,41.036527],"type":"Point"}
}