{
  "type": "Feature",
  "properties": {
    "iso:country":"US",
    "sg:address":"423 W 300 N",
    "sg:city":"Lehi",
    "sg:classifiers":[
        {
            "category":"Building & Trades",
            "subcategory":"Construction",
            "type":"Services"
        }
    ],
    "sg:phone":"+1 801 768 1575",
    "sg:postcode":"84043",
    "sg:province":"UT",
    "sg:tags":[
        "marking",
        "maintenance",
        "parking"
    ],
    "wof:name":"Lehi City Of Public Works Dept",
    "wof:placetype":"venue"
},
  "geometry": {"coordinates":[-111.856897,40.391467],"type":"Point"}
}