{
  "type": "Feature",
  "properties": {
    "iso:country":"US",
    "sg:address":"55 N 300 E",
    "sg:city":"Tremonton",
    "sg:classifiers":[
        {
            "category":"Autos & Motor Vehicles",
            "subcategory":"Auto Supplies",
            "type":"Retail Goods"
        }
    ],
    "sg:phone":"+1 435 257 3395",
    "sg:postcode":"84337",
    "sg:province":"UT",
    "sg:tags":[
        "wheel",
        "shock",
        "alignment",
        "tire"
    ],
    "wof:name":"Big O Tires",
    "wof:placetype":"venue"
},
  "geometry": {"coordinates":[-112.16181899999999,41.712271],"type":"Point"}
}