{
  "type": "Feature",
  "properties": {
    "iso:country":"US",
    "sg:address":"7980 S State St",
    "sg:city":"Midvale",
    "sg:classifiers":[
        {
            "category":"Professional",
            "type":"Services"
        }
    ],
    "sg:phone":"+1 801 255 6334",
    "sg:postcode":"84047",
    "sg:province":"UT",
    "sg:tags":[
        "establishment"
    ],
    "wof:name":"Perfect Connextions",
    "wof:placetype":"venue"
},
  "geometry": {"coordinates":[-111.890844,40.607981],"type":"Point"}
}