{
  "type": "Feature",
  "properties": {
    "iso:country":"US",
    "sg:address":"3064 Tyler Ave",
    "sg:city":"Ogden",
    "sg:classifiers":[
        {
            "category":"Shopping",
            "subcategory":"Used Merchandise",
            "type":"Retail Goods"
        }
    ],
    "sg:phone":"+1 801 629 0803",
    "sg:postcode":"84403",
    "sg:province":"UT",
    "wof:name":"George T Morrison Enterprises",
    "wof:placetype":"venue"
},
  "geometry": {"coordinates":[-111.945176,41.208084],"type":"Point"}
}