{
  "type": "Feature",
  "properties": {
    "iso:country":"US",
    "sg:address":"2250 N University Pkwy",
    "sg:city":"Provo",
    "sg:classifiers":[
        {
            "category":"Wholesale",
            "subcategory":"Machinery & Supplies",
            "type":"Manufacturing & Wholesale Goods"
        }
    ],
    "sg:phone":"+1 801 375 6555",
    "sg:postcode":"84604",
    "sg:province":"UT",
    "sg:tags":[
        "bookbinder",
        "equipment"
    ],
    "wof:name":"ASMUS Co",
    "wof:placetype":"venue"
},
  "geometry": {"coordinates":[-111.66813999999999,40.263731],"type":"Point"}
}