{
  "type": "Feature",
  "properties": {
    "iso:country":"US",
    "sg:address":"750 E 3000 N",
    "sg:city":"Layton",
    "sg:classifiers":[
        {
            "category":"Home & Garden",
            "subcategory":"Building Materials",
            "type":"Retail Goods"
        }
    ],
    "sg:phone":"+1 801 771 6744",
    "sg:postcode":"84041",
    "sg:province":"UT",
    "sg:tags":[
        "ready",
        "concrete",
        "mfg"
    ],
    "wof:name":"Geneva Rock Products Inc",
    "wof:placetype":"venue"
},
  "geometry": {"coordinates":[-111.950408,41.10243],"type":"Point"}
}