{
  "type": "Feature",
  "properties": {
    "iso:country":"US",
    "sg:address":"885 E 2500 N",
    "sg:city":"Logan",
    "sg:classifiers":[
        {
            "category":"Shopping",
            "subcategory":"Gifts & Souvenirs",
            "type":"Retail Goods"
        }
    ],
    "sg:phone":"+1 435 753 6226",
    "sg:postcode":"84341",
    "sg:province":"UT",
    "wof:name":"Meriettas Fine Porcelain LLC",
    "wof:placetype":"venue"
},
  "geometry": {"coordinates":[-111.81111,41.777866],"type":"Point"}
}