{
  "type": "Feature",
  "properties": {
    "iso:country":"US",
    "sg:address":"975 N Main St",
    "sg:city":"Tooele",
    "sg:classifiers":[
        {
            "category":"Restaurant",
            "type":"Food & Drink"
        }
    ],
    "sg:menulink":"http://www.allmenus.com/ut/tooele-grantsville/192349-wendys/menu/",
    "sg:phone":"+1 435 833 0998",
    "sg:postcode":"84074",
    "sg:province":"UT",
    "sg:tags":[
        "burger",
        "american",
        "soup"
    ],
    "wof:name":"Wendy's",
    "wof:placetype":"venue"
},
  "geometry": {"coordinates":[-112.298123,40.548023],"type":"Point"}
}