{
  "type": "Feature",
  "properties": {
    "iso:country":"US",
    "sg:address":"3596 S 300 W",
    "sg:city":"South Salt Lake",
    "sg:classifiers":[
        {
            "category":"Wholesale",
            "subcategory":"Electrical",
            "type":"Manufacturing & Wholesale Goods"
        }
    ],
    "sg:phone":"+1 801 265 8911",
    "sg:postcode":"84115",
    "sg:province":"UT",
    "sg:tags":[
        "computer",
        "supply",
        "custom",
        "equipment",
        "program",
        "electronic"
    ],
    "wof:name":"Abbey Systems Inc",
    "wof:placetype":"venue"
},
  "geometry": {"coordinates":[-111.899801,40.692175],"type":"Point"}
}