{
  "type": "Feature",
  "properties": {
    "iso:country":"US",
    "sg:address":"251 E 1200 S",
    "sg:city":"Orem",
    "sg:classifiers":[
        {
            "category":"Health Services",
            "subcategory":"Clinic",
            "type":"Services"
        }
    ],
    "sg:phone":"+1 801 226 2255",
    "sg:postcode":"84058",
    "sg:province":"UT",
    "sg:tags":[
        "specialty",
        "outpatient"
    ],
    "wof:name":"Gathering Place The",
    "wof:placetype":"venue"
},
  "geometry": {"coordinates":[-111.689324,40.275224],"type":"Point"}
}