{
  "type": "Feature",
  "properties": {
    "iso:country":"US",
    "sg:address":"12233 Jonathan View Ln",
    "sg:city":"Draper",
    "sg:classifiers":[
        {
            "category":"Professional",
            "subcategory":"Management & Consulting",
            "type":"Services"
        }
    ],
    "sg:phone":"+1 801 571 8944",
    "sg:postcode":"84020",
    "sg:province":"UT",
    "wof:name":"Envision Marketing Services",
    "wof:placetype":"venue"
},
  "geometry": {"coordinates":[-111.916698,40.528224],"type":"Point"}
}