{
  "type": "Feature",
  "properties": {
    "iso:country":"US",
    "sg:address":"1671 N 800 W",
    "sg:city":"Orem",
    "sg:classifiers":[
        {
            "category":"Retail",
            "subcategory":"Laundry & Dry Cleaning",
            "type":"Services"
        }
    ],
    "sg:phone":"+1 801 225 7471",
    "sg:postcode":"84057",
    "sg:province":"UT",
    "sg:tags":[
        "dyeing",
        "commercial",
        "carpet"
    ],
    "wof:name":"Guaranteed Quality Clg LLC",
    "wof:placetype":"venue"
},
  "geometry": {"coordinates":[-111.71532500000001,40.327696],"type":"Point"}
}