{
  "type": "Feature",
  "properties": {
    "iso:country":"US",
    "sg:address":"5078 Gaskill Way",
    "sg:city":"West Jordan",
    "sg:classifiers":[
        {
            "category":"Building & Trades",
            "subcategory":"Construction",
            "type":"Services"
        }
    ],
    "sg:phone":"+1 801 280 5078",
    "sg:postcode":"84088",
    "sg:province":"UT",
    "sg:tags":[
        "house"
    ],
    "wof:name":"Royal Homes",
    "wof:placetype":"venue"
},
  "geometry": {"coordinates":[-112.011478,40.597383],"type":"Point"}
}