{
  "type": "Feature",
  "properties": {
    "iso:country":"US",
    "sg:address":"1330 N 100 E",
    "sg:city":"Pleasant Grove",
    "sg:classifiers":[
        {
            "category":"Freight",
            "type":"Transportation"
        }
    ],
    "sg:phone":"+1 801 785 8663",
    "sg:postcode":"84062",
    "sg:province":"UT",
    "sg:tags":[
        "trucking"
    ],
    "wof:name":"Motor Transport",
    "wof:placetype":"venue"
},
  "geometry": {"coordinates":[-111.73974200000001,40.377938],"type":"Point"}
}