{
  "type": "Feature",
  "properties": {
    "iso:country":"US",
    "sg:address":"445 E 200 S",
    "sg:city":"Salt Lake City",
    "sg:classifiers":[
        {
            "category":"Manufacturing",
            "subcategory":"Retail Goods",
            "type":"Manufacturing & Wholesale Goods"
        }
    ],
    "sg:phone":"+1 801 363 8537",
    "sg:postcode":"84111",
    "sg:province":"UT",
    "sg:tags":[
        "manufacturer"
    ],
    "wof:name":"Technicraft Industries",
    "wof:placetype":"venue"
},
  "geometry": {"coordinates":[-111.878884,40.765079],"type":"Point"}
}