{
  "type": "Feature",
  "properties": {
    "iso:country":"US",
    "sg:address":"3618 W 6000 S",
    "sg:city":"Roy",
    "sg:classifiers":[
        {
            "category":"Health Services",
            "subcategory":"Doctor",
            "type":"Services"
        }
    ],
    "sg:phone":"+1 801 985 3457",
    "sg:postcode":"84067",
    "sg:province":"UT",
    "sg:tags":[
        "medical"
    ],
    "wof:name":"Max Anesthesia Inc",
    "wof:placetype":"venue"
},
  "geometry": {"coordinates":[-112.06813200000001,41.154467],"type":"Point"}
}