{
  "type": "Feature",
  "properties": {
    "iso:country":"US",
    "sg:address":"1480 Orchard Dr",
    "sg:city":"Bountiful",
    "sg:classifiers":[
        {
            "category":"Health Services",
            "subcategory":"Chiropractor",
            "type":"Services"
        }
    ],
    "sg:phone":"+1 801 292 5611",
    "sg:postcode":"84010",
    "sg:province":"UT",
    "wof:name":"Neumann Chiropractic",
    "wof:placetype":"venue"
},
  "geometry": {"coordinates":[-111.87490699999999,40.87548],"type":"Point"}
}