{
  "type": "Feature",
  "properties": {
    "iso:country":"US",
    "sg:address":"1223 N Hwy 40",
    "sg:city":"Heber City",
    "sg:classifiers":[
        {
            "category":"Bars & Pubs",
            "type":"Food & Drink"
        }
    ],
    "sg:phone":"+1 435 654 5532",
    "sg:postcode":"84032",
    "sg:province":"UT",
    "sg:tags":[
        "drinking"
    ],
    "wof:name":"Other End Bar & Grill",
    "wof:placetype":"venue"
},
  "geometry": {"coordinates":[-111.409341,40.530622],"type":"Point"}
}