{
  "type": "Feature",
  "properties": {
    "iso:country":"US",
    "sg:address":"4425 S 500 W",
    "sg:city":"Salt Lake City",
    "sg:classifiers":[
        {
            "category":"Communications",
            "type":"Services"
        }
    ],
    "sg:phone":"+1 801 375 7433",
    "sg:postcode":"84123",
    "sg:province":"UT",
    "wof:name":"Tri Tel Communications Inc",
    "wof:placetype":"venue"
},
  "geometry": {"coordinates":[-111.905372,40.676244],"type":"Point"}
}