{
  "type": "Feature",
  "properties": {
    "iso:country":"US",
    "sg:address":"1154 E 140 N",
    "sg:city":"Lindon",
    "sg:classifiers":[
        {
            "category":"Professional",
            "subcategory":"Accounting & Tax Preparation",
            "type":"Services"
        }
    ],
    "sg:phone":"+1 801 796 9573",
    "sg:postcode":"84042",
    "sg:province":"UT",
    "sg:tags":[
        "accountant"
    ],
    "wof:name":"Pearce Sueann",
    "wof:placetype":"venue"
},
  "geometry": {"coordinates":[-111.688106,40.341446],"type":"Point"}
}