{
  "type": "Feature",
  "properties": {
    "iso:country":"US",
    "sg:address":"1577 S 2250 E",
    "sg:city":"Spanish Fork",
    "sg:classifiers":[
        {
            "category":"Health Services",
            "subcategory":"Doctor",
            "type":"Services"
        }
    ],
    "sg:phone":"+1 801 794 2698",
    "sg:postcode":"84660",
    "sg:province":"UT",
    "sg:tags":[
        "medical"
    ],
    "wof:name":"Business Practice LLC",
    "wof:placetype":"venue"
},
  "geometry": {"coordinates":[-111.616992,40.089226],"type":"Point"}
}