{
  "type": "Feature",
  "properties": {
    "iso:country":"US",
    "sg:address":"250 W 300 N",
    "sg:city":"Roosevelt",
    "sg:classifiers":[
        {
            "category":"Health Services",
            "subcategory":"Doctor",
            "type":"Services"
        }
    ],
    "sg:phone":"+1 435 722 6130",
    "sg:postcode":"84066",
    "sg:province":"UT",
    "sg:tags":[
        "medical"
    ],
    "wof:name":"Lynn Morrill Do",
    "wof:placetype":"venue"
},
  "geometry": {"coordinates":[-109.995975,40.303477],"type":"Point"}
}