{
  "type": "Feature",
  "properties": {
    "iso:country":"US",
    "sg:address":"890 E Sage Cir",
    "sg:city":"Pleasant Grove",
    "sg:classifiers":[
        {
            "category":"Building & Trades",
            "subcategory":"Construction",
            "type":"Services"
        }
    ],
    "sg:phone":"+1 801 990 1843",
    "sg:postcode":"84062",
    "sg:province":"UT",
    "sg:tags":[
        "concrete",
        "contractor"
    ],
    "wof:name":"Decorative Concrete Sys",
    "wof:placetype":"venue"
},
  "geometry": {"coordinates":[-111.71865,40.373223],"type":"Point"}
}