{
  "type": "Feature",
  "properties": {
    "iso:country":"US",
    "sg:address":"136 Heber Ave",
    "sg:city":"Park City",
    "sg:classifiers":[
        {
            "category":"Restaurant",
            "type":"Food & Drink"
        }
    ],
    "sg:menulink":"http://www.allmenus.com/ut/park-city/15371-jean-louis-restaurant/menu/",
    "sg:phone":"+1 435 200 0260",
    "sg:postcode":"84060",
    "sg:province":"UT",
    "sg:tags":[
        "french"
    ],
    "wof:name":"Jean Louis Restaurant",
    "wof:placetype":"venue"
},
  "geometry": {"coordinates":[-111.496837,40.64629],"type":"Point"}
}