{
  "type": "Feature",
  "properties": {
    "iso:country":"US",
    "sg:address":"115 N 1200 W",
    "sg:city":"Orem",
    "sg:classifiers":[
        {
            "category":"Home & Garden",
            "subcategory":"Building Materials",
            "type":"Retail Goods"
        }
    ],
    "sg:phone":"+1 801 225 1155",
    "sg:postcode":"84057",
    "sg:province":"UT",
    "sg:tags":[
        "paint",
        "supply"
    ],
    "wof:name":"Auto Body Supply Of Orem",
    "wof:placetype":"venue"
},
  "geometry": {"coordinates":[-111.724349,40.297769],"type":"Point"}
}