{
  "type": "Feature",
  "properties": {
    "iso:country":"US",
    "sg:address":"2250 S Redwood Rd",
    "sg:city":"Salt Lake City",
    "sg:classifiers":[
        {
            "category":"Banks & Credit Unions",
            "subcategory":"Bank",
            "type":"Services"
        }
    ],
    "sg:phone":"+1 801 579 6353",
    "sg:postcode":"84119",
    "sg:province":"UT",
    "sg:tags":[
        "state"
    ],
    "wof:name":"Wasatch Mountain Federal Cr Un",
    "wof:placetype":"venue"
},
  "geometry": {"coordinates":[-111.93904000000001,40.721619],"type":"Point"}
}