{
  "type": "Feature",
  "properties": {
    "iso:country":"US",
    "sg:address":"1596 N 400 W",
    "sg:city":"Layton",
    "sg:classifiers":[
        {
            "category":"Manufacturing",
            "subcategory":"Printing",
            "type":"Manufacturing & Wholesale Goods"
        }
    ],
    "sg:phone":"+1 801 773 3360",
    "sg:postcode":"84041",
    "sg:province":"UT",
    "sg:tags":[
        "directory",
        "publisher",
        "telephone"
    ],
    "wof:name":"Transwestern Publishing",
    "wof:placetype":"venue"
},
  "geometry": {"coordinates":[-111.97337899999999,41.083289],"type":"Point"}
}