{
  "type": "Feature",
  "properties": {
    "iso:country":"US",
    "sg:address":"147 S State St",
    "sg:city":"Salt Lake City",
    "sg:classifiers":[
        {
            "category":"Bars & Pubs",
            "type":"Food & Drink"
        }
    ],
    "sg:phone":"+1 801 532 9327",
    "sg:postcode":"84111",
    "sg:province":"UT",
    "sg:tags":[
        "drinking"
    ],
    "wof:name":"Radio City Lounge",
    "wof:placetype":"venue"
},
  "geometry": {"coordinates":[-111.888153,40.767142],"type":"Point"}
}