{
  "type": "Feature",
  "properties": {
    "iso:country":"US",
    "sg:address":"4010 Glade Hollow Way",
    "sg:city":"Bountiful",
    "sg:classifiers":[
        {
            "category":"Communications",
            "type":"Services"
        }
    ],
    "sg:phone":"+1 801 292 6337",
    "sg:postcode":"84010",
    "sg:province":"UT",
    "sg:tags":[
        "communication"
    ],
    "wof:name":"Archway Communications Inc",
    "wof:placetype":"venue"
},
  "geometry": {"coordinates":[-111.877672,40.846138],"type":"Point"}
}