{
  "type": "Feature",
  "properties": {
    "iso:country":"US",
    "sg:address":"6710 Highland Dr",
    "sg:city":"Salt Lake City",
    "sg:classifiers":[
        {
            "category":"Professional",
            "subcategory":"Business Services",
            "type":"Services"
        }
    ],
    "sg:phone":"+1 801 944 7387",
    "sg:postcode":"84121",
    "sg:province":"UT",
    "wof:name":"K&R Associates Inc",
    "wof:placetype":"venue"
},
  "geometry": {"coordinates":[-111.834051,40.628925],"type":"Point"}
}