{
  "type": "Feature",
  "properties": {
    "iso:country":"US",
    "sg:address":"6250 S 1300 W",
    "sg:city":"Salt Lake City",
    "sg:classifiers":[
        {
            "category":"Professional",
            "subcategory":"Management & Consulting",
            "type":"Services"
        }
    ],
    "sg:phone":"+1 801 268 2424",
    "sg:postcode":"84123",
    "sg:province":"UT",
    "wof:name":"J E Hunt & Associates Inc",
    "wof:placetype":"venue"
},
  "geometry": {"coordinates":[-111.92930800000001,40.634235],"type":"Point"}
}