{
  "type": "Feature",
  "properties": {
    "iso:country":"US",
    "sg:address":"591 W 800 S",
    "sg:city":"Bountiful",
    "sg:classifiers":[
        {
            "category":"Retail",
            "subcategory":"Auto Repair",
            "type":"Services"
        }
    ],
    "sg:phone":"+1 801 292 3111",
    "sg:postcode":"84010",
    "sg:province":"UT",
    "sg:tags":[
        "body",
        "opera",
        "building",
        "nonresidential"
    ],
    "wof:name":"D & M Upholstery",
    "wof:placetype":"venue"
},
  "geometry": {"coordinates":[-111.894803,40.881284],"type":"Point"}
}