{
  "type": "Feature",
  "properties": {
    "iso:country":"US",
    "sg:address":"330 S Fort Ln",
    "sg:city":"Layton",
    "sg:classifiers":[
        {
            "category":"Retail",
            "subcategory":"Auto Repair",
            "type":"Services"
        }
    ],
    "sg:phone":"+1 801 544 4766",
    "sg:postcode":"84041",
    "sg:province":"UT",
    "sg:tags":[
        "automotive",
        "used",
        "automobile"
    ],
    "wof:name":"Hatch Repair Services",
    "wof:placetype":"venue"
},
  "geometry": {"coordinates":[-111.957702,41.055163],"type":"Point"}
}