{
  "type": "Feature",
  "properties": {
    "iso:country":"US",
    "sg:address":"475 N Main St",
    "sg:city":"Alpine",
    "sg:classifiers":[
        {
            "category":"Building & Trades",
            "subcategory":"Cleaning & Sanitation",
            "type":"Services"
        }
    ],
    "sg:phone":"+1 801 763 7520",
    "sg:postcode":"84004",
    "sg:province":"UT",
    "sg:tags":[
        "maintenance"
    ],
    "wof:name":"Thompson Family Enterprises",
    "wof:placetype":"venue"
},
  "geometry": {"coordinates":[-111.777885,40.460526],"type":"Point"}
}