{
  "type": "Feature",
  "properties": {
    "iso:country":"US",
    "sg:address":"1447 N Main St",
    "sg:city":"Spanish Fork",
    "sg:classifiers":[
        {
            "category":"Retail",
            "subcategory":"Auto Repair",
            "type":"Services"
        }
    ],
    "sg:phone":"+1 801 798 1822",
    "sg:postcode":"84660",
    "sg:province":"UT",
    "sg:tags":[
        "repairing",
        "automobile"
    ],
    "wof:name":"Glegg's Auto Repair",
    "wof:placetype":"venue"
},
  "geometry": {"coordinates":[-111.65469400000001,40.128408],"type":"Point"}
}