{
  "type": "Feature",
  "properties": {
    "iso:country":"US",
    "sg:address":"1893 W 2100 S",
    "sg:city":"Ogden",
    "sg:classifiers":[
        {
            "category":"Retail",
            "subcategory":"Auto Repair",
            "type":"Services"
        }
    ],
    "sg:phone":"+1 801 731 6793",
    "sg:postcode":"84401",
    "sg:province":"UT",
    "sg:tags":[
        "automotive"
    ],
    "wof:name":"Lane Wilson Parts and Service",
    "wof:placetype":"venue"
},
  "geometry": {"coordinates":[-112.02077199999999,41.228784],"type":"Point"}
}