{
  "type": "Feature",
  "properties": {
    "iso:country":"US",
    "sg:address":"3055 W 2100 S Expy",
    "sg:city":"Salt Lake City",
    "sg:classifiers":[
        {
            "category":"Professional",
            "subcategory":"Art Services",
            "type":"Services"
        }
    ],
    "sg:phone":"+1 801 908 6122",
    "sg:postcode":"84119",
    "sg:province":"UT",
    "sg:tags":[
        "exhibit",
        "industrial",
        "graphic",
        "design",
        "fabrication"
    ],
    "wof:name":"Exhibit Center LLC",
    "wof:placetype":"venue"
},
  "geometry": {"coordinates":[-111.963779,40.726285],"type":"Point"}
}