{
  "type": "Feature",
  "properties": {
    "iso:country":"US",
    "sg:address":"4274 S 1500 E",
    "sg:city":"Vernal",
    "sg:classifiers":[
        {
            "category":"Retail",
            "subcategory":"Repair Shop",
            "type":"Services"
        }
    ],
    "sg:phone":"+1 435 789 6613",
    "sg:postcode":"84078",
    "sg:province":"UT",
    "sg:tags":[
        "horseshoeing"
    ],
    "wof:name":"Glen Harrison",
    "wof:placetype":"venue"
},
  "geometry": {"coordinates":[-109.498891,40.39345],"type":"Point"}
}