{
  "type": "Feature",
  "properties": {
    "iso:country":"US",
    "sg:address":"30 E 100 S",
    "sg:city":"Salt Lake City",
    "sg:classifiers":[
        {
            "category":"Banks & Credit Unions",
            "subcategory":"Investment Brokerage",
            "type":"Services"
        }
    ],
    "sg:phone":"+1 801 333 3140",
    "sg:postcode":"84111",
    "sg:province":"UT",
    "sg:tags":[
        "stock",
        "bond"
    ],
    "sg:website":"www.dadco.com",
    "wof:name":"D A Davidson & Co",
    "wof:placetype":"venue"
},
  "geometry": {"coordinates":[-111.89060600000001,40.767099],"type":"Point"}
}