{
  "type": "Feature",
  "properties": {
    "iso:country":"US",
    "sg:address":"7648 Thomas Cir",
    "sg:city":"West Jordan",
    "sg:classifiers":[
        {
            "category":"Insurance",
            "subcategory":"Insurance Agent",
            "type":"Services"
        }
    ],
    "sg:phone":"+1 801 562 5362",
    "sg:postcode":"84084",
    "sg:province":"UT",
    "sg:tags":[
        "broker"
    ],
    "wof:name":"Bresnahan & Associates",
    "wof:placetype":"venue"
},
  "geometry": {"coordinates":[-111.959875,40.612611],"type":"Point"}
}