{
  "type": "Feature",
  "properties": {
    "iso:country":"US",
    "sg:address":"2825 Cottonwood Pkwy",
    "sg:city":"Salt Lake City",
    "sg:classifiers":[
        {
            "category":"Professional",
            "subcategory":"Business Services",
            "type":"Services"
        }
    ],
    "sg:phone":"+1 801 990 3284",
    "sg:postcode":"84121",
    "sg:province":"UT",
    "wof:name":"Patriot Inc",
    "wof:placetype":"venue"
},
  "geometry": {"coordinates":[-111.811212,40.632768],"type":"Point"}
}