{
  "type": "Feature",
  "properties": {
    "iso:country":"US",
    "sg:address":"5019 E Meadows Dr",
    "sg:city":"Park City",
    "sg:classifiers":[
        {
            "category":"Professional",
            "subcategory":"Management & Consulting",
            "type":"Services"
        }
    ],
    "sg:phone":"+1 435 649 0365",
    "sg:postcode":"84098",
    "sg:province":"UT",
    "wof:name":"Rcb Management",
    "wof:placetype":"venue"
},
  "geometry": {"coordinates":[-111.53795599999999,40.706624],"type":"Point"}
}