{
  "type": "Feature",
  "properties": {
    "iso:country":"US",
    "sg:address":"266 E Main St",
    "sg:city":"Lehi",
    "sg:classifiers":[
        {
            "category":"Wholesale",
            "subcategory":"Construction Materials",
            "type":"Manufacturing & Wholesale Goods"
        }
    ],
    "sg:phone":"+1 801 768 4146",
    "sg:postcode":"84043",
    "sg:province":"UT",
    "sg:tags":[
        "granite"
    ],
    "wof:name":"High Country Affordable Cntrtp",
    "wof:placetype":"venue"
},
  "geometry": {"coordinates":[-111.845112,40.387915],"type":"Point"}
}