{
  "type": "Feature",
  "properties": {
    "iso:country":"US",
    "sg:address":"2064 Alexander St",
    "sg:city":"West Valley",
    "sg:classifiers":[
        {
            "category":"Real Estate",
            "subcategory":"Developer",
            "type":"Services"
        }
    ],
    "sg:phone":"+1 801 973 7774",
    "sg:postcode":"84119",
    "sg:province":"UT",
    "wof:name":"Kenner Associates Inc",
    "wof:placetype":"venue"
},
  "geometry": {"coordinates":[-111.94698699999999,40.718438],"type":"Point"}
}