{
  "type": "Feature",
  "properties": {
    "iso:country":"US",
    "sg:address":"44 E 1200 N",
    "sg:city":"Orem",
    "sg:classifiers":[
        {
            "category":"Professional",
            "subcategory":"Business Services",
            "type":"Services"
        }
    ],
    "sg:phone":"+1 801 226 7026",
    "sg:postcode":"84057",
    "sg:province":"UT",
    "wof:name":"Samuel Kamoe Enterprise",
    "wof:placetype":"venue"
},
  "geometry": {"coordinates":[-111.69557399999999,40.319171],"type":"Point"}
}