{
  "type": "Feature",
  "properties": {
    "iso:country":"US",
    "sg:address":"599 Washington Blvd",
    "sg:city":"Ogden",
    "sg:classifiers":[
        {
            "category":"Retail",
            "subcategory":"Laundry & Dry Cleaning",
            "type":"Services"
        }
    ],
    "sg:phone":"+1 801 621 1616",
    "sg:postcode":"84404",
    "sg:province":"UT",
    "sg:tags":[
        "operated",
        "cleaners",
        "coin"
    ],
    "wof:name":"Norge Village",
    "wof:placetype":"venue"
},
  "geometry": {"coordinates":[-111.96973699999999,41.254619],"type":"Point"}
}