{
  "type": "Feature",
  "properties": {
    "iso:country":"US",
    "sg:address":"1335 N 700 W",
    "sg:city":"Mapleton",
    "sg:classifiers":[
        {
            "category":"Building & Trades",
            "subcategory":"Construction",
            "type":"Services"
        }
    ],
    "sg:phone":"+1 801 489 7353",
    "sg:postcode":"84664",
    "sg:province":"UT",
    "sg:tags":[
        "house"
    ],
    "wof:name":"Kyle J Roylance Construct",
    "wof:placetype":"venue"
},
  "geometry": {"coordinates":[-111.58713400000001,40.142302],"type":"Point"}
}