{
  "type": "Feature",
  "properties": {
    "iso:country":"US",
    "sg:address":"1921 N 280 W",
    "sg:city":"Orem",
    "sg:classifiers":[
        {
            "category":"Professional",
            "subcategory":"Business Services",
            "type":"Services"
        }
    ],
    "sg:phone":"+1 801 225 7122",
    "sg:postcode":"84057",
    "sg:province":"UT",
    "wof:name":"Glp Enterprises LLC",
    "wof:placetype":"venue"
},
  "geometry": {"coordinates":[-111.703014,40.331934],"type":"Point"}
}