{
  "type": "Feature",
  "properties": {
    "iso:country":"US",
    "sg:address":"4663 Cherry St",
    "sg:city":"Murray",
    "sg:classifiers":[
        {
            "category":"Professional",
            "subcategory":"Advertising",
            "type":"Services"
        }
    ],
    "sg:phone":"+1 801 264 8330",
    "sg:postcode":"84123",
    "sg:province":"UT",
    "sg:website":"www.ips1.com",
    "wof:name":"IPS-Intermountain Premium",
    "wof:placetype":"venue"
},
  "geometry": {"coordinates":[-111.90404700000001,40.671385],"type":"Point"}
}