{
  "type": "Feature",
  "properties": {
    "iso:country":"US",
    "sg:address":"522 W 2700 S",
    "sg:city":"Syracuse",
    "sg:classifiers":[
        {
            "category":"Education",
            "subcategory":"Special Training",
            "type":"Public Place"
        }
    ],
    "sg:phone":"+1 801 774 0728",
    "sg:postcode":"84075",
    "sg:province":"UT",
    "sg:tags":[
        "center"
    ],
    "wof:name":"Syracuse Montessori",
    "wof:placetype":"venue"
},
  "geometry": {"coordinates":[-112.036495,41.074759],"type":"Point"}
}