{
  "type": "Feature",
  "properties": {
    "iso:country":"US",
    "sg:address":"607 S 100 W",
    "sg:city":"Payson",
    "sg:classifiers":[
        {
            "category":"Personal",
            "subcategory":"Beauty Salon",
            "type":"Services"
        }
    ],
    "sg:phone":"+1 801 465 8267",
    "sg:postcode":"84651",
    "sg:province":"UT",
    "wof:name":"Sunsational Style Salon",
    "wof:placetype":"venue"
},
  "geometry": {"coordinates":[-111.73395499999999,40.03462],"type":"Point"}
}