{
  "type": "Feature",
  "properties": {
    "iso:country":"US",
    "sg:address":"341 S 250 E",
    "sg:city":"Orem",
    "sg:classifiers":[
        {
            "category":"Professional",
            "subcategory":"Business Services",
            "type":"Services"
        }
    ],
    "sg:phone":"+1 801 224 9253",
    "sg:postcode":"84058",
    "sg:province":"UT",
    "wof:name":"Gaelic Enterprises Inc",
    "wof:placetype":"venue"
},
  "geometry": {"coordinates":[-111.68958000000001,40.29081],"type":"Point"}
}