{
  "type": "Feature",
  "properties": {
    "iso:country":"US",
    "sg:address":"3310 S 2700 E",
    "sg:city":"Salt Lake City",
    "sg:classifiers":[
        {
            "category":"Travel",
            "subcategory":"Travel Agent",
            "type":"Entertainment"
        }
    ],
    "sg:phone":"+1 801 485 0505",
    "sg:postcode":"84109",
    "sg:province":"UT",
    "sg:tags":[
        "agency",
        "bureau"
    ],
    "wof:name":"Great Basin Travel",
    "wof:placetype":"venue"
},
  "geometry": {"coordinates":[-111.81502,40.699239],"type":"Point"}
}