{
  "type": "Feature",
  "properties": {
    "iso:country":"US",
    "sg:address":"2157 S 3300 W",
    "sg:city":"Syracuse",
    "sg:classifiers":[
        {
            "category":"Building & Trades",
            "subcategory":"Plumbing",
            "type":"Services"
        }
    ],
    "sg:phone":"+1 801 728 3482",
    "sg:postcode":"84075",
    "sg:province":"UT",
    "sg:tags":[
        "conditioning",
        "air",
        "system",
        "contractor"
    ],
    "wof:name":"Desert Climate Heating & Air C",
    "wof:placetype":"venue"
},
  "geometry": {"coordinates":[-112.089467,41.083668],"type":"Point"}
}