{
  "type": "Feature",
  "properties": {
    "iso:country":"US",
    "sg:address":"1358 S West Temple",
    "sg:city":"Salt Lake City",
    "sg:classifiers":[
        {
            "category":"Manufacturing",
            "subcategory":"Printing",
            "type":"Manufacturing & Wholesale Goods"
        }
    ],
    "sg:phone":"+1 801 485 8894",
    "sg:postcode":"84115",
    "sg:province":"UT",
    "sg:tags":[
        "publisher"
    ],
    "wof:name":"Utah Lighthouse Ministry",
    "wof:placetype":"venue"
},
  "geometry": {"coordinates":[-111.89401599999999,40.741365],"type":"Point"}
}