{
  "type": "Feature",
  "properties": {
    "iso:country":"US",
    "sg:address":"4205 W 3550 S",
    "sg:city":"West Valley",
    "sg:classifiers":[
        {
            "category":"Professional",
            "subcategory":"Computer Services",
            "type":"Services"
        }
    ],
    "sg:phone":"+1 801 243 7555",
    "sg:postcode":"84120",
    "sg:province":"UT",
    "sg:tags":[
        "repair"
    ],
    "wof:name":"P C Care Plus",
    "wof:placetype":"venue"
},
  "geometry": {"coordinates":[-111.992299,40.694249],"type":"Point"}
}