{
  "type": "Feature",
  "properties": {
    "iso:country":"US",
    "sg:address":"5624 S 1900 W",
    "sg:city":"Salt Lake City",
    "sg:classifiers":[
        {
            "category":"Real Estate",
            "subcategory":"Real Estate Operator",
            "type":"Services"
        }
    ],
    "sg:phone":"+1 801 968 2639",
    "sg:postcode":"84118",
    "sg:province":"UT",
    "sg:tags":[
        "apartment"
    ],
    "wof:name":"Summerwood Apartments",
    "wof:placetype":"venue"
},
  "geometry": {"coordinates":[-111.943237,40.648454],"type":"Point"}
}