{
  "type": "Feature",
  "properties": {
    "iso:country":"US",
    "sg:address":"1315 Riverside Ave",
    "sg:city":"Provo",
    "sg:classifiers":[
        {
            "category":"Wholesale",
            "subcategory":"Stationery",
            "type":"Manufacturing & Wholesale Goods"
        }
    ],
    "sg:phone":"+1 801 355 0642",
    "sg:postcode":"84604",
    "sg:province":"UT",
    "sg:tags":[
        "personal",
        "industrial",
        "paper"
    ],
    "wof:name":"Rocky Mountain Market Area",
    "wof:placetype":"venue"
},
  "geometry": {"coordinates":[-111.671173,40.250535],"type":"Point"}
}