{
  "type": "Feature",
  "properties": {
    "iso:country":"US",
    "sg:address":"1879 Lincoln St",
    "sg:city":"Salt Lake City",
    "sg:classifiers":[
        {
            "category":"Communications",
            "subcategory":"Film & Video Production",
            "type":"Services"
        }
    ],
    "sg:phone":"+1 801 487 5357",
    "sg:postcode":"84105",
    "sg:province":"UT",
    "sg:tags":[
        "motion"
    ],
    "wof:name":"Km Productions LLC",
    "wof:placetype":"venue"
},
  "geometry": {"coordinates":[-111.863793,40.729107],"type":"Point"}
}