{
  "type": "Feature",
  "properties": {
    "iso:country":"US",
    "sg:address":"628 N 1300 E",
    "sg:city":"St George",
    "sg:classifiers":[
        {
            "category":"Wholesale",
            "subcategory":"Hardware",
            "type":"Manufacturing & Wholesale Goods"
        }
    ],
    "sg:phone":"+1 435 628 5259",
    "sg:postcode":"84770",
    "sg:province":"UT",
    "wof:name":"Gustave A Larson Company",
    "wof:placetype":"venue"
},
  "geometry": {"coordinates":[-113.556442,37.117544],"type":"Point"}
}