{
  "type": "Feature",
  "properties": {
    "iso:country":"US",
    "sg:address":"3509 N 2225 E",
    "sg:city":"Layton",
    "sg:classifiers":[
        {
            "category":"Wholesale",
            "subcategory":"Vending Machines",
            "type":"Manufacturing & Wholesale Goods"
        }
    ],
    "sg:phone":"+1 801 774 9523",
    "sg:postcode":"84040",
    "sg:province":"UT",
    "sg:tags":[
        "operator"
    ],
    "wof:name":"Global Vending LLC",
    "wof:placetype":"venue"
},
  "geometry": {"coordinates":[-111.923265,41.111118],"type":"Point"}
}