{
  "type": "Feature",
  "properties": {
    "iso:country":"US",
    "sg:address":"300 N 400 E",
    "sg:city":"Logan",
    "sg:classifiers":[
        {
            "category":"Organizations",
            "subcategory":"Religious Organization",
            "type":"Services"
        }
    ],
    "sg:phone":"+1 435 755 5517",
    "sg:postcode":"84321",
    "sg:province":"UT",
    "sg:tags":[
        "mormon",
        "church"
    ],
    "wof:name":"Logan Seventeenth Ward",
    "wof:placetype":"venue"
},
  "geometry": {"coordinates":[-111.824456,41.737709],"type":"Point"}
}