{
  "type": "Feature",
  "properties": {
    "iso:country":"US",
    "sg:address":"498 E Howard Dr",
    "sg:city":"Sandy",
    "sg:classifiers":[
        {
            "category":"Manufacturing",
            "subcategory":"Signs",
            "type":"Manufacturing & Wholesale Goods"
        }
    ],
    "sg:phone":"+1 801 576 0448",
    "sg:postcode":"84070",
    "sg:province":"UT",
    "sg:tags":[
        "specialty",
        "mfg"
    ],
    "wof:name":"Flags For All Reasons",
    "wof:placetype":"venue"
},
  "geometry": {"coordinates":[-111.878557,40.578766],"type":"Point"}
}