{
  "type": "Feature",
  "properties": {
    "iso:country":"US",
    "sg:address":"1066 Pioneer Rd",
    "sg:city":"Salt Lake City",
    "sg:classifiers":[
        {
            "category":"Building & Trades",
            "subcategory":"Equipment Rental",
            "type":"Services"
        }
    ],
    "sg:phone":"+1 801 975 0742",
    "sg:postcode":"84104",
    "sg:province":"UT",
    "wof:name":"Safety-Kleen",
    "wof:placetype":"venue"
},
  "geometry": {"coordinates":[-111.958134,40.741433],"type":"Point"}
}