{
  "type": "Feature",
  "properties": {
    "iso:country":"US",
    "sg:address":"2681 Parleys Way",
    "sg:city":"Salt Lake City",
    "sg:classifiers":[
        {
            "category":"Health Services",
            "subcategory":"Health Practitioner",
            "type":"Services"
        }
    ],
    "sg:phone":"+1 801 364 2779",
    "sg:postcode":"84109",
    "sg:province":"UT",
    "sg:tags":[
        "psychologist"
    ],
    "wof:name":"Daniel P Sternberg",
    "wof:placetype":"venue"
},
  "geometry": {"coordinates":[-111.814187,40.718922],"type":"Point"}
}