{
  "type": "Feature",
  "properties": {
    "iso:country":"US",
    "sg:address":"45 S 1300 E",
    "sg:city":"Logan",
    "sg:classifiers":[
        {
            "category":"Real Estate",
            "subcategory":"Real Estate Operator",
            "type":"Services"
        }
    ],
    "sg:phone":"+1 435 752 6365",
    "sg:postcode":"84321",
    "sg:province":"UT",
    "sg:tags":[
        "building",
        "nonresidential"
    ],
    "wof:name":"Heninger Family Properties LLC",
    "wof:placetype":"venue"
},
  "geometry": {"coordinates":[-111.801473,41.731102],"type":"Point"}
}