{
  "type": "Feature",
  "properties": {
    "iso:country":"US",
    "sg:address":"2465 S 1200 W",
    "sg:city":"Syracuse",
    "sg:classifiers":[
        {
            "category":"Building & Trades",
            "subcategory":"Construction",
            "type":"Services"
        }
    ],
    "sg:phone":"+1 801 779 1700",
    "sg:postcode":"84075",
    "sg:province":"UT",
    "sg:tags":[
        "general",
        "contractor"
    ],
    "wof:name":"Rainey Construction Inc",
    "wof:placetype":"venue"
},
  "geometry": {"coordinates":[-112.049289,41.077126],"type":"Point"}
}