{
  "type": "Feature",
  "properties": {
    "iso:country":"US",
    "sg:address":"45 W 100 N",
    "sg:city":"Price",
    "sg:classifiers":[
        {
            "category":"Shopping",
            "type":"Retail Goods"
        }
    ],
    "sg:phone":"+1 435 637 4400",
    "sg:postcode":"84501",
    "sg:province":"UT",
    "sg:tags":[
        "monument"
    ],
    "wof:name":"Morris Worley Monument Sales",
    "wof:placetype":"venue"
},
  "geometry": {"coordinates":[-110.812404,39.600908],"type":"Point"}
}