{
  "type": "Feature",
  "properties": {
    "iso:country":"US",
    "sg:address":"860 E 4500 S",
    "sg:city":"Salt Lake City",
    "sg:classifiers":[
        {
            "category":"Personal",
            "type":"Services"
        }
    ],
    "sg:phone":"+1 801 355 3995",
    "sg:postcode":"84107",
    "sg:province":"UT",
    "sg:tags":[
        "therapist",
        "massage"
    ],
    "wof:name":"Allen Raab Licensed Massage",
    "wof:placetype":"venue"
},
  "geometry": {"coordinates":[-111.86555199999999,40.67423],"type":"Point"}
}