{
  "type": "Feature",
  "properties": {
    "iso:country":"US",
    "sg:address":"1261 Capistrano Dr",
    "sg:city":"Salt Lake City",
    "sg:classifiers":[
        {
            "category":"Shopping",
            "subcategory":"Discount & Variety Stores",
            "type":"Retail Goods"
        }
    ],
    "sg:phone":"+1 801 792 0939",
    "sg:postcode":"84116",
    "sg:province":"UT",
    "sg:tags":[
        "sales",
        "merchandise"
    ],
    "wof:name":"C & F",
    "wof:placetype":"venue"
},
  "geometry": {"coordinates":[-111.92397800000001,40.796342],"type":"Point"}
}