{
  "type": "Feature",
  "properties": {
    "iso:country":"US",
    "sg:address":"902 E 2700 S",
    "sg:city":"Salt Lake City",
    "sg:classifiers":[
        {
            "category":"Food & Beverages",
            "subcategory":"Bakery",
            "type":"Retail Goods"
        }
    ],
    "sg:phone":"+1 801 467 7291",
    "sg:postcode":"84106",
    "sg:province":"UT",
    "sg:tags":[
        "product",
        "baker",
        "mfg"
    ],
    "sg:website":"www.granitebridal.com",
    "wof:name":"Granite Bakery Inc",
    "wof:placetype":"venue"
},
  "geometry": {"coordinates":[-111.863705,40.712597],"type":"Point"}
}