{
  "type": "Feature",
  "properties": {
    "iso:country":"US",
    "sg:address":"33 Allegiance Cir",
    "sg:city":"Evanston",
    "sg:classifiers":[
        {
            "category":"Government",
            "subcategory":"Office",
            "type":"Public Place"
        }
    ],
    "sg:phone":"+1 307 783 6470",
    "sg:postcode":"82930",
    "sg:province":"UT",
    "sg:tags":[
        "city",
        "planning",
        "dev"
    ],
    "wof:name":"Evanston Community Development",
    "wof:placetype":"venue"
},
  "geometry": {"coordinates":[-110.992018,41.261795],"type":"Point"}
}