{
  "type": "Feature",
  "properties": {
    "iso:country":"US",
    "sg:address":"1290 S 500 W",
    "sg:city":"Woods Cross",
    "sg:classifiers":[
        {
            "category":"Retail",
            "subcategory":"Auto Rental",
            "type":"Services"
        }
    ],
    "sg:phone":"+1 801 294 5716",
    "sg:postcode":"84010",
    "sg:province":"UT",
    "sg:tags":[
        "renting",
        "automobile"
    ],
    "wof:name":"Hertz Rent A Car",
    "wof:placetype":"venue"
},
  "geometry": {"coordinates":[-111.892313,40.877281],"type":"Point"}
}