{
  "type": "Feature",
  "properties": {
    "iso:country":"US",
    "sg:address":"1935 W 4700 S",
    "sg:city":"Kearns",
    "sg:classifiers":[
        {
            "category":"Shopping",
            "subcategory":"Books",
            "type":"Retail Goods"
        }
    ],
    "sg:phone":"+1 801 966 5800",
    "sg:postcode":"84118",
    "sg:province":"UT",
    "sg:tags":[
        "dealer"
    ],
    "wof:name":"P J's College Books",
    "wof:placetype":"venue"
},
  "geometry": {"coordinates":[-111.93924199999999,40.667578],"type":"Point"}
}