{
  "type": "Feature",
  "properties": {
    "iso:country":"US",
    "sg:address":"898 S State St",
    "sg:city":"Orem",
    "sg:classifiers":[
        {
            "category":"Professional",
            "subcategory":"Business Services",
            "type":"Services"
        }
    ],
    "sg:phone":"+1 801 225 2322",
    "sg:postcode":"84097",
    "sg:province":"UT",
    "sg:tags":[
        "appraiser"
    ],
    "wof:name":"Scott J Bartlome & Co",
    "wof:placetype":"venue"
},
  "geometry": {"coordinates":[-111.687838,40.280851],"type":"Point"}
}