{
  "type": "Feature",
  "properties": {
    "iso:country":"US",
    "sg:address":"5655 W 5960 S",
    "sg:city":"Salt Lake City",
    "sg:classifiers":[
        {
            "category":"Building & Trades",
            "subcategory":"Construction",
            "type":"Services"
        }
    ],
    "sg:phone":"+1 801 955 7083",
    "sg:postcode":"84118",
    "sg:province":"UT",
    "sg:tags":[
        "contractor"
    ],
    "wof:name":"Macs Fencing LLC",
    "wof:placetype":"venue"
},
  "geometry": {"coordinates":[-112.025645,40.643014],"type":"Point"}
}