{
  "type": "Feature",
  "properties": {
    "iso:country":"US",
    "sg:address":"3603 W Main St",
    "sg:city":"Vernal",
    "sg:classifiers":[
        {
            "category":"Building & Trades",
            "subcategory":"Construction",
            "type":"Services"
        }
    ],
    "sg:phone":"+1 435 781 6564",
    "sg:postcode":"84078",
    "sg:province":"UT",
    "wof:name":"Uintah Basin Technologies LLC",
    "wof:placetype":"venue"
},
  "geometry": {"coordinates":[-109.597725,40.455325],"type":"Point"}
}