{
  "type": "Feature",
  "properties": {
    "iso:country":"US",
    "sg:address":"1825 Mountain Springs Pkwy",
    "sg:city":"Springville",
    "sg:classifiers":[
        {
            "category":"Building & Trades",
            "subcategory":"Construction",
            "type":"Services"
        }
    ],
    "sg:phone":"+1 801 491 8898",
    "sg:postcode":"84663",
    "sg:province":"UT",
    "sg:tags":[
        "excavating",
        "contractor"
    ],
    "wof:name":"Van Con",
    "wof:placetype":"venue"
},
  "geometry": {"coordinates":[-111.637337,40.185119],"type":"Point"}
}