{
  "type": "Feature",
  "properties": {
    "iso:country":"US",
    "sg:address":"963 Creekhill Ln",
    "sg:city":"Midvale",
    "sg:classifiers":[
        {
            "category":"Shopping",
            "subcategory":"Computers & Home Electronics",
            "type":"Retail Goods"
        }
    ],
    "sg:phone":"+1 801 255 4928",
    "sg:postcode":"84047",
    "sg:province":"UT",
    "sg:tags":[
        "publishing"
    ],
    "wof:name":"Key Word Publishing",
    "wof:placetype":"venue"
},
  "geometry": {"coordinates":[-111.86357099999999,40.618042],"type":"Point"}
}