{
  "type": "Feature",
  "properties": {
    "iso:country":"US",
    "sg:address":"1676 Progress Way",
    "sg:city":"Tooele",
    "sg:classifiers":[
        {
            "category":"Retail",
            "subcategory":"Auto Repair",
            "type":"Services"
        }
    ],
    "sg:phone":"+1 435 882 0313",
    "sg:postcode":"84074",
    "sg:province":"UT",
    "sg:tags":[
        "repairing",
        "automobile"
    ],
    "wof:name":"Bob's Garage & Diesel",
    "wof:placetype":"venue"
},
  "geometry": {"coordinates":[-112.294881,40.564243],"type":"Point"}
}