{
  "type": "Feature",
  "properties": {
    "iso:country":"US",
    "sg:address":"511 W Main St",
    "sg:city":"Vernal",
    "sg:classifiers":[
        {
            "category":"Shopping",
            "subcategory":"Bicycles & Sporting Goods",
            "type":"Retail Goods"
        }
    ],
    "sg:phone":"+1 435 789 2199",
    "sg:postcode":"84078",
    "sg:province":"UT",
    "sg:website":"www.basinsports.com",
    "wof:name":"Basin Sports",
    "wof:placetype":"venue"
},
  "geometry": {"coordinates":[-109.539646,40.45551],"type":"Point"}
}