{
  "type": "Feature",
  "properties": {
    "iso:country":"US",
    "sg:address":"2070 Wall Ave",
    "sg:city":"Ogden",
    "sg:classifiers":[
        {
            "category":"Building & Trades",
            "subcategory":"Construction",
            "type":"Services"
        }
    ],
    "sg:phone":"+1 801 621 3571",
    "sg:postcode":"84401",
    "sg:province":"UT",
    "sg:tags":[
        "fire",
        "restoration",
        "damage"
    ],
    "sg:website":"www.utdk.com",
    "wof:name":"Utah Disaster Kleenup",
    "wof:placetype":"venue"
},
  "geometry": {"coordinates":[-111.97857399999999,41.229405],"type":"Point"}
}