{
  "type": "Feature",
  "properties": {
    "iso:country":"US",
    "sg:address":"1012 E 1100 S",
    "sg:city":"Spanish Fork",
    "sg:classifiers":[
        {
            "category":"Professional",
            "subcategory":"Computer Services",
            "type":"Services"
        }
    ],
    "sg:phone":"+1 801 798 1089",
    "sg:postcode":"84660",
    "sg:province":"UT",
    "sg:tags":[
        "related"
    ],
    "wof:name":"Data Safe",
    "wof:placetype":"venue"
},
  "geometry": {"coordinates":[-111.63637,40.0952],"type":"Point"}
}