{
  "type": "Feature",
  "properties": {
    "iso:country":"US",
    "sg:address":"1216 Wasatch Dr",
    "sg:city":"Salt Lake City",
    "sg:classifiers":[
        {
            "category":"Building & Trades",
            "subcategory":"Construction",
            "type":"Services"
        }
    ],
    "sg:phone":"+1 801 583 9451",
    "sg:postcode":"84108",
    "sg:province":"UT",
    "sg:tags":[
        "tennis",
        "court"
    ],
    "wof:name":"Coach Mike's Tennis Court Co",
    "wof:placetype":"venue"
},
  "geometry": {"coordinates":[-111.820387,40.746911],"type":"Point"}
}