{
  "type": "Feature",
  "properties": {
    "iso:country":"US",
    "sg:address":"1471 Pioneer Rd",
    "sg:city":"Salt Lake City",
    "sg:classifiers":[
        {
            "category":"Wholesale",
            "subcategory":"Non-durable Goods",
            "type":"Manufacturing & Wholesale Goods"
        }
    ],
    "sg:phone":"+1 801 886 0770",
    "sg:postcode":"84104",
    "sg:province":"UT",
    "wof:name":"Anastasia Fine Imports",
    "wof:placetype":"venue"
},
  "geometry": {"coordinates":[-111.95796300000001,40.738912],"type":"Point"}
}