{
  "type": "Feature",
  "properties": {
    "iso:country":"US",
    "sg:address":"8777 Helen Dr",
    "sg:city":"Magna",
    "sg:classifiers":[
        {
            "category":"Building & Trades",
            "subcategory":"Construction",
            "type":"Services"
        }
    ],
    "sg:phone":"+1 801 250 4441",
    "sg:postcode":"84044",
    "sg:province":"UT",
    "sg:tags":[
        "contractor"
    ],
    "wof:name":"Sharp Aluminum",
    "wof:placetype":"venue"
},
  "geometry": {"coordinates":[-112.10003,40.702056],"type":"Point"}
}