{
  "type": "Feature",
  "properties": {
    "iso:country":"US",
    "sg:address":"2324 Myers Ln",
    "sg:city":"Riverton",
    "sg:phone":"+1 801 254 4638",
    "sg:postcode":"84065",
    "sg:province":"UT",
    "sg:tags":[
        "farm",
        "grain",
        "cash"
    ],
    "wof:name":"Rindlesbach Farms",
    "wof:placetype":"venue"
},
  "geometry": {"coordinates":[-111.95010000000001,40.536941],"type":"Point"}
}