{
  "type": "Feature",
  "properties": {
    "iso:country":"US",
    "sg:address":"2724 S 3600 W",
    "sg:city":"Salt Lake City",
    "sg:classifiers":[
        {
            "category":"Freight",
            "type":"Transportation"
        }
    ],
    "sg:phone":"+1 801 955 9792",
    "sg:postcode":"84119",
    "sg:province":"UT",
    "sg:tags":[
        "arrangement"
    ],
    "wof:name":"Landstar",
    "wof:placetype":"venue"
},
  "geometry": {"coordinates":[-111.977217,40.710776],"type":"Point"}
}