{
  "type": "Feature",
  "properties": {
    "iso:country":"US",
    "sg:address":"1270 W 1480 N",
    "sg:city":"Orem",
    "sg:classifiers":[
        {
            "category":"Building & Trades",
            "subcategory":"Construction",
            "type":"Services"
        }
    ],
    "sg:phone":"+1 801 916 8445",
    "sg:postcode":"84057",
    "sg:province":"UT",
    "sg:tags":[
        "residential"
    ],
    "wof:name":"Tate Cnstr & Remodel LLC",
    "wof:placetype":"venue"
},
  "geometry": {"coordinates":[-111.725711,40.324255],"type":"Point"}
}