{
  "type": "Feature",
  "properties": {
    "iso:country":"US",
    "sg:address":"115 E 320 N",
    "sg:city":"Salem",
    "sg:classifiers":[
        {
            "category":"Wholesale",
            "subcategory":"Machinery & Supplies",
            "type":"Manufacturing & Wholesale Goods"
        }
    ],
    "sg:phone":"+1 801 423 8080",
    "sg:postcode":"84653",
    "sg:province":"UT",
    "sg:tags":[
        "equipment",
        "mining"
    ],
    "sg:website":"www.knotts-co.com",
    "wof:name":"Knotts & Co",
    "wof:placetype":"venue"
},
  "geometry": {"coordinates":[-111.67057200000001,40.059477],"type":"Point"}
}