{
  "type": "Feature",
  "properties": {
    "iso:country":"US",
    "sg:address":"21 S Main St",
    "sg:city":"Tropic",
    "sg:classifiers":[
        {
            "category":"Travel",
            "subcategory":"Hotels & Motels",
            "type":"Entertainment"
        }
    ],
    "sg:phone":"+1 435 679 8998",
    "sg:postcode":"84776",
    "sg:province":"UT",
    "wof:name":"Bybee's Steppingstone Motel",
    "wof:placetype":"venue"
},
  "geometry": {"coordinates":[-112.081778,37.622738],"type":"Point"}
}