{
  "type": "Feature",
  "properties": {
    "iso:country":"US",
    "sg:address":"295 E 2600 N",
    "sg:city":"Lehi",
    "sg:classifiers":[
        {
            "category":"Real Estate",
            "subcategory":"Real Estate Agent",
            "type":"Services"
        }
    ],
    "sg:phone":"+1 801 768 0921",
    "sg:postcode":"84043",
    "sg:province":"UT",
    "wof:name":"Keith Nickle Appraisal Inc",
    "wof:placetype":"venue"
},
  "geometry": {"coordinates":[-111.84370699999999,40.420795],"type":"Point"}
}