{
  "type": "Feature",
  "properties": {
    "iso:country":"US",
    "sg:address":"537 N 700 E",
    "sg:city":"Logan",
    "sg:classifiers":[
        {
            "category":"Building & Trades",
            "subcategory":"Construction",
            "type":"Services"
        }
    ],
    "sg:phone":"+1 435 752 7300",
    "sg:postcode":"84321",
    "sg:province":"UT",
    "sg:tags":[
        "general",
        "contractor"
    ],
    "wof:name":"Evergreen Up Construction",
    "wof:placetype":"venue"
},
  "geometry": {"coordinates":[-111.816771,41.74188],"type":"Point"}
}