{
  "type": "Feature",
  "properties": {
    "iso:country":"US",
    "sg:address":"3691 Santa Anita Dr",
    "sg:city":"St George",
    "sg:classifiers":[
        {
            "category":"Building & Trades",
            "subcategory":"Construction",
            "type":"Services"
        }
    ],
    "sg:phone":"+1 435 986 9911",
    "sg:postcode":"84790",
    "sg:province":"UT",
    "sg:tags":[
        "residential"
    ],
    "wof:name":"Excel Land Development",
    "wof:placetype":"venue"
},
  "geometry": {"coordinates":[-113.59395600000001,37.043776],"type":"Point"}
}