{
  "type": "Feature",
  "properties": {
    "iso:country":"US",
    "sg:address":"310 N Draper Ln",
    "sg:city":"Provo",
    "sg:classifiers":[
        {
            "category":"Manufacturing",
            "subcategory":"Metals",
            "type":"Manufacturing & Wholesale Goods"
        }
    ],
    "sg:phone":"+1 801 377 6200",
    "sg:postcode":"84601",
    "sg:province":"UT",
    "sg:tags":[
        "coating"
    ],
    "wof:name":"Durakote",
    "wof:placetype":"venue"
},
  "geometry": {"coordinates":[-111.68321899999999,40.234818],"type":"Point"}
}