{
  "type": "Feature",
  "properties": {
    "iso:country":"US",
    "sg:address":"10450 S State St",
    "sg:city":"Sandy",
    "sg:classifiers":[
        {
            "category":"Personal",
            "subcategory":"Beauty Salon",
            "type":"Services"
        }
    ],
    "sg:phone":"+1 801 571 8981",
    "sg:postcode":"84070",
    "sg:province":"UT",
    "sg:tags":[
        "unisex",
        "hair"
    ],
    "wof:name":"Regis Salons",
    "wof:placetype":"venue"
},
  "geometry": {"coordinates":[-111.890871,40.560326],"type":"Point"}
}