{
  "type": "Feature",
  "properties": {
    "iso:country":"US",
    "sg:address":"1773 Wilford Dr",
    "sg:city":"Kaysville",
    "sg:classifiers":[
        {
            "category":"Professional",
            "subcategory":"Employment Agencies",
            "type":"Services"
        }
    ],
    "sg:phone":"+1 801 546 2969",
    "sg:postcode":"84037",
    "sg:province":"UT",
    "sg:tags":[
        "opportunity"
    ],
    "wof:name":"Boss Temporary Svc Inc",
    "wof:placetype":"venue"
},
  "geometry": {"coordinates":[-111.94327,41.008451],"type":"Point"}
}