{
  "type": "Feature",
  "properties": {
    "iso:country":"US",
    "sg:address":"4981 Viewmont Cir",
    "sg:city":"Salt Lake City",
    "sg:classifiers":[
        {
            "category":"Wholesale",
            "subcategory":"Vending Machines",
            "type":"Manufacturing & Wholesale Goods"
        }
    ],
    "sg:phone":"+1 801 272 7848",
    "sg:postcode":"84117",
    "sg:province":"UT",
    "sg:tags":[
        "operator"
    ],
    "wof:name":"Vending West",
    "wof:placetype":"venue"
},
  "geometry": {"coordinates":[-111.822801,40.661597],"type":"Point"}
}