{
  "type": "Feature",
  "properties": {
    "iso:country":"US",
    "sg:address":"5959 Old Fashion Pl",
    "sg:city":"Salt Lake City",
    "sg:classifiers":[
        {
            "category":"Real Estate",
            "subcategory":"Real Estate Agent",
            "type":"Services"
        }
    ],
    "sg:phone":"+1 801 262 2752",
    "sg:postcode":"84123",
    "sg:province":"UT",
    "sg:tags":[
        "appraiser"
    ],
    "wof:name":"Pullan Appraisal Svc",
    "wof:placetype":"venue"
},
  "geometry": {"coordinates":[-111.935658,40.642854],"type":"Point"}
}