{
  "type": "Feature",
  "properties": {
    "iso:country":"US",
    "sg:address":"5047 Cree Dr",
    "sg:city":"Salt Lake City",
    "sg:classifiers":[
        {
            "category":"Retail",
            "subcategory":"Repair Shop",
            "type":"Services"
        }
    ],
    "sg:phone":"+1 801 949 1618",
    "sg:postcode":"84120",
    "sg:province":"UT",
    "sg:tags":[
        "repairing",
        "piano",
        "refinishing"
    ],
    "wof:name":"Heirloom Piano Co",
    "wof:placetype":"venue"
},
  "geometry": {"coordinates":[-112.01173199999999,40.692655],"type":"Point"}
}