{
  "type": "Feature",
  "properties": {
    "iso:country":"US",
    "sg:address":"8138 Cottonwood Hills Cir",
    "sg:city":"Sandy",
    "sg:classifiers":[
        {
            "category":"Professional",
            "subcategory":"Business Services",
            "type":"Services"
        }
    ],
    "sg:phone":"+1 801 566 9559",
    "sg:postcode":"84094",
    "sg:province":"UT",
    "wof:name":"Spec Plnrs & Prntng",
    "wof:placetype":"venue"
},
  "geometry": {"coordinates":[-111.85553,40.603542],"type":"Point"}
}