{
  "type": "Feature",
  "properties": {
    "iso:country":"US",
    "sg:address":"5266 Begonia Pl",
    "sg:city":"West Jordan",
    "sg:classifiers":[
        {
            "category":"Building & Trades",
            "subcategory":"Landscaping Services",
            "type":"Services"
        }
    ],
    "sg:phone":"+1 801 955 0178",
    "sg:postcode":"84084",
    "sg:province":"UT",
    "wof:name":"High Rise Lawn Care",
    "wof:placetype":"venue"
},
  "geometry": {"coordinates":[-112.015421,40.632278],"type":"Point"}
}