{
  "type": "Feature",
  "properties": {
    "iso:country":"US",
    "sg:address":"431 Wright Brothers Dr",
    "sg:city":"Salt Lake City",
    "sg:classifiers":[
        {
            "category":"Wholesale",
            "subcategory":"Hardware",
            "type":"Manufacturing & Wholesale Goods"
        }
    ],
    "sg:phone":"+1 801 328 3986",
    "sg:postcode":"84116",
    "sg:province":"UT",
    "sg:tags":[
        "tool"
    ],
    "sg:website":"www.nps.net",
    "wof:name":"NPS Industrial",
    "wof:placetype":"venue"
},
  "geometry": {"coordinates":[-112.005821,40.777614],"type":"Point"}
}