{
  "type": "Feature",
  "properties": {
    "iso:country":"US",
    "sg:address":"581 Sider Dr",
    "sg:city":"North Salt Lake",
    "sg:classifiers":[
        {
            "category":"Banks & Credit Unions",
            "subcategory":"Financial Services",
            "type":"Services"
        }
    ],
    "sg:phone":"+1 801 298 7272",
    "sg:postcode":"84054",
    "sg:province":"UT",
    "sg:tags":[
        "trust",
        "management"
    ],
    "wof:name":"Youngs Family Trust",
    "wof:placetype":"venue"
},
  "geometry": {"coordinates":[-111.900035,40.843954],"type":"Point"}
}