{
  "type": "Feature",
  "properties": {
    "iso:country":"US",
    "sg:address":"601 Gage Ave",
    "sg:city":"Evanston",
    "sg:classifiers":[
        {
            "category":"Building & Trades",
            "subcategory":"Construction",
            "type":"Services"
        }
    ],
    "sg:phone":"+1 307 789 7751",
    "sg:postcode":"82930",
    "sg:province":"UT",
    "sg:tags":[
        "house"
    ],
    "wof:name":"Jon Le Vasseur Construction",
    "wof:placetype":"venue"
},
  "geometry": {"coordinates":[-110.980799,41.247386],"type":"Point"}
}