{
  "type": "Feature",
  "properties": {
    "iso:country":"US",
    "sg:address":"10852 S 2000 E",
    "sg:city":"Sandy",
    "sg:classifiers":[
        {
            "category":"Retail",
            "subcategory":"Animal Services",
            "type":"Services"
        }
    ],
    "sg:phone":"+1 801 571 1712",
    "sg:postcode":"84092",
    "sg:province":"UT",
    "sg:tags":[
        "operation"
    ],
    "wof:name":"Alta Hills Farm",
    "wof:placetype":"venue"
},
  "geometry": {"coordinates":[-111.834622,40.555697],"type":"Point"}
}