{
  "type": "Feature",
  "properties": {
    "iso:country":"US",
    "sg:address":"11623 S State St",
    "sg:city":"Draper",
    "sg:classifiers":[
        {
            "category":"Building & Trades",
            "subcategory":"Landscaping Services",
            "type":"Services"
        }
    ],
    "sg:phone":"+1 801 501 0708",
    "sg:postcode":"84020",
    "sg:province":"UT",
    "sg:tags":[
        "landscape",
        "contractor"
    ],
    "wof:name":"Grass Master Hydroseeding",
    "wof:placetype":"venue"
},
  "geometry": {"coordinates":[-111.891108,40.544],"type":"Point"}
}