{
  "type": "Feature",
  "properties": {
    "iso:country":"US",
    "sg:address":"900 S Bluff St",
    "sg:city":"St George",
    "sg:classifiers":[
        {
            "category":"Shopping",
            "type":"Retail Goods"
        }
    ],
    "sg:phone":"+1 435 674 9900",
    "sg:postcode":"84770",
    "sg:province":"UT",
    "sg:tags":[
        "merchandise"
    ],
    "wof:name":"House of Hearing",
    "wof:placetype":"venue"
},
  "geometry": {"coordinates":[-113.58636,37.094255],"type":"Point"}
}