{
  "type": "Feature",
  "properties": {
    "iso:country":"US",
    "sg:address":"3818 N 100 E",
    "sg:city":"Provo",
    "sg:classifiers":[
        {
            "category":"Wholesale",
            "subcategory":"Medical Equipment & Supplies",
            "type":"Manufacturing & Wholesale Goods"
        }
    ],
    "sg:phone":"+1 801 224 4931",
    "sg:postcode":"84604",
    "sg:province":"UT",
    "sg:tags":[
        "hospital"
    ],
    "wof:name":"Jackson Medical Inc",
    "wof:placetype":"venue"
},
  "geometry": {"coordinates":[-111.656088,40.284277],"type":"Point"}
}