{
  "type": "Feature",
  "properties": {
    "iso:country":"US",
    "sg:address":"891 N 700 E",
    "sg:city":"Bountiful",
    "sg:classifiers":[
        {
            "category":"Professional",
            "subcategory":"Business Services",
            "type":"Services"
        }
    ],
    "sg:phone":"+1 801 298 0064",
    "sg:postcode":"84010",
    "sg:province":"UT",
    "sg:tags":[
        "automobile",
        "appraiser"
    ],
    "wof:name":"Independent Damage Appraisal",
    "wof:placetype":"venue"
},
  "geometry": {"coordinates":[-111.866545,40.89648],"type":"Point"}
}