{
  "type": "Feature",
  "properties": {
    "iso:country":"US",
    "sg:address":"15 S 100 W",
    "sg:city":"Fairview",
    "sg:classifiers":[
        {
            "category":"Professional",
            "type":"Services"
        }
    ],
    "sg:phone":"+1 435 427 9477",
    "sg:postcode":"84629",
    "sg:province":"UT",
    "sg:tags":[
        "establishment"
    ],
    "wof:name":"Cox & Cox",
    "wof:placetype":"venue"
},
  "geometry": {"coordinates":[-111.441332,39.628068],"type":"Point"}
}