{
  "type": "Feature",
  "properties": {
    "iso:country":"US",
    "sg:address":"1188 Brickyard Rd",
    "sg:city":"Salt Lake City",
    "sg:classifiers":[
        {
            "category":"Personal",
            "type":"Services"
        }
    ],
    "sg:phone":"+1 801 463 4700",
    "sg:postcode":"84106",
    "sg:province":"UT",
    "sg:tags":[
        "wear",
        "formal"
    ],
    "wof:name":"Clark's Tuxedo",
    "wof:placetype":"venue"
},
  "geometry": {"coordinates":[-111.859782,40.703829],"type":"Point"}
}