{
  "type": "Feature",
  "properties": {
    "iso:country":"US",
    "sg:address":"700 N 2625 W",
    "sg:city":"Clearfield",
    "sg:classifiers":[
        {
            "category":"Bars & Pubs",
            "type":"Food & Drink"
        }
    ],
    "sg:phone":"+1 801 773 1650",
    "sg:postcode":"84015",
    "sg:province":"UT",
    "sg:tags":[
        "drinking"
    ],
    "wof:name":"Tin Cup Meadows LLC",
    "wof:placetype":"venue"
},
  "geometry": {"coordinates":[-112.077426,41.124284],"type":"Point"}
}