{
  "type": "Feature",
  "properties": {
    "iso:country":"US",
    "sg:address":"11208 Star Cir",
    "sg:city":"Sandy",
    "sg:classifiers":[
        {
            "category":"Retail",
            "subcategory":"Repair Shop",
            "type":"Services"
        }
    ],
    "sg:phone":"+1 801 571 9380",
    "sg:postcode":"84092",
    "sg:province":"UT",
    "wof:name":"Dautel Cleaning LLC",
    "wof:placetype":"venue"
},
  "geometry": {"coordinates":[-111.84651100000001,40.547969],"type":"Point"}
}