{
  "type": "Feature",
  "properties": {
    "iso:country":"US",
    "sg:address":"914 E 900 S",
    "sg:city":"Salt Lake City",
    "sg:classifiers":[
        {
            "category":"Wholesale",
            "subcategory":"Books, Periodicals, & Newspapers",
            "type":"Manufacturing & Wholesale Goods"
        },
        {
            "category":"Shopping",
            "subcategory":"Clothing, Apparel, & Fashions",
            "type":"Retail Goods"
        }
    ],
    "sg:phone":"+1 801 359 4150",
    "sg:postcode":"84105",
    "sg:province":"UT",
    "sg:tags":[
        "infant",
        "wear"
    ],
    "wof:name":"Children's Hour",
    "wof:placetype":"venue"
},
  "geometry": {"coordinates":[-111.864301,40.749715],"type":"Point"}
}