{
  "type": "Feature",
  "properties": {
    "iso:country":"US",
    "sg:address":"555 W 9000 S",
    "sg:city":"Sandy",
    "sg:classifiers":[
        {
            "category":"Wholesale",
            "subcategory":"Plants",
            "type":"Manufacturing & Wholesale Goods"
        }
    ],
    "sg:phone":"+1 801 266 1000",
    "sg:postcode":"84070",
    "sg:province":"UT",
    "sg:tags":[
        "florist"
    ],
    "wof:name":"Tai-Pan Trading Intl Inc",
    "wof:placetype":"venue"
},
  "geometry": {"coordinates":[-111.907515,40.587793],"type":"Point"}
}