{
  "type": "Feature",
  "properties": {
    "iso:country":"US",
    "sg:address":"1280 W 1500 S",
    "sg:city":"Woods Cross",
    "sg:classifiers":[
        {
            "category":"Professional",
            "type":"Services"
        }
    ],
    "sg:phone":"+1 801 295 6829",
    "sg:postcode":"84087",
    "sg:province":"UT",
    "wof:name":"William C Calhoon",
    "wof:placetype":"venue"
},
  "geometry": {"coordinates":[-111.918806,40.874778],"type":"Point"}
}