{
  "type": "Feature",
  "properties": {
    "iso:country":"US",
    "sg:address":"960 S Morgan Valley Dr",
    "sg:city":"Morgan",
    "sg:classifiers":[
        {
            "category":"Retail",
            "subcategory":"Portrait Studio",
            "type":"Services"
        }
    ],
    "sg:phone":"+1 801 829 3372",
    "sg:postcode":"84050",
    "sg:province":"UT",
    "sg:tags":[
        "photo"
    ],
    "wof:name":"Picture This Fmly Phtgrphy LLC",
    "wof:placetype":"venue"
},
  "geometry": {"coordinates":[-111.690685,41.009854],"type":"Point"}
}