{
  "type": "Feature",
  "properties": {
    "iso:country":"US",
    "sg:address":"51 W Center St",
    "sg:city":"Provo",
    "sg:classifiers":[
        {
            "category":"Wholesale",
            "subcategory":"Groceries",
            "type":"Manufacturing & Wholesale Goods"
        }
    ],
    "sg:phone":"+1 801 356 6592",
    "sg:postcode":"84601",
    "sg:province":"UT",
    "sg:tags":[
        "food",
        "product",
        "health"
    ],
    "wof:name":"Platinum Edge",
    "wof:placetype":"venue"
},
  "geometry": {"coordinates":[-111.659738,40.233575],"type":"Point"}
}