{
  "type": "Feature",
  "properties": {
    "iso:country":"US",
    "sg:address":"613 W 200 S",
    "sg:city":"Vernal",
    "sg:classifiers":[
        {
            "category":"Organizations",
            "subcategory":"Religious Organization",
            "type":"Services"
        }
    ],
    "sg:phone":"+1 435 789 1360",
    "sg:postcode":"84078",
    "sg:province":"UT",
    "wof:name":"Beehive Clothing Dist Ctr",
    "wof:placetype":"venue"
},
  "geometry": {"coordinates":[-109.54077100000001,40.452671],"type":"Point"}
}