{
  "type": "Feature",
  "properties": {
    "iso:country":"US",
    "sg:address":"551 W 9460 S",
    "sg:city":"Sandy",
    "sg:classifiers":[
        {
            "category":"Manufacturing",
            "subcategory":"Rubber & Plastics",
            "type":"Manufacturing & Wholesale Goods"
        }
    ],
    "sg:phone":"+1 801 255 4224",
    "sg:postcode":"84070",
    "sg:province":"UT",
    "sg:tags":[
        "product",
        "fabricated",
        "mfg"
    ],
    "wof:name":"Cath-Tip Inc",
    "wof:placetype":"venue"
},
  "geometry": {"coordinates":[-111.90644,40.579504],"type":"Point"}
}