{
  "type": "Feature",
  "properties": {
    "iso:country":"US",
    "sg:address":"834 16th Ave",
    "sg:city":"Salt Lake City",
    "sg:classifiers":[
        {
            "category":"Professional",
            "type":"Services"
        }
    ],
    "sg:phone":"+1 801 532 3814",
    "sg:postcode":"84103",
    "sg:province":"UT",
    "wof:name":"Masterfit LLC",
    "wof:placetype":"venue"
},
  "geometry": {"coordinates":[-111.868019,40.787205],"type":"Point"}
}