{
  "type": "Feature",
  "properties": {
    "iso:country":"US",
    "sg:address":"3315 Hanover Park Dr",
    "sg:city":"Salt Lake City",
    "sg:classifiers":[
        {
            "category":"Professional",
            "subcategory":"Business Services",
            "type":"Services"
        }
    ],
    "sg:phone":"+1 801 973 9827",
    "sg:postcode":"84119",
    "sg:province":"UT",
    "wof:name":"Trinidad R Torres",
    "wof:placetype":"venue"
},
  "geometry": {"coordinates":[-111.96979399999999,40.710043],"type":"Point"}
}