{
  "type": "Feature",
  "properties": {
    "iso:country":"US",
    "sg:address":"355 W 470 S",
    "sg:city":"Lindon",
    "sg:classifiers":[
        {
            "category":"Professional",
            "subcategory":"Computer Services",
            "type":"Services"
        }
    ],
    "sg:phone":"+1 801 223 9722",
    "sg:postcode":"84042",
    "sg:province":"UT",
    "sg:tags":[
        "school",
        "processing",
        "datum",
        "programing",
        "custom"
    ],
    "wof:name":"Westwind Technologies",
    "wof:placetype":"venue"
},
  "geometry": {"coordinates":[-111.72250099999999,40.32871],"type":"Point"}
}