{
  "type": "Feature",
  "properties": {
    "iso:country":"US",
    "sg:address":"2290 S 1300 E",
    "sg:city":"Salt Lake City",
    "sg:classifiers":[
        {
            "category":"Shopping",
            "subcategory":"Optical Goods",
            "type":"Retail Goods"
        }
    ],
    "sg:phone":"+1 801 467 8989",
    "sg:postcode":"84106",
    "sg:province":"UT",
    "wof:name":"Shopco",
    "wof:placetype":"venue"
},
  "geometry": {"coordinates":[-111.85380000000001,40.720932],"type":"Point"}
}