{
  "type": "Feature",
  "properties": {
    "iso:country":"US",
    "sg:address":"1423 Beacon Hill Dr",
    "sg:city":"Salt Lake City",
    "sg:classifiers":[
        {
            "category":"Personal",
            "type":"Services"
        }
    ],
    "sg:phone":"+1 801 266 4117",
    "sg:postcode":"84123",
    "sg:province":"UT",
    "wof:name":"Salubrious Massage Inc",
    "wof:placetype":"venue"
},
  "geometry": {"coordinates":[-111.93181300000001,40.654033],"type":"Point"}
}