{
  "type": "Feature",
  "properties": {
    "iso:country":"US",
    "sg:address":"1610 W 1600 S",
    "sg:city":"Springville",
    "sg:classifiers":[
        {
            "category":"Manufacturing",
            "subcategory":"Tools & Machinery",
            "type":"Manufacturing & Wholesale Goods"
        }
    ],
    "sg:phone":"+1 801 489 4466",
    "sg:postcode":"84663",
    "sg:province":"UT",
    "sg:tags":[
        "robot"
    ],
    "sg:website":"www.robotronics.com",
    "wof:name":"Robotronics",
    "wof:placetype":"venue"
},
  "geometry": {"coordinates":[-111.613114,40.144694],"type":"Point"}
}