{
  "type": "Feature",
  "properties": {
    "iso:country":"US",
    "sg:address":"332 E 6220 S",
    "sg:city":"Salt Lake City",
    "sg:classifiers":[
        {
            "category":"Professional",
            "type":"Services"
        }
    ],
    "sg:phone":"+1 801 262 3867",
    "sg:postcode":"84107",
    "sg:province":"UT",
    "wof:name":"Big Cottonwood Pine Tree Wtr",
    "wof:placetype":"venue"
},
  "geometry": {"coordinates":[-111.877802,40.637503],"type":"Point"}
}