{
  "type": "Feature",
  "properties": {
    "iso:country":"US",
    "sg:address":"2477 Fort Union Blvd",
    "sg:city":"Salt Lake City",
    "sg:classifiers":[
        {
            "category":"Recreation",
            "type":"Entertainment"
        }
    ],
    "sg:phone":"+1 801 942 2693",
    "sg:postcode":"84121",
    "sg:province":"UT",
    "sg:tags":[
        "martial",
        "arts",
        "instruction"
    ],
    "wof:name":"Paul Evans Martial Arts",
    "wof:placetype":"venue"
},
  "geometry": {"coordinates":[-111.82261800000001,40.624047],"type":"Point"}
}