{
  "type": "Feature",
  "properties": {
    "iso:country":"US",
    "sg:address":"318 7th St",
    "sg:city":"Evanston",
    "sg:classifiers":[
        {
            "category":"Professional",
            "subcategory":"Lawyer & Legal Services",
            "type":"Services"
        }
    ],
    "sg:phone":"+1 307 789 7003",
    "sg:postcode":"82930",
    "sg:province":"UT",
    "sg:tags":[
        "attorney"
    ],
    "wof:name":"Combs Law Office",
    "wof:placetype":"venue"
},
  "geometry": {"coordinates":[-110.963936,41.264866],"type":"Point"}
}