{
  "type": "Feature",
  "properties": {
    "iso:country":"US",
    "sg:address":"1930 W 6000 S",
    "sg:city":"Roy",
    "sg:classifiers":[
        {
            "category":"Retail",
            "subcategory":"Auto Repair",
            "type":"Services"
        }
    ],
    "sg:phone":"+1 801 776 4330",
    "sg:postcode":"84067",
    "sg:province":"UT",
    "sg:tags":[
        "automotive"
    ],
    "wof:name":"Roy Phillips 66",
    "wof:placetype":"venue"
},
  "geometry": {"coordinates":[-112.028336,41.154505],"type":"Point"}
}