{
  "type": "Feature",
  "properties": {
    "iso:country":"US",
    "sg:address":"5201 Intermountain Dr",
    "sg:city":"Salt Lake City",
    "sg:classifiers":[
        {
            "category":"Shopping",
            "subcategory":"Department Store",
            "type":"Retail Goods"
        }
    ],
    "sg:phone":"+1 801 569 9254",
    "sg:postcode":"84107",
    "sg:province":"UT",
    "wof:name":"Costco Warehouse",
    "wof:placetype":"venue"
},
  "geometry": {"coordinates":[-111.891132,40.65642],"type":"Point"}
}