{
  "type": "Feature",
  "properties": {
    "iso:country":"US",
    "sg:address":"323 S 1850 E",
    "sg:city":"Springville",
    "sg:classifiers":[
        {
            "category":"Real Estate",
            "subcategory":"Real Estate Agent",
            "type":"Services"
        }
    ],
    "sg:phone":"+1 801 489 8832",
    "sg:postcode":"84606",
    "sg:province":"UT",
    "wof:name":"Westfield Real Estate",
    "wof:placetype":"venue"
},
  "geometry": {"coordinates":[-111.577174,40.163278],"type":"Point"}
}