{
  "type": "Feature",
  "properties": {
    "iso:country":"US",
    "sg:address":"1150 W 3050 S",
    "sg:city":"Ogden",
    "sg:classifiers":[
        {
            "category":"Retail",
            "subcategory":"Auto Repair",
            "type":"Services"
        }
    ],
    "sg:phone":"+1 801 612 0200",
    "sg:postcode":"84401",
    "sg:province":"UT",
    "sg:tags":[
        "general"
    ],
    "wof:name":"Daves Master TEC Auto Clinic",
    "wof:placetype":"venue"
},
  "geometry": {"coordinates":[-112.010063,41.209376],"type":"Point"}
}