{
  "type": "Feature",
  "properties": {
    "iso:country":"US",
    "sg:address":"2606 S 3270 W",
    "sg:city":"Salt Lake City",
    "sg:classifiers":[
        {
            "category":"Building & Trades",
            "subcategory":"Construction",
            "type":"Services"
        }
    ],
    "sg:phone":"+1 801 972 1190",
    "sg:postcode":"84119",
    "sg:province":"UT",
    "sg:tags":[
        "restoration",
        "preservation"
    ],
    "wof:name":"Restruction Corp",
    "wof:placetype":"venue"
},
  "geometry": {"coordinates":[-111.96928200000001,40.71199],"type":"Point"}
}