{
  "type": "Feature",
  "properties": {
    "iso:country":"US",
    "sg:address":"2656 W 4700 S",
    "sg:city":"Salt Lake City",
    "sg:classifiers":[
        {
            "category":"Shopping",
            "subcategory":"Tobacco",
            "type":"Retail Goods"
        }
    ],
    "sg:phone":"+1 801 967 3834",
    "sg:postcode":"84118",
    "sg:province":"UT",
    "sg:tags":[
        "product"
    ],
    "wof:name":"Tobacco Hut",
    "wof:placetype":"venue"
},
  "geometry": {"coordinates":[-111.95699399999999,40.667703],"type":"Point"}
}