{
  "type": "Feature",
  "properties": {
    "iso:country":"US",
    "sg:address":"361 E 700 S",
    "sg:city":"Mount Pleasant",
    "sg:classifiers":[
        {
            "category":"Retail",
            "subcategory":"Laundry & Dry Cleaning",
            "type":"Services"
        }
    ],
    "sg:phone":"+1 435 462 9578",
    "sg:postcode":"84647",
    "sg:province":"UT",
    "wof:name":"A Plus Carpet Cleaning A+",
    "wof:placetype":"venue"
},
  "geometry": {"coordinates":[-111.448764,39.53664],"type":"Point"}
}