{
  "type": "Feature",
  "properties": {
    "iso:country":"US",
    "sg:address":"790 E Main St",
    "sg:city":"Hyrum",
    "sg:classifiers":[
        {
            "category":"Shopping",
            "subcategory":"Pharmacy",
            "type":"Retail Goods"
        }
    ],
    "sg:phone":"+1 435 245 6422",
    "sg:postcode":"84319",
    "sg:province":"UT",
    "sg:tags":[
        "drug",
        "store"
    ],
    "wof:name":"Reeds Pharmacy",
    "wof:placetype":"venue"
},
  "geometry": {"coordinates":[-111.832646,41.633652],"type":"Point"}
}