{
  "type": "Feature",
  "properties": {
    "iso:country":"US",
    "sg:address":"2855 S Hwy 89",
    "sg:city":"Brigham City",
    "sg:classifiers":[
        {
            "category":"Autos & Motor Vehicles",
            "subcategory":"Recreational Vehicle Sales",
            "type":"Retail Goods"
        }
    ],
    "sg:phone":"+1 435 723 2814",
    "sg:postcode":"84302",
    "sg:province":"UT",
    "wof:name":"Tims Toppers",
    "wof:placetype":"venue"
},
  "geometry": {"coordinates":[-112.03815299999999,41.457449],"type":"Point"}
}