{
  "type": "Feature",
  "properties": {
    "iso:country":"US",
    "sg:address":"2976 N 650 E",
    "sg:city":"Provo",
    "sg:classifiers":[
        {
            "category":"Building & Trades",
            "subcategory":"Construction",
            "type":"Services"
        }
    ],
    "sg:phone":"+1 801 373 8303",
    "sg:postcode":"84604",
    "sg:province":"UT",
    "sg:tags":[
        "hanging",
        "contractor"
    ],
    "wof:name":"Ray Morgan Painting",
    "wof:placetype":"venue"
},
  "geometry": {"coordinates":[-111.647505,40.273707],"type":"Point"}
}