{
  "type": "Feature",
  "properties": {
    "iso:country":"US",
    "sg:address":"1333 State Hwy 193",
    "sg:city":"Layton",
    "sg:classifiers":[
        {
            "category":"Home & Garden",
            "subcategory":"Garden Supply",
            "type":"Retail Goods"
        }
    ],
    "sg:phone":"+1 801 771 1475",
    "sg:postcode":"84040",
    "sg:province":"UT",
    "sg:tags":[
        "topsoil"
    ],
    "wof:name":"Jerry Jaques Topsoil",
    "wof:placetype":"venue"
},
  "geometry": {"coordinates":[-111.942914,41.101748],"type":"Point"}
}