{
  "type": "Feature",
  "properties": {
    "iso:country":"US",
    "sg:address":"2773 W 4700 S",
    "sg:city":"Salt Lake City",
    "sg:classifiers":[
        {
            "category":"Insurance",
            "subcategory":"Insurance Agent",
            "type":"Services"
        }
    ],
    "sg:phone":"+1 801 840 2651",
    "sg:postcode":"84118",
    "sg:province":"UT",
    "wof:name":"Farmers Insurance Group",
    "wof:placetype":"venue"
},
  "geometry": {"coordinates":[-111.959082,40.667549],"type":"Point"}
}