{
  "type": "Feature",
  "properties": {
    "iso:country":"US",
    "sg:address":"1515 N 150 E",
    "sg:city":"Springville",
    "sg:classifiers":[
        {
            "category":"Building & Trades",
            "subcategory":"Construction",
            "type":"Services"
        }
    ],
    "sg:phone":"+1 801 489 5982",
    "sg:postcode":"84663",
    "sg:province":"UT",
    "sg:tags":[
        "contractor"
    ],
    "wof:name":"Paramount General Contractors",
    "wof:placetype":"venue"
},
  "geometry": {"coordinates":[-111.608394,40.185761],"type":"Point"}
}