{
  "type": "Feature",
  "properties": {
    "iso:country":"US",
    "sg:address":"100 N Orchard Dr",
    "sg:city":"North Salt Lake",
    "sg:classifiers":[
        {
            "category":"Professional",
            "subcategory":"Management & Consulting",
            "type":"Services"
        }
    ],
    "sg:phone":"+1 801 936 0645",
    "sg:postcode":"84054",
    "sg:province":"UT",
    "sg:tags":[
        "business"
    ],
    "wof:name":"Stinky Good Inc",
    "wof:placetype":"venue"
},
  "geometry": {"coordinates":[-111.903333,40.843548],"type":"Point"}
}