{
  "type": "Feature",
  "properties": {
    "iso:country":"US",
    "sg:address":"6002 Riverbend Dr",
    "sg:city":"Salt Lake City",
    "sg:classifiers":[
        {
            "category":"Banks & Credit Unions",
            "subcategory":"Bank",
            "type":"Services"
        }
    ],
    "sg:phone":"+1 801 268 0592",
    "sg:postcode":"84123",
    "sg:province":"UT",
    "sg:tags":[
        "mortgage"
    ],
    "wof:name":"Riverbend Mortgage Corp",
    "wof:placetype":"venue"
},
  "geometry": {"coordinates":[-111.914575,40.639864],"type":"Point"}
}