{
  "type": "Feature",
  "properties": {
    "iso:country":"US",
    "sg:address":"354 N State St",
    "sg:city":"Orem",
    "sg:classifiers":[
        {
            "category":"Retail",
            "subcategory":"Repair Shop",
            "type":"Services"
        }
    ],
    "sg:phone":"+1 801 226 6606",
    "sg:postcode":"84057",
    "sg:province":"UT",
    "sg:tags":[
        "upholsterer"
    ],
    "wof:name":"Craftsman Upholstery-Interiors",
    "wof:placetype":"venue"
},
  "geometry": {"coordinates":[-111.697801,40.303525],"type":"Point"}
}