{
  "type": "Feature",
  "properties": {
    "iso:country":"US",
    "sg:address":"321 N Mall Dr",
    "sg:city":"St George",
    "sg:classifiers":[
        {
            "category":"Real Estate",
            "subcategory":"Real Estate Agent",
            "type":"Services"
        }
    ],
    "sg:phone":"+1 435 673 0359",
    "sg:postcode":"84790",
    "sg:province":"UT",
    "wof:name":"Porter & Assoc Inc",
    "wof:placetype":"venue"
},
  "geometry": {"coordinates":[-113.54330400000001,37.112872],"type":"Point"}
}