{
  "type": "Feature",
  "properties": {
    "iso:country":"US",
    "sg:address":"4245 S 3760 W",
    "sg:city":"Salt Lake City",
    "sg:classifiers":[
        {
            "category":"Professional",
            "subcategory":"Advertising",
            "type":"Services"
        }
    ],
    "sg:phone":"+1 801 967 1093",
    "sg:postcode":"84120",
    "sg:province":"UT",
    "sg:tags":[
        "mail",
        "direct"
    ],
    "wof:name":"Collins Group",
    "wof:placetype":"venue"
},
  "geometry": {"coordinates":[-111.980726,40.678302],"type":"Point"}
}