{
  "type": "Feature",
  "properties": {
    "iso:country":"US",
    "sg:address":"94 N 340 W",
    "sg:city":"Orem",
    "sg:classifiers":[
        {
            "category":"Farming",
            "subcategory":"Farm",
            "type":"Manufacturing & Wholesale Goods"
        }
    ],
    "sg:phone":"+1 801 434 4623",
    "sg:postcode":"84057",
    "sg:province":"UT",
    "sg:tags":[
        "general"
    ],
    "wof:name":"Poli Enterprises Inc",
    "wof:placetype":"venue"
},
  "geometry": {"coordinates":[-111.703091,40.297309],"type":"Point"}
}