{
  "type": "Feature",
  "properties": {
    "iso:country":"US",
    "sg:address":"110 E 100 S",
    "sg:city":"Kanab",
    "sg:classifiers":[
        {
            "category":"Government",
            "subcategory":"Court House",
            "type":"Public Place"
        }
    ],
    "sg:phone":"+1 435 644 3201",
    "sg:postcode":"84741",
    "sg:province":"UT",
    "sg:tags":[
        "city"
    ],
    "wof:name":"Kanab City Youth Court",
    "wof:placetype":"venue"
},
  "geometry": {"coordinates":[-112.526218,37.046321],"type":"Point"}
}