{
  "type": "Feature",
  "properties": {
    "iso:country":"US",
    "sg:address":"6928 S 775 E",
    "sg:city":"Midvale",
    "sg:classifiers":[
        {
            "category":"Education",
            "subcategory":"School",
            "type":"Public Place"
        }
    ],
    "sg:phone":"+1 801 255 0444",
    "sg:postcode":"84047",
    "sg:province":"UT",
    "wof:name":"Manzanita Inc",
    "wof:placetype":"venue"
},
  "geometry": {"coordinates":[-111.870063,40.625038],"type":"Point"}
}