{
  "type": "Feature",
  "properties": {
    "iso:country":"US",
    "sg:address":"673 Union Sq",
    "sg:city":"Sandy",
    "sg:classifiers":[
        {
            "category":"Personal",
            "type":"Services"
        }
    ],
    "sg:phone":"+1 801 572 1240",
    "sg:postcode":"84070",
    "sg:province":"UT",
    "sg:tags":[
        "wear",
        "formal"
    ],
    "sg:website":"www.tuxedojunctionslc.com",
    "wof:name":"Tuxedo Junction Inc",
    "wof:placetype":"venue"
},
  "geometry": {"coordinates":[-111.87353400000001,40.579976],"type":"Point"}
}