{
  "type": "Feature",
  "properties": {
    "iso:country":"US",
    "sg:address":"601 N 800 W",
    "sg:city":"Provo",
    "sg:classifiers":[
        {
            "category":"Professional",
            "subcategory":"Business Services",
            "type":"Services"
        }
    ],
    "sg:phone":"+1 801 607 5205",
    "sg:postcode":"84601",
    "sg:province":"UT",
    "wof:name":"Columbia River Enterprises",
    "wof:placetype":"venue"
},
  "geometry": {"coordinates":[-111.67298599999999,40.241871],"type":"Point"}
}