{
  "type": "Feature",
  "properties": {
    "iso:country":"US",
    "sg:address":"1102 Washington Blvd",
    "sg:city":"Ogden",
    "sg:classifiers":[
        {
            "category":"Shopping",
            "subcategory":"Books",
            "type":"Retail Goods"
        }
    ],
    "sg:phone":"+1 801 394 4666",
    "sg:postcode":"84404",
    "sg:province":"UT",
    "sg:tags":[
        "dealer"
    ],
    "wof:name":"Seagull Book & Tape",
    "wof:placetype":"venue"
},
  "geometry": {"coordinates":[-111.969866,41.244314],"type":"Point"}
}