{
  "type": "Feature",
  "properties": {
    "iso:country":"US",
    "sg:address":"433 W 1800 S",
    "sg:city":"Orem",
    "sg:classifiers":[
        {
            "category":"Manufacturing",
            "subcategory":"Tools & Machinery",
            "type":"Manufacturing & Wholesale Goods"
        }
    ],
    "sg:phone":"+1 801 224 5878",
    "sg:postcode":"84058",
    "sg:province":"UT",
    "sg:tags":[
        "farm",
        "mfg"
    ],
    "wof:name":"Excel Manufacturing Inc",
    "wof:placetype":"venue"
},
  "geometry": {"coordinates":[-111.706835,40.264382],"type":"Point"}
}