{
  "type": "Feature",
  "properties": {
    "iso:country":"US",
    "sg:address":"421 E 2780 N",
    "sg:city":"Provo",
    "sg:classifiers":[
        {
            "category":"Building & Trades",
            "subcategory":"Electrical",
            "type":"Services"
        }
    ],
    "sg:phone":"+1 801 377 0785",
    "sg:postcode":"84604",
    "sg:province":"UT",
    "sg:tags":[
        "electrical",
        "contractor"
    ],
    "wof:name":"Kdb Electric",
    "wof:placetype":"venue"
},
  "geometry": {"coordinates":[-111.65140100000001,40.2701],"type":"Point"}
}