{
  "type": "Feature",
  "properties": {
    "iso:country":"US",
    "sg:address":"11055 S 1000 E",
    "sg:city":"Sandy",
    "sg:classifiers":[
        {
            "category":"Building & Trades",
            "subcategory":"Construction",
            "type":"Services"
        }
    ],
    "sg:phone":"+1 801 523 1160",
    "sg:postcode":"84094",
    "sg:province":"UT",
    "sg:tags":[
        "contractor"
    ],
    "wof:name":"Nelson Contractors Inc",
    "wof:placetype":"venue"
},
  "geometry": {"coordinates":[-111.86267100000001,40.550963],"type":"Point"}
}