{
  "type": "Feature",
  "properties": {
    "iso:country":"US",
    "sg:address":"932 S Bluff St",
    "sg:city":"Saint George",
    "sg:classifiers":[
        {
            "category":"Restaurant",
            "type":"Food & Drink"
        }
    ],
    "sg:menulink":"http://www.allmenus.com/ut/st-george/75023-pizza-hut/menu/",
    "sg:phone":"+1 435 628 8822",
    "sg:postcode":"84770",
    "sg:province":"UT",
    "sg:tags":[
        "american",
        "pizza"
    ],
    "wof:name":"Pizza Hut",
    "wof:placetype":"venue"
},
  "geometry": {"coordinates":[-113.586105,37.092698],"type":"Point"}
}