{
  "type": "Feature",
  "properties": {
    "iso:country":"US",
    "sg:address":"91 S 100 W",
    "sg:city":"Mount Pleasant",
    "sg:classifiers":[
        {
            "category":"Organizations",
            "subcategory":"Religious Organization",
            "type":"Services"
        }
    ],
    "sg:phone":"+1 435 462 2667",
    "sg:postcode":"84647",
    "sg:province":"UT",
    "wof:name":"1st Prsbtryn Church",
    "wof:placetype":"venue"
},
  "geometry": {"coordinates":[-111.45717,39.545403],"type":"Point"}
}