{
  "type": "Feature",
  "properties": {
    "iso:country":"US",
    "sg:address":"1998 N Main St",
    "sg:city":"Layton",
    "sg:classifiers":[
        {
            "category":"Food & Beverages",
            "subcategory":"Groceries & Convenience Stores",
            "type":"Retail Goods"
        }
    ],
    "sg:phone":"+1 801 773 7127",
    "sg:postcode":"84041",
    "sg:province":"UT",
    "wof:name":"7-Eleven",
    "wof:placetype":"venue"
},
  "geometry": {"coordinates":[-111.99844899999999,41.086506],"type":"Point"}
}