{
  "type": "Feature",
  "properties": {
    "iso:country":"US",
    "sg:address":"1027 N Main St",
    "sg:city":"Cedar City",
    "sg:classifiers":[
        {
            "category":"Real Estate",
            "subcategory":"Developer",
            "type":"Services"
        },
        {
            "category":"Real Estate",
            "subcategory":"Real Estate Operator",
            "type":"Services"
        }
    ],
    "sg:phone":"+1 435 586 2022",
    "sg:postcode":"84720",
    "sg:province":"UT",
    "sg:tags":[
        "mobile",
        "home",
        "site"
    ],
    "wof:name":"Mountain View Mobile Home",
    "wof:placetype":"venue"
},
  "geometry": {"coordinates":[-113.06264899999999,37.6949],"type":"Point"}
}