{
  "type": "Feature",
  "properties": {
    "iso:country":"US",
    "sg:address":"280 W 100 N",
    "sg:city":"Provo",
    "sg:classifiers":[
        {
            "category":"Food & Beverages",
            "subcategory":"Specialty",
            "type":"Retail Goods"
        }
    ],
    "sg:phone":"+1 801 375 5409",
    "sg:postcode":"84601",
    "sg:province":"UT",
    "sg:tags":[
        "tea",
        "coffee",
        "store"
    ],
    "wof:name":"Juice n Java",
    "wof:placetype":"venue"
},
  "geometry": {"coordinates":[-111.662863,40.235187],"type":"Point"}
}