{
  "type": "Feature",
  "properties": {
    "iso:country":"US",
    "sg:address":"275 S 200 E",
    "sg:city":"Nephi",
    "sg:classifiers":[
        {
            "category":"Wholesale",
            "subcategory":"Machinery & Supplies",
            "type":"Manufacturing & Wholesale Goods"
        }
    ],
    "sg:phone":"+1 435 623 2544",
    "sg:postcode":"84648",
    "sg:province":"UT",
    "sg:tags":[
        "equipment",
        "establishment"
    ],
    "wof:name":"Lloyd V Sundquist",
    "wof:placetype":"venue"
},
  "geometry": {"coordinates":[-111.832222,39.704465],"type":"Point"}
}