{
  "type": "Feature",
  "properties": {
    "iso:country":"US",
    "sg:address":"4785 W 3500 S",
    "sg:city":"Salt Lake City",
    "sg:classifiers":[
        {
            "category":"Wholesale",
            "subcategory":"Construction Materials",
            "type":"Manufacturing & Wholesale Goods"
        },
        {
            "category":"Home & Garden",
            "subcategory":"Building Materials",
            "type":"Retail Goods"
        }
    ],
    "sg:phone":"+1 801 969 1491",
    "sg:postcode":"84120",
    "sg:province":"UT",
    "sg:tags":[
        "glass",
        "window",
        "plate"
    ],
    "wof:name":"Central Glass Co",
    "wof:placetype":"venue"
},
  "geometry": {"coordinates":[-112.005107,40.696502],"type":"Point"}
}