{
  "type": "Feature",
  "properties": {
    "iso:country":"US",
    "sg:address":"295 N 120 W",
    "sg:city":"Vernal",
    "sg:classifiers":[
        {
            "category":"Building & Trades",
            "subcategory":"Construction",
            "type":"Services"
        }
    ],
    "sg:phone":"+1 435 781 8376",
    "sg:postcode":"84078",
    "sg:province":"UT",
    "sg:tags":[
        "house"
    ],
    "wof:name":"Enchantment Homes",
    "wof:placetype":"venue"
},
  "geometry": {"coordinates":[-109.53116300000001,40.46107],"type":"Point"}
}