{
  "type": "Feature",
  "properties": {
    "iso:country":"US",
    "sg:address":"367 W 700 N",
    "sg:city":"Provo",
    "sg:classifiers":[
        {
            "category":"Retail",
            "subcategory":"Auto Repair",
            "type":"Services"
        }
    ],
    "sg:phone":"+1 801 836 2828",
    "sg:postcode":"84601",
    "sg:province":"UT",
    "sg:tags":[
        "wrecker"
    ],
    "wof:name":"Nish's Towing",
    "wof:placetype":"venue"
},
  "geometry": {"coordinates":[-111.664748,40.242971],"type":"Point"}
}