{
  "type": "Feature",
  "properties": {
    "iso:country":"US",
    "sg:address":"7631 Lark Meadow Cove",
    "sg:city":"Midvale",
    "sg:classifiers":[
        {
            "category":"Organizations",
            "subcategory":"Religious Organization",
            "type":"Services"
        }
    ],
    "sg:phone":"+1 801 565 8566",
    "sg:postcode":"84047",
    "sg:province":"UT",
    "sg:tags":[
        "church"
    ],
    "wof:name":"St Germain Foundation",
    "wof:placetype":"venue"
},
  "geometry": {"coordinates":[-111.873654,40.61241],"type":"Point"}
}