{
  "type": "Feature",
  "properties": {
    "iso:country":"US",
    "sg:address":"3473 W Kathy Ave",
    "sg:city":"Salt Lake City",
    "sg:classifiers":[
        {
            "category":"Travel",
            "subcategory":"Travel Agent",
            "type":"Entertainment"
        }
    ],
    "sg:phone":"+1 801 968 9276",
    "sg:postcode":"84119",
    "sg:province":"UT",
    "sg:tags":[
        "agency"
    ],
    "wof:name":"B & L World Wide Travel",
    "wof:placetype":"venue"
},
  "geometry": {"coordinates":[-111.974344,40.672597],"type":"Point"}
}