{
  "type": "Feature",
  "properties": {
    "iso:country":"US",
    "sg:address":"1000 S Main St",
    "sg:city":"Richfield",
    "sg:classifiers":[
        {
            "category":"Autos & Motor Vehicles",
            "subcategory":"Automobile Sales",
            "type":"Retail Goods"
        }
    ],
    "sg:phone":"+1 435 896 8436",
    "sg:postcode":"84701",
    "sg:province":"UT",
    "sg:tags":[
        "car",
        "truck",
        "dealer"
    ],
    "sg:website":"www.jorgford.com",
    "wof:name":"Jorgensen Ford Mercury",
    "wof:placetype":"venue"
},
  "geometry": {"coordinates":[-112.088775,38.753997],"type":"Point"}
}