{
  "type": "Feature",
  "properties": {
    "iso:country":"US",
    "sg:address":"280 N 100 E",
    "sg:city":"Joseph",
    "sg:classifiers":[
        {
            "category":"Utilities",
            "subcategory":"Water",
            "type":"Services"
        }
    ],
    "sg:phone":"+1 435 527 4791",
    "sg:postcode":"84739",
    "sg:province":"UT",
    "sg:tags":[
        "supply"
    ],
    "wof:name":"Sevier River Water Users",
    "wof:placetype":"venue"
},
  "geometry": {"coordinates":[-112.215856,38.627976],"type":"Point"}
}