{
  "type": "Feature",
  "properties": {
    "iso:country":"US",
    "sg:address":"143 E 400 N",
    "sg:city":"Bountiful",
    "sg:classifiers":[
        {
            "category":"Health Services",
            "subcategory":"Chiropractor",
            "type":"Services"
        }
    ],
    "sg:phone":"+1 801 295 7801",
    "sg:postcode":"84010",
    "sg:province":"UT",
    "wof:name":"Thompson Michael R Chir",
    "wof:placetype":"venue"
},
  "geometry": {"coordinates":[-111.876999,40.893902],"type":"Point"}
}