{
  "type": "Feature",
  "properties": {
    "iso:country":"US",
    "sg:address":"301 S Main St",
    "sg:city":"Heber City",
    "sg:classifiers":[
        {
            "category":"Government",
            "subcategory":"Police Station",
            "type":"Public Place"
        }
    ],
    "sg:phone":"+1 435 654 3040",
    "sg:postcode":"84032",
    "sg:province":"UT",
    "sg:tags":[
        "govt",
        "protection",
        "local"
    ],
    "wof:name":"City Heber Police Department",
    "wof:placetype":"venue"
},
  "geometry": {"coordinates":[-111.41353599999999,40.50372],"type":"Point"}
}