{
  "type": "Feature",
  "properties": {
    "iso:country":"US",
    "sg:address":"720 W Price River Dr",
    "sg:city":"Price",
    "sg:classifiers":[
        {
            "category":"Shopping",
            "subcategory":"Department Store",
            "type":"Retail Goods"
        }
    ],
    "sg:phone":"+1 435 637 1999",
    "sg:postcode":"84501",
    "sg:province":"UT",
    "sg:tags":[
        "shop"
    ],
    "wof:name":"Dollar Tree",
    "wof:placetype":"venue"
},
  "geometry": {"coordinates":[-110.82306699999999,39.60069],"type":"Point"}
}