{
  "type": "Feature",
  "properties": {
    "iso:country":"US",
    "sg:address":"1586 Hollywood Ave",
    "sg:city":"Salt Lake City",
    "sg:classifiers":[
        {
            "category":"Shopping",
            "subcategory":"Jewelry",
            "type":"Retail Goods"
        }
    ],
    "sg:phone":"+1 801 467 4725",
    "sg:postcode":"84105",
    "sg:province":"UT",
    "wof:name":"Black Cat Design",
    "wof:placetype":"venue"
},
  "geometry": {"coordinates":[-111.847585,40.727414],"type":"Point"}
}