{
  "type": "Feature",
  "properties": {
    "iso:country":"US",
    "sg:address":"1327 W 2550 S",
    "sg:city":"Ogden",
    "sg:classifiers":[
        {
            "category":"Manufacturing",
            "subcategory":"Metals",
            "type":"Manufacturing & Wholesale Goods"
        }
    ],
    "sg:phone":"+1 801 627 5580",
    "sg:postcode":"84401",
    "sg:province":"UT",
    "sg:tags":[
        "fluid",
        "power",
        "mfg"
    ],
    "wof:name":"Evco House of Hose",
    "wof:placetype":"venue"
},
  "geometry": {"coordinates":[-112.010784,41.219471],"type":"Point"}
}