{
  "type": "Feature",
  "properties": {
    "iso:country":"US",
    "sg:address":"4050 S 5600 W",
    "sg:city":"Salt Lake City",
    "sg:classifiers":[
        {
            "category":"Home & Garden",
            "subcategory":"Building Materials",
            "type":"Retail Goods"
        }
    ],
    "sg:phone":"+1 801 967 6829",
    "sg:postcode":"84120",
    "sg:province":"UT",
    "sg:tags":[
        "center"
    ],
    "wof:name":"Lowe's",
    "wof:placetype":"venue"
},
  "geometry": {"coordinates":[-112.02482500000001,40.683186],"type":"Point"}
}