{
  "type": "Feature",
  "properties": {
    "iso:country":"US",
    "sg:address":"160 E 100 S",
    "sg:city":"Hurricane",
    "sg:classifiers":[
        {
            "category":"Professional",
            "subcategory":"Business Services",
            "type":"Services"
        }
    ],
    "sg:phone":"+1 435 635 7451",
    "sg:postcode":"84737",
    "sg:province":"UT",
    "wof:name":"Beutler Enterprises Inc",
    "wof:placetype":"venue"
},
  "geometry": {"coordinates":[-113.28294099999999,37.176746],"type":"Point"}
}