{
  "type": "Feature",
  "properties": {
    "iso:country":"US",
    "sg:address":"239 S Main St",
    "sg:city":"Cedar City",
    "sg:classifiers":[
        {
            "category":"Insurance",
            "subcategory":"Insurance Agent",
            "type":"Services"
        }
    ],
    "sg:phone":"+1 435 586 2211",
    "sg:postcode":"84720",
    "sg:province":"UT",
    "wof:name":"Certified Insurance Svc Inc",
    "wof:placetype":"venue"
},
  "geometry": {"coordinates":[-113.06148399999999,37.671064],"type":"Point"}
}