{
  "type": "Feature",
  "properties": {
    "iso:country":"US",
    "sg:address":"357 W 6160 S",
    "sg:city":"Murray",
    "sg:classifiers":[
        {
            "category":"Professional",
            "type":"Services"
        }
    ],
    "sg:phone":"+1 801 685 2309",
    "sg:postcode":"84107",
    "sg:province":"UT",
    "sg:tags":[
        "establishment"
    ],
    "wof:name":"Dowdle & Daughters LC",
    "wof:placetype":"venue"
},
  "geometry": {"coordinates":[-111.899199,40.637272],"type":"Point"}
}