{
  "type": "Feature",
  "properties": {
    "iso:country":"US",
    "sg:address":"11210 Melissa Cir",
    "sg:city":"Sandy",
    "sg:classifiers":[
        {
            "category":"Home & Garden",
            "subcategory":"Home Furnishings",
            "type":"Retail Goods"
        }
    ],
    "sg:phone":"+1 801 571 9237",
    "sg:postcode":"84092",
    "sg:province":"UT",
    "wof:name":"Davies Draperies",
    "wof:placetype":"venue"
},
  "geometry": {"coordinates":[-111.84572900000001,40.54815],"type":"Point"}
}