{
  "type": "Feature",
  "properties": {
    "iso:country":"US",
    "sg:address":"1256 Freshman Cir",
    "sg:city":"Salt Lake City",
    "sg:classifiers":[
        {
            "category":"Shopping",
            "subcategory":"Clothing, Apparel, & Fashions",
            "type":"Retail Goods"
        }
    ],
    "sg:phone":"+1 801 268 3875",
    "sg:postcode":"84117",
    "sg:province":"UT",
    "sg:tags":[
        "direct",
        "sales"
    ],
    "wof:name":"Coffee Inspirations Inc",
    "wof:placetype":"venue"
},
  "geometry": {"coordinates":[-111.856004,40.671037],"type":"Point"}
}