{
  "type": "Feature",
  "properties": {
    "iso:country":"US",
    "sg:address":"245 N 800 West St",
    "sg:city":"Ferron",
    "sg:classifiers":[
        {
            "category":"Retail",
            "subcategory":"Repair Shop",
            "type":"Services"
        }
    ],
    "sg:phone":"+1 435 384 2444",
    "sg:postcode":"84523",
    "sg:province":"UT",
    "sg:tags":[
        "upholsterer"
    ],
    "wof:name":"Leslie's Custom Sewing",
    "wof:placetype":"venue"
},
  "geometry": {"coordinates":[-111.15061900000001,39.095556],"type":"Point"}
}