{
  "type": "Feature",
  "properties": {
    "iso:country":"US",
    "sg:address":"3760 S 150 E",
    "sg:city":"Salt Lake City",
    "sg:classifiers":[
        {
            "category":"Retail",
            "subcategory":"Auto Repair",
            "type":"Services"
        }
    ],
    "sg:phone":"+1 801 266 7755",
    "sg:postcode":"84115",
    "sg:province":"UT",
    "sg:tags":[
        "repairing",
        "automobile"
    ],
    "wof:name":"Southgate Auto Repair",
    "wof:placetype":"venue"
},
  "geometry": {"coordinates":[-111.88690099999999,40.689805],"type":"Point"}
}