{
  "type": "Feature",
  "properties": {
    "iso:country":"US",
    "sg:address":"11204 Sandy Dunes Dr",
    "sg:city":"Sandy",
    "sg:classifiers":[
        {
            "category":"Professional",
            "type":"Services"
        }
    ],
    "sg:phone":"+1 801 495 1689",
    "sg:postcode":"84094",
    "sg:province":"UT",
    "wof:name":"Jerl Corporation",
    "wof:placetype":"venue"
},
  "geometry": {"coordinates":[-111.871674,40.548352],"type":"Point"}
}