{
  "type": "Feature",
  "properties": {
    "iso:country":"US",
    "sg:address":"3196 S Washington St",
    "sg:city":"South Salt Lake",
    "sg:classifiers":[
        {
            "category":"Home & Garden",
            "subcategory":"Building Materials",
            "type":"Retail Goods"
        }
    ],
    "sg:phone":"+1 801 467 2620",
    "sg:postcode":"84115",
    "sg:province":"UT",
    "sg:tags":[
        "shutter"
    ],
    "sg:website":"www.worldsbestshutters.com",
    "wof:name":"Ken's World's Best Shutters",
    "wof:placetype":"venue"
},
  "geometry": {"coordinates":[-111.89802899999999,40.702451],"type":"Point"}
}