{
  "type": "Feature",
  "properties": {
    "iso:country":"US",
    "sg:address":"5447 Axel Park Rd",
    "sg:city":"West Jordan",
    "sg:classifiers":[
        {
            "category":"Manufacturing",
            "subcategory":"Metals",
            "type":"Manufacturing & Wholesale Goods"
        }
    ],
    "sg:phone":"+1 801 282 9375",
    "sg:postcode":"84088",
    "sg:province":"UT",
    "sg:tags":[
        "galvanizing"
    ],
    "wof:name":"Jordan River Galvanizing LLC",
    "wof:placetype":"venue"
},
  "geometry": {"coordinates":[-112.01875800000001,40.57648],"type":"Point"}
}