{
  "type": "Feature",
  "properties": {
    "iso:country":"US",
    "sg:address":"1290 Washington Blvd",
    "sg:city":"Ogden",
    "sg:classifiers":[
        {
            "category":"Restaurant",
            "type":"Food & Drink"
        }
    ],
    "sg:phone":"+1 801 392 9737",
    "sg:postcode":"84404",
    "sg:province":"UT",
    "sg:tags":[
        "eating"
    ],
    "wof:name":"Cowpoke Bbq",
    "wof:placetype":"venue"
},
  "geometry": {"coordinates":[-111.96987,41.244149],"type":"Point"}
}