{
  "type": "Feature",
  "properties": {
    "iso:country":"US",
    "sg:address":"830 Brookside Dr",
    "sg:city":"Springville",
    "sg:classifiers":[
        {
            "category":"Building & Trades",
            "subcategory":"Landscaping Services",
            "type":"Services"
        }
    ],
    "sg:phone":"+1 801 489 3173",
    "sg:postcode":"84663",
    "sg:province":"UT",
    "wof:name":"Toms Landscaping",
    "wof:placetype":"venue"
},
  "geometry": {"coordinates":[-111.595579,40.160604],"type":"Point"}
}