{
  "type": "Feature",
  "properties": {
    "iso:country":"US",
    "sg:address":"496 N 900 E",
    "sg:city":"Provo",
    "sg:classifiers":[
        {
            "category":"Restaurant",
            "type":"Food & Drink"
        }
    ],
    "sg:menulink":"http://www.allmenus.com/ut/provo-orem/86054-little-caesars-pizza/menu/",
    "sg:phone":"+1 801 374 2315",
    "sg:postcode":"84606",
    "sg:province":"UT",
    "sg:tags":[
        "american",
        "pizza"
    ],
    "wof:name":"Little Caesar's Pizza",
    "wof:placetype":"venue"
},
  "geometry": {"coordinates":[-111.64311499999999,40.241233],"type":"Point"}
}