{
  "type": "Feature",
  "properties": {
    "iso:country":"US",
    "sg:address":"1355 N University Ave",
    "sg:city":"Provo",
    "sg:classifiers":[
        {
            "category":"Health Services",
            "subcategory":"Health Practitioner",
            "type":"Services"
        }
    ],
    "sg:phone":"+1 801 221 0223",
    "sg:postcode":"84604",
    "sg:province":"UT",
    "sg:tags":[
        "psychologist"
    ],
    "wof:name":"Preferred Family Clinic",
    "wof:placetype":"venue"
},
  "geometry": {"coordinates":[-111.65867799999999,40.251832],"type":"Point"}
}