{
  "type": "Feature",
  "properties": {
    "iso:country":"US",
    "sg:address":"195 E 100 S",
    "sg:city":"Bicknell",
    "sg:classifiers":[
        {
            "category":"Shopping",
            "subcategory":"Hobbies, Toys, & Games",
            "type":"Retail Goods"
        }
    ],
    "sg:phone":"+1 435 425 3180",
    "sg:postcode":"84715",
    "sg:province":"UT",
    "sg:tags":[
        "craft",
        "supply"
    ],
    "wof:name":"Rummage Creations",
    "wof:placetype":"venue"
},
  "geometry": {"coordinates":[-111.540758,38.339294],"type":"Point"}
}