{
  "type": "Feature",
  "properties": {
    "iso:country":"US",
    "sg:address":"65 W 300 N",
    "sg:city":"Delta",
    "sg:classifiers":[
        {
            "category":"Education",
            "subcategory":"School",
            "type":"Public Place"
        }
    ],
    "sg:phone":"+1 435 864 2160",
    "sg:postcode":"84624",
    "sg:province":"UT",
    "wof:name":"Delta Seminary",
    "wof:placetype":"venue"
},
  "geometry": {"coordinates":[-112.575934,39.35728],"type":"Point"}
}