{
  "type": "Feature",
  "properties": {
    "iso:country":"US",
    "sg:address":"1929 N 400 W",
    "sg:city":"Centerville",
    "sg:classifiers":[
        {
            "category":"Real Estate",
            "subcategory":"Real Estate Agent",
            "type":"Services"
        }
    ],
    "sg:phone":"+1 801 298 4412",
    "sg:postcode":"84014",
    "sg:province":"UT",
    "sg:tags":[
        "management"
    ],
    "wof:name":"J & M Property Control",
    "wof:placetype":"venue"
},
  "geometry": {"coordinates":[-111.886188,40.945262],"type":"Point"}
}