{
  "type": "Feature",
  "properties": {
    "iso:country":"US",
    "sg:address":"849 Greenwood Ter",
    "sg:city":"Salt Lake City",
    "sg:classifiers":[
        {
            "category":"Professional",
            "subcategory":"Business Services",
            "type":"Services"
        }
    ],
    "sg:phone":"+1 801 583 0778",
    "sg:postcode":"84105",
    "sg:province":"UT",
    "sg:tags":[
        "interior",
        "consultant",
        "design",
        "decorator"
    ],
    "wof:name":"Van Dam Jackie Interior Design",
    "wof:placetype":"venue"
},
  "geometry": {"coordinates":[-111.845246,40.749928],"type":"Point"}
}