{
  "type": "Feature",
  "properties": {
    "iso:country":"US",
    "sg:address":"37 S Main St",
    "sg:city":"Manti",
    "sg:classifiers":[
        {
            "category":"Organizations",
            "subcategory":"Religious Organization",
            "type":"Services"
        }
    ],
    "sg:phone":"+1 435 835 7667",
    "sg:postcode":"84642",
    "sg:province":"UT",
    "wof:name":"True & Lving Chrch Chrst Saint",
    "wof:placetype":"venue"
},
  "geometry": {"coordinates":[-111.63690099999999,39.264904],"type":"Point"}
}