{
  "type": "Feature",
  "properties": {
    "iso:country":"US",
    "sg:address":"1850 E 9400 S",
    "sg:city":"Sandy",
    "sg:classifiers":[
        {
            "category":"Restaurant",
            "type":"Food & Drink"
        }
    ],
    "sg:menulink":"http://www.allmenus.com/ut/salt-lake-city/38673-smoky-mountain-pizza--pasta/menu/",
    "sg:phone":"+1 801 523 7070",
    "sg:postcode":"84093",
    "sg:province":"UT",
    "sg:tags":[
        "american",
        "pizza"
    ],
    "wof:name":"Smoky Mountain Pizza & Pasta",
    "wof:placetype":"venue"
},
  "geometry": {"coordinates":[-111.838446,40.580412],"type":"Point"}
}