{
  "type": "Feature",
  "properties": {
    "iso:country":"US",
    "sg:address":"368 E 100 S",
    "sg:city":"Salt Lake City",
    "sg:classifiers":[
        {
            "category":"Restaurant",
            "type":"Food & Drink"
        }
    ],
    "sg:phone":"+1 801 531 1111",
    "sg:postcode":"84111",
    "sg:province":"UT",
    "sg:tags":[
        "eating"
    ],
    "wof:name":"Canton Village",
    "wof:placetype":"venue"
},
  "geometry": {"coordinates":[-111.879706,40.7671],"type":"Point"}
}