{
  "type": "Feature",
  "properties": {
    "iso:country":"US",
    "sg:address":"2050 N Main St",
    "sg:city":"Layton",
    "sg:classifiers":[
        {
            "category":"Banks & Credit Unions",
            "subcategory":"Bank",
            "type":"Services"
        }
    ],
    "sg:phone":"+1 801 776 6203",
    "sg:postcode":"84041",
    "sg:province":"UT",
    "wof:name":"Wells Fargo Bank",
    "wof:placetype":"venue"
},
  "geometry": {"coordinates":[-112.00161,41.089834],"type":"Point"}
}