{
  "type": "Feature",
  "properties": {
    "iso:country":"US",
    "sg:address":"10528 S Columbine Way",
    "sg:city":"Sandy",
    "sg:classifiers":[
        {
            "category":"Real Estate",
            "subcategory":"Architect",
            "type":"Services"
        }
    ],
    "sg:phone":"+1 801 495 9619",
    "sg:postcode":"84094",
    "sg:province":"UT",
    "sg:tags":[
        "architectural"
    ],
    "wof:name":"Tuttle & Assoc Inc",
    "wof:placetype":"venue"
},
  "geometry": {"coordinates":[-111.85728400000001,40.560519],"type":"Point"}
}