{
  "type": "Feature",
  "properties": {
    "iso:country":"US",
    "sg:address":"10685 S 1300 E",
    "sg:city":"Sandy",
    "sg:classifiers":[
        {
            "category":"Wholesale",
            "subcategory":"Non-durable Goods",
            "type":"Manufacturing & Wholesale Goods"
        }
    ],
    "sg:phone":"+1 801 572 5050",
    "sg:postcode":"84094",
    "sg:province":"UT",
    "wof:name":"Johnson Supply Co Inc",
    "wof:placetype":"venue"
},
  "geometry": {"coordinates":[-111.853208,40.557118],"type":"Point"}
}