{
  "type": "Feature",
  "properties": {
    "iso:country":"US",
    "sg:address":"3865 S 3750 W",
    "sg:city":"Ogden",
    "sg:classifiers":[
        {
            "category":"Building & Trades",
            "subcategory":"Construction",
            "type":"Services"
        }
    ],
    "sg:phone":"+1 801 731 0805",
    "sg:postcode":"84401",
    "sg:province":"UT",
    "sg:tags":[
        "contractor"
    ],
    "wof:name":"Simply Roofing LLC",
    "wof:placetype":"venue"
},
  "geometry": {"coordinates":[-112.06838999999999,41.193268],"type":"Point"}
}