{
  "type": "Feature",
  "properties": {
    "iso:country":"US",
    "sg:address":"780 S 2000 W",
    "sg:city":"Syracuse",
    "sg:classifiers":[
        {
            "category":"Real Estate",
            "subcategory":"Real Estate Services",
            "type":"Services"
        }
    ],
    "sg:phone":"+1 801 779 4048",
    "sg:postcode":"84075",
    "sg:province":"UT",
    "sg:tags":[
        "company",
        "title"
    ],
    "wof:name":"Founders Title Co",
    "wof:placetype":"venue"
},
  "geometry": {"coordinates":[-112.064637,41.101909],"type":"Point"}
}