{
  "type": "Feature",
  "properties": {
    "iso:country":"US",
    "sg:address":"58 N 100 E",
    "sg:city":"Roosevelt",
    "sg:classifiers":[
        {
            "category":"Building & Trades",
            "subcategory":"Equipment Rental",
            "type":"Services"
        }
    ],
    "sg:phone":"+1 435 722 2047",
    "sg:postcode":"84066",
    "sg:province":"UT",
    "sg:tags":[
        "oil",
        "well",
        "supply"
    ],
    "wof:name":"Hanover Co",
    "wof:placetype":"venue"
},
  "geometry": {"coordinates":[-109.990267,40.300041],"type":"Point"}
}