{
  "type": "Feature",
  "properties": {
    "iso:country":"US",
    "sg:address":"605 E Tabernacle St",
    "sg:city":"St George",
    "sg:classifiers":[
        {
            "category":"Building & Trades",
            "subcategory":"Construction",
            "type":"Services"
        }
    ],
    "sg:phone":"+1 435 628 1843",
    "sg:postcode":"84770",
    "sg:province":"UT",
    "sg:tags":[
        "specializing",
        "pr",
        "aluminum",
        "contractor",
        "siding",
        "vinyl"
    ],
    "wof:name":"Smart Enterprises Inc",
    "wof:placetype":"venue"
},
  "geometry": {"coordinates":[-113.570498,37.108221],"type":"Point"}
}