{
  "type": "Feature",
  "properties": {
    "iso:country":"US",
    "sg:address":"432 N 300 W",
    "sg:city":"Salt Lake City",
    "sg:classifiers":[
        {
            "category":"Organizations",
            "subcategory":"Non-profit Organization",
            "type":"Services"
        }
    ],
    "sg:phone":"+1 801 364 3138",
    "sg:postcode":"84103",
    "sg:province":"UT",
    "sg:tags":[
        "information",
        "alcoholism",
        "treatment"
    ],
    "wof:name":"Northwest Passage",
    "wof:placetype":"venue"
},
  "geometry": {"coordinates":[-111.89960499999999,40.779061],"type":"Point"}
}