{
  "type": "Feature",
  "properties": {
    "iso:country":"US",
    "sg:address":"45 E 200 N",
    "sg:city":"Spanish Fork",
    "sg:classifiers":[
        {
            "category":"Restaurant",
            "type":"Food & Drink"
        }
    ],
    "sg:phone":"+1 801 798 0794",
    "sg:postcode":"84660",
    "sg:province":"UT",
    "sg:tags":[
        "eating"
    ],
    "wof:name":"Buns N Brews",
    "wof:placetype":"venue"
},
  "geometry": {"coordinates":[-111.654161,40.112527],"type":"Point"}
}