{
  "type": "Feature",
  "properties": {
    "iso:country":"US",
    "sg:address":"13270 S 6665 W",
    "sg:city":"Riverton",
    "sg:classifiers":[
        {
            "category":"Building & Trades",
            "subcategory":"Construction",
            "type":"Services"
        }
    ],
    "sg:phone":"+1 801 302 1132",
    "sg:postcode":"84096",
    "sg:province":"UT",
    "sg:tags":[
        "house",
        "industrial",
        "co"
    ],
    "wof:name":"Cascade Builders Inc",
    "wof:placetype":"venue"
},
  "geometry": {"coordinates":[-112.050004,40.509969],"type":"Point"}
}