{
  "type": "Feature",
  "properties": {
    "iso:country":"US",
    "sg:address":"6415 S 3000 E",
    "sg:city":"Salt Lake City",
    "sg:classifiers":[
        {
            "category":"Banks & Credit Unions",
            "subcategory":"Bank",
            "type":"Services"
        }
    ],
    "sg:phone":"+1 801 733 6304",
    "sg:postcode":"84121",
    "sg:province":"UT",
    "sg:tags":[
        "loan",
        "real estate"
    ],
    "wof:name":"American Home Mortgage",
    "wof:placetype":"venue"
},
  "geometry": {"coordinates":[-111.80596799999999,40.634216],"type":"Point"}
}