{
  "type": "Feature",
  "properties": {
    "iso:country":"US",
    "sg:address":"10450 S State St Ste 1406",
    "sg:city":"Sandy",
    "sg:classifiers":[
        {
            "category":"Personal",
            "subcategory":"Massage",
            "type":"Services"
        },
        {
            "category":"Personal",
            "subcategory":"Beauty Salon",
            "type":"Services"
        },
        {
            "category":"Personal",
            "subcategory":"Barber",
            "type":"Services"
        },
        {
            "category":"Personal",
            "subcategory":"Day Spa",
            "type":"Services"
        },
        {
            "category":"Personal",
            "subcategory":"Skin Care",
            "type":"Services"
        }
    ],
    "sg:phone":"+1 801 495 9252",
    "sg:postcode":"84070",
    "sg:province":"UT",
    "sg:tags":[
        "hair",
        "therapist",
        "stylist"
    ],
    "sg:website":"http://sanctuarysouthtowne.com/",
    "wof:name":"Sanctuary Day Spa",
    "wof:placetype":"venue"
},
  "geometry": {"coordinates":[-111.890931,40.561582],"type":"Point"}
}