{
  "type": "Feature",
  "properties": {
    "iso:country":"US",
    "sg:address":"40 N 300 E",
    "sg:city":"St George",
    "sg:classifiers":[
        {
            "category":"Professional",
            "subcategory":"Research",
            "type":"Services"
        }
    ],
    "sg:phone":"+1 435 628 5528",
    "sg:postcode":"84770",
    "sg:province":"UT",
    "sg:tags":[
        "commercial",
        "physical"
    ],
    "wof:name":"Jean Brown Assoc Inc",
    "wof:placetype":"venue"
},
  "geometry": {"coordinates":[-113.576882,37.109211],"type":"Point"}
}