{
  "type": "Feature",
  "properties": {
    "iso:country":"US",
    "sg:address":"2244 Redondo Ave",
    "sg:city":"Salt Lake City",
    "sg:classifiers":[
        {
            "category":"Building & Trades",
            "subcategory":"Construction",
            "type":"Services"
        }
    ],
    "sg:phone":"+1 801 467 5568",
    "sg:postcode":"84108",
    "sg:province":"UT",
    "sg:tags":[
        "contracting"
    ],
    "wof:name":"Richards Construction Co",
    "wof:placetype":"venue"
},
  "geometry": {"coordinates":[-111.82829599999999,40.726761],"type":"Point"}
}