{
  "type": "Feature",
  "properties": {
    "iso:country":"US",
    "sg:address":"1751 Country Cir",
    "sg:city":"Centerville",
    "sg:classifiers":[
        {
            "category":"Building & Trades",
            "subcategory":"Construction",
            "type":"Services"
        }
    ],
    "sg:phone":"+1 801 298 6388",
    "sg:postcode":"84014",
    "sg:province":"UT",
    "sg:tags":[
        "downspouts",
        "gutter"
    ],
    "wof:name":"Gene's Mobile Svc & Siding",
    "wof:placetype":"venue"
},
  "geometry": {"coordinates":[-111.887541,40.943311],"type":"Point"}
}