{
  "type": "Feature",
  "properties": {
    "iso:country":"US",
    "sg:address":"709 N 400 W Ste 1",
    "sg:city":"North Salt Lake",
    "sg:classifiers":[
        {
            "category":"Building & Trades",
            "subcategory":"Construction",
            "type":"Services"
        }
    ],
    "sg:phone":"+1 801 294 4132",
    "sg:postcode":"84054",
    "sg:province":"UT",
    "sg:tags":[
        "contractor"
    ],
    "wof:name":"American First Builders",
    "wof:placetype":"venue"
},
  "geometry": {"coordinates":[-111.920605,40.855101],"type":"Point"}
}