{
  "type": "Feature",
  "properties": {
    "iso:country":"US",
    "sg:address":"1466 E 4230 S",
    "sg:city":"Holladay",
    "sg:classifiers":[
        {
            "category":"Building & Trades",
            "subcategory":"Construction",
            "type":"Services"
        }
    ],
    "sg:phone":"+1 801 272 6384",
    "sg:postcode":"84124",
    "sg:province":"UT",
    "sg:tags":[
        "general",
        "contractor"
    ],
    "wof:name":"Thornton Construction",
    "wof:placetype":"venue"
},
  "geometry": {"coordinates":[-111.85000700000001,40.679429],"type":"Point"}
}