{
  "type": "Feature",
  "properties": {
    "iso:country":"US",
    "sg:address":"1442 Bus Park Dr",
    "sg:city":"Orem",
    "sg:classifiers":[
        {
            "category":"Wholesale",
            "subcategory":"Groceries",
            "type":"Manufacturing & Wholesale Goods"
        }
    ],
    "sg:phone":"+1 801 225 2152",
    "sg:postcode":"84058",
    "sg:province":"UT",
    "sg:tags":[
        "food",
        "product",
        "health"
    ],
    "sg:website":"www.enaturalcare.com",
    "wof:name":"Natural Care Products Inc",
    "wof:placetype":"venue"
},
  "geometry": {"coordinates":[-111.73030900000001,40.27438],"type":"Point"}
}