{
  "type": "Feature",
  "properties": {
    "iso:country":"US",
    "sg:address":"778 N 1250 W",
    "sg:city":"Centerville",
    "sg:classifiers":[
        {
            "category":"Retail",
            "subcategory":"Veterinary Services",
            "type":"Services"
        }
    ],
    "sg:phone":"+1 801 296 1230",
    "sg:postcode":"84014",
    "sg:province":"UT",
    "sg:tags":[
        "veterinarian"
    ],
    "wof:name":"Orchard Animal Clinic",
    "wof:placetype":"venue"
},
  "geometry": {"coordinates":[-111.896886,40.925701],"type":"Point"}
}