{
  "type": "Feature",
  "properties": {
    "iso:country":"US",
    "sg:address":"7960 W 3500 S",
    "sg:city":"Magna",
    "sg:classifiers":[
        {
            "category":"Professional",
            "type":"Services"
        }
    ],
    "sg:phone":"+1 801 252 7339",
    "sg:postcode":"84044",
    "sg:province":"UT",
    "sg:tags":[
        "establishment"
    ],
    "wof:name":"Justin C Stewart Plaza",
    "wof:placetype":"venue"
},
  "geometry": {"coordinates":[-112.081312,40.696557],"type":"Point"}
}