{
  "type": "Feature",
  "properties": {
    "iso:country":"US",
    "sg:address":"1263 S Carbon Ave",
    "sg:city":"Price",
    "sg:classifiers":[
        {
            "category":"Wholesale",
            "subcategory":"Machinery & Supplies",
            "type":"Manufacturing & Wholesale Goods"
        }
    ],
    "sg:phone":"+1 435 637 5300",
    "sg:postcode":"84501",
    "sg:province":"UT",
    "sg:tags":[
        "equipment",
        "industrial"
    ],
    "wof:name":"United States Welding Inc",
    "wof:placetype":"venue"
},
  "geometry": {"coordinates":[-110.81490700000001,39.582198],"type":"Point"}
}