{
  "type": "Feature",
  "properties": {
    "iso:country":"US",
    "sg:address":"2650 Decker Lake Ln",
    "sg:city":"Salt Lake City",
    "sg:classifiers":[
        {
            "category":"Banks & Credit Unions",
            "subcategory":"Bank",
            "type":"Services"
        }
    ],
    "sg:phone":"+1 801 924 2200",
    "sg:postcode":"84119",
    "sg:province":"UT",
    "sg:tags":[
        "personal",
        "mortgage"
    ],
    "wof:name":"Loan Administration",
    "wof:placetype":"venue"
},
  "geometry": {"coordinates":[-111.94353099999999,40.713694],"type":"Point"}
}