{
  "type": "Feature",
  "properties": {
    "iso:country":"US",
    "sg:address":"377 W 200 S",
    "sg:city":"Vernal",
    "sg:classifiers":[
        {
            "category":"Freight",
            "type":"Transportation"
        }
    ],
    "sg:phone":"+1 435 781 0138",
    "sg:postcode":"84078",
    "sg:province":"UT",
    "sg:tags":[
        "warehouse",
        "self",
        "storage"
    ],
    "wof:name":"Frito Lay Warehouse",
    "wof:placetype":"venue"
},
  "geometry": {"coordinates":[-109.535315,40.45273],"type":"Point"}
}