{
  "type": "Feature",
  "properties": {
    "iso:country":"US",
    "sg:address":"4066 S 4000 W",
    "sg:city":"Salt Lake City",
    "sg:classifiers":[
        {
            "category":"Health Services",
            "subcategory":"Doctor",
            "type":"Services"
        }
    ],
    "sg:phone":"+1 801 968 2864",
    "sg:postcode":"84120",
    "sg:province":"UT",
    "sg:tags":[
        "dentist"
    ],
    "wof:name":"BKP Dental",
    "wof:placetype":"venue"
},
  "geometry": {"coordinates":[-111.986671,40.682674],"type":"Point"}
}