{
  "type": "Feature",
  "properties": {
    "iso:country":"US",
    "sg:address":"684 N 800 West St",
    "sg:city":"Orem",
    "sg:classifiers":[
        {
            "category":"Health Services",
            "subcategory":"Doctor",
            "type":"Services"
        }
    ],
    "sg:phone":"+1 801 224 2250",
    "sg:postcode":"84057",
    "sg:province":"UT",
    "sg:tags":[
        "medical"
    ],
    "wof:name":"Physicial & Spt Therapy Svcs",
    "wof:placetype":"venue"
},
  "geometry": {"coordinates":[-111.71487399999999,40.309158],"type":"Point"}
}