{
  "type": "Feature",
  "properties": {
    "iso:country":"US",
    "sg:address":"575 S 500 W",
    "sg:city":"Bountiful",
    "sg:classifiers":[
        {
            "category":"Manufacturing",
            "subcategory":"Tools & Machinery",
            "type":"Manufacturing & Wholesale Goods"
        }
    ],
    "sg:phone":"+1 801 295 6047",
    "sg:postcode":"84010",
    "sg:province":"UT",
    "sg:tags":[
        "cleaners",
        "household",
        "vacuum"
    ],
    "wof:name":"Mountain Central Vacuum Syst",
    "wof:placetype":"venue"
},
  "geometry": {"coordinates":[-111.892146,40.88374],"type":"Point"}
}