{
  "type": "Feature",
  "properties": {
    "iso:country":"US",
    "sg:address":"725 Colorado St",
    "sg:city":"Salt Lake City",
    "sg:classifiers":[
        {
            "category":"Professional",
            "subcategory":"Computer Services",
            "type":"Services"
        }
    ],
    "sg:phone":"+1 801 575 6609",
    "sg:postcode":"84116",
    "sg:province":"UT",
    "sg:tags":[
        "programing",
        "custom"
    ],
    "wof:name":"Zip Zone Technologies",
    "wof:placetype":"venue"
},
  "geometry": {"coordinates":[-111.929744,40.787818],"type":"Point"}
}