{
  "type": "Feature",
  "properties": {
    "iso:country":"US",
    "sg:address":"3663 Bountiful Blvd",
    "sg:city":"Bountiful",
    "sg:classifiers":[
        {
            "category":"Professional",
            "subcategory":"Business Services",
            "type":"Services"
        }
    ],
    "sg:phone":"+1 801 295 1999",
    "sg:postcode":"84010",
    "sg:province":"UT",
    "wof:name":"C J Technologies Inc",
    "wof:placetype":"venue"
},
  "geometry": {"coordinates":[-111.869793,40.849874],"type":"Point"}
}