{
  "type": "Feature",
  "properties": {
    "iso:country":"US",
    "sg:address":"2829 W 950 N",
    "sg:city":"Provo",
    "sg:classifiers":[
        {
            "category":"Organizations",
            "subcategory":"Labor Organization",
            "type":"Services"
        }
    ],
    "sg:phone":"+1 801 377 0170",
    "sg:postcode":"84601",
    "sg:province":"UT",
    "wof:name":"Bradley Lavona Family Lc",
    "wof:placetype":"venue"
},
  "geometry": {"coordinates":[-111.71162099999999,40.246169],"type":"Point"}
}