{
  "type": "Feature",
  "properties": {
    "iso:country":"US",
    "sg:address":"340 N 200 E",
    "sg:city":"Kanab",
    "sg:classifiers":[
        {
            "category":"Organizations",
            "subcategory":"Religious Organization",
            "type":"Services"
        }
    ],
    "sg:phone":"+1 435 644 3195",
    "sg:postcode":"84741",
    "sg:province":"UT",
    "sg:tags":[
        "church"
    ],
    "wof:name":"Kingdom Hall Of Jehovahs",
    "wof:placetype":"venue"
},
  "geometry": {"coordinates":[-112.52421200000001,37.053442],"type":"Point"}
}