{
  "type": "Feature",
  "properties": {
    "iso:country":"US",
    "sg:address":"3601 S 2700 W",
    "sg:city":"Salt Lake City",
    "sg:classifiers":[
        {
            "category":"Shopping",
            "type":"Retail Goods"
        }
    ],
    "sg:phone":"+1 801 965 8515",
    "sg:postcode":"84119",
    "sg:province":"UT",
    "sg:tags":[
        "tree",
        "christmas",
        "artificial"
    ],
    "wof:name":"Christmas Cottage",
    "wof:placetype":"venue"
},
  "geometry": {"coordinates":[-111.957919,40.69545],"type":"Point"}
}