{
  "type": "Feature",
  "properties": {
    "iso:country":"US",
    "sg:address":"122 W South Temple",
    "sg:city":"Salt Lake City",
    "sg:classifiers":[
        {
            "category":"Travel",
            "subcategory":"Hotels & Motels",
            "type":"Entertainment"
        }
    ],
    "sg:phone":"+1 801 521 0130",
    "sg:postcode":"84101",
    "sg:province":"UT",
    "sg:tags":[
        "operation",
        "eating"
    ],
    "sg:website":"www.plaza-hotel.com",
    "wof:name":"Best Western Inn",
    "wof:placetype":"venue"
},
  "geometry": {"coordinates":[-111.89619,40.769421],"type":"Point"}
}