{
  "type": "Feature",
  "properties": {
    "iso:country":"US",
    "sg:address":"2580 Jefferson Ave",
    "sg:city":"Ogden",
    "sg:classifiers":[
        {
            "category":"Museum",
            "type":"Entertainment"
        }
    ],
    "sg:phone":"+1 801 392 6935",
    "sg:postcode":"84401",
    "sg:province":"UT",
    "sg:tags":[
        "dance",
        "studio",
        "gallery"
    ],
    "wof:name":"Eccles Community Art Center",
    "wof:placetype":"venue"
},
  "geometry": {"coordinates":[-111.964809,41.220192],"type":"Point"}
}