{
  "type": "Feature",
  "properties": {
    "iso:country":"US",
    "sg:address":"1198 Brickyard Rd",
    "sg:city":"Salt Lake City",
    "sg:classifiers":[
        {
            "category":"Shopping",
            "subcategory":"Music",
            "type":"Retail Goods"
        }
    ],
    "sg:phone":"+1 801 487 9928",
    "sg:postcode":"84106",
    "sg:province":"UT",
    "sg:tags":[
        "compact",
        "record",
        "disc",
        "tape"
    ],
    "wof:name":"Musicland",
    "wof:placetype":"venue"
},
  "geometry": {"coordinates":[-111.860195,40.703625],"type":"Point"}
}