{
  "type": "Feature",
  "properties": {
    "iso:country":"US",
    "sg:address":"12660 Fort St",
    "sg:city":"Draper",
    "sg:classifiers":[
        {
            "category":"Banks & Credit Unions",
            "subcategory":"Investment Brokerage",
            "type":"Services"
        }
    ],
    "sg:phone":"+1 801 619 7900",
    "sg:postcode":"84020",
    "sg:province":"UT",
    "sg:tags":[
        "security"
    ],
    "wof:name":"A G Edwards & Sons Inc",
    "wof:placetype":"venue"
},
  "geometry": {"coordinates":[-111.86462400000001,40.521418],"type":"Point"}
}