{
  "type": "Feature",
  "properties": {
    "iso:country":"US",
    "sg:address":"5565 Leo Park Rd",
    "sg:city":"West Jordan",
    "sg:classifiers":[
        {
            "category":"Building & Trades",
            "subcategory":"Plumbing",
            "type":"Services"
        }
    ],
    "sg:phone":"+1 801 280 7473",
    "sg:postcode":"84088",
    "sg:province":"UT",
    "sg:tags":[
        "mechanical",
        "contractor"
    ],
    "wof:name":"C L Wayman Pipeline",
    "wof:placetype":"venue"
},
  "geometry": {"coordinates":[-112.023129,40.580212],"type":"Point"}
}