{
  "type": "Feature",
  "properties": {
    "iso:country":"US",
    "sg:address":"1601 E State St",
    "sg:city":"Lehi",
    "sg:classifiers":[
        {
            "category":"Manufacturing",
            "subcategory":"Furniture",
            "type":"Manufacturing & Wholesale Goods"
        },
        {
            "category":"Home & Garden",
            "subcategory":"Home Furnishings",
            "type":"Retail Goods"
        }
    ],
    "sg:phone":"+1 801 766 0422",
    "sg:postcode":"84043",
    "sg:province":"UT",
    "sg:tags":[
        "venetian",
        "blind",
        "window",
        "shutter",
        "mfg"
    ],
    "wof:name":"Best Buy Blinds and Shutters",
    "wof:placetype":"venue"
},
  "geometry": {"coordinates":[-111.825902,40.388548],"type":"Point"}
}