{
  "type": "Feature",
  "properties": {
    "iso:country":"US",
    "sg:address":"9 Exchange Place, Suite #200 Suite #200",
    "sg:city":"Salt Lake City",
    "sg:classifiers":[
        {
            "category":"Professional",
            "subcategory":"Computer Services",
            "type":"Services"
        }
    ],
    "sg:phone":"+1 801 355 6002",
    "sg:postcode":"84111",
    "sg:province":"UT",
    "sg:website":"http://www.alliancehealthnetworks.com/",
    "wof:name":" Alliance Health Networks",
    "wof:placetype":"venue"
},
  "geometry": {"coordinates":[-111.889791,40.761482],"type":"Point"}
}