{
  "type": "Feature",
  "properties": {
    "iso:country":"US",
    "sg:address":"1128 E 100 S",
    "sg:city":"Lindon",
    "sg:classifiers":[
        {
            "category":"Wholesale",
            "subcategory":"Non-durable Goods",
            "type":"Manufacturing & Wholesale Goods"
        }
    ],
    "sg:phone":"+1 801 785 0455",
    "sg:postcode":"84042",
    "sg:province":"UT",
    "sg:tags":[
        "rep",
        "mfg",
        "advertising",
        "specialty"
    ],
    "wof:name":"Ad Graffics-Frontier Hats",
    "wof:placetype":"venue"
},
  "geometry": {"coordinates":[-111.689719,40.3356],"type":"Point"}
}