{
  "type": "Feature",
  "properties": {
    "iso:country":"US",
    "sg:address":"1064 E 420 S",
    "sg:city":"Provo",
    "sg:classifiers":[
        {
            "category":"Recreation",
            "type":"Entertainment"
        }
    ],
    "sg:phone":"+1 801 223 4662",
    "sg:postcode":"84606",
    "sg:province":"UT",
    "wof:name":"Authentic Wing Chun Kung Fu",
    "wof:placetype":"venue"
},
  "geometry": {"coordinates":[-111.64139299999999,40.227916],"type":"Point"}
}