{
  "type": "Feature",
  "properties": {
    "iso:country":"US",
    "sg:address":"136 Paracle Cir",
    "sg:city":"Farmington",
    "sg:classifiers":[
        {
            "category":"Real Estate",
            "subcategory":"Real Estate Agent",
            "type":"Services"
        }
    ],
    "sg:phone":"+1 801 451 6362",
    "sg:postcode":"84025",
    "sg:province":"UT",
    "wof:name":"Triton LLC",
    "wof:placetype":"venue"
},
  "geometry": {"coordinates":[-111.884291,40.973694],"type":"Point"}
}