{
  "type": "Feature",
  "properties": {
    "iso:country":"US",
    "sg:address":"2072 Rainbow Point Dr",
    "sg:city":"Salt Lake City",
    "sg:classifiers":[
        {
            "category":"Professional",
            "subcategory":"Management & Consulting",
            "type":"Services"
        }
    ],
    "sg:phone":"+1 801 274 9034",
    "sg:postcode":"84124",
    "sg:province":"UT",
    "sg:tags":[
        "business"
    ],
    "wof:name":"Druker Consulting",
    "wof:placetype":"venue"
},
  "geometry": {"coordinates":[-111.830399,40.685589],"type":"Point"}
}