{
  "type": "Feature",
  "properties": {
    "iso:country":"US",
    "sg:address":"2594 S 3270 W",
    "sg:city":"Salt Lake City",
    "sg:classifiers":[
        {
            "category":"Manufacturing",
            "subcategory":"Metals",
            "type":"Manufacturing & Wholesale Goods"
        }
    ],
    "sg:phone":"+1 801 973 2321",
    "sg:postcode":"84119",
    "sg:province":"UT",
    "sg:tags":[
        "coating",
        "powder"
    ],
    "wof:name":"Powder Works",
    "wof:placetype":"venue"
},
  "geometry": {"coordinates":[-111.969285,40.713672],"type":"Point"}
}