{
  "type": "Feature",
  "properties": {
    "iso:country":"US",
    "sg:address":"1340 Carrie Dr",
    "sg:city":"Kaysville",
    "sg:classifiers":[
        {
            "category":"Professional",
            "subcategory":"Advertising",
            "type":"Services"
        }
    ],
    "sg:phone":"+1 801 546 1375",
    "sg:postcode":"84037",
    "sg:province":"UT",
    "sg:tags":[
        "distribution"
    ],
    "sg:website":"www.litegrip.com",
    "wof:name":"Litegrip LLC Co",
    "wof:placetype":"venue"
},
  "geometry": {"coordinates":[-111.907814,41.034058],"type":"Point"}
}