{
  "type": "Feature",
  "properties": {
    "iso:country":"US",
    "sg:address":"2975 S 300 W",
    "sg:city":"Salt Lake City",
    "sg:classifiers":[
        {
            "category":"Manufacturing",
            "subcategory":"Tools & Machinery",
            "type":"Manufacturing & Wholesale Goods"
        }
    ],
    "sg:phone":"+1 801 466 2686",
    "sg:postcode":"84115",
    "sg:province":"UT",
    "sg:tags":[
        "metalworking",
        "product",
        "electric",
        "mfg"
    ],
    "wof:name":"Entec Composite Machines Co",
    "wof:placetype":"venue"
},
  "geometry": {"coordinates":[-111.89962300000001,40.707304],"type":"Point"}
}