{
  "type": "Feature",
  "properties": {
    "iso:country":"US",
    "sg:address":"3055 S State St",
    "sg:city":"South Salt Lake",
    "sg:classifiers":[
        {
            "category":"Arts & Performance",
            "subcategory":"Theater",
            "type":"Entertainment"
        },
        {
            "category":"Bars & Pubs",
            "type":"Food & Drink"
        }
    ],
    "sg:phone":"+1 801 484 4846",
    "sg:postcode":"84115",
    "sg:province":"UT",
    "sg:tags":[
        "entertainer",
        "drinking"
    ],
    "wof:name":"State Street Sociables",
    "wof:placetype":"venue"
},
  "geometry": {"coordinates":[-111.888184,40.703672],"type":"Point"}
}