{
  "type": "Feature",
  "properties": {
    "iso:country":"US",
    "sg:address":"2332 Rockview Dr",
    "sg:city":"Sandy",
    "sg:classifiers":[
        {
            "category":"Building & Trades",
            "subcategory":"Plumbing",
            "type":"Services"
        }
    ],
    "sg:phone":"+1 801 943 4195",
    "sg:postcode":"84092",
    "sg:province":"UT",
    "sg:tags":[
        "mechanical",
        "contractor"
    ],
    "wof:name":"Colt Temperature Ctrl & Tube",
    "wof:placetype":"venue"
},
  "geometry": {"coordinates":[-111.823489,40.567918],"type":"Point"}
}