{
  "type": "Feature",
  "properties": {
    "iso:country":"US",
    "sg:address":"2275 E 9400 S",
    "sg:city":"Sandy",
    "sg:classifiers":[
        {
            "category":"Banks & Credit Unions",
            "subcategory":"Bank",
            "type":"Services"
        }
    ],
    "sg:phone":"+1 801 943 6300",
    "sg:postcode":"84093",
    "sg:province":"UT",
    "sg:tags":[
        "state"
    ],
    "wof:name":"University Utah Credit Union",
    "wof:placetype":"venue"
},
  "geometry": {"coordinates":[-111.826185,40.580173],"type":"Point"}
}