{
  "type": "Feature",
  "properties": {
    "iso:country":"US",
    "sg:address":"10273 S 2165 E",
    "sg:city":"Sandy",
    "sg:classifiers":[
        {
            "category":"Real Estate",
            "subcategory":"Developer",
            "type":"Services"
        }
    ],
    "sg:phone":"+1 801 944 4865",
    "sg:postcode":"84092",
    "sg:province":"UT",
    "wof:name":"Ss Jones Properties LLC",
    "wof:placetype":"venue"
},
  "geometry": {"coordinates":[-111.828953,40.564079],"type":"Point"}
}