{
  "type": "Feature",
  "properties": {
    "iso:country":"US",
    "sg:address":"261 N 1430 E",
    "sg:city":"Logan",
    "sg:classifiers":[
        {
            "category":"Retail",
            "subcategory":"Portrait Studio",
            "type":"Services"
        }
    ],
    "sg:phone":"+1 435 757 8620",
    "sg:postcode":"84321",
    "sg:province":"UT",
    "sg:tags":[
        "photographer",
        "wedding"
    ],
    "wof:name":"Moving Pictures Photography",
    "wof:placetype":"venue"
},
  "geometry": {"coordinates":[-111.798996,41.736989],"type":"Point"}
}