{
  "type": "Feature",
  "properties": {
    "iso:country":"US",
    "sg:address":"1550 N Main St",
    "sg:city":"Logan",
    "sg:classifiers":[
        {
            "category":"Personal",
            "subcategory":"Beauty Salon",
            "type":"Services"
        }
    ],
    "sg:phone":"+1 435 755 0646",
    "sg:postcode":"84341",
    "sg:province":"UT",
    "sg:tags":[
        "shop"
    ],
    "wof:name":"Smart Style",
    "wof:placetype":"venue"
},
  "geometry": {"coordinates":[-111.834233,41.760862],"type":"Point"}
}