{
  "type": "Feature",
  "properties": {
    "iso:country":"US",
    "sg:address":"463 S Main St",
    "sg:city":"Bountiful",
    "sg:classifiers":[
        {
            "category":"Professional",
            "subcategory":"Business Services",
            "type":"Services"
        }
    ],
    "sg:phone":"+1 801 298 1265",
    "sg:postcode":"84010",
    "sg:province":"UT",
    "sg:tags":[
        "personal",
        "bureau",
        "broker",
        "agent"
    ],
    "wof:name":"Straight Chiropractic",
    "wof:placetype":"venue"
},
  "geometry": {"coordinates":[-111.88061999999999,40.884871],"type":"Point"}
}