{
  "type": "Feature",
  "properties": {
    "iso:country":"US",
    "sg:address":"5518 Willow Ln",
    "sg:city":"Murray",
    "sg:classifiers":[
        {
            "category":"Real Estate",
            "subcategory":"Real Estate Operator",
            "type":"Services"
        },
        {
            "category":"Organizations",
            "subcategory":"Community Association",
            "type":"Services"
        }
    ],
    "sg:phone":"+1 801 256 0465",
    "sg:postcode":"84107",
    "sg:province":"UT",
    "sg:tags":[
        "owner",
        "condominium"
    ],
    "wof:name":"Willow Condominium Assn",
    "wof:placetype":"venue"
},
  "geometry": {"coordinates":[-111.87679,40.652057],"type":"Point"}
}