{
  "type": "Feature",
  "properties": {
    "iso:country":"US",
    "sg:address":"22 W Main St",
    "sg:city":"Mount Pleasant",
    "sg:classifiers":[
        {
            "category":"Food & Beverages",
            "subcategory":"Liquor & Beverages",
            "type":"Retail Goods"
        }
    ],
    "sg:phone":"+1 435 462 3258",
    "sg:postcode":"84647",
    "sg:province":"UT",
    "sg:tags":[
        "alcoholic"
    ],
    "wof:name":"Banda Inc",
    "wof:placetype":"venue"
},
  "geometry": {"coordinates":[-111.455687,39.546868],"type":"Point"}
}