{
  "type": "Feature",
  "properties": {
    "iso:country":"US",
    "sg:address":"5383 S 900 E",
    "sg:city":"Salt Lake City",
    "sg:classifiers":[
        {
            "category":"Real Estate",
            "subcategory":"Real Estate Agent",
            "type":"Services"
        }
    ],
    "sg:phone":"+1 801 277 3500",
    "sg:postcode":"84117",
    "sg:province":"UT",
    "wof:name":"Re/Max Metro",
    "wof:placetype":"venue"
},
  "geometry": {"coordinates":[-111.865927,40.654258],"type":"Point"}
}