{
  "type": "Feature",
  "properties": {
    "iso:country":"US",
    "sg:address":"4277 S 700 E",
    "sg:city":"Salt Lake City",
    "sg:classifiers":[
        {
            "category":"Retail",
            "subcategory":"Portrait Studio",
            "type":"Services"
        }
    ],
    "sg:phone":"+1 801 288 0425",
    "sg:postcode":"84107",
    "sg:province":"UT",
    "sg:tags":[
        "photographer",
        "photo"
    ],
    "wof:name":"Courtney Ryan Photography",
    "wof:placetype":"venue"
},
  "geometry": {"coordinates":[-111.871349,40.678881],"type":"Point"}
}