{
  "type": "Feature",
  "properties": {
    "iso:country":"US",
    "sg:address":"514 S 500 W",
    "sg:city":"Provo",
    "sg:classifiers":[
        {
            "category":"Retail",
            "subcategory":"Auto Rental",
            "type":"Services"
        }
    ],
    "sg:phone":"+1 801 377 3699",
    "sg:postcode":"84601",
    "sg:province":"UT",
    "sg:tags":[
        "trailer",
        "utility"
    ],
    "wof:name":"Rent A Toy Inc",
    "wof:placetype":"venue"
},
  "geometry": {"coordinates":[-111.667552,40.226018],"type":"Point"}
}