{
  "type": "Feature",
  "properties": {
    "iso:country":"US",
    "sg:address":"1688 Eastoaks Dr",
    "sg:city":"Kaysville",
    "sg:classifiers":[
        {
            "category":"Food & Beverages",
            "subcategory":"Fruits & Vegetables",
            "type":"Retail Goods"
        }
    ],
    "sg:phone":"+1 801 546 9512",
    "sg:postcode":"84037",
    "sg:province":"UT",
    "sg:tags":[
        "produce"
    ],
    "wof:name":"Starkey Orchards",
    "wof:placetype":"venue"
},
  "geometry": {"coordinates":[-111.89828799999999,41.023227],"type":"Point"}
}