{
  "type": "Feature",
  "properties": {
    "iso:country":"US",
    "sg:address":"2244 E 3500 N",
    "sg:city":"Layton",
    "sg:classifiers":[
        {
            "category":"Wholesale",
            "subcategory":"Medical Equipment & Supplies",
            "type":"Manufacturing & Wholesale Goods"
        }
    ],
    "sg:phone":"+1 801 771 7232",
    "sg:postcode":"84040",
    "sg:province":"UT",
    "wof:name":"Jam Medical Inc",
    "wof:placetype":"venue"
},
  "geometry": {"coordinates":[-111.92239600000001,41.111048],"type":"Point"}
}