{
  "type": "Feature",
  "properties": {
    "iso:country":"US",
    "sg:address":"6991 Commerce Park Dr",
    "sg:city":"Midvale",
    "sg:classifiers":[
        {
            "category":"Wholesale",
            "subcategory":"Machinery & Supplies",
            "type":"Manufacturing & Wholesale Goods"
        }
    ],
    "sg:phone":"+1 801 561 5011",
    "sg:postcode":"84047",
    "sg:province":"UT",
    "sg:tags":[
        "pump"
    ],
    "wof:name":"Reed Supply",
    "wof:placetype":"venue"
},
  "geometry": {"coordinates":[-111.908428,40.623865],"type":"Point"}
}