{
  "type": "Feature",
  "properties": {
    "iso:country":"US",
    "sg:address":"4915 W 650 N",
    "sg:city":"Clearfield",
    "sg:classifiers":[
        {
            "category":"Building & Trades",
            "subcategory":"Construction",
            "type":"Services"
        }
    ],
    "sg:phone":"+1 801 773 9014",
    "sg:postcode":"84015",
    "sg:province":"UT",
    "sg:tags":[
        "house"
    ],
    "wof:name":"Brick Boys Construction Inc",
    "wof:placetype":"venue"
},
  "geometry": {"coordinates":[-112.120695,41.123197],"type":"Point"}
}