{
  "type": "Feature",
  "properties": {
    "iso:country":"US",
    "sg:address":"670 Main St",
    "sg:city":"Coalville",
    "sg:classifiers":[
        {
            "category":"Farming",
            "subcategory":"Farm",
            "type":"Manufacturing & Wholesale Goods"
        }
    ],
    "sg:phone":"+1 435 336 2387",
    "sg:postcode":"84017",
    "sg:province":"UT",
    "sg:tags":[
        "crop",
        "general"
    ],
    "wof:name":"Cedarcrest Farm",
    "wof:placetype":"venue"
},
  "geometry": {"coordinates":[-111.39651600000001,40.934522],"type":"Point"}
}