{
  "type": "Feature",
  "properties": {
    "iso:country":"US",
    "sg:address":"51 E Main St",
    "sg:city":"American Fork",
    "sg:classifiers":[
        {
            "category":"Organizations",
            "subcategory":"Professional Association",
            "type":"Services"
        }
    ],
    "sg:phone":"+1 801 756 5110",
    "sg:postcode":"84003",
    "sg:province":"UT",
    "sg:tags":[
        "chambers",
        "commerce"
    ],
    "wof:name":"American Fork Chamber-Commerce",
    "wof:placetype":"venue"
},
  "geometry": {"coordinates":[-111.796094,40.37685],"type":"Point"}
}