{
  "type": "Feature",
  "properties": {
    "iso:country":"US",
    "sg:address":"8345 Creek Hollow Cove",
    "sg:city":"Sandy",
    "sg:classifiers":[
        {
            "category":"Manufacturing",
            "subcategory":"Electronics",
            "type":"Manufacturing & Wholesale Goods"
        }
    ],
    "sg:phone":"+1 801 947 9001",
    "sg:postcode":"84093",
    "sg:province":"UT",
    "sg:tags":[
        "devices",
        "mfg"
    ],
    "wof:name":"Sandy Semiconductor Inc",
    "wof:placetype":"venue"
},
  "geometry": {"coordinates":[-111.826384,40.601334],"type":"Point"}
}