{
  "type": "Feature",
  "properties": {
    "iso:country":"US",
    "sg:address":"401 N 400 W",
    "sg:city":"North Salt Lake",
    "sg:classifiers":[
        {
            "category":"Building & Trades",
            "subcategory":"Cleaning & Sanitation",
            "type":"Services"
        }
    ],
    "sg:phone":"+1 801 294 2992",
    "sg:postcode":"84054",
    "sg:province":"UT",
    "sg:tags":[
        "maintenance"
    ],
    "wof:name":"Onyx Industrial Services Inc",
    "wof:placetype":"venue"
},
  "geometry": {"coordinates":[-111.920653,40.85052],"type":"Point"}
}