{
  "type": "Feature",
  "properties": {
    "iso:country":"US",
    "sg:address":"171 W 1435 S",
    "sg:city":"Orem",
    "sg:classifiers":[
        {
            "category":"Shopping",
            "subcategory":"Clothing, Apparel, & Fashions",
            "type":"Retail Goods"
        }
    ],
    "sg:phone":"+1 801 226 3296",
    "sg:postcode":"84058",
    "sg:province":"UT",
    "sg:tags":[
        "baby",
        "accessory"
    ],
    "wof:name":"Body Baby",
    "wof:placetype":"venue"
},
  "geometry": {"coordinates":[-111.698662,40.271224],"type":"Point"}
}