{
  "type": "Feature",
  "properties": {
    "iso:country":"US",
    "sg:address":"6216 S State St",
    "sg:city":"Murray",
    "sg:classifiers":[
        {
            "category":"Personal",
            "subcategory":"Beauty Salon",
            "type":"Services"
        }
    ],
    "sg:phone":"+1 801 262 7335",
    "sg:postcode":"84107",
    "sg:province":"UT",
    "sg:tags":[
        "shop"
    ],
    "wof:name":"Salon By Designs",
    "wof:placetype":"venue"
},
  "geometry": {"coordinates":[-111.88947400000001,40.633487],"type":"Point"}
}