{
  "type": "Feature",
  "properties": {
    "iso:country":"US",
    "sg:address":"501 S 1300 E",
    "sg:city":"Provo",
    "sg:classifiers":[
        {
            "category":"Wholesale",
            "subcategory":"Electrical",
            "type":"Manufacturing & Wholesale Goods"
        }
    ],
    "sg:phone":"+1 801 374 5662",
    "sg:postcode":"84606",
    "sg:province":"UT",
    "sg:tags":[
        "equipment",
        "lighting",
        "system"
    ],
    "wof:name":"Orion Outdoor Lighting Inc",
    "wof:placetype":"venue"
},
  "geometry": {"coordinates":[-111.636151,40.227168],"type":"Point"}
}