{
  "type": "Feature",
  "properties": {
    "iso:country":"US",
    "sg:address":"1421 W 1750 N",
    "sg:city":"Layton",
    "sg:classifiers":[
        {
            "category":"Building & Trades",
            "subcategory":"Construction",
            "type":"Services"
        }
    ],
    "sg:phone":"+1 801 776 4325",
    "sg:postcode":"84041",
    "sg:province":"UT",
    "sg:tags":[
        "contractor"
    ],
    "wof:name":"Triangle Masonry Inc",
    "wof:placetype":"venue"
},
  "geometry": {"coordinates":[-111.989729,41.085859],"type":"Point"}
}