{
  "type": "Feature",
  "properties": {
    "iso:country":"US",
    "sg:address":"229 N Pingree Ave",
    "sg:city":"Ogden",
    "sg:classifiers":[
        {
            "category":"Wholesale",
            "subcategory":"Motor Vehicles",
            "type":"Manufacturing & Wholesale Goods"
        }
    ],
    "sg:phone":"+1 801 392 5799",
    "sg:postcode":"84404",
    "sg:province":"UT",
    "wof:name":"Hunter Service",
    "wof:placetype":"venue"
},
  "geometry": {"coordinates":[-111.977073,41.263289],"type":"Point"}
}