{
  "type": "Feature",
  "properties": {
    "iso:country":"US",
    "sg:address":"1771 Siesta Dr",
    "sg:city":"Sandy",
    "sg:classifiers":[
        {
            "category":"Wholesale",
            "subcategory":"Hardware",
            "type":"Manufacturing & Wholesale Goods"
        }
    ],
    "sg:phone":"+1 801 942 3711",
    "sg:postcode":"84093",
    "sg:province":"UT",
    "sg:tags":[
        "plumbing",
        "cooling",
        "heating"
    ],
    "wof:name":"Gt Marketing",
    "wof:placetype":"venue"
},
  "geometry": {"coordinates":[-111.839125,40.610485],"type":"Point"}
}