{
  "type": "Feature",
  "properties": {
    "iso:country":"US",
    "sg:address":"41 N 300 W",
    "sg:city":"Washington",
    "sg:classifiers":[
        {
            "category":"Professional",
            "subcategory":"Business Services",
            "type":"Services"
        }
    ],
    "sg:phone":"+1 435 627 1232",
    "sg:postcode":"84780",
    "sg:province":"UT",
    "wof:name":"Downtowne Vintage Design",
    "wof:placetype":"venue"
},
  "geometry": {"coordinates":[-113.514886,37.130956],"type":"Point"}
}