{
  "type": "Feature",
  "properties": {
    "iso:country":"US",
    "sg:address":"2794 Westerling Way",
    "sg:city":"Salt Lake City",
    "sg:classifiers":[
        {
            "category":"Freight",
            "type":"Transportation"
        }
    ],
    "sg:phone":"+1 801 943 7586",
    "sg:postcode":"84121",
    "sg:province":"UT",
    "sg:tags":[
        "operator",
        "trucking"
    ],
    "wof:name":"Kadlec Joseph Transport",
    "wof:placetype":"venue"
},
  "geometry": {"coordinates":[-111.81139,40.614816],"type":"Point"}
}