{
  "type": "Feature",
  "properties": {
    "iso:country":"US",
    "sg:address":"220 N 2400 E",
    "sg:city":"Layton",
    "sg:classifiers":[
        {
            "category":"Wholesale",
            "subcategory":"Electrical",
            "type":"Manufacturing & Wholesale Goods"
        }
    ],
    "sg:phone":"+1 801 544 7874",
    "sg:postcode":"84040",
    "sg:province":"UT",
    "sg:tags":[
        "florescent",
        "tube",
        "light",
        "bulb"
    ],
    "wof:name":"Lighting West Inc",
    "wof:placetype":"venue"
},
  "geometry": {"coordinates":[-111.920607,41.062055],"type":"Point"}
}