{
  "type": "Feature",
  "properties": {
    "iso:country":"US",
    "sg:address":"4505 Holladay Cir",
    "sg:city":"Salt Lake City",
    "sg:classifiers":[
        {
            "category":"Building & Trades",
            "subcategory":"Construction",
            "type":"Services"
        }
    ],
    "sg:phone":"+1 801 277 4204",
    "sg:postcode":"84117",
    "sg:province":"UT",
    "sg:tags":[
        "contractor"
    ],
    "wof:name":"Just Drywall Repair",
    "wof:placetype":"venue"
},
  "geometry": {"coordinates":[-111.84069599999999,40.67386],"type":"Point"}
}