{
  "type": "Feature",
  "properties": {
    "iso:country":"US",
    "sg:address":"5352 Lucky Clover Ln",
    "sg:city":"Salt Lake City",
    "sg:classifiers":[
        {
            "category":"Professional",
            "subcategory":"Management & Consulting",
            "type":"Services"
        }
    ],
    "sg:phone":"+1 801 269 9006",
    "sg:postcode":"84123",
    "sg:province":"UT",
    "wof:name":"Manufacturing",
    "wof:placetype":"venue"
},
  "geometry": {"coordinates":[-111.915116,40.656246],"type":"Point"}
}