{
  "type": "Feature",
  "properties": {
    "iso:country":"US",
    "sg:address":"15455 N 5400 W",
    "sg:city":"Riverside",
    "sg:classifiers":[
        {
            "category":"Retail",
            "subcategory":"Portrait Studio",
            "type":"Services"
        }
    ],
    "sg:phone":"+1 435 458 3786",
    "sg:postcode":"84334",
    "sg:province":"UT",
    "sg:tags":[
        "photographer"
    ],
    "wof:name":"Mac Farlane Photography",
    "wof:placetype":"venue"
},
  "geometry": {"coordinates":[-112.149553,41.789328],"type":"Point"}
}