{
  "type": "Feature",
  "properties": {
    "iso:country":"US",
    "sg:address":"2429 E Cavalier Dr",
    "sg:city":"Salt Lake City",
    "sg:classifiers":[
        {
            "category":"Building & Trades",
            "subcategory":"Construction",
            "type":"Services"
        }
    ],
    "sg:phone":"+1 801 942 6391",
    "sg:postcode":"84121",
    "sg:province":"UT",
    "sg:tags":[
        "contractor"
    ],
    "wof:name":"Daves Quality Roofing Inc",
    "wof:placetype":"venue"
},
  "geometry": {"coordinates":[-111.82225200000001,40.619363],"type":"Point"}
}