{
  "type": "Feature",
  "properties": {
    "iso:country":"US",
    "sg:address":"30 Thomas Ct",
    "sg:city":"Logan",
    "sg:classifiers":[
        {
            "category":"Organizations",
            "subcategory":"Labor Organization",
            "type":"Services"
        }
    ],
    "sg:phone":"+1 435 752 3215",
    "sg:postcode":"84321",
    "sg:province":"UT",
    "wof:name":"751 North 200 East Lc",
    "wof:placetype":"venue"
},
  "geometry": {"coordinates":[-111.861012,41.727762],"type":"Point"}
}