{
  "type": "Feature",
  "properties": {
    "iso:country":"US",
    "sg:address":"948 US Hwy 89",
    "sg:city":"Panguitch",
    "sg:classifiers":[
        {
            "category":"Utilities",
            "subcategory":"Natural Gas",
            "type":"Services"
        }
    ],
    "sg:phone":"+1 435 676 8180",
    "sg:postcode":"84759",
    "sg:province":"UT",
    "wof:name":"Ameri Gas Inc",
    "wof:placetype":"venue"
},
  "geometry": {"coordinates":[-112.43598799999999,37.832639],"type":"Point"}
}