{
  "type": "Feature",
  "properties": {
    "iso:country":"US",
    "sg:address":"8815 S State St",
    "sg:city":"Sandy",
    "sg:classifiers":[
        {
            "category":"Autos & Motor Vehicles",
            "subcategory":"Automobile Sales",
            "type":"Retail Goods"
        }
    ],
    "sg:phone":"+1 801 255 1314",
    "sg:postcode":"84070",
    "sg:province":"UT",
    "sg:tags":[
        "used"
    ],
    "wof:name":"Midvalley Auto Sales",
    "wof:placetype":"venue"
},
  "geometry": {"coordinates":[-111.890748,40.591445],"type":"Point"}
}