{
  "type": "Feature",
  "properties": {
    "iso:country":"US",
    "sg:address":"2365 N State Rd 32",
    "sg:city":"Kamas",
    "sg:classifiers":[
        {
            "category":"Wholesale",
            "subcategory":"Plants",
            "type":"Manufacturing & Wholesale Goods"
        }
    ],
    "sg:phone":"+1 435 783 4134",
    "sg:postcode":"84036",
    "sg:province":"UT",
    "sg:tags":[
        "supply"
    ],
    "wof:name":"Noles Nursery",
    "wof:placetype":"venue"
},
  "geometry": {"coordinates":[-111.28099899999999,40.679494],"type":"Point"}
}