{
  "type": "Feature",
  "properties": {
    "iso:country":"US",
    "sg:address":"916 W North Temple",
    "sg:city":"Salt Lake City",
    "sg:classifiers":[
        {
            "category":"Restaurant",
            "type":"Food & Drink"
        }
    ],
    "sg:menulink":"http://www.allmenus.com/ut/salt-lake-city/212947-mcdonalds/menu/",
    "sg:phone":"+1 801 521 4211",
    "sg:postcode":"84116",
    "sg:province":"UT",
    "sg:tags":[
        "burger",
        "american"
    ],
    "wof:name":"McDonald's",
    "wof:placetype":"venue"
},
  "geometry": {"coordinates":[-111.91753199999999,40.771496],"type":"Point"}
}