{
  "type": "Feature",
  "properties": {
    "iso:country":"US",
    "sg:address":"529 9th Ave",
    "sg:city":"Midvale",
    "sg:classifiers":[
        {
            "category":"Social Services",
            "type":"Services"
        }
    ],
    "sg:phone":"+1 801 569 1201",
    "sg:postcode":"84047",
    "sg:province":"UT",
    "sg:tags":[
        "shelter",
        "homeless"
    ],
    "sg:website":"www.theroadhome.org",
    "wof:name":"Road Home",
    "wof:placetype":"venue"
},
  "geometry": {"coordinates":[-111.907476,40.618878],"type":"Point"}
}