{
  "type": "Feature",
  "properties": {
    "iso:country":"US",
    "sg:address":"684 E Hwy 40",
    "sg:city":"Roosevelt",
    "sg:classifiers":[
        {
            "category":"Wholesale",
            "subcategory":"Machinery & Supplies",
            "type":"Manufacturing & Wholesale Goods"
        }
    ],
    "sg:phone":"+1 435 722 3722",
    "sg:postcode":"84066",
    "sg:province":"UT",
    "sg:tags":[
        "equipment",
        "irrigation",
        "system"
    ],
    "wof:name":"Intermountain Farmers Irrgtn",
    "wof:placetype":"venue"
},
  "geometry": {"coordinates":[-109.98139399999999,40.302095],"type":"Point"}
}