{
  "type": "Feature",
  "properties": {
    "iso:country":"US",
    "sg:address":"7720 S 480 W",
    "sg:city":"Midvale",
    "sg:classifiers":[
        {
            "category":"Health Services",
            "subcategory":"Chiropractor",
            "type":"Services"
        }
    ],
    "sg:phone":"+1 801 255 3871",
    "sg:postcode":"84047",
    "sg:province":"UT",
    "wof:name":"Joseph P Bell DC",
    "wof:placetype":"venue"
},
  "geometry": {"coordinates":[-111.904512,40.610936],"type":"Point"}
}