{
  "type": "Feature",
  "properties": {
    "iso:country":"US",
    "sg:address":"1385 S 500 W",
    "sg:city":"Bountiful",
    "sg:classifiers":[
        {
            "category":"Professional",
            "subcategory":"Management & Consulting",
            "type":"Services"
        }
    ],
    "sg:phone":"+1 801 292 7226",
    "sg:postcode":"84010",
    "sg:province":"UT",
    "wof:name":"Robintinos Restaurant",
    "wof:placetype":"venue"
},
  "geometry": {"coordinates":[-111.89216999999999,40.874935],"type":"Point"}
}