{
  "type": "Feature",
  "properties": {
    "iso:country":"US",
    "sg:address":"80 S Center St",
    "sg:city":"Elsinore",
    "sg:classifiers":[
        {
            "category":"Building & Trades",
            "subcategory":"Pest Control",
            "type":"Services"
        }
    ],
    "sg:phone":"+1 435 527 1618",
    "sg:postcode":"84724",
    "sg:province":"UT",
    "wof:name":"Bugsmith Termite & Pest Cntrl",
    "wof:placetype":"venue"
},
  "geometry": {"coordinates":[-112.14869400000001,38.681746],"type":"Point"}
}