{
  "type": "Feature",
  "properties": {
    "iso:country":"US",
    "sg:address":"9646 N Shiloh Way",
    "sg:city":"Lehi",
    "sg:classifiers":[
        {
            "category":"Freight",
            "type":"Transportation"
        }
    ],
    "sg:phone":"+1 801 754 3456",
    "sg:postcode":"84043",
    "sg:province":"UT",
    "sg:tags":[
        "operator",
        "trucking"
    ],
    "wof:name":"Mark Baum Trucking",
    "wof:placetype":"venue"
},
  "geometry": {"coordinates":[-111.984582,40.388683],"type":"Point"}
}