{
  "type": "Feature",
  "properties": {
    "iso:country":"US",
    "sg:address":"2010 W 7455 S",
    "sg:city":"West Jordan",
    "sg:classifiers":[
        {
            "category":"Professional",
            "subcategory":"Business Services",
            "type":"Services"
        }
    ],
    "sg:phone":"+1 801 563 5872",
    "sg:postcode":"84084",
    "sg:province":"UT",
    "sg:tags":[
        "embroidery"
    ],
    "wof:name":"Incentives Plus",
    "wof:placetype":"venue"
},
  "geometry": {"coordinates":[-111.944523,40.615872],"type":"Point"}
}