{
  "type": "Feature",
  "properties": {
    "iso:country":"US",
    "sg:address":"14892 Concord Park Dr",
    "sg:city":"Riverton",
    "sg:classifiers":[
        {
            "category":"Building & Trades",
            "subcategory":"Construction",
            "type":"Services"
        }
    ],
    "sg:phone":"+1 801 255 2483",
    "sg:postcode":"84065",
    "sg:province":"UT",
    "sg:tags":[
        "carpentry",
        "contractor"
    ],
    "wof:name":"European Cabinet Co",
    "wof:placetype":"venue"
},
  "geometry": {"coordinates":[-111.911857,40.479387],"type":"Point"}
}