{
  "type": "Feature",
  "properties": {
    "iso:country":"US",
    "sg:address":"461 W 4150 N",
    "sg:city":"Provo",
    "sg:classifiers":[
        {
            "category":"Professional",
            "type":"Services"
        }
    ],
    "sg:phone":"+1 801 222 0626",
    "sg:postcode":"84604",
    "sg:province":"UT",
    "wof:name":"Hydro Safe LLC",
    "wof:placetype":"venue"
},
  "geometry": {"coordinates":[-111.66485900000001,40.288414],"type":"Point"}
}