{
  "type": "Feature",
  "properties": {
    "iso:country":"US",
    "sg:address":"425 W Canyon Rd",
    "sg:city":"Fillmore",
    "sg:classifiers":[
        {
            "category":"Manufacturing",
            "subcategory":"Tools & Machinery",
            "type":"Manufacturing & Wholesale Goods"
        }
    ],
    "sg:phone":"+1 435 743 6329",
    "sg:postcode":"84631",
    "sg:province":"UT",
    "sg:tags":[
        "equipment",
        "mfg",
        "supply"
    ],
    "wof:name":"Larsen Service",
    "wof:placetype":"venue"
},
  "geometry": {"coordinates":[-112.335491,38.964431],"type":"Point"}
}