{
  "type": "Feature",
  "properties": {
    "iso:country":"US",
    "sg:address":"450 E 200 S",
    "sg:city":"Moab",
    "sg:classifiers":[
        {
            "category":"Professional",
            "subcategory":"Computer Services",
            "type":"Services"
        }
    ],
    "sg:phone":"+1 435 259 3180",
    "sg:postcode":"84532",
    "sg:province":"UT",
    "sg:tags":[
        "datum",
        "commercial",
        "desi"
    ],
    "wof:name":"Donegan Graphics",
    "wof:placetype":"venue"
},
  "geometry": {"coordinates":[-109.541918,38.570101],"type":"Point"}
}