{
  "type": "Feature",
  "properties": {
    "iso:country":"US",
    "sg:address":"2465 Progress Dr",
    "sg:city":"West Valley",
    "sg:classifiers":[
        {
            "category":"Wholesale",
            "subcategory":"Hardware",
            "type":"Manufacturing & Wholesale Goods"
        }
    ],
    "sg:phone":"+1 801 972 5011",
    "sg:postcode":"84119",
    "sg:province":"UT",
    "sg:tags":[
        "equipment",
        "heating",
        "system"
    ],
    "sg:website":"www.midgley-huber.com",
    "wof:name":"Midgley-Huber Inc",
    "wof:placetype":"venue"
},
  "geometry": {"coordinates":[-111.944388,40.717233],"type":"Point"}
}