{
  "type": "Feature",
  "properties": {
    "iso:country":"US",
    "sg:address":"6842 Pine Knot Dr",
    "sg:city":"Salt Lake City",
    "sg:classifiers":[
        {
            "category":"Professional",
            "subcategory":"Business Services",
            "type":"Services"
        }
    ],
    "sg:phone":"+1 801 942 0854",
    "sg:postcode":"84121",
    "sg:province":"UT",
    "wof:name":"Fairy Tale Weddings",
    "wof:placetype":"venue"
},
  "geometry": {"coordinates":[-111.853683,40.627639],"type":"Point"}
}