{
  "type": "Feature",
  "properties": {
    "iso:country":"US",
    "sg:address":"1792 S 1175 E",
    "sg:city":"Bountiful",
    "sg:classifiers":[
        {
            "category":"Real Estate",
            "subcategory":"Real Estate Agent",
            "type":"Services"
        }
    ],
    "sg:phone":"+1 801 292 5277",
    "sg:postcode":"84010",
    "sg:province":"UT",
    "wof:name":"Afin Corp",
    "wof:placetype":"venue"
},
  "geometry": {"coordinates":[-111.85694599999999,40.872994],"type":"Point"}
}