{
  "type": "Feature",
  "properties": {
    "iso:country":"US",
    "sg:address":"4651 Riverside Dr",
    "sg:city":"Murray",
    "sg:classifiers":[
        {
            "category":"Retail",
            "subcategory":"Auto Repair",
            "type":"Services"
        }
    ],
    "sg:phone":"+1 801 265 0959",
    "sg:postcode":"84123",
    "sg:province":"UT",
    "sg:tags":[
        "machine",
        "automotive",
        "shop",
        "automobile"
    ],
    "wof:name":"Pro Machine Shop",
    "wof:placetype":"venue"
},
  "geometry": {"coordinates":[-111.905564,40.670819],"type":"Point"}
}