{
  "type": "Feature",
  "properties": {
    "iso:country":"US",
    "sg:address":"3975 Highland Dr",
    "sg:city":"Salt Lake City",
    "sg:classifiers":[
        {
            "category":"Building & Trades",
            "subcategory":"Construction",
            "type":"Services"
        }
    ],
    "sg:phone":"+1 801 424 9752",
    "sg:postcode":"84124",
    "sg:province":"UT",
    "sg:tags":[
        "general",
        "contractor"
    ],
    "wof:name":"Performance Construction",
    "wof:placetype":"venue"
},
  "geometry": {"coordinates":[-111.844336,40.68515],"type":"Point"}
}