{
  "type": "Feature",
  "properties": {
    "iso:country":"US",
    "sg:address":"4149 Persimmon Pl",
    "sg:city":"Salt Lake City",
    "sg:classifiers":[
        {
            "category":"Home & Garden",
            "subcategory":"Hardware",
            "type":"Retail Goods"
        }
    ],
    "sg:phone":"+1 801 266 5530",
    "sg:postcode":"84123",
    "sg:province":"UT",
    "wof:name":"Zertec Services LLC",
    "wof:placetype":"venue"
},
  "geometry": {"coordinates":[-111.93129500000001,40.68049],"type":"Point"}
}