{
  "type": "Feature",
  "properties": {
    "iso:country":"US",
    "sg:address":"2343 E Charros Rd",
    "sg:city":"Sandy",
    "sg:classifiers":[
        {
            "category":"Professional",
            "subcategory":"Business Services",
            "type":"Services"
        }
    ],
    "sg:phone":"+1 801 553 8553",
    "sg:postcode":"84092",
    "sg:province":"UT",
    "wof:name":"Merchant Financial PDT Group",
    "wof:placetype":"venue"
},
  "geometry": {"coordinates":[-111.823706,40.555668],"type":"Point"}
}