{
  "type": "Feature",
  "properties": {
    "iso:country":"US",
    "sg:address":"470 E 3900 S",
    "sg:city":"Salt Lake City",
    "sg:classifiers":[
        {
            "category":"Shopping",
            "type":"Retail Goods"
        }
    ],
    "sg:phone":"+1 801 266 7768",
    "sg:postcode":"84107",
    "sg:province":"UT",
    "sg:tags":[
        "orthopedic",
        "appliance"
    ],
    "sg:website":"www.spotutah.com",
    "wof:name":"SPOT",
    "wof:placetype":"venue"
},
  "geometry": {"coordinates":[-111.877433,40.68699],"type":"Point"}
}