{
  "type": "Feature",
  "properties": {
    "iso:country":"US",
    "sg:address":"1396 Liberty Ave",
    "sg:city":"Ogden",
    "sg:classifiers":[
        {
            "category":"Education",
            "subcategory":"School",
            "type":"Public Place"
        }
    ],
    "sg:phone":"+1 801 625 8865",
    "sg:postcode":"84404",
    "sg:province":"UT",
    "wof:name":"Mound Fort Middle School Inc",
    "wof:placetype":"venue"
},
  "geometry": {"coordinates":[-111.960621,41.241378],"type":"Point"}
}