{
  "type": "Feature",
  "properties": {
    "iso:country":"US",
    "sg:address":"3601 S 2700 W",
    "sg:city":"Salt Lake City",
    "sg:classifiers":[
        {
            "category":"Cinema",
            "subcategory":"Movie Theater",
            "type":"Entertainment"
        }
    ],
    "sg:phone":"+1 801 969 7271",
    "sg:postcode":"84119",
    "sg:province":"UT",
    "wof:name":"Valley Fair Movies 9",
    "wof:placetype":"venue"
},
  "geometry": {"coordinates":[-111.957919,40.69545],"type":"Point"}
}