{
  "type": "Feature",
  "properties": {
    "iso:country":"US",
    "sg:address":"536 Evesham Dr",
    "sg:city":"Salt Lake City",
    "sg:classifiers":[
        {
            "category":"Real Estate",
            "subcategory":"Real Estate Agent",
            "type":"Services"
        }
    ],
    "sg:phone":"+1 801 281 1568",
    "sg:postcode":"84107",
    "sg:province":"UT",
    "wof:name":"Parkcrest Realty",
    "wof:placetype":"venue"
},
  "geometry": {"coordinates":[-111.87577400000001,40.642454],"type":"Point"}
}