{
  "type": "Feature",
  "properties": {
    "iso:country":"US",
    "sg:address":"2374 N 850 W",
    "sg:city":"Provo",
    "sg:classifiers":[
        {
            "category":"Shopping",
            "subcategory":"Clothing, Apparel, & Fashions",
            "type":"Retail Goods"
        }
    ],
    "sg:phone":"+1 801 375 1441",
    "sg:postcode":"84604",
    "sg:province":"UT",
    "sg:tags":[
        "shop",
        "bridal"
    ],
    "wof:name":"Sharilyn's Bridal Designs",
    "wof:placetype":"venue"
},
  "geometry": {"coordinates":[-111.673562,40.266648],"type":"Point"}
}