{
  "type": "Feature",
  "properties": {
    "iso:country":"US",
    "sg:address":"1244 N Main St",
    "sg:city":"Tooele",
    "sg:classifiers":[
        {
            "category":"Health Services",
            "subcategory":"Chiropractor",
            "type":"Services"
        }
    ],
    "sg:phone":"+1 435 833 9200",
    "sg:postcode":"84074",
    "sg:province":"UT",
    "wof:name":"Tooele Valley Spine Ctr",
    "wof:placetype":"venue"
},
  "geometry": {"coordinates":[-112.297321,40.55607],"type":"Point"}
}