{
  "type": "Feature",
  "properties": {
    "iso:country":"US",
    "sg:address":"5462 S 200 W",
    "sg:city":"Ogden",
    "sg:classifiers":[
        {
            "category":"Professional",
            "subcategory":"Management & Consulting",
            "type":"Services"
        }
    ],
    "sg:phone":"+1 801 475 0697",
    "sg:postcode":"84405",
    "sg:province":"UT",
    "sg:tags":[
        "public",
        "relations"
    ],
    "wof:name":"Smart Pro",
    "wof:placetype":"venue"
},
  "geometry": {"coordinates":[-111.981295,41.164659],"type":"Point"}
}