{
  "type": "Feature",
  "properties": {
    "iso:country":"US",
    "sg:address":"47 W Forest St",
    "sg:city":"Brigham City",
    "sg:classifiers":[
        {
            "category":"Health Services",
            "subcategory":"Doctor",
            "type":"Services"
        }
    ],
    "sg:phone":"+1 435 723 5297",
    "sg:postcode":"84302",
    "sg:province":"UT",
    "sg:tags":[
        "medical"
    ],
    "wof:name":"D L Bunderson MD",
    "wof:placetype":"venue"
},
  "geometry": {"coordinates":[-112.01641100000001,41.510317],"type":"Point"}
}