{
  "type": "Feature",
  "properties": {
    "iso:country":"US",
    "sg:address":"779 S Bluff St",
    "sg:city":"St George",
    "sg:classifiers":[
        {
            "category":"Shopping",
            "subcategory":"Books",
            "type":"Retail Goods"
        }
    ],
    "sg:phone":"+1 435 628 4495",
    "sg:postcode":"84770",
    "sg:province":"UT",
    "wof:name":"Deseret Book Store",
    "wof:placetype":"venue"
},
  "geometry": {"coordinates":[-113.586646,37.095524],"type":"Point"}
}