{
  "type": "Feature",
  "properties": {
    "iso:country":"US",
    "sg:address":"12569 S 2700 W",
    "sg:city":"Riverton",
    "sg:classifiers":[
        {
            "category":"Building & Trades",
            "subcategory":"Construction",
            "type":"Services"
        }
    ],
    "sg:phone":"+1 801 254 2560",
    "sg:postcode":"84065",
    "sg:province":"UT",
    "sg:tags":[
        "general",
        "contractor"
    ],
    "sg:website":"www.royalviewhomes.com",
    "wof:name":"Royal View Homes",
    "wof:placetype":"venue"
},
  "geometry": {"coordinates":[-111.957646,40.524978],"type":"Point"}
}