{
  "type": "Feature",
  "properties": {
    "iso:country":"US",
    "sg:address":"963 Stowe Dr",
    "sg:city":"Ogden",
    "sg:classifiers":[
        {
            "category":"Building & Trades",
            "subcategory":"Construction",
            "type":"Services"
        }
    ],
    "sg:phone":"+1 801 725 9385",
    "sg:postcode":"84404",
    "sg:province":"UT",
    "sg:tags":[
        "roofing",
        "siding",
        "work",
        "contractor",
        "gutter"
    ],
    "wof:name":"Millenium Builders Inc",
    "wof:placetype":"venue"
},
  "geometry": {"coordinates":[-111.934017,41.245949],"type":"Point"}
}