{
  "type": "Feature",
  "properties": {
    "iso:country":"US",
    "sg:address":"8548 Scottish Dr",
    "sg:city":"Sandy",
    "sg:classifiers":[
        {
            "category":"Communications",
            "subcategory":"Film & Video Production",
            "type":"Services"
        }
    ],
    "sg:phone":"+1 801 943 6585",
    "sg:postcode":"84093",
    "sg:province":"UT",
    "sg:tags":[
        "motion"
    ],
    "wof:name":"Ideaday Productions Inc",
    "wof:placetype":"venue"
},
  "geometry": {"coordinates":[-111.80327,40.596342],"type":"Point"}
}