{
  "type": "Feature",
  "properties": {
    "iso:country":"US",
    "sg:address":"2690 E 2100 S",
    "sg:city":"Salt Lake City",
    "sg:classifiers":[
        {
            "category":"Manufacturing",
            "subcategory":"Chemicals & Compounds",
            "type":"Manufacturing & Wholesale Goods"
        }
    ],
    "sg:phone":"+1 801 463 6511",
    "sg:postcode":"84109",
    "sg:province":"UT",
    "sg:tags":[
        "miller",
        "drug"
    ],
    "wof:name":"Mitchell & Mitchell Corp",
    "wof:placetype":"venue"
},
  "geometry": {"coordinates":[-111.814561,40.725744],"type":"Point"}
}