{
  "type": "Feature",
  "properties": {
    "iso:country":"US",
    "sg:address":"4001 S 700 E",
    "sg:city":"Salt Lake City",
    "sg:classifiers":[
        {
            "category":"Insurance",
            "subcategory":"Health Insurance",
            "type":"Services"
        }
    ],
    "sg:phone":"+1 801 262 0171",
    "sg:postcode":"84107",
    "sg:province":"UT",
    "sg:tags":[
        "agency"
    ],
    "wof:name":"UNUM Life Insurance Co Amer",
    "wof:placetype":"venue"
},
  "geometry": {"coordinates":[-111.87129,40.683391],"type":"Point"}
}