{
  "type": "Feature",
  "properties": {
    "iso:country":"US",
    "sg:address":"150 E Center St",
    "sg:city":"Spanish Fork",
    "sg:classifiers":[
        {
            "category":"Health Services",
            "subcategory":"Nursing And Care Facility",
            "type":"Services"
        }
    ],
    "sg:phone":"+1 801 661 0726",
    "sg:postcode":"84660",
    "sg:province":"UT",
    "wof:name":"Hales Resthome Inc",
    "wof:placetype":"venue"
},
  "geometry": {"coordinates":[-111.65230699999999,40.109744],"type":"Point"}
}