{
  "type": "Feature",
  "properties": {
    "iso:country":"US",
    "sg:address":"504 E Main St",
    "sg:city":"Price",
    "sg:classifiers":[
        {
            "category":"Autos & Motor Vehicles",
            "subcategory":"Fuel & Gas Station",
            "type":"Retail Goods"
        },
        {
            "category":"Retail",
            "subcategory":"Auto Repair",
            "type":"Services"
        }
    ],
    "sg:phone":"+1 435 637 8120",
    "sg:postcode":"84501",
    "sg:province":"UT",
    "sg:tags":[
        "repairing",
        "automobile",
        "station",
        "gasoline",
        "supply"
    ],
    "wof:name":"John's Auto-Tech & Tire",
    "wof:placetype":"venue"
},
  "geometry": {"coordinates":[-110.801621,39.599496],"type":"Point"}
}