{
  "type": "Feature",
  "properties": {
    "iso:country":"US",
    "sg:address":"480 W 800 N",
    "sg:city":"Orem",
    "sg:classifiers":[
        {
            "category":"Banks & Credit Unions",
            "subcategory":"Investment Brokerage",
            "type":"Services"
        }
    ],
    "sg:phone":"+1 801 226 6036",
    "sg:postcode":"84057",
    "sg:province":"UT",
    "sg:tags":[
        "consultant",
        "planning",
        "financial"
    ],
    "wof:name":"Payne Financial Management",
    "wof:placetype":"venue"
},
  "geometry": {"coordinates":[-111.709795,40.312138],"type":"Point"}
}