{
  "type": "Feature",
  "properties": {
    "iso:country":"US",
    "sg:address":"1327 S 800 E",
    "sg:city":"Orem",
    "sg:classifiers":[
        {
            "category":"Professional",
            "subcategory":"Lawyer & Legal Services",
            "type":"Services"
        }
    ],
    "sg:phone":"+1 801 229 1805",
    "sg:postcode":"84097",
    "sg:province":"UT",
    "wof:name":"Burton Rulon T",
    "wof:placetype":"venue"
},
  "geometry": {"coordinates":[-111.675971,40.272656],"type":"Point"}
}