{
  "type": "Feature",
  "properties": {
    "iso:country":"US",
    "sg:address":"308 E 4500 S",
    "sg:city":"Salt Lake City",
    "sg:classifiers":[
        {
            "category":"Real Estate",
            "subcategory":"Developer",
            "type":"Services"
        }
    ],
    "sg:phone":"+1 801 281 2223",
    "sg:postcode":"84107",
    "sg:province":"UT",
    "wof:name":"Cold Springs At Red Hawk Ranch",
    "wof:placetype":"venue"
},
  "geometry": {"coordinates":[-111.88186399999999,40.674248],"type":"Point"}
}