{
  "type": "Feature",
  "properties": {
    "iso:country":"US",
    "sg:address":"505 N Kays Dr",
    "sg:city":"Kaysville",
    "sg:classifiers":[
        {
            "category":"Food & Beverages",
            "subcategory":"Specialty",
            "type":"Retail Goods"
        }
    ],
    "sg:phone":"+1 801 546 3262",
    "sg:postcode":"84037",
    "sg:province":"UT",
    "sg:tags":[
        "control",
        "product",
        "weight"
    ],
    "wof:name":"Lean & Free",
    "wof:placetype":"venue"
},
  "geometry": {"coordinates":[-111.956878,41.037628],"type":"Point"}
}