{
  "type": "Feature",
  "properties": {
    "iso:country":"US",
    "sg:address":"116 S Main St",
    "sg:city":"Monticello",
    "sg:classifiers":[
        {
            "category":"Shopping",
            "subcategory":"Gifts & Souvenirs",
            "type":"Retail Goods"
        }
    ],
    "sg:phone":"+1 435 587 3355",
    "sg:postcode":"84535",
    "sg:province":"UT",
    "sg:tags":[
        "shop"
    ],
    "wof:name":"Unique Creations",
    "wof:placetype":"venue"
},
  "geometry": {"coordinates":[-109.343046,37.870959],"type":"Point"}
}