{
  "type": "Feature",
  "properties": {
    "iso:country":"US",
    "sg:address":"3260 S Eldredge St",
    "sg:city":"Salt Lake City",
    "sg:classifiers":[
        {
            "category":"Wholesale",
            "subcategory":"Machinery & Supplies",
            "type":"Manufacturing & Wholesale Goods"
        },
        {
            "category":"Retail",
            "subcategory":"Repair Shop",
            "type":"Services"
        }
    ],
    "sg:phone":"+1 801 832 9700",
    "sg:postcode":"84115",
    "sg:province":"UT",
    "sg:tags":[
        "transportation",
        "trade",
        "equipment",
        "s",
        "contractor",
        "welding"
    ],
    "wof:name":"Custom Propeller & Marine Inc",
    "wof:placetype":"venue"
},
  "geometry": {"coordinates":[-111.901172,40.700935],"type":"Point"}
}