{
  "type": "Feature",
  "properties": {
    "iso:country":"US",
    "sg:address":"9653 S 700 E",
    "sg:city":"Sandy",
    "sg:classifiers":[
        {
            "category":"Professional",
            "subcategory":"Accounting & Tax Preparation",
            "type":"Services"
        }
    ],
    "sg:phone":"+1 801 565 1201",
    "sg:postcode":"84070",
    "sg:province":"UT",
    "sg:tags":[
        "accountant"
    ],
    "wof:name":"Springer & Company Inc",
    "wof:placetype":"venue"
},
  "geometry": {"coordinates":[-111.872117,40.576181],"type":"Point"}
}