{
  "type": "Feature",
  "properties": {
    "iso:country":"US",
    "sg:address":"114 W 1300 S",
    "sg:city":"Salt Lake City",
    "sg:classifiers":[
        {
            "category":"Food & Beverages",
            "subcategory":"Groceries & Convenience Stores",
            "type":"Retail Goods"
        }
    ],
    "sg:phone":"+1 801 485 8049",
    "sg:postcode":"84115",
    "sg:province":"UT",
    "wof:name":"7-Eleven",
    "wof:placetype":"venue"
},
  "geometry": {"coordinates":[-111.891203,40.741687],"type":"Point"}
}