{
  "type": "Feature",
  "properties": {
    "iso:country":"US",
    "sg:address":"111 E Telegraph St",
    "sg:city":"Washington",
    "sg:classifiers":[
        {
            "category":"Personal",
            "subcategory":"Beauty Salon",
            "type":"Services"
        }
    ],
    "sg:phone":"+1 435 673 3291",
    "sg:postcode":"84780",
    "sg:province":"UT",
    "sg:tags":[
        "shop",
        "barber"
    ],
    "wof:name":"Mikes Barber & Beauty Shop",
    "wof:placetype":"venue"
},
  "geometry": {"coordinates":[-113.50752,37.130347],"type":"Point"}
}