{
  "type": "Feature",
  "properties": {
    "iso:country":"US",
    "sg:address":"1828 Fort Canyon Rd",
    "sg:city":"Alpine",
    "sg:classifiers":[
        {
            "category":"Arts & Performance",
            "subcategory":"Theater",
            "type":"Entertainment"
        }
    ],
    "sg:phone":"+1 801 232 0905",
    "sg:postcode":"84004",
    "sg:province":"UT",
    "sg:tags":[
        "group"
    ],
    "wof:name":"5 Browns Inc",
    "wof:placetype":"venue"
},
  "geometry": {"coordinates":[-111.78274399999999,40.477049],"type":"Point"}
}