{
  "type": "Feature",
  "properties": {
    "iso:country":"US",
    "sg:address":"86 Allegiance Cir",
    "sg:city":"Evanston",
    "sg:classifiers":[
        {
            "category":"Mining & Drilling",
            "type":"Manufacturing & Wholesale Goods"
        }
    ],
    "sg:phone":"+1 307 783 8300",
    "sg:postcode":"82930",
    "sg:province":"UT",
    "sg:tags":[
        "well"
    ],
    "wof:name":"Wahsatch Gathering Systems",
    "wof:placetype":"venue"
},
  "geometry": {"coordinates":[-110.99527399999999,41.259487],"type":"Point"}
}