{
  "type": "Feature",
  "properties": {
    "iso:country":"US",
    "sg:address":"1450 S 2000 W",
    "sg:city":"Syracuse",
    "sg:classifiers":[
        {
            "category":"Education",
            "subcategory":"School",
            "type":"Public Place"
        }
    ],
    "sg:phone":"+1 801 402 6800",
    "sg:postcode":"84075",
    "sg:province":"UT",
    "wof:name":"Syracuse Junior High Schl 420",
    "wof:placetype":"venue"
},
  "geometry": {"coordinates":[-112.064652,41.091855],"type":"Point"}
}