{
  "type": "Feature",
  "properties": {
    "iso:country":"US",
    "sg:address":"978 Industrial Park Dr",
    "sg:city":"Orem",
    "sg:classifiers":[
        {
            "category":"Communications",
            "type":"Services"
        }
    ],
    "sg:phone":"+1 801 434 4025",
    "sg:postcode":"84057",
    "sg:province":"UT",
    "wof:name":"Cleartek Communications",
    "wof:placetype":"venue"
},
  "geometry": {"coordinates":[-111.727976,40.314736],"type":"Point"}
}