{
  "type": "Feature",
  "properties": {
    "iso:country":"US",
    "sg:address":"1090 S 1100 E",
    "sg:city":"Salt Lake City",
    "sg:classifiers":[
        {
            "category":"Education",
            "subcategory":"Special Training",
            "type":"Public Place"
        }
    ],
    "sg:phone":"+1 801 582 7915",
    "sg:postcode":"84105",
    "sg:province":"UT",
    "sg:tags":[
        "program"
    ],
    "wof:name":"Mortgage Educators",
    "wof:placetype":"venue"
},
  "geometry": {"coordinates":[-111.859635,40.745133],"type":"Point"}
}