{
  "type": "Feature",
  "properties": {
    "iso:country":"US",
    "sg:address":"4732 S 1950 W",
    "sg:city":"Salt Lake City",
    "sg:classifiers":[
        {
            "category":"Social Services",
            "subcategory":"Child Care",
            "type":"Services"
        }
    ],
    "sg:phone":"+1 801 955 8988",
    "sg:postcode":"84118",
    "sg:province":"UT",
    "wof:name":"Lit'l Scholars Daycare",
    "wof:placetype":"venue"
},
  "geometry": {"coordinates":[-111.943338,40.665861],"type":"Point"}
}