{
  "type": "Feature",
  "properties": {
    "iso:country":"US",
    "sg:address":"1050 E 3300 S",
    "sg:city":"Salt Lake City",
    "sg:classifiers":[
        {
            "category":"Professional",
            "subcategory":"Lawyer & Legal Services",
            "type":"Services"
        }
    ],
    "sg:phone":"+1 801 487 0704",
    "sg:postcode":"84106",
    "sg:province":"UT",
    "sg:tags":[
        "attorney"
    ],
    "wof:name":"Mark H Gould",
    "wof:placetype":"venue"
},
  "geometry": {"coordinates":[-111.860997,40.699815],"type":"Point"}
}