{
  "type": "Feature",
  "properties": {
    "iso:country":"US",
    "sg:address":"604 Woodside Ave",
    "sg:city":"Park City",
    "sg:classifiers":[
        {
            "category":"Banks & Credit Unions",
            "subcategory":"Financial Services",
            "type":"Services"
        }
    ],
    "sg:phone":"+1 435 658 5790",
    "sg:postcode":"84060",
    "sg:province":"UT",
    "sg:tags":[
        "company",
        "holding"
    ],
    "wof:name":"Park City Holdings LLC",
    "wof:placetype":"venue"
},
  "geometry": {"coordinates":[-111.497693,40.644157],"type":"Point"}
}