{
  "type": "Feature",
  "properties": {
    "iso:country":"US",
    "sg:address":"2253 S 500 E",
    "sg:city":"Salt Lake City",
    "sg:classifiers":[
        {
            "category":"Shopping",
            "type":"Retail Goods"
        }
    ],
    "sg:phone":"+1 801 466 3559",
    "sg:postcode":"84106",
    "sg:province":"UT",
    "sg:tags":[
        "merchandise"
    ],
    "wof:name":"Christopher Radko Co",
    "wof:placetype":"venue"
},
  "geometry": {"coordinates":[-111.87675299999999,40.721056],"type":"Point"}
}