{
  "type": "Feature",
  "properties": {
    "iso:country":"US",
    "sg:address":"108 N 300 E",
    "sg:city":"Roosevelt",
    "sg:classifiers":[
        {
            "category":"Home & Garden",
            "subcategory":"Carpets & Floor Coverings",
            "type":"Retail Goods"
        }
    ],
    "sg:phone":"+1 435 722 9185",
    "sg:postcode":"84066",
    "sg:province":"UT",
    "sg:tags":[
        "dealer",
        "rug"
    ],
    "wof:name":"Doug Gilley's Carpets",
    "wof:placetype":"venue"
},
  "geometry": {"coordinates":[-109.987263,40.302017],"type":"Point"}
}