{
  "type": "Feature",
  "properties": {
    "iso:country":"US",
    "sg:address":"1660 N 50 E",
    "sg:city":"Orem",
    "sg:classifiers":[
        {
            "category":"Education",
            "subcategory":"School",
            "type":"Public Place"
        }
    ],
    "sg:phone":"+1 801 227 8720",
    "sg:postcode":"84057",
    "sg:province":"UT",
    "sg:website":"www.alpine.k12.ut.us",
    "wof:name":"North Ridge Elementary School",
    "wof:placetype":"venue"
},
  "geometry": {"coordinates":[-111.69525299999999,40.327612],"type":"Point"}
}