{
  "type": "Feature",
  "properties": {
    "iso:country":"US",
    "sg:address":"16 S 300 W",
    "sg:city":"St George",
    "sg:classifiers":[
        {
            "category":"Education",
            "subcategory":"School",
            "type":"Public Place"
        }
    ],
    "sg:phone":"+1 435 674 6464",
    "sg:postcode":"84770",
    "sg:province":"UT",
    "sg:tags":[
        "educational"
    ],
    "wof:name":"Alternative Language",
    "wof:placetype":"venue"
},
  "geometry": {"coordinates":[-113.58978,37.107976],"type":"Point"}
}