{
  "type": "Feature",
  "properties": {
    "iso:country":"US",
    "sg:address":"762 N 1890 W",
    "sg:city":"Provo",
    "sg:classifiers":[
        {
            "category":"Professional",
            "subcategory":"Testing Lab",
            "type":"Services"
        }
    ],
    "sg:phone":"+1 801 691 0406",
    "sg:postcode":"84601",
    "sg:province":"UT",
    "sg:tags":[
        "analytical",
        "laboratory"
    ],
    "wof:name":"Rand Labs",
    "wof:placetype":"venue"
},
  "geometry": {"coordinates":[-111.690133,40.244002],"type":"Point"}
}