{
  "type": "Feature",
  "properties": {
    "iso:country":"US",
    "sg:address":"1769 Wasatch Dr",
    "sg:city":"Salt Lake City",
    "sg:classifiers":[
        {
            "category":"Banks & Credit Unions",
            "subcategory":"Financial Services",
            "type":"Services"
        }
    ],
    "sg:phone":"+1 801 467 0390",
    "sg:postcode":"84108",
    "sg:province":"UT",
    "sg:tags":[
        "investment",
        "closed"
    ],
    "wof:name":"Paschal Investment Company",
    "wof:placetype":"venue"
},
  "geometry": {"coordinates":[-111.815528,40.73329],"type":"Point"}
}