{
  "type": "Feature",
  "properties": {
    "iso:country":"US",
    "sg:address":"4251 S 4800 W",
    "sg:city":"Salt Lake City",
    "sg:classifiers":[
        {
            "category":"Organizations",
            "subcategory":"Religious Organization",
            "type":"Services"
        }
    ],
    "sg:phone":"+1 801 964 7254",
    "sg:postcode":"84120",
    "sg:province":"UT",
    "sg:tags":[
        "mormon",
        "church"
    ],
    "wof:name":"Ridgeland Ward",
    "wof:placetype":"venue"
},
  "geometry": {"coordinates":[-112.005652,40.677481],"type":"Point"}
}