{
  "type": "Feature",
  "properties": {
    "iso:country":"US",
    "sg:address":"2040 S 2300 E",
    "sg:city":"Salt Lake City",
    "sg:classifiers":[
        {
            "category":"Banks & Credit Unions",
            "subcategory":"Bank",
            "type":"Services"
        }
    ],
    "sg:phone":"+1 801 246 4955",
    "sg:postcode":"84108",
    "sg:province":"UT",
    "wof:name":"Wells Fargo Bank",
    "wof:placetype":"venue"
},
  "geometry": {"coordinates":[-111.825154,40.726029],"type":"Point"}
}