{
  "type": "Feature",
  "properties": {
    "iso:country":"US",
    "sg:address":"3707 N Canyon Rd",
    "sg:city":"Provo",
    "sg:classifiers":[
        {
            "category":"Real Estate",
            "subcategory":"Real Estate Agent",
            "type":"Services"
        }
    ],
    "sg:phone":"+1 801 226 2424",
    "sg:postcode":"84604",
    "sg:province":"UT",
    "wof:name":"Flying J Inc Real Estate",
    "wof:placetype":"venue"
},
  "geometry": {"coordinates":[-111.651877,40.282559],"type":"Point"}
}