{
  "type": "Feature",
  "properties": {
    "iso:country":"US",
    "sg:address":"210 N Main St",
    "sg:city":"Panguitch",
    "sg:classifiers":[
        {
            "category":"Travel",
            "subcategory":"Hotels & Motels",
            "type":"Entertainment"
        }
    ],
    "sg:phone":"+1 435 676 8296",
    "sg:postcode":"84759",
    "sg:province":"UT",
    "sg:tags":[
        "resort"
    ],
    "wof:name":"Canyon Lodge Motel",
    "wof:placetype":"venue"
},
  "geometry": {"coordinates":[-112.43558400000001,37.82598],"type":"Point"}
}