{
  "type": "Feature",
  "properties": {
    "iso:country":"US",
    "sg:address":"1265 Sunset Dr",
    "sg:city":"Salt Lake City",
    "sg:classifiers":[
        {
            "category":"Professional",
            "type":"Services"
        }
    ],
    "sg:phone":"+1 801 363 8483",
    "sg:postcode":"84116",
    "sg:province":"UT",
    "wof:name":"Betty J Anderson",
    "wof:placetype":"venue"
},
  "geometry": {"coordinates":[-111.928704,40.798626],"type":"Point"}
}