{
  "type": "Feature",
  "properties": {
    "iso:country":"US",
    "sg:address":"8015 S 3530 W",
    "sg:city":"West Jordan",
    "sg:classifiers":[
        {
            "category":"Food & Beverages",
            "subcategory":"Specialty",
            "type":"Retail Goods"
        }
    ],
    "sg:phone":"+1 801 561 5712",
    "sg:postcode":"84088",
    "sg:province":"UT",
    "sg:tags":[
        "tea",
        "coffee"
    ],
    "wof:name":"Brew Monkey Coffee House",
    "wof:placetype":"venue"
},
  "geometry": {"coordinates":[-111.975132,40.605886],"type":"Point"}
}