{
  "type": "Feature",
  "properties": {
    "iso:country":"US",
    "sg:address":"12 W Forest St",
    "sg:city":"Brigham City",
    "sg:classifiers":[
        {
            "category":"Building & Trades",
            "subcategory":"Plumbing",
            "type":"Services"
        }
    ],
    "sg:phone":"+1 435 723 2150",
    "sg:postcode":"84302",
    "sg:province":"UT",
    "sg:tags":[
        "contractor"
    ],
    "wof:name":"Brigham Heating & Cooling",
    "wof:placetype":"venue"
},
  "geometry": {"coordinates":[-112.01586,41.510479],"type":"Point"}
}