{
  "type": "Feature",
  "properties": {
    "iso:country":"US",
    "sg:address":"Snowbird Entry 3 Route 210",
    "sg:city":"Sandy",
    "sg:classifiers":[
        {
            "category":"Restaurant",
            "type":"Food & Drink"
        }
    ],
    "sg:menulink":"http://www.allmenus.com/ut/salt-lake-city/36356-the-lodge-bistro/menu/",
    "sg:phone":"+1 801 933 2145",
    "sg:postcode":"84092",
    "sg:province":"UT",
    "sg:tags":[
        "new",
        "american"
    ],
    "wof:name":"The Lodge Bistro",
    "wof:placetype":"venue"
},
  "geometry": {"coordinates":[-111.823881,40.579139],"type":"Point"}
}