{
  "type": "Feature",
  "properties": {
    "iso:country":"US",
    "sg:address":"7613 Jordan Landing Blvd",
    "sg:city":"West Jordan",
    "sg:classifiers":[
        {
            "category":"Insurance",
            "subcategory":"Insurance Agent",
            "type":"Services"
        }
    ],
    "sg:phone":"+1 801 260 0102",
    "sg:postcode":"84084",
    "sg:province":"UT",
    "wof:name":"State Farm Insurance",
    "wof:placetype":"venue"
},
  "geometry": {"coordinates":[-111.985615,40.611928],"type":"Point"}
}