{
  "type": "Feature",
  "properties": {
    "iso:country":"US",
    "sg:address":"3844 S 300 E",
    "sg:city":"South Salt Lake",
    "sg:classifiers":[
        {
            "category":"Shopping",
            "subcategory":"Clothing, Apparel, & Fashions",
            "type":"Retail Goods"
        }
    ],
    "sg:phone":"+1 801 265 1895",
    "sg:postcode":"84115",
    "sg:province":"UT",
    "wof:name":"X Zone Clothing",
    "wof:placetype":"venue"
},
  "geometry": {"coordinates":[-111.882863,40.687627],"type":"Point"}
}