{
  "type": "Feature",
  "properties": {
    "iso:country":"US",
    "sg:address":"38 E Hope St",
    "sg:city":"St George",
    "sg:classifiers":[
        {
            "category":"Professional",
            "type":"Services"
        }
    ],
    "sg:phone":"+1 435 628 2085",
    "sg:postcode":"84770",
    "sg:province":"UT",
    "wof:name":"Esmatrix Inc",
    "wof:placetype":"venue"
},
  "geometry": {"coordinates":[-113.582519,37.114878],"type":"Point"}
}