{
  "type": "Feature",
  "properties": {
    "iso:country":"US",
    "sg:address":"231 E 100 S",
    "sg:city":"Salt Lake City",
    "sg:classifiers":[
        {
            "category":"Organizations",
            "subcategory":"Religious Organization",
            "type":"Services"
        }
    ],
    "sg:phone":"+1 801 322 3400",
    "sg:postcode":"84111",
    "sg:province":"UT",
    "sg:tags":[
        "church"
    ],
    "sg:website":"www.stmarkscathedral-ut.org",
    "wof:name":"Cathedral Church Of St Mark's",
    "wof:placetype":"venue"
},
  "geometry": {"coordinates":[-111.883307,40.767252],"type":"Point"}
}