{
  "type": "Feature",
  "properties": {
    "iso:country":"US",
    "sg:address":"255 E Main St",
    "sg:city":"Price",
    "sg:classifiers":[
        {
            "category":"Professional",
            "subcategory":"Accounting & Tax Preparation",
            "type":"Services"
        }
    ],
    "sg:phone":"+1 435 613 9159",
    "sg:postcode":"84501",
    "sg:province":"UT",
    "sg:tags":[
        "return",
        "filing"
    ],
    "wof:name":"Security Finance Corp",
    "wof:placetype":"venue"
},
  "geometry": {"coordinates":[-110.806428,39.599637],"type":"Point"}
}