{
  "type": "Feature",
  "properties": {
    "iso:country":"US",
    "sg:address":"6975 Union Park Center",
    "sg:city":"Midvale",
    "sg:classifiers":[
        {
            "category":"Banks & Credit Unions",
            "subcategory":"Investment Brokerage",
            "type":"Services"
        }
    ],
    "sg:phone":"+1 801 566 6639",
    "sg:postcode":"84047",
    "sg:province":"UT",
    "sg:tags":[
        "consultant",
        "planning",
        "financial"
    ],
    "wof:name":"Net Worth Advisory Group",
    "wof:placetype":"venue"
},
  "geometry": {"coordinates":[-111.86049800000001,40.62518],"type":"Point"}
}