{
  "type": "Feature",
  "properties": {
    "iso:country":"US",
    "sg:address":"2230 N University Pkwy",
    "sg:city":"Provo",
    "sg:classifiers":[
        {
            "category":"Health Services",
            "subcategory":"Doctor",
            "type":"Services"
        }
    ],
    "sg:phone":"+1 801 375 3355",
    "sg:postcode":"84604",
    "sg:province":"UT",
    "sg:tags":[
        "dentist"
    ],
    "wof:name":"Lauren Dalzen Inc",
    "wof:placetype":"venue"
},
  "geometry": {"coordinates":[-111.668554,40.263999],"type":"Point"}
}