{
  "type": "Feature",
  "properties": {
    "iso:country":"US",
    "sg:address":"1356 N 650 E",
    "sg:city":"Bountiful",
    "sg:classifiers":[
        {
            "category":"Organizations",
            "subcategory":"Religious Organization",
            "type":"Services"
        }
    ],
    "sg:phone":"+1 801 299 4049",
    "sg:postcode":"84010",
    "sg:province":"UT",
    "sg:tags":[
        "mormon",
        "church"
    ],
    "wof:name":"Bountiful Thirteenth Ward",
    "wof:placetype":"venue"
},
  "geometry": {"coordinates":[-111.86720699999999,40.902636],"type":"Point"}
}