{
  "type": "Feature",
  "properties": {
    "iso:country":"US",
    "sg:address":"350 S 500 W",
    "sg:city":"Cedar City",
    "sg:classifiers":[
        {
            "category":"Professional",
            "subcategory":"Engineering",
            "type":"Services"
        }
    ],
    "sg:phone":"+1 435 586 1345",
    "sg:postcode":"84720",
    "sg:province":"UT",
    "wof:name":"TNT Engineering",
    "wof:placetype":"venue"
},
  "geometry": {"coordinates":[-113.07038900000001,37.673142],"type":"Point"}
}