{
  "type": "Feature",
  "properties": {
    "iso:country":"US",
    "sg:address":"80 S Main St",
    "sg:city":"Roosevelt",
    "sg:classifiers":[
        {
            "category":"Shopping",
            "subcategory":"Used Merchandise",
            "type":"Retail Goods"
        }
    ],
    "sg:phone":"+1 435 722 5626",
    "sg:postcode":"84036",
    "sg:province":"UT",
    "sg:tags":[
        "pawnbroker"
    ],
    "wof:name":"Quick Cash & Loan",
    "wof:placetype":"venue"
},
  "geometry": {"coordinates":[-111.280866,40.641833],"type":"Point"}
}