{
  "type": "Feature",
  "properties": {
    "iso:country":"US",
    "sg:address":"4177 W 4100 S",
    "sg:city":"Salt Lake City",
    "sg:classifiers":[
        {
            "category":"Banks & Credit Unions",
            "subcategory":"Bank",
            "type":"Services"
        }
    ],
    "sg:phone":"+1 801 966 0092",
    "sg:postcode":"84120",
    "sg:province":"UT",
    "sg:tags":[
        "loan",
        "real estate"
    ],
    "wof:name":"Global Lending Inc",
    "wof:placetype":"venue"
},
  "geometry": {"coordinates":[-111.99128899999999,40.681998],"type":"Point"}
}