{
  "type": "Feature",
  "properties": {
    "iso:country":"US",
    "sg:address":"3496 S 1300 E",
    "sg:city":"Salt Lake City",
    "sg:classifiers":[
        {
            "category":"Professional",
            "subcategory":"Business Services",
            "type":"Services"
        }
    ],
    "sg:phone":"+1 801 484 4069",
    "sg:postcode":"84106",
    "sg:province":"UT",
    "wof:name":"Bailey Family Ltd Partnership",
    "wof:placetype":"venue"
},
  "geometry": {"coordinates":[-111.854107,40.694169],"type":"Point"}
}