{
  "type": "Feature",
  "properties": {
    "iso:country":"US",
    "sg:address":"85 E 700 N",
    "sg:city":"Orem",
    "sg:classifiers":[
        {
            "category":"Organizations",
            "subcategory":"Religious Organization",
            "type":"Services"
        }
    ],
    "sg:phone":"+1 801 222 0327",
    "sg:postcode":"84057",
    "sg:province":"UT",
    "sg:tags":[
        "church"
    ],
    "wof:name":"Church Of Jesus Christ Of Lds",
    "wof:placetype":"venue"
},
  "geometry": {"coordinates":[-111.69369,40.310093],"type":"Point"}
}