{
  "type": "Feature",
  "properties": {
    "iso:country":"US",
    "sg:address":"1037 E 1330 S",
    "sg:city":"Spanish Fork",
    "sg:classifiers":[
        {
            "category":"Building & Trades",
            "subcategory":"Construction",
            "type":"Services"
        }
    ],
    "sg:phone":"+1 801 798 3700",
    "sg:postcode":"84660",
    "sg:province":"UT",
    "sg:tags":[
        "house",
        "nonresidential"
    ],
    "wof:name":"Monte Mecham Construction",
    "wof:placetype":"venue"
},
  "geometry": {"coordinates":[-111.63741,40.092891],"type":"Point"}
}