{
  "type": "Feature",
  "properties": {
    "iso:country":"US",
    "sg:address":"6280 W Meander Ave",
    "sg:city":"Salt Lake City",
    "sg:classifiers":[
        {
            "category":"Building & Trades",
            "subcategory":"Cleaning & Sanitation",
            "type":"Services"
        }
    ],
    "sg:phone":"+1 801 830 7783",
    "sg:postcode":"84128",
    "sg:province":"UT",
    "sg:tags":[
        "industrial"
    ],
    "wof:name":"Bac-It-Systems",
    "wof:placetype":"venue"
},
  "geometry": {"coordinates":[-112.04266800000001,40.69562],"type":"Point"}
}