{
  "type": "Feature",
  "properties": {
    "iso:country":"US",
    "sg:address":"3724 W 5600 S",
    "sg:city":"Spanish Fork",
    "sg:classifiers":[
        {
            "category":"Building & Trades",
            "subcategory":"Equipment Rental",
            "type":"Services"
        }
    ],
    "sg:phone":"+1 801 798 1184",
    "sg:postcode":"84660",
    "sg:province":"UT",
    "sg:tags":[
        "crane"
    ],
    "wof:name":"Chris's Crane Svc",
    "wof:placetype":"venue"
},
  "geometry": {"coordinates":[-111.74229,40.129225],"type":"Point"}
}