{
  "type": "Feature",
  "properties": {
    "iso:country":"US",
    "sg:address":"1964 E 1275 N",
    "sg:city":"Layton",
    "sg:classifiers":[
        {
            "category":"Wholesale",
            "subcategory":"Chemicals & Plastics",
            "type":"Manufacturing & Wholesale Goods"
        }
    ],
    "sg:phone":"+1 801 544 5033",
    "sg:postcode":"84040",
    "sg:province":"UT",
    "sg:tags":[
        "oxygen"
    ],
    "wof:name":"B & W Oxygen & Supply",
    "wof:placetype":"venue"
},
  "geometry": {"coordinates":[-111.929152,41.078465],"type":"Point"}
}