{
  "type": "Feature",
  "properties": {
    "iso:country":"US",
    "sg:address":"150 E 900 S",
    "sg:city":"Salt Lake City",
    "sg:classifiers":[
        {
            "category":"Insurance",
            "subcategory":"Insurance Agent",
            "type":"Services"
        }
    ],
    "sg:phone":"+1 801 364 7800",
    "sg:postcode":"84111",
    "sg:province":"UT",
    "wof:name":"Kent E Christensen Agency Inc",
    "wof:placetype":"venue"
},
  "geometry": {"coordinates":[-111.885437,40.749703],"type":"Point"}
}