{
  "type": "Feature",
  "properties": {
    "iso:country":"US",
    "sg:address":"86 E University Pkwy",
    "sg:city":"Orem",
    "sg:classifiers":[
        {
            "category":"Shopping",
            "subcategory":"Hobbies, Toys, & Games",
            "type":"Retail Goods"
        }
    ],
    "sg:phone":"+1 801 224 4448",
    "sg:postcode":"84058",
    "sg:province":"UT",
    "wof:name":"Toys R Us",
    "wof:placetype":"venue"
},
  "geometry": {"coordinates":[-111.691929,40.273451],"type":"Point"}
}