{
  "type": "Feature",
  "properties": {
    "iso:country":"US",
    "sg:address":"161 N 400 W",
    "sg:city":"Cedar City",
    "sg:classifiers":[
        {
            "category":"Personal",
            "type":"Services"
        }
    ],
    "sg:phone":"+1 435 586 8606",
    "sg:postcode":"84720",
    "sg:province":"UT",
    "wof:name":"Modestly Yours",
    "wof:placetype":"venue"
},
  "geometry": {"coordinates":[-113.068637,37.679688],"type":"Point"}
}