{
  "type": "Feature",
  "properties": {
    "iso:country":"US",
    "sg:address":"542 Alpine Hwy",
    "sg:city":"Alpine",
    "sg:classifiers":[
        {
            "category":"Banks & Credit Unions",
            "subcategory":"Financial Services",
            "type":"Services"
        }
    ],
    "sg:phone":"+1 801 756 4236",
    "sg:postcode":"84004",
    "sg:province":"UT",
    "sg:tags":[
        "company",
        "holding"
    ],
    "wof:name":"Bangerter Realty",
    "wof:placetype":"venue"
},
  "geometry": {"coordinates":[-111.78149500000001,40.446061],"type":"Point"}
}