{
  "type": "Feature",
  "properties": {
    "iso:country":"US",
    "sg:address":"1250 W 2350 N",
    "sg:city":"Ogden",
    "sg:classifiers":[
        {
            "category":"Manufacturing",
            "subcategory":"Metals",
            "type":"Manufacturing & Wholesale Goods"
        }
    ],
    "sg:phone":"+1 801 782 3769",
    "sg:postcode":"84404",
    "sg:province":"UT",
    "sg:tags":[
        "coating"
    ],
    "sg:website":"www.westerncoating.com",
    "wof:name":"Western Coating Inc",
    "wof:placetype":"venue"
},
  "geometry": {"coordinates":[-112.009359,41.30147],"type":"Point"}
}