{
  "type": "Feature",
  "properties": {
    "iso:country":"US",
    "sg:address":"67 W 100 S",
    "sg:city":"Salt Lake City",
    "sg:classifiers":[
        {
            "category":"Restaurant",
            "type":"Food & Drink"
        }
    ],
    "sg:menulink":"http://www.allmenus.com/ut/salt-lake-city/15361-mikado/menu/",
    "sg:phone":"+1 801 328 0929",
    "sg:postcode":"84101",
    "sg:province":"UT",
    "sg:tags":[
        "japanese",
        "asian"
    ],
    "wof:name":"Mikado",
    "wof:placetype":"venue"
},
  "geometry": {"coordinates":[-111.892861,40.767109],"type":"Point"}
}