{
  "type": "Feature",
  "properties": {
    "iso:country":"US",
    "sg:address":"505 E 600 S",
    "sg:city":"Salt Lake City",
    "sg:classifiers":[
        {
            "category":"Cafe",
            "type":"Food & Drink"
        }
    ],
    "sg:menulink":"http://www.allmenus.com/ut/salt-lake-city/152180-hard-rock-cafe/menu/",
    "sg:phone":"+1 801 532 7625",
    "sg:postcode":"84102",
    "sg:province":"UT",
    "sg:tags":[
        "american"
    ],
    "wof:name":"Hard Rock Cafe",
    "wof:placetype":"venue"
},
  "geometry": {"coordinates":[-111.876555,40.756306],"type":"Point"}
}