{
  "type": "Feature",
  "properties": {
    "iso:country":"US",
    "sg:address":"730 W 900 S",
    "sg:city":"Salt Lake City",
    "sg:phone":"+1 801 532 7481",
    "sg:postcode":"84104",
    "sg:province":"UT",
    "sg:tags":[
        "equipment",
        "supply"
    ],
    "wof:name":"Andrus",
    "wof:placetype":"venue"
},
  "geometry": {"coordinates":[-111.913157,40.749829],"type":"Point"}
}