{
  "type": "Feature",
  "properties": {
    "iso:country":"US",
    "sg:address":"263 W 2950 S",
    "sg:city":"Salt Lake City",
    "sg:classifiers":[
        {
            "category":"Wholesale",
            "subcategory":"Machinery & Supplies",
            "type":"Manufacturing & Wholesale Goods"
        }
    ],
    "sg:phone":"+1 801 486 3881",
    "sg:postcode":"84115",
    "sg:province":"UT",
    "sg:tags":[
        "printer",
        "cartridge"
    ],
    "wof:name":"Colour Systems Intl",
    "wof:placetype":"venue"
},
  "geometry": {"coordinates":[-111.89818099999999,40.70736],"type":"Point"}
}