{
  "type": "Feature",
  "properties": {
    "iso:country":"US",
    "sg:address":"300 Airport Rd",
    "sg:city":"Heber City",
    "sg:classifiers":[
        {
            "category":"Building & Trades",
            "subcategory":"Construction",
            "type":"Services"
        }
    ],
    "sg:phone":"+1 435 654 2463",
    "sg:postcode":"84032",
    "sg:province":"UT",
    "sg:tags":[
        "excavation",
        "contractor"
    ],
    "wof:name":"Witt Excavating Inc",
    "wof:placetype":"venue"
},
  "geometry": {"coordinates":[-111.41761200000001,40.486897],"type":"Point"}
}