{
  "type": "Feature",
  "properties": {
    "iso:country":"US",
    "sg:address":"883 N 1600 E",
    "sg:city":"Mapleton",
    "sg:classifiers":[
        {
            "category":"Building & Trades",
            "subcategory":"Electrical",
            "type":"Services"
        }
    ],
    "sg:phone":"+1 801 489 5682",
    "sg:postcode":"84664",
    "sg:province":"UT",
    "sg:tags":[
        "electrical",
        "contractor"
    ],
    "wof:name":"TNT Electric Inc",
    "wof:placetype":"venue"
},
  "geometry": {"coordinates":[-111.55987,40.138005],"type":"Point"}
}