{
  "type": "Feature",
  "properties": {
    "iso:country":"US",
    "sg:address":"1850 Sidewinder Dr",
    "sg:city":"Park City",
    "sg:classifiers":[
        {
            "category":"Health Services",
            "subcategory":"Doctor",
            "type":"Services"
        }
    ],
    "sg:phone":"+1 435 615 0250",
    "sg:postcode":"84060",
    "sg:province":"UT",
    "sg:tags":[
        "physician",
        "surgeon"
    ],
    "sg:website":"www.healthsouth.com",
    "wof:name":"Healthsouth Diagnostic Ctr",
    "wof:placetype":"venue"
},
  "geometry": {"coordinates":[-111.497201,40.664156],"type":"Point"}
}