{
  "type": "Feature",
  "properties": {
    "iso:country":"US",
    "sg:address":"245 Playa Della Rosita",
    "sg:city":"Washington",
    "sg:classifiers":[
        {
            "category":"Real Estate",
            "subcategory":"Real Estate Operator",
            "type":"Services"
        }
    ],
    "sg:phone":"+1 435 628 3255",
    "sg:postcode":"84780",
    "sg:province":"UT",
    "sg:tags":[
        "building",
        "apartment"
    ],
    "wof:name":"Ridge View Apartments Inc",
    "wof:placetype":"venue"
},
  "geometry": {"coordinates":[-113.521371,37.135442],"type":"Point"}
}