{
  "type": "Feature",
  "properties": {
    "iso:country":"US",
    "sg:address":"70 S Center St",
    "sg:city":"Goshen",
    "sg:classifiers":[
        {
            "category":"Organizations",
            "subcategory":"Religious Organization",
            "type":"Services"
        }
    ],
    "sg:phone":"+1 801 667 3232",
    "sg:postcode":"84633",
    "sg:province":"UT",
    "sg:tags":[
        "church"
    ],
    "wof:name":"Church Of Jesus Christ Of Lds",
    "wof:placetype":"venue"
},
  "geometry": {"coordinates":[-111.90033699999999,39.951435],"type":"Point"}
}