{
  "type": "Feature",
  "properties": {
    "iso:country":"US",
    "sg:address":"579 Heritage Park Blvd",
    "sg:city":"Layton",
    "sg:classifiers":[
        {
            "category":"Building & Trades",
            "subcategory":"Construction",
            "type":"Services"
        }
    ],
    "sg:phone":"+1 801 728 7040",
    "sg:postcode":"84041",
    "sg:province":"UT",
    "sg:tags":[
        "project"
    ],
    "wof:name":"Summit Construction",
    "wof:placetype":"venue"
},
  "geometry": {"coordinates":[-111.97761800000001,41.083035],"type":"Point"}
}