{
  "type": "Feature",
  "properties": {
    "iso:country":"US",
    "sg:address":"8160 Highland Dr",
    "sg:city":"Sandy",
    "sg:classifiers":[
        {
            "category":"Professional",
            "subcategory":"Lawyer & Legal Services",
            "type":"Services"
        }
    ],
    "sg:phone":"+1 801 943 0995",
    "sg:postcode":"84093",
    "sg:province":"UT",
    "sg:tags":[
        "attorney"
    ],
    "wof:name":"Jay W Taylor",
    "wof:placetype":"venue"
},
  "geometry": {"coordinates":[-111.833123,40.603667],"type":"Point"}
}