{
  "type": "Feature",
  "properties": {
    "iso:country":"US",
    "sg:address":"3707 Bronco Cir",
    "sg:city":"Magna",
    "sg:classifiers":[
        {
            "category":"Food & Beverages",
            "subcategory":"Candy",
            "type":"Retail Goods"
        }
    ],
    "sg:phone":"+1 801 250 9355",
    "sg:postcode":"84044",
    "sg:province":"UT",
    "wof:name":"Sweet Life",
    "wof:placetype":"venue"
},
  "geometry": {"coordinates":[-112.077426,40.691891],"type":"Point"}
}