{
  "type": "Feature",
  "properties": {
    "iso:country":"US",
    "sg:address":"475 N 700 W",
    "sg:city":"Centerville",
    "sg:classifiers":[
        {
            "category":"Fast Food",
            "type":"Food & Drink"
        }
    ],
    "sg:phone":"+1 800 786 1000",
    "sg:postcode":"84014",
    "sg:province":"UT",
    "sg:tags":[
        "burger"
    ],
    "wof:name":"In-N-Out Burger",
    "wof:placetype":"venue"
},
  "geometry": {"coordinates":[-111.88648000000001,40.925597],"type":"Point"}
}