{
  "type": "Feature",
  "properties": {
    "iso:country":"US",
    "sg:address":"8931 N Cove Dr",
    "sg:city":"Park City",
    "sg:classifiers":[
        {
            "category":"Home & Garden",
            "subcategory":"Home Furnishings",
            "type":"Retail Goods"
        }
    ],
    "sg:phone":"+1 435 714 0714",
    "sg:postcode":"84098",
    "sg:province":"UT",
    "sg:tags":[
        "venetian",
        "blind"
    ],
    "wof:name":"Blue Spruce Blinds & Carpets",
    "wof:placetype":"venue"
},
  "geometry": {"coordinates":[-111.598747,40.758115],"type":"Point"}
}