{
  "type": "Feature",
  "properties": {
    "iso:country":"US",
    "sg:address":"640 S Main St",
    "sg:city":"Moab",
    "sg:classifiers":[
        {
            "category":"Restaurant",
            "type":"Food & Drink"
        }
    ],
    "sg:phone":"+1 435 259 8800",
    "sg:postcode":"84532",
    "sg:province":"UT",
    "sg:tags":[
        "eating"
    ],
    "wof:name":"McDonalds",
    "wof:placetype":"venue"
},
  "geometry": {"coordinates":[-109.550556,38.566221],"type":"Point"}
}