{
  "type": "Feature",
  "properties": {
    "iso:country":"US",
    "sg:address":"843 N 2400 W",
    "sg:city":"Provo",
    "sg:classifiers":[
        {
            "category":"Real Estate",
            "subcategory":"Real Estate Agent",
            "type":"Services"
        }
    ],
    "sg:phone":"+1 801 374 3088",
    "sg:postcode":"84601",
    "sg:province":"UT",
    "sg:tags":[
        "management"
    ],
    "wof:name":"Gunnell & Gunnell",
    "wof:placetype":"venue"
},
  "geometry": {"coordinates":[-111.700379,40.244518],"type":"Point"}
}