{
  "type": "Feature",
  "properties": {
    "iso:country":"US",
    "sg:address":"113 N 1200 W",
    "sg:city":"Orem",
    "sg:classifiers":[
        {
            "category":"Wholesale",
            "subcategory":"Machinery & Supplies",
            "type":"Manufacturing & Wholesale Goods"
        }
    ],
    "sg:phone":"+1 801 226 2882",
    "sg:postcode":"84057",
    "sg:province":"UT",
    "sg:tags":[
        "industrial",
        "fluid",
        "power",
        "mfg"
    ],
    "wof:name":"Jolleys Evco LLC",
    "wof:placetype":"venue"
},
  "geometry": {"coordinates":[-111.724349,40.297805],"type":"Point"}
}