{
  "type": "Feature",
  "properties": {
    "iso:country":"US",
    "sg:address":"425 Sheep Lane Dr",
    "sg:city":"Levan",
    "sg:classifiers":[
        {
            "category":"Government",
            "subcategory":"Police Station",
            "type":"Public Place"
        }
    ],
    "sg:phone":"+1 435 623 1344",
    "sg:postcode":"84648",
    "sg:province":"UT",
    "sg:tags":[
        "protection"
    ],
    "wof:name":"Sherriffs Offices",
    "wof:placetype":"venue"
},
  "geometry": {"coordinates":[-111.843648,39.675786],"type":"Point"}
}