{
  "type": "Feature",
  "properties": {
    "iso:country":"US",
    "sg:address":"8967 S Altair Dr",
    "sg:city":"Sandy",
    "sg:classifiers":[
        {
            "category":"Shopping",
            "type":"Retail Goods"
        }
    ],
    "sg:phone":"+1 801 255 2888",
    "sg:postcode":"84093",
    "sg:province":"UT",
    "sg:tags":[
        "banner"
    ],
    "wof:name":"Build A Banner",
    "wof:placetype":"venue"
},
  "geometry": {"coordinates":[-111.847706,40.590068],"type":"Point"}
}