{
  "type": "Feature",
  "properties": {
    "iso:country":"US",
    "sg:address":"3535 Directors Row",
    "sg:city":"Salt Lake City",
    "sg:classifiers":[
        {
            "category":"Autos & Motor Vehicles",
            "subcategory":"Auto Supplies",
            "type":"Retail Goods"
        }
    ],
    "sg:phone":"+1 801 886 1470",
    "sg:postcode":"84104",
    "sg:province":"UT",
    "sg:tags":[
        "automobile",
        "parts"
    ],
    "sg:website":"www.keystone-auto.com",
    "wof:name":"Keystone Automotive",
    "wof:placetype":"venue"
},
  "geometry": {"coordinates":[-111.974446,40.745677],"type":"Point"}
}