{
  "type": "Feature",
  "properties": {
    "iso:country":"US",
    "sg:address":"795 S 150 W",
    "sg:city":"Tremonton",
    "sg:classifiers":[
        {
            "category":"Building & Trades",
            "subcategory":"Construction",
            "type":"Services"
        }
    ],
    "sg:phone":"+1 435 257 0168",
    "sg:postcode":"84337",
    "sg:province":"UT",
    "sg:tags":[
        "concrete",
        "contractor"
    ],
    "wof:name":"Mehi Inc",
    "wof:placetype":"venue"
},
  "geometry": {"coordinates":[-112.167733,41.703052],"type":"Point"}
}