{
  "type": "Feature",
  "properties": {
    "iso:country":"US",
    "sg:address":"4304 el Camino St",
    "sg:city":"Salt Lake City",
    "sg:classifiers":[
        {
            "category":"Professional",
            "subcategory":"Management & Consulting",
            "type":"Services"
        }
    ],
    "sg:phone":"+1 801 967 5655",
    "sg:postcode":"84119",
    "sg:province":"UT",
    "wof:name":"Axis",
    "wof:placetype":"venue"
},
  "geometry": {"coordinates":[-111.940707,40.676827],"type":"Point"}
}