{
  "type": "Feature",
  "properties": {
    "iso:country":"US",
    "sg:address":"10433 S Crocus St",
    "sg:city":"Sandy",
    "sg:classifiers":[
        {
            "category":"Building & Trades",
            "subcategory":"Construction",
            "type":"Services"
        }
    ],
    "sg:phone":"+1 801 571 6881",
    "sg:postcode":"84094",
    "sg:province":"UT",
    "sg:tags":[
        "heavy"
    ],
    "wof:name":"Dicks Bckhoe Sewer Connection",
    "wof:placetype":"venue"
},
  "geometry": {"coordinates":[-111.865931,40.56087],"type":"Point"}
}