{
  "type": "Feature",
  "properties": {
    "iso:country":"US",
    "sg:address":"375 W Center St",
    "sg:city":"Spanish Fork",
    "sg:classifiers":[
        {
            "category":"Shopping",
            "type":"Retail Goods"
        }
    ],
    "sg:phone":"+1 801 224 9444",
    "sg:postcode":"84660",
    "sg:province":"UT",
    "sg:tags":[
        "hearing",
        "equipment",
        "supply",
        "impaired"
    ],
    "wof:name":"Miracle-Ear",
    "wof:placetype":"venue"
},
  "geometry": {"coordinates":[-111.660488,40.109771],"type":"Point"}
}