{
  "type": "Feature",
  "properties": {
    "iso:country":"US",
    "sg:address":"20 W 1400 S",
    "sg:city":"Garland",
    "sg:classifiers":[
        {
            "category":"Restaurant",
            "type":"Food & Drink"
        },
        {
            "category":"Food & Beverages",
            "subcategory":"Bakery",
            "type":"Retail Goods"
        }
    ],
    "sg:phone":"+1 435 257 3947",
    "sg:postcode":"84312",
    "sg:province":"UT",
    "sg:tags":[
        "eating",
        "caterer"
    ],
    "wof:name":"Munns' Sweet Shoppe",
    "wof:placetype":"venue"
},
  "geometry": {"coordinates":[-112.16243799999999,41.726472],"type":"Point"}
}