{
  "type": "Feature",
  "properties": {
    "iso:country":"US",
    "sg:address":"1435 S State St",
    "sg:city":"Salt Lake City",
    "sg:classifiers":[
        {
            "category":"Shopping",
            "subcategory":"Computers & Home Electronics",
            "type":"Retail Goods"
        }
    ],
    "sg:phone":"+1 801 485 6855",
    "sg:postcode":"84115",
    "sg:province":"UT",
    "sg:tags":[
        "equipment",
        "peripheral",
        "software"
    ],
    "wof:name":"Soft Tech",
    "wof:placetype":"venue"
},
  "geometry": {"coordinates":[-111.888138,40.740221],"type":"Point"}
}