{
  "type": "Feature",
  "properties": {
    "iso:country":"US",
    "sg:address":"965 E 830 S",
    "sg:city":"Pleasant Grove",
    "sg:classifiers":[
        {
            "category":"Social Services",
            "subcategory":"Child Care",
            "type":"Services"
        }
    ],
    "sg:phone":"+1 801 796 9410",
    "sg:postcode":"84062",
    "sg:province":"UT",
    "sg:tags":[
        "day"
    ],
    "wof:name":"Moran Martha Day Care",
    "wof:placetype":"venue"
},
  "geometry": {"coordinates":[-111.719528,40.353823],"type":"Point"}
}