{
  "type": "Feature",
  "properties": {
    "iso:country":"US",
    "sg:address":"216 Marla Way",
    "sg:city":"Midvale",
    "sg:classifiers":[
        {
            "category":"Building & Trades",
            "subcategory":"Construction",
            "type":"Services"
        }
    ],
    "sg:phone":"+1 801 561 2071",
    "sg:postcode":"84047",
    "sg:province":"UT",
    "sg:tags":[
        "concrete",
        "contractor"
    ],
    "wof:name":"Pyramid Concrete Construction",
    "wof:placetype":"venue"
},
  "geometry": {"coordinates":[-111.884642,40.619041],"type":"Point"}
}