{
  "type": "Feature",
  "properties": {
    "iso:country":"US",
    "sg:address":"302 N 525 E",
    "sg:city":"Springville",
    "sg:classifiers":[
        {
            "category":"Professional",
            "subcategory":"Business Services",
            "type":"Services"
        }
    ],
    "sg:phone":"+1 801 602 9007",
    "sg:postcode":"84663",
    "sg:province":"UT",
    "wof:name":"White Knight Enterprises",
    "wof:placetype":"venue"
},
  "geometry": {"coordinates":[-111.60086200000001,40.171983],"type":"Point"}
}