{
  "type": "Feature",
  "properties": {
    "iso:country":"US",
    "sg:address":"5976 S 6300 W",
    "sg:city":"Hooper",
    "sg:classifiers":[
        {
            "category":"Building & Trades",
            "subcategory":"Construction",
            "type":"Services"
        }
    ],
    "sg:phone":"+1 801 776 8243",
    "sg:postcode":"84315",
    "sg:province":"UT",
    "sg:tags":[
        "house"
    ],
    "wof:name":"Rocky Mountain Quality Cnstr",
    "wof:placetype":"venue"
},
  "geometry": {"coordinates":[-112.132668,41.153568],"type":"Point"}
}