{
  "type": "Feature",
  "properties": {
    "iso:country":"US",
    "sg:address":"8930 Quail Hollow Dr",
    "sg:city":"Sandy",
    "sg:classifiers":[
        {
            "category":"Professional",
            "subcategory":"Computer Services",
            "type":"Services"
        }
    ],
    "sg:phone":"+1 801 942 3769",
    "sg:postcode":"84093",
    "sg:province":"UT",
    "sg:tags":[
        "prepackaged",
        "software"
    ],
    "wof:name":"Gold Disk Software",
    "wof:placetype":"venue"
},
  "geometry": {"coordinates":[-111.81562,40.586771],"type":"Point"}
}