{
  "type": "Feature",
  "properties": {
    "iso:country":"US",
    "sg:address":"131 E Main St",
    "sg:city":"Salina",
    "sg:classifiers":[
        {
            "category":"Home & Garden",
            "subcategory":"Furniture",
            "type":"Retail Goods"
        }
    ],
    "sg:phone":"+1 435 529 2001",
    "sg:postcode":"84654",
    "sg:province":"UT",
    "wof:name":"Southern Livin'",
    "wof:placetype":"venue"
},
  "geometry": {"coordinates":[-111.856945,38.957647],"type":"Point"}
}