{
  "type": "Feature",
  "properties": {
    "iso:country":"US",
    "sg:address":"1177 S Jordan Pkwy",
    "sg:city":"South Jordan",
    "sg:classifiers":[
        {
            "category":"Building & Trades",
            "subcategory":"Construction",
            "type":"Services"
        }
    ],
    "sg:phone":"+1 801 825 4590",
    "sg:postcode":"84095",
    "sg:province":"UT",
    "sg:tags":[
        "house"
    ],
    "wof:name":"Gerald J Page Construction Co",
    "wof:placetype":"venue"
},
  "geometry": {"coordinates":[-111.924459,40.561526],"type":"Point"}
}