{
  "type": "Feature",
  "properties": {
    "iso:country":"US",
    "sg:address":"380 W 750 S",
    "sg:city":"Logan",
    "sg:classifiers":[
        {
            "category":"Professional",
            "subcategory":"Management & Consulting",
            "type":"Services"
        }
    ],
    "sg:phone":"+1 435 755 8585",
    "sg:postcode":"84321",
    "sg:province":"UT",
    "wof:name":"Commodities Risk Analysis",
    "wof:placetype":"venue"
},
  "geometry": {"coordinates":[-111.845894,41.717865],"type":"Point"}
}