{
  "type": "Feature",
  "properties": {
    "iso:country":"US",
    "sg:address":"82 N Roundabout Way",
    "sg:city":"Cedar City",
    "sg:classifiers":[
        {
            "category":"Farming",
            "subcategory":"Livestock Farm",
            "type":"Manufacturing & Wholesale Goods"
        }
    ],
    "sg:phone":"+1 435 586 7255",
    "sg:postcode":"84720",
    "sg:province":"UT",
    "sg:tags":[
        "animal",
        "general"
    ],
    "wof:name":"Howard W & Becky Jones",
    "wof:placetype":"venue"
},
  "geometry": {"coordinates":[-113.096462,37.678931],"type":"Point"}
}