{
  "type": "Feature",
  "properties": {
    "iso:country":"US",
    "sg:address":"1630 Wall Ave",
    "sg:city":"Ogden",
    "sg:classifiers":[
        {
            "category":"Wholesale",
            "subcategory":"Auto Parts",
            "type":"Manufacturing & Wholesale Goods"
        }
    ],
    "sg:phone":"+1 801 627 5833",
    "sg:postcode":"84404",
    "sg:province":"UT",
    "wof:name":"TDS",
    "wof:placetype":"venue"
},
  "geometry": {"coordinates":[-111.97842300000001,41.237392],"type":"Point"}
}