{
  "type": "Feature",
  "properties": {
    "iso:country":"US",
    "sg:address":"1567 Beechwood Cir",
    "sg:city":"Salt Lake City",
    "sg:classifiers":[
        {
            "category":"Professional",
            "subcategory":"Management & Consulting",
            "type":"Services"
        }
    ],
    "sg:phone":"+1 801 262 4895",
    "sg:postcode":"84123",
    "sg:province":"UT",
    "wof:name":"J&S Management",
    "wof:placetype":"venue"
},
  "geometry": {"coordinates":[-111.93544900000001,40.670912],"type":"Point"}
}