{
  "type": "Feature",
  "properties": {
    "iso:country":"US",
    "sg:address":"1703 Yalecrest Ave",
    "sg:city":"Salt Lake City",
    "sg:classifiers":[
        {
            "category":"Professional",
            "subcategory":"Lawyer & Legal Services",
            "type":"Services"
        }
    ],
    "sg:phone":"+1 801 582 7020",
    "sg:postcode":"84108",
    "sg:province":"UT",
    "wof:name":"Jones Properties Lc",
    "wof:placetype":"venue"
},
  "geometry": {"coordinates":[-111.839428,40.746962],"type":"Point"}
}