{
  "type": "Feature",
  "properties": {
    "iso:country":"US",
    "sg:address":"552 S 1200 E",
    "sg:city":"Salt Lake City",
    "sg:classifiers":[
        {
            "category":"Retail",
            "subcategory":"Portrait Studio",
            "type":"Services"
        }
    ],
    "sg:phone":"+1 801 582 9559",
    "sg:postcode":"84102",
    "sg:province":"UT",
    "wof:name":"Colvin Studio Inc",
    "wof:placetype":"venue"
},
  "geometry": {"coordinates":[-111.85681099999999,40.75747],"type":"Point"}
}