{
  "type": "Feature",
  "properties": {
    "iso:country":"US",
    "sg:address":"2506 Easton St",
    "sg:city":"Salt Lake City",
    "sg:classifiers":[
        {
            "category":"Building & Trades",
            "subcategory":"Construction",
            "type":"Services"
        }
    ],
    "sg:phone":"+1 801 968 6632",
    "sg:postcode":"84118",
    "sg:province":"UT",
    "sg:tags":[
        "control",
        "corrosion"
    ],
    "sg:website":"www.haztec.net",
    "wof:name":"Haztec Of America Inc",
    "wof:placetype":"venue"
},
  "geometry": {"coordinates":[-111.953964,40.647063],"type":"Point"}
}