{
  "type": "Feature",
  "properties": {
    "iso:country":"US",
    "sg:address":"2181 California Ave",
    "sg:city":"Salt Lake City",
    "sg:classifiers":[
        {
            "category":"Wholesale",
            "subcategory":"Non-durable Goods",
            "type":"Manufacturing & Wholesale Goods"
        }
    ],
    "sg:phone":"+1 801 954 0554",
    "sg:postcode":"84104",
    "sg:province":"UT",
    "sg:tags":[
        "novelty",
        "gift"
    ],
    "wof:name":"Gift In A Balloon",
    "wof:placetype":"venue"
},
  "geometry": {"coordinates":[-111.95046600000001,40.740406],"type":"Point"}
}