{
  "type": "Feature",
  "properties": {
    "iso:country":"US",
    "sg:address":"2954 Rolling Knolls Dr",
    "sg:city":"Provo",
    "sg:classifiers":[
        {
            "category":"Building & Trades",
            "subcategory":"Construction",
            "type":"Services"
        }
    ],
    "sg:phone":"+1 801 375 4152",
    "sg:postcode":"84604",
    "sg:province":"UT",
    "sg:tags":[
        "house"
    ],
    "wof:name":"Hutchings Construction",
    "wof:placetype":"venue"
},
  "geometry": {"coordinates":[-111.63439099999999,40.272639],"type":"Point"}
}