{
  "type": "Feature",
  "properties": {
    "iso:country":"US",
    "sg:address":"44 Sarah St",
    "sg:city":"Providence",
    "sg:classifiers":[
        {
            "category":"Building & Trades",
            "subcategory":"Construction",
            "type":"Services"
        }
    ],
    "sg:phone":"+1 435 753 8798",
    "sg:postcode":"84332",
    "sg:province":"UT",
    "sg:tags":[
        "house"
    ],
    "wof:name":"Millcreek Construction Inc",
    "wof:placetype":"venue"
},
  "geometry": {"coordinates":[-111.80312000000001,41.706756],"type":"Point"}
}