{
  "type": "Feature",
  "properties": {
    "iso:country":"US",
    "sg:address":"222 N Bluff St",
    "sg:city":"St George",
    "sg:classifiers":[
        {
            "category":"Retail",
            "subcategory":"Car Wash",
            "type":"Services"
        }
    ],
    "sg:phone":"+1 435 673 3813",
    "sg:postcode":"84770",
    "sg:province":"UT",
    "sg:tags":[
        "operated",
        "polishing",
        "washing"
    ],
    "wof:name":"Ultra Wash",
    "wof:placetype":"venue"
},
  "geometry": {"coordinates":[-113.59510899999999,37.112986],"type":"Point"}
}