{
  "type": "Feature",
  "properties": {
    "iso:country":"US",
    "sg:address":"2200 Sidewinder Dr",
    "sg:city":"Park City",
    "sg:classifiers":[
        {
            "category":"Restaurant",
            "type":"Food & Drink"
        }
    ],
    "sg:menulink":"http://www.allmenus.com/ut/park-city/15356-grub-steak-restaurant/menu/",
    "sg:phone":"+1 435 649 8060",
    "sg:postcode":"84060",
    "sg:province":"UT",
    "sg:tags":[
        "american",
        "steakhouse"
    ],
    "wof:name":"Grub Steak Restaurant",
    "wof:placetype":"venue"
},
  "geometry": {"coordinates":[-111.493666,40.664118],"type":"Point"}
}