{
  "type": "Feature",
  "properties": {
    "iso:country":"US",
    "sg:address":"1723 Harvard Ave",
    "sg:city":"Salt Lake City",
    "sg:classifiers":[
        {
            "category":"Recreation",
            "type":"Entertainment"
        }
    ],
    "sg:phone":"+1 801 581 0187",
    "sg:postcode":"84108",
    "sg:province":"UT",
    "sg:tags":[
        "tennis",
        "instruction"
    ],
    "wof:name":"Trabert Tennis Corp",
    "wof:placetype":"venue"
},
  "geometry": {"coordinates":[-111.840013,40.744557],"type":"Point"}
}