{
  "type": "Feature",
  "properties": {
    "iso:country":"US",
    "sg:address":"3520 Lincoln Ave",
    "sg:city":"Ogden",
    "sg:classifiers":[
        {
            "category":"Professional",
            "subcategory":"Detective & Security Services",
            "type":"Services"
        }
    ],
    "sg:phone":"+1 801 394 4826",
    "sg:postcode":"84401",
    "sg:province":"UT",
    "sg:tags":[
        "car"
    ],
    "wof:name":"Utah Detective Agcy & SEC Svcs",
    "wof:placetype":"venue"
},
  "geometry": {"coordinates":[-111.976491,41.199252],"type":"Point"}
}