{
  "type": "Feature",
  "properties": {
    "iso:country":"US",
    "sg:address":"5995 Amelia Earhart Dr",
    "sg:city":"Salt Lake City",
    "sg:classifiers":[
        {
            "category":"Shopping",
            "subcategory":"Department Store",
            "type":"Retail Goods"
        }
    ],
    "sg:phone":"+1 801 333 7700",
    "sg:postcode":"84116",
    "sg:province":"UT",
    "sg:tags":[
        "shop"
    ],
    "sg:website":"www.dollartree.com",
    "wof:name":"Dollar Tree",
    "wof:placetype":"venue"
},
  "geometry": {"coordinates":[-112.03603,40.778715],"type":"Point"}
}