{
  "type": "Feature",
  "properties": {
    "iso:country":"US",
    "sg:address":"15046 Rose Canyon Rd",
    "sg:city":"Riverton",
    "sg:classifiers":[
        {
            "category":"Utilities",
            "subcategory":"Telephone",
            "type":"Services"
        }
    ],
    "sg:phone":"+1 801 254 0113",
    "sg:postcode":"84096",
    "sg:province":"UT",
    "sg:tags":[
        "communications"
    ],
    "wof:name":"Hills Distributing",
    "wof:placetype":"venue"
},
  "geometry": {"coordinates":[-112.07508799999999,40.473795],"type":"Point"}
}