{
  "type": "Feature",
  "properties": {
    "iso:country":"US",
    "sg:address":"7893 S Goslin Ct",
    "sg:city":"West Jordan",
    "sg:classifiers":[
        {
            "category":"Personal",
            "subcategory":"Beauty Salon",
            "type":"Services"
        }
    ],
    "sg:phone":"+1 801 280 9280",
    "sg:postcode":"84088",
    "sg:province":"UT",
    "sg:tags":[
        "shop"
    ],
    "wof:name":"Reflections Hair Salon",
    "wof:placetype":"venue"
},
  "geometry": {"coordinates":[-112.00355999999999,40.607589],"type":"Point"}
}