{
  "type": "Feature",
  "properties": {
    "iso:country":"US",
    "sg:address":"591 S 1500 W",
    "sg:city":"Vernal",
    "sg:classifiers":[
        {
            "category":"Autos & Motor Vehicles",
            "subcategory":"Motorcycle Sales",
            "type":"Retail Goods"
        }
    ],
    "sg:phone":"+1 435 789 7463",
    "sg:postcode":"84078",
    "sg:province":"UT",
    "sg:tags":[
        "scooter"
    ],
    "wof:name":"York Motor Sports",
    "wof:placetype":"venue"
},
  "geometry": {"coordinates":[-109.556996,40.446841],"type":"Point"}
}