{
  "type": "Feature",
  "properties": {
    "iso:country":"US",
    "sg:address":"5725 Harold Gatty Dr",
    "sg:city":"Salt Lake City",
    "sg:classifiers":[
        {
            "category":"Manufacturing",
            "subcategory":"Tools & Machinery",
            "type":"Manufacturing & Wholesale Goods"
        }
    ],
    "sg:phone":"+1 801 328 9901",
    "sg:postcode":"84116",
    "sg:province":"UT",
    "sg:tags":[
        "physician",
        "surgeon"
    ],
    "sg:website":"www.sterigenics.com",
    "wof:name":"IBA",
    "wof:placetype":"venue"
},
  "geometry": {"coordinates":[-112.02900200000001,40.781236],"type":"Point"}
}