{
  "type": "Feature",
  "properties": {
    "iso:country":"US",
    "sg:address":"298 S Main St",
    "sg:city":"Fillmore",
    "sg:classifiers":[
        {
            "category":"Shopping",
            "subcategory":"Florist",
            "type":"Retail Goods"
        }
    ],
    "sg:phone":"+1 435 743 5169",
    "sg:postcode":"84631",
    "sg:province":"UT",
    "wof:name":"Fillmore Country Floral",
    "wof:placetype":"venue"
},
  "geometry": {"coordinates":[-112.323593,38.962361],"type":"Point"}
}