{
  "type": "Feature",
  "properties": {
    "iso:country":"US",
    "sg:address":"4697 Bronbreck Dr",
    "sg:city":"Salt Lake City",
    "sg:classifiers":[
        {
            "category":"Professional",
            "subcategory":"Business Services",
            "type":"Services"
        }
    ],
    "sg:phone":"+1 801 277 6824",
    "sg:postcode":"84117",
    "sg:province":"UT",
    "wof:name":"Draper Agency",
    "wof:placetype":"venue"
},
  "geometry": {"coordinates":[-111.807744,40.663557],"type":"Point"}
}