{
  "type": "Feature",
  "properties": {
    "iso:country":"US",
    "sg:address":"8914 S State St",
    "sg:city":"Sandy",
    "sg:classifiers":[
        {
            "category":"Banks & Credit Unions",
            "subcategory":"Bank",
            "type":"Services"
        }
    ],
    "sg:phone":"+1 801 307 0376",
    "sg:postcode":"84070",
    "sg:province":"UT",
    "sg:tags":[
        "cashing",
        "check"
    ],
    "wof:name":"Checkmate",
    "wof:placetype":"venue"
},
  "geometry": {"coordinates":[-111.89093699999999,40.590209],"type":"Point"}
}