{
  "type": "Feature",
  "properties": {
    "iso:country":"US",
    "sg:address":"320 E 2000 N",
    "sg:city":"Layton",
    "sg:classifiers":[
        {
            "category":"Manufacturing",
            "subcategory":"Tools & Machinery",
            "type":"Manufacturing & Wholesale Goods"
        }
    ],
    "sg:phone":"+1 801 776 0639",
    "sg:postcode":"84041",
    "sg:province":"UT",
    "sg:tags":[
        "industrial",
        "mfg"
    ],
    "wof:name":"A1 Precision Machining Co Inc",
    "wof:placetype":"venue"
},
  "geometry": {"coordinates":[-111.960871,41.089103],"type":"Point"}
}