{
  "type": "Feature",
  "properties": {
    "iso:country":"US",
    "sg:address":"88 E 1160 S",
    "sg:city":"St George",
    "sg:classifiers":[
        {
            "category":"Wholesale",
            "subcategory":"Hardware",
            "type":"Manufacturing & Wholesale Goods"
        }
    ],
    "sg:phone":"+1 435 652 4581",
    "sg:postcode":"84770",
    "sg:province":"UT",
    "sg:tags":[
        "air",
        "parts",
        "conditioning",
        "supply"
    ],
    "wof:name":"St George Cooling",
    "wof:placetype":"venue"
},
  "geometry": {"coordinates":[-113.581095,37.088475],"type":"Point"}
}