{
  "type": "Feature",
  "properties": {
    "iso:country":"US",
    "sg:address":"410 W 900 South St",
    "sg:city":"Fillmore",
    "sg:classifiers":[
        {
            "category":"Travel",
            "subcategory":"Campground",
            "type":"Entertainment"
        }
    ],
    "sg:phone":"+1 435 743 4420",
    "sg:postcode":"84631",
    "sg:province":"UT",
    "wof:name":"Fillmore KOA Campground",
    "wof:placetype":"venue"
},
  "geometry": {"coordinates":[-112.339057,38.941521],"type":"Point"}
}