{
  "type": "Feature",
  "properties": {
    "iso:country":"US",
    "sg:address":"135 N Main St",
    "sg:city":"Moab",
    "sg:classifiers":[
        {
            "category":"Wholesale",
            "subcategory":"Drugs",
            "type":"Manufacturing & Wholesale Goods"
        }
    ],
    "sg:phone":"+1 435 259 0017",
    "sg:postcode":"84532",
    "sg:province":"UT",
    "sg:tags":[
        "prep"
    ],
    "wof:name":"Victoria White Eagle Body Care",
    "wof:placetype":"venue"
},
  "geometry": {"coordinates":[-109.550843,38.575844],"type":"Point"}
}