{
  "type": "Feature",
  "properties": {
    "iso:country":"US",
    "sg:address":"90 E 1300 S",
    "sg:city":"Price",
    "sg:classifiers":[
        {
            "category":"Manufacturing",
            "subcategory":"Tools & Machinery",
            "type":"Manufacturing & Wholesale Goods"
        }
    ],
    "sg:phone":"+1 435 637 2708",
    "sg:postcode":"84501",
    "sg:province":"UT",
    "sg:tags":[
        "trencher"
    ],
    "wof:name":"Lake Shore Inc",
    "wof:placetype":"venue"
},
  "geometry": {"coordinates":[-110.814407,39.582344],"type":"Point"}
}