{
  "type": "Feature",
  "properties": {
    "iso:country":"US",
    "sg:address":"91 E Main St",
    "sg:city":"Wellsville",
    "sg:classifiers":[
        {
            "category":"Food & Beverages",
            "subcategory":"Groceries & Convenience Stores",
            "type":"Retail Goods"
        }
    ],
    "sg:phone":"+1 435 245 3625",
    "sg:postcode":"84339",
    "sg:province":"UT",
    "wof:name":"Wellsville Market & Deli",
    "wof:placetype":"venue"
},
  "geometry": {"coordinates":[-111.931785,41.63882],"type":"Point"}
}