{
  "type": "Feature",
  "properties": {
    "iso:country":"US",
    "sg:address":"4252 Highland Dr",
    "sg:city":"Salt Lake City",
    "sg:classifiers":[
        {
            "category":"Health Services",
            "subcategory":"Doctor",
            "type":"Services"
        }
    ],
    "sg:phone":"+1 801 272 4251",
    "sg:postcode":"84124",
    "sg:province":"UT",
    "wof:name":"Scott G Ferguson Jr DDS PC",
    "wof:placetype":"venue"
},
  "geometry": {"coordinates":[-111.842744,40.678643],"type":"Point"}
}