{
  "type": "Feature",
  "properties": {
    "iso:country":"US",
    "sg:address":"465 S Bluff St",
    "sg:city":"St George",
    "sg:classifiers":[
        {
            "category":"Manufacturing",
            "subcategory":"Buildings",
            "type":"Manufacturing & Wholesale Goods"
        }
    ],
    "sg:phone":"+1 435 674 3750",
    "sg:postcode":"84770",
    "sg:province":"UT",
    "sg:tags":[
        "prefabricated",
        "wood",
        "architectural",
        "mfg"
    ],
    "wof:name":"Southern Utah Cedar Homes",
    "wof:placetype":"venue"
},
  "geometry": {"coordinates":[-113.588741,37.100219],"type":"Point"}
}