{
  "type": "Feature",
  "properties": {
    "iso:country":"US",
    "sg:address":"102 W 12200 S",
    "sg:city":"Draper",
    "sg:classifiers":[
        {
            "category":"Internet Cafe",
            "subcategory":"None",
            "type":"Food & Drink"
        }
    ],
    "sg:phone":"+1 801 566 0670",
    "sg:postcode":"84020",
    "sg:province":"UT",
    "sg:tags":[
        "product"
    ],
    "sg:website":"http://www.hyperxmedia.com",
    "wof:name":"Hyper X Media",
    "wof:placetype":"venue"
},
  "geometry": {"coordinates":[-111.892891,40.529259],"type":"Point"}
}