{
  "type": "Feature",
  "properties": {
    "iso:country":"US",
    "sg:address":"1649 Springwater Dr",
    "sg:city":"Orem",
    "sg:classifiers":[
        {
            "category":"Professional",
            "type":"Services"
        }
    ],
    "sg:phone":"+1 801 426 5504",
    "sg:postcode":"84058",
    "sg:province":"UT",
    "wof:name":"Ranmac Inc",
    "wof:placetype":"venue"
},
  "geometry": {"coordinates":[-111.735406,40.282065],"type":"Point"}
}