{
  "type": "Feature",
  "properties": {
    "iso:country":"US",
    "sg:address":"1067 24th St",
    "sg:city":"Ogden",
    "sg:classifiers":[
        {
            "category":"Health Services",
            "subcategory":"Doctor",
            "type":"Services"
        }
    ],
    "sg:phone":"+1 801 621 5892",
    "sg:postcode":"84401",
    "sg:province":"UT",
    "wof:name":"Leland Pack",
    "wof:placetype":"venue"
},
  "geometry": {"coordinates":[-111.951356,41.222429],"type":"Point"}
}