{
  "type": "Feature",
  "properties": {
    "iso:country":"US",
    "sg:address":"1345 Cliffside Dr",
    "sg:city":"Logan",
    "sg:classifiers":[
        {
            "category":"Wholesale",
            "subcategory":"Toys & Hobbies",
            "type":"Manufacturing & Wholesale Goods"
        }
    ],
    "sg:phone":"+1 435 752 6175",
    "sg:postcode":"84321",
    "sg:province":"UT",
    "wof:name":"Ground Zero Cards & Hobbies",
    "wof:placetype":"venue"
},
  "geometry": {"coordinates":[-111.80209499999999,41.734151],"type":"Point"}
}