{
  "type": "Feature",
  "properties": {
    "iso:country":"US",
    "sg:address":"21 S Rio Grande St",
    "sg:city":"Salt Lake City",
    "sg:classifiers":[
        {
            "category":"Shopping",
            "type":"Retail Goods"
        }
    ],
    "sg:phone":"+1 801 456 0375",
    "sg:postcode":"84101",
    "sg:province":"UT",
    "sg:tags":[
        "candle"
    ],
    "wof:name":"Breaking The Mold",
    "wof:placetype":"venue"
},
  "geometry": {"coordinates":[-111.90409099999999,40.762817],"type":"Point"}
}