{
  "type": "Feature",
  "properties": {
    "iso:country":"US",
    "sg:address":"94 S Main St",
    "sg:city":"Helper",
    "sg:classifiers":[
        {
            "category":"Sports & Exercise",
            "subcategory":"Bowling",
            "type":"Entertainment"
        }
    ],
    "sg:phone":"+1 435 472 5015",
    "sg:postcode":"84526",
    "sg:province":"UT",
    "sg:tags":[
        "center"
    ],
    "wof:name":"Gateway Lanes",
    "wof:placetype":"venue"
},
  "geometry": {"coordinates":[-110.85462699999999,39.687699],"type":"Point"}
}