{
  "type": "Feature",
  "properties": {
    "iso:country":"US",
    "sg:address":"338 E 300 S",
    "sg:city":"Salt Lake City",
    "sg:classifiers":[
        {
            "category":"Real Estate",
            "subcategory":"Real Estate Operator",
            "type":"Services"
        }
    ],
    "sg:phone":"+1 801 534 1211",
    "sg:postcode":"84111",
    "sg:province":"UT",
    "sg:tags":[
        "apartment"
    ],
    "wof:name":"Kathleen Robinson Huntsma Apts",
    "wof:placetype":"venue"
},
  "geometry": {"coordinates":[-111.880618,40.762752],"type":"Point"}
}