{
  "type": "Feature",
  "properties": {
    "iso:country":"US",
    "sg:address":"10920 S State St",
    "sg:city":"Sandy",
    "sg:classifiers":[
        {
            "category":"Autos & Motor Vehicles",
            "subcategory":"Automobile Sales",
            "type":"Retail Goods"
        }
    ],
    "sg:phone":"+1 801 553 5200",
    "sg:postcode":"84070",
    "sg:province":"UT",
    "sg:tags":[
        "car",
        "dealer"
    ],
    "sg:website":"www.lhm.com",
    "wof:name":"Larry H Miller Subaru",
    "wof:placetype":"venue"
},
  "geometry": {"coordinates":[-111.890849,40.552077],"type":"Point"}
}