{
  "type": "Feature",
  "properties": {
    "iso:country":"US",
    "sg:address":"1894 W 5400 S",
    "sg:city":"Salt Lake City",
    "sg:classifiers":[
        {
            "category":"Recreation",
            "type":"Entertainment"
        }
    ],
    "sg:phone":"+1 801 982 0119",
    "sg:postcode":"84118",
    "sg:province":"UT",
    "sg:tags":[
        "martial",
        "arts",
        "instruction"
    ],
    "wof:name":"Taylorsville Martial Arts",
    "wof:placetype":"venue"
},
  "geometry": {"coordinates":[-111.944306,40.653187],"type":"Point"}
}