{
  "type": "Feature",
  "properties": {
    "iso:country":"US",
    "sg:address":"10707 S 580 E",
    "sg:city":"Sandy",
    "sg:classifiers":[
        {
            "category":"Professional",
            "subcategory":"Management & Consulting",
            "type":"Services"
        }
    ],
    "sg:phone":"+1 801 571 6591",
    "sg:postcode":"84070",
    "sg:province":"UT",
    "sg:tags":[
        "retail",
        "direct",
        "sales"
    ],
    "wof:name":"Mary Kay Cosmetics",
    "wof:placetype":"venue"
},
  "geometry": {"coordinates":[-111.874871,40.556598],"type":"Point"}
}