{
  "type": "Feature",
  "properties": {
    "iso:country":"US",
    "sg:address":"1082 Fort Union Blvd",
    "sg:city":"Midvale",
    "sg:classifiers":[
        {
            "category":"Utilities",
            "subcategory":"Mobile Phone",
            "type":"Services"
        }
    ],
    "sg:phone":"+1 801 568 5154",
    "sg:postcode":"84047",
    "sg:province":"UT",
    "sg:tags":[
        "telephone",
        "cellular"
    ],
    "wof:name":"Verizon Wireless",
    "wof:placetype":"venue"
},
  "geometry": {"coordinates":[-111.861531,40.623541],"type":"Point"}
}