{
  "type": "Feature",
  "properties": {
    "iso:country":"US",
    "sg:address":"215 2nd Ave",
    "sg:city":"Salt Lake City",
    "sg:classifiers":[
        {
            "category":"Retail",
            "subcategory":"Photofinishing",
            "type":"Services"
        }
    ],
    "sg:phone":"+1 801 363 3429",
    "sg:postcode":"84103",
    "sg:province":"UT",
    "sg:tags":[
        "laboratory",
        "portrait",
        "studio",
        "photo"
    ],
    "wof:name":"Altus Photo Design",
    "wof:placetype":"venue"
},
  "geometry": {"coordinates":[-111.88245000000001,40.771777],"type":"Point"}
}