{
  "type": "Feature",
  "properties": {
    "iso:country":"US",
    "sg:address":"251 N State St",
    "sg:city":"Orem",
    "sg:classifiers":[
        {
            "category":"Food & Beverages",
            "subcategory":"Groceries & Convenience Stores",
            "type":"Retail Goods"
        }
    ],
    "sg:phone":"+1 801 225 5239",
    "sg:postcode":"84057",
    "sg:province":"UT",
    "wof:name":"Walkers Food & Fuel",
    "wof:placetype":"venue"
},
  "geometry": {"coordinates":[-111.697174,40.301696],"type":"Point"}
}