{
  "type": "Feature",
  "properties": {
    "iso:country":"US",
    "sg:address":"460 N 900 E",
    "sg:city":"Provo",
    "sg:classifiers":[
        {
            "category":"Sports & Exercise",
            "subcategory":"Gym",
            "type":"Entertainment"
        }
    ],
    "sg:phone":"+1 801 377 2666",
    "sg:postcode":"84606",
    "sg:province":"UT",
    "sg:tags":[
        "club",
        "health",
        "studio",
        "gymnasium"
    ],
    "sg:website":"www.goldsgym.com",
    "wof:name":"Gold's Gym",
    "wof:placetype":"venue"
},
  "geometry": {"coordinates":[-111.643074,40.241155],"type":"Point"}
}