{
  "type": "Feature",
  "properties": {
    "iso:country":"US",
    "sg:address":"22 E 200 N",
    "sg:city":"Farmington",
    "sg:classifiers":[
        {
            "category":"Building & Trades",
            "subcategory":"Construction",
            "type":"Services"
        }
    ],
    "sg:phone":"+1 801 447 8498",
    "sg:postcode":"84025",
    "sg:province":"UT",
    "sg:tags":[
        "house"
    ],
    "wof:name":"Silver Pointe Construction",
    "wof:placetype":"venue"
},
  "geometry": {"coordinates":[-111.885712,40.983654],"type":"Point"}
}