{
  "type": "Feature",
  "properties": {
    "iso:country":"US",
    "sg:address":"268 Main St",
    "sg:city":"Park City",
    "sg:classifiers":[
        {
            "category":"Bars & Pubs",
            "type":"Food & Drink"
        }
    ],
    "sg:phone":"+1 435 615 7588",
    "sg:postcode":"84060",
    "sg:province":"UT",
    "sg:tags":[
        "club",
        "night"
    ],
    "wof:name":"Plan B",
    "wof:placetype":"venue"
},
  "geometry": {"coordinates":[-111.495456,40.642792],"type":"Point"}
}