{
  "type": "Feature",
  "properties": {
    "iso:country":"US",
    "sg:address":"9468 Union Sq",
    "sg:city":"Sandy",
    "sg:classifiers":[
        {
            "category":"Food & Beverages",
            "subcategory":"Groceries & Convenience Stores",
            "type":"Retail Goods"
        }
    ],
    "sg:phone":"+1 801 572 4920",
    "sg:postcode":"84070",
    "sg:province":"UT",
    "sg:tags":[
        "delicatessen",
        "caterer"
    ],
    "sg:website":"www.wasatchdeli.com",
    "wof:name":"Wasatch Deli & Catering",
    "wof:placetype":"venue"
},
  "geometry": {"coordinates":[-111.87226800000001,40.580204],"type":"Point"}
}