{
  "type": "Feature",
  "properties": {
    "iso:country":"US",
    "sg:address":"3712 Pacific Ave",
    "sg:city":"Ogden",
    "sg:classifiers":[
        {
            "category":"Home & Garden",
            "subcategory":"Building Materials",
            "type":"Retail Goods"
        }
    ],
    "sg:phone":"+1 801 621 4633",
    "sg:postcode":"84401",
    "sg:province":"UT",
    "wof:name":"ICI Dulux Paint Centers",
    "wof:placetype":"venue"
},
  "geometry": {"coordinates":[-111.985311,41.197755],"type":"Point"}
}