{
  "type": "Feature",
  "properties": {
    "iso:country":"US",
    "sg:address":"115 W Main St",
    "sg:city":"Mount Pleasant",
    "sg:classifiers":[
        {
            "category":"Banks & Credit Unions",
            "subcategory":"Bank",
            "type":"Services"
        }
    ],
    "sg:phone":"+1 435 462 3108",
    "sg:postcode":"84647",
    "sg:province":"UT",
    "sg:tags":[
        "national",
        "commercial"
    ],
    "wof:name":"Wells Fargo Bank N A",
    "wof:placetype":"venue"
},
  "geometry": {"coordinates":[-111.458938,39.546719],"type":"Point"}
}