{
  "type": "Feature",
  "properties": {
    "iso:country":"US",
    "sg:address":"1902 Mary Dott Way",
    "sg:city":"Salt Lake City",
    "sg:classifiers":[
        {
            "category":"Professional",
            "subcategory":"Management & Consulting",
            "type":"Services"
        }
    ],
    "sg:phone":"+1 801 484 8068",
    "sg:postcode":"84106",
    "sg:province":"UT",
    "sg:tags":[
        "business"
    ],
    "wof:name":"SLC Environmental LLC",
    "wof:placetype":"venue"
},
  "geometry": {"coordinates":[-111.837476,40.707567],"type":"Point"}
}