{
  "type": "Feature",
  "properties": {
    "iso:country":"US",
    "sg:address":"261 Julie Ann Ct",
    "sg:city":"Tooele",
    "sg:classifiers":[
        {
            "category":"Professional",
            "subcategory":"Management & Consulting",
            "type":"Services"
        }
    ],
    "sg:phone":"+1 435 882 4329",
    "sg:postcode":"84074",
    "sg:province":"UT",
    "sg:tags":[
        "retail",
        "direct",
        "sales"
    ],
    "wof:name":"Tobie Warner",
    "wof:placetype":"venue"
},
  "geometry": {"coordinates":[-112.305955,40.517137],"type":"Point"}
}