{
  "type": "Feature",
  "properties": {
    "iso:country":"US",
    "sg:address":"280 W 100 N",
    "sg:city":"Roosevelt",
    "sg:classifiers":[
        {
            "category":"Real Estate",
            "subcategory":"Real Estate Agent",
            "type":"Services"
        }
    ],
    "sg:phone":"+1 435 722 3702",
    "sg:postcode":"84066",
    "sg:province":"UT",
    "wof:name":"Connie Larsen Lamb",
    "wof:placetype":"venue"
},
  "geometry": {"coordinates":[-109.995486,40.300885],"type":"Point"}
}