{
  "type": "Feature",
  "properties": {
    "iso:country":"US",
    "sg:address":"4826 S 2200 W",
    "sg:city":"Salt Lake City",
    "sg:classifiers":[
        {
            "category":"Building & Trades",
            "subcategory":"Landscaping Services",
            "type":"Services"
        }
    ],
    "sg:phone":"+1 801 965 9455",
    "sg:postcode":"84118",
    "sg:province":"UT",
    "sg:tags":[
        "lawn",
        "maintenance",
        "grounds"
    ],
    "wof:name":"Mower For Less",
    "wof:placetype":"venue"
},
  "geometry": {"coordinates":[-111.9485,40.664691],"type":"Point"}
}