{
  "type": "Feature",
  "properties": {
    "iso:country":"US",
    "sg:address":"39 S Main St",
    "sg:city":"Cedar City",
    "sg:classifiers":[
        {
            "category":"Autos & Motor Vehicles",
            "subcategory":"Automobile Sales",
            "type":"Retail Goods"
        }
    ],
    "sg:phone":"+1 435 586 6591",
    "sg:postcode":"84720",
    "sg:province":"UT",
    "sg:tags":[
        "car",
        "dealer"
    ],
    "sg:website":"www.luntmotor.com",
    "wof:name":"Lunt Motor Co",
    "wof:placetype":"venue"
},
  "geometry": {"coordinates":[-113.061575,37.676809],"type":"Point"}
}