{
  "type": "Feature",
  "properties": {
    "iso:country":"US",
    "sg:address":"4420 S State St",
    "sg:city":"Salt Lake City",
    "sg:classifiers":[
        {
            "category":"Autos & Motor Vehicles",
            "subcategory":"Automobile Sales",
            "type":"Retail Goods"
        }
    ],
    "sg:phone":"+1 801 262 5550",
    "sg:postcode":"84107",
    "sg:province":"UT",
    "sg:tags":[
        "used"
    ],
    "wof:name":"T W Auto Wholesale",
    "wof:placetype":"venue"
},
  "geometry": {"coordinates":[-111.88836000000001,40.674607],"type":"Point"}
}