{
  "type": "Feature",
  "properties": {
    "iso:country":"US",
    "sg:address":"55 N Main St",
    "sg:city":"Manti",
    "sg:classifiers":[
        {
            "category":"Insurance",
            "subcategory":"Insurance Agent",
            "type":"Services"
        }
    ],
    "sg:phone":"+1 435 835 8890",
    "sg:postcode":"84642",
    "sg:province":"UT",
    "wof:name":"Mr Insurance",
    "wof:placetype":"venue"
},
  "geometry": {"coordinates":[-111.63704300000001,39.265819],"type":"Point"}
}