{
  "type": "Feature",
  "properties": {
    "iso:country":"US",
    "sg:address":"1918 E 9400 S",
    "sg:city":"Sandy",
    "sg:classifiers":[
        {
            "category":"Professional",
            "subcategory":"Business Services",
            "type":"Services"
        },
        {
            "category":"Government",
            "subcategory":"Post Office",
            "type":"Public Place"
        }
    ],
    "sg:phone":"+1 801 571 8974",
    "sg:postcode":"84093",
    "sg:province":"UT",
    "sg:tags":[
        "delivery",
        "messenger",
        "courier"
    ],
    "wof:name":"Parcels And Papers",
    "wof:placetype":"venue"
},
  "geometry": {"coordinates":[-111.83722400000001,40.580426],"type":"Point"}
}