{
  "type": "Feature",
  "properties": {
    "iso:country":"US",
    "sg:address":"126 W 1070 S",
    "sg:city":"Hurricane",
    "sg:classifiers":[
        {
            "category":"Building & Trades",
            "subcategory":"Plumbing",
            "type":"Services"
        }
    ],
    "sg:phone":"+1 435 635 2236",
    "sg:postcode":"84737",
    "sg:province":"UT",
    "sg:tags":[
        "contractor"
    ],
    "wof:name":"Sunland Plumbing",
    "wof:placetype":"venue"
},
  "geometry": {"coordinates":[-113.29007300000001,37.160903],"type":"Point"}
}