{
  "type": "Feature",
  "properties": {
    "iso:country":"US",
    "sg:address":"1273 W 500 N",
    "sg:city":"Salt Lake City",
    "sg:classifiers":[
        {
            "category":"Personal",
            "subcategory":"Beauty Salon",
            "type":"Services"
        }
    ],
    "sg:phone":"+1 801 328 0588",
    "sg:postcode":"84116",
    "sg:province":"UT",
    "wof:name":"Eu Belle Beauty Salon",
    "wof:placetype":"venue"
},
  "geometry": {"coordinates":[-111.92785600000001,40.780127],"type":"Point"}
}