{
  "type": "Feature",
  "properties": {
    "iso:country":"US",
    "sg:address":"1470 S 600 W",
    "sg:city":"Bountiful",
    "sg:classifiers":[
        {
            "category":"Building & Trades",
            "subcategory":"Electrical",
            "type":"Services"
        }
    ],
    "sg:phone":"+1 801 295 2271",
    "sg:postcode":"84010",
    "sg:province":"UT",
    "sg:tags":[
        "security",
        "installation"
    ],
    "wof:name":"ABS",
    "wof:placetype":"venue"
},
  "geometry": {"coordinates":[-111.89595799999999,40.875077],"type":"Point"}
}