{
  "type": "Feature",
  "properties": {
    "iso:country":"US",
    "sg:address":"2100 S West Temple",
    "sg:city":"Salt Lake City",
    "sg:classifiers":[
        {
            "category":"Retail",
            "subcategory":"Auto Repair",
            "type":"Services"
        }
    ],
    "sg:phone":"+1 801 486 0733",
    "sg:postcode":"84115",
    "sg:province":"UT",
    "sg:tags":[
        "automotive",
        "brake",
        "general"
    ],
    "wof:name":"Mr Muffler",
    "wof:placetype":"venue"
},
  "geometry": {"coordinates":[-111.893967,40.724595],"type":"Point"}
}