{
  "type": "Feature",
  "properties": {
    "iso:country":"US",
    "sg:address":"2106 N 1000 E",
    "sg:city":"Lehi",
    "sg:classifiers":[
        {
            "category":"Shopping",
            "subcategory":"Hobbies, Toys, & Games",
            "type":"Retail Goods"
        }
    ],
    "sg:phone":"+1 801 766 9633",
    "sg:postcode":"84043",
    "sg:province":"UT",
    "sg:tags":[
        "craft"
    ],
    "wof:name":"I'm Scrappin",
    "wof:placetype":"venue"
},
  "geometry": {"coordinates":[-111.833417,40.41453],"type":"Point"}
}