{
  "type": "Feature",
  "properties": {
    "iso:country":"US",
    "sg:address":"465 E 600 S",
    "sg:city":"St George",
    "sg:classifiers":[
        {
            "category":"Farming",
            "subcategory":"Farm",
            "type":"Manufacturing & Wholesale Goods"
        }
    ],
    "sg:phone":"+1 435 673 2589",
    "sg:postcode":"84770",
    "sg:province":"UT",
    "sg:tags":[
        "crop",
        "general"
    ],
    "wof:name":"Hafen Bros Farm",
    "wof:placetype":"venue"
},
  "geometry": {"coordinates":[-113.57367600000001,37.098059],"type":"Point"}
}