{
  "type": "Feature",
  "properties": {
    "iso:country":"US",
    "sg:address":"363 E Main St",
    "sg:city":"Vernal",
    "sg:classifiers":[
        {
            "category":"Insurance",
            "subcategory":"Health Insurance",
            "type":"Services"
        },
        {
            "category":"Insurance",
            "subcategory":"Insurance Agent",
            "type":"Services"
        }
    ],
    "sg:phone":"+1 435 789 3171",
    "sg:postcode":"84078",
    "sg:province":"UT",
    "sg:tags":[
        "plan"
    ],
    "sg:website":"www.mayberryinsurance.com",
    "wof:name":"Mayberry Insurance Svc Inc",
    "wof:placetype":"venue"
},
  "geometry": {"coordinates":[-109.521907,40.455869],"type":"Point"}
}