{
  "type": "Feature",
  "properties": {
    "iso:country":"US",
    "sg:address":"396 Rosewood Dr",
    "sg:city":"Hyrum",
    "sg:classifiers":[
        {
            "category":"Real Estate",
            "subcategory":"Real Estate Agent",
            "type":"Services"
        }
    ],
    "sg:phone":"+1 435 245 7570",
    "sg:postcode":"84319",
    "sg:province":"UT",
    "wof:name":"Teters Appraisal Services",
    "wof:placetype":"venue"
},
  "geometry": {"coordinates":[-111.839861,41.625594],"type":"Point"}
}