{
  "type": "Feature",
  "properties": {
    "iso:country":"US",
    "sg:address":"1730 S State St",
    "sg:city":"Provo",
    "sg:classifiers":[
        {
            "category":"Food & Beverages",
            "subcategory":"Groceries & Convenience Stores",
            "type":"Retail Goods"
        }
    ],
    "sg:phone":"+1 801 377 4483",
    "sg:postcode":"84606",
    "sg:province":"UT",
    "sg:tags":[
        "grocer"
    ],
    "wof:name":"Sunrise Food Mart",
    "wof:placetype":"venue"
},
  "geometry": {"coordinates":[-111.631253,40.209661],"type":"Point"}
}