{
  "type": "Feature",
  "properties": {
    "iso:country":"US",
    "sg:address":"215 E 1600 N",
    "sg:city":"Santaquin",
    "sg:classifiers":[
        {
            "category":"Building & Trades",
            "subcategory":"Plumbing",
            "type":"Services"
        }
    ],
    "sg:phone":"+1 801 754 3155",
    "sg:postcode":"84655",
    "sg:province":"UT",
    "sg:tags":[
        "contractor"
    ],
    "wof:name":"US Mechanical",
    "wof:placetype":"venue"
},
  "geometry": {"coordinates":[-111.838437,40.025629],"type":"Point"}
}