{
  "type": "Feature",
  "properties": {
    "iso:country":"US",
    "sg:address":"4540 S 900 E",
    "sg:city":"Salt Lake City",
    "sg:classifiers":[
        {
            "category":"Social Services",
            "subcategory":"Child Care",
            "type":"Services"
        }
    ],
    "sg:phone":"+1 801 266 3590",
    "sg:postcode":"84117",
    "sg:province":"UT",
    "sg:tags":[
        "day"
    ],
    "wof:name":"Learning Tree",
    "wof:placetype":"venue"
},
  "geometry": {"coordinates":[-111.865618,40.673371],"type":"Point"}
}