{
  "type": "Feature",
  "properties": {
    "iso:country":"US",
    "sg:address":"7776 S 2175 E",
    "sg:city":"Ogden",
    "sg:classifiers":[
        {
            "category":"Organizations",
            "subcategory":"Religious Organization",
            "type":"Services"
        }
    ],
    "sg:phone":"+1 801 475 7866",
    "sg:postcode":"84405",
    "sg:province":"UT",
    "wof:name":"Faith Enterprises Inc",
    "wof:placetype":"venue"
},
  "geometry": {"coordinates":[-111.922838,41.126428],"type":"Point"}
}