{
  "type": "Feature",
  "properties": {
    "iso:country":"US",
    "sg:address":"114 F St",
    "sg:city":"Salt Lake City",
    "sg:classifiers":[
        {
            "category":"Health Services",
            "subcategory":"Clinic",
            "type":"Services"
        }
    ],
    "sg:phone":"+1 435 640 1152",
    "sg:postcode":"84103",
    "sg:province":"UT",
    "sg:tags":[
        "specialty",
        "outpatient"
    ],
    "wof:name":"Women Beyond Cancer",
    "wof:placetype":"venue"
},
  "geometry": {"coordinates":[-111.87598,40.772519],"type":"Point"}
}