{
  "type": "Feature",
  "properties": {
    "iso:country":"US",
    "sg:address":"3070 Rasmussen Rd",
    "sg:city":"Park City",
    "sg:classifiers":[
        {
            "category":"Manufacturing",
            "subcategory":"Metals",
            "type":"Manufacturing & Wholesale Goods"
        }
    ],
    "sg:phone":"+1 435 940 9222",
    "sg:postcode":"84098",
    "sg:province":"UT",
    "sg:tags":[
        "seismic",
        "brace",
        "producer"
    ],
    "wof:name":"Star Seismic LLC",
    "wof:placetype":"venue"
},
  "geometry": {"coordinates":[-111.566525,40.749561],"type":"Point"}
}