{
  "type": "Feature",
  "properties": {
    "iso:country":"US",
    "sg:address":"2075 S 700 E",
    "sg:city":"Salt Lake City",
    "sg:classifiers":[
        {
            "category":"Manufacturing",
            "subcategory":"Food",
            "type":"Manufacturing & Wholesale Goods"
        }
    ],
    "sg:phone":"+1 801 484 1251",
    "sg:postcode":"84105",
    "sg:province":"UT",
    "sg:tags":[
        "bakery"
    ],
    "wof:name":"Bakers De Normandie",
    "wof:placetype":"venue"
},
  "geometry": {"coordinates":[-111.87101699999999,40.726147],"type":"Point"}
}