{
  "type": "Feature",
  "properties": {
    "iso:country":"US",
    "sg:address":"609 N Main St",
    "sg:city":"Panguitch",
    "sg:classifiers":[
        {
            "category":"Insurance",
            "subcategory":"Insurance Agent",
            "type":"Services"
        }
    ],
    "sg:phone":"+1 435 676 2240",
    "sg:postcode":"84759",
    "sg:province":"UT",
    "wof:name":"Yardley Insurance",
    "wof:placetype":"venue"
},
  "geometry": {"coordinates":[-112.435722,37.832344],"type":"Point"}
}