{
  "type": "Feature",
  "properties": {
    "iso:country":"US",
    "sg:address":"12352 Rose Creek Ln",
    "sg:city":"Kamas",
    "sg:classifiers":[
        {
            "category":"Professional",
            "type":"Services"
        }
    ],
    "sg:phone":"+1 435 782 5003",
    "sg:postcode":"84065",
    "sg:province":"UT",
    "sg:tags":[
        "establishment"
    ],
    "wof:name":"Forum Capital",
    "wof:placetype":"venue"
},
  "geometry": {"coordinates":[-112.064893,40.483662],"type":"Point"}
}