{
  "type": "Feature",
  "properties": {
    "iso:country":"US",
    "sg:address":"1592 Oakcrest Dr",
    "sg:city":"Ogden",
    "sg:classifiers":[
        {
            "category":"Professional",
            "type":"Services"
        }
    ],
    "sg:phone":"+1 801 392 6186",
    "sg:postcode":"84403",
    "sg:province":"UT",
    "wof:name":"In House Service Bureau Inc",
    "wof:placetype":"venue"
},
  "geometry": {"coordinates":[-111.939216,41.182264],"type":"Point"}
}