{
  "type": "Feature",
  "properties": {
    "iso:country":"US",
    "sg:address":"245 E 860 N",
    "sg:city":"Hurricane",
    "sg:classifiers":[
        {
            "category":"Government",
            "subcategory":"Office",
            "type":"Public Place"
        }
    ],
    "sg:phone":"+1 435 635 3817",
    "sg:postcode":"84737",
    "sg:province":"UT",
    "sg:tags":[
        "hearing",
        "security",
        "appeal",
        "for",
        "social"
    ],
    "wof:name":"Hearing & Appeals",
    "wof:placetype":"venue"
},
  "geometry": {"coordinates":[-113.284387,37.189227],"type":"Point"}
}