{
  "type": "Feature",
  "properties": {
    "iso:country":"US",
    "sg:address":"5242 College Dr",
    "sg:city":"Salt Lake City",
    "sg:classifiers":[
        {
            "category":"Professional",
            "subcategory":"Employment Agencies",
            "type":"Services"
        }
    ],
    "sg:phone":"+1 801 685 7070",
    "sg:postcode":"84123",
    "sg:province":"UT",
    "sg:tags":[
        "medical",
        "help"
    ],
    "wof:name":"Salt Lake Homecare",
    "wof:placetype":"venue"
},
  "geometry": {"coordinates":[-111.905794,40.657253],"type":"Point"}
}