{
  "type": "Feature",
  "properties": {
    "iso:country":"US",
    "sg:address":"1136 E 100 S",
    "sg:city":"Salt Lake City",
    "sg:classifiers":[
        {
            "category":"Professional",
            "subcategory":"Business Services",
            "type":"Services"
        }
    ],
    "sg:phone":"+1 801 359 0711",
    "sg:postcode":"84102",
    "sg:province":"UT",
    "wof:name":"Capener Company",
    "wof:placetype":"venue"
},
  "geometry": {"coordinates":[-111.858999,40.767104],"type":"Point"}
}