{
  "type": "Feature",
  "properties": {
    "iso:country":"US",
    "sg:address":"650 W 100 N",
    "sg:city":"Provo",
    "sg:classifiers":[
        {
            "category":"Government",
            "subcategory":"Office",
            "type":"Public Place"
        }
    ],
    "sg:phone":"+1 801 374 1331",
    "sg:postcode":"84601",
    "sg:province":"UT",
    "sg:tags":[
        "housing",
        "program"
    ],
    "wof:name":"Housing Authority of Provo",
    "wof:placetype":"venue"
},
  "geometry": {"coordinates":[-111.670328,40.235209],"type":"Point"}
}