{
  "type": "Feature",
  "properties": {
    "iso:country":"US",
    "sg:address":"53 S Mahogany Way",
    "sg:city":"Payson",
    "sg:classifiers":[
        {
            "category":"Retail",
            "subcategory":"Portrait Studio",
            "type":"Services"
        }
    ],
    "sg:phone":"+1 801 423 9100",
    "sg:postcode":"84651",
    "sg:province":"UT",
    "sg:tags":[
        "photo"
    ],
    "wof:name":"Melanie Paxton Photography",
    "wof:placetype":"venue"
},
  "geometry": {"coordinates":[-111.680221,40.012586],"type":"Point"}
}