{
  "type": "Feature",
  "properties": {
    "iso:country":"US",
    "sg:address":"5567 Commerce Dr",
    "sg:city":"Salt Lake City",
    "sg:classifiers":[
        {
            "category":"Autos & Motor Vehicles",
            "subcategory":"Recreational Vehicle Sales",
            "type":"Retail Goods"
        }
    ],
    "sg:phone":"+1 801 262 5904",
    "sg:postcode":"84107",
    "sg:province":"UT",
    "wof:name":"Top It of Salt Lake",
    "wof:placetype":"venue"
},
  "geometry": {"coordinates":[-111.901973,40.644235],"type":"Point"}
}