{
  "type": "Feature",
  "properties": {
    "iso:country":"US",
    "sg:address":"685 E 1700 N",
    "sg:city":"Provo",
    "sg:classifiers":[
        {
            "category":"Education",
            "subcategory":"School",
            "type":"Public Place"
        }
    ],
    "sg:phone":"+1 801 378 4835",
    "sg:postcode":"84604",
    "sg:province":"UT",
    "sg:tags":[
        "university"
    ],
    "wof:name":"Receiving Department",
    "wof:placetype":"venue"
},
  "geometry": {"coordinates":[-111.64369000000001,40.256756],"type":"Point"}
}