{
  "type": "Feature",
  "properties": {
    "iso:country":"US",
    "sg:address":"230 W 200 S",
    "sg:city":"Salt Lake City",
    "sg:classifiers":[
        {
            "category":"Manufacturing",
            "subcategory":"Jewelry",
            "type":"Manufacturing & Wholesale Goods"
        },
        {
            "category":"Shopping",
            "subcategory":"Jewelry",
            "type":"Retail Goods"
        }
    ],
    "sg:phone":"+1 801 363 3333",
    "sg:postcode":"84101",
    "sg:province":"UT",
    "sg:tags":[
        "precious",
        "jeweler",
        "metal",
        "mfg"
    ],
    "sg:website":"www.saltlakesilver.com",
    "wof:name":"Salt Lake Silver Ring",
    "wof:placetype":"venue"
},
  "geometry": {"coordinates":[-111.89887,40.765071],"type":"Point"}
}