{
  "type": "Feature",
  "properties": {
    "iso:country":"US",
    "sg:address":"7623 Main St",
    "sg:city":"Midvale",
    "sg:classifiers":[
        {
            "category":"Professional",
            "subcategory":"Accounting & Tax Preparation",
            "type":"Services"
        }
    ],
    "sg:phone":"+1 801 569 9480",
    "sg:postcode":"84047",
    "sg:province":"UT",
    "wof:name":"Keith Sizemore",
    "wof:placetype":"venue"
},
  "geometry": {"coordinates":[-111.910218,40.612613],"type":"Point"}
}