{
  "type": "Feature",
  "properties": {
    "iso:country":"US",
    "sg:address":"1060 E 450 North St",
    "sg:city":"Provo",
    "sg:classifiers":[
        {
            "category":"Real Estate",
            "subcategory":"Real Estate Operator",
            "type":"Services"
        }
    ],
    "sg:phone":"+1 801 371 6600",
    "sg:postcode":"84606",
    "sg:province":"UT",
    "sg:tags":[
        "building",
        "apartment"
    ],
    "wof:name":"Roman Gardens Apartments",
    "wof:placetype":"venue"
},
  "geometry": {"coordinates":[-111.640581,40.239881],"type":"Point"}
}