{
  "type": "Feature",
  "properties": {
    "iso:country":"US",
    "sg:address":"1895 E 5775 South St",
    "sg:city":"Ogden",
    "sg:classifiers":[
        {
            "category":"Retail",
            "subcategory":"Portrait Studio",
            "type":"Services"
        }
    ],
    "sg:phone":"+1 801 475 6201",
    "sg:postcode":"84403",
    "sg:province":"UT",
    "sg:tags":[
        "photo"
    ],
    "wof:name":"Specialty Videos Inc",
    "wof:placetype":"venue"
},
  "geometry": {"coordinates":[-111.93566800000001,41.157889],"type":"Point"}
}