{
  "type": "Feature",
  "properties": {
    "iso:country":"US",
    "sg:address":"271 E 450 N",
    "sg:city":"Lindon",
    "sg:classifiers":[
        {
            "category":"Cinema",
            "subcategory":"Movie Rental",
            "type":"Entertainment"
        }
    ],
    "sg:phone":"+1 801 360 0793",
    "sg:postcode":"84042",
    "sg:province":"UT",
    "sg:tags":[
        "video",
        "tape"
    ],
    "wof:name":"Entertainment Marketplace",
    "wof:placetype":"venue"
},
  "geometry": {"coordinates":[-111.708513,40.346663],"type":"Point"}
}