{
  "type": "Feature",
  "properties": {
    "iso:country":"US",
    "sg:address":"1622 W Erickson Park Dr",
    "sg:city":"West Jordan",
    "sg:classifiers":[
        {
            "category":"Building & Trades",
            "subcategory":"Electrical",
            "type":"Services"
        }
    ],
    "sg:phone":"+1 801 567 1473",
    "sg:postcode":"84084",
    "sg:province":"UT",
    "sg:tags":[
        "electrical",
        "contractor"
    ],
    "wof:name":"Ahlstrom Electrical Services",
    "wof:placetype":"venue"
},
  "geometry": {"coordinates":[-111.937044,40.618514],"type":"Point"}
}