{
  "type": "Feature",
  "properties": {
    "iso:country":"US",
    "sg:address":"491 Julep Dr",
    "sg:city":"Salt Lake City",
    "sg:classifiers":[
        {
            "category":"Banks & Credit Unions",
            "subcategory":"Bank",
            "type":"Services"
        }
    ],
    "sg:phone":"+1 801 263 2244",
    "sg:postcode":"84107",
    "sg:province":"UT",
    "sg:tags":[
        "mortgage"
    ],
    "wof:name":"Liahona Publishing",
    "wof:placetype":"venue"
},
  "geometry": {"coordinates":[-111.877084,40.672379],"type":"Point"}
}