{
  "type": "Feature",
  "properties": {
    "iso:country":"US",
    "sg:address":"1182 W 120 N",
    "sg:city":"St George",
    "sg:classifiers":[
        {
            "category":"Real Estate",
            "subcategory":"Developer",
            "type":"Services"
        }
    ],
    "sg:phone":"+1 435 628 4663",
    "sg:postcode":"84770",
    "sg:province":"UT",
    "sg:tags":[
        "broker"
    ],
    "wof:name":"Go Realty",
    "wof:placetype":"venue"
},
  "geometry": {"coordinates":[-113.60900700000001,37.110673],"type":"Point"}
}