{
  "type": "Feature",
  "properties": {
    "iso:country":"US",
    "sg:address":"5383 S 900 E",
    "sg:city":"Salt Lake City",
    "sg:classifiers":[
        {
            "category":"Travel",
            "subcategory":"Travel Agent",
            "type":"Entertainment"
        }
    ],
    "sg:phone":"+1 801 267 5700",
    "sg:postcode":"84117",
    "sg:province":"UT",
    "sg:tags":[
        "agency"
    ],
    "wof:name":"Jensen Baron",
    "wof:placetype":"venue"
},
  "geometry": {"coordinates":[-111.865927,40.654258],"type":"Point"}
}