{
  "type": "Feature",
  "properties": {
    "iso:country":"US",
    "sg:address":"8652 S 4000 W",
    "sg:city":"West Jordan",
    "sg:classifiers":[
        {
            "category":"Utilities",
            "subcategory":"Refuse",
            "type":"Services"
        }
    ],
    "sg:phone":"+1 801 280 8200",
    "sg:postcode":"84088",
    "sg:province":"UT",
    "sg:tags":[
        "system"
    ],
    "wof:name":"America A Recycle Waste",
    "wof:placetype":"venue"
},
  "geometry": {"coordinates":[-111.986498,40.593827],"type":"Point"}
}