{
  "type": "Feature",
  "properties": {
    "iso:country":"US",
    "sg:address":"2010 W 3775 S",
    "sg:city":"Roy",
    "sg:classifiers":[
        {
            "category":"Building & Trades",
            "subcategory":"Construction",
            "type":"Services"
        }
    ],
    "sg:phone":"+1 801 731 5595",
    "sg:postcode":"84067",
    "sg:province":"UT",
    "sg:tags":[
        "contractor"
    ],
    "wof:name":"Utah Tile & Stone Restoration",
    "wof:placetype":"venue"
},
  "geometry": {"coordinates":[-112.028571,41.194864],"type":"Point"}
}