{
  "type": "Feature",
  "properties": {
    "iso:country":"US",
    "sg:address":"1849 N Freedom Blvd",
    "sg:city":"Provo",
    "sg:classifiers":[
        {
            "category":"Real Estate",
            "subcategory":"Real Estate Operator",
            "type":"Services"
        }
    ],
    "sg:phone":"+1 801 377 1511",
    "sg:postcode":"84604",
    "sg:province":"UT",
    "sg:tags":[
        "apartment"
    ],
    "sg:website":"www.raintreeapt.com",
    "wof:name":"Raintree Apartments",
    "wof:placetype":"venue"
},
  "geometry": {"coordinates":[-111.66157800000001,40.26101],"type":"Point"}
}