{
  "type": "Feature",
  "properties": {
    "iso:country":"US",
    "sg:address":"1296 W 300 N",
    "sg:city":"Clearfield",
    "sg:classifiers":[
        {
            "category":"Restaurant",
            "type":"Food & Drink"
        }
    ],
    "sg:phone":"+1 801 773 3164",
    "sg:postcode":"84015",
    "sg:province":"UT",
    "sg:tags":[
        "eating",
        "pizza"
    ],
    "wof:name":"Rita's Pizzeria",
    "wof:placetype":"venue"
},
  "geometry": {"coordinates":[-112.05093599999999,41.118158],"type":"Point"}
}