{
  "type": "Feature",
  "properties": {
    "iso:country":"US",
    "sg:address":"1500 N 400 W",
    "sg:city":"Clearfield",
    "sg:classifiers":[
        {
            "category":"Organizations",
            "subcategory":"Religious Organization",
            "type":"Services"
        }
    ],
    "sg:phone":"+1 801 299 4050",
    "sg:postcode":"84015",
    "sg:province":"UT",
    "sg:tags":[
        "mormon",
        "church"
    ],
    "wof:name":"The Corporation of The Pres of",
    "wof:placetype":"venue"
},
  "geometry": {"coordinates":[-112.03393199999999,41.135146],"type":"Point"}
}