{
  "type": "Feature",
  "properties": {
    "iso:country":"US",
    "sg:address":"164 S Main St",
    "sg:city":"Richfield",
    "sg:classifiers":[
        {
            "category":"Food & Beverages",
            "subcategory":"Bakery",
            "type":"Retail Goods"
        }
    ],
    "sg:phone":"+1 435 896 1759",
    "sg:postcode":"84701",
    "sg:province":"UT",
    "sg:tags":[
        "baker"
    ],
    "wof:name":"Lynda's Little Pie Shoppe",
    "wof:placetype":"venue"
},
  "geometry": {"coordinates":[-112.08477000000001,38.765765],"type":"Point"}
}