{
  "type": "Feature",
  "properties": {
    "iso:country":"US",
    "sg:address":"8200 S State St",
    "sg:city":"Midvale",
    "sg:classifiers":[
        {
            "category":"Taxi",
            "type":"Transportation"
        }
    ],
    "sg:phone":"+1 801 566 8500",
    "sg:postcode":"84047",
    "sg:province":"UT",
    "sg:tags":[
        "taxicab"
    ],
    "wof:name":"A Valley Cab",
    "wof:placetype":"venue"
},
  "geometry": {"coordinates":[-111.890828,40.603444],"type":"Point"}
}