{
  "type": "Feature",
  "properties": {
    "iso:country":"US",
    "sg:address":"3 W Hillcrest Cir",
    "sg:city":"Salt Lake City",
    "sg:classifiers":[
        {
            "category":"Organizations",
            "subcategory":"Religious Organization",
            "type":"Services"
        }
    ],
    "sg:phone":"+1 801 262 6799",
    "sg:postcode":"84107",
    "sg:province":"UT",
    "wof:name":"Ces Salt Lake West Area Dirs",
    "wof:placetype":"venue"
},
  "geometry": {"coordinates":[-111.89198399999999,40.652729],"type":"Point"}
}