{
  "type": "Feature",
  "properties": {
    "iso:country":"US",
    "sg:address":"267 S Cottonwood Dr",
    "sg:city":"Delta",
    "sg:classifiers":[
        {
            "category":"Wholesale",
            "subcategory":"Jewelry",
            "type":"Manufacturing & Wholesale Goods"
        }
    ],
    "sg:phone":"+1 435 864 4286",
    "sg:postcode":"84624",
    "sg:province":"UT",
    "sg:tags":[
        "stone"
    ],
    "wof:name":"Tina Nielson",
    "wof:placetype":"venue"
},
  "geometry": {"coordinates":[-112.297265,39.533851],"type":"Point"}
}