{
  "type": "Feature",
  "properties": {
    "iso:country":"US",
    "sg:address":"2549 Melbourne St",
    "sg:city":"Salt Lake City",
    "sg:classifiers":[
        {
            "category":"Professional",
            "type":"Services"
        }
    ],
    "sg:phone":"+1 801 486 0836",
    "sg:postcode":"84106",
    "sg:province":"UT",
    "wof:name":"Cole Holland Inc",
    "wof:placetype":"venue"
},
  "geometry": {"coordinates":[-111.838767,40.716082],"type":"Point"}
}