{
  "type": "Feature",
  "properties": {
    "iso:country":"US",
    "sg:address":"1065 N 1620 W",
    "sg:city":"St George",
    "sg:classifiers":[
        {
            "category":"Building & Trades",
            "subcategory":"Construction",
            "type":"Services"
        }
    ],
    "sg:phone":"+1 435 703 0440",
    "sg:postcode":"84770",
    "sg:province":"UT",
    "sg:tags":[
        "nonresidential"
    ],
    "wof:name":"Chemmax Solutions",
    "wof:placetype":"venue"
},
  "geometry": {"coordinates":[-113.618865,37.126556],"type":"Point"}
}