{
  "type": "Feature",
  "properties": {
    "iso:country":"US",
    "sg:address":"11959 Aspen Ridge Rd",
    "sg:city":"Sandy",
    "sg:classifiers":[
        {
            "category":"Professional",
            "type":"Services"
        }
    ],
    "sg:phone":"+1 801 553 2184",
    "sg:postcode":"84094",
    "sg:province":"UT",
    "wof:name":"Cyberquest Inc",
    "wof:placetype":"venue"
},
  "geometry": {"coordinates":[-111.853776,40.535028],"type":"Point"}
}