{
  "type": "Feature",
  "properties": {
    "iso:country":"US",
    "sg:address":"149 Bear River Dr",
    "sg:city":"Evanston",
    "sg:classifiers":[
        {
            "category":"Bars & Pubs",
            "type":"Food & Drink"
        }
    ],
    "sg:phone":"+1 307 789 3050",
    "sg:postcode":"82930",
    "sg:province":"UT",
    "wof:name":"Our Bar",
    "wof:placetype":"venue"
},
  "geometry": {"coordinates":[-110.95999500000001,41.270763],"type":"Point"}
}