{
  "type": "Feature",
  "properties": {
    "iso:country":"US",
    "sg:address":"1655 E 3300 S",
    "sg:city":"Salt Lake City",
    "sg:classifiers":[
        {
            "category":"Education",
            "subcategory":"College",
            "type":"Public Place"
        }
    ],
    "sg:phone":"+1 801 493 8700",
    "sg:postcode":"84106",
    "sg:province":"UT",
    "sg:tags":[
        "academic",
        "school"
    ],
    "wof:name":"Applied Technology College",
    "wof:placetype":"venue"
},
  "geometry": {"coordinates":[-111.843981,40.700024],"type":"Point"}
}