{
  "type": "Feature",
  "properties": {
    "iso:country":"US",
    "sg:address":"12757 Minuteman Dr",
    "sg:city":"Draper",
    "sg:classifiers":[
        {
            "category":"Manufacturing",
            "subcategory":"Building Materials",
            "type":"Manufacturing & Wholesale Goods"
        }
    ],
    "sg:phone":"+1 801 572 6550",
    "sg:postcode":"84020",
    "sg:province":"UT",
    "sg:tags":[
        "cabinet"
    ],
    "sg:website":"www.cottonwoodcabinets.com",
    "wof:name":"Cottonwood Mill & Cabinet",
    "wof:placetype":"venue"
},
  "geometry": {"coordinates":[-111.890618,40.515525],"type":"Point"}
}