{
  "type": "Feature",
  "properties": {
    "iso:country":"US",
    "sg:address":"8825 Renegade Rd",
    "sg:city":"Sandy",
    "sg:classifiers":[
        {
            "category":"Professional",
            "subcategory":"Art Services",
            "type":"Services"
        }
    ],
    "sg:phone":"+1 801 942 5599",
    "sg:postcode":"84093",
    "sg:province":"UT",
    "sg:tags":[
        "commercial",
        "design"
    ],
    "wof:name":"Designs By Julie",
    "wof:placetype":"venue"
},
  "geometry": {"coordinates":[-111.824997,40.590928],"type":"Point"}
}