{
  "type": "Feature",
  "properties": {
    "iso:country":"US",
    "sg:address":"544 S 100 W",
    "sg:city":"St George",
    "sg:classifiers":[
        {
            "category":"Health Services",
            "subcategory":"Health Practitioner",
            "type":"Services"
        }
    ],
    "sg:phone":"+1 435 628 2248",
    "sg:postcode":"84770",
    "sg:province":"UT",
    "wof:name":"Healing Potentials Unlimited",
    "wof:placetype":"venue"
},
  "geometry": {"coordinates":[-113.585567,37.098938],"type":"Point"}
}