{
  "type": "Feature",
  "properties": {
    "iso:country":"US",
    "sg:address":"959 W 3925 N",
    "sg:city":"Ogden",
    "sg:classifiers":[
        {
            "category":"Mining & Drilling",
            "type":"Manufacturing & Wholesale Goods"
        }
    ],
    "sg:phone":"+1 801 726 9700",
    "sg:postcode":"84414",
    "sg:province":"UT",
    "sg:tags":[
        "propane",
        "sales"
    ],
    "wof:name":"Hone Propane Inc",
    "wof:placetype":"venue"
},
  "geometry": {"coordinates":[-111.99713199999999,41.328782],"type":"Point"}
}