{
  "type": "Feature",
  "properties": {
    "iso:country":"US",
    "sg:address":"2942 W 12825 S",
    "sg:city":"Riverton",
    "sg:classifiers":[
        {
            "category":"Building & Trades",
            "subcategory":"Construction",
            "type":"Services"
        }
    ],
    "sg:phone":"+1 801 253 7273",
    "sg:postcode":"84065",
    "sg:province":"UT",
    "sg:tags":[
        "excavating",
        "contractor"
    ],
    "wof:name":"South Valley Backflow Testing",
    "wof:placetype":"venue"
},
  "geometry": {"coordinates":[-111.961151,40.518278],"type":"Point"}
}