{
  "type": "Feature",
  "properties": {
    "iso:country":"US",
    "sg:address":"3415 S 2700 E",
    "sg:city":"Salt Lake City",
    "sg:classifiers":[
        {
            "category":"Building & Trades",
            "subcategory":"Construction",
            "type":"Services"
        }
    ],
    "sg:phone":"+1 801 466 8535",
    "sg:postcode":"84109",
    "sg:province":"UT",
    "sg:tags":[
        "house",
        "nonresidential"
    ],
    "wof:name":"Rigby Remodel Inc",
    "wof:placetype":"venue"
},
  "geometry": {"coordinates":[-111.814876,40.696837],"type":"Point"}
}