{
  "type": "Feature",
  "properties": {
    "iso:country":"US",
    "sg:address":"3730 W 4700 S",
    "sg:city":"Salt Lake City",
    "sg:classifiers":[
        {
            "category":"Health Services",
            "subcategory":"Optometrist",
            "type":"Services"
        }
    ],
    "sg:phone":"+1 801 963 7453",
    "sg:postcode":"84118",
    "sg:province":"UT",
    "wof:name":"Moran Eye Center",
    "wof:placetype":"venue"
},
  "geometry": {"coordinates":[-111.981358,40.667629],"type":"Point"}
}