{
  "type": "Feature",
  "properties": {
    "iso:country":"US",
    "sg:address":"11 W Forest St",
    "sg:city":"Brigham City",
    "sg:classifiers":[
        {
            "category":"Insurance",
            "subcategory":"Title Insurance",
            "type":"Services"
        }
    ],
    "sg:phone":"+1 435 723 5207",
    "sg:postcode":"84302",
    "sg:province":"UT",
    "wof:name":"First American Title Ins Co",
    "wof:placetype":"venue"
},
  "geometry": {"coordinates":[-112.015857,41.510329],"type":"Point"}
}