{
  "type": "Feature",
  "properties": {
    "iso:country":"US",
    "sg:address":"4901 S State St",
    "sg:city":"Murray",
    "sg:classifiers":[
        {
            "category":"Banks & Credit Unions",
            "subcategory":"Bank",
            "type":"Services"
        }
    ],
    "sg:phone":"+1 801 266 0811",
    "sg:postcode":"84107",
    "sg:province":"UT",
    "sg:tags":[
        "depository",
        "banking",
        "loan",
        "mortgage"
    ],
    "wof:name":"Check Cash Advance",
    "wof:placetype":"venue"
},
  "geometry": {"coordinates":[-111.888227,40.665486],"type":"Point"}
}