{
  "type": "Feature",
  "properties": {
    "iso:country":"US",
    "sg:address":"4552 Midland Dr",
    "sg:city":"Roy",
    "sg:classifiers":[
        {
            "category":"Professional",
            "type":"Services"
        }
    ],
    "sg:phone":"+1 801 731 6265",
    "sg:postcode":"84067",
    "sg:province":"UT",
    "wof:name":"J & S Wallace Family Trus",
    "wof:placetype":"venue"
},
  "geometry": {"coordinates":[-112.05793199999999,41.182533],"type":"Point"}
}