{
  "type": "Feature",
  "properties": {
    "iso:country":"US",
    "sg:address":"150 E Center St",
    "sg:city":"Moab",
    "sg:classifiers":[
        {
            "category":"Education",
            "subcategory":"Special Training",
            "type":"Public Place"
        }
    ],
    "sg:phone":"+1 435 259 6948",
    "sg:postcode":"84532",
    "sg:province":"UT",
    "sg:tags":[
        "educational"
    ],
    "sg:website":"www.glogerm.com",
    "wof:name":"Glo Germ",
    "wof:placetype":"venue"
},
  "geometry": {"coordinates":[-109.547828,38.573196],"type":"Point"}
}