{
  "type": "Feature",
  "properties": {
    "iso:country":"US",
    "sg:address":"787 Walden Hills Dr",
    "sg:city":"Murray",
    "sg:classifiers":[
        {
            "category":"Building & Trades",
            "subcategory":"Construction",
            "type":"Services"
        }
    ],
    "sg:phone":"+1 801 261 2035",
    "sg:postcode":"84123",
    "sg:province":"UT",
    "sg:tags":[
        "house",
        "nonresidential",
        "general",
        "contractor"
    ],
    "wof:name":"Raintree Builders Inc",
    "wof:placetype":"venue"
},
  "geometry": {"coordinates":[-111.913157,40.650073],"type":"Point"}
}