{
  "type": "Feature",
  "properties": {
    "iso:country":"US",
    "sg:address":"3946 S 6165 W",
    "sg:city":"Salt Lake City",
    "sg:classifiers":[
        {
            "category":"Manufacturing",
            "subcategory":"Retail Goods",
            "type":"Manufacturing & Wholesale Goods"
        }
    ],
    "sg:phone":"+1 801 982 0550",
    "sg:postcode":"84128",
    "sg:province":"UT",
    "sg:tags":[
        "product",
        "mfg"
    ],
    "wof:name":"Mhm Customs & Mfg",
    "wof:placetype":"venue"
},
  "geometry": {"coordinates":[-112.03839600000001,40.68565],"type":"Point"}
}