{
  "type": "Feature",
  "properties": {
    "iso:country":"US",
    "sg:address":"259 E 60 N",
    "sg:city":"Lindon",
    "sg:classifiers":[
        {
            "category":"Building & Trades",
            "subcategory":"Construction",
            "type":"Services"
        }
    ],
    "sg:phone":"+1 801 785 9970",
    "sg:postcode":"84042",
    "sg:province":"UT",
    "sg:tags":[
        "concrete",
        "contractor"
    ],
    "wof:name":"Allman Concrete Construction",
    "wof:placetype":"venue"
},
  "geometry": {"coordinates":[-111.70767499999999,40.339076],"type":"Point"}
}