{
  "type": "Feature",
  "properties": {
    "iso:country":"US",
    "sg:address":"1075 S Hwy 191",
    "sg:city":"Moab",
    "sg:classifiers":[
        {
            "category":"Travel",
            "subcategory":"Hotels & Motels",
            "type":"Entertainment"
        }
    ],
    "sg:phone":"+1 435 259 8352",
    "sg:postcode":"84532",
    "sg:province":"UT",
    "wof:name":"J R's Desert Inn-Self Storage",
    "wof:placetype":"venue"
},
  "geometry": {"coordinates":[-109.54443499999999,38.558518],"type":"Point"}
}