{
  "type": "Feature",
  "properties": {
    "iso:country":"US",
    "sg:address":"50 W 200 S",
    "sg:city":"Springville",
    "sg:classifiers":[
        {
            "category":"Health Services",
            "subcategory":"Medical Lab",
            "type":"Services"
        }
    ],
    "sg:phone":"+1 801 362 0764",
    "sg:postcode":"84663",
    "sg:province":"UT",
    "sg:tags":[
        "laboratory"
    ],
    "wof:name":"Love Orthodontic Lab",
    "wof:placetype":"venue"
},
  "geometry": {"coordinates":[-111.611755,40.163934],"type":"Point"}
}