{
  "type": "Feature",
  "properties": {
    "iso:country":"US",
    "sg:address":"237 S Geneva Rd",
    "sg:city":"Orem",
    "sg:classifiers":[
        {
            "category":"Shopping",
            "subcategory":"Clothing, Apparel, & Fashions",
            "type":"Retail Goods"
        }
    ],
    "sg:phone":"+1 801 426 4957",
    "sg:postcode":"84058",
    "sg:province":"UT",
    "sg:tags":[
        "leather"
    ],
    "sg:website":"www.rusticoleather.com",
    "wof:name":"Rustico",
    "wof:placetype":"venue"
},
  "geometry": {"coordinates":[-111.733726,40.296181],"type":"Point"}
}