{
  "type": "Feature",
  "properties": {
    "iso:country":"US",
    "sg:address":"1750 W 1500 S",
    "sg:city":"Salt Lake City",
    "sg:classifiers":[
        {
            "category":"Organizations",
            "subcategory":"Religious Organization",
            "type":"Services"
        }
    ],
    "sg:phone":"+1 801 468 5929",
    "sg:postcode":"84104",
    "sg:province":"UT",
    "sg:tags":[
        "church"
    ],
    "wof:name":"Church Of Jesus Christ Of Lds",
    "wof:placetype":"venue"
},
  "geometry": {"coordinates":[-111.94176899999999,40.737713],"type":"Point"}
}