{
  "type": "Feature",
  "properties": {
    "iso:country":"US",
    "sg:address":"8928 Flatiron Dr",
    "sg:city":"Sandy",
    "sg:classifiers":[
        {
            "category":"Professional",
            "type":"Services"
        }
    ],
    "sg:phone":"+1 801 886 9152",
    "sg:postcode":"84093",
    "sg:province":"UT",
    "sg:tags":[
        "establishment"
    ],
    "wof:name":"IFS",
    "wof:placetype":"venue"
},
  "geometry": {"coordinates":[-111.827842,40.58902],"type":"Point"}
}