{
  "type": "Feature",
  "properties": {
    "iso:country":"US",
    "sg:address":"517 W 1000 N",
    "sg:city":"Orem",
    "sg:classifiers":[
        {
            "category":"Personal",
            "type":"Services"
        }
    ],
    "sg:phone":"+1 801 225 8211",
    "sg:postcode":"84057",
    "sg:province":"UT",
    "wof:name":"J Mower Massage",
    "wof:placetype":"venue"
},
  "geometry": {"coordinates":[-111.708872,40.31546],"type":"Point"}
}