{
  "type": "Feature",
  "properties": {
    "iso:country":"US",
    "sg:address":"979 Dammeron Valley Dr W",
    "sg:city":"Dammeron Valley",
    "sg:classifiers":[
        {
            "category":"Building & Trades",
            "subcategory":"Construction",
            "type":"Services"
        }
    ],
    "sg:phone":"+1 435 574 3762",
    "sg:postcode":"84783",
    "sg:province":"UT",
    "sg:tags":[
        "house"
    ],
    "wof:name":"Bradley Construction",
    "wof:placetype":"venue"
},
  "geometry": {"coordinates":[-113.672686,37.30314],"type":"Point"}
}