{
  "type": "Feature",
  "properties": {
    "iso:country":"US",
    "sg:address":"558 S Main St",
    "sg:city":"Gunnison",
    "sg:classifiers":[
        {
            "category":"Insurance",
            "subcategory":"Insurance Agent",
            "type":"Services"
        }
    ],
    "sg:phone":"+1 435 528 7253",
    "sg:postcode":"84634",
    "sg:province":"UT",
    "wof:name":"Donaldson Insurance",
    "wof:placetype":"venue"
},
  "geometry": {"coordinates":[-111.81889099999999,39.143505],"type":"Point"}
}