{
  "type": "Feature",
  "properties": {
    "iso:country":"US",
    "sg:address":"4924 Boulder Glen Cir",
    "sg:city":"West Jordan",
    "sg:classifiers":[
        {
            "category":"Utilities",
            "subcategory":"Telephone",
            "type":"Services"
        }
    ],
    "sg:phone":"+1 801 280 0667",
    "sg:postcode":"84088",
    "sg:province":"UT",
    "sg:tags":[
        "communications"
    ],
    "wof:name":"Highland Brands LLC",
    "wof:placetype":"venue"
},
  "geometry": {"coordinates":[-112.00870500000001,40.590167],"type":"Point"}
}