{
  "type": "Feature",
  "properties": {
    "iso:country":"US",
    "sg:address":"5766 Sierra Grande Cir",
    "sg:city":"Salt Lake City",
    "sg:classifiers":[
        {
            "category":"Communications",
            "type":"Services"
        }
    ],
    "sg:phone":"+1 801 966 7482",
    "sg:postcode":"84118",
    "sg:province":"UT",
    "sg:tags":[
        "communication"
    ],
    "wof:name":"Media Interface",
    "wof:placetype":"venue"
},
  "geometry": {"coordinates":[-111.964023,40.646251],"type":"Point"}
}