{
  "type": "Feature",
  "properties": {
    "iso:country":"US",
    "sg:address":"8686 S 1300 E",
    "sg:city":"Sandy",
    "sg:classifiers":[
        {
            "category":"Professional",
            "subcategory":"Management & Consulting",
            "type":"Services"
        }
    ],
    "sg:phone":"+1 801 566 6500",
    "sg:postcode":"84094",
    "sg:province":"UT",
    "sg:tags":[
        "consultant",
        "educational"
    ],
    "sg:website":"www.teachstream.com",
    "wof:name":"Lipton Professional Devel",
    "wof:placetype":"venue"
},
  "geometry": {"coordinates":[-111.853263,40.592817],"type":"Point"}
}