{
  "type": "Feature",
  "properties": {
    "iso:country":"US",
    "sg:address":"1685 Fort Union Blvd",
    "sg:city":"Salt Lake City",
    "sg:classifiers":[
        {
            "category":"Real Estate",
            "subcategory":"Real Estate Operator",
            "type":"Services"
        }
    ],
    "sg:phone":"+1 801 942 0775",
    "sg:postcode":"84121",
    "sg:province":"UT",
    "sg:tags":[
        "apartment"
    ],
    "wof:name":"Boulder Hollow Apartments",
    "wof:placetype":"venue"
},
  "geometry": {"coordinates":[-111.844489,40.625273],"type":"Point"}
}