{
  "type": "Feature",
  "properties": {
    "iso:country":"US",
    "sg:address":"602 E 500 S",
    "sg:city":"Provo",
    "sg:classifiers":[
        {
            "category":"Restaurant",
            "type":"Food & Drink"
        }
    ],
    "sg:phone":"+1 801 533 2700",
    "sg:postcode":"84606",
    "sg:province":"UT",
    "wof:name":"Grand Buffet",
    "wof:placetype":"venue"
},
  "geometry": {"coordinates":[-111.64637,40.226919],"type":"Point"}
}