{
  "type": "Feature",
  "properties": {
    "iso:country":"US",
    "sg:address":"3431 S Hwy 89",
    "sg:city":"Brigham City",
    "sg:classifiers":[
        {
            "category":"Food & Beverages",
            "subcategory":"Fruits & Vegetables",
            "type":"Retail Goods"
        }
    ],
    "sg:phone":"+1 435 734 1700",
    "sg:postcode":"84302",
    "sg:province":"UT",
    "sg:tags":[
        "produce"
    ],
    "wof:name":"Tagges Famous Fruit",
    "wof:placetype":"venue"
},
  "geometry": {"coordinates":[-112.03768700000001,41.447923],"type":"Point"}
}