{
  "type": "Feature",
  "properties": {
    "iso:country":"US",
    "sg:address":"105 W Main St",
    "sg:city":"Tremonton",
    "sg:classifiers":[
        {
            "category":"Organizations",
            "subcategory":"Religious Organization",
            "type":"Services"
        }
    ],
    "sg:phone":"+1 435 257 8366",
    "sg:postcode":"84337",
    "sg:province":"UT",
    "sg:tags":[
        "church"
    ],
    "wof:name":"Grace Bible Church",
    "wof:placetype":"venue"
},
  "geometry": {"coordinates":[-112.16758400000001,41.711625],"type":"Point"}
}