{
  "type": "Feature",
  "properties": {
    "iso:country":"US",
    "sg:address":"4208 Nike Dr",
    "sg:city":"West Jordan",
    "sg:classifiers":[
        {
            "category":"Building & Trades",
            "subcategory":"Plumbing",
            "type":"Services"
        }
    ],
    "sg:phone":"+1 801 972 0905",
    "sg:postcode":"84088",
    "sg:province":"UT",
    "sg:tags":[
        "sheet",
        "work",
        "metal",
        "contractor"
    ],
    "wof:name":"Titan Sheet Metal",
    "wof:placetype":"venue"
},
  "geometry": {"coordinates":[-111.993527,40.599374],"type":"Point"}
}