{
  "type": "Feature",
  "properties": {
    "iso:country":"US",
    "sg:address":"169 E Mutton Hollow Rd",
    "sg:city":"Kaysville",
    "sg:classifiers":[
        {
            "category":"Banks & Credit Unions",
            "subcategory":"Financial Services",
            "type":"Services"
        }
    ],
    "sg:phone":"+1 801 546 1714",
    "sg:postcode":"84037",
    "sg:province":"UT",
    "sg:tags":[
        "investor"
    ],
    "wof:name":"Tcb Investments LLP",
    "wof:placetype":"venue"
},
  "geometry": {"coordinates":[-111.93650100000001,41.054057],"type":"Point"}
}