{
  "type": "Feature",
  "properties": {
    "iso:country":"US",
    "sg:address":"231 Cottage Ave",
    "sg:city":"Sandy",
    "sg:phone":"+1 801 566 3199",
    "sg:postcode":"84070",
    "sg:province":"UT",
    "sg:tags":[
        "use",
        "for",
        "mobility",
        "medical",
        "equipment",
        "vehicle",
        "home"
    ],
    "wof:name":"Mobility Solutions Inc",
    "wof:placetype":"venue"
},
  "geometry": {"coordinates":[-111.898509,40.592262],"type":"Point"}
}