{
  "type": "Feature",
  "properties": {
    "iso:country":"US",
    "sg:address":"45 S 300 E",
    "sg:city":"Kamas",
    "sg:classifiers":[
        {
            "category":"Education",
            "subcategory":"School",
            "type":"Public Place"
        }
    ],
    "sg:phone":"+1 435 783 4313",
    "sg:postcode":"84036",
    "sg:province":"UT",
    "wof:name":"South Summit High School",
    "wof:placetype":"venue"
},
  "geometry": {"coordinates":[-111.27424600000001,40.642418],"type":"Point"}
}