{
  "type": "Feature",
  "properties": {
    "iso:country":"US",
    "sg:address":"307 W 200 S",
    "sg:city":"Salt Lake City",
    "sg:classifiers":[
        {
            "category":"Real Estate",
            "subcategory":"Developer",
            "type":"Services"
        }
    ],
    "sg:phone":"+1 801 366 9001",
    "sg:postcode":"84101",
    "sg:province":"UT",
    "sg:tags":[
        "a",
        "as",
        "land"
    ],
    "wof:name":"Prince Development LLC",
    "wof:placetype":"venue"
},
  "geometry": {"coordinates":[-111.902399,40.764921],"type":"Point"}
}