{
  "type": "Feature",
  "properties": {
    "iso:country":"US",
    "sg:address":"5221 Commerce Dr",
    "sg:city":"Murray",
    "sg:classifiers":[
        {
            "category":"Home & Garden",
            "subcategory":"Carpets & Floor Coverings",
            "type":"Retail Goods"
        },
        {
            "category":"Building & Trades",
            "subcategory":"Construction",
            "type":"Services"
        }
    ],
    "sg:phone":"+1 801 293 9130",
    "sg:postcode":"84107",
    "sg:province":"UT",
    "sg:tags":[
        "dealer",
        "rug"
    ],
    "wof:name":"Workman Floor Covering LLC",
    "wof:placetype":"venue"
},
  "geometry": {"coordinates":[-111.89855,40.660309],"type":"Point"}
}