{
  "type": "Feature",
  "properties": {
    "iso:country":"US",
    "sg:address":"46 N 300 W",
    "sg:city":"Lehi",
    "sg:classifiers":[
        {
            "category":"Professional",
            "subcategory":"Management & Consulting",
            "type":"Services"
        }
    ],
    "sg:phone":"+1 801 768 0111",
    "sg:postcode":"84043",
    "sg:province":"UT",
    "sg:tags":[
        "retail",
        "direct",
        "sales"
    ],
    "wof:name":"Melanie A Boren",
    "wof:placetype":"venue"
},
  "geometry": {"coordinates":[-111.853712,40.388404],"type":"Point"}
}