{
  "type": "Feature",
  "properties": {
    "iso:country":"US",
    "sg:address":"157 N 400 West St",
    "sg:city":"Orem",
    "sg:classifiers":[
        {
            "category":"Health Services",
            "subcategory":"Podiatrist",
            "type":"Services"
        }
    ],
    "sg:phone":"+1 801 765 1718",
    "sg:postcode":"84057",
    "sg:province":"UT",
    "wof:name":"Scott Mc Kell DPM",
    "wof:placetype":"venue"
},
  "geometry": {"coordinates":[-111.699628,40.304408],"type":"Point"}
}