{
  "type": "Feature",
  "properties": {
    "iso:country":"US",
    "sg:address":"136 S 100 E",
    "sg:city":"Brigham City",
    "sg:classifiers":[
        {
            "category":"Shopping",
            "subcategory":"Clothing, Apparel, & Fashions",
            "type":"Retail Goods"
        }
    ],
    "sg:phone":"+1 435 723 2337",
    "sg:postcode":"84302",
    "sg:province":"UT",
    "wof:name":"Twigs & Sprigs Boutique",
    "wof:placetype":"venue"
},
  "geometry": {"coordinates":[-112.01433900000001,41.50681],"type":"Point"}
}