{
  "type": "Feature",
  "properties": {
    "iso:country":"US",
    "sg:address":"998 N Main St",
    "sg:city":"Spanish Fork",
    "sg:classifiers":[
        {
            "category":"Restaurant",
            "type":"Food & Drink"
        }
    ],
    "sg:menulink":"http://www.allmenus.com/ut/spanish-fork-payson/35649-the-pizza-factory/menu/",
    "sg:phone":"+1 801 794 2211",
    "sg:postcode":"84660",
    "sg:province":"UT",
    "sg:tags":[
        "american",
        "pizza"
    ],
    "wof:name":"The Pizza Factory",
    "wof:placetype":"venue"
},
  "geometry": {"coordinates":[-111.65201399999999,40.122895],"type":"Point"}
}