{
  "type": "Feature",
  "properties": {
    "iso:country":"US",
    "sg:address":"116 S 850 E",
    "sg:city":"Lehi",
    "sg:classifiers":[
        {
            "category":"Retail",
            "subcategory":"Auto Repair",
            "type":"Services"
        }
    ],
    "sg:phone":"+1 801 766 1914",
    "sg:postcode":"84043",
    "sg:province":"UT",
    "sg:tags":[
        "automotive",
        "general"
    ],
    "sg:website":"www.jiffylube.com",
    "wof:name":"Jiffy Lube",
    "wof:placetype":"venue"
},
  "geometry": {"coordinates":[-111.83573199999999,40.388234],"type":"Point"}
}