{
  "type": "Feature",
  "properties": {
    "iso:country":"US",
    "sg:address":"2308 Ogden City Mall",
    "sg:city":"Ogden",
    "sg:classifiers":[
        {
            "category":"Shopping",
            "subcategory":"Gifts & Souvenirs",
            "type":"Retail Goods"
        }
    ],
    "sg:phone":"+1 801 393 4531",
    "sg:postcode":"84401",
    "sg:province":"UT",
    "sg:tags":[
        "shop",
        "card"
    ],
    "wof:name":"Card America",
    "wof:placetype":"venue"
},
  "geometry": {"coordinates":[-111.971778,41.222956],"type":"Point"}
}