{
  "type": "Feature",
  "properties": {
    "iso:country":"US",
    "sg:address":"1881 W 820 North St",
    "sg:city":"Provo",
    "sg:classifiers":[
        {
            "category":"Professional",
            "subcategory":"Computer Services",
            "type":"Services"
        }
    ],
    "sg:phone":"+1 801 377 4707",
    "sg:postcode":"84601",
    "sg:province":"UT",
    "sg:tags":[
        "website",
        "design",
        "software"
    ],
    "wof:name":"Inshift Technologies LLC",
    "wof:placetype":"venue"
},
  "geometry": {"coordinates":[-111.689694,40.245125],"type":"Point"}
}