{
  "type": "Feature",
  "properties": {
    "iso:country":"US",
    "sg:address":"400 W 500 S",
    "sg:city":"Bountiful",
    "sg:classifiers":[
        {
            "category":"Autos & Motor Vehicles",
            "subcategory":"Auto Supplies",
            "type":"Retail Goods"
        }
    ],
    "sg:phone":"+1 801 292 2111",
    "sg:postcode":"84010",
    "sg:province":"UT",
    "sg:tags":[
        "tire"
    ],
    "sg:website":"www.bigotires.com",
    "wof:name":"Big O Tire Stores",
    "wof:placetype":"venue"
},
  "geometry": {"coordinates":[-111.889999,40.884399],"type":"Point"}
}