{
  "type": "Feature",
  "properties": {
    "iso:country":"US",
    "sg:address":"575 E University Pkwy",
    "sg:city":"Orem",
    "sg:classifiers":[
        {
            "category":"Shopping",
            "subcategory":"Department Store",
            "type":"Retail Goods"
        }
    ],
    "sg:phone":"+1 801 426 6950",
    "sg:postcode":"84058",
    "sg:province":"UT",
    "sg:website":"www.eddiebauer.com",
    "wof:name":"Eddie Bauer",
    "wof:placetype":"venue"
},
  "geometry": {"coordinates":[-111.679216,40.273273],"type":"Point"}
}