{
  "type": "Feature",
  "properties": {
    "iso:country":"US",
    "sg:address":"12313 S 900 E",
    "sg:city":"Draper",
    "sg:classifiers":[
        {
            "category":"Insurance",
            "subcategory":"Insurance Agent",
            "type":"Services"
        }
    ],
    "sg:phone":"+1 801 571 8711",
    "sg:postcode":"84020",
    "sg:province":"UT",
    "wof:name":"State Farm Insurance",
    "wof:placetype":"venue"
},
  "geometry": {"coordinates":[-111.866209,40.525299],"type":"Point"}
}