{
  "type": "Feature",
  "properties": {
    "iso:country":"US",
    "sg:address":"862 E State Rd",
    "sg:city":"American Fork",
    "sg:classifiers":[
        {
            "category":"Autos & Motor Vehicles",
            "subcategory":"Fuel & Gas Station",
            "type":"Retail Goods"
        }
    ],
    "sg:phone":"+1 801 492 0833",
    "sg:postcode":"84003",
    "sg:province":"UT",
    "sg:tags":[
        "station",
        "gasoline"
    ],
    "wof:name":"Chevron",
    "wof:placetype":"venue"
},
  "geometry": {"coordinates":[-111.76934199999999,40.370211],"type":"Point"}
}