{
  "type": "Feature",
  "properties": {
    "iso:country":"US",
    "sg:address":"3260 W 500 S",
    "sg:city":"Salt Lake City",
    "sg:classifiers":[
        {
            "category":"Utilities",
            "subcategory":"Refuse",
            "type":"Services"
        },
        {
            "category":"Wholesale",
            "subcategory":"Scrap",
            "type":"Manufacturing & Wholesale Goods"
        }
    ],
    "sg:phone":"+1 801 954 8888",
    "sg:postcode":"84104",
    "sg:province":"UT",
    "sg:tags":[
        "center",
        "producer",
        "recycling",
        "metal",
        "system",
        "nonferrous",
        "secondary"
    ],
    "sg:website":"www.mtlm.com",
    "wof:name":"Metal Management West Inc",
    "wof:placetype":"venue"
},
  "geometry": {"coordinates":[-111.96879300000001,40.758482],"type":"Point"}
}