{
  "type": "Feature",
  "properties": {
    "iso:country":"US",
    "sg:address":"192 N Grant Ave",
    "sg:city":"American Fork",
    "sg:classifiers":[
        {
            "category":"Freight",
            "type":"Transportation"
        }
    ],
    "sg:phone":"+1 801 756 6058",
    "sg:postcode":"84003",
    "sg:province":"UT",
    "sg:tags":[
        "commercial",
        "storage"
    ],
    "wof:name":"Jedco Storage Units",
    "wof:placetype":"venue"
},
  "geometry": {"coordinates":[-111.79416399999999,40.380657],"type":"Point"}
}