{
  "type": "Feature",
  "properties": {
    "iso:country":"US",
    "sg:address":"2684 Terah Maria Dr",
    "sg:city":"Salt Lake City",
    "sg:classifiers":[
        {
            "category":"Health Services",
            "subcategory":"Medical Lab",
            "type":"Services"
        }
    ],
    "sg:phone":"+1 801 957 1986",
    "sg:postcode":"84118",
    "sg:province":"UT",
    "sg:tags":[
        "laboratory"
    ],
    "wof:name":"Crazy Chrome Dental Lab",
    "wof:placetype":"venue"
},
  "geometry": {"coordinates":[-111.957741,40.661909],"type":"Point"}
}