{
  "type": "Feature",
  "properties": {
    "iso:country":"US",
    "sg:address":"677 N 3050 E",
    "sg:city":"St George",
    "sg:classifiers":[
        {
            "category":"Wholesale",
            "subcategory":"Chemicals & Plastics",
            "type":"Manufacturing & Wholesale Goods"
        }
    ],
    "sg:phone":"+1 435 627 1033",
    "sg:postcode":"84790",
    "sg:province":"UT",
    "sg:tags":[
        "equipment",
        "industrial"
    ],
    "wof:name":"Djb Gas Services Inc",
    "wof:placetype":"venue"
},
  "geometry": {"coordinates":[-113.520805,37.120845],"type":"Point"}
}