{
  "type": "Feature",
  "properties": {
    "iso:country":"US",
    "sg:address":"38 W 100 N",
    "sg:city":"Vernal",
    "sg:classifiers":[
        {
            "category":"Real Estate",
            "subcategory":"Surveying",
            "type":"Services"
        }
    ],
    "sg:phone":"+1 435 789 1365",
    "sg:postcode":"84078",
    "sg:province":"UT",
    "sg:tags":[
        "surveyor"
    ],
    "wof:name":"Timberline Land Surveying",
    "wof:placetype":"venue"
},
  "geometry": {"coordinates":[-109.529816,40.457215],"type":"Point"}
}