{
  "type": "Feature",
  "properties": {
    "iso:country":"US",
    "sg:address":"9690 S 1300 E",
    "sg:city":"Sandy",
    "sg:classifiers":[
        {
            "category":"Health Services",
            "subcategory":"Health Practitioner",
            "type":"Services"
        }
    ],
    "sg:phone":"+1 801 501 4310",
    "sg:postcode":"84094",
    "sg:province":"UT",
    "wof:name":"Inter Mountain Health Care IHC",
    "wof:placetype":"venue"
},
  "geometry": {"coordinates":[-111.85319699999999,40.577717],"type":"Point"}
}