{
  "type": "Feature",
  "properties": {
    "iso:country":"US",
    "sg:address":"7090 Union Park Center",
    "sg:city":"Midvale",
    "sg:classifiers":[
        {
            "category":"Professional",
            "type":"Services"
        }
    ],
    "sg:phone":"+1 801 304 5800",
    "sg:postcode":"84047",
    "sg:province":"UT",
    "wof:name":"Team Red Line Racing LLC",
    "wof:placetype":"venue"
},
  "geometry": {"coordinates":[-111.859075,40.62375],"type":"Point"}
}