{
  "type": "Feature",
  "properties": {
    "iso:country":"US",
    "sg:address":"2990 E Riverside Dr",
    "sg:city":"St George",
    "sg:classifiers":[
        {
            "category":"Manufacturing",
            "subcategory":"Printing",
            "type":"Manufacturing & Wholesale Goods"
        }
    ],
    "sg:phone":"+1 435 634 8090",
    "sg:postcode":"84790",
    "sg:province":"UT",
    "sg:tags":[
        "newspaper"
    ],
    "wof:name":"Utah Prime Times Inc",
    "wof:placetype":"venue"
},
  "geometry": {"coordinates":[-113.537678,37.100001],"type":"Point"}
}