{
  "type": "Feature",
  "properties": {
    "iso:country":"US",
    "sg:address":"865 E 100 S",
    "sg:city":"St George",
    "sg:classifiers":[
        {
            "category":"Organizations",
            "subcategory":"Religious Organization",
            "type":"Services"
        }
    ],
    "sg:phone":"+1 435 673 6486",
    "sg:postcode":"84770",
    "sg:province":"UT",
    "sg:tags":[
        "mormon",
        "church"
    ],
    "wof:name":"St George College Fifth Ward",
    "wof:placetype":"venue"
},
  "geometry": {"coordinates":[-113.56543499999999,37.106504],"type":"Point"}
}