{
  "type": "Feature",
  "properties": {
    "iso:country":"US",
    "sg:address":"1375 Cedar Ridge Rd",
    "sg:city":"Lehi",
    "sg:classifiers":[
        {
            "category":"Real Estate",
            "subcategory":"Real Estate Agent",
            "type":"Services"
        }
    ],
    "sg:phone":"+1 801 768 0609",
    "sg:postcode":"84043",
    "sg:province":"UT",
    "wof:name":"Gray Eagle Land Co LLC",
    "wof:placetype":"venue"
},
  "geometry": {"coordinates":[-111.83228,40.406191],"type":"Point"}
}