{
  "type": "Feature",
  "properties": {
    "iso:country":"US",
    "sg:address":"922 S 800 E",
    "sg:city":"Salt Lake City",
    "sg:classifiers":[
        {
            "category":"Building & Trades",
            "subcategory":"Construction",
            "type":"Services"
        }
    ],
    "sg:phone":"+1 801 364 8290",
    "sg:postcode":"84105",
    "sg:province":"UT",
    "sg:tags":[
        "concrete",
        "contractor"
    ],
    "wof:name":"Archuleta Ivo C Con Contrs",
    "wof:placetype":"venue"
},
  "geometry": {"coordinates":[-111.868268,40.74858],"type":"Point"}
}