{
  "type": "Feature",
  "properties": {
    "iso:country":"US",
    "sg:address":"472 Vintage Dr",
    "sg:city":"Provo",
    "sg:classifiers":[
        {
            "category":"Banks & Credit Unions",
            "subcategory":"Financial Services",
            "type":"Services"
        }
    ],
    "sg:phone":"+1 801 434 8001",
    "sg:postcode":"84604",
    "sg:province":"UT",
    "sg:tags":[
        "investor"
    ],
    "wof:name":"First Priority Investments",
    "wof:placetype":"venue"
},
  "geometry": {"coordinates":[-111.666839,40.294807],"type":"Point"}
}