{
  "type": "Feature",
  "properties": {
    "iso:country":"US",
    "sg:address":"6856 S 700 E",
    "sg:city":"Midvale",
    "sg:classifiers":[
        {
            "category":"Government",
            "subcategory":"Office",
            "type":"Public Place"
        }
    ],
    "sg:phone":"+1 801 565 1267",
    "sg:postcode":"84047",
    "sg:province":"UT",
    "sg:tags":[
        "county",
        "program",
        "health"
    ],
    "wof:name":"Salt Lake County Mental Health",
    "wof:placetype":"venue"
},
  "geometry": {"coordinates":[-111.87213,40.628055],"type":"Point"}
}