{
  "type": "Feature",
  "properties": {
    "iso:country":"US",
    "sg:address":"20 S Main St",
    "sg:city":"Alpine",
    "sg:classifiers":[
        {
            "category":"Health Services",
            "subcategory":"Doctor",
            "type":"Services"
        }
    ],
    "sg:phone":"+1 801 756 3570",
    "sg:postcode":"84004",
    "sg:province":"UT",
    "wof:name":"Grant T Stucki DDS",
    "wof:placetype":"venue"
},
  "geometry": {"coordinates":[-111.777908,40.453028],"type":"Point"}
}