{
  "type": "Feature",
  "properties": {
    "iso:country":"US",
    "sg:address":"595 S 200 E",
    "sg:city":"Hyrum",
    "sg:classifiers":[
        {
            "category":"Organizations",
            "subcategory":"Religious Organization",
            "type":"Services"
        }
    ],
    "sg:phone":"+1 435 245 3543",
    "sg:postcode":"84319",
    "sg:province":"UT",
    "sg:tags":[
        "church"
    ],
    "wof:name":"Church Of Jesus Christ Of Lds",
    "wof:placetype":"venue"
},
  "geometry": {"coordinates":[-111.850133,41.621533],"type":"Point"}
}