{
  "type": "Feature",
  "properties": {
    "iso:country":"US",
    "sg:address":"1235 California Ave",
    "sg:city":"Salt Lake City",
    "sg:classifiers":[
        {
            "category":"Social Services",
            "type":"Services"
        }
    ],
    "sg:phone":"+1 801 972 5708",
    "sg:postcode":"84104",
    "sg:province":"UT",
    "wof:name":"Baptist Concern Center",
    "wof:placetype":"venue"
},
  "geometry": {"coordinates":[-111.926006,40.740371],"type":"Point"}
}