{
  "type": "Feature",
  "properties": {
    "iso:country":"US",
    "sg:address":"275 N 1600 E",
    "sg:city":"Tremonton",
    "sg:classifiers":[
        {
            "category":"Organizations",
            "subcategory":"Non-profit Organization",
            "type":"Services"
        }
    ],
    "sg:phone":"+1 435 257 5975",
    "sg:postcode":"84337",
    "sg:province":"UT",
    "sg:tags":[
        "irrigation",
        "system"
    ],
    "wof:name":"Bear River Canal Co Inc",
    "wof:placetype":"venue"
},
  "geometry": {"coordinates":[-112.142213,41.712416],"type":"Point"}
}