{
  "type": "Feature",
  "properties": {
    "iso:country":"US",
    "sg:address":"7141 Hwy U-111",
    "sg:city":"Magna",
    "sg:classifiers":[
        {
            "category":"Utilities",
            "subcategory":"Refuse",
            "type":"Services"
        }
    ],
    "sg:phone":"+1 801 508 0790",
    "sg:postcode":"84096",
    "sg:province":"UT",
    "sg:tags":[
        "landfill"
    ],
    "wof:name":"Bland Recycling LLC",
    "wof:placetype":"venue"
},
  "geometry": {"coordinates":[-111.850284,39.848111],"type":"Point"}
}