{
  "type": "Feature",
  "properties": {
    "iso:country":"US",
    "sg:address":"3915 Ogden Ave",
    "sg:city":"Ogden",
    "sg:classifiers":[
        {
            "category":"Health Services",
            "subcategory":"Doctor",
            "type":"Services"
        }
    ],
    "sg:phone":"+1 801 621 3383",
    "sg:postcode":"84403",
    "sg:province":"UT",
    "sg:tags":[
        "dentist"
    ],
    "wof:name":"Adams Delos C DDS",
    "wof:placetype":"venue"
},
  "geometry": {"coordinates":[-111.96974,41.190701],"type":"Point"}
}