{
  "type": "Feature",
  "properties": {
    "iso:country":"US",
    "sg:address":"7877 Mountain View Rd",
    "sg:city":"Tooele",
    "sg:classifiers":[
        {
            "category":"Banks & Credit Unions",
            "subcategory":"Investment Brokerage",
            "type":"Services"
        }
    ],
    "sg:phone":"+1 801 352 8778",
    "sg:postcode":"84074",
    "sg:province":"UT",
    "sg:tags":[
        "consultant",
        "planning",
        "financial"
    ],
    "wof:name":"Householder Group",
    "wof:placetype":"venue"
},
  "geometry": {"coordinates":[-112.263175,40.672188],"type":"Point"}
}