{
  "type": "Feature",
  "properties": {
    "iso:country":"US",
    "sg:address":"3087 Windmill Dr",
    "sg:city":"Santa Clara",
    "sg:classifiers":[
        {
            "category":"Building & Trades",
            "subcategory":"Construction",
            "type":"Services"
        }
    ],
    "sg:phone":"+1 435 628 1521",
    "sg:postcode":"84765",
    "sg:province":"UT",
    "sg:tags":[
        "electrical",
        "contractor"
    ],
    "wof:name":"Plasteri Kauffman Barrett",
    "wof:placetype":"venue"
},
  "geometry": {"coordinates":[-113.654918,37.142025],"type":"Point"}
}