{
  "type": "Feature",
  "properties": {
    "iso:country":"US",
    "sg:address":"2497 Fort Union Blvd",
    "sg:city":"Salt Lake City",
    "sg:classifiers":[
        {
            "category":"Professional",
            "subcategory":"Management & Consulting",
            "type":"Services"
        }
    ],
    "sg:phone":"+1 801 942 6300",
    "sg:postcode":"84121",
    "sg:province":"UT",
    "sg:tags":[
        "consultant",
        "business"
    ],
    "sg:website":"www.sellersgroup.net",
    "wof:name":"Sellers Management & Dev Co",
    "wof:placetype":"venue"
},
  "geometry": {"coordinates":[-111.822833,40.624047],"type":"Point"}
}