{
  "type": "Feature",
  "properties": {
    "iso:country":"US",
    "sg:address":"1126 E 11000 S",
    "sg:city":"Sandy",
    "sg:classifiers":[
        {
            "category":"Arena",
            "subcategory":"Sports Club",
            "type":"Entertainment"
        }
    ],
    "sg:phone":"+1 801 571 9422",
    "sg:postcode":"84094",
    "sg:province":"UT",
    "sg:tags":[
        "soccer"
    ],
    "wof:name":"American Youth Soccer Orgnztn",
    "wof:placetype":"venue"
},
  "geometry": {"coordinates":[-111.861315,40.551501],"type":"Point"}
}