{
  "type": "Feature",
  "properties": {
    "iso:country":"US",
    "sg:address":"1200 N 1400 W",
    "sg:city":"St George",
    "sg:classifiers":[
        {
            "category":"Organizations",
            "subcategory":"Religious Organization",
            "type":"Services"
        }
    ],
    "sg:phone":"+1 435 674 9921",
    "sg:postcode":"84770",
    "sg:province":"UT",
    "sg:tags":[
        "mormon",
        "church"
    ],
    "wof:name":"Snow Canyon Ninth Ward",
    "wof:placetype":"venue"
},
  "geometry": {"coordinates":[-113.614576,37.128738],"type":"Point"}
}