{
  "type": "Feature",
  "properties": {
    "iso:country":"US",
    "sg:address":"389 Industrial Rd",
    "sg:city":"St George",
    "sg:classifiers":[
        {
            "category":"Government",
            "subcategory":"Office",
            "type":"Public Place"
        }
    ],
    "sg:phone":"+1 435 634 1354",
    "sg:postcode":"84770",
    "sg:province":"UT",
    "sg:tags":[
        "immigration"
    ],
    "wof:name":"Immigration Cutoms Enforcement",
    "wof:placetype":"venue"
},
  "geometry": {"coordinates":[-113.56067899999999,37.113173],"type":"Point"}
}