{
  "type": "Feature",
  "properties": {
    "iso:country":"US",
    "sg:address":"4110 Highland Dr",
    "sg:city":"Salt Lake City",
    "sg:classifiers":[
        {
            "category":"Insurance",
            "subcategory":"Insurance Agent",
            "type":"Services"
        }
    ],
    "sg:phone":"+1 801 274 6360",
    "sg:postcode":"84124",
    "sg:province":"UT",
    "wof:name":"Barrett Insurance Inc",
    "wof:placetype":"venue"
},
  "geometry": {"coordinates":[-111.843705,40.683046],"type":"Point"}
}