{
  "type": "Feature",
  "properties": {
    "iso:country":"US",
    "sg:address":"275 N Main St",
    "sg:city":"Richfield",
    "sg:classifiers":[
        {
            "category":"Autos & Motor Vehicles",
            "subcategory":"Automobile Sales",
            "type":"Retail Goods"
        }
    ],
    "sg:phone":"+1 435 896 5486",
    "sg:postcode":"84701",
    "sg:province":"UT",
    "sg:tags":[
        "car",
        "dealer"
    ],
    "wof:name":"High Country Auto Ctr",
    "wof:placetype":"venue"
},
  "geometry": {"coordinates":[-112.084777,38.771214],"type":"Point"}
}