{
  "type": "Feature",
  "properties": {
    "iso:country":"US",
    "sg:address":"7043 Cottonwood St",
    "sg:city":"Midvale",
    "sg:classifiers":[
        {
            "category":"Wholesale",
            "subcategory":"Medical Equipment & Supplies",
            "type":"Manufacturing & Wholesale Goods"
        },
        {
            "category":"Health Services",
            "subcategory":"Hospital",
            "type":"Services"
        }
    ],
    "sg:phone":"+1 801 566 1200",
    "sg:postcode":"84047",
    "sg:province":"UT",
    "sg:tags":[
        "instrument",
        "surgical"
    ],
    "sg:website":"http://www.utahmed.com",
    "wof:name":"Utah Medical Products, Inc.",
    "wof:placetype":"venue"
},
  "geometry": {"coordinates":[-111.899664,40.623702],"type":"Point"}
}