{
  "type": "Feature",
  "properties": {
    "iso:country":"US",
    "sg:address":"138 E 2700 S",
    "sg:city":"Salt Lake City",
    "sg:classifiers":[
        {
            "category":"Retail",
            "subcategory":"Auto Repair",
            "type":"Services"
        }
    ],
    "sg:phone":"+1 801 485 5089",
    "sg:postcode":"84115",
    "sg:province":"UT",
    "sg:tags":[
        "repairing",
        "automobile"
    ],
    "wof:name":"Amess-Automotive Machine Equip",
    "wof:placetype":"venue"
},
  "geometry": {"coordinates":[-111.888256,40.712676],"type":"Point"}
}