{
  "type": "Feature",
  "properties": {
    "iso:country":"US",
    "sg:address":"2262 Washington Blvd",
    "sg:city":"Ogden",
    "sg:classifiers":[
        {
            "category":"Personal",
            "subcategory":"Tattoo Parlor",
            "type":"Services"
        }
    ],
    "sg:phone":"+1 801 394 3560",
    "sg:postcode":"84401",
    "sg:province":"UT",
    "sg:tags":[
        "tattooing"
    ],
    "wof:name":"Sacred Art Tattoo",
    "wof:placetype":"venue"
},
  "geometry": {"coordinates":[-111.97028899999999,41.225327],"type":"Point"}
}