{
  "type": "Feature",
  "properties": {
    "iso:country":"US",
    "sg:address":"585 N Main St",
    "sg:city":"Cedar City",
    "sg:classifiers":[
        {
            "category":"Recreation",
            "type":"Entertainment"
        }
    ],
    "sg:phone":"+1 435 586 4497",
    "sg:postcode":"84720",
    "sg:province":"UT",
    "sg:tags":[
        "parks"
    ],
    "wof:name":"Parks & Recreation Dept",
    "wof:placetype":"venue"
},
  "geometry": {"coordinates":[-113.06189999999999,37.68762],"type":"Point"}
}