{
  "type": "Feature",
  "properties": {
    "iso:country":"US",
    "sg:address":"229 N Highland Blvd",
    "sg:city":"Brigham City",
    "sg:classifiers":[
        {
            "category":"Building & Trades",
            "subcategory":"Construction",
            "type":"Services"
        }
    ],
    "sg:phone":"+1 435 723 7596",
    "sg:postcode":"84302",
    "sg:province":"UT",
    "sg:tags":[
        "house"
    ],
    "wof:name":"KAs Construction Inc",
    "wof:placetype":"venue"
},
  "geometry": {"coordinates":[-111.99688999999999,41.51609],"type":"Point"}
}