{
  "type": "Feature",
  "properties": {
    "iso:country":"US",
    "sg:address":"5210 Skeeswood Dr",
    "sg:city":"Salt Lake City",
    "sg:classifiers":[
        {
            "category":"Banks & Credit Unions",
            "subcategory":"Bank",
            "type":"Services"
        }
    ],
    "sg:phone":"+1 801 968 5165",
    "sg:postcode":"84118",
    "sg:province":"UT",
    "sg:tags":[
        "loan",
        "real estate"
    ],
    "wof:name":"P T Enterprises Mortgage",
    "wof:placetype":"venue"
},
  "geometry": {"coordinates":[-111.973395,40.654476],"type":"Point"}
}