{
  "type": "Feature",
  "properties": {
    "iso:country":"US",
    "sg:address":"1115 E Main St",
    "sg:city":"Delta",
    "sg:classifiers":[
        {
            "category":"Retail",
            "subcategory":"Veterinary Services",
            "type":"Services"
        }
    ],
    "sg:phone":"+1 435 864 3921",
    "sg:postcode":"84624",
    "sg:province":"UT",
    "sg:tags":[
        "clinic",
        "veterinarian"
    ],
    "wof:name":"Great Basin Veterinary Service",
    "wof:placetype":"venue"
},
  "geometry": {"coordinates":[-112.553895,39.352625],"type":"Point"}
}