{
  "type": "Feature",
  "properties": {
    "iso:country":"US",
    "sg:address":"1688 N Reservoir Rd",
    "sg:city":"Blanding",
    "sg:classifiers":[
        {
            "category":"Building & Trades",
            "subcategory":"Construction",
            "type":"Services"
        }
    ],
    "sg:phone":"+1 435 678 2523",
    "sg:postcode":"84511",
    "sg:province":"UT",
    "sg:tags":[
        "maker",
        "cabinet"
    ],
    "sg:website":"www.taylorpalmerknives.com",
    "wof:name":"Taylor Made Wooden Heritage",
    "wof:placetype":"venue"
},
  "geometry": {"coordinates":[-109.482693,37.658285],"type":"Point"}
}