{
  "type": "Feature",
  "properties": {
    "iso:country":"US",
    "sg:address":"50 N Main St",
    "sg:city":"Payson",
    "sg:classifiers":[
        {
            "category":"Personal",
            "subcategory":"Beauty Salon",
            "type":"Services"
        }
    ],
    "sg:phone":"+1 801 465 3052",
    "sg:postcode":"84651",
    "sg:province":"UT",
    "wof:name":"Jo Ann's Head Shed",
    "wof:placetype":"venue"
},
  "geometry": {"coordinates":[-111.732202,40.044069],"type":"Point"}
}