{
  "type": "Feature",
  "properties": {
    "iso:country":"US",
    "sg:address":"590 E 300 N",
    "sg:city":"Price",
    "sg:classifiers":[
        {
            "category":"Wholesale",
            "subcategory":"Groceries",
            "type":"Manufacturing & Wholesale Goods"
        }
    ],
    "sg:phone":"+1 435 637 8252",
    "sg:postcode":"84501",
    "sg:province":"UT",
    "sg:tags":[
        "baker"
    ],
    "wof:name":"Castle Valley Distributing",
    "wof:placetype":"venue"
},
  "geometry": {"coordinates":[-110.800228,39.604155],"type":"Point"}
}