{
  "type": "Feature",
  "properties": {
    "iso:country":"US",
    "sg:address":"79 S Fort Ln",
    "sg:city":"Layton",
    "sg:classifiers":[
        {
            "category":"Sports & Exercise",
            "subcategory":"Race Track",
            "type":"Entertainment"
        }
    ],
    "sg:phone":"+1 801 593 0884",
    "sg:postcode":"84041",
    "sg:province":"UT",
    "wof:name":"M P Racing",
    "wof:placetype":"venue"
},
  "geometry": {"coordinates":[-111.95756299999999,41.058602],"type":"Point"}
}