{
  "type": "Feature",
  "properties": {
    "iso:country":"US",
    "sg:address":"2841 Cobblemoor Ln",
    "sg:city":"Sandy",
    "sg:classifiers":[
        {
            "category":"Professional",
            "subcategory":"Lawyer & Legal Services",
            "type":"Services"
        }
    ],
    "sg:phone":"+1 801 942 7749",
    "sg:postcode":"84093",
    "sg:province":"UT",
    "wof:name":"S W H & J H H Ltd",
    "wof:placetype":"venue"
},
  "geometry": {"coordinates":[-111.811148,40.588112],"type":"Point"}
}