{
  "type": "Feature",
  "properties": {
    "iso:country":"US",
    "sg:address":"639 S 100 W",
    "sg:city":"Santaquin",
    "sg:classifiers":[
        {
            "category":"Freight",
            "type":"Transportation"
        }
    ],
    "sg:phone":"+1 801 754 5456",
    "sg:postcode":"84655",
    "sg:province":"UT",
    "sg:tags":[
        "operator",
        "local",
        "trucking"
    ],
    "wof:name":"Jbm Hauling & Maintenance",
    "wof:placetype":"venue"
},
  "geometry": {"coordinates":[-111.786913,39.965611],"type":"Point"}
}