{
  "type": "Feature",
  "properties": {
    "iso:country":"US",
    "sg:address":"38 E 400 S",
    "sg:city":"Bountiful",
    "sg:classifiers":[
        {
            "category":"Education",
            "subcategory":"Dance Studio",
            "type":"Public Place"
        }
    ],
    "sg:phone":"+1 801 487 0565",
    "sg:postcode":"84010",
    "sg:province":"UT",
    "sg:tags":[
        "instruction",
        "dancing"
    ],
    "wof:name":"Children's Ballet Theatre",
    "wof:placetype":"venue"
},
  "geometry": {"coordinates":[-111.879075,40.885126],"type":"Point"}
}