{
  "type": "Feature",
  "properties": {
    "iso:country":"US",
    "sg:address":"14901 Heritagecrest Way",
    "sg:city":"Riverton",
    "sg:classifiers":[
        {
            "category":"Shopping",
            "subcategory":"Bicycles & Sporting Goods",
            "type":"Retail Goods"
        }
    ],
    "sg:phone":"+1 801 523 2452",
    "sg:postcode":"84065",
    "sg:province":"UT",
    "sg:tags":[
        "equipment",
        "playground"
    ],
    "sg:website":"www.sof-fall.com",
    "wof:name":"Sof' Fall Inc",
    "wof:placetype":"venue"
},
  "geometry": {"coordinates":[-111.911451,40.480474],"type":"Point"}
}