{
  "type": "Feature",
  "properties": {
    "iso:country":"US",
    "sg:address":"605 N 300 W",
    "sg:city":"Salt Lake City",
    "sg:classifiers":[
        {
            "category":"Manufacturing",
            "subcategory":"Retail Goods",
            "type":"Manufacturing & Wholesale Goods"
        }
    ],
    "sg:phone":"+1 801 328 0591",
    "sg:postcode":"84103",
    "sg:province":"UT",
    "sg:tags":[
        "body",
        "auto",
        "lead",
        "mfg"
    ],
    "wof:name":"Art By Alex",
    "wof:placetype":"venue"
},
  "geometry": {"coordinates":[-111.899759,40.784204],"type":"Point"}
}