{
  "type": "Feature",
  "properties": {
    "iso:country":"US",
    "sg:address":"95 S 500 E",
    "sg:city":"Roosevelt",
    "sg:classifiers":[
        {
            "category":"Home & Garden",
            "subcategory":"Furniture",
            "type":"Retail Goods"
        }
    ],
    "sg:phone":"+1 435 722 2884",
    "sg:postcode":"84066",
    "sg:province":"UT",
    "sg:tags":[
        "appliance"
    ],
    "wof:name":"Sullivans Inc",
    "wof:placetype":"venue"
},
  "geometry": {"coordinates":[-109.984308,40.2982],"type":"Point"}
}