{
  "type": "Feature",
  "properties": {
    "iso:country":"US",
    "sg:address":"4644 Holladay Blvd",
    "sg:city":"Holladay",
    "sg:classifiers":[
        {
            "category":"Building & Trades",
            "subcategory":"Equipment Rental",
            "type":"Services"
        },
        {
            "category":"Banks & Credit Unions",
            "subcategory":"Bank",
            "type":"Services"
        }
    ],
    "sg:phone":"+1 801 277 7557",
    "sg:postcode":"84117",
    "sg:province":"UT",
    "sg:tags":[
        "personal",
        "leasing",
        "institution"
    ],
    "wof:name":"Spectrum Capital Co",
    "wof:placetype":"venue"
},
  "geometry": {"coordinates":[-111.827105,40.671054],"type":"Point"}
}