{
  "type": "Feature",
  "properties": {
    "iso:country":"US",
    "sg:address":"773 N Main St",
    "sg:city":"Brigham City",
    "sg:classifiers":[
        {
            "category":"Building & Trades",
            "subcategory":"Plumbing",
            "type":"Services"
        }
    ],
    "sg:phone":"+1 435 723 4822",
    "sg:postcode":"84302",
    "sg:province":"UT",
    "sg:tags":[
        "conditioning",
        "air",
        "system",
        "contractor"
    ],
    "wof:name":"Air Heat & Conditioning",
    "wof:placetype":"venue"
},
  "geometry": {"coordinates":[-112.015528,41.525717],"type":"Point"}
}