{
  "type": "Feature",
  "properties": {
    "iso:country":"US",
    "sg:address":"1155 Club House Dr",
    "sg:city":"Roosevelt",
    "sg:classifiers":[
        {
            "category":"Sports & Exercise",
            "subcategory":"Golf",
            "type":"Entertainment"
        }
    ],
    "sg:phone":"+1 435 722 3213",
    "sg:postcode":"84066",
    "sg:province":"UT",
    "sg:tags":[
        "course"
    ],
    "wof:name":"Roosevelt Golf Shop",
    "wof:placetype":"venue"
},
  "geometry": {"coordinates":[-110.013278,40.309047],"type":"Point"}
}