{
  "type": "Feature",
  "properties": {
    "iso:country":"US",
    "sg:address":"868 25th St",
    "sg:city":"Ogden",
    "sg:classifiers":[
        {
            "category":"Organizations",
            "subcategory":"Membership Organization",
            "type":"Services"
        }
    ],
    "sg:phone":"+1 801 621 6540",
    "sg:postcode":"84401",
    "sg:province":"UT",
    "wof:name":"Ogden Valley Business Assn",
    "wof:placetype":"venue"
},
  "geometry": {"coordinates":[-111.95690999999999,41.220548],"type":"Point"}
}