{
  "type": "Feature",
  "properties": {
    "iso:country":"US",
    "sg:address":"180 W Main St",
    "sg:city":"Mt Pleasant",
    "sg:classifiers":[
        {
            "category":"Autos & Motor Vehicles",
            "subcategory":"Auto Supplies",
            "type":"Retail Goods"
        }
    ],
    "sg:phone":"+1 435 462 2605",
    "sg:postcode":"84647",
    "sg:province":"UT",
    "sg:tags":[
        "automobile",
        "parts"
    ],
    "wof:name":"Express Auto Parts",
    "wof:placetype":"venue"
},
  "geometry": {"coordinates":[-111.45761,39.546866],"type":"Point"}
}