{
  "type": "Feature",
  "properties": {
    "iso:country":"US",
    "sg:address":"63 E State Rd",
    "sg:city":"Pleasant Grove",
    "sg:classifiers":[
        {
            "category":"Insurance",
            "subcategory":"Insurance Agent",
            "type":"Services"
        }
    ],
    "sg:phone":"+1 801 785 4711",
    "sg:postcode":"84062",
    "sg:province":"UT",
    "sg:website":"www.insurance-essentials.com",
    "wof:name":"Insurance Essentials Agency",
    "wof:placetype":"venue"
},
  "geometry": {"coordinates":[-111.739057,40.358234],"type":"Point"}
}