{
  "type": "Feature",
  "properties": {
    "iso:country":"US",
    "sg:address":"1635 W Briar Rose Pl",
    "sg:city":"Salt Lake City",
    "sg:classifiers":[
        {
            "category":"Freight",
            "type":"Transportation"
        }
    ],
    "sg:phone":"+1 801 808 1888",
    "sg:postcode":"84104",
    "sg:province":"UT",
    "sg:tags":[
        "trucking"
    ],
    "wof:name":"Exit 15 Trucking Inc",
    "wof:placetype":"venue"
},
  "geometry": {"coordinates":[-111.93719900000001,40.73354],"type":"Point"}
}