{
  "type": "Feature",
  "properties": {
    "iso:country":"US",
    "sg:address":"450 S Main St",
    "sg:city":"Ephraim",
    "sg:classifiers":[
        {
            "category":"Travel",
            "subcategory":"Hotels & Motels",
            "type":"Entertainment"
        }
    ],
    "sg:phone":"+1 435 283 4566",
    "sg:postcode":"84627",
    "sg:province":"UT",
    "sg:tags":[
        "operation"
    ],
    "wof:name":"Willow Creek Inn",
    "wof:placetype":"venue"
},
  "geometry": {"coordinates":[-111.58725200000001,39.351916],"type":"Point"}
}