{
  "type": "Feature",
  "properties": {
    "iso:country":"US",
    "sg:address":"530 S 500",
    "sg:city":"Woods Cross",
    "sg:classifiers":[
        {
            "category":"Autos & Motor Vehicles",
            "subcategory":"Auto Supplies",
            "type":"Retail Goods"
        }
    ],
    "sg:phone":"+1 801 292 0179",
    "sg:postcode":"84087",
    "sg:province":"UT",
    "sg:tags":[
        "tire"
    ],
    "wof:name":"Firestone Tire & Service Centers",
    "wof:placetype":"venue"
},
  "geometry": {"coordinates":[-111.910004,40.879002],"type":"Point"}
}