{
  "type": "Feature",
  "properties": {
    "iso:country":"US",
    "sg:address":"2682 Meadowridge Dr",
    "sg:city":"West Jordan",
    "sg:classifiers":[
        {
            "category":"Personal",
            "subcategory":"Beauty Salon",
            "type":"Services"
        }
    ],
    "sg:phone":"+1 801 569 8695",
    "sg:postcode":"84088",
    "sg:province":"UT",
    "sg:tags":[
        "shop"
    ],
    "wof:name":"Pat's Curl & Cuts",
    "wof:placetype":"venue"
},
  "geometry": {"coordinates":[-111.95738799999999,40.581492],"type":"Point"}
}