{
  "type": "Feature",
  "properties": {
    "iso:country":"US",
    "sg:address":"6191 S State St",
    "sg:city":"Salt Lake City",
    "sg:classifiers":[
        {
            "category":"Shopping",
            "subcategory":"Jewelry",
            "type":"Retail Goods"
        }
    ],
    "sg:phone":"+1 801 261 4999",
    "sg:postcode":"84107",
    "sg:province":"UT",
    "sg:tags":[
        "precious",
        "mfg",
        "metal",
        "jeweler"
    ],
    "wof:name":"Masseys Jewelers",
    "wof:placetype":"venue"
},
  "geometry": {"coordinates":[-111.889163,40.636285],"type":"Point"}
}