{
  "type": "Feature",
  "properties": {
    "iso:country":"US",
    "sg:address":"2950 S Hwy 191",
    "sg:city":"Moab",
    "sg:classifiers":[
        {
            "category":"Building & Trades",
            "subcategory":"Construction",
            "type":"Services"
        }
    ],
    "sg:phone":"+1 435 259 4289",
    "sg:postcode":"84532",
    "sg:province":"UT",
    "sg:tags":[
        "boring",
        "drilling",
        "contractor"
    ],
    "wof:name":"Balsley Well Svc",
    "wof:placetype":"venue"
},
  "geometry": {"coordinates":[-109.50439,38.529129],"type":"Point"}
}