{
  "type": "Feature",
  "properties": {
    "iso:country":"US",
    "sg:address":"355 Knowlton St",
    "sg:city":"Layton",
    "sg:classifiers":[
        {
            "category":"Real Estate",
            "subcategory":"Real Estate Operator",
            "type":"Services"
        }
    ],
    "sg:phone":"+1 801 546 0083",
    "sg:postcode":"84041",
    "sg:province":"UT",
    "sg:tags":[
        "building",
        "apartment"
    ],
    "wof:name":"Layton Pointe Apartments",
    "wof:placetype":"venue"
},
  "geometry": {"coordinates":[-111.958215,41.053494],"type":"Point"}
}