{
  "type": "Feature",
  "properties": {
    "iso:country":"US",
    "sg:address":"4430 W 5740 S",
    "sg:city":"Salt Lake City",
    "sg:classifiers":[
        {
            "category":"Building & Trades",
            "subcategory":"Construction",
            "type":"Services"
        }
    ],
    "sg:phone":"+1 801 982 7724",
    "sg:postcode":"84118",
    "sg:province":"UT",
    "sg:tags":[
        "roofing",
        "siding",
        "contractor"
    ],
    "wof:name":"Action Roofing",
    "wof:placetype":"venue"
},
  "geometry": {"coordinates":[-111.995172,40.647045],"type":"Point"}
}