{
  "type": "Feature",
  "properties": {
    "iso:country":"US",
    "sg:address":"1635 Yalecrest Ave",
    "sg:city":"Salt Lake City",
    "sg:classifiers":[
        {
            "category":"Professional",
            "subcategory":"Business Services",
            "type":"Services"
        }
    ],
    "sg:phone":"+1 801 583 1297",
    "sg:postcode":"84105",
    "sg:province":"UT",
    "wof:name":"Emma Mary Deland Foundation",
    "wof:placetype":"venue"
},
  "geometry": {"coordinates":[-111.846219,40.745459],"type":"Point"}
}