{
  "type": "Feature",
  "properties": {
    "iso:country":"US",
    "sg:address":"4580 Suncrest Dr",
    "sg:city":"Salt Lake City",
    "sg:classifiers":[
        {
            "category":"Professional",
            "type":"Services"
        }
    ],
    "sg:phone":"+1 801 277 9612",
    "sg:postcode":"84117",
    "sg:province":"UT",
    "wof:name":"Windy Ridge Pipeline & Reservr",
    "wof:placetype":"venue"
},
  "geometry": {"coordinates":[-111.836399,40.67195],"type":"Point"}
}