{
  "type": "Feature",
  "properties": {
    "iso:country":"US",
    "sg:address":"1910 Prospector Ave",
    "sg:city":"Park City",
    "sg:classifiers":[
        {
            "category":"Real Estate",
            "subcategory":"Real Estate Operator",
            "type":"Services"
        }
    ],
    "sg:phone":"+1 435 649 9199",
    "sg:postcode":"84060",
    "sg:province":"UT",
    "sg:tags":[
        "condominium"
    ],
    "wof:name":"Summit Point Construction",
    "wof:placetype":"venue"
},
  "geometry": {"coordinates":[-111.500398,40.662182],"type":"Point"}
}