{
  "type": "Feature",
  "properties": {
    "iso:country":"US",
    "sg:address":"9057 W 2700 S",
    "sg:city":"Magna",
    "sg:classifiers":[
        {
            "category":"Organizations",
            "subcategory":"Non-profit Organization",
            "type":"Services"
        }
    ],
    "sg:phone":"+1 801 250 7323",
    "sg:postcode":"84044",
    "sg:province":"UT",
    "wof:name":"Veterans Of Foreign Wars",
    "wof:placetype":"venue"
},
  "geometry": {"coordinates":[-112.107968,40.710894],"type":"Point"}
}