{
  "type": "Feature",
  "properties": {
    "iso:country":"US",
    "sg:address":"52 E 1370 South Pl",
    "sg:city":"Logan",
    "sg:classifiers":[
        {
            "category":"Professional",
            "subcategory":"Business Services",
            "type":"Services"
        }
    ],
    "sg:phone":"+1 435 753 7529",
    "sg:postcode":"84321",
    "sg:province":"UT",
    "wof:name":"Fobs Enterprises LLC",
    "wof:placetype":"venue"
},
  "geometry": {"coordinates":[-111.84536,41.704113],"type":"Point"}
}