{
  "type": "Feature",
  "properties": {
    "iso:country":"US",
    "sg:address":"5739 S 3225 W",
    "sg:city":"Salt Lake City",
    "sg:classifiers":[
        {
            "category":"Sports & Exercise",
            "subcategory":"Gym",
            "type":"Entertainment"
        }
    ],
    "sg:phone":"+1 801 979 1699",
    "sg:postcode":"84118",
    "sg:province":"UT",
    "sg:tags":[
        "personal",
        "trainer"
    ],
    "wof:name":"Fit In Fitness-In Home",
    "wof:placetype":"venue"
},
  "geometry": {"coordinates":[-111.96792499999999,40.646901],"type":"Point"}
}