{
  "type": "Feature",
  "properties": {
    "iso:country":"US",
    "sg:address":"4636 Highland Dr",
    "sg:city":"Salt Lake City",
    "sg:classifiers":[
        {
            "category":"Personal",
            "subcategory":"Beauty Salon",
            "type":"Services"
        }
    ],
    "sg:phone":"+1 801 278 3086",
    "sg:postcode":"84117",
    "sg:province":"UT",
    "wof:name":"Le Studio",
    "wof:placetype":"venue"
},
  "geometry": {"coordinates":[-111.84021199999999,40.669672],"type":"Point"}
}