{
  "type": "Feature",
  "properties": {
    "iso:country":"US",
    "sg:address":"6950 Redwood Rd",
    "sg:city":"West Jordan",
    "sg:classifiers":[
        {
            "category":"Coffee & Tea",
            "type":"Food & Drink"
        }
    ],
    "sg:menulink":"http://www.allmenus.com/ut/salt-lake-city/118414-starbucks-coffee/menu/",
    "sg:phone":"+1 801 568 1685",
    "sg:postcode":"84084",
    "sg:province":"UT",
    "sg:tags":[
        "american"
    ],
    "wof:name":"Starbucks Coffee",
    "wof:placetype":"venue"
},
  "geometry": {"coordinates":[-111.93872,40.624918],"type":"Point"}
}