{
  "type": "Feature",
  "properties": {
    "iso:country":"US",
    "sg:address":"103 N 300 W",
    "sg:city":"Salt Lake City",
    "sg:classifiers":[
        {
            "category":"Restaurant",
            "type":"Food & Drink"
        }
    ],
    "sg:phone":"+1 801 363 8148",
    "sg:postcode":"84103",
    "sg:province":"UT",
    "sg:tags":[
        "eating"
    ],
    "wof:name":"Subway",
    "wof:placetype":"venue"
},
  "geometry": {"coordinates":[-111.89975200000001,40.773649],"type":"Point"}
}