{
  "type": "Feature",
  "properties": {
    "iso:country":"US",
    "sg:address":"80 N 400 E",
    "sg:city":"American Fork",
    "sg:classifiers":[
        {
            "category":"Shopping",
            "subcategory":"Computers & Home Electronics",
            "type":"Retail Goods"
        }
    ],
    "sg:phone":"+1 801 763 1911",
    "sg:postcode":"84003",
    "sg:province":"UT",
    "sg:tags":[
        "equipment",
        "dealer"
    ],
    "wof:name":"My Computer Now",
    "wof:placetype":"venue"
},
  "geometry": {"coordinates":[-111.787902,40.378311],"type":"Point"}
}