{
  "type": "Feature",
  "properties": {
    "iso:country":"US",
    "sg:address":"7013 S 1620 E",
    "sg:city":"Salt Lake City",
    "sg:classifiers":[
        {
            "category":"Shopping",
            "subcategory":"Gifts & Souvenirs",
            "type":"Retail Goods"
        }
    ],
    "sg:phone":"+1 801 944 6844",
    "sg:postcode":"84121",
    "sg:province":"UT",
    "wof:name":"MI Tierra Treasures of Ecuador",
    "wof:placetype":"venue"
},
  "geometry": {"coordinates":[-111.845668,40.623524],"type":"Point"}
}