{
  "type": "Feature",
  "properties": {
    "iso:country":"US",
    "sg:address":"6248 Chatterleigh Ave",
    "sg:city":"Salt Lake City",
    "sg:classifiers":[
        {
            "category":"Professional",
            "subcategory":"Accounting & Tax Preparation",
            "type":"Services"
        }
    ],
    "sg:phone":"+1 801 968 7838",
    "sg:postcode":"84128",
    "sg:province":"UT",
    "wof:name":"Tax & Bookkeeping Service",
    "wof:placetype":"venue"
},
  "geometry": {"coordinates":[-112.040211,40.687374],"type":"Point"}
}