{
  "type": "Feature",
  "properties": {
    "iso:country":"US",
    "sg:address":"2280 E 900 S",
    "sg:city":"Salt Lake City",
    "sg:classifiers":[
        {
            "category":"Building & Trades",
            "subcategory":"Landscaping Services",
            "type":"Services"
        }
    ],
    "sg:phone":"+1 801 554 8233",
    "sg:postcode":"84108",
    "sg:province":"UT",
    "sg:tags":[
        "landscape",
        "contractor"
    ],
    "wof:name":"Schocker Sprinkler & Landscape",
    "wof:placetype":"venue"
},
  "geometry": {"coordinates":[-111.826004,40.749545],"type":"Point"}
}