{
  "type": "Feature",
  "properties": {
    "iso:country":"US",
    "sg:address":"2121 W 4800 S",
    "sg:city":"Roy",
    "sg:classifiers":[
        {
            "category":"Professional",
            "subcategory":"Management & Consulting",
            "type":"Services"
        }
    ],
    "sg:phone":"+1 801 773 6480",
    "sg:postcode":"84067",
    "sg:province":"UT",
    "sg:tags":[
        "food",
        "retail",
        "direct",
        "sales"
    ],
    "wof:name":"Wilcox Enterprises",
    "wof:placetype":"venue"
},
  "geometry": {"coordinates":[-112.0303,41.17612],"type":"Point"}
}