{
  "type": "Feature",
  "properties": {
    "iso:country":"US",
    "sg:address":"540 E 100 N",
    "sg:city":"Moab",
    "sg:classifiers":[
        {
            "category":"Real Estate",
            "subcategory":"Real Estate Operator",
            "type":"Services"
        }
    ],
    "sg:phone":"+1 435 259 5104",
    "sg:postcode":"84532",
    "sg:province":"UT",
    "sg:tags":[
        "apartment"
    ],
    "wof:name":"Rockridge Senior Housing",
    "wof:placetype":"venue"
},
  "geometry": {"coordinates":[-109.53997099999999,38.574029],"type":"Point"}
}