{
  "type": "Feature",
  "properties": {
    "iso:country":"US",
    "sg:address":"484 Westfield Rd",
    "sg:city":"Alpine",
    "sg:classifiers":[
        {
            "category":"Wholesale",
            "subcategory":"Sporting Goods",
            "type":"Manufacturing & Wholesale Goods"
        }
    ],
    "sg:phone":"+1 801 756 5222",
    "sg:postcode":"84004",
    "sg:province":"UT",
    "wof:name":"Jaran Industries",
    "wof:placetype":"venue"
},
  "geometry": {"coordinates":[-111.787132,40.454593],"type":"Point"}
}