{
  "type": "Feature",
  "properties": {
    "iso:country":"US",
    "sg:address":"220 N Main St",
    "sg:city":"Brigham City",
    "sg:classifiers":[
        {
            "category":"Shopping",
            "subcategory":"Pharmacy",
            "type":"Retail Goods"
        }
    ],
    "sg:phone":"+1 435 723 5243",
    "sg:postcode":"84302",
    "sg:province":"UT",
    "sg:tags":[
        "drug",
        "store"
    ],
    "wof:name":"Rite Aid",
    "wof:placetype":"venue"
},
  "geometry": {"coordinates":[-112.015548,41.515248],"type":"Point"}
}