{
  "type": "Feature",
  "properties": {
    "iso:country":"US",
    "sg:address":"1947 W 350 N",
    "sg:city":"Clearfield",
    "sg:classifiers":[
        {
            "category":"Professional",
            "subcategory":"Business Services",
            "type":"Services"
        }
    ],
    "sg:phone":"+1 801 775 0391",
    "sg:postcode":"84015",
    "sg:province":"UT",
    "wof:name":"Kutterer Partners LLC",
    "wof:placetype":"venue"
},
  "geometry": {"coordinates":[-112.06321800000001,41.119017],"type":"Point"}
}