{
  "type": "Feature",
  "properties": {
    "iso:country":"US",
    "sg:address":"4544 Highland Dr",
    "sg:city":"Holladay",
    "sg:classifiers":[
        {
            "category":"Professional",
            "type":"Services"
        }
    ],
    "sg:phone":"+1 801 278 0426",
    "sg:postcode":"84117",
    "sg:province":"UT",
    "sg:tags":[
        "establishment"
    ],
    "wof:name":"Beacon Hills",
    "wof:placetype":"venue"
},
  "geometry": {"coordinates":[-111.84113000000001,40.67292],"type":"Point"}
}