{
  "type": "Feature",
  "properties": {
    "iso:country":"US",
    "sg:address":"2492 E 6200 S",
    "sg:city":"Holladay",
    "sg:classifiers":[
        {
            "category":"Health Services",
            "subcategory":"Clinic",
            "type":"Services"
        },
        {
            "category":"Health Services",
            "subcategory":"Medical Lab",
            "type":"Services"
        }
    ],
    "sg:phone":"+1 801 424 2181",
    "sg:postcode":"84121",
    "sg:province":"UT",
    "sg:tags":[
        "laboratory"
    ],
    "wof:name":"Ultrascan Health Imaging LLC",
    "wof:placetype":"venue"
},
  "geometry": {"coordinates":[-111.819309,40.638431],"type":"Point"}
}