{
  "type": "Feature",
  "properties": {
    "iso:country":"US",
    "sg:address":"8045 S 615 E",
    "sg:city":"Sandy",
    "sg:classifiers":[
        {
            "category":"Wholesale",
            "subcategory":"Construction Materials",
            "type":"Manufacturing & Wholesale Goods"
        },
        {
            "category":"Professional",
            "subcategory":"Detective & Security Services",
            "type":"Services"
        }
    ],
    "sg:phone":"+1 801 304 4283",
    "sg:postcode":"84070",
    "sg:province":"UT",
    "sg:tags":[
        "control",
        "gates",
        "access",
        "equipment",
        "automated",
        "gate"
    ],
    "wof:name":"Buchanan Access Systems LLC",
    "wof:placetype":"venue"
},
  "geometry": {"coordinates":[-111.874244,40.604913],"type":"Point"}
}