{
  "type": "Feature",
  "properties": {
    "iso:country":"US",
    "sg:address":"11040 Lynford Dr",
    "sg:city":"Sandy",
    "sg:classifiers":[
        {
            "category":"Building & Trades",
            "subcategory":"Landscaping Services",
            "type":"Services"
        }
    ],
    "sg:phone":"+1 801 576 1884",
    "sg:postcode":"84092",
    "sg:province":"UT",
    "wof:name":"Baltic Landscape Curbing",
    "wof:placetype":"venue"
},
  "geometry": {"coordinates":[-111.85067100000001,40.550922],"type":"Point"}
}