{
  "type": "Feature",
  "properties": {
    "iso:country":"US",
    "sg:address":"1559 S 1460 E",
    "sg:city":"Spanish Fork",
    "sg:classifiers":[
        {
            "category":"Organizations",
            "subcategory":"Religious Organization",
            "type":"Services"
        }
    ],
    "sg:phone":"+1 801 794 2227",
    "sg:postcode":"84660",
    "sg:province":"UT",
    "sg:tags":[
        "church"
    ],
    "wof:name":"Native American Church",
    "wof:placetype":"venue"
},
  "geometry": {"coordinates":[-111.62972600000001,40.089123],"type":"Point"}
}