{
  "type": "Feature",
  "properties": {
    "iso:country":"US",
    "sg:address":"564 W 800 S",
    "sg:city":"Bountiful",
    "sg:classifiers":[
        {
            "category":"Manufacturing",
            "subcategory":"Building Materials",
            "type":"Manufacturing & Wholesale Goods"
        }
    ],
    "sg:phone":"+1 801 292 8115",
    "sg:postcode":"84010",
    "sg:province":"UT",
    "sg:tags":[
        "cabinet"
    ],
    "wof:name":"Lam Wood Inc",
    "wof:placetype":"venue"
},
  "geometry": {"coordinates":[-111.89519300000001,40.881434],"type":"Point"}
}