{
  "type": "Feature",
  "properties": {
    "iso:country":"US",
    "sg:address":"3333 Highland Dr",
    "sg:city":"Salt Lake City",
    "sg:classifiers":[
        {
            "category":"Home & Garden",
            "subcategory":"Carpets & Floor Coverings",
            "type":"Retail Goods"
        }
    ],
    "sg:phone":"+1 801 467 7847",
    "sg:postcode":"84106",
    "sg:province":"UT",
    "wof:name":"Aposhian Dghlian Oriental Rugs",
    "wof:placetype":"venue"
},
  "geometry": {"coordinates":[-111.850482,40.699553],"type":"Point"}
}