{
  "type": "Feature",
  "properties": {
    "iso:country":"US",
    "sg:address":"1441 Fort Union Blvd",
    "sg:city":"Salt Lake City",
    "sg:classifiers":[
        {
            "category":"Banks & Credit Unions",
            "subcategory":"Bank",
            "type":"Services"
        }
    ],
    "sg:phone":"+1 801 942 3979",
    "sg:postcode":"84121",
    "sg:province":"UT",
    "sg:tags":[
        "broker",
        "mortgage"
    ],
    "wof:name":"Homestead Mortgage Services Lc",
    "wof:placetype":"venue"
},
  "geometry": {"coordinates":[-111.850971,40.625813],"type":"Point"}
}