{
  "type": "Feature",
  "properties": {
    "iso:country":"US",
    "sg:address":"221 N Main St",
    "sg:city":"Alpine",
    "sg:classifiers":[
        {
            "category":"Professional",
            "subcategory":"Business Services",
            "type":"Services"
        }
    ],
    "sg:phone":"+1 801 756 8111",
    "sg:postcode":"84004",
    "sg:province":"UT",
    "sg:website":"www.marvinpayne.com",
    "wof:name":"Babymoon Recording",
    "wof:placetype":"venue"
},
  "geometry": {"coordinates":[-111.777901,40.456638],"type":"Point"}
}