{
  "type": "Feature",
  "properties": {
    "iso:country":"US",
    "sg:address":"140 W 9000 S",
    "sg:city":"Sandy",
    "sg:classifiers":[
        {
            "category":"Professional",
            "subcategory":"Lawyer & Legal Services",
            "type":"Services"
        }
    ],
    "sg:phone":"+1 801 562 1459",
    "sg:postcode":"84070",
    "sg:province":"UT",
    "sg:tags":[
        "attorney"
    ],
    "wof:name":"D Scott Little & Associates",
    "wof:placetype":"venue"
},
  "geometry": {"coordinates":[-111.893885,40.588151],"type":"Point"}
}