{
  "type": "Feature",
  "properties": {
    "iso:country":"US",
    "sg:address":"8770 Jeremy Rd",
    "sg:city":"Park City",
    "sg:classifiers":[
        {
            "category":"Real Estate",
            "subcategory":"Real Estate Agent",
            "type":"Services"
        }
    ],
    "sg:phone":"+1 435 649 8700",
    "sg:postcode":"84098",
    "sg:province":"UT",
    "wof:name":"Chapman-Richards Assoc",
    "wof:placetype":"venue"
},
  "geometry": {"coordinates":[-111.57872399999999,40.762082],"type":"Point"}
}