{
  "type": "Feature",
  "properties": {
    "iso:country":"US",
    "sg:address":"70 N Main St",
    "sg:city":"Roosevelt",
    "sg:classifiers":[
        {
            "category":"Insurance",
            "subcategory":"Insurance Agent",
            "type":"Services"
        }
    ],
    "sg:phone":"+1 435 722 5006",
    "sg:postcode":"84054",
    "sg:province":"UT",
    "wof:name":"Eastern Ut Insurance",
    "wof:placetype":"venue"
},
  "geometry": {"coordinates":[-111.911733,40.841925],"type":"Point"}
}