{
  "type": "Feature",
  "properties": {
    "iso:country":"US",
    "sg:address":"262 W 3300 N",
    "sg:city":"Provo",
    "sg:classifiers":[
        {
            "category":"Retail",
            "subcategory":"Auto Rental",
            "type":"Services"
        }
    ],
    "sg:phone":"+1 801 607 2471",
    "sg:postcode":"84604",
    "sg:province":"UT",
    "sg:tags":[
        "passenger",
        "car"
    ],
    "wof:name":"Rnt Rentals LLC",
    "wof:placetype":"venue"
},
  "geometry": {"coordinates":[-111.665002,40.277071],"type":"Point"}
}