{
  "type": "Feature",
  "properties": {
    "iso:country":"US",
    "sg:address":"1115 W 300 S",
    "sg:city":"Salt Lake City",
    "sg:classifiers":[
        {
            "category":"Education",
            "subcategory":"School",
            "type":"Public Place"
        }
    ],
    "sg:phone":"+1 801 578 8158",
    "sg:postcode":"84104",
    "sg:province":"UT",
    "wof:name":"Franklin Elementary School",
    "wof:placetype":"venue"
},
  "geometry": {"coordinates":[-111.924207,40.762729],"type":"Point"}
}