{
  "type": "Feature",
  "properties": {
    "iso:country":"US",
    "sg:address":"476 Heritage Park Blvd",
    "sg:city":"Layton",
    "sg:classifiers":[
        {
            "category":"Banks & Credit Unions",
            "subcategory":"Bank",
            "type":"Services"
        }
    ],
    "sg:phone":"+1 801 728 0552",
    "sg:postcode":"84041",
    "sg:province":"UT",
    "sg:tags":[
        "federal",
        "savings",
        "institution"
    ],
    "wof:name":"World Savings",
    "wof:placetype":"venue"
},
  "geometry": {"coordinates":[-111.973679,41.08272],"type":"Point"}
}