{
  "type": "Feature",
  "properties": {
    "iso:country":"US",
    "sg:address":"623 W 200 S",
    "sg:city":"Tooele",
    "sg:classifiers":[
        {
            "category":"Building & Trades",
            "subcategory":"Construction",
            "type":"Services"
        }
    ],
    "sg:phone":"+1 435 882 6281",
    "sg:postcode":"84074",
    "sg:province":"UT",
    "sg:tags":[
        "house"
    ],
    "wof:name":"Bob Harris Construction Inc",
    "wof:placetype":"venue"
},
  "geometry": {"coordinates":[-112.321106,40.526846],"type":"Point"}
}