{
  "type": "Feature",
  "properties": {
    "iso:country":"US",
    "sg:address":"7638 S State St",
    "sg:city":"Midvale",
    "sg:classifiers":[
        {
            "category":"Retail",
            "subcategory":"Repair Shop",
            "type":"Services"
        }
    ],
    "sg:phone":"+1 801 282 6902",
    "sg:postcode":"84047",
    "sg:province":"UT",
    "sg:tags":[
        "refinishing",
        "furniture"
    ],
    "wof:name":"Paul's Furniture Repair",
    "wof:placetype":"venue"
},
  "geometry": {"coordinates":[-111.89083100000001,40.610985],"type":"Point"}
}