{
  "type": "Feature",
  "properties": {
    "iso:country":"US",
    "sg:address":"394 W 100 S",
    "sg:city":"Logan",
    "sg:classifiers":[
        {
            "category":"Professional",
            "subcategory":"Business Services",
            "type":"Services"
        }
    ],
    "sg:phone":"+1 435 770 7128",
    "sg:postcode":"84321",
    "sg:province":"UT",
    "wof:name":"Designflex",
    "wof:placetype":"venue"
},
  "geometry": {"coordinates":[-111.84524500000001,41.729553],"type":"Point"}
}