{
  "type": "Feature",
  "properties": {
    "iso:country":"US",
    "sg:address":"3555 W 1500 S",
    "sg:city":"Salt Lake City",
    "sg:classifiers":[
        {
            "category":"Manufacturing",
            "subcategory":"Tools & Machinery",
            "type":"Manufacturing & Wholesale Goods"
        }
    ],
    "sg:phone":"+1 801 887 5114",
    "sg:postcode":"84104",
    "sg:province":"UT",
    "sg:tags":[
        "instrument",
        "surgical"
    ],
    "sg:website":"www.mti-inc.us",
    "wof:name":"MTI Inc",
    "wof:placetype":"venue"
},
  "geometry": {"coordinates":[-111.973916,40.738472],"type":"Point"}
}