{
  "type": "Feature",
  "properties": {
    "iso:country":"US",
    "sg:address":"302 S Main St",
    "sg:city":"Logan",
    "sg:classifiers":[
        {
            "category":"Building & Trades",
            "subcategory":"Construction",
            "type":"Services"
        }
    ],
    "sg:phone":"+1 435 752 7940",
    "sg:postcode":"84321",
    "sg:province":"UT",
    "sg:tags":[
        "excavating",
        "contractor"
    ],
    "wof:name":"Allied Construction",
    "wof:placetype":"venue"
},
  "geometry": {"coordinates":[-111.83504000000001,41.725903],"type":"Point"}
}