{
  "type": "Feature",
  "properties": {
    "iso:country":"US",
    "sg:address":"2706 Estates Dr",
    "sg:city":"Park City",
    "sg:classifiers":[
        {
            "category":"Home & Garden",
            "subcategory":"Furniture",
            "type":"Retail Goods"
        }
    ],
    "sg:phone":"+1 435 645 8866",
    "sg:postcode":"84060",
    "sg:province":"UT",
    "sg:tags":[
        "bedding"
    ],
    "wof:name":"European Linens & Design",
    "wof:placetype":"venue"
},
  "geometry": {"coordinates":[-111.499574,40.681207],"type":"Point"}
}