{
  "type": "Feature",
  "properties": {
    "iso:country":"US",
    "sg:address":"1468 Rio Virgin Dr",
    "sg:city":"Washington",
    "sg:classifiers":[
        {
            "category":"Professional",
            "type":"Services"
        }
    ],
    "sg:phone":"+1 435 674 5600",
    "sg:postcode":"84780",
    "sg:province":"UT",
    "sg:tags":[
        "establishment"
    ],
    "wof:name":"Wecor",
    "wof:placetype":"venue"
},
  "geometry": {"coordinates":[-113.484791,37.111705],"type":"Point"}
}