{
  "type": "Feature",
  "properties": {
    "iso:country":"US",
    "sg:address":"1389 E 13430 S",
    "sg:city":"Draper",
    "sg:classifiers":[
        {
            "category":"Shopping",
            "subcategory":"Clothing, Apparel, & Fashions",
            "type":"Retail Goods"
        }
    ],
    "sg:phone":"+1 801 571 1644",
    "sg:postcode":"84020",
    "sg:province":"UT",
    "sg:tags":[
        "family"
    ],
    "wof:name":"Beesley Outpost LLC",
    "wof:placetype":"venue"
},
  "geometry": {"coordinates":[-111.85162099999999,40.507264],"type":"Point"}
}