{
  "type": "Feature",
  "properties": {
    "iso:country":"US",
    "sg:address":"676 W 1340 S",
    "sg:city":"Payson",
    "sg:classifiers":[
        {
            "category":"Building & Trades",
            "subcategory":"Plumbing",
            "type":"Services"
        }
    ],
    "sg:phone":"+1 801 225 1183",
    "sg:postcode":"84601",
    "sg:province":"UT",
    "sg:tags":[
        "contractor"
    ],
    "wof:name":"Admiral Plumbing",
    "wof:placetype":"venue"
},
  "geometry": {"coordinates":[-111.669245,40.215879],"type":"Point"}
}