{
  "type": "Feature",
  "properties": {
    "iso:country":"US",
    "sg:address":"22 N Main St",
    "sg:city":"Roosevelt",
    "sg:classifiers":[
        {
            "category":"Shopping",
            "subcategory":"Hobbies, Toys, & Games",
            "type":"Retail Goods"
        }
    ],
    "sg:phone":"+1 435 725 1000",
    "sg:postcode":"84069",
    "sg:province":"UT",
    "wof:name":"Country Hollow Gifts",
    "wof:placetype":"venue"
},
  "geometry": {"coordinates":[-112.446085,40.337289],"type":"Point"}
}