{
  "type": "Feature",
  "properties": {
    "iso:country":"US",
    "sg:address":"363 S 500 E",
    "sg:city":"Salt Lake City",
    "sg:classifiers":[
        {
            "category":"Personal",
            "subcategory":"Beauty Salon",
            "type":"Services"
        }
    ],
    "sg:phone":"+1 801 364 3330",
    "sg:postcode":"84102",
    "sg:province":"UT",
    "sg:tags":[
        "spa",
        "day"
    ],
    "wof:name":"Akasha Salon & Day Spa",
    "wof:placetype":"venue"
},
  "geometry": {"coordinates":[-111.87670300000001,40.761207],"type":"Point"}
}