{
  "type": "Feature",
  "properties": {
    "iso:country":"US",
    "sg:address":"9201 S 1300 E",
    "sg:city":"Sandy",
    "sg:classifiers":[
        {
            "category":"Home & Garden",
            "subcategory":"Garden Supply",
            "type":"Retail Goods"
        }
    ],
    "sg:phone":"+1 801 571 9241",
    "sg:postcode":"84094",
    "sg:province":"UT",
    "sg:tags":[
        "lawn"
    ],
    "wof:name":"Western Garden Center Inc",
    "wof:placetype":"venue"
},
  "geometry": {"coordinates":[-111.853121,40.584161],"type":"Point"}
}