{
  "type": "Feature",
  "properties": {
    "iso:country":"US",
    "sg:address":"8189 S 2660 E",
    "sg:city":"Sandy",
    "sg:classifiers":[
        {
            "category":"Wholesale",
            "subcategory":"Machinery & Supplies",
            "type":"Manufacturing & Wholesale Goods"
        }
    ],
    "sg:phone":"+1 801 947 7674",
    "sg:postcode":"84093",
    "sg:province":"UT",
    "sg:tags":[
        "equipment",
        "industrial"
    ],
    "wof:name":"Equipment Exchange Services Lc",
    "wof:placetype":"venue"
},
  "geometry": {"coordinates":[-111.815934,40.602622],"type":"Point"}
}