{
  "type": "Feature",
  "properties": {
    "iso:country":"US",
    "sg:address":"7871 E 1300 N",
    "sg:city":"Huntsville",
    "sg:classifiers":[
        {
            "category":"Banks & Credit Unions",
            "subcategory":"Financial Services",
            "type":"Services"
        }
    ],
    "sg:phone":"+1 801 745 0075",
    "sg:postcode":"84317",
    "sg:province":"UT",
    "sg:tags":[
        "trust",
        "management"
    ],
    "wof:name":"Knowles Family Trust",
    "wof:placetype":"venue"
},
  "geometry": {"coordinates":[-111.758008,41.283743],"type":"Point"}
}