{
  "type": "Feature",
  "properties": {
    "iso:country":"US",
    "sg:address":"13947 Minuteman Dr",
    "sg:city":"Draper",
    "sg:classifiers":[
        {
            "category":"Home & Garden",
            "subcategory":"Hardware",
            "type":"Retail Goods"
        }
    ],
    "sg:phone":"+1 801 748 2528",
    "sg:postcode":"84020",
    "sg:province":"UT",
    "sg:tags":[
        "tool",
        "used"
    ],
    "wof:name":"Invest Tools Inc",
    "wof:placetype":"venue"
},
  "geometry": {"coordinates":[-111.890478,40.494131],"type":"Point"}
}