{
  "type": "Feature",
  "properties": {
    "iso:country":"US",
    "sg:address":"1032 S Geneva Rd",
    "sg:city":"Orem",
    "sg:classifiers":[
        {
            "category":"Building & Trades",
            "subcategory":"Construction",
            "type":"Services"
        }
    ],
    "sg:phone":"+1 801 221 2611",
    "sg:postcode":"84058",
    "sg:province":"UT",
    "sg:tags":[
        "dry wall",
        "contractor"
    ],
    "wof:name":"JTB Construction & Drywall",
    "wof:placetype":"venue"
},
  "geometry": {"coordinates":[-111.730147,40.278346],"type":"Point"}
}