{
  "type": "Feature",
  "properties": {
    "iso:country":"US",
    "sg:address":"1586 E 400 S",
    "sg:city":"Springville",
    "sg:classifiers":[
        {
            "category":"Building & Trades",
            "subcategory":"Cleaning & Sanitation",
            "type":"Services"
        }
    ],
    "sg:phone":"+1 801 489 6910",
    "sg:postcode":"84663",
    "sg:province":"UT",
    "sg:tags":[
        "maintenance"
    ],
    "wof:name":"Hart Felt Cleaning Services",
    "wof:placetype":"venue"
},
  "geometry": {"coordinates":[-111.58234,40.160789],"type":"Point"}
}