{
  "type": "Feature",
  "properties": {
    "iso:country":"US",
    "sg:address":"742 N 530 E",
    "sg:city":"Orem",
    "sg:classifiers":[
        {
            "category":"Real Estate",
            "subcategory":"Real Estate Agent",
            "type":"Services"
        }
    ],
    "sg:phone":"+1 801 655 4500",
    "sg:postcode":"84097",
    "sg:province":"UT",
    "wof:name":"Utah Realty Solutions",
    "wof:placetype":"venue"
},
  "geometry": {"coordinates":[-111.682796,40.310376],"type":"Point"}
}