{
  "type": "Feature",
  "properties": {
    "iso:country":"US",
    "sg:address":"1308 S 2500 W",
    "sg:city":"Vernal",
    "sg:classifiers":[
        {
            "category":"Mining & Drilling",
            "type":"Manufacturing & Wholesale Goods"
        }
    ],
    "sg:phone":"+1 435 789 7390",
    "sg:postcode":"84078",
    "sg:province":"UT",
    "sg:tags":[
        "rigging",
        "oil",
        "well"
    ],
    "wof:name":"Royal Well Service",
    "wof:placetype":"venue"
},
  "geometry": {"coordinates":[-109.576273,40.436182],"type":"Point"}
}