{
  "type": "Feature",
  "properties": {
    "iso:country":"US",
    "sg:address":"55 E Main St",
    "sg:city":"Circleville",
    "sg:classifiers":[
        {
            "category":"Restaurant",
            "type":"Food & Drink"
        }
    ],
    "sg:phone":"+1 435 577 2477",
    "sg:postcode":"84723",
    "sg:province":"UT",
    "sg:tags":[
        "eating"
    ],
    "wof:name":"Circleville Cafe",
    "wof:placetype":"venue"
},
  "geometry": {"coordinates":[-112.271854,38.17181],"type":"Point"}
}