{
  "type": "Feature",
  "properties": {
    "iso:country":"US",
    "sg:address":"545 Fort Dr",
    "sg:city":"Pleasant Grove",
    "sg:classifiers":[
        {
            "category":"Organizations",
            "subcategory":"Labor Organization",
            "type":"Services"
        }
    ],
    "sg:phone":"+1 801 785 2055",
    "sg:postcode":"84062",
    "sg:province":"UT",
    "wof:name":"Dw Properties Lc",
    "wof:placetype":"venue"
},
  "geometry": {"coordinates":[-111.712897,40.35664],"type":"Point"}
}