{
  "type": "Feature",
  "properties": {
    "iso:country":"US",
    "sg:address":"2271 Alta Canyon Dr",
    "sg:city":"Sandy",
    "sg:classifiers":[
        {
            "category":"Wholesale",
            "subcategory":"Electrical",
            "type":"Manufacturing & Wholesale Goods"
        },
        {
            "category":"Wholesale",
            "subcategory":"Durable Goods & Equipment",
            "type":"Manufacturing & Wholesale Goods"
        }
    ],
    "sg:phone":"+1 801 944 9090",
    "sg:postcode":"84093",
    "sg:province":"UT",
    "sg:tags":[
        "representative",
        "manufacturer"
    ],
    "wof:name":"Crossroads Marketing Inc",
    "wof:placetype":"venue"
},
  "geometry": {"coordinates":[-111.824932,40.595099],"type":"Point"}
}