{
  "type": "Feature",
  "properties": {
    "iso:country":"US",
    "sg:address":"885 E 13800 S",
    "sg:city":"Draper",
    "sg:classifiers":[
        {
            "category":"Professional",
            "subcategory":"Management & Consulting",
            "type":"Services"
        }
    ],
    "sg:phone":"+1 801 572 2709",
    "sg:postcode":"84020",
    "sg:province":"UT",
    "sg:tags":[
        "consultant",
        "business"
    ],
    "wof:name":"Le Corp Inc",
    "wof:placetype":"venue"
},
  "geometry": {"coordinates":[-111.868358,40.500735],"type":"Point"}
}