{
  "type": "Feature",
  "properties": {
    "iso:country":"US",
    "sg:address":"475 W 100 S",
    "sg:city":"Vernal",
    "sg:classifiers":[
        {
            "category":"Organizations",
            "subcategory":"Religious Organization",
            "type":"Services"
        }
    ],
    "sg:phone":"+1 435 789 7483",
    "sg:postcode":"84078",
    "sg:province":"UT",
    "sg:tags":[
        "mormon",
        "church"
    ],
    "wof:name":"Glines Third Ward",
    "wof:placetype":"venue"
},
  "geometry": {"coordinates":[-109.537002,40.454111],"type":"Point"}
}