{
  "type": "Feature",
  "properties": {
    "iso:country":"US",
    "sg:address":"875 W Main St",
    "sg:city":"Salina",
    "sg:classifiers":[
        {
            "category":"Freight",
            "type":"Transportation"
        }
    ],
    "sg:phone":"+1 435 529 4354",
    "sg:postcode":"84654",
    "sg:province":"UT",
    "sg:tags":[
        "operator",
        "trucking"
    ],
    "wof:name":"Robinson Transport Museum",
    "wof:placetype":"venue"
},
  "geometry": {"coordinates":[-111.871089,38.956468],"type":"Point"}
}