{
  "type": "Feature",
  "properties": {
    "iso:country":"US",
    "sg:address":"432 W 800 N",
    "sg:city":"Orem",
    "sg:classifiers":[
        {
            "category":"Banks & Credit Unions",
            "subcategory":"Bank",
            "type":"Services"
        }
    ],
    "sg:phone":"+1 801 235 9762",
    "sg:postcode":"84057",
    "sg:province":"UT",
    "sg:tags":[
        "loan",
        "real estate"
    ],
    "wof:name":"Countrywide Home Loans",
    "wof:placetype":"venue"
},
  "geometry": {"coordinates":[-111.71017399999999,40.312132],"type":"Point"}
}