{
  "type": "Feature",
  "properties": {
    "iso:country":"US",
    "sg:address":"1267 W 800 N",
    "sg:city":"Mapleton",
    "sg:classifiers":[
        {
            "category":"Manufacturing",
            "subcategory":"Glass & Minerals",
            "type":"Manufacturing & Wholesale Goods"
        }
    ],
    "sg:phone":"+1 801 489 6111",
    "sg:postcode":"84664",
    "sg:province":"UT",
    "sg:tags":[
        "burial",
        "mfg",
        "tank",
        "septic",
        "vault"
    ],
    "wof:name":"Thorpe Burial Vault Inc",
    "wof:placetype":"venue"
},
  "geometry": {"coordinates":[-111.597268,40.137383],"type":"Point"}
}