{
  "type": "Feature",
  "properties": {
    "iso:country":"US",
    "sg:address":"7678 S 5040 W",
    "sg:city":"West Jordan",
    "sg:classifiers":[
        {
            "category":"Professional",
            "subcategory":"Employment Agencies",
            "type":"Services"
        }
    ],
    "sg:phone":"+1 801 280 1004",
    "sg:postcode":"84084",
    "sg:province":"UT",
    "sg:tags":[
        "consultant",
        "search",
        "executive"
    ],
    "wof:name":"PRI LLC",
    "wof:placetype":"venue"
},
  "geometry": {"coordinates":[-112.010914,40.611234],"type":"Point"}
}