{
  "type": "Feature",
  "properties": {
    "iso:country":"US",
    "sg:address":"1452 Foxboro Dr",
    "sg:city":"Salt Lake City",
    "sg:classifiers":[
        {
            "category":"Organizations",
            "subcategory":"Community Association",
            "type":"Services"
        }
    ],
    "sg:phone":"+1 801 583 4762",
    "sg:postcode":"84106",
    "sg:province":"UT",
    "sg:tags":[
        "club"
    ],
    "wof:name":"Polo Club Home Owners Assn",
    "wof:placetype":"venue"
},
  "geometry": {"coordinates":[-111.84822800000001,40.691707],"type":"Point"}
}