{
  "type": "Feature",
  "properties": {
    "iso:country":"US",
    "sg:address":"5 Northridge Way",
    "sg:city":"Sandy",
    "sg:classifiers":[
        {
            "category":"Organizations",
            "subcategory":"Membership Organization",
            "type":"Services"
        }
    ],
    "sg:phone":"+1 801 572 4269",
    "sg:postcode":"84092",
    "sg:province":"UT",
    "wof:name":"D S Houseboat Association LLC",
    "wof:placetype":"venue"
},
  "geometry": {"coordinates":[-111.812862,40.552288],"type":"Point"}
}