{
  "type": "Feature",
  "properties": {
    "iso:country":"US",
    "sg:address":"560 W 800 S",
    "sg:city":"Bountiful",
    "sg:classifiers":[
        {
            "category":"Retail",
            "subcategory":"Auto Repair",
            "type":"Services"
        }
    ],
    "sg:phone":"+1 801 295 5503",
    "sg:postcode":"84010",
    "sg:province":"UT",
    "wof:name":"Express Automotive",
    "wof:placetype":"venue"
},
  "geometry": {"coordinates":[-111.892998,40.8815],"type":"Point"}
}