{
  "type": "Feature",
  "properties": {
    "iso:country":"US",
    "sg:address":"1079 Vine St",
    "sg:city":"Salt Lake City",
    "sg:classifiers":[
        {
            "category":"Real Estate",
            "subcategory":"Real Estate Agent",
            "type":"Services"
        }
    ],
    "sg:phone":"+1 801 288 1152",
    "sg:postcode":"84121",
    "sg:province":"UT",
    "wof:name":"Synergistic RE Investments",
    "wof:placetype":"venue"
},
  "geometry": {"coordinates":[-111.862471,40.641109],"type":"Point"}
}