{
  "type": "Feature",
  "properties": {
    "iso:country":"US",
    "sg:address":"4067 W 5415 S",
    "sg:city":"Kearns",
    "sg:classifiers":[
        {
            "category":"Shopping",
            "subcategory":"Shoes",
            "type":"Retail Goods"
        }
    ],
    "sg:phone":"+1 801 964 9390",
    "sg:postcode":"84118",
    "sg:province":"UT",
    "wof:name":"Payless Shoe Source",
    "wof:placetype":"venue"
},
  "geometry": {"coordinates":[-111.98815999999999,40.652721],"type":"Point"}
}