{
  "type": "Feature",
  "properties": {
    "iso:country":"US",
    "sg:address":"147 W Angelo Ave",
    "sg:city":"South Salt Lake",
    "sg:classifiers":[
        {
            "category":"Building & Trades",
            "subcategory":"Electrical",
            "type":"Services"
        }
    ],
    "sg:phone":"+1 801 467 7100",
    "sg:postcode":"84115",
    "sg:province":"UT",
    "sg:tags":[
        "electrical",
        "electric",
        "contractor"
    ],
    "wof:name":"Coke Electric Inc",
    "wof:placetype":"venue"
},
  "geometry": {"coordinates":[-111.89554,40.702753],"type":"Point"}
}