{
  "type": "Feature",
  "properties": {
    "iso:country":"US",
    "sg:address":"280 State St",
    "sg:city":"Clearfield",
    "sg:classifiers":[
        {
            "category":"Freight",
            "type":"Transportation"
        }
    ],
    "sg:phone":"+1 801 773 0800",
    "sg:postcode":"84015",
    "sg:province":"UT",
    "sg:tags":[
        "commercial",
        "storage"
    ],
    "wof:name":"Towne Storage Clearfield",
    "wof:placetype":"venue"
},
  "geometry": {"coordinates":[-112.022128,41.10996],"type":"Point"}
}