{
  "type": "Feature",
  "properties": {
    "iso:country":"US",
    "sg:address":"4355 W 2200 N",
    "sg:city":"Ogden",
    "sg:classifiers":[
        {
            "category":"Professional",
            "subcategory":"Accounting & Tax Preparation",
            "type":"Services"
        }
    ],
    "sg:phone":"+1 801 731 1262",
    "sg:postcode":"84404",
    "sg:province":"UT",
    "wof:name":"Professional Tax Service",
    "wof:placetype":"venue"
},
  "geometry": {"coordinates":[-112.08623900000001,41.297932],"type":"Point"}
}