{
  "type": "Feature",
  "properties": {
    "iso:country":"US",
    "sg:address":"9195 S 2200 W",
    "sg:city":"West Jordan",
    "sg:classifiers":[
        {
            "category":"Real Estate",
            "subcategory":"Real Estate Agent",
            "type":"Services"
        }
    ],
    "sg:phone":"+1 801 566 1601",
    "sg:postcode":"84088",
    "sg:province":"UT",
    "wof:name":"Mc Dougal Realtors Inc",
    "wof:placetype":"venue"
},
  "geometry": {"coordinates":[-111.948133,40.583289],"type":"Point"}
}