{
  "type": "Feature",
  "properties": {
    "iso:country":"US",
    "sg:address":"50 E Main St",
    "sg:city":"Vernal",
    "sg:classifiers":[
        {
            "category":"Retail",
            "subcategory":"Portrait Studio",
            "type":"Services"
        }
    ],
    "sg:phone":"+1 435 781 2221",
    "sg:postcode":"84078",
    "sg:province":"UT",
    "sg:tags":[
        "photographer"
    ],
    "wof:name":"Digipix",
    "wof:placetype":"venue"
},
  "geometry": {"coordinates":[-109.52774100000001,40.455653],"type":"Point"}
}