{
  "type": "Feature",
  "properties": {
    "iso:country":"US",
    "sg:address":"210 S 300 E",
    "sg:city":"Provo",
    "sg:classifiers":[
        {
            "category":"Building & Trades",
            "subcategory":"Landscaping Services",
            "type":"Services"
        }
    ],
    "sg:phone":"+1 801 356 8653",
    "sg:postcode":"84606",
    "sg:province":"UT",
    "sg:tags":[
        "landscape"
    ],
    "wof:name":"Ruben Galea",
    "wof:placetype":"venue"
},
  "geometry": {"coordinates":[-111.65352900000001,40.229805],"type":"Point"}
}