{
  "type": "Feature",
  "properties": {
    "iso:country":"US",
    "sg:address":"5828 Harrison Blvd",
    "sg:city":"Ogden",
    "sg:classifiers":[
        {
            "category":"Freight",
            "type":"Transportation"
        }
    ],
    "sg:phone":"+1 801 475 9200",
    "sg:postcode":"84403",
    "sg:province":"UT",
    "sg:tags":[
        "commercial",
        "storage",
        "general"
    ],
    "wof:name":"Wildcat Self Storage",
    "wof:placetype":"venue"
},
  "geometry": {"coordinates":[-111.93967499999999,41.157332],"type":"Point"}
}