{
  "type": "Feature",
  "properties": {
    "iso:country":"US",
    "sg:address":"240 W 4050 N",
    "sg:city":"Ogden",
    "sg:classifiers":[
        {
            "category":"Shopping",
            "subcategory":"Clothing, Apparel, & Fashions",
            "type":"Retail Goods"
        }
    ],
    "sg:phone":"+1 801 782 0916",
    "sg:postcode":"84414",
    "sg:province":"UT",
    "wof:name":"Apple Blossom Boutique",
    "wof:placetype":"venue"
},
  "geometry": {"coordinates":[-111.982366,41.330092],"type":"Point"}
}