{
  "type": "Feature",
  "properties": {
    "iso:country":"US",
    "sg:address":"395 S 200 E",
    "sg:city":"Kanab",
    "sg:classifiers":[
        {
            "category":"Organizations",
            "subcategory":"Religious Organization",
            "type":"Services"
        }
    ],
    "sg:phone":"+1 435 644 2994",
    "sg:postcode":"84741",
    "sg:province":"UT",
    "wof:name":"New Hope Bible Church",
    "wof:placetype":"venue"
},
  "geometry": {"coordinates":[-112.524131,37.0429],"type":"Point"}
}