{
  "type": "Feature",
  "properties": {
    "iso:country":"US",
    "sg:address":"5300 S 900 E",
    "sg:city":"Salt Lake City",
    "sg:classifiers":[
        {
            "category":"Real Estate",
            "subcategory":"Real Estate Agent",
            "type":"Services"
        }
    ],
    "sg:phone":"+1 801 261 4114",
    "sg:postcode":"84117",
    "sg:province":"UT",
    "wof:name":"Ponderosa Realtors Inc",
    "wof:placetype":"venue"
},
  "geometry": {"coordinates":[-111.86600799999999,40.654748],"type":"Point"}
}