{
  "type": "Feature",
  "properties": {
    "iso:country":"US",
    "sg:address":"84 E Park Dr",
    "sg:city":"Kaysville",
    "sg:classifiers":[
        {
            "category":"Professional",
            "subcategory":"Computer Services",
            "type":"Services"
        }
    ],
    "sg:phone":"+1 801 546 1882",
    "sg:postcode":"84037",
    "sg:province":"UT",
    "sg:tags":[
        "company",
        "printing"
    ],
    "wof:name":"Reliable Business Systems",
    "wof:placetype":"venue"
},
  "geometry": {"coordinates":[-111.936381,41.015004],"type":"Point"}
}