{
  "type": "Feature",
  "properties": {
    "iso:country":"US",
    "sg:address":"9119 Daybreak Dr",
    "sg:city":"Sandy",
    "sg:classifiers":[
        {
            "category":"Building & Trades",
            "subcategory":"Landscaping Services",
            "type":"Services"
        }
    ],
    "sg:phone":"+1 801 733 5821",
    "sg:postcode":"84093",
    "sg:province":"UT",
    "sg:tags":[
        "landscape"
    ],
    "wof:name":"Grasshopper Landscape",
    "wof:placetype":"venue"
},
  "geometry": {"coordinates":[-111.826933,40.586577],"type":"Point"}
}