{
  "type": "Feature",
  "properties": {
    "iso:country":"US",
    "sg:address":"688 W 2050 N",
    "sg:city":"Clearfield",
    "sg:classifiers":[
        {
            "category":"Wholesale",
            "subcategory":"Machinery & Supplies",
            "type":"Manufacturing & Wholesale Goods"
        }
    ],
    "sg:phone":"+1 801 775 0341",
    "sg:postcode":"84015",
    "sg:province":"UT",
    "sg:tags":[
        "equipment",
        "household",
        "establishment"
    ],
    "wof:name":"Custom Central Vac",
    "wof:placetype":"venue"
},
  "geometry": {"coordinates":[-112.03864299999999,41.143158],"type":"Point"}
}