{
  "type": "Feature",
  "properties": {
    "iso:country":"US",
    "sg:address":"3069 W 13680 S",
    "sg:city":"Riverton",
    "sg:classifiers":[
        {
            "category":"Building & Trades",
            "subcategory":"Electrical",
            "type":"Services"
        }
    ],
    "sg:phone":"+1 801 446 6487",
    "sg:postcode":"84065",
    "sg:province":"UT",
    "sg:tags":[
        "electric",
        "contractor"
    ],
    "wof:name":"Silver Creek Electric",
    "wof:placetype":"venue"
},
  "geometry": {"coordinates":[-111.965315,40.502692],"type":"Point"}
}