{
  "type": "Feature",
  "properties": {
    "iso:country":"US",
    "sg:address":"280 E Main St",
    "sg:city":"Price",
    "sg:classifiers":[
        {
            "category":"Autos & Motor Vehicles",
            "subcategory":"Auto Supplies",
            "type":"Retail Goods"
        }
    ],
    "sg:phone":"+1 435 637 6100",
    "sg:postcode":"84501",
    "sg:province":"UT",
    "sg:tags":[
        "repair",
        "tire"
    ],
    "sg:website":"www.americancarcare.com",
    "wof:name":"Grako's American Car Care Ctr",
    "wof:placetype":"venue"
},
  "geometry": {"coordinates":[-110.805784,39.599492],"type":"Point"}
}