{
  "type": "Feature",
  "properties": {
    "iso:country":"US",
    "sg:address":"1277 W 12600 S",
    "sg:city":"Riverton",
    "sg:classifiers":[
        {
            "category":"Manufacturing",
            "subcategory":"Printing",
            "type":"Manufacturing & Wholesale Goods"
        }
    ],
    "sg:phone":"+1 801 254 5974",
    "sg:postcode":"84065",
    "sg:province":"UT",
    "sg:tags":[
        "newspaper"
    ],
    "wof:name":"Murray Journal",
    "wof:placetype":"venue"
},
  "geometry": {"coordinates":[-111.926526,40.522263],"type":"Point"}
}