{
  "type": "Feature",
  "properties": {
    "iso:country":"US",
    "sg:address":"4820 US Hwy 189",
    "sg:city":"Oakley",
    "sg:classifiers":[
        {
            "category":"Government",
            "subcategory":"Post Office",
            "type":"Public Place"
        }
    ],
    "sg:phone":"+1 435 783 5256",
    "sg:postcode":"84032",
    "sg:province":"UT",
    "wof:name":"US Post Office",
    "wof:placetype":"venue"
},
  "geometry": {"coordinates":[-111.427132,40.560288],"type":"Point"}
}