{
  "type": "Feature",
  "properties": {
    "iso:country":"US",
    "sg:address":"303 E Main St",
    "sg:city":"Delta",
    "sg:classifiers":[
        {
            "category":"Wholesale",
            "subcategory":"Electrical",
            "type":"Manufacturing & Wholesale Goods"
        },
        {
            "category":"Banks & Credit Unions",
            "subcategory":"Bank",
            "type":"Services"
        }
    ],
    "sg:phone":"+1 435 864 4177",
    "sg:postcode":"84624",
    "sg:province":"UT",
    "sg:tags":[
        "loan",
        "electronic",
        "real estate"
    ],
    "wof:name":"Premier Financial",
    "wof:placetype":"venue"
},
  "geometry": {"coordinates":[-112.566925,39.352384],"type":"Point"}
}