{
  "type": "Feature",
  "properties": {
    "iso:country":"US",
    "sg:address":"7847 Tynedale Ct",
    "sg:city":"Sandy",
    "sg:classifiers":[
        {
            "category":"Building & Trades",
            "subcategory":"Construction",
            "type":"Services"
        }
    ],
    "sg:phone":"+1 801 733 4333",
    "sg:postcode":"84093",
    "sg:province":"UT",
    "sg:tags":[
        "contractor"
    ],
    "wof:name":"Chytraus Building & Dev Corp",
    "wof:placetype":"venue"
},
  "geometry": {"coordinates":[-111.844677,40.608204],"type":"Point"}
}