{
  "type": "Feature",
  "properties": {
    "iso:country":"US",
    "sg:address":"969 Vine St",
    "sg:city":"Salt Lake City",
    "sg:classifiers":[
        {
            "category":"Building & Trades",
            "subcategory":"Construction",
            "type":"Services"
        }
    ],
    "sg:phone":"+1 801 266 3543",
    "sg:postcode":"84121",
    "sg:province":"UT",
    "sg:tags":[
        "contractor"
    ],
    "wof:name":"Larkin Masonry & Construction",
    "wof:placetype":"venue"
},
  "geometry": {"coordinates":[-111.86418500000001,40.641864],"type":"Point"}
}