{
  "type": "Feature",
  "properties": {
    "iso:country":"US",
    "sg:address":"780 State St",
    "sg:city":"Clearfield",
    "sg:classifiers":[
        {
            "category":"Personal",
            "subcategory":"Beauty Salon",
            "type":"Services"
        }
    ],
    "sg:phone":"+1 801 773 7813",
    "sg:postcode":"84015",
    "sg:province":"UT",
    "sg:tags":[
        "shop"
    ],
    "wof:name":"Hair Works",
    "wof:placetype":"venue"
},
  "geometry": {"coordinates":[-112.01445699999999,41.10271],"type":"Point"}
}