{
  "type": "Feature",
  "properties": {
    "iso:country":"US",
    "sg:address":"426 E Swenson Ave",
    "sg:city":"Springville",
    "sg:classifiers":[
        {
            "category":"Building & Trades",
            "subcategory":"Construction",
            "type":"Services"
        }
    ],
    "sg:phone":"+1 801 361 0445",
    "sg:postcode":"84663",
    "sg:province":"UT",
    "sg:tags":[
        "handyman"
    ],
    "wof:name":"Firefighter Handyman",
    "wof:placetype":"venue"
},
  "geometry": {"coordinates":[-111.598434,40.157561],"type":"Point"}
}