{
  "type": "Feature",
  "properties": {
    "iso:country":"US",
    "sg:address":"2247 Sunset Dr",
    "sg:city":"Lehi",
    "sg:classifiers":[
        {
            "category":"Building & Trades",
            "subcategory":"Construction",
            "type":"Services"
        }
    ],
    "sg:phone":"+1 801 768 1716",
    "sg:postcode":"84043",
    "sg:province":"UT",
    "sg:tags":[
        "contractor",
        "mfg"
    ],
    "wof:name":"Designer Strways Spclity Mllwk",
    "wof:placetype":"venue"
},
  "geometry": {"coordinates":[-111.863192,40.415336],"type":"Point"}
}