{
  "type": "Feature",
  "properties": {
    "iso:country":"US",
    "sg:address":"2549 S 550 E",
    "sg:city":"Bountiful",
    "sg:classifiers":[
        {
            "category":"Building & Trades",
            "subcategory":"Plumbing",
            "type":"Services"
        }
    ],
    "sg:phone":"+1 801 292 7062",
    "sg:postcode":"84010",
    "sg:province":"UT",
    "sg:tags":[
        "contractor"
    ],
    "wof:name":"Jerry Ledingham Plumbing",
    "wof:placetype":"venue"
},
  "geometry": {"coordinates":[-111.870028,40.862596],"type":"Point"}
}