{
  "type": "Feature",
  "properties": {
    "iso:country":"US",
    "sg:address":"865 Red Rock Rd",
    "sg:city":"St George",
    "sg:classifiers":[
        {
            "category":"Building & Trades",
            "subcategory":"Construction",
            "type":"Services"
        }
    ],
    "sg:phone":"+1 435 673 0981",
    "sg:postcode":"84770",
    "sg:province":"UT",
    "sg:tags":[
        "hanging",
        "contractor"
    ],
    "wof:name":"Wally Brown Painting",
    "wof:placetype":"venue"
},
  "geometry": {"coordinates":[-113.558316,37.121571],"type":"Point"}
}