{
  "type": "Feature",
  "properties": {
    "iso:country":"US",
    "sg:address":"689 S 75 E",
    "sg:city":"Cedar City",
    "sg:classifiers":[
        {
            "category":"Education",
            "subcategory":"Special Training",
            "type":"Public Place"
        }
    ],
    "sg:phone":"+1 435 586 7599",
    "sg:postcode":"84720",
    "sg:province":"UT",
    "sg:tags":[
        "center"
    ],
    "wof:name":"Learning Ladder",
    "wof:placetype":"venue"
},
  "geometry": {"coordinates":[-113.060135,37.664835],"type":"Point"}
}