{
  "type": "Feature",
  "properties": {
    "iso:country":"US",
    "sg:address":"645 W 200 N",
    "sg:city":"North Salt Lake",
    "sg:classifiers":[
        {
            "category":"Manufacturing",
            "subcategory":"Tools & Machinery",
            "type":"Manufacturing & Wholesale Goods"
        }
    ],
    "sg:phone":"+1 801 936 8082",
    "sg:postcode":"84054",
    "sg:province":"UT",
    "sg:tags":[
        "equipment",
        "commercial",
        "design",
        "calculating",
        "mfg"
    ],
    "wof:name":"Companion Systems",
    "wof:placetype":"venue"
},
  "geometry": {"coordinates":[-111.925635,40.846061],"type":"Point"}
}