{
  "type": "Feature",
  "properties": {
    "iso:country":"US",
    "sg:address":"450 W 870 S",
    "sg:city":"Orem",
    "sg:classifiers":[
        {
            "category":"Building & Trades",
            "subcategory":"Electrical",
            "type":"Services"
        }
    ],
    "sg:phone":"+1 801 226 5335",
    "sg:postcode":"84058",
    "sg:province":"UT",
    "sg:tags":[
        "electrical",
        "contractor"
    ],
    "wof:name":"Eurolectric Technologies Inc",
    "wof:placetype":"venue"
},
  "geometry": {"coordinates":[-111.70712,40.281555],"type":"Point"}
}