{
  "type": "Feature",
  "properties": {
    "iso:country":"US",
    "sg:address":"1330 W 3300 S",
    "sg:city":"Ogden",
    "sg:classifiers":[
        {
            "category":"Wholesale",
            "subcategory":"Home Furnishings",
            "type":"Manufacturing & Wholesale Goods"
        }
    ],
    "sg:phone":"+1 801 627 2450",
    "sg:postcode":"84401",
    "sg:province":"UT",
    "wof:name":"Levelor Home Fashions",
    "wof:placetype":"venue"
},
  "geometry": {"coordinates":[-112.012822,41.205237],"type":"Point"}
}