{
  "type": "Feature",
  "properties": {
    "iso:country":"US",
    "sg:address":"165 N 1330 W",
    "sg:city":"Orem",
    "sg:classifiers":[
        {
            "category":"Building & Trades",
            "subcategory":"Construction",
            "type":"Services"
        }
    ],
    "sg:phone":"+1 801 426 7883",
    "sg:postcode":"84057",
    "sg:province":"UT",
    "sg:tags":[
        "contractor"
    ],
    "wof:name":"Builders Sequoia",
    "wof:placetype":"venue"
},
  "geometry": {"coordinates":[-111.727447,40.297143],"type":"Point"}
}