{
  "type": "Feature",
  "properties": {
    "iso:country":"US",
    "sg:address":"11475 W 10400 N",
    "sg:city":"Tremonton",
    "sg:classifiers":[
        {
            "category":"Organizations",
            "subcategory":"Religious Organization",
            "type":"Services"
        }
    ],
    "sg:phone":"+1 435 854 3745",
    "sg:postcode":"84337",
    "sg:province":"UT",
    "sg:tags":[
        "church"
    ],
    "wof:name":"Church Of Jesus Christ Of Lds",
    "wof:placetype":"venue"
},
  "geometry": {"coordinates":[-112.294302,41.694233],"type":"Point"}
}