{
  "type": "Feature",
  "properties": {
    "iso:country":"US",
    "sg:address":"420 W 1500 S",
    "sg:city":"Bountiful",
    "sg:classifiers":[
        {
            "category":"Insurance",
            "subcategory":"Insurance Agent",
            "type":"Services"
        }
    ],
    "sg:phone":"+1 801 298 1856",
    "sg:postcode":"84010",
    "sg:province":"UT",
    "wof:name":"Prudential",
    "wof:placetype":"venue"
},
  "geometry": {"coordinates":[-111.889015,40.874817],"type":"Point"}
}