{
  "type": "Feature",
  "properties": {
    "iso:country":"US",
    "sg:address":"567 N 550 W",
    "sg:city":"Orem",
    "sg:classifiers":[
        {
            "category":"Building & Trades",
            "subcategory":"Construction",
            "type":"Services"
        }
    ],
    "sg:phone":"+1 801 224 8949",
    "sg:postcode":"84057",
    "sg:province":"UT",
    "sg:tags":[
        "excavation",
        "contractor"
    ],
    "wof:name":"Lone Star Excavation Inc",
    "wof:placetype":"venue"
},
  "geometry": {"coordinates":[-111.708997,40.306235],"type":"Point"}
}