{
  "type": "Feature",
  "properties": {
    "iso:country":"US",
    "sg:address":"35 S Main St",
    "sg:city":"Brigham City",
    "sg:classifiers":[
        {
            "category":"Personal",
            "subcategory":"Beauty Salon",
            "type":"Services"
        }
    ],
    "sg:phone":"+1 435 723 2854",
    "sg:postcode":"84302",
    "sg:province":"UT",
    "sg:tags":[
        "shop"
    ],
    "wof:name":"Robert's Hair Fashions",
    "wof:placetype":"venue"
},
  "geometry": {"coordinates":[-112.015687,41.50849],"type":"Point"}
}