{
  "type": "Feature",
  "properties": {
    "iso:country":"US",
    "sg:address":"928 W South Temple",
    "sg:city":"Salt Lake City",
    "sg:classifiers":[
        {
            "category":"Wholesale",
            "subcategory":"Machinery & Supplies",
            "type":"Manufacturing & Wholesale Goods"
        }
    ],
    "sg:phone":"+1 801 355 4171",
    "sg:postcode":"84104",
    "sg:province":"UT",
    "wof:name":"R V Specialties Inc",
    "wof:placetype":"venue"
},
  "geometry": {"coordinates":[-111.917651,40.76941],"type":"Point"}
}