{
  "type": "Feature",
  "properties": {
    "iso:country":"US",
    "sg:address":"420 S 800 E",
    "sg:city":"Salt Lake City",
    "sg:classifiers":[
        {
            "category":"Organizations",
            "subcategory":"Religious Organization",
            "type":"Services"
        }
    ],
    "sg:phone":"+1 801 578 6717",
    "sg:postcode":"84102",
    "sg:province":"UT",
    "sg:tags":[
        "church"
    ],
    "wof:name":"Church Of Jesus Christ Of Lds",
    "wof:placetype":"venue"
},
  "geometry": {"coordinates":[-111.868268,40.758927],"type":"Point"}
}