{
  "type": "Feature",
  "properties": {
    "iso:country":"US",
    "sg:address":"2239 S 1520 W",
    "sg:city":"Syracuse",
    "sg:classifiers":[
        {
            "category":"Recreation",
            "type":"Entertainment"
        }
    ],
    "sg:phone":"+1 801 773 7563",
    "sg:postcode":"84075",
    "sg:province":"UT",
    "wof:name":"Lane Memory Custom Cake",
    "wof:placetype":"venue"
},
  "geometry": {"coordinates":[-112.055829,41.082744],"type":"Point"}
}