{
  "type": "Feature",
  "properties": {
    "iso:country":"US",
    "sg:address":"11442 Mayberry Ct",
    "sg:city":"Draper",
    "sg:classifiers":[
        {
            "category":"Building & Trades",
            "subcategory":"Landscaping Services",
            "type":"Services"
        }
    ],
    "sg:phone":"+1 801 523 0457",
    "sg:postcode":"84020",
    "sg:province":"UT",
    "wof:name":"Wells Lawncare",
    "wof:placetype":"venue"
},
  "geometry": {"coordinates":[-111.884626,40.543244],"type":"Point"}
}