{
  "type": "Feature",
  "properties": {
    "iso:country":"US",
    "sg:address":"7504 Blackfriar Cir",
    "sg:city":"West Jordan",
    "sg:classifiers":[
        {
            "category":"Building & Trades",
            "subcategory":"Landscaping Services",
            "type":"Services"
        }
    ],
    "sg:phone":"+1 801 561 4926",
    "sg:postcode":"84084",
    "sg:province":"UT",
    "sg:tags":[
        "landscape"
    ],
    "wof:name":"Mangum Yard Care",
    "wof:placetype":"venue"
},
  "geometry": {"coordinates":[-111.96843800000001,40.615385],"type":"Point"}
}