{
  "type": "Feature",
  "properties": {
    "iso:country":"US",
    "sg:address":"1752 W 800 S",
    "sg:city":"Orem",
    "sg:classifiers":[
        {
            "category":"Building & Trades",
            "subcategory":"Plumbing",
            "type":"Services"
        }
    ],
    "sg:phone":"+1 801 426 4532",
    "sg:postcode":"84058",
    "sg:province":"UT",
    "sg:tags":[
        "contractor"
    ],
    "wof:name":"Millenergy LLC",
    "wof:placetype":"venue"
},
  "geometry": {"coordinates":[-111.736856,40.281628],"type":"Point"}
}