{
  "type": "Feature",
  "properties": {
    "iso:country":"US",
    "sg:address":"576 E 1840 N",
    "sg:city":"Orem",
    "sg:classifiers":[
        {
            "category":"Professional",
            "subcategory":"Business Services",
            "type":"Services"
        }
    ],
    "sg:phone":"+1 801 226 3879",
    "sg:postcode":"84097",
    "sg:province":"UT",
    "wof:name":"Nut Craker Enterprises Ltd",
    "wof:placetype":"venue"
},
  "geometry": {"coordinates":[-111.684462,40.330667],"type":"Point"}
}