{
  "type": "Feature",
  "properties": {
    "iso:country":"US",
    "sg:address":"929 Wellspring Rd",
    "sg:city":"Midvale",
    "sg:classifiers":[
        {
            "category":"Professional",
            "subcategory":"Computer Services",
            "type":"Services"
        }
    ],
    "sg:phone":"+1 801 631 5155",
    "sg:postcode":"84047",
    "sg:province":"UT",
    "sg:tags":[
        "datum"
    ],
    "wof:name":"Raptor Graphix",
    "wof:placetype":"venue"
},
  "geometry": {"coordinates":[-111.86219699999999,40.626491],"type":"Point"}
}