{
  "type": "Feature",
  "properties": {
    "iso:country":"US",
    "sg:address":"3014 Fawn Dr",
    "sg:city":"Park City",
    "sg:classifiers":[
        {
            "category":"Organizations",
            "subcategory":"Community Association",
            "type":"Services"
        }
    ],
    "sg:phone":"+1 435 645 5350",
    "sg:postcode":"84098",
    "sg:province":"UT",
    "sg:tags":[
        "club"
    ],
    "wof:name":"Park City Mountain Sports Club",
    "wof:placetype":"venue"
},
  "geometry": {"coordinates":[-111.569864,40.744178],"type":"Point"}
}