{
  "type": "Feature",
  "properties": {
    "iso:country":"US",
    "sg:address":"415 State Rte 10",
    "sg:city":"Huntington",
    "sg:classifiers":[
        {
            "category":"Mining & Drilling",
            "type":"Manufacturing & Wholesale Goods"
        }
    ],
    "sg:phone":"+1 435 687 9792",
    "sg:postcode":"84528",
    "sg:province":"UT",
    "sg:tags":[
        "gypsum",
        "milling"
    ],
    "wof:name":"Gypsum Resource Development",
    "wof:placetype":"venue"
},
  "geometry": {"coordinates":[-110.96462200000001,39.333935],"type":"Point"}
}