{
  "type": "Feature",
  "properties": {
    "iso:country":"US",
    "sg:address":"2456 W 1425 S",
    "sg:city":"Syracuse",
    "sg:classifiers":[
        {
            "category":"Building & Trades",
            "subcategory":"Construction",
            "type":"Services"
        }
    ],
    "sg:phone":"+1 801 773 6392",
    "sg:postcode":"84075",
    "sg:province":"UT",
    "sg:tags":[
        "concrete",
        "contractor"
    ],
    "wof:name":"Vintage Concrete Construction",
    "wof:placetype":"venue"
},
  "geometry": {"coordinates":[-112.073149,41.093142],"type":"Point"}
}