{
  "type": "Feature",
  "properties": {
    "iso:country":"US",
    "sg:address":"1850 W 1500 S",
    "sg:city":"Salt Lake City",
    "sg:classifiers":[
        {
            "category":"Wholesale",
            "subcategory":"Non-durable Goods",
            "type":"Manufacturing & Wholesale Goods"
        }
    ],
    "sg:phone":"+1 801 956 0300",
    "sg:postcode":"84104",
    "sg:province":"UT",
    "sg:tags":[
        "rubber",
        "sponge"
    ],
    "wof:name":"G & M Mattress & Foam",
    "wof:placetype":"venue"
},
  "geometry": {"coordinates":[-111.940269,40.737717],"type":"Point"}
}