{
  "type": "Feature",
  "properties": {
    "iso:country":"US",
    "sg:address":"153 E 2550 N",
    "sg:city":"Ogden",
    "sg:classifiers":[
        {
            "category":"Wholesale",
            "subcategory":"Farm Supplies",
            "type":"Manufacturing & Wholesale Goods"
        }
    ],
    "sg:phone":"+1 801 782 4465",
    "sg:postcode":"84414",
    "sg:province":"UT",
    "sg:tags":[
        "raw",
        "product",
        "material"
    ],
    "wof:name":"Shooting Star Ranch",
    "wof:placetype":"venue"
},
  "geometry": {"coordinates":[-111.977378,41.304024],"type":"Point"}
}