{
  "type": "Feature",
  "properties": {
    "iso:country":"US",
    "sg:address":"1338 Green St",
    "sg:city":"Salt Lake City",
    "sg:classifiers":[
        {
            "category":"Professional",
            "subcategory":"Secretarial Services",
            "type":"Services"
        }
    ],
    "sg:phone":"+1 801 466 8887",
    "sg:postcode":"84105",
    "sg:province":"UT",
    "sg:tags":[
        "reporting"
    ],
    "wof:name":"MTS",
    "wof:placetype":"venue"
},
  "geometry": {"coordinates":[-111.872236,40.741082],"type":"Point"}
}