{
  "type": "Feature",
  "properties": {
    "iso:country":"US",
    "sg:address":"147 S 200 W",
    "sg:city":"Richfield",
    "sg:classifiers":[
        {
            "category":"Arena",
            "subcategory":"Sports Club",
            "type":"Entertainment"
        }
    ],
    "sg:phone":"+1 435 896 8087",
    "sg:postcode":"84701",
    "sg:province":"UT",
    "wof:name":"Race Association Skaters Etc",
    "wof:placetype":"venue"
},
  "geometry": {"coordinates":[-112.088302,38.766029],"type":"Point"}
}