{
  "type": "Feature",
  "properties": {
    "iso:country":"US",
    "sg:address":"1327 Diane Dr",
    "sg:city":"Salt Lake City",
    "sg:classifiers":[
        {
            "category":"Freight",
            "type":"Transportation"
        }
    ],
    "sg:phone":"+1 801 262 1327",
    "sg:postcode":"84123",
    "sg:province":"UT",
    "sg:tags":[
        "local",
        "except",
        "trucking"
    ],
    "wof:name":"Dick Madsen Transport",
    "wof:placetype":"venue"
},
  "geometry": {"coordinates":[-111.930177,40.648273],"type":"Point"}
}