{
  "type": "Feature",
  "properties": {
    "iso:country":"US",
    "sg:address":"6477 Indian Hollow Ln",
    "sg:city":"Herriman",
    "sg:classifiers":[
        {
            "category":"Building & Trades",
            "subcategory":"Construction",
            "type":"Services"
        }
    ],
    "sg:phone":"+1 801 253 9290",
    "sg:postcode":"84096",
    "sg:province":"UT",
    "sg:tags":[
        "concrete",
        "restoration",
        "cleaning",
        "repair"
    ],
    "wof:name":"Yard Vision",
    "wof:placetype":"venue"
},
  "geometry": {"coordinates":[-112.046633,40.494923],"type":"Point"}
}