{
  "type": "Feature",
  "properties": {
    "iso:country":"US",
    "sg:address":"3612 W 2100 S",
    "sg:city":"Salt Lake City",
    "sg:classifiers":[
        {
            "category":"Building & Trades",
            "subcategory":"Construction",
            "type":"Services"
        }
    ],
    "sg:phone":"+1 801 954 8401",
    "sg:postcode":"84120",
    "sg:province":"UT",
    "sg:tags":[
        "general",
        "contractor"
    ],
    "wof:name":"Turner Construction Company",
    "wof:placetype":"venue"
},
  "geometry": {"coordinates":[-111.977411,40.726204],"type":"Point"}
}