{
  "type": "Feature",
  "properties": {
    "iso:country":"US",
    "sg:address":"235 E Main St",
    "sg:city":"American Fork",
    "sg:classifiers":[
        {
            "category":"Health Services",
            "subcategory":"Doctor",
            "type":"Services"
        }
    ],
    "sg:phone":"+1 801 763 9696",
    "sg:postcode":"84003",
    "sg:province":"UT",
    "sg:tags":[
        "physician",
        "surgeon"
    ],
    "wof:name":"Robert C Richards MD",
    "wof:placetype":"venue"
},
  "geometry": {"coordinates":[-111.791282,40.376819],"type":"Point"}
}