{
  "type": "Feature",
  "properties": {
    "iso:country":"US",
    "sg:address":"161 N 700 W",
    "sg:city":"Cedar City",
    "sg:classifiers":[
        {
            "category":"Real Estate",
            "subcategory":"Real Estate Agent",
            "type":"Services"
        }
    ],
    "sg:phone":"+1 435 586 6944",
    "sg:postcode":"84720",
    "sg:province":"UT",
    "wof:name":"Iron County Board Of Realtors",
    "wof:placetype":"venue"
},
  "geometry": {"coordinates":[-113.07279800000001,37.680137],"type":"Point"}
}