{
  "type": "Feature",
  "properties": {
    "iso:country":"US",
    "sg:address":"3290 W 3500 S",
    "sg:city":"Heber City",
    "sg:phone":"+1 435 654 1843",
    "sg:postcode":"84032",
    "sg:province":"UT",
    "sg:tags":[
        "farm",
        "field",
        "crop",
        "general"
    ],
    "wof:name":"Cjp Family 2 LLC",
    "wof:placetype":"venue"
},
  "geometry": {"coordinates":[-111.466611,40.464624],"type":"Point"}
}