{
  "type": "Feature",
  "properties": {
    "iso:country":"US",
    "sg:address":"5918 W 9960 N",
    "sg:city":"American Fork",
    "sg:classifiers":[
        {
            "category":"Building & Trades",
            "subcategory":"Construction",
            "type":"Services"
        }
    ],
    "sg:phone":"+1 801 756 1541",
    "sg:postcode":"84003",
    "sg:province":"UT",
    "sg:tags":[
        "builder",
        "stair",
        "contractor"
    ],
    "wof:name":"Quality Stair Installations",
    "wof:placetype":"venue"
},
  "geometry": {"coordinates":[-111.800792,40.412891],"type":"Point"}
}