{
  "type": "Feature",
  "properties": {
    "iso:country":"US",
    "sg:address":"4722 S 4015 W",
    "sg:city":"Kearns",
    "sg:classifiers":[
        {
            "category":"Restaurant",
            "type":"Food & Drink"
        }
    ],
    "sg:phone":"+1 801 964 1553",
    "sg:postcode":"84118",
    "sg:province":"UT",
    "wof:name":"Acapulco Restaurant",
    "wof:placetype":"venue"
},
  "geometry": {"coordinates":[-111.986088,40.667575],"type":"Point"}
}