{
  "type": "Feature",
  "properties": {
    "iso:country":"US",
    "sg:address":"391 Walker St",
    "sg:city":"Moab",
    "sg:classifiers":[
        {
            "category":"Utilities",
            "subcategory":"Telephone",
            "type":"Services"
        }
    ],
    "sg:phone":"+1 435 259 6644",
    "sg:postcode":"84532",
    "sg:province":"UT",
    "sg:tags":[
        "communications",
        "company"
    ],
    "wof:name":"Canyonlands Telephone Center",
    "wof:placetype":"venue"
},
  "geometry": {"coordinates":[-109.535267,38.566975],"type":"Point"}
}