{
  "type": "Feature",
  "properties": {
    "iso:country":"US",
    "sg:address":"4487 W 2575 N",
    "sg:city":"Ogden",
    "sg:classifiers":[
        {
            "category":"Professional",
            "subcategory":"Management & Consulting",
            "type":"Services"
        }
    ],
    "sg:phone":"+1 801 732 0932",
    "sg:postcode":"84404",
    "sg:province":"UT",
    "sg:tags":[
        "business"
    ],
    "wof:name":"Keyway Strategies",
    "wof:placetype":"venue"
},
  "geometry": {"coordinates":[-112.08654900000001,41.304671],"type":"Point"}
}