{
  "type": "Feature",
  "properties": {
    "iso:country":"US",
    "sg:address":"770 W 210 S",
    "sg:city":"Orem",
    "sg:classifiers":[
        {
            "category":"Professional",
            "subcategory":"Computer Services",
            "type":"Services"
        }
    ],
    "sg:phone":"+1 801 225 7975",
    "sg:postcode":"84058",
    "sg:province":"UT",
    "sg:tags":[
        "programing",
        "custom"
    ],
    "wof:name":"Lan Fan Technology",
    "wof:placetype":"venue"
},
  "geometry": {"coordinates":[-111.71393999999999,40.293446],"type":"Point"}
}