{
  "type": "Feature",
  "properties": {
    "iso:country":"US",
    "sg:address":"1023 Mecham Ln",
    "sg:city":"Midvale",
    "sg:classifiers":[
        {
            "category":"Wholesale",
            "subcategory":"Machinery & Supplies",
            "type":"Manufacturing & Wholesale Goods"
        }
    ],
    "sg:phone":"+1 801 566 7888",
    "sg:postcode":"84047",
    "sg:province":"UT",
    "sg:tags":[
        "equipment",
        "industrial"
    ],
    "wof:name":"Crown Litho Supply Inc",
    "wof:placetype":"venue"
},
  "geometry": {"coordinates":[-111.858276,40.613775],"type":"Point"}
}