{
  "type": "Feature",
  "properties": {
    "iso:country":"US",
    "sg:address":"10247 Vilas Dr",
    "sg:city":"Sandy",
    "sg:classifiers":[
        {
            "category":"Professional",
            "subcategory":"Management & Consulting",
            "type":"Services"
        }
    ],
    "sg:phone":"+1 801 942 9923",
    "sg:postcode":"84092",
    "sg:province":"UT",
    "sg:tags":[
        "medical",
        "administration",
        "business"
    ],
    "wof:name":"Carepoint Network Inc",
    "wof:placetype":"venue"
},
  "geometry": {"coordinates":[-111.82541500000001,40.565028],"type":"Point"}
}