{
  "type": "Feature",
  "properties": {
    "iso:country":"US",
    "sg:address":"124 S 600 W",
    "sg:city":"Logan",
    "sg:classifiers":[
        {
            "category":"Professional",
            "subcategory":"Advertising",
            "type":"Services"
        }
    ],
    "sg:phone":"+1 435 787 9800",
    "sg:postcode":"84321",
    "sg:province":"UT",
    "sg:tags":[
        "mail",
        "mailing",
        "direct",
        "shipping"
    ],
    "wof:name":"Mailing Dynamics Corp",
    "wof:placetype":"venue"
},
  "geometry": {"coordinates":[-111.84981999999999,41.729229],"type":"Point"}
}