{
  "type": "Feature",
  "properties": {
    "iso:country":"US",
    "sg:address":"3454 W 8600 S",
    "sg:city":"West Jordan",
    "sg:classifiers":[
        {
            "category":"Freight",
            "type":"Transportation"
        }
    ],
    "sg:phone":"+1 801 563 0100",
    "sg:postcode":"84088",
    "sg:province":"UT",
    "sg:tags":[
        "operator",
        "trucking"
    ],
    "wof:name":"Savannah Transport Inc",
    "wof:placetype":"venue"
},
  "geometry": {"coordinates":[-111.971062,40.595181],"type":"Point"}
}