{
  "type": "Feature",
  "properties": {
    "iso:country":"US",
    "sg:address":"2107 W 3500 S",
    "sg:city":"Salt Lake City",
    "sg:classifiers":[
        {
            "category":"Health Services",
            "subcategory":"Clinic",
            "type":"Services"
        }
    ],
    "sg:phone":"+1 801 973 9675",
    "sg:postcode":"84119",
    "sg:province":"UT",
    "wof:name":"Planned Parenthood Assn Utah",
    "wof:placetype":"venue"
},
  "geometry": {"coordinates":[-111.947213,40.696657],"type":"Point"}
}