{
  "type": "Feature",
  "properties": {
    "iso:country":"US",
    "sg:address":"2712 Industrial Dr",
    "sg:city":"Ogden",
    "sg:classifiers":[
        {
            "category":"Professional",
            "subcategory":"Management & Consulting",
            "type":"Services"
        }
    ],
    "sg:phone":"+1 801 546 3180",
    "sg:postcode":"84401",
    "sg:province":"UT",
    "sg:tags":[
        "electrical",
        "contractor"
    ],
    "wof:name":"Mountain States Electric Inc",
    "wof:placetype":"venue"
},
  "geometry": {"coordinates":[-112.013149,41.21668],"type":"Point"}
}