{
  "type": "Feature",
  "properties": {
    "iso:country":"US",
    "sg:address":"5577 Wells Park Rd",
    "sg:city":"West Jordan",
    "sg:classifiers":[
        {
            "category":"Manufacturing",
            "subcategory":"Tools & Machinery",
            "type":"Manufacturing & Wholesale Goods"
        }
    ],
    "sg:phone":"+1 801 280 4738",
    "sg:postcode":"84088",
    "sg:province":"UT",
    "sg:tags":[
        "repair",
        "industrial",
        "electrical",
        "mfg"
    ],
    "wof:name":"Kyden Machine Inc",
    "wof:placetype":"venue"
},
  "geometry": {"coordinates":[-112.023825,40.577089],"type":"Point"}
}