{
  "type": "Feature",
  "properties": {
    "iso:country":"US",
    "sg:address":"1501 Spring Leaf Dr",
    "sg:city":"Salt Lake City",
    "sg:classifiers":[
        {
            "category":"Professional",
            "subcategory":"Management & Consulting",
            "type":"Services"
        }
    ],
    "sg:phone":"+1 801 272 3651",
    "sg:postcode":"84117",
    "sg:province":"UT",
    "sg:tags":[
        "business"
    ],
    "wof:name":"Nell Bonnie Consultant",
    "wof:placetype":"venue"
},
  "geometry": {"coordinates":[-111.848597,40.656818],"type":"Point"}
}