{
  "type": "Feature",
  "properties": {
    "iso:country":"US",
    "sg:address":"7336 S Winesap Cir",
    "sg:city":"Salt Lake City",
    "sg:classifiers":[
        {
            "category":"Professional",
            "type":"Services"
        }
    ],
    "sg:phone":"+1 801 944 1954",
    "sg:postcode":"84121",
    "sg:province":"UT",
    "wof:name":"L C Garden Thyme",
    "wof:placetype":"venue"
},
  "geometry": {"coordinates":[-111.792886,40.617761],"type":"Point"}
}