{
  "type": "Feature",
  "properties": {
    "iso:country":"US",
    "sg:address":"715 E 3900 S",
    "sg:city":"Salt Lake City",
    "sg:classifiers":[
        {
            "category":"Health Services",
            "subcategory":"Optometrist",
            "type":"Services"
        }
    ],
    "sg:phone":"+1 801 263 3698",
    "sg:postcode":"84107",
    "sg:province":"UT",
    "wof:name":"Kris Hill Od",
    "wof:placetype":"venue"
},
  "geometry": {"coordinates":[-111.869347,40.687138],"type":"Point"}
}