{
  "type": "Feature",
  "properties": {
    "iso:country":"US",
    "sg:address":"188 E Center St",
    "sg:city":"Heber City",
    "sg:classifiers":[
        {
            "category":"Professional",
            "type":"Services"
        }
    ],
    "sg:phone":"+1 435 657 1708",
    "sg:postcode":"84032",
    "sg:province":"UT",
    "wof:name":"Du Huh Designs Inc",
    "wof:placetype":"venue"
},
  "geometry": {"coordinates":[-111.410129,40.507532],"type":"Point"}
}