{
  "type": "Feature",
  "properties": {
    "iso:country":"US",
    "sg:address":"10529 N 6400 W",
    "sg:city":"Highland",
    "sg:classifiers":[
        {
            "category":"Building & Trades",
            "subcategory":"Construction",
            "type":"Services"
        }
    ],
    "sg:phone":"+1 801 763 5884",
    "sg:postcode":"84003",
    "sg:province":"UT",
    "sg:tags":[
        "siding",
        "contractor"
    ],
    "wof:name":"JBL Construction & Exteriors",
    "wof:placetype":"venue"
},
  "geometry": {"coordinates":[-111.81170400000001,40.423162],"type":"Point"}
}