{
  "type": "Feature",
  "properties": {
    "iso:country":"US",
    "sg:address":"1800 S West Temple St",
    "sg:city":"Salt Lake City",
    "sg:classifiers":[
        {
            "category":"Professional",
            "subcategory":"Computer Services",
            "type":"Services"
        },
        {
            "category":"Manufacturing",
            "subcategory":"Printing",
            "type":"Manufacturing & Wholesale Goods"
        }
    ],
    "sg:phone":"+1 801 466 9222",
    "sg:postcode":"84115",
    "sg:province":"UT",
    "sg:tags":[
        "development",
        "multimedia",
        "software"
    ],
    "sg:website":"www.freegameoffer.com",
    "wof:name":"Oquirrh Productions",
    "wof:placetype":"venue"
},
  "geometry": {"coordinates":[-111.893935,40.730451],"type":"Point"}
}