{
  "type": "Feature",
  "properties": {
    "iso:country":"US",
    "sg:address":"2188 S 1000 E",
    "sg:city":"Salt Lake City",
    "sg:classifiers":[
        {
            "category":"Home & Garden",
            "subcategory":"Home Furnishings",
            "type":"Retail Goods"
        }
    ],
    "sg:phone":"+1 801 487 9666",
    "sg:postcode":"84106",
    "sg:province":"UT",
    "wof:name":"Clean Blind & Repair",
    "wof:placetype":"venue"
},
  "geometry": {"coordinates":[-111.862753,40.723265],"type":"Point"}
}