{
  "type": "Feature",
  "properties": {
    "iso:country":"US",
    "sg:address":"2975 W 300 N",
    "sg:city":"Lehi",
    "sg:classifiers":[
        {
            "category":"Professional",
            "subcategory":"Lawyer & Legal Services",
            "type":"Services"
        }
    ],
    "sg:phone":"+1 801 990 1919",
    "sg:postcode":"84043",
    "sg:province":"UT",
    "sg:tags":[
        "attorney"
    ],
    "sg:website":"www.keithbartonlaw.com",
    "wof:name":"J Craig Swapp Law Offices",
    "wof:placetype":"venue"
},
  "geometry": {"coordinates":[-111.900837,40.391354],"type":"Point"}
}