{
  "type": "Feature",
  "properties": {
    "iso:country":"US",
    "sg:address":"575 Bulrush Way",
    "sg:city":"Salt Lake City",
    "sg:classifiers":[
        {
            "category":"Professional",
            "subcategory":"Accounting & Tax Preparation",
            "type":"Services"
        }
    ],
    "sg:phone":"+1 801 486 6145",
    "sg:postcode":"84106",
    "sg:province":"UT",
    "wof:name":"ABC Accounting",
    "wof:placetype":"venue"
},
  "geometry": {"coordinates":[-111.874843,40.700486],"type":"Point"}
}