{
  "type": "Feature",
  "properties": {
    "iso:country":"US",
    "sg:address":"314 W 650 S",
    "sg:city":"Bountiful",
    "sg:classifiers":[
        {
            "category":"Real Estate",
            "subcategory":"Real Estate Operator",
            "type":"Services"
        }
    ],
    "sg:phone":"+1 801 295 4781",
    "sg:postcode":"84010",
    "sg:province":"UT",
    "sg:tags":[
        "apartment"
    ],
    "wof:name":"Chateau Park Apartments",
    "wof:placetype":"venue"
},
  "geometry": {"coordinates":[-111.888,40.882401],"type":"Point"}
}