{
  "type": "Feature",
  "properties": {
    "iso:country":"US",
    "sg:address":"738 Main St",
    "sg:city":"Park City",
    "sg:classifiers":[
        {
            "category":"Coffee & Tea",
            "type":"Food & Drink"
        },
        {
            "category":"Internet Cafe",
            "type":"Food & Drink"
        }
    ],
    "sg:menulink":"http://www.allmenus.com/ut/park-city/61297-alpine-internet-cafe/menu/",
    "sg:phone":"+1 435 649 0051",
    "sg:postcode":"84060",
    "sg:province":"UT",
    "sg:tags":[
        "american"
    ],
    "wof:name":"Alpine Internet Cafe",
    "wof:placetype":"venue"
},
  "geometry": {"coordinates":[-111.49622599999999,40.644347],"type":"Point"}
}