{
  "type": "Feature",
  "properties": {
    "iso:country":"US",
    "sg:address":"1338 Santa Clara Pkwy",
    "sg:city":"Santa Clara",
    "sg:classifiers":[
        {
            "category":"Insurance",
            "subcategory":"Insurance Agent",
            "type":"Services"
        }
    ],
    "sg:phone":"+1 435 673 5343",
    "sg:postcode":"84765",
    "sg:province":"UT",
    "wof:name":"Leann Nebeker",
    "wof:placetype":"venue"
},
  "geometry": {"coordinates":[-113.642206,37.131817],"type":"Point"}
}