{
  "type": "Feature",
  "properties": {
    "iso:country":"US",
    "sg:address":"4832 Highland Dr",
    "sg:city":"Salt Lake City",
    "sg:classifiers":[
        {
            "category":"Shopping",
            "subcategory":"Jewelry",
            "type":"Retail Goods"
        }
    ],
    "sg:phone":"+1 801 274 2029",
    "sg:postcode":"84117",
    "sg:province":"UT",
    "sg:tags":[
        "jeweler"
    ],
    "wof:name":"Wrapz Jewelry",
    "wof:placetype":"venue"
},
  "geometry": {"coordinates":[-111.83918,40.66481],"type":"Point"}
}