{
  "type": "Feature",
  "properties": {
    "iso:country":"US",
    "sg:address":"9025 S 2100 E",
    "sg:city":"Sandy",
    "sg:classifiers":[
        {
            "category":"Building & Trades",
            "subcategory":"Construction",
            "type":"Services"
        }
    ],
    "sg:phone":"+1 801 453 9914",
    "sg:postcode":"84093",
    "sg:province":"UT",
    "sg:tags":[
        "designer",
        "dealer",
        "pool",
        "swimming"
    ],
    "wof:name":"Pond Pool & Spa Waterworks Inc",
    "wof:placetype":"venue"
},
  "geometry": {"coordinates":[-111.830832,40.587502],"type":"Point"}
}