{
  "type": "Feature",
  "properties": {
    "iso:country":"US",
    "sg:address":"2934 N 725 W",
    "sg:city":"Layton",
    "sg:classifiers":[
        {
            "category":"Freight",
            "type":"Transportation"
        }
    ],
    "sg:phone":"+1 801 776 3644",
    "sg:postcode":"84041",
    "sg:province":"UT",
    "sg:tags":[
        "operator",
        "local",
        "trucking"
    ],
    "wof:name":"Mountainsyde Hauling Inc",
    "wof:placetype":"venue"
},
  "geometry": {"coordinates":[-111.97927,41.102477],"type":"Point"}
}