{
  "type": "Feature",
  "properties": {
    "iso:country":"US",
    "sg:address":"2700 S 900 W",
    "sg:city":"Salt Lake City",
    "sg:classifiers":[
        {
            "category":"Manufacturing",
            "subcategory":"Rubber & Plastics",
            "type":"Manufacturing & Wholesale Goods"
        }
    ],
    "sg:phone":"+1 801 355 2705",
    "sg:postcode":"84119",
    "sg:province":"UT",
    "sg:website":"www.utahplasticsgroup.com",
    "wof:name":"Utah Plastics Group Inc",
    "wof:placetype":"venue"
},
  "geometry": {"coordinates":[-111.917265,40.713666],"type":"Point"}
}