{
  "type": "Feature",
  "properties": {
    "iso:country":"US",
    "sg:address":"1415 N 400 E",
    "sg:city":"Logan",
    "sg:classifiers":[
        {
            "category":"Health Services",
            "subcategory":"Chiropractor",
            "type":"Services"
        }
    ],
    "sg:phone":"+1 435 753 2840",
    "sg:postcode":"84341",
    "sg:province":"UT",
    "wof:name":"Peterson Chiropractic",
    "wof:placetype":"venue"
},
  "geometry": {"coordinates":[-111.82406400000001,41.758709],"type":"Point"}
}