{
  "type": "Feature",
  "properties": {
    "iso:country":"US",
    "sg:address":"60 W Center St",
    "sg:city":"Venice",
    "sg:classifiers":[
        {
            "category":"Education",
            "subcategory":"School",
            "type":"Public Place"
        }
    ],
    "sg:phone":"+1 435 896 8776",
    "sg:postcode":"84701",
    "sg:province":"UT",
    "sg:tags":[
        "academic",
        "special"
    ],
    "wof:name":"Sevier District Preschool",
    "wof:placetype":"venue"
},
  "geometry": {"coordinates":[-112.085812,38.768133],"type":"Point"}
}