{
  "type": "Feature",
  "properties": {
    "iso:country":"US",
    "sg:address":"1395 E 1600 S",
    "sg:city":"Mapleton",
    "sg:classifiers":[
        {
            "category":"Real Estate",
            "subcategory":"Real Estate Agent",
            "type":"Services"
        }
    ],
    "sg:phone":"+1 801 836 4677",
    "sg:postcode":"84664",
    "sg:province":"UT",
    "wof:name":"Blackhawk Realty",
    "wof:placetype":"venue"
},
  "geometry": {"coordinates":[-111.564256,40.116052],"type":"Point"}
}