{
  "type": "Feature",
  "properties": {
    "iso:country":"US",
    "sg:address":"4342 Harrison Blvd",
    "sg:city":"Ogden",
    "sg:classifiers":[
        {
            "category":"Restaurant",
            "type":"Food & Drink"
        }
    ],
    "sg:phone":"+1 801 627 8000",
    "sg:postcode":"84403",
    "sg:province":"UT",
    "sg:tags":[
        "pizzeria"
    ],
    "wof:name":"San Francisco Sourdough Pizza",
    "wof:placetype":"venue"
},
  "geometry": {"coordinates":[-111.949021,41.183253],"type":"Point"}
}