{
  "type": "Feature",
  "properties": {
    "iso:country":"US",
    "sg:address":"478 W 1420 S",
    "sg:city":"Cedar City",
    "sg:classifiers":[
        {
            "category":"Insurance",
            "subcategory":"Insurance Agent",
            "type":"Services"
        }
    ],
    "sg:phone":"+1 916 852 6447",
    "sg:postcode":"84720",
    "sg:province":"UT",
    "wof:name":"Jeffrey D Peterson Insur Svcs",
    "wof:placetype":"venue"
},
  "geometry": {"coordinates":[-113.069841,37.651788],"type":"Point"}
}