{
  "type": "Feature",
  "properties": {
    "iso:country":"US",
    "sg:address":"1882 S West Temple",
    "sg:city":"Salt Lake City",
    "sg:classifiers":[
        {
            "category":"Real Estate",
            "subcategory":"Real Estate Operator",
            "type":"Services"
        }
    ],
    "sg:phone":"+1 801 485 5712",
    "sg:postcode":"84115",
    "sg:province":"UT",
    "sg:tags":[
        "apartment"
    ],
    "wof:name":"Hidden Villa Apartments",
    "wof:placetype":"venue"
},
  "geometry": {"coordinates":[-111.89400999999999,40.729121],"type":"Point"}
}