{
  "type": "Feature",
  "properties": {
    "iso:country":"US",
    "sg:address":"800 S Oak Dr",
    "sg:city":"Salem",
    "sg:classifiers":[
        {
            "category":"Professional",
            "subcategory":"Business Services",
            "type":"Services"
        }
    ],
    "sg:phone":"+1 801 423 2782",
    "sg:postcode":"84653",
    "sg:province":"UT",
    "wof:name":"Vitality Alliance Assoc LLC",
    "wof:placetype":"venue"
},
  "geometry": {"coordinates":[-111.657027,40.012147],"type":"Point"}
}