{
  "type": "Feature",
  "properties": {
    "iso:country":"US",
    "sg:address":"508 E 300 N",
    "sg:city":"Richfield",
    "sg:classifiers":[
        {
            "category":"Manufacturing",
            "subcategory":"Signs",
            "type":"Manufacturing & Wholesale Goods"
        }
    ],
    "sg:phone":"+1 435 896 8018",
    "sg:postcode":"84701",
    "sg:province":"UT",
    "sg:tags":[
        "specialty",
        "mfg"
    ],
    "wof:name":"Sign Central",
    "wof:placetype":"venue"
},
  "geometry": {"coordinates":[-112.07575799999999,38.772162],"type":"Point"}
}