{
  "type": "Feature",
  "properties": {
    "iso:country":"US",
    "sg:address":"581 N Locust Ave",
    "sg:city":"Lindon",
    "sg:classifiers":[
        {
            "category":"Professional",
            "subcategory":"Accounting & Tax Preparation",
            "type":"Services"
        }
    ],
    "sg:phone":"+1 801 785 3161",
    "sg:postcode":"84042",
    "sg:province":"UT",
    "sg:tags":[
        "accountant"
    ],
    "wof:name":"Johnson & Assoc",
    "wof:placetype":"venue"
},
  "geometry": {"coordinates":[-111.720985,40.34906],"type":"Point"}
}