{
  "type": "Feature",
  "properties": {
    "iso:country":"US",
    "sg:address":"750 N Vernal Ave",
    "sg:city":"Vernal",
    "sg:classifiers":[
        {
            "category":"Freight",
            "type":"Transportation"
        }
    ],
    "sg:phone":"+1 435 789 3482",
    "sg:postcode":"84078",
    "sg:province":"UT",
    "sg:tags":[
        "commercial",
        "storage"
    ],
    "wof:name":"Stuff-It Seff Storage",
    "wof:placetype":"venue"
},
  "geometry": {"coordinates":[-109.528789,40.468192],"type":"Point"}
}