{
  "type": "Feature",
  "properties": {
    "iso:country":"US",
    "sg:address":"234 W Main St",
    "sg:city":"Delta",
    "sg:classifiers":[
        {
            "category":"Retail",
            "subcategory":"Self-service Laundry",
            "type":"Services"
        }
    ],
    "sg:phone":"+1 435 864 2041",
    "sg:postcode":"84624",
    "sg:province":"UT",
    "sg:tags":[
        "operation",
        "coin"
    ],
    "wof:name":"Diamond D Motor Lodge",
    "wof:placetype":"venue"
},
  "geometry": {"coordinates":[-112.58074999999999,39.352467],"type":"Point"}
}