{
  "type": "Feature",
  "properties": {
    "iso:country":"US",
    "sg:address":"355 S 200 E",
    "sg:city":"St George",
    "sg:classifiers":[
        {
            "category":"Shopping",
            "subcategory":"Clothing, Apparel, & Fashions",
            "type":"Retail Goods"
        }
    ],
    "sg:phone":"+1 435 673 3662",
    "sg:postcode":"84770",
    "sg:province":"UT",
    "sg:tags":[
        "religious"
    ],
    "wof:name":"Beehive Clothing Center",
    "wof:placetype":"venue"
},
  "geometry": {"coordinates":[-113.579036,37.102153],"type":"Point"}
}