{
  "type": "Feature",
  "properties": {
    "iso:country":"US",
    "sg:address":"127 N 400 W",
    "sg:city":"Kaysville",
    "sg:classifiers":[
        {
            "category":"Professional",
            "subcategory":"Business Services",
            "type":"Services"
        }
    ],
    "sg:phone":"+1 801 546 8390",
    "sg:postcode":"84037",
    "sg:province":"UT",
    "wof:name":"Rm Enterprises Inc",
    "wof:placetype":"venue"
},
  "geometry": {"coordinates":[-111.946225,41.037722],"type":"Point"}
}