{
  "type": "Feature",
  "properties": {
    "iso:country":"US",
    "sg:address":"1971 W North Temple",
    "sg:city":"Salt Lake City",
    "sg:classifiers":[
        {
            "category":"Communications",
            "subcategory":"Radio Station",
            "type":"Services"
        }
    ],
    "sg:phone":"+1 801 363 1818",
    "sg:postcode":"84116",
    "sg:province":"UT",
    "sg:website":"www.krcl.org",
    "wof:name":"KRCL",
    "wof:placetype":"venue"
},
  "geometry": {"coordinates":[-111.946072,40.771442],"type":"Point"}
}