{
  "type": "Feature",
  "properties": {
    "iso:country":"US",
    "sg:address":"100 E 4150 S",
    "sg:city":"Ogden",
    "sg:classifiers":[
        {
            "category":"Education",
            "subcategory":"School",
            "type":"Public Place"
        }
    ],
    "sg:phone":"+1 801 626 2509",
    "sg:postcode":"84405",
    "sg:province":"UT",
    "wof:name":"Club Heights Elementary SC",
    "wof:placetype":"venue"
},
  "geometry": {"coordinates":[-111.977919,41.187417],"type":"Point"}
}