{
  "type": "Feature",
  "properties": {
    "iso:country":"US",
    "sg:address":"543 E 200 N",
    "sg:city":"Price",
    "sg:classifiers":[
        {
            "category":"Manufacturing",
            "subcategory":"Tools & Machinery",
            "type":"Manufacturing & Wholesale Goods"
        }
    ],
    "sg:phone":"+1 435 637 0529",
    "sg:postcode":"84501",
    "sg:province":"UT",
    "sg:tags":[
        "industrial",
        "electrical",
        "apparatus",
        "mfg"
    ],
    "wof:name":"B & J Ventures",
    "wof:placetype":"venue"
},
  "geometry": {"coordinates":[-110.801368,39.602533],"type":"Point"}
}