{
  "type": "Feature",
  "properties": {
    "iso:country":"US",
    "sg:address":"429 Belview Ave",
    "sg:city":"Salt Lake City",
    "sg:classifiers":[
        {
            "category":"Building & Trades",
            "subcategory":"Plumbing",
            "type":"Services"
        }
    ],
    "sg:phone":"+1 801 268 0692",
    "sg:postcode":"84107",
    "sg:province":"UT",
    "sg:tags":[
        "contractor"
    ],
    "wof:name":"K C Heating & Air Conditioning",
    "wof:placetype":"venue"
},
  "geometry": {"coordinates":[-111.879578,40.640819],"type":"Point"}
}