{
  "type": "Feature",
  "properties": {
    "iso:country":"US",
    "sg:address":"815 E Saint George Blvd",
    "sg:city":"St George",
    "sg:classifiers":[
        {
            "category":"Restaurant",
            "type":"Food & Drink"
        }
    ],
    "sg:phone":"+1 435 656 3900",
    "sg:postcode":"84770",
    "sg:province":"UT",
    "wof:name":"Jimmy Johns Sandwich Shop",
    "wof:placetype":"venue"
},
  "geometry": {"coordinates":[-113.566062,37.109879],"type":"Point"}
}