{
  "type": "Feature",
  "properties": {
    "iso:country":"US",
    "sg:address":"2128 Constitution Blvd",
    "sg:city":"Salt Lake City",
    "sg:classifiers":[
        {
            "category":"Wholesale",
            "subcategory":"Machinery & Supplies",
            "type":"Manufacturing & Wholesale Goods"
        }
    ],
    "sg:phone":"+1 801 977 0475",
    "sg:postcode":"84119",
    "sg:province":"UT",
    "sg:tags":[
        "equipment",
        "industrial",
        "fabricated",
        "mfg"
    ],
    "wof:name":"R C M Mechanical Inc",
    "wof:placetype":"venue"
},
  "geometry": {"coordinates":[-111.95813699999999,40.725051],"type":"Point"}
}