{
  "type": "Feature",
  "properties": {
    "iso:country":"US",
    "sg:address":"125 E 300 S",
    "sg:city":"Moab",
    "sg:classifiers":[
        {
            "category":"Manufacturing",
            "subcategory":"Apparel",
            "type":"Manufacturing & Wholesale Goods"
        }
    ],
    "sg:phone":"+1 435 259 9876",
    "sg:postcode":"84532",
    "sg:province":"UT",
    "wof:name":"Entrada Embroidery",
    "wof:placetype":"venue"
},
  "geometry": {"coordinates":[-109.548197,38.568741],"type":"Point"}
}