{
  "type": "Feature",
  "properties": {
    "iso:country":"US",
    "sg:address":"330 S 300 E",
    "sg:city":"Salt Lake City",
    "sg:classifiers":[
        {
            "category":"Banks & Credit Unions",
            "subcategory":"Investment Brokerage",
            "type":"Services"
        }
    ],
    "sg:phone":"+1 801 322 4868",
    "sg:postcode":"84111",
    "sg:province":"UT",
    "sg:tags":[
        "consultant",
        "planning",
        "financial"
    ],
    "wof:name":"American Express Financial Adv",
    "wof:placetype":"venue"
},
  "geometry": {"coordinates":[-111.88257400000001,40.76132],"type":"Point"}
}