{
  "type": "Feature",
  "properties": {
    "iso:country":"US",
    "sg:address":"3609 S 900 E",
    "sg:city":"Salt Lake City",
    "sg:classifiers":[
        {
            "category":"Freight",
            "type":"Transportation"
        }
    ],
    "sg:phone":"+1 801 463 6300",
    "sg:postcode":"84106",
    "sg:province":"UT",
    "sg:tags":[
        "commercial",
        "storage"
    ],
    "wof:name":"9th East Self Storage",
    "wof:placetype":"venue"
},
  "geometry": {"coordinates":[-111.86539999999999,40.692819],"type":"Point"}
}