{
  "type": "Feature",
  "properties": {
    "iso:country":"US",
    "sg:address":"355 S 300 E",
    "sg:city":"Salt Lake City",
    "sg:classifiers":[
        {
            "category":"Organizations",
            "subcategory":"Religious Organization",
            "type":"Services"
        }
    ],
    "sg:phone":"+1 801 278 5608",
    "sg:postcode":"84111",
    "sg:province":"UT",
    "sg:tags":[
        "church"
    ],
    "wof:name":"St Peter & Paul Orthodox Chr",
    "wof:placetype":"venue"
},
  "geometry": {"coordinates":[-111.882425,40.761852],"type":"Point"}
}