{
  "type": "Feature",
  "properties": {
    "iso:country":"US",
    "sg:address":"3878 Washington Blvd",
    "sg:city":"Ogden",
    "sg:classifiers":[
        {
            "category":"Retail",
            "subcategory":"Laundry & Dry Cleaning",
            "type":"Services"
        }
    ],
    "sg:phone":"+1 801 392 7103",
    "sg:postcode":"84403",
    "sg:province":"UT",
    "sg:tags":[
        "drycleaning",
        "plant",
        "coin"
    ],
    "wof:name":"Forsey Laundry & Cleaning",
    "wof:placetype":"venue"
},
  "geometry": {"coordinates":[-111.97104299999999,41.19345],"type":"Point"}
}