{
  "type": "Feature",
  "properties": {
    "iso:country":"US",
    "sg:address":"4705 S 200 W",
    "sg:city":"Salt Lake City",
    "sg:classifiers":[
        {
            "category":"Retail",
            "subcategory":"Auto Repair",
            "type":"Services"
        }
    ],
    "sg:phone":"+1 801 685 2569",
    "sg:postcode":"84107",
    "sg:province":"UT",
    "sg:tags":[
        "automotive"
    ],
    "wof:name":"Legacy Towing Inc",
    "wof:placetype":"venue"
},
  "geometry": {"coordinates":[-111.89694799999999,40.671925],"type":"Point"}
}