{
  "type": "Feature",
  "properties": {
    "iso:country":"US",
    "sg:address":"585 Aspen Dr",
    "sg:city":"Park City",
    "sg:classifiers":[
        {
            "category":"Manufacturing",
            "subcategory":"Tools & Machinery",
            "type":"Manufacturing & Wholesale Goods"
        }
    ],
    "sg:phone":"+1 435 645 7132",
    "sg:postcode":"84098",
    "sg:province":"UT",
    "sg:tags":[
        "eyes",
        "artificial"
    ],
    "wof:name":"Center For Prosthetics",
    "wof:placetype":"venue"
},
  "geometry": {"coordinates":[-111.61273300000001,40.749031],"type":"Point"}
}