{
  "type": "Feature",
  "properties": {
    "iso:country":"US",
    "sg:address":"714 W 3300 S",
    "sg:city":"Bountiful",
    "sg:classifiers":[
        {
            "category":"Freight",
            "type":"Transportation"
        }
    ],
    "sg:phone":"+1 801 514 3560",
    "sg:postcode":"84010",
    "sg:province":"UT",
    "sg:tags":[
        "delivery"
    ],
    "wof:name":"Mobl Express",
    "wof:placetype":"venue"
},
  "geometry": {"coordinates":[-111.898275,40.853691],"type":"Point"}
}