{
  "type": "Feature",
  "properties": {
    "iso:country":"US",
    "sg:address":"4465 Century Dr",
    "sg:city":"Murray",
    "sg:classifiers":[
        {
            "category":"Travel",
            "subcategory":"Hotels & Motels",
            "type":"Entertainment"
        }
    ],
    "sg:phone":"+1 801 268 2533",
    "sg:postcode":"84123",
    "sg:province":"UT",
    "wof:name":"Holiday Inn Express",
    "wof:placetype":"venue"
},
  "geometry": {"coordinates":[-111.90366299999999,40.676837],"type":"Point"}
}