{
  "type": "Feature",
  "properties": {
    "iso:country":"US",
    "sg:address":"3652 S 900 East St",
    "sg:city":"Salt Lake City",
    "sg:classifiers":[
        {
            "category":"Professional",
            "subcategory":"Business Services",
            "type":"Services"
        }
    ],
    "sg:phone":"+1 801 264 0447",
    "sg:postcode":"84106",
    "sg:province":"UT",
    "wof:name":"FL Design Group",
    "wof:placetype":"venue"
},
  "geometry": {"coordinates":[-111.86555,40.692481],"type":"Point"}
}