{
  "type": "Feature",
  "properties": {
    "iso:country":"US",
    "sg:address":"160 W 500 N",
    "sg:city":"Heber City",
    "sg:classifiers":[
        {
            "category":"Organizations",
            "subcategory":"Non-profit Organization",
            "type":"Services"
        },
        {
            "category":"Professional",
            "subcategory":"Management & Consulting",
            "type":"Services"
        }
    ],
    "sg:phone":"+1 435 654 5500",
    "sg:postcode":"84032",
    "sg:province":"UT",
    "sg:tags":[
        "nurse",
        "skilled",
        "facility"
    ],
    "wof:name":"Rocky Mountain Care Heber",
    "wof:placetype":"venue"
},
  "geometry": {"coordinates":[-111.415975,40.514314],"type":"Point"}
}