{
  "type": "Feature",
  "properties": {
    "iso:country":"US",
    "sg:address":"4728 N 450 W",
    "sg:city":"Provo",
    "sg:classifiers":[
        {
            "category":"Farming",
            "subcategory":"Farm & Veterinary Services",
            "type":"Manufacturing & Wholesale Goods"
        }
    ],
    "sg:phone":"+1 801 235 9268",
    "sg:postcode":"84604",
    "sg:province":"UT",
    "sg:tags":[
        "preparation",
        "crop",
        "for",
        "market"
    ],
    "wof:name":"Max Pyne",
    "wof:placetype":"venue"
},
  "geometry": {"coordinates":[-111.66534799999999,40.295821],"type":"Point"}
}