{
  "type": "Feature",
  "properties": {
    "iso:country":"US",
    "sg:address":"15 S Main St",
    "sg:city":"Beaver",
    "sg:classifiers":[
        {
            "category":"Insurance",
            "subcategory":"Insurance Agent",
            "type":"Services"
        }
    ],
    "sg:phone":"+1 435 438 5445",
    "sg:postcode":"84751",
    "sg:province":"UT",
    "wof:name":"White Insurance",
    "wof:placetype":"venue"
},
  "geometry": {"coordinates":[-113.01068600000001,38.397041],"type":"Point"}
}