{
  "type": "Feature",
  "properties": {
    "iso:country":"US",
    "sg:address":"351 W Center St",
    "sg:city":"Cedar City",
    "sg:classifiers":[
        {
            "category":"Education",
            "subcategory":"College",
            "type":"Public Place"
        }
    ],
    "sg:phone":"+1 435 586 7700",
    "sg:postcode":"84720",
    "sg:province":"UT",
    "sg:tags":[
        "department",
        "university",
        "receiving"
    ],
    "wof:name":"Plant Operations",
    "wof:placetype":"venue"
},
  "geometry": {"coordinates":[-113.070108,37.676971],"type":"Point"}
}