{
  "type": "Feature",
  "properties": {
    "iso:country":"US",
    "sg:address":"1690 Maplewood Way",
    "sg:city":"St George",
    "sg:classifiers":[
        {
            "category":"Building & Trades",
            "subcategory":"Cleaning & Sanitation",
            "type":"Services"
        }
    ],
    "sg:phone":"+1 435 628 5590",
    "sg:postcode":"84790",
    "sg:province":"UT",
    "sg:tags":[
        "maintenance"
    ],
    "wof:name":"Precision Window Cleaning",
    "wof:placetype":"venue"
},
  "geometry": {"coordinates":[-113.54931500000001,37.060868],"type":"Point"}
}