{
  "type": "Feature",
  "properties": {
    "iso:country":"US",
    "sg:address":"436 N Redwood Rd",
    "sg:city":"Salt Lake City",
    "sg:classifiers":[
        {
            "category":"Shopping",
            "subcategory":"Music",
            "type":"Retail Goods"
        }
    ],
    "sg:phone":"+1 801 596 3271",
    "sg:postcode":"84116",
    "sg:province":"UT",
    "wof:name":"Rmvh LLC",
    "wof:placetype":"venue"
},
  "geometry": {"coordinates":[-111.93931000000001,40.778303],"type":"Point"}
}