{
  "type": "Feature",
  "properties": {
    "iso:country":"US",
    "sg:address":"8612 S 1300 E",
    "sg:city":"Sandy",
    "sg:classifiers":[
        {
            "category":"Food & Beverages",
            "subcategory":"Groceries & Convenience Stores",
            "type":"Retail Goods"
        }
    ],
    "sg:phone":"+1 801 561 5331",
    "sg:postcode":"84094",
    "sg:province":"UT",
    "sg:tags":[
        "station"
    ],
    "wof:name":"Conoco 44012",
    "wof:placetype":"venue"
},
  "geometry": {"coordinates":[-111.85325400000001,40.593571],"type":"Point"}
}