{
  "type": "Feature",
  "properties": {
    "iso:country":"US",
    "sg:address":"1816 Prospector Ave",
    "sg:city":"Park City",
    "sg:classifiers":[
        {
            "category":"Real Estate",
            "subcategory":"Real Estate Agent",
            "type":"Services"
        }
    ],
    "sg:phone":"+1 435 655 3860",
    "sg:postcode":"84060",
    "sg:province":"UT",
    "wof:name":"Mountain Seas Development",
    "wof:placetype":"venue"
},
  "geometry": {"coordinates":[-111.500417,40.662186],"type":"Point"}
}