{
  "type": "Feature",
  "properties": {
    "iso:country":"US",
    "sg:address":"1425 S State St",
    "sg:city":"Orem",
    "sg:classifiers":[
        {
            "category":"Professional",
            "subcategory":"Lawyer & Legal Services",
            "type":"Services"
        }
    ],
    "sg:phone":"+1 801 852 2828",
    "sg:postcode":"84097",
    "sg:province":"UT",
    "sg:tags":[
        "attorney"
    ],
    "wof:name":"Robert J De Bry & Assoc",
    "wof:placetype":"venue"
},
  "geometry": {"coordinates":[-111.682997,40.270135],"type":"Point"}
}