{
  "type": "Feature",
  "properties": {
    "iso:country":"US",
    "sg:address":"48 W 700 S",
    "sg:city":"St George",
    "sg:classifiers":[
        {
            "category":"Social Services",
            "subcategory":"Adult Care",
            "type":"Services"
        }
    ],
    "sg:phone":"+1 435 673 7398",
    "sg:postcode":"84770",
    "sg:province":"UT",
    "sg:tags":[
        "home",
        "residential"
    ],
    "wof:name":"Rosecrest Manor",
    "wof:placetype":"venue"
},
  "geometry": {"coordinates":[-113.584293,37.096407],"type":"Point"}
}