{
  "type": "Feature",
  "properties": {
    "iso:country":"US",
    "sg:address":"6644 Cottonwood St",
    "sg:city":"Salt Lake City",
    "sg:classifiers":[
        {
            "category":"Home & Garden",
            "subcategory":"Building Materials",
            "type":"Retail Goods"
        }
    ],
    "sg:phone":"+1 801 747 3550",
    "sg:postcode":"84107",
    "sg:province":"UT",
    "sg:tags":[
        "plumbing",
        "fixture",
        "supply"
    ],
    "wof:name":"S & S Specialty Parts",
    "wof:placetype":"venue"
},
  "geometry": {"coordinates":[-111.899703,40.630372],"type":"Point"}
}