{
  "type": "Feature",
  "properties": {
    "iso:country":"US",
    "sg:address":"1333 N Main St",
    "sg:city":"Cedar City",
    "sg:classifiers":[
        {
            "category":"Shopping",
            "type":"Retail Goods"
        }
    ],
    "sg:phone":"+1 435 586 0379",
    "sg:postcode":"84720",
    "sg:province":"UT",
    "sg:tags":[
        "equipment",
        "care",
        "health",
        "home"
    ],
    "sg:website":"www.praxair.com",
    "wof:name":"Praxair Healthcare Svc",
    "wof:placetype":"venue"
},
  "geometry": {"coordinates":[-113.063951,37.700713],"type":"Point"}
}