{
  "type": "Feature",
  "properties": {
    "iso:country":"US",
    "sg:address":"403 E 2700 S",
    "sg:city":"South Salt Lake",
    "sg:classifiers":[
        {
            "category":"Professional",
            "subcategory":"Business Services",
            "type":"Services"
        }
    ],
    "sg:phone":"+1 801 487 6611",
    "sg:postcode":"84115",
    "sg:province":"UT",
    "sg:tags":[
        "process",
        "server"
    ],
    "wof:name":"Constable Info-Best Process",
    "wof:placetype":"venue"
},
  "geometry": {"coordinates":[-111.87875200000001,40.712727],"type":"Point"}
}