{
  "type": "Feature",
  "properties": {
    "iso:country":"US",
    "sg:address":"1061 Crestview Cir",
    "sg:city":"Salt Lake City",
    "sg:classifiers":[
        {
            "category":"Home & Garden",
            "subcategory":"Hardware",
            "type":"Retail Goods"
        }
    ],
    "sg:phone":"+1 801 582 7832",
    "sg:postcode":"84108",
    "sg:province":"UT",
    "wof:name":"David Boyd Wagstaff",
    "wof:placetype":"venue"
},
  "geometry": {"coordinates":[-111.811092,40.746011],"type":"Point"}
}