{
  "type": "Feature",
  "properties": {
    "iso:country":"US",
    "sg:address":"5806 Jordan Canal Rd",
    "sg:city":"Salt Lake City",
    "sg:classifiers":[
        {
            "category":"Building & Trades",
            "subcategory":"Construction",
            "type":"Services"
        }
    ],
    "sg:phone":"+1 801 966 5952",
    "sg:postcode":"84118",
    "sg:province":"UT",
    "sg:tags":[
        "heavy"
    ],
    "wof:name":"Ba Critchfield Construction",
    "wof:placetype":"venue"
},
  "geometry": {"coordinates":[-111.94746600000001,40.644637],"type":"Point"}
}