{
  "type": "Feature",
  "properties": {
    "iso:country":"US",
    "sg:address":"346 Mountain Way Dr",
    "sg:city":"Orem",
    "sg:classifiers":[
        {
            "category":"Professional",
            "type":"Services"
        }
    ],
    "sg:phone":"+1 801 225 7960",
    "sg:postcode":"84058",
    "sg:province":"UT",
    "sg:tags":[
        "establishment"
    ],
    "wof:name":"Florentine Art Works",
    "wof:placetype":"venue"
},
  "geometry": {"coordinates":[-111.729124,40.290859],"type":"Point"}
}