{
  "type": "Feature",
  "properties": {
    "iso:country":"US",
    "sg:address":"1283 N. 400 W",
    "sg:city":"Bountiful",
    "sg:classifiers":[
        {
            "category":"Building & Trades",
            "subcategory":"Construction",
            "type":"Services"
        }
    ],
    "sg:phone":"+1 801 419 2306",
    "sg:postcode":"84010",
    "sg:province":"UT",
    "sg:tags":[
        "contractor"
    ],
    "wof:name":"A.P.C Concrete Pumping",
    "wof:placetype":"venue"
},
  "geometry": {"coordinates":[-111.890223,40.902369],"type":"Point"}
}