{
  "type": "Feature",
  "properties": {
    "iso:country":"US",
    "sg:address":"1425 S State St",
    "sg:city":"Salina",
    "sg:classifiers":[
        {
            "category":"Banks & Credit Unions",
            "subcategory":"Financial Services",
            "type":"Services"
        }
    ],
    "sg:phone":"+1 435 529 7447",
    "sg:postcode":"84654",
    "sg:province":"UT",
    "sg:tags":[
        "company",
        "bank",
        "holding"
    ],
    "wof:name":"Salina Creek R V Camp",
    "wof:placetype":"venue"
},
  "geometry": {"coordinates":[-111.85456000000001,38.935649],"type":"Point"}
}