{
  "type": "Feature",
  "properties": {
    "iso:country":"US",
    "sg:address":"359 S Main St",
    "sg:city":"Richfield",
    "sg:classifiers":[
        {
            "category":"Shopping",
            "subcategory":"Used Merchandise",
            "type":"Retail Goods"
        }
    ],
    "sg:phone":"+1 435 896 7988",
    "sg:postcode":"84701",
    "sg:province":"UT",
    "wof:name":"Nothing New Antiques",
    "wof:placetype":"venue"
},
  "geometry": {"coordinates":[-112.08462,38.763088],"type":"Point"}
}