{
  "type": "Feature",
  "properties": {
    "iso:country":"US",
    "sg:address":"4179 Riverboat Rd",
    "sg:city":"Murray",
    "sg:classifiers":[
        {
            "category":"Professional",
            "type":"Services"
        },
        {
            "category":"Real Estate",
            "subcategory":"Real Estate Agent",
            "type":"Services"
        }
    ],
    "sg:phone":"+1 801 281 4705",
    "sg:postcode":"84123",
    "sg:province":"UT",
    "sg:tags":[
        "establishment"
    ],
    "wof:name":"Carr America",
    "wof:placetype":"venue"
},
  "geometry": {"coordinates":[-111.91653599999999,40.677375],"type":"Point"}
}