{
  "type": "Feature",
  "properties": {
    "iso:country":"US",
    "sg:address":"6120 S 300 W",
    "sg:city":"Salt Lake City",
    "sg:classifiers":[
        {
            "category":"Wholesale",
            "subcategory":"Electrical",
            "type":"Manufacturing & Wholesale Goods"
        }
    ],
    "sg:phone":"+1 801 293 1600",
    "sg:postcode":"84107",
    "sg:province":"UT",
    "sg:tags":[
        "equipment"
    ],
    "wof:name":"Salt Lake Winelectric Co",
    "wof:placetype":"venue"
},
  "geometry": {"coordinates":[-111.898529,40.637607],"type":"Point"}
}