{
  "type": "Feature",
  "properties": {
    "iso:country":"US",
    "sg:address":"583 W Billinis Rd",
    "sg:city":"Salt Lake City",
    "sg:classifiers":[
        {
            "category":"Food & Beverages",
            "subcategory":"Specialty",
            "type":"Retail Goods"
        }
    ],
    "sg:phone":"+1 801 288 9966",
    "sg:postcode":"84115",
    "sg:province":"UT",
    "sg:tags":[
        "gourmet",
        "shop"
    ],
    "wof:name":"Chef Tomass Gourmet Foods",
    "wof:placetype":"venue"
},
  "geometry": {"coordinates":[-111.90600000000001,40.694182],"type":"Point"}
}