{
  "type": "Feature",
  "properties": {
    "iso:country":"US",
    "sg:address":"140 W 9000 S",
    "sg:city":"Sandy",
    "sg:classifiers":[
        {
            "category":"Real Estate",
            "subcategory":"Real Estate Agent",
            "type":"Services"
        }
    ],
    "sg:phone":"+1 801 566 1181",
    "sg:postcode":"84070",
    "sg:province":"UT",
    "wof:name":"Tri State Realtors",
    "wof:placetype":"venue"
},
  "geometry": {"coordinates":[-111.893885,40.588151],"type":"Point"}
}