{
  "type": "Feature",
  "properties": {
    "iso:country":"US",
    "sg:address":"4663 S 2700 W",
    "sg:city":"West Valley",
    "sg:classifiers":[
        {
            "category":"Restaurant",
            "type":"Food & Drink"
        }
    ],
    "sg:phone":"+1 801 965 1939",
    "sg:postcode":"84119",
    "sg:province":"UT",
    "wof:name":"Arby's",
    "wof:placetype":"venue"
},
  "geometry": {"coordinates":[-111.957954,40.674358],"type":"Point"}
}