{
  "type": "Feature",
  "properties": {
    "iso:country":"US",
    "sg:address":"570 N Mill Rd",
    "sg:city":"Heber City",
    "sg:classifiers":[
        {
            "category":"Social Services",
            "subcategory":"Child Care",
            "type":"Services"
        }
    ],
    "sg:phone":"+1 435 654 0961",
    "sg:postcode":"84032",
    "sg:province":"UT",
    "sg:tags":[
        "day"
    ],
    "wof:name":"Wee Care Too Preschool",
    "wof:placetype":"venue"
},
  "geometry": {"coordinates":[-111.395346,40.510886],"type":"Point"}
}