{
  "type": "Feature",
  "properties": {
    "iso:country":"US",
    "sg:address":"85 N 400 East St",
    "sg:city":"Beaver",
    "sg:classifiers":[
        {
            "category":"Local Transit",
            "type":"Transportation"
        }
    ],
    "sg:phone":"+1 435 438 5887",
    "sg:postcode":"84713",
    "sg:province":"UT",
    "sg:tags":[
        "ambulance"
    ],
    "wof:name":"Ambulance Billing Office",
    "wof:placetype":"venue"
},
  "geometry": {"coordinates":[-112.63436799999999,38.274701],"type":"Point"}
}