{
  "type": "Feature",
  "properties": {
    "iso:country":"US",
    "sg:address":"1031 Chartwell Ct",
    "sg:city":"Salt Lake City",
    "sg:classifiers":[
        {
            "category":"Professional",
            "subcategory":"Management & Consulting",
            "type":"Services"
        }
    ],
    "sg:phone":"+1 801 321 0532",
    "sg:postcode":"84103",
    "sg:province":"UT",
    "sg:tags":[
        "consultant",
        "business"
    ],
    "wof:name":"Alvina M Hall",
    "wof:placetype":"venue"
},
  "geometry": {"coordinates":[-111.886852,40.792518],"type":"Point"}
}