{
  "type": "Feature",
  "properties": {
    "iso:country":"US",
    "sg:address":"2151 W 700 S",
    "sg:city":"Ogden",
    "sg:classifiers":[
        {
            "category":"Manufacturing",
            "subcategory":"Metals",
            "type":"Manufacturing & Wholesale Goods"
        }
    ],
    "sg:phone":"+1 801 731 3470",
    "sg:postcode":"84404",
    "sg:province":"UT",
    "wof:name":"Brass Crown Plating",
    "wof:placetype":"venue"
},
  "geometry": {"coordinates":[-112.033444,41.251847],"type":"Point"}
}