{
  "type": "Feature",
  "properties": {
    "iso:country":"US",
    "sg:address":"975 Stowe Dr",
    "sg:city":"Ogden",
    "sg:classifiers":[
        {
            "category":"Retail",
            "subcategory":"Repair Shop",
            "type":"Services"
        }
    ],
    "sg:phone":"+1 801 393 9079",
    "sg:postcode":"84404",
    "sg:province":"UT",
    "sg:tags":[
        "repairing",
        "piano",
        "refinishing"
    ],
    "wof:name":"Young Wilford Piano Tuning",
    "wof:placetype":"venue"
},
  "geometry": {"coordinates":[-111.93450900000001,41.245855],"type":"Point"}
}