{
  "type": "Feature",
  "properties": {
    "iso:country":"US",
    "sg:address":"1240 S Main St",
    "sg:city":"Heber City",
    "sg:classifiers":[
        {
            "category":"Retail",
            "subcategory":"Auto Repair",
            "type":"Services"
        }
    ],
    "sg:phone":"+1 435 657 9696",
    "sg:postcode":"84032",
    "sg:province":"UT",
    "sg:tags":[
        "automobile",
        "lubrication"
    ],
    "wof:name":"Wes' Express Care",
    "wof:placetype":"venue"
},
  "geometry": {"coordinates":[-111.413376,40.492967],"type":"Point"}
}