{
  "type": "Feature",
  "properties": {
    "iso:country":"US",
    "sg:address":"939 S 700 W",
    "sg:city":"Salt Lake City",
    "sg:classifiers":[
        {
            "category":"Manufacturing",
            "subcategory":"Lumber",
            "type":"Manufacturing & Wholesale Goods"
        }
    ],
    "sg:phone":"+1 801 972 0260",
    "sg:postcode":"84104",
    "sg:province":"UT",
    "sg:tags":[
        "hardwood",
        "mills",
        "dimension",
        "flooring"
    ],
    "sg:website":"www.sportcourt.com",
    "wof:name":"Connor Sport Court Intl",
    "wof:placetype":"venue"
},
  "geometry": {"coordinates":[-111.91101999999999,40.744221],"type":"Point"}
}