{
  "type": "Feature",
  "properties": {
    "iso:country":"US",
    "sg:address":"250 N Main St",
    "sg:city":"Kaysville",
    "sg:classifiers":[
        {
            "category":"Banks & Credit Unions",
            "subcategory":"Bank",
            "type":"Services"
        }
    ],
    "sg:phone":"+1 801 546 1266",
    "sg:postcode":"84037",
    "sg:province":"UT",
    "sg:tags":[
        "national",
        "commercial"
    ],
    "wof:name":"Wells Fargo",
    "wof:placetype":"venue"
},
  "geometry": {"coordinates":[-111.940966,41.040216],"type":"Point"}
}