{
  "type": "Feature",
  "properties": {
    "iso:country":"US",
    "sg:address":"1150 E Riverside Dr",
    "sg:city":"St George",
    "sg:classifiers":[
        {
            "category":"Government",
            "subcategory":"Post Office",
            "type":"Public Place"
        }
    ],
    "sg:phone":"+1 435 688 1496",
    "sg:postcode":"84790",
    "sg:province":"UT",
    "wof:name":"US Post Office",
    "wof:placetype":"venue"
},
  "geometry": {"coordinates":[-113.527342,37.106332],"type":"Point"}
}