{
  "type": "Feature",
  "properties": {
    "iso:country":"US",
    "sg:address":"2009 E 6225 S",
    "sg:city":"Ogden",
    "sg:classifiers":[
        {
            "category":"Wholesale",
            "subcategory":"Stationery",
            "type":"Manufacturing & Wholesale Goods"
        }
    ],
    "sg:phone":"+1 801 479 5939",
    "sg:postcode":"84403",
    "sg:province":"UT",
    "sg:tags":[
        "adhesive",
        "business",
        "form",
        "scrap",
        "for",
        "book"
    ],
    "wof:name":"J & V Enterprises Inc",
    "wof:placetype":"venue"
},
  "geometry": {"coordinates":[-111.928954,41.149806],"type":"Point"}
}