{
  "type": "Feature",
  "properties": {
    "iso:country":"US",
    "sg:address":"2932 Sierra Point Pl",
    "sg:city":"Salt Lake City",
    "sg:classifiers":[
        {
            "category":"Cinema",
            "subcategory":"Movie Rental",
            "type":"Entertainment"
        }
    ],
    "sg:phone":"+1 801 486 0356",
    "sg:postcode":"84109",
    "sg:province":"UT",
    "sg:tags":[
        "video",
        "tape"
    ],
    "wof:name":"Canyon Video Inc",
    "wof:placetype":"venue"
},
  "geometry": {"coordinates":[-111.831801,40.707535],"type":"Point"}
}