{
  "type": "Feature",
  "properties": {
    "iso:country":"US",
    "sg:address":"9 Exchange Pl",
    "sg:city":"Salt Lake City",
    "sg:classifiers":[
        {
            "category":"Utilities",
            "subcategory":"Telephone",
            "type":"Services"
        },
        {
            "category":"Professional",
            "subcategory":"Computer Services",
            "type":"Services"
        }
    ],
    "sg:phone":"+1 801 363 7554",
    "sg:postcode":"84111",
    "sg:province":"UT",
    "sg:tags":[
        "consulting",
        "it",
        "dev",
        "internet",
        "home",
        "page"
    ],
    "sg:website":"www.isgsec.com",
    "wof:name":"Internet Solutions Group",
    "wof:placetype":"venue"
},
  "geometry": {"coordinates":[-111.889832,40.761482],"type":"Point"}
}