{
  "type": "Feature",
  "properties": {
    "iso:country":"US",
    "sg:address":"590 E 100 N",
    "sg:city":"Price",
    "sg:classifiers":[
        {
            "category":"Personal",
            "subcategory":"Beauty Salon",
            "type":"Services"
        }
    ],
    "sg:phone":"+1 435 637 2720",
    "sg:postcode":"84501",
    "sg:province":"UT",
    "wof:name":"Hair Solutions",
    "wof:placetype":"venue"
},
  "geometry": {"coordinates":[-110.80082299999999,39.600926],"type":"Point"}
}