{
  "type": "Feature",
  "properties": {
    "iso:country":"US",
    "sg:address":"585 N Main St",
    "sg:city":"Providence",
    "sg:classifiers":[
        {
            "category":"Real Estate",
            "subcategory":"Architect",
            "type":"Services"
        }
    ],
    "sg:phone":"+1 435 752 5410",
    "sg:postcode":"84332",
    "sg:province":"UT",
    "wof:name":"Christopherson Architectural",
    "wof:placetype":"venue"
},
  "geometry": {"coordinates":[-111.82339899999999,41.691171],"type":"Point"}
}