{
  "type": "Feature",
  "properties": {
    "iso:country":"US",
    "sg:address":"27 C St",
    "sg:city":"Salt Lake City",
    "sg:classifiers":[
        {
            "category":"Organizations",
            "subcategory":"Religious Organization",
            "type":"Services"
        }
    ],
    "sg:phone":"+1 801 328 8641",
    "sg:postcode":"84103",
    "sg:province":"UT",
    "sg:tags":[
        "church"
    ],
    "sg:website":"www.dioslc.org",
    "wof:name":"Catholic Church Offices",
    "wof:placetype":"venue"
},
  "geometry": {"coordinates":[-111.880629,40.769903],"type":"Point"}
}