{
  "type": "Feature",
  "properties": {
    "iso:country":"US",
    "sg:address":"2518 Parleys Way",
    "sg:city":"Salt Lake City",
    "sg:classifiers":[
        {
            "category":"Professional",
            "subcategory":"Business Services",
            "type":"Services"
        }
    ],
    "sg:phone":"+1 801 582 3176",
    "sg:postcode":"84109",
    "sg:province":"UT",
    "wof:name":"Data Transcon Inc",
    "wof:placetype":"venue"
},
  "geometry": {"coordinates":[-111.818804,40.721605],"type":"Point"}
}