{
  "type": "Feature",
  "properties": {
    "iso:country":"US",
    "sg:address":"1580 Washington Blvd",
    "sg:city":"Ogden",
    "sg:classifiers":[
        {
            "category":"Manufacturing",
            "subcategory":"Textiles",
            "type":"Manufacturing & Wholesale Goods"
        }
    ],
    "sg:phone":"+1 801 392 5081",
    "sg:postcode":"84404",
    "sg:province":"UT",
    "sg:tags":[
        "thread"
    ],
    "wof:name":"Sudhan Threading",
    "wof:placetype":"venue"
},
  "geometry": {"coordinates":[-111.96996799999999,41.239487],"type":"Point"}
}