{
  "type": "Feature",
  "properties": {
    "iso:country":"US",
    "sg:address":"234 E 100 S",
    "sg:city":"Salt Lake City",
    "sg:classifiers":[
        {
            "category":"Shopping",
            "subcategory":"Computers & Home Electronics",
            "type":"Retail Goods"
        },
        {
            "category":"Professional",
            "subcategory":"Computer Services",
            "type":"Services"
        }
    ],
    "sg:phone":"+1 801 521 6900",
    "sg:postcode":"84111",
    "sg:province":"UT",
    "sg:tags":[
        "software",
        "programing",
        "custom"
    ],
    "wof:name":"Shining Armor Software",
    "wof:placetype":"venue"
},
  "geometry": {"coordinates":[-111.883396,40.767102],"type":"Point"}
}