{
  "type": "Feature",
  "properties": {
    "iso:country":"US",
    "sg:address":"50 Park Rd",
    "sg:city":"Evanston",
    "sg:classifiers":[
        {
            "category":"Autos & Motor Vehicles",
            "subcategory":"Motorcycle Sales",
            "type":"Retail Goods"
        }
    ],
    "sg:phone":"+1 307 789 4140",
    "sg:postcode":"82930",
    "sg:province":"UT",
    "sg:tags":[
        "scooter"
    ],
    "wof:name":"Bear River Yamaha",
    "wof:placetype":"venue"
},
  "geometry": {"coordinates":[-110.962352,41.270951],"type":"Point"}
}