{
  "type": "Feature",
  "properties": {
    "iso:country":"US",
    "sg:address":"9834 S 300 E",
    "sg:city":"Sandy",
    "sg:classifiers":[
        {
            "category":"Building & Trades",
            "subcategory":"Construction",
            "type":"Services"
        }
    ],
    "sg:phone":"+1 801 571 4399",
    "sg:postcode":"84070",
    "sg:province":"UT",
    "sg:tags":[
        "masonry",
        "subcontractor"
    ],
    "wof:name":"Shell Enterprises Inc",
    "wof:placetype":"venue"
},
  "geometry": {"coordinates":[-111.881659,40.573261],"type":"Point"}
}