{
  "type": "Feature",
  "properties": {
    "iso:country":"US",
    "sg:address":"210 E 3300 S",
    "sg:city":"Salt Lake City",
    "sg:classifiers":[
        {
            "category":"Building & Trades",
            "subcategory":"Construction",
            "type":"Services"
        }
    ],
    "sg:phone":"+1 801 487 2473",
    "sg:postcode":"84115",
    "sg:province":"UT",
    "sg:tags":[
        "concrete",
        "restoration",
        "cleaning",
        "repair"
    ],
    "wof:name":"Concrete Raising Co",
    "wof:placetype":"venue"
},
  "geometry": {"coordinates":[-111.884017,40.699784],"type":"Point"}
}