{
  "type": "Feature",
  "properties": {
    "iso:country":"US",
    "sg:address":"2010 Kidd Cir",
    "sg:city":"Park City",
    "sg:classifiers":[
        {
            "category":"Professional",
            "subcategory":"Business Services",
            "type":"Services"
        }
    ],
    "sg:phone":"+1 435 615 7333",
    "sg:postcode":"84098",
    "sg:province":"UT",
    "wof:name":"Kinsail Enterprises Inc",
    "wof:placetype":"venue"
},
  "geometry": {"coordinates":[-111.547195,40.697195],"type":"Point"}
}