{
  "type": "Feature",
  "properties": {
    "iso:country":"US",
    "sg:address":"1639 Indiana Ave",
    "sg:city":"Salt Lake City",
    "sg:classifiers":[
        {
            "category":"Building & Trades",
            "subcategory":"Construction",
            "type":"Services"
        }
    ],
    "sg:phone":"+1 801 972 4143",
    "sg:postcode":"84104",
    "sg:province":"UT",
    "sg:tags":[
        "concrete",
        "contractor"
    ],
    "wof:name":"Dawson Asphalt Inc",
    "wof:placetype":"venue"
},
  "geometry": {"coordinates":[-111.93880299999999,40.75117],"type":"Point"}
}