{
  "type": "Feature",
  "properties": {
    "iso:country":"US",
    "sg:address":"13078 Trotter Ct",
    "sg:city":"Riverton",
    "sg:classifiers":[
        {
            "category":"Building & Trades",
            "subcategory":"Construction",
            "type":"Services"
        }
    ],
    "sg:phone":"+1 801 446 2188",
    "sg:postcode":"84065",
    "sg:province":"UT",
    "sg:tags":[
        "residential",
        "nonresidential"
    ],
    "wof:name":"David M Lloyd Construction",
    "wof:placetype":"venue"
},
  "geometry": {"coordinates":[-111.93333,40.514205],"type":"Point"}
}