{
  "type": "Feature",
  "properties": {
    "iso:country":"US",
    "sg:address":"1777 W 12600 S",
    "sg:city":"Riverton",
    "sg:classifiers":[
        {
            "category":"Food & Beverages",
            "subcategory":"Groceries & Convenience Stores",
            "type":"Retail Goods"
        }
    ],
    "sg:phone":"+1 801 254 0761",
    "sg:postcode":"84065",
    "sg:province":"UT",
    "sg:tags":[
        "grocer"
    ],
    "sg:website":"www.petersonsmarketplace.com",
    "wof:name":"Peterson Marketplace",
    "wof:placetype":"venue"
},
  "geometry": {"coordinates":[-111.939988,40.522223],"type":"Point"}
}