{
  "type": "Feature",
  "properties": {
    "iso:country":"US",
    "sg:address":"1383 Major St",
    "sg:city":"Salt Lake City",
    "sg:classifiers":[
        {
            "category":"Wholesale",
            "subcategory":"Machinery & Supplies",
            "type":"Manufacturing & Wholesale Goods"
        }
    ],
    "sg:phone":"+1 801 487 8596",
    "sg:postcode":"84115",
    "sg:province":"UT",
    "sg:tags":[
        "car"
    ],
    "wof:name":"Davis Distributing Co",
    "wof:placetype":"venue"
},
  "geometry": {"coordinates":[-111.889557,40.739072],"type":"Point"}
}