{
  "type": "Feature",
  "properties": {
    "iso:country":"US",
    "sg:address":"1704 W Sunset Blvd",
    "sg:city":"St George",
    "sg:classifiers":[
        {
            "category":"Real Estate",
            "subcategory":"Real Estate Agent",
            "type":"Services"
        }
    ],
    "sg:phone":"+1 435 634 9371",
    "sg:postcode":"84770",
    "sg:province":"UT",
    "sg:tags":[
        "building",
        "manager",
        "contractor"
    ],
    "wof:name":"Ence Storage Centers",
    "wof:placetype":"venue"
},
  "geometry": {"coordinates":[-113.620223,37.122928],"type":"Point"}
}