{
  "type": "Feature",
  "properties": {
    "iso:country":"US",
    "sg:address":"640 S 500 W",
    "sg:city":"Woods Cross",
    "sg:classifiers":[
        {
            "category":"Autos & Motor Vehicles",
            "subcategory":"Auto Supplies",
            "type":"Retail Goods"
        }
    ],
    "sg:phone":"+1 801 294 7155",
    "sg:postcode":"84010",
    "sg:province":"UT",
    "sg:tags":[
        "tire"
    ],
    "wof:name":"640 South Llc",
    "wof:placetype":"venue"
},
  "geometry": {"coordinates":[-111.892341,40.88284],"type":"Point"}
}