{
  "type": "Feature",
  "properties": {
    "iso:country":"US",
    "sg:address":"55 N 300 E",
    "sg:city":"Wellsville",
    "sg:classifiers":[
        {
            "category":"Organizations",
            "subcategory":"Labor Organization",
            "type":"Services"
        }
    ],
    "sg:phone":"+1 435 245 7895",
    "sg:postcode":"84339",
    "sg:province":"UT",
    "wof:name":"Custom Marble Creations Lc",
    "wof:placetype":"venue"
},
  "geometry": {"coordinates":[-111.92612800000001,41.639584],"type":"Point"}
}