{
  "type": "Feature",
  "properties": {
    "iso:country":"US",
    "sg:address":"1304 S 1400 E",
    "sg:city":"Salt Lake City",
    "sg:classifiers":[
        {
            "category":"Professional",
            "subcategory":"Management & Consulting",
            "type":"Services"
        }
    ],
    "sg:phone":"+1 801 582 7385",
    "sg:postcode":"84105",
    "sg:province":"UT",
    "sg:tags":[
        "counselor",
        "public",
        "relations"
    ],
    "wof:name":"Grace Communications Inc",
    "wof:placetype":"venue"
},
  "geometry": {"coordinates":[-111.850987,40.740817],"type":"Point"}
}