{
  "type": "Feature",
  "properties": {
    "iso:country":"US",
    "sg:address":"489 N Main St",
    "sg:city":"Richfield",
    "sg:classifiers":[
        {
            "category":"Health Services",
            "subcategory":"Chiropractor",
            "type":"Services"
        }
    ],
    "sg:phone":"+1 435 896 8820",
    "sg:postcode":"84701",
    "sg:province":"UT",
    "wof:name":"Rose Chiropractic",
    "wof:placetype":"venue"
},
  "geometry": {"coordinates":[-112.084757,38.773828],"type":"Point"}
}