{
  "type": "Feature",
  "properties": {
    "iso:country":"US",
    "sg:address":"11241 Windy Peak Ridge Dr",
    "sg:city":"Sandy",
    "sg:classifiers":[
        {
            "category":"Professional",
            "subcategory":"Computer Services",
            "type":"Services"
        }
    ],
    "sg:phone":"+1 801 495 2212",
    "sg:postcode":"84094",
    "sg:province":"UT",
    "sg:tags":[
        "consulting",
        "related",
        "business"
    ],
    "wof:name":"Colson Consulting",
    "wof:placetype":"venue"
},
  "geometry": {"coordinates":[-111.85882100000001,40.547205],"type":"Point"}
}