{
  "type": "Feature",
  "properties": {
    "iso:country":"US",
    "sg:address":"185 N State St",
    "sg:city":"Richmond",
    "sg:classifiers":[
        {
            "category":"Retail",
            "subcategory":"Auto Repair",
            "type":"Services"
        }
    ],
    "sg:phone":"+1 435 258 5367",
    "sg:postcode":"84333",
    "sg:province":"UT",
    "sg:tags":[
        "automobile",
        "top",
        "upholstery"
    ],
    "wof:name":"Auto Upholstry Anna's",
    "wof:placetype":"venue"
},
  "geometry": {"coordinates":[-111.808667,41.925009],"type":"Point"}
}