{
  "type": "Feature",
  "properties": {
    "iso:country":"US",
    "sg:address":"7390 Creek Road Suite 204",
    "sg:city":"Sandy",
    "sg:classifiers":[
        {
            "category":"Professional",
            "subcategory":"Computer Services",
            "type":"Services"
        }
    ],
    "sg:postcode":"84093",
    "sg:province":"UT",
    "sg:tags":[
        "optimization",
        "wide-are-network",
        "increase-performance"
    ],
    "sg:website":"http://www.exinda.com/",
    "wof:name":"Exinda",
    "wof:placetype":"venue"
},
  "geometry": {"coordinates":[-111.85617499999999,40.615353],"type":"Point"}
}