{
  "type": "Feature",
  "properties": {
    "iso:country":"US",
    "sg:address":"1119 Clubhouse Dr",
    "sg:city":"Salt Lake City",
    "sg:classifiers":[
        {
            "category":"Food & Beverages",
            "subcategory":"Specialty",
            "type":"Retail Goods"
        }
    ],
    "sg:phone":"+1 801 904 3540",
    "sg:postcode":"84123",
    "sg:province":"UT",
    "wof:name":"Good Foods 2 Eat",
    "wof:placetype":"venue"
},
  "geometry": {"coordinates":[-111.92309400000001,40.685484],"type":"Point"}
}