{
  "type": "Feature",
  "properties": {
    "iso:country":"US",
    "sg:address":"313 S 740 E",
    "sg:city":"American Fork",
    "sg:classifiers":[
        {
            "category":"Retail",
            "subcategory":"Laundry & Dry Cleaning",
            "type":"Services"
        }
    ],
    "sg:phone":"+1 801 763 5409",
    "sg:postcode":"84003",
    "sg:province":"UT",
    "wof:name":"Pure Clean Intl",
    "wof:placetype":"venue"
},
  "geometry": {"coordinates":[-111.77889500000001,40.370149],"type":"Point"}
}