{
  "type": "Feature",
  "properties": {
    "iso:country":"US",
    "sg:address":"387 W 200 N",
    "sg:city":"Cedar City",
    "sg:classifiers":[
        {
            "category":"Banks & Credit Unions",
            "subcategory":"Bank",
            "type":"Services"
        }
    ],
    "sg:phone":"+1 435 865 6909",
    "sg:postcode":"84720",
    "sg:province":"UT",
    "sg:tags":[
        "loan",
        "real estate"
    ],
    "wof:name":"Tudor",
    "wof:placetype":"venue"
},
  "geometry": {"coordinates":[-113.068386,37.680874],"type":"Point"}
}