{
  "type": "Feature",
  "properties": {
    "iso:country":"US",
    "sg:address":"389 N 100 W",
    "sg:city":"Cedar City",
    "sg:classifiers":[
        {
            "category":"Retail",
            "subcategory":"Animal Services",
            "type":"Services"
        }
    ],
    "sg:phone":"+1 435 867 5888",
    "sg:postcode":"84720",
    "sg:province":"UT",
    "sg:tags":[
        "pet",
        "grooming",
        "washing"
    ],
    "wof:name":"Paws & Reflect Pet Ctr",
    "wof:placetype":"venue"
},
  "geometry": {"coordinates":[-113.06361800000001,37.684581],"type":"Point"}
}