{
  "type": "Feature",
  "properties": {
    "iso:country":"US",
    "sg:address":"4090 Highland Dr",
    "sg:city":"Holladay",
    "sg:classifiers":[
        {
            "category":"Retail",
            "subcategory":"Auto Repair",
            "type":"Services"
        }
    ],
    "sg:phone":"+1 801 278 0429",
    "sg:postcode":"84124",
    "sg:province":"UT",
    "sg:tags":[
        "repairing",
        "automobile"
    ],
    "wof:name":"Holladay Tunex",
    "wof:placetype":"venue"
},
  "geometry": {"coordinates":[-111.843609,40.682642],"type":"Point"}
}