{
  "type": "Feature",
  "properties": {
    "iso:country":"US",
    "sg:address":"1435 Bennett Cir",
    "sg:city":"Farmington",
    "sg:classifiers":[
        {
            "category":"Professional",
            "subcategory":"Management & Consulting",
            "type":"Services"
        }
    ],
    "sg:phone":"+1 801 451 9348",
    "sg:postcode":"84025",
    "sg:province":"UT",
    "wof:name":"Jennifer R Mettler",
    "wof:placetype":"venue"
},
  "geometry": {"coordinates":[-111.900355,41.004335],"type":"Point"}
}