{
  "type": "Feature",
  "properties": {
    "iso:country":"US",
    "sg:address":"4363 S Weymouth Pl",
    "sg:city":"Salt Lake City",
    "sg:classifiers":[
        {
            "category":"Professional",
            "subcategory":"Management & Consulting",
            "type":"Services"
        }
    ],
    "sg:phone":"+1 801 969 4336",
    "sg:postcode":"84119",
    "sg:province":"UT",
    "sg:tags":[
        "business"
    ],
    "wof:name":"Jensen Business Consultants",
    "wof:placetype":"venue"
},
  "geometry": {"coordinates":[-111.962073,40.676237],"type":"Point"}
}