{
  "type": "Feature",
  "properties": {
    "iso:country":"US",
    "sg:address":"3009 S 2000 E",
    "sg:city":"Salt Lake City",
    "sg:classifiers":[
        {
            "category":"Manufacturing",
            "subcategory":"Printing",
            "type":"Manufacturing & Wholesale Goods"
        }
    ],
    "sg:phone":"+1 801 486 0698",
    "sg:postcode":"84109",
    "sg:province":"UT",
    "sg:tags":[
        "publisher",
        "periodical"
    ],
    "sg:website":"www.offroadpub.com",
    "wof:name":"Off Road Publications",
    "wof:placetype":"venue"
},
  "geometry": {"coordinates":[-111.83406100000001,40.704454],"type":"Point"}
}