{
  "type": "Feature",
  "properties": {
    "iso:country":"US",
    "sg:address":"66 W Harding Ave",
    "sg:city":"Cedar City",
    "sg:classifiers":[
        {
            "category":"Professional",
            "subcategory":"Management & Consulting",
            "type":"Services"
        }
    ],
    "sg:phone":"+1 435 865 9727",
    "sg:postcode":"84720",
    "sg:province":"UT",
    "sg:tags":[
        "consultant"
    ],
    "wof:name":"Brock Asset Consulting",
    "wof:placetype":"venue"
},
  "geometry": {"coordinates":[-113.06280099999999,37.678612],"type":"Point"}
}