{
  "type": "Feature",
  "properties": {
    "iso:country":"US",
    "sg:address":"1335 S Hoffman Ln",
    "sg:city":"Randolph",
    "sg:classifiers":[
        {
            "category":"Government",
            "subcategory":"Fire Station",
            "type":"Public Place"
        }
    ],
    "sg:phone":"+1 435 793 6545",
    "sg:postcode":"84064",
    "sg:province":"UT",
    "sg:tags":[
        "department"
    ],
    "wof:name":"Randolph Fire Chief",
    "wof:placetype":"venue"
},
  "geometry": {"coordinates":[-111.143002,41.645723],"type":"Point"}
}