{
  "type": "Feature",
  "properties": {
    "iso:country":"US",
    "sg:address":"601 W 6960 S",
    "sg:city":"Midvale",
    "sg:classifiers":[
        {
            "category":"Building & Trades",
            "subcategory":"Construction",
            "type":"Services"
        }
    ],
    "sg:phone":"+1 801 565 4500",
    "sg:postcode":"84047",
    "sg:province":"UT",
    "sg:tags":[
        "excavation",
        "underground",
        "utility",
        "contractor"
    ],
    "wof:name":"Steeds Crpt Clg & Restoration",
    "wof:placetype":"venue"
},
  "geometry": {"coordinates":[-111.907613,40.62499],"type":"Point"}
}