{
  "type": "Feature",
  "properties": {
    "iso:country":"US",
    "sg:address":"2746 E 3220 South St",
    "sg:city":"Salt Lake City",
    "sg:classifiers":[
        {
            "category":"Building & Trades",
            "subcategory":"Construction",
            "type":"Services"
        }
    ],
    "sg:phone":"+1 801 463 0654",
    "sg:postcode":"84109",
    "sg:province":"UT",
    "sg:tags":[
        "foundation"
    ],
    "wof:name":"RME",
    "wof:placetype":"venue"
},
  "geometry": {"coordinates":[-111.81126500000001,40.700777],"type":"Point"}
}