{
  "type": "Feature",
  "properties": {
    "iso:country":"US",
    "sg:address":"1898 N 50 W",
    "sg:city":"Orem",
    "sg:classifiers":[
        {
            "category":"Real Estate",
            "subcategory":"Architect",
            "type":"Services"
        }
    ],
    "sg:phone":"+1 801 765 1212",
    "sg:postcode":"84057",
    "sg:province":"UT",
    "wof:name":"Richard Gardner & Assoc",
    "wof:placetype":"venue"
},
  "geometry": {"coordinates":[-111.697368,40.331671],"type":"Point"}
}