{
  "type": "Feature",
  "properties": {
    "iso:country":"US",
    "sg:address":"3685 W 8850 S",
    "sg:city":"West Jordan",
    "sg:classifiers":[
        {
            "category":"Building & Trades",
            "subcategory":"Electrical",
            "type":"Services"
        }
    ],
    "sg:phone":"+1 801 280 0581",
    "sg:postcode":"84088",
    "sg:province":"UT",
    "sg:tags":[
        "electrical",
        "electric",
        "contractor"
    ],
    "wof:name":"Bateman Brothers Electric Inc",
    "wof:placetype":"venue"
},
  "geometry": {"coordinates":[-111.978785,40.590547],"type":"Point"}
}