{
  "type": "Feature",
  "properties": {
    "iso:country":"US",
    "sg:address":"2250 Deer Valley Dr",
    "sg:city":"Park City",
    "sg:classifiers":[
        {
            "category":"Restaurant",
            "type":"Food & Drink"
        }
    ],
    "sg:phone":"+1 435 645 6724",
    "sg:postcode":"84060",
    "sg:province":"UT",
    "sg:tags":[
        "eating"
    ],
    "wof:name":"Royal Street Cafe",
    "wof:placetype":"venue"
},
  "geometry": {"coordinates":[-111.50513100000001,40.656671],"type":"Point"}
}