{
  "type": "Feature",
  "properties": {
    "iso:country":"US",
    "sg:address":"5685 S 625 E",
    "sg:city":"Salt Lake City",
    "sg:classifiers":[
        {
            "category":"Restaurant",
            "type":"Food & Drink"
        }
    ],
    "sg:phone":"+1 801 261 0820",
    "sg:postcode":"84107",
    "sg:province":"UT",
    "sg:tags":[
        "eating"
    ],
    "wof:name":"Basque Club of Utah",
    "wof:placetype":"venue"
},
  "geometry": {"coordinates":[-111.873791,40.648305],"type":"Point"}
}