{
  "type": "Feature",
  "properties": {
    "iso:country":"US",
    "sg:address":"1668 N 1515 E",
    "sg:city":"Logan",
    "sg:classifiers":[
        {
            "category":"Organizations",
            "subcategory":"Membership Organization",
            "type":"Services"
        }
    ],
    "sg:phone":"+1 435 752 5749",
    "sg:postcode":"84341",
    "sg:province":"UT",
    "wof:name":"Cottage Lane Townhomes Assn",
    "wof:placetype":"venue"
},
  "geometry": {"coordinates":[-111.796944,41.76138],"type":"Point"}
}