{
  "type": "Feature",
  "properties": {
    "iso:country":"US",
    "sg:address":"4 Pepperwood Pt",
    "sg:city":"Sandy",
    "sg:classifiers":[
        {
            "category":"Restaurant",
            "type":"Food & Drink"
        }
    ],
    "sg:phone":"+1 801 571 3321",
    "sg:postcode":"84092",
    "sg:province":"UT",
    "sg:tags":[
        "eating"
    ],
    "wof:name":"Jerry G McClain Fmly First LP",
    "wof:placetype":"venue"
},
  "geometry": {"coordinates":[-111.81987599999999,40.555958],"type":"Point"}
}