{
  "type": "Feature",
  "properties": {
    "iso:country":"US",
    "sg:address":"1704 W 2550 S",
    "sg:city":"Ogden",
    "sg:classifiers":[
        {
            "category":"Manufacturing",
            "subcategory":"Tools & Machinery",
            "type":"Manufacturing & Wholesale Goods"
        }
    ],
    "sg:phone":"+1 801 395 1868",
    "sg:postcode":"84401",
    "sg:province":"UT",
    "sg:tags":[
        "pattern",
        "industrial",
        "mfg"
    ],
    "wof:name":"Industrial Supply",
    "wof:placetype":"venue"
},
  "geometry": {"coordinates":[-112.020833,41.219708],"type":"Point"}
}