{
  "type": "Feature",
  "properties": {
    "iso:country":"US",
    "sg:address":"6163 S 700 W",
    "sg:city":"Salt Lake City",
    "sg:classifiers":[
        {
            "category":"Banks & Credit Unions",
            "subcategory":"Bank",
            "type":"Services"
        }
    ],
    "sg:phone":"+1 801 859 2679",
    "sg:postcode":"84123",
    "sg:province":"UT",
    "sg:tags":[
        "broker",
        "mortgage"
    ],
    "wof:name":"National Mortgage Brokers Inc",
    "wof:placetype":"venue"
},
  "geometry": {"coordinates":[-111.91012499999999,40.636561],"type":"Point"}
}