{
  "type": "Feature",
  "properties": {
    "iso:country":"US",
    "sg:address":"185 S State St",
    "sg:city":"Salt Lake City",
    "sg:classifiers":[
        {
            "category":"Restaurant",
            "type":"Food & Drink"
        }
    ],
    "sg:phone":"+1 801 328 2149",
    "sg:postcode":"84111",
    "sg:province":"UT",
    "sg:tags":[
        "eating"
    ],
    "wof:name":"Steaks To Go LLC",
    "wof:placetype":"venue"
},
  "geometry": {"coordinates":[-111.88815200000001,40.76528],"type":"Point"}
}