{
  "type": "Feature",
  "properties": {
    "iso:country":"US",
    "sg:address":"3030 S Main St",
    "sg:city":"Salt Lake City",
    "sg:classifiers":[
        {
            "category":"Banks & Credit Unions",
            "subcategory":"Investment Brokerage",
            "type":"Services"
        }
    ],
    "sg:phone":"+1 801 466 8701",
    "sg:postcode":"84115",
    "sg:province":"UT",
    "sg:tags":[
        "security",
        "stock",
        "bond"
    ],
    "wof:name":"American Funds & Trusts Inc",
    "wof:placetype":"venue"
},
  "geometry": {"coordinates":[-111.891201,40.705114],"type":"Point"}
}