{
  "type": "Feature",
  "properties": {
    "iso:country":"US",
    "sg:address":"31 S 100 E",
    "sg:city":"Kaysville",
    "sg:classifiers":[
        {
            "category":"Building & Trades",
            "subcategory":"Landscaping Services",
            "type":"Services"
        }
    ],
    "sg:phone":"+1 801 544 3836",
    "sg:postcode":"84037",
    "sg:province":"UT",
    "sg:tags":[
        "landscape"
    ],
    "wof:name":"Backcountry Landscape Inc",
    "wof:placetype":"venue"
},
  "geometry": {"coordinates":[-111.936297,41.033716],"type":"Point"}
}