{
  "type": "Feature",
  "properties": {
    "iso:country":"US",
    "sg:address":"219 W Central Ave",
    "sg:city":"Salt Lake City",
    "sg:classifiers":[
        {
            "category":"Building & Trades",
            "subcategory":"Construction",
            "type":"Services"
        }
    ],
    "sg:phone":"+1 801 281 2525",
    "sg:postcode":"84107",
    "sg:province":"UT",
    "sg:tags":[
        "concrete",
        "contractor"
    ],
    "wof:name":"Curbside Concrete Inc",
    "wof:placetype":"venue"
},
  "geometry": {"coordinates":[-111.897705,40.682326],"type":"Point"}
}