{
  "type": "Feature",
  "properties": {
    "iso:country":"US",
    "sg:address":"509 Main St",
    "sg:city":"Park City",
    "sg:classifiers":[
        {
            "category":"Home & Garden",
            "subcategory":"Home Furnishings",
            "type":"Retail Goods"
        }
    ],
    "sg:phone":"+1 435 658 2771",
    "sg:postcode":"84060",
    "sg:province":"UT",
    "sg:tags":[
        "linen"
    ],
    "sg:website":"www.elegantlinenspc.com",
    "wof:name":"Elegant Linens Of Park City",
    "wof:placetype":"venue"
},
  "geometry": {"coordinates":[-111.49688,40.645697],"type":"Point"}
}