{
  "type": "Feature",
  "properties": {
    "iso:country":"US",
    "sg:address":"339 W 840 S",
    "sg:city":"Orem",
    "sg:classifiers":[
        {
            "category":"Building & Trades",
            "subcategory":"Landscaping Services",
            "type":"Services"
        }
    ],
    "sg:phone":"+1 801 224 7510",
    "sg:postcode":"84058",
    "sg:province":"UT",
    "sg:tags":[
        "tree"
    ],
    "wof:name":"Cherry Tree Uni B6",
    "wof:placetype":"venue"
},
  "geometry": {"coordinates":[-111.703853,40.281856],"type":"Point"}
}