{
  "type": "Feature",
  "properties": {
    "iso:country":"US",
    "sg:address":"1475 Wilton Way",
    "sg:city":"Salt Lake City",
    "sg:classifiers":[
        {
            "category":"Banks & Credit Unions",
            "subcategory":"Financial Services",
            "type":"Services"
        }
    ],
    "sg:phone":"+1 801 582 6709",
    "sg:postcode":"84108",
    "sg:province":"UT",
    "sg:tags":[
        "company",
        "holding"
    ],
    "wof:name":"Paulson Holdings LLC",
    "wof:placetype":"venue"
},
  "geometry": {"coordinates":[-111.807509,40.74138],"type":"Point"}
}