{
  "type": "Feature",
  "properties": {
    "iso:country":"US",
    "sg:address":"3100 Highland Dr",
    "sg:city":"Salt Lake City",
    "sg:classifiers":[
        {
            "category":"Food & Beverages",
            "subcategory":"Bakery",
            "type":"Retail Goods"
        }
    ],
    "sg:phone":"+1 801 486 5908",
    "sg:postcode":"84106",
    "sg:province":"UT",
    "wof:name":"Beau Brummel Bakery",
    "wof:placetype":"venue"
},
  "geometry": {"coordinates":[-111.852158,40.703559],"type":"Point"}
}