{
  "type": "Feature",
  "properties": {
    "iso:country":"US",
    "sg:address":"1454 Bus Park Dr",
    "sg:city":"Orem",
    "sg:classifiers":[
        {
            "category":"Communications",
            "subcategory":"Radio Station",
            "type":"Services"
        }
    ],
    "sg:phone":"+1 801 224 1400",
    "sg:postcode":"84058",
    "sg:province":"UT",
    "sg:tags":[
        "company",
        "broadcasting"
    ],
    "wof:name":"KSRR",
    "wof:placetype":"venue"
},
  "geometry": {"coordinates":[-111.729894,40.274385],"type":"Point"}
}