{
  "type": "Feature",
  "properties": {
    "iso:country":"US",
    "sg:address":"555 N 1000 W",
    "sg:city":"Logan",
    "sg:classifiers":[
        {
            "category":"Professional",
            "type":"Services"
        }
    ],
    "sg:phone":"+1 435 753 1950",
    "sg:postcode":"84321",
    "sg:province":"UT",
    "sg:tags":[
        "establishment"
    ],
    "wof:name":"Triag Corp",
    "wof:placetype":"venue"
},
  "geometry": {"coordinates":[-111.859331,41.742048],"type":"Point"}
}