{
  "type": "Feature",
  "properties": {
    "iso:country":"US",
    "sg:address":"1119 Westminster Ave",
    "sg:city":"Salt Lake City",
    "sg:classifiers":[
        {
            "category":"Building & Trades",
            "subcategory":"Cleaning & Sanitation",
            "type":"Services"
        }
    ],
    "sg:phone":"+1 801 486 1362",
    "sg:postcode":"84105",
    "sg:province":"UT",
    "sg:tags":[
        "maintenance"
    ],
    "wof:name":"Extreme Window Cleaning",
    "wof:placetype":"venue"
},
  "geometry": {"coordinates":[-111.857139,40.729344],"type":"Point"}
}