{
  "type": "Feature",
  "properties": {
    "iso:country":"US",
    "sg:address":"1316 US Hwy 89",
    "sg:city":"Farmington",
    "sg:classifiers":[
        {
            "category":"Food & Beverages",
            "subcategory":"Groceries & Convenience Stores",
            "type":"Retail Goods"
        }
    ],
    "sg:phone":"+1 801 451 0581",
    "sg:postcode":"84025",
    "sg:province":"UT",
    "sg:tags":[
        "photofinishing"
    ],
    "wof:name":"Smiths",
    "wof:placetype":"venue"
},
  "geometry": {"coordinates":[-111.908599,41.00185],"type":"Point"}
}