{
  "type": "Feature",
  "properties": {
    "iso:country":"US",
    "sg:address":"2171 W 7000 S",
    "sg:city":"West Jordan",
    "sg:classifiers":[
        {
            "category":"Building & Trades",
            "subcategory":"Construction",
            "type":"Services"
        }
    ],
    "sg:phone":"+1 801 565 8710",
    "sg:postcode":"84084",
    "sg:province":"UT",
    "sg:tags":[
        "house"
    ],
    "wof:name":"Haycock Construction and Rmdlg",
    "wof:placetype":"venue"
},
  "geometry": {"coordinates":[-111.94803400000001,40.623934],"type":"Point"}
}