{
  "type": "Feature",
  "properties": {
    "iso:country":"US",
    "sg:address":"18 Main St",
    "sg:city":"Green River",
    "sg:classifiers":[
        {
            "category":"Restaurant",
            "type":"Food & Drink"
        }
    ],
    "sg:phone":"+1 435 564 3563",
    "sg:postcode":"84525",
    "sg:province":"UT",
    "wof:name":"Chow Hound",
    "wof:placetype":"venue"
},
  "geometry": {"coordinates":[-110.162125,38.995512],"type":"Point"}
}