{
  "type": "Feature",
  "properties": {
    "iso:country":"US",
    "sg:address":"2154 E 3300 S",
    "sg:city":"Salt Lake City",
    "sg:classifiers":[
        {
            "category":"Banks & Credit Unions",
            "subcategory":"Financial Services",
            "type":"Services"
        }
    ],
    "sg:phone":"+1 801 486 2059",
    "sg:postcode":"84109",
    "sg:province":"UT",
    "sg:tags":[
        "investor"
    ],
    "wof:name":"Fulco Investment Inc",
    "wof:placetype":"venue"
},
  "geometry": {"coordinates":[-111.827161,40.699795],"type":"Point"}
}