{
  "type": "Feature",
  "properties": {
    "iso:country":"US",
    "sg:address":"10 E South Temple",
    "sg:city":"Salt Lake City",
    "sg:classifiers":[
        {
            "category":"Professional",
            "subcategory":"Research",
            "type":"Services"
        }
    ],
    "sg:phone":"+1 801 322 3555",
    "sg:postcode":"84111",
    "sg:province":"UT",
    "sg:tags":[
        "foundation",
        "philanthropic"
    ],
    "wof:name":"Simmons Family Foundation",
    "wof:placetype":"venue"
},
  "geometry": {"coordinates":[-111.88840999999999,40.769274],"type":"Point"}
}