{
  "type": "Feature",
  "properties": {
    "iso:country":"US",
    "sg:address":"2550 Washington Blvd",
    "sg:city":"Ogden",
    "sg:classifiers":[
        {
            "category":"Professional",
            "subcategory":"Lawyer & Legal Services",
            "type":"Services"
        }
    ],
    "sg:phone":"+1 801 627 9100",
    "sg:postcode":"84401",
    "sg:province":"UT",
    "sg:tags":[
        "attorney",
        "practice",
        "general"
    ],
    "wof:name":"Law Office Michael Studebaker",
    "wof:placetype":"venue"
},
  "geometry": {"coordinates":[-111.97044200000001,41.21963],"type":"Point"}
}