{
  "type": "Feature",
  "properties": {
    "iso:country":"US",
    "sg:address":"1247 S Main St",
    "sg:city":"Kaysville",
    "sg:classifiers":[
        {
            "category":"Travel",
            "subcategory":"Campground",
            "type":"Entertainment"
        }
    ],
    "sg:phone":"+1 801 451 7437",
    "sg:postcode":"84037",
    "sg:province":"UT",
    "wof:name":"Cherry Hill Pie Pantry",
    "wof:placetype":"venue"
},
  "geometry": {"coordinates":[-111.914975,41.013535],"type":"Point"}
}