{
  "type": "Feature",
  "properties": {
    "iso:country":"US",
    "sg:address":"235 E State Rd",
    "sg:city":"American Fork",
    "sg:classifiers":[
        {
            "category":"Retail",
            "subcategory":"Auto Repair",
            "type":"Services"
        }
    ],
    "sg:phone":"+1 801 756 7047",
    "sg:postcode":"84003",
    "sg:province":"UT",
    "sg:tags":[
        "body"
    ],
    "wof:name":"AF Collision Repair Inc",
    "wof:placetype":"venue"
},
  "geometry": {"coordinates":[-111.79137799999999,40.375418],"type":"Point"}
}