{
  "type": "Feature",
  "properties": {
    "iso:country":"US",
    "sg:address":"92 N Vernal Ave",
    "sg:city":"Vernal",
    "sg:classifiers":[
        {
            "category":"Professional",
            "subcategory":"Accounting & Tax Preparation",
            "type":"Services"
        }
    ],
    "sg:phone":"+1 435 789 0961",
    "sg:postcode":"84078",
    "sg:province":"UT",
    "sg:tags":[
        "accountant"
    ],
    "wof:name":"Caldwell Coombs & Foley LLP",
    "wof:placetype":"venue"
},
  "geometry": {"coordinates":[-109.528465,40.455805],"type":"Point"}
}