{
  "type": "Feature",
  "properties": {
    "iso:country":"US",
    "sg:address":"2093 E 9400 S",
    "sg:city":"Sandy",
    "sg:classifiers":[
        {
            "category":"Retail",
            "subcategory":"Laundry & Dry Cleaning",
            "type":"Services"
        }
    ],
    "sg:phone":"+1 801 943 8886",
    "sg:postcode":"84093",
    "sg:province":"UT",
    "sg:tags":[
        "cleaners"
    ],
    "wof:name":"Kenton Henrie's Cleaners",
    "wof:placetype":"venue"
},
  "geometry": {"coordinates":[-111.831327,40.58054],"type":"Point"}
}