{
  "type": "Feature",
  "properties": {
    "iso:country":"US",
    "sg:address":"3920 S 1100 E",
    "sg:city":"Salt Lake City",
    "sg:classifiers":[
        {
            "category":"Health Services",
            "subcategory":"Medical Lab",
            "type":"Services"
        }
    ],
    "sg:phone":"+1 801 264 8351",
    "sg:postcode":"84124",
    "sg:province":"UT",
    "sg:tags":[
        "laboratory"
    ],
    "wof:name":"Laboratory Corporation America",
    "wof:placetype":"venue"
},
  "geometry": {"coordinates":[-111.859889,40.686238],"type":"Point"}
}