{
  "type": "Feature",
  "properties": {
    "iso:country":"US",
    "sg:address":"4639 Holladay Blvd",
    "sg:city":"Holladay",
    "sg:classifiers":[
        {
            "category":"Home & Garden",
            "subcategory":"Building Materials",
            "type":"Retail Goods"
        }
    ],
    "sg:phone":"+1 801 277 2621",
    "sg:postcode":"84117",
    "sg:province":"UT",
    "sg:tags":[
        "lumber"
    ],
    "sg:website":"www.burtonlumber.com",
    "wof:name":"Burton Lumber",
    "wof:placetype":"venue"
},
  "geometry": {"coordinates":[-111.82651199999999,40.670912],"type":"Point"}
}