{
  "type": "Feature",
  "properties": {
    "iso:country":"US",
    "sg:address":"2917 Highland Dr",
    "sg:city":"Salt Lake City",
    "sg:classifiers":[
        {
            "category":"Food & Beverages",
            "subcategory":"Groceries & Convenience Stores",
            "type":"Retail Goods"
        }
    ],
    "sg:phone":"+1 801 486 1453",
    "sg:postcode":"84106",
    "sg:province":"UT",
    "wof:name":"7-Eleven",
    "wof:placetype":"venue"
},
  "geometry": {"coordinates":[-111.853424,40.707649],"type":"Point"}
}