{
  "type": "Feature",
  "properties": {
    "iso:country":"US",
    "sg:address":"156 W 450 N",
    "sg:city":"Lindon",
    "sg:classifiers":[
        {
            "category":"Building & Trades",
            "subcategory":"Cleaning & Sanitation",
            "type":"Services"
        }
    ],
    "sg:phone":"+1 801 785 5723",
    "sg:postcode":"84042",
    "sg:province":"UT",
    "sg:tags":[
        "maintenance"
    ],
    "wof:name":"R G D",
    "wof:placetype":"venue"
},
  "geometry": {"coordinates":[-111.717854,40.346205],"type":"Point"}
}