{
  "type": "Feature",
  "properties": {
    "iso:country":"US",
    "sg:address":"780 S 400 W",
    "sg:city":"Salt Lake City",
    "sg:classifiers":[
        {
            "category":"Home & Garden",
            "subcategory":"Building Materials",
            "type":"Retail Goods"
        }
    ],
    "sg:phone":"+1 801 355 7577",
    "sg:postcode":"84101",
    "sg:province":"UT",
    "sg:tags":[
        "glass",
        "window",
        "plate"
    ],
    "wof:name":"Central Glass Co",
    "wof:placetype":"venue"
},
  "geometry": {"coordinates":[-111.902599,40.753718],"type":"Point"}
}