{
  "type": "Feature",
  "properties": {
    "iso:country":"US",
    "sg:address":"1833 N 600 W",
    "sg:city":"Woods Cross",
    "sg:classifiers":[
        {
            "category":"Professional",
            "subcategory":"Management & Consulting",
            "type":"Services"
        }
    ],
    "sg:phone":"+1 801 294 5210",
    "sg:postcode":"84087",
    "sg:province":"UT",
    "sg:tags":[
        "retail",
        "direct",
        "sales"
    ],
    "wof:name":"Grolier Educational",
    "wof:placetype":"venue"
},
  "geometry": {"coordinates":[-111.895377,40.909248],"type":"Point"}
}