{
  "type": "Feature",
  "properties": {
    "iso:country":"US",
    "sg:address":"99 N 2nd St",
    "sg:city":"Tooele",
    "sg:classifiers":[
        {
            "category":"Restaurant",
            "type":"Food & Drink"
        }
    ],
    "sg:phone":"+1 435 882 6267",
    "sg:postcode":"84074",
    "sg:province":"UT",
    "sg:tags":[
        "caterer"
    ],
    "wof:name":"Zanny's Beauty Solan",
    "wof:placetype":"venue"
},
  "geometry": {"coordinates":[-112.290511,40.531317],"type":"Point"}
}