{
  "type": "Feature",
  "properties": {
    "iso:country":"US",
    "sg:address":"1220 E 3300 S",
    "sg:city":"Salt Lake City",
    "sg:classifiers":[
        {
            "category":"Home & Garden",
            "subcategory":"Home Furnishings",
            "type":"Retail Goods"
        }
    ],
    "sg:phone":"+1 801 484 8571",
    "sg:postcode":"84106",
    "sg:province":"UT",
    "sg:tags":[
        "lighting",
        "fixture"
    ],
    "sg:website":"www.feltlighting.com",
    "wof:name":"Felt Lighting Inc",
    "wof:placetype":"venue"
},
  "geometry": {"coordinates":[-111.85712100000001,40.69984],"type":"Point"}
}