{
  "type": "Feature",
  "properties": {
    "iso:country":"US",
    "sg:address":"1480 S 1100 E",
    "sg:city":"Salt Lake City",
    "sg:classifiers":[
        {
            "category":"Manufacturing",
            "subcategory":"Paper Products",
            "type":"Manufacturing & Wholesale Goods"
        }
    ],
    "sg:phone":"+1 801 694 9006",
    "sg:postcode":"84105",
    "sg:province":"UT",
    "sg:tags":[
        "stationery",
        "prod"
    ],
    "wof:name":"Coil Designs",
    "wof:placetype":"venue"
},
  "geometry": {"coordinates":[-111.85968,40.737675],"type":"Point"}
}