{
  "type": "Feature",
  "properties": {
    "iso:country":"US",
    "sg:address":"2094 E Deer Run Dr",
    "sg:city":"Ogden",
    "sg:classifiers":[
        {
            "category":"Building & Trades",
            "subcategory":"Construction",
            "type":"Services"
        }
    ],
    "sg:phone":"+1 801 476 1022",
    "sg:postcode":"84405",
    "sg:province":"UT",
    "sg:tags":[
        "general",
        "contractor"
    ],
    "wof:name":"J A Halverson Mechanical Inc",
    "wof:placetype":"venue"
},
  "geometry": {"coordinates":[-111.926666,41.120976],"type":"Point"}
}