{
  "type": "Feature",
  "properties": {
    "iso:country":"US",
    "sg:address":"421 E 700 S",
    "sg:city":"Centerville",
    "sg:classifiers":[
        {
            "category":"Real Estate",
            "subcategory":"Real Estate Agent",
            "type":"Services"
        }
    ],
    "sg:phone":"+1 801 299 1707",
    "sg:postcode":"84014",
    "sg:province":"UT",
    "wof:name":"Ellis Kevin J & Assoc REA",
    "wof:placetype":"venue"
},
  "geometry": {"coordinates":[-111.871853,40.909844],"type":"Point"}
}