{
  "type": "Feature",
  "properties": {
    "iso:country":"US",
    "sg:address":"966 S Redwood Rd",
    "sg:city":"Salt Lake City",
    "sg:classifiers":[
        {
            "category":"Cinema",
            "subcategory":"Movie Rental",
            "type":"Entertainment"
        }
    ],
    "sg:phone":"+1 801 978 0524",
    "sg:postcode":"84104",
    "sg:province":"UT",
    "sg:tags":[
        "leasing",
        "video",
        "disc",
        "tape"
    ],
    "wof:name":"LA Milpa",
    "wof:placetype":"venue"
},
  "geometry": {"coordinates":[-111.93907,40.747978],"type":"Point"}
}