{
  "type": "Feature",
  "properties": {
    "iso:country":"US",
    "sg:address":"1001 N 1200 W",
    "sg:city":"Orem",
    "sg:classifiers":[
        {
            "category":"Mining & Drilling",
            "type":"Manufacturing & Wholesale Goods"
        }
    ],
    "sg:phone":"+1 801 221 9500",
    "sg:postcode":"84057",
    "sg:province":"UT",
    "sg:tags":[
        "stone"
    ],
    "wof:name":"Stone Source Inc",
    "wof:placetype":"venue"
},
  "geometry": {"coordinates":[-111.72463399999999,40.315512],"type":"Point"}
}