{
  "type": "Feature",
  "properties": {
    "iso:country":"US",
    "sg:address":"578 S Blossom Cir",
    "sg:city":"Kaysville",
    "sg:classifiers":[
        {
            "category":"Organizations",
            "subcategory":"Labor Organization",
            "type":"Services"
        }
    ],
    "sg:phone":"+1 801 546 6280",
    "sg:postcode":"84037",
    "sg:province":"UT",
    "wof:name":"Dreamwork Innovations Lc",
    "wof:placetype":"venue"
},
  "geometry": {"coordinates":[-111.90160400000001,41.024226],"type":"Point"}
}