{
  "type": "Feature",
  "properties": {
    "iso:country":"US",
    "sg:address":"25 W 400 N",
    "sg:city":"Monroe",
    "sg:classifiers":[
        {
            "category":"Building & Trades",
            "subcategory":"Construction",
            "type":"Services"
        }
    ],
    "sg:phone":"+1 435 527 3247",
    "sg:postcode":"84754",
    "sg:province":"UT",
    "sg:tags":[
        "house"
    ],
    "wof:name":"Springer Construction",
    "wof:placetype":"venue"
},
  "geometry": {"coordinates":[-112.12311800000001,38.638792],"type":"Point"}
}