{
  "type": "Feature",
  "properties": {
    "iso:country":"US",
    "sg:address":"1612 E 3300 S",
    "sg:city":"Salt Lake City",
    "sg:classifiers":[
        {
            "category":"Real Estate",
            "subcategory":"Real Estate Operator",
            "type":"Services"
        }
    ],
    "sg:phone":"+1 801 486 3330",
    "sg:postcode":"84106",
    "sg:province":"UT",
    "sg:tags":[
        "property",
        "lessor"
    ],
    "wof:name":"Early Enterprises",
    "wof:placetype":"venue"
},
  "geometry": {"coordinates":[-111.843598,40.699877],"type":"Point"}
}