{
  "type": "Feature",
  "properties": {
    "iso:country":"US",
    "sg:address":"385 N Main St",
    "sg:city":"Centerfield",
    "sg:classifiers":[
        {
            "category":"Home & Garden",
            "subcategory":"Garden Supply",
            "type":"Retail Goods"
        }
    ],
    "sg:phone":"+1 435 528 3679",
    "sg:postcode":"84622",
    "sg:province":"UT",
    "sg:tags":[
        "nurseryman"
    ],
    "wof:name":"Skyview Landscape Nursery",
    "wof:placetype":"venue"
},
  "geometry": {"coordinates":[-111.819131,39.13263],"type":"Point"}
}