{
  "type": "Feature",
  "properties": {
    "iso:country":"US",
    "sg:address":"2417 E 9110 S",
    "sg:city":"Sandy",
    "sg:classifiers":[
        {
            "category":"Professional",
            "subcategory":"Lawyer & Legal Services",
            "type":"Services"
        }
    ],
    "sg:phone":"+1 801 942 2078",
    "sg:postcode":"84093",
    "sg:province":"UT",
    "sg:tags":[
        "attorney"
    ],
    "wof:name":"D Kendall Perkins Attrny",
    "wof:placetype":"venue"
},
  "geometry": {"coordinates":[-111.821175,40.585763],"type":"Point"}
}