{
  "type": "Feature",
  "properties": {
    "iso:country":"US",
    "sg:address":"537 W 600 S",
    "sg:city":"Salt Lake City",
    "sg:classifiers":[
        {
            "category":"Professional",
            "subcategory":"Business Services",
            "type":"Services"
        }
    ],
    "sg:phone":"+1 801 595 1900",
    "sg:postcode":"84101",
    "sg:province":"UT",
    "wof:name":"Business Concepts",
    "wof:placetype":"venue"
},
  "geometry": {"coordinates":[-111.907218,40.756217],"type":"Point"}
}