{
  "type": "Feature",
  "properties": {
    "iso:country":"US",
    "sg:address":"66 W 2100 S",
    "sg:city":"Salt Lake City",
    "sg:classifiers":[
        {
            "category":"Insurance",
            "subcategory":"Insurance Agent",
            "type":"Services"
        }
    ],
    "sg:phone":"+1 801 486 3141",
    "sg:postcode":"84115",
    "sg:province":"UT",
    "wof:name":"Allstate Insurance",
    "wof:placetype":"venue"
},
  "geometry": {"coordinates":[-111.893523,40.725506],"type":"Point"}
}