{
  "type": "Feature",
  "properties": {
    "iso:country":"US",
    "sg:address":"1192 Canyon Rd",
    "sg:city":"Logan",
    "sg:classifiers":[
        {
            "category":"Shopping",
            "subcategory":"Florist",
            "type":"Retail Goods"
        }
    ],
    "sg:phone":"+1 435 752 6348",
    "sg:postcode":"84321",
    "sg:province":"UT",
    "wof:name":"Pehrson Floral Inc",
    "wof:placetype":"venue"
},
  "geometry": {"coordinates":[-111.80691899999999,41.739322],"type":"Point"}
}