{
  "type": "Feature",
  "properties": {
    "iso:country":"US",
    "sg:address":"3544 Lincoln Ave",
    "sg:city":"Ogden",
    "sg:classifiers":[
        {
            "category":"Education",
            "subcategory":"Special Training",
            "type":"Public Place"
        }
    ],
    "sg:phone":"+1 801 393 3009",
    "sg:postcode":"84401",
    "sg:province":"UT",
    "wof:name":"Learning Technics",
    "wof:placetype":"venue"
},
  "geometry": {"coordinates":[-111.976477,41.199737],"type":"Point"}
}