{
  "type": "Feature",
  "properties": {
    "iso:country":"US",
    "sg:address":"392 W Winchester St",
    "sg:city":"Murray",
    "sg:classifiers":[
        {
            "category":"Wholesale",
            "subcategory":"Sporting Goods",
            "type":"Manufacturing & Wholesale Goods"
        }
    ],
    "sg:phone":"+1 801 268 1565",
    "sg:postcode":"84107",
    "sg:province":"UT",
    "sg:tags":[
        "spa",
        "hot",
        "tub"
    ],
    "sg:website":"www.hwpinc.com",
    "wof:name":"HWP Inc",
    "wof:placetype":"venue"
},
  "geometry": {"coordinates":[-111.90243599999999,40.632532],"type":"Point"}
}