{
  "type": "Feature",
  "properties": {
    "iso:country":"US",
    "sg:address":"128 N Main St",
    "sg:city":"Layton",
    "sg:classifiers":[
        {
            "category":"Home & Garden",
            "subcategory":"Carpets & Floor Coverings",
            "type":"Retail Goods"
        }
    ],
    "sg:phone":"+1 801 544 2284",
    "sg:postcode":"84041",
    "sg:province":"UT",
    "wof:name":"Abbey Carpet Of Layton",
    "wof:placetype":"venue"
},
  "geometry": {"coordinates":[-111.968827,41.063284],"type":"Point"}
}