{
  "type": "Feature",
  "properties": {
    "iso:country":"US",
    "sg:address":"48 Guinevere Cir",
    "sg:city":"Roosevelt",
    "sg:classifiers":[
        {
            "category":"Retail",
            "subcategory":"Repair Shop",
            "type":"Services"
        }
    ],
    "sg:phone":"+1 435 722 2319",
    "sg:postcode":"84066",
    "sg:province":"UT",
    "sg:tags":[
        "welding"
    ],
    "wof:name":"Phillip Kettle Welding",
    "wof:placetype":"venue"
},
  "geometry": {"coordinates":[-110.006624,40.299079],"type":"Point"}
}