{
  "type": "Feature",
  "properties": {
    "iso:country":"US",
    "sg:address":"3448 S 100 W",
    "sg:city":"Bountiful",
    "sg:classifiers":[
        {
            "category":"Real Estate",
            "subcategory":"Surveying",
            "type":"Services"
        }
    ],
    "sg:phone":"+1 801 298 1615",
    "sg:postcode":"84010",
    "sg:province":"UT",
    "wof:name":"Richardson Surveying Inc",
    "wof:placetype":"venue"
},
  "geometry": {"coordinates":[-111.88286100000001,40.852355],"type":"Point"}
}