{
  "type": "Feature",
  "properties": {
    "iso:country":"US",
    "sg:address":"6246 S Redwood Rd",
    "sg:city":"Salt Lake City",
    "sg:classifiers":[
        {
            "category":"Social Services",
            "subcategory":"Job Training",
            "type":"Services"
        }
    ],
    "sg:phone":"+1 801 955 0690",
    "sg:postcode":"84123",
    "sg:province":"UT",
    "sg:tags":[
        "rehabilitation"
    ],
    "wof:name":"Mountain Land Rehab",
    "wof:placetype":"venue"
},
  "geometry": {"coordinates":[-111.938829,40.636277],"type":"Point"}
}