{
  "type": "Feature",
  "properties": {
    "iso:country":"US",
    "sg:address":"148 E 13800 S",
    "sg:city":"Draper",
    "sg:classifiers":[
        {
            "category":"Building & Trades",
            "subcategory":"Construction",
            "type":"Services"
        }
    ],
    "sg:phone":"+1 801 571 2450",
    "sg:postcode":"84020",
    "sg:province":"UT",
    "sg:tags":[
        "dry wall",
        "contractor"
    ],
    "wof:name":"Leon Christensen Dry Wall Inc",
    "wof:placetype":"venue"
},
  "geometry": {"coordinates":[-111.885578,40.500609],"type":"Point"}
}