{
  "type": "Feature",
  "properties": {
    "iso:country":"US",
    "sg:address":"11491 Cranberry Hill Ct",
    "sg:city":"Draper",
    "sg:classifiers":[
        {
            "category":"Shopping",
            "subcategory":"Computers & Home Electronics",
            "type":"Retail Goods"
        }
    ],
    "sg:phone":"+1 801 572 0474",
    "sg:postcode":"84020",
    "sg:province":"UT",
    "sg:tags":[
        "equipment",
        "dealer"
    ],
    "wof:name":"En Pointe Technologies",
    "wof:placetype":"venue"
},
  "geometry": {"coordinates":[-111.882302,40.542558],"type":"Point"}
}