{
  "type": "Feature",
  "properties": {
    "iso:country":"US",
    "sg:address":"881 E 2730 N",
    "sg:city":"Provo",
    "sg:classifiers":[
        {
            "category":"Food & Beverages",
            "subcategory":"Specialty",
            "type":"Retail Goods"
        }
    ],
    "sg:phone":"+1 801 375 7722",
    "sg:postcode":"84604",
    "sg:province":"UT",
    "wof:name":"New Image Health Center",
    "wof:placetype":"venue"
},
  "geometry": {"coordinates":[-111.64274,40.269804],"type":"Point"}
}