{
  "type": "Feature",
  "properties": {
    "iso:country":"US",
    "sg:address":"2804 S State St",
    "sg:city":"Salt Lake City",
    "sg:classifiers":[
        {
            "category":"Retail",
            "subcategory":"Repair Shop",
            "type":"Services"
        }
    ],
    "sg:phone":"+1 801 467 6644",
    "sg:postcode":"84115",
    "sg:province":"UT",
    "wof:name":"Davidson Doll Hospital",
    "wof:placetype":"venue"
},
  "geometry": {"coordinates":[-111.88832600000001,40.709772],"type":"Point"}
}