{
  "type": "Feature",
  "properties": {
    "iso:country":"US",
    "sg:address":"52 Main St",
    "sg:city":"Coalville",
    "sg:classifiers":[
        {
            "category":"Retail",
            "subcategory":"Auto Repair",
            "type":"Services"
        }
    ],
    "sg:phone":"+1 435 336 2213",
    "sg:postcode":"84017",
    "sg:province":"UT",
    "sg:tags":[
        "repairing",
        "automobile"
    ],
    "wof:name":"Autoville",
    "wof:placetype":"venue"
},
  "geometry": {"coordinates":[-111.399896,40.918766],"type":"Point"}
}