{
  "type": "Feature",
  "properties": {
    "iso:country":"US",
    "sg:address":"106 State St",
    "sg:city":"Sandy",
    "sg:classifiers":[
        {
            "category":"Shopping",
            "subcategory":"Clothing, Apparel, & Fashions",
            "type":"Retail Goods"
        }
    ],
    "sg:phone":"+1 801 523 3977",
    "sg:postcode":"84062",
    "sg:province":"UT",
    "wof:name":"Timothy Flannery",
    "wof:placetype":"venue"
},
  "geometry": {"coordinates":[-111.738184,40.357289],"type":"Point"}
}