{
  "type": "Feature",
  "properties": {
    "iso:country":"US",
    "sg:address":"676 W 800 S",
    "sg:city":"Alpine",
    "sg:classifiers":[
        {
            "category":"Mining & Drilling",
            "type":"Manufacturing & Wholesale Goods"
        }
    ],
    "sg:phone":"+1 801 756 6388",
    "sg:postcode":"84004",
    "sg:province":"UT",
    "sg:tags":[
        "coal"
    ],
    "wof:name":"SMS Stolworthy Mining Services",
    "wof:placetype":"venue"
},
  "geometry": {"coordinates":[-111.791866,40.441528],"type":"Point"}
}