{
  "type": "Feature",
  "properties": {
    "iso:country":"US",
    "sg:address":"675 E 500 S",
    "sg:city":"Salt Lake City",
    "sg:classifiers":[
        {
            "category":"Wholesale",
            "subcategory":"Office Equipment",
            "type":"Manufacturing & Wholesale Goods"
        }
    ],
    "sg:phone":"+1 801 535 8500",
    "sg:postcode":"84102",
    "sg:province":"UT",
    "wof:name":"Xerox",
    "wof:placetype":"venue"
},
  "geometry": {"coordinates":[-111.871696,40.75856],"type":"Point"}
}