{
  "type": "Feature",
  "properties": {
    "iso:country":"US",
    "sg:address":"706 Country Club",
    "sg:city":"Tooele",
    "sg:classifiers":[
        {
            "category":"Wholesale",
            "subcategory":"Non-durable Goods",
            "type":"Manufacturing & Wholesale Goods"
        }
    ],
    "sg:phone":"+1 435 833 9463",
    "sg:postcode":"84074",
    "sg:province":"UT",
    "sg:tags":[
        "mail",
        "house"
    ],
    "wof:name":"A 1 Wholesale Gift & Treasures",
    "wof:placetype":"venue"
},
  "geometry": {"coordinates":[-112.296897,40.633821],"type":"Point"}
}