{
  "type": "Feature",
  "properties": {
    "iso:country":"US",
    "sg:address":"1309 W 400 N",
    "sg:city":"Woods Cross",
    "sg:classifiers":[
        {
            "category":"Real Estate",
            "subcategory":"Real Estate Agent",
            "type":"Services"
        }
    ],
    "sg:phone":"+1 801 299 7780",
    "sg:postcode":"84087",
    "sg:province":"UT",
    "wof:name":"Realty Quest",
    "wof:placetype":"venue"
},
  "geometry": {"coordinates":[-111.916072,40.893955],"type":"Point"}
}