{
  "type": "Feature",
  "properties": {
    "iso:country":"US",
    "sg:address":"58 S 950 W",
    "sg:city":"Brigham City",
    "sg:classifiers":[
        {
            "category":"Government",
            "subcategory":"Office",
            "type":"Public Place"
        }
    ],
    "sg:phone":"+1 435 723 5887",
    "sg:postcode":"84302",
    "sg:province":"UT",
    "sg:tags":[
        "wildlife",
        "conservation",
        "agency"
    ],
    "wof:name":"Bear Rvr Migratory Bird Refuge",
    "wof:placetype":"venue"
},
  "geometry": {"coordinates":[-112.03137099999999,41.509436],"type":"Point"}
}