{
  "type": "Feature",
  "properties": {
    "iso:country":"US",
    "sg:address":"578 E University Pkwy",
    "sg:city":"Orem",
    "sg:classifiers":[
        {
            "category":"Home & Garden",
            "subcategory":"Household Appliances",
            "type":"Retail Goods"
        }
    ],
    "sg:phone":"+1 801 426 5302",
    "sg:postcode":"84097",
    "sg:province":"UT",
    "sg:tags":[
        "cleaners",
        "vacuum"
    ],
    "wof:name":"Oreck Vacuums",
    "wof:placetype":"venue"
},
  "geometry": {"coordinates":[-111.679322,40.273142],"type":"Point"}
}