{
  "type": "Feature",
  "properties": {
    "iso:country":"US",
    "sg:address":"201 S Main St",
    "sg:city":"Salt Lake City",
    "sg:classifiers":[
        {
            "category":"Professional",
            "subcategory":"Research",
            "type":"Services"
        },
        {
            "category":"Professional",
            "subcategory":"Management & Consulting",
            "type":"Services"
        }
    ],
    "sg:phone":"+1 801 364 6233",
    "sg:postcode":"84111",
    "sg:province":"UT",
    "sg:tags":[
        "economic",
        "analysis",
        "business"
    ],
    "sg:website":"www.lecg.com",
    "wof:name":"Lecg LLC",
    "wof:placetype":"venue"
},
  "geometry": {"coordinates":[-111.891093,40.762823],"type":"Point"}
}