{
  "type": "Feature",
  "properties": {
    "iso:country":"US",
    "sg:address":"1137 Hackamore Dr",
    "sg:city":"Draper",
    "sg:classifiers":[
        {
            "category":"Real Estate",
            "subcategory":"Developer",
            "type":"Services"
        }
    ],
    "sg:phone":"+1 801 571 1638",
    "sg:postcode":"84020",
    "sg:province":"UT",
    "wof:name":"Crescent Office Park LLC",
    "wof:placetype":"venue"
},
  "geometry": {"coordinates":[-111.858655,40.502457],"type":"Point"}
}