{
  "type": "Feature",
  "properties": {
    "iso:country":"US",
    "sg:address":"2665 Lincoln Ave",
    "sg:city":"Ogden",
    "sg:classifiers":[
        {
            "category":"Shopping",
            "subcategory":"Clothing, Apparel, & Fashions",
            "type":"Retail Goods"
        }
    ],
    "sg:phone":"+1 801 621 2600",
    "sg:postcode":"84401",
    "sg:province":"UT",
    "wof:name":"La Esperanza",
    "wof:placetype":"venue"
},
  "geometry": {"coordinates":[-111.976264,41.217091],"type":"Point"}
}