{
  "type": "Feature",
  "properties": {
    "iso:country":"US",
    "sg:address":"1262 N Main St",
    "sg:city":"Tooele",
    "sg:classifiers":[
        {
            "category":"Retail",
            "subcategory":"Car Wash",
            "type":"Services"
        }
    ],
    "sg:phone":"+1 435 884 5528",
    "sg:postcode":"84074",
    "sg:province":"UT",
    "sg:tags":[
        "operated",
        "polishing",
        "washing"
    ],
    "wof:name":"One Way Car Wash",
    "wof:placetype":"venue"
},
  "geometry": {"coordinates":[-112.29736800000001,40.555808],"type":"Point"}
}