{
  "type": "Feature",
  "properties": {
    "iso:country":"US",
    "sg:address":"919 Redford Dr",
    "sg:city":"Provo",
    "sg:classifiers":[
        {
            "category":"Retail",
            "subcategory":"Portrait Studio",
            "type":"Services"
        }
    ],
    "sg:phone":"+1 801 224 2378",
    "sg:postcode":"84604",
    "sg:province":"UT",
    "sg:tags":[
        "photo"
    ],
    "wof:name":"Doti Portrait Art Photography",
    "wof:placetype":"venue"
},
  "geometry": {"coordinates":[-111.643834,40.293679],"type":"Point"}
}