{
  "type": "Feature",
  "properties": {
    "iso:country":"US",
    "sg:address":"639 E 1500 S",
    "sg:city":"Kaysville",
    "sg:classifiers":[
        {
            "category":"Manufacturing",
            "subcategory":"Glass & Minerals",
            "type":"Manufacturing & Wholesale Goods"
        }
    ],
    "sg:phone":"+1 801 451 6958",
    "sg:postcode":"84037",
    "sg:province":"UT",
    "sg:tags":[
        "product",
        "mfg"
    ],
    "wof:name":"Sher & Sher Alike Creatio",
    "wof:placetype":"venue"
},
  "geometry": {"coordinates":[-111.924851,41.010579],"type":"Point"}
}