{
  "type": "Feature",
  "properties": {
    "iso:country":"US",
    "sg:address":"2470 E 6660 S",
    "sg:city":"Salt Lake City",
    "sg:classifiers":[
        {
            "category":"Professional",
            "subcategory":"Advertising",
            "type":"Services"
        }
    ],
    "sg:phone":"+1 801 943 6466",
    "sg:postcode":"84121",
    "sg:province":"UT",
    "sg:tags":[
        "agency"
    ],
    "wof:name":"Link Advertising",
    "wof:placetype":"venue"
},
  "geometry": {"coordinates":[-111.821079,40.630199],"type":"Point"}
}