{
  "type": "Feature",
  "properties": {
    "iso:country":"US",
    "sg:address":"9782 N 5740 W",
    "sg:city":"American Fork",
    "sg:classifiers":[
        {
            "category":"Building & Trades",
            "subcategory":"Construction",
            "type":"Services"
        }
    ],
    "sg:phone":"+1 801 763 7567",
    "sg:postcode":"84003",
    "sg:province":"UT",
    "sg:tags":[
        "house"
    ],
    "wof:name":"Edward Anderson Construction",
    "wof:placetype":"venue"
},
  "geometry": {"coordinates":[-111.794943,40.409718],"type":"Point"}
}