{
  "type": "Feature",
  "properties": {
    "iso:country":"US",
    "sg:address":"87 E Center St",
    "sg:city":"Spanish Fork",
    "sg:classifiers":[
        {
            "category":"Insurance",
            "subcategory":"Insurance Agent",
            "type":"Services"
        }
    ],
    "sg:phone":"+1 801 798 7461",
    "sg:postcode":"84660",
    "sg:province":"UT",
    "wof:name":"Western States Insurance",
    "wof:placetype":"venue"
},
  "geometry": {"coordinates":[-111.65358500000001,40.109898],"type":"Point"}
}