{
  "type": "Feature",
  "properties": {
    "iso:country":"US",
    "sg:address":"11204 Tall Pines Way",
    "sg:city":"Sandy",
    "sg:classifiers":[
        {
            "category":"Real Estate",
            "subcategory":"Real Estate Operator",
            "type":"Services"
        }
    ],
    "sg:phone":"+1 801 576 9212",
    "sg:postcode":"84092",
    "sg:province":"UT",
    "sg:tags":[
        "building",
        "nonresidential"
    ],
    "wof:name":"Solution Properties LLC",
    "wof:placetype":"venue"
},
  "geometry": {"coordinates":[-111.83466799999999,40.546965],"type":"Point"}
}