{
  "type": "Feature",
  "properties": {
    "iso:country":"US",
    "sg:address":"2370 Washington Blvd",
    "sg:city":"Ogden",
    "sg:classifiers":[
        {
            "category":"Shopping",
            "subcategory":"Jewelry",
            "type":"Retail Goods"
        }
    ],
    "sg:phone":"+1 801 778 2032",
    "sg:postcode":"84401",
    "sg:province":"UT",
    "wof:name":"Finlay Fine Jewelry Corp",
    "wof:placetype":"venue"
},
  "geometry": {"coordinates":[-111.97031800000001,41.224249],"type":"Point"}
}