{
  "type": "Feature",
  "properties": {
    "iso:country":"US",
    "sg:address":"4440 S 4000 W",
    "sg:city":"Delta",
    "sg:classifiers":[
        {
            "category":"Banks & Credit Unions",
            "subcategory":"Financial Services",
            "type":"Services"
        }
    ],
    "sg:phone":"+1 435 864 3628",
    "sg:postcode":"84624",
    "sg:province":"UT",
    "sg:tags":[
        "trust",
        "management"
    ],
    "wof:name":"Waldo Black Family Trust",
    "wof:placetype":"venue"
},
  "geometry": {"coordinates":[-112.652779,39.287064],"type":"Point"}
}