{
  "type": "Feature",
  "properties": {
    "iso:country":"US",
    "sg:address":"620 N 1600 W",
    "sg:city":"Lewiston",
    "sg:phone":"+1 435 258 2657",
    "sg:postcode":"84320",
    "sg:province":"UT",
    "sg:tags":[
        "farm",
        "field",
        "crop"
    ],
    "wof:name":"Russell Hatch",
    "wof:placetype":"venue"
},
  "geometry": {"coordinates":[-111.895655,41.97891],"type":"Point"}
}