{
  "type": "Feature",
  "properties": {
    "iso:country":"US",
    "sg:address":"8110 Top of the World Dr",
    "sg:city":"Salt Lake City",
    "sg:classifiers":[
        {
            "category":"Banks & Credit Unions",
            "subcategory":"Investment Brokerage",
            "type":"Services"
        }
    ],
    "sg:phone":"+1 801 944 4292",
    "sg:postcode":"84121",
    "sg:province":"UT",
    "sg:tags":[
        "consultant",
        "planning",
        "financial"
    ],
    "wof:name":"Financial Services & Insurance",
    "wof:placetype":"venue"
},
  "geometry": {"coordinates":[-111.791893,40.603458],"type":"Point"}
}