{
  "type": "Feature",
  "properties": {
    "iso:country":"US",
    "sg:address":"1101 S Freeport Industrial Pkwy",
    "sg:city":"Clearfield",
    "sg:classifiers":[
        {
            "category":"Freight",
            "type":"Transportation"
        }
    ],
    "sg:phone":"+1 801 525 1007",
    "sg:postcode":"84015",
    "sg:province":"UT",
    "sg:tags":[
        "trucking"
    ],
    "wof:name":"Scully Distribution",
    "wof:placetype":"venue"
},
  "geometry": {"coordinates":[-112.020239,41.097802],"type":"Point"}
}