{
  "type": "Feature",
  "properties": {
    "iso:country":"US",
    "sg:address":"311 N 600 E",
    "sg:city":"Orem",
    "sg:classifiers":[
        {
            "category":"Personal",
            "subcategory":"Beauty Salon",
            "type":"Services"
        }
    ],
    "sg:phone":"+1 801 226 1055",
    "sg:postcode":"84097",
    "sg:province":"UT",
    "sg:tags":[
        "shop"
    ],
    "wof:name":"Designer Cuts Styles By Myrna",
    "wof:placetype":"venue"
},
  "geometry": {"coordinates":[-111.68139499999999,40.302458],"type":"Point"}
}