{
  "type": "Feature",
  "properties": {
    "iso:country":"US",
    "sg:address":"2405 Orton Cir",
    "sg:city":"Salt Lake City",
    "sg:classifiers":[
        {
            "category":"Manufacturing",
            "subcategory":"Tools & Machinery",
            "type":"Manufacturing & Wholesale Goods"
        }
    ],
    "sg:phone":"+1 801 974 1700",
    "sg:postcode":"84119",
    "sg:province":"UT",
    "sg:tags":[
        "medical",
        "devices",
        "mfg"
    ],
    "wof:name":"PVS",
    "wof:placetype":"venue"
},
  "geometry": {"coordinates":[-111.950289,40.719156],"type":"Point"}
}