{
  "type": "Feature",
  "properties": {
    "iso:country":"US",
    "sg:address":"586 S Main St",
    "sg:city":"Cedar City",
    "sg:classifiers":[
        {
            "category":"Education",
            "subcategory":"Dance Studio",
            "type":"Public Place"
        }
    ],
    "sg:phone":"+1 435 586 3267",
    "sg:postcode":"84720",
    "sg:province":"UT",
    "sg:tags":[
        "instruction",
        "dancing"
    ],
    "wof:name":"Dansworks Studio",
    "wof:placetype":"venue"
},
  "geometry": {"coordinates":[-113.06258099999999,37.667467],"type":"Point"}
}