{
  "type": "Feature",
  "properties": {
    "iso:country":"US",
    "sg:address":"650 S 500 W",
    "sg:city":"Woods Cross",
    "sg:classifiers":[
        {
            "category":"Restaurant",
            "type":"Food & Drink"
        }
    ],
    "sg:menulink":"http://www.allmenus.com/ut/south-davis/116225-quiznos-sub/menu/",
    "sg:phone":"+1 801 397 0101",
    "sg:postcode":"84010",
    "sg:province":"UT",
    "sg:tags":[
        "wrap",
        "american",
        "sandwich"
    ],
    "wof:name":"Quiznos Sub",
    "wof:placetype":"venue"
},
  "geometry": {"coordinates":[-111.892139,40.882731],"type":"Point"}
}