{
  "type": "Feature",
  "properties": {
    "iso:country":"US",
    "sg:address":"180 W 36th St",
    "sg:city":"Ogden",
    "sg:classifiers":[
        {
            "category":"Personal",
            "subcategory":"Beauty Salon",
            "type":"Services"
        }
    ],
    "sg:phone":"+1 801 627 4873",
    "sg:postcode":"84405",
    "sg:province":"UT",
    "sg:tags":[
        "shop"
    ],
    "wof:name":"Los Angles Cnnction Hair Dsign",
    "wof:placetype":"venue"
},
  "geometry": {"coordinates":[-111.98265499999999,41.197949],"type":"Point"}
}