{
  "type": "Feature",
  "properties": {
    "iso:country":"US",
    "sg:address":"667 W Center St",
    "sg:city":"Midvale",
    "sg:classifiers":[
        {
            "category":"Organizations",
            "subcategory":"Religious Organization",
            "type":"Services"
        }
    ],
    "sg:phone":"+1 801 566 3772",
    "sg:postcode":"84047",
    "sg:province":"UT",
    "sg:tags":[
        "child",
        "day",
        "care"
    ],
    "wof:name":"Hillsdale Nursery School",
    "wof:placetype":"venue"
},
  "geometry": {"coordinates":[-111.917936,40.610051],"type":"Point"}
}