{
  "type": "Feature",
  "properties": {
    "iso:country":"US",
    "sg:address":"2265 Calanus Cir",
    "sg:city":"St George",
    "sg:classifiers":[
        {
            "category":"Wholesale",
            "subcategory":"Hardware",
            "type":"Manufacturing & Wholesale Goods"
        }
    ],
    "sg:phone":"+1 435 673 6323",
    "sg:postcode":"84790",
    "sg:province":"UT",
    "sg:tags":[
        "plumbing"
    ],
    "wof:name":"Parke S Stovepipe Inc",
    "wof:placetype":"venue"
},
  "geometry": {"coordinates":[-113.57046200000001,37.071313],"type":"Point"}
}