{
  "type": "Feature",
  "properties": {
    "iso:country":"US",
    "sg:address":"4140 S 500 W",
    "sg:city":"Murray",
    "sg:classifiers":[
        {
            "category":"Professional",
            "subcategory":"Business Services",
            "type":"Services"
        },
        {
            "category":"Manufacturing",
            "subcategory":"Apparel",
            "type":"Manufacturing & Wholesale Goods"
        }
    ],
    "sg:phone":"+1 801 269 1282",
    "sg:postcode":"84123",
    "sg:province":"UT",
    "sg:tags":[
        "mfg",
        "printing",
        "advertising",
        "special",
        "embroidery"
    ],
    "sg:website":"www.creativexp.com",
    "wof:name":"Creative Expressions Inc",
    "wof:placetype":"venue"
},
  "geometry": {"coordinates":[-111.905545,40.682405],"type":"Point"}
}