{
  "type": "Feature",
  "properties": {
    "iso:country":"US",
    "sg:address":"2785 Shamrock Dr",
    "sg:city":"Ogden",
    "sg:classifiers":[
        {
            "category":"Organizations",
            "subcategory":"Labor Organization",
            "type":"Services"
        }
    ],
    "sg:phone":"+1 801 626 6130",
    "sg:postcode":"84403",
    "sg:province":"UT",
    "wof:name":"Shamrock Development Lc",
    "wof:placetype":"venue"
},
  "geometry": {"coordinates":[-111.930825,41.213735],"type":"Point"}
}