{
  "type": "Feature",
  "properties": {
    "iso:country":"US",
    "sg:address":"451 E 200 S",
    "sg:city":"Lehi",
    "sg:classifiers":[
        {
            "category":"Recreation",
            "type":"Entertainment"
        }
    ],
    "sg:phone":"+1 801 768 7190",
    "sg:postcode":"84043",
    "sg:province":"UT",
    "sg:tags":[
        "pool",
        "swimming"
    ],
    "wof:name":"Lehi City Swimming Pool",
    "wof:placetype":"venue"
},
  "geometry": {"coordinates":[-111.841874,40.385825],"type":"Point"}
}