{
  "type": "Feature",
  "properties": {
    "iso:country":"US",
    "sg:address":"1366 N 7000 E",
    "sg:city":"Huntsville",
    "sg:classifiers":[
        {
            "category":"Building & Trades",
            "subcategory":"Construction",
            "type":"Services"
        }
    ],
    "sg:phone":"+1 801 745 2366",
    "sg:postcode":"84317",
    "sg:province":"UT",
    "sg:tags":[
        "contractor"
    ],
    "wof:name":"Diamond Blade Tile",
    "wof:placetype":"venue"
},
  "geometry": {"coordinates":[-111.779408,41.281735],"type":"Point"}
}