{
  "type": "Feature",
  "properties": {
    "iso:country":"US",
    "sg:address":"7726 Buckboard Dr",
    "sg:city":"Park City",
    "sg:classifiers":[
        {
            "category":"Manufacturing",
            "subcategory":"Toys & Sporting Goods",
            "type":"Manufacturing & Wholesale Goods"
        }
    ],
    "sg:phone":"+1 435 655 9667",
    "sg:postcode":"84098",
    "sg:province":"UT",
    "sg:tags":[
        "mfg"
    ],
    "wof:name":"Oquirrh Sports Technology",
    "wof:placetype":"venue"
},
  "geometry": {"coordinates":[-111.586517,40.745255],"type":"Point"}
}