{
  "type": "Feature",
  "properties": {
    "iso:country":"US",
    "sg:address":"3365 W 7800 S",
    "sg:city":"West Jordan",
    "sg:classifiers":[
        {
            "category":"Restaurant",
            "type":"Food & Drink"
        }
    ],
    "sg:phone":"+1 801 280 0835",
    "sg:postcode":"84088",
    "sg:province":"UT",
    "wof:name":"Arctic Circle Restaurants",
    "wof:placetype":"venue"
},
  "geometry": {"coordinates":[-111.97245599999999,40.609381],"type":"Point"}
}