{
  "type": "Feature",
  "properties": {
    "iso:country":"US",
    "sg:address":"90 W Main St",
    "sg:city":"Salina",
    "sg:classifiers":[
        {
            "category":"Education",
            "subcategory":"Library",
            "type":"Public Place"
        }
    ],
    "sg:phone":"+1 435 529 7753",
    "sg:postcode":"84654",
    "sg:province":"UT",
    "wof:name":"City Library",
    "wof:placetype":"venue"
},
  "geometry": {"coordinates":[-111.861597,38.957663],"type":"Point"}
}