{
  "type": "Feature",
  "properties": {
    "iso:country":"US",
    "sg:address":"12694 S Redwood Rd",
    "sg:city":"Riverton",
    "sg:classifiers":[
        {
            "category":"Health Services",
            "subcategory":"Doctor",
            "type":"Services"
        }
    ],
    "sg:phone":"+1 801 254 1278",
    "sg:postcode":"84065",
    "sg:province":"UT",
    "sg:tags":[
        "dentist"
    ],
    "wof:name":"B Charles Pugh DDS",
    "wof:placetype":"venue"
},
  "geometry": {"coordinates":[-111.938806,40.521122],"type":"Point"}
}