{
  "type": "Feature",
  "properties": {
    "iso:country":"US",
    "sg:address":"559 W 1085 N",
    "sg:city":"Orem",
    "sg:classifiers":[
        {
            "category":"Professional",
            "type":"Services"
        }
    ],
    "sg:phone":"+1 801 224 1665",
    "sg:postcode":"84057",
    "sg:province":"UT",
    "wof:name":"Nuhorizons Nevada Develop",
    "wof:placetype":"venue"
},
  "geometry": {"coordinates":[-111.708972,40.317012],"type":"Point"}
}