{
  "type": "Feature",
  "properties": {
    "iso:country":"US",
    "sg:address":"162 E 400 N",
    "sg:city":"Logan",
    "sg:classifiers":[
        {
            "category":"Retail",
            "subcategory":"Funeral Services",
            "type":"Services"
        }
    ],
    "sg:phone":"+1 435 752 3261",
    "sg:postcode":"84321",
    "sg:province":"UT",
    "sg:tags":[
        "director",
        "mortuary"
    ],
    "wof:name":"Nelson Funeral Home Inc",
    "wof:placetype":"venue"
},
  "geometry": {"coordinates":[-111.830429,41.738903],"type":"Point"}
}