{
  "type": "Feature",
  "properties": {
    "iso:country":"US",
    "sg:address":"2448 N University Pkwy",
    "sg:city":"Provo",
    "sg:classifiers":[
        {
            "category":"Restaurant",
            "type":"Food & Drink"
        }
    ],
    "sg:phone":"+1 801 377 2150",
    "sg:postcode":"84604",
    "sg:province":"UT",
    "wof:name":"Gualbertos",
    "wof:placetype":"venue"
},
  "geometry": {"coordinates":[-111.670846,40.265521],"type":"Point"}
}