{
  "type": "Feature",
  "properties": {
    "iso:country":"US",
    "sg:address":"4601 Tudor Ct",
    "sg:city":"Salt Lake City",
    "sg:classifiers":[
        {
            "category":"Professional",
            "type":"Services"
        }
    ],
    "sg:phone":"+1 801 963 1388",
    "sg:postcode":"84120",
    "sg:province":"UT",
    "wof:name":"Regulators Incorporated",
    "wof:placetype":"venue"
},
  "geometry": {"coordinates":[-112.001167,40.706293],"type":"Point"}
}