{
  "type": "Feature",
  "properties": {
    "iso:country":"US",
    "sg:address":"4017 Riverdale Rd",
    "sg:city":"Ogden",
    "sg:classifiers":[
        {
            "category":"Professional",
            "subcategory":"Computer Services",
            "type":"Services"
        }
    ],
    "sg:phone":"+1 801 393 7368",
    "sg:postcode":"84405",
    "sg:province":"UT",
    "wof:name":"Colortyme",
    "wof:placetype":"venue"
},
  "geometry": {"coordinates":[-111.98227,41.189801],"type":"Point"}
}