{
  "type": "Feature",
  "properties": {
    "iso:country":"US",
    "sg:address":"5250 W 4000 S",
    "sg:city":"Hooper",
    "sg:classifiers":[
        {
            "category":"Professional",
            "subcategory":"Management & Consulting",
            "type":"Services"
        }
    ],
    "sg:phone":"+1 801 731 3705",
    "sg:postcode":"84315",
    "sg:province":"UT",
    "sg:tags":[
        "business"
    ],
    "wof:name":"Joseph L Hull Consulting LLC",
    "wof:placetype":"venue"
},
  "geometry": {"coordinates":[-112.10541499999999,41.190831],"type":"Point"}
}