{
  "type": "Feature",
  "properties": {
    "iso:country":"US",
    "sg:address":"175 W 1300 S",
    "sg:city":"Salt Lake City",
    "sg:classifiers":[
        {
            "category":"Freight",
            "type":"Transportation"
        }
    ],
    "sg:phone":"+1 801 483 1948",
    "sg:postcode":"84115",
    "sg:province":"UT",
    "sg:tags":[
        "warehouse"
    ],
    "wof:name":"Sears",
    "wof:placetype":"venue"
},
  "geometry": {"coordinates":[-111.89585700000001,40.741536],"type":"Point"}
}