{
  "type": "Feature",
  "properties": {
    "iso:country":"US",
    "sg:address":"1063 E Center St",
    "sg:city":"Bountiful",
    "sg:classifiers":[
        {
            "category":"Shopping",
            "subcategory":"Gifts & Souvenirs",
            "type":"Retail Goods"
        }
    ],
    "sg:phone":"+1 801 295 3039",
    "sg:postcode":"84010",
    "sg:province":"UT",
    "wof:name":"Donnas Gifts",
    "wof:placetype":"venue"
},
  "geometry": {"coordinates":[-111.86022800000001,40.889799],"type":"Point"}
}