{
  "type": "Feature",
  "properties": {
    "iso:country":"US",
    "sg:address":"9831 S 6045 W",
    "sg:city":"West Jordan",
    "sg:classifiers":[
        {
            "category":"Shopping",
            "subcategory":"Computers & Home Electronics",
            "type":"Retail Goods"
        },
        {
            "category":"Cinema",
            "subcategory":"Movie Rental",
            "type":"Entertainment"
        }
    ],
    "sg:phone":"+1 801 680 1993",
    "sg:postcode":"84088",
    "sg:province":"UT",
    "sg:tags":[
        "video",
        "audio",
        "tape"
    ],
    "wof:name":"Newport Audio & Video",
    "wof:placetype":"venue"
},
  "geometry": {"coordinates":[-112.034935,40.572988],"type":"Point"}
}