{
  "type": "Feature",
  "properties": {
    "iso:country":"US",
    "sg:address":"2187 S Industrial Park Rd",
    "sg:city":"Richfield",
    "sg:classifiers":[
        {
            "category":"Building & Trades",
            "subcategory":"Construction",
            "type":"Services"
        },
        {
            "category":"Home & Garden",
            "subcategory":"Furniture",
            "type":"Retail Goods"
        }
    ],
    "sg:phone":"+1 435 896 4528",
    "sg:postcode":"84701",
    "sg:province":"UT",
    "sg:tags":[
        "material",
        "kitchen",
        "cabinet",
        "equipment",
        "contractor",
        "carpentry"
    ],
    "wof:name":"Peppercorn Woodworks Inc",
    "wof:placetype":"venue"
},
  "geometry": {"coordinates":[-112.0966,38.734937],"type":"Point"}
}