{
  "type": "Feature",
  "properties": {
    "iso:country":"US",
    "sg:address":"532 S 1000 W",
    "sg:city":"Payson",
    "sg:classifiers":[
        {
            "category":"Personal",
            "subcategory":"Beauty Salon",
            "type":"Services"
        }
    ],
    "sg:phone":"+1 801 465 4233",
    "sg:postcode":"84651",
    "sg:province":"UT",
    "sg:tags":[
        "shop"
    ],
    "wof:name":"Sharper Cut",
    "wof:placetype":"venue"
},
  "geometry": {"coordinates":[-111.74954700000001,40.037189],"type":"Point"}
}