{
  "type": "Feature",
  "properties": {
    "iso:country":"US",
    "sg:address":"11083 Foxmoor Dr",
    "sg:city":"Sandy",
    "sg:classifiers":[
        {
            "category":"Retail",
            "subcategory":"Auto Repair",
            "type":"Services"
        }
    ],
    "sg:phone":"+1 801 576 2593",
    "sg:postcode":"84092",
    "sg:province":"UT",
    "sg:tags":[
        "automotive"
    ],
    "wof:name":"Patterson & Assoc",
    "wof:placetype":"venue"
},
  "geometry": {"coordinates":[-111.83853000000001,40.54952],"type":"Point"}
}