{
  "type": "Feature",
  "properties": {
    "iso:country":"US",
    "sg:address":"1770 Country Springs Cir",
    "sg:city":"Bountiful",
    "sg:classifiers":[
        {
            "category":"Professional",
            "subcategory":"Management & Consulting",
            "type":"Services"
        }
    ],
    "sg:phone":"+1 801 299 1732",
    "sg:postcode":"84010",
    "sg:province":"UT",
    "wof:name":"Jle Consulting Inc",
    "wof:placetype":"venue"
},
  "geometry": {"coordinates":[-111.883905,40.908822],"type":"Point"}
}