{
  "type": "Feature",
  "properties": {
    "iso:country":"US",
    "sg:address":"1357 E Main St",
    "sg:city":"Lehi",
    "sg:classifiers":[
        {
            "category":"Food & Beverages",
            "subcategory":"Groceries & Convenience Stores",
            "type":"Retail Goods"
        }
    ],
    "sg:phone":"+1 801 768 4477",
    "sg:postcode":"84043",
    "sg:province":"UT",
    "wof:name":"La Estrella",
    "wof:placetype":"venue"
},
  "geometry": {"coordinates":[-111.830561,40.38838],"type":"Point"}
}