{
  "type": "Feature",
  "properties": {
    "iso:country":"US",
    "sg:address":"245 Apple Dr",
    "sg:city":"Hyrum",
    "sg:classifiers":[
        {
            "category":"Organizations",
            "subcategory":"Religious Organization",
            "type":"Services"
        }
    ],
    "sg:phone":"+1 435 245 4039",
    "sg:postcode":"84319",
    "sg:province":"UT",
    "sg:tags":[
        "mormon",
        "church"
    ],
    "wof:name":"The Corporation of The Pres of",
    "wof:placetype":"venue"
},
  "geometry": {"coordinates":[-111.834425,41.638141],"type":"Point"}
}