{
  "type": "Feature",
  "properties": {
    "iso:country":"US",
    "sg:address":"1150 W 2100 S",
    "sg:city":"Salt Lake City",
    "sg:classifiers":[
        {
            "category":"Retail",
            "subcategory":"Auto Rental",
            "type":"Services"
        }
    ],
    "sg:phone":"+1 801 972 1585",
    "sg:postcode":"84119",
    "sg:province":"UT",
    "sg:tags":[
        "truck",
        "trailer",
        "utility"
    ],
    "wof:name":"Gelco Tip Trailer Leasing",
    "wof:placetype":"venue"
},
  "geometry": {"coordinates":[-111.926117,40.72597],"type":"Point"}
}