{
  "type": "Feature",
  "properties": {
    "iso:country":"US",
    "sg:address":"1844 S 3850 W",
    "sg:city":"Salt Lake City",
    "sg:classifiers":[
        {
            "category":"Professional",
            "subcategory":"Management & Consulting",
            "type":"Services"
        }
    ],
    "sg:phone":"+1 801 972 9673",
    "sg:postcode":"84104",
    "sg:province":"UT",
    "sg:tags":[
        "fuel"
    ],
    "wof:name":"Inc Network Management",
    "wof:placetype":"venue"
},
  "geometry": {"coordinates":[-111.98321799999999,40.730451],"type":"Point"}
}