{
  "type": "Feature",
  "properties": {
    "iso:country":"US",
    "sg:address":"1570 24th St",
    "sg:city":"Ogden",
    "sg:classifiers":[
        {
            "category":"Building & Trades",
            "subcategory":"Construction",
            "type":"Services"
        }
    ],
    "sg:phone":"+1 801 334 6928",
    "sg:postcode":"84401",
    "sg:province":"UT",
    "sg:tags":[
        "house"
    ],
    "wof:name":"Ds Home Repair & Painting",
    "wof:placetype":"venue"
},
  "geometry": {"coordinates":[-111.938971,41.222419],"type":"Point"}
}