{
  "type": "Feature",
  "properties": {
    "iso:country":"US",
    "sg:address":"4801 Wasatch St",
    "sg:city":"Salt Lake City",
    "sg:classifiers":[
        {
            "category":"Bakery",
            "type":"Food & Drink"
        },
        {
            "category":"Bagels",
            "type":"Food & Drink"
        }
    ],
    "sg:menulink":"http://www.allmenus.com/ut/salt-lake-city/37298-einstein-bros/menu/",
    "sg:phone":"+1 801 278 6339",
    "sg:postcode":"84107",
    "sg:province":"UT",
    "sg:tags":[
        "sandwich",
        "salad",
        "soup",
        "american",
        "pastry",
        "wrap"
    ],
    "wof:name":"Einstein Bros",
    "wof:placetype":"venue"
},
  "geometry": {"coordinates":[-111.88393600000001,40.667062],"type":"Point"}
}