{
  "type": "Feature",
  "properties": {
    "iso:country":"US",
    "sg:address":"5611 S 1900 W",
    "sg:city":"Roy",
    "sg:classifiers":[
        {
            "category":"Government",
            "subcategory":"Office",
            "type":"Public Place"
        }
    ],
    "sg:phone":"+1 801 774 0543",
    "sg:postcode":"84067",
    "sg:province":"UT",
    "sg:tags":[
        "station",
        "recruiting"
    ],
    "wof:name":"Navy Recruiting Station",
    "wof:placetype":"venue"
},
  "geometry": {"coordinates":[-112.026121,41.15985],"type":"Point"}
}