{
  "type": "Feature",
  "properties": {
    "iso:country":"US",
    "sg:address":"6270 S 725 East St",
    "sg:city":"Salt Lake City",
    "sg:classifiers":[
        {
            "category":"Retail",
            "subcategory":"Repair Shop",
            "type":"Services"
        }
    ],
    "sg:phone":"+1 801 270 0884",
    "sg:postcode":"84107",
    "sg:province":"UT",
    "sg:tags":[
        "electrical"
    ],
    "wof:name":"Ultimate Home Electronics",
    "wof:placetype":"venue"
},
  "geometry": {"coordinates":[-111.872282,40.636788],"type":"Point"}
}