{
  "type": "Feature",
  "properties": {
    "iso:country":"US",
    "sg:address":"1740 S Main St",
    "sg:city":"Salt Lake City",
    "sg:classifiers":[
        {
            "category":"Organizations",
            "subcategory":"Labor Organization",
            "type":"Services"
        }
    ],
    "sg:phone":"+1 801 484 4469",
    "sg:postcode":"84115",
    "sg:province":"UT",
    "sg:tags":[
        "insurance"
    ],
    "wof:name":"Machinist Labor Union",
    "wof:placetype":"venue"
},
  "geometry": {"coordinates":[-111.891139,40.73279],"type":"Point"}
}