{
  "type": "Feature",
  "properties": {
    "iso:country":"US",
    "sg:address":"3451 S 5600 W",
    "sg:city":"West Valley",
    "sg:classifiers":[
        {
            "category":"Health Services",
            "subcategory":"Doctor",
            "type":"Services"
        }
    ],
    "sg:phone":"+1 801 963 1880",
    "sg:postcode":"84120",
    "sg:province":"UT",
    "sg:tags":[
        "physician",
        "surgeon"
    ],
    "wof:name":"Westview Womens & Family Ctr",
    "wof:placetype":"venue"
},
  "geometry": {"coordinates":[-112.02478000000001,40.698872],"type":"Point"}
}