{
  "type": "Feature",
  "properties": {
    "iso:country":"US",
    "sg:address":"856 Sage Dr",
    "sg:city":"Cedar City",
    "sg:classifiers":[
        {
            "category":"Banks & Credit Unions",
            "subcategory":"Bank",
            "type":"Services"
        }
    ],
    "sg:phone":"+1 435 867 1884",
    "sg:postcode":"84720",
    "sg:province":"UT",
    "sg:tags":[
        "loan",
        "real estate"
    ],
    "wof:name":"First Colony Mortgage Co",
    "wof:placetype":"venue"
},
  "geometry": {"coordinates":[-113.080536,37.663314],"type":"Point"}
}