{
  "type": "Feature",
  "properties": {
    "iso:country":"US",
    "sg:address":"1262 Compton Rd",
    "sg:city":"Farmington",
    "sg:classifiers":[
        {
            "category":"Professional",
            "subcategory":"Business Services",
            "type":"Services"
        }
    ],
    "sg:phone":"+1 801 451 7442",
    "sg:postcode":"84025",
    "sg:province":"UT",
    "wof:name":"Embark Enterprises Inc",
    "wof:placetype":"venue"
},
  "geometry": {"coordinates":[-111.89201300000001,41.001061],"type":"Point"}
}