{
  "type": "Feature",
  "properties": {
    "iso:country":"US",
    "sg:address":"1989 Quailstone Dr",
    "sg:city":"Salt Lake City",
    "sg:classifiers":[
        {
            "category":"Retail",
            "subcategory":"Portrait Studio",
            "type":"Services"
        }
    ],
    "sg:phone":"+1 801 964 5036",
    "sg:postcode":"84118",
    "sg:province":"UT",
    "sg:tags":[
        "photo"
    ],
    "wof:name":"Kelly Wanberg Photography",
    "wof:placetype":"venue"
},
  "geometry": {"coordinates":[-111.94464600000001,40.664851],"type":"Point"}
}