{
  "type": "Feature",
  "properties": {
    "iso:country":"US",
    "sg:address":"1951 Gines Ln",
    "sg:city":"Kamas",
    "sg:classifiers":[
        {
            "category":"Autos & Motor Vehicles",
            "subcategory":"Motorcycle Sales",
            "type":"Retail Goods"
        }
    ],
    "sg:phone":"+1 801 486 6805",
    "sg:postcode":"84036",
    "sg:province":"UT",
    "sg:tags":[
        "all",
        "terrain"
    ],
    "wof:name":"Rokon Of Utah",
    "wof:placetype":"venue"
},
  "geometry": {"coordinates":[-111.24337,40.595924],"type":"Point"}
}