{
  "type": "Feature",
  "properties": {
    "iso:country":"US",
    "sg:address":"952 S Carbon Ave",
    "sg:city":"Price",
    "sg:classifiers":[
        {
            "category":"Government",
            "subcategory":"Office",
            "type":"Public Place"
        }
    ],
    "sg:phone":"+1 435 637 8629",
    "sg:postcode":"84501",
    "sg:province":"UT",
    "wof:name":"Project Engineers Office",
    "wof:placetype":"venue"
},
  "geometry": {"coordinates":[-110.812854,39.586489],"type":"Point"}
}