{
  "type": "Feature",
  "properties": {
    "iso:country":"US",
    "sg:address":"1037 Straw Hat Ln",
    "sg:city":"Draper",
    "sg:classifiers":[
        {
            "category":"Professional",
            "subcategory":"Business Services",
            "type":"Services"
        }
    ],
    "sg:phone":"+1 801 501 0915",
    "sg:postcode":"84020",
    "sg:province":"UT",
    "wof:name":"Schmidt & Associates Inc",
    "wof:placetype":"venue"
},
  "geometry": {"coordinates":[-111.861885,40.495285],"type":"Point"}
}