{
  "type": "Feature",
  "properties": {
    "iso:country":"US",
    "sg:address":"397 S 800 W",
    "sg:city":"Salina",
    "sg:classifiers":[
        {
            "category":"Professional",
            "subcategory":"Research",
            "type":"Services"
        }
    ],
    "sg:phone":"+1 435 529 1011",
    "sg:postcode":"84660",
    "sg:province":"UT",
    "sg:tags":[
        "laboratory"
    ],
    "wof:name":"Standard Laboratories Inc",
    "wof:placetype":"venue"
},
  "geometry": {"coordinates":[-111.668879,40.105191],"type":"Point"}
}