{
  "type": "Feature",
  "properties": {
    "iso:country":"US",
    "sg:address":"266 W 200 N",
    "sg:city":"Kanab",
    "sg:classifiers":[
        {
            "category":"Health Services",
            "subcategory":"Nursing And Care Facility",
            "type":"Services"
        },
        {
            "category":"Real Estate",
            "subcategory":"Real Estate Operator",
            "type":"Services"
        }
    ],
    "sg:phone":"+1 435 644 3432",
    "sg:postcode":"84741",
    "sg:province":"UT",
    "sg:tags":[
        "home",
        "apartment",
        "community",
        "retirement"
    ],
    "wof:name":"Lazy Days Apartments",
    "wof:placetype":"venue"
},
  "geometry": {"coordinates":[-112.53358,37.051642],"type":"Point"}
}