{
  "type": "Feature",
  "properties": {
    "iso:country":"US",
    "sg:address":"10721 Hidden Ridge Ln",
    "sg:city":"Sandy",
    "sg:classifiers":[
        {
            "category":"Wholesale",
            "subcategory":"Electrical",
            "type":"Manufacturing & Wholesale Goods"
        }
    ],
    "sg:phone":"+1 801 733 0073",
    "sg:postcode":"84092",
    "sg:province":"UT",
    "sg:tags":[
        "equipment",
        "electronic",
        "supply"
    ],
    "wof:name":"Qvs",
    "wof:placetype":"venue"
},
  "geometry": {"coordinates":[-111.80462300000001,40.557049],"type":"Point"}
}