{
  "type": "Feature",
  "properties": {
    "iso:country":"US",
    "sg:address":"700 Bitner Rd",
    "sg:city":"Park City",
    "sg:classifiers":[
        {
            "category":"Banks & Credit Unions",
            "subcategory":"Financial Services",
            "type":"Services"
        }
    ],
    "sg:phone":"+1 435 647 5655",
    "sg:postcode":"84098",
    "sg:province":"UT",
    "sg:tags":[
        "personal",
        "investment"
    ],
    "wof:name":"Haverford Group The",
    "wof:placetype":"venue"
},
  "geometry": {"coordinates":[-111.528722,40.72335],"type":"Point"}
}