{
  "type": "Feature",
  "properties": {
    "iso:country":"US",
    "sg:address":"589 Woodland Hills Dr",
    "sg:city":"Bountiful",
    "sg:classifiers":[
        {
            "category":"Shopping",
            "subcategory":"Gifts & Souvenirs",
            "type":"Retail Goods"
        }
    ],
    "sg:phone":"+1 801 295 8737",
    "sg:postcode":"84010",
    "sg:province":"UT",
    "wof:name":"Endearing Impressions",
    "wof:placetype":"venue"
},
  "geometry": {"coordinates":[-111.862937,40.883307],"type":"Point"}
}