{
  "type": "Feature",
  "properties": {
    "iso:country":"US",
    "sg:address":"2031 Lincoln Ave",
    "sg:city":"Ogden",
    "sg:classifiers":[
        {
            "category":"Shopping",
            "type":"Retail Goods"
        }
    ],
    "sg:phone":"+1 801 399 2080",
    "sg:postcode":"84401",
    "sg:province":"UT",
    "sg:tags":[
        "merchandise"
    ],
    "wof:name":"Etched In Stone Design Co",
    "wof:placetype":"venue"
},
  "geometry": {"coordinates":[-111.975931,41.231007],"type":"Point"}
}