{
  "type": "Feature",
  "properties": {
    "iso:country":"US",
    "sg:address":"1136 E 12300 S",
    "sg:city":"Draper",
    "sg:classifiers":[
        {
            "category":"Health Services",
            "subcategory":"Chiropractor",
            "type":"Services"
        }
    ],
    "sg:phone":"+1 801 553 9691",
    "sg:postcode":"84020",
    "sg:province":"UT",
    "wof:name":"Dudley Chiropractic PC",
    "wof:placetype":"venue"
},
  "geometry": {"coordinates":[-111.859919,40.528061],"type":"Point"}
}