{
  "type": "Feature",
  "properties": {
    "iso:country":"US",
    "sg:address":"1090 Fort Union Blvd",
    "sg:city":"Midvale",
    "sg:classifiers":[
        {
            "category":"Shopping",
            "type":"Retail Goods"
        }
    ],
    "sg:phone":"+1 801 352 1510",
    "sg:postcode":"84047",
    "sg:province":"UT",
    "sg:tags":[
        "merchandise",
        "animal"
    ],
    "sg:website":"www.petco.com",
    "wof:name":"PETCO",
    "wof:placetype":"venue"
},
  "geometry": {"coordinates":[-111.861643,40.623469],"type":"Point"}
}