{
  "type": "Feature",
  "properties": {
    "iso:country":"US",
    "sg:address":"55 S 300 W",
    "sg:city":"Hurricane",
    "sg:classifiers":[
        {
            "category":"Health Services",
            "subcategory":"Chiropractor",
            "type":"Services"
        }
    ],
    "sg:phone":"+1 435 635 3828",
    "sg:postcode":"84737",
    "sg:province":"UT",
    "wof:name":"Long Chiropractic",
    "wof:placetype":"venue"
},
  "geometry": {"coordinates":[-113.293874,37.175801],"type":"Point"}
}