{
  "type": "Feature",
  "properties": {
    "iso:country":"US",
    "sg:address":"1406 S 400 W",
    "sg:city":"South Salt Lake",
    "sg:classifiers":[
        {
            "category":"Building & Trades",
            "subcategory":"Electrical",
            "type":"Services"
        }
    ],
    "sg:phone":"+1 801 466 3409",
    "sg:postcode":"84115",
    "sg:province":"UT",
    "sg:tags":[
        "electrical",
        "electric",
        "contractor"
    ],
    "wof:name":"Beacon Engineering & Electric",
    "wof:placetype":"venue"
},
  "geometry": {"coordinates":[-111.902591,40.739238],"type":"Point"}
}