{
  "type": "Feature",
  "properties": {
    "iso:country":"US",
    "sg:address":"1505 W 7800 S",
    "sg:city":"West Jordan",
    "sg:classifiers":[
        {
            "category":"Home & Garden",
            "subcategory":"Building Materials",
            "type":"Retail Goods"
        }
    ],
    "sg:phone":"+1 801 255 4281",
    "sg:postcode":"84088",
    "sg:province":"UT",
    "sg:tags":[
        "glass",
        "window",
        "plate"
    ],
    "wof:name":"Diamond Glass Co",
    "wof:placetype":"venue"
},
  "geometry": {"coordinates":[-111.933492,40.609453],"type":"Point"}
}