{
  "type": "Feature",
  "properties": {
    "iso:country":"US",
    "sg:address":"921 E 10715 S",
    "sg:city":"Sandy",
    "sg:classifiers":[
        {
            "category":"Real Estate",
            "subcategory":"Real Estate Operator",
            "type":"Services"
        }
    ],
    "sg:phone":"+1 801 572 2824",
    "sg:postcode":"84094",
    "sg:province":"UT",
    "sg:tags":[
        "building",
        "nonresidential"
    ],
    "wof:name":"Jackson Properties LLC",
    "wof:placetype":"venue"
},
  "geometry": {"coordinates":[-111.86577,40.556711],"type":"Point"}
}