{
  "type": "Feature",
  "properties": {
    "iso:country":"US",
    "sg:address":"2290 S 1500 E",
    "sg:city":"Vernal",
    "sg:classifiers":[
        {
            "category":"Freight",
            "type":"Transportation"
        }
    ],
    "sg:phone":"+1 435 789 2563",
    "sg:postcode":"84078",
    "sg:province":"UT",
    "sg:tags":[
        "commercial",
        "storage"
    ],
    "wof:name":"Quality Storage",
    "wof:placetype":"venue"
},
  "geometry": {"coordinates":[-109.499408,40.422177],"type":"Point"}
}