{
  "type": "Feature",
  "properties": {
    "iso:country":"US",
    "sg:address":"11194 S 1000 E",
    "sg:city":"Sandy",
    "sg:classifiers":[
        {
            "category":"Organizations",
            "subcategory":"Religious Organization",
            "type":"Services"
        }
    ],
    "sg:phone":"+1 801 572 0747",
    "sg:postcode":"84094",
    "sg:province":"UT",
    "wof:name":"Alta Canyon Baptist Church",
    "wof:placetype":"venue"
},
  "geometry": {"coordinates":[-111.862799,40.547282],"type":"Point"}
}