{
  "type": "Feature",
  "properties": {
    "iso:country":"US",
    "sg:address":"515 E 4500 S",
    "sg:city":"Murray",
    "sg:classifiers":[
        {
            "category":"Professional",
            "subcategory":"Accounting & Tax Preparation",
            "type":"Services"
        }
    ],
    "sg:phone":"+1 801 270 8055",
    "sg:postcode":"84107",
    "sg:province":"UT",
    "sg:tags":[
        "accountant"
    ],
    "wof:name":"Bryan J Richmond CPA",
    "wof:placetype":"venue"
},
  "geometry": {"coordinates":[-111.87490200000001,40.674407],"type":"Point"}
}