{
  "type": "Feature",
  "properties": {
    "iso:country":"US",
    "sg:address":"2045 Churchwood Dr",
    "sg:city":"Tooele",
    "sg:classifiers":[
        {
            "category":"Organizations",
            "subcategory":"Religious Organization",
            "type":"Services"
        }
    ],
    "sg:phone":"+1 435 882 1077",
    "sg:postcode":"84074",
    "sg:province":"UT",
    "sg:tags":[
        "church"
    ],
    "wof:name":"Church Of Jesus Christ Of Lds",
    "wof:placetype":"venue"
},
  "geometry": {"coordinates":[-112.25393200000001,40.572224],"type":"Point"}
}