{
  "type": "Feature",
  "properties": {
    "iso:country":"US",
    "sg:address":"22 W 400 S",
    "sg:city":"Orem",
    "sg:classifiers":[
        {
            "category":"Social Services",
            "subcategory":"Child Care",
            "type":"Services"
        }
    ],
    "sg:phone":"+1 801 221 9406",
    "sg:postcode":"84058",
    "sg:province":"UT",
    "sg:tags":[
        "day"
    ],
    "wof:name":"One Fine Day",
    "wof:placetype":"venue"
},
  "geometry": {"coordinates":[-111.695995,40.289883],"type":"Point"}
}