{
  "type": "Feature",
  "properties": {
    "iso:country":"US",
    "sg:address":"2518 N 850 W",
    "sg:city":"Provo",
    "sg:classifiers":[
        {
            "category":"Professional",
            "subcategory":"Business Services",
            "type":"Services"
        }
    ],
    "sg:phone":"+1 801 377 3586",
    "sg:postcode":"84604",
    "sg:province":"UT",
    "wof:name":"Simmerman Enterprises Inc",
    "wof:placetype":"venue"
},
  "geometry": {"coordinates":[-111.673215,40.269155],"type":"Point"}
}