{
  "type": "Feature",
  "properties": {
    "iso:country":"US",
    "sg:address":"76 S Holden St",
    "sg:city":"Midvale",
    "sg:classifiers":[
        {
            "category":"Home & Garden",
            "subcategory":"Furniture",
            "type":"Retail Goods"
        }
    ],
    "sg:phone":"+1 801 562 1933",
    "sg:postcode":"84047",
    "sg:province":"UT",
    "wof:name":"Black Goose Country Furniture",
    "wof:placetype":"venue"
},
  "geometry": {"coordinates":[-111.913118,40.610387],"type":"Point"}
}