{
  "type": "Feature",
  "properties": {
    "iso:country":"US",
    "sg:address":"2150 S 1300 E",
    "sg:city":"Salt Lake City",
    "sg:classifiers":[
        {
            "category":"Professional",
            "subcategory":"Management & Consulting",
            "type":"Services"
        }
    ],
    "sg:phone":"+1 917 204 2441",
    "sg:postcode":"84106",
    "sg:province":"UT",
    "wof:name":"Captus Inc",
    "wof:placetype":"venue"
},
  "geometry": {"coordinates":[-111.853956,40.724358],"type":"Point"}
}