{
  "type": "Feature",
  "properties": {
    "iso:country":"US",
    "sg:address":"307 W 200 S",
    "sg:city":"Salt Lake City",
    "sg:classifiers":[
        {
            "category":"Restaurant",
            "type":"Food & Drink"
        }
    ],
    "sg:phone":"+1 801 328 8688",
    "sg:postcode":"84101",
    "sg:province":"UT",
    "sg:tags":[
        "eating"
    ],
    "wof:name":"China Lee Lei",
    "wof:placetype":"venue"
},
  "geometry": {"coordinates":[-111.902399,40.764921],"type":"Point"}
}