{
  "type": "Feature",
  "properties": {
    "iso:country":"US",
    "sg:address":"1757 Washington Blvd",
    "sg:city":"Ogden",
    "sg:classifiers":[
        {
            "category":"Autos & Motor Vehicles",
            "subcategory":"Auto Supplies",
            "type":"Retail Goods"
        }
    ],
    "sg:phone":"+1 801 621 0801",
    "sg:postcode":"84404",
    "sg:province":"UT",
    "wof:name":"Bridgestone/Firestone NA Tire",
    "wof:placetype":"venue"
},
  "geometry": {"coordinates":[-111.970218,41.235048],"type":"Point"}
}