{
  "type": "Feature",
  "properties": {
    "iso:country":"US",
    "sg:address":"5389 Ferncrest Cir",
    "sg:city":"Salt Lake City",
    "sg:classifiers":[
        {
            "category":"Professional",
            "subcategory":"Computer Services",
            "type":"Services"
        }
    ],
    "sg:phone":"+1 801 967 8902",
    "sg:postcode":"84118",
    "sg:province":"UT",
    "sg:tags":[
        "datum"
    ],
    "wof:name":"Outrageously Affrdbl Web Sites",
    "wof:placetype":"venue"
},
  "geometry": {"coordinates":[-111.96304000000001,40.655181],"type":"Point"}
}