{
  "type": "Feature",
  "properties": {
    "iso:country":"US",
    "sg:address":"126 N 640 W",
    "sg:city":"North Salt Lake",
    "sg:classifiers":[
        {
            "category":"Building & Trades",
            "subcategory":"Construction",
            "type":"Services"
        }
    ],
    "sg:phone":"+1 801 936 9550",
    "sg:postcode":"84054",
    "sg:province":"UT",
    "sg:tags":[
        "insulation",
        "heat",
        "contractor"
    ],
    "wof:name":"Thermal West Ind Inc",
    "wof:placetype":"venue"
},
  "geometry": {"coordinates":[-111.926062,40.844999],"type":"Point"}
}