{
  "type": "Feature",
  "properties": {
    "iso:country":"US",
    "sg:address":"3038 E Tinamous Rd",
    "sg:city":"Lehi",
    "sg:classifiers":[
        {
            "category":"Building & Trades",
            "subcategory":"Cleaning & Sanitation",
            "type":"Services"
        }
    ],
    "sg:phone":"+1 801 789 4483",
    "sg:postcode":"84043",
    "sg:province":"UT",
    "sg:tags":[
        "maintenance"
    ],
    "wof:name":"Marias Cleaning Service",
    "wof:placetype":"venue"
},
  "geometry": {"coordinates":[-111.985804,40.357315],"type":"Point"}
}