{
  "type": "Feature",
  "properties": {
    "iso:country":"US",
    "sg:address":"391 E 5300 S",
    "sg:city":"Salt Lake City",
    "sg:classifiers":[
        {
            "category":"Building & Trades",
            "subcategory":"Electrical",
            "type":"Services"
        }
    ],
    "sg:phone":"+1 801 266 3431",
    "sg:postcode":"84107",
    "sg:province":"UT",
    "sg:tags":[
        "electrical",
        "contractor"
    ],
    "wof:name":"Sherman Freeze Electric",
    "wof:placetype":"venue"
},
  "geometry": {"coordinates":[-111.87989899999999,40.656159],"type":"Point"}
}