{
  "type": "Feature",
  "properties": {
    "iso:country":"US",
    "sg:address":"720 E Main St",
    "sg:city":"Price",
    "sg:classifiers":[
        {
            "category":"Communications",
            "subcategory":"Film & Video Production",
            "type":"Services"
        }
    ],
    "sg:phone":"+1 435 637 1074",
    "sg:postcode":"84501",
    "sg:province":"UT",
    "sg:tags":[
        "motion"
    ],
    "wof:name":"Feature Films For Families",
    "wof:placetype":"venue"
},
  "geometry": {"coordinates":[-110.79783500000001,39.599499],"type":"Point"}
}