{
  "type": "Feature",
  "properties": {
    "iso:country":"US",
    "sg:address":"1820 N 6900 E",
    "sg:city":"Croydon",
    "sg:classifiers":[
        {
            "category":"Autos & Motor Vehicles",
            "subcategory":"Automobile Sales",
            "type":"Retail Goods"
        }
    ],
    "sg:phone":"+1 801 829 0667",
    "sg:postcode":"84018",
    "sg:province":"UT",
    "wof:name":"Dallas Ferguson Auto",
    "wof:placetype":"venue"
},
  "geometry": {"coordinates":[-111.510041,41.072932],"type":"Point"}
}