{
  "type": "Feature",
  "properties": {
    "iso:country":"US",
    "sg:address":"1300 N Main St",
    "sg:city":"Spanish Fork",
    "sg:classifiers":[
        {
            "category":"Food & Beverages",
            "subcategory":"Groceries & Convenience Stores",
            "type":"Retail Goods"
        }
    ],
    "sg:phone":"+1 801 798 2137",
    "sg:postcode":"84660",
    "sg:province":"UT",
    "wof:name":"Pit Stop",
    "wof:placetype":"venue"
},
  "geometry": {"coordinates":[-111.654556,40.126512],"type":"Point"}
}