{
  "type": "Feature",
  "properties": {
    "iso:country":"US",
    "sg:address":"1770 W 4100 S",
    "sg:city":"West Valley",
    "sg:classifiers":[
        {
            "category":"Shopping",
            "subcategory":"Department Store",
            "type":"Retail Goods"
        }
    ],
    "sg:phone":"+1 801 973 7101",
    "sg:postcode":"84119",
    "sg:province":"UT",
    "wof:name":"Kmart",
    "wof:placetype":"venue"
},
  "geometry": {"coordinates":[-111.939049,40.682196],"type":"Point"}
}