{
  "type": "Feature",
  "properties": {
    "iso:country":"US",
    "sg:address":"312 N Main St",
    "sg:city":"Moab",
    "sg:classifiers":[
        {
            "category":"Autos & Motor Vehicles",
            "subcategory":"Auto Supplies",
            "type":"Retail Goods"
        }
    ],
    "sg:phone":"+1 435 259 7909",
    "sg:postcode":"84532",
    "sg:province":"UT",
    "sg:tags":[
        "tire"
    ],
    "wof:name":"Chip's Grand Tire Co",
    "wof:placetype":"venue"
},
  "geometry": {"coordinates":[-109.55077300000001,38.579095],"type":"Point"}
}