{
  "type": "Feature",
  "properties": {
    "iso:country":"US",
    "sg:address":"335 S 1300 E",
    "sg:city":"Bountiful",
    "sg:classifiers":[
        {
            "category":"Real Estate",
            "subcategory":"Real Estate Operator",
            "type":"Services"
        }
    ],
    "sg:phone":"+1 801 292 0331",
    "sg:postcode":"84010",
    "sg:province":"UT",
    "sg:tags":[
        "building",
        "nonresidential"
    ],
    "wof:name":"Campbell Properties LLC",
    "wof:placetype":"venue"
},
  "geometry": {"coordinates":[-111.853435,40.883641],"type":"Point"}
}