{
  "type": "Feature",
  "properties": {
    "iso:country":"US",
    "sg:address":"4633 Quail Vista Ln",
    "sg:city":"Salt Lake City",
    "sg:classifiers":[
        {
            "category":"Building & Trades",
            "subcategory":"Landscaping Services",
            "type":"Services"
        }
    ],
    "sg:phone":"+1 801 201 7852",
    "sg:postcode":"84117",
    "sg:province":"UT",
    "sg:tags":[
        "landscape"
    ],
    "wof:name":"R Yard Inc",
    "wof:placetype":"venue"
},
  "geometry": {"coordinates":[-111.860123,40.668448],"type":"Point"}
}