{
  "type": "Feature",
  "properties": {
    "iso:country":"US",
    "sg:address":"3449 Creek Rd",
    "sg:city":"Salt Lake City",
    "sg:classifiers":[
        {
            "category":"Professional",
            "type":"Services"
        }
    ],
    "sg:phone":"+1 801 456 0178",
    "sg:postcode":"84121",
    "sg:province":"UT",
    "wof:name":"Sunn Classic Pictures Inc",
    "wof:placetype":"venue"
},
  "geometry": {"coordinates":[-111.7966,40.604895],"type":"Point"}
}