{
  "type": "Feature",
  "properties": {
    "iso:country":"US",
    "sg:address":"2222 E 6525 S",
    "sg:city":"Salt Lake City",
    "sg:classifiers":[
        {
            "category":"Personal",
            "subcategory":"Beauty Salon",
            "type":"Services"
        }
    ],
    "sg:phone":"+1 801 942 0856",
    "sg:postcode":"84121",
    "sg:province":"UT",
    "sg:tags":[
        "shop"
    ],
    "wof:name":"Elite Design & Repair Inc",
    "wof:placetype":"venue"
},
  "geometry": {"coordinates":[-111.82719400000001,40.632455],"type":"Point"}
}