{
  "type": "Feature",
  "properties": {
    "iso:country":"US",
    "sg:address":"1448 W 1800 N",
    "sg:city":"Clearfield",
    "sg:classifiers":[
        {
            "category":"Organizations",
            "subcategory":"Religious Organization",
            "type":"Services"
        }
    ],
    "sg:phone":"+1 801 774 2055",
    "sg:postcode":"84015",
    "sg:province":"UT",
    "sg:tags":[
        "mormon",
        "church"
    ],
    "wof:name":"Clinton Eleventh Ward",
    "wof:placetype":"venue"
},
  "geometry": {"coordinates":[-112.054194,41.139945],"type":"Point"}
}