{
  "type": "Feature",
  "properties": {
    "iso:country":"US",
    "sg:address":"8655 Alta Cove Dr",
    "sg:city":"Sandy",
    "sg:classifiers":[
        {
            "category":"Professional",
            "subcategory":"Business Services",
            "type":"Services"
        }
    ],
    "sg:phone":"+1 801 944 1763",
    "sg:postcode":"84093",
    "sg:province":"UT",
    "wof:name":"Utopian Interior Design",
    "wof:placetype":"venue"
},
  "geometry": {"coordinates":[-111.829493,40.593597],"type":"Point"}
}