{
  "type": "Feature",
  "properties": {
    "iso:country":"US",
    "sg:address":"5387 N Enoch Rd",
    "sg:city":"Cedar City",
    "sg:classifiers":[
        {
            "category":"Professional",
            "subcategory":"Business Services",
            "type":"Services"
        }
    ],
    "sg:phone":"+1 435 867 9701",
    "sg:postcode":"84720",
    "sg:province":"UT",
    "wof:name":"At Home Technologies",
    "wof:placetype":"venue"
},
  "geometry": {"coordinates":[-113.024446,37.772545],"type":"Point"}
}