{
  "type": "Feature",
  "properties": {
    "iso:country":"US",
    "sg:address":"4314 W 4100 S",
    "sg:city":"Salt Lake City",
    "sg:classifiers":[
        {
            "category":"Organizations",
            "subcategory":"Professional Association",
            "type":"Services"
        }
    ],
    "sg:phone":"+1 801 969 1471",
    "sg:postcode":"84120",
    "sg:province":"UT",
    "wof:name":"West Valley Firefighters Assn",
    "wof:placetype":"venue"
},
  "geometry": {"coordinates":[-111.994195,40.682143],"type":"Point"}
}