{
  "type": "Feature",
  "properties": {
    "iso:country":"US",
    "sg:address":"124 20th St",
    "sg:city":"Ogden",
    "sg:classifiers":[
        {
            "category":"Manufacturing",
            "subcategory":"Tools & Machinery",
            "type":"Manufacturing & Wholesale Goods"
        }
    ],
    "sg:phone":"+1 801 621 1170",
    "sg:postcode":"84401",
    "sg:province":"UT",
    "wof:name":"Wright Auto Machine",
    "wof:placetype":"venue"
},
  "geometry": {"coordinates":[-111.976495,41.231263],"type":"Point"}
}