{
  "type": "Feature",
  "properties": {
    "iso:country":"US",
    "sg:address":"12351 Gateway Park Pl",
    "sg:city":"Draper",
    "sg:classifiers":[
        {
            "category":"Building & Trades",
            "subcategory":"Construction",
            "type":"Services"
        }
    ],
    "sg:phone":"+1 801 576 0067",
    "sg:postcode":"84020",
    "sg:province":"UT",
    "sg:tags":[
        "nonresidential"
    ],
    "wof:name":"Valley Veiw Building Maintance",
    "wof:placetype":"venue"
},
  "geometry": {"coordinates":[-111.902906,40.526012],"type":"Point"}
}