{
  "type": "Feature",
  "properties": {
    "iso:country":"US",
    "sg:address":"3789 W Atmore Rd",
    "sg:city":"West Jordan",
    "sg:classifiers":[
        {
            "category":"Real Estate",
            "subcategory":"Real Estate Agent",
            "type":"Services"
        }
    ],
    "sg:phone":"+1 801 966 6004",
    "sg:postcode":"84084",
    "sg:province":"UT",
    "wof:name":"Al and Patricia Fenimore",
    "wof:placetype":"venue"
},
  "geometry": {"coordinates":[-111.981353,40.635075],"type":"Point"}
}