{
  "type": "Feature",
  "properties": {
    "iso:country":"US",
    "sg:address":"1928 Bryan Rd",
    "sg:city":"Tooele",
    "sg:phone":"+1 435 833 9606",
    "sg:postcode":"84074",
    "sg:province":"UT",
    "sg:tags":[
        "irrigation",
        "company"
    ],
    "wof:name":"Settlement Canyon Irrigation",
    "wof:placetype":"venue"
},
  "geometry": {"coordinates":[-112.273886,40.609289],"type":"Point"}
}