{
  "type": "Feature",
  "properties": {
    "iso:country":"US",
    "sg:address":"501 Homesteader Ct",
    "sg:city":"Powell",
    "sg:classifiers":[
        {
            "category":"Sports & Exercise",
            "subcategory":"Sports Center",
            "type":"Entertainment"
        }
    ],
    "sg:phone":"+1 307 754 5711",
    "sg:postcode":"82435",
    "sg:province":"WY",
    "sg:tags":[
        "amateur",
        "team"
    ],
    "wof:name":"Powell Recreation District",
    "wof:placetype":"venue"
},
  "geometry": {"coordinates":[-111.871446,40.930746],"type":"Point"}
}