{
  "type": "Feature",
  "properties": {
    "iso:country":"US",
    "sg:address":"542 Blueridge Dr",
    "sg:city":"Tooele",
    "sg:classifiers":[
        {
            "category":"Shopping",
            "type":"Retail Goods"
        }
    ],
    "sg:phone":"+1 435 882 1382",
    "sg:postcode":"84074",
    "sg:province":"UT",
    "sg:tags":[
        "trophy",
        "medal",
        "award"
    ],
    "wof:name":"Tooele Trophy & Plaque",
    "wof:placetype":"venue"
},
  "geometry": {"coordinates":[-112.27964,40.542661],"type":"Point"}
}