{
  "type": "Feature",
  "properties": {
    "iso:country":"US",
    "sg:address":"689 E Center St",
    "sg:city":"Kaysville",
    "sg:classifiers":[
        {
            "category":"Professional",
            "subcategory":"Business Services",
            "type":"Services"
        }
    ],
    "sg:phone":"+1 801 544 8321",
    "sg:postcode":"84037",
    "sg:province":"UT",
    "wof:name":"Stewart SD Enterprises",
    "wof:placetype":"venue"
},
  "geometry": {"coordinates":[-111.924313,41.034835],"type":"Point"}
}