{
  "type": "Feature",
  "properties": {
    "iso:country":"US",
    "sg:address":"1074 S Main St",
    "sg:city":"Heber City",
    "sg:classifiers":[
        {
            "category":"Banks & Credit Unions",
            "subcategory":"Bank",
            "type":"Services"
        }
    ],
    "sg:phone":"+1 435 901 5494",
    "sg:postcode":"84032",
    "sg:province":"UT",
    "sg:tags":[
        "broker",
        "mortgage"
    ],
    "wof:name":"America One Mortgage",
    "wof:placetype":"venue"
},
  "geometry": {"coordinates":[-111.413538,40.493515],"type":"Point"}
}