{
  "type": "Feature",
  "properties": {
    "iso:country":"US",
    "sg:address":"330 E 3200 N",
    "sg:city":"Provo",
    "sg:classifiers":[
        {
            "category":"Professional",
            "type":"Services"
        }
    ],
    "sg:phone":"+1 801 377 3756",
    "sg:postcode":"84604",
    "sg:province":"UT",
    "sg:tags":[
        "establishment"
    ],
    "wof:name":"Jarom Loveridge",
    "wof:placetype":"venue"
},
  "geometry": {"coordinates":[-111.65309499999999,40.275969],"type":"Point"}
}