{
  "type": "Feature",
  "properties": {
    "iso:country":"US",
    "sg:address":"2500 S Main St",
    "sg:city":"South Salt Lake",
    "sg:classifiers":[
        {
            "category":"Bars & Pubs",
            "type":"Food & Drink"
        }
    ],
    "sg:phone":"+1 801 466 0567",
    "sg:postcode":"84115",
    "sg:province":"UT",
    "sg:website":"www.bonwoodbowl.com",
    "wof:name":"Bonwood Trophy Room",
    "wof:placetype":"venue"
},
  "geometry": {"coordinates":[-111.891189,40.716465],"type":"Point"}
}