{
  "type": "Feature",
  "properties": {
    "iso:country":"US",
    "sg:address":"1212 Beck St",
    "sg:city":"Salt Lake City",
    "sg:classifiers":[
        {
            "category":"Utilities",
            "subcategory":"Fuel Oil & Lpg",
            "type":"Services"
        }
    ],
    "sg:phone":"+1 801 322 5878",
    "sg:postcode":"84116",
    "sg:province":"UT",
    "sg:tags":[
        "propane",
        "gas"
    ],
    "wof:name":"AmeriGas",
    "wof:placetype":"venue"
},
  "geometry": {"coordinates":[-111.90796400000001,40.797842],"type":"Point"}
}