{
  "type": "Feature",
  "properties": {
    "iso:country":"US",
    "sg:address":"2390 N 2350 E",
    "sg:city":"Layton",
    "sg:classifiers":[
        {
            "category":"Real Estate",
            "subcategory":"Real Estate Agent",
            "type":"Services"
        }
    ],
    "sg:phone":"+1 801 546 1890",
    "sg:postcode":"84040",
    "sg:province":"UT",
    "wof:name":"Fielding Realty",
    "wof:placetype":"venue"
},
  "geometry": {"coordinates":[-111.920969,41.094703],"type":"Point"}
}