{
  "type": "Feature",
  "properties": {
    "iso:country":"US",
    "sg:address":"2441 S 1560 W",
    "sg:city":"Woods Cross",
    "sg:classifiers":[
        {
            "category":"Shopping",
            "subcategory":"Crafts & Fabrics",
            "type":"Retail Goods"
        }
    ],
    "sg:phone":"+1 801 298 1979",
    "sg:postcode":"84087",
    "sg:province":"UT",
    "sg:tags":[
        "art",
        "supply"
    ],
    "wof:name":"Lasting Impression",
    "wof:placetype":"venue"
},
  "geometry": {"coordinates":[-111.924004,40.863499],"type":"Point"}
}