{
  "type": "Feature",
  "properties": {
    "iso:country":"US",
    "sg:address":"155 E 400 S",
    "sg:city":"Richfield",
    "sg:classifiers":[
        {
            "category":"Organizations",
            "subcategory":"Religious Organization",
            "type":"Services"
        }
    ],
    "sg:phone":"+1 435 586 8571",
    "sg:postcode":"84701",
    "sg:province":"UT",
    "sg:tags":[
        "church"
    ],
    "wof:name":"Church Of Jesus Christ Of Lds",
    "wof:placetype":"venue"
},
  "geometry": {"coordinates":[-112.081611,38.762594],"type":"Point"}
}