{
  "type": "Feature",
  "properties": {
    "iso:country":"US",
    "sg:address":"799 N Redwood Rd",
    "sg:city":"Salt Lake City",
    "sg:classifiers":[
        {
            "category":"Building & Trades",
            "subcategory":"Equipment Rental",
            "type":"Services"
        }
    ],
    "sg:phone":"+1 801 521 8001",
    "sg:postcode":"84116",
    "sg:province":"UT",
    "sg:tags":[
        "yard"
    ],
    "wof:name":"Rent-A-Center",
    "wof:placetype":"venue"
},
  "geometry": {"coordinates":[-111.939368,40.784741],"type":"Point"}
}