{
  "type": "Feature",
  "properties": {
    "iso:country":"US",
    "sg:address":"84 S Main St",
    "sg:city":"Bountiful",
    "sg:classifiers":[
        {
            "category":"Banks & Credit Unions",
            "subcategory":"Investment Brokerage",
            "type":"Services"
        }
    ],
    "sg:phone":"+1 801 295 3351",
    "sg:postcode":"84010",
    "sg:province":"UT",
    "wof:name":"Security Investment Co",
    "wof:placetype":"venue"
},
  "geometry": {"coordinates":[-111.880776,40.889219],"type":"Point"}
}