{
  "type": "Feature",
  "properties": {
    "iso:country":"US",
    "sg:address":"1525 Gladiola St",
    "sg:city":"Salt Lake City",
    "sg:classifiers":[
        {
            "category":"Building & Trades",
            "subcategory":"Construction",
            "type":"Services"
        }
    ],
    "sg:phone":"+1 801 975 7160",
    "sg:postcode":"84104",
    "sg:province":"UT",
    "sg:tags":[
        "dry wall",
        "contractor"
    ],
    "wof:name":"Richard Brande Drywall Co",
    "wof:placetype":"venue"
},
  "geometry": {"coordinates":[-111.971671,40.737747],"type":"Point"}
}