{
  "type": "Feature",
  "properties": {
    "iso:country":"US",
    "sg:address":"350 W 800 N",
    "sg:city":"Salt Lake City",
    "sg:classifiers":[
        {
            "category":"Building & Trades",
            "subcategory":"Construction",
            "type":"Services"
        }
    ],
    "sg:phone":"+1 801 278 0251",
    "sg:postcode":"84103",
    "sg:province":"UT",
    "sg:tags":[
        "company"
    ],
    "wof:name":"Construction Materials Tech",
    "wof:placetype":"venue"
},
  "geometry": {"coordinates":[-111.901301,40.786808],"type":"Point"}
}