{
  "type": "Feature",
  "properties": {
    "iso:country":"US",
    "sg:address":"533 W Lakeview Rd",
    "sg:city":"Lindon",
    "sg:classifiers":[
        {
            "category":"Real Estate",
            "subcategory":"Real Estate Services",
            "type":"Services"
        },
        {
            "category":"Real Estate",
            "subcategory":"Real Estate Agent",
            "type":"Services"
        }
    ],
    "sg:phone":"+1 801 785 6025",
    "sg:postcode":"84042",
    "sg:province":"UT",
    "sg:tags":[
        "buyer",
        "broker"
    ],
    "wof:name":"Terry Dee Real Estate",
    "wof:placetype":"venue"
},
  "geometry": {"coordinates":[-111.728137,40.341957],"type":"Point"}
}