{
  "type": "Feature",
  "properties": {
    "iso:country":"US",
    "sg:address":"11811 S 700 W",
    "sg:city":"Draper",
    "sg:classifiers":[
        {
            "category":"Building & Trades",
            "subcategory":"Landscaping Services",
            "type":"Services"
        }
    ],
    "sg:phone":"+1 801 571 6278",
    "sg:postcode":"84020",
    "sg:province":"UT",
    "wof:name":"Davis & Sons Enterprises",
    "wof:placetype":"venue"
},
  "geometry": {"coordinates":[-111.91023300000001,40.535582],"type":"Point"}
}