{
  "type": "Feature",
  "properties": {
    "iso:country":"US",
    "sg:address":"852 S State St",
    "sg:city":"Orem",
    "sg:classifiers":[
        {
            "category":"Restaurant",
            "type":"Food & Drink"
        }
    ],
    "sg:phone":"+1 801 434 8424",
    "sg:postcode":"84097",
    "sg:province":"UT",
    "wof:name":"Bangkok Grill",
    "wof:placetype":"venue"
},
  "geometry": {"coordinates":[-111.688321,40.282057],"type":"Point"}
}