{
  "type": "Feature",
  "properties": {
    "iso:country":"US",
    "sg:address":"1076 Lake St",
    "sg:city":"Salt Lake City",
    "sg:classifiers":[
        {
            "category":"Restaurant",
            "type":"Food & Drink"
        }
    ],
    "sg:phone":"+1 801 531 8438",
    "sg:postcode":"84105",
    "sg:province":"UT",
    "sg:tags":[
        "eating"
    ],
    "wof:name":"Nibble or A Bite",
    "wof:placetype":"venue"
},
  "geometry": {"coordinates":[-111.869693,40.744419],"type":"Point"}
}