{
  "type": "Feature",
  "properties": {
    "iso:country":"US",
    "sg:address":"96 S Main St",
    "sg:city":"Payson",
    "sg:classifiers":[
        {
            "category":"Personal",
            "subcategory":"Shoe Repair & Shine",
            "type":"Services"
        }
    ],
    "sg:phone":"+1 801 465 4450",
    "sg:postcode":"84651",
    "sg:province":"UT",
    "sg:tags":[
        "parlor",
        "gallery"
    ],
    "wof:name":"Fantasy As ME Mm N ML Sp",
    "wof:placetype":"venue"
},
  "geometry": {"coordinates":[-111.732361,40.04254],"type":"Point"}
}