{
  "type": "Feature",
  "properties": {
    "iso:country":"US",
    "sg:address":"920 W 600 N",
    "sg:city":"Brigham City",
    "sg:classifiers":[
        {
            "category":"Wholesale",
            "subcategory":"Construction Materials",
            "type":"Manufacturing & Wholesale Goods"
        }
    ],
    "sg:phone":"+1 435 734 2785",
    "sg:postcode":"84302",
    "sg:province":"UT",
    "sg:tags":[
        "post",
        "fitting",
        "fence"
    ],
    "wof:name":"Smi Southern Post Co",
    "wof:placetype":"venue"
},
  "geometry": {"coordinates":[-112.03065700000001,41.522521],"type":"Point"}
}