{
  "type": "Feature",
  "properties": {
    "iso:country":"US",
    "sg:address":"346 E Main St",
    "sg:city":"Vernal",
    "sg:classifiers":[
        {
            "category":"Utilities",
            "subcategory":"Refuse",
            "type":"Services"
        }
    ],
    "sg:phone":"+1 435 789 2743",
    "sg:postcode":"84078",
    "sg:province":"UT",
    "sg:tags":[
        "sanitation"
    ],
    "wof:name":"G & H Garbage Svc",
    "wof:placetype":"venue"
},
  "geometry": {"coordinates":[-109.522283,40.455715],"type":"Point"}
}