{
  "type": "Feature",
  "properties": {
    "iso:country":"US",
    "sg:address":"871 E 1025 S",
    "sg:city":"Ogden",
    "sg:classifiers":[
        {
            "category":"Government",
            "subcategory":"Office",
            "type":"Public Place"
        }
    ],
    "sg:phone":"+1 801 777 5723",
    "sg:postcode":"84404",
    "sg:province":"UT",
    "sg:tags":[
        "national",
        "security"
    ],
    "wof:name":"Hill Air Force Base",
    "wof:placetype":"venue"
},
  "geometry": {"coordinates":[-111.956506,41.245966],"type":"Point"}
}