{
  "type": "Feature",
  "properties": {
    "iso:country":"US",
    "sg:address":"997 E 40 N",
    "sg:city":"Springville",
    "sg:classifiers":[
        {
            "category":"Building & Trades",
            "subcategory":"Construction",
            "type":"Services"
        }
    ],
    "sg:phone":"+1 801 491 6832",
    "sg:postcode":"84663",
    "sg:province":"UT",
    "sg:tags":[
        "contractor"
    ],
    "wof:name":"Aragon Marble & Tile Inc",
    "wof:placetype":"venue"
},
  "geometry": {"coordinates":[-111.592523,40.167383],"type":"Point"}
}