{
  "type": "Feature",
  "properties": {
    "iso:country":"US",
    "sg:address":"4141 S State St",
    "sg:city":"Salt Lake City",
    "sg:classifiers":[
        {
            "category":"Bars & Pubs",
            "type":"Food & Drink"
        }
    ],
    "sg:phone":"+1 801 261 3463",
    "sg:postcode":"84107",
    "sg:province":"UT",
    "sg:tags":[
        "drinking"
    ],
    "wof:name":"Phat Mammals LLC",
    "wof:placetype":"venue"
},
  "geometry": {"coordinates":[-111.888172,40.681769],"type":"Point"}
}