{
  "type": "Feature",
  "properties": {
    "iso:country":"US",
    "sg:address":"8845 Cedar St",
    "sg:city":"West Jordan",
    "sg:classifiers":[
        {
            "category":"Professional",
            "subcategory":"Engineering",
            "type":"Services"
        }
    ],
    "sg:phone":"+1 801 566 3619",
    "sg:postcode":"84088",
    "sg:province":"UT",
    "wof:name":"Michael G Heinecke",
    "wof:placetype":"venue"
},
  "geometry": {"coordinates":[-111.931515,40.590393],"type":"Point"}
}