{
  "type": "Feature",
  "properties": {
    "iso:country":"US",
    "sg:address":"4020 S 700 E",
    "sg:city":"Murray",
    "sg:classifiers":[
        {
            "category":"Real Estate",
            "subcategory":"Architect",
            "type":"Services"
        }
    ],
    "sg:phone":"+1 801 261 0305",
    "sg:postcode":"84107",
    "sg:province":"UT",
    "sg:tags":[
        "firm",
        "home",
        "planning",
        "design"
    ],
    "wof:name":"Hearthstone Design Inc",
    "wof:placetype":"venue"
},
  "geometry": {"coordinates":[-111.87144000000001,40.683865],"type":"Point"}
}