{
  "type": "Feature",
  "properties": {
    "iso:country":"US",
    "sg:address":"235 W 300 S",
    "sg:city":"Provo",
    "sg:classifiers":[
        {
            "category":"Retail",
            "subcategory":"Auto Repair",
            "type":"Services"
        }
    ],
    "sg:phone":"+1 801 373 9696",
    "sg:postcode":"84601",
    "sg:province":"UT",
    "sg:tags":[
        "repairing",
        "automobile",
        "general"
    ],
    "wof:name":"Japanese Auto Repair Inc",
    "wof:placetype":"venue"
},
  "geometry": {"coordinates":[-111.663505,40.229626],"type":"Point"}
}