{
  "type": "Feature",
  "properties": {
    "iso:country":"US",
    "sg:address":"74 S Main St",
    "sg:city":"Salt Lake City",
    "sg:classifiers":[
        {
            "category":"Food & Beverages",
            "subcategory":"Candy",
            "type":"Retail Goods"
        }
    ],
    "sg:phone":"+1 801 532 2312",
    "sg:postcode":"84101",
    "sg:province":"UT",
    "wof:name":"Sees Candies Ut003",
    "wof:placetype":"venue"
},
  "geometry": {"coordinates":[-111.89117,40.768803],"type":"Point"}
}