{
  "type": "Feature",
  "properties": {
    "iso:country":"US",
    "sg:address":"456 E State Rd",
    "sg:city":"American Fork",
    "sg:classifiers":[
        {
            "category":"Personal",
            "subcategory":"Beauty Salon",
            "type":"Services"
        }
    ],
    "sg:phone":"+1 801 763 8050",
    "sg:postcode":"84003",
    "sg:province":"UT",
    "sg:tags":[
        "manicuring"
    ],
    "wof:name":"L A Nail",
    "wof:placetype":"venue"
},
  "geometry": {"coordinates":[-111.786573,40.374175],"type":"Point"}
}