{
  "type": "Feature",
  "properties": {
    "iso:country":"US",
    "sg:address":"261 N Commercial St",
    "sg:city":"Morgan",
    "sg:classifiers":[
        {
            "category":"Manufacturing",
            "subcategory":"Tools & Machinery",
            "type":"Manufacturing & Wholesale Goods"
        }
    ],
    "sg:phone":"+1 801 829 3021",
    "sg:postcode":"84050",
    "sg:province":"UT",
    "sg:tags":[
        "machine",
        "shop"
    ],
    "wof:name":"Bart's Machine Shop Inc",
    "wof:placetype":"venue"
},
  "geometry": {"coordinates":[-111.67496199999999,41.045499],"type":"Point"}
}