{
  "type": "Feature",
  "properties": {
    "iso:country":"US",
    "sg:address":"818 Summit Dr",
    "sg:city":"Smithfield",
    "sg:classifiers":[
        {
            "category":"Professional",
            "subcategory":"Management & Consulting",
            "type":"Services"
        }
    ],
    "sg:phone":"+1 435 797 1116",
    "sg:postcode":"84335",
    "sg:province":"UT",
    "sg:tags":[
        "consultant"
    ],
    "wof:name":"Stan Albrecht",
    "wof:placetype":"venue"
},
  "geometry": {"coordinates":[-111.80886700000001,41.842054],"type":"Point"}
}