{
  "type": "Feature",
  "properties": {
    "iso:country":"US",
    "sg:address":"668 S Main St",
    "sg:city":"Brigham City",
    "sg:classifiers":[
        {
            "category":"Shopping",
            "subcategory":"Used Merchandise",
            "type":"Retail Goods"
        }
    ],
    "sg:phone":"+1 435 723 8741",
    "sg:postcode":"84302",
    "sg:province":"UT",
    "sg:tags":[
        "organization",
        "religious"
    ],
    "wof:name":"Deseret Industries",
    "wof:placetype":"venue"
},
  "geometry": {"coordinates":[-112.01606099999999,41.49765],"type":"Point"}
}