{
  "type": "Feature",
  "properties": {
    "iso:country":"US",
    "sg:address":"260 S 1300 E",
    "sg:city":"Salt Lake City",
    "sg:classifiers":[
        {
            "category":"Restaurant",
            "type":"Food & Drink"
        }
    ],
    "sg:menulink":"http://www.allmenus.com/ut/salt-lake-city/35623-market-street-grill/menu/",
    "sg:phone":"+1 801 583 8808",
    "sg:postcode":"84102",
    "sg:province":"UT",
    "sg:tags":[
        "seafood",
        "american"
    ],
    "wof:name":"Market Street Grill",
    "wof:placetype":"venue"
},
  "geometry": {"coordinates":[-111.85388,40.763701],"type":"Point"}
}