{
  "type": "Feature",
  "properties": {
    "iso:country":"US",
    "sg:address":"695 E Mill St",
    "sg:city":"Bountiful",
    "sg:classifiers":[
        {
            "category":"Professional",
            "subcategory":"Management & Consulting",
            "type":"Services"
        }
    ],
    "sg:phone":"+1 801 294 9517",
    "sg:postcode":"84010",
    "sg:province":"UT",
    "wof:name":"Kw Marketing Inc",
    "wof:placetype":"venue"
},
  "geometry": {"coordinates":[-111.86769,40.879841],"type":"Point"}
}