{
  "type": "Feature",
  "properties": {
    "iso:country":"US",
    "sg:address":"1992 W Antelope Dr",
    "sg:city":"Layton",
    "sg:classifiers":[
        {
            "category":"Personal",
            "subcategory":"Tanning Parlor",
            "type":"Services"
        }
    ],
    "sg:phone":"+1 801 774 6022",
    "sg:postcode":"84041",
    "sg:province":"UT",
    "sg:tags":[
        "salon"
    ],
    "wof:name":"A Shore Tan",
    "wof:placetype":"venue"
},
  "geometry": {"coordinates":[-112.006472,41.0892],"type":"Point"}
}