{
  "type": "Feature",
  "properties": {
    "iso:country":"US",
    "sg:address":"1015 S State St",
    "sg:city":"Orem",
    "sg:classifiers":[
        {
            "category":"Freight",
            "type":"Transportation"
        }
    ],
    "sg:phone":"+1 801 375 0080",
    "sg:postcode":"84097",
    "sg:province":"UT",
    "sg:tags":[
        "operator",
        "local",
        "trucking"
    ],
    "wof:name":"Dunkley Piano Movers",
    "wof:placetype":"venue"
},
  "geometry": {"coordinates":[-111.686289,40.277519],"type":"Point"}
}