{
  "type": "Feature",
  "properties": {
    "iso:country":"US",
    "sg:address":"7840 Main St",
    "sg:city":"Midvale",
    "sg:classifiers":[
        {
            "category":"Building & Trades",
            "subcategory":"Landscaping Services",
            "type":"Services"
        }
    ],
    "sg:phone":"+1 801 561 3431",
    "sg:postcode":"84047",
    "sg:province":"UT",
    "wof:name":"Jeff Borovatz Landscaping",
    "wof:placetype":"venue"
},
  "geometry": {"coordinates":[-111.910264,40.609623],"type":"Point"}
}