{
  "type": "Feature",
  "properties": {
    "iso:country":"US",
    "sg:address":"9987 Marble St",
    "sg:city":"Sandy",
    "sg:classifiers":[
        {
            "category":"Building & Trades",
            "subcategory":"Construction",
            "type":"Services"
        }
    ],
    "sg:phone":"+1 801 910 2181",
    "sg:postcode":"84094",
    "sg:province":"UT",
    "sg:tags":[
        "painter"
    ],
    "wof:name":"Accu-Paint & Refinish",
    "wof:placetype":"venue"
},
  "geometry": {"coordinates":[-111.857285,40.570286],"type":"Point"}
}