{
  "type": "Feature",
  "properties": {
    "iso:country":"US",
    "sg:address":"45 N 900 E",
    "sg:city":"St George",
    "sg:classifiers":[
        {
            "category":"Building & Trades",
            "subcategory":"Construction",
            "type":"Services"
        }
    ],
    "sg:phone":"+1 435 673 2154",
    "sg:postcode":"84770",
    "sg:province":"UT",
    "sg:tags":[
        "steel",
        "erection",
        "fabrication",
        "structural"
    ],
    "wof:name":"McArthur Welding",
    "wof:placetype":"venue"
},
  "geometry": {"coordinates":[-113.564302,37.109038],"type":"Point"}
}