{
  "type": "Feature",
  "properties": {
    "iso:country":"US",
    "sg:address":"815 W 3050 S",
    "sg:city":"Syracuse",
    "sg:classifiers":[
        {
            "category":"Real Estate",
            "subcategory":"Real Estate Agent",
            "type":"Services"
        }
    ],
    "sg:phone":"+1 801 690 1813",
    "sg:postcode":"84075",
    "sg:province":"UT",
    "wof:name":"Pentella Real Estate & Dev",
    "wof:placetype":"venue"
},
  "geometry": {"coordinates":[-112.03981400000001,41.06969],"type":"Point"}
}