{
  "type": "Feature",
  "properties": {
    "iso:country":"US",
    "sg:address":"466 N Main St",
    "sg:city":"Clearfield",
    "sg:classifiers":[
        {
            "category":"Building & Trades",
            "subcategory":"Construction",
            "type":"Services"
        }
    ],
    "sg:phone":"+1 801 774 6060",
    "sg:postcode":"84015",
    "sg:province":"UT",
    "sg:tags":[
        "general",
        "contractor"
    ],
    "wof:name":"R H Van Komen & Co",
    "wof:placetype":"venue"
},
  "geometry": {"coordinates":[-112.02594499999999,41.120922],"type":"Point"}
}