{
  "type": "Feature",
  "properties": {
    "iso:country":"US",
    "sg:address":"8494 Jardim Way",
    "sg:city":"Sandy",
    "sg:classifiers":[
        {
            "category":"Building & Trades",
            "subcategory":"Plumbing",
            "type":"Services"
        }
    ],
    "sg:phone":"+1 801 453 0270",
    "sg:postcode":"84093",
    "sg:province":"UT",
    "sg:tags":[
        "contractor"
    ],
    "wof:name":"Gs Plumbing",
    "wof:placetype":"venue"
},
  "geometry": {"coordinates":[-111.835933,40.596404],"type":"Point"}
}