{
  "type": "Feature",
  "properties": {
    "iso:country":"US",
    "sg:address":"3084 S 8400 W",
    "sg:city":"Magna",
    "sg:classifiers":[
        {
            "category":"Organizations",
            "subcategory":"Religious Organization",
            "type":"Services"
        }
    ],
    "sg:phone":"+1 801 252 2514",
    "sg:postcode":"84044",
    "sg:province":"UT",
    "sg:tags":[
        "bishop"
    ],
    "wof:name":"Pleasant Green Fourth Ward",
    "wof:placetype":"venue"
},
  "geometry": {"coordinates":[-112.091885,40.70394],"type":"Point"}
}