{
  "type": "Feature",
  "properties": {
    "iso:country":"US",
    "sg:address":"789 Bamberger Dr",
    "sg:city":"American Fork",
    "sg:classifiers":[
        {
            "category":"Professional",
            "subcategory":"Research",
            "type":"Services"
        }
    ],
    "sg:phone":"+1 801 763 1811",
    "sg:postcode":"84003",
    "sg:province":"UT",
    "wof:name":"Anasazi Cultural Research",
    "wof:placetype":"venue"
},
  "geometry": {"coordinates":[-111.777671,40.373698],"type":"Point"}
}