{
  "type": "Feature",
  "properties": {
    "iso:country":"US",
    "sg:address":"2950 Upland Dr",
    "sg:city":"Salt Lake City",
    "sg:classifiers":[
        {
            "category":"Professional",
            "type":"Services"
        }
    ],
    "sg:phone":"+1 801 274 1559",
    "sg:postcode":"84109",
    "sg:province":"UT",
    "wof:name":"Accelered",
    "wof:placetype":"venue"
},
  "geometry": {"coordinates":[-111.808865,40.688875],"type":"Point"}
}