{
  "type": "Feature",
  "properties": {
    "iso:country":"US",
    "sg:address":"2060 W Moonglow Pl",
    "sg:city":"St George",
    "sg:classifiers":[
        {
            "category":"Mining & Drilling",
            "type":"Manufacturing & Wholesale Goods"
        }
    ],
    "sg:phone":"+1 435 628 0385",
    "sg:postcode":"84770",
    "sg:province":"UT",
    "sg:tags":[
        "metal"
    ],
    "wof:name":"Sandel Mining Corp",
    "wof:placetype":"venue"
},
  "geometry": {"coordinates":[-113.627313,37.118014],"type":"Point"}
}