{
  "type": "Feature",
  "properties": {
    "iso:country":"US",
    "sg:address":"255 S Geneva Rd",
    "sg:city":"Orem",
    "sg:classifiers":[
        {
            "category":"Building & Trades",
            "subcategory":"Construction",
            "type":"Services"
        },
        {
            "category":"Wholesale",
            "subcategory":"Auto Parts",
            "type":"Manufacturing & Wholesale Goods"
        }
    ],
    "sg:phone":"+1 801 225 2308",
    "sg:postcode":"84058",
    "sg:province":"UT",
    "sg:tags":[
        "equipment",
        "rebuilt",
        "truck",
        "contractor"
    ],
    "wof:name":"Rawlings Auto Wrecking Inc",
    "wof:placetype":"venue"
},
  "geometry": {"coordinates":[-111.733729,40.296508],"type":"Point"}
}