{
  "type": "Feature",
  "properties": {
    "iso:country":"US",
    "sg:address":"1331 W 1225 S",
    "sg:city":"Cedar City",
    "sg:classifiers":[
        {
            "category":"Building & Trades",
            "subcategory":"Plumbing",
            "type":"Services"
        }
    ],
    "sg:phone":"+1 435 865 7430",
    "sg:postcode":"84720",
    "sg:province":"UT",
    "sg:tags":[
        "contractor"
    ],
    "wof:name":"In & Out Plumbing & Mech Inc",
    "wof:placetype":"venue"
},
  "geometry": {"coordinates":[-113.07989600000001,37.656286],"type":"Point"}
}