{
  "type": "Feature",
  "properties": {
    "iso:country":"US",
    "sg:address":"8415 S 700 W",
    "sg:city":"Sandy",
    "sg:classifiers":[
        {
            "category":"Banks & Credit Unions",
            "subcategory":"Investment Brokerage",
            "type":"Services"
        }
    ],
    "sg:phone":"+1 801 304 9966",
    "sg:postcode":"84070",
    "sg:province":"UT",
    "wof:name":"Vsp Investments",
    "wof:placetype":"venue"
},
  "geometry": {"coordinates":[-111.910331,40.59951],"type":"Point"}
}