{
  "type": "Feature",
  "properties": {
    "iso:country":"US",
    "sg:address":"910 Main St",
    "sg:city":"Green River",
    "sg:classifiers":[
        {
            "category":"Travel",
            "subcategory":"Campground",
            "type":"Entertainment"
        }
    ],
    "sg:phone":"+1 435 564 8195",
    "sg:postcode":"84525",
    "sg:province":"UT",
    "wof:name":"United Campgrounds",
    "wof:placetype":"venue"
},
  "geometry": {"coordinates":[-110.142655,38.991288],"type":"Point"}
}