{
  "type": "Feature",
  "properties": {
    "iso:country":"US",
    "sg:address":"47 N Main St",
    "sg:city":"Kaysville",
    "sg:classifiers":[
        {
            "category":"Personal",
            "type":"Services"
        }
    ],
    "sg:phone":"+1 801 546 3874",
    "sg:postcode":"84037",
    "sg:province":"UT",
    "sg:tags":[
        "credit",
        "debt",
        "counseling"
    ],
    "wof:name":"Utah Debtor's Legal Relief",
    "wof:placetype":"venue"
},
  "geometry": {"coordinates":[-111.938687,41.035507],"type":"Point"}
}