{
  "type": "Feature",
  "properties": {
    "iso:country":"US",
    "sg:address":"3344 Polk Ave",
    "sg:city":"Ogden",
    "sg:classifiers":[
        {
            "category":"Banks & Credit Unions",
            "subcategory":"Investment Brokerage",
            "type":"Services"
        }
    ],
    "sg:phone":"+1 801 392 6249",
    "sg:postcode":"84403",
    "sg:province":"UT",
    "sg:tags":[
        "advisory"
    ],
    "wof:name":"Strategic Financial Options",
    "wof:placetype":"venue"
},
  "geometry": {"coordinates":[-111.943558,41.203],"type":"Point"}
}