{
  "type": "Feature",
  "properties": {
    "iso:country":"US",
    "sg:address":"689 N State St",
    "sg:city":"Hurricane",
    "sg:classifiers":[
        {
            "category":"Manufacturing",
            "subcategory":"Glass & Minerals",
            "type":"Manufacturing & Wholesale Goods"
        }
    ],
    "sg:phone":"+1 435 874 2889",
    "sg:postcode":"84737",
    "sg:province":"UT",
    "sg:tags":[
        "ready"
    ],
    "wof:name":"Sun & Sand Svc",
    "wof:placetype":"venue"
},
  "geometry": {"coordinates":[-113.279967,37.18724],"type":"Point"}
}