{
  "type": "Feature",
  "properties": {
    "iso:country":"US",
    "sg:address":"690 W 100 N",
    "sg:city":"Hurricane",
    "sg:classifiers":[
        {
            "category":"Building & Trades",
            "subcategory":"Equipment Rental",
            "type":"Services"
        }
    ],
    "sg:phone":"+1 435 635 4508",
    "sg:postcode":"84737",
    "sg:province":"UT",
    "wof:name":"Roseys Rentals",
    "wof:placetype":"venue"
},
  "geometry": {"coordinates":[-113.30041199999999,37.178027],"type":"Point"}
}