{
  "type": "Feature",
  "properties": {
    "iso:country":"US",
    "sg:address":"10225 Oak Creek Ln",
    "sg:city":"American Fork",
    "sg:classifiers":[
        {
            "category":"Communications",
            "subcategory":"Film & Video Production",
            "type":"Services"
        }
    ],
    "sg:phone":"+1 801 492 1200",
    "sg:postcode":"84003",
    "sg:province":"UT",
    "sg:tags":[
        "motion"
    ],
    "wof:name":"Iron Rod Filmworks LLC",
    "wof:placetype":"venue"
},
  "geometry": {"coordinates":[-111.779892,40.419712],"type":"Point"}
}