{
  "type": "Feature",
  "properties": {
    "iso:country":"US",
    "sg:address":"593 W 2325 N",
    "sg:city":"Layton",
    "sg:classifiers":[
        {
            "category":"Building & Trades",
            "subcategory":"Construction",
            "type":"Services"
        }
    ],
    "sg:phone":"+1 801 775 0730",
    "sg:postcode":"84041",
    "sg:province":"UT",
    "sg:tags":[
        "contractor"
    ],
    "wof:name":"Berg Roofing Inc",
    "wof:placetype":"venue"
},
  "geometry": {"coordinates":[-111.97731899999999,41.093805],"type":"Point"}
}