{
  "type": "Feature",
  "properties": {
    "iso:country":"US",
    "sg:address":"2630 S 300 W",
    "sg:city":"South Salt Lake",
    "sg:classifiers":[
        {
            "category":"Education",
            "subcategory":"Dance Studio",
            "type":"Public Place"
        },
        {
            "category":"Arts & Performance",
            "subcategory":"Theater",
            "type":"Entertainment"
        }
    ],
    "sg:phone":"+1 801 467 0700",
    "sg:postcode":"84115",
    "sg:province":"UT",
    "sg:tags":[
        "entertainer"
    ],
    "wof:name":"American Bush Inc",
    "wof:placetype":"venue"
},
  "geometry": {"coordinates":[-111.89975099999999,40.714301],"type":"Point"}
}