{
  "type": "Feature",
  "properties": {
    "iso:country":"US",
    "sg:address":"290 E 1400 S",
    "sg:city":"Bountiful",
    "sg:classifiers":[
        {
            "category":"Professional",
            "subcategory":"Detective & Security Services",
            "type":"Services"
        }
    ],
    "sg:phone":"+1 801 298 3295",
    "sg:postcode":"84010",
    "sg:province":"UT",
    "sg:tags":[
        "car"
    ],
    "wof:name":"Fdr Laborties",
    "wof:placetype":"venue"
},
  "geometry": {"coordinates":[-111.873316,40.875618],"type":"Point"}
}