{
  "type": "Feature",
  "properties": {
    "iso:country":"US",
    "sg:address":"3070 Rasmussen Rd",
    "sg:city":"Park City",
    "sg:classifiers":[
        {
            "category":"Professional",
            "subcategory":"Art Services",
            "type":"Services"
        }
    ],
    "sg:phone":"+1 435 647 5833",
    "sg:postcode":"84098",
    "sg:province":"UT",
    "sg:tags":[
        "commercial",
        "design"
    ],
    "wof:name":"Matt Yeates Design",
    "wof:placetype":"venue"
},
  "geometry": {"coordinates":[-111.566525,40.749561],"type":"Point"}
}