{
  "type": "Feature",
  "properties": {
    "iso:country":"US",
    "sg:address":"4767 Bronbreck Dr",
    "sg:city":"Salt Lake City",
    "sg:classifiers":[
        {
            "category":"Wholesale",
            "subcategory":"Non-durable Goods",
            "type":"Manufacturing & Wholesale Goods"
        }
    ],
    "sg:phone":"+1 801 277 4761",
    "sg:postcode":"84117",
    "sg:province":"UT",
    "wof:name":"High Desert Trading LLC",
    "wof:placetype":"venue"
},
  "geometry": {"coordinates":[-111.807479,40.664318],"type":"Point"}
}