{
  "type": "Feature",
  "properties": {
    "iso:country":"US",
    "sg:address":"2537 S 1000 W",
    "sg:city":"Syracuse",
    "sg:classifiers":[
        {
            "category":"Banks & Credit Unions",
            "subcategory":"Financial Services",
            "type":"Services"
        }
    ],
    "sg:phone":"+1 801 825 6516",
    "sg:postcode":"84075",
    "sg:province":"UT",
    "sg:tags":[
        "investor"
    ],
    "wof:name":"Tasties Investments LLC",
    "wof:placetype":"venue"
},
  "geometry": {"coordinates":[-112.045311,41.074976],"type":"Point"}
}