{
  "type": "Feature",
  "properties": {
    "iso:country":"US",
    "sg:address":"3370 Polk Ave",
    "sg:city":"Ogden",
    "sg:classifiers":[
        {
            "category":"Education",
            "subcategory":"School",
            "type":"Public Place"
        }
    ],
    "sg:phone":"+1 801 737 8450",
    "sg:postcode":"84403",
    "sg:province":"UT",
    "wof:name":"Wasatch Elementary School",
    "wof:placetype":"venue"
},
  "geometry": {"coordinates":[-111.943427,41.203259],"type":"Point"}
}