{
  "type": "Feature",
  "properties": {
    "iso:country":"US",
    "sg:address":"1154 S 1300 E",
    "sg:city":"Bountiful",
    "sg:classifiers":[
        {
            "category":"Banks & Credit Unions",
            "subcategory":"Financial Services",
            "type":"Services"
        }
    ],
    "sg:phone":"+1 801 292 3668",
    "sg:postcode":"84010",
    "sg:province":"UT",
    "sg:tags":[
        "investor"
    ],
    "wof:name":"Hogan Dg Investments LLC",
    "wof:placetype":"venue"
},
  "geometry": {"coordinates":[-111.853539,40.878086],"type":"Point"}
}