{
  "type": "Feature",
  "properties": {
    "iso:country":"US",
    "sg:address":"1260 W 1150 N",
    "sg:city":"Provo",
    "sg:classifiers":[
        {
            "category":"Organizations",
            "subcategory":"Religious Organization",
            "type":"Services"
        }
    ],
    "sg:phone":"+1 801 370 6761",
    "sg:postcode":"84604",
    "sg:province":"UT",
    "sg:tags":[
        "church"
    ],
    "wof:name":"Church Of Jesus Christ Of Lds",
    "wof:placetype":"venue"
},
  "geometry": {"coordinates":[-111.68092900000001,40.24986],"type":"Point"}
}