{
  "type": "Feature",
  "properties": {
    "iso:country":"US",
    "sg:address":"1202 E 500 S",
    "sg:city":"Spanish Fork",
    "sg:classifiers":[
        {
            "category":"Building & Trades",
            "subcategory":"Construction",
            "type":"Services"
        }
    ],
    "sg:phone":"+1 801 798 1330",
    "sg:postcode":"84660",
    "sg:province":"UT",
    "sg:tags":[
        "residential",
        "commercial"
    ],
    "wof:name":"Tkl Construction",
    "wof:placetype":"venue"
},
  "geometry": {"coordinates":[-111.632198,40.103798],"type":"Point"}
}