{
  "type": "Feature",
  "properties": {
    "iso:country":"US",
    "sg:address":"870 N Highway 89",
    "sg:city":"North Salt Lake",
    "sg:classifiers":[
        {
            "category":"Banks & Credit Unions",
            "subcategory":"Bank",
            "type":"Services"
        }
    ],
    "sg:phone":"+1 801 292 4108",
    "sg:postcode":"84054",
    "sg:province":"UT",
    "sg:website":"www.zionsbank.com",
    "wof:name":"Zions Bank",
    "wof:placetype":"venue"
},
  "geometry": {"coordinates":[-111.896004,40.861198],"type":"Point"}
}