{
  "type": "Feature",
  "properties": {
    "iso:country":"US",
    "sg:address":"885 E 3900 S",
    "sg:city":"Murray",
    "sg:classifiers":[
        {
            "category":"Restaurant",
            "type":"Food & Drink"
        }
    ],
    "sg:phone":"+1 801 269 1177",
    "sg:postcode":"84107",
    "sg:province":"UT",
    "wof:name":"Cancun Cafe",
    "wof:placetype":"venue"
},
  "geometry": {"coordinates":[-111.86608,40.687141],"type":"Point"}
}