{
  "type": "Feature",
  "properties": {
    "iso:country":"US",
    "sg:address":"4591 S 5600 W",
    "sg:city":"West Valley",
    "sg:classifiers":[
        {
            "category":"Restaurant",
            "type":"Food & Drink"
        }
    ],
    "sg:phone":"+1 801 968 2130",
    "sg:postcode":"84120",
    "sg:province":"UT",
    "sg:website":"www.absdrivein.com",
    "wof:name":"Ab's Drive-In",
    "wof:placetype":"venue"
},
  "geometry": {"coordinates":[-112.02462,40.67256],"type":"Point"}
}