{
  "type": "Feature",
  "properties": {
    "iso:country":"US",
    "sg:address":"1425 N. 400 West",
    "sg:city":"Beaver",
    "sg:classifiers":[
        {
            "category":"Restaurant",
            "type":"Food & Drink"
        }
    ],
    "sg:menulink":"http://www.allmenus.com/ut/beaver/68464-pizza-factory/menu/",
    "sg:phone":"+1 435 438 5761",
    "sg:postcode":"84713",
    "sg:province":"UT",
    "sg:tags":[
        "american",
        "pizza"
    ],
    "wof:name":"Pizza Factory",
    "wof:placetype":"venue"
},
  "geometry": {"coordinates":[-112.64847899999999,38.293133],"type":"Point"}
}