{
  "type": "Feature",
  "properties": {
    "iso:country":"US",
    "sg:address":"2984 S 300 W",
    "sg:city":"Salt Lake City",
    "sg:classifiers":[
        {
            "category":"Autos & Motor Vehicles",
            "subcategory":"Auto Supplies",
            "type":"Retail Goods"
        }
    ],
    "sg:phone":"+1 801 413 0300",
    "sg:postcode":"84115",
    "sg:province":"UT",
    "sg:tags":[
        "equipment",
        "racing",
        "car",
        "automobile"
    ],
    "wof:name":"Import Car Tuner",
    "wof:placetype":"venue"
},
  "geometry": {"coordinates":[-111.89978600000001,40.705909],"type":"Point"}
}