{
  "type": "Feature",
  "properties": {
    "iso:country":"US",
    "sg:address":"7148 S 2470 W",
    "sg:city":"West Jordan",
    "sg:classifiers":[
        {
            "category":"Building & Trades",
            "subcategory":"Construction",
            "type":"Services"
        }
    ],
    "sg:phone":"+1 801 561 8853",
    "sg:postcode":"84084",
    "sg:province":"UT",
    "sg:tags":[
        "house"
    ],
    "wof:name":"Vance Construction",
    "wof:placetype":"venue"
},
  "geometry": {"coordinates":[-111.95358,40.621833],"type":"Point"}
}