{
  "type": "Feature",
  "properties": {
    "iso:country":"US",
    "sg:address":"8890 S 1030 W",
    "sg:city":"West Jordan",
    "sg:classifiers":[
        {
            "category":"Food & Beverages",
            "subcategory":"Bakery",
            "type":"Retail Goods"
        }
    ],
    "sg:phone":"+1 801 748 4230",
    "sg:postcode":"84088",
    "sg:province":"UT",
    "sg:tags":[
        "baker"
    ],
    "wof:name":"Globe Bakery",
    "wof:placetype":"venue"
},
  "geometry": {"coordinates":[-111.92089900000001,40.588746],"type":"Point"}
}