{
  "type": "Feature",
  "properties": {
    "iso:country":"US",
    "sg:address":"151 S 500 E",
    "sg:city":"Salt Lake City",
    "sg:classifiers":[
        {
            "category":"Shopping",
            "subcategory":"Books",
            "type":"Retail Goods"
        }
    ],
    "sg:phone":"+1 801 322 1162",
    "sg:postcode":"84102",
    "sg:province":"UT",
    "sg:tags":[
        "a",
        "gift",
        "operates"
    ],
    "wof:name":"Golden Braid Books",
    "wof:placetype":"venue"
},
  "geometry": {"coordinates":[-111.876707,40.766115],"type":"Point"}
}