{
  "type": "Feature",
  "properties": {
    "iso:country":"US",
    "sg:address":"8956 Taft Hill Dr",
    "sg:city":"Sandy",
    "sg:classifiers":[
        {
            "category":"Shopping",
            "subcategory":"Computers & Home Electronics",
            "type":"Retail Goods"
        }
    ],
    "sg:phone":"+1 801 733 8866",
    "sg:postcode":"84093",
    "sg:province":"UT",
    "sg:tags":[
        "system"
    ],
    "wof:name":"Home Theater Technologies",
    "wof:placetype":"venue"
},
  "geometry": {"coordinates":[-111.81893599999999,40.588772],"type":"Point"}
}