{
  "type": "Feature",
  "properties": {
    "iso:country":"US",
    "sg:address":"46 W 600 N",
    "sg:city":"Logan",
    "sg:classifiers":[
        {
            "category":"Retail",
            "subcategory":"Self-service Laundry",
            "type":"Services"
        }
    ],
    "sg:phone":"+1 435 752 9946",
    "sg:postcode":"84321",
    "sg:province":"UT",
    "wof:name":"Laundry Basket",
    "wof:placetype":"venue"
},
  "geometry": {"coordinates":[-111.83477499999999,41.742547],"type":"Point"}
}