{
  "type": "Feature",
  "properties": {
    "iso:country":"US",
    "sg:address":"860 E 4500 S",
    "sg:city":"Salt Lake City",
    "sg:classifiers":[
        {
            "category":"Banks & Credit Unions",
            "subcategory":"Bank",
            "type":"Services"
        }
    ],
    "sg:phone":"+1 801 892 5000",
    "sg:postcode":"84107",
    "sg:province":"UT",
    "sg:tags":[
        "personal",
        "institution"
    ],
    "wof:name":"National Benefit Alliance",
    "wof:placetype":"venue"
},
  "geometry": {"coordinates":[-111.86555199999999,40.67423],"type":"Point"}
}