{
  "type": "Feature",
  "properties": {
    "iso:country":"US",
    "sg:address":"4569 Sunstone Rd",
    "sg:city":"Salt Lake City",
    "sg:classifiers":[
        {
            "category":"Professional",
            "type":"Services"
        }
    ],
    "sg:phone":"+1 801 290 2876",
    "sg:postcode":"84123",
    "sg:province":"UT",
    "sg:tags":[
        "establishment"
    ],
    "wof:name":"Swank & Swank",
    "wof:placetype":"venue"
},
  "geometry": {"coordinates":[-111.9123,40.670535],"type":"Point"}
}