{
  "type": "Feature",
  "properties": {
    "iso:country":"US",
    "sg:address":"172 Shelly Louise Dr",
    "sg:city":"Sandy",
    "sg:classifiers":[
        {
            "category":"Retail",
            "subcategory":"Repair Shop",
            "type":"Services"
        }
    ],
    "sg:phone":"+1 801 571 0684",
    "sg:postcode":"84070",
    "sg:province":"UT",
    "wof:name":"Bexar Repairs",
    "wof:placetype":"venue"
},
  "geometry": {"coordinates":[-111.885019,40.562571],"type":"Point"}
}