{
  "type": "Feature",
  "properties": {
    "iso:country":"US",
    "sg:address":"254 W 100 S",
    "sg:city":"American Fork",
    "sg:classifiers":[
        {
            "category":"Building & Trades",
            "subcategory":"Cleaning & Sanitation",
            "type":"Services"
        }
    ],
    "sg:phone":"+1 801 756 8357",
    "sg:postcode":"84003",
    "sg:province":"UT",
    "sg:tags":[
        "maintenance"
    ],
    "wof:name":"Western Pipe Maintenance Inc",
    "wof:placetype":"venue"
},
  "geometry": {"coordinates":[-111.80540499999999,40.374824],"type":"Point"}
}