{
  "type": "Feature",
  "properties": {
    "iso:country":"US",
    "sg:address":"270 S 300 W",
    "sg:city":"Lehi",
    "sg:classifiers":[
        {
            "category":"Home & Garden",
            "subcategory":"Household Appliances",
            "type":"Retail Goods"
        }
    ],
    "sg:phone":"+1 801 768 9788",
    "sg:postcode":"84043",
    "sg:province":"UT",
    "sg:tags":[
        "pump"
    ],
    "wof:name":"Dicksco",
    "wof:placetype":"venue"
},
  "geometry": {"coordinates":[-111.853719,40.385103],"type":"Point"}
}