{
  "type": "Feature",
  "properties": {
    "iso:country":"US",
    "sg:address":"9802 N 5740 W",
    "sg:city":"Highland",
    "sg:classifiers":[
        {
            "category":"Building & Trades",
            "subcategory":"Construction",
            "type":"Services"
        }
    ],
    "sg:phone":"+1 801 763 8999",
    "sg:postcode":"84003",
    "sg:province":"UT",
    "sg:tags":[
        "painter"
    ],
    "wof:name":"Orion Painting & Coatings",
    "wof:placetype":"venue"
},
  "geometry": {"coordinates":[-111.79494,40.409586],"type":"Point"}
}