{
  "type": "Feature",
  "properties": {
    "iso:country":"US",
    "sg:address":"225 9th St",
    "sg:city":"Evanston",
    "sg:classifiers":[
        {
            "category":"Government",
            "subcategory":"Office",
            "type":"Public Place"
        }
    ],
    "sg:phone":"+1 307 783 0306",
    "sg:postcode":"82930",
    "sg:province":"UT",
    "wof:name":"Uinta County Recorder",
    "wof:placetype":"venue"
},
  "geometry": {"coordinates":[-110.965036,41.266848],"type":"Point"}
}