{
  "type": "Feature",
  "properties": {
    "iso:country":"US",
    "sg:address":"3469 Wall Ave",
    "sg:city":"Ogden",
    "sg:classifiers":[
        {
            "category":"Home & Garden",
            "subcategory":"Building Materials",
            "type":"Retail Goods"
        }
    ],
    "sg:phone":"+1 801 394 7725",
    "sg:postcode":"84401",
    "sg:province":"UT",
    "sg:tags":[
        "lumber"
    ],
    "wof:name":"Stock Building Supply",
    "wof:placetype":"venue"
},
  "geometry": {"coordinates":[-111.979354,41.202888],"type":"Point"}
}