{
  "type": "Feature",
  "properties": {
    "iso:country":"US",
    "sg:address":"1440 S 2900 W",
    "sg:city":"Ogden",
    "sg:classifiers":[
        {
            "category":"Personal",
            "subcategory":"Beauty Salon",
            "type":"Services"
        }
    ],
    "sg:phone":"+1 801 731 6185",
    "sg:postcode":"84401",
    "sg:province":"UT",
    "wof:name":"Jackis Salon",
    "wof:placetype":"venue"
},
  "geometry": {"coordinates":[-112.051284,41.235068],"type":"Point"}
}