{
  "type": "Feature",
  "properties": {
    "iso:country":"US",
    "sg:address":"377 E 300 S",
    "sg:city":"Springville",
    "sg:classifiers":[
        {
            "category":"Building & Trades",
            "subcategory":"Construction",
            "type":"Services"
        }
    ],
    "sg:phone":"+1 801 489 7718",
    "sg:postcode":"84663",
    "sg:province":"UT",
    "sg:tags":[
        "contractor"
    ],
    "wof:name":"Allan Lowe Roofing",
    "wof:placetype":"venue"
},
  "geometry": {"coordinates":[-111.604382,40.162531],"type":"Point"}
}