{
  "type": "Feature",
  "properties": {
    "iso:country":"US",
    "sg:address":"996 N 2770 W",
    "sg:city":"Provo",
    "sg:classifiers":[
        {
            "category":"Retail",
            "subcategory":"Portrait Studio",
            "type":"Services"
        }
    ],
    "sg:phone":"+1 801 374 6854",
    "sg:postcode":"84601",
    "sg:province":"UT",
    "sg:tags":[
        "photographer"
    ],
    "wof:name":"Trisha Bigler Photography",
    "wof:placetype":"venue"
},
  "geometry": {"coordinates":[-111.707689,40.247133],"type":"Point"}
}