{
  "type": "Feature",
  "properties": {
    "iso:country":"US",
    "sg:address":"425 N Main St",
    "sg:city":"Centerfield",
    "sg:classifiers":[
        {
            "category":"Wholesale",
            "subcategory":"Machinery & Supplies",
            "type":"Manufacturing & Wholesale Goods"
        }
    ],
    "sg:phone":"+1 435 528 7089",
    "sg:postcode":"84622",
    "sg:province":"UT",
    "sg:tags":[
        "equipment",
        "irrigation",
        "system"
    ],
    "wof:name":"Jim Reynolds Irrigation Systs",
    "wof:placetype":"venue"
},
  "geometry": {"coordinates":[-111.81897499999999,39.136285],"type":"Point"}
}