{
  "type": "Feature",
  "properties": {
    "iso:country":"US",
    "sg:address":"316 S Westview Dr",
    "sg:city":"Cedar City",
    "sg:classifiers":[
        {
            "category":"Retail",
            "subcategory":"Repair Shop",
            "type":"Services"
        }
    ],
    "sg:phone":"+1 435 586 5257",
    "sg:postcode":"84720",
    "sg:province":"UT",
    "sg:tags":[
        "welding"
    ],
    "wof:name":"Desiron Ornamental Welding Inc",
    "wof:placetype":"venue"
},
  "geometry": {"coordinates":[-113.124622,37.671564],"type":"Point"}
}