{
  "type": "Feature",
  "properties": {
    "iso:country":"US",
    "sg:address":"5770 Fashion Blvd",
    "sg:city":"Murray",
    "sg:classifiers":[
        {
            "category":"Health Services",
            "subcategory":"Health Practitioner",
            "type":"Services"
        }
    ],
    "sg:phone":"+1 801 314 2054",
    "sg:postcode":"84107",
    "sg:province":"UT",
    "sg:tags":[
        "therapist",
        "physical"
    ],
    "wof:name":"IHC Rehabilitation Svc",
    "wof:placetype":"venue"
},
  "geometry": {"coordinates":[-111.882977,40.642381],"type":"Point"}
}