{
  "type": "Feature",
  "properties": {
    "iso:country":"US",
    "sg:address":"2110 Orchard Dr",
    "sg:city":"Bountiful",
    "sg:classifiers":[
        {
            "category":"Food & Beverages",
            "subcategory":"Bakery",
            "type":"Retail Goods"
        }
    ],
    "sg:phone":"+1 801 292 4877",
    "sg:postcode":"84010",
    "sg:province":"UT",
    "sg:tags":[
        "baker"
    ],
    "wof:name":"Wonderbread-Hostess",
    "wof:placetype":"venue"
},
  "geometry": {"coordinates":[-111.878803,40.866942],"type":"Point"}
}