{
  "type": "Feature",
  "properties": {
    "iso:country":"US",
    "sg:address":"10625 S 1300 E",
    "sg:city":"Sandy",
    "sg:classifiers":[
        {
            "category":"Banks & Credit Unions",
            "subcategory":"Bank",
            "type":"Services"
        }
    ],
    "sg:phone":"+1 801 572 8847",
    "sg:postcode":"84094",
    "sg:province":"UT",
    "wof:name":"Wells Fargo Bank",
    "wof:placetype":"venue"
},
  "geometry": {"coordinates":[-111.85319200000001,40.558298],"type":"Point"}
}