{
  "type": "Feature",
  "properties": {
    "iso:country":"US",
    "sg:address":"2685 S 700 E",
    "sg:city":"Salt Lake City",
    "sg:classifiers":[
        {
            "category":"Shopping",
            "subcategory":"Florist",
            "type":"Retail Goods"
        }
    ],
    "sg:phone":"+1 801 466 6644",
    "sg:postcode":"84106",
    "sg:province":"UT",
    "wof:name":"Flower Patch",
    "wof:placetype":"venue"
},
  "geometry": {"coordinates":[-111.871189,40.712364],"type":"Point"}
}