{
  "type": "Feature",
  "properties": {
    "iso:country":"US",
    "sg:address":"1313 E 4170 S",
    "sg:city":"Holladay",
    "sg:classifiers":[
        {
            "category":"Education",
            "subcategory":"Junior College",
            "type":"Public Place"
        }
    ],
    "sg:phone":"+1 801 272 4677",
    "sg:postcode":"84124",
    "sg:province":"UT",
    "sg:tags":[
        "technical",
        "institute"
    ],
    "wof:name":"Professional Education Inst",
    "wof:placetype":"venue"
},
  "geometry": {"coordinates":[-111.85158300000001,40.681082],"type":"Point"}
}