{
  "type": "Feature",
  "properties": {
    "iso:country":"US",
    "sg:address":"160 W 400 S",
    "sg:city":"Vernal",
    "sg:classifiers":[
        {
            "category":"Professional",
            "type":"Services"
        }
    ],
    "sg:phone":"+1 435 789 7949",
    "sg:postcode":"84078",
    "sg:province":"UT",
    "sg:tags":[
        "establishment"
    ],
    "wof:name":"Jones & Jones",
    "wof:placetype":"venue"
},
  "geometry": {"coordinates":[-109.531198,40.449852],"type":"Point"}
}