{
  "type": "Feature",
  "properties": {
    "iso:country":"US",
    "sg:address":"1864 W 9640 S",
    "sg:city":"South Jordan",
    "sg:classifiers":[
        {
            "category":"Shopping",
            "subcategory":"Computers & Home Electronics",
            "type":"Retail Goods"
        }
    ],
    "sg:phone":"+1 801 254 3051",
    "sg:postcode":"84095",
    "sg:province":"UT",
    "sg:tags":[
        "software"
    ],
    "wof:name":"Progressive Computer Systems",
    "wof:placetype":"venue"
},
  "geometry": {"coordinates":[-111.94002,40.576207],"type":"Point"}
}