{
  "type": "Feature",
  "properties": {
    "iso:country":"US",
    "sg:address":"2263 Sego Lily Dr",
    "sg:city":"Wellington",
    "sg:classifiers":[
        {
            "category":"Professional",
            "subcategory":"Business Services",
            "type":"Services"
        }
    ],
    "sg:phone":"+1 435 613 1586",
    "sg:postcode":"84542",
    "sg:province":"UT",
    "wof:name":"Lees Pilot Car Service",
    "wof:placetype":"venue"
},
  "geometry": {"coordinates":[-110.75620000000001,39.563508],"type":"Point"}
}