{
  "type": "Feature",
  "properties": {
    "iso:country":"US",
    "sg:address":"2639 N 3750 E",
    "sg:city":"Eden",
    "sg:classifiers":[
        {
            "category":"Professional",
            "subcategory":"Engineering",
            "type":"Services"
        }
    ],
    "sg:phone":"+1 801 745 2009",
    "sg:postcode":"84310",
    "sg:province":"UT",
    "sg:tags":[
        "material"
    ],
    "wof:name":"Systems In Hot Water",
    "wof:placetype":"venue"
},
  "geometry": {"coordinates":[-111.854249,41.308315],"type":"Point"}
}