{
  "type": "Feature",
  "properties": {
    "iso:country":"US",
    "sg:address":"675 Wright Brothers Dr",
    "sg:city":"Salt Lake City",
    "sg:classifiers":[
        {
            "category":"Manufacturing",
            "subcategory":"Furniture",
            "type":"Manufacturing & Wholesale Goods"
        }
    ],
    "sg:phone":"+1 801 537 8100",
    "sg:postcode":"84116",
    "sg:province":"UT",
    "sg:tags":[
        "mattress"
    ],
    "wof:name":"Select Comfort Corp",
    "wof:placetype":"venue"
},
  "geometry": {"coordinates":[-112.00586699999999,40.783523],"type":"Point"}
}