{
  "type": "Feature",
  "properties": {
    "iso:country":"US",
    "sg:address":"441 E 2825 N",
    "sg:city":"Provo",
    "sg:classifiers":[
        {
            "category":"Organizations",
            "subcategory":"Labor Organization",
            "type":"Services"
        }
    ],
    "sg:phone":"+1 801 356 3513",
    "sg:postcode":"84604",
    "sg:province":"UT",
    "wof:name":"Dewey Children Enterprises Lc",
    "wof:placetype":"venue"
},
  "geometry": {"coordinates":[-111.648028,40.271277],"type":"Point"}
}