{
  "type": "Feature",
  "properties": {
    "iso:country":"US",
    "sg:address":"260 S Green Springs Dr",
    "sg:city":"Washington",
    "sg:classifiers":[
        {
            "category":"Food & Beverages",
            "subcategory":"Groceries & Convenience Stores",
            "type":"Retail Goods"
        }
    ],
    "sg:phone":"+1 435 674 9575",
    "sg:postcode":"84780",
    "sg:province":"UT",
    "wof:name":"Harts Gas & Food",
    "wof:placetype":"venue"
},
  "geometry": {"coordinates":[-113.524698,37.128185],"type":"Point"}
}