{
  "type": "Feature",
  "properties": {
    "iso:country":"US",
    "sg:address":"264 S 200 E",
    "sg:city":"Monroe",
    "sg:classifiers":[
        {
            "category":"Building & Trades",
            "subcategory":"Construction",
            "type":"Services"
        }
    ],
    "sg:phone":"+1 435 527 4318",
    "sg:postcode":"84754",
    "sg:province":"UT",
    "sg:tags":[
        "downspouts",
        "gutter"
    ],
    "wof:name":"Monroe Siding & Rain Gutter",
    "wof:placetype":"venue"
},
  "geometry": {"coordinates":[-112.117071,38.627403],"type":"Point"}
}