{
  "type": "Feature",
  "properties": {
    "iso:country":"US",
    "sg:address":"989 E 800 N",
    "sg:city":"Spanish Fork",
    "sg:classifiers":[
        {
            "category":"Retail",
            "subcategory":"Auto Repair",
            "type":"Services"
        }
    ],
    "sg:phone":"+1 801 794 0800",
    "sg:postcode":"84660",
    "sg:province":"UT",
    "sg:tags":[
        "repairing",
        "automobile"
    ],
    "wof:name":"All Tune & Lube Spanish Fork",
    "wof:placetype":"venue"
},
  "geometry": {"coordinates":[-111.63724000000001,40.120187],"type":"Point"}
}