{
  "type": "Feature",
  "properties": {
    "iso:country":"US",
    "sg:address":"637 E 630 N",
    "sg:city":"Pleasant Grove",
    "sg:classifiers":[
        {
            "category":"Building & Trades",
            "subcategory":"Construction",
            "type":"Services"
        }
    ],
    "sg:phone":"+1 801 785 4637",
    "sg:postcode":"84062",
    "sg:province":"UT",
    "sg:tags":[
        "house"
    ],
    "wof:name":"R J Walker Construction Co",
    "wof:placetype":"venue"
},
  "geometry": {"coordinates":[-111.726095,40.370383],"type":"Point"}
}