{
  "type": "Feature",
  "properties": {
    "iso:country":"US",
    "sg:address":"12689 Whisper Brook Bay",
    "sg:city":"Draper",
    "sg:classifiers":[
        {
            "category":"Real Estate",
            "subcategory":"Real Estate Services",
            "type":"Services"
        }
    ],
    "sg:phone":"+1 801 255 1313",
    "sg:postcode":"84020",
    "sg:province":"UT",
    "sg:tags":[
        "company",
        "title"
    ],
    "wof:name":"Majestic Title Insurance LLC",
    "wof:placetype":"venue"
},
  "geometry": {"coordinates":[-111.872867,40.521135],"type":"Point"}
}