{
  "type": "Feature",
  "properties": {
    "iso:country":"US",
    "sg:address":"1961 E 2125 N",
    "sg:city":"Layton",
    "sg:classifiers":[
        {
            "category":"Professional",
            "subcategory":"Computer Services",
            "type":"Services"
        }
    ],
    "sg:phone":"+1 801 544 8085",
    "sg:postcode":"84040",
    "sg:province":"UT",
    "sg:tags":[
        "programing",
        "custom"
    ],
    "wof:name":"Tracy Haviland",
    "wof:placetype":"venue"
},
  "geometry": {"coordinates":[-111.92993,41.091212],"type":"Point"}
}