{
  "type": "Feature",
  "properties": {
    "iso:country":"US",
    "sg:address":"444 W 400 N",
    "sg:city":"Vernal",
    "sg:classifiers":[
        {
            "category":"Organizations",
            "subcategory":"Religious Organization",
            "type":"Services"
        }
    ],
    "sg:phone":"+1 435 789 3113",
    "sg:postcode":"84078",
    "sg:province":"UT",
    "sg:tags":[
        "elementary",
        "school",
        "church",
        "secondary"
    ],
    "wof:name":"World Vision Assembly Of God",
    "wof:placetype":"venue"
},
  "geometry": {"coordinates":[-109.537133,40.461993],"type":"Point"}
}