{
  "type": "Feature",
  "properties": {
    "iso:country":"US",
    "sg:address":"12066 Kings Crossing Way",
    "sg:city":"Riverton",
    "sg:classifiers":[
        {
            "category":"Manufacturing",
            "subcategory":"Signs",
            "type":"Manufacturing & Wholesale Goods"
        }
    ],
    "sg:phone":"+1 801 352 9933",
    "sg:postcode":"84065",
    "sg:province":"UT",
    "wof:name":"Artistic Routing Technologies",
    "wof:placetype":"venue"
},
  "geometry": {"coordinates":[-111.963437,40.533115],"type":"Point"}
}