{
  "type": "Feature",
  "properties": {
    "iso:country":"US",
    "sg:address":"669 8th Ave",
    "sg:city":"Midvale",
    "sg:classifiers":[
        {
            "category":"Building & Trades",
            "subcategory":"Electrical",
            "type":"Services"
        }
    ],
    "sg:phone":"+1 801 569 9674",
    "sg:postcode":"84047",
    "sg:province":"UT",
    "sg:tags":[
        "electric",
        "contractor"
    ],
    "wof:name":"Infinity Electrical Inc",
    "wof:placetype":"venue"
},
  "geometry": {"coordinates":[-111.909751,40.616944],"type":"Point"}
}