{
  "type": "Feature",
  "properties": {
    "iso:country":"US",
    "sg:address":"13111 Minuteman Dr",
    "sg:city":"Draper",
    "sg:classifiers":[
        {
            "category":"Autos & Motor Vehicles",
            "subcategory":"Recreational Vehicle Sales",
            "type":"Retail Goods"
        }
    ],
    "sg:phone":"+1 801 572 6340",
    "sg:postcode":"84020",
    "sg:province":"UT",
    "wof:name":"Camping World",
    "wof:placetype":"venue"
},
  "geometry": {"coordinates":[-111.89061,40.511832],"type":"Point"}
}