{
  "type": "Feature",
  "properties": {
    "iso:country":"US",
    "sg:address":"1413 Marilyn Dr",
    "sg:city":"Ogden",
    "sg:classifiers":[
        {
            "category":"Organizations",
            "subcategory":"Labor Organization",
            "type":"Services"
        }
    ],
    "sg:phone":"+1 801 605 4099",
    "sg:postcode":"84403",
    "sg:province":"UT",
    "wof:name":"Kenny Properties Lc",
    "wof:placetype":"venue"
},
  "geometry": {"coordinates":[-111.941935,41.214966],"type":"Point"}
}