{
  "type": "Feature",
  "properties": {
    "iso:country":"US",
    "sg:address":"3432 Oakledge Rd",
    "sg:city":"Salt Lake City",
    "sg:classifiers":[
        {
            "category":"Professional",
            "subcategory":"Management & Consulting",
            "type":"Services"
        }
    ],
    "sg:phone":"+1 801 942 1414",
    "sg:postcode":"84121",
    "sg:province":"UT",
    "sg:tags":[
        "retail",
        "direct",
        "sales"
    ],
    "wof:name":"Panda Craft",
    "wof:placetype":"venue"
},
  "geometry": {"coordinates":[-111.798165,40.60546],"type":"Point"}
}