{
  "type": "Feature",
  "properties": {
    "iso:country":"US",
    "sg:address":"1105 N Washington Blvd",
    "sg:city":"Ogden",
    "sg:classifiers":[
        {
            "category":"Organizations",
            "subcategory":"Religious Organization",
            "type":"Services"
        }
    ],
    "sg:phone":"+1 801 782 2810",
    "sg:postcode":"84404",
    "sg:province":"UT",
    "wof:name":"Ascension Lutheran Church Inc",
    "wof:placetype":"venue"
},
  "geometry": {"coordinates":[-111.969336,41.278274],"type":"Point"}
}