{
  "type": "Feature",
  "properties": {
    "iso:country":"US",
    "sg:address":"3586 E Hermes Dr",
    "sg:city":"Holladay",
    "sg:classifiers":[
        {
            "category":"Retail",
            "subcategory":"Repair Shop",
            "type":"Services"
        },
        {
            "category":"Building & Trades",
            "subcategory":"Plumbing",
            "type":"Services"
        }
    ],
    "sg:phone":"+1 801 272 2940",
    "sg:postcode":"84124",
    "sg:province":"UT",
    "sg:tags":[
        "boiler",
        "cleaning"
    ],
    "wof:name":"Gordon B Godfrey",
    "wof:placetype":"venue"
},
  "geometry": {"coordinates":[-111.793717,40.681423],"type":"Point"}
}