{
  "type": "Feature",
  "properties": {
    "iso:country":"US",
    "sg:address":"132 S 600 E",
    "sg:city":"Salt Lake City",
    "sg:classifiers":[
        {
            "category":"Professional",
            "subcategory":"Business Services",
            "type":"Services"
        }
    ],
    "sg:phone":"+1 801 328 2285",
    "sg:postcode":"84102",
    "sg:province":"UT",
    "sg:tags":[
        "printing",
        "broker"
    ],
    "wof:name":"M Print Lc",
    "wof:placetype":"venue"
},
  "geometry": {"coordinates":[-111.873994,40.765714],"type":"Point"}
}