{
  "type": "Feature",
  "properties": {
    "iso:country":"US",
    "sg:address":"435 Meadow Brook Dr",
    "sg:city":"Salina",
    "sg:classifiers":[
        {
            "category":"Farming",
            "subcategory":"Livestock Farm",
            "type":"Manufacturing & Wholesale Goods"
        }
    ],
    "sg:phone":"+1 435 529 3997",
    "sg:postcode":"84654",
    "sg:province":"UT",
    "sg:tags":[
        "beef",
        "feedlot",
        "cattle"
    ],
    "wof:name":"Randy Crane",
    "wof:placetype":"venue"
},
  "geometry": {"coordinates":[-111.864513,38.955092],"type":"Point"}
}