{
  "type": "Feature",
  "properties": {
    "iso:country":"US",
    "sg:address":"2688 S Redwood Rd",
    "sg:city":"Salt Lake City",
    "sg:classifiers":[
        {
            "category":"Utilities",
            "subcategory":"Telephone",
            "type":"Services"
        }
    ],
    "sg:phone":"+1 801 978 9235",
    "sg:postcode":"84119",
    "sg:province":"UT",
    "sg:tags":[
        "company"
    ],
    "wof:name":"Newline",
    "wof:placetype":"venue"
},
  "geometry": {"coordinates":[-111.939048,40.713268],"type":"Point"}
}