{
  "type": "Feature",
  "properties": {
    "iso:country":"US",
    "sg:address":"49 W 400 S",
    "sg:city":"Manti",
    "sg:classifiers":[
        {
            "category":"Building & Trades",
            "subcategory":"Electrical",
            "type":"Services"
        }
    ],
    "sg:phone":"+1 435 835 6941",
    "sg:postcode":"84642",
    "sg:province":"UT",
    "sg:tags":[
        "electrical",
        "contractor"
    ],
    "wof:name":"Beus Electric",
    "wof:placetype":"venue"
},
  "geometry": {"coordinates":[-111.638108,39.259542],"type":"Point"}
}