{
  "type": "Feature",
  "properties": {
    "iso:country":"US",
    "sg:address":"842 Colony Cir",
    "sg:city":"Washington",
    "sg:classifiers":[
        {
            "category":"Professional",
            "subcategory":"Business Services",
            "type":"Services"
        }
    ],
    "sg:phone":"+1 435 635 8777",
    "sg:postcode":"84780",
    "sg:province":"UT",
    "wof:name":"Granite Bail Bonds",
    "wof:placetype":"venue"
},
  "geometry": {"coordinates":[-113.496268,37.132132],"type":"Point"}
}