{
  "type": "Feature",
  "properties": {
    "iso:country":"US",
    "sg:address":"736 S 900 E",
    "sg:city":"St George",
    "sg:classifiers":[
        {
            "category":"Health Services",
            "subcategory":"Doctor",
            "type":"Services"
        }
    ],
    "sg:phone":"+1 435 656 3764",
    "sg:postcode":"84790",
    "sg:province":"UT",
    "sg:tags":[
        "physician",
        "surgeon"
    ],
    "wof:name":"St George Radiology Ultrasound",
    "wof:placetype":"venue"
},
  "geometry": {"coordinates":[-113.564398,37.095679],"type":"Point"}
}