{
  "type": "Feature",
  "properties": {
    "iso:country":"US",
    "sg:address":"406 Culross Ln",
    "sg:city":"Tooele",
    "sg:classifiers":[
        {
            "category":"Building & Trades",
            "subcategory":"Construction",
            "type":"Services"
        }
    ],
    "sg:phone":"+1 801 364 2544",
    "sg:postcode":"84020",
    "sg:province":"UT",
    "sg:tags":[
        "home",
        "builder"
    ],
    "wof:name":"Richmond American Homes",
    "wof:placetype":"venue"
},
  "geometry": {"coordinates":[-111.878781,40.485769],"type":"Point"}
}