{
  "type": "Feature",
  "properties": {
    "iso:country":"US",
    "sg:address":"9284 S 3550 West St",
    "sg:city":"Payson",
    "sg:classifiers":[
        {
            "category":"Utilities",
            "subcategory":"Water",
            "type":"Services"
        }
    ],
    "sg:phone":"+1 801 465 4971",
    "sg:postcode":"84651",
    "sg:province":"UT",
    "sg:tags":[
        "supply"
    ],
    "wof:name":"Old Field Water Users Assn",
    "wof:placetype":"venue"
},
  "geometry": {"coordinates":[-111.738303,40.061931],"type":"Point"}
}