{
  "type": "Feature",
  "properties": {
    "iso:country":"US",
    "sg:address":"1480 Orchard Dr",
    "sg:city":"Bountiful",
    "sg:classifiers":[
        {
            "category":"Health Services",
            "subcategory":"Doctor",
            "type":"Services"
        }
    ],
    "sg:phone":"+1 801 295 7171",
    "sg:postcode":"84010",
    "sg:province":"UT",
    "sg:tags":[
        "dentist"
    ],
    "wof:name":"Rocky Mountain Dental",
    "wof:placetype":"venue"
},
  "geometry": {"coordinates":[-111.87490699999999,40.87548],"type":"Point"}
}