{
  "type": "Feature",
  "properties": {
    "iso:country":"US",
    "sg:address":"2735 American Saddler Dr",
    "sg:city":"Park City",
    "sg:classifiers":[
        {
            "category":"Organizations",
            "subcategory":"Community Association",
            "type":"Services"
        }
    ],
    "sg:phone":"+1 435 658 1977",
    "sg:postcode":"84060",
    "sg:province":"UT",
    "wof:name":"Fairway Meadows Homeowners",
    "wof:placetype":"venue"
},
  "geometry": {"coordinates":[-111.50049199999999,40.681458],"type":"Point"}
}