{
  "type": "Feature",
  "properties": {
    "iso:country":"US",
    "sg:address":"3410 W 2400 S",
    "sg:city":"West Valley",
    "sg:classifiers":[
        {
            "category":"Freight",
            "type":"Transportation"
        }
    ],
    "sg:phone":"+1 801 972 6778",
    "sg:postcode":"84119",
    "sg:province":"UT",
    "sg:tags":[
        "commercial",
        "storage"
    ],
    "wof:name":"Ideal Storage",
    "wof:placetype":"venue"
},
  "geometry": {"coordinates":[-111.971952,40.718677],"type":"Point"}
}