{
  "type": "Feature",
  "properties": {
    "iso:country":"US",
    "sg:address":"1892 N 1120 W",
    "sg:city":"Provo",
    "sg:classifiers":[
        {
            "category":"Professional",
            "subcategory":"Lawyer & Legal Services",
            "type":"Services"
        }
    ],
    "sg:phone":"+1 801 375 8800",
    "sg:postcode":"84604",
    "sg:province":"UT",
    "sg:tags":[
        "attorney"
    ],
    "wof:name":"Allan & Easton",
    "wof:placetype":"venue"
},
  "geometry": {"coordinates":[-111.676011,40.258932],"type":"Point"}
}