{
  "type": "Feature",
  "properties": {
    "iso:country":"US",
    "sg:address":"11486 Hagan Rd",
    "sg:city":"Sandy",
    "sg:classifiers":[
        {
            "category":"Professional",
            "subcategory":"Lawyer & Legal Services",
            "type":"Services"
        }
    ],
    "sg:phone":"+1 801 571 3020",
    "sg:postcode":"84092",
    "sg:province":"UT",
    "wof:name":"CMR Legal Nurse Consultin",
    "wof:placetype":"venue"
},
  "geometry": {"coordinates":[-111.849656,40.540231],"type":"Point"}
}