{
  "type": "Feature",
  "properties": {
    "iso:country":"US",
    "sg:address":"1483 Greenfield Ave",
    "sg:city":"Salt Lake City",
    "sg:classifiers":[
        {
            "category":"Professional",
            "subcategory":"Management & Consulting",
            "type":"Services"
        }
    ],
    "sg:phone":"+1 801 272 9537",
    "sg:postcode":"84121",
    "sg:province":"UT",
    "sg:tags":[
        "business"
    ],
    "wof:name":"Kim Garrick Consulting",
    "wof:placetype":"venue"
},
  "geometry": {"coordinates":[-111.849948,40.631803],"type":"Point"}
}