{
  "type": "Feature",
  "properties": {
    "iso:country":"US",
    "sg:address":"1390 Canyon Dr",
    "sg:city":"Ogden",
    "sg:classifiers":[
        {
            "category":"Building & Trades",
            "subcategory":"Construction",
            "type":"Services"
        }
    ],
    "sg:phone":"+1 801 479 3212",
    "sg:postcode":"84405",
    "sg:province":"UT",
    "sg:tags":[
        "house"
    ],
    "wof:name":"R & R Handyman Services LLC",
    "wof:placetype":"venue"
},
  "geometry": {"coordinates":[-111.942669,41.13609],"type":"Point"}
}