{
  "type": "Feature",
  "properties": {
    "iso:country":"US",
    "sg:address":"109 D St",
    "sg:city":"Helper",
    "sg:classifiers":[
        {
            "category":"Professional",
            "type":"Services"
        }
    ],
    "sg:phone":"+1 435 472 0680",
    "sg:postcode":"84526",
    "sg:province":"UT",
    "sg:tags":[
        "establishment"
    ],
    "wof:name":"D Cole",
    "wof:placetype":"venue"
},
  "geometry": {"coordinates":[-110.853835,39.692147],"type":"Point"}
}