{
  "type": "Feature",
  "properties": {
    "iso:country":"US",
    "sg:address":"8667 S 1120 W",
    "sg:city":"West Jordan",
    "sg:classifiers":[
        {
            "category":"Building & Trades",
            "subcategory":"Pest Control",
            "type":"Services"
        }
    ],
    "sg:phone":"+1 801 256 3323",
    "sg:postcode":"84088",
    "sg:province":"UT",
    "wof:name":"All Pest-Pest Control",
    "wof:placetype":"venue"
},
  "geometry": {"coordinates":[-111.923265,40.593844],"type":"Point"}
}