{
  "type": "Feature",
  "properties": {
    "iso:country":"US",
    "sg:address":"810 W 200 S",
    "sg:city":"Clearfield",
    "sg:classifiers":[
        {
            "category":"Professional",
            "subcategory":"Management & Consulting",
            "type":"Services"
        }
    ],
    "sg:phone":"+1 801 779 9801",
    "sg:postcode":"84015",
    "sg:province":"UT",
    "sg:tags":[
        "business"
    ],
    "wof:name":"Marketcap Consultingcom Inc",
    "wof:placetype":"venue"
},
  "geometry": {"coordinates":[-112.044724,41.110948],"type":"Point"}
}