{
  "type": "Feature",
  "properties": {
    "iso:country":"US",
    "sg:address":"1542 E 3010 S",
    "sg:city":"Salt Lake City",
    "sg:classifiers":[
        {
            "category":"Real Estate",
            "subcategory":"Real Estate Agent",
            "type":"Services"
        }
    ],
    "sg:phone":"+1 801 467 8822",
    "sg:postcode":"84106",
    "sg:province":"UT",
    "sg:tags":[
        "leasing",
        "rental"
    ],
    "wof:name":"Bowyer Enterprises Lc",
    "wof:placetype":"venue"
},
  "geometry": {"coordinates":[-111.845377,40.705489],"type":"Point"}
}