{
  "type": "Feature",
  "properties": {
    "iso:country":"US",
    "sg:address":"1313 US Hwy 89",
    "sg:city":"Farmington",
    "sg:classifiers":[
        {
            "category":"Shopping",
            "subcategory":"Department Store",
            "type":"Retail Goods"
        }
    ],
    "sg:phone":"+1 801 451 0070",
    "sg:postcode":"84025",
    "sg:province":"UT",
    "sg:tags":[
        "building",
        "operator",
        "nonresidential"
    ],
    "wof:name":"Kmart",
    "wof:placetype":"venue"
},
  "geometry": {"coordinates":[-111.90861200000001,41.001884],"type":"Point"}
}