{
  "type": "Feature",
  "properties": {
    "iso:country":"US",
    "sg:address":"1054 Sagehill Dr",
    "sg:city":"Salt Lake City",
    "sg:classifiers":[
        {
            "category":"Organizations",
            "subcategory":"Religious Organization",
            "type":"Services"
        }
    ],
    "sg:phone":"+1 801 262 6755",
    "sg:postcode":"84124",
    "sg:province":"UT",
    "wof:name":"Utah Gospel Mission",
    "wof:placetype":"venue"
},
  "geometry": {"coordinates":[-111.859869,40.67832],"type":"Point"}
}