{
  "type": "Feature",
  "properties": {
    "iso:country":"US",
    "sg:address":"125 S 600 E",
    "sg:city":"Spanish Fork",
    "sg:classifiers":[
        {
            "category":"Building & Trades",
            "subcategory":"Construction",
            "type":"Services"
        }
    ],
    "sg:phone":"+1 801 798 9385",
    "sg:postcode":"84660",
    "sg:province":"UT",
    "sg:tags":[
        "house"
    ],
    "wof:name":"Prime Building & Development",
    "wof:placetype":"venue"
},
  "geometry": {"coordinates":[-111.644098,40.108088],"type":"Point"}
}