{
  "type": "Feature",
  "properties": {
    "iso:country":"US",
    "sg:address":"14663 Culross Ln",
    "sg:city":"Draper",
    "sg:classifiers":[
        {
            "category":"Professional",
            "subcategory":"Advertising",
            "type":"Services"
        }
    ],
    "sg:phone":"+1 801 576 2550",
    "sg:postcode":"84020",
    "sg:province":"UT",
    "sg:tags":[
        "distribution"
    ],
    "wof:name":"Herbalife Distributor",
    "wof:placetype":"venue"
},
  "geometry": {"coordinates":[-111.87962400000001,40.485053],"type":"Point"}
}