{
  "type": "Feature",
  "properties": {
    "iso:country":"US",
    "sg:address":"680 N 350 W",
    "sg:city":"American Fork",
    "sg:classifiers":[
        {
            "category":"Organizations",
            "subcategory":"Religious Organization",
            "type":"Services"
        }
    ],
    "sg:phone":"+1 801 763 2067",
    "sg:postcode":"84003",
    "sg:province":"UT",
    "sg:tags":[
        "church"
    ],
    "wof:name":"Church Of Jesus Christ Of Lds",
    "wof:placetype":"venue"
},
  "geometry": {"coordinates":[-111.80790500000001,40.389212],"type":"Point"}
}