{
  "type": "Feature",
  "properties": {
    "iso:country":"US",
    "sg:address":"2963 S 5600 W",
    "sg:city":"West Valley City",
    "sg:classifiers":[
        {
            "category":"Restaurant",
            "type":"Food & Drink"
        }
    ],
    "sg:menulink":"http://www.allmenus.com/ut/salt-lake-city/165446-del-taco/menu/",
    "sg:phone":"+1 801 966 8050",
    "sg:postcode":"84128",
    "sg:province":"UT",
    "sg:tags":[
        "american",
        "mexican",
        "tex-mex"
    ],
    "wof:name":"Del Taco",
    "wof:placetype":"venue"
},
  "geometry": {"coordinates":[-112.024241,40.706274],"type":"Point"}
}