{
  "type": "Feature",
  "properties": {
    "iso:country":"US",
    "sg:address":"2617 S 2000 W",
    "sg:city":"Wellsville",
    "sg:classifiers":[
        {
            "category":"Wholesale",
            "subcategory":"Farm Supplies",
            "type":"Manufacturing & Wholesale Goods"
        }
    ],
    "sg:phone":"+1 435 753 5628",
    "sg:postcode":"84339",
    "sg:province":"UT",
    "sg:tags":[
        "livestock"
    ],
    "wof:name":"Curtis-Hoyt Company",
    "wof:placetype":"venue"
},
  "geometry": {"coordinates":[-111.881434,41.685207],"type":"Point"}
}