{
  "type": "Feature",
  "properties": {
    "iso:country":"US",
    "sg:address":"150 Locust St",
    "sg:city":"Clearfield",
    "sg:classifiers":[
        {
            "category":"Recreation",
            "type":"Entertainment"
        }
    ],
    "sg:phone":"+1 801 776 5126",
    "sg:postcode":"84015",
    "sg:province":"UT",
    "wof:name":"Advanced Wellness",
    "wof:placetype":"venue"
},
  "geometry": {"coordinates":[-112.01595,41.112371],"type":"Point"}
}