{
  "type": "Feature",
  "properties": {
    "iso:country":"US",
    "sg:address":"1059 Emerson Ave",
    "sg:city":"Salt Lake City",
    "sg:classifiers":[
        {
            "category":"Communications",
            "subcategory":"Film & Video Production",
            "type":"Services"
        }
    ],
    "sg:phone":"+1 801 487 3072",
    "sg:postcode":"84105",
    "sg:province":"UT",
    "sg:tags":[
        "motion"
    ],
    "wof:name":"A Media Mix",
    "wof:placetype":"venue"
},
  "geometry": {"coordinates":[-111.86125800000001,40.737165],"type":"Point"}
}