{
  "type": "Feature",
  "properties": {
    "iso:country":"US",
    "sg:address":"1451 Yuma St",
    "sg:city":"Salt Lake City",
    "sg:classifiers":[
        {
            "category":"Professional",
            "subcategory":"Lawyer & Legal Services",
            "type":"Services"
        }
    ],
    "sg:phone":"+1 801 582 6223",
    "sg:postcode":"84108",
    "sg:province":"UT",
    "wof:name":"Sego Junction",
    "wof:placetype":"venue"
},
  "geometry": {"coordinates":[-111.831656,40.737766],"type":"Point"}
}