{
  "type": "Feature",
  "properties": {
    "iso:country":"US",
    "sg:address":"887 McCormick Way",
    "sg:city":"Layton",
    "sg:classifiers":[
        {
            "category":"Wholesale",
            "subcategory":"Hardware",
            "type":"Manufacturing & Wholesale Goods"
        },
        {
            "category":"Shopping",
            "type":"Retail Goods"
        }
    ],
    "sg:phone":"+1 801 444 0606",
    "sg:postcode":"84041",
    "sg:province":"UT",
    "sg:tags":[
        "purifying",
        "cleaning",
        "merchandise",
        "air"
    ],
    "sg:website":"www.surroundair.com",
    "wof:name":"Indoor Purification Systems",
    "wof:placetype":"venue"
},
  "geometry": {"coordinates":[-111.991702,41.07299],"type":"Point"}
}