{
  "type": "Feature",
  "properties": {
    "iso:country":"US",
    "sg:address":"2047 E 10095 S",
    "sg:city":"Sandy",
    "sg:classifiers":[
        {
            "category":"Professional",
            "subcategory":"Computer Services",
            "type":"Services"
        }
    ],
    "sg:phone":"+1 801 942 4736",
    "sg:postcode":"84092",
    "sg:province":"UT",
    "sg:tags":[
        "repair"
    ],
    "wof:name":"Sentinel Computing",
    "wof:placetype":"venue"
},
  "geometry": {"coordinates":[-111.833733,40.567796],"type":"Point"}
}