{
  "type": "Feature",
  "properties": {
    "iso:country":"US",
    "sg:address":"1420 W Main St",
    "sg:city":"Tremonton",
    "sg:classifiers":[
        {
            "category":"Wholesale",
            "subcategory":"Petroleum",
            "type":"Manufacturing & Wholesale Goods"
        }
    ],
    "sg:phone":"+1 435 257 5107",
    "sg:postcode":"84337",
    "sg:province":"UT",
    "sg:tags":[
        "bulk",
        "liquefied",
        "station",
        "gas"
    ],
    "wof:name":"Miller Gas Co",
    "wof:placetype":"venue"
},
  "geometry": {"coordinates":[-112.186914,41.711301],"type":"Point"}
}