{
  "type": "Feature",
  "properties": {
    "iso:country":"US",
    "sg:address":"4423 W Hawthorne Ct",
    "sg:city":"Pleasant Grove",
    "sg:classifiers":[
        {
            "category":"Professional",
            "subcategory":"Business Services",
            "type":"Services"
        }
    ],
    "sg:phone":"+1 801 785 5099",
    "sg:postcode":"84062",
    "sg:province":"UT",
    "wof:name":"Applied Data Systems",
    "wof:placetype":"venue"
},
  "geometry": {"coordinates":[-111.763493,40.419686],"type":"Point"}
}