{
  "type": "Feature",
  "properties": {
    "iso:country":"US",
    "sg:address":"499 State St",
    "sg:city":"Clearfield",
    "sg:classifiers":[
        {
            "category":"Food & Beverages",
            "subcategory":"Groceries & Convenience Stores",
            "type":"Retail Goods"
        }
    ],
    "sg:phone":"+1 801 825 2889",
    "sg:postcode":"84015",
    "sg:province":"UT",
    "sg:tags":[
        "market"
    ],
    "wof:name":"Tenochtitlan Market",
    "wof:placetype":"venue"
},
  "geometry": {"coordinates":[-112.018683,41.106859],"type":"Point"}
}