{
  "type": "Feature",
  "properties": {
    "iso:country":"US",
    "sg:address":"5899 S State St",
    "sg:city":"Salt Lake City",
    "sg:classifiers":[
        {
            "category":"Personal",
            "type":"Services"
        }
    ],
    "sg:phone":"+1 801 268 1600",
    "sg:postcode":"84107",
    "sg:province":"UT",
    "wof:name":"Quick Weight Loss Center",
    "wof:placetype":"venue"
},
  "geometry": {"coordinates":[-111.888747,40.645962],"type":"Point"}
}