{
  "type": "Feature",
  "properties": {
    "iso:country":"US",
    "sg:address":"538 N Bluff St",
    "sg:city":"St George",
    "sg:classifiers":[
        {
            "category":"Building & Trades",
            "subcategory":"Landscaping Services",
            "type":"Services"
        }
    ],
    "sg:phone":"+1 435 628 1703",
    "sg:postcode":"84770",
    "sg:province":"UT",
    "sg:tags":[
        "lawn",
        "maintenance",
        "grounds"
    ],
    "wof:name":"Supreme Green",
    "wof:placetype":"venue"
},
  "geometry": {"coordinates":[-113.59729299999999,37.117809],"type":"Point"}
}