{
  "type": "Feature",
  "properties": {
    "iso:country":"US",
    "sg:address":"2740 Lemel Cir",
    "sg:city":"Salt Lake City",
    "sg:classifiers":[
        {
            "category":"Wholesale",
            "subcategory":"Chemicals & Plastics",
            "type":"Manufacturing & Wholesale Goods"
        }
    ],
    "sg:phone":"+1 801 487 1048",
    "sg:postcode":"84115",
    "sg:province":"UT",
    "wof:name":"Powder Keg Powder Coating",
    "wof:placetype":"venue"
},
  "geometry": {"coordinates":[-111.902841,40.711714],"type":"Point"}
}