{
  "type": "Feature",
  "properties": {
    "iso:country":"US",
    "sg:address":"8052 Willow Stream Dr",
    "sg:city":"Sandy",
    "sg:classifiers":[
        {
            "category":"Real Estate",
            "subcategory":"Real Estate Agent",
            "type":"Services"
        }
    ],
    "sg:phone":"+1 801 947 0200",
    "sg:postcode":"84093",
    "sg:province":"UT",
    "wof:name":"Sherlock Of Homes",
    "wof:placetype":"venue"
},
  "geometry": {"coordinates":[-111.83079600000001,40.604913],"type":"Point"}
}