{
  "type": "Feature",
  "properties": {
    "iso:country":"US",
    "sg:address":"855 S 500 W",
    "sg:city":"Salt Lake City",
    "sg:classifiers":[
        {
            "category":"Wholesale",
            "subcategory":"Farm Supplies",
            "type":"Manufacturing & Wholesale Goods"
        }
    ],
    "sg:phone":"+1 801 363 2300",
    "sg:postcode":"84101",
    "sg:province":"UT",
    "sg:tags":[
        "wool"
    ],
    "wof:name":"R C Elliott & Co",
    "wof:placetype":"venue"
},
  "geometry": {"coordinates":[-111.905305,40.750964],"type":"Point"}
}