{
  "type": "Feature",
  "properties": {
    "iso:country":"US",
    "sg:address":"2855 S State St",
    "sg:city":"Provo",
    "sg:classifiers":[
        {
            "category":"Building & Trades",
            "subcategory":"Construction",
            "type":"Services"
        }
    ],
    "sg:phone":"+1 801 370 8638",
    "sg:postcode":"84606",
    "sg:province":"UT",
    "sg:tags":[
        "grading",
        "contractor"
    ],
    "wof:name":"Public Works Weed Control",
    "wof:placetype":"venue"
},
  "geometry": {"coordinates":[-111.61545700000001,40.196245],"type":"Point"}
}