{
  "type": "Feature",
  "properties": {
    "iso:country":"US",
    "sg:address":"877 N 400 W",
    "sg:city":"Layton",
    "sg:classifiers":[
        {
            "category":"Travel",
            "subcategory":"Hotels & Motels",
            "type":"Entertainment"
        }
    ],
    "sg:phone":"+1 801 544 5577",
    "sg:postcode":"84041",
    "sg:province":"UT",
    "sg:website":"www.comfortinn.com",
    "wof:name":"Comfort Inn",
    "wof:placetype":"venue"
},
  "geometry": {"coordinates":[-111.97220900000001,41.070037],"type":"Point"}
}