{
  "type": "Feature",
  "properties": {
    "iso:country":"US",
    "sg:address":"444 S Main St",
    "sg:city":"Cedar City",
    "sg:classifiers":[
        {
            "category":"Professional",
            "subcategory":"Accounting & Tax Preparation",
            "type":"Services"
        }
    ],
    "sg:phone":"+1 435 586 9338",
    "sg:postcode":"84720",
    "sg:province":"UT",
    "sg:tags":[
        "accountant"
    ],
    "wof:name":"Floyd D Pickering CPA",
    "wof:placetype":"venue"
},
  "geometry": {"coordinates":[-113.061645,37.669759],"type":"Point"}
}