{
  "type": "Feature",
  "properties": {
    "iso:country":"US",
    "sg:address":"615 Arapeen Dr",
    "sg:city":"Salt Lake City",
    "sg:classifiers":[
        {
            "category":"Health Services",
            "subcategory":"Clinic",
            "type":"Services"
        }
    ],
    "sg:phone":"+1 801 581 4299",
    "sg:postcode":"84108",
    "sg:province":"UT",
    "sg:tags":[
        "tissue",
        "human"
    ],
    "wof:name":"Intermountain Tissue Center",
    "wof:placetype":"venue"
},
  "geometry": {"coordinates":[-111.82672700000001,40.755627],"type":"Point"}
}