{
  "type": "Feature",
  "properties": {
    "iso:country":"US",
    "sg:address":"561 W 200 S",
    "sg:city":"Salt Lake City",
    "sg:classifiers":[
        {
            "category":"Professional",
            "subcategory":"Art Services",
            "type":"Services"
        }
    ],
    "sg:phone":"+1 801 355 9541",
    "sg:postcode":"84101",
    "sg:province":"UT",
    "sg:tags":[
        "graphic",
        "designer"
    ],
    "sg:website":"www.modern8.com",
    "wof:name":"Modern 8",
    "wof:placetype":"venue"
},
  "geometry": {"coordinates":[-111.90814899999999,40.764916],"type":"Point"}
}