{
  "type": "Feature",
  "properties": {
    "iso:country":"US",
    "sg:address":"2215 S Carolyn Way",
    "sg:city":"Bountiful",
    "sg:classifiers":[
        {
            "category":"Insurance",
            "subcategory":"Insurance Agent",
            "type":"Services"
        }
    ],
    "sg:phone":"+1 801 292 6314",
    "sg:postcode":"84010",
    "sg:province":"UT",
    "wof:name":"Christensen Insurance Inc",
    "wof:placetype":"venue"
},
  "geometry": {"coordinates":[-111.860567,40.866178],"type":"Point"}
}