{
  "type": "Feature",
  "properties": {
    "iso:country":"US",
    "sg:address":"4689 Copper Mine Dr",
    "sg:city":"Riverton",
    "sg:classifiers":[
        {
            "category":"Building & Trades",
            "subcategory":"Construction",
            "type":"Services"
        }
    ],
    "sg:phone":"+1 801 446 2128",
    "sg:postcode":"84096",
    "sg:province":"UT",
    "sg:tags":[
        "contracting",
        "general"
    ],
    "wof:name":"Premium General Contracting",
    "wof:placetype":"venue"
},
  "geometry": {"coordinates":[-112.00235499999999,40.534231],"type":"Point"}
}