{
  "type": "Feature",
  "properties": {
    "iso:country":"US",
    "sg:address":"7493 N 9150 W",
    "sg:city":"Lehi",
    "sg:classifiers":[
        {
            "category":"Retail",
            "subcategory":"Animal Services",
            "type":"Services"
        }
    ],
    "sg:phone":"+1 801 768 0866",
    "sg:postcode":"84043",
    "sg:province":"UT",
    "wof:name":"Utah Cutting Horse Association",
    "wof:placetype":"venue"
},
  "geometry": {"coordinates":[-111.876879,40.371025],"type":"Point"}
}