{
  "type": "Feature",
  "properties": {
    "iso:country":"US",
    "sg:address":"8054 S State St",
    "sg:city":"Midvale",
    "sg:classifiers":[
        {
            "category":"Retail",
            "subcategory":"Auto Repair",
            "type":"Services"
        }
    ],
    "sg:phone":"+1 801 561 3601",
    "sg:postcode":"84047",
    "sg:province":"UT",
    "sg:tags":[
        "repairing",
        "automobile"
    ],
    "wof:name":"Frank's Auto & Diesel",
    "wof:placetype":"venue"
},
  "geometry": {"coordinates":[-111.890835,40.60534],"type":"Point"}
}