{
  "type": "Feature",
  "properties": {
    "iso:country":"US",
    "sg:address":"4016 W 5050 S",
    "sg:city":"Roy",
    "sg:classifiers":[
        {
            "category":"Professional",
            "type":"Services"
        }
    ],
    "sg:phone":"+1 801 731 5238",
    "sg:postcode":"84067",
    "sg:province":"UT",
    "wof:name":"Dream Catcher Specialties",
    "wof:placetype":"venue"
},
  "geometry": {"coordinates":[-112.075625,41.171749],"type":"Point"}
}