{
  "type": "Feature",
  "properties": {
    "iso:country":"US",
    "sg:address":"106 E 1120 N",
    "sg:city":"Logan",
    "sg:classifiers":[
        {
            "category":"Shopping",
            "subcategory":"Used Merchandise",
            "type":"Retail Goods"
        },
        {
            "category":"Retail",
            "subcategory":"Repair Shop",
            "type":"Services"
        }
    ],
    "sg:phone":"+1 435 753 3700",
    "sg:postcode":"84341",
    "sg:province":"UT",
    "sg:tags":[
        "entertainment",
        "household",
        "appliance",
        "high",
        "stereophonic",
        "home",
        "fidelity"
    ],
    "wof:name":"Tech Specialists",
    "wof:placetype":"venue"
},
  "geometry": {"coordinates":[-111.832707,41.75246],"type":"Point"}
}