{
  "type": "Feature",
  "properties": {
    "iso:country":"US",
    "sg:address":"291 E 1400 S",
    "sg:city":"St George",
    "sg:classifiers":[
        {
            "category":"Social Services",
            "subcategory":"Job Training",
            "type":"Services"
        }
    ],
    "sg:phone":"+1 435 628 0900",
    "sg:postcode":"84790",
    "sg:province":"UT",
    "wof:name":"Contactpoint LLC",
    "wof:placetype":"venue"
},
  "geometry": {"coordinates":[-113.57763,37.084506],"type":"Point"}
}