{
  "type": "Feature",
  "properties": {
    "iso:country":"US",
    "sg:address":"995 N 1725 W",
    "sg:city":"St George",
    "sg:classifiers":[
        {
            "category":"Building & Trades",
            "subcategory":"Construction",
            "type":"Services"
        }
    ],
    "sg:phone":"+1 435 986 0135",
    "sg:postcode":"84770",
    "sg:province":"UT",
    "sg:tags":[
        "general",
        "contractor"
    ],
    "wof:name":"Yel Con Inc",
    "wof:placetype":"venue"
},
  "geometry": {"coordinates":[-113.620734,37.125623],"type":"Point"}
}