{
  "type": "Feature",
  "properties": {
    "iso:country":"US",
    "sg:address":"222 W 9210 S",
    "sg:city":"Sandy",
    "sg:classifiers":[
        {
            "category":"Autos & Motor Vehicles",
            "subcategory":"Auto Supplies",
            "type":"Retail Goods"
        }
    ],
    "sg:phone":"+1 801 953 5298",
    "sg:postcode":"84070",
    "sg:province":"UT",
    "sg:tags":[
        "automobile",
        "parts"
    ],
    "wof:name":"Above All Customs",
    "wof:placetype":"venue"
},
  "geometry": {"coordinates":[-111.89767399999999,40.584146],"type":"Point"}
}