{
  "type": "Feature",
  "properties": {
    "iso:country":"US",
    "sg:address":"392 W Winchester St",
    "sg:city":"Salt Lake City",
    "sg:classifiers":[
        {
            "category":"Wholesale",
            "subcategory":"Sporting Goods",
            "type":"Manufacturing & Wholesale Goods"
        }
    ],
    "sg:phone":"+1 801 268 8890",
    "sg:postcode":"84107",
    "sg:province":"UT",
    "wof:name":"Hot Water Products",
    "wof:placetype":"venue"
},
  "geometry": {"coordinates":[-111.90243599999999,40.632532],"type":"Point"}
}