{
  "type": "Feature",
  "properties": {
    "iso:country":"US",
    "sg:address":"3854 S 4000 W",
    "sg:city":"Delta",
    "sg:classifiers":[
        {
            "category":"Professional",
            "type":"Services"
        }
    ],
    "sg:phone":"+1 435 864 5424",
    "sg:postcode":"84624",
    "sg:province":"UT",
    "sg:tags":[
        "establishment"
    ],
    "wof:name":"Cameron",
    "wof:placetype":"venue"
},
  "geometry": {"coordinates":[-112.652598,39.299499],"type":"Point"}
}