{
  "type": "Feature",
  "properties": {
    "iso:country":"US",
    "sg:address":"785 E 200 S",
    "sg:city":"Lehi",
    "sg:classifiers":[
        {
            "category":"Health Services",
            "subcategory":"Chiropractor",
            "type":"Services"
        }
    ],
    "sg:phone":"+1 801 766 1256",
    "sg:postcode":"84043",
    "sg:province":"UT",
    "wof:name":"Active Lf Chiropractic Clinic",
    "wof:placetype":"venue"
},
  "geometry": {"coordinates":[-111.835751,40.385986],"type":"Point"}
}