{
  "type": "Feature",
  "properties": {
    "iso:country":"US",
    "sg:address":"384 Commerce Loop",
    "sg:city":"Orem",
    "sg:classifiers":[
        {
            "category":"Freight",
            "type":"Transportation"
        }
    ],
    "sg:phone":"+1 801 426 4730",
    "sg:postcode":"84058",
    "sg:province":"UT",
    "sg:tags":[
        "warehouse",
        "public"
    ],
    "wof:name":"Master Wall Inc",
    "wof:placetype":"venue"
},
  "geometry": {"coordinates":[-111.727501,40.290053],"type":"Point"}
}