{
  "type": "Feature",
  "properties": {
    "iso:country":"US",
    "sg:address":"1002 S State St",
    "sg:city":"Orem",
    "sg:classifiers":[
        {
            "category":"Insurance",
            "subcategory":"Insurance Agent",
            "type":"Services"
        }
    ],
    "sg:phone":"+1 801 225 5400",
    "sg:postcode":"84097",
    "sg:province":"UT",
    "wof:name":"Brian J Lee Insurance Agency",
    "wof:placetype":"venue"
},
  "geometry": {"coordinates":[-111.68680999999999,40.278365],"type":"Point"}
}