{
  "type": "Feature",
  "properties": {
    "iso:country":"US",
    "sg:address":"1212 N Airport Rd",
    "sg:city":"Cedar City",
    "sg:classifiers":[
        {
            "category":"Building & Trades",
            "subcategory":"Construction",
            "type":"Services"
        }
    ],
    "sg:phone":"+1 435 865 5779",
    "sg:postcode":"84720",
    "sg:province":"UT",
    "sg:tags":[
        "painter"
    ],
    "wof:name":"Heavy Equipment & Painting",
    "wof:placetype":"venue"
},
  "geometry": {"coordinates":[-113.087121,37.698248],"type":"Point"}
}