{
  "type": "Feature",
  "properties": {
    "iso:country":"US",
    "sg:address":"2282 W 4250 S",
    "sg:city":"Roy",
    "sg:classifiers":[
        {
            "category":"Building & Trades",
            "subcategory":"Construction",
            "type":"Services"
        }
    ],
    "sg:phone":"+1 801 731 7754",
    "sg:postcode":"84067",
    "sg:province":"UT",
    "sg:tags":[
        "house"
    ],
    "wof:name":"T Green Construction",
    "wof:placetype":"venue"
},
  "geometry": {"coordinates":[-112.034868,41.186082],"type":"Point"}
}