{
  "type": "Feature",
  "properties": {
    "iso:country":"US",
    "sg:address":"3136 W Lemay Ave",
    "sg:city":"West Valley",
    "sg:classifiers":[
        {
            "category":"Professional",
            "type":"Services"
        }
    ],
    "sg:phone":"+1 801 955 0264",
    "sg:postcode":"84119",
    "sg:province":"UT",
    "sg:tags":[
        "establishment"
    ],
    "wof:name":"J & D Forms",
    "wof:placetype":"venue"
},
  "geometry": {"coordinates":[-111.96579800000001,40.698216],"type":"Point"}
}