{
  "type": "Feature",
  "properties": {
    "iso:country":"US",
    "sg:address":"4387 Harrison Blvd",
    "sg:city":"Ogden",
    "sg:classifiers":[
        {
            "category":"Restaurant",
            "type":"Food & Drink"
        }
    ],
    "sg:phone":"+1 801 476 3228",
    "sg:postcode":"84403",
    "sg:province":"UT",
    "sg:tags":[
        "bakery",
        "retail",
        "eating"
    ],
    "wof:name":"Einstein Brothers Bagels",
    "wof:placetype":"venue"
},
  "geometry": {"coordinates":[-111.949155,41.184079],"type":"Point"}
}