{
  "type": "Feature",
  "properties": {
    "iso:country":"US",
    "sg:address":"13062 Quincee Ct",
    "sg:city":"Riverton",
    "sg:classifiers":[
        {
            "category":"Building & Trades",
            "subcategory":"Electrical",
            "type":"Services"
        }
    ],
    "sg:phone":"+1 801 253 5170",
    "sg:postcode":"84065",
    "sg:province":"UT",
    "sg:tags":[
        "electrical",
        "contractor"
    ],
    "wof:name":"Bryans Electric",
    "wof:placetype":"venue"
},
  "geometry": {"coordinates":[-111.968064,40.514397],"type":"Point"}
}