{
  "type": "Feature",
  "properties": {
    "iso:country":"US",
    "sg:address":"1400 S 1900 E",
    "sg:city":"Salt Lake City",
    "sg:classifiers":[
        {
            "category":"Real Estate",
            "subcategory":"Real Estate Agent",
            "type":"Services"
        }
    ],
    "sg:phone":"+1 801 584 3198",
    "sg:postcode":"84108",
    "sg:province":"UT",
    "sg:tags":[
        "management"
    ],
    "wof:name":"Monument Park FM Group",
    "wof:placetype":"venue"
},
  "geometry": {"coordinates":[-111.83650799999999,40.739928],"type":"Point"}
}