{
  "type": "Feature",
  "properties": {
    "iso:country":"US",
    "sg:address":"3978 Sunnyvale Dr",
    "sg:city":"Salt Lake City",
    "sg:classifiers":[
        {
            "category":"Building & Trades",
            "subcategory":"Construction",
            "type":"Services"
        }
    ],
    "sg:phone":"+1 801 968 2331",
    "sg:postcode":"84120",
    "sg:province":"UT",
    "sg:tags":[
        "contractor"
    ],
    "wof:name":"ABC Restoration Inc",
    "wof:placetype":"venue"
},
  "geometry": {"coordinates":[-111.99260700000001,40.685966],"type":"Point"}
}