{
  "type": "Feature",
  "properties": {
    "iso:country":"US",
    "sg:address":"160 S 500 E",
    "sg:city":"Spanish Fork",
    "sg:classifiers":[
        {
            "category":"Home & Garden",
            "subcategory":"Building Materials",
            "type":"Retail Goods"
        }
    ],
    "sg:phone":"+1 801 756 9990",
    "sg:postcode":"84660",
    "sg:province":"UT",
    "sg:tags":[
        "glass",
        "window",
        "plate"
    ],
    "wof:name":"Safelite Auto Glass",
    "wof:placetype":"venue"
},
  "geometry": {"coordinates":[-111.646034,40.107629],"type":"Point"}
}