{
  "type": "Feature",
  "properties": {
    "iso:country":"US",
    "sg:address":"330 N 900 E",
    "sg:city":"Nephi",
    "sg:classifiers":[
        {
            "category":"Restaurant",
            "type":"Food & Drink"
        }
    ],
    "sg:phone":"+1 435 623 4204",
    "sg:postcode":"84648",
    "sg:province":"UT",
    "sg:tags":[
        "eating"
    ],
    "wof:name":"Lotsa Motsa Pizza",
    "wof:placetype":"venue"
},
  "geometry": {"coordinates":[-111.81904299999999,39.714234],"type":"Point"}
}