{
  "type": "Feature",
  "properties": {
    "iso:country":"US",
    "sg:address":"2403 S State St",
    "sg:city":"Provo",
    "sg:classifiers":[
        {
            "category":"Wholesale",
            "subcategory":"Auto Parts",
            "type":"Manufacturing & Wholesale Goods"
        }
    ],
    "sg:phone":"+1 801 377 2060",
    "sg:postcode":"84606",
    "sg:province":"UT",
    "sg:tags":[
        "automobile",
        "rebuilt"
    ],
    "wof:name":"State Street Auto Wrecking",
    "wof:placetype":"venue"
},
  "geometry": {"coordinates":[-111.621385,40.201598],"type":"Point"}
}