{
  "type": "Feature",
  "properties": {
    "iso:country":"US",
    "sg:address":"48 E State Rd",
    "sg:city":"Pleasant Grove",
    "sg:classifiers":[
        {
            "category":"Restaurant",
            "type":"Food & Drink"
        }
    ],
    "sg:menulink":"http://www.allmenus.com/ut/american-fork-pleasant-grove/132868-subway/menu/",
    "sg:phone":"+1 801 785 9600",
    "sg:postcode":"84062",
    "sg:province":"UT",
    "sg:tags":[
        "american",
        "sandwich"
    ],
    "wof:name":"Subway",
    "wof:placetype":"venue"
},
  "geometry": {"coordinates":[-111.739701,40.35853],"type":"Point"}
}