{
  "type": "Feature",
  "properties": {
    "iso:country":"US",
    "sg:address":"2288 Ogden City Mall",
    "sg:city":"Ogden",
    "sg:classifiers":[
        {
            "category":"Shopping",
            "subcategory":"Shoes",
            "type":"Retail Goods"
        }
    ],
    "sg:phone":"+1 801 392 5021",
    "sg:postcode":"84401",
    "sg:province":"UT",
    "wof:name":"Foot Locker",
    "wof:placetype":"venue"
},
  "geometry": {"coordinates":[-111.971434,41.225978],"type":"Point"}
}