{
  "type": "Feature",
  "properties": {
    "iso:country":"US",
    "sg:address":"425 E Paradise Dr",
    "sg:city":"Orem",
    "sg:classifiers":[
        {
            "category":"Building & Trades",
            "subcategory":"Construction",
            "type":"Services"
        }
    ],
    "sg:phone":"+1 801 224 2901",
    "sg:postcode":"84097",
    "sg:province":"UT",
    "sg:tags":[
        "contractor",
        "painting",
        "hanging"
    ],
    "wof:name":"Brockys Paint Inc",
    "wof:placetype":"venue"
},
  "geometry": {"coordinates":[-111.684995,40.300628],"type":"Point"}
}