{
  "type": "Feature",
  "properties": {
    "iso:country":"US",
    "sg:address":"7054 S 1700 E",
    "sg:city":"Salt Lake City",
    "sg:classifiers":[
        {
            "category":"Professional",
            "subcategory":"Detective & Security Services",
            "type":"Services"
        }
    ],
    "sg:phone":"+1 801 453 9202",
    "sg:postcode":"84121",
    "sg:province":"UT",
    "wof:name":"Risk Enterprises International",
    "wof:placetype":"venue"
},
  "geometry": {"coordinates":[-111.84390500000001,40.622651],"type":"Point"}
}