{
  "type": "Feature",
  "properties": {
    "iso:country":"US",
    "sg:address":"1951 N 600 E",
    "sg:city":"Orem",
    "sg:classifiers":[
        {
            "category":"Home & Garden",
            "subcategory":"Furniture",
            "type":"Retail Goods"
        }
    ],
    "sg:phone":"+1 801 226 6224",
    "sg:postcode":"84097",
    "sg:province":"UT",
    "sg:tags":[
        "interior",
        "window",
        "floor",
        "covering"
    ],
    "wof:name":"Upstairs Downstairs Home Furn",
    "wof:placetype":"venue"
},
  "geometry": {"coordinates":[-111.68221699999999,40.332578],"type":"Point"}
}