{
  "type": "Feature",
  "properties": {
    "iso:country":"US",
    "sg:address":"6560 Landmark Dr",
    "sg:city":"Park City",
    "sg:classifiers":[
        {
            "category":"Restaurant",
            "type":"Food & Drink"
        }
    ],
    "sg:phone":"+1 435 940 1530",
    "sg:postcode":"84098",
    "sg:province":"UT",
    "wof:name":"J B's Restaurant",
    "wof:placetype":"venue"
},
  "geometry": {"coordinates":[-111.54830200000001,40.728944],"type":"Point"}
}