{
  "type": "Feature",
  "properties": {
    "iso:country":"US",
    "sg:address":"166 N Main St",
    "sg:city":"Panguitch",
    "sg:classifiers":[
        {
            "category":"Social Services",
            "subcategory":"Child Care",
            "type":"Services"
        }
    ],
    "sg:phone":"+1 435 676 2523",
    "sg:postcode":"84759",
    "sg:province":"UT",
    "sg:tags":[
        "day"
    ],
    "wof:name":"Suu Head Start",
    "wof:placetype":"venue"
},
  "geometry": {"coordinates":[-112.43557699999999,37.825326],"type":"Point"}
}