{
  "type": "Feature",
  "properties": {
    "iso:country":"US",
    "sg:address":"652 Hampton Ct",
    "sg:city":"Alpine",
    "sg:classifiers":[
        {
            "category":"Manufacturing",
            "subcategory":"Retail Goods",
            "type":"Manufacturing & Wholesale Goods"
        }
    ],
    "sg:phone":"+1 801 763 0980",
    "sg:postcode":"84004",
    "sg:province":"UT",
    "sg:tags":[
        "for",
        "mfg",
        "bow",
        "packaging",
        "purpose",
        "ribbon"
    ],
    "wof:name":"Transtar Converting",
    "wof:placetype":"venue"
},
  "geometry": {"coordinates":[-111.76608899999999,40.461372],"type":"Point"}
}