{
  "type": "Feature",
  "properties": {
    "iso:country":"US",
    "sg:address":"3369 W 8475 S",
    "sg:city":"West Jordan",
    "sg:classifiers":[
        {
            "category":"Building & Trades",
            "subcategory":"Construction",
            "type":"Services"
        }
    ],
    "sg:phone":"+1 801 565 0899",
    "sg:postcode":"84088",
    "sg:province":"UT",
    "sg:tags":[
        "carpentry",
        "contractor"
    ],
    "wof:name":"Hatch Carpentry Inc",
    "wof:placetype":"venue"
},
  "geometry": {"coordinates":[-111.96808299999999,40.598182],"type":"Point"}
}