{
  "type": "Feature",
  "properties": {
    "iso:country":"US",
    "sg:address":"1361 S 3200 W",
    "sg:city":"Salt Lake City",
    "sg:classifiers":[
        {
            "category":"Freight",
            "type":"Transportation"
        }
    ],
    "sg:phone":"+1 801 975 9400",
    "sg:postcode":"84104",
    "sg:province":"UT",
    "sg:tags":[
        "trucking"
    ],
    "sg:website":"www.usfreddaway.com",
    "wof:name":"USF Reddaway Inc",
    "wof:placetype":"venue"
},
  "geometry": {"coordinates":[-111.96762699999999,40.738907],"type":"Point"}
}