{
  "type": "Feature",
  "properties": {
    "iso:country":"US",
    "sg:address":"1120 E 3125 N",
    "sg:city":"Layton",
    "sg:classifiers":[
        {
            "category":"Real Estate",
            "subcategory":"Real Estate Operator",
            "type":"Services"
        }
    ],
    "sg:phone":"+1 801 771 0572",
    "sg:postcode":"84040",
    "sg:province":"UT",
    "sg:tags":[
        "farm",
        "property",
        "grain",
        "cash",
        "lessor"
    ],
    "wof:name":"Keith Price",
    "wof:placetype":"venue"
},
  "geometry": {"coordinates":[-111.944452,41.105108],"type":"Point"}
}