{
  "type": "Feature",
  "properties": {
    "iso:country":"US",
    "sg:address":"59 S 700 E",
    "sg:city":"Price",
    "sg:classifiers":[
        {
            "category":"Health Services",
            "subcategory":"Nursing And Care Facility",
            "type":"Services"
        }
    ],
    "sg:phone":"+1 435 613 8887",
    "sg:postcode":"84501",
    "sg:province":"UT",
    "sg:tags":[
        "skilled"
    ],
    "wof:name":"Community Nursing Service",
    "wof:placetype":"venue"
},
  "geometry": {"coordinates":[-110.797839,39.59871],"type":"Point"}
}