{
  "type": "Feature",
  "properties": {
    "iso:country":"US",
    "sg:address":"1905 W 4700 S",
    "sg:city":"Salt Lake City",
    "sg:classifiers":[
        {
            "category":"Building & Trades",
            "subcategory":"Construction",
            "type":"Services"
        }
    ],
    "sg:phone":"+1 801 955 1779",
    "sg:postcode":"84118",
    "sg:province":"UT",
    "sg:tags":[
        "resurfacing",
        "laying",
        "refinishing",
        "floor"
    ],
    "sg:website":"www.dustgone.com",
    "wof:name":"Dust Gone Svc",
    "wof:placetype":"venue"
},
  "geometry": {"coordinates":[-111.939646,40.667577],"type":"Point"}
}