{
  "type": "Feature",
  "properties": {
    "iso:country":"US",
    "sg:address":"1518 Forest Green Dr",
    "sg:city":"Ogden",
    "sg:classifiers":[
        {
            "category":"Organizations",
            "subcategory":"Labor Organization",
            "type":"Services"
        }
    ],
    "sg:phone":"+1 801 621 6258",
    "sg:postcode":"84403",
    "sg:province":"UT",
    "sg:tags":[
        "engineering"
    ],
    "wof:name":"Product Engineering Lc",
    "wof:placetype":"venue"
},
  "geometry": {"coordinates":[-111.94028,41.180644],"type":"Point"}
}