{
  "type": "Feature",
  "properties": {
    "iso:country":"US",
    "sg:address":"136 S 100 E",
    "sg:city":"Smithfield",
    "sg:classifiers":[
        {
            "category":"Retail",
            "subcategory":"Auto Repair",
            "type":"Services"
        }
    ],
    "sg:phone":"+1 435 563 4054",
    "sg:postcode":"84335",
    "sg:province":"UT",
    "sg:tags":[
        "automobile",
        "restoration",
        "classic"
    ],
    "wof:name":"Dunes Automotive",
    "wof:placetype":"venue"
},
  "geometry": {"coordinates":[-111.829826,41.833528],"type":"Point"}
}