{
  "type": "Feature",
  "properties": {
    "iso:country":"US",
    "sg:address":"1745 Sidewinder Dr",
    "sg:city":"Park City",
    "sg:classifiers":[
        {
            "category":"Insurance",
            "subcategory":"Insurance Agent",
            "type":"Services"
        }
    ],
    "sg:phone":"+1 435 649 0152",
    "sg:postcode":"84060",
    "sg:province":"UT",
    "wof:name":"Perry's Insurance",
    "wof:placetype":"venue"
},
  "geometry": {"coordinates":[-111.498896,40.663447],"type":"Point"}
}