{
  "type": "Feature",
  "properties": {
    "iso:country":"US",
    "sg:address":"766 S 600 E",
    "sg:city":"Centerville",
    "sg:classifiers":[
        {
            "category":"Shopping",
            "subcategory":"Hobbies, Toys, & Games",
            "type":"Retail Goods"
        }
    ],
    "sg:phone":"+1 801 298 7965",
    "sg:postcode":"84014",
    "sg:province":"UT",
    "wof:name":"Bamberger Railroad Co",
    "wof:placetype":"venue"
},
  "geometry": {"coordinates":[-111.86970700000001,40.909351],"type":"Point"}
}