{
  "type": "Feature",
  "properties": {
    "iso:country":"US",
    "sg:address":"1065 S 500 W Ste W1",
    "sg:city":"Woods Cross",
    "sg:classifiers":[
        {
            "category":"Building & Trades",
            "subcategory":"Plumbing",
            "type":"Services"
        }
    ],
    "sg:phone":"+1 801 292 3104",
    "sg:postcode":"84010",
    "sg:province":"UT",
    "wof:name":"Bountiful Plumbing and Heat",
    "wof:placetype":"venue"
},
  "geometry": {"coordinates":[-111.89202899999999,40.878043],"type":"Point"}
}