{
  "type": "Feature",
  "properties": {
    "iso:country":"US",
    "sg:address":"3250 N 750 E",
    "sg:city":"Layton",
    "sg:classifiers":[
        {
            "category":"Retail",
            "subcategory":"Auto Repair",
            "type":"Services"
        }
    ],
    "sg:phone":"+1 801 547 1057",
    "sg:postcode":"84041",
    "sg:province":"UT",
    "sg:tags":[
        "repairing",
        "automobile",
        "general"
    ],
    "wof:name":"Japan Engine Supply Sales",
    "wof:placetype":"venue"
},
  "geometry": {"coordinates":[-111.952326,41.104983],"type":"Point"}
}