{
  "type": "Feature",
  "properties": {
    "iso:country":"US",
    "sg:address":"1032 W 2610 S",
    "sg:city":"Salt Lake City",
    "sg:classifiers":[
        {
            "category":"Wholesale",
            "subcategory":"Auto Parts",
            "type":"Manufacturing & Wholesale Goods"
        }
    ],
    "sg:phone":"+1 801 972 4313",
    "sg:postcode":"84119",
    "sg:province":"UT",
    "sg:tags":[
        "automotive",
        "distribution"
    ],
    "wof:name":"Independent Whse Aliance LLC",
    "wof:placetype":"venue"
},
  "geometry": {"coordinates":[-111.921092,40.714814],"type":"Point"}
}