{
  "type": "Feature",
  "properties": {
    "iso:country":"US",
    "sg:address":"4033 W 9580 S",
    "sg:city":"South Jordan",
    "sg:classifiers":[
        {
            "category":"Health Services",
            "subcategory":"Doctor",
            "type":"Services"
        }
    ],
    "sg:phone":"+1 801 584 1240",
    "sg:postcode":"84095",
    "sg:province":"UT",
    "sg:tags":[
        "medical"
    ],
    "wof:name":"Graham Brandy",
    "wof:placetype":"venue"
},
  "geometry": {"coordinates":[-111.986418,40.577337],"type":"Point"}
}