{
  "type": "Feature",
  "properties": {
    "iso:country":"US",
    "sg:address":"4294 S 4500 W",
    "sg:city":"Ogden",
    "sg:classifiers":[
        {
            "category":"Banks & Credit Unions",
            "subcategory":"Bank",
            "type":"Services"
        }
    ],
    "sg:phone":"+1 801 731 5777",
    "sg:postcode":"84401",
    "sg:province":"UT",
    "sg:tags":[
        "mortgage"
    ],
    "wof:name":"Home Appreciation Enterprises",
    "wof:placetype":"venue"
},
  "geometry": {"coordinates":[-112.088154,41.185411],"type":"Point"}
}