{
  "type": "Feature",
  "properties": {
    "iso:country":"US",
    "sg:address":"63 W Main St",
    "sg:city":"Vernal",
    "sg:classifiers":[
        {
            "category":"Real Estate",
            "subcategory":"Real Estate Agent",
            "type":"Services"
        }
    ],
    "sg:phone":"+1 435 789 3132",
    "sg:postcode":"84078",
    "sg:province":"UT",
    "wof:name":"United Country Real Estate",
    "wof:placetype":"venue"
},
  "geometry": {"coordinates":[-109.52970999999999,40.455627],"type":"Point"}
}