{
  "type": "Feature",
  "properties": {
    "iso:country":"US",
    "sg:address":"1775 W 1280 N",
    "sg:city":"St George",
    "sg:classifiers":[
        {
            "category":"Building & Trades",
            "subcategory":"Landscaping Services",
            "type":"Services"
        }
    ],
    "sg:phone":"+1 435 229 8478",
    "sg:postcode":"84770",
    "sg:province":"UT",
    "wof:name":"Redrock Landscapes",
    "wof:placetype":"venue"
},
  "geometry": {"coordinates":[-113.623806,37.130127],"type":"Point"}
}