{
  "type": "Feature",
  "properties": {
    "iso:country":"US",
    "sg:address":"4543 S 700 E",
    "sg:city":"Salt Lake City",
    "sg:classifiers":[
        {
            "category":"Professional",
            "subcategory":"Lawyer & Legal Services",
            "type":"Services"
        }
    ],
    "sg:phone":"+1 801 263 3344",
    "sg:postcode":"84107",
    "sg:province":"UT",
    "sg:tags":[
        "law"
    ],
    "wof:name":"Poole & Associates PC",
    "wof:placetype":"venue"
},
  "geometry": {"coordinates":[-111.871376,40.673266],"type":"Point"}
}