{
  "type": "Feature",
  "properties": {
    "iso:country":"US",
    "sg:address":"5628 Wild Mustang Ct",
    "sg:city":"Riverton",
    "sg:classifiers":[
        {
            "category":"Retail",
            "subcategory":"Laundry & Dry Cleaning",
            "type":"Services"
        }
    ],
    "sg:phone":"+1 801 446 5648",
    "sg:postcode":"84096",
    "sg:province":"UT",
    "wof:name":"High Prfmce Crpt & Uphl Cle",
    "wof:placetype":"venue"
},
  "geometry": {"coordinates":[-112.024978,40.504334],"type":"Point"}
}