{
  "type": "Feature",
  "properties": {
    "iso:country":"US",
    "sg:address":"247 N 100 W",
    "sg:city":"Spanish Fork",
    "sg:classifiers":[
        {
            "category":"Building & Trades",
            "subcategory":"Construction",
            "type":"Services"
        }
    ],
    "sg:phone":"+1 801 798 6351",
    "sg:postcode":"84660",
    "sg:province":"UT",
    "sg:tags":[
        "builder",
        "operative"
    ],
    "wof:name":"Joe R Jarvis Construction",
    "wof:placetype":"venue"
},
  "geometry": {"coordinates":[-111.656614,40.11314],"type":"Point"}
}