{
  "type": "Feature",
  "properties": {
    "iso:country":"US",
    "sg:address":"4217 S 4625 W",
    "sg:city":"Salt Lake City",
    "sg:classifiers":[
        {
            "category":"Building & Trades",
            "subcategory":"Construction",
            "type":"Services"
        }
    ],
    "sg:phone":"+1 801 967 4179",
    "sg:postcode":"84120",
    "sg:province":"UT",
    "sg:tags":[
        "builder",
        "operative"
    ],
    "wof:name":"Qwc Inc",
    "wof:placetype":"venue"
},
  "geometry": {"coordinates":[-112.001345,40.678731],"type":"Point"}
}