{
  "type": "Feature",
  "properties": {
    "iso:country":"US",
    "sg:address":"805 N Redwood Rd",
    "sg:city":"North Salt Lake",
    "sg:classifiers":[
        {
            "category":"Freight",
            "type":"Transportation"
        }
    ],
    "sg:phone":"+1 801 292 0222",
    "sg:postcode":"84054",
    "sg:province":"UT",
    "sg:tags":[
        "dry",
        "bulk",
        "local",
        "operator",
        "trucking"
    ],
    "wof:name":"Spreader Specialists Inc",
    "wof:placetype":"venue"
},
  "geometry": {"coordinates":[-111.929744,40.849693],"type":"Point"}
}