{
  "type": "Feature",
  "properties": {
    "iso:country":"US",
    "sg:address":"323 S 100 E",
    "sg:city":"Kanab",
    "sg:classifiers":[
        {
            "category":"Real Estate",
            "subcategory":"Real Estate Agent",
            "type":"Services"
        }
    ],
    "sg:phone":"+1 435 644 2232",
    "sg:postcode":"84741",
    "sg:province":"UT",
    "wof:name":"Adobe Realty",
    "wof:placetype":"venue"
},
  "geometry": {"coordinates":[-112.526315,37.042591],"type":"Point"}
}