{
  "type": "Feature",
  "properties": {
    "iso:country":"US",
    "sg:address":"2649 Sable Cir",
    "sg:city":"Salt Lake City",
    "sg:classifiers":[
        {
            "category":"Professional",
            "subcategory":"Computer Services",
            "type":"Services"
        }
    ],
    "sg:phone":"+1 801 673 2445",
    "sg:postcode":"84118",
    "sg:province":"UT",
    "sg:tags":[
        "design",
        "system"
    ],
    "wof:name":"Grid Protocal",
    "wof:placetype":"venue"
},
  "geometry": {"coordinates":[-111.956816,40.666583],"type":"Point"}
}