{
  "type": "Feature",
  "properties": {
    "iso:country":"US",
    "sg:address":"570 W Weber Canyon Rd",
    "sg:city":"Kamas",
    "sg:classifiers":[
        {
            "category":"Professional",
            "subcategory":"Accounting & Tax Preparation",
            "type":"Services"
        }
    ],
    "sg:phone":"+1 435 783 4307",
    "sg:postcode":"84036",
    "sg:province":"UT",
    "sg:tags":[
        "bookkeeping",
        "general"
    ],
    "wof:name":"Sharrel Cummings CPA",
    "wof:placetype":"venue"
},
  "geometry": {"coordinates":[-111.291718,40.719861],"type":"Point"}
}