{
  "type": "Feature",
  "properties": {
    "iso:country":"US",
    "sg:address":"702 S Main St",
    "sg:city":"Moab",
    "sg:classifiers":[
        {
            "category":"Personal",
            "subcategory":"Beauty Salon",
            "type":"Services"
        }
    ],
    "sg:phone":"+1 435 259 0219",
    "sg:postcode":"84532",
    "sg:province":"UT",
    "sg:tags":[
        "manicuring"
    ],
    "wof:name":"Lee Nails",
    "wof:placetype":"venue"
},
  "geometry": {"coordinates":[-109.55037900000001,38.565547],"type":"Point"}
}