{
  "type": "Feature",
  "properties": {
    "iso:country":"US",
    "sg:address":"1989 Airport Rd",
    "sg:city":"Price",
    "sg:classifiers":[
        {
            "category":"Retail",
            "subcategory":"Veterinary Services",
            "type":"Services"
        }
    ],
    "sg:phone":"+1 435 637 5797",
    "sg:postcode":"84501",
    "sg:province":"UT",
    "sg:tags":[
        "hospital"
    ],
    "wof:name":"Animal Hospital",
    "wof:placetype":"venue"
},
  "geometry": {"coordinates":[-110.78075,39.599136],"type":"Point"}
}