{
  "type": "Feature",
  "properties": {
    "iso:country":"US",
    "sg:address":"11605 Nicklaus Rd",
    "sg:city":"Sandy",
    "sg:classifiers":[
        {
            "category":"Professional",
            "type":"Services"
        }
    ],
    "sg:phone":"+1 801 571 8939",
    "sg:postcode":"84092",
    "sg:province":"UT",
    "wof:name":"Geomin Inc",
    "wof:placetype":"venue"
},
  "geometry": {"coordinates":[-111.844694,40.539853],"type":"Point"}
}