{
  "type": "Feature",
  "properties": {
    "iso:country":"US",
    "sg:address":"1760 Park Ave",
    "sg:city":"Park City",
    "sg:classifiers":[
        {
            "category":"Coffee & Tea",
            "type":"Food & Drink"
        }
    ],
    "sg:menulink":"http://www.allmenus.com/ut/park-city/118373-starbucks-coffee/menu/",
    "sg:phone":"+1 435 649 6134",
    "sg:postcode":"84060",
    "sg:province":"UT",
    "sg:tags":[
        "american"
    ],
    "wof:name":"Starbucks Coffee",
    "wof:placetype":"venue"
},
  "geometry": {"coordinates":[-111.50729200000001,40.659431],"type":"Point"}
}