{
  "type": "Feature",
  "properties": {
    "iso:country":"US",
    "sg:address":"6295 McConkie Rd",
    "sg:city":"Vernal",
    "sg:classifiers":[
        {
            "category":"Professional",
            "subcategory":"Business Services",
            "type":"Services"
        }
    ],
    "sg:phone":"+1 435 789 9042",
    "sg:postcode":"84078",
    "sg:province":"UT",
    "sg:tags":[
        "water",
        "hauling"
    ],
    "wof:name":"Greg Mc Kenzie Trucking",
    "wof:placetype":"venue"
},
  "geometry": {"coordinates":[-109.638254,40.54588],"type":"Point"}
}