{
  "type": "Feature",
  "properties": {
    "iso:country":"US",
    "sg:address":"176 W Main St",
    "sg:city":"Tremonton",
    "sg:classifiers":[
        {
            "category":"Home & Garden",
            "subcategory":"Hardware",
            "type":"Retail Goods"
        }
    ],
    "sg:phone":"+1 435 257 5682",
    "sg:postcode":"84337",
    "sg:province":"UT",
    "wof:name":"R & R Hardware",
    "wof:placetype":"venue"
},
  "geometry": {"coordinates":[-112.16853,41.711746],"type":"Point"}
}