{
  "type": "Feature",
  "properties": {
    "iso:country":"US",
    "sg:address":"3903 Airport Rd",
    "sg:city":"Ogden",
    "sg:classifiers":[
        {
            "category":"Government",
            "subcategory":"Office",
            "type":"Public Place"
        }
    ],
    "sg:phone":"+1 801 625 5569",
    "sg:postcode":"84405",
    "sg:province":"UT",
    "sg:tags":[
        "control",
        "tower"
    ],
    "wof:name":"Airport Traffic Control Tower",
    "wof:placetype":"venue"
},
  "geometry": {"coordinates":[-111.998276,41.203874],"type":"Point"}
}