{
  "type": "Feature",
  "properties": {
    "iso:country":"US",
    "sg:address":"4351 S Redwood Rd",
    "sg:city":"Salt Lake City",
    "sg:classifiers":[
        {
            "category":"Health Services",
            "subcategory":"Clinic",
            "type":"Services"
        }
    ],
    "sg:phone":"+1 801 263 6103",
    "sg:postcode":"84123",
    "sg:province":"UT",
    "sg:tags":[
        "mental"
    ],
    "wof:name":"Valley Mental Health",
    "wof:placetype":"venue"
},
  "geometry": {"coordinates":[-111.938785,40.676133],"type":"Point"}
}