{
  "type": "Feature",
  "properties": {
    "iso:country":"US",
    "sg:address":"2062 W 1800 N",
    "sg:city":"Clearfield",
    "sg:classifiers":[
        {
            "category":"Food & Beverages",
            "subcategory":"Groceries & Convenience Stores",
            "type":"Retail Goods"
        }
    ],
    "sg:phone":"+1 801 776 8144",
    "sg:postcode":"84015",
    "sg:province":"UT",
    "wof:name":"Albertsons 393",
    "wof:placetype":"venue"
},
  "geometry": {"coordinates":[-112.06787199999999,41.139949],"type":"Point"}
}