{
  "type": "Feature",
  "properties": {
    "iso:country":"US",
    "sg:address":"523 E 7200 S",
    "sg:city":"Midvale",
    "sg:classifiers":[
        {
            "category":"Personal",
            "type":"Services"
        },
        {
            "category":"Health Services",
            "subcategory":"Clinic",
            "type":"Services"
        }
    ],
    "sg:phone":"+1 801 568 9905",
    "sg:postcode":"84047",
    "sg:province":"UT",
    "sg:tags":[
        "therapist",
        "massage"
    ],
    "wof:name":"Holistic Pain Relief Clinic",
    "wof:placetype":"venue"
},
  "geometry": {"coordinates":[-111.87737199999999,40.620706],"type":"Point"}
}