{
  "type": "Feature",
  "properties": {
    "iso:country":"US",
    "sg:address":"1393 N 400 W",
    "sg:city":"Centerville",
    "sg:classifiers":[
        {
            "category":"Wholesale",
            "subcategory":"Sporting Goods",
            "type":"Manufacturing & Wholesale Goods"
        }
    ],
    "sg:phone":"+1 801 296 6921",
    "sg:postcode":"84014",
    "sg:province":"UT",
    "sg:tags":[
        "equipment",
        "bowling"
    ],
    "wof:name":"Trade Select",
    "wof:placetype":"venue"
},
  "geometry": {"coordinates":[-111.885565,40.93403],"type":"Point"}
}