{
  "type": "Feature",
  "properties": {
    "iso:country":"US",
    "sg:address":"601 College St",
    "sg:city":"Dove Creek",
    "sg:classifiers":[
        {
            "category":"Organizations",
            "subcategory":"Religious Organization",
            "type":"Services"
        }
    ],
    "sg:phone":"+1 970 677 2304",
    "sg:postcode":"81324",
    "sg:province":"UT",
    "sg:tags":[
        "church"
    ],
    "wof:name":"Methodist Church",
    "wof:placetype":"venue"
},
  "geometry": {"coordinates":[-108.903074,37.768648],"type":"Point"}
}