{
  "type": "Feature",
  "properties": {
    "iso:country":"US",
    "sg:address":"1050 E Galena Dr",
    "sg:city":"Sandy",
    "sg:classifiers":[
        {
            "category":"Organizations",
            "subcategory":"Religious Organization",
            "type":"Services"
        }
    ],
    "sg:phone":"+1 801 576 2862",
    "sg:postcode":"84094",
    "sg:province":"UT",
    "sg:tags":[
        "church"
    ],
    "wof:name":"Church Of Jesus Christ Of Lds",
    "wof:placetype":"venue"
},
  "geometry": {"coordinates":[-111.862937,40.572789],"type":"Point"}
}