{
  "type": "Feature",
  "properties": {
    "iso:country":"US",
    "sg:address":"2145 W 700 S",
    "sg:city":"Lehi",
    "sg:classifiers":[
        {
            "category":"Professional",
            "subcategory":"Business Services",
            "type":"Services"
        }
    ],
    "sg:phone":"+1 801 766 6065",
    "sg:postcode":"84043",
    "sg:province":"UT",
    "wof:name":"Bb Enterprises of Utah Inc",
    "wof:placetype":"venue"
},
  "geometry": {"coordinates":[-111.883697,40.379693],"type":"Point"}
}