{
  "type": "Feature",
  "properties": {
    "iso:country":"US",
    "sg:address":"1650 N 1250 W",
    "sg:city":"Provo",
    "sg:classifiers":[
        {
            "category":"Building & Trades",
            "subcategory":"Construction",
            "type":"Services"
        }
    ],
    "sg:phone":"+1 801 373 5729",
    "sg:postcode":"84604",
    "sg:province":"UT",
    "sg:tags":[
        "house",
        "contractor"
    ],
    "wof:name":"Ladell R Baum Construction",
    "wof:placetype":"venue"
},
  "geometry": {"coordinates":[-111.679852,40.255903],"type":"Point"}
}