{
  "type": "Feature",
  "properties": {
    "iso:country":"US",
    "sg:address":"3944 S 400 E",
    "sg:city":"Salt Lake City",
    "sg:classifiers":[
        {
            "category":"Government",
            "subcategory":"Office",
            "type":"Public Place"
        }
    ],
    "sg:phone":"+1 801 483 5444",
    "sg:postcode":"84107",
    "sg:province":"UT",
    "wof:name":"Adult Residential Trtmt Unit",
    "wof:placetype":"venue"
},
  "geometry": {"coordinates":[-111.879976,40.685823],"type":"Point"}
}