{
  "type": "Feature",
  "properties": {
    "iso:country":"US",
    "sg:address":"937 N 200 E",
    "sg:city":"American Fork",
    "sg:classifiers":[
        {
            "category":"Building & Trades",
            "subcategory":"Plumbing",
            "type":"Services"
        }
    ],
    "sg:phone":"+1 801 756 3320",
    "sg:postcode":"84003",
    "sg:province":"UT",
    "sg:tags":[
        "mechanical",
        "contractor"
    ],
    "wof:name":"Diamond G Mechanical Contrs",
    "wof:placetype":"venue"
},
  "geometry": {"coordinates":[-111.79311300000001,40.395914],"type":"Point"}
}