{
  "type": "Feature",
  "properties": {
    "iso:country":"US",
    "sg:address":"271 E 1500 S",
    "sg:city":"Orem",
    "sg:classifiers":[
        {
            "category":"Retail",
            "subcategory":"Laundry & Dry Cleaning",
            "type":"Services"
        }
    ],
    "sg:phone":"+1 801 224 2050",
    "sg:postcode":"84058",
    "sg:province":"UT",
    "sg:tags":[
        "cleaners",
        "rug",
        "carpet"
    ],
    "wof:name":"Thoro-Kleen Carpet Care",
    "wof:placetype":"venue"
},
  "geometry": {"coordinates":[-111.688863,40.26973],"type":"Point"}
}