{
  "type": "Feature",
  "properties": {
    "iso:country":"US",
    "sg:address":"805 S Main St",
    "sg:city":"Bountiful",
    "sg:classifiers":[
        {
            "category":"Government",
            "subcategory":"Office",
            "type":"Public Place"
        }
    ],
    "sg:phone":"+1 801 298 6145",
    "sg:postcode":"84010",
    "sg:province":"UT",
    "sg:tags":[
        "village"
    ],
    "wof:name":"Bountiful City Prosecutor",
    "wof:placetype":"venue"
},
  "geometry": {"coordinates":[-111.880858,40.88064],"type":"Point"}
}