{
  "type": "Feature",
  "properties": {
    "iso:country":"US",
    "sg:address":"1309 S 500 W",
    "sg:city":"Woods Cross",
    "sg:classifiers":[
        {
            "category":"Retail",
            "subcategory":"Auto Repair",
            "type":"Services"
        }
    ],
    "sg:phone":"+1 801 295 5146",
    "sg:postcode":"84010",
    "sg:province":"UT",
    "sg:tags":[
        "automobile",
        "lubrication"
    ],
    "wof:name":"Shell Rapid Lube",
    "wof:placetype":"venue"
},
  "geometry": {"coordinates":[-111.892166,40.876055],"type":"Point"}
}