{
  "type": "Feature",
  "properties": {
    "iso:country":"US",
    "sg:address":"553 E Gentile St",
    "sg:city":"Layton",
    "sg:classifiers":[
        {
            "category":"Freight",
            "type":"Transportation"
        }
    ],
    "sg:phone":"+1 801 547 1049",
    "sg:postcode":"84041",
    "sg:province":"UT",
    "sg:tags":[
        "commercial",
        "storage"
    ],
    "wof:name":"Morgan Brothers",
    "wof:placetype":"venue"
},
  "geometry": {"coordinates":[-111.95552600000001,41.060176],"type":"Point"}
}