{
  "type": "Feature",
  "properties": {
    "iso:country":"US",
    "sg:address":"5560 N 1180 W",
    "sg:city":"St George",
    "sg:classifiers":[
        {
            "category":"Real Estate",
            "subcategory":"Real Estate Agent",
            "type":"Services"
        }
    ],
    "sg:phone":"+1 435 674 2744",
    "sg:postcode":"84770",
    "sg:province":"UT",
    "wof:name":"Rex & Rex",
    "wof:placetype":"venue"
},
  "geometry": {"coordinates":[-113.60936100000001,37.206964],"type":"Point"}
}