{
  "type": "Feature",
  "properties": {
    "iso:country":"US",
    "sg:address":"1388 N Main St",
    "sg:city":"Park City",
    "sg:classifiers":[
        {
            "category":"Recreation",
            "type":"Entertainment"
        }
    ],
    "sg:phone":"+1 435 655 0999",
    "sg:postcode":"84041",
    "sg:province":"UT",
    "sg:tags":[
        "center"
    ],
    "wof:name":"Basin Recreation",
    "wof:placetype":"venue"
},
  "geometry": {"coordinates":[-111.989642,41.080402],"type":"Point"}
}