{
  "type": "Feature",
  "properties": {
    "iso:country":"US",
    "sg:address":"405 Willowbrook Dr",
    "sg:city":"Richfield",
    "sg:classifiers":[
        {
            "category":"Building & Trades",
            "subcategory":"Cleaning & Sanitation",
            "type":"Services"
        }
    ],
    "sg:phone":"+1 435 896 0187",
    "sg:postcode":"84701",
    "sg:province":"UT",
    "sg:tags":[
        "maintenance"
    ],
    "wof:name":"Chimney Rock Entertainment",
    "wof:placetype":"venue"
},
  "geometry": {"coordinates":[-112.09136599999999,38.781718],"type":"Point"}
}