{
  "type": "Feature",
  "properties": {
    "iso:country":"US",
    "sg:address":"608 W 9320 S",
    "sg:city":"Sandy",
    "sg:classifiers":[
        {
            "category":"Manufacturing",
            "subcategory":"Printing",
            "type":"Manufacturing & Wholesale Goods"
        }
    ],
    "sg:phone":"+1 801 553 1101",
    "sg:postcode":"84070",
    "sg:province":"UT",
    "sg:tags":[
        "multimedia"
    ],
    "sg:website":"www.verite.com",
    "wof:name":"Verite' Multimedia",
    "wof:placetype":"venue"
},
  "geometry": {"coordinates":[-111.90735599999999,40.582113],"type":"Point"}
}