{
  "type": "Feature",
  "properties": {
    "iso:country":"US",
    "sg:address":"587 N 560 W",
    "sg:city":"Santaquin",
    "sg:classifiers":[
        {
            "category":"Wholesale",
            "subcategory":"Farm Supplies",
            "type":"Manufacturing & Wholesale Goods"
        }
    ],
    "sg:phone":"+1 801 754 0170",
    "sg:postcode":"84655",
    "sg:province":"UT",
    "wof:name":"Burningham Feed",
    "wof:placetype":"venue"
},
  "geometry": {"coordinates":[-111.797011,39.985454],"type":"Point"}
}