{
  "type": "Feature",
  "properties": {
    "iso:country":"US",
    "sg:address":"665 N 100 E",
    "sg:city":"Cedar City",
    "sg:classifiers":[
        {
            "category":"Government",
            "subcategory":"Office",
            "type":"Public Place"
        }
    ],
    "sg:phone":"+1 435 586 1122",
    "sg:postcode":"84720",
    "sg:province":"UT",
    "wof:name":"Paiute Indian Housing Auth",
    "wof:placetype":"venue"
},
  "geometry": {"coordinates":[-113.060339,37.688778],"type":"Point"}
}