{
  "type": "Feature",
  "properties": {
    "iso:country":"US",
    "sg:address":"424 Marina Cir",
    "sg:city":"Lehi",
    "sg:classifiers":[
        {
            "category":"Professional",
            "subcategory":"Detective & Security Services",
            "type":"Services"
        }
    ],
    "sg:phone":"+1 801 766 9444",
    "sg:postcode":"84045",
    "sg:province":"UT",
    "sg:tags":[
        "private",
        "investigator"
    ],
    "wof:name":"David L Fuehrer & Associates",
    "wof:placetype":"venue"
},
  "geometry": {"coordinates":[-111.90452999999999,40.350915],"type":"Point"}
}