{
  "type": "Feature",
  "properties": {
    "iso:country":"US",
    "sg:address":"3803 S Market St",
    "sg:city":"Salt Lake City",
    "sg:classifiers":[
        {
            "category":"Building & Trades",
            "subcategory":"Electrical",
            "type":"Services"
        }
    ],
    "sg:phone":"+1 801 982 9209",
    "sg:postcode":"84119",
    "sg:province":"UT",
    "sg:tags":[
        "electrical",
        "contractor"
    ],
    "wof:name":"Identity Communications",
    "wof:placetype":"venue"
},
  "geometry": {"coordinates":[-111.959675,40.689138],"type":"Point"}
}