{
  "type": "Feature",
  "properties": {
    "iso:country":"US",
    "sg:address":"470 E 1100 N",
    "sg:city":"North Salt Lake",
    "sg:classifiers":[
        {
            "category":"Banks & Credit Unions",
            "subcategory":"Bank",
            "type":"Services"
        }
    ],
    "sg:phone":"+1 801 295 8333",
    "sg:postcode":"84054",
    "sg:province":"UT",
    "sg:tags":[
        "loan"
    ],
    "wof:name":"Advance Til Payday",
    "wof:placetype":"venue"
},
  "geometry": {"coordinates":[-111.899058,40.861447],"type":"Point"}
}