{
  "type": "Feature",
  "properties": {
    "iso:country":"US",
    "sg:address":"5789 Ballerina Way",
    "sg:city":"Riverton",
    "sg:classifiers":[
        {
            "category":"Building & Trades",
            "subcategory":"Landscaping Services",
            "type":"Services"
        }
    ],
    "sg:phone":"+1 801 254 9349",
    "sg:postcode":"84096",
    "sg:province":"UT",
    "wof:name":"Santas Tree Helper",
    "wof:placetype":"venue"
},
  "geometry": {"coordinates":[-112.030586,40.506226],"type":"Point"}
}