{
  "type": "Feature",
  "properties": {
    "iso:country":"US",
    "sg:address":"3601 Yosemite Dr",
    "sg:city":"Salt Lake City",
    "sg:classifiers":[
        {
            "category":"Home & Garden",
            "subcategory":"Hardware",
            "type":"Retail Goods"
        }
    ],
    "sg:phone":"+1 801 474 0053",
    "sg:postcode":"84109",
    "sg:province":"UT",
    "wof:name":"Eye On Hardware Inc",
    "wof:placetype":"venue"
},
  "geometry": {"coordinates":[-111.79351699999999,40.701875],"type":"Point"}
}