{
  "type": "Feature",
  "properties": {
    "iso:country":"US",
    "sg:address":"2007 S 300 W",
    "sg:city":"Salt Lake City",
    "sg:classifiers":[
        {
            "category":"Manufacturing",
            "subcategory":"Food",
            "type":"Manufacturing & Wholesale Goods"
        }
    ],
    "sg:phone":"+1 801 484 1431",
    "sg:postcode":"84115",
    "sg:province":"UT",
    "sg:tags":[
        "preparation",
        "mfg",
        "potato"
    ],
    "wof:name":"Manuels Fine Foods",
    "wof:placetype":"venue"
},
  "geometry": {"coordinates":[-111.89963400000001,40.725545],"type":"Point"}
}