{
  "type": "Feature",
  "properties": {
    "iso:country":"US",
    "sg:address":"11840 S 1300 W",
    "sg:city":"Riverton",
    "sg:classifiers":[
        {
            "category":"Wholesale",
            "subcategory":"Auto Parts",
            "type":"Manufacturing & Wholesale Goods"
        },
        {
            "category":"Manufacturing",
            "subcategory":"Motor Vehicles & Parts",
            "type":"Manufacturing & Wholesale Goods"
        }
    ],
    "sg:phone":"+1 801 254 7394",
    "sg:postcode":"84065",
    "sg:province":"UT",
    "sg:tags":[
        "equipment",
        "truck",
        "supply"
    ],
    "wof:name":"Luverne Truck Equipment Inc",
    "wof:placetype":"venue"
},
  "geometry": {"coordinates":[-111.929215,40.535967],"type":"Point"}
}