{
  "type": "Feature",
  "properties": {
    "iso:country":"US",
    "sg:address":"955 W Antelope Dr",
    "sg:city":"Layton",
    "sg:classifiers":[
        {
            "category":"Banks & Credit Unions",
            "subcategory":"Bank",
            "type":"Services"
        }
    ],
    "sg:phone":"+1 801 776 4212",
    "sg:postcode":"84041",
    "sg:province":"UT",
    "sg:tags":[
        "mortgage"
    ],
    "wof:name":"Mountain America Credit Union",
    "wof:placetype":"venue"
},
  "geometry": {"coordinates":[-111.981109,41.089111],"type":"Point"}
}