{
  "type": "Feature",
  "properties": {
    "iso:country":"US",
    "sg:address":"11585 S State St",
    "sg:city":"Draper",
    "sg:classifiers":[
        {
            "category":"Communications",
            "subcategory":"Film & Video Production",
            "type":"Services"
        }
    ],
    "sg:phone":"+1 801 571 0174",
    "sg:postcode":"84020",
    "sg:province":"UT",
    "sg:tags":[
        "taping"
    ],
    "wof:name":"Mov'n Pictures",
    "wof:placetype":"venue"
},
  "geometry": {"coordinates":[-111.891154,40.543247],"type":"Point"}
}