{
  "type": "Feature",
  "properties": {
    "iso:country":"US",
    "sg:address":"180 N Main St",
    "sg:city":"Smithfield",
    "sg:classifiers":[
        {
            "category":"Restaurant",
            "type":"Food & Drink"
        }
    ],
    "sg:phone":"+1 435 563 3477",
    "sg:postcode":"84335",
    "sg:province":"UT",
    "sg:tags":[
        "eating"
    ],
    "wof:name":"McDonalds",
    "wof:placetype":"venue"
},
  "geometry": {"coordinates":[-111.832639,41.838595],"type":"Point"}
}