{
  "type": "Feature",
  "properties": {
    "iso:country":"US",
    "sg:address":"1189 S Jones Rd",
    "sg:city":"Monroe",
    "sg:classifiers":[
        {
            "category":"Retail",
            "subcategory":"Auto Rental",
            "type":"Services"
        }
    ],
    "sg:phone":"+1 435 527 3447",
    "sg:postcode":"84754",
    "sg:province":"UT",
    "sg:tags":[
        "utility",
        "recreational",
        "leasing",
        "trailer",
        "vehicle"
    ],
    "wof:name":"Rent Your Fun Rv Rentals",
    "wof:placetype":"venue"
},
  "geometry": {"coordinates":[-112.129555,38.613385],"type":"Point"}
}