{
  "type": "Feature",
  "properties": {
    "iso:country":"US",
    "sg:address":"3080 N Fairfield Rd",
    "sg:city":"Layton",
    "sg:classifiers":[
        {
            "category":"Building & Trades",
            "subcategory":"Construction",
            "type":"Services"
        }
    ],
    "sg:phone":"+1 801 771 4164",
    "sg:postcode":"84041",
    "sg:province":"UT",
    "sg:tags":[
        "home",
        "builder"
    ],
    "wof:name":"Buckley Homes Inc",
    "wof:placetype":"venue"
},
  "geometry": {"coordinates":[-111.94995,41.104038],"type":"Point"}
}