{
  "type": "Feature",
  "properties": {
    "iso:country":"US",
    "sg:address":"1717 W 270 S",
    "sg:city":"Provo",
    "sg:classifiers":[
        {
            "category":"Building & Trades",
            "subcategory":"Plumbing",
            "type":"Services"
        }
    ],
    "sg:phone":"+1 801 374 6773",
    "sg:postcode":"84601",
    "sg:province":"UT",
    "sg:tags":[
        "contractor"
    ],
    "wof:name":"Jensen",
    "wof:placetype":"venue"
},
  "geometry": {"coordinates":[-111.689694,40.229754],"type":"Point"}
}