{
  "type": "Feature",
  "properties": {
    "iso:country":"US",
    "sg:address":"441 E 500 N",
    "sg:city":"Centerville",
    "sg:classifiers":[
        {
            "category":"Retail",
            "subcategory":"Repair Shop",
            "type":"Services"
        }
    ],
    "sg:phone":"+1 801 748 2488",
    "sg:postcode":"84014",
    "sg:province":"UT",
    "sg:tags":[
        "contractor"
    ],
    "wof:name":"Advanced Outdoor Power",
    "wof:placetype":"venue"
},
  "geometry": {"coordinates":[-111.87124900000001,40.922505],"type":"Point"}
}