{
  "type": "Feature",
  "properties": {
    "iso:country":"US",
    "sg:address":"1305 N 1000 W",
    "sg:city":"Logan",
    "sg:classifiers":[
        {
            "category":"Professional",
            "subcategory":"Business Services",
            "type":"Services"
        },
        {
            "category":"Manufacturing",
            "subcategory":"Electronics",
            "type":"Manufacturing & Wholesale Goods"
        }
    ],
    "sg:phone":"+1 435 752 4301",
    "sg:postcode":"84321",
    "sg:province":"UT",
    "sg:tags":[
        "optical",
        "component",
        "devices",
        "mfg"
    ],
    "wof:name":"Wasatch Photonics Inc",
    "wof:placetype":"venue"
},
  "geometry": {"coordinates":[-111.859048,41.751461],"type":"Point"}
}