{
  "type": "Feature",
  "properties": {
    "iso:country":"US",
    "sg:address":"409 Main St",
    "sg:city":"Dove Creek",
    "sg:classifiers":[
        {
            "category":"Government",
            "subcategory":"Police Station",
            "type":"Public Place"
        }
    ],
    "sg:phone":"+1 970 677 2257",
    "sg:postcode":"81324",
    "sg:province":"UT",
    "sg:tags":[
        "sheriff"
    ],
    "wof:name":"Dolores County Sheriff",
    "wof:placetype":"venue"
},
  "geometry": {"coordinates":[-108.90388799999999,37.76765],"type":"Point"}
}