{
  "type": "Feature",
  "properties": {
    "iso:country":"US",
    "sg:address":"409 E 7500 S",
    "sg:city":"Midvale",
    "sg:classifiers":[
        {
            "category":"Personal",
            "subcategory":"Beauty Salon",
            "type":"Services"
        }
    ],
    "sg:phone":"+1 801 566 9171",
    "sg:postcode":"84047",
    "sg:province":"UT",
    "sg:tags":[
        "shop"
    ],
    "wof:name":"Abravane' Salon",
    "wof:placetype":"venue"
},
  "geometry": {"coordinates":[-111.88079999999999,40.615133],"type":"Point"}
}