{
  "type": "Feature",
  "properties": {
    "iso:country":"US",
    "sg:address":"6699 Landmark Dr",
    "sg:city":"Park City",
    "sg:classifiers":[
        {
            "category":"Food & Beverages",
            "subcategory":"Bakery",
            "type":"Retail Goods"
        }
    ],
    "sg:phone":"+1 435 940 1200",
    "sg:postcode":"84098",
    "sg:province":"UT",
    "sg:tags":[
        "cookie",
        "cracker"
    ],
    "wof:name":"Mrs Field's Original Cookies",
    "wof:placetype":"venue"
},
  "geometry": {"coordinates":[-111.550138,40.730212],"type":"Point"}
}