{
  "type": "Feature",
  "properties": {
    "iso:country":"US",
    "sg:address":"4089 Riverdale Rd",
    "sg:city":"Ogden",
    "sg:classifiers":[
        {
            "category":"Banks & Credit Unions",
            "subcategory":"Bank",
            "type":"Services"
        }
    ],
    "sg:phone":"+1 801 399 3336",
    "sg:postcode":"84405",
    "sg:province":"UT",
    "sg:tags":[
        "consumer",
        "finance"
    ],
    "wof:name":"American General Finance Corp",
    "wof:placetype":"venue"
},
  "geometry": {"coordinates":[-111.983098,41.188893],"type":"Point"}
}