{
  "type": "Feature",
  "properties": {
    "iso:country":"US",
    "sg:address":"430 E South Temple",
    "sg:city":"Salt Lake City",
    "sg:classifiers":[
        {
            "category":"Personal",
            "subcategory":"Beauty Salon",
            "type":"Services"
        }
    ],
    "sg:phone":"+1 801 355 4247",
    "sg:postcode":"84111",
    "sg:province":"UT",
    "sg:tags":[
        "shop"
    ],
    "wof:name":"High Tech Hair and Nails",
    "wof:placetype":"venue"
},
  "geometry": {"coordinates":[-111.87964100000001,40.769352],"type":"Point"}
}