{
  "type": "Feature",
  "properties": {
    "iso:country":"US",
    "sg:address":"11451 S 700 E",
    "sg:city":"Draper",
    "sg:classifiers":[
        {
            "category":"Banks & Credit Unions",
            "subcategory":"Bank",
            "type":"Services"
        }
    ],
    "sg:phone":"+1 801 576 9898",
    "sg:postcode":"84020",
    "sg:province":"UT",
    "sg:tags":[
        "mortgage",
        "loan",
        "broker",
        "real estate"
    ],
    "wof:name":"Cobblestone Mortgage LLC",
    "wof:placetype":"venue"
},
  "geometry": {"coordinates":[-111.87154,40.54173],"type":"Point"}
}