{
  "type": "Feature",
  "properties": {
    "iso:country":"US",
    "sg:address":"5974 Impressions Dr",
    "sg:city":"Salt Lake City",
    "sg:classifiers":[
        {
            "category":"Insurance",
            "subcategory":"Insurance Agent",
            "type":"Services"
        }
    ],
    "sg:phone":"+1 801 969 2888",
    "sg:postcode":"84118",
    "sg:province":"UT",
    "wof:name":"Wright Insurance Agency The",
    "wof:placetype":"venue"
},
  "geometry": {"coordinates":[-112.015631,40.642496],"type":"Point"}
}