{
  "type": "Feature",
  "properties": {
    "iso:country":"US",
    "sg:address":"750 S 650 West St",
    "sg:city":"Provo",
    "sg:classifiers":[
        {
            "category":"Shopping",
            "subcategory":"Clothing, Apparel, & Fashions",
            "type":"Retail Goods"
        }
    ],
    "sg:phone":"+1 801 377 3034",
    "sg:postcode":"84601",
    "sg:province":"UT",
    "sg:tags":[
        "family"
    ],
    "wof:name":"Kriel Clothing Company",
    "wof:placetype":"venue"
},
  "geometry": {"coordinates":[-111.670255,40.224748],"type":"Point"}
}