{
  "type": "Feature",
  "properties": {
    "iso:country":"US",
    "sg:address":"202 E 3300 S",
    "sg:city":"Salt Lake City",
    "sg:classifiers":[
        {
            "category":"Retail",
            "subcategory":"Laundry & Dry Cleaning",
            "type":"Services"
        }
    ],
    "sg:phone":"+1 801 467 3922",
    "sg:postcode":"84115",
    "sg:province":"UT",
    "sg:tags":[
        "drycleaning",
        "plant",
        "coin",
        "power"
    ],
    "wof:name":"Century Laundry",
    "wof:placetype":"venue"
},
  "geometry": {"coordinates":[-111.88381699999999,40.699784],"type":"Point"}
}