{
  "type": "Feature",
  "properties": {
    "iso:country":"US",
    "sg:address":"326 E Main St",
    "sg:city":"Grantsville",
    "sg:classifiers":[
        {
            "category":"Real Estate",
            "subcategory":"Real Estate Agent",
            "type":"Services"
        }
    ],
    "sg:phone":"+1 435 884 0555",
    "sg:postcode":"84029",
    "sg:province":"UT",
    "wof:name":"Choice Real Estate Svc",
    "wof:placetype":"venue"
},
  "geometry": {"coordinates":[-112.451007,40.599678],"type":"Point"}
}