{
  "type": "Feature",
  "properties": {
    "iso:country":"US",
    "sg:address":"1022 E 1st Ave",
    "sg:city":"Salt Lake City",
    "sg:classifiers":[
        {
            "category":"Banks & Credit Unions",
            "subcategory":"Financial Services",
            "type":"Services"
        }
    ],
    "sg:phone":"+1 801 364 3876",
    "sg:postcode":"84103",
    "sg:province":"UT",
    "sg:tags":[
        "investment",
        "closed"
    ],
    "wof:name":"Premium Resource Corp",
    "wof:placetype":"venue"
},
  "geometry": {"coordinates":[-111.858654,40.770483],"type":"Point"}
}