{
  "type": "Feature",
  "properties": {
    "iso:country":"US",
    "sg:address":"795 E 340 S",
    "sg:city":"American Fork",
    "sg:classifiers":[
        {
            "category":"Professional",
            "subcategory":"Advertising",
            "type":"Services"
        }
    ],
    "sg:phone":"+1 801 407 8381",
    "sg:postcode":"84003",
    "sg:province":"UT",
    "sg:tags":[
        "counselor"
    ],
    "sg:website":"www.1on1.com",
    "wof:name":"One On One Marketing",
    "wof:placetype":"venue"
},
  "geometry": {"coordinates":[-111.778559,40.370667],"type":"Point"}
}