{
  "type": "Feature",
  "properties": {
    "iso:country":"US",
    "sg:address":"2352 Fort Union Blvd",
    "sg:city":"Salt Lake City",
    "sg:classifiers":[
        {
            "category":"Personal",
            "subcategory":"Beauty Salon",
            "type":"Services"
        }
    ],
    "sg:phone":"+1 801 733 6566",
    "sg:postcode":"84121",
    "sg:province":"UT",
    "sg:tags":[
        "shop"
    ],
    "wof:name":"Deja Vu Salon",
    "wof:placetype":"venue"
},
  "geometry": {"coordinates":[-111.821686,40.623893],"type":"Point"}
}