{
  "type": "Feature",
  "properties": {
    "iso:country":"US",
    "sg:address":"412 W 10th N",
    "sg:city":"Logan",
    "sg:classifiers":[
        {
            "category":"Manufacturing",
            "subcategory":"Chemicals & Compounds",
            "type":"Manufacturing & Wholesale Goods"
        }
    ],
    "sg:phone":"+1 435 752 4244",
    "sg:postcode":"84337",
    "sg:province":"UT",
    "sg:tags":[
        "desert",
        "ice",
        "mfg"
    ],
    "wof:name":"Borden Chemical Inc",
    "wof:placetype":"venue"
},
  "geometry": {"coordinates":[-112.169016,41.726313],"type":"Point"}
}