{
  "type": "Feature",
  "properties": {
    "iso:country":"US",
    "sg:address":"490 S 500 E",
    "sg:city":"Kaysville",
    "sg:classifiers":[
        {
            "category":"Education",
            "subcategory":"School",
            "type":"Public Place"
        }
    ],
    "sg:phone":"+1 801 402 0450",
    "sg:postcode":"84037",
    "sg:province":"UT",
    "wof:name":"Mountain High 730",
    "wof:placetype":"venue"
},
  "geometry": {"coordinates":[-111.928164,41.027066],"type":"Point"}
}