{
  "type": "Feature",
  "properties": {
    "iso:country":"US",
    "sg:address":"1102 N 1250 W",
    "sg:city":"Layton",
    "sg:classifiers":[
        {
            "category":"Shopping",
            "subcategory":"Catalog Store",
            "type":"Retail Goods"
        }
    ],
    "sg:phone":"+1 801 543 1321",
    "sg:postcode":"84041",
    "sg:province":"UT",
    "sg:tags":[
        "equipment",
        "physical",
        "fitness"
    ],
    "wof:name":"Donnas Fitness",
    "wof:placetype":"venue"
},
  "geometry": {"coordinates":[-111.988714,41.075711],"type":"Point"}
}