{
  "type": "Feature",
  "properties": {
    "iso:country":"US",
    "sg:address":"2003 Texas St",
    "sg:city":"Salt Lake City",
    "sg:classifiers":[
        {
            "category":"Building & Trades",
            "subcategory":"Construction",
            "type":"Services"
        }
    ],
    "sg:phone":"+1 801 487 0456",
    "sg:postcode":"84108",
    "sg:province":"UT",
    "sg:tags":[
        "house"
    ],
    "wof:name":"Al Construction Svcs",
    "wof:placetype":"venue"
},
  "geometry": {"coordinates":[-111.821971,40.726078],"type":"Point"}
}