{
  "type": "Feature",
  "properties": {
    "iso:country":"US",
    "sg:address":"125 E State Rd",
    "sg:city":"Pleasant Grove",
    "sg:classifiers":[
        {
            "category":"Coffee & Tea",
            "type":"Food & Drink"
        },
        {
            "category":"Food & Beverages",
            "subcategory":"Bakery",
            "type":"Retail Goods"
        },
        {
            "category":"Bakery",
            "type":"Food & Drink"
        },
        {
            "category":"Donuts",
            "type":"Food & Drink"
        }
    ],
    "sg:menulink":"http://www.allmenus.com/ut/american-fork-pleasant-grove/230941-daylight-donuts/menu/",
    "sg:phone":"+1 801 785 7922",
    "sg:postcode":"84062",
    "sg:province":"UT",
    "sg:tags":[
        "tea",
        "coffee",
        "bakery",
        "american",
        "pastry"
    ],
    "wof:name":"Daylight Donuts",
    "wof:placetype":"venue"
},
  "geometry": {"coordinates":[-111.738681,40.357716],"type":"Point"}
}