{
  "type": "Feature",
  "properties": {
    "iso:country":"US",
    "sg:address":"118 W Parrish Ln",
    "sg:city":"Centerville",
    "sg:classifiers":[
        {
            "category":"Communications",
            "type":"Services"
        },
        {
            "category":"Wholesale",
            "subcategory":"Computers",
            "type":"Manufacturing & Wholesale Goods"
        }
    ],
    "sg:phone":"+1 801 294 3213",
    "sg:postcode":"84014",
    "sg:province":"UT",
    "sg:tags":[
        "web",
        "design"
    ],
    "sg:website":"www.elitepowerpc.com",
    "wof:name":"Elite Power PC",
    "wof:placetype":"venue"
},
  "geometry": {"coordinates":[-111.880812,40.921637],"type":"Point"}
}