{
  "type": "Feature",
  "properties": {
    "iso:country":"US",
    "sg:address":"86 S 100 W",
    "sg:city":"Hyrum",
    "sg:classifiers":[
        {
            "category":"Building & Trades",
            "subcategory":"Construction",
            "type":"Services"
        }
    ],
    "sg:phone":"+1 435 245 5119",
    "sg:postcode":"84319",
    "sg:province":"UT",
    "sg:tags":[
        "residential"
    ],
    "wof:name":"Design Master Home",
    "wof:placetype":"venue"
},
  "geometry": {"coordinates":[-111.85816,41.632275],"type":"Point"}
}