{
  "type": "Feature",
  "properties": {
    "iso:country":"US",
    "sg:address":"1362 Princeton Ave",
    "sg:city":"Salt Lake City",
    "sg:classifiers":[
        {
            "category":"Professional",
            "subcategory":"Computer Services",
            "type":"Services"
        }
    ],
    "sg:phone":"+1 801 867 9211",
    "sg:postcode":"84105",
    "sg:province":"UT",
    "sg:tags":[
        "related"
    ],
    "wof:name":"Collerannet",
    "wof:placetype":"venue"
},
  "geometry": {"coordinates":[-111.851838,40.743019],"type":"Point"}
}