{
  "type": "Feature",
  "properties": {
    "iso:country":"US",
    "sg:address":"366 E 1100 S",
    "sg:city":"Mapleton",
    "sg:classifiers":[
        {
            "category":"Insurance",
            "subcategory":"Hazard Insurance",
            "type":"Services"
        }
    ],
    "sg:phone":"+1 801 489 7288",
    "sg:postcode":"84664",
    "sg:province":"UT",
    "sg:tags":[
        "warranty",
        "home",
        "plan"
    ],
    "sg:website":"www.easwarranty.com",
    "wof:name":"Elite Auto Svc Inc",
    "wof:placetype":"venue"
},
  "geometry": {"coordinates":[-111.572193,40.120353],"type":"Point"}
}