{
  "type": "Feature",
  "properties": {
    "iso:country":"US",
    "sg:address":"780 S 900 W",
    "sg:city":"Salt Lake City",
    "sg:classifiers":[
        {
            "category":"Food & Beverages",
            "subcategory":"Groceries & Convenience Stores",
            "type":"Retail Goods"
        }
    ],
    "sg:phone":"+1 801 364 9948",
    "sg:postcode":"84104",
    "sg:province":"UT",
    "wof:name":"7-Eleven",
    "wof:placetype":"venue"
},
  "geometry": {"coordinates":[-111.916895,40.753708],"type":"Point"}
}