{
  "type": "Feature",
  "properties": {
    "iso:country":"US",
    "sg:address":"12141 Vahe St",
    "sg:city":"Draper",
    "sg:classifiers":[
        {
            "category":"Building & Trades",
            "subcategory":"Construction",
            "type":"Services"
        }
    ],
    "sg:phone":"+1 801 495 9530",
    "sg:postcode":"84020",
    "sg:province":"UT",
    "sg:tags":[
        "interior",
        "carpentry",
        "contractor"
    ],
    "wof:name":"Pat Holst Construction Inc",
    "wof:placetype":"venue"
},
  "geometry": {"coordinates":[-111.917436,40.526909],"type":"Point"}
}