{
  "type": "Feature",
  "properties": {
    "iso:country":"US",
    "sg:address":"1380 S 2500 W",
    "sg:city":"Vernal",
    "sg:classifiers":[
        {
            "category":"Autos & Motor Vehicles",
            "subcategory":"Recreational Vehicle Sales",
            "type":"Retail Goods"
        }
    ],
    "sg:phone":"+1 435 790 5099",
    "sg:postcode":"84078",
    "sg:province":"UT",
    "sg:tags":[
        "parts",
        "trailer"
    ],
    "wof:name":"Reynolds",
    "wof:placetype":"venue"
},
  "geometry": {"coordinates":[-109.57625400000001,40.435122],"type":"Point"}
}