{
  "type": "Feature",
  "properties": {
    "iso:country":"US",
    "sg:address":"165 S Main St",
    "sg:city":"Payson",
    "sg:classifiers":[
        {
            "category":"Manufacturing",
            "subcategory":"Musical Instruments",
            "type":"Manufacturing & Wholesale Goods"
        }
    ],
    "sg:phone":"+1 801 465 0887",
    "sg:postcode":"84651",
    "sg:province":"UT",
    "sg:tags":[
        "mfg"
    ],
    "wof:name":"Harpvision",
    "wof:placetype":"venue"
},
  "geometry": {"coordinates":[-111.732218,40.041569],"type":"Point"}
}