{
  "type": "Feature",
  "properties": {
    "iso:country":"US",
    "sg:address":"183 S Main St",
    "sg:city":"Hurricane",
    "sg:classifiers":[
        {
            "category":"Building & Trades",
            "subcategory":"Construction",
            "type":"Services"
        }
    ],
    "sg:phone":"+1 435 635 3150",
    "sg:postcode":"84737",
    "sg:province":"UT",
    "sg:tags":[
        "contractor"
    ],
    "wof:name":"Southern Utah Roofing Inc",
    "wof:placetype":"venue"
},
  "geometry": {"coordinates":[-113.28805199999999,37.173848],"type":"Point"}
}