{
  "type": "Feature",
  "properties": {
    "iso:country":"US",
    "sg:address":"1433 E 1140 N",
    "sg:city":"Logan",
    "sg:classifiers":[
        {
            "category":"Banks & Credit Unions",
            "subcategory":"Financial Services",
            "type":"Services"
        }
    ],
    "sg:phone":"+1 435 752 8942",
    "sg:postcode":"84341",
    "sg:province":"UT",
    "sg:tags":[
        "investor"
    ],
    "wof:name":"Thornley Fmly Investments LLC",
    "wof:placetype":"venue"
},
  "geometry": {"coordinates":[-111.797715,41.751999],"type":"Point"}
}