{
  "type": "Feature",
  "properties": {
    "iso:country":"US",
    "sg:address":"639 W Erda Way",
    "sg:city":"Tooele",
    "sg:classifiers":[
        {
            "category":"Home & Garden",
            "subcategory":"Building Materials",
            "type":"Retail Goods"
        }
    ],
    "sg:phone":"+1 801 261 0597",
    "sg:postcode":"84074",
    "sg:province":"UT",
    "sg:tags":[
        "door",
        "gate",
        "operating",
        "devices"
    ],
    "wof:name":"Toone Door Co",
    "wof:placetype":"venue"
},
  "geometry": {"coordinates":[-112.31876699999999,40.601541],"type":"Point"}
}