{
  "type": "Feature",
  "properties": {
    "iso:country":"US",
    "sg:address":"1277 W 12600 S",
    "sg:city":"Riverton",
    "sg:classifiers":[
        {
            "category":"Wholesale",
            "subcategory":"Machinery & Supplies",
            "type":"Manufacturing & Wholesale Goods"
        },
        {
            "category":"Building & Trades",
            "subcategory":"Equipment Rental",
            "type":"Services"
        }
    ],
    "sg:phone":"+1 801 561 9299",
    "sg:postcode":"84065",
    "sg:province":"UT",
    "sg:tags":[
        "heavy",
        "construction",
        "industrial",
        "contractor"
    ],
    "wof:name":"Banks Equipment",
    "wof:placetype":"venue"
},
  "geometry": {"coordinates":[-111.926526,40.522263],"type":"Point"}
}