{
  "type": "Feature",
  "properties": {
    "iso:country":"US",
    "sg:address":"2587 Nottingham Way",
    "sg:city":"Salt Lake City",
    "sg:classifiers":[
        {
            "category":"Recreation",
            "type":"Entertainment"
        }
    ],
    "sg:phone":"+1 801 581 9438",
    "sg:postcode":"84108",
    "sg:province":"UT",
    "wof:name":"Stretch N Grow of Utah Inc",
    "wof:placetype":"venue"
},
  "geometry": {"coordinates":[-111.81575100000001,40.740812],"type":"Point"}
}