{
  "type": "Feature",
  "properties": {
    "iso:country":"US",
    "sg:address":"9501 W 900 S",
    "sg:city":"Ogden",
    "sg:classifiers":[
        {
            "category":"Home & Garden",
            "subcategory":"Building Materials",
            "type":"Retail Goods"
        }
    ],
    "sg:phone":"+1 801 731 8663",
    "sg:postcode":"84404",
    "sg:province":"UT",
    "wof:name":"Jewett-Cameron Lumber Corp",
    "wof:placetype":"venue"
},
  "geometry": {"coordinates":[-112.212734,41.250038],"type":"Point"}
}