{
  "type": "Feature",
  "properties": {
    "iso:country":"US",
    "sg:address":"2855 Golden Meadows Dr",
    "sg:city":"Riverton",
    "sg:classifiers":[
        {
            "category":"Building & Trades",
            "subcategory":"Construction",
            "type":"Services"
        }
    ],
    "sg:phone":"+1 801 254 8892",
    "sg:postcode":"84065",
    "sg:province":"UT",
    "sg:tags":[
        "house"
    ],
    "wof:name":"Bronson Construction Inc",
    "wof:placetype":"venue"
},
  "geometry": {"coordinates":[-111.960534,40.512671],"type":"Point"}
}