{
  "type": "Feature",
  "properties": {
    "iso:country":"US",
    "sg:address":"1955 W 4250 S",
    "sg:city":"Roy",
    "sg:classifiers":[
        {
            "category":"Building & Trades",
            "subcategory":"Construction",
            "type":"Services"
        }
    ],
    "sg:phone":"+1 435 723 4026",
    "sg:postcode":"84067",
    "sg:province":"UT",
    "sg:tags":[
        "resurfacing",
        "laying",
        "refinishing",
        "floor"
    ],
    "wof:name":"Tufco West Ind Flooring Inc",
    "wof:placetype":"venue"
},
  "geometry": {"coordinates":[-112.029765,41.185958],"type":"Point"}
}