{
  "type": "Feature",
  "properties": {
    "iso:country":"US",
    "sg:address":"37 E Central Ave",
    "sg:city":"Murray",
    "sg:classifiers":[
        {
            "category":"Autos & Motor Vehicles",
            "subcategory":"Automobile Sales",
            "type":"Retail Goods"
        }
    ],
    "sg:phone":"+1 801 262 8600",
    "sg:postcode":"84107",
    "sg:province":"UT",
    "sg:tags":[
        "truck"
    ],
    "wof:name":"Moffat Truck Sales",
    "wof:placetype":"venue"
},
  "geometry": {"coordinates":[-111.889218,40.68223],"type":"Point"}
}