{
  "type": "Feature",
  "properties": {
    "iso:country":"US",
    "sg:address":"1012 Bradsley Pl",
    "sg:city":"Salt Lake City",
    "sg:classifiers":[
        {
            "category":"Professional",
            "type":"Services"
        }
    ],
    "sg:phone":"+1 801 974 3033",
    "sg:postcode":"84119",
    "sg:province":"UT",
    "sg:tags":[
        "establishment"
    ],
    "wof:name":"Great American Traveler",
    "wof:placetype":"venue"
},
  "geometry": {"coordinates":[-111.919436,40.71705],"type":"Point"}
}