{
  "type": "Feature",
  "properties": {
    "iso:country":"US",
    "sg:address":"85 S Main St",
    "sg:city":"Fillmore",
    "sg:classifiers":[
        {
            "category":"Food & Beverages",
            "subcategory":"Liquor & Beverages",
            "type":"Retail Goods"
        }
    ],
    "sg:phone":"+1 435 743 5788",
    "sg:postcode":"84631",
    "sg:province":"UT",
    "sg:tags":[
        "alcoholic"
    ],
    "wof:name":"Fillmore Package Agency",
    "wof:placetype":"venue"
},
  "geometry": {"coordinates":[-112.323554,38.967078],"type":"Point"}
}