{
  "type": "Feature",
  "properties": {
    "iso:country":"US",
    "sg:address":"3010 W 500 S",
    "sg:city":"Salt Lake City",
    "sg:classifiers":[
        {
            "category":"Manufacturing",
            "subcategory":"Metals",
            "type":"Manufacturing & Wholesale Goods"
        }
    ],
    "sg:phone":"+1 801 746 2900",
    "sg:postcode":"84104",
    "sg:province":"UT",
    "sg:tags":[
        "product",
        "primary",
        "mfg"
    ],
    "wof:name":"American Eagle Welding Inc",
    "wof:placetype":"venue"
},
  "geometry": {"coordinates":[-111.962334,40.758488],"type":"Point"}
}