{
  "type": "Feature",
  "properties": {
    "iso:country":"US",
    "sg:address":"802 N 2200 W",
    "sg:city":"Salt Lake City",
    "sg:classifiers":[
        {
            "category":"Social Services",
            "subcategory":"Child Care",
            "type":"Services"
        }
    ],
    "sg:phone":"+1 801 536 0993",
    "sg:postcode":"84116",
    "sg:province":"UT",
    "wof:name":"Puddle Jumpers",
    "wof:placetype":"venue"
},
  "geometry": {"coordinates":[-111.953475,40.785754],"type":"Point"}
}