{
  "type": "Feature",
  "properties": {
    "iso:country":"US",
    "sg:address":"2307 N Hill Field Rd Suite 101",
    "sg:city":"Layton",
    "sg:classifiers":[
        {
            "category":"Health Services",
            "subcategory":"Dentist",
            "type":"Services"
        }
    ],
    "sg:phone":"+1 801 773 5285",
    "sg:postcode":"84041",
    "sg:province":"UT",
    "sg:tags":[
        "dentists-cosmetic",
        "dentists-pediatric",
        "dentistry"
    ],
    "sg:website":"http://drbrough.com",
    "wof:name":"Dr. Brough Family & Cosmetic Dentistry",
    "wof:placetype":"venue"
},
  "geometry": {"coordinates":[-111.973449,41.093583],"type":"Point"}
}