{
  "type": "Feature",
  "properties": {
    "iso:country":"US",
    "sg:address":"195 Meadowlark Dr",
    "sg:city":"Alpine",
    "sg:classifiers":[
        {
            "category":"Professional",
            "subcategory":"Management & Consulting",
            "type":"Services"
        }
    ],
    "sg:phone":"+1 801 492 7820",
    "sg:postcode":"84004",
    "sg:province":"UT",
    "sg:tags":[
        "marketing",
        "consultant"
    ],
    "wof:name":"FMT Inc",
    "wof:placetype":"venue"
},
  "geometry": {"coordinates":[-111.780456,40.466339],"type":"Point"}
}