{
  "type": "Feature",
  "properties": {
    "iso:country":"US",
    "sg:address":"8579 Elk Mesa Rd",
    "sg:city":"Magna",
    "sg:classifiers":[
        {
            "category":"Retail",
            "subcategory":"Repair Shop",
            "type":"Services"
        }
    ],
    "sg:phone":"+1 801 566 9229",
    "sg:postcode":"84044",
    "sg:province":"UT",
    "sg:tags":[
        "refrigeration"
    ],
    "wof:name":"Service Express",
    "wof:placetype":"venue"
},
  "geometry": {"coordinates":[-112.096237,40.69347],"type":"Point"}
}