{
  "type": "Feature",
  "properties": {
    "iso:country":"US",
    "sg:address":"2744 Willow Hills Dr",
    "sg:city":"Sandy",
    "sg:classifiers":[
        {
            "category":"Professional",
            "subcategory":"Business Services",
            "type":"Services"
        }
    ],
    "sg:phone":"+1 801 947 1723",
    "sg:postcode":"84093",
    "sg:province":"UT",
    "sg:tags":[
        "appraiser"
    ],
    "wof:name":"RDH Appraisal",
    "wof:placetype":"venue"
},
  "geometry": {"coordinates":[-111.81516499999999,40.58902],"type":"Point"}
}