{
  "type": "Feature",
  "properties": {
    "iso:country":"US",
    "sg:address":"1520 Kensington Ave",
    "sg:city":"Salt Lake City",
    "sg:classifiers":[
        {
            "category":"Manufacturing",
            "subcategory":"Rubber & Plastics",
            "type":"Manufacturing & Wholesale Goods"
        }
    ],
    "sg:phone":"+1 801 467 3051",
    "sg:postcode":"84105",
    "sg:province":"UT",
    "sg:tags":[
        "product",
        "fabricated",
        "mfg"
    ],
    "wof:name":"Jamison Engineering",
    "wof:placetype":"venue"
},
  "geometry": {"coordinates":[-111.845681,40.736191],"type":"Point"}
}