{
  "type": "Feature",
  "properties": {
    "iso:country":"US",
    "sg:address":"415 Aspen Dr",
    "sg:city":"Park City",
    "sg:classifiers":[
        {
            "category":"Organizations",
            "subcategory":"Religious Organization",
            "type":"Services"
        }
    ],
    "sg:phone":"+1 435 649 0407",
    "sg:postcode":"84098",
    "sg:province":"UT",
    "sg:tags":[
        "church"
    ],
    "wof:name":"Park City Baptist Church",
    "wof:placetype":"venue"
},
  "geometry": {"coordinates":[-111.61024,40.747494],"type":"Point"}
}