{
  "type": "Feature",
  "properties": {
    "iso:country":"US",
    "sg:address":"314 E State Rd",
    "sg:city":"Pleasant Grove",
    "sg:classifiers":[
        {
            "category":"Personal",
            "subcategory":"Beauty Salon",
            "type":"Services"
        }
    ],
    "sg:phone":"+1 801 785 3100",
    "sg:postcode":"84062",
    "sg:province":"UT",
    "wof:name":"Dollar Cuts",
    "wof:placetype":"venue"
},
  "geometry": {"coordinates":[-111.7349,40.354617],"type":"Point"}
}