{
  "type": "Feature",
  "properties": {
    "iso:country":"US",
    "sg:address":"45 N 500 E",
    "sg:city":"St George",
    "sg:classifiers":[
        {
            "category":"Home & Garden",
            "subcategory":"Household Appliances",
            "type":"Retail Goods"
        }
    ],
    "sg:phone":"+1 435 673 9671",
    "sg:postcode":"84770",
    "sg:province":"UT",
    "sg:tags":[
        "electrical",
        "furniture"
    ],
    "wof:name":"Jensens Vacuum Sew & Waterbeds",
    "wof:placetype":"venue"
},
  "geometry": {"coordinates":[-113.572757,37.109081],"type":"Point"}
}