{
  "type": "Feature",
  "properties": {
    "iso:country":"US",
    "sg:address":"8657 Highland Dr",
    "sg:city":"Sandy",
    "sg:classifiers":[
        {
            "category":"Restaurant",
            "type":"Food & Drink"
        }
    ],
    "sg:phone":"+1 801 733 9633",
    "sg:postcode":"84093",
    "sg:province":"UT",
    "wof:name":"Salsa Fiesta",
    "wof:placetype":"venue"
},
  "geometry": {"coordinates":[-111.832097,40.593841],"type":"Point"}
}