{
  "type": "Feature",
  "properties": {
    "iso:country":"US",
    "sg:address":"1082 N 500 W",
    "sg:city":"Brigham City",
    "sg:classifiers":[
        {
            "category":"Government",
            "subcategory":"Office",
            "type":"Public Place"
        }
    ],
    "sg:phone":"+1 435 723 5716",
    "sg:postcode":"84302",
    "sg:province":"UT",
    "sg:tags":[
        "village"
    ],
    "wof:name":"Brigham City City Office",
    "wof:placetype":"venue"
},
  "geometry": {"coordinates":[-112.02267999999999,41.530682],"type":"Point"}
}