{
  "type": "Feature",
  "properties": {
    "iso:country":"US",
    "sg:address":"5241 Farm Station Way",
    "sg:city":"Salt Lake City",
    "sg:classifiers":[
        {
            "category":"Professional",
            "type":"Services"
        }
    ],
    "sg:phone":"+1 801 966 3540",
    "sg:postcode":"84120",
    "sg:province":"UT",
    "wof:name":"Mc Grapx Inc",
    "wof:placetype":"venue"
},
  "geometry": {"coordinates":[-112.015832,40.689613],"type":"Point"}
}