{
  "type": "Feature",
  "properties": {
    "iso:country":"US",
    "sg:address":"332 E 11000 S",
    "sg:city":"Sandy",
    "sg:classifiers":[
        {
            "category":"Building & Trades",
            "subcategory":"Construction",
            "type":"Services"
        }
    ],
    "sg:phone":"+1 801 571 0859",
    "sg:postcode":"84070",
    "sg:province":"UT",
    "sg:tags":[
        "contractor"
    ],
    "wof:name":"Dennis Bringhurst Masonry",
    "wof:placetype":"venue"
},
  "geometry": {"coordinates":[-111.880573,40.551497],"type":"Point"}
}