{
  "type": "Feature",
  "properties": {
    "iso:country":"US",
    "sg:address":"526 W 500 N",
    "sg:city":"American Fork",
    "sg:classifiers":[
        {
            "category":"Professional",
            "subcategory":"Management & Consulting",
            "type":"Services"
        }
    ],
    "sg:phone":"+1 801 756 1994",
    "sg:postcode":"84003",
    "sg:province":"UT",
    "sg:tags":[
        "business"
    ],
    "wof:name":"Ballard Consulting Inc",
    "wof:placetype":"venue"
},
  "geometry": {"coordinates":[-111.81218200000001,40.387167],"type":"Point"}
}