{
  "type": "Feature",
  "properties": {
    "iso:country":"US",
    "sg:address":"384 N Main St",
    "sg:city":"Nephi",
    "sg:classifiers":[
        {
            "category":"Building & Trades",
            "subcategory":"Electrical",
            "type":"Services"
        }
    ],
    "sg:phone":"+1 435 623 0312",
    "sg:postcode":"84648",
    "sg:province":"UT",
    "sg:tags":[
        "electrical",
        "contractor"
    ],
    "wof:name":"Sage Electric",
    "wof:placetype":"venue"
},
  "geometry": {"coordinates":[-111.83607600000001,39.713107],"type":"Point"}
}