{
  "type": "Feature",
  "properties": {
    "iso:country":"US",
    "sg:address":"3275 N 700 W",
    "sg:city":"Ogden",
    "sg:classifiers":[
        {
            "category":"Building & Trades",
            "subcategory":"Construction",
            "type":"Services"
        }
    ],
    "sg:phone":"+1 801 745 2826",
    "sg:postcode":"84414",
    "sg:province":"UT",
    "sg:tags":[
        "general",
        "contractor"
    ],
    "wof:name":"Bridgerland Builders Inc",
    "wof:placetype":"venue"
},
  "geometry": {"coordinates":[-111.99526299999999,41.318663],"type":"Point"}
}