{
  "type": "Feature",
  "properties": {
    "iso:country":"US",
    "sg:address":"12357 S 450 E",
    "sg:city":"Draper",
    "sg:classifiers":[
        {
            "category":"Health Services",
            "subcategory":"Optometrist",
            "type":"Services"
        }
    ],
    "sg:phone":"+1 801 572 9804",
    "sg:postcode":"84020",
    "sg:province":"UT",
    "wof:name":"South Hills Family Eye Care",
    "wof:placetype":"venue"
},
  "geometry": {"coordinates":[-111.877959,40.525307],"type":"Point"}
}