{
  "type": "Feature",
  "properties": {
    "iso:country":"US",
    "sg:address":"2595 S 800 W",
    "sg:city":"Logan",
    "sg:classifiers":[
        {
            "category":"Personal",
            "subcategory":"Beauty Salon",
            "type":"Services"
        }
    ],
    "sg:phone":"+1 435 753 5159",
    "sg:postcode":"84321",
    "sg:province":"UT",
    "sg:tags":[
        "shop"
    ],
    "wof:name":"Back Door Beauty",
    "wof:placetype":"venue"
},
  "geometry": {"coordinates":[-111.852464,41.685625],"type":"Point"}
}