{
  "type": "Feature",
  "properties": {
    "iso:country":"US",
    "sg:address":"1436 E 820 N",
    "sg:city":"Orem",
    "sg:classifiers":[
        {
            "category":"Banks & Credit Unions",
            "subcategory":"Bank",
            "type":"Services"
        }
    ],
    "sg:phone":"+1 801 225 1267",
    "sg:postcode":"84097",
    "sg:province":"UT",
    "sg:tags":[
        "broker",
        "mortgage"
    ],
    "wof:name":"Investment Lending Inc",
    "wof:placetype":"venue"
},
  "geometry": {"coordinates":[-111.66092500000001,40.31303],"type":"Point"}
}