{
  "type": "Feature",
  "properties": {
    "iso:country":"US",
    "sg:address":"955 E 900 S",
    "sg:city":"Salt Lake City",
    "sg:classifiers":[
        {
            "category":"Shopping",
            "subcategory":"Musical Instruments",
            "type":"Retail Goods"
        }
    ],
    "sg:phone":"+1 801 364 7207",
    "sg:postcode":"84105",
    "sg:province":"UT",
    "wof:name":"Gary Vessel Violin Makers",
    "wof:placetype":"venue"
},
  "geometry": {"coordinates":[-111.862816,40.749869],"type":"Point"}
}