{
  "type": "Feature",
  "properties": {
    "iso:country":"US",
    "sg:address":"508 Ogden Canyon",
    "sg:city":"Ogden",
    "sg:classifiers":[
        {
            "category":"Restaurant",
            "type":"Food & Drink"
        }
    ],
    "sg:phone":"+1 801 392 6775",
    "sg:postcode":"84401",
    "sg:province":"UT",
    "wof:name":"Graycliff Lodge Restaurant",
    "wof:placetype":"venue"
},
  "geometry": {"coordinates":[-111.915891,41.237305],"type":"Point"}
}