{
  "type": "Feature",
  "properties": {
    "iso:country":"US",
    "sg:address":"527 N 600 W",
    "sg:city":"Kaysville",
    "sg:classifiers":[
        {
            "category":"Building & Trades",
            "subcategory":"Construction",
            "type":"Services"
        }
    ],
    "sg:phone":"+1 801 698 1399",
    "sg:postcode":"84037",
    "sg:province":"UT",
    "sg:tags":[
        "woodworker"
    ],
    "wof:name":"R & E Woodworks",
    "wof:placetype":"venue"
},
  "geometry": {"coordinates":[-111.95001000000001,41.045439],"type":"Point"}
}