{
  "type": "Feature",
  "properties": {
    "iso:country":"US",
    "sg:address":"536 N 700 W",
    "sg:city":"North Salt Lake",
    "sg:classifiers":[
        {
            "category":"Insurance",
            "subcategory":"Health Insurance",
            "type":"Services"
        }
    ],
    "sg:phone":"+1 801 294 3126",
    "sg:postcode":"84054",
    "sg:province":"UT",
    "sg:tags":[
        "market"
    ],
    "wof:name":"A Mt Labs",
    "wof:placetype":"venue"
},
  "geometry": {"coordinates":[-111.927802,40.851671],"type":"Point"}
}