{
  "type": "Feature",
  "properties": {
    "iso:country":"US",
    "sg:address":"1436 W 14600 S",
    "sg:city":"Riverton",
    "sg:classifiers":[
        {
            "category":"Building & Trades",
            "subcategory":"Cleaning & Sanitation",
            "type":"Services"
        }
    ],
    "sg:phone":"+1 801 604 2209",
    "sg:postcode":"84065",
    "sg:province":"UT",
    "sg:tags":[
        "window"
    ],
    "wof:name":"Mr.Hovey's Window Cleaning",
    "wof:placetype":"venue"
},
  "geometry": {"coordinates":[-111.933404,40.486488],"type":"Point"}
}