{
  "type": "Feature",
  "properties": {
    "iso:country":"US",
    "sg:address":"3430 W 13175 S",
    "sg:city":"Riverton",
    "sg:classifiers":[
        {
            "category":"Professional",
            "subcategory":"Accounting & Tax Preparation",
            "type":"Services"
        }
    ],
    "sg:phone":"+1 801 253 2089",
    "sg:postcode":"84065",
    "sg:province":"UT",
    "wof:name":"Elder Tax Accounting",
    "wof:placetype":"venue"
},
  "geometry": {"coordinates":[-111.97248500000001,40.51206],"type":"Point"}
}