{
  "type": "Feature",
  "properties": {
    "iso:country":"US",
    "sg:address":"126 W 500 S",
    "sg:city":"Spanish Fork",
    "sg:classifiers":[
        {
            "category":"Home & Garden",
            "subcategory":"Furniture",
            "type":"Retail Goods"
        }
    ],
    "sg:phone":"+1 801 798 0657",
    "sg:postcode":"84660",
    "sg:province":"UT",
    "sg:tags":[
        "top",
        "counter"
    ],
    "wof:name":"Marvin Laughlin Countertops",
    "wof:placetype":"venue"
},
  "geometry": {"coordinates":[-111.658584,40.102405],"type":"Point"}
}