{
  "type": "Feature",
  "properties": {
    "iso:country":"US",
    "sg:address":"70 E 200 N",
    "sg:city":"Cedar City",
    "sg:classifiers":[
        {
            "category":"Shopping",
            "subcategory":"Bicycles & Sporting Goods",
            "type":"Retail Goods"
        }
    ],
    "sg:phone":"+1 435 586 7469",
    "sg:postcode":"84720",
    "sg:province":"UT",
    "sg:tags":[
        "equipment",
        "skateboard"
    ],
    "wof:name":"Beach Break",
    "wof:placetype":"venue"
},
  "geometry": {"coordinates":[-113.06106,37.680815],"type":"Point"}
}