{
  "type": "Feature",
  "properties": {
    "iso:country":"US",
    "sg:address":"4700 S 900 E",
    "sg:city":"Salt Lake City",
    "sg:classifiers":[
        {
            "category":"Manufacturing",
            "subcategory":"Printing",
            "type":"Manufacturing & Wholesale Goods"
        }
    ],
    "sg:phone":"+1 801 270 0280",
    "sg:postcode":"84117",
    "sg:province":"UT",
    "sg:tags":[
        "commercial"
    ],
    "wof:name":"H P Inc Copy & Print Ctr",
    "wof:placetype":"venue"
},
  "geometry": {"coordinates":[-111.865313,40.669281],"type":"Point"}
}