{
  "type": "Feature",
  "properties": {
    "iso:country":"US",
    "sg:address":"522 W 3900 N",
    "sg:city":"Ogden",
    "sg:classifiers":[
        {
            "category":"Home & Garden",
            "subcategory":"Furniture",
            "type":"Retail Goods"
        }
    ],
    "sg:phone":"+1 801 603 2782",
    "sg:postcode":"84414",
    "sg:province":"UT",
    "wof:name":"Cloud 9 Furniture & Design LLC",
    "wof:placetype":"venue"
},
  "geometry": {"coordinates":[-111.988574,41.327309],"type":"Point"}
}