{
  "type": "Feature",
  "properties": {
    "iso:country":"US",
    "sg:address":"247 E 1400 S",
    "sg:city":"Garland",
    "sg:classifiers":[
        {
            "category":"Health Services",
            "subcategory":"Doctor",
            "type":"Services"
        }
    ],
    "sg:phone":"+1 435 257 3779",
    "sg:postcode":"84312",
    "sg:province":"UT",
    "sg:tags":[
        "medical"
    ],
    "wof:name":"Rod T Gardner DDS PC",
    "wof:placetype":"venue"
},
  "geometry": {"coordinates":[-112.157663,41.726566],"type":"Point"}
}