{
  "type": "Feature",
  "properties": {
    "iso:country":"US",
    "sg:address":"1302 S 900 W",
    "sg:city":"Salt Lake City",
    "sg:classifiers":[
        {
            "category":"Retail",
            "subcategory":"Auto Repair",
            "type":"Services"
        }
    ],
    "sg:phone":"+1 801 973 6008",
    "sg:postcode":"84104",
    "sg:province":"UT",
    "sg:tags":[
        "repairing",
        "automobile"
    ],
    "wof:name":"Gateway Auto Tech",
    "wof:placetype":"venue"
},
  "geometry": {"coordinates":[-111.916884,40.740562],"type":"Point"}
}