{
  "type": "Feature",
  "properties": {
    "iso:country":"US",
    "sg:address":"3760 Highland Dr",
    "sg:city":"Salt Lake City",
    "sg:classifiers":[
        {
            "category":"Banks & Credit Unions",
            "subcategory":"Bank",
            "type":"Services"
        }
    ],
    "sg:phone":"+1 801 495 9352",
    "sg:postcode":"84106",
    "sg:province":"UT",
    "sg:tags":[
        "loan",
        "real estate"
    ],
    "wof:name":"Mortgage Consultants Inc",
    "wof:placetype":"venue"
},
  "geometry": {"coordinates":[-111.845635,40.688476],"type":"Point"}
}