{
  "type": "Feature",
  "properties": {
    "iso:country":"US",
    "sg:address":"1194 S Jordan Pkwy",
    "sg:city":"South Jordan",
    "sg:classifiers":[
        {
            "category":"Banks & Credit Unions",
            "subcategory":"Bank",
            "type":"Services"
        }
    ],
    "sg:phone":"+1 801 983 5626",
    "sg:postcode":"84095",
    "sg:province":"UT",
    "sg:tags":[
        "loan",
        "real estate"
    ],
    "wof:name":"A Better Mortgage",
    "wof:placetype":"venue"
},
  "geometry": {"coordinates":[-111.92531700000001,40.561813],"type":"Point"}
}