{
  "type": "Feature",
  "properties": {
    "iso:country":"US",
    "sg:address":"1612 Harrison Dr",
    "sg:city":"Evanston",
    "sg:classifiers":[
        {
            "category":"Restaurant",
            "type":"Food & Drink"
        }
    ],
    "sg:phone":"+1 307 789 1373",
    "sg:postcode":"82930",
    "sg:province":"UT",
    "wof:name":"Wally's Burgers",
    "wof:placetype":"venue"
},
  "geometry": {"coordinates":[-110.972672,41.26406],"type":"Point"}
}