{
  "type": "Feature",
  "properties": {
    "iso:country":"US",
    "sg:address":"6160 S 2250 E",
    "sg:city":"Ogden",
    "sg:classifiers":[
        {
            "category":"Shopping",
            "subcategory":"Gifts & Souvenirs",
            "type":"Retail Goods"
        }
    ],
    "sg:phone":"+1 801 476 8769",
    "sg:postcode":"84403",
    "sg:province":"UT",
    "wof:name":"Occasional Gift Basket Lc",
    "wof:placetype":"venue"
},
  "geometry": {"coordinates":[-111.923542,41.152768],"type":"Point"}
}