{
  "type": "Feature",
  "properties": {
    "iso:country":"US",
    "sg:address":"825 N 200 W",
    "sg:city":"Logan",
    "sg:classifiers":[
        {
            "category":"Organizations",
            "subcategory":"Religious Organization",
            "type":"Services"
        }
    ],
    "sg:phone":"+1 435 755 5539",
    "sg:postcode":"84321",
    "sg:province":"UT",
    "sg:tags":[
        "church"
    ],
    "wof:name":"Church Of Jesus Christ Of Lds",
    "wof:placetype":"venue"
},
  "geometry": {"coordinates":[-111.83957100000001,41.747252],"type":"Point"}
}