{
  "type": "Feature",
  "properties": {
    "iso:country":"US",
    "sg:address":"160 N Main St",
    "sg:city":"Nephi",
    "sg:classifiers":[
        {
            "category":"Government",
            "subcategory":"Office",
            "type":"Public Place"
        }
    ],
    "sg:phone":"+1 435 623 1593",
    "sg:postcode":"84648",
    "sg:province":"UT",
    "sg:tags":[
        "road",
        "care"
    ],
    "wof:name":"Road Shed",
    "wof:placetype":"venue"
},
  "geometry": {"coordinates":[-111.83607000000001,39.710572],"type":"Point"}
}