{
  "type": "Feature",
  "properties": {
    "iso:country":"US",
    "sg:address":"4630 Ptarmigan Loop",
    "sg:city":"Park City",
    "sg:classifiers":[
        {
            "category":"Travel",
            "subcategory":"Travel Agent",
            "type":"Entertainment"
        }
    ],
    "sg:phone":"+1 435 649 6015",
    "sg:postcode":"84098",
    "sg:province":"UT",
    "sg:tags":[
        "operator",
        "tour"
    ],
    "wof:name":"Meander Adventures",
    "wof:placetype":"venue"
},
  "geometry": {"coordinates":[-111.53737,40.69868],"type":"Point"}
}