{
  "type": "Feature",
  "properties": {
    "iso:country":"US",
    "sg:address":"5098 Amelia Earhart Dr",
    "sg:city":"Salt Lake City",
    "sg:classifiers":[
        {
            "category":"Wholesale",
            "subcategory":"Furniture",
            "type":"Manufacturing & Wholesale Goods"
        }
    ],
    "sg:phone":"+1 801 355 8811",
    "sg:postcode":"84116",
    "sg:province":"UT",
    "wof:name":"SHI Office Furniture",
    "wof:placetype":"venue"
},
  "geometry": {"coordinates":[-112.014824,40.77647],"type":"Point"}
}