{
  "type": "Feature",
  "properties": {
    "iso:country":"US",
    "sg:address":"835 W 1200 S",
    "sg:city":"Orem",
    "sg:classifiers":[
        {
            "category":"Food & Beverages",
            "subcategory":"Groceries & Convenience Stores",
            "type":"Retail Goods"
        }
    ],
    "sg:phone":"+1 801 802 8866",
    "sg:postcode":"84058",
    "sg:province":"UT",
    "wof:name":"Parkway C-Store",
    "wof:placetype":"venue"
},
  "geometry": {"coordinates":[-111.716756,40.275258],"type":"Point"}
}