{
  "type": "Feature",
  "properties": {
    "iso:country":"US",
    "sg:address":"85 Center St",
    "sg:city":"Holden",
    "sg:classifiers":[
        {
            "category":"Banks & Credit Unions",
            "subcategory":"Financial Services",
            "type":"Services"
        }
    ],
    "sg:phone":"+1 435 795 2207",
    "sg:postcode":"84636",
    "sg:province":"UT",
    "sg:tags":[
        "trust",
        "investment",
        "real estate"
    ],
    "wof:name":"Boiver Investments LLC",
    "wof:placetype":"venue"
},
  "geometry": {"coordinates":[-112.27299600000001,39.099348],"type":"Point"}
}