{
  "type": "Feature",
  "properties": {
    "iso:country":"US",
    "sg:address":"4644 Hunters Ridge Cir",
    "sg:city":"Salt Lake City",
    "sg:classifiers":[
        {
            "category":"Building & Trades",
            "subcategory":"Construction",
            "type":"Services"
        }
    ],
    "sg:phone":"+1 801 272 4154",
    "sg:postcode":"84124",
    "sg:province":"UT",
    "sg:tags":[
        "residential"
    ],
    "wof:name":"Lupine Enterprises Inc",
    "wof:placetype":"venue"
},
  "geometry": {"coordinates":[-111.79701,40.669536],"type":"Point"}
}