{
  "type": "Feature",
  "properties": {
    "iso:country":"US",
    "sg:address":"39 Exchange Pl",
    "sg:city":"Salt Lake City",
    "sg:classifiers":[
        {
            "category":"Professional",
            "subcategory":"Lawyer & Legal Services",
            "type":"Services"
        }
    ],
    "sg:phone":"+1 801 533 9400",
    "sg:postcode":"84111",
    "sg:province":"UT",
    "sg:tags":[
        "attorney"
    ],
    "wof:name":"David Anderson",
    "wof:placetype":"venue"
},
  "geometry": {"coordinates":[-111.89058199999999,40.761482],"type":"Point"}
}