{
  "type": "Feature",
  "properties": {
    "iso:country":"US",
    "sg:address":"7021 Commerce Park Dr",
    "sg:city":"Midvale",
    "sg:classifiers":[
        {
            "category":"Retail",
            "subcategory":"Repair Shop",
            "type":"Services"
        }
    ],
    "sg:phone":"+1 801 255 1444",
    "sg:postcode":"84047",
    "sg:province":"UT",
    "sg:tags":[
        "scooter",
        "motorcycle",
        "motor"
    ],
    "wof:name":"Motorcycle Repair & Rendezvous",
    "wof:placetype":"venue"
},
  "geometry": {"coordinates":[-111.908429,40.623471],"type":"Point"}
}