{
  "type": "Feature",
  "properties": {
    "iso:country":"US",
    "sg:address":"3837 S 300 E",
    "sg:city":"South Salt Lake",
    "sg:classifiers":[
        {
            "category":"Real Estate",
            "subcategory":"Real Estate Operator",
            "type":"Services"
        }
    ],
    "sg:phone":"+1 801 270 0965",
    "sg:postcode":"84115",
    "sg:province":"UT",
    "sg:tags":[
        "apartment"
    ],
    "wof:name":"Villa Charmont Apartments",
    "wof:placetype":"venue"
},
  "geometry": {"coordinates":[-111.882716,40.687444],"type":"Point"}
}