{
  "type": "Feature",
  "properties": {
    "iso:country":"US",
    "sg:address":"3625 W 510 N",
    "sg:city":"Salt Lake City",
    "sg:classifiers":[
        {
            "category":"Airline",
            "type":"Transportation"
        }
    ],
    "sg:phone":"+1 801 578 2700",
    "sg:postcode":"84116",
    "sg:province":"UT",
    "sg:tags":[
        "scheduled",
        "product",
        "petroleum",
        "air"
    ],
    "wof:name":"Delta Airlines",
    "wof:placetype":"venue"
},
  "geometry": {"coordinates":[-111.978602,40.780064],"type":"Point"}
}