{
  "type": "Feature",
  "properties": {
    "iso:country":"US",
    "sg:address":"322 Penny Parade Dr",
    "sg:city":"Salt Lake City",
    "sg:classifiers":[
        {
            "category":"Professional",
            "subcategory":"Business Services",
            "type":"Services"
        }
    ],
    "sg:phone":"+1 801 532 1680",
    "sg:postcode":"84103",
    "sg:province":"UT",
    "wof:name":"Sharon Newton",
    "wof:placetype":"venue"
},
  "geometry": {"coordinates":[-111.879643,40.7826],"type":"Point"}
}