{
  "type": "Feature",
  "properties": {
    "iso:country":"US",
    "sg:address":"1002 E South Temple St",
    "sg:city":"Salt Lake City",
    "sg:classifiers":[
        {
            "category":"Health Services",
            "subcategory":"Doctor",
            "type":"Services"
        }
    ],
    "sg:phone":"+1 801 350 4000",
    "sg:postcode":"84102",
    "sg:province":"UT",
    "wof:name":"Breast Care Ctr",
    "wof:placetype":"venue"
},
  "geometry": {"coordinates":[-111.861098,40.769277],"type":"Point"}
}