{
  "type": "Feature",
  "properties": {
    "iso:country":"US",
    "sg:address":"4835 Highland Dr",
    "sg:city":"Salt Lake City",
    "sg:classifiers":[
        {
            "category":"Professional",
            "type":"Services"
        }
    ],
    "sg:phone":"+1 801 278 9294",
    "sg:postcode":"84117",
    "sg:province":"UT",
    "sg:tags":[
        "establishment"
    ],
    "wof:name":"Commemorative Design",
    "wof:placetype":"venue"
},
  "geometry": {"coordinates":[-111.83904699999999,40.664914],"type":"Point"}
}