{
  "type": "Feature",
  "properties": {
    "iso:country":"US",
    "sg:address":"102 W Main St",
    "sg:city":"Tremonton",
    "sg:classifiers":[
        {
            "category":"Education",
            "subcategory":"School",
            "type":"Public Place"
        }
    ],
    "sg:phone":"+1 435 458 2700",
    "sg:postcode":"84337",
    "sg:province":"UT",
    "sg:website":"www.boxelder.k12.ut.us",
    "wof:name":"Fielding School",
    "wof:placetype":"venue"
},
  "geometry": {"coordinates":[-112.167569,41.711776],"type":"Point"}
}