{
  "type": "Feature",
  "properties": {
    "iso:country":"US",
    "sg:address":"4624 Holladay Blvd",
    "sg:city":"Holladay",
    "sg:classifiers":[
        {
            "category":"Health Services",
            "subcategory":"Medical Lab",
            "type":"Services"
        }
    ],
    "sg:phone":"+1 801 424 1066",
    "sg:postcode":"84117",
    "sg:province":"UT",
    "sg:tags":[
        "laboratory",
        "dental"
    ],
    "wof:name":"Intermountain Dental Design",
    "wof:placetype":"venue"
},
  "geometry": {"coordinates":[-111.826178,40.670264],"type":"Point"}
}