{
  "type": "Feature",
  "properties": {
    "iso:country":"US",
    "sg:address":"5645 Waterbury Way",
    "sg:city":"Salt Lake City",
    "sg:classifiers":[
        {
            "category":"Restaurant",
            "type":"Food & Drink"
        }
    ],
    "sg:phone":"+1 801 272 6667",
    "sg:postcode":"84121",
    "sg:province":"UT",
    "sg:tags":[
        "eating"
    ],
    "wof:name":"Blimpie",
    "wof:placetype":"venue"
},
  "geometry": {"coordinates":[-111.848129,40.645181],"type":"Point"}
}