{
  "type": "Feature",
  "properties": {
    "iso:country":"US",
    "sg:address":"496 E Main St",
    "sg:city":"Vernal",
    "sg:classifiers":[
        {
            "category":"Professional",
            "type":"Services"
        }
    ],
    "sg:phone":"+1 435 789 7894",
    "sg:postcode":"84078",
    "sg:province":"UT",
    "sg:tags":[
        "business"
    ],
    "wof:name":"Northeastern Utah Visitor",
    "wof:placetype":"venue"
},
  "geometry": {"coordinates":[-109.52109,40.455733],"type":"Point"}
}