{
  "type": "Feature",
  "properties": {
    "iso:country":"US",
    "sg:address":"195 N Main St",
    "sg:city":"Randolph",
    "sg:classifiers":[
        {
            "category":"Government",
            "subcategory":"Office",
            "type":"Public Place"
        }
    ],
    "sg:phone":"+1 435 793 3905",
    "sg:postcode":"84064",
    "sg:province":"UT",
    "sg:tags":[
        "federal"
    ],
    "wof:name":"Natural Resources Conservation",
    "wof:placetype":"venue"
},
  "geometry": {"coordinates":[-111.184991,41.668429],"type":"Point"}
}