{
  "type": "Feature",
  "properties": {
    "iso:country":"US",
    "sg:address":"2538 W 6830 S",
    "sg:city":"West Jordan",
    "sg:classifiers":[
        {
            "category":"Wholesale",
            "subcategory":"Motor Vehicles",
            "type":"Manufacturing & Wholesale Goods"
        }
    ],
    "sg:phone":"+1 801 566 0779",
    "sg:postcode":"84084",
    "sg:province":"UT",
    "sg:tags":[
        "used",
        "truck"
    ],
    "wof:name":"Moffat Truck Sales",
    "wof:placetype":"venue"
},
  "geometry": {"coordinates":[-111.952061,40.62724],"type":"Point"}
}