{
  "type": "Feature",
  "properties": {
    "iso:country":"US",
    "sg:address":"312 N Main St",
    "sg:city":"Spanish Fork",
    "sg:classifiers":[
        {
            "category":"Health Services",
            "subcategory":"Doctor",
            "type":"Services"
        }
    ],
    "sg:phone":"+1 801 794 9684",
    "sg:postcode":"84660",
    "sg:province":"UT",
    "sg:tags":[
        "dentist"
    ],
    "wof:name":"Shane Taylor DDS PC",
    "wof:placetype":"venue"
},
  "geometry": {"coordinates":[-111.65467200000001,40.114858],"type":"Point"}
}