{
  "type": "Feature",
  "properties": {
    "iso:country":"US",
    "sg:address":"8284 S 560 E",
    "sg:city":"Sandy",
    "sg:classifiers":[
        {
            "category":"Wholesale",
            "subcategory":"Electrical",
            "type":"Manufacturing & Wholesale Goods"
        }
    ],
    "sg:phone":"+1 801 352 1036",
    "sg:postcode":"84070",
    "sg:province":"UT",
    "sg:tags":[
        "equipment",
        "electric",
        "supply"
    ],
    "wof:name":"H V Power Inc",
    "wof:placetype":"venue"
},
  "geometry": {"coordinates":[-111.875496,40.600758],"type":"Point"}
}