{
  "type": "Feature",
  "properties": {
    "iso:country":"US",
    "sg:address":"222 E 3060 N",
    "sg:city":"Provo",
    "sg:classifiers":[
        {
            "category":"Building & Trades",
            "subcategory":"Plumbing",
            "type":"Services"
        }
    ],
    "sg:phone":"+1 801 377 3114",
    "sg:postcode":"84604",
    "sg:province":"UT",
    "sg:tags":[
        "plumbing",
        "contractor"
    ],
    "wof:name":"Chriss Plumbing",
    "wof:placetype":"venue"
},
  "geometry": {"coordinates":[-111.65490800000001,40.274263],"type":"Point"}
}