{
  "type": "Feature",
  "properties": {
    "iso:country":"US",
    "sg:address":"12401 S 450 E",
    "sg:city":"Draper",
    "sg:classifiers":[
        {
            "category":"Manufacturing",
            "subcategory":"Motor Vehicles & Parts",
            "type":"Manufacturing & Wholesale Goods"
        }
    ],
    "sg:phone":"+1 801 523 1161",
    "sg:postcode":"84020",
    "sg:province":"UT",
    "sg:tags":[
        "mfg",
        "trimming"
    ],
    "wof:name":"Softshell Tech & Optipure",
    "wof:placetype":"venue"
},
  "geometry": {"coordinates":[-111.877934,40.525736],"type":"Point"}
}