{
  "type": "Feature",
  "properties": {
    "iso:country":"US",
    "sg:address":"2895 S Hwy 191",
    "sg:city":"Moab",
    "sg:classifiers":[
        {
            "category":"Professional",
            "type":"Services"
        }
    ],
    "sg:phone":"+1 435 259 4631",
    "sg:postcode":"84532",
    "sg:province":"UT",
    "wof:name":"Rsw Penta Star Inc",
    "wof:placetype":"venue"
},
  "geometry": {"coordinates":[-109.505067,38.530026],"type":"Point"}
}