{
  "type": "Feature",
  "properties": {
    "iso:country":"US",
    "sg:address":"4002 Highland Dr",
    "sg:city":"Holladay",
    "sg:classifiers":[
        {
            "category":"Bars & Pubs",
            "type":"Food & Drink"
        },
        {
            "category":"Restaurant",
            "type":"Food & Drink"
        }
    ],
    "sg:phone":"+1 801 278 5100",
    "sg:postcode":"84124",
    "sg:province":"UT",
    "sg:tags":[
        "club",
        "drinking",
        "eating",
        "night"
    ],
    "wof:name":"Sandpiper",
    "wof:placetype":"venue"
},
  "geometry": {"coordinates":[-111.84508,40.686901],"type":"Point"}
}