{
  "type": "Feature",
  "properties": {
    "iso:country":"US",
    "sg:address":"12699 Clover Dr",
    "sg:city":"Draper",
    "sg:classifiers":[
        {
            "category":"Personal",
            "subcategory":"Beauty Salon",
            "type":"Services"
        }
    ],
    "sg:phone":"+1 801 523 9009",
    "sg:postcode":"84020",
    "sg:province":"UT",
    "sg:tags":[
        "shop"
    ],
    "wof:name":"Salon Montage",
    "wof:placetype":"venue"
},
  "geometry": {"coordinates":[-111.877726,40.520996],"type":"Point"}
}