{
  "type": "Feature",
  "properties": {
    "iso:country":"US",
    "sg:address":"970 State Hwy 118",
    "sg:city":"Richfield",
    "sg:classifiers":[
        {
            "category":"Shopping",
            "type":"Retail Goods"
        }
    ],
    "sg:phone":"+1 435 896 5414",
    "sg:postcode":"84701",
    "sg:province":"UT",
    "sg:tags":[
        "supply",
        "merchandise",
        "f"
    ],
    "wof:name":"Pets N Stuff",
    "wof:placetype":"venue"
},
  "geometry": {"coordinates":[-112.086611,38.752347],"type":"Point"}
}