{
  "type": "Feature",
  "properties": {
    "iso:country":"US",
    "sg:address":"73 N Main St",
    "sg:city":"Logan",
    "sg:classifiers":[
        {
            "category":"Shopping",
            "type":"Retail Goods"
        }
    ],
    "sg:phone":"+1 435 752 0245",
    "sg:postcode":"84321",
    "sg:province":"UT",
    "sg:tags":[
        "coin",
        "dealer",
        "supply"
    ],
    "wof:name":"Gold Coin & Diamond Exchange",
    "wof:placetype":"venue"
},
  "geometry": {"coordinates":[-111.835038,41.731892],"type":"Point"}
}