{
  "type": "Feature",
  "properties": {
    "iso:country":"US",
    "sg:address":"24 E 100 N",
    "sg:city":"Panguitch",
    "sg:classifiers":[
        {
            "category":"Home & Garden",
            "subcategory":"Building Materials",
            "type":"Retail Goods"
        }
    ],
    "sg:phone":"+1 435 676 8836",
    "sg:postcode":"84759",
    "sg:province":"UT",
    "sg:tags":[
        "lumber"
    ],
    "wof:name":"H & R Building Supply",
    "wof:placetype":"venue"
},
  "geometry": {"coordinates":[-112.433786,37.824402],"type":"Point"}
}