{
  "type": "Feature",
  "properties": {
    "iso:country":"US",
    "sg:address":"1515 W 2200 S",
    "sg:city":"Salt Lake City",
    "sg:classifiers":[
        {
            "category":"Manufacturing",
            "subcategory":"Tools & Machinery",
            "type":"Manufacturing & Wholesale Goods"
        }
    ],
    "sg:phone":"+1 801 886 2255",
    "sg:postcode":"84119",
    "sg:province":"UT",
    "sg:tags":[
        "protection",
        "monitoring",
        "asset",
        "system"
    ],
    "wof:name":"Independent Witness Inc",
    "wof:placetype":"venue"
},
  "geometry": {"coordinates":[-111.932579,40.723489],"type":"Point"}
}