{
  "type": "Feature",
  "properties": {
    "iso:country":"US",
    "sg:address":"581 N 2360 W",
    "sg:city":"Salt Lake City",
    "sg:classifiers":[
        {
            "category":"Government",
            "subcategory":"Fire Station",
            "type":"Public Place"
        }
    ],
    "sg:phone":"+1 801 575 2911",
    "sg:postcode":"84116",
    "sg:province":"UT",
    "sg:tags":[
        "protection"
    ],
    "wof:name":"Salt Lake City Firestation 11",
    "wof:placetype":"venue"
},
  "geometry": {"coordinates":[-111.957413,40.782299],"type":"Point"}
}