{
  "type": "Feature",
  "properties": {
    "iso:country":"US",
    "sg:address":"5469 S Redwood Rd",
    "sg:city":"Murray",
    "sg:classifiers":[
        {
            "category":"Restaurant",
            "type":"Food & Drink"
        }
    ],
    "sg:phone":"+1 801 265 1426",
    "sg:postcode":"84123",
    "sg:province":"UT",
    "wof:name":"Mc Donald's",
    "wof:placetype":"venue"
},
  "geometry": {"coordinates":[-111.93870699999999,40.650676],"type":"Point"}
}