{
  "type": "Feature",
  "properties": {
    "iso:country":"US",
    "sg:address":"342 W 200 S",
    "sg:city":"Salt Lake City",
    "sg:classifiers":[
        {
            "category":"Professional",
            "type":"Services"
        }
    ],
    "sg:phone":"+1 801 321 8242",
    "sg:postcode":"84101",
    "sg:province":"UT",
    "sg:tags":[
        "establishment"
    ],
    "wof:name":"P Lx Technology",
    "wof:placetype":"venue"
},
  "geometry": {"coordinates":[-111.901464,40.76507],"type":"Point"}
}