{
  "type": "Feature",
  "properties": {
    "iso:country":"US",
    "sg:address":"160 W South Temple",
    "sg:city":"Salt Lake City",
    "sg:classifiers":[
        {
            "category":"Local Transit",
            "type":"Transportation"
        }
    ],
    "sg:phone":"+1 801 355 9579",
    "sg:postcode":"84101",
    "sg:province":"UT",
    "sg:tags":[
        "bus",
        "line"
    ],
    "wof:name":"Greyhound Bus Lines",
    "wof:placetype":"venue"
},
  "geometry": {"coordinates":[-111.89535100000001,40.769421],"type":"Point"}
}