{
  "type": "Feature",
  "properties": {
    "iso:country":"US",
    "sg:address":"367 E Center St",
    "sg:city":"Moab",
    "sg:classifiers":[
        {
            "category":"Professional",
            "type":"Services"
        }
    ],
    "sg:phone":"+1 435 259 6633",
    "sg:postcode":"84532",
    "sg:province":"UT",
    "wof:name":"Jeff Mc Clary Inc",
    "wof:placetype":"venue"
},
  "geometry": {"coordinates":[-109.54296600000001,38.573336],"type":"Point"}
}