{
  "type": "Feature",
  "properties": {
    "iso:country":"US",
    "sg:address":"7894 Belfast Dr",
    "sg:city":"Magna",
    "sg:classifiers":[
        {
            "category":"Shopping",
            "type":"Retail Goods"
        }
    ],
    "sg:phone":"+1 801 250 7683",
    "sg:postcode":"84044",
    "sg:province":"UT",
    "sg:tags":[
        "candle"
    ],
    "wof:name":"Candle Pabtry",
    "wof:placetype":"venue"
},
  "geometry": {"coordinates":[-112.080511,40.687261],"type":"Point"}
}