{
  "type": "Feature",
  "properties": {
    "iso:country":"US",
    "sg:address":"3109 Swaps Dr",
    "sg:city":"St George",
    "sg:classifiers":[
        {
            "category":"Manufacturing",
            "subcategory":"Tools & Machinery",
            "type":"Manufacturing & Wholesale Goods"
        }
    ],
    "sg:phone":"+1 435 634 1157",
    "sg:postcode":"84790",
    "sg:province":"UT",
    "sg:tags":[
        "industrial",
        "mfg"
    ],
    "wof:name":"W B Enterprises",
    "wof:placetype":"venue"
},
  "geometry": {"coordinates":[-113.59299799999999,37.05562],"type":"Point"}
}