{
  "type": "Feature",
  "properties": {
    "iso:country":"US",
    "sg:address":"2201 N 400 E",
    "sg:city":"Ogden",
    "sg:classifiers":[
        {
            "category":"Health Services",
            "subcategory":"Doctor",
            "type":"Services"
        }
    ],
    "sg:phone":"+1 801 782 6681",
    "sg:postcode":"84414",
    "sg:province":"UT",
    "wof:name":"Northview Dental Associates",
    "wof:placetype":"venue"
},
  "geometry": {"coordinates":[-111.968917,41.299257],"type":"Point"}
}