{
  "type": "Feature",
  "properties": {
    "iso:country":"US",
    "sg:address":"375 Chipeta Way",
    "sg:city":"Salt Lake City",
    "sg:classifiers":[
        {
            "category":"Health Services",
            "subcategory":"Health Practitioner",
            "type":"Services"
        }
    ],
    "sg:phone":"+1 801 581 6004",
    "sg:postcode":"84108",
    "sg:province":"UT",
    "sg:tags":[
        "psychologist"
    ],
    "wof:name":"Counseling Psychology Practice",
    "wof:placetype":"venue"
},
  "geometry": {"coordinates":[-111.825222,40.760381],"type":"Point"}
}