{
  "type": "Feature",
  "properties": {
    "iso:country":"US",
    "sg:address":"383 Meadow Cir",
    "sg:city":"Logan",
    "sg:classifiers":[
        {
            "category":"Professional",
            "subcategory":"Computer Services",
            "type":"Services"
        }
    ],
    "sg:phone":"+1 435 787 2053",
    "sg:postcode":"84321",
    "sg:province":"UT",
    "sg:tags":[
        "prepackaged",
        "software"
    ],
    "wof:name":"Redsands Software LLC",
    "wof:placetype":"venue"
},
  "geometry": {"coordinates":[-111.853323,41.724375],"type":"Point"}
}