{
  "type": "Feature",
  "properties": {
    "iso:country":"US",
    "sg:address":"3269 S Main St",
    "sg:city":"Salt Lake City",
    "sg:classifiers":[
        {
            "category":"Shopping",
            "subcategory":"Used Merchandise",
            "type":"Retail Goods"
        }
    ],
    "sg:phone":"+1 801 486 3111",
    "sg:postcode":"84115",
    "sg:province":"UT",
    "sg:tags":[
        "book",
        "rare",
        "dealer"
    ],
    "sg:website":"www.benchmarkbooks.com",
    "wof:name":"Benchmark Books",
    "wof:placetype":"venue"
},
  "geometry": {"coordinates":[-111.891046,40.701263],"type":"Point"}
}