{
  "type": "Feature",
  "properties": {
    "iso:country":"US",
    "sg:address":"661 W State Rd",
    "sg:city":"American Fork",
    "sg:classifiers":[
        {
            "category":"Autos & Motor Vehicles",
            "subcategory":"Auto Supplies",
            "type":"Retail Goods"
        }
    ],
    "sg:phone":"+1 801 763 8604",
    "sg:postcode":"84003",
    "sg:province":"UT",
    "sg:tags":[
        "tire"
    ],
    "wof:name":"Discount Tire Co",
    "wof:placetype":"venue"
},
  "geometry": {"coordinates":[-111.81738900000001,40.384981],"type":"Point"}
}