{
  "type": "Feature",
  "properties": {
    "iso:country":"US",
    "sg:address":"3598 S 500 W",
    "sg:city":"Salt Lake City",
    "sg:classifiers":[
        {
            "category":"Banks & Credit Unions",
            "subcategory":"Bank",
            "type":"Services"
        }
    ],
    "sg:phone":"+1 801 293 0226",
    "sg:postcode":"84115",
    "sg:province":"UT",
    "sg:tags":[
        "loan",
        "real estate"
    ],
    "wof:name":"Millennium Financial Group",
    "wof:placetype":"venue"
},
  "geometry": {"coordinates":[-111.90557099999999,40.692912],"type":"Point"}
}