{
  "type": "Feature",
  "properties": {
    "iso:country":"US",
    "sg:address":"172 W 9400 S",
    "sg:city":"Sandy",
    "sg:classifiers":[
        {
            "category":"Wholesale",
            "subcategory":"Machinery & Supplies",
            "type":"Manufacturing & Wholesale Goods"
        }
    ],
    "sg:phone":"+1 801 566 2112",
    "sg:postcode":"84070",
    "sg:province":"UT",
    "sg:tags":[
        "equipment",
        "material",
        "handling"
    ],
    "sg:website":"www.aideq.com",
    "wof:name":"Aid Equipment Co",
    "wof:placetype":"venue"
},
  "geometry": {"coordinates":[-111.895971,40.580737],"type":"Point"}
}