{
  "type": "Feature",
  "properties": {
    "iso:country":"US",
    "sg:address":"1416 W 2500 S",
    "sg:city":"Vernal",
    "sg:classifiers":[
        {
            "category":"Freight",
            "type":"Transportation"
        }
    ],
    "sg:phone":"+1 435 789 9726",
    "sg:postcode":"84078",
    "sg:province":"UT",
    "sg:tags":[
        "trucking"
    ],
    "wof:name":"Stacy Hall Trucking Inc",
    "wof:placetype":"venue"
},
  "geometry": {"coordinates":[-109.55510599999999,40.419049],"type":"Point"}
}