{
  "type": "Feature",
  "properties": {
    "iso:country":"US",
    "sg:address":"2827 Breeze Dr",
    "sg:city":"Magna",
    "sg:classifiers":[
        {
            "category":"Building & Trades",
            "subcategory":"Construction",
            "type":"Services"
        }
    ],
    "sg:phone":"+1 801 250 7834",
    "sg:postcode":"84044",
    "sg:province":"UT",
    "sg:tags":[
        "industrial"
    ],
    "wof:name":"Bm & J Inc",
    "wof:placetype":"venue"
},
  "geometry": {"coordinates":[-112.088776,40.707915],"type":"Point"}
}