{
  "type": "Feature",
  "properties": {
    "iso:country":"US",
    "sg:address":"2032 E Lincoln Cir",
    "sg:city":"Salt Lake City",
    "sg:classifiers":[
        {
            "category":"Banks & Credit Unions",
            "subcategory":"Financial Services",
            "type":"Services"
        }
    ],
    "sg:phone":"+1 801 272 0779",
    "sg:postcode":"84124",
    "sg:province":"UT",
    "sg:tags":[
        "investor"
    ],
    "wof:name":"Davis G&J Investments LLC",
    "wof:placetype":"venue"
},
  "geometry": {"coordinates":[-111.832217,40.683144],"type":"Point"}
}