{
  "type": "Feature",
  "properties": {
    "iso:country":"US",
    "sg:address":"10865 Granite Dr",
    "sg:city":"Sandy",
    "sg:classifiers":[
        {
            "category":"Manufacturing",
            "subcategory":"Petroleum Products",
            "type":"Manufacturing & Wholesale Goods"
        }
    ],
    "sg:phone":"+1 801 558 3134",
    "sg:postcode":"84094",
    "sg:province":"UT",
    "sg:tags":[
        "processing",
        "hydrocarbon"
    ],
    "wof:name":"Cowhouse Partners LLC",
    "wof:placetype":"venue"
},
  "geometry": {"coordinates":[-111.858425,40.554006],"type":"Point"}
}