{
  "type": "Feature",
  "properties": {
    "iso:country":"US",
    "sg:address":"759 E 400 S",
    "sg:city":"Springville",
    "sg:classifiers":[
        {
            "category":"Food & Beverages",
            "subcategory":"Groceries & Convenience Stores",
            "type":"Retail Goods"
        }
    ],
    "sg:phone":"+1 801 489 0345",
    "sg:postcode":"84663",
    "sg:province":"UT",
    "sg:tags":[
        "grocer",
        "clothing"
    ],
    "wof:name":"Ream's Food Stores",
    "wof:placetype":"venue"
},
  "geometry": {"coordinates":[-111.598384,40.161126],"type":"Point"}
}