{
  "type": "Feature",
  "properties": {
    "iso:country":"US",
    "sg:address":"88 E Fiddlers Canyon Dr",
    "sg:city":"Cedar City",
    "sg:classifiers":[
        {
            "category":"Government",
            "subcategory":"Office",
            "type":"Public Place"
        }
    ],
    "sg:phone":"+1 435 586 0367",
    "sg:postcode":"84720",
    "sg:province":"UT",
    "sg:tags":[
        "transportation"
    ],
    "wof:name":"Motor Vehicle Department",
    "wof:placetype":"venue"
},
  "geometry": {"coordinates":[-113.058679,37.711714],"type":"Point"}
}