{
  "type": "Feature",
  "properties": {
    "iso:country":"US",
    "sg:address":"2335 S Montero Cir",
    "sg:city":"Washington",
    "sg:classifiers":[
        {
            "category":"Manufacturing",
            "subcategory":"Electronics",
            "type":"Manufacturing & Wholesale Goods"
        }
    ],
    "sg:phone":"+1 435 627 9505",
    "sg:postcode":"84780",
    "sg:province":"UT",
    "wof:name":"Saint Electronics",
    "wof:placetype":"venue"
},
  "geometry": {"coordinates":[-113.519487,37.099154],"type":"Point"}
}