{
  "type": "Feature",
  "properties": {
    "iso:country":"US",
    "sg:address":"2159 S 700 E",
    "sg:city":"Salt Lake City",
    "sg:classifiers":[
        {
            "category":"Professional",
            "subcategory":"Lawyer & Legal Services",
            "type":"Services"
        }
    ],
    "sg:phone":"+1 801 485 3707",
    "sg:postcode":"84106",
    "sg:province":"UT",
    "sg:tags":[
        "firm",
        "attorney",
        "law"
    ],
    "wof:name":"Steffensen and Law Office",
    "wof:placetype":"venue"
},
  "geometry": {"coordinates":[-111.871032,40.722851],"type":"Point"}
}