{
  "type": "Feature",
  "properties": {
    "iso:country":"US",
    "sg:address":"1713 Princeton Ave",
    "sg:city":"Salt Lake City",
    "sg:classifiers":[
        {
            "category":"Recreation",
            "type":"Entertainment"
        },
        {
            "category":"Travel",
            "subcategory":"Travel Agent",
            "type":"Entertainment"
        }
    ],
    "sg:phone":"+1 801 582 6269",
    "sg:postcode":"84108",
    "sg:province":"UT",
    "sg:tags":[
        "operator",
        "tour",
        "tours",
        "sightseeing"
    ],
    "wof:name":"Salt Lake Historical Tours Inc",
    "wof:placetype":"venue"
},
  "geometry": {"coordinates":[-111.839652,40.743769],"type":"Point"}
}