{
  "type": "Feature",
  "properties": {
    "iso:country":"US",
    "sg:address":"535 S 200 W",
    "sg:city":"Bountiful",
    "sg:classifiers":[
        {
            "category":"Food & Beverages",
            "subcategory":"Groceries & Convenience Stores",
            "type":"Retail Goods"
        }
    ],
    "sg:phone":"+1 801 292 2386",
    "sg:postcode":"84010",
    "sg:province":"UT",
    "sg:tags":[
        "supermarket",
        "chain"
    ],
    "wof:name":"Albertsons 373",
    "wof:placetype":"venue"
},
  "geometry": {"coordinates":[-111.88557900000001,40.883439],"type":"Point"}
}