{
  "type": "Feature",
  "properties": {
    "iso:country":"US",
    "sg:address":"1129 N 875 W",
    "sg:city":"Cedar City",
    "sg:classifiers":[
        {
            "category":"Building & Trades",
            "subcategory":"Construction",
            "type":"Services"
        }
    ],
    "sg:phone":"+1 435 867 9152",
    "sg:postcode":"84720",
    "sg:province":"UT",
    "sg:tags":[
        "home",
        "builder"
    ],
    "wof:name":"Carriage Homes",
    "wof:placetype":"venue"
},
  "geometry": {"coordinates":[-113.07478,37.697468],"type":"Point"}
}