{
  "type": "Feature",
  "properties": {
    "iso:country":"US",
    "sg:address":"789 Bamberger Dr",
    "sg:city":"American Fork",
    "sg:classifiers":[
        {
            "category":"Organizations",
            "subcategory":"Non-profit Organization",
            "type":"Services"
        }
    ],
    "sg:phone":"+1 801 772 1030",
    "sg:postcode":"84003",
    "sg:province":"UT",
    "sg:tags":[
        "info",
        "addiction",
        "abuse",
        "treatment",
        "drug"
    ],
    "wof:name":"Turning Point Ctr",
    "wof:placetype":"venue"
},
  "geometry": {"coordinates":[-111.777671,40.373698],"type":"Point"}
}