{
  "type": "Feature",
  "properties": {
    "iso:country":"US",
    "sg:address":"746 E Winchester St",
    "sg:city":"Salt Lake City",
    "sg:classifiers":[
        {
            "category":"Professional",
            "subcategory":"Employment Agencies",
            "type":"Services"
        }
    ],
    "sg:phone":"+1 801 261 8880",
    "sg:postcode":"84107",
    "sg:province":"UT",
    "sg:tags":[
        "help",
        "contractor"
    ],
    "sg:website":"www.spherion.com",
    "wof:name":"Spherion",
    "wof:placetype":"venue"
},
  "geometry": {"coordinates":[-111.869333,40.631718],"type":"Point"}
}