{
  "type": "Feature",
  "properties": {
    "iso:country":"US",
    "sg:address":"7814 Pheasant Wood Dr",
    "sg:city":"Sandy",
    "sg:classifiers":[
        {
            "category":"Professional",
            "type":"Services"
        }
    ],
    "sg:phone":"+1 801 942 9951",
    "sg:postcode":"84093",
    "sg:province":"UT",
    "wof:name":"South Eden Foundation",
    "wof:placetype":"venue"
},
  "geometry": {"coordinates":[-111.84253,40.612191],"type":"Point"}
}