{
  "type": "Feature",
  "properties": {
    "iso:country":"US",
    "sg:address":"898 E 3300 S",
    "sg:city":"Salt Lake City",
    "sg:classifiers":[
        {
            "category":"Government",
            "subcategory":"Police Station",
            "type":"Public Place"
        }
    ],
    "sg:phone":"+1 801 483 0661",
    "sg:postcode":"84106",
    "sg:province":"UT",
    "sg:tags":[
        "sheriff"
    ],
    "wof:name":"Salt Lake County Sheriff",
    "wof:placetype":"venue"
},
  "geometry": {"coordinates":[-111.867636,40.699878],"type":"Point"}
}