{
  "type": "Feature",
  "properties": {
    "iso:country":"US",
    "sg:address":"411 E Main St",
    "sg:city":"Delta",
    "sg:classifiers":[
        {
            "category":"Restaurant",
            "type":"Food & Drink"
        }
    ],
    "sg:phone":"+1 435 864 4790",
    "sg:postcode":"84624",
    "sg:province":"UT",
    "wof:name":"Leo's Delta Freeze",
    "wof:placetype":"venue"
},
  "geometry": {"coordinates":[-112.564896,39.352418],"type":"Point"}
}