{
  "type": "Feature",
  "properties": {
    "iso:country":"US",
    "sg:address":"256 Oak Dr",
    "sg:city":"North Salt Lake",
    "sg:classifiers":[
        {
            "category":"Insurance",
            "subcategory":"Insurance Agent",
            "type":"Services"
        }
    ],
    "sg:phone":"+1 801 292 1865",
    "sg:postcode":"84054",
    "sg:province":"UT",
    "wof:name":"Social Security Advocates",
    "wof:placetype":"venue"
},
  "geometry": {"coordinates":[-111.89666,40.846434],"type":"Point"}
}