{
  "type": "Feature",
  "properties": {
    "iso:country":"US",
    "sg:address":"478 W 800 N",
    "sg:city":"Orem",
    "sg:classifiers":[
        {
            "category":"Health Services",
            "subcategory":"Doctor",
            "type":"Services"
        }
    ],
    "sg:phone":"+1 801 227 0511",
    "sg:postcode":"84057",
    "sg:province":"UT",
    "wof:name":"Utah Valley Endodontics",
    "wof:placetype":"venue"
},
  "geometry": {"coordinates":[-111.709811,40.312137],"type":"Point"}
}