{
  "type": "Feature",
  "properties": {
    "iso:country":"US",
    "sg:address":"60 E 250 N",
    "sg:city":"North Salt Lake",
    "sg:classifiers":[
        {
            "category":"Professional",
            "type":"Services"
        }
    ],
    "sg:phone":"+1 801 299 8416",
    "sg:postcode":"84054",
    "sg:province":"UT",
    "wof:name":"Rimcorr Inc",
    "wof:placetype":"venue"
},
  "geometry": {"coordinates":[-111.911012,40.846535],"type":"Point"}
}