{
  "type": "Feature",
  "properties": {
    "iso:country":"US",
    "sg:address":"13592 Pony Express Rd",
    "sg:city":"Draper",
    "sg:classifiers":[
        {
            "category":"Food & Beverages",
            "subcategory":"Groceries & Convenience Stores",
            "type":"Retail Goods"
        }
    ],
    "sg:phone":"+1 801 553 9220",
    "sg:postcode":"84020",
    "sg:province":"UT",
    "wof:name":"7-Eleven",
    "wof:placetype":"venue"
},
  "geometry": {"coordinates":[-111.89184400000001,40.505258],"type":"Point"}
}