{
  "type": "Feature",
  "properties": {
    "iso:country":"US",
    "sg:address":"38 W 3500 S",
    "sg:city":"Bountiful",
    "sg:classifiers":[
        {
            "category":"Health Services",
            "subcategory":"Doctor",
            "type":"Services"
        }
    ],
    "sg:phone":"+1 801 292 3212",
    "sg:postcode":"84010",
    "sg:province":"UT",
    "sg:tags":[
        "physician",
        "surgeon"
    ],
    "wof:name":"Bountiful Radiology Assoc",
    "wof:placetype":"venue"
},
  "geometry": {"coordinates":[-111.880898,40.851409],"type":"Point"}
}