{
  "type": "Feature",
  "properties": {
    "iso:country":"US",
    "sg:address":"8793 Hwy 36",
    "sg:city":"Tooele",
    "sg:classifiers":[
        {
            "category":"Autos & Motor Vehicles",
            "subcategory":"Fuel & Gas Station",
            "type":"Retail Goods"
        }
    ],
    "sg:phone":"+1 801 250 5298",
    "sg:postcode":"84074",
    "sg:province":"UT",
    "sg:tags":[
        "mart",
        "mini",
        "station",
        "gasoline"
    ],
    "wof:name":"Chevron",
    "wof:placetype":"venue"
},
  "geometry": {"coordinates":[-112.268094,40.686128],"type":"Point"}
}