{
  "type": "Feature",
  "properties": {
    "iso:country":"US",
    "sg:address":"3800 W 5400 S",
    "sg:city":"Kearns",
    "sg:classifiers":[
        {
            "category":"Retail",
            "subcategory":"Veterinary Services",
            "type":"Services"
        }
    ],
    "sg:phone":"+1 801 966 6348",
    "sg:postcode":"84118",
    "sg:province":"UT",
    "sg:tags":[
        "veterinarian"
    ],
    "wof:name":"West Lake Veterinary Hospital",
    "wof:placetype":"venue"
},
  "geometry": {"coordinates":[-111.977261,40.653146],"type":"Point"}
}