{
  "type": "Feature",
  "properties": {
    "iso:country":"US",
    "sg:address":"291 S Main St",
    "sg:city":"Smithfield",
    "sg:classifiers":[
        {
            "category":"Health Services",
            "subcategory":"Health Practitioner",
            "type":"Services"
        }
    ],
    "sg:phone":"+1 435 563 6211",
    "sg:postcode":"84335",
    "sg:province":"UT",
    "wof:name":"George NP Wooton",
    "wof:placetype":"venue"
},
  "geometry": {"coordinates":[-111.83292899999999,41.830423],"type":"Point"}
}