{
  "type": "Feature",
  "properties": {
    "iso:country":"US",
    "sg:address":"1520 Fort Canyon Rd",
    "sg:city":"Alpine",
    "sg:classifiers":[
        {
            "category":"Banks & Credit Unions",
            "subcategory":"Financial Services",
            "type":"Services"
        }
    ],
    "sg:phone":"+1 801 756 3082",
    "sg:postcode":"84004",
    "sg:province":"UT",
    "sg:tags":[
        "company",
        "holding"
    ],
    "wof:name":"Alpine Real Estate Holdings LL",
    "wof:placetype":"venue"
},
  "geometry": {"coordinates":[-111.782003,40.472574],"type":"Point"}
}