{
  "type": "Feature",
  "properties": {
    "iso:country":"US",
    "sg:address":"10951 S 5600 W",
    "sg:city":"Payson",
    "sg:classifiers":[
        {
            "category":"Manufacturing",
            "subcategory":"Retail Goods",
            "type":"Manufacturing & Wholesale Goods"
        }
    ],
    "sg:phone":"+1 801 465 4618",
    "sg:postcode":"84651",
    "sg:province":"UT",
    "sg:tags":[
        "product",
        "mfg"
    ],
    "wof:name":"Small Industries",
    "wof:placetype":"venue"
},
  "geometry": {"coordinates":[-111.78711199999999,40.031588],"type":"Point"}
}