{
  "type": "Feature",
  "properties": {
    "iso:country":"US",
    "sg:address":"321 E State Rd",
    "sg:city":"American Fork",
    "sg:classifiers":[
        {
            "category":"Banks & Credit Unions",
            "subcategory":"Bank",
            "type":"Services"
        }
    ],
    "sg:phone":"+1 801 492 9008",
    "sg:postcode":"84003",
    "sg:province":"UT",
    "sg:tags":[
        "loan",
        "real estate"
    ],
    "wof:name":"Countrywide Home Loans",
    "wof:placetype":"venue"
},
  "geometry": {"coordinates":[-111.789631,40.374989],"type":"Point"}
}