{
  "type": "Feature",
  "properties": {
    "iso:country":"US",
    "sg:address":"6193 S State St",
    "sg:city":"Salt Lake City",
    "sg:classifiers":[
        {
            "category":"Shopping",
            "type":"Retail Goods"
        }
    ],
    "sg:phone":"+1 801 293 0109",
    "sg:postcode":"84107",
    "sg:province":"UT",
    "sg:tags":[
        "merchandise"
    ],
    "wof:name":"Nextel",
    "wof:placetype":"venue"
},
  "geometry": {"coordinates":[-111.889161,40.636344],"type":"Point"}
}