{
  "type": "Feature",
  "properties": {
    "iso:country":"US",
    "sg:address":"7379 S Silver King Cir",
    "sg:city":"Salt Lake City",
    "sg:classifiers":[
        {
            "category":"Building & Trades",
            "subcategory":"Landscaping Services",
            "type":"Services"
        }
    ],
    "sg:phone":"+1 801 255 9531",
    "sg:postcode":"84121",
    "sg:province":"UT",
    "sg:tags":[
        "landscape"
    ],
    "wof:name":"Butterfield Ldscpg & Grdns",
    "wof:placetype":"venue"
},
  "geometry": {"coordinates":[-111.783732,40.617345],"type":"Point"}
}