{
  "type": "Feature",
  "properties": {
    "iso:country":"US",
    "sg:address":"444 S River Rd",
    "sg:city":"St George",
    "sg:classifiers":[
        {
            "category":"Airline",
            "type":"Transportation"
        }
    ],
    "sg:phone":"+1 435 634 3000",
    "sg:postcode":"84790",
    "sg:province":"UT",
    "sg:tags":[
        "scheduled"
    ],
    "wof:name":"Skywest Inc",
    "wof:placetype":"venue"
},
  "geometry": {"coordinates":[-113.555735,37.100435],"type":"Point"}
}