{
  "type": "Feature",
  "properties": {
    "iso:country":"US",
    "sg:address":"366 E 10560 S",
    "sg:city":"Sandy",
    "sg:classifiers":[
        {
            "category":"Professional",
            "subcategory":"Engineering",
            "type":"Services"
        }
    ],
    "sg:phone":"+1 801 571 0930",
    "sg:postcode":"84070",
    "sg:province":"UT",
    "wof:name":"T3 Engineering Pllc",
    "wof:placetype":"venue"
},
  "geometry": {"coordinates":[-111.87944299999999,40.559478],"type":"Point"}
}