{
  "type": "Feature",
  "properties": {
    "iso:country":"US",
    "sg:address":"9121 Monroe St",
    "sg:city":"Sandy",
    "sg:classifiers":[
        {
            "category":"Real Estate",
            "subcategory":"Real Estate Operator",
            "type":"Services"
        }
    ],
    "sg:phone":"+1 801 233 0355",
    "sg:postcode":"84070",
    "sg:province":"UT",
    "sg:tags":[
        "building",
        "parks"
    ],
    "wof:name":"Monroe Professional Plaza",
    "wof:placetype":"venue"
},
  "geometry": {"coordinates":[-111.895965,40.585307],"type":"Point"}
}