{
  "type": "Feature",
  "properties": {
    "iso:country":"US",
    "sg:address":"496 E 1100 N",
    "sg:city":"North Salt Lake",
    "sg:classifiers":[
        {
            "category":"Restaurant",
            "type":"Food & Drink"
        }
    ],
    "sg:menulink":"http://www.allmenus.com/ut/south-davis/235441-taco-time/menu/",
    "sg:phone":"+1 801 397 5554",
    "sg:postcode":"84054",
    "sg:province":"UT",
    "sg:tags":[
        "american",
        "mexican",
        "tex-mex"
    ],
    "wof:name":"Taco Time",
    "wof:placetype":"venue"
},
  "geometry": {"coordinates":[-111.89863200000001,40.861441],"type":"Point"}
}