{
  "type": "Feature",
  "properties": {
    "iso:country":"US",
    "sg:address":"333 E Main St",
    "sg:city":"American Fork",
    "sg:classifiers":[
        {
            "category":"Home & Garden",
            "subcategory":"Furniture",
            "type":"Retail Goods"
        }
    ],
    "sg:phone":"+1 435 645 9003",
    "sg:postcode":"84003",
    "sg:province":"UT",
    "wof:name":"International Furniture",
    "wof:placetype":"venue"
},
  "geometry": {"coordinates":[-111.79037099999999,40.376813],"type":"Point"}
}