{
  "type": "Feature",
  "properties": {
    "iso:country":"US",
    "sg:address":"1372 W 7800 S",
    "sg:city":"West Jordan",
    "sg:classifiers":[
        {
            "category":"Home & Garden",
            "subcategory":"Furniture",
            "type":"Retail Goods"
        }
    ],
    "sg:phone":"+1 801 255 1702",
    "sg:postcode":"84088",
    "sg:province":"UT",
    "sg:tags":[
        "mfg",
        "wood",
        "kitchen",
        "cabinet"
    ],
    "wof:name":"Closets & Cabinets Etc",
    "wof:placetype":"venue"
},
  "geometry": {"coordinates":[-111.930294,40.609623],"type":"Point"}
}