{
  "type": "Feature",
  "properties": {
    "iso:country":"US",
    "sg:address":"6850 Nye Dr",
    "sg:city":"Salt Lake City",
    "sg:classifiers":[
        {
            "category":"Social Services",
            "subcategory":"Adult Care",
            "type":"Services"
        }
    ],
    "sg:phone":"+1 801 943 0790",
    "sg:postcode":"84121",
    "sg:province":"UT",
    "sg:tags":[
        "home",
        "residential"
    ],
    "wof:name":"Community Treatment Altrntvs",
    "wof:placetype":"venue"
},
  "geometry": {"coordinates":[-111.83009800000001,40.628088],"type":"Point"}
}