{
  "type": "Feature",
  "properties": {
    "iso:country":"US",
    "sg:address":"49 E 100 N",
    "sg:city":"American Fork",
    "sg:classifiers":[
        {
            "category":"Retail",
            "subcategory":"Funeral Services",
            "type":"Services"
        }
    ],
    "sg:phone":"+1 801 756 3564",
    "sg:postcode":"84003",
    "sg:province":"UT",
    "sg:tags":[
        "director"
    ],
    "wof:name":"Anderson & Sons Mortuary",
    "wof:placetype":"venue"
},
  "geometry": {"coordinates":[-111.79598300000001,40.37911],"type":"Point"}
}