{
  "type": "Feature",
  "properties": {
    "iso:country":"US",
    "sg:address":"268 Main St",
    "sg:city":"Coalville",
    "sg:classifiers":[
        {
            "category":"Retail",
            "subcategory":"Funeral Services",
            "type":"Services"
        }
    ],
    "sg:phone":"+1 435 336 5521",
    "sg:postcode":"84017",
    "sg:province":"UT",
    "sg:tags":[
        "director"
    ],
    "wof:name":"Walker Mortuary",
    "wof:placetype":"venue"
},
  "geometry": {"coordinates":[-111.401337,40.923396],"type":"Point"}
}