{
  "type": "Feature",
  "properties": {
    "iso:country":"US",
    "sg:address":"395 E 10425 S",
    "sg:city":"Sandy",
    "sg:classifiers":[
        {
            "category":"Manufacturing",
            "subcategory":"Furniture",
            "type":"Manufacturing & Wholesale Goods"
        }
    ],
    "sg:phone":"+1 801 576 9600",
    "sg:postcode":"84070",
    "sg:province":"UT",
    "wof:name":"Hanes Industries",
    "wof:placetype":"venue"
},
  "geometry": {"coordinates":[-111.878204,40.562152],"type":"Point"}
}