{
  "type": "Feature",
  "properties": {
    "iso:country":"US",
    "sg:address":"3373 N 1050 E",
    "sg:city":"Ogden",
    "sg:classifiers":[
        {
            "category":"Building & Trades",
            "subcategory":"Electrical",
            "type":"Services"
        }
    ],
    "sg:phone":"+1 801 737 0125",
    "sg:postcode":"84414",
    "sg:province":"UT",
    "sg:tags":[
        "electrical",
        "contractor"
    ],
    "wof:name":"Harmony Electric Inc",
    "wof:placetype":"venue"
},
  "geometry": {"coordinates":[-111.947339,41.321032],"type":"Point"}
}