{
  "type": "Feature",
  "properties": {
    "iso:country":"US",
    "sg:address":"1780 W 7800 S",
    "sg:city":"West Jordan",
    "sg:classifiers":[
        {
            "category":"Restaurant",
            "type":"Food & Drink"
        }
    ],
    "sg:phone":"+1 801 561 0217",
    "sg:postcode":"84088",
    "sg:province":"UT",
    "sg:website":"www.mcdonalds.com",
    "wof:name":"Mc Donald's",
    "wof:placetype":"venue"
},
  "geometry": {"coordinates":[-111.939852,40.609589],"type":"Point"}
}