{
  "type": "Feature",
  "properties": {
    "iso:country":"US",
    "sg:address":"5775 W 4100 S",
    "sg:city":"West Valley",
    "sg:classifiers":[
        {
            "category":"Organizations",
            "subcategory":"Religious Organization",
            "type":"Services"
        }
    ],
    "sg:phone":"+1 801 964 3033",
    "sg:postcode":"84128",
    "sg:province":"UT",
    "sg:tags":[
        "church"
    ],
    "wof:name":"Church Of Jesus Christ Of Lds",
    "wof:placetype":"venue"
},
  "geometry": {"coordinates":[-112.028723,40.681993],"type":"Point"}
}