{
  "type": "Feature",
  "properties": {
    "iso:country":"US",
    "sg:address":"120 N State St",
    "sg:city":"Orem",
    "sg:classifiers":[
        {
            "category":"Restaurant",
            "type":"Food & Drink"
        }
    ],
    "sg:menulink":"http://www.allmenus.com/ut/provo-orem/69583-dominos-pizza/menu/",
    "sg:phone":"+1 801 226 2100",
    "sg:postcode":"84057",
    "sg:province":"UT",
    "sg:tags":[
        "american",
        "wing",
        "pizza"
    ],
    "wof:name":"Domino's Pizza",
    "wof:placetype":"venue"
},
  "geometry": {"coordinates":[-111.695936,40.299283],"type":"Point"}
}