{
  "type": "Feature",
  "properties": {
    "iso:country":"US",
    "sg:address":"6262 Johnson Canyon Rd",
    "sg:city":"Kanab",
    "sg:classifiers":[
        {
            "category":"Farming",
            "subcategory":"Livestock Farm",
            "type":"Manufacturing & Wholesale Goods"
        }
    ],
    "sg:phone":"+1 435 644 5846",
    "sg:postcode":"84741",
    "sg:province":"UT",
    "sg:tags":[
        "beef",
        "feedlot",
        "cattle"
    ],
    "wof:name":"Allemann Farm",
    "wof:placetype":"venue"
},
  "geometry": {"coordinates":[-112.369224,37.08771],"type":"Point"}
}