{
  "type": "Feature",
  "properties": {
    "iso:country":"US",
    "sg:address":"565 W 2600 S",
    "sg:city":"Bountiful",
    "sg:classifiers":[
        {
            "category":"Health Services",
            "subcategory":"Chiropractor",
            "type":"Services"
        }
    ],
    "sg:phone":"+1 801 298 4646",
    "sg:postcode":"84010",
    "sg:province":"UT",
    "sg:tags":[
        "medical"
    ],
    "wof:name":"Bountiful Family Wellness Ctr",
    "wof:placetype":"venue"
},
  "geometry": {"coordinates":[-111.893271,40.861675],"type":"Point"}
}