{
  "type": "Feature",
  "properties": {
    "iso:country":"US",
    "sg:address":"3465 N Hwy 13",
    "sg:city":"Corinne",
    "sg:classifiers":[
        {
            "category":"Organizations",
            "subcategory":"Religious Organization",
            "type":"Services"
        }
    ],
    "sg:phone":"+1 435 744 2966",
    "sg:postcode":"84307",
    "sg:province":"UT",
    "sg:tags":[
        "church"
    ],
    "wof:name":"Church Of Jesus Christ Of Lds",
    "wof:placetype":"venue"
},
  "geometry": {"coordinates":[-112.129689,41.569193],"type":"Point"}
}