{
  "type": "Feature",
  "properties": {
    "iso:country":"US",
    "sg:address":"39 S 800 E",
    "sg:city":"Spanish Fork",
    "sg:classifiers":[
        {
            "category":"Shopping",
            "subcategory":"Gifts & Souvenirs",
            "type":"Retail Goods"
        }
    ],
    "sg:phone":"+1 801 798 1381",
    "sg:postcode":"84660",
    "sg:province":"UT",
    "wof:name":"Kandaces Party Planning Gifts",
    "wof:placetype":"venue"
},
  "geometry": {"coordinates":[-111.640608,40.109235],"type":"Point"}
}