{
  "type": "Feature",
  "properties": {
    "iso:country":"US",
    "sg:address":"4722 Harkness Dr",
    "sg:city":"West Jordan",
    "sg:classifiers":[
        {
            "category":"Professional",
            "type":"Services"
        }
    ],
    "sg:phone":"+1 801 280 2330",
    "sg:postcode":"84088",
    "sg:province":"UT",
    "sg:tags":[
        "educational"
    ],
    "wof:name":"Resolution Assistance Corp",
    "wof:placetype":"venue"
},
  "geometry": {"coordinates":[-112.00413,40.583404],"type":"Point"}
}