{
  "type": "Feature",
  "properties": {
    "iso:country":"US",
    "sg:address":"65 Wadsworth Park Dr",
    "sg:city":"Draper",
    "sg:classifiers":[
        {
            "category":"Communications",
            "type":"Services"
        }
    ],
    "sg:phone":"+1 801 619 1815",
    "sg:postcode":"84020",
    "sg:province":"UT",
    "wof:name":"Accelerated Communications",
    "wof:placetype":"venue"
},
  "geometry": {"coordinates":[-111.889171,40.500678],"type":"Point"}
}