{
  "type": "Feature",
  "properties": {
    "iso:country":"US",
    "sg:address":"533 W 2600 S",
    "sg:city":"Bountiful",
    "sg:classifiers":[
        {
            "category":"Banks & Credit Unions",
            "subcategory":"Investment Brokerage",
            "type":"Services"
        }
    ],
    "sg:phone":"+1 801 296 6605",
    "sg:postcode":"84010",
    "sg:province":"UT",
    "sg:tags":[
        "consultant",
        "planning",
        "financial",
        "advisory"
    ],
    "wof:name":"Inverness Counsel Inc",
    "wof:placetype":"venue"
},
  "geometry": {"coordinates":[-111.892759,40.861671],"type":"Point"}
}