{
  "type": "Feature",
  "properties": {
    "iso:country":"US",
    "sg:address":"1977 S 2000 W",
    "sg:city":"Syracuse",
    "sg:classifiers":[
        {
            "category":"Shopping",
            "subcategory":"Luggage & Leather Goods",
            "type":"Retail Goods"
        }
    ],
    "sg:phone":"+1 801 774 6219",
    "sg:postcode":"84075",
    "sg:province":"UT",
    "sg:tags":[
        "jewelry"
    ],
    "wof:name":"Cognition Missionary Depot LLC",
    "wof:placetype":"venue"
},
  "geometry": {"coordinates":[-112.064536,41.086007],"type":"Point"}
}