{
  "type": "Feature",
  "properties": {
    "iso:country":"US",
    "sg:address":"1522 S 1250 W",
    "sg:city":"Syracuse",
    "sg:classifiers":[
        {
            "category":"Shopping",
            "subcategory":"Stationery & Office Supplies",
            "type":"Retail Goods"
        }
    ],
    "sg:phone":"+1 801 544 6014",
    "sg:postcode":"84075",
    "sg:province":"UT",
    "sg:tags":[
        "printing",
        "commercial"
    ],
    "wof:name":"Missionary Stationery Bus LLC",
    "wof:placetype":"venue"
},
  "geometry": {"coordinates":[-112.050777,41.092858],"type":"Point"}
}