{
  "type": "Feature",
  "properties": {
    "iso:country":"US",
    "sg:address":"1175 Crest Gate Cir",
    "sg:city":"Salt Lake City",
    "sg:classifiers":[
        {
            "category":"Professional",
            "subcategory":"Business Services",
            "type":"Services"
        }
    ],
    "sg:phone":"+1 801 266 7326",
    "sg:postcode":"84123",
    "sg:province":"UT",
    "wof:name":"Pettit Family Ltd Partnership",
    "wof:placetype":"venue"
},
  "geometry": {"coordinates":[-111.925628,40.661531],"type":"Point"}
}