{
  "type": "Feature",
  "properties": {
    "iso:country":"US",
    "sg:address":"750 Ridgeview Dr",
    "sg:city":"St George",
    "sg:classifiers":[
        {
            "category":"Social Services",
            "type":"Services"
        }
    ],
    "sg:phone":"+1 435 673 4870",
    "sg:postcode":"84770",
    "sg:province":"UT",
    "sg:tags":[
        "clinic",
        "specialty",
        "outpatient"
    ],
    "wof:name":"Counseling Assoc",
    "wof:placetype":"venue"
},
  "geometry": {"coordinates":[-113.599245,37.119965],"type":"Point"}
}