{
  "type": "Feature",
  "properties": {
    "iso:country":"US",
    "sg:address":"2061 Murray Holladay Rd",
    "sg:city":"Salt Lake City",
    "sg:classifiers":[
        {
            "category":"Real Estate",
            "subcategory":"Architect",
            "type":"Services"
        }
    ],
    "sg:phone":"+1 801 424 2703",
    "sg:postcode":"84117",
    "sg:province":"UT",
    "sg:tags":[
        "architectural"
    ],
    "wof:name":"Dennis Butler and Assc",
    "wof:placetype":"venue"
},
  "geometry": {"coordinates":[-111.831909,40.665827],"type":"Point"}
}