{
  "type": "Feature",
  "properties": {
    "iso:country":"US",
    "sg:address":"90 E 100 S",
    "sg:city":"St George",
    "sg:classifiers":[
        {
            "category":"Banks & Credit Unions",
            "subcategory":"Bank",
            "type":"Services"
        }
    ],
    "sg:phone":"+1 435 649 3300",
    "sg:postcode":"84770",
    "sg:province":"UT",
    "sg:tags":[
        "loan",
        "real estate"
    ],
    "wof:name":"Statewide Funding South",
    "wof:placetype":"venue"
},
  "geometry": {"coordinates":[-113.58142100000001,37.106416],"type":"Point"}
}