{
  "type": "Feature",
  "properties": {
    "iso:country":"US",
    "sg:address":"45 S Main St",
    "sg:city":"Smithfield",
    "sg:classifiers":[
        {
            "category":"Home & Garden",
            "subcategory":"Home Furnishings",
            "type":"Retail Goods"
        }
    ],
    "sg:phone":"+1 435 563 0230",
    "sg:postcode":"84335",
    "sg:province":"UT",
    "sg:tags":[
        "quilting"
    ],
    "wof:name":"Stitches",
    "wof:placetype":"venue"
},
  "geometry": {"coordinates":[-111.83278900000001,41.835606],"type":"Point"}
}