{
  "type": "Feature",
  "properties": {
    "iso:country":"US",
    "sg:address":"4325 S 300 W",
    "sg:city":"Murray",
    "sg:classifiers":[
        {
            "category":"Retail",
            "subcategory":"Auto Repair",
            "type":"Services"
        }
    ],
    "sg:phone":"+1 801 264 9911",
    "sg:postcode":"84107",
    "sg:province":"UT",
    "sg:tags":[
        "repairing",
        "automobile"
    ],
    "wof:name":"German Car Svc-Werner-Melvin",
    "wof:placetype":"venue"
},
  "geometry": {"coordinates":[-111.899659,40.679303],"type":"Point"}
}