{
  "type": "Feature",
  "properties": {
    "iso:country":"US",
    "sg:address":"10946 S Conestoga Dr",
    "sg:city":"Spanish Fork",
    "sg:classifiers":[
        {
            "category":"Wholesale",
            "subcategory":"Computers",
            "type":"Manufacturing & Wholesale Goods"
        }
    ],
    "sg:phone":"+1 801 873 3288",
    "sg:postcode":"84660",
    "sg:province":"UT",
    "wof:name":"Em 3 Systems Inc",
    "wof:placetype":"venue"
},
  "geometry": {"coordinates":[-111.565332,40.02611],"type":"Point"}
}