{
  "type": "Feature",
  "properties": {
    "iso:country":"US",
    "sg:address":"2447 Lincoln Ave",
    "sg:city":"Ogden",
    "sg:classifiers":[
        {
            "category":"Government",
            "subcategory":"Office",
            "type":"Public Place"
        }
    ],
    "sg:phone":"+1 801 778 6550",
    "sg:postcode":"84401",
    "sg:province":"UT",
    "sg:tags":[
        "state",
        "taxation"
    ],
    "wof:name":"Tax Commission",
    "wof:placetype":"venue"
},
  "geometry": {"coordinates":[-111.976122,41.222435],"type":"Point"}
}