{
  "type": "Feature",
  "properties": {
    "iso:country":"US",
    "sg:address":"5905 S State St",
    "sg:city":"Salt Lake City",
    "sg:classifiers":[
        {
            "category":"Coffee & Tea",
            "type":"Food & Drink"
        }
    ],
    "sg:menulink":"http://www.allmenus.com/ut/salt-lake-city/118411-starbucks-coffee/menu/",
    "sg:phone":"+1 801 266 3922",
    "sg:postcode":"84107",
    "sg:province":"UT",
    "sg:tags":[
        "american"
    ],
    "wof:name":"Starbucks Coffee",
    "wof:placetype":"venue"
},
  "geometry": {"coordinates":[-111.888436,40.642694],"type":"Point"}
}