{
  "type": "Feature",
  "properties": {
    "iso:country":"US",
    "sg:address":"55 W Saint George Blvd",
    "sg:city":"St George",
    "sg:classifiers":[
        {
            "category":"Building & Trades",
            "subcategory":"Equipment Rental",
            "type":"Services"
        }
    ],
    "sg:phone":"+1 435 627 0486",
    "sg:postcode":"84770",
    "sg:province":"UT",
    "wof:name":"Bruces Furniture Electronics",
    "wof:placetype":"venue"
},
  "geometry": {"coordinates":[-113.584399,37.109826],"type":"Point"}
}