{
  "type": "Feature",
  "properties": {
    "iso:country":"US",
    "sg:address":"7951 S State St",
    "sg:city":"Midvale",
    "sg:classifiers":[
        {
            "category":"Autos & Motor Vehicles",
            "subcategory":"Automobile Sales",
            "type":"Retail Goods"
        }
    ],
    "sg:phone":"+1 801 562 8884",
    "sg:postcode":"84047",
    "sg:province":"UT",
    "sg:tags":[
        "car",
        "used",
        "dealer"
    ],
    "wof:name":"Dave's Auto Sales",
    "wof:placetype":"venue"
},
  "geometry": {"coordinates":[-111.890691,40.607377],"type":"Point"}
}