{
  "type": "Feature",
  "properties": {
    "iso:country":"US",
    "sg:address":"618 W 1100 S",
    "sg:city":"Vernal",
    "sg:classifiers":[
        {
            "category":"Shopping",
            "subcategory":"Crafts & Fabrics",
            "type":"Retail Goods"
        }
    ],
    "sg:phone":"+1 435 789 6090",
    "sg:postcode":"84078",
    "sg:province":"UT",
    "sg:tags":[
        "sewing"
    ],
    "wof:name":"Ivys",
    "wof:placetype":"venue"
},
  "geometry": {"coordinates":[-109.539472,40.439602],"type":"Point"}
}