{
  "type": "Feature",
  "properties": {
    "iso:country":"US",
    "sg:address":"11318 Sandy Ridge Dr",
    "sg:city":"Sandy",
    "sg:classifiers":[
        {
            "category":"Wholesale",
            "subcategory":"Vending Machines",
            "type":"Manufacturing & Wholesale Goods"
        }
    ],
    "sg:phone":"+1 801 571 2693",
    "sg:postcode":"84094",
    "sg:province":"UT",
    "sg:tags":[
        "operator"
    ],
    "wof:name":"Supreme Snacks Vending Company",
    "wof:placetype":"venue"
},
  "geometry": {"coordinates":[-111.855194,40.545265],"type":"Point"}
}