{
  "type": "Feature",
  "properties": {
    "iso:country":"US",
    "sg:address":"666 S Main St",
    "sg:city":"Brigham City",
    "sg:classifiers":[
        {
            "category":"Shopping",
            "subcategory":"Discount & Variety Stores",
            "type":"Retail Goods"
        }
    ],
    "sg:phone":"+1 435 723 0665",
    "sg:postcode":"84302",
    "sg:province":"UT",
    "sg:tags":[
        "building",
        "operator",
        "nonresidential"
    ],
    "wof:name":"Bargain Outlet",
    "wof:placetype":"venue"
},
  "geometry": {"coordinates":[-112.016066,41.4976],"type":"Point"}
}