{
  "type": "Feature",
  "properties": {
    "iso:country":"US",
    "sg:address":"1630 Cahoon St",
    "sg:city":"Ogden",
    "sg:classifiers":[
        {
            "category":"Restaurant",
            "type":"Food & Drink"
        }
    ],
    "sg:phone":"+1 801 392 8262",
    "sg:postcode":"84401",
    "sg:province":"UT",
    "sg:tags":[
        "caterer"
    ],
    "wof:name":"R & S Country Catering",
    "wof:placetype":"venue"
},
  "geometry": {"coordinates":[-111.93512699999999,41.22341],"type":"Point"}
}