{
  "type": "Feature",
  "properties": {
    "iso:country":"US",
    "sg:address":"152 Downington Ave",
    "sg:city":"Salt Lake City",
    "sg:classifiers":[
        {
            "category":"Retail",
            "subcategory":"Repair Shop",
            "type":"Services"
        }
    ],
    "sg:phone":"+1 801 466 1235",
    "sg:postcode":"84115",
    "sg:province":"UT",
    "sg:tags":[
        "repairing",
        "piano",
        "refinishing"
    ],
    "wof:name":"Backels Piano Svc",
    "wof:placetype":"venue"
},
  "geometry": {"coordinates":[-111.886636,40.730597],"type":"Point"}
}