{
  "type": "Feature",
  "properties": {
    "iso:country":"US",
    "sg:address":"350 W 700 S",
    "sg:city":"Pleasant Grove",
    "sg:classifiers":[
        {
            "category":"Building & Trades",
            "subcategory":"Construction",
            "type":"Services"
        }
    ],
    "sg:phone":"+1 801 521 4422",
    "sg:postcode":"84062",
    "sg:province":"UT",
    "sg:tags":[
        "concrete",
        "contractor"
    ],
    "wof:name":"All State Pumping",
    "wof:placetype":"venue"
},
  "geometry": {"coordinates":[-111.75197,40.355126],"type":"Point"}
}