{
  "type": "Feature",
  "properties": {
    "iso:country":"US",
    "sg:address":"803 S 1640 W",
    "sg:city":"Orem",
    "sg:classifiers":[
        {
            "category":"Manufacturing",
            "subcategory":"Building Materials",
            "type":"Manufacturing & Wholesale Goods"
        }
    ],
    "sg:phone":"+1 801 798 6881",
    "sg:postcode":"84058",
    "sg:province":"UT",
    "sg:tags":[
        "mfg",
        "wood",
        "kitchen",
        "cabinet"
    ],
    "wof:name":"Jensens Classic Woodworking",
    "wof:placetype":"venue"
},
  "geometry": {"coordinates":[-111.734562,40.282455],"type":"Point"}
}