{
  "type": "Feature",
  "properties": {
    "iso:country":"US",
    "sg:address":"448 N 200 E",
    "sg:city":"American Fork",
    "sg:classifiers":[
        {
            "category":"Building & Trades",
            "subcategory":"Construction",
            "type":"Services"
        }
    ],
    "sg:phone":"+1 801 763 8423",
    "sg:postcode":"84003",
    "sg:province":"UT",
    "sg:tags":[
        "house"
    ],
    "wof:name":"George Price Construction",
    "wof:placetype":"venue"
},
  "geometry": {"coordinates":[-111.793098,40.386033],"type":"Point"}
}