{
  "type": "Feature",
  "properties": {
    "iso:country":"US",
    "sg:address":"565 W Old Highway Rd",
    "sg:city":"Morgan",
    "sg:classifiers":[
        {
            "category":"Shopping",
            "subcategory":"Clothing, Apparel, & Fashions",
            "type":"Retail Goods"
        }
    ],
    "sg:phone":"+1 801 829 6753",
    "sg:postcode":"84050",
    "sg:province":"UT",
    "wof:name":"Sportique",
    "wof:placetype":"venue"
},
  "geometry": {"coordinates":[-111.71641099999999,41.074184],"type":"Point"}
}