{
  "type": "Feature",
  "properties": {
    "iso:country":"US",
    "sg:address":"833 S Main St",
    "sg:city":"Salt Lake City",
    "sg:classifiers":[
        {
            "category":"Freight",
            "type":"Transportation"
        }
    ],
    "sg:phone":"+1 801 521 7712",
    "sg:postcode":"84111",
    "sg:province":"UT",
    "sg:tags":[
        "special"
    ],
    "wof:name":"Downtown Music",
    "wof:placetype":"venue"
},
  "geometry": {"coordinates":[-111.891006,40.750485],"type":"Point"}
}