{
  "type": "Feature",
  "properties": {
    "iso:country":"US",
    "sg:address":"1333 N Main St",
    "sg:city":"Cedar City",
    "sg:classifiers":[
        {
            "category":"Health Services",
            "subcategory":"Doctor",
            "type":"Services"
        }
    ],
    "sg:phone":"+1 435 586 0077",
    "sg:postcode":"84720",
    "sg:province":"UT",
    "sg:tags":[
        "physician",
        "surgeon"
    ],
    "wof:name":"Valley View Pediatrics",
    "wof:placetype":"venue"
},
  "geometry": {"coordinates":[-113.063951,37.700713],"type":"Point"}
}