{
  "type": "Feature",
  "properties": {
    "iso:country":"US",
    "sg:address":"700 N 500 E",
    "sg:city":"Payson",
    "sg:classifiers":[
        {
            "category":"Manufacturing",
            "subcategory":"Motor Vehicles & Parts",
            "type":"Manufacturing & Wholesale Goods"
        }
    ],
    "sg:phone":"+1 801 465 4841",
    "sg:postcode":"84651",
    "sg:province":"UT",
    "sg:tags":[
        "automobile",
        "supply"
    ],
    "wof:name":"Genuine Parts Co Rayloc Div",
    "wof:placetype":"venue"
},
  "geometry": {"coordinates":[-111.725419,40.055824],"type":"Point"}
}