{
  "type": "Feature",
  "properties": {
    "iso:country":"US",
    "sg:address":"1696 E 1300 S",
    "sg:city":"Ogden",
    "sg:classifiers":[
        {
            "category":"Wholesale",
            "subcategory":"Computers",
            "type":"Manufacturing & Wholesale Goods"
        }
    ],
    "sg:phone":"+1 801 399 3862",
    "sg:postcode":"84404",
    "sg:province":"UT",
    "wof:name":"Romus International",
    "wof:placetype":"venue"
},
  "geometry": {"coordinates":[-111.933262,41.242439],"type":"Point"}
}