{
  "type": "Feature",
  "properties": {
    "iso:country":"US",
    "sg:address":"2140 N 400 E",
    "sg:city":"Ogden",
    "sg:classifiers":[
        {
            "category":"Retail",
            "subcategory":"Funeral Services",
            "type":"Services"
        }
    ],
    "sg:phone":"+1 801 782 6666",
    "sg:postcode":"84414",
    "sg:province":"UT",
    "wof:name":"Lindquist Mortuary",
    "wof:placetype":"venue"
},
  "geometry": {"coordinates":[-111.96878599999999,41.297468],"type":"Point"}
}