{
  "type": "Feature",
  "properties": {
    "iso:country":"US",
    "sg:address":"6354 S 725 East St",
    "sg:city":"Salt Lake City",
    "sg:classifiers":[
        {
            "category":"Insurance",
            "subcategory":"Insurance Agent",
            "type":"Services"
        }
    ],
    "sg:phone":"+1 801 281 6615",
    "sg:postcode":"84107",
    "sg:province":"UT",
    "wof:name":"Benchmark Benefits Insurance",
    "wof:placetype":"venue"
},
  "geometry": {"coordinates":[-111.87223,40.635777],"type":"Point"}
}