{
  "type": "Feature",
  "properties": {
    "iso:country":"US",
    "sg:address":"95 S 100 W",
    "sg:city":"Logan",
    "sg:classifiers":[
        {
            "category":"Autos & Motor Vehicles",
            "subcategory":"Fuel & Gas Station",
            "type":"Retail Goods"
        }
    ],
    "sg:phone":"+1 435 753 0098",
    "sg:postcode":"84321",
    "sg:province":"UT",
    "sg:tags":[
        "station",
        "gasoline"
    ],
    "wof:name":"Bear Lake Chevron",
    "wof:placetype":"venue"
},
  "geometry": {"coordinates":[-111.83770800000001,41.729611],"type":"Point"}
}