{
  "type": "Feature",
  "properties": {
    "iso:country":"US",
    "sg:address":"1946 W 320 S",
    "sg:city":"Cedar City",
    "sg:classifiers":[
        {
            "category":"Organizations",
            "subcategory":"Labor Organization",
            "type":"Services"
        }
    ],
    "sg:phone":"+1 435 586 0723",
    "sg:postcode":"84720",
    "sg:province":"UT",
    "wof:name":"Russian Utah Trading Co Lc",
    "wof:placetype":"venue"
},
  "geometry": {"coordinates":[-113.08604,37.672058],"type":"Point"}
}