{
  "type": "Feature",
  "properties": {
    "iso:country":"US",
    "sg:address":"807 W 600 S",
    "sg:city":"Provo",
    "sg:classifiers":[
        {
            "category":"Manufacturing",
            "subcategory":"Lumber",
            "type":"Manufacturing & Wholesale Goods"
        }
    ],
    "sg:phone":"+1 801 852 6644",
    "sg:postcode":"84601",
    "sg:province":"UT",
    "sg:tags":[
        "government"
    ],
    "wof:name":"Provo Urban Forestry",
    "wof:placetype":"venue"
},
  "geometry": {"coordinates":[-111.67273400000001,40.225703],"type":"Point"}
}