{
  "type": "Feature",
  "properties": {
    "iso:country":"US",
    "sg:address":"5770 W 5100 S",
    "sg:city":"Salt Lake City",
    "sg:classifiers":[
        {
            "category":"Education",
            "subcategory":"School",
            "type":"Public Place"
        }
    ],
    "sg:phone":"+1 801 964 7955",
    "sg:postcode":"84118",
    "sg:province":"UT",
    "wof:name":"Silver Hills Elementary School",
    "wof:placetype":"venue"
},
  "geometry": {"coordinates":[-112.024764,40.656945],"type":"Point"}
}