{
  "type": "Feature",
  "properties": {
    "iso:country":"US",
    "sg:address":"2023 Bengal Hills Cove",
    "sg:city":"Salt Lake City",
    "sg:classifiers":[
        {
            "category":"Professional",
            "type":"Services"
        }
    ],
    "sg:phone":"+1 801 942 4551",
    "sg:postcode":"84121",
    "sg:province":"UT",
    "wof:name":"Mike Steph Inc",
    "wof:placetype":"venue"
},
  "geometry": {"coordinates":[-111.833636,40.617987],"type":"Point"}
}