{
  "type": "Feature",
  "properties": {
    "iso:country":"US",
    "sg:address":"2120 E 3900 S",
    "sg:city":"Salt Lake City",
    "sg:classifiers":[
        {
            "category":"Professional",
            "subcategory":"Advertising",
            "type":"Services"
        }
    ],
    "sg:phone":"+1 801 272 1281",
    "sg:postcode":"84124",
    "sg:province":"UT",
    "sg:tags":[
        "counselor"
    ],
    "wof:name":"Cause Marketing Solutions",
    "wof:placetype":"venue"
},
  "geometry": {"coordinates":[-111.83033399999999,40.687007],"type":"Point"}
}