{
  "type": "Feature",
  "properties": {
    "iso:country":"US",
    "sg:address":"850 Brush Wellman Rd",
    "sg:city":"Delta",
    "sg:classifiers":[
        {
            "category":"Utilities",
            "subcategory":"Electric",
            "type":"Services"
        }
    ],
    "sg:phone":"+1 435 864 4561",
    "sg:postcode":"84624",
    "sg:province":"UT",
    "wof:name":"I P S C",
    "wof:placetype":"venue"
},
  "geometry": {"coordinates":[-112.56885800000001,39.492913],"type":"Point"}
}