{
  "type": "Feature",
  "properties": {
    "iso:country":"US",
    "sg:address":"4059 Westlake Ave",
    "sg:city":"Salt Lake City",
    "sg:classifiers":[
        {
            "category":"Wholesale",
            "subcategory":"Electrical",
            "type":"Manufacturing & Wholesale Goods"
        }
    ],
    "sg:phone":"+1 801 399 9990",
    "sg:postcode":"84120",
    "sg:province":"UT",
    "wof:name":"Sewing Machine Doctor",
    "wof:placetype":"venue"
},
  "geometry": {"coordinates":[-111.986974,40.673402],"type":"Point"}
}