{
  "type": "Feature",
  "properties": {
    "iso:country":"US",
    "sg:address":"221 E 300 South St",
    "sg:city":"Gunnison",
    "sg:classifiers":[
        {
            "category":"Building & Trades",
            "subcategory":"Plumbing",
            "type":"Services"
        }
    ],
    "sg:phone":"+1 435 528 3988",
    "sg:postcode":"84634",
    "sg:province":"UT",
    "sg:tags":[
        "contractor"
    ],
    "wof:name":"Hill Heating & AC",
    "wof:placetype":"venue"
},
  "geometry": {"coordinates":[-111.811431,39.150728],"type":"Point"}
}