{
  "type": "Feature",
  "properties": {
    "iso:country":"US",
    "sg:address":"620 Medical Dr Ste 150",
    "sg:city":"Bountiful",
    "sg:classifiers":[
        {
            "category":"Health Services",
            "subcategory":"Doctor",
            "type":"Services"
        }
    ],
    "sg:phone":"+1 801 298 0574",
    "sg:postcode":"84010",
    "sg:province":"UT",
    "sg:tags":[
        "practice",
        "family"
    ],
    "wof:name":"Cope Family Medicine Patient Accounts",
    "wof:placetype":"venue"
},
  "geometry": {"coordinates":[-111.868878,40.88678],"type":"Point"}
}