{
  "type": "Feature",
  "properties": {
    "iso:country":"US",
    "sg:address":"170 N 200 W",
    "sg:city":"St George",
    "sg:classifiers":[
        {
            "category":"Manufacturing",
            "subcategory":"Printing",
            "type":"Manufacturing & Wholesale Goods"
        }
    ],
    "sg:phone":"+1 435 656 4800",
    "sg:postcode":"84770",
    "sg:province":"UT",
    "sg:tags":[
        "publisher"
    ],
    "wof:name":"Sierra West Publishing",
    "wof:placetype":"venue"
},
  "geometry": {"coordinates":[-113.587468,37.110401],"type":"Point"}
}