{
  "type": "Feature",
  "properties": {
    "iso:country":"US",
    "sg:address":"2586 N 850 W",
    "sg:city":"Provo",
    "sg:classifiers":[
        {
            "category":"Professional",
            "type":"Services"
        }
    ],
    "sg:phone":"+1 801 375 7741",
    "sg:postcode":"84604",
    "sg:province":"UT",
    "sg:tags":[
        "establishment"
    ],
    "wof:name":"Hill & Hill",
    "wof:placetype":"venue"
},
  "geometry": {"coordinates":[-111.673394,40.268588],"type":"Point"}
}