{
  "type": "Feature",
  "properties": {
    "iso:country":"US",
    "sg:address":"324 W Center St",
    "sg:city":"Logan",
    "sg:classifiers":[
        {
            "category":"Shopping",
            "subcategory":"Crafts & Fabrics",
            "type":"Retail Goods"
        }
    ],
    "sg:phone":"+1 435 752 1394",
    "sg:postcode":"84321",
    "sg:province":"UT",
    "sg:tags":[
        "personal",
        "leather",
        "sewing",
        "mfg"
    ],
    "wof:name":"Sew Original",
    "wof:placetype":"venue"
},
  "geometry": {"coordinates":[-111.843901,41.731454],"type":"Point"}
}