{
  "type": "Feature",
  "properties": {
    "iso:country":"US",
    "sg:address":"2845 US Hwy 40",
    "sg:city":"Roosevelt",
    "sg:classifiers":[
        {
            "category":"Freight",
            "type":"Transportation"
        }
    ],
    "sg:phone":"+1 435 823 5136",
    "sg:postcode":"84066",
    "sg:province":"UT",
    "sg:tags":[
        "field",
        "oil",
        "hauling"
    ],
    "wof:name":"Troy Murray Trucking",
    "wof:placetype":"venue"
},
  "geometry": {"coordinates":[-110.042793,40.267053],"type":"Point"}
}