{
  "type": "Feature",
  "properties": {
    "iso:country":"US",
    "sg:address":"1630 E 480 S",
    "sg:city":"Pleasant Grove",
    "sg:classifiers":[
        {
            "category":"Freight",
            "type":"Transportation"
        }
    ],
    "sg:phone":"+1 801 319 7408",
    "sg:postcode":"84062",
    "sg:province":"UT",
    "sg:tags":[
        "vendor",
        "commercial",
        "driver",
        "vehicle"
    ],
    "wof:name":"Larry W Christensen",
    "wof:placetype":"venue"
},
  "geometry": {"coordinates":[-111.703126,40.357866],"type":"Point"}
}