{
  "type": "Feature",
  "properties": {
    "iso:country":"US",
    "sg:address":"9164 Maison Dr",
    "sg:city":"Sandy",
    "sg:classifiers":[
        {
            "category":"Professional",
            "type":"Services"
        }
    ],
    "sg:phone":"+1 801 571 6767",
    "sg:postcode":"84093",
    "sg:province":"UT",
    "wof:name":"Contract Safety Services",
    "wof:placetype":"venue"
},
  "geometry": {"coordinates":[-111.838318,40.584969],"type":"Point"}
}