{
  "type": "Feature",
  "properties": {
    "iso:country":"US",
    "sg:address":"484 N 300 E",
    "sg:city":"Logan",
    "sg:classifiers":[
        {
            "category":"Insurance",
            "subcategory":"Insurance Agent",
            "type":"Services"
        }
    ],
    "sg:phone":"+1 435 752 2282",
    "sg:postcode":"84321",
    "sg:province":"UT",
    "wof:name":"Investors Marketing",
    "wof:placetype":"venue"
},
  "geometry": {"coordinates":[-111.82688899999999,41.739206],"type":"Point"}
}