{
  "type": "Feature",
  "properties": {
    "iso:country":"US",
    "sg:address":"1135 W Sunset Blvd",
    "sg:city":"St George",
    "sg:phone":"+1 435 628 1494",
    "sg:postcode":"84770",
    "sg:province":"UT",
    "sg:tags":[
        "leather"
    ],
    "wof:name":"Equine Supply",
    "wof:placetype":"venue"
},
  "geometry": {"coordinates":[-113.607732,37.124044],"type":"Point"}
}