{
  "type": "Feature",
  "properties": {
    "iso:country":"US",
    "sg:address":"720 E 10600 S",
    "sg:city":"Sandy",
    "sg:classifiers":[
        {
            "category":"Food & Beverages",
            "subcategory":"Candy",
            "type":"Retail Goods"
        },
        {
            "category":"Wholesale",
            "subcategory":"Groceries",
            "type":"Manufacturing & Wholesale Goods"
        }
    ],
    "sg:phone":"+1 801 572 7706",
    "sg:postcode":"84094",
    "sg:province":"UT",
    "sg:tags":[
        "confectionery"
    ],
    "wof:name":"Chocolate Cottage",
    "wof:placetype":"venue"
},
  "geometry": {"coordinates":[-111.87110699999999,40.558711],"type":"Point"}
}