{
  "type": "Feature",
  "properties": {
    "iso:country":"US",
    "sg:address":"1981 S Main St",
    "sg:city":"Lewiston",
    "sg:classifiers":[
        {
            "category":"Organizations",
            "subcategory":"Labor Organization",
            "type":"Services"
        }
    ],
    "sg:phone":"+1 435 258 2400",
    "sg:postcode":"84320",
    "sg:province":"UT",
    "wof:name":"Uinta Academy Lc",
    "wof:placetype":"venue"
},
  "geometry": {"coordinates":[-111.856202,41.939854],"type":"Point"}
}