{
  "type": "Feature",
  "properties": {
    "iso:country":"US",
    "sg:address":"350 S 400 E",
    "sg:city":"Salt Lake City",
    "sg:classifiers":[
        {
            "category":"Professional",
            "subcategory":"Advertising",
            "type":"Services"
        }
    ],
    "sg:phone":"+1 801 363 0310",
    "sg:postcode":"84111",
    "sg:province":"UT",
    "sg:tags":[
        "counselor",
        "agency"
    ],
    "wof:name":"J Walter Thompson Company",
    "wof:placetype":"venue"
},
  "geometry": {"coordinates":[-111.879712,40.761764],"type":"Point"}
}