{
  "type": "Feature",
  "properties": {
    "iso:country":"US",
    "sg:address":"451 N 1300 E",
    "sg:city":"St George",
    "sg:classifiers":[
        {
            "category":"Shopping",
            "subcategory":"Musical Instruments",
            "type":"Retail Goods"
        }
    ],
    "sg:phone":"+1 435 986 9666",
    "sg:postcode":"84770",
    "sg:province":"UT",
    "wof:name":"Summerhays Music",
    "wof:placetype":"venue"
},
  "geometry": {"coordinates":[-113.556488,37.115692],"type":"Point"}
}