{
  "type": "Feature",
  "properties": {
    "iso:country":"US",
    "sg:address":"65 E 1200 S",
    "sg:city":"Kamas",
    "sg:classifiers":[
        {
            "category":"Retail",
            "subcategory":"Repair Shop",
            "type":"Services"
        }
    ],
    "sg:phone":"+1 435 783 2197",
    "sg:postcode":"84036",
    "sg:province":"UT",
    "sg:tags":[
        "welding"
    ],
    "wof:name":"Atkinson Welding",
    "wof:placetype":"venue"
},
  "geometry": {"coordinates":[-111.275049,40.625312],"type":"Point"}
}