{
  "type": "Feature",
  "properties": {
    "iso:country":"US",
    "sg:address":"1148 S 300 W",
    "sg:city":"Salt Lake City",
    "sg:classifiers":[
        {
            "category":"Manufacturing",
            "subcategory":"Signs",
            "type":"Manufacturing & Wholesale Goods"
        }
    ],
    "sg:phone":"+1 801 487 8481",
    "sg:postcode":"84101",
    "sg:province":"UT",
    "sg:website":"www.yesco.com",
    "wof:name":"Young Electric Sign Co",
    "wof:placetype":"venue"
},
  "geometry": {"coordinates":[-111.89973500000001,40.744635],"type":"Point"}
}