{
  "type": "Feature",
  "properties": {
    "iso:country":"US",
    "sg:address":"260 S 200 W",
    "sg:city":"Salt Lake City",
    "sg:classifiers":[
        {
            "category":"Restaurant",
            "type":"Food & Drink"
        }
    ],
    "sg:menulink":"http://www.allmenus.com/ut/salt-lake-city/36207-settebello-pizzaria-napoletana/menu/",
    "sg:phone":"+1 801 322 3556",
    "sg:postcode":"84101",
    "sg:province":"UT",
    "sg:tags":[
        "american",
        "pizza"
    ],
    "wof:name":"Settebello Pizzaria Napoletana",
    "wof:placetype":"venue"
},
  "geometry": {"coordinates":[-111.896821,40.763638],"type":"Point"}
}