{
  "type": "Feature",
  "properties": {
    "iso:country":"US",
    "sg:address":"1590 W Center St",
    "sg:city":"Orem",
    "sg:classifiers":[
        {
            "category":"Manufacturing",
            "subcategory":"Metals",
            "type":"Manufacturing & Wholesale Goods"
        }
    ],
    "sg:phone":"+1 801 225 8986",
    "sg:postcode":"84057",
    "sg:province":"UT",
    "sg:tags":[
        "steel"
    ],
    "wof:name":"Grabber Transwest",
    "wof:placetype":"venue"
},
  "geometry": {"coordinates":[-111.733519,40.297201],"type":"Point"}
}