{
  "type": "Feature",
  "properties": {
    "iso:country":"US",
    "sg:address":"213 Princeton Dr",
    "sg:city":"Midvale",
    "sg:classifiers":[
        {
            "category":"Manufacturing",
            "subcategory":"Retail Goods",
            "type":"Manufacturing & Wholesale Goods"
        }
    ],
    "sg:phone":"+1 801 561 0367",
    "sg:postcode":"84047",
    "sg:province":"UT",
    "sg:tags":[
        "product",
        "mfg"
    ],
    "wof:name":"Salty Dog Manufacturing LLC",
    "wof:placetype":"venue"
},
  "geometry": {"coordinates":[-111.89812000000001,40.598975],"type":"Point"}
}