{
  "type": "Feature",
  "properties": {
    "iso:country":"US",
    "sg:address":"8456 W 3370 S",
    "sg:city":"Magna",
    "sg:classifiers":[
        {
            "category":"Wholesale",
            "subcategory":"Machinery & Supplies",
            "type":"Manufacturing & Wholesale Goods"
        }
    ],
    "sg:phone":"+1 801 252 0244",
    "sg:postcode":"84044",
    "sg:province":"UT",
    "sg:tags":[
        "industrial"
    ],
    "wof:name":"Big Ball Bearings",
    "wof:placetype":"venue"
},
  "geometry": {"coordinates":[-112.092843,40.698862],"type":"Point"}
}