{
  "type": "Feature",
  "properties": {
    "iso:country":"US",
    "sg:address":"3415 S 300 W",
    "sg:city":"South Salt Lake",
    "sg:classifiers":[
        {
            "category":"Shopping",
            "subcategory":"Discount & Variety Stores",
            "type":"Retail Goods"
        }
    ],
    "sg:phone":"+1 801 466 5635",
    "sg:postcode":"84115",
    "sg:province":"UT",
    "sg:tags":[
        "merchandise",
        "general"
    ],
    "wof:name":"Easy Money Auto Sales",
    "wof:placetype":"venue"
},
  "geometry": {"coordinates":[-111.899644,40.693049],"type":"Point"}
}