{
  "type": "Feature",
  "properties": {
    "iso:country":"US",
    "sg:address":"6471 Travis Jones Ln",
    "sg:city":"Salt Lake City",
    "sg:classifiers":[
        {
            "category":"Home & Garden",
            "subcategory":"Carpets & Floor Coverings",
            "type":"Retail Goods"
        }
    ],
    "sg:phone":"+1 801 685 0146",
    "sg:postcode":"84107",
    "sg:province":"UT",
    "wof:name":"Bigford & Associates",
    "wof:placetype":"venue"
},
  "geometry": {"coordinates":[-111.897541,40.632881],"type":"Point"}
}