{
  "type": "Feature",
  "properties": {
    "iso:country":"US",
    "sg:address":"1411 Anvil Dr",
    "sg:city":"Draper",
    "sg:classifiers":[
        {
            "category":"Retail",
            "subcategory":"Laundry & Dry Cleaning",
            "type":"Services"
        }
    ],
    "sg:phone":"+1 801 495 0313",
    "sg:postcode":"84020",
    "sg:province":"UT",
    "wof:name":"Distinctive Carpet Cleaning",
    "wof:placetype":"venue"
},
  "geometry": {"coordinates":[-111.849909,40.524173],"type":"Point"}
}