{
  "type": "Feature",
  "properties": {
    "iso:country":"US",
    "sg:address":"68 N Main St",
    "sg:city":"Brigham City",
    "sg:classifiers":[
        {
            "category":"Wholesale",
            "subcategory":"Auto Parts",
            "type":"Manufacturing & Wholesale Goods"
        }
    ],
    "sg:phone":"+1 435 723 5042",
    "sg:postcode":"84302",
    "sg:province":"UT",
    "sg:tags":[
        "automobile",
        "supply"
    ],
    "wof:name":"Parts House",
    "wof:placetype":"venue"
},
  "geometry": {"coordinates":[-112.01562199999999,41.511969],"type":"Point"}
}