{
  "type": "Feature",
  "properties": {
    "iso:country":"US",
    "sg:address":"915 Princeton Ave",
    "sg:city":"Salt Lake City",
    "sg:classifiers":[
        {
            "category":"Wholesale",
            "subcategory":"Sporting Goods",
            "type":"Manufacturing & Wholesale Goods"
        }
    ],
    "sg:phone":"+1 801 531 8814",
    "sg:postcode":"84105",
    "sg:province":"UT",
    "sg:tags":[
        "pool",
        "swimming"
    ],
    "wof:name":"Professional Pool Covers",
    "wof:placetype":"venue"
},
  "geometry": {"coordinates":[-111.86277,40.743963],"type":"Point"}
}