{
  "type": "Feature",
  "properties": {
    "iso:country":"US",
    "sg:address":"2107 W 2200 S",
    "sg:city":"Salt Lake City",
    "sg:classifiers":[
        {
            "category":"Manufacturing",
            "subcategory":"Rubber & Plastics",
            "type":"Manufacturing & Wholesale Goods"
        }
    ],
    "sg:phone":"+1 801 975 2656",
    "sg:postcode":"84119",
    "sg:province":"UT",
    "sg:tags":[
        "product",
        "mfg"
    ],
    "wof:name":"Alemar Precision Tooling",
    "wof:placetype":"venue"
},
  "geometry": {"coordinates":[-111.94689099999999,40.72324],"type":"Point"}
}