{
  "type": "Feature",
  "properties": {
    "iso:country":"US",
    "sg:address":"1128 Draper Pkwy",
    "sg:city":"Draper",
    "sg:classifiers":[
        {
            "category":"Restaurant",
            "type":"Food & Drink"
        }
    ],
    "sg:menulink":"http://www.allmenus.com/ut/salt-lake-city/132807-subway/menu/",
    "sg:phone":"+1 801 572 7601",
    "sg:postcode":"84020",
    "sg:province":"UT",
    "sg:tags":[
        "american",
        "sandwich"
    ],
    "wof:name":"Subway",
    "wof:placetype":"venue"
},
  "geometry": {"coordinates":[-111.85860599999999,40.528337],"type":"Point"}
}