{
  "type": "Feature",
  "properties": {
    "iso:country":"US",
    "sg:address":"2800 Adams St",
    "sg:city":"Salt Lake City",
    "sg:classifiers":[
        {
            "category":"Professional",
            "subcategory":"Accounting & Tax Preparation",
            "type":"Services"
        }
    ],
    "sg:phone":"+1 801 301 8137",
    "sg:postcode":"84115",
    "sg:province":"UT",
    "sg:tags":[
        "return",
        "filing"
    ],
    "wof:name":"Metro Trade LLC",
    "wof:placetype":"venue"
},
  "geometry": {"coordinates":[-111.878705,40.710471],"type":"Point"}
}