{
  "type": "Feature",
  "properties": {
    "iso:country":"US",
    "sg:address":"3856 W 5400 S",
    "sg:city":"Salt Lake City",
    "sg:classifiers":[
        {
            "category":"Insurance",
            "subcategory":"Insurance Agent",
            "type":"Services"
        }
    ],
    "sg:phone":"+1 801 955 0828",
    "sg:postcode":"84118",
    "sg:province":"UT",
    "sg:tags":[
        "life"
    ],
    "wof:name":"Primerica",
    "wof:placetype":"venue"
},
  "geometry": {"coordinates":[-111.986424,40.653136],"type":"Point"}
}