{
  "type": "Feature",
  "properties": {
    "iso:country":"US",
    "sg:address":"225 W Main St",
    "sg:city":"Delta",
    "sg:classifiers":[
        {
            "category":"Banks & Credit Unions",
            "subcategory":"Bank",
            "type":"Services"
        }
    ],
    "sg:phone":"+1 435 864 2737",
    "sg:postcode":"84624",
    "sg:province":"UT",
    "sg:tags":[
        "national",
        "commercial"
    ],
    "wof:name":"Wells Fargo",
    "wof:placetype":"venue"
},
  "geometry": {"coordinates":[-112.58093100000001,39.352318],"type":"Point"}
}