{
  "type": "Feature",
  "properties": {
    "iso:country":"US",
    "sg:address":"1961 Texas St",
    "sg:city":"Salt Lake City",
    "sg:classifiers":[
        {
            "category":"Arts & Performance",
            "subcategory":"Theater",
            "type":"Entertainment"
        }
    ],
    "sg:phone":"+1 801 485 0651",
    "sg:postcode":"84108",
    "sg:province":"UT",
    "sg:tags":[
        "theatrical"
    ],
    "wof:name":"Kennedy",
    "wof:placetype":"venue"
},
  "geometry": {"coordinates":[-111.821966,40.729149],"type":"Point"}
}