{
  "type": "Feature",
  "properties": {
    "iso:country":"US",
    "sg:address":"9371 Hawley Park Rd",
    "sg:city":"West Jordan",
    "sg:classifiers":[
        {
            "category":"Building & Trades",
            "subcategory":"Construction",
            "type":"Services"
        }
    ],
    "sg:phone":"+1 801 282 0608",
    "sg:postcode":"84088",
    "sg:province":"UT",
    "sg:tags":[
        "painter"
    ],
    "wof:name":"R L Swenson Painting Co",
    "wof:placetype":"venue"
},
  "geometry": {"coordinates":[-112.023993,40.57906],"type":"Point"}
}