{
  "type": "Feature",
  "properties": {
    "iso:country":"US",
    "sg:address":"717 S Nick Ln",
    "sg:city":"Price",
    "sg:classifiers":[
        {
            "category":"Building & Trades",
            "subcategory":"Construction",
            "type":"Services"
        }
    ],
    "sg:phone":"+1 435 637 0829",
    "sg:postcode":"84501",
    "sg:province":"UT",
    "sg:tags":[
        "general",
        "carport",
        "contractor"
    ],
    "wof:name":"Southeast Aluminum Company",
    "wof:placetype":"venue"
},
  "geometry": {"coordinates":[-110.794541,39.589824],"type":"Point"}
}