{
  "type": "Feature",
  "properties": {
    "iso:country":"US",
    "sg:address":"2325 Carbonville Rd",
    "sg:city":"Price",
    "sg:classifiers":[
        {
            "category":"Home & Garden",
            "subcategory":"Garden Supply",
            "type":"Retail Goods"
        }
    ],
    "sg:phone":"+1 435 637 6105",
    "sg:postcode":"84526",
    "sg:province":"UT",
    "sg:tags":[
        "nurseryman"
    ],
    "wof:name":"Plant Patch",
    "wof:placetype":"venue"
},
  "geometry": {"coordinates":[-110.856758,39.637987],"type":"Point"}
}