{
  "type": "Feature",
  "properties": {
    "iso:country":"US",
    "sg:address":"706 E 50 S",
    "sg:city":"American Fork",
    "sg:classifiers":[
        {
            "category":"Recreation",
            "type":"Entertainment"
        }
    ],
    "sg:phone":"+1 801 492 1995",
    "sg:postcode":"84003",
    "sg:province":"UT",
    "sg:tags":[
        "martial",
        "arts",
        "instruction"
    ],
    "wof:name":"American Studios-Martial Arts",
    "wof:placetype":"venue"
},
  "geometry": {"coordinates":[-111.779027,40.375602],"type":"Point"}
}