{
  "type": "Feature",
  "properties": {
    "iso:country":"US",
    "sg:address":"110 W 1200 S",
    "sg:city":"Logan",
    "sg:classifiers":[
        {
            "category":"Manufacturing",
            "subcategory":"Printing",
            "type":"Manufacturing & Wholesale Goods"
        }
    ],
    "sg:phone":"+1 435 753 6413",
    "sg:postcode":"84321",
    "sg:province":"UT",
    "sg:tags":[
        "commercial"
    ],
    "sg:website":"www.printwatkins.com",
    "wof:name":"Wasatch Envelopes",
    "wof:placetype":"venue"
},
  "geometry": {"coordinates":[-111.83659900000001,41.710148],"type":"Point"}
}