{
  "type": "Feature",
  "properties": {
    "iso:country":"US",
    "sg:address":"241 S Country Manor Ln",
    "sg:city":"Alpine",
    "sg:classifiers":[
        {
            "category":"Professional",
            "subcategory":"Management & Consulting",
            "type":"Services"
        }
    ],
    "sg:phone":"+1 801 756 7759",
    "sg:postcode":"84004",
    "sg:province":"UT",
    "wof:name":"Dealer Direct Services Inc",
    "wof:placetype":"venue"
},
  "geometry": {"coordinates":[-111.756721,40.450753],"type":"Point"}
}