{
  "type": "Feature",
  "properties": {
    "iso:country":"US",
    "sg:address":"1020 Pioneer Rd",
    "sg:city":"Draper",
    "sg:classifiers":[
        {
            "category":"Government",
            "subcategory":"Police Station",
            "type":"Public Place"
        }
    ],
    "sg:phone":"+1 801 576 6550",
    "sg:postcode":"84020",
    "sg:province":"UT",
    "sg:tags":[
        "department"
    ],
    "wof:name":"Draper Police Dept",
    "wof:placetype":"venue"
},
  "geometry": {"coordinates":[-111.85879,40.525245],"type":"Point"}
}