{
  "type": "Feature",
  "properties": {
    "iso:country":"US",
    "sg:address":"4740 S State St",
    "sg:city":"Salt Lake City",
    "sg:classifiers":[
        {
            "category":"Autos & Motor Vehicles",
            "subcategory":"Automobile Sales",
            "type":"Retail Goods"
        }
    ],
    "sg:phone":"+1 801 467 7227",
    "sg:postcode":"84107",
    "sg:province":"UT",
    "sg:tags":[
        "car",
        "dealer"
    ],
    "wof:name":"Car Center",
    "wof:placetype":"venue"
},
  "geometry": {"coordinates":[-111.888351,40.667058],"type":"Point"}
}