{
  "type": "Feature",
  "properties": {
    "iso:country":"US",
    "sg:address":"55 S 500 E",
    "sg:city":"Heber City",
    "sg:classifiers":[
        {
            "category":"Education",
            "subcategory":"College",
            "type":"Public Place"
        }
    ],
    "sg:phone":"+1 435 654 3211",
    "sg:postcode":"84032",
    "sg:province":"UT",
    "sg:tags":[
        "academic",
        "school"
    ],
    "wof:name":"Utah State University Ext Svc",
    "wof:placetype":"venue"
},
  "geometry": {"coordinates":[-111.404692,40.506816],"type":"Point"}
}