{
  "type": "Feature",
  "properties": {
    "iso:country":"US",
    "sg:address":"1557 S 1900 E",
    "sg:city":"Salt Lake City",
    "sg:classifiers":[
        {
            "category":"Professional",
            "subcategory":"Art Services",
            "type":"Services"
        }
    ],
    "sg:phone":"+1 801 581 0334",
    "sg:postcode":"84108",
    "sg:province":"UT",
    "sg:tags":[
        "calligrapher"
    ],
    "wof:name":"Letter Factory",
    "wof:placetype":"venue"
},
  "geometry": {"coordinates":[-111.83643499999999,40.734759],"type":"Point"}
}