{
  "type": "Feature",
  "properties": {
    "iso:country":"US",
    "sg:address":"3312 Homestead Rd",
    "sg:city":"Park City",
    "sg:classifiers":[
        {
            "category":"Personal",
            "type":"Services"
        }
    ],
    "sg:phone":"+1 801 463 0500",
    "sg:postcode":"84098",
    "sg:province":"UT",
    "wof:name":"Warehouse",
    "wof:placetype":"venue"
},
  "geometry": {"coordinates":[-111.578146,40.762364],"type":"Point"}
}