{
  "type": "Feature",
  "properties": {
    "iso:country":"US",
    "sg:address":"2889 E 3300 S",
    "sg:city":"Salt Lake City",
    "sg:classifiers":[
        {
            "category":"Banks & Credit Unions",
            "subcategory":"Investment Brokerage",
            "type":"Services"
        }
    ],
    "sg:phone":"+1 801 463 4900",
    "sg:postcode":"84109",
    "sg:province":"UT",
    "sg:tags":[
        "security"
    ],
    "wof:name":"Edward Jones Co",
    "wof:placetype":"venue"
},
  "geometry": {"coordinates":[-111.81454600000001,40.699931],"type":"Point"}
}