{
  "type": "Feature",
  "properties": {
    "iso:country":"US",
    "sg:address":"397 N 300 E",
    "sg:city":"Bountiful",
    "sg:classifiers":[
        {
            "category":"Building & Trades",
            "subcategory":"Construction",
            "type":"Services"
        }
    ],
    "sg:phone":"+1 801 296 1173",
    "sg:postcode":"84010",
    "sg:province":"UT",
    "sg:tags":[
        "contractor"
    ],
    "wof:name":"Bedrock Masonry",
    "wof:placetype":"venue"
},
  "geometry": {"coordinates":[-111.874004,40.89257],"type":"Point"}
}