{
  "type": "Feature",
  "properties": {
    "iso:country":"US",
    "sg:address":"1670 E 1300 S",
    "sg:city":"Salt Lake City",
    "sg:classifiers":[
        {
            "category":"Manufacturing",
            "subcategory":"Apparel",
            "type":"Manufacturing & Wholesale Goods"
        },
        {
            "category":"Shopping",
            "subcategory":"Clothing, Apparel, & Fashions",
            "type":"Retail Goods"
        }
    ],
    "sg:phone":"+1 801 582 5010",
    "sg:postcode":"84105",
    "sg:province":"UT",
    "sg:tags":[
        "shop",
        "bridal",
        "dress",
        "mfg"
    ],
    "wof:name":"Penelope's",
    "wof:placetype":"venue"
},
  "geometry": {"coordinates":[-111.84260399999999,40.741567],"type":"Point"}
}