{
  "type": "Feature",
  "properties": {
    "iso:country":"US",
    "sg:address":"344 S 500 W",
    "sg:city":"Bountiful",
    "sg:classifiers":[
        {
            "category":"Shopping",
            "subcategory":"Hobbies, Toys, & Games",
            "type":"Retail Goods"
        }
    ],
    "sg:phone":"+1 801 292 4923",
    "sg:postcode":"84010",
    "sg:province":"UT",
    "wof:name":"Blow Out Toys",
    "wof:placetype":"venue"
},
  "geometry": {"coordinates":[-111.892296,40.887013],"type":"Point"}
}