{
  "type": "Feature",
  "properties": {
    "iso:country":"US",
    "sg:address":"3735 W 1000 N",
    "sg:city":"Tremonton",
    "sg:classifiers":[
        {
            "category":"Manufacturing",
            "subcategory":"Tools & Machinery",
            "type":"Manufacturing & Wholesale Goods"
        }
    ],
    "sg:phone":"+1 435 257 5388",
    "sg:postcode":"84337",
    "sg:province":"UT",
    "sg:tags":[
        "pattern",
        "industrial",
        "mfg"
    ],
    "wof:name":"Pattern Gal Express",
    "wof:placetype":"venue"
},
  "geometry": {"coordinates":[-112.201437,41.725388],"type":"Point"}
}