{
  "type": "Feature",
  "properties": {
    "iso:country":"US",
    "sg:address":"842 E 280 S",
    "sg:city":"Orem",
    "sg:classifiers":[
        {
            "category":"Professional",
            "subcategory":"Management & Consulting",
            "type":"Services"
        }
    ],
    "sg:phone":"+1 801 226 5079",
    "sg:postcode":"84097",
    "sg:province":"UT",
    "sg:tags":[
        "business"
    ],
    "wof:name":"Usable Software",
    "wof:placetype":"venue"
},
  "geometry": {"coordinates":[-111.67614500000001,40.291749],"type":"Point"}
}