{
  "type": "Feature",
  "properties": {
    "iso:country":"US",
    "sg:address":"1540 N Hill Field Rd",
    "sg:city":"Layton",
    "sg:classifiers":[
        {
            "category":"Restaurant",
            "type":"Food & Drink"
        }
    ],
    "sg:menulink":"http://www.allmenus.com/ut/north-davis/132824-subway/menu/",
    "sg:phone":"+1 801 547 1497",
    "sg:postcode":"84041",
    "sg:province":"UT",
    "sg:tags":[
        "american",
        "sandwich"
    ],
    "wof:name":"Subway",
    "wof:placetype":"venue"
},
  "geometry": {"coordinates":[-111.97340699999999,41.082523],"type":"Point"}
}