{
  "type": "Feature",
  "properties": {
    "iso:country":"US",
    "sg:address":"788 W 17th St",
    "sg:city":"Ogden",
    "sg:classifiers":[
        {
            "category":"Wholesale",
            "subcategory":"Auto Parts",
            "type":"Manufacturing & Wholesale Goods"
        }
    ],
    "sg:phone":"+1 801 627 1956",
    "sg:postcode":"84404",
    "sg:province":"UT",
    "sg:tags":[
        "material",
        "used"
    ],
    "wof:name":"A Howell Wrecking",
    "wof:placetype":"venue"
},
  "geometry": {"coordinates":[-112.00859800000001,41.237528],"type":"Point"}
}