{
  "type": "Feature",
  "properties": {
    "iso:country":"US",
    "sg:address":"1245 Deer Valley Dr",
    "sg:city":"Park City",
    "sg:classifiers":[
        {
            "category":"Real Estate",
            "subcategory":"Real Estate Agent",
            "type":"Services"
        }
    ],
    "sg:phone":"+1 435 649 6606",
    "sg:postcode":"84060",
    "sg:province":"UT",
    "sg:tags":[
        "buyer",
        "broker"
    ],
    "sg:website":"www.resortquestparkcity.com",
    "wof:name":"Resort Property Management Inc",
    "wof:placetype":"venue"
},
  "geometry": {"coordinates":[-111.50507500000001,40.656673],"type":"Point"}
}