{
  "type": "Feature",
  "properties": {
    "iso:country":"US",
    "sg:address":"459 Nichols Ln",
    "sg:city":"Moab",
    "sg:classifiers":[
        {
            "category":"Professional",
            "type":"Services"
        }
    ],
    "sg:phone":"+1 435 259 6622",
    "sg:postcode":"84532",
    "sg:province":"UT",
    "sg:tags":[
        "establishment"
    ],
    "wof:name":"Settle J",
    "wof:placetype":"venue"
},
  "geometry": {"coordinates":[-109.542334,38.571518],"type":"Point"}
}