{
  "type": "Feature",
  "properties": {
    "iso:country":"US",
    "sg:address":"1198 Murphy Ln",
    "sg:city":"Moab",
    "sg:classifiers":[
        {
            "category":"Building & Trades",
            "subcategory":"Construction",
            "type":"Services"
        }
    ],
    "sg:phone":"+1 435 259 7807",
    "sg:postcode":"84532",
    "sg:province":"UT",
    "sg:tags":[
        "mfg",
        "custom",
        "cabinet"
    ],
    "wof:name":"Heatons Custom Cabinets",
    "wof:placetype":"venue"
},
  "geometry": {"coordinates":[-109.52200499999999,38.555798],"type":"Point"}
}