{
  "type": "Feature",
  "properties": {
    "iso:country":"US",
    "sg:address":"162 E 200 S",
    "sg:city":"Hurricane",
    "sg:classifiers":[
        {
            "category":"Building & Trades",
            "subcategory":"Construction",
            "type":"Services"
        }
    ],
    "sg:phone":"+1 435 635 7361",
    "sg:postcode":"84737",
    "sg:province":"UT",
    "sg:tags":[
        "house"
    ],
    "wof:name":"Allen Campbell Construction",
    "wof:placetype":"venue"
},
  "geometry": {"coordinates":[-113.285754,37.173539],"type":"Point"}
}