{
  "type": "Feature",
  "properties": {
    "iso:country":"US",
    "sg:address":"1587 S Main St",
    "sg:city":"Salt Lake City",
    "sg:classifiers":[
        {
            "category":"Communications",
            "subcategory":"Film & Video Production",
            "type":"Services"
        }
    ],
    "sg:phone":"+1 801 463 9292",
    "sg:postcode":"84115",
    "sg:province":"UT",
    "sg:tags":[
        "motion",
        "taping"
    ],
    "sg:website":"www.whiterabbitproductions.com",
    "wof:name":"White Rabbit Productions Inc",
    "wof:placetype":"venue"
},
  "geometry": {"coordinates":[-111.890991,40.733591],"type":"Point"}
}