{
  "type": "Feature",
  "properties": {
    "iso:country":"US",
    "sg:address":"876 W 12th St",
    "sg:city":"Ogden",
    "sg:classifiers":[
        {
            "category":"Health Services",
            "subcategory":"Chiropractor",
            "type":"Services"
        }
    ],
    "sg:phone":"+1 801 399 9802",
    "sg:postcode":"84404",
    "sg:province":"UT",
    "wof:name":"Adam Doxey",
    "wof:placetype":"venue"
},
  "geometry": {"coordinates":[-111.999616,41.24456],"type":"Point"}
}