{
  "type": "Feature",
  "properties": {
    "iso:country":"US",
    "sg:address":"57 N 100 E",
    "sg:city":"Roosevelt",
    "sg:classifiers":[
        {
            "category":"Government",
            "subcategory":"Court House",
            "type":"Public Place"
        }
    ],
    "sg:phone":"+1 435 722 0995",
    "sg:postcode":"84066",
    "sg:province":"UT",
    "sg:tags":[
        "county",
        "counsel"
    ],
    "wof:name":"Duchesne County Attorney",
    "wof:placetype":"venue"
},
  "geometry": {"coordinates":[-109.990346,40.300841],"type":"Point"}
}