{
  "type": "Feature",
  "properties": {
    "iso:country":"US",
    "sg:address":"1701 W Riverdale Rd",
    "sg:city":"Roy",
    "sg:classifiers":[
        {
            "category":"Freight",
            "type":"Transportation"
        }
    ],
    "sg:phone":"+1 801 773 5090",
    "sg:postcode":"84067",
    "sg:province":"UT",
    "sg:tags":[
        "general"
    ],
    "wof:name":"A A Alpine Storage",
    "wof:placetype":"venue"
},
  "geometry": {"coordinates":[-112.021407,41.169979],"type":"Point"}
}