{
  "type": "Feature",
  "properties": {
    "iso:country":"US",
    "sg:address":"2685 Foothill Dr",
    "sg:city":"Provo",
    "sg:classifiers":[
        {
            "category":"Organizations",
            "subcategory":"Labor Organization",
            "type":"Services"
        }
    ],
    "sg:phone":"+1 801 377 1051",
    "sg:postcode":"84604",
    "sg:province":"UT",
    "wof:name":"Kkl Development Lc",
    "wof:placetype":"venue"
},
  "geometry": {"coordinates":[-111.634237,40.26954],"type":"Point"}
}