{
  "type": "Feature",
  "properties": {
    "iso:country":"US",
    "sg:address":"45 W University Pkwy",
    "sg:city":"Orem",
    "sg:classifiers":[
        {
            "category":"Autos & Motor Vehicles",
            "subcategory":"Automobile Sales",
            "type":"Retail Goods"
        }
    ],
    "sg:phone":"+1 801 225 6866",
    "sg:postcode":"84058",
    "sg:province":"UT",
    "sg:tags":[
        "car",
        "dealer"
    ],
    "sg:website":"www.barberbrothers.com",
    "wof:name":"B Arber Brothers Mitsubishi",
    "wof:placetype":"venue"
},
  "geometry": {"coordinates":[-111.703867,40.273513],"type":"Point"}
}