{
  "type": "Feature",
  "properties": {
    "iso:country":"US",
    "sg:address":"1101 University Village",
    "sg:city":"Salt Lake City",
    "sg:classifiers":[
        {
            "category":"Professional",
            "subcategory":"Management & Consulting",
            "type":"Services"
        }
    ],
    "sg:phone":"+1 801 525 1994",
    "sg:postcode":"84108",
    "sg:province":"UT",
    "sg:tags":[
        "consultant",
        "business"
    ],
    "wof:name":"Academic Clothing Co",
    "wof:placetype":"venue"
},
  "geometry": {"coordinates":[-111.828067,40.753425],"type":"Point"}
}