{
  "type": "Feature",
  "properties": {
    "iso:country":"US",
    "sg:address":"2436 Allison Way",
    "sg:city":"Syracuse",
    "sg:classifiers":[
        {
            "category":"Social Services",
            "subcategory":"Child Care",
            "type":"Services"
        }
    ],
    "sg:phone":"+1 801 774 8429",
    "sg:postcode":"84075",
    "sg:province":"UT",
    "sg:tags":[
        "day"
    ],
    "wof:name":"Performance Preschool",
    "wof:placetype":"venue"
},
  "geometry": {"coordinates":[-112.056946,41.078045],"type":"Point"}
}