{
  "type": "Feature",
  "properties": {
    "iso:country":"US",
    "sg:address":"296 S 2390 W",
    "sg:city":"Provo",
    "sg:classifiers":[
        {
            "category":"Professional",
            "subcategory":"Business Services",
            "type":"Services"
        }
    ],
    "sg:phone":"+1 801 343 7712",
    "sg:postcode":"84601",
    "sg:province":"UT",
    "wof:name":"Nasio Viliami",
    "wof:placetype":"venue"
},
  "geometry": {"coordinates":[-111.700746,40.229791],"type":"Point"}
}