{
  "type": "Feature",
  "properties": {
    "iso:country":"US",
    "sg:address":"1002 W 1500 N",
    "sg:city":"Orem",
    "sg:classifiers":[
        {
            "category":"Building & Trades",
            "subcategory":"Construction",
            "type":"Services"
        }
    ],
    "sg:phone":"+1 801 226 5311",
    "sg:postcode":"84057",
    "sg:province":"UT",
    "sg:tags":[
        "contractor"
    ],
    "wof:name":"CLAYCO Inc",
    "wof:placetype":"venue"
},
  "geometry": {"coordinates":[-111.72113299999999,40.324583],"type":"Point"}
}