{
  "type": "Feature",
  "properties": {
    "iso:country":"US",
    "sg:address":"2725 E 3300 S",
    "sg:city":"Salt Lake City",
    "sg:classifiers":[
        {
            "category":"Real Estate",
            "subcategory":"Architect",
            "type":"Services"
        }
    ],
    "sg:phone":"+1 801 832 9292",
    "sg:postcode":"84109",
    "sg:province":"UT",
    "wof:name":"Green Associates",
    "wof:placetype":"venue"
},
  "geometry": {"coordinates":[-111.810625,40.69992],"type":"Point"}
}