{
  "type": "Feature",
  "properties": {
    "iso:country":"US",
    "sg:address":"304 W 400 S",
    "sg:city":"Manti",
    "sg:classifiers":[
        {
            "category":"Wholesale",
            "subcategory":"Durable Goods & Equipment",
            "type":"Manufacturing & Wholesale Goods"
        }
    ],
    "sg:phone":"+1 435 835 7729",
    "sg:postcode":"84642",
    "sg:province":"UT",
    "wof:name":"Portacase International",
    "wof:placetype":"venue"
},
  "geometry": {"coordinates":[-111.644476,39.259726],"type":"Point"}
}