{
  "type": "Feature",
  "properties": {
    "iso:country":"US",
    "sg:address":"1210 Hillsden Dr",
    "sg:city":"Layton",
    "sg:classifiers":[
        {
            "category":"Education",
            "subcategory":"Special Training",
            "type":"Public Place"
        }
    ],
    "sg:phone":"+1 801 547 0121",
    "sg:postcode":"84040",
    "sg:province":"UT",
    "wof:name":"Pro Show Music Studio",
    "wof:placetype":"venue"
},
  "geometry": {"coordinates":[-111.943657,41.068748],"type":"Point"}
}