{
  "type": "Feature",
  "properties": {
    "iso:country":"US",
    "sg:address":"85 Quarter Dr",
    "sg:city":"Logan",
    "sg:classifiers":[
        {
            "category":"Professional",
            "type":"Services"
        }
    ],
    "sg:phone":"+1 435 258 2833",
    "sg:postcode":"84321",
    "sg:province":"UT",
    "wof:name":"Navajo Sheep Project Service",
    "wof:placetype":"venue"
},
  "geometry": {"coordinates":[-111.836296,41.662707],"type":"Point"}
}