{
  "type": "Feature",
  "properties": {
    "iso:country":"US",
    "sg:address":"471 W 600 N",
    "sg:city":"Tremonton",
    "sg:classifiers":[
        {
            "category":"Health Services",
            "subcategory":"Chiropractor",
            "type":"Services"
        }
    ],
    "sg:phone":"+1 435 257 2131",
    "sg:postcode":"84337",
    "sg:province":"UT",
    "wof:name":"Rigby Chiropractic",
    "wof:placetype":"venue"
},
  "geometry": {"coordinates":[-112.17431000000001,41.718694],"type":"Point"}
}