{
  "type": "Feature",
  "properties": {
    "iso:country":"US",
    "sg:address":"195 W 1100 S",
    "sg:city":"Brigham City",
    "sg:classifiers":[
        {
            "category":"Government",
            "subcategory":"Office",
            "type":"Public Place"
        }
    ],
    "sg:phone":"+1 435 734 3300",
    "sg:postcode":"84302",
    "sg:province":"UT",
    "wof:name":"Extension Service",
    "wof:placetype":"venue"
},
  "geometry": {"coordinates":[-112.01906700000001,41.486481],"type":"Point"}
}