{
  "type": "Feature",
  "properties": {
    "iso:country":"US",
    "sg:address":"25 Appaloosa Loop",
    "sg:city":"Cedar City",
    "sg:classifiers":[
        {
            "category":"Building & Trades",
            "subcategory":"Construction",
            "type":"Services"
        }
    ],
    "sg:phone":"+1 435 586 0443",
    "sg:postcode":"84720",
    "sg:province":"UT",
    "sg:tags":[
        "house"
    ],
    "wof:name":"Last Chance Construction Inc",
    "wof:placetype":"venue"
},
  "geometry": {"coordinates":[-113.065668,37.744106],"type":"Point"}
}