{
  "type": "Feature",
  "properties": {
    "iso:country":"US",
    "sg:address":"4814 N 600 E",
    "sg:city":"Cedar City",
    "sg:classifiers":[
        {
            "category":"Mining & Drilling",
            "type":"Manufacturing & Wholesale Goods"
        }
    ],
    "sg:phone":"+1 435 586 3061",
    "sg:postcode":"84720",
    "sg:province":"UT",
    "sg:tags":[
        "water",
        "well"
    ],
    "wof:name":"Grimshaw & Sons Well Drilling",
    "wof:placetype":"venue"
},
  "geometry": {"coordinates":[-113.050712,37.764997],"type":"Point"}
}