{
  "type": "Feature",
  "properties": {
    "iso:country":"US",
    "sg:address":"6133 Carriage Park Cir",
    "sg:city":"Salt Lake City",
    "sg:classifiers":[
        {
            "category":"Professional",
            "subcategory":"Management & Consulting",
            "type":"Services"
        }
    ],
    "sg:phone":"+1 801 272 1590",
    "sg:postcode":"84121",
    "sg:province":"UT",
    "sg:tags":[
        "business"
    ],
    "wof:name":"Leon Hammond",
    "wof:placetype":"venue"
},
  "geometry": {"coordinates":[-111.84029099999999,40.639267],"type":"Point"}
}