{
  "type": "Feature",
  "properties": {
    "iso:country":"US",
    "sg:address":"9255 S 255 W",
    "sg:city":"Sandy",
    "sg:classifiers":[
        {
            "category":"Wholesale",
            "subcategory":"Machinery & Supplies",
            "type":"Manufacturing & Wholesale Goods"
        }
    ],
    "sg:phone":"+1 801 233 0410",
    "sg:postcode":"84070",
    "sg:province":"UT",
    "sg:tags":[
        "dry wall",
        "contractor"
    ],
    "wof:name":"Calply",
    "wof:placetype":"venue"
},
  "geometry": {"coordinates":[-111.89917,40.580933],"type":"Point"}
}