{
  "type": "Feature",
  "properties": {
    "iso:country":"US",
    "sg:address":"1350 E 1450 S",
    "sg:city":"Clearfield",
    "sg:classifiers":[
        {
            "category":"Government",
            "subcategory":"Court House",
            "type":"Public Place"
        }
    ],
    "sg:phone":"+1 801 776 7392",
    "sg:postcode":"84015",
    "sg:province":"UT",
    "sg:tags":[
        "state",
        "counsel"
    ],
    "wof:name":"Attorney General",
    "wof:placetype":"venue"
},
  "geometry": {"coordinates":[-112.000457,41.092819],"type":"Point"}
}