{
  "type": "Feature",
  "properties": {
    "iso:country":"US",
    "sg:address":"479 E 2100 S",
    "sg:city":"Salt Lake City",
    "sg:classifiers":[
        {
            "category":"Home & Garden",
            "subcategory":"Furniture",
            "type":"Retail Goods"
        }
    ],
    "sg:phone":"+1 801 255 3117",
    "sg:postcode":"84115",
    "sg:province":"UT",
    "sg:tags":[
        "futon"
    ],
    "sg:website":"www.futonsandbeds.com",
    "wof:name":"Futons & Beds",
    "wof:placetype":"venue"
},
  "geometry": {"coordinates":[-111.878676,40.725516],"type":"Point"}
}