{
  "type": "Feature",
  "properties": {
    "iso:country":"US",
    "sg:address":"351 N 100 E",
    "sg:city":"Nephi",
    "sg:classifiers":[
        {
            "category":"Organizations",
            "subcategory":"Religious Organization",
            "type":"Services"
        }
    ],
    "sg:phone":"+1 435 623 0721",
    "sg:postcode":"84648",
    "sg:province":"UT",
    "wof:name":"Church Jesus Chrst Later Day",
    "wof:placetype":"venue"
},
  "geometry": {"coordinates":[-111.834232,39.714242],"type":"Point"}
}