{
  "type": "Feature",
  "properties": {
    "iso:country":"US",
    "sg:address":"949 Fairview Ave",
    "sg:city":"Salt Lake City",
    "sg:classifiers":[
        {
            "category":"Professional",
            "type":"Services"
        }
    ],
    "sg:phone":"+1 801 581 1286",
    "sg:postcode":"84105",
    "sg:province":"UT",
    "sg:tags":[
        "establishment"
    ],
    "wof:name":"Arndtkevin E",
    "wof:placetype":"venue"
},
  "geometry": {"coordinates":[-111.845426,40.748105],"type":"Point"}
}