{
  "type": "Feature",
  "properties": {
    "iso:country":"US",
    "sg:address":"515 Pickett Cir",
    "sg:city":"Salt Lake City",
    "sg:classifiers":[
        {
            "category":"Home & Garden",
            "subcategory":"Building Materials",
            "type":"Retail Goods"
        }
    ],
    "sg:phone":"+1 801 972 1717",
    "sg:postcode":"84115",
    "sg:province":"UT",
    "sg:tags":[
        "plumbing",
        "fixture",
        "supply"
    ],
    "wof:name":"Euro Craft Kitchen & Bath Dsgn",
    "wof:placetype":"venue"
},
  "geometry": {"coordinates":[-111.906327,40.730873],"type":"Point"}
}