{
  "type": "Feature",
  "properties": {
    "iso:country":"US",
    "sg:address":"533 N 1230 E",
    "sg:city":"Orem",
    "sg:classifiers":[
        {
            "category":"Organizations",
            "subcategory":"Labor Organization",
            "type":"Services"
        }
    ],
    "sg:phone":"+1 801 225 4562",
    "sg:postcode":"84097",
    "sg:province":"UT",
    "wof:name":"T&D Heppler Investments Lc",
    "wof:placetype":"venue"
},
  "geometry": {"coordinates":[-111.666652,40.30773],"type":"Point"}
}