{
  "type": "Feature",
  "properties": {
    "iso:country":"US",
    "sg:address":"11705 Littler Rd",
    "sg:city":"Sandy",
    "sg:classifiers":[
        {
            "category":"Professional",
            "subcategory":"Management & Consulting",
            "type":"Services"
        }
    ],
    "sg:phone":"+1 801 571 3757",
    "sg:postcode":"84092",
    "sg:province":"UT",
    "sg:tags":[
        "business"
    ],
    "wof:name":"Kjr Management & Consulting LL",
    "wof:placetype":"venue"
},
  "geometry": {"coordinates":[-111.852535,40.539667],"type":"Point"}
}