{
  "type": "Feature",
  "properties": {
    "iso:country":"US",
    "sg:address":"1380 Navajo St",
    "sg:city":"Salt Lake City",
    "sg:classifiers":[
        {
            "category":"Education",
            "subcategory":"School",
            "type":"Public Place"
        }
    ],
    "sg:phone":"+1 801 974 8315",
    "sg:postcode":"84104",
    "sg:province":"UT",
    "wof:name":"Mountain View Elementary Schl",
    "wof:placetype":"venue"
},
  "geometry": {"coordinates":[-111.929526,40.739145],"type":"Point"}
}