{
  "type": "Feature",
  "properties": {
    "iso:country":"US",
    "sg:address":"6 W Main St",
    "sg:city":"Richmond",
    "sg:classifiers":[
        {
            "category":"Education",
            "subcategory":"Library",
            "type":"Public Place"
        }
    ],
    "sg:phone":"+1 435 258 5525",
    "sg:postcode":"84333",
    "sg:province":"UT",
    "wof:name":"Richmond City Library",
    "wof:placetype":"venue"
},
  "geometry": {"coordinates":[-111.811435,41.922731],"type":"Point"}
}