{
  "type": "Feature",
  "properties": {
    "iso:country":"US",
    "sg:address":"57 S 900 W",
    "sg:city":"Salt Lake City",
    "sg:classifiers":[
        {
            "category":"Manufacturing",
            "subcategory":"Signs",
            "type":"Manufacturing & Wholesale Goods"
        }
    ],
    "sg:phone":"+1 801 350 0542",
    "sg:postcode":"84104",
    "sg:province":"UT",
    "sg:tags":[
        "specialty",
        "mfg"
    ],
    "wof:name":"Lopez Enterprises Inc",
    "wof:placetype":"venue"
},
  "geometry": {"coordinates":[-111.91675600000001,40.768346],"type":"Point"}
}