{
  "type": "Feature",
  "properties": {
    "iso:country":"US",
    "sg:address":"4015 S West Temple",
    "sg:city":"Murray",
    "sg:classifiers":[
        {
            "category":"Retail",
            "subcategory":"Auto Repair",
            "type":"Services"
        }
    ],
    "sg:phone":"+1 801 261 4900",
    "sg:postcode":"84107",
    "sg:province":"UT",
    "sg:tags":[
        "body",
        "automobile",
        "painting",
        "general"
    ],
    "wof:name":"Royal Autobody & Paint",
    "wof:placetype":"venue"
},
  "geometry": {"coordinates":[-111.893896,40.686796],"type":"Point"}
}