{
  "type": "Feature",
  "properties": {
    "iso:country":"US",
    "sg:address":"1684 S Mill Rd",
    "sg:city":"Spanish Fork",
    "sg:classifiers":[
        {
            "category":"Wholesale",
            "subcategory":"Farm Supplies",
            "type":"Manufacturing & Wholesale Goods"
        }
    ],
    "sg:phone":"+1 801 798 2060",
    "sg:postcode":"84660",
    "sg:province":"UT",
    "sg:tags":[
        "livestock"
    ],
    "wof:name":"Joe Warren",
    "wof:placetype":"venue"
},
  "geometry": {"coordinates":[-111.672237,40.093368],"type":"Point"}
}