{
  "type": "Feature",
  "properties": {
    "iso:country":"US",
    "sg:address":"211 S 200 E",
    "sg:city":"Price",
    "sg:classifiers":[
        {
            "category":"Professional",
            "subcategory":"Credit Reporting & Collection",
            "type":"Services"
        }
    ],
    "sg:phone":"+1 435 637 8500",
    "sg:postcode":"84501",
    "sg:province":"UT",
    "sg:tags":[
        "agency"
    ],
    "wof:name":"Professional Collections",
    "wof:placetype":"venue"
},
  "geometry": {"coordinates":[-110.80722400000001,39.596526],"type":"Point"}
}