{
  "type": "Feature",
  "properties": {
    "iso:country":"US",
    "sg:address":"1934 S 200 E",
    "sg:city":"Clearfield",
    "sg:classifiers":[
        {
            "category":"Wholesale",
            "subcategory":"Durable Goods & Equipment",
            "type":"Manufacturing & Wholesale Goods"
        }
    ],
    "sg:phone":"+1 801 728 4710",
    "sg:postcode":"84015",
    "sg:province":"UT",
    "wof:name":"Steves Online Wholesale",
    "wof:placetype":"venue"
},
  "geometry": {"coordinates":[-112.022505,41.085259],"type":"Point"}
}