{
  "type": "Feature",
  "properties": {
    "iso:country":"US",
    "sg:address":"12091 Cattail Cir",
    "sg:city":"Draper",
    "sg:classifiers":[
        {
            "category":"Building & Trades",
            "subcategory":"Construction",
            "type":"Services"
        }
    ],
    "sg:phone":"+1 801 571 5325",
    "sg:postcode":"84020",
    "sg:province":"UT",
    "sg:tags":[
        "contractor"
    ],
    "wof:name":"Nation Wide Builders Inc",
    "wof:placetype":"venue"
},
  "geometry": {"coordinates":[-111.863516,40.531381],"type":"Point"}
}