{
  "type": "Feature",
  "properties": {
    "iso:country":"US",
    "sg:address":"9325 S Redwood Rd",
    "sg:city":"West Jordan",
    "sg:classifiers":[
        {
            "category":"Retail",
            "subcategory":"Auto Repair",
            "type":"Services"
        }
    ],
    "sg:phone":"+1 801 561 8705",
    "sg:postcode":"84088",
    "sg:province":"UT",
    "sg:tags":[
        "general"
    ],
    "wof:name":"Expert Automotive",
    "wof:placetype":"venue"
},
  "geometry": {"coordinates":[-111.93861699999999,40.581214],"type":"Point"}
}