{
  "type": "Feature",
  "properties": {
    "iso:country":"US",
    "sg:address":"347 N 200 E",
    "sg:city":"Kanab",
    "sg:classifiers":[
        {
            "category":"Travel",
            "subcategory":"Hotels & Motels",
            "type":"Entertainment"
        }
    ],
    "sg:phone":"+1 435 644 3869",
    "sg:postcode":"84741",
    "sg:province":"UT",
    "wof:name":"Rock Cottage",
    "wof:placetype":"venue"
},
  "geometry": {"coordinates":[-112.524362,37.053416],"type":"Point"}
}