{
  "type": "Feature",
  "properties": {
    "iso:country":"US",
    "sg:address":"3322 E Joyce Dr",
    "sg:city":"Salt Lake City",
    "sg:classifiers":[
        {
            "category":"Professional",
            "subcategory":"Engineering",
            "type":"Services"
        }
    ],
    "sg:phone":"+1 801 485 8571",
    "sg:postcode":"84109",
    "sg:province":"UT",
    "wof:name":"Aquifer Science",
    "wof:placetype":"venue"
},
  "geometry": {"coordinates":[-111.799301,40.705915],"type":"Point"}
}