{
  "type": "Feature",
  "properties": {
    "iso:country":"US",
    "sg:address":"75 Fort Union Blvd",
    "sg:city":"Midvale",
    "sg:classifiers":[
        {
            "category":"Shopping",
            "subcategory":"Clothing, Apparel, & Fashions",
            "type":"Retail Goods"
        }
    ],
    "sg:phone":"+1 801 743 2861",
    "sg:postcode":"84047",
    "sg:province":"UT",
    "sg:tags":[
        "shop",
        "bridal"
    ],
    "wof:name":"Frenze",
    "wof:placetype":"venue"
},
  "geometry": {"coordinates":[-111.888234,40.620875],"type":"Point"}
}