{
  "type": "Feature",
  "properties": {
    "iso:country":"US",
    "sg:address":"60 S Main St",
    "sg:city":"Tooele",
    "sg:classifiers":[
        {
            "category":"Professional",
            "subcategory":"Computer Services",
            "type":"Services"
        }
    ],
    "sg:phone":"+1 435 837 6933",
    "sg:postcode":"84074",
    "sg:province":"UT",
    "sg:tags":[
        "internet"
    ],
    "sg:website":"www.wirelessbeehive.com",
    "wof:name":"WIRELESSBEEHIVE.COM",
    "wof:placetype":"venue"
},
  "geometry": {"coordinates":[-112.29867299999999,40.529358],"type":"Point"}
}