{
  "type": "Feature",
  "properties": {
    "iso:country":"US",
    "sg:address":"833 Grandridge Dr",
    "sg:city":"Salt Lake City",
    "sg:classifiers":[
        {
            "category":"Organizations",
            "subcategory":"Labor Organization",
            "type":"Services"
        }
    ],
    "sg:phone":"+1 801 364 3171",
    "sg:postcode":"84103",
    "sg:province":"UT",
    "wof:name":"Sonntag Enterprises Lc",
    "wof:placetype":"venue"
},
  "geometry": {"coordinates":[-111.879051,40.785576],"type":"Point"}
}