{
  "type": "Feature",
  "properties": {
    "iso:country":"US",
    "sg:address":"2105 S Main St",
    "sg:city":"Salt Lake City",
    "sg:classifiers":[
        {
            "category":"Bars & Pubs",
            "type":"Food & Drink"
        }
    ],
    "sg:phone":"+1 801 486 3344",
    "sg:postcode":"84115",
    "sg:province":"UT",
    "wof:name":"Manny's Tavern",
    "wof:placetype":"venue"
},
  "geometry": {"coordinates":[-111.891024,40.723893],"type":"Point"}
}