{
  "type": "Feature",
  "properties": {
    "iso:country":"US",
    "sg:address":"293 State St",
    "sg:city":"Clearfield",
    "sg:classifiers":[
        {
            "category":"Personal",
            "subcategory":"Tattoo Parlor",
            "type":"Services"
        }
    ],
    "sg:phone":"+1 801 773 1634",
    "sg:postcode":"84015",
    "sg:province":"UT",
    "sg:tags":[
        "tattooing"
    ],
    "wof:name":"Tattoos Loyalty",
    "wof:placetype":"venue"
},
  "geometry": {"coordinates":[-112.022154,41.110235],"type":"Point"}
}