{
  "type": "Feature",
  "properties": {
    "iso:country":"US",
    "sg:address":"162 N 300 E",
    "sg:city":"Huntington",
    "sg:classifiers":[
        {
            "category":"Bars & Pubs",
            "type":"Food & Drink"
        }
    ],
    "sg:phone":"+1 435 687 9142",
    "sg:postcode":"84528",
    "sg:province":"UT",
    "sg:tags":[
        "drinking"
    ],
    "wof:name":"Hemming My Way",
    "wof:placetype":"venue"
},
  "geometry": {"coordinates":[-110.95771499999999,39.329645],"type":"Point"}
}