{
  "type": "Feature",
  "properties": {
    "iso:country":"US",
    "sg:address":"1072 Village Way",
    "sg:city":"Alpine",
    "sg:classifiers":[
        {
            "category":"Professional",
            "subcategory":"Business Services",
            "type":"Services"
        }
    ],
    "sg:phone":"+1 801 756 3309",
    "sg:postcode":"84004",
    "sg:province":"UT",
    "wof:name":"Helix LLC",
    "wof:placetype":"venue"
},
  "geometry": {"coordinates":[-111.760102,40.452211],"type":"Point"}
}