{
  "type": "Feature",
  "properties": {
    "iso:country":"US",
    "sg:address":"1700 W 200 S",
    "sg:city":"Kamas",
    "sg:classifiers":[
        {
            "category":"Banks & Credit Unions",
            "subcategory":"Financial Services",
            "type":"Services"
        }
    ],
    "sg:phone":"+1 435 783 4640",
    "sg:postcode":"84036",
    "sg:province":"UT",
    "sg:tags":[
        "trust",
        "management"
    ],
    "wof:name":"G&D 1st Family Limitd Partnr",
    "wof:placetype":"venue"
},
  "geometry": {"coordinates":[-111.311576,40.636756],"type":"Point"}
}