{
  "type": "Feature",
  "properties": {
    "iso:country":"US",
    "sg:address":"220 Quail Way",
    "sg:city":"Logan",
    "sg:classifiers":[
        {
            "category":"Retail",
            "subcategory":"Auto Repair",
            "type":"Services"
        }
    ],
    "sg:phone":"+1 435 752 5402",
    "sg:postcode":"84321",
    "sg:province":"UT",
    "sg:tags":[
        "transmission"
    ],
    "wof:name":"Economy Auto Inc",
    "wof:placetype":"venue"
},
  "geometry": {"coordinates":[-111.799728,41.735383],"type":"Point"}
}