{
  "type": "Feature",
  "properties": {
    "iso:country":"US",
    "sg:address":"2892 Brookburn Rd",
    "sg:city":"Salt Lake City",
    "sg:classifiers":[
        {
            "category":"Wholesale",
            "subcategory":"Auto Parts",
            "type":"Manufacturing & Wholesale Goods"
        }
    ],
    "sg:phone":"+1 801 274 1224",
    "sg:postcode":"84109",
    "sg:province":"UT",
    "wof:name":"Functional Products",
    "wof:placetype":"venue"
},
  "geometry": {"coordinates":[-111.814837,40.694366],"type":"Point"}
}