{
  "type": "Feature",
  "properties": {
    "iso:country":"US",
    "sg:address":"3638 W 2100 S",
    "sg:city":"Salt Lake City",
    "sg:classifiers":[
        {
            "category":"Wholesale",
            "subcategory":"Groceries",
            "type":"Manufacturing & Wholesale Goods"
        }
    ],
    "sg:phone":"+1 801 974 4300",
    "sg:postcode":"84120",
    "sg:province":"UT",
    "sg:tags":[
        "food",
        "tea",
        "coffee",
        "broker"
    ],
    "wof:name":"Starnes Distributing Inc",
    "wof:placetype":"venue"
},
  "geometry": {"coordinates":[-111.97806799999999,40.726147],"type":"Point"}
}