{
  "type": "Feature",
  "properties": {
    "iso:country":"US",
    "sg:address":"2139 W 1630 N",
    "sg:city":"Clearfield",
    "sg:classifiers":[
        {
            "category":"Retail",
            "subcategory":"Repair Shop",
            "type":"Services"
        }
    ],
    "sg:phone":"+1 801 603 4428",
    "sg:postcode":"84015",
    "sg:province":"UT",
    "sg:tags":[
        "spa",
        "hot",
        "tub"
    ],
    "wof:name":"KLT Repair & Svc",
    "wof:placetype":"venue"
},
  "geometry": {"coordinates":[-112.067111,41.137375],"type":"Point"}
}