{
  "type": "Feature",
  "properties": {
    "iso:country":"US",
    "sg:address":"31 S 400 W",
    "sg:city":"Orem",
    "sg:classifiers":[
        {
            "category":"Professional",
            "subcategory":"Engineering",
            "type":"Services"
        }
    ],
    "sg:phone":"+1 801 377 1790",
    "sg:postcode":"84058",
    "sg:province":"UT",
    "sg:tags":[
        "engineer"
    ],
    "wof:name":"M W Brown Engineering",
    "wof:placetype":"venue"
},
  "geometry": {"coordinates":[-111.705169,40.297113],"type":"Point"}
}