{
  "type": "Feature",
  "properties": {
    "iso:country":"US",
    "sg:address":"7145 E 900 S",
    "sg:city":"Huntsville",
    "sg:classifiers":[
        {
            "category":"Professional",
            "subcategory":"Computer Services",
            "type":"Services"
        }
    ],
    "sg:phone":"+1 801 745 3370",
    "sg:postcode":"84317",
    "sg:province":"UT",
    "sg:tags":[
        "programing",
        "custom"
    ],
    "wof:name":"Micro Free",
    "wof:placetype":"venue"
},
  "geometry": {"coordinates":[-111.77449900000001,41.248219],"type":"Point"}
}