{
  "type": "Feature",
  "properties": {
    "iso:country":"US",
    "sg:address":"1043 Thrushwood Dr",
    "sg:city":"Logan",
    "sg:classifiers":[
        {
            "category":"Building & Trades",
            "subcategory":"Electrical",
            "type":"Services"
        }
    ],
    "sg:phone":"+1 435 753 1013",
    "sg:postcode":"84321",
    "sg:province":"UT",
    "sg:tags":[
        "electric",
        "contractor"
    ],
    "wof:name":"Thornley Electric",
    "wof:placetype":"venue"
},
  "geometry": {"coordinates":[-111.806211,41.734713],"type":"Point"}
}