{
  "type": "Feature",
  "properties": {
    "iso:country":"US",
    "sg:address":"428 2nd St",
    "sg:city":"Ogden",
    "sg:classifiers":[
        {
            "category":"Retail",
            "subcategory":"Laundry & Dry Cleaning",
            "type":"Services"
        }
    ],
    "sg:phone":"+1 801 392 7821",
    "sg:postcode":"84404",
    "sg:province":"UT",
    "sg:tags":[
        "cleaners"
    ],
    "wof:name":"Sagels Cleaners & Shirt Ldry",
    "wof:placetype":"venue"
},
  "geometry": {"coordinates":[-111.96768,41.259234],"type":"Point"}
}