{
  "type": "Feature",
  "properties": {
    "iso:country":"US",
    "sg:address":"3505 California Ave",
    "sg:city":"Salt Lake City",
    "sg:classifiers":[
        {
            "category":"Freight",
            "type":"Transportation"
        }
    ],
    "sg:phone":"+1 801 887 7225",
    "sg:postcode":"84104",
    "sg:province":"UT",
    "sg:tags":[
        "commercial",
        "storage"
    ],
    "wof:name":"Pack N Store",
    "wof:placetype":"venue"
},
  "geometry": {"coordinates":[-111.986153,40.742594],"type":"Point"}
}