{
  "type": "Feature",
  "properties": {
    "iso:country":"US",
    "sg:address":"2004 Washington Blvd",
    "sg:city":"Ogden",
    "sg:classifiers":[
        {
            "category":"Autos & Motor Vehicles",
            "subcategory":"Fuel & Gas Station",
            "type":"Retail Goods"
        }
    ],
    "sg:phone":"+1 801 621 4155",
    "sg:postcode":"84401",
    "sg:province":"UT",
    "sg:tags":[
        "station",
        "gasoline"
    ],
    "wof:name":"Boulevard Automotive",
    "wof:placetype":"venue"
},
  "geometry": {"coordinates":[-111.97024,41.229112],"type":"Point"}
}