{
  "type": "Feature",
  "properties": {
    "iso:country":"US",
    "sg:address":"1050 E Telegraph St",
    "sg:city":"Washington",
    "sg:classifiers":[
        {
            "category":"Freight",
            "type":"Transportation"
        }
    ],
    "sg:phone":"+1 435 652 8280",
    "sg:postcode":"84780",
    "sg:province":"UT",
    "sg:tags":[
        "special"
    ],
    "wof:name":"Bella Vista Storage",
    "wof:placetype":"venue"
},
  "geometry": {"coordinates":[-113.49320299999999,37.130633],"type":"Point"}
}