{
  "type": "Feature",
  "properties": {
    "iso:country":"US",
    "sg:address":"830 N 500 W",
    "sg:city":"Bountiful",
    "sg:classifiers":[
        {
            "category":"Shopping",
            "subcategory":"Hobbies, Toys, & Games",
            "type":"Retail Goods"
        }
    ],
    "sg:phone":"+1 801 294 4213",
    "sg:postcode":"84010",
    "sg:province":"UT",
    "wof:name":"Hobbie Guy RC",
    "wof:placetype":"venue"
},
  "geometry": {"coordinates":[-111.89213100000001,40.896124],"type":"Point"}
}