{
  "type": "Feature",
  "properties": {
    "iso:country":"US",
    "sg:address":"50 S 900 E",
    "sg:city":"Salt Lake City",
    "sg:classifiers":[
        {
            "category":"Insurance",
            "subcategory":"Insurance Agent",
            "type":"Services"
        }
    ],
    "sg:phone":"+1 801 359 7661",
    "sg:postcode":"84102",
    "sg:province":"UT",
    "wof:name":"Farmers Insurance Group",
    "wof:placetype":"venue"
},
  "geometry": {"coordinates":[-111.865407,40.768267],"type":"Point"}
}