{
  "type": "Feature",
  "properties": {
    "iso:country":"US",
    "sg:address":"108 S Main St",
    "sg:city":"St George",
    "sg:classifiers":[
        {
            "category":"Manufacturing",
            "subcategory":"Retail Goods",
            "type":"Manufacturing & Wholesale Goods"
        }
    ],
    "sg:phone":"+1 435 673 0748",
    "sg:postcode":"84770",
    "sg:province":"UT",
    "sg:tags":[
        "mfg",
        "hard",
        "floor",
        "covering"
    ],
    "wof:name":"Dave S Floor Coverings",
    "wof:placetype":"venue"
},
  "geometry": {"coordinates":[-113.583405,37.106355],"type":"Point"}
}