{
  "type": "Feature",
  "properties": {
    "iso:country":"US",
    "sg:address":"1499 Ascot Cir",
    "sg:city":"Sandy",
    "sg:classifiers":[
        {
            "category":"Professional",
            "subcategory":"Lawyer & Legal Services",
            "type":"Services"
        }
    ],
    "sg:phone":"+1 801 572 5558",
    "sg:postcode":"84092",
    "sg:province":"UT",
    "wof:name":"Craig P McCullough",
    "wof:placetype":"venue"
},
  "geometry": {"coordinates":[-111.850245,40.553618],"type":"Point"}
}