{
  "type": "Feature",
  "properties": {
    "iso:country":"US",
    "sg:address":"2766 Forthill Rd",
    "sg:city":"Lehi",
    "sg:classifiers":[
        {
            "category":"Building & Trades",
            "subcategory":"Construction",
            "type":"Services"
        }
    ],
    "sg:phone":"+1 801 766 8666",
    "sg:postcode":"84043",
    "sg:province":"UT",
    "sg:tags":[
        "carpenter"
    ],
    "wof:name":"All Utah Construction",
    "wof:placetype":"venue"
},
  "geometry": {"coordinates":[-111.990588,40.364254],"type":"Point"}
}