{
  "type": "Feature",
  "properties": {
    "iso:country":"US",
    "sg:address":"501 N Main St",
    "sg:city":"Richfield",
    "sg:classifiers":[
        {
            "category":"Organizations",
            "subcategory":"Religious Organization",
            "type":"Services"
        }
    ],
    "sg:phone":"+1 435 896 6868",
    "sg:postcode":"84701",
    "sg:province":"UT",
    "sg:tags":[
        "church"
    ],
    "wof:name":"First Baptist Church Inc",
    "wof:placetype":"venue"
},
  "geometry": {"coordinates":[-112.084689,38.776084],"type":"Point"}
}