{
  "type": "Feature",
  "properties": {
    "iso:country":"US",
    "sg:address":"10211 S 3200 W",
    "sg:city":"South Jordan",
    "sg:classifiers":[
        {
            "category":"Building & Trades",
            "subcategory":"Construction",
            "type":"Services"
        }
    ],
    "sg:phone":"+1 801 254 6132",
    "sg:postcode":"84095",
    "sg:province":"UT",
    "sg:tags":[
        "contractor"
    ],
    "wof:name":"Bidwell Construction",
    "wof:placetype":"venue"
},
  "geometry": {"coordinates":[-111.967191,40.564705],"type":"Point"}
}