{
  "type": "Feature",
  "properties": {
    "iso:country":"US",
    "sg:address":"2400 Alta Canyon Dr",
    "sg:city":"Sandy",
    "sg:classifiers":[
        {
            "category":"Organizations",
            "subcategory":"Religious Organization",
            "type":"Services"
        }
    ],
    "sg:phone":"+1 801 944 2156",
    "sg:postcode":"84093",
    "sg:province":"UT",
    "sg:tags":[
        "church"
    ],
    "wof:name":"Church Of Jesus Christ Of Lds",
    "wof:placetype":"venue"
},
  "geometry": {"coordinates":[-111.823752,40.594976],"type":"Point"}
}