{
  "type": "Feature",
  "properties": {
    "iso:country":"US",
    "sg:address":"8073 W 3380 S",
    "sg:city":"Magna",
    "sg:classifiers":[
        {
            "category":"Building & Trades",
            "subcategory":"Cleaning & Sanitation",
            "type":"Services"
        }
    ],
    "sg:phone":"+1 801 250 9129",
    "sg:postcode":"84044",
    "sg:province":"UT",
    "sg:tags":[
        "maintenance"
    ],
    "wof:name":"Blasi Cuality Cleaning",
    "wof:placetype":"venue"
},
  "geometry": {"coordinates":[-112.085005,40.698729],"type":"Point"}
}