{
  "type": "Feature",
  "properties": {
    "iso:country":"US",
    "sg:address":"2230 N University Pkwy",
    "sg:city":"Provo",
    "sg:classifiers":[
        {
            "category":"Personal",
            "subcategory":"Adult",
            "type":"Services"
        }
    ],
    "sg:phone":"+1 801 356 2336",
    "sg:postcode":"84604",
    "sg:province":"UT",
    "sg:tags":[
        "organization",
        "religious"
    ],
    "wof:name":"LDS Singles Online",
    "wof:placetype":"venue"
},
  "geometry": {"coordinates":[-111.668554,40.263999],"type":"Point"}
}