{
  "type": "Feature",
  "properties": {
    "iso:country":"US",
    "sg:address":"358 Mountain Way Dr",
    "sg:city":"Orem",
    "sg:classifiers":[
        {
            "category":"Wholesale",
            "subcategory":"Sporting Goods",
            "type":"Manufacturing & Wholesale Goods"
        }
    ],
    "sg:phone":"+1 801 785 7546",
    "sg:postcode":"84058",
    "sg:province":"UT",
    "sg:tags":[
        "bicycle"
    ],
    "sg:website":"www.lizardskins.com",
    "wof:name":"Lizard Skins",
    "wof:placetype":"venue"
},
  "geometry": {"coordinates":[-111.72927900000001,40.290682],"type":"Point"}
}