{
  "type": "Feature",
  "properties": {
    "iso:country":"US",
    "sg:address":"1320 S University Ave",
    "sg:city":"Provo",
    "sg:classifiers":[
        {
            "category":"Restaurant",
            "type":"Food & Drink"
        }
    ],
    "sg:menulink":"http://www.allmenus.com/ut/provo-orem/132817-subway/menu/",
    "sg:phone":"+1 801 356 0848",
    "sg:postcode":"84601",
    "sg:province":"UT",
    "sg:tags":[
        "american",
        "sandwich"
    ],
    "wof:name":"Subway",
    "wof:placetype":"venue"
},
  "geometry": {"coordinates":[-111.658957,40.215838],"type":"Point"}
}