{
  "type": "Feature",
  "properties": {
    "iso:country":"US",
    "sg:address":"1117 S Jordan Pkwy",
    "sg:city":"South Jordan",
    "sg:classifiers":[
        {
            "category":"Professional",
            "subcategory":"Business Services",
            "type":"Services"
        }
    ],
    "sg:phone":"+1 801 254 0811",
    "sg:postcode":"84095",
    "sg:province":"UT",
    "wof:name":"Vern & Robyn Provost",
    "wof:placetype":"venue"
},
  "geometry": {"coordinates":[-111.92277799999999,40.561068],"type":"Point"}
}