{
  "type": "Feature",
  "properties": {
    "iso:country":"US",
    "sg:address":"3438 E Buck Cir",
    "sg:city":"Salt Lake City",
    "sg:classifiers":[
        {
            "category":"Professional",
            "type":"Services"
        }
    ],
    "sg:phone":"+1 801 944 7310",
    "sg:postcode":"84121",
    "sg:province":"UT",
    "wof:name":"Service Industry Info LLC",
    "wof:placetype":"venue"
},
  "geometry": {"coordinates":[-111.797814,40.62002],"type":"Point"}
}