{
  "type": "Feature",
  "properties": {
    "iso:country":"US",
    "sg:address":"35 N 200 W",
    "sg:city":"Tremonton",
    "sg:classifiers":[
        {
            "category":"Retail",
            "subcategory":"Auto Repair",
            "type":"Services"
        }
    ],
    "sg:phone":"+1 435 257 7007",
    "sg:postcode":"84337",
    "sg:province":"UT",
    "sg:tags":[
        "glass",
        "replacement"
    ],
    "wof:name":"Windshield Wizzard",
    "wof:placetype":"venue"
},
  "geometry": {"coordinates":[-112.169076,41.712443],"type":"Point"}
}