{
  "type": "Feature",
  "properties": {
    "iso:country":"US",
    "sg:address":"1343 Flint Meadow Dr",
    "sg:city":"Kaysville",
    "sg:classifiers":[
        {
            "category":"Professional",
            "type":"Services"
        }
    ],
    "sg:phone":"+1 801 444 9470",
    "sg:postcode":"84037",
    "sg:province":"UT",
    "sg:tags":[
        "establishment"
    ],
    "wof:name":"General Atomics Advanced",
    "wof:placetype":"venue"
},
  "geometry": {"coordinates":[-111.965687,41.044086],"type":"Point"}
}