{
  "type": "Feature",
  "properties": {
    "iso:country":"US",
    "sg:address":"41 W Stauffer Ln",
    "sg:city":"Murray",
    "sg:classifiers":[
        {
            "category":"Professional",
            "subcategory":"Art Services",
            "type":"Services"
        }
    ],
    "sg:phone":"+1 801 268 2528",
    "sg:postcode":"84107",
    "sg:province":"UT",
    "sg:tags":[
        "photographer"
    ],
    "wof:name":"Panorama Productions",
    "wof:placetype":"venue"
},
  "geometry": {"coordinates":[-111.89134,40.647689],"type":"Point"}
}