{
  "type": "Feature",
  "properties": {
    "iso:country":"US",
    "sg:address":"80 N Main St",
    "sg:city":"Bountiful",
    "sg:classifiers":[
        {
            "category":"Professional",
            "subcategory":"Lawyer & Legal Services",
            "type":"Services"
        }
    ],
    "sg:phone":"+1 801 292 0409",
    "sg:postcode":"84010",
    "sg:province":"UT",
    "sg:tags":[
        "attorney"
    ],
    "wof:name":"Douglas E Adair Atty At Law",
    "wof:placetype":"venue"
},
  "geometry": {"coordinates":[-111.88063200000001,40.88957],"type":"Point"}
}