{
  "type": "Feature",
  "properties": {
    "iso:country":"US",
    "sg:address":"485 E 600 N",
    "sg:city":"Orem",
    "sg:classifiers":[
        {
            "category":"Professional",
            "subcategory":"Computer Services",
            "type":"Services"
        }
    ],
    "sg:phone":"+1 801 224 3220",
    "sg:postcode":"84097",
    "sg:province":"UT",
    "sg:tags":[
        "related"
    ],
    "wof:name":"Salon Central",
    "wof:placetype":"venue"
},
  "geometry": {"coordinates":[-111.68443499999999,40.308249],"type":"Point"}
}