{
  "type": "Feature",
  "properties": {
    "iso:country":"US",
    "sg:address":"568 250 N St",
    "sg:city":"Vernal",
    "sg:classifiers":[
        {
            "category":"Building & Trades",
            "subcategory":"Construction",
            "type":"Services"
        }
    ],
    "sg:phone":"+1 435 789 3071",
    "sg:postcode":"84078",
    "sg:province":"UT",
    "sg:tags":[
        "contractor"
    ],
    "wof:name":"TNT Drywall Inc",
    "wof:placetype":"venue"
},
  "geometry": {"coordinates":[-112.323808,40.539057],"type":"Point"}
}