{
  "type": "Feature",
  "properties": {
    "iso:country":"US",
    "sg:address":"1404 Lombardy Pl",
    "sg:city":"Murray",
    "sg:classifiers":[
        {
            "category":"Professional",
            "type":"Services"
        }
    ],
    "sg:phone":"+1 801 278 3515",
    "sg:postcode":"84121",
    "sg:province":"UT",
    "sg:tags":[
        "establishment"
    ],
    "wof:name":"Chicagosweeteners Inc",
    "wof:placetype":"venue"
},
  "geometry": {"coordinates":[-111.851826,40.635327],"type":"Point"}
}