{
  "type": "Feature",
  "properties": {
    "iso:country":"US",
    "sg:address":"4835 Highland Dr",
    "sg:city":"Salt Lake City",
    "sg:classifiers":[
        {
            "category":"Autos & Motor Vehicles",
            "subcategory":"Auto Supplies",
            "type":"Retail Goods"
        }
    ],
    "sg:phone":"+1 801 277 5404",
    "sg:postcode":"84117",
    "sg:province":"UT",
    "sg:tags":[
        "tire"
    ],
    "wof:name":"Firestone Tire & Svc Ctr",
    "wof:placetype":"venue"
},
  "geometry": {"coordinates":[-111.83904699999999,40.664914],"type":"Point"}
}