{
  "type": "Feature",
  "properties": {
    "iso:country":"US",
    "sg:address":"457 W Main St",
    "sg:city":"Grantsville",
    "sg:classifiers":[
        {
            "category":"Bars & Pubs",
            "type":"Food & Drink"
        }
    ],
    "sg:phone":"+1 435 884 9808",
    "sg:postcode":"84029",
    "sg:province":"UT",
    "sg:tags":[
        "drinking"
    ],
    "wof:name":"Dead Dog Saloon",
    "wof:placetype":"venue"
},
  "geometry": {"coordinates":[-112.477425,40.599961],"type":"Point"}
}