{
  "type": "Feature",
  "properties": {
    "iso:country":"US",
    "sg:address":"1300 S State St",
    "sg:city":"Orem",
    "sg:classifiers":[
        {
            "category":"Retail",
            "subcategory":"Repair Shop",
            "type":"Services"
        }
    ],
    "sg:phone":"+1 801 765 4545",
    "sg:postcode":"84097",
    "sg:province":"UT",
    "sg:tags":[
        "watch"
    ],
    "wof:name":"Precision Time",
    "wof:placetype":"venue"
},
  "geometry": {"coordinates":[-111.683728,40.27151],"type":"Point"}
}