{
  "type": "Feature",
  "properties": {
    "iso:country":"US",
    "sg:address":"2400 W 8660 S",
    "sg:city":"West Jordan",
    "sg:classifiers":[
        {
            "category":"Sports & Exercise",
            "subcategory":"Golf",
            "type":"Entertainment"
        }
    ],
    "sg:phone":"+1 801 255 9211",
    "sg:postcode":"84088",
    "sg:province":"UT",
    "sg:tags":[
        "course"
    ],
    "sg:website":"www.slcountygolf.com",
    "wof:name":"Mountain View Golf Course",
    "wof:placetype":"venue"
},
  "geometry": {"coordinates":[-111.952459,40.594107],"type":"Point"}
}