{
  "type": "Feature",
  "properties": {
    "iso:country":"US",
    "sg:address":"237 E 1000 N",
    "sg:city":"Orem",
    "sg:classifiers":[
        {
            "category":"Building & Trades",
            "subcategory":"Construction",
            "type":"Services"
        }
    ],
    "sg:phone":"+1 801 225 5902",
    "sg:postcode":"84057",
    "sg:province":"UT",
    "sg:tags":[
        "contractor"
    ],
    "wof:name":"Kens Drywall LLC",
    "wof:placetype":"venue"
},
  "geometry": {"coordinates":[-111.689969,40.315655],"type":"Point"}
}