{
  "type": "Feature",
  "properties": {
    "iso:country":"US",
    "sg:address":"1034 N 1010 W",
    "sg:city":"Pleasant Grove",
    "sg:classifiers":[
        {
            "category":"Building & Trades",
            "subcategory":"Construction",
            "type":"Services"
        }
    ],
    "sg:phone":"+1 801 785 5386",
    "sg:postcode":"84062",
    "sg:province":"UT",
    "sg:tags":[
        "carpentry",
        "general",
        "contractor"
    ],
    "wof:name":"Pintail Construction LLC",
    "wof:placetype":"venue"
},
  "geometry": {"coordinates":[-111.75489,40.375114],"type":"Point"}
}