{
  "type": "Feature",
  "properties": {
    "iso:country":"US",
    "sg:address":"1810 Siggard Dr",
    "sg:city":"Salt Lake City",
    "sg:classifiers":[
        {
            "category":"Manufacturing",
            "subcategory":"Apparel",
            "type":"Manufacturing & Wholesale Goods"
        }
    ],
    "sg:phone":"+1 801 467 8751",
    "sg:postcode":"84106",
    "sg:province":"UT",
    "sg:tags":[
        "art",
        "direction",
        "graphic",
        "design"
    ],
    "wof:name":"Natty Threads",
    "wof:placetype":"venue"
},
  "geometry": {"coordinates":[-111.84220000000001,40.691809],"type":"Point"}
}