{
  "type": "Feature",
  "properties": {
    "iso:country":"US",
    "sg:address":"2243 Sugar Factory Rd",
    "sg:city":"West Jordan",
    "sg:classifiers":[
        {
            "category":"Building & Trades",
            "subcategory":"Construction",
            "type":"Services"
        }
    ],
    "sg:phone":"+1 801 256 3404",
    "sg:postcode":"84088",
    "sg:province":"UT",
    "sg:tags":[
        "general",
        "residential",
        "work",
        "painting",
        "contractor"
    ],
    "wof:name":"Simmons Construction Inc",
    "wof:placetype":"venue"
},
  "geometry": {"coordinates":[-111.949923,40.60073],"type":"Point"}
}