{
  "type": "Feature",
  "properties": {
    "iso:country":"US",
    "sg:address":"3950 S 700 E",
    "sg:city":"Murray",
    "sg:classifiers":[
        {
            "category":"Shopping",
            "subcategory":"Computers & Home Electronics",
            "type":"Retail Goods"
        }
    ],
    "sg:phone":"+1 801 265 9996",
    "sg:postcode":"84107",
    "sg:province":"UT",
    "sg:tags":[
        "software"
    ],
    "wof:name":"EQUIS Intl",
    "wof:placetype":"venue"
},
  "geometry": {"coordinates":[-111.871443,40.686592],"type":"Point"}
}