{
  "type": "Feature",
  "properties": {
    "iso:country":"US",
    "sg:address":"5775 S 2700 W",
    "sg:city":"Salt Lake City",
    "sg:classifiers":[
        {
            "category":"Building & Trades",
            "subcategory":"Cleaning & Sanitation",
            "type":"Services"
        }
    ],
    "sg:phone":"+1 801 964 3020",
    "sg:postcode":"84118",
    "sg:province":"UT",
    "sg:tags":[
        "maintenance"
    ],
    "wof:name":"Murray Ut Facility Management",
    "wof:placetype":"venue"
},
  "geometry": {"coordinates":[-111.957767,40.646211],"type":"Point"}
}