{
  "type": "Feature",
  "properties": {
    "iso:country":"US",
    "sg:address":"2845 Buchanan Ave",
    "sg:city":"Ogden",
    "sg:classifiers":[
        {
            "category":"Banks & Credit Unions",
            "subcategory":"Financial Services",
            "type":"Services"
        }
    ],
    "sg:phone":"+1 801 392 7289",
    "sg:postcode":"84403",
    "sg:province":"UT",
    "sg:tags":[
        "investor"
    ],
    "wof:name":"Arango Investment Co",
    "wof:placetype":"venue"
},
  "geometry": {"coordinates":[-111.931899,41.213768],"type":"Point"}
}