{
  "type": "Feature",
  "properties": {
    "iso:country":"US",
    "sg:address":"290 S 1300 E",
    "sg:city":"Salt Lake City",
    "sg:classifiers":[
        {
            "category":"Banks & Credit Unions",
            "subcategory":"Bank",
            "type":"Services"
        }
    ],
    "sg:phone":"+1 801 535 1204",
    "sg:postcode":"84102",
    "sg:province":"UT",
    "sg:tags":[
        "state",
        "commercial"
    ],
    "wof:name":"Keybank National Association",
    "wof:placetype":"venue"
},
  "geometry": {"coordinates":[-111.85395699999999,40.764833],"type":"Point"}
}