{
  "type": "Feature",
  "properties": {
    "iso:country":"US",
    "sg:address":"32 E 100 S",
    "sg:city":"St George",
    "sg:classifiers":[
        {
            "category":"Professional",
            "subcategory":"Lawyer & Legal Services",
            "type":"Services"
        }
    ],
    "sg:phone":"+1 435 628 2884",
    "sg:postcode":"84770",
    "sg:province":"UT",
    "sg:tags":[
        "attorney"
    ],
    "wof:name":"Scarth & Dent",
    "wof:placetype":"venue"
},
  "geometry": {"coordinates":[-113.582711,37.106418],"type":"Point"}
}