{
  "type": "Feature",
  "properties": {
    "iso:country":"US",
    "sg:address":"905 24th St",
    "sg:city":"Ogden",
    "sg:classifiers":[
        {
            "category":"Real Estate",
            "subcategory":"Developer",
            "type":"Services"
        }
    ],
    "sg:phone":"+1 801 778 0088",
    "sg:postcode":"84401",
    "sg:province":"UT",
    "sg:tags":[
        "land",
        "general",
        "contractor"
    ],
    "wof:name":"Calute Construction",
    "wof:placetype":"venue"
},
  "geometry": {"coordinates":[-111.953785,41.222461],"type":"Point"}
}