{
  "type": "Feature",
  "properties": {
    "iso:country":"US",
    "sg:address":"700 S 550 East St",
    "sg:city":"Provo",
    "sg:classifiers":[
        {
            "category":"Manufacturing",
            "subcategory":"Metals",
            "type":"Manufacturing & Wholesale Goods"
        }
    ],
    "sg:phone":"+1 801 364 1252",
    "sg:postcode":"84606",
    "sg:province":"UT",
    "sg:tags":[
        "steel"
    ],
    "sg:website":"www.chicagobridge.com",
    "wof:name":"Chicago Bridge & Iron Co",
    "wof:placetype":"venue"
},
  "geometry": {"coordinates":[-111.64936,40.224411],"type":"Point"}
}