{
  "type": "Feature",
  "properties": {
    "iso:country":"US",
    "sg:address":"180 State Rte 43",
    "sg:city":"Manila",
    "sg:classifiers":[
        {
            "category":"Organizations",
            "subcategory":"Religious Organization",
            "type":"Services"
        }
    ],
    "sg:phone":"+1 435 784 3622",
    "sg:postcode":"84046",
    "sg:province":"UT",
    "sg:tags":[
        "church"
    ],
    "wof:name":"Grace Cummunity Baptist Church",
    "wof:placetype":"venue"
},
  "geometry": {"coordinates":[-109.718915,40.988221],"type":"Point"}
}