{
  "type": "Feature",
  "properties": {
    "iso:country":"US",
    "sg:address":"1773 Cornwall Ct",
    "sg:city":"Sandy",
    "sg:classifiers":[
        {
            "category":"Professional",
            "type":"Services"
        }
    ],
    "sg:phone":"+1 801 572 1163",
    "sg:postcode":"84092",
    "sg:province":"UT",
    "wof:name":"Granita Park LLC",
    "wof:placetype":"venue"
},
  "geometry": {"coordinates":[-111.841037,40.540832],"type":"Point"}
}