{
  "type": "Feature",
  "properties": {
    "iso:country":"US",
    "sg:address":"473 S River Rd",
    "sg:city":"St George",
    "sg:classifiers":[
        {
            "category":"Professional",
            "subcategory":"Advertising",
            "type":"Services"
        }
    ],
    "sg:phone":"+1 435 652 8495",
    "sg:postcode":"84790",
    "sg:province":"UT",
    "sg:tags":[
        "mailing",
        "shipping"
    ],
    "wof:name":"UPS Store",
    "wof:placetype":"venue"
},
  "geometry": {"coordinates":[-113.555571,37.101019],"type":"Point"}
}