{
  "type": "Feature",
  "properties": {
    "iso:country":"US",
    "sg:address":"27 E Main St",
    "sg:city":"Lehi",
    "sg:classifiers":[
        {
            "category":"Professional",
            "subcategory":"Engineering",
            "type":"Services"
        }
    ],
    "sg:phone":"+1 801 768 4544",
    "sg:postcode":"84043",
    "sg:province":"UT",
    "sg:tags":[
        "engineer"
    ],
    "wof:name":"Trane Engineering",
    "wof:placetype":"venue"
},
  "geometry": {"coordinates":[-111.847763,40.388],"type":"Point"}
}