{
  "type": "Feature",
  "properties": {
    "iso:country":"US",
    "sg:address":"350 W Broadway",
    "sg:city":"Salt Lake City",
    "sg:classifiers":[
        {
            "category":"Professional",
            "type":"Services"
        }
    ],
    "sg:phone":"+1 801 363 3659",
    "sg:postcode":"84101",
    "sg:province":"UT",
    "sg:tags":[
        "establishment"
    ],
    "wof:name":"Chris Jenson Creative",
    "wof:placetype":"venue"
},
  "geometry": {"coordinates":[-111.901286,40.762895],"type":"Point"}
}