{
  "type": "Feature",
  "properties": {
    "iso:country":"US",
    "sg:address":"535 W State St",
    "sg:city":"Hurricane",
    "sg:classifiers":[
        {
            "category":"Restaurant",
            "type":"Food & Drink"
        }
    ],
    "sg:menulink":"http://www.allmenus.com/ut/hurricane/77725-papa-murphys/menu/",
    "sg:phone":"+1 435 635 7272",
    "sg:postcode":"84737",
    "sg:province":"UT",
    "sg:tags":[
        "american",
        "pizza"
    ],
    "wof:name":"Papa Murphy's",
    "wof:placetype":"venue"
},
  "geometry": {"coordinates":[-113.298214,37.176467],"type":"Point"}
}