{
  "type": "Feature",
  "properties": {
    "iso:country":"US",
    "sg:address":"3579 S Redwood Rd",
    "sg:city":"Salt Lake City",
    "sg:classifiers":[
        {
            "category":"Professional",
            "subcategory":"Management & Consulting",
            "type":"Services"
        }
    ],
    "sg:phone":"+1 801 972 8753",
    "sg:postcode":"84119",
    "sg:province":"UT",
    "sg:tags":[
        "business"
    ],
    "wof:name":"Sprinkel & Assoc",
    "wof:placetype":"venue"
},
  "geometry": {"coordinates":[-111.938823,40.695253],"type":"Point"}
}