{
  "type": "Feature",
  "properties": {
    "iso:country":"US",
    "sg:address":"1552 N Geneva Rd",
    "sg:city":"Provo",
    "sg:classifiers":[
        {
            "category":"Organizations",
            "subcategory":"Labor Organization",
            "type":"Services"
        }
    ],
    "sg:phone":"+1 801 374 0896",
    "sg:postcode":"84601",
    "sg:province":"UT",
    "wof:name":"Donald D Reese Investments Lc",
    "wof:placetype":"venue"
},
  "geometry": {"coordinates":[-111.70774900000001,40.253904],"type":"Point"}
}