{
  "type": "Feature",
  "properties": {
    "iso:country":"US",
    "sg:address":"855 W 1500 N",
    "sg:city":"Lehi",
    "sg:classifiers":[
        {
            "category":"Health Services",
            "subcategory":"Nursing And Care Facility",
            "type":"Services"
        },
        {
            "category":"Social Services",
            "subcategory":"Adult Care",
            "type":"Services"
        }
    ],
    "sg:phone":"+1 801 768 4712",
    "sg:postcode":"84043",
    "sg:province":"UT",
    "sg:tags":[
        "home",
        "convalescent",
        "residential"
    ],
    "wof:name":"Greenwood Mnor Assisted Living",
    "wof:placetype":"venue"
},
  "geometry": {"coordinates":[-111.86412300000001,40.405959],"type":"Point"}
}