{
  "type": "Feature",
  "properties": {
    "iso:country":"US",
    "sg:address":"244 E 1000 S",
    "sg:city":"Bountiful",
    "sg:classifiers":[
        {
            "category":"Professional",
            "subcategory":"Computer Services",
            "type":"Services"
        }
    ],
    "sg:phone":"+1 801 296 0534",
    "sg:postcode":"84010",
    "sg:province":"UT",
    "sg:tags":[
        "programing",
        "custom"
    ],
    "wof:name":"Cbt International Inc",
    "wof:placetype":"venue"
},
  "geometry": {"coordinates":[-111.873678,40.879237],"type":"Point"}
}