{
  "type": "Feature",
  "properties": {
    "iso:country":"US",
    "sg:address":"525 E Ridge Dr",
    "sg:city":"Alpine",
    "sg:classifiers":[
        {
            "category":"Building & Trades",
            "subcategory":"Construction",
            "type":"Services"
        }
    ],
    "sg:phone":"+1 801 772 1095",
    "sg:postcode":"84004",
    "sg:province":"UT",
    "sg:tags":[
        "house"
    ],
    "wof:name":"Jordan Construction",
    "wof:placetype":"venue"
},
  "geometry": {"coordinates":[-111.768522,40.447186],"type":"Point"}
}