{
  "type": "Feature",
  "properties": {
    "iso:country":"US",
    "sg:address":"2210 US Hwy 40",
    "sg:city":"Roosevelt",
    "sg:classifiers":[
        {
            "category":"Home & Garden",
            "subcategory":"Garden Supply",
            "type":"Retail Goods"
        }
    ],
    "sg:phone":"+1 435 722 0898",
    "sg:postcode":"84066",
    "sg:province":"UT",
    "sg:tags":[
        "nurseryman"
    ],
    "wof:name":"Allred's Yard & Garden",
    "wof:placetype":"venue"
},
  "geometry": {"coordinates":[-110.039423,40.268667],"type":"Point"}
}