{
  "type": "Feature",
  "properties": {
    "iso:country":"US",
    "sg:address":"3515 Airport Rd",
    "sg:city":"Ogden",
    "sg:classifiers":[
        {
            "category":"Government",
            "subcategory":"Office",
            "type":"Public Place"
        }
    ],
    "sg:phone":"+1 801 625 5470",
    "sg:postcode":"84405",
    "sg:province":"UT",
    "sg:tags":[
        "forest"
    ],
    "wof:name":"Forest Service",
    "wof:placetype":"venue"
},
  "geometry": {"coordinates":[-112.007107,41.192751],"type":"Point"}
}