{
  "type": "Feature",
  "properties": {
    "iso:country":"US",
    "sg:address":"3662 S Vernal Ave",
    "sg:city":"Vernal",
    "sg:classifiers":[
        {
            "category":"Freight",
            "type":"Transportation"
        }
    ],
    "sg:phone":"+1 435 781 1097",
    "sg:postcode":"84078",
    "sg:province":"UT",
    "sg:tags":[
        "operator",
        "trucking"
    ],
    "wof:name":"Rockin Double D Express Inc",
    "wof:placetype":"venue"
},
  "geometry": {"coordinates":[-109.527852,40.401613],"type":"Point"}
}