{
  "type": "Feature",
  "properties": {
    "iso:country":"US",
    "sg:address":"4991 Naylor Ln",
    "sg:city":"Murray",
    "sg:classifiers":[
        {
            "category":"Building & Trades",
            "subcategory":"Construction",
            "type":"Services"
        }
    ],
    "sg:phone":"+1 801 554 0120",
    "sg:postcode":"84107",
    "sg:province":"UT",
    "sg:tags":[
        "home",
        "builder"
    ],
    "wof:name":"Eagle Construction LLC",
    "wof:placetype":"venue"
},
  "geometry": {"coordinates":[-111.87028599999999,40.664786],"type":"Point"}
}