{
  "type": "Feature",
  "properties": {
    "iso:country":"US",
    "sg:address":"870 N 300 E",
    "sg:city":"Pleasant Grove",
    "sg:classifiers":[
        {
            "category":"Home & Garden",
            "subcategory":"Furniture",
            "type":"Retail Goods"
        }
    ],
    "sg:phone":"+1 801 796 3666",
    "sg:postcode":"84062",
    "sg:province":"UT",
    "wof:name":"Modular Office Srvcs",
    "wof:placetype":"venue"
},
  "geometry": {"coordinates":[-111.735614,40.371403],"type":"Point"}
}