{
  "type": "Feature",
  "properties": {
    "iso:country":"US",
    "sg:address":"1374 Old Mission Rd",
    "sg:city":"Sandy",
    "sg:classifiers":[
        {
            "category":"Building & Trades",
            "subcategory":"Construction",
            "type":"Services"
        }
    ],
    "sg:phone":"+1 801 568 0976",
    "sg:postcode":"84093",
    "sg:province":"UT",
    "sg:tags":[
        "hanging",
        "contractor"
    ],
    "wof:name":"Mr Painter",
    "wof:placetype":"venue"
},
  "geometry": {"coordinates":[-111.85169399999999,40.60721],"type":"Point"}
}