{
  "type": "Feature",
  "properties": {
    "iso:country":"US",
    "sg:address":"900 N 400 E",
    "sg:city":"North Salt Lake",
    "sg:classifiers":[
        {
            "category":"Manufacturing",
            "subcategory":"Printing",
            "type":"Manufacturing & Wholesale Goods"
        }
    ],
    "sg:phone":"+1 801 294 4455",
    "sg:postcode":"84054",
    "sg:province":"UT",
    "wof:name":"Pacificolor",
    "wof:placetype":"venue"
},
  "geometry": {"coordinates":[-111.90207700000001,40.859069],"type":"Point"}
}