{
  "type": "Feature",
  "properties": {
    "iso:country":"US",
    "sg:address":"372 Ranch Dr",
    "sg:city":"Alpine",
    "sg:classifiers":[
        {
            "category":"Restaurant",
            "type":"Food & Drink"
        }
    ],
    "sg:phone":"+1 801 756 5794",
    "sg:postcode":"84004",
    "sg:province":"UT",
    "sg:tags":[
        "eating"
    ],
    "wof:name":"Ice Shed",
    "wof:placetype":"venue"
},
  "geometry": {"coordinates":[-111.79382099999999,40.447837],"type":"Point"}
}