{
  "type": "Feature",
  "properties": {
    "iso:country":"US",
    "sg:address":"5306 W 9910 N",
    "sg:city":"American Fork",
    "sg:classifiers":[
        {
            "category":"Shopping",
            "subcategory":"Computers & Home Electronics",
            "type":"Retail Goods"
        }
    ],
    "sg:phone":"+1 801 763 0517",
    "sg:postcode":"84003",
    "sg:province":"UT",
    "wof:name":"Corda Technologies Inc",
    "wof:placetype":"venue"
},
  "geometry": {"coordinates":[-111.78553599999999,40.411998],"type":"Point"}
}