{
  "type": "Feature",
  "properties": {
    "iso:country":"US",
    "sg:address":"2649 W 290 N",
    "sg:city":"Hurricane",
    "sg:classifiers":[
        {
            "category":"Building & Trades",
            "subcategory":"Landscaping Services",
            "type":"Services"
        }
    ],
    "sg:phone":"+1 435 635 8149",
    "sg:postcode":"84737",
    "sg:province":"UT",
    "wof:name":"Matthews Landscaping",
    "wof:placetype":"venue"
},
  "geometry": {"coordinates":[-113.367051,37.174554],"type":"Point"}
}