{
  "type": "Feature",
  "properties": {
    "iso:country":"US",
    "sg:address":"8619 Sandy Pkwy",
    "sg:city":"Sandy",
    "sg:classifiers":[
        {
            "category":"Building & Trades",
            "subcategory":"Construction",
            "type":"Services"
        }
    ],
    "sg:phone":"+1 801 255 4183",
    "sg:postcode":"84070",
    "sg:province":"UT",
    "sg:tags":[
        "general",
        "contractor"
    ],
    "wof:name":"Brubaker Construction",
    "wof:placetype":"venue"
},
  "geometry": {"coordinates":[-111.90545899999999,40.596124],"type":"Point"}
}