{
  "type": "Feature",
  "properties": {
    "iso:country":"US",
    "sg:address":"3572 W 2200 S",
    "sg:city":"Wellsville",
    "sg:classifiers":[
        {
            "category":"Freight",
            "type":"Transportation"
        }
    ],
    "sg:phone":"+1 435 752 6984",
    "sg:postcode":"84339",
    "sg:province":"UT",
    "sg:tags":[
        "operator",
        "local",
        "trucking"
    ],
    "wof:name":"C & K Trucking",
    "wof:placetype":"venue"
},
  "geometry": {"coordinates":[-111.913158,41.692563],"type":"Point"}
}