{
  "type": "Feature",
  "properties": {
    "iso:country":"US",
    "sg:address":"1600 Pinebrook Blvd",
    "sg:city":"Park City",
    "sg:classifiers":[
        {
            "category":"Professional",
            "subcategory":"Computer Services",
            "type":"Services"
        }
    ],
    "sg:phone":"+1 435 649 3886",
    "sg:postcode":"84098",
    "sg:province":"UT",
    "sg:tags":[
        "related"
    ],
    "wof:name":"Information Tech Specialist",
    "wof:placetype":"venue"
},
  "geometry": {"coordinates":[-111.571787,40.743466],"type":"Point"}
}