{
  "type": "Feature",
  "properties": {
    "iso:country":"US",
    "sg:address":"525 S State St",
    "sg:city":"Salt Lake City",
    "sg:classifiers":[
        {
            "category":"Wholesale",
            "subcategory":"Electrical",
            "type":"Manufacturing & Wholesale Goods"
        }
    ],
    "sg:phone":"+1 801 364 9904",
    "sg:postcode":"84111",
    "sg:province":"UT",
    "sg:tags":[
        "equipment",
        "electric",
        "supply"
    ],
    "wof:name":"Steed Electric & Lighting Co",
    "wof:placetype":"venue"
},
  "geometry": {"coordinates":[-111.888147,40.756838],"type":"Point"}
}