{
  "type": "Feature",
  "properties": {
    "iso:country":"US",
    "sg:address":"11483 S State St",
    "sg:city":"Draper",
    "sg:classifiers":[
        {
            "category":"Health Services",
            "subcategory":"Chiropractor",
            "type":"Services"
        }
    ],
    "sg:phone":"+1 801 571 7670",
    "sg:postcode":"84020",
    "sg:province":"UT",
    "sg:tags":[
        "chiropractic"
    ],
    "wof:name":"Maple Ridge Chiropractic LLC",
    "wof:placetype":"venue"
},
  "geometry": {"coordinates":[-111.891233,40.541222],"type":"Point"}
}