{
  "type": "Feature",
  "properties": {
    "iso:country":"US",
    "sg:address":"344 E Saunders St",
    "sg:city":"Salt Lake City",
    "sg:classifiers":[
        {
            "category":"Manufacturing",
            "subcategory":"Toys & Sporting Goods",
            "type":"Manufacturing & Wholesale Goods"
        }
    ],
    "sg:phone":"+1 801 583 1670",
    "sg:postcode":"84107",
    "sg:province":"UT",
    "sg:tags":[
        "mfg"
    ],
    "wof:name":"TLC Travel Inc",
    "wof:placetype":"venue"
},
  "geometry": {"coordinates":[-111.88120499999999,40.651781],"type":"Point"}
}