{
  "type": "Feature",
  "properties": {
    "iso:country":"US",
    "sg:address":"7852 Pioneer St",
    "sg:city":"Midvale",
    "sg:classifiers":[
        {
            "category":"Education",
            "subcategory":"School",
            "type":"Public Place"
        }
    ],
    "sg:phone":"+1 801 412 2150",
    "sg:postcode":"84047",
    "sg:province":"UT",
    "sg:website":"www.jordan.k12.ut.us",
    "wof:name":"Midvale Middle School",
    "wof:placetype":"venue"
},
  "geometry": {"coordinates":[-111.899698,40.608515],"type":"Point"}
}