{
  "type": "Feature",
  "properties": {
    "iso:country":"US",
    "sg:address":"19 N Main St",
    "sg:city":"Richfield",
    "sg:classifiers":[
        {
            "category":"Shopping",
            "subcategory":"Jewelry",
            "type":"Retail Goods"
        }
    ],
    "sg:phone":"+1 435 896 8811",
    "sg:postcode":"84701",
    "sg:province":"UT",
    "wof:name":"Diamond Store",
    "wof:placetype":"venue"
},
  "geometry": {"coordinates":[-112.08477600000001,38.769198],"type":"Point"}
}