{
  "type": "Feature",
  "properties": {
    "iso:country":"US",
    "sg:address":"340 S 400 W",
    "sg:city":"Payson",
    "sg:classifiers":[
        {
            "category":"Retail",
            "subcategory":"Animal Services",
            "type":"Services"
        }
    ],
    "sg:phone":"+1 801 465 2228",
    "sg:postcode":"84651",
    "sg:province":"UT",
    "wof:name":"Pet Palus",
    "wof:placetype":"venue"
},
  "geometry": {"coordinates":[-111.73790200000001,40.039173],"type":"Point"}
}