{
  "type": "Feature",
  "properties": {
    "iso:country":"US",
    "sg:address":"644 N 800 W",
    "sg:city":"Cedar City",
    "sg:classifiers":[
        {
            "category":"Retail",
            "subcategory":"Auto Repair",
            "type":"Services"
        }
    ],
    "sg:phone":"+1 435 586 8360",
    "sg:postcode":"84720",
    "sg:province":"UT",
    "sg:tags":[
        "repairing",
        "automobile"
    ],
    "wof:name":"Juan Ortega",
    "wof:placetype":"venue"
},
  "geometry": {"coordinates":[-113.07386,37.68664],"type":"Point"}
}