{
  "type": "Feature",
  "properties": {
    "iso:country":"US",
    "sg:address":"507 E Lake View Dr",
    "sg:city":"Payson",
    "sg:classifiers":[
        {
            "category":"Organizations",
            "subcategory":"Labor Organization",
            "type":"Services"
        }
    ],
    "sg:phone":"+1 801 423 1847",
    "sg:postcode":"84651",
    "sg:province":"UT",
    "wof:name":"Ingram Financial Lc",
    "wof:placetype":"venue"
},
  "geometry": {"coordinates":[-111.675591,40.00758],"type":"Point"}
}