{
  "type": "Feature",
  "properties": {
    "iso:country":"US",
    "sg:address":"1020 Westridge Dr",
    "sg:city":"St George",
    "sg:classifiers":[
        {
            "category":"Building & Trades",
            "subcategory":"Construction",
            "type":"Services"
        }
    ],
    "sg:phone":"+1 435 674 7327",
    "sg:postcode":"84770",
    "sg:province":"UT",
    "sg:tags":[
        "contractor"
    ],
    "wof:name":"Saint George Gunite",
    "wof:placetype":"venue"
},
  "geometry": {"coordinates":[-113.61617200000001,37.123224],"type":"Point"}
}