{
  "type": "Feature",
  "properties": {
    "iso:country":"US",
    "sg:address":"1128 N Main St",
    "sg:city":"Centerville",
    "sg:classifiers":[
        {
            "category":"Retail",
            "subcategory":"Laundry & Dry Cleaning",
            "type":"Services"
        }
    ],
    "sg:phone":"+1 801 298 8125",
    "sg:postcode":"84014",
    "sg:province":"UT",
    "sg:tags":[
        "trade",
        "contractor"
    ],
    "wof:name":"Flood Company The",
    "wof:placetype":"venue"
},
  "geometry": {"coordinates":[-111.878885,40.931298],"type":"Point"}
}