{
  "type": "Feature",
  "properties": {
    "iso:country":"US",
    "sg:address":"2375 S 900 E",
    "sg:city":"Salt Lake City",
    "sg:classifiers":[
        {
            "category":"Recreation",
            "type":"Entertainment"
        }
    ],
    "sg:phone":"+1 801 487 6120",
    "sg:postcode":"84106",
    "sg:province":"UT",
    "sg:tags":[
        "concessionaire"
    ],
    "wof:name":"Western Food Svc",
    "wof:placetype":"venue"
},
  "geometry": {"coordinates":[-111.865289,40.718485],"type":"Point"}
}