{
  "type": "Feature",
  "properties": {
    "iso:country":"US",
    "sg:address":"360 N 100 E",
    "sg:city":"Hyde Park",
    "sg:classifiers":[
        {
            "category":"Health Services",
            "subcategory":"Doctor",
            "type":"Services"
        }
    ],
    "sg:phone":"+1 435 563 9154",
    "sg:postcode":"84318",
    "sg:province":"UT",
    "wof:name":"Frank Harris",
    "wof:placetype":"venue"
},
  "geometry": {"coordinates":[-111.816408,41.805814],"type":"Point"}
}