{
  "type": "Feature",
  "properties": {
    "iso:country":"US",
    "sg:address":"6070 Wakefield Way",
    "sg:city":"Salt Lake City",
    "sg:classifiers":[
        {
            "category":"Retail",
            "subcategory":"Auto Rental",
            "type":"Services"
        }
    ],
    "sg:phone":"+1 801 466 8239",
    "sg:postcode":"84118",
    "sg:province":"UT",
    "sg:tags":[
        "renting",
        "truck",
        "leasing"
    ],
    "wof:name":"Budget Truck Rental",
    "wof:placetype":"venue"
},
  "geometry": {"coordinates":[-112.031458,40.640711],"type":"Point"}
}