{
  "type": "Feature",
  "properties": {
    "iso:country":"US",
    "sg:address":"3230 W 300 N",
    "sg:city":"Clearfield",
    "sg:classifiers":[
        {
            "category":"Farming",
            "subcategory":"Farm",
            "type":"Manufacturing & Wholesale Goods"
        }
    ],
    "sg:phone":"+1 801 825 8950",
    "sg:postcode":"84015",
    "sg:province":"UT",
    "sg:tags":[
        "crop",
        "general"
    ],
    "wof:name":"Stanley Wise",
    "wof:placetype":"venue"
},
  "geometry": {"coordinates":[-112.088561,41.118165],"type":"Point"}
}