{
  "type": "Feature",
  "properties": {
    "iso:country":"US",
    "sg:address":"202 N Beryl Hwy",
    "sg:city":"Beryl",
    "sg:classifiers":[
        {
            "category":"Education",
            "subcategory":"School",
            "type":"Public Place"
        }
    ],
    "sg:phone":"+1 435 439 5550",
    "sg:postcode":"84714",
    "sg:province":"UT",
    "wof:name":"Escalante Valley Elem School",
    "wof:placetype":"venue"
},
  "geometry": {"coordinates":[-113.656069,37.711094],"type":"Point"}
}