{
  "type": "Feature",
  "properties": {
    "iso:country":"US",
    "sg:address":"44 W Main St",
    "sg:city":"Price",
    "sg:classifiers":[
        {
            "category":"Manufacturing",
            "subcategory":"Soap",
            "type":"Manufacturing & Wholesale Goods"
        }
    ],
    "sg:phone":"+1 435 637 9869",
    "sg:postcode":"84501",
    "sg:province":"UT",
    "sg:tags":[
        "mfg"
    ],
    "wof:name":"Log Home Soaps",
    "wof:placetype":"venue"
},
  "geometry": {"coordinates":[-110.812363,39.599657],"type":"Point"}
}