{
  "type": "Feature",
  "properties": {
    "iso:country":"US",
    "sg:address":"516 N Vernal Ave",
    "sg:city":"Vernal",
    "sg:classifiers":[
        {
            "category":"Retail",
            "subcategory":"Auto Repair",
            "type":"Services"
        }
    ],
    "sg:phone":"+1 435 781 6586",
    "sg:postcode":"84078",
    "sg:province":"UT",
    "sg:tags":[
        "repairing",
        "automobile"
    ],
    "wof:name":"Preece Auto Svc Ctr",
    "wof:placetype":"venue"
},
  "geometry": {"coordinates":[-109.528632,40.463971],"type":"Point"}
}