{
  "type": "Feature",
  "properties": {
    "iso:country":"US",
    "sg:address":"1466 E 970 N",
    "sg:city":"Orem",
    "sg:classifiers":[
        {
            "category":"Health Services",
            "subcategory":"Doctor",
            "type":"Services"
        }
    ],
    "sg:phone":"+1 801 226 8246",
    "sg:postcode":"84097",
    "sg:province":"UT",
    "sg:tags":[
        "medical"
    ],
    "wof:name":"Mark Teresa Bowman Fmly Ltd PA",
    "wof:placetype":"venue"
},
  "geometry": {"coordinates":[-111.660584,40.314969],"type":"Point"}
}