{
  "type": "Feature",
  "properties": {
    "iso:country":"US",
    "sg:address":"1827 W 1350 S",
    "sg:city":"Ogden",
    "sg:classifiers":[
        {
            "category":"Building & Trades",
            "subcategory":"Construction",
            "type":"Services"
        }
    ],
    "sg:phone":"+1 801 731 6000",
    "sg:postcode":"84401",
    "sg:province":"UT",
    "sg:tags":[
        "contractor"
    ],
    "wof:name":"Affordable Sandblasting & Pntg",
    "wof:placetype":"venue"
},
  "geometry": {"coordinates":[-112.023794,41.242515],"type":"Point"}
}