{
  "type": "Feature",
  "properties": {
    "iso:country":"US",
    "sg:address":"224 S 200 W, Suite 230",
    "sg:city":"Salt Lake City",
    "sg:classifiers":[
        {
            "category":"Professional",
            "subcategory":"Computer Services",
            "type":"Services"
        }
    ],
    "sg:phone":"+1 866 376 4685",
    "sg:postcode":"84101",
    "sg:province":"UT",
    "sg:website":"http://www.3point5.com",
    "wof:name":"3point5.com",
    "wof:placetype":"venue"
},
  "geometry": {"coordinates":[-111.89688700000001,40.764454],"type":"Point"}
}