{
  "type": "Feature",
  "properties": {
    "iso:country":"US",
    "sg:address":"3825 N Lost Creek Rd",
    "sg:city":"Croydon",
    "sg:classifiers":[
        {
            "category":"Farming",
            "subcategory":"Livestock Farm",
            "type":"Manufacturing & Wholesale Goods"
        }
    ],
    "sg:phone":"+1 801 966 1393",
    "sg:postcode":"84018",
    "sg:province":"UT",
    "sg:tags":[
        "beef",
        "feedlot",
        "cattle"
    ],
    "wof:name":"Crouch Ranch",
    "wof:placetype":"venue"
},
  "geometry": {"coordinates":[-111.489457,41.081389],"type":"Point"}
}