{
  "type": "Feature",
  "properties": {
    "iso:country":"US",
    "sg:address":"1075 S 1700 W",
    "sg:city":"Salt Lake City",
    "sg:classifiers":[
        {
            "category":"Wholesale",
            "subcategory":"Hardware",
            "type":"Manufacturing & Wholesale Goods"
        }
    ],
    "sg:phone":"+1 801 886 2827",
    "sg:postcode":"84104",
    "sg:province":"UT",
    "sg:tags":[
        "nut",
        "bolt"
    ],
    "wof:name":"Western Industrial Parts Inc",
    "wof:placetype":"venue"
},
  "geometry": {"coordinates":[-111.938917,40.745432],"type":"Point"}
}