{
  "type": "Feature",
  "properties": {
    "iso:country":"US",
    "sg:address":"3281 W 6400 S",
    "sg:city":"Spanish Fork",
    "sg:classifiers":[
        {
            "category":"Building & Trades",
            "subcategory":"Construction",
            "type":"Services"
        }
    ],
    "sg:phone":"+1 801 798 9392",
    "sg:postcode":"84660",
    "sg:province":"UT",
    "sg:tags":[
        "contractor"
    ],
    "wof:name":"Youd Roofing Specialist Inc",
    "wof:placetype":"venue"
},
  "geometry": {"coordinates":[-111.73835099999999,40.114534],"type":"Point"}
}