{
  "type": "Feature",
  "properties": {
    "iso:country":"US",
    "sg:address":"614 W 600 S",
    "sg:city":"Salt Lake City",
    "sg:classifiers":[
        {
            "category":"Wholesale",
            "subcategory":"Hardware",
            "type":"Manufacturing & Wholesale Goods"
        }
    ],
    "sg:phone":"+1 801 359 3744",
    "sg:postcode":"84104",
    "sg:province":"UT",
    "sg:tags":[
        "refrigeration",
        "industrial",
        "e"
    ],
    "wof:name":"Efmco Systems Design Group",
    "wof:placetype":"venue"
},
  "geometry": {"coordinates":[-111.908705,40.756385],"type":"Point"}
}