{
  "type": "Feature",
  "properties": {
    "iso:country":"US",
    "sg:address":"7213 S 900 E",
    "sg:city":"Midvale",
    "sg:classifiers":[
        {
            "category":"Personal",
            "subcategory":"Beauty Salon",
            "type":"Services"
        }
    ],
    "sg:phone":"+1 801 569 1389",
    "sg:postcode":"84047",
    "sg:province":"UT",
    "sg:tags":[
        "nail"
    ],
    "wof:name":"Queen Nails",
    "wof:placetype":"venue"
},
  "geometry": {"coordinates":[-111.86593499999999,40.620983],"type":"Point"}
}