{
  "type": "Feature",
  "properties": {
    "iso:country":"US",
    "sg:address":"1425 W Center St",
    "sg:city":"Orem",
    "sg:classifiers":[
        {
            "category":"Personal",
            "type":"Services"
        }
    ],
    "sg:phone":"+1 801 225 7946",
    "sg:postcode":"84057",
    "sg:province":"UT",
    "sg:tags":[
        "general"
    ],
    "wof:name":"Security First Storage",
    "wof:placetype":"venue"
},
  "geometry": {"coordinates":[-111.729539,40.297062],"type":"Point"}
}