{
  "type": "Feature",
  "properties": {
    "iso:country":"US",
    "sg:address":"11 E State St",
    "sg:city":"Farmington",
    "sg:classifiers":[
        {
            "category":"Personal",
            "subcategory":"Beauty Salon",
            "type":"Services"
        }
    ],
    "sg:phone":"+1 801 451 7341",
    "sg:postcode":"84025",
    "sg:province":"UT",
    "sg:tags":[
        "shop"
    ],
    "wof:name":"Deeanns Clip & Curl",
    "wof:placetype":"venue"
},
  "geometry": {"coordinates":[-111.88622700000001,40.98055],"type":"Point"}
}