{
  "type": "Feature",
  "properties": {
    "iso:country":"US",
    "sg:address":"6236 Shenandoah Park Ave",
    "sg:city":"Salt Lake City",
    "sg:classifiers":[
        {
            "category":"Banks & Credit Unions",
            "subcategory":"Financial Services",
            "type":"Services"
        }
    ],
    "sg:phone":"+1 801 272 4622",
    "sg:postcode":"84121",
    "sg:province":"UT",
    "sg:tags":[
        "investor"
    ],
    "wof:name":"Cannonwood Investments LLC",
    "wof:placetype":"venue"
},
  "geometry": {"coordinates":[-111.841787,40.635325],"type":"Point"}
}