{
  "type": "Feature",
  "properties": {
    "iso:country":"US",
    "sg:address":"49 Main St",
    "sg:city":"Green River",
    "sg:classifiers":[
        {
            "category":"Banks & Credit Unions",
            "subcategory":"Bank",
            "type":"Services"
        }
    ],
    "sg:phone":"+1 435 564 3486",
    "sg:postcode":"84525",
    "sg:province":"UT",
    "wof:name":"Key Bank",
    "wof:placetype":"venue"
},
  "geometry": {"coordinates":[-110.162773,38.995443],"type":"Point"}
}