{
  "type": "Feature",
  "properties": {
    "iso:country":"US",
    "sg:address":"2735 S 2000 E",
    "sg:city":"Salt Lake City",
    "sg:classifiers":[
        {
            "category":"Wholesale",
            "subcategory":"Plants",
            "type":"Manufacturing & Wholesale Goods"
        }
    ],
    "sg:phone":"+1 801 485 2542",
    "sg:postcode":"84109",
    "sg:province":"UT",
    "sg:tags":[
        "interior",
        "p",
        "cactus",
        "garden",
        "supply"
    ],
    "wof:name":"Cactus and Tropicals Inc",
    "wof:placetype":"venue"
},
  "geometry": {"coordinates":[-111.834082,40.712112],"type":"Point"}
}