{
  "type": "Feature",
  "properties": {
    "iso:country":"US",
    "sg:address":"1098 Hackamore Dr",
    "sg:city":"Draper",
    "sg:classifiers":[
        {
            "category":"Building & Trades",
            "subcategory":"Electrical",
            "type":"Services"
        }
    ],
    "sg:phone":"+1 801 572 2998",
    "sg:postcode":"84020",
    "sg:province":"UT",
    "sg:tags":[
        "electrical",
        "contractor"
    ],
    "wof:name":"Electro Specialties",
    "wof:placetype":"venue"
},
  "geometry": {"coordinates":[-111.859453,40.501479],"type":"Point"}
}