{
  "type": "Feature",
  "properties": {
    "iso:country":"US",
    "sg:address":"7005 W Gates Ave",
    "sg:city":"Salt Lake City",
    "sg:classifiers":[
        {
            "category":"Professional",
            "type":"Services"
        }
    ],
    "sg:phone":"+1 801 981 8376",
    "sg:postcode":"84128",
    "sg:province":"UT",
    "wof:name":"Container Services",
    "wof:placetype":"venue"
},
  "geometry": {"coordinates":[-112.061419,40.716866],"type":"Point"}
}