{
  "type": "Feature",
  "properties": {
    "iso:country":"US",
    "sg:address":"3521 S Westwood Dr",
    "sg:city":"Salt Lake City",
    "sg:classifiers":[
        {
            "category":"Professional",
            "type":"Services"
        }
    ],
    "sg:phone":"+1 801 272 4957",
    "sg:postcode":"84109",
    "sg:province":"UT",
    "sg:tags":[
        "geophysicist"
    ],
    "wof:name":"Utah Geophysical",
    "wof:placetype":"venue"
},
  "geometry": {"coordinates":[-111.789455,40.695629],"type":"Point"}
}