{
  "type": "Feature",
  "properties": {
    "iso:country":"US",
    "sg:address":"4207 W 3550 S",
    "sg:city":"Salt Lake City",
    "sg:classifiers":[
        {
            "category":"Building & Trades",
            "subcategory":"Construction",
            "type":"Services"
        }
    ],
    "sg:phone":"+1 801 679 1952",
    "sg:postcode":"84120",
    "sg:province":"UT",
    "sg:tags":[
        "excavation",
        "contractor"
    ],
    "wof:name":"Henderson Brothers Inc",
    "wof:placetype":"venue"
},
  "geometry": {"coordinates":[-111.992261,40.694249],"type":"Point"}
}