{
  "type": "Feature",
  "properties": {
    "iso:country":"US",
    "sg:address":"10502 S 2700 W",
    "sg:city":"South Jordan",
    "sg:classifiers":[
        {
            "category":"Building & Trades",
            "subcategory":"Construction",
            "type":"Services"
        }
    ],
    "sg:phone":"+1 801 254 0661",
    "sg:postcode":"84095",
    "sg:province":"UT",
    "sg:tags":[
        "house",
        "handyman"
    ],
    "wof:name":"All Round Home Repair",
    "wof:placetype":"venue"
},
  "geometry": {"coordinates":[-111.957825,40.560423],"type":"Point"}
}