{
  "type": "Feature",
  "properties": {
    "iso:country":"US",
    "sg:address":"7001 S 900 East St",
    "sg:city":"Midvale",
    "sg:classifiers":[
        {
            "category":"Organizations",
            "subcategory":"Labor Organization",
            "type":"Services"
        }
    ],
    "sg:phone":"+1 801 255 7101",
    "sg:postcode":"84047",
    "sg:province":"UT",
    "wof:name":"Steven Duke",
    "wof:placetype":"venue"
},
  "geometry": {"coordinates":[-111.86588999999999,40.624547],"type":"Point"}
}