{
  "type": "Feature",
  "properties": {
    "iso:country":"US",
    "sg:address":"4390 S Main St",
    "sg:city":"Salt Lake City",
    "sg:classifiers":[
        {
            "category":"Building & Trades",
            "subcategory":"Electrical",
            "type":"Services"
        }
    ],
    "sg:phone":"+1 801 265 5107",
    "sg:postcode":"84107",
    "sg:province":"UT",
    "sg:tags":[
        "electrical",
        "contractor"
    ],
    "wof:name":"Qwest",
    "wof:placetype":"venue"
},
  "geometry": {"coordinates":[-111.891329,40.675227],"type":"Point"}
}