{
  "type": "Feature",
  "properties": {
    "iso:country":"US",
    "sg:address":"562 S Main St",
    "sg:city":"Bountiful",
    "sg:classifiers":[
        {
            "category":"Banks & Credit Unions",
            "subcategory":"Bank",
            "type":"Services"
        }
    ],
    "sg:phone":"+1 801 535 1225",
    "sg:postcode":"84010",
    "sg:province":"UT",
    "wof:name":"Key Bank",
    "wof:placetype":"venue"
},
  "geometry": {"coordinates":[-111.880751,40.883167],"type":"Point"}
}