{
  "type": "Feature",
  "properties": {
    "iso:country":"US",
    "sg:address":"145 N 100 E",
    "sg:city":"Richfield",
    "sg:classifiers":[
        {
            "category":"Health Services",
            "subcategory":"Optometrist",
            "type":"Services"
        }
    ],
    "sg:phone":"+1 435 896 8142",
    "sg:postcode":"84701",
    "sg:province":"UT",
    "wof:name":"Valley Vision Clinic",
    "wof:placetype":"venue"
},
  "geometry": {"coordinates":[-112.083018,38.77024],"type":"Point"}
}