{
  "type": "Feature",
  "properties": {
    "iso:country":"US",
    "sg:address":"3030 Elmwood Dr",
    "sg:city":"Riverton",
    "sg:classifiers":[
        {
            "category":"Utilities",
            "subcategory":"Water",
            "type":"Services"
        }
    ],
    "sg:phone":"+1 801 254 5141",
    "sg:postcode":"84065",
    "sg:province":"UT",
    "sg:tags":[
        "supply"
    ],
    "wof:name":"Elm Meadows Water Users",
    "wof:placetype":"venue"
},
  "geometry": {"coordinates":[-111.964482,40.52621],"type":"Point"}
}