{
  "type": "Feature",
  "properties": {
    "iso:country":"US",
    "sg:address":"1464 W 900 S",
    "sg:city":"Spanish Fork",
    "sg:classifiers":[
        {
            "category":"Banks & Credit Unions",
            "subcategory":"Financial Services",
            "type":"Services"
        }
    ],
    "sg:phone":"+1 801 798 3982",
    "sg:postcode":"84660",
    "sg:province":"UT",
    "sg:tags":[
        "trust",
        "management"
    ],
    "wof:name":"T & J Woodhouse Properties Lc",
    "wof:placetype":"venue"
},
  "geometry": {"coordinates":[-111.68953999999999,40.098385],"type":"Point"}
}