{
  "type": "Feature",
  "properties": {
    "iso:country":"US",
    "sg:address":"307 Washington Blvd",
    "sg:city":"Ogden",
    "sg:classifiers":[
        {
            "category":"Wholesale",
            "subcategory":"Machinery & Supplies",
            "type":"Manufacturing & Wholesale Goods"
        }
    ],
    "sg:phone":"+1 801 394 0112",
    "sg:postcode":"84404",
    "sg:province":"UT",
    "sg:tags":[
        "barbecue",
        "equipment"
    ],
    "wof:name":"Traeger Wood Pellet Bbq Grills",
    "wof:placetype":"venue"
},
  "geometry": {"coordinates":[-111.96970399999999,41.256246],"type":"Point"}
}