{
  "type": "Feature",
  "properties": {
    "iso:country":"US",
    "sg:address":"481 S 100 W",
    "sg:city":"Monticello",
    "sg:classifiers":[
        {
            "category":"Freight",
            "type":"Transportation"
        }
    ],
    "sg:phone":"+1 435 587 2158",
    "sg:postcode":"84535",
    "sg:province":"UT",
    "sg:tags":[
        "trucking"
    ],
    "wof:name":"Harris Transport",
    "wof:placetype":"venue"
},
  "geometry": {"coordinates":[-109.34476100000001,37.865756],"type":"Point"}
}