{
  "type": "Feature",
  "properties": {
    "iso:country":"US",
    "sg:address":"2896 S 500 E",
    "sg:city":"Salt Lake City",
    "sg:classifiers":[
        {
            "category":"Shopping",
            "type":"Retail Goods"
        }
    ],
    "sg:phone":"+1 801 474 3995",
    "sg:postcode":"84106",
    "sg:province":"UT",
    "sg:tags":[
        "cosmetic",
        "perfume"
    ],
    "wof:name":"Aloette Cosmetics",
    "wof:placetype":"venue"
},
  "geometry": {"coordinates":[-111.876957,40.708395],"type":"Point"}
}