{
  "type": "Feature",
  "properties": {
    "iso:country":"US",
    "sg:address":"1274 E 600 N Cir",
    "sg:city":"American Fork",
    "sg:classifiers":[
        {
            "category":"Museum",
            "type":"Entertainment"
        }
    ],
    "sg:phone":"+1 801 763 1066",
    "sg:postcode":"84003",
    "sg:province":"UT",
    "sg:tags":[
        "organization",
        "religious",
        "gallery"
    ],
    "wof:name":"Somerville Manor",
    "wof:placetype":"venue"
},
  "geometry": {"coordinates":[-111.764464,40.389854],"type":"Point"}
}