{
  "type": "Feature",
  "properties": {
    "iso:country":"US",
    "sg:address":"780 W 600 N",
    "sg:city":"Tremonton",
    "sg:classifiers":[
        {
            "category":"Building & Trades",
            "subcategory":"Plumbing",
            "type":"Services"
        }
    ],
    "sg:phone":"+1 435 257 0317",
    "sg:postcode":"84337",
    "sg:province":"UT",
    "sg:tags":[
        "plumbing",
        "contractor"
    ],
    "wof:name":"Mike Norr Plumbing Inc",
    "wof:placetype":"venue"
},
  "geometry": {"coordinates":[-112.17887,41.718745],"type":"Point"}
}