{
  "type": "Feature",
  "properties": {
    "iso:country":"US",
    "sg:address":"228 W 150 N",
    "sg:city":"Hyde Park",
    "sg:classifiers":[
        {
            "category":"Building & Trades",
            "subcategory":"Plumbing",
            "type":"Services"
        }
    ],
    "sg:phone":"+1 435 563 0611",
    "sg:postcode":"84318",
    "sg:province":"UT",
    "sg:tags":[
        "contractor"
    ],
    "wof:name":"Lees Plumbing Inc",
    "wof:placetype":"venue"
},
  "geometry": {"coordinates":[-111.82626999999999,41.801995],"type":"Point"}
}