{
  "type": "Feature",
  "properties": {
    "iso:country":"US",
    "sg:address":"1127 Shannon Dr",
    "sg:city":"Farmington",
    "sg:classifiers":[
        {
            "category":"Wholesale",
            "subcategory":"Non-durable Goods",
            "type":"Manufacturing & Wholesale Goods"
        }
    ],
    "sg:phone":"+1 801 451 7927",
    "sg:postcode":"84025",
    "sg:province":"UT",
    "sg:tags":[
        "interior"
    ],
    "wof:name":"Accentuous",
    "wof:placetype":"venue"
},
  "geometry": {"coordinates":[-111.88928199999999,40.999014],"type":"Point"}
}