{
  "type": "Feature",
  "properties": {
    "iso:country":"US",
    "sg:address":"438 Commerce Rd",
    "sg:city":"Orem",
    "sg:classifiers":[
        {
            "category":"Manufacturing",
            "subcategory":"Metals",
            "type":"Manufacturing & Wholesale Goods"
        }
    ],
    "sg:phone":"+1 801 434 9883",
    "sg:postcode":"84058",
    "sg:province":"UT",
    "sg:tags":[
        "tower"
    ],
    "sg:website":"www.intermountaintower.com",
    "wof:name":"Intermountain Tower Specialist",
    "wof:placetype":"venue"
},
  "geometry": {"coordinates":[-111.72969399999999,40.289304],"type":"Point"}
}