{
  "type": "Feature",
  "properties": {
    "iso:country":"US",
    "sg:address":"1051 N Bluff St",
    "sg:city":"St George",
    "sg:classifiers":[
        {
            "category":"Cinema",
            "subcategory":"Movie Theater",
            "type":"Entertainment"
        }
    ],
    "sg:phone":"+1 435 673 1994",
    "sg:postcode":"84770",
    "sg:province":"UT",
    "wof:name":"Sunset Corners Stadium 8",
    "wof:placetype":"venue"
},
  "geometry": {"coordinates":[-113.601912,37.128192],"type":"Point"}
}