{
  "type": "Feature",
  "properties": {
    "iso:country":"US",
    "sg:address":"34 E 1490 South Pl",
    "sg:city":"Logan",
    "sg:classifiers":[
        {
            "category":"Building & Trades",
            "subcategory":"Landscaping Services",
            "type":"Services"
        }
    ],
    "sg:phone":"+1 435 755 5855",
    "sg:postcode":"84321",
    "sg:province":"UT",
    "sg:tags":[
        "lawn",
        "maintenance",
        "grounds"
    ],
    "wof:name":"B JS Lawn & Pest Control",
    "wof:placetype":"venue"
},
  "geometry": {"coordinates":[-111.847055,41.704217],"type":"Point"}
}