{
  "type": "Feature",
  "properties": {
    "iso:country":"US",
    "sg:address":"1162 E 1850 S",
    "sg:city":"Bountiful",
    "sg:classifiers":[
        {
            "category":"Social Services",
            "type":"Services"
        }
    ],
    "sg:phone":"+1 801 292 7456",
    "sg:postcode":"84010",
    "sg:province":"UT",
    "wof:name":"Blake Assoc Counseling & Cons",
    "wof:placetype":"venue"
},
  "geometry": {"coordinates":[-111.856505,40.870389],"type":"Point"}
}