{
  "type": "Feature",
  "properties": {
    "iso:country":"US",
    "sg:address":"4775 Westpoint Dr",
    "sg:city":"Salt Lake City",
    "sg:classifiers":[
        {
            "category":"Personal",
            "subcategory":"Beauty Salon",
            "type":"Services"
        }
    ],
    "sg:phone":"+1 801 965 1962",
    "sg:postcode":"84120",
    "sg:province":"UT",
    "sg:tags":[
        "shop"
    ],
    "wof:name":"Shear Perfection",
    "wof:placetype":"venue"
},
  "geometry": {"coordinates":[-112.00322799999999,40.670498],"type":"Point"}
}