{
  "type": "Feature",
  "properties": {
    "iso:country":"US",
    "sg:address":"843 Clover Meadow Dr",
    "sg:city":"Salt Lake City",
    "sg:classifiers":[
        {
            "category":"Building & Trades",
            "subcategory":"Construction",
            "type":"Services"
        }
    ],
    "sg:phone":"+1 801 261 1636",
    "sg:postcode":"84123",
    "sg:province":"UT",
    "sg:tags":[
        "house"
    ],
    "wof:name":"Ken Nickle Construction Co",
    "wof:placetype":"venue"
},
  "geometry": {"coordinates":[-111.914203,40.654167],"type":"Point"}
}