{
  "type": "Feature",
  "properties": {
    "iso:country":"US",
    "sg:address":"995 Hillside Dr",
    "sg:city":"Provo",
    "sg:classifiers":[
        {
            "category":"Real Estate",
            "subcategory":"Real Estate Agent",
            "type":"Services"
        }
    ],
    "sg:phone":"+1 801 226 8272",
    "sg:postcode":"84604",
    "sg:province":"UT",
    "sg:tags":[
        "broker"
    ],
    "wof:name":"Bankers Realty RE Svcs",
    "wof:placetype":"venue"
},
  "geometry": {"coordinates":[-111.640064,40.297633],"type":"Point"}
}