{
  "type": "Feature",
  "properties": {
    "iso:country":"US",
    "sg:address":"2527 S Main St",
    "sg:city":"Woods Cross",
    "sg:classifiers":[
        {
            "category":"Autos & Motor Vehicles",
            "subcategory":"Auto Supplies",
            "type":"Retail Goods"
        }
    ],
    "sg:phone":"+1 801 298 7312",
    "sg:postcode":"84010",
    "sg:province":"UT",
    "sg:tags":[
        "tire"
    ],
    "sg:website":"www.discounttire.com/makeappt",
    "wof:name":"Discount Tire",
    "wof:placetype":"venue"
},
  "geometry": {"coordinates":[-111.895313,40.86214],"type":"Point"}
}