{
  "type": "Feature",
  "properties": {
    "iso:country":"US",
    "sg:address":"949 E 10600 S",
    "sg:city":"Sandy",
    "sg:classifiers":[
        {
            "category":"Organizations",
            "subcategory":"Religious Organization",
            "type":"Services"
        }
    ],
    "sg:phone":"+1 801 576 2904",
    "sg:postcode":"84094",
    "sg:province":"UT",
    "sg:tags":[
        "mormon",
        "church"
    ],
    "wof:name":"Crescent Fourth Ward",
    "wof:placetype":"venue"
},
  "geometry": {"coordinates":[-111.863766,40.55883],"type":"Point"}
}