{
  "type": "Feature",
  "properties": {
    "iso:country":"US",
    "sg:address":"1939 W 800 N",
    "sg:city":"Mapleton",
    "sg:classifiers":[
        {
            "category":"Wholesale",
            "subcategory":"Home Furnishings",
            "type":"Manufacturing & Wholesale Goods"
        }
    ],
    "sg:phone":"+1 801 491 7266",
    "sg:postcode":"84664",
    "sg:province":"UT",
    "sg:tags":[
        "closet",
        "accessory"
    ],
    "wof:name":"Closet Guy",
    "wof:placetype":"venue"
},
  "geometry": {"coordinates":[-111.599783,40.137372],"type":"Point"}
}