{
  "type": "Feature",
  "properties": {
    "iso:country":"US",
    "sg:address":"1265 N 500 E",
    "sg:city":"Richfield",
    "sg:classifiers":[
        {
            "category":"Organizations",
            "subcategory":"Religious Organization",
            "type":"Services"
        }
    ],
    "sg:phone":"+1 435 896 8181",
    "sg:postcode":"84701",
    "sg:province":"UT",
    "sg:tags":[
        "church"
    ],
    "wof:name":"Church Of Jesus Christ Of Lds",
    "wof:placetype":"venue"
},
  "geometry": {"coordinates":[-112.076386,38.788255],"type":"Point"}
}