{
  "type": "Feature",
  "properties": {
    "iso:country":"US",
    "sg:address":"642 Pinyon Dr",
    "sg:city":"Dugway",
    "sg:classifiers":[
        {
            "category":"Building & Trades",
            "subcategory":"Cleaning & Sanitation",
            "type":"Services"
        }
    ],
    "sg:phone":"+1 435 831 4702",
    "sg:postcode":"84022",
    "sg:province":"UT",
    "sg:tags":[
        "janitorial"
    ],
    "wof:name":"Harley Fike",
    "wof:placetype":"venue"
},
  "geometry": {"coordinates":[-112.74306300000001,40.230297],"type":"Point"}
}