{
  "type": "Feature",
  "properties": {
    "iso:country":"US",
    "sg:address":"233 W 1300 S",
    "sg:city":"Salt Lake City",
    "sg:classifiers":[
        {
            "category":"Organizations",
            "subcategory":"Labor Organization",
            "type":"Services"
        }
    ],
    "sg:phone":"+1 801 467 1051",
    "sg:postcode":"84115",
    "sg:province":"UT",
    "wof:name":"Local 38",
    "wof:placetype":"venue"
},
  "geometry": {"coordinates":[-111.899304,40.741532],"type":"Point"}
}