{
  "type": "Feature",
  "properties": {
    "iso:country":"US",
    "sg:address":"120 S Main St",
    "sg:city":"Randolph",
    "sg:classifiers":[
        {
            "category":"Communications",
            "type":"Services"
        }
    ],
    "sg:phone":"+1 435 793 9954",
    "sg:postcode":"84064",
    "sg:province":"UT",
    "wof:name":"Pacific Communications",
    "wof:placetype":"venue"
},
  "geometry": {"coordinates":[-111.18496500000001,41.663027],"type":"Point"}
}