{
  "type": "Feature",
  "properties": {
    "iso:country":"US",
    "sg:address":"3000 W 4600 N",
    "sg:city":"Brigham City",
    "sg:classifiers":[
        {
            "category":"Travel",
            "subcategory":"Travel Agent",
            "type":"Entertainment"
        }
    ],
    "sg:phone":"+1 435 279 8935",
    "sg:postcode":"84302",
    "sg:province":"UT",
    "sg:tags":[
        "agency",
        "bureau"
    ],
    "wof:name":"1-2-3 Super Travel",
    "wof:placetype":"venue"
},
  "geometry": {"coordinates":[-112.087777,41.593201],"type":"Point"}
}