{
  "type": "Feature",
  "properties": {
    "iso:country":"US",
    "sg:address":"320 S 300 E",
    "sg:city":"Salt Lake City",
    "sg:classifiers":[
        {
            "category":"Building & Trades",
            "subcategory":"Construction",
            "type":"Services"
        }
    ],
    "sg:phone":"+1 801 463 3830",
    "sg:postcode":"84111",
    "sg:province":"UT",
    "sg:tags":[
        "general",
        "contractor"
    ],
    "wof:name":"Rhino Sports",
    "wof:placetype":"venue"
},
  "geometry": {"coordinates":[-111.88257400000001,40.761099],"type":"Point"}
}