{
  "type": "Feature",
  "properties": {
    "iso:country":"US",
    "sg:address":"8944 S State St",
    "sg:city":"Sandy",
    "sg:classifiers":[
        {
            "category":"Shopping",
            "subcategory":"Shoes",
            "type":"Retail Goods"
        }
    ],
    "sg:phone":"+1 801 561 8778",
    "sg:postcode":"84070",
    "sg:province":"UT",
    "sg:tags":[
        "orthopedic",
        "footwear"
    ],
    "wof:name":"Good Feet Of Utah",
    "wof:placetype":"venue"
},
  "geometry": {"coordinates":[-111.890933,40.589305],"type":"Point"}
}