{
  "type": "Feature",
  "properties": {
    "iso:country":"US",
    "sg:address":"1772 S Redwood Rd",
    "sg:city":"Salt Lake City",
    "sg:classifiers":[
        {
            "category":"Home & Garden",
            "subcategory":"Household Appliances",
            "type":"Retail Goods"
        }
    ],
    "sg:phone":"+1 801 972 8797",
    "sg:postcode":"84104",
    "sg:province":"UT",
    "wof:name":"USA Appliances",
    "wof:placetype":"venue"
},
  "geometry": {"coordinates":[-111.93903899999999,40.731093],"type":"Point"}
}