{
  "type": "Feature",
  "properties": {
    "iso:country":"US",
    "sg:address":"2201 Alexander St",
    "sg:city":"West Valley",
    "sg:classifiers":[
        {
            "category":"Wholesale",
            "subcategory":"Durable Goods & Equipment",
            "type":"Manufacturing & Wholesale Goods"
        }
    ],
    "sg:phone":"+1 801 977 0641",
    "sg:postcode":"84119",
    "sg:province":"UT",
    "sg:tags":[
        "representative",
        "manufacturer"
    ],
    "wof:name":"Comed Medical Specialties Inc",
    "wof:placetype":"venue"
},
  "geometry": {"coordinates":[-111.948931,40.717701],"type":"Point"}
}