{
  "type": "Feature",
  "properties": {
    "iso:country":"US",
    "sg:address":"2681 N 750 E",
    "sg:city":"Ogden",
    "sg:classifiers":[
        {
            "category":"Professional",
            "subcategory":"Business Services",
            "type":"Services"
        }
    ],
    "sg:phone":"+1 801 737 0697",
    "sg:postcode":"84414",
    "sg:province":"UT",
    "wof:name":"Parkinson Enterprises Inc",
    "wof:placetype":"venue"
},
  "geometry": {"coordinates":[-111.956373,41.307666],"type":"Point"}
}