{
  "type": "Feature",
  "properties": {
    "iso:country":"US",
    "sg:address":"111 N 200 E",
    "sg:city":"Price",
    "sg:classifiers":[
        {
            "category":"Health Services",
            "subcategory":"Doctor",
            "type":"Services"
        }
    ],
    "sg:phone":"+1 435 637 0430",
    "sg:postcode":"84501",
    "sg:province":"UT",
    "wof:name":"Monte Dansie DDS",
    "wof:placetype":"venue"
},
  "geometry": {"coordinates":[-110.807405,39.602296],"type":"Point"}
}