{
  "type": "Feature",
  "properties": {
    "iso:country":"US",
    "sg:address":"193 S Bluff St",
    "sg:city":"St George",
    "sg:classifiers":[
        {
            "category":"Home & Garden",
            "subcategory":"Furniture",
            "type":"Retail Goods"
        }
    ],
    "sg:phone":"+1 435 656 5454",
    "sg:postcode":"84770",
    "sg:province":"UT",
    "wof:name":"Rooster Hollow",
    "wof:placetype":"venue"
},
  "geometry": {"coordinates":[-113.59286400000001,37.104946],"type":"Point"}
}