{
  "type": "Feature",
  "properties": {
    "iso:country":"US",
    "sg:address":"3015 Daybreaker Dr",
    "sg:city":"Park City",
    "sg:classifiers":[
        {
            "category":"Real Estate",
            "subcategory":"Real Estate Agent",
            "type":"Services"
        }
    ],
    "sg:phone":"+1 435 615 8575",
    "sg:postcode":"84098",
    "sg:province":"UT",
    "wof:name":"Daybreak Realty PC",
    "wof:placetype":"venue"
},
  "geometry": {"coordinates":[-111.581723,40.768038],"type":"Point"}
}