{
  "type": "Feature",
  "properties": {
    "iso:country":"US",
    "sg:address":"1975 Orchard Dr",
    "sg:city":"Bountiful",
    "sg:classifiers":[
        {
            "category":"Retail",
            "subcategory":"Veterinary Services",
            "type":"Services"
        }
    ],
    "sg:phone":"+1 801 298 2314",
    "sg:postcode":"84010",
    "sg:province":"UT",
    "sg:tags":[
        "veterinarian"
    ],
    "sg:website":"www.lakeviewanimal.com",
    "wof:name":"Lakeview Animal Hospital",
    "wof:placetype":"venue"
},
  "geometry": {"coordinates":[-111.876999,40.868801],"type":"Point"}
}