{
  "type": "Feature",
  "properties": {
    "iso:country":"US",
    "sg:address":"1020 N 250 W",
    "sg:city":"Bountiful",
    "sg:classifiers":[
        {
            "category":"Organizations",
            "subcategory":"Religious Organization",
            "type":"Services"
        }
    ],
    "sg:phone":"+1 801 299 4237",
    "sg:postcode":"84010",
    "sg:province":"UT",
    "sg:tags":[
        "mormon",
        "church"
    ],
    "wof:name":"The Corporation of The Pres of",
    "wof:placetype":"venue"
},
  "geometry": {"coordinates":[-111.88694700000001,40.900082],"type":"Point"}
}