{
  "type": "Feature",
  "properties": {
    "iso:country":"US",
    "sg:address":"354 Mountain Way Dr",
    "sg:city":"Orem",
    "sg:classifiers":[
        {
            "category":"Professional",
            "subcategory":"Art Services",
            "type":"Services"
        }
    ],
    "sg:phone":"+1 801 224 9696",
    "sg:postcode":"84058",
    "sg:province":"UT",
    "sg:tags":[
        "photography",
        "event"
    ],
    "wof:name":"Propix",
    "wof:placetype":"venue"
},
  "geometry": {"coordinates":[-111.729236,40.290773],"type":"Point"}
}