{
  "type": "Feature",
  "properties": {
    "iso:country":"US",
    "sg:address":"1015 N 500 E",
    "sg:city":"North Salt Lake",
    "sg:classifiers":[
        {
            "category":"Fast Food",
            "type":"Food & Drink"
        },
        {
            "category":"Food & Beverages",
            "subcategory":"Meat & Fish",
            "type":"Retail Goods"
        }
    ],
    "sg:phone":"+1 801 295 0222",
    "sg:postcode":"84054",
    "sg:province":"UT",
    "sg:tags":[
        "burger",
        "hot",
        "dog"
    ],
    "wof:name":"Best Burger",
    "wof:placetype":"venue"
},
  "geometry": {"coordinates":[-111.899002,40.861099],"type":"Point"}
}