{
  "type": "Feature",
  "properties": {
    "iso:country":"US",
    "sg:address":"2424 Vineyard Rd",
    "sg:city":"Santa Clara",
    "sg:classifiers":[
        {
            "category":"Social Services",
            "subcategory":"Child Care",
            "type":"Services"
        }
    ],
    "sg:phone":"+1 435 673 3945",
    "sg:postcode":"84765",
    "sg:province":"UT",
    "sg:tags":[
        "day"
    ],
    "wof:name":"Kathy Ence Preschool",
    "wof:placetype":"venue"
},
  "geometry": {"coordinates":[-113.63996899999999,37.123249],"type":"Point"}
}