{
  "type": "Feature",
  "properties": {
    "iso:country":"US",
    "sg:address":"372 E 12600 S",
    "sg:city":"Draper",
    "sg:classifiers":[
        {
            "category":"Professional",
            "subcategory":"Business Services",
            "type":"Services"
        }
    ],
    "sg:phone":"+1 801 571 5252",
    "sg:postcode":"84020",
    "sg:province":"UT",
    "wof:name":"Southridge Corporate Serv",
    "wof:placetype":"venue"
},
  "geometry": {"coordinates":[-111.879368,40.522399],"type":"Point"}
}