{
  "type": "Feature",
  "properties": {
    "iso:country":"US",
    "sg:address":"1812 Empire Rd",
    "sg:city":"Salt Lake City",
    "sg:classifiers":[
        {
            "category":"Freight",
            "type":"Transportation"
        }
    ],
    "sg:phone":"+1 801 886 1088",
    "sg:postcode":"84104",
    "sg:province":"UT",
    "sg:tags":[
        "commercial",
        "storage"
    ],
    "wof:name":"Valley Storage West",
    "wof:placetype":"venue"
},
  "geometry": {"coordinates":[-111.942756,40.729075],"type":"Point"}
}