{
  "type": "Feature",
  "properties": {
    "iso:country":"US",
    "sg:address":"8284 Coolidge St",
    "sg:city":"Midvale",
    "sg:classifiers":[
        {
            "category":"Freight",
            "type":"Transportation"
        }
    ],
    "sg:phone":"+1 801 255 1410",
    "sg:postcode":"84047",
    "sg:province":"UT",
    "sg:tags":[
        "car",
        "railroad",
        "rental"
    ],
    "wof:name":"Louis Ault",
    "wof:placetype":"venue"
},
  "geometry": {"coordinates":[-111.894312,40.60413],"type":"Point"}
}