{
  "type": "Feature",
  "properties": {
    "iso:country":"US",
    "sg:address":"7465 Brook Hollow Loop Rd",
    "sg:city":"Park City",
    "sg:classifiers":[
        {
            "category":"Restaurant",
            "type":"Food & Drink"
        }
    ],
    "sg:phone":"+1 435 649 0144",
    "sg:postcode":"84098",
    "sg:province":"UT",
    "sg:tags":[
        "eating"
    ],
    "wof:name":"Park City Specialty Foods",
    "wof:placetype":"venue"
},
  "geometry": {"coordinates":[-111.567184,40.743352],"type":"Point"}
}