{
  "type": "Feature",
  "properties": {
    "iso:country":"US",
    "sg:address":"906 Granite Peak Dr",
    "sg:city":"Sandy",
    "sg:classifiers":[
        {
            "category":"Shopping",
            "subcategory":"Hobbies, Toys, & Games",
            "type":"Retail Goods"
        }
    ],
    "sg:phone":"+1 801 571 5658",
    "sg:postcode":"84094",
    "sg:province":"UT",
    "sg:tags":[
        "basket"
    ],
    "wof:name":"Kay's Country Baskets",
    "wof:placetype":"venue"
},
  "geometry": {"coordinates":[-111.863477,40.549511],"type":"Point"}
}