{
  "type": "Feature",
  "properties": {
    "iso:country":"US",
    "sg:address":"165 N 545 W",
    "sg:city":"Bountiful",
    "sg:classifiers":[
        {
            "category":"Shopping",
            "subcategory":"Stationery & Office Supplies",
            "type":"Retail Goods"
        }
    ],
    "sg:phone":"+1 801 292 7625",
    "sg:postcode":"84010",
    "sg:province":"UT",
    "sg:tags":[
        "equipment"
    ],
    "wof:name":"Office Depot",
    "wof:placetype":"venue"
},
  "geometry": {"coordinates":[-111.852723,40.89675],"type":"Point"}
}