{
  "type": "Feature",
  "properties": {
    "iso:country":"US",
    "sg:address":"5520 Aristada Ave",
    "sg:city":"West Jordan",
    "sg:classifiers":[
        {
            "category":"Social Services",
            "subcategory":"Child Care",
            "type":"Services"
        }
    ],
    "sg:phone":"+1 801 967 2068",
    "sg:postcode":"84084",
    "sg:province":"UT",
    "sg:tags":[
        "day"
    ],
    "wof:name":"Precious Cargo Kids Center",
    "wof:placetype":"venue"
},
  "geometry": {"coordinates":[-112.022406,40.628115],"type":"Point"}
}