{
  "type": "Feature",
  "properties": {
    "iso:country":"US",
    "sg:address":"5053 W 7770 S",
    "sg:city":"West Jordan",
    "sg:classifiers":[
        {
            "category":"Building & Trades",
            "subcategory":"Construction",
            "type":"Services"
        }
    ],
    "sg:phone":"+1 801 282 9910",
    "sg:postcode":"84084",
    "sg:province":"UT",
    "sg:tags":[
        "concrete",
        "restoration",
        "repair",
        "cleaning",
        "contractor"
    ],
    "wof:name":"Butcher Concrete Raising Co",
    "wof:placetype":"venue"
},
  "geometry": {"coordinates":[-112.011729,40.609891],"type":"Point"}
}