{
  "type": "Feature",
  "properties": {
    "iso:country":"US",
    "sg:address":"1327 E 2300 N",
    "sg:city":"Logan",
    "sg:classifiers":[
        {
            "category":"Real Estate",
            "subcategory":"Real Estate Agent",
            "type":"Services"
        }
    ],
    "sg:phone":"+1 435 753 9300",
    "sg:postcode":"84341",
    "sg:province":"UT",
    "sg:tags":[
        "appraiser"
    ],
    "wof:name":"Appraisal Institute",
    "wof:placetype":"venue"
},
  "geometry": {"coordinates":[-111.798754,41.773061],"type":"Point"}
}