{
  "type": "Feature",
  "properties": {
    "iso:country":"US",
    "sg:address":"5476 Peggy Ln",
    "sg:city":"Salt Lake City",
    "sg:classifiers":[
        {
            "category":"Professional",
            "subcategory":"Advertising",
            "type":"Services"
        }
    ],
    "sg:phone":"+1 801 569 2222",
    "sg:postcode":"84120",
    "sg:province":"UT",
    "sg:tags":[
        "outdoor"
    ],
    "wof:name":"Global Imaging Solutions Inc",
    "wof:placetype":"venue"
},
  "geometry": {"coordinates":[-112.022713,40.680421],"type":"Point"}
}