{
  "type": "Feature",
  "properties": {
    "iso:country":"US",
    "sg:address":"701 W Main St",
    "sg:city":"Bluff",
    "sg:classifiers":[
        {
            "category":"Travel",
            "subcategory":"Hotels & Motels",
            "type":"Entertainment"
        }
    ],
    "sg:phone":"+1 435 672 2303",
    "sg:postcode":"84516",
    "sg:province":"UT",
    "sg:website":"www.desertroseinn.com",
    "wof:name":"Desert Rose Inn",
    "wof:placetype":"venue"
},
  "geometry": {"coordinates":[-111.10368800000001,39.128218],"type":"Point"}
}