{
  "type": "Feature",
  "properties": {
    "iso:country":"US",
    "sg:address":"355 Crestline Cir",
    "sg:city":"Salt Lake City",
    "sg:classifiers":[
        {
            "category":"Shopping",
            "subcategory":"Clothing, Apparel, & Fashions",
            "type":"Retail Goods"
        }
    ],
    "sg:phone":"+1 801 359 6980",
    "sg:postcode":"84103",
    "sg:province":"UT",
    "sg:tags":[
        "family"
    ],
    "wof:name":"Phil M Howard Jr",
    "wof:placetype":"venue"
},
  "geometry": {"coordinates":[-111.852954,40.777346],"type":"Point"}
}