{
  "type": "Feature",
  "properties": {
    "iso:country":"US",
    "sg:address":"701 E 2100 S",
    "sg:city":"Salt Lake City",
    "sg:classifiers":[
        {
            "category":"Shopping",
            "subcategory":"Jewelry",
            "type":"Retail Goods"
        }
    ],
    "sg:phone":"+1 801 521 9114",
    "sg:postcode":"84106",
    "sg:province":"UT",
    "sg:tags":[
        "jeweler"
    ],
    "wof:name":"Kings Custom Jewelers",
    "wof:placetype":"venue"
},
  "geometry": {"coordinates":[-111.86819199999999,40.725419],"type":"Point"}
}