{
  "type": "Feature",
  "properties": {
    "iso:country":"US",
    "sg:address":"2178 S 900 E",
    "sg:city":"Salt Lake City",
    "sg:classifiers":[
        {
            "category":"Health Services",
            "subcategory":"Podiatrist",
            "type":"Services"
        }
    ],
    "sg:phone":"+1 801 466 1333",
    "sg:postcode":"84106",
    "sg:province":"UT",
    "wof:name":"Southeast Foot Clinic",
    "wof:placetype":"venue"
},
  "geometry": {"coordinates":[-111.865413,40.723691],"type":"Point"}
}