{
  "type": "Feature",
  "properties": {
    "iso:country":"US",
    "sg:address":"3305 S State St",
    "sg:city":"Salt Lake City",
    "sg:classifiers":[
        {
            "category":"Restaurant",
            "type":"Food & Drink"
        }
    ],
    "sg:phone":"+1 801 467 4939",
    "sg:postcode":"84115",
    "sg:province":"UT",
    "sg:tags":[
        "eating"
    ],
    "wof:name":"Subway",
    "wof:placetype":"venue"
},
  "geometry": {"coordinates":[-111.88817899999999,40.699326],"type":"Point"}
}