{
  "type": "Feature",
  "properties": {
    "iso:country":"US",
    "sg:address":"67 N 700 E",
    "sg:city":"St George",
    "sg:classifiers":[
        {
            "category":"Food & Beverages",
            "subcategory":"Bakery",
            "type":"Retail Goods"
        }
    ],
    "sg:phone":"+1 435 986 8263",
    "sg:postcode":"84770",
    "sg:province":"UT",
    "wof:name":"Daylight Donuts",
    "wof:placetype":"venue"
},
  "geometry": {"coordinates":[-113.56855299999999,37.108715],"type":"Point"}
}