{
  "type": "Feature",
  "properties": {
    "iso:country":"US",
    "sg:address":"3520 S 1200 E",
    "sg:city":"Salt Lake City",
    "sg:classifiers":[
        {
            "category":"Building & Trades",
            "subcategory":"Construction",
            "type":"Services"
        }
    ],
    "sg:phone":"+1 801 483 9268",
    "sg:postcode":"84106",
    "sg:province":"UT",
    "sg:tags":[
        "house"
    ],
    "wof:name":"Heaton RC Const Inc",
    "wof:placetype":"venue"
},
  "geometry": {"coordinates":[-111.856942,40.695696],"type":"Point"}
}