{
  "type": "Feature",
  "properties": {
    "iso:country":"US",
    "sg:address":"75 E Center St",
    "sg:city":"Richfield",
    "sg:classifiers":[
        {
            "category":"Government",
            "subcategory":"Office",
            "type":"Public Place"
        }
    ],
    "sg:phone":"+1 435 896 6439",
    "sg:postcode":"84701",
    "sg:province":"UT",
    "sg:tags":[
        "village"
    ],
    "wof:name":"Richfield City Ctr",
    "wof:placetype":"venue"
},
  "geometry": {"coordinates":[-112.083423,38.768143],"type":"Point"}
}