{
  "type": "Feature",
  "properties": {
    "iso:country":"US",
    "sg:address":"497 E 400 N",
    "sg:city":"Bountiful",
    "sg:classifiers":[
        {
            "category":"Manufacturing",
            "subcategory":"Printing",
            "type":"Manufacturing & Wholesale Goods"
        }
    ],
    "sg:phone":"+1 801 295 6003",
    "sg:postcode":"84010",
    "sg:province":"UT",
    "sg:tags":[
        "publishing"
    ],
    "wof:name":"Canon Press Inc",
    "wof:placetype":"venue"
},
  "geometry": {"coordinates":[-111.869275,40.894084],"type":"Point"}
}