{
  "type": "Feature",
  "properties": {
    "iso:country":"US",
    "sg:address":"1767 Beus Dr",
    "sg:city":"Ogden",
    "sg:classifiers":[
        {
            "category":"Communications",
            "type":"Services"
        }
    ],
    "sg:phone":"+1 801 393 2596",
    "sg:postcode":"84403",
    "sg:province":"UT",
    "sg:tags":[
        "communication"
    ],
    "wof:name":"Cyborg Communications",
    "wof:placetype":"venue"
},
  "geometry": {"coordinates":[-111.93145,41.18866],"type":"Point"}
}