{
  "type": "Feature",
  "properties": {
    "iso:country":"US",
    "sg:address":"3967 S 400 E",
    "sg:city":"Salt Lake City",
    "sg:classifiers":[
        {
            "category":"Manufacturing",
            "subcategory":"Printing",
            "type":"Manufacturing & Wholesale Goods"
        }
    ],
    "sg:phone":"+1 801 281 2911",
    "sg:postcode":"84107",
    "sg:province":"UT",
    "sg:tags":[
        "publishing"
    ],
    "wof:name":"McAlvan Press",
    "wof:placetype":"venue"
},
  "geometry": {"coordinates":[-111.879819,40.686248],"type":"Point"}
}