{
  "type": "Feature",
  "properties": {
    "iso:country":"US",
    "sg:address":"280 N Main St",
    "sg:city":"Bountiful",
    "sg:classifiers":[
        {
            "category":"Health Services",
            "subcategory":"Doctor",
            "type":"Services"
        }
    ],
    "sg:phone":"+1 801 292 8665",
    "sg:postcode":"84010",
    "sg:province":"UT",
    "sg:tags":[
        "medical"
    ],
    "wof:name":"Primary Chld Rhbilitaion Ctr N",
    "wof:placetype":"venue"
},
  "geometry": {"coordinates":[-111.880647,40.89225],"type":"Point"}
}