{
  "type": "Feature",
  "properties": {
    "iso:country":"US",
    "sg:address":"3645 W 1987 S",
    "sg:city":"Salt Lake City",
    "sg:classifiers":[
        {
            "category":"Wholesale",
            "subcategory":"Chemicals & Plastics",
            "type":"Manufacturing & Wholesale Goods"
        }
    ],
    "sg:phone":"+1 801 977 0508",
    "sg:postcode":"84104",
    "sg:province":"UT",
    "sg:tags":[
        "representative",
        "manufacturer"
    ],
    "wof:name":"Bowers Industrial Sales Inc",
    "wof:placetype":"venue"
},
  "geometry": {"coordinates":[-111.979392,40.727658],"type":"Point"}
}