{
  "type": "Feature",
  "properties": {
    "iso:country":"US",
    "sg:address":"3057 W Elk Run Dr",
    "sg:city":"Park City",
    "sg:classifiers":[
        {
            "category":"Professional",
            "subcategory":"Management & Consulting",
            "type":"Services"
        }
    ],
    "sg:phone":"+1 435 649 1979",
    "sg:postcode":"84098",
    "sg:province":"UT",
    "wof:name":"D E C Enterprises",
    "wof:placetype":"venue"
},
  "geometry": {"coordinates":[-111.571682,40.744723],"type":"Point"}
}