{
  "type": "Feature",
  "properties": {
    "iso:country":"US",
    "sg:address":"3155 W 13800 S",
    "sg:city":"Riverton",
    "sg:classifiers":[
        {
            "category":"Professional",
            "type":"Services"
        }
    ],
    "sg:phone":"+1 801 446 5610",
    "sg:postcode":"84065",
    "sg:province":"UT",
    "sg:tags":[
        "establishment"
    ],
    "wof:name":"Grandma's Touch",
    "wof:placetype":"venue"
},
  "geometry": {"coordinates":[-111.965709,40.500448],"type":"Point"}
}