{
  "type": "Feature",
  "properties": {
    "iso:country":"US",
    "sg:address":"65 N 1330 W",
    "sg:city":"Orem",
    "sg:classifiers":[
        {
            "category":"Wholesale",
            "subcategory":"Groceries",
            "type":"Manufacturing & Wholesale Goods"
        }
    ],
    "sg:phone":"+1 801 235 0840",
    "sg:postcode":"84057",
    "sg:province":"UT",
    "wof:name":"Dees Cereals",
    "wof:placetype":"venue"
},
  "geometry": {"coordinates":[-111.727389,40.298573],"type":"Point"}
}