{
  "type": "Feature",
  "properties": {
    "iso:country":"US",
    "sg:address":"1371 W 360 N",
    "sg:city":"St George",
    "sg:classifiers":[
        {
            "category":"Building & Trades",
            "subcategory":"Construction",
            "type":"Services"
        }
    ],
    "sg:phone":"+1 435 673 8524",
    "sg:postcode":"84770",
    "sg:province":"UT",
    "sg:tags":[
        "contractor"
    ],
    "wof:name":"American Tile & Marble",
    "wof:placetype":"venue"
},
  "geometry": {"coordinates":[-113.612317,37.11459],"type":"Point"}
}