{
  "type": "Feature",
  "properties": {
    "iso:country":"US",
    "sg:address":"145 E 1300 S",
    "sg:city":"Salt Lake City",
    "sg:classifiers":[
        {
            "category":"Restaurant",
            "type":"Food & Drink"
        }
    ],
    "sg:menulink":"http://www.allmenus.com/ut/salt-lake-city/214596-5-buck-pizza/menu/",
    "sg:phone":"+1 801 532 8900",
    "sg:postcode":"84115",
    "sg:province":"UT",
    "sg:tags":[
        "american",
        "pizza"
    ],
    "wof:name":"5 Buck Pizza",
    "wof:placetype":"venue"
},
  "geometry": {"coordinates":[-111.88673799999999,40.742087],"type":"Point"}
}