{
  "type": "Feature",
  "properties": {
    "iso:country":"US",
    "sg:address":"1256 S 860 W",
    "sg:city":"Cedar City",
    "sg:classifiers":[
        {
            "category":"Home & Garden",
            "subcategory":"Home Furnishings",
            "type":"Retail Goods"
        }
    ],
    "sg:phone":"+1 435 586 3265",
    "sg:postcode":"84720",
    "sg:province":"UT",
    "wof:name":"Emilys Draperies",
    "wof:placetype":"venue"
},
  "geometry": {"coordinates":[-113.07395099999999,37.655114],"type":"Point"}
}