{
  "type": "Feature",
  "properties": {
    "iso:country":"US",
    "sg:address":"2845 W 4700 S",
    "sg:city":"Salt Lake City",
    "sg:classifiers":[
        {
            "category":"Shopping",
            "subcategory":"Pharmacy",
            "type":"Retail Goods"
        }
    ],
    "sg:phone":"+1 801 840 4350",
    "sg:postcode":"84118",
    "sg:province":"UT",
    "wof:name":"IHC Pharmacy Svc",
    "wof:placetype":"venue"
},
  "geometry": {"coordinates":[-111.960618,40.667543],"type":"Point"}
}