{
  "type": "Feature",
  "properties": {
    "iso:country":"US",
    "sg:address":"3734 W 6100 S",
    "sg:city":"Wellsville",
    "sg:classifiers":[
        {
            "category":"Personal",
            "subcategory":"Beauty Salon",
            "type":"Services"
        }
    ],
    "sg:phone":"+1 435 757 5255",
    "sg:postcode":"84339",
    "sg:province":"UT",
    "wof:name":"Artistic Impressions",
    "wof:placetype":"venue"
},
  "geometry": {"coordinates":[-111.923776,41.622239],"type":"Point"}
}