{
  "type": "Feature",
  "properties": {
    "iso:country":"US",
    "sg:address":"125 W Main St",
    "sg:city":"Circleville",
    "sg:classifiers":[
        {
            "category":"Banks & Credit Unions",
            "subcategory":"Bank",
            "type":"Services"
        }
    ],
    "sg:phone":"+1 435 577 2827",
    "sg:postcode":"84723",
    "sg:province":"UT",
    "wof:name":"State Bank Of Southern Utah",
    "wof:placetype":"venue"
},
  "geometry": {"coordinates":[-112.275936,38.171635],"type":"Point"}
}