{
  "type": "Feature",
  "properties": {
    "iso:country":"US",
    "sg:address":"8770 S 1480 W",
    "sg:city":"West Jordan",
    "sg:classifiers":[
        {
            "category":"Building & Trades",
            "subcategory":"Construction",
            "type":"Services"
        }
    ],
    "sg:phone":"+1 801 255 0562",
    "sg:postcode":"84088",
    "sg:province":"UT",
    "sg:tags":[
        "house"
    ],
    "wof:name":"Oakwood Homes",
    "wof:placetype":"venue"
},
  "geometry": {"coordinates":[-111.93355099999999,40.592034],"type":"Point"}
}