{
  "type": "Feature",
  "properties": {
    "iso:country":"US",
    "sg:address":"4045 S 6780 W",
    "sg:city":"Salt Lake City",
    "sg:classifiers":[
        {
            "category":"Building & Trades",
            "subcategory":"Plumbing",
            "type":"Services"
        }
    ],
    "sg:phone":"+1 801 250 1693",
    "sg:postcode":"84128",
    "sg:province":"UT",
    "sg:tags":[
        "conditioning",
        "air",
        "system",
        "contractor"
    ],
    "wof:name":"Big Bear Heating & Cooling",
    "wof:placetype":"venue"
},
  "geometry": {"coordinates":[-112.052986,40.684964],"type":"Point"}
}