{
  "type": "Feature",
  "properties": {
    "iso:country":"US",
    "sg:address":"3335 N 700 E",
    "sg:city":"Ogden",
    "sg:classifiers":[
        {
            "category":"Wholesale",
            "subcategory":"Hardware",
            "type":"Manufacturing & Wholesale Goods"
        }
    ],
    "sg:phone":"+1 801 786 2162",
    "sg:postcode":"84414",
    "sg:province":"UT",
    "sg:tags":[
        "refrigeration"
    ],
    "wof:name":"Hillphoenix",
    "wof:placetype":"venue"
},
  "geometry": {"coordinates":[-111.958068,41.321559],"type":"Point"}
}