{
  "type": "Feature",
  "properties": {
    "iso:country":"US",
    "sg:address":"427 Main St",
    "sg:city":"Park City",
    "sg:classifiers":[
        {
            "category":"Restaurant",
            "type":"Food & Drink"
        }
    ],
    "sg:menulink":"http://www.allmenus.com/ut/park-city/61291-the-room/menu/",
    "sg:phone":"+1 435 655 0820",
    "sg:postcode":"84060",
    "sg:province":"UT",
    "sg:tags":[
        "new",
        "american"
    ],
    "wof:name":"The Room",
    "wof:placetype":"venue"
},
  "geometry": {"coordinates":[-111.495739,40.643449],"type":"Point"}
}