{
  "type": "Feature",
  "properties": {
    "iso:country":"US",
    "sg:address":"1083 W 1700 S",
    "sg:city":"Salt Lake City",
    "sg:classifiers":[
        {
            "category":"Retail",
            "subcategory":"Auto Repair",
            "type":"Services"
        }
    ],
    "sg:phone":"+1 801 973 6780",
    "sg:postcode":"84104",
    "sg:province":"UT",
    "sg:tags":[
        "truck"
    ],
    "wof:name":"Pete's Diesel Repair",
    "wof:placetype":"venue"
},
  "geometry": {"coordinates":[-111.923141,40.733423],"type":"Point"}
}