{
  "type": "Feature",
  "properties": {
    "iso:country":"US",
    "sg:address":"135 N 200 E",
    "sg:city":"Logan",
    "sg:classifiers":[
        {
            "category":"Building & Trades",
            "subcategory":"Construction",
            "type":"Services"
        }
    ],
    "sg:phone":"+1 435 787 4500",
    "sg:postcode":"84321",
    "sg:province":"UT",
    "sg:tags":[
        "general",
        "contractor"
    ],
    "wof:name":"Aardvark Construction",
    "wof:placetype":"venue"
},
  "geometry": {"coordinates":[-111.81819,41.684364],"type":"Point"}
}