{
  "type": "Feature",
  "properties": {
    "iso:country":"US",
    "sg:address":"490 E 1700 S",
    "sg:city":"Clearfield",
    "sg:classifiers":[
        {
            "category":"Autos & Motor Vehicles",
            "subcategory":"Fuel & Gas Station",
            "type":"Retail Goods"
        }
    ],
    "sg:phone":"+1 801 614 0444",
    "sg:postcode":"84015",
    "sg:province":"UT",
    "sg:tags":[
        "oil"
    ],
    "wof:name":"Shell Rapid Lube",
    "wof:placetype":"venue"
},
  "geometry": {"coordinates":[-112.015491,41.08907],"type":"Point"}
}