{
  "type": "Feature",
  "properties": {
    "iso:country":"US",
    "sg:address":"3340 1500 W",
    "sg:city":"Ogden",
    "sg:classifiers":[
        {
            "category":"Manufacturing",
            "subcategory":"Tools & Machinery",
            "type":"Manufacturing & Wholesale Goods"
        }
    ],
    "sg:phone":"+1 801 334 6800",
    "sg:postcode":"84401",
    "sg:province":"UT",
    "sg:tags":[
        "machine",
        "shop"
    ],
    "wof:name":"CNA Precision Machining Inc",
    "wof:placetype":"venue"
},
  "geometry": {"coordinates":[-112.016504,41.204571],"type":"Point"}
}