{
  "type": "Feature",
  "properties": {
    "iso:country":"US",
    "sg:address":"2210 US Hwy 40",
    "sg:city":"Heber City",
    "sg:classifiers":[
        {
            "category":"Government",
            "subcategory":"Office",
            "type":"Public Place"
        }
    ],
    "sg:phone":"+1 435 654 4369",
    "sg:postcode":"84032",
    "sg:province":"UT",
    "sg:tags":[
        "conservation"
    ],
    "wof:name":"Soil Conservation Dist",
    "wof:placetype":"venue"
},
  "geometry": {"coordinates":[-111.409195,40.533223],"type":"Point"}
}