{
  "type": "Feature",
  "properties": {
    "iso:country":"US",
    "sg:address":"185 S State St",
    "sg:city":"Salt Lake City",
    "sg:classifiers":[
        {
            "category":"Real Estate",
            "subcategory":"Real Estate Agent",
            "type":"Services"
        }
    ],
    "sg:phone":"+1 801 363 5453",
    "sg:postcode":"84111",
    "sg:province":"UT",
    "sg:tags":[
        "investment"
    ],
    "wof:name":"Jones Lang Lasalle Mgmt Svc",
    "wof:placetype":"venue"
},
  "geometry": {"coordinates":[-111.88815200000001,40.76528],"type":"Point"}
}