{
  "type": "Feature",
  "properties": {
    "iso:country":"US",
    "sg:address":"2731 E 3750 N",
    "sg:city":"Layton",
    "sg:classifiers":[
        {
            "category":"Professional",
            "subcategory":"Management & Consulting",
            "type":"Services"
        }
    ],
    "sg:phone":"+1 801 771 6069",
    "sg:postcode":"84040",
    "sg:province":"UT",
    "wof:name":"Mayne Stream Marketing Inc",
    "wof:placetype":"venue"
},
  "geometry": {"coordinates":[-111.913667,41.113931],"type":"Point"}
}