{
  "type": "Feature",
  "properties": {
    "iso:country":"US",
    "sg:address":"200 N Redwood Rd",
    "sg:city":"North Salt Lake",
    "sg:classifiers":[
        {
            "category":"Retail",
            "subcategory":"Auto Repair",
            "type":"Services"
        }
    ],
    "sg:phone":"+1 801 936 1780",
    "sg:postcode":"84054",
    "sg:province":"UT",
    "sg:tags":[
        "body",
        "automobile",
        "painting"
    ],
    "wof:name":"Collision Zone",
    "wof:placetype":"venue"
},
  "geometry": {"coordinates":[-111.930396,40.84426],"type":"Point"}
}