{
  "type": "Feature",
  "properties": {
    "iso:country":"US",
    "sg:address":"492 Plateau Rd",
    "sg:city":"Tooele",
    "sg:classifiers":[
        {
            "category":"Building & Trades",
            "subcategory":"Electrical",
            "type":"Services"
        }
    ],
    "sg:phone":"+1 435 884 0967",
    "sg:postcode":"84074",
    "sg:province":"UT",
    "sg:tags":[
        "electric",
        "contractor"
    ],
    "wof:name":"Middle Canyon Electric LLC",
    "wof:placetype":"venue"
},
  "geometry": {"coordinates":[-112.275616,40.539844],"type":"Point"}
}