{
  "type": "Feature",
  "properties": {
    "iso:country":"US",
    "sg:address":"654 N 800 E",
    "sg:city":"Spanish Fork",
    "sg:classifiers":[
        {
            "category":"Professional",
            "subcategory":"Business Services",
            "type":"Services"
        }
    ],
    "sg:phone":"+1 801 798 2777",
    "sg:postcode":"84660",
    "sg:province":"UT",
    "wof:name":"Sonidone Enterprises",
    "wof:placetype":"venue"
},
  "geometry": {"coordinates":[-111.64051600000001,40.118109],"type":"Point"}
}