{
  "type": "Feature",
  "properties": {
    "iso:country":"US",
    "sg:address":"3155 W 5400 S",
    "sg:city":"Kearns",
    "sg:classifiers":[
        {
            "category":"Education",
            "subcategory":"Dance Studio",
            "type":"Public Place"
        }
    ],
    "sg:phone":"+1 801 957 0495",
    "sg:postcode":"84118",
    "sg:province":"UT",
    "sg:tags":[
        "instruction",
        "dancing"
    ],
    "wof:name":"Mountain View Stars",
    "wof:placetype":"venue"
},
  "geometry": {"coordinates":[-111.966927,40.653017],"type":"Point"}
}