{
  "type": "Feature",
  "properties": {
    "iso:country":"US",
    "sg:address":"315 N 1st St",
    "sg:city":"Tooele",
    "sg:classifiers":[
        {
            "category":"Building & Trades",
            "subcategory":"Electrical",
            "type":"Services"
        }
    ],
    "sg:phone":"+1 435 843 0185",
    "sg:postcode":"84074",
    "sg:province":"UT",
    "sg:tags":[
        "electric",
        "contractor"
    ],
    "wof:name":"All-Tech Electric & Telecomms",
    "wof:placetype":"venue"
},
  "geometry": {"coordinates":[-112.29181699999999,40.538287],"type":"Point"}
}