{
  "type": "Feature",
  "properties": {
    "iso:country":"US",
    "sg:address":"3870 S 5900 W",
    "sg:city":"Hooper",
    "sg:classifiers":[
        {
            "category":"Freight",
            "type":"Transportation"
        }
    ],
    "sg:phone":"+1 801 731 5226",
    "sg:postcode":"84315",
    "sg:province":"UT",
    "sg:tags":[
        "operator",
        "local",
        "trucking"
    ],
    "wof:name":"Stringham Rural Delivery",
    "wof:placetype":"venue"
},
  "geometry": {"coordinates":[-112.122433,41.191067],"type":"Point"}
}