{
  "type": "Feature",
  "properties": {
    "iso:country":"US",
    "sg:address":"543 E 400 S",
    "sg:city":"Provo",
    "sg:classifiers":[
        {
            "category":"Building & Trades",
            "subcategory":"Landscaping Services",
            "type":"Services"
        }
    ],
    "sg:phone":"+1 801 373 6542",
    "sg:postcode":"84606",
    "sg:province":"UT",
    "wof:name":"Workmans Lawn Salon Inc",
    "wof:placetype":"venue"
},
  "geometry": {"coordinates":[-111.648904,40.228408],"type":"Point"}
}