{
  "type": "Feature",
  "properties": {
    "iso:country":"US",
    "sg:address":"634 E 700 N",
    "sg:city":"Centerville",
    "sg:classifiers":[
        {
            "category":"Banks & Credit Unions",
            "subcategory":"Financial Services",
            "type":"Services"
        }
    ],
    "sg:phone":"+1 801 292 7190",
    "sg:postcode":"84014",
    "sg:province":"UT",
    "sg:tags":[
        "investor"
    ],
    "wof:name":"Heiner Investments LLC",
    "wof:placetype":"venue"
},
  "geometry": {"coordinates":[-111.869114,40.924893],"type":"Point"}
}