{
  "type": "Feature",
  "properties": {
    "iso:country":"US",
    "sg:address":"875 W Red Cliffs Dr",
    "sg:city":"Washington",
    "sg:classifiers":[
        {
            "category":"Building & Trades",
            "subcategory":"Equipment Rental",
            "type":"Services"
        }
    ],
    "sg:phone":"+1 435 627 8551",
    "sg:postcode":"84780",
    "sg:province":"UT",
    "sg:tags":[
        "yard"
    ],
    "wof:name":"Rent-A-Center",
    "wof:placetype":"venue"
},
  "geometry": {"coordinates":[-113.524607,37.12676],"type":"Point"}
}