{
  "type": "Feature",
  "properties": {
    "iso:country":"US",
    "sg:address":"5663 S Redwood Rd",
    "sg:city":"Salt Lake City",
    "sg:classifiers":[
        {
            "category":"Professional",
            "subcategory":"Business Services",
            "type":"Services"
        }
    ],
    "sg:phone":"+1 801 269 1141",
    "sg:postcode":"84123",
    "sg:province":"UT",
    "sg:tags":[
        "firm",
        "financial"
    ],
    "wof:name":"Family Financial Solutions LLC",
    "wof:placetype":"venue"
},
  "geometry": {"coordinates":[-111.938727,40.648599],"type":"Point"}
}