{
  "type": "Feature",
  "properties": {
    "iso:country":"US",
    "sg:address":"460 N Main St",
    "sg:city":"Logan",
    "sg:classifiers":[
        {
            "category":"Insurance",
            "subcategory":"Insurance Agent",
            "type":"Services"
        }
    ],
    "sg:phone":"+1 435 750 0212",
    "sg:postcode":"84321",
    "sg:province":"UT",
    "wof:name":"Zions Investment Securiti",
    "wof:placetype":"venue"
},
  "geometry": {"coordinates":[-111.834648,41.739852],"type":"Point"}
}