{
  "type": "Feature",
  "properties": {
    "iso:country":"US",
    "sg:address":"1690 Cannes Way",
    "sg:city":"Salt Lake City",
    "sg:classifiers":[
        {
            "category":"Building & Trades",
            "subcategory":"Construction",
            "type":"Services"
        }
    ],
    "sg:phone":"+1 801 277 6812",
    "sg:postcode":"84121",
    "sg:province":"UT",
    "sg:tags":[
        "contractor"
    ],
    "wof:name":"King I Digs",
    "wof:placetype":"venue"
},
  "geometry": {"coordinates":[-111.843014,40.642332],"type":"Point"}
}