{
  "type": "Feature",
  "properties": {
    "iso:country":"US",
    "sg:address":"758 N 1890 W",
    "sg:city":"Provo",
    "sg:classifiers":[
        {
            "category":"Wholesale",
            "subcategory":"Machinery & Supplies",
            "type":"Manufacturing & Wholesale Goods"
        }
    ],
    "sg:phone":"+1 801 373 0475",
    "sg:postcode":"84601",
    "sg:province":"UT",
    "sg:tags":[
        "equipment",
        "safety",
        "clothing"
    ],
    "wof:name":"Saratoga Trading Co",
    "wof:placetype":"venue"
},
  "geometry": {"coordinates":[-111.68938,40.244026],"type":"Point"}
}