{
  "type": "Feature",
  "properties": {
    "iso:country":"US",
    "sg:address":"9614 S 500 W",
    "sg:city":"Sandy",
    "sg:classifiers":[
        {
            "category":"Manufacturing",
            "subcategory":"Wood Products",
            "type":"Manufacturing & Wholesale Goods"
        },
        {
            "category":"Home & Garden",
            "subcategory":"Furniture",
            "type":"Retail Goods"
        }
    ],
    "sg:phone":"+1 801 233 0034",
    "sg:postcode":"84070",
    "sg:province":"UT",
    "sg:tags":[
        "mfg",
        "cabinet"
    ],
    "wof:name":"Cottage Wood Design Inc",
    "wof:placetype":"venue"
},
  "geometry": {"coordinates":[-111.905563,40.577438],"type":"Point"}
}