{
  "type": "Feature",
  "properties": {
    "iso:country":"US",
    "sg:address":"556 N 500 E",
    "sg:city":"Centerville",
    "sg:classifiers":[
        {
            "category":"Organizations",
            "subcategory":"Religious Organization",
            "type":"Services"
        }
    ],
    "sg:phone":"+1 801 299 4114",
    "sg:postcode":"84014",
    "sg:province":"UT",
    "sg:tags":[
        "church"
    ],
    "wof:name":"Centerville Third LDS Ward",
    "wof:placetype":"venue"
},
  "geometry": {"coordinates":[-111.87087099999999,40.924236],"type":"Point"}
}