{
  "type": "Feature",
  "properties": {
    "iso:country":"US",
    "sg:address":"2040 W 2000 N",
    "sg:city":"St George",
    "sg:classifiers":[
        {
            "category":"Education",
            "subcategory":"School",
            "type":"Public Place"
        }
    ],
    "sg:phone":"+1 435 652 4712",
    "sg:postcode":"84770",
    "sg:province":"UT",
    "sg:tags":[
        "elementary"
    ],
    "wof:name":"Coral Cliffs Elementary School",
    "wof:placetype":"venue"
},
  "geometry": {"coordinates":[-113.62716399999999,37.143086],"type":"Point"}
}