{
  "type": "Feature",
  "properties": {
    "iso:country":"US",
    "sg:address":"1194 S Main St",
    "sg:city":"Springville",
    "sg:classifiers":[
        {
            "category":"Shopping",
            "type":"Retail Goods"
        },
        {
            "category":"Manufacturing",
            "subcategory":"Retail Goods",
            "type":"Manufacturing & Wholesale Goods"
        }
    ],
    "sg:phone":"+1 801 489 3845",
    "sg:postcode":"84663",
    "sg:province":"UT",
    "sg:tags":[
        "product",
        "outdoor",
        "mfg",
        "specialty",
        "lighting",
        "merchandise"
    ],
    "wof:name":"Wilderness Woods",
    "wof:placetype":"venue"
},
  "geometry": {"coordinates":[-111.608993,40.147211],"type":"Point"}
}