{
  "type": "Feature",
  "properties": {
    "iso:country":"US",
    "sg:address":"570 S Main St",
    "sg:city":"Spanish Fork",
    "sg:classifiers":[
        {
            "category":"Home & Garden",
            "subcategory":"Garden Supply",
            "type":"Retail Goods"
        }
    ],
    "sg:phone":"+1 801 798 7625",
    "sg:postcode":"84660",
    "sg:province":"UT",
    "sg:tags":[
        "landscaping",
        "equipment"
    ],
    "wof:name":"Rocks & Stuff Inc",
    "wof:placetype":"venue"
},
  "geometry": {"coordinates":[-111.65534100000001,40.101421],"type":"Point"}
}