{
  "type": "Feature",
  "properties": {
    "iso:country":"US",
    "sg:address":"622 Kane Creek Blvd",
    "sg:city":"Moab",
    "sg:classifiers":[
        {
            "category":"Real Estate",
            "subcategory":"Real Estate Operator",
            "type":"Services"
        }
    ],
    "sg:phone":"+1 435 259 8715",
    "sg:postcode":"84532",
    "sg:province":"UT",
    "sg:tags":[
        "building",
        "apartment"
    ],
    "wof:name":"Huntridge Plaza Apts Inc",
    "wof:placetype":"venue"
},
  "geometry": {"coordinates":[-109.552727,38.566039],"type":"Point"}
}