{
  "type": "Feature",
  "properties": {
    "iso:country":"US",
    "sg:address":"1448 S 680 W",
    "sg:city":"Provo",
    "sg:classifiers":[
        {
            "category":"Shopping",
            "subcategory":"Florist",
            "type":"Retail Goods"
        }
    ],
    "sg:phone":"+1 801 373 0864",
    "sg:postcode":"84601",
    "sg:province":"UT",
    "sg:tags":[
        "merchandise"
    ],
    "wof:name":"Heaven & Earth Creations",
    "wof:placetype":"venue"
},
  "geometry": {"coordinates":[-111.670682,40.214363],"type":"Point"}
}