{
  "type": "Feature",
  "properties": {
    "iso:country":"US",
    "sg:address":"672 W 750 N",
    "sg:city":"American Fork",
    "sg:classifiers":[
        {
            "category":"Travel",
            "subcategory":"Hotels & Motels",
            "type":"Entertainment"
        }
    ],
    "sg:phone":"+1 801 756 5269",
    "sg:postcode":"84003",
    "sg:province":"UT",
    "sg:tags":[
        "operation"
    ],
    "wof:name":"Parker House",
    "wof:placetype":"venue"
},
  "geometry": {"coordinates":[-111.815409,40.392209],"type":"Point"}
}