{
  "type": "Feature",
  "properties": {
    "iso:country":"US",
    "sg:address":"10150 Centennial Pkwy",
    "sg:city":"Sandy",
    "sg:classifiers":[
        {
            "category":"Professional",
            "subcategory":"Computer Services",
            "type":"Services"
        }
    ],
    "sg:phone":"+1 801 256 2011",
    "sg:postcode":"84070",
    "sg:province":"UT",
    "sg:tags":[
        "graphics"
    ],
    "wof:name":"SGI",
    "wof:placetype":"venue"
},
  "geometry": {"coordinates":[-111.895804,40.567205],"type":"Point"}
}