{
  "type": "Feature",
  "properties": {
    "iso:country":"US",
    "sg:address":"1225 Crystal Ave",
    "sg:city":"West Valley",
    "sg:classifiers":[
        {
            "category":"Building & Trades",
            "subcategory":"Landscaping Services",
            "type":"Services"
        }
    ],
    "sg:phone":"+1 801 908 6913",
    "sg:postcode":"84119",
    "sg:province":"UT",
    "sg:tags":[
        "tree"
    ],
    "wof:name":"A A Tree Svc",
    "wof:placetype":"venue"
},
  "geometry": {"coordinates":[-111.926682,40.714198],"type":"Point"}
}