{
  "type": "Feature",
  "properties": {
    "iso:country":"US",
    "sg:address":"9799 N 4600 W",
    "sg:city":"Pleasant Grove",
    "sg:classifiers":[
        {
            "category":"Health Services",
            "subcategory":"Medical Lab",
            "type":"Services"
        }
    ],
    "sg:phone":"+1 801 772 0303",
    "sg:postcode":"84062",
    "sg:province":"UT",
    "sg:tags":[
        "laboratory",
        "dental"
    ],
    "wof:name":"Barnes Orthodontic Lab Inc",
    "wof:placetype":"venue"
},
  "geometry": {"coordinates":[-111.768573,40.41036],"type":"Point"}
}