{
  "type": "Feature",
  "properties": {
    "iso:country":"US",
    "sg:address":"7443 S 3200 W",
    "sg:city":"West Jordan",
    "sg:classifiers":[
        {
            "category":"Personal",
            "type":"Services"
        }
    ],
    "sg:phone":"+1 801 566 6312",
    "sg:postcode":"84084",
    "sg:province":"UT",
    "wof:name":"Below The Belt Inc",
    "wof:placetype":"venue"
},
  "geometry": {"coordinates":[-111.96728899999999,40.615197],"type":"Point"}
}