{
  "type": "Feature",
  "properties": {
    "iso:country":"US",
    "sg:address":"123 W 5300 S",
    "sg:city":"Murray",
    "sg:classifiers":[
        {
            "category":"Insurance",
            "subcategory":"Insurance Agent",
            "type":"Services"
        }
    ],
    "sg:phone":"+1 801 262 9000",
    "sg:postcode":"84107",
    "sg:province":"UT",
    "wof:name":"Ross R Brunson Insurance Inc",
    "wof:placetype":"venue"
},
  "geometry": {"coordinates":[-111.894215,40.655716],"type":"Point"}
}