{
  "type": "Feature",
  "properties": {
    "iso:country":"US",
    "sg:address":"3830 S Main St",
    "sg:city":"Salt Lake City",
    "sg:classifiers":[
        {
            "category":"Autos & Motor Vehicles",
            "subcategory":"Automobile Sales",
            "type":"Retail Goods"
        }
    ],
    "sg:phone":"+1 801 263 6300",
    "sg:postcode":"84115",
    "sg:province":"UT",
    "sg:tags":[
        "car",
        "dealer"
    ],
    "wof:name":"Crecent Auto Sales",
    "wof:placetype":"venue"
},
  "geometry": {"coordinates":[-111.891189,40.688492],"type":"Point"}
}