{
  "type": "Feature",
  "properties": {
    "iso:country":"US",
    "sg:address":"198 N 100 E",
    "sg:city":"St George",
    "sg:classifiers":[
        {
            "category":"Manufacturing",
            "subcategory":"Printing",
            "type":"Manufacturing & Wholesale Goods"
        }
    ],
    "sg:phone":"+1 435 628 6286",
    "sg:postcode":"84770",
    "sg:province":"UT",
    "sg:tags":[
        "publisher"
    ],
    "wof:name":"West Vista",
    "wof:placetype":"venue"
},
  "geometry": {"coordinates":[-113.58117,37.10989],"type":"Point"}
}