{
  "type": "Feature",
  "properties": {
    "iso:country":"US",
    "sg:address":"155 N 400 W",
    "sg:city":"Orem",
    "sg:classifiers":[
        {
            "category":"Health Services",
            "subcategory":"Doctor",
            "type":"Services"
        }
    ],
    "sg:phone":"+1 801 224 1300",
    "sg:postcode":"84057",
    "sg:province":"UT",
    "sg:tags":[
        "physician",
        "surgeon"
    ],
    "sg:website":"www.ctfp.com",
    "wof:name":"Cherry Tree Family Practice",
    "wof:placetype":"venue"
},
  "geometry": {"coordinates":[-111.705364,40.299815],"type":"Point"}
}