{
  "type": "Feature",
  "properties": {
    "iso:country":"US",
    "sg:address":"683 W 5300 S",
    "sg:city":"Murray",
    "sg:classifiers":[
        {
            "category":"Personal",
            "subcategory":"Tanning Parlor",
            "type":"Services"
        }
    ],
    "sg:phone":"+1 801 263 2100",
    "sg:postcode":"84123",
    "sg:province":"UT",
    "sg:tags":[
        "salon"
    ],
    "wof:name":"Tan-Fastik",
    "wof:placetype":"venue"
},
  "geometry": {"coordinates":[-111.90803200000001,40.653948],"type":"Point"}
}