{
  "type": "Feature",
  "properties": {
    "iso:country":"US",
    "sg:address":"2709 S 8585 W",
    "sg:city":"Magna",
    "sg:classifiers":[
        {
            "category":"Personal",
            "subcategory":"Shoe Repair & Shine",
            "type":"Services"
        }
    ],
    "sg:phone":"+1 801 250 4502",
    "sg:postcode":"84044",
    "sg:province":"UT",
    "sg:tags":[
        "repairing",
        "boot",
        "shoes"
    ],
    "wof:name":"Tony's Shoes & Repair",
    "wof:placetype":"venue"
},
  "geometry": {"coordinates":[-112.09733900000001,40.711135],"type":"Point"}
}