{
  "type": "Feature",
  "properties": {
    "iso:country":"US",
    "sg:address":"1495 N 1880 W",
    "sg:city":"Provo",
    "sg:classifiers":[
        {
            "category":"Professional",
            "subcategory":"Business Services",
            "type":"Services"
        }
    ],
    "sg:phone":"+1 801 377 5498",
    "sg:postcode":"84604",
    "sg:province":"UT",
    "wof:name":"Memories",
    "wof:placetype":"venue"
},
  "geometry": {"coordinates":[-111.690968,40.254293],"type":"Point"}
}