{
  "type": "Feature",
  "properties": {
    "iso:country":"US",
    "sg:address":"9538 S 670 W",
    "sg:city":"Sandy",
    "sg:classifiers":[
        {
            "category":"Retail",
            "subcategory":"Auto Repair",
            "type":"Services"
        }
    ],
    "sg:phone":"+1 801 255 3152",
    "sg:postcode":"84070",
    "sg:province":"UT",
    "sg:tags":[
        "body"
    ],
    "wof:name":"Sutherland Collision Repair",
    "wof:placetype":"venue"
},
  "geometry": {"coordinates":[-111.909554,40.579283],"type":"Point"}
}