{
  "type": "Feature",
  "properties": {
    "iso:country":"US",
    "sg:address":"1043 W 1420 N",
    "sg:city":"Orem",
    "sg:classifiers":[
        {
            "category":"Retail",
            "subcategory":"Repair Shop",
            "type":"Services"
        }
    ],
    "sg:phone":"+1 801 225 9110",
    "sg:postcode":"84057",
    "sg:province":"UT",
    "wof:name":"Daves Video Repair",
    "wof:placetype":"venue"
},
  "geometry": {"coordinates":[-111.720099,40.32294],"type":"Point"}
}