{
  "type": "Feature",
  "properties": {
    "iso:country":"US",
    "sg:address":"4662 S 200 W",
    "sg:city":"Murray",
    "sg:classifiers":[
        {
            "category":"Building & Trades",
            "subcategory":"Construction",
            "type":"Services"
        }
    ],
    "sg:phone":"+1 801 268 8300",
    "sg:postcode":"84107",
    "sg:province":"UT",
    "sg:tags":[
        "fire",
        "house",
        "restoration",
        "damage"
    ],
    "wof:name":"Leavitt Restoration Svcs LLC",
    "wof:placetype":"venue"
},
  "geometry": {"coordinates":[-111.896917,40.670877],"type":"Point"}
}