{
  "type": "Feature",
  "properties": {
    "iso:country":"US",
    "sg:address":"1054 N 1800 E",
    "sg:city":"Logan",
    "sg:classifiers":[
        {
            "category":"Professional",
            "type":"Services"
        }
    ],
    "sg:phone":"+1 435 753 2949",
    "sg:postcode":"84341",
    "sg:province":"UT",
    "wof:name":"Eric Wallis Arts Inc",
    "wof:placetype":"venue"
},
  "geometry": {"coordinates":[-111.789179,41.750417],"type":"Point"}
}