{
  "type": "Feature",
  "properties": {
    "iso:country":"US",
    "sg:address":"129 W 1700 S",
    "sg:city":"Salt Lake City",
    "sg:classifiers":[
        {
            "category":"Shopping",
            "subcategory":"Clothing, Apparel, & Fashions",
            "type":"Retail Goods"
        }
    ],
    "sg:phone":"+1 801 487 2541",
    "sg:postcode":"84115",
    "sg:province":"UT",
    "sg:tags":[
        "salvage",
        "surplus",
        "merchandise"
    ],
    "wof:name":"Salt Lake Instrument Svc",
    "wof:placetype":"venue"
},
  "geometry": {"coordinates":[-111.89476500000001,40.733433],"type":"Point"}
}