{
  "type": "Feature",
  "properties": {
    "iso:country":"US",
    "sg:address":"687 N Main St",
    "sg:city":"Layton",
    "sg:classifiers":[
        {
            "category":"Retail",
            "subcategory":"Auto Repair",
            "type":"Services"
        }
    ],
    "sg:phone":"+1 801 544 2347",
    "sg:postcode":"84041",
    "sg:province":"UT",
    "sg:tags":[
        "general"
    ],
    "wof:name":"Simmons Auto Repair",
    "wof:placetype":"venue"
},
  "geometry": {"coordinates":[-111.976658,41.070404],"type":"Point"}
}