{
  "type": "Feature",
  "properties": {
    "iso:country":"US",
    "sg:address":"1651 Emerson Ave",
    "sg:city":"Salt Lake City",
    "sg:classifiers":[
        {
            "category":"Professional",
            "subcategory":"Business Services",
            "type":"Services"
        }
    ],
    "sg:phone":"+1 801 467 3493",
    "sg:postcode":"84105",
    "sg:province":"UT",
    "wof:name":"W&M Ltd Partnership",
    "wof:placetype":"venue"
},
  "geometry": {"coordinates":[-111.843496,40.737246],"type":"Point"}
}