{
  "type": "Feature",
  "properties": {
    "iso:country":"US",
    "sg:address":"225 Main St S",
    "sg:city":"Malta",
    "sg:classifiers":[
        {
            "category":"Building & Trades",
            "subcategory":"Construction",
            "type":"Services"
        }
    ],
    "sg:phone":"+1 208 645 2290",
    "sg:postcode":"83342",
    "sg:province":"UT",
    "sg:tags":[
        "excavating",
        "contractor"
    ],
    "wof:name":"J R Thornton Construction",
    "wof:placetype":"venue"
},
  "geometry": {"coordinates":[-113.369236,42.300935],"type":"Point"}
}