{
  "type": "Feature",
  "properties": {
    "iso:country":"US",
    "sg:address":"13815 White Tail Cove",
    "sg:city":"Riverton",
    "sg:classifiers":[
        {
            "category":"Building & Trades",
            "subcategory":"Construction",
            "type":"Services"
        }
    ],
    "sg:phone":"+1 801 253 1577",
    "sg:postcode":"84065",
    "sg:province":"UT",
    "sg:tags":[
        "contractor"
    ],
    "wof:name":"Licea Plastering Inc",
    "wof:placetype":"venue"
},
  "geometry": {"coordinates":[-111.982591,40.498993],"type":"Point"}
}