{
  "type": "Feature",
  "properties": {
    "iso:country":"US",
    "sg:address":"6522 E Big Cottonwood Canyon Rd",
    "sg:city":"Salt Lake City",
    "sg:classifiers":[
        {
            "category":"Restaurant",
            "type":"Food & Drink"
        }
    ],
    "sg:phone":"+1 801 733 0511",
    "sg:postcode":"84121",
    "sg:province":"UT",
    "sg:tags":[
        "eating"
    ],
    "wof:name":"Quiznos Subs",
    "wof:placetype":"venue"
},
  "geometry": {"coordinates":[-111.798327,40.623002],"type":"Point"}
}