{
  "type": "Feature",
  "properties": {
    "iso:country":"US",
    "sg:address":"2 N Medical Dr",
    "sg:city":"Salt Lake City",
    "sg:classifiers":[
        {
            "category":"Social Services",
            "subcategory":"Child Care",
            "type":"Services"
        }
    ],
    "sg:phone":"+1 801 581 1330",
    "sg:postcode":"84113",
    "sg:province":"UT",
    "sg:tags":[
        "day"
    ],
    "wof:name":"Jewish Community Center",
    "wof:placetype":"venue"
},
  "geometry": {"coordinates":[-111.83876100000001,40.7727],"type":"Point"}
}