{
  "type": "Feature",
  "properties": {
    "iso:country":"US",
    "sg:address":"430 N 470 W",
    "sg:city":"Lehi",
    "sg:classifiers":[
        {
            "category":"Building & Trades",
            "subcategory":"Construction",
            "type":"Services"
        }
    ],
    "sg:phone":"+1 801 979 1995",
    "sg:postcode":"84043",
    "sg:province":"UT",
    "sg:tags":[
        "contractor"
    ],
    "wof:name":"Judys Precision Tile Co",
    "wof:placetype":"venue"
},
  "geometry": {"coordinates":[-111.856375,40.392945],"type":"Point"}
}