{
  "type": "Feature",
  "properties": {
    "iso:country":"US",
    "sg:address":"470 Lawndale Dr",
    "sg:city":"Salt Lake City",
    "sg:classifiers":[
        {
            "category":"Shopping",
            "type":"Retail Goods"
        }
    ],
    "sg:phone":"+1 801 264 1001",
    "sg:postcode":"84115",
    "sg:province":"UT",
    "sg:tags":[
        "instrument",
        "medical",
        "mfg",
        "diagnostic"
    ],
    "wof:name":"Jtech Medical Industries Inc",
    "wof:placetype":"venue"
},
  "geometry": {"coordinates":[-111.90212699999999,40.716316],"type":"Point"}
}