{
  "type": "Feature",
  "properties": {
    "iso:country":"US",
    "sg:address":"1685 Creekside Ln",
    "sg:city":"Park City",
    "sg:classifiers":[
        {
            "category":"Professional",
            "subcategory":"Management & Consulting",
            "type":"Services"
        }
    ],
    "sg:phone":"+1 435 645 7909",
    "sg:postcode":"84098",
    "sg:province":"UT",
    "wof:name":"Truvision Communications LLC",
    "wof:placetype":"venue"
},
  "geometry": {"coordinates":[-111.543674,40.706859],"type":"Point"}
}