{
  "type": "Feature",
  "properties": {
    "iso:country":"US",
    "sg:address":"14878 Steep Mountain Dr",
    "sg:city":"Draper",
    "sg:classifiers":[
        {
            "category":"Professional",
            "subcategory":"Employment Agencies",
            "type":"Services"
        }
    ],
    "sg:phone":"+1 801 495 0786",
    "sg:postcode":"84020",
    "sg:province":"UT",
    "sg:tags":[
        "opportunity"
    ],
    "wof:name":"Utah Nanny Exchange",
    "wof:placetype":"venue"
},
  "geometry": {"coordinates":[-111.87940399999999,40.479291],"type":"Point"}
}