{
  "type": "Feature",
  "properties": {
    "iso:country":"US",
    "sg:address":"377 N Main St",
    "sg:city":"Layton",
    "sg:classifiers":[
        {
            "category":"Insurance",
            "subcategory":"Insurance Agent",
            "type":"Services"
        }
    ],
    "sg:phone":"+1 801 544 4238",
    "sg:postcode":"84041",
    "sg:province":"UT",
    "wof:name":"Zions Insurance",
    "wof:placetype":"venue"
},
  "geometry": {"coordinates":[-111.971802,41.066119],"type":"Point"}
}