{
  "type": "Feature",
  "properties": {
    "iso:country":"US",
    "sg:address":"486 Riversands Rd",
    "sg:city":"Moab",
    "sg:classifiers":[
        {
            "category":"Ferry",
            "type":"Transportation"
        }
    ],
    "sg:phone":"+1 435 259 7366",
    "sg:postcode":"84532",
    "sg:province":"UT",
    "sg:tags":[
        "river",
        "expedition"
    ],
    "wof:name":"Western Warehouse",
    "wof:placetype":"venue"
},
  "geometry": {"coordinates":[-109.56625,38.580591],"type":"Point"}
}