{
  "type": "Feature",
  "properties": {
    "iso:country":"US",
    "sg:address":"1606 W Malvern Ave",
    "sg:city":"West Valley",
    "sg:classifiers":[
        {
            "category":"Personal",
            "subcategory":"Beauty Salon",
            "type":"Services"
        }
    ],
    "sg:phone":"+1 801 891 4227",
    "sg:postcode":"84119",
    "sg:province":"UT",
    "wof:name":"Bobbie's Hair & Nail Salon",
    "wof:placetype":"venue"
},
  "geometry": {"coordinates":[-111.938613,40.713491],"type":"Point"}
}