{
  "type": "Feature",
  "properties": {
    "iso:country":"US",
    "sg:address":"1030 W 650 S",
    "sg:city":"Layton",
    "sg:classifiers":[
        {
            "category":"Local Transit",
            "type":"Transportation"
        }
    ],
    "sg:phone":"+1 801 544 0211",
    "sg:postcode":"84041",
    "sg:province":"UT",
    "sg:tags":[
        "passenger"
    ],
    "wof:name":"Utah Executive Limousine",
    "wof:placetype":"venue"
},
  "geometry": {"coordinates":[-111.98424199999999,41.050602],"type":"Point"}
}