{
  "type": "Feature",
  "properties": {
    "iso:country":"US",
    "sg:address":"2337 W 880 N",
    "sg:city":"Provo",
    "sg:classifiers":[
        {
            "category":"Retail",
            "subcategory":"Auto Repair",
            "type":"Services"
        }
    ],
    "sg:phone":"+1 801 373 4083",
    "sg:postcode":"84601",
    "sg:province":"UT",
    "sg:tags":[
        "body"
    ],
    "wof:name":"Paint Doctor Inc",
    "wof:placetype":"venue"
},
  "geometry": {"coordinates":[-111.701971,40.245472],"type":"Point"}
}