{
  "type": "Feature",
  "properties": {
    "iso:country":"US",
    "sg:address":"1074 S 890 E",
    "sg:city":"Orem",
    "sg:classifiers":[
        {
            "category":"Insurance",
            "subcategory":"Insurance Agent",
            "type":"Services"
        }
    ],
    "sg:phone":"+1 801 225 3673",
    "sg:postcode":"84097",
    "sg:province":"UT",
    "sg:tags":[
        "audit"
    ],
    "wof:name":"Universal Service Co",
    "wof:placetype":"venue"
},
  "geometry": {"coordinates":[-111.674029,40.27729],"type":"Point"}
}