{
  "type": "Feature",
  "properties": {
    "iso:country":"US",
    "sg:address":"1740 S 580 W",
    "sg:city":"Woods Cross",
    "sg:classifiers":[
        {
            "category":"Building & Trades",
            "subcategory":"Plumbing",
            "type":"Services"
        }
    ],
    "sg:phone":"+1 801 292 2502",
    "sg:postcode":"84087",
    "sg:province":"UT",
    "sg:tags":[
        "contractor"
    ],
    "wof:name":"AMA Heating Air",
    "wof:placetype":"venue"
},
  "geometry": {"coordinates":[-111.895391,40.872718],"type":"Point"}
}