{
  "type": "Feature",
  "properties": {
    "iso:country":"US",
    "sg:address":"30 N Main St",
    "sg:city":"Heber City",
    "sg:classifiers":[
        {
            "category":"Real Estate",
            "subcategory":"Real Estate Agent",
            "type":"Services"
        }
    ],
    "sg:phone":"+1 435 654 2600",
    "sg:postcode":"84032",
    "sg:province":"UT",
    "sg:tags":[
        "consultant",
        "appraiser"
    ],
    "wof:name":"Giles Alan M RE Appraisal",
    "wof:placetype":"venue"
},
  "geometry": {"coordinates":[-111.413405,40.508575],"type":"Point"}
}