{
  "type": "Feature",
  "properties": {
    "iso:country":"US",
    "sg:address":"270 Maple St",
    "sg:city":"Tooele",
    "sg:classifiers":[
        {
            "category":"Organizations",
            "subcategory":"Non-profit Organization",
            "type":"Services"
        }
    ],
    "sg:phone":"+1 435 882 1278",
    "sg:postcode":"84074",
    "sg:province":"UT",
    "sg:tags":[
        "social"
    ],
    "wof:name":"Tooele Community Action",
    "wof:placetype":"venue"
},
  "geometry": {"coordinates":[-112.291383,40.531227],"type":"Point"}
}