{
  "type": "Feature",
  "properties": {
    "iso:country":"US",
    "sg:address":"2677 W 1390 N",
    "sg:city":"Provo",
    "sg:classifiers":[
        {
            "category":"Professional",
            "subcategory":"Business Services",
            "type":"Services"
        }
    ],
    "sg:phone":"+1 801 374 1040",
    "sg:postcode":"84601",
    "sg:province":"UT",
    "wof:name":"Padgett Business Services",
    "wof:placetype":"venue"
},
  "geometry": {"coordinates":[-111.706312,40.251955],"type":"Point"}
}