{
  "type": "Feature",
  "properties": {
    "iso:country":"US",
    "sg:address":"747 S Main St",
    "sg:city":"Brigham City",
    "sg:classifiers":[
        {
            "category":"Shopping",
            "subcategory":"Department Store",
            "type":"Retail Goods"
        }
    ],
    "sg:phone":"+1 435 723 1400",
    "sg:postcode":"84302",
    "sg:province":"UT",
    "sg:tags":[
        "optical",
        "n"
    ],
    "wof:name":"Shopko Store 104",
    "wof:placetype":"venue"
},
  "geometry": {"coordinates":[-112.015959,41.49499],"type":"Point"}
}