{
  "type": "Feature",
  "properties": {
    "iso:country":"US",
    "sg:address":"95 E Center St",
    "sg:city":"Kamas",
    "sg:classifiers":[
        {
            "category":"Building & Trades",
            "subcategory":"Construction",
            "type":"Services"
        }
    ],
    "sg:phone":"+1 435 649 1515",
    "sg:postcode":"84036",
    "sg:province":"UT",
    "sg:tags":[
        "painter"
    ],
    "wof:name":"Big Mountain Painting",
    "wof:placetype":"venue"
},
  "geometry": {"coordinates":[-111.28065100000001,40.643206],"type":"Point"}
}