{
  "type": "Feature",
  "properties": {
    "iso:country":"US",
    "sg:address":"8564 Daneborg Dr",
    "sg:city":"Salt Lake City",
    "sg:classifiers":[
        {
            "category":"Retail",
            "subcategory":"Animal Services",
            "type":"Services"
        }
    ],
    "sg:phone":"+1 801 554 0077",
    "sg:postcode":"84121",
    "sg:province":"UT",
    "wof:name":"Pets-R-Purr-fect Portraits",
    "wof:placetype":"venue"
},
  "geometry": {"coordinates":[-111.798795,40.595553],"type":"Point"}
}