{
  "type": "Feature",
  "properties": {
    "iso:country":"US",
    "sg:address":"12215 S 900 E",
    "sg:city":"Draper",
    "sg:classifiers":[
        {
            "category":"Shopping",
            "type":"Retail Goods"
        }
    ],
    "sg:phone":"+1 801 501 0818",
    "sg:postcode":"84020",
    "sg:province":"UT",
    "sg:tags":[
        "pet",
        "food",
        "supply"
    ],
    "wof:name":"Dog's Meow",
    "wof:placetype":"venue"
},
  "geometry": {"coordinates":[-111.86619,40.527193],"type":"Point"}
}