{
  "type": "Feature",
  "properties": {
    "iso:country":"US",
    "sg:address":"1827 Cottonwood Club Cir",
    "sg:city":"Salt Lake City",
    "sg:classifiers":[
        {
            "category":"Banks & Credit Unions",
            "subcategory":"Financial Services",
            "type":"Services"
        }
    ],
    "sg:phone":"+1 801 274 2880",
    "sg:postcode":"84117",
    "sg:province":"UT",
    "sg:tags":[
        "investor"
    ],
    "wof:name":"Concord Investment Company",
    "wof:placetype":"venue"
},
  "geometry": {"coordinates":[-111.839051,40.655182],"type":"Point"}
}