{
  "type": "Feature",
  "properties": {
    "iso:country":"US",
    "sg:address":"598 E Center St",
    "sg:city":"Pleasant Grove",
    "sg:classifiers":[
        {
            "category":"Building & Trades",
            "subcategory":"Construction",
            "type":"Services"
        }
    ],
    "sg:phone":"+1 801 785 4836",
    "sg:postcode":"84062",
    "sg:province":"UT",
    "sg:tags":[
        "contractor"
    ],
    "wof:name":"Murdock Fencing",
    "wof:placetype":"venue"
},
  "geometry": {"coordinates":[-111.730614,40.363915],"type":"Point"}
}