{
  "type": "Feature",
  "properties": {
    "iso:country":"US",
    "sg:address":"2734 E State Rd 35",
    "sg:city":"Kamas",
    "sg:classifiers":[
        {
            "category":"Food & Beverages",
            "subcategory":"Groceries & Convenience Stores",
            "type":"Retail Goods"
        }
    ],
    "sg:phone":"+1 435 783 6329",
    "sg:postcode":"84036",
    "sg:province":"UT",
    "wof:name":"Woodland Cash Store",
    "wof:placetype":"venue"
},
  "geometry": {"coordinates":[-111.227452,40.581315],"type":"Point"}
}