{
  "type": "Feature",
  "properties": {
    "iso:country":"US",
    "sg:address":"9710 S 700 E",
    "sg:city":"Sandy",
    "sg:classifiers":[
        {
            "category":"Recreation",
            "type":"Entertainment"
        }
    ],
    "sg:phone":"+1 801 495 4653",
    "sg:postcode":"84070",
    "sg:province":"UT",
    "wof:name":"Byers West Group LLC",
    "wof:placetype":"venue"
},
  "geometry": {"coordinates":[-111.872252,40.574142],"type":"Point"}
}