{
  "type": "Feature",
  "properties": {
    "iso:country":"US",
    "sg:address":"2247 W 8660 S",
    "sg:city":"West Jordan",
    "sg:classifiers":[
        {
            "category":"Social Services",
            "subcategory":"Child Care",
            "type":"Services"
        }
    ],
    "sg:phone":"+1 801 565 1058",
    "sg:postcode":"84088",
    "sg:province":"UT",
    "sg:tags":[
        "day"
    ],
    "sg:website":"www.challengerschool.com",
    "wof:name":"Challenger Schools",
    "wof:placetype":"venue"
},
  "geometry": {"coordinates":[-111.94989200000001,40.593939],"type":"Point"}
}