{
  "type": "Feature",
  "properties": {
    "iso:country":"US",
    "sg:address":"485 Country Club",
    "sg:city":"Tooele",
    "sg:classifiers":[
        {
            "category":"Education",
            "subcategory":"School",
            "type":"Public Place"
        }
    ],
    "sg:phone":"+1 435 833 1968",
    "sg:postcode":"84074",
    "sg:province":"UT",
    "wof:name":"Stansbury Park Elementary",
    "wof:placetype":"venue"
},
  "geometry": {"coordinates":[-112.297466,40.633247],"type":"Point"}
}