{
  "type": "Feature",
  "properties": {
    "iso:country":"US",
    "sg:address":"5000 S 8400 W",
    "sg:city":"Magna",
    "sg:classifiers":[
        {
            "category":"Professional",
            "subcategory":"Computer Services",
            "type":"Services"
        }
    ],
    "sg:phone":"+1 801 251 3710",
    "sg:postcode":"84044",
    "sg:province":"UT",
    "sg:tags":[
        "repair"
    ],
    "wof:name":"Diebold Information & Sec Syts",
    "wof:placetype":"venue"
},
  "geometry": {"coordinates":[-112.091047,40.665359],"type":"Point"}
}