{
  "type": "Feature",
  "properties": {
    "iso:country":"US",
    "sg:address":"243 E Saint George Blvd",
    "sg:city":"St George",
    "sg:classifiers":[
        {
            "category":"Banks & Credit Unions",
            "subcategory":"Bank",
            "type":"Services"
        }
    ],
    "sg:phone":"+1 435 673 7635",
    "sg:postcode":"84770",
    "sg:province":"UT",
    "sg:tags":[
        "mortgage"
    ],
    "wof:name":"Preferred Funding",
    "wof:placetype":"venue"
},
  "geometry": {"coordinates":[-113.578249,37.10995],"type":"Point"}
}