{
  "type": "Feature",
  "properties": {
    "iso:country":"US",
    "sg:address":"535 W 400 N",
    "sg:city":"Bountiful",
    "sg:classifiers":[
        {
            "category":"Ice Cream",
            "type":"Food & Drink"
        }
    ],
    "sg:phone":"+1 801 706 3013",
    "sg:postcode":"84010",
    "sg:province":"UT",
    "sg:tags":[
        "frozen",
        "yogurt"
    ],
    "sg:website":"www.scoopology.com/",
    "wof:name":"Scoopology",
    "wof:placetype":"venue"
},
  "geometry": {"coordinates":[-111.893041,40.893969],"type":"Point"}
}