{
  "type": "Feature",
  "properties": {
    "iso:country":"US",
    "sg:address":"651 W Antelope Dr",
    "sg:city":"Layton",
    "sg:classifiers":[
        {
            "category":"Restaurant",
            "type":"Food & Drink"
        }
    ],
    "sg:menulink":"http://www.allmenus.com/ut/north-davis/40247-fazolis/menu/",
    "sg:phone":"+1 801 825 1200",
    "sg:postcode":"84041",
    "sg:province":"UT",
    "sg:tags":[
        "italian"
    ],
    "wof:name":"Fazoli's",
    "wof:placetype":"venue"
},
  "geometry": {"coordinates":[-111.978256,41.089176],"type":"Point"}
}