{
  "type": "Feature",
  "properties": {
    "iso:country":"US",
    "sg:address":"1460 E 140 S",
    "sg:city":"Pleasant Grove",
    "sg:classifiers":[
        {
            "category":"Wholesale",
            "subcategory":"Books, Periodicals, & Newspapers",
            "type":"Manufacturing & Wholesale Goods"
        }
    ],
    "sg:phone":"+1 801 785 0822",
    "sg:postcode":"84062",
    "sg:province":"UT",
    "wof:name":"Mark Scoville Inc",
    "wof:placetype":"venue"
},
  "geometry": {"coordinates":[-111.70707400000001,40.361777],"type":"Point"}
}