{
  "type": "Feature",
  "properties": {
    "iso:country":"US",
    "sg:address":"8467 Dynasty Way",
    "sg:city":"Salt Lake City",
    "sg:classifiers":[
        {
            "category":"Health Services",
            "subcategory":"Medical Lab",
            "type":"Services"
        }
    ],
    "sg:phone":"+1 801 733 4358",
    "sg:postcode":"84121",
    "sg:province":"UT",
    "sg:tags":[
        "laboratory",
        "dental"
    ],
    "wof:name":"Oral Design Dental Laboratory",
    "wof:placetype":"venue"
},
  "geometry": {"coordinates":[-111.79639,40.59698],"type":"Point"}
}