{
  "type": "Feature",
  "properties": {
    "iso:country":"US",
    "sg:address":"8741 S 250 E",
    "sg:city":"Sandy",
    "sg:classifiers":[
        {
            "category":"Shopping",
            "type":"Retail Goods"
        }
    ],
    "sg:phone":"+1 801 255 2927",
    "sg:postcode":"84070",
    "sg:province":"UT",
    "sg:tags":[
        "merchandise"
    ],
    "wof:name":"Monument Uranium Company",
    "wof:placetype":"venue"
},
  "geometry": {"coordinates":[-111.88294999999999,40.592744],"type":"Point"}
}