{
  "type": "Feature",
  "properties": {
    "iso:country":"US",
    "sg:address":"1279 W 2200 S",
    "sg:city":"Salt Lake City",
    "sg:classifiers":[
        {
            "category":"Government",
            "subcategory":"Office",
            "type":"Public Place"
        }
    ],
    "sg:phone":"+1 801 954 0411",
    "sg:postcode":"84119",
    "sg:province":"UT",
    "sg:tags":[
        "station",
        "recruiting"
    ],
    "wof:name":"Recruiting Station",
    "wof:placetype":"venue"
},
  "geometry": {"coordinates":[-111.92665,40.723833],"type":"Point"}
}