{
  "type": "Feature",
  "properties": {
    "iso:country":"US",
    "sg:address":"4641 Roundtable Rd",
    "sg:city":"Salt Lake City",
    "sg:classifiers":[
        {
            "category":"Building & Trades",
            "subcategory":"Plumbing",
            "type":"Services"
        }
    ],
    "sg:phone":"+1 801 955 5255",
    "sg:postcode":"84120",
    "sg:province":"UT",
    "sg:tags":[
        "contractor"
    ],
    "wof:name":"Ha Maintanice",
    "wof:placetype":"venue"
},
  "geometry": {"coordinates":[-112.00205,40.704427],"type":"Point"}
}