{
  "type": "Feature",
  "properties": {
    "iso:country":"US",
    "sg:address":"1372 W 8230 S",
    "sg:city":"West Jordan",
    "sg:classifiers":[
        {
            "category":"Building & Trades",
            "subcategory":"Construction",
            "type":"Services"
        }
    ],
    "sg:phone":"+1 801 569 2839",
    "sg:postcode":"84088",
    "sg:province":"UT",
    "wof:name":"Heat Paving Inc",
    "wof:placetype":"venue"
},
  "geometry": {"coordinates":[-111.93104099999999,40.601828],"type":"Point"}
}