{
  "type": "Feature",
  "properties": {
    "iso:country":"US",
    "sg:address":"159 N 1250 W",
    "sg:city":"Centerville",
    "sg:classifiers":[
        {
            "category":"Retail",
            "subcategory":"Storage",
            "type":"Services"
        }
    ],
    "sg:phone":"+1 801 203 3240",
    "sg:postcode":"84014",
    "sg:province":"UT",
    "sg:tags":[
        "household",
        "commercial"
    ],
    "wof:name":"Aspen Springs Storage & RV Parking",
    "wof:placetype":"venue"
},
  "geometry": {"coordinates":[-111.896842,40.918447],"type":"Point"}
}