{
  "type": "Feature",
  "properties": {
    "iso:country":"US",
    "sg:address":"50 W Canyon Crest Rd",
    "sg:city":"Alpine",
    "sg:classifiers":[
        {
            "category":"Banks & Credit Unions",
            "subcategory":"Bank",
            "type":"Services"
        }
    ],
    "sg:phone":"+1 801 772 0828",
    "sg:postcode":"84004",
    "sg:province":"UT",
    "wof:name":"Indy Mac Bank",
    "wof:placetype":"venue"
},
  "geometry": {"coordinates":[-111.78044,40.44874],"type":"Point"}
}