{
  "type": "Feature",
  "properties": {
    "iso:country":"US",
    "sg:address":"1270 S 2500 W",
    "sg:city":"Syracuse",
    "sg:classifiers":[
        {
            "category":"Personal",
            "subcategory":"Beauty Salon",
            "type":"Services"
        }
    ],
    "sg:phone":"+1 801 825 1638",
    "sg:postcode":"84075",
    "sg:province":"UT",
    "sg:tags":[
        "shop"
    ],
    "wof:name":"Stuarts Electrolysis",
    "wof:placetype":"venue"
},
  "geometry": {"coordinates":[-112.074299,41.095514],"type":"Point"}
}