{
  "type": "Feature",
  "properties": {
    "iso:country":"US",
    "sg:address":"64 N Main St",
    "sg:city":"Roosevelt",
    "sg:classifiers":[
        {
            "category":"Banks & Credit Unions",
            "subcategory":"Bank",
            "type":"Services"
        }
    ],
    "sg:phone":"+1 435 725 2926",
    "sg:postcode":"84069",
    "sg:province":"UT",
    "sg:tags":[
        "loan",
        "real estate"
    ],
    "wof:name":"Freedom Mortgage",
    "wof:placetype":"venue"
},
  "geometry": {"coordinates":[-112.446764,40.3386],"type":"Point"}
}