{
  "type": "Feature",
  "properties": {
    "iso:country":"US",
    "sg:address":"428 N 700 E",
    "sg:city":"Orem",
    "sg:classifiers":[
        {
            "category":"Communications",
            "subcategory":"Film & Video Production",
            "type":"Services"
        }
    ],
    "sg:phone":"+1 801 225 5499",
    "sg:postcode":"84097",
    "sg:province":"UT",
    "sg:tags":[
        "taping"
    ],
    "wof:name":"I V Group",
    "wof:placetype":"venue"
},
  "geometry": {"coordinates":[-111.67891299999999,40.304723],"type":"Point"}
}