{
  "type": "Feature",
  "properties": {
    "iso:country":"US",
    "sg:address":"603 N 2620 W",
    "sg:city":"Provo",
    "sg:classifiers":[
        {
            "category":"Shopping",
            "subcategory":"Jewelry",
            "type":"Retail Goods"
        }
    ],
    "sg:phone":"+1 801 377 2158",
    "sg:postcode":"84601",
    "sg:province":"UT",
    "wof:name":"Taylors Jewelry",
    "wof:placetype":"venue"
},
  "geometry": {"coordinates":[-111.705134,40.242427],"type":"Point"}
}