{
  "type": "Feature",
  "properties": {
    "iso:country":"US",
    "sg:address":"2000 W 2300 S",
    "sg:city":"Salt Lake City",
    "sg:classifiers":[
        {
            "category":"Manufacturing",
            "subcategory":"Printing",
            "type":"Manufacturing & Wholesale Goods"
        }
    ],
    "sg:phone":"+1 801 972 6150",
    "sg:postcode":"84119",
    "sg:province":"UT",
    "sg:tags":[
        "lithographic",
        "commercial"
    ],
    "wof:name":"K/P Corporation",
    "wof:placetype":"venue"
},
  "geometry": {"coordinates":[-111.94976800000001,40.721256],"type":"Point"}
}