{
  "type": "Feature",
  "properties": {
    "iso:country":"US",
    "sg:address":"12727 Whisper Point Ct",
    "sg:city":"Draper",
    "sg:classifiers":[
        {
            "category":"Banks & Credit Unions",
            "subcategory":"Financial Services",
            "type":"Services"
        }
    ],
    "sg:phone":"+1 801 566 0893",
    "sg:postcode":"84020",
    "sg:province":"UT",
    "sg:tags":[
        "company",
        "holding"
    ],
    "wof:name":"Kerve",
    "wof:placetype":"venue"
},
  "geometry": {"coordinates":[-111.87030900000001,40.520661],"type":"Point"}
}