{
  "type": "Feature",
  "properties": {
    "iso:country":"US",
    "sg:address":"975 E 6600 S",
    "sg:city":"Ogden",
    "sg:classifiers":[
        {
            "category":"Health Services",
            "subcategory":"Doctor",
            "type":"Services"
        }
    ],
    "sg:phone":"+1 801 398 6200",
    "sg:postcode":"84405",
    "sg:province":"UT",
    "sg:tags":[
        "medical"
    ],
    "wof:name":"Joel Porter MD",
    "wof:placetype":"venue"
},
  "geometry": {"coordinates":[-111.956625,41.147828],"type":"Point"}
}