{
  "type": "Feature",
  "properties": {
    "iso:country":"US",
    "sg:address":"500 S 1750 W",
    "sg:city":"Springville",
    "sg:classifiers":[
        {
            "category":"Restaurant",
            "type":"Food & Drink"
        }
    ],
    "sg:menulink":"http://www.allmenus.com/ut/springville-mapleton/74995-pizza-hut/menu/",
    "sg:phone":"+1 801 489 3222",
    "sg:postcode":"84663",
    "sg:province":"UT",
    "sg:tags":[
        "american",
        "pizza"
    ],
    "wof:name":"Pizza Hut",
    "wof:placetype":"venue"
},
  "geometry": {"coordinates":[-111.64239999999999,40.160636],"type":"Point"}
}