{
  "type": "Feature",
  "properties": {
    "iso:country":"US",
    "sg:address":"2500 S 2300 W",
    "sg:city":"Salt Lake City",
    "sg:classifiers":[
        {
            "category":"Manufacturing",
            "subcategory":"Printing",
            "type":"Manufacturing & Wholesale Goods"
        }
    ],
    "sg:phone":"+1 801 978 3399",
    "sg:postcode":"84119",
    "sg:province":"UT",
    "sg:tags":[
        "printer",
        "commercial"
    ],
    "sg:website":"www.dmdcolor.com",
    "wof:name":"Diamond Collar",
    "wof:placetype":"venue"
},
  "geometry": {"coordinates":[-111.95075300000001,40.71618],"type":"Point"}
}