{
  "type": "Feature",
  "properties": {
    "iso:country":"US",
    "sg:address":"678 E Vine St",
    "sg:city":"Salt Lake City",
    "sg:classifiers":[
        {
            "category":"Manufacturing",
            "subcategory":"Printing",
            "type":"Manufacturing & Wholesale Goods"
        }
    ],
    "sg:phone":"+1 801 363 9815",
    "sg:postcode":"84107",
    "sg:province":"UT",
    "sg:tags":[
        "periodical"
    ],
    "wof:name":"Trader Publishing Company",
    "wof:placetype":"venue"
},
  "geometry": {"coordinates":[-111.87236,40.655541],"type":"Point"}
}