{
  "type": "Feature",
  "properties": {
    "iso:country":"US",
    "sg:address":"3064 N 2175 E",
    "sg:city":"Layton",
    "sg:classifiers":[
        {
            "category":"Professional",
            "subcategory":"Business Services",
            "type":"Services"
        }
    ],
    "sg:phone":"+1 801 771 5134",
    "sg:postcode":"84040",
    "sg:province":"UT",
    "wof:name":"Lakeman Drafting Design",
    "wof:placetype":"venue"
},
  "geometry": {"coordinates":[-111.923481,41.104313],"type":"Point"}
}