{
  "type": "Feature",
  "properties": {
    "iso:country":"US",
    "sg:address":"5 S 500 W",
    "sg:city":"Salt Lake City",
    "sg:classifiers":[
        {
            "category":"Shopping",
            "type":"Retail Goods"
        }
    ],
    "sg:phone":"+1 801 531 6567",
    "sg:postcode":"84101",
    "sg:province":"UT",
    "sg:tags":[
        "awning",
        "canopy"
    ],
    "wof:name":"KOOL Breeze Home Improvement",
    "wof:placetype":"venue"
},
  "geometry": {"coordinates":[-111.90531799999999,40.768601],"type":"Point"}
}