{
  "type": "Feature",
  "properties": {
    "iso:country":"US",
    "sg:address":"195 E Main St",
    "sg:city":"Richmond",
    "sg:classifiers":[
        {
            "category":"Shopping",
            "subcategory":"Hobbies, Toys, & Games",
            "type":"Retail Goods"
        }
    ],
    "sg:phone":"+1 435 258 2817",
    "sg:postcode":"84333",
    "sg:province":"UT",
    "sg:tags":[
        "equipment",
        "ceramic",
        "supply"
    ],
    "wof:name":"Cache Valley Ceramics-Supplies",
    "wof:placetype":"venue"
},
  "geometry": {"coordinates":[-111.803155,41.922624],"type":"Point"}
}