{
  "type": "Feature",
  "properties": {
    "iso:country":"US",
    "sg:address":"1313 E 660 N",
    "sg:city":"Orem",
    "sg:classifiers":[
        {
            "category":"Local Transit",
            "type":"Transportation"
        }
    ],
    "sg:phone":"+1 801 364 8788",
    "sg:postcode":"84097",
    "sg:province":"UT",
    "sg:tags":[
        "limousine"
    ],
    "wof:name":"Medallion Limousine",
    "wof:placetype":"venue"
},
  "geometry": {"coordinates":[-111.66336200000001,40.309075],"type":"Point"}
}