{
  "type": "Feature",
  "properties": {
    "iso:country":"US",
    "sg:address":"5928 Willow Wood Ln",
    "sg:city":"Ogden",
    "sg:classifiers":[
        {
            "category":"Professional",
            "subcategory":"Engineering",
            "type":"Services"
        }
    ],
    "sg:phone":"+1 801 479 4900",
    "sg:postcode":"84403",
    "sg:province":"UT",
    "wof:name":"Engineers A CSM Professional",
    "wof:placetype":"venue"
},
  "geometry": {"coordinates":[-111.93244199999999,41.155853],"type":"Point"}
}