{
  "type": "Feature",
  "properties": {
    "iso:country":"US",
    "sg:address":"1950 W 4400 S",
    "sg:city":"Roy",
    "sg:classifiers":[
        {
            "category":"Organizations",
            "subcategory":"Religious Organization",
            "type":"Services"
        }
    ],
    "sg:phone":"+1 801 731 3671",
    "sg:postcode":"84067",
    "sg:province":"UT",
    "wof:name":"Kingdom Hall",
    "wof:placetype":"venue"
},
  "geometry": {"coordinates":[-112.026984,41.183468],"type":"Point"}
}