{
  "type": "Feature",
  "properties": {
    "iso:country":"US",
    "sg:address":"1370 Beck St",
    "sg:city":"Salt Lake City",
    "sg:classifiers":[
        {
            "category":"Wholesale",
            "subcategory":"Auto Parts",
            "type":"Manufacturing & Wholesale Goods"
        }
    ],
    "sg:phone":"+1 801 532 2341",
    "sg:postcode":"84116",
    "sg:province":"UT",
    "wof:name":"Miles Unlimited Inc",
    "wof:placetype":"venue"
},
  "geometry": {"coordinates":[-111.90441199999999,40.79507],"type":"Point"}
}