{
  "type": "Feature",
  "properties": {
    "iso:country":"US",
    "sg:address":"720 Timpanogos Pkwy",
    "sg:city":"Orem",
    "sg:classifiers":[
        {
            "category":"Professional",
            "subcategory":"Computer Services",
            "type":"Services"
        }
    ],
    "sg:phone":"+1 801 222 0200",
    "sg:postcode":"84097",
    "sg:province":"UT",
    "sg:tags":[
        "consultant",
        "designer"
    ],
    "sg:website":"www.so-sys.com",
    "wof:name":"Open Solutions Sosystems",
    "wof:placetype":"venue"
},
  "geometry": {"coordinates":[-111.678561,40.321485],"type":"Point"}
}