{
  "type": "Feature",
  "properties": {
    "iso:country":"US",
    "sg:address":"692 Caserio Cir",
    "sg:city":"Washington",
    "sg:classifiers":[
        {
            "category":"Professional",
            "subcategory":"Business Services",
            "type":"Services"
        }
    ],
    "sg:phone":"+1 435 627 9971",
    "sg:postcode":"84780",
    "sg:province":"UT",
    "wof:name":"C&R Enterprises",
    "wof:placetype":"venue"
},
  "geometry": {"coordinates":[-113.521604,37.09747],"type":"Point"}
}