{
  "type": "Feature",
  "properties": {
    "iso:country":"US",
    "sg:address":"251 Gordon Ln",
    "sg:city":"Salt Lake City",
    "sg:classifiers":[
        {
            "category":"Freight",
            "type":"Transportation"
        }
    ],
    "sg:phone":"+1 801 486 4970",
    "sg:postcode":"84107",
    "sg:province":"UT",
    "sg:tags":[
        "commercial",
        "storage"
    ],
    "wof:name":"Cottonwood Storage",
    "wof:placetype":"venue"
},
  "geometry": {"coordinates":[-111.88444699999999,40.679192],"type":"Point"}
}