{
  "type": "Feature",
  "properties": {
    "iso:country":"US",
    "sg:address":"1931 Ryan Park Ave",
    "sg:city":"Sandy",
    "sg:classifiers":[
        {
            "category":"Home & Garden",
            "subcategory":"Building Materials",
            "type":"Retail Goods"
        }
    ],
    "sg:phone":"+1 801 561 1304",
    "sg:postcode":"84092",
    "sg:province":"UT",
    "sg:tags":[
        "shutter"
    ],
    "wof:name":"Marc Denning",
    "wof:placetype":"venue"
},
  "geometry": {"coordinates":[-111.83562000000001,40.549968],"type":"Point"}
}