{
  "type": "Feature",
  "properties": {
    "iso:country":"US",
    "sg:address":"4999 S Fairbrook Ln",
    "sg:city":"Holladay",
    "sg:classifiers":[
        {
            "category":"Building & Trades",
            "subcategory":"Plumbing",
            "type":"Services"
        }
    ],
    "sg:phone":"+1 801 278 7600",
    "sg:postcode":"84117",
    "sg:province":"UT",
    "sg:tags":[
        "conditioning",
        "air",
        "system",
        "contractor"
    ],
    "wof:name":"Comfort Level",
    "wof:placetype":"venue"
},
  "geometry": {"coordinates":[-111.82919699999999,40.659571],"type":"Point"}
}