{
  "type": "Feature",
  "properties": {
    "iso:country":"US",
    "sg:address":"6975 N 2200 W",
    "sg:city":"Park City",
    "sg:classifiers":[
        {
            "category":"Real Estate",
            "subcategory":"Real Estate Agent",
            "type":"Services"
        }
    ],
    "sg:phone":"+1 435 645 3954",
    "sg:postcode":"84098",
    "sg:province":"UT",
    "sg:tags":[
        "operation"
    ],
    "wof:name":"Crestview Condominiums",
    "wof:placetype":"venue"
},
  "geometry": {"coordinates":[-111.551557,40.729437],"type":"Point"}
}