{
  "type": "Feature",
  "properties": {
    "iso:country":"US",
    "sg:address":"11617 Terendale Ln",
    "sg:city":"Sandy",
    "sg:classifiers":[
        {
            "category":"Professional",
            "subcategory":"Computer Services",
            "type":"Services"
        }
    ],
    "sg:phone":"+1 801 572 0667",
    "sg:postcode":"84092",
    "sg:province":"UT",
    "sg:tags":[
        "reseller"
    ],
    "wof:name":"Specialized Business Systems",
    "wof:placetype":"venue"
},
  "geometry": {"coordinates":[-111.829528,40.541181],"type":"Point"}
}