{
  "type": "Feature",
  "properties": {
    "iso:country":"US",
    "sg:address":"720 Belnap Cir",
    "sg:city":"Ogden",
    "sg:classifiers":[
        {
            "category":"Building & Trades",
            "subcategory":"Electrical",
            "type":"Services"
        }
    ],
    "sg:phone":"+1 801 920 3285",
    "sg:postcode":"84403",
    "sg:province":"UT",
    "sg:tags":[
        "electrical",
        "contractor"
    ],
    "wof:name":"Rash Electric",
    "wof:placetype":"venue"
},
  "geometry": {"coordinates":[-111.96146,41.205489],"type":"Point"}
}