{
  "type": "Feature",
  "properties": {
    "iso:country":"US",
    "sg:address":"2148 Twilight Ct",
    "sg:city":"Park City",
    "sg:classifiers":[
        {
            "category":"Building & Trades",
            "subcategory":"Construction",
            "type":"Services"
        }
    ],
    "sg:phone":"+1 435 649 9403",
    "sg:postcode":"84060",
    "sg:province":"UT",
    "sg:tags":[
        "house"
    ],
    "wof:name":"Carlquist Const",
    "wof:placetype":"venue"
},
  "geometry": {"coordinates":[-111.49435099999999,40.673245],"type":"Point"}
}