{
  "type": "Feature",
  "properties": {
    "iso:country":"US",
    "sg:address":"957 N 400 E",
    "sg:city":"North Salt Lake",
    "sg:classifiers":[
        {
            "category":"Retail",
            "subcategory":"Auto Repair",
            "type":"Services"
        }
    ],
    "sg:phone":"+1 801 693 7160",
    "sg:postcode":"84054",
    "sg:province":"UT",
    "wof:name":"Christopher Imports Christopher Nissan",
    "wof:placetype":"venue"
},
  "geometry": {"coordinates":[-111.902221,40.858624],"type":"Point"}
}