{
  "type": "Feature",
  "properties": {
    "iso:country":"US",
    "sg:address":"11087 S 1300 W",
    "sg:city":"South Jordan",
    "sg:classifiers":[
        {
            "category":"Professional",
            "subcategory":"Business Services",
            "type":"Services"
        }
    ],
    "sg:phone":"+1 801 254 4328",
    "sg:postcode":"84095",
    "sg:province":"UT",
    "wof:name":"Rodney W Butterfield",
    "wof:placetype":"venue"
},
  "geometry": {"coordinates":[-111.929044,40.549744],"type":"Point"}
}