{
  "type": "Feature",
  "properties": {
    "iso:country":"US",
    "sg:address":"775 S 300 W",
    "sg:city":"Salt Lake City",
    "sg:classifiers":[
        {
            "category":"Retail",
            "subcategory":"Auto Repair",
            "type":"Services"
        }
    ],
    "sg:phone":"+1 801 328 1829",
    "sg:postcode":"84101",
    "sg:province":"UT",
    "sg:tags":[
        "repairing",
        "automobile"
    ],
    "wof:name":"Car Doctor",
    "wof:placetype":"venue"
},
  "geometry": {"coordinates":[-111.89959,40.752376],"type":"Point"}
}