{
  "type": "Feature",
  "properties": {
    "iso:country":"US",
    "sg:address":"876 N 1000 E",
    "sg:city":"Price",
    "sg:classifiers":[
        {
            "category":"Building & Trades",
            "subcategory":"Plumbing",
            "type":"Services"
        }
    ],
    "sg:phone":"+1 435 637 3743",
    "sg:postcode":"84501",
    "sg:province":"UT",
    "sg:tags":[
        "plumbing",
        "contractor"
    ],
    "wof:name":"Miller Plumbing Co",
    "wof:placetype":"venue"
},
  "geometry": {"coordinates":[-110.796027,39.613904],"type":"Point"}
}