{
  "type": "Feature",
  "properties": {
    "iso:country":"US",
    "sg:address":"1200 Towne Centre Blvd",
    "sg:city":"Provo",
    "sg:classifiers":[
        {
            "category":"Autos & Motor Vehicles",
            "subcategory":"Automobile Sales",
            "type":"Retail Goods"
        },
        {
            "category":"Retail",
            "subcategory":"Auto Rental",
            "type":"Services"
        }
    ],
    "sg:phone":"+1 801 494 1529",
    "sg:postcode":"84601",
    "sg:province":"UT",
    "sg:tags":[
        "car",
        "leasing",
        "van"
    ],
    "sg:website":"http://avis.com/IYP_tl",
    "wof:name":"Avis Rent A Car",
    "wof:placetype":"venue"
},
  "geometry": {"coordinates":[-111.66046900000001,40.21785],"type":"Point"}
}