{
  "type": "Feature",
  "properties": {
    "iso:country":"US",
    "sg:address":"513 N Main St",
    "sg:city":"Heber City",
    "sg:classifiers":[
        {
            "category":"Cinema",
            "subcategory":"Movie Rental",
            "type":"Entertainment"
        }
    ],
    "sg:phone":"+1 435 657 1388",
    "sg:postcode":"84032",
    "sg:province":"UT",
    "sg:tags":[
        "video",
        "tape"
    ],
    "wof:name":"Video Update 614",
    "wof:placetype":"venue"
},
  "geometry": {"coordinates":[-111.413203,40.514836],"type":"Point"}
}