{
  "type": "Feature",
  "properties": {
    "iso:country":"US",
    "sg:address":"1220 S Jordan Pkwy",
    "sg:city":"South Jordan",
    "sg:classifiers":[
        {
            "category":"Professional",
            "subcategory":"Advertising",
            "type":"Services"
        }
    ],
    "sg:phone":"+1 801 446 9797",
    "sg:postcode":"84095",
    "sg:province":"UT",
    "sg:tags":[
        "counselor"
    ],
    "wof:name":"Atomic Advertising",
    "wof:placetype":"venue"
},
  "geometry": {"coordinates":[-111.926501,40.56205],"type":"Point"}
}