{
  "type": "Feature",
  "properties": {
    "iso:country":"US",
    "sg:address":"3290 Washington Blvd",
    "sg:city":"Ogden",
    "sg:classifiers":[
        {
            "category":"Wholesale",
            "subcategory":"Auto Parts",
            "type":"Manufacturing & Wholesale Goods"
        }
    ],
    "sg:phone":"+1 801 399 3317",
    "sg:postcode":"84401",
    "sg:province":"UT",
    "sg:tags":[
        "paint",
        "truck",
        "glass"
    ],
    "wof:name":"Salt Lake Auto Paint & Glass",
    "wof:placetype":"venue"
},
  "geometry": {"coordinates":[-111.970772,41.204369],"type":"Point"}
}