{
  "type": "Feature",
  "properties": {
    "iso:country":"US",
    "sg:address":"215 W 330 N",
    "sg:city":"La Verkin",
    "sg:classifiers":[
        {
            "category":"Retail",
            "subcategory":"Auto Repair",
            "type":"Services"
        }
    ],
    "sg:phone":"+1 435 635 4037",
    "sg:postcode":"84745",
    "sg:province":"UT",
    "sg:tags":[
        "mobile",
        "home",
        "towing"
    ],
    "wof:name":"A & I Mobile Home Towing",
    "wof:placetype":"venue"
},
  "geometry": {"coordinates":[-113.274424,37.207782],"type":"Point"}
}