{
  "type": "Feature",
  "properties": {
    "iso:country":"US",
    "sg:address":"146 W Malvern Ave",
    "sg:city":"Salt Lake City",
    "sg:classifiers":[
        {
            "category":"Retail",
            "subcategory":"Auto Repair",
            "type":"Services"
        }
    ],
    "sg:phone":"+1 801 467 9933",
    "sg:postcode":"84115",
    "sg:province":"UT",
    "sg:tags":[
        "body"
    ],
    "wof:name":"Other Body Shop",
    "wof:placetype":"venue"
},
  "geometry": {"coordinates":[-111.895661,40.713556],"type":"Point"}
}