{
  "type": "Feature",
  "properties": {
    "iso:country":"US",
    "sg:address":"2598 Cave Hollow Way",
    "sg:city":"Bountiful",
    "sg:classifiers":[
        {
            "category":"Professional",
            "subcategory":"Management & Consulting",
            "type":"Services"
        }
    ],
    "sg:phone":"+1 801 299 8361",
    "sg:postcode":"84010",
    "sg:province":"UT",
    "sg:tags":[
        "business"
    ],
    "wof:name":"Cave Hollow Marketing",
    "wof:placetype":"venue"
},
  "geometry": {"coordinates":[-111.843152,40.861447],"type":"Point"}
}