{
  "type": "Feature",
  "properties": {
    "iso:country":"US",
    "sg:address":"203 Coventry Ln",
    "sg:city":"North Salt Lake",
    "sg:classifiers":[
        {
            "category":"Real Estate",
            "subcategory":"Real Estate Agent",
            "type":"Services"
        }
    ],
    "sg:phone":"+1 801 936 4340",
    "sg:postcode":"84054",
    "sg:province":"UT",
    "wof:name":"Sure Sell Realty",
    "wof:placetype":"venue"
},
  "geometry": {"coordinates":[-111.896135,40.836943],"type":"Point"}
}