{
  "type": "Feature",
  "properties": {
    "iso:country":"US",
    "sg:address":"4078 S Cowan Way",
    "sg:city":"Salt Lake City",
    "sg:classifiers":[
        {
            "category":"Professional",
            "subcategory":"Art Services",
            "type":"Services"
        }
    ],
    "sg:phone":"+1 801 969 9995",
    "sg:postcode":"84120",
    "sg:province":"UT",
    "sg:tags":[
        "commercial",
        "design"
    ],
    "wof:name":"Crisandra Crafts",
    "wof:placetype":"venue"
},
  "geometry": {"coordinates":[-111.995266,40.682868],"type":"Point"}
}