{
  "type": "Feature",
  "properties": {
    "iso:country":"US",
    "sg:address":"3316 W 2100 S",
    "sg:city":"Salt Lake City",
    "sg:classifiers":[
        {
            "category":"Retail",
            "subcategory":"Auto Repair",
            "type":"Services"
        }
    ],
    "sg:phone":"+1 801 974 9900",
    "sg:postcode":"84119",
    "sg:province":"UT",
    "sg:tags":[
        "automotive",
        "glass",
        "replacement"
    ],
    "wof:name":"Nationwide Autoglass",
    "wof:placetype":"venue"
},
  "geometry": {"coordinates":[-111.968165,40.726886],"type":"Point"}
}