{
  "type": "Feature",
  "properties": {
    "iso:country":"US",
    "sg:address":"897 W 100 N",
    "sg:city":"North Salt Lake",
    "sg:classifiers":[
        {
            "category":"Building & Trades",
            "subcategory":"Plumbing",
            "type":"Services"
        }
    ],
    "sg:phone":"+1 801 296 9005",
    "sg:postcode":"84054",
    "sg:province":"UT",
    "sg:tags":[
        "conditioning",
        "air",
        "system",
        "contractor"
    ],
    "wof:name":"Anglers Hvac",
    "wof:placetype":"venue"
},
  "geometry": {"coordinates":[-111.93472,40.844533],"type":"Point"}
}