{
  "type": "Feature",
  "properties": {
    "iso:country":"US",
    "sg:address":"9667 Indian Ridge Dr",
    "sg:city":"Sandy",
    "sg:classifiers":[
        {
            "category":"Personal",
            "subcategory":"Beauty Salon",
            "type":"Services"
        }
    ],
    "sg:phone":"+1 801 571 9363",
    "sg:postcode":"84092",
    "sg:province":"UT",
    "sg:tags":[
        "shop"
    ],
    "wof:name":"Hair Klassics",
    "wof:placetype":"venue"
},
  "geometry": {"coordinates":[-111.852369,40.575312],"type":"Point"}
}