{
  "type": "Feature",
  "properties": {
    "iso:country":"US",
    "sg:address":"566 E 1300 S",
    "sg:city":"Orem",
    "sg:classifiers":[
        {
            "category":"Food & Beverages",
            "subcategory":"Fruits & Vegetables",
            "type":"Retail Goods"
        },
        {
            "category":"Restaurant",
            "type":"Food & Drink"
        }
    ],
    "sg:phone":"+1 801 223 9360",
    "sg:postcode":"84097",
    "sg:province":"UT",
    "sg:tags":[
        "juice",
        "eating"
    ],
    "wof:name":"Jamba Juice",
    "wof:placetype":"venue"
},
  "geometry": {"coordinates":[-111.679097,40.273095],"type":"Point"}
}