{
  "type": "Feature",
  "properties": {
    "iso:country":"US",
    "sg:address":"2929 S Main St",
    "sg:city":"Salt Lake City",
    "sg:classifiers":[
        {
            "category":"Health Services",
            "subcategory":"Clinic",
            "type":"Services"
        }
    ],
    "sg:phone":"+1 801 581 6730",
    "sg:postcode":"84115",
    "sg:province":"UT",
    "wof:name":"Physical Medical Systems Inc",
    "wof:placetype":"venue"
},
  "geometry": {"coordinates":[-111.891048,40.707929],"type":"Point"}
}