{
  "type": "Feature",
  "properties": {
    "iso:country":"US",
    "sg:address":"1333 E 3300 S",
    "sg:city":"Salt Lake City",
    "sg:classifiers":[
        {
            "category":"Banks & Credit Unions",
            "subcategory":"Investment Brokerage",
            "type":"Services"
        }
    ],
    "sg:phone":"+1 801 466 4747",
    "sg:postcode":"84106",
    "sg:province":"UT",
    "sg:tags":[
        "advisory",
        "financial"
    ],
    "wof:name":"Truworx Financial LLC",
    "wof:placetype":"venue"
},
  "geometry": {"coordinates":[-111.851569,40.699985],"type":"Point"}
}