{
  "type": "Feature",
  "properties": {
    "iso:country":"US",
    "sg:address":"572 Park Ave",
    "sg:city":"Park City",
    "sg:classifiers":[
        {
            "category":"Professional",
            "subcategory":"Business Services",
            "type":"Services"
        }
    ],
    "sg:phone":"+1 435 655 2621",
    "sg:postcode":"84017",
    "sg:province":"UT",
    "sg:tags":[
        "event"
    ],
    "wof:name":"Young Riders",
    "wof:placetype":"venue"
},
  "geometry": {"coordinates":[-111.49760000000001,40.645382],"type":"Point"}
}