{
  "type": "Feature",
  "properties": {
    "iso:country":"US",
    "sg:address":"1555 W 1170 N",
    "sg:city":"St George",
    "sg:classifiers":[
        {
            "category":"Health Services",
            "subcategory":"Nursing And Care Facility",
            "type":"Services"
        }
    ],
    "sg:phone":"+1 435 634 0202",
    "sg:postcode":"84770",
    "sg:province":"UT",
    "sg:tags":[
        "living",
        "assisted"
    ],
    "wof:name":"Beehive Homes Washington City",
    "wof:placetype":"venue"
},
  "geometry": {"coordinates":[-113.618055,37.127968],"type":"Point"}
}