{
  "type": "Feature",
  "properties": {
    "iso:country":"US",
    "sg:address":"175 S Main St",
    "sg:city":"Salt Lake City",
    "sg:classifiers":[
        {
            "category":"Insurance",
            "subcategory":"Insurance Agent",
            "type":"Services"
        }
    ],
    "sg:phone":"+1 801 363 9575",
    "sg:postcode":"84111",
    "sg:province":"UT",
    "sg:website":"www.andersoninsurancegroup.net",
    "wof:name":"Anderson Benefits Group",
    "wof:placetype":"venue"
},
  "geometry": {"coordinates":[-111.891018,40.766641],"type":"Point"}
}