{
  "type": "Feature",
  "properties": {
    "iso:country":"US",
    "sg:address":"98 Main St",
    "sg:city":"Coalville",
    "sg:classifiers":[
        {
            "category":"Building & Trades",
            "subcategory":"Construction",
            "type":"Services"
        }
    ],
    "sg:phone":"+1 435 336 1019",
    "sg:postcode":"84017",
    "sg:province":"UT",
    "sg:tags":[
        "mantel"
    ],
    "wof:name":"Chalk Creek Woodworking",
    "wof:placetype":"venue"
},
  "geometry": {"coordinates":[-111.399293,40.917629],"type":"Point"}
}