{
  "type": "Feature",
  "properties": {
    "iso:country":"US",
    "sg:address":"837 E South Temple",
    "sg:city":"Salt Lake City",
    "sg:classifiers":[
        {
            "category":"Professional",
            "subcategory":"Advertising",
            "type":"Services"
        }
    ],
    "sg:phone":"+1 801 531 6877",
    "sg:postcode":"84102",
    "sg:province":"UT",
    "sg:tags":[
        "counselor",
        "agency"
    ],
    "sg:website":"www.rrpartners.com",
    "wof:name":"R & R Partners Inc",
    "wof:placetype":"venue"
},
  "geometry": {"coordinates":[-111.86809599999999,40.769428],"type":"Point"}
}