{
  "type": "Feature",
  "properties": {
    "iso:country":"US",
    "sg:address":"6169 State Hwy 410",
    "sg:city":"Mountain View",
    "sg:classifiers":[
        {
            "category":"Professional",
            "type":"Services"
        }
    ],
    "sg:phone":"+1 307 782 3508",
    "sg:postcode":"82939",
    "sg:province":"UT",
    "sg:tags":[
        "establishment"
    ],
    "wof:name":"William Crawford Inc",
    "wof:placetype":"venue"
},
  "geometry": {"coordinates":[-110.336293,41.311002],"type":"Point"}
}