{
  "type": "Feature",
  "properties": {
    "iso:country":"US",
    "sg:address":"7536 S Birch St",
    "sg:city":"Midvale",
    "sg:classifiers":[
        {
            "category":"Building & Trades",
            "subcategory":"Construction",
            "type":"Services"
        }
    ],
    "sg:phone":"+1 801 566 9854",
    "sg:postcode":"84047",
    "sg:province":"UT",
    "sg:tags":[
        "hanging",
        "contractor"
    ],
    "wof:name":"Strong Painting",
    "wof:placetype":"venue"
},
  "geometry": {"coordinates":[-111.893021,40.612211],"type":"Point"}
}