{
  "type": "Feature",
  "properties": {
    "iso:country":"US",
    "sg:address":"20 S Main St",
    "sg:city":"Kaysville",
    "sg:classifiers":[
        {
            "category":"Restaurant",
            "type":"Food & Drink"
        }
    ],
    "sg:phone":"+1 801 498 7575",
    "sg:postcode":"84037",
    "sg:province":"UT",
    "wof:name":"B C Chicken",
    "wof:placetype":"venue"
},
  "geometry": {"coordinates":[-111.93872500000001,41.034002],"type":"Point"}
}