{
  "type": "Feature",
  "properties": {
    "iso:country":"US",
    "sg:address":"975 E 3300 S",
    "sg:city":"Salt Lake City",
    "sg:classifiers":[
        {
            "category":"Real Estate",
            "subcategory":"Real Estate Agent",
            "type":"Services"
        }
    ],
    "sg:phone":"+1 801 486 2141",
    "sg:postcode":"84106",
    "sg:province":"UT",
    "wof:name":"ERA",
    "wof:placetype":"venue"
},
  "geometry": {"coordinates":[-111.863249,40.699965],"type":"Point"}
}