{
  "type": "Feature",
  "properties": {
    "iso:country":"US",
    "sg:address":"179 W Haven Ave",
    "sg:city":"Salt Lake City",
    "sg:classifiers":[
        {
            "category":"Organizations",
            "subcategory":"Professional Association",
            "type":"Services"
        }
    ],
    "sg:phone":"+1 801 486 8449",
    "sg:postcode":"84115",
    "sg:province":"UT",
    "sg:tags":[
        "business"
    ],
    "wof:name":"Sheet Metals Contrs Assn Utah",
    "wof:placetype":"venue"
},
  "geometry": {"coordinates":[-111.896897,40.720935],"type":"Point"}
}