{
  "type": "Feature",
  "properties": {
    "iso:country":"US",
    "sg:address":"5965 S 1500 E",
    "sg:city":"Vernal",
    "sg:phone":"+1 435 781 1915",
    "sg:postcode":"84078",
    "sg:province":"UT",
    "sg:tags":[
        "equine",
        "f",
        "farm",
        "cash",
        "crop",
        "field",
        "grain"
    ],
    "wof:name":"Tom Hadden",
    "wof:placetype":"venue"
},
  "geometry": {"coordinates":[-109.498125,40.368278],"type":"Point"}
}