{
  "type": "Feature",
  "properties": {
    "iso:country":"US",
    "sg:address":"10380 E State Hwy 210",
    "sg:city":"Alta",
    "sg:classifiers":[
        {
            "category":"Professional",
            "type":"Services"
        }
    ],
    "sg:phone":"+1 801 742 1000",
    "sg:postcode":"84092",
    "sg:province":"UT",
    "sg:tags":[
        "establishment"
    ],
    "wof:name":"Webguy Productions",
    "wof:placetype":"venue"
},
  "geometry": {"coordinates":[-111.62667999999999,40.591718],"type":"Point"}
}