{
  "type": "Feature",
  "properties": {
    "iso:country":"US",
    "sg:address":"36 E Center St",
    "sg:city":"Ephraim",
    "sg:classifiers":[
        {
            "category":"Health Services",
            "subcategory":"Health Practitioner",
            "type":"Services"
        }
    ],
    "sg:phone":"+1 435 283 5662",
    "sg:postcode":"84627",
    "sg:province":"UT",
    "wof:name":"Mark Nilsson Physical Therapy",
    "wof:placetype":"venue"
},
  "geometry": {"coordinates":[-111.58619400000001,39.359715],"type":"Point"}
}