{
  "type": "Feature",
  "properties": {
    "iso:country":"US",
    "sg:address":"173 E 300 S",
    "sg:city":"Salt Lake City",
    "sg:classifiers":[
        {
            "category":"Retail",
            "subcategory":"Portrait Studio",
            "type":"Services"
        }
    ],
    "sg:phone":"+1 801 328 8827",
    "sg:postcode":"84111",
    "sg:province":"UT",
    "wof:name":"Saans Photo",
    "wof:placetype":"venue"
},
  "geometry": {"coordinates":[-111.885891,40.762902],"type":"Point"}
}