{
  "type": "Feature",
  "properties": {
    "iso:country":"US",
    "sg:address":"291 N 300 E",
    "sg:city":"American Fork",
    "sg:classifiers":[
        {
            "category":"Health Services",
            "subcategory":"Doctor",
            "type":"Services"
        }
    ],
    "sg:phone":"+1 801 756 2346",
    "sg:postcode":"84003",
    "sg:province":"UT",
    "wof:name":"Neal B Evans DDS",
    "wof:placetype":"venue"
},
  "geometry": {"coordinates":[-111.790655,40.381916],"type":"Point"}
}