{
  "type": "Feature",
  "properties": {
    "iso:country":"US",
    "sg:address":"868 E 1400 N",
    "sg:city":"Mapleton",
    "sg:classifiers":[
        {
            "category":"Banks & Credit Unions",
            "subcategory":"Financial Services",
            "type":"Services"
        }
    ],
    "sg:phone":"+1 801 489 5891",
    "sg:postcode":"84664",
    "sg:province":"UT",
    "sg:tags":[
        "trust",
        "management"
    ],
    "wof:name":"Pratt Family Trust",
    "wof:placetype":"venue"
},
  "geometry": {"coordinates":[-111.568864,40.143147],"type":"Point"}
}