{
  "type": "Feature",
  "properties": {
    "iso:country":"US",
    "sg:address":"2886 W 880 N",
    "sg:city":"Provo",
    "sg:classifiers":[
        {
            "category":"Arts & Performance",
            "subcategory":"Theater",
            "type":"Entertainment"
        }
    ],
    "sg:phone":"+1 801 375 9611",
    "sg:postcode":"84601",
    "sg:province":"UT",
    "sg:tags":[
        "live",
        "music"
    ],
    "wof:name":"Soundwaves Mobile Dance",
    "wof:placetype":"venue"
},
  "geometry": {"coordinates":[-111.710244,40.245596],"type":"Point"}
}