{
  "type": "Feature",
  "properties": {
    "iso:country":"US",
    "sg:address":"1140 N 1200 W",
    "sg:city":"Orem",
    "sg:classifiers":[
        {
            "category":"Home & Garden",
            "subcategory":"Home Furnishings",
            "type":"Retail Goods"
        }
    ],
    "sg:phone":"+1 801 224 8365",
    "sg:postcode":"84057",
    "sg:province":"UT",
    "sg:tags":[
        "lighting",
        "fixture"
    ],
    "sg:website":"www.lightingspecialists.com",
    "wof:name":"Lighting Specialists",
    "wof:placetype":"venue"
},
  "geometry": {"coordinates":[-111.724575,40.317525],"type":"Point"}
}