{
  "type": "Feature",
  "properties": {
    "iso:country":"US",
    "sg:address":"1280 US Hwy 89",
    "sg:city":"Richfield",
    "sg:classifiers":[
        {
            "category":"Restaurant",
            "type":"Food & Drink"
        }
    ],
    "sg:phone":"+1 435 896 4496",
    "sg:postcode":"84701",
    "sg:province":"UT",
    "sg:tags":[
        "pizza"
    ],
    "wof:name":"Pizza Hut",
    "wof:placetype":"venue"
},
  "geometry": {"coordinates":[-112.053347,38.785761],"type":"Point"}
}