{
  "type": "Feature",
  "properties": {
    "iso:country":"US",
    "sg:address":"489 E Stanley Cir",
    "sg:city":"Washington",
    "sg:classifiers":[
        {
            "category":"Shopping",
            "subcategory":"Crafts & Fabrics",
            "type":"Retail Goods"
        }
    ],
    "sg:phone":"+1 435 628 4523",
    "sg:postcode":"84780",
    "sg:province":"UT",
    "sg:tags":[
        "sewing"
    ],
    "wof:name":"Sew What of Southern Utah",
    "wof:placetype":"venue"
},
  "geometry": {"coordinates":[-113.50082500000001,37.102849],"type":"Point"}
}