{
  "type": "Feature",
  "properties": {
    "iso:country":"US",
    "sg:address":"1269 W 500 N",
    "sg:city":"Salt Lake City",
    "sg:classifiers":[
        {
            "category":"Education",
            "subcategory":"Special Training",
            "type":"Public Place"
        }
    ],
    "sg:phone":"+1 801 363 0935",
    "sg:postcode":"84116",
    "sg:province":"UT",
    "sg:tags":[
        "instruction",
        "driving"
    ],
    "wof:name":"Dan's Driving School",
    "wof:placetype":"venue"
},
  "geometry": {"coordinates":[-111.927947,40.780127],"type":"Point"}
}