{
  "type": "Feature",
  "properties": {
    "iso:country":"US",
    "sg:address":"8549 S 240 E",
    "sg:city":"Sandy",
    "sg:classifiers":[
        {
            "category":"Autos & Motor Vehicles",
            "subcategory":"Automobile Sales",
            "type":"Retail Goods"
        }
    ],
    "sg:phone":"+1 801 255 6350",
    "sg:postcode":"84070",
    "sg:province":"UT",
    "wof:name":"Wasatch Aviation Consultant",
    "wof:placetype":"venue"
},
  "geometry": {"coordinates":[-111.883358,40.595825],"type":"Point"}
}