{
  "type": "Feature",
  "properties": {
    "iso:country":"US",
    "sg:address":"3148 W 9765 S",
    "sg:city":"South Jordan",
    "sg:classifiers":[
        {
            "category":"Manufacturing",
            "subcategory":"Tools & Machinery",
            "type":"Manufacturing & Wholesale Goods"
        }
    ],
    "sg:phone":"+1 801 264 1726",
    "sg:postcode":"84095",
    "sg:province":"UT",
    "sg:tags":[
        "machine",
        "mfg",
        "accessory"
    ],
    "wof:name":"American Specialty Mfg",
    "wof:placetype":"venue"
},
  "geometry": {"coordinates":[-111.96568499999999,40.573913],"type":"Point"}
}