{
  "type": "Feature",
  "properties": {
    "iso:country":"US",
    "sg:address":"1505 S 40 E",
    "sg:city":"Provo",
    "sg:classifiers":[
        {
            "category":"Travel",
            "subcategory":"Hotels & Motels",
            "type":"Entertainment"
        }
    ],
    "sg:phone":"+1 801 377 6597",
    "sg:postcode":"84606",
    "sg:province":"UT",
    "wof:name":"Sleep Inn",
    "wof:placetype":"venue"
},
  "geometry": {"coordinates":[-111.657673,40.213776],"type":"Point"}
}