{
  "type": "Feature",
  "properties": {
    "iso:country":"US",
    "sg:address":"255 N State St",
    "sg:city":"La Verkin",
    "sg:classifiers":[
        {
            "category":"Manufacturing",
            "subcategory":"Rubber & Plastics",
            "type":"Manufacturing & Wholesale Goods"
        }
    ],
    "sg:phone":"+1 435 879 2713",
    "sg:postcode":"84745",
    "sg:province":"UT",
    "wof:name":"Research & Results Engineering",
    "wof:placetype":"venue"
},
  "geometry": {"coordinates":[-113.27218000000001,37.205992],"type":"Point"}
}