{
  "type": "Feature",
  "properties": {
    "iso:country":"US",
    "sg:address":"5495 Shea Dr",
    "sg:city":"Salt Lake City",
    "sg:classifiers":[
        {
            "category":"Freight",
            "type":"Transportation"
        }
    ],
    "sg:phone":"+1 801 521 0077",
    "sg:postcode":"84104",
    "sg:province":"UT",
    "sg:tags":[
        "hauling",
        "trucking"
    ],
    "wof:name":"Wilson Transport Inc",
    "wof:placetype":"venue"
},
  "geometry": {"coordinates":[-112.023146,40.752778],"type":"Point"}
}