{
  "type": "Feature",
  "properties": {
    "iso:country":"US",
    "sg:address":"733 N Main St",
    "sg:city":"Spanish Fork",
    "sg:classifiers":[
        {
            "category":"Building & Trades",
            "subcategory":"Equipment Rental",
            "type":"Services"
        }
    ],
    "sg:phone":"+1 801 798 6652",
    "sg:postcode":"84660",
    "sg:province":"UT",
    "sg:tags":[
        "contractor"
    ],
    "wof:name":"B & B Rental",
    "wof:placetype":"venue"
},
  "geometry": {"coordinates":[-111.65477199999999,40.119735],"type":"Point"}
}