{
  "type": "Feature",
  "properties": {
    "iso:country":"US",
    "sg:address":"1456 E 820 N",
    "sg:city":"Orem",
    "sg:classifiers":[
        {
            "category":"Professional",
            "subcategory":"Advertising",
            "type":"Services"
        }
    ],
    "sg:phone":"+1 801 222 4500",
    "sg:postcode":"84097",
    "sg:province":"UT",
    "sg:tags":[
        "agency"
    ],
    "wof:name":"Sum Media",
    "wof:placetype":"venue"
},
  "geometry": {"coordinates":[-111.66124600000001,40.313033],"type":"Point"}
}