{
  "type": "Feature",
  "properties": {
    "iso:country":"US",
    "sg:address":"816 N 3500 W",
    "sg:city":"Vernal",
    "sg:classifiers":[
        {
            "category":"Retail",
            "subcategory":"Repair Shop",
            "type":"Services"
        }
    ],
    "sg:phone":"+1 435 789 1279",
    "sg:postcode":"84078",
    "sg:province":"UT",
    "sg:tags":[
        "on",
        "welding",
        "site",
        "contractor"
    ],
    "wof:name":"Christofferson Welding Inc",
    "wof:placetype":"venue"
},
  "geometry": {"coordinates":[-109.59554799999999,40.466295],"type":"Point"}
}