{
  "type": "Feature",
  "properties": {
    "iso:country":"US",
    "sg:address":"8069 Ceder Ct",
    "sg:city":"Ogden",
    "sg:classifiers":[
        {
            "category":"Building & Trades",
            "subcategory":"Construction",
            "type":"Services"
        }
    ],
    "sg:phone":"+1 801 476 0368",
    "sg:postcode":"84405",
    "sg:province":"UT",
    "sg:tags":[
        "contractor"
    ],
    "wof:name":"Hopper Roofing",
    "wof:placetype":"venue"
},
  "geometry": {"coordinates":[-111.929227,41.121948],"type":"Point"}
}