{
  "type": "Feature",
  "properties": {
    "iso:country":"US",
    "sg:address":"1988 Bear Mountain Dr",
    "sg:city":"Draper",
    "sg:classifiers":[
        {
            "category":"Travel",
            "subcategory":"Travel Agent",
            "type":"Entertainment"
        }
    ],
    "sg:phone":"+1 801 576 8772",
    "sg:postcode":"84020",
    "sg:province":"UT",
    "sg:tags":[
        "agency",
        "bureau"
    ],
    "wof:name":"Wasatch Travel & Tours",
    "wof:placetype":"venue"
},
  "geometry": {"coordinates":[-111.834913,40.522795],"type":"Point"}
}