{
  "type": "Feature",
  "properties": {
    "iso:country":"US",
    "sg:address":"2493 S 1700 E",
    "sg:city":"Salt Lake City",
    "sg:classifiers":[
        {
            "category":"Professional",
            "subcategory":"Accounting & Tax Preparation",
            "type":"Services"
        }
    ],
    "sg:phone":"+1 801 463 1869",
    "sg:postcode":"84106",
    "sg:province":"UT",
    "wof:name":"Cls Unlimited",
    "wof:placetype":"venue"
},
  "geometry": {"coordinates":[-111.842035,40.718417],"type":"Point"}
}