{
  "type": "Feature",
  "properties": {
    "iso:country":"US",
    "sg:address":"1900 Canal Rd",
    "sg:city":"West Jordan",
    "sg:classifiers":[
        {
            "category":"Farming",
            "subcategory":"Farm",
            "type":"Manufacturing & Wholesale Goods"
        }
    ],
    "sg:phone":"+1 801 968 7497",
    "sg:postcode":"84084",
    "sg:province":"UT",
    "sg:tags":[
        "crop",
        "general"
    ],
    "wof:name":"Dale Steadman",
    "wof:placetype":"venue"
},
  "geometry": {"coordinates":[-111.947091,40.629008],"type":"Point"}
}