{
  "type": "Feature",
  "properties": {
    "iso:country":"US",
    "sg:address":"1225 N 900 E",
    "sg:city":"Bountiful",
    "sg:classifiers":[
        {
            "category":"Professional",
            "subcategory":"Business Services",
            "type":"Services"
        }
    ],
    "sg:phone":"+1 801 292 2152",
    "sg:postcode":"84010",
    "sg:province":"UT",
    "wof:name":"McQuiston Enterprises Inc",
    "wof:placetype":"venue"
},
  "geometry": {"coordinates":[-111.863685,40.902451],"type":"Point"}
}