{
  "type": "Feature",
  "properties": {
    "iso:country":"US",
    "sg:address":"101 Kokopelli Cir",
    "sg:city":"Springdale",
    "sg:classifiers":[
        {
            "category":"Professional",
            "subcategory":"Business Services",
            "type":"Services"
        }
    ],
    "sg:phone":"+1 435 772 3432",
    "sg:postcode":"84767",
    "sg:province":"UT",
    "wof:name":"Larry D West",
    "wof:placetype":"venue"
},
  "geometry": {"coordinates":[-112.99287099999999,37.191339],"type":"Point"}
}