{
  "type": "Feature",
  "properties": {
    "iso:country":"US",
    "sg:address":"816 W 150 S",
    "sg:city":"Clearfield",
    "sg:classifiers":[
        {
            "category":"Professional",
            "subcategory":"Management & Consulting",
            "type":"Services"
        }
    ],
    "sg:phone":"+1 801 779 4225",
    "sg:postcode":"84015",
    "sg:province":"UT",
    "sg:tags":[
        "business"
    ],
    "wof:name":"Jane DOE Consulting",
    "wof:placetype":"venue"
},
  "geometry": {"coordinates":[-112.043724,41.111773],"type":"Point"}
}