{
  "type": "Feature",
  "properties": {
    "iso:country":"US",
    "sg:address":"3550 Iowa Ave",
    "sg:city":"Ogden",
    "sg:classifiers":[
        {
            "category":"Manufacturing",
            "subcategory":"Furniture",
            "type":"Manufacturing & Wholesale Goods"
        }
    ],
    "sg:phone":"+1 801 940 6733",
    "sg:postcode":"84403",
    "sg:province":"UT",
    "sg:tags":[
        "wooden",
        "equipment",
        "computer",
        "mfg"
    ],
    "wof:name":"Hardware Haven Inc",
    "wof:placetype":"venue"
},
  "geometry": {"coordinates":[-111.947271,41.198479],"type":"Point"}
}