{
  "type": "Feature",
  "properties": {
    "iso:country":"US",
    "sg:address":"765 N 700 W",
    "sg:city":"North Salt Lake",
    "sg:classifiers":[
        {
            "category":"Building & Trades",
            "subcategory":"Landscaping Services",
            "type":"Services"
        }
    ],
    "sg:phone":"+1 801 260 1800",
    "sg:postcode":"84054",
    "sg:province":"UT",
    "sg:tags":[
        "architect",
        "landscape"
    ],
    "wof:name":"Suburban Property Maintenance and Landscaping",
    "wof:placetype":"venue"
},
  "geometry": {"coordinates":[-111.928012,40.852847],"type":"Point"}
}