{
  "type": "Feature",
  "properties": {
    "iso:country":"US",
    "sg:address":"1030 N 400 E",
    "sg:city":"North Salt Lake",
    "sg:classifiers":[
        {
            "category":"Travel",
            "subcategory":"Hotels & Motels",
            "type":"Entertainment"
        }
    ],
    "sg:phone":"+1 801 292 7666",
    "sg:postcode":"84054",
    "sg:province":"UT",
    "sg:website":"www.bwcottontreeinn.com/Saltlake...",
    "wof:name":"Best Western Cotton Tree Inn",
    "wof:placetype":"venue"
},
  "geometry": {"coordinates":[-111.902,40.859402],"type":"Point"}
}