{
  "type": "Feature",
  "properties": {
    "iso:country":"US",
    "sg:address":"13551 S 200 W",
    "sg:city":"Draper",
    "sg:classifiers":[
        {
            "category":"Restaurant",
            "type":"Food & Drink"
        }
    ],
    "sg:menulink":"http://www.allmenus.com/ut/salt-lake-city/116230-quiznos-sub/menu/",
    "sg:phone":"+1 801 545 0921",
    "sg:postcode":"84020",
    "sg:province":"UT",
    "sg:tags":[
        "wrap",
        "american",
        "sandwich"
    ],
    "wof:name":"Quiznos Sub",
    "wof:placetype":"venue"
},
  "geometry": {"coordinates":[-111.896428,40.505159],"type":"Point"}
}