{
  "type": "Feature",
  "properties": {
    "iso:country":"US",
    "sg:address":"55 W Main St",
    "sg:city":"Lehi",
    "sg:classifiers":[
        {
            "category":"Professional",
            "subcategory":"Accounting & Tax Preparation",
            "type":"Services"
        }
    ],
    "sg:phone":"+1 801 766 6049",
    "sg:postcode":"84043",
    "sg:province":"UT",
    "sg:tags":[
        "return",
        "filing"
    ],
    "wof:name":"Liberty Tax",
    "wof:placetype":"venue"
},
  "geometry": {"coordinates":[-111.85005099999999,40.387805],"type":"Point"}
}