{
  "type": "Feature",
  "properties": {
    "iso:country":"US",
    "sg:address":"514 N 300 W",
    "sg:city":"Kaysville",
    "sg:classifiers":[
        {
            "category":"Real Estate",
            "subcategory":"Real Estate Agent",
            "type":"Services"
        }
    ],
    "sg:phone":"+1 801 544 4231",
    "sg:postcode":"84037",
    "sg:province":"UT",
    "wof:name":"St Marks Garden",
    "wof:placetype":"venue"
},
  "geometry": {"coordinates":[-111.94381,41.041601],"type":"Point"}
}