{
  "type": "Feature",
  "properties": {
    "iso:country":"US",
    "sg:address":"196 W Main St",
    "sg:city":"Richmond",
    "sg:classifiers":[
        {
            "category":"Shopping",
            "subcategory":"Used Merchandise",
            "type":"Retail Goods"
        }
    ],
    "sg:phone":"+1 435 258 4422",
    "sg:postcode":"84333",
    "sg:province":"UT",
    "wof:name":"Old Depot",
    "wof:placetype":"venue"
},
  "geometry": {"coordinates":[-111.81375300000001,41.922771],"type":"Point"}
}