{
  "type": "Feature",
  "properties": {
    "iso:country":"US",
    "sg:address":"738 10th Ave",
    "sg:city":"Salt Lake City",
    "sg:classifiers":[
        {
            "category":"Professional",
            "subcategory":"Lawyer & Legal Services",
            "type":"Services"
        }
    ],
    "sg:phone":"+1 801 582 6495",
    "sg:postcode":"84103",
    "sg:province":"UT",
    "sg:tags":[
        "attorney"
    ],
    "wof:name":"H Dennis Piercey Attorney",
    "wof:placetype":"venue"
},
  "geometry": {"coordinates":[-111.868053,40.780679],"type":"Point"}
}