{
  "type": "Feature",
  "properties": {
    "iso:country":"US",
    "sg:address":"4325 Jupiter Dr",
    "sg:city":"Holladay",
    "sg:classifiers":[
        {
            "category":"Social Services",
            "subcategory":"Child Care",
            "type":"Services"
        }
    ],
    "sg:phone":"+1 801 424 0275",
    "sg:postcode":"84124",
    "sg:province":"UT",
    "sg:tags":[
        "kindergarten",
        "academic",
        "school",
        "day"
    ],
    "wof:name":"Montossori of Olympus Cove",
    "wof:placetype":"venue"
},
  "geometry": {"coordinates":[-111.79033200000001,40.677669],"type":"Point"}
}