{
  "type": "Feature",
  "properties": {
    "iso:country":"US",
    "sg:address":"8815 Harrison St",
    "sg:city":"Sandy",
    "sg:classifiers":[
        {
            "category":"Manufacturing",
            "subcategory":"Tools & Machinery",
            "type":"Manufacturing & Wholesale Goods"
        }
    ],
    "sg:phone":"+1 801 561 4200",
    "sg:postcode":"84070",
    "sg:province":"UT",
    "sg:tags":[
        "mfg",
        "equipment",
        "industrial",
        "professional"
    ],
    "wof:name":"Precision Laser Processing",
    "wof:placetype":"venue"
},
  "geometry": {"coordinates":[-111.90059599999999,40.591131],"type":"Point"}
}