{
  "type": "Feature",
  "properties": {
    "iso:country":"US",
    "sg:address":"7652 Holden St",
    "sg:city":"Midvale",
    "sg:classifiers":[
        {
            "category":"Home & Garden",
            "subcategory":"Furniture",
            "type":"Retail Goods"
        }
    ],
    "sg:phone":"+1 801 562 1933",
    "sg:postcode":"84047",
    "sg:province":"UT",
    "wof:name":"Black Goose Design",
    "wof:placetype":"venue"
},
  "geometry": {"coordinates":[-111.91246099999999,40.612275],"type":"Point"}
}