{
  "type": "Feature",
  "properties": {
    "iso:country":"US",
    "sg:address":"1680 Industrial Rd",
    "sg:city":"Salt Lake City",
    "sg:classifiers":[
        {
            "category":"Shopping",
            "subcategory":"Used Merchandise",
            "type":"Retail Goods"
        }
    ],
    "sg:phone":"+1 801 240 2580",
    "sg:postcode":"84104",
    "sg:province":"UT",
    "sg:tags":[
        "shop",
        "thrift"
    ],
    "wof:name":"Deseret Manufacturing",
    "wof:placetype":"venue"
},
  "geometry": {"coordinates":[-111.944822,40.73356],"type":"Point"}
}