{
  "type": "Feature",
  "properties": {
    "iso:country":"US",
    "sg:address":"175 N State St",
    "sg:city":"Lindon",
    "sg:classifiers":[
        {
            "category":"Professional",
            "subcategory":"Management & Consulting",
            "type":"Services"
        }
    ],
    "sg:phone":"+1 801 785 9777",
    "sg:postcode":"84042",
    "sg:province":"UT",
    "sg:tags":[
        "business"
    ],
    "sg:website":"www.somewhereinntime.com",
    "wof:name":"Somewhere Inn Time",
    "wof:placetype":"venue"
},
  "geometry": {"coordinates":[-111.719013,40.339974],"type":"Point"}
}