{
  "type": "Feature",
  "properties": {
    "iso:country":"US",
    "sg:address":"535 E 4500 S",
    "sg:city":"Salt Lake City",
    "sg:classifiers":[
        {
            "category":"Travel",
            "subcategory":"Travel Agent",
            "type":"Entertainment"
        }
    ],
    "sg:phone":"+1 801 266 2775",
    "sg:postcode":"84107",
    "sg:province":"UT",
    "sg:tags":[
        "agency",
        "bureau"
    ],
    "wof:name":"Thomas Travel",
    "wof:placetype":"venue"
},
  "geometry": {"coordinates":[-111.875373,40.674409],"type":"Point"}
}