{
  "type": "Feature",
  "properties": {
    "iso:country":"US",
    "sg:address":"1000 Newgate Mall",
    "sg:city":"Ogden",
    "sg:classifiers":[
        {
            "category":"Shopping",
            "type":"Retail Goods"
        }
    ],
    "sg:phone":"+1 801 392 0992",
    "sg:postcode":"84405",
    "sg:province":"UT",
    "sg:tags":[
        "merchandise"
    ],
    "wof:name":"Miracle-Ear",
    "wof:placetype":"venue"
},
  "geometry": {"coordinates":[-111.97716800000001,41.195505],"type":"Point"}
}