{
  "type": "Feature",
  "properties": {
    "iso:country":"US",
    "sg:address":"5210 S 1900 W",
    "sg:city":"Roy",
    "sg:classifiers":[
        {
            "category":"Manufacturing",
            "subcategory":"Apparel",
            "type":"Manufacturing & Wholesale Goods"
        }
    ],
    "sg:phone":"+1 801 773 2262",
    "sg:postcode":"84067",
    "sg:province":"UT",
    "sg:tags":[
        "personal",
        "dress",
        "mfg"
    ],
    "wof:name":"Bridal Satins Gowns & Tuxedos",
    "wof:placetype":"venue"
},
  "geometry": {"coordinates":[-112.025961,41.16828],"type":"Point"}
}