{
  "type": "Feature",
  "properties": {
    "iso:country":"US",
    "sg:address":"475 E Tabernacle St",
    "sg:city":"St George",
    "sg:classifiers":[
        {
            "category":"Health Services",
            "subcategory":"Clinic",
            "type":"Services"
        }
    ],
    "sg:phone":"+1 435 628 9015",
    "sg:postcode":"84770",
    "sg:province":"UT",
    "sg:tags":[
        "aids",
        "testing",
        "hearing"
    ],
    "wof:name":"Precision Hearing",
    "wof:placetype":"venue"
},
  "geometry": {"coordinates":[-113.57346,37.108261],"type":"Point"}
}