{
  "type": "Feature",
  "properties": {
    "iso:country":"US",
    "sg:address":"850 24th St",
    "sg:city":"Ogden",
    "sg:classifiers":[
        {
            "category":"Professional",
            "subcategory":"Engineering",
            "type":"Services"
        }
    ],
    "sg:phone":"+1 801 392 4211",
    "sg:postcode":"84401",
    "sg:province":"UT",
    "wof:name":"Love Engineering",
    "wof:placetype":"venue"
},
  "geometry": {"coordinates":[-111.95766999999999,41.222665],"type":"Point"}
}