{
  "type": "Feature",
  "properties": {
    "iso:country":"US",
    "sg:address":"528 W 300 N",
    "sg:city":"St George",
    "sg:classifiers":[
        {
            "category":"Wholesale",
            "subcategory":"Groceries",
            "type":"Manufacturing & Wholesale Goods"
        }
    ],
    "sg:phone":"+1 435 627 8464",
    "sg:postcode":"84770",
    "sg:province":"UT",
    "sg:tags":[
        "raw",
        "material",
        "natural"
    ],
    "wof:name":"Natural Styles",
    "wof:placetype":"venue"
},
  "geometry": {"coordinates":[-113.594296,37.113416],"type":"Point"}
}