{
  "type": "Feature",
  "properties": {
    "iso:country":"US",
    "sg:address":"1117 N 400 E",
    "sg:city":"North Salt Lake",
    "sg:phone":"+1 801 298 3252",
    "sg:postcode":"84054",
    "sg:province":"UT",
    "sg:tags":[
        "gas"
    ],
    "wof:name":"Jardine Petroleum Co",
    "wof:placetype":"venue"
},
  "geometry": {"coordinates":[-111.900318,40.861252],"type":"Point"}
}