{
  "type": "Feature",
  "properties": {
    "iso:country":"US",
    "sg:address":"165 W Canyon Crest Rd",
    "sg:city":"Alpine",
    "sg:classifiers":[
        {
            "category":"Banks & Credit Unions",
            "subcategory":"Bank",
            "type":"Services"
        }
    ],
    "sg:phone":"+1 801 763 8629",
    "sg:postcode":"84004",
    "sg:province":"UT",
    "sg:tags":[
        "personal",
        "financing",
        "institution"
    ],
    "wof:name":"Integrity Group",
    "wof:placetype":"venue"
},
  "geometry": {"coordinates":[-111.779301,40.44785],"type":"Point"}
}