{
  "type": "Feature",
  "properties": {
    "iso:country":"US",
    "sg:address":"360 N 1080 E",
    "sg:city":"Provo",
    "sg:classifiers":[
        {
            "category":"Retail",
            "subcategory":"Laundry & Dry Cleaning",
            "type":"Services"
        }
    ],
    "sg:phone":"+1 801 377 1576",
    "sg:postcode":"84606",
    "sg:province":"UT",
    "sg:tags":[
        "cleaners",
        "rug",
        "carpet"
    ],
    "wof:name":"Chem Clean",
    "wof:placetype":"venue"
},
  "geometry": {"coordinates":[-111.63991,40.237784],"type":"Point"}
}