{
  "type": "Feature",
  "properties": {
    "iso:country":"US",
    "sg:address":"266 W 100 N",
    "sg:city":"Vernal",
    "sg:classifiers":[
        {
            "category":"Health Services",
            "subcategory":"Chiropractor",
            "type":"Services"
        }
    ],
    "sg:phone":"+1 435 781 6035",
    "sg:postcode":"84078",
    "sg:province":"UT",
    "wof:name":"Travis Allan Chiropractor",
    "wof:placetype":"venue"
},
  "geometry": {"coordinates":[-109.533749,40.45716],"type":"Point"}
}