{
  "type": "Feature",
  "properties": {
    "iso:country":"US",
    "sg:address":"1625 S 900 W",
    "sg:city":"Salt Lake City",
    "sg:classifiers":[
        {
            "category":"Government",
            "subcategory":"Office",
            "type":"Public Place"
        }
    ],
    "sg:phone":"+1 801 977 6800",
    "sg:postcode":"84104",
    "sg:province":"UT",
    "sg:tags":[
        "state",
        "inspection"
    ],
    "sg:website":"www.abc.utah.gov",
    "wof:name":"Alcoholic Beverage Control",
    "wof:placetype":"venue"
},
  "geometry": {"coordinates":[-111.916729,40.732779],"type":"Point"}
}