{
  "type": "Feature",
  "properties": {
    "iso:country":"US",
    "sg:address":"8685 W 3500 S",
    "sg:city":"Magna",
    "sg:classifiers":[
        {
            "category":"Banks & Credit Unions",
            "subcategory":"Investment Brokerage",
            "type":"Services"
        }
    ],
    "sg:phone":"+1 435 843 9081",
    "sg:postcode":"84044",
    "sg:province":"UT",
    "sg:tags":[
        "security"
    ],
    "wof:name":"Chad Holman",
    "wof:placetype":"venue"
},
  "geometry": {"coordinates":[-112.098139,40.696442],"type":"Point"}
}