{
  "type": "Feature",
  "properties": {
    "iso:country":"US",
    "sg:address":"941 E 3300 S",
    "sg:city":"Salt Lake City",
    "sg:classifiers":[
        {
            "category":"Professional",
            "subcategory":"Accounting & Tax Preparation",
            "type":"Services"
        }
    ],
    "sg:phone":"+1 801 486 0096",
    "sg:postcode":"84106",
    "sg:province":"UT",
    "sg:tags":[
        "accountant"
    ],
    "wof:name":"Morison Andersen & Strong",
    "wof:placetype":"venue"
},
  "geometry": {"coordinates":[-111.865244,40.699961],"type":"Point"}
}