{
  "type": "Feature",
  "properties": {
    "iso:country":"US",
    "sg:address":"401 W Brigham Rd",
    "sg:city":"St George",
    "sg:classifiers":[
        {
            "category":"Government",
            "subcategory":"Office",
            "type":"Public Place"
        }
    ],
    "sg:phone":"+1 435 628 1311",
    "sg:postcode":"84790",
    "sg:province":"UT",
    "sg:tags":[
        "state",
        "program"
    ],
    "wof:name":"Transportation Dept",
    "wof:placetype":"venue"
},
  "geometry": {"coordinates":[-113.591572,37.060265],"type":"Point"}
}