{
  "type": "Feature",
  "properties": {
    "iso:country":"US",
    "sg:address":"1228 W 1200 N",
    "sg:city":"Orem",
    "sg:classifiers":[
        {
            "category":"Organizations",
            "subcategory":"Religious Organization",
            "type":"Services"
        }
    ],
    "sg:phone":"+1 801 764 9736",
    "sg:postcode":"84057",
    "sg:province":"UT",
    "sg:tags":[
        "church"
    ],
    "wof:name":"Calvary Chapel Of Utah Valley",
    "wof:placetype":"venue"
},
  "geometry": {"coordinates":[-111.72539500000001,40.319154],"type":"Point"}
}