{
  "type": "Feature",
  "properties": {
    "iso:country":"US",
    "sg:address":"1849 S Main St",
    "sg:city":"Orem",
    "sg:classifiers":[
        {
            "category":"Professional",
            "subcategory":"Business Services",
            "type":"Services"
        }
    ],
    "sg:phone":"+1 801 224 0201",
    "sg:postcode":"84058",
    "sg:province":"UT",
    "wof:name":"Lls Enterprises Inc",
    "wof:placetype":"venue"
},
  "geometry": {"coordinates":[-111.694812,40.26276],"type":"Point"}
}