{
  "type": "Feature",
  "properties": {
    "iso:country":"US",
    "sg:address":"490 N Main St",
    "sg:city":"Tooele",
    "sg:classifiers":[
        {
            "category":"Restaurant",
            "type":"Food & Drink"
        }
    ],
    "sg:phone":"+1 435 882 3608",
    "sg:postcode":"84074",
    "sg:province":"UT",
    "sg:tags":[
        "eating"
    ],
    "wof:name":"American Burgers",
    "wof:placetype":"venue"
},
  "geometry": {"coordinates":[-112.298394,40.538698],"type":"Point"}
}