{
  "type": "Feature",
  "properties": {
    "iso:country":"US",
    "sg:address":"4516 S 700 E",
    "sg:city":"Salt Lake City",
    "sg:classifiers":[
        {
            "category":"Banks & Credit Unions",
            "subcategory":"Bank",
            "type":"Services"
        }
    ],
    "sg:phone":"+1 801 484 5658",
    "sg:postcode":"84107",
    "sg:province":"UT",
    "sg:tags":[
        "loan",
        "real estate"
    ],
    "sg:website":"www.republic-mortgage.com",
    "wof:name":"Republic Mortgage",
    "wof:placetype":"venue"
},
  "geometry": {"coordinates":[-111.871438,40.67381],"type":"Point"}
}