{
  "type": "Feature",
  "properties": {
    "iso:country":"US",
    "sg:address":"2371 Dakota Ave",
    "sg:city":"Provo",
    "sg:classifiers":[
        {
            "category":"Building & Trades",
            "subcategory":"Plumbing",
            "type":"Services"
        }
    ],
    "sg:phone":"+1 801 818 0296",
    "sg:postcode":"84606",
    "sg:province":"UT",
    "sg:tags":[
        "contractor"
    ],
    "wof:name":"Jones Mechanical Inc",
    "wof:placetype":"venue"
},
  "geometry": {"coordinates":[-111.620518,40.20306],"type":"Point"}
}