{
  "type": "Feature",
  "properties": {
    "iso:country":"US",
    "sg:address":"6855 E 1900 N",
    "sg:city":"Croydon",
    "sg:classifiers":[
        {
            "category":"Building & Trades",
            "subcategory":"Construction",
            "type":"Services"
        }
    ],
    "sg:phone":"+1 801 829 3983",
    "sg:postcode":"84018",
    "sg:province":"UT",
    "sg:tags":[
        "contractor"
    ],
    "wof:name":"TNT Fence Inc",
    "wof:placetype":"venue"
},
  "geometry": {"coordinates":[-111.513493,41.068601],"type":"Point"}
}