{
  "type": "Feature",
  "properties": {
    "iso:country":"US",
    "sg:address":"1695 S State St",
    "sg:city":"Springville",
    "sg:classifiers":[
        {
            "category":"Restaurant",
            "type":"Food & Drink"
        }
    ],
    "sg:phone":"+1 801 489 7920",
    "sg:postcode":"84663",
    "sg:province":"UT",
    "wof:name":"T Bone Restaurant",
    "wof:placetype":"venue"
},
  "geometry": {"coordinates":[-111.602675,40.144742],"type":"Point"}
}