{
  "type": "Feature",
  "properties": {
    "iso:country":"US",
    "sg:address":"137 S Main St",
    "sg:city":"Kanab",
    "sg:classifiers":[
        {
            "category":"Cinema",
            "subcategory":"Movie Theater",
            "type":"Entertainment"
        }
    ],
    "sg:phone":"+1 435 644 2182",
    "sg:postcode":"84741",
    "sg:province":"UT",
    "sg:tags":[
        "motion",
        "picture"
    ],
    "wof:name":"Kanab Theater",
    "wof:placetype":"venue"
},
  "geometry": {"coordinates":[-112.528445,37.045767],"type":"Point"}
}