{
  "type": "Feature",
  "properties": {
    "iso:country":"US",
    "sg:address":"1645 State Hwy 193",
    "sg:city":"Layton",
    "sg:classifiers":[
        {
            "category":"Professional",
            "subcategory":"Accounting & Tax Preparation",
            "type":"Services"
        }
    ],
    "sg:phone":"+1 801 771 3600",
    "sg:postcode":"84040",
    "sg:province":"UT",
    "sg:tags":[
        "spa",
        "health",
        "processor"
    ],
    "wof:name":"National Fitness Fincl Systems",
    "wof:placetype":"venue"
},
  "geometry": {"coordinates":[-111.934528,41.101682],"type":"Point"}
}