{
  "type": "Feature",
  "properties": {
    "iso:country":"US",
    "sg:address":"1891 S 2300 E",
    "sg:city":"Salt Lake City",
    "sg:classifiers":[
        {
            "category":"Farming",
            "subcategory":"Livestock Farm",
            "type":"Manufacturing & Wholesale Goods"
        }
    ],
    "sg:phone":"+1 801 486 8814",
    "sg:postcode":"84108",
    "sg:province":"UT",
    "sg:tags":[
        "beef",
        "feedlot",
        "cattle"
    ],
    "wof:name":"Olsen Land & Grazing Inc",
    "wof:placetype":"venue"
},
  "geometry": {"coordinates":[-111.824991,40.728627],"type":"Point"}
}