{
  "type": "Feature",
  "properties": {
    "iso:country":"US",
    "sg:address":"11319 N 5830 W",
    "sg:city":"American Fork",
    "sg:classifiers":[
        {
            "category":"Professional",
            "subcategory":"Engineering",
            "type":"Services"
        }
    ],
    "sg:phone":"+1 801 492 0122",
    "sg:postcode":"84003",
    "sg:province":"UT",
    "sg:tags":[
        "engineer"
    ],
    "wof:name":"Lone Peak Labs Inc",
    "wof:placetype":"venue"
},
  "geometry": {"coordinates":[-111.79841999999999,40.437677],"type":"Point"}
}