{
  "type": "Feature",
  "properties": {
    "iso:country":"US",
    "sg:address":"4395 Windsor Dr",
    "sg:city":"Provo",
    "sg:classifiers":[
        {
            "category":"Manufacturing",
            "subcategory":"Printing",
            "type":"Manufacturing & Wholesale Goods"
        }
    ],
    "sg:phone":"+1 801 802 7888",
    "sg:postcode":"84604",
    "sg:province":"UT",
    "sg:tags":[
        "publisher"
    ],
    "wof:name":"Stylewriter Publications",
    "wof:placetype":"venue"
},
  "geometry": {"coordinates":[-111.637207,40.292956],"type":"Point"}
}