{
  "type": "Feature",
  "properties": {
    "iso:country":"US",
    "sg:address":"2650 S 300 W",
    "sg:city":"Salt Lake City",
    "sg:classifiers":[
        {
            "category":"Professional",
            "subcategory":"Business Services",
            "type":"Services"
        }
    ],
    "sg:phone":"+1 801 466 8585",
    "sg:postcode":"84115",
    "sg:province":"UT",
    "sg:tags":[
        "embroidery"
    ],
    "wof:name":"Image Tree",
    "wof:placetype":"venue"
},
  "geometry": {"coordinates":[-111.89975099999999,40.714756],"type":"Point"}
}