{
  "type": "Feature",
  "properties": {
    "iso:country":"US",
    "sg:address":"7730 Quicksilver Dr",
    "sg:city":"Salt Lake City",
    "sg:classifiers":[
        {
            "category":"Social Services",
            "type":"Services"
        }
    ],
    "sg:phone":"+1 801 942 5900",
    "sg:postcode":"84121",
    "sg:province":"UT",
    "wof:name":"Rebecca Good MA Rnc",
    "wof:placetype":"venue"
},
  "geometry": {"coordinates":[-111.78916099999999,40.611102],"type":"Point"}
}