{
  "type": "Feature",
  "properties": {
    "iso:country":"US",
    "sg:address":"109 S Starcrest Dr",
    "sg:city":"Orem",
    "sg:classifiers":[
        {
            "category":"Wholesale",
            "subcategory":"Toys & Hobbies",
            "type":"Manufacturing & Wholesale Goods"
        }
    ],
    "sg:phone":"+1 801 434 7453",
    "sg:postcode":"84058",
    "sg:province":"UT",
    "wof:name":"Boardgameratings Com",
    "wof:placetype":"venue"
},
  "geometry": {"coordinates":[-111.693251,40.275751],"type":"Point"}
}