{
  "type": "Feature",
  "properties": {
    "iso:country":"US",
    "sg:address":"5819 Main Point Blvd",
    "sg:city":"Ogden",
    "sg:classifiers":[
        {
            "category":"Wholesale",
            "subcategory":"Vending Machines",
            "type":"Manufacturing & Wholesale Goods"
        }
    ],
    "sg:phone":"+1 801 479 9219",
    "sg:postcode":"84405",
    "sg:province":"UT",
    "sg:tags":[
        "operator"
    ],
    "wof:name":"Munchems Vending Co",
    "wof:placetype":"venue"
},
  "geometry": {"coordinates":[-111.947366,41.157537],"type":"Point"}
}