{
  "type": "Feature",
  "properties": {
    "iso:country":"US",
    "sg:address":"1886 N 5900 W",
    "sg:city":"Ogden",
    "sg:classifiers":[
        {
            "category":"Real Estate",
            "subcategory":"Real Estate Operator",
            "type":"Services"
        }
    ],
    "sg:phone":"+1 801 731 0794",
    "sg:postcode":"84404",
    "sg:province":"UT",
    "sg:tags":[
        "building",
        "nonresidential"
    ],
    "wof:name":"Sdf Properties LLC",
    "wof:placetype":"venue"
},
  "geometry": {"coordinates":[-112.122473,41.285307],"type":"Point"}
}