{
  "type": "Feature",
  "properties": {
    "iso:country":"US",
    "sg:address":"321 Lawndale Dr",
    "sg:city":"Salt Lake City",
    "sg:classifiers":[
        {
            "category":"Food & Beverages",
            "subcategory":"Bakery",
            "type":"Retail Goods"
        }
    ],
    "sg:phone":"+1 801 463 2284",
    "sg:postcode":"84115",
    "sg:province":"UT",
    "sg:tags":[
        "cookie",
        "cracker"
    ],
    "wof:name":"Mrs Field's Original Cookies",
    "wof:placetype":"venue"
},
  "geometry": {"coordinates":[-111.90257,40.714196],"type":"Point"}
}