{
  "type": "Feature",
  "properties": {
    "iso:country":"US",
    "sg:address":"415 W Apple St",
    "sg:city":"Grantsville",
    "sg:classifiers":[
        {
            "category":"Organizations",
            "subcategory":"Religious Organization",
            "type":"Services"
        }
    ],
    "sg:phone":"+1 435 884 6472",
    "sg:postcode":"84029",
    "sg:province":"UT",
    "sg:tags":[
        "mormon",
        "church"
    ],
    "wof:name":"Grantsville West Seventh Ward",
    "wof:placetype":"venue"
},
  "geometry": {"coordinates":[-112.47829299999999,40.597677],"type":"Point"}
}