{
  "type": "Feature",
  "properties": {
    "iso:country":"US",
    "sg:address":"61 W 3900 S",
    "sg:city":"Salt Lake City",
    "sg:classifiers":[
        {
            "category":"Professional",
            "subcategory":"Management & Consulting",
            "type":"Services"
        }
    ],
    "sg:phone":"+1 801 265 1192",
    "sg:postcode":"84107",
    "sg:province":"UT",
    "wof:name":"Administrative Services",
    "wof:placetype":"venue"
},
  "geometry": {"coordinates":[-111.8925,40.686921],"type":"Point"}
}