{
  "type": "Feature",
  "properties": {
    "iso:country":"US",
    "sg:address":"125 S 2550 W",
    "sg:city":"Ogden",
    "sg:classifiers":[
        {
            "category":"Building & Trades",
            "subcategory":"Construction",
            "type":"Services"
        }
    ],
    "sg:phone":"+1 801 731 1952",
    "sg:postcode":"84404",
    "sg:province":"UT",
    "sg:tags":[
        "house"
    ],
    "wof:name":"Stark Construction Co",
    "wof:placetype":"venue"
},
  "geometry": {"coordinates":[-112.04102899999999,41.261947],"type":"Point"}
}