{
  "type": "Feature",
  "properties": {
    "iso:country":"US",
    "sg:address":"169 N 3rd E",
    "sg:city":"Logan",
    "sg:classifiers":[
        {
            "category":"Wholesale",
            "subcategory":"Hardware",
            "type":"Manufacturing & Wholesale Goods"
        }
    ],
    "sg:phone":"+1 435 752 1982",
    "sg:postcode":"84337",
    "sg:province":"UT",
    "sg:tags":[
        "refrigeration"
    ],
    "wof:name":"Valley Refrigeration",
    "wof:placetype":"venue"
},
  "geometry": {"coordinates":[-112.161863,41.713557],"type":"Point"}
}