{
  "type": "Feature",
  "properties": {
    "iso:country":"US",
    "sg:address":"1975 W 3500 S",
    "sg:city":"Salt Lake City",
    "sg:classifiers":[
        {
            "category":"Organizations",
            "subcategory":"Labor Organization",
            "type":"Services"
        }
    ],
    "sg:phone":"+1 801 977 0732",
    "sg:postcode":"84119",
    "sg:province":"UT",
    "wof:name":"Painters Local 77",
    "wof:placetype":"venue"
},
  "geometry": {"coordinates":[-111.947213,40.696657],"type":"Point"}
}