{
  "type": "Feature",
  "properties": {
    "iso:country":"US",
    "sg:address":"564 Mason Cir",
    "sg:city":"Roosevelt",
    "sg:classifiers":[
        {
            "category":"Autos & Motor Vehicles",
            "subcategory":"Auto Supplies",
            "type":"Retail Goods"
        }
    ],
    "sg:phone":"+1 435 722 5045",
    "sg:postcode":"84066",
    "sg:province":"UT",
    "wof:name":"Dan Karren",
    "wof:placetype":"venue"
},
  "geometry": {"coordinates":[-110.015541,40.305899],"type":"Point"}
}