{
  "type": "Feature",
  "properties": {
    "iso:country":"US",
    "sg:address":"10039 Rockview Cir",
    "sg:city":"Sandy",
    "sg:classifiers":[
        {
            "category":"Shopping",
            "subcategory":"Clothing, Apparel, & Fashions",
            "type":"Retail Goods"
        }
    ],
    "sg:phone":"+1 801 355 3133",
    "sg:postcode":"84092",
    "sg:province":"UT",
    "sg:tags":[
        "shorts",
        "sock",
        "boxer",
        "t",
        "tie",
        "dress"
    ],
    "wof:name":"Soc Shop",
    "wof:placetype":"venue"
},
  "geometry": {"coordinates":[-111.821743,40.56861],"type":"Point"}
}