{
  "type": "Feature",
  "properties": {
    "iso:country":"US",
    "sg:address":"410 Woodhill Rd",
    "sg:city":"Price",
    "sg:classifiers":[
        {
            "category":"Restaurant",
            "type":"Food & Drink"
        }
    ],
    "sg:phone":"+1 435 637 7711",
    "sg:postcode":"84501",
    "sg:province":"UT",
    "sg:tags":[
        "eating"
    ],
    "wof:name":"J BS Restaurant",
    "wof:placetype":"venue"
},
  "geometry": {"coordinates":[-110.82000600000001,39.614273],"type":"Point"}
}