{
  "type": "Feature",
  "properties": {
    "iso:country":"US",
    "sg:address":"793 W Salem Canal Rd",
    "sg:city":"Salem",
    "sg:classifiers":[
        {
            "category":"Farming",
            "subcategory":"Livestock Farm",
            "type":"Manufacturing & Wholesale Goods"
        }
    ],
    "sg:phone":"+1 801 465 3351",
    "sg:postcode":"84653",
    "sg:province":"UT",
    "sg:tags":[
        "animal",
        "general"
    ],
    "wof:name":"Dan Vacher",
    "wof:placetype":"venue"
},
  "geometry": {"coordinates":[-111.68666399999999,40.03875],"type":"Point"}
}