{
  "type": "Feature",
  "properties": {
    "iso:country":"US",
    "sg:address":"2186 Lincoln Ave",
    "sg:city":"Ogden",
    "sg:classifiers":[
        {
            "category":"Government",
            "subcategory":"Office",
            "type":"Public Place"
        }
    ],
    "sg:phone":"+1 801 629 8017",
    "sg:postcode":"84401",
    "sg:province":"UT",
    "wof:name":"Weber Area Consolidated Dsptch",
    "wof:placetype":"venue"
},
  "geometry": {"coordinates":[-111.975825,41.228842],"type":"Point"}
}