{
  "type": "Feature",
  "properties": {
    "iso:country":"US",
    "sg:address":"3871 W 5400 S",
    "sg:city":"Kearns",
    "sg:classifiers":[
        {
            "category":"Food & Beverages",
            "subcategory":"Groceries & Convenience Stores",
            "type":"Retail Goods"
        }
    ],
    "sg:phone":"+1 801 966 8298",
    "sg:postcode":"84118",
    "sg:province":"UT",
    "sg:tags":[
        "grocer"
    ],
    "sg:website":"www.albertsons.com",
    "wof:name":"Albertsons",
    "wof:placetype":"venue"
},
  "geometry": {"coordinates":[-111.98581299999999,40.652989],"type":"Point"}
}