{
  "type": "Feature",
  "properties": {
    "iso:country":"US",
    "sg:address":"2745 California Ave",
    "sg:city":"Salt Lake City",
    "sg:classifiers":[
        {
            "category":"Mining & Drilling",
            "type":"Manufacturing & Wholesale Goods"
        }
    ],
    "sg:phone":"+1 801 973 6667",
    "sg:postcode":"84104",
    "sg:province":"UT",
    "sg:tags":[
        "water",
        "metal",
        "well"
    ],
    "sg:website":"www.boartlongyear.com",
    "wof:name":"Lang Exploratory Drilling",
    "wof:placetype":"venue"
},
  "geometry": {"coordinates":[-111.962127,40.740339],"type":"Point"}
}