{
  "type": "Feature",
  "properties": {
    "iso:country":"US",
    "sg:address":"1917 Herbert Ave",
    "sg:city":"Salt Lake City",
    "sg:classifiers":[
        {
            "category":"Professional",
            "subcategory":"Detective & Security Services",
            "type":"Services"
        }
    ],
    "sg:phone":"+1 801 582 6289",
    "sg:postcode":"84108",
    "sg:province":"UT",
    "sg:tags":[
        "system"
    ],
    "wof:name":"Agutter Security",
    "wof:placetype":"venue"
},
  "geometry": {"coordinates":[-111.83380200000001,40.746127],"type":"Point"}
}