{
  "type": "Feature",
  "properties": {
    "iso:country":"US",
    "sg:address":"278 N Main St",
    "sg:city":"Tooele",
    "sg:classifiers":[
        {
            "category":"Autos & Motor Vehicles",
            "subcategory":"Auto Supplies",
            "type":"Retail Goods"
        }
    ],
    "sg:phone":"+1 435 882 6810",
    "sg:postcode":"84074",
    "sg:province":"UT",
    "sg:tags":[
        "automobile",
        "parts"
    ],
    "wof:name":"NAPA Auto Parts",
    "wof:placetype":"venue"
},
  "geometry": {"coordinates":[-112.29842499999999,40.536858],"type":"Point"}
}