{
  "type": "Feature",
  "properties": {
    "iso:country":"US",
    "sg:address":"1465 E 2100 S",
    "sg:city":"Salt Lake City",
    "sg:classifiers":[
        {
            "category":"Restaurant",
            "type":"Food & Drink"
        }
    ],
    "sg:phone":"+1 801 484 1351",
    "sg:postcode":"84105",
    "sg:province":"UT",
    "sg:tags":[
        "ice",
        "cream"
    ],
    "wof:name":"Baskin-Robbins",
    "wof:placetype":"venue"
},
  "geometry": {"coordinates":[-111.849473,40.725969],"type":"Point"}
}