{
  "type": "Feature",
  "properties": {
    "iso:country":"US",
    "sg:address":"101 N Commercial St",
    "sg:city":"Morgan",
    "sg:classifiers":[
        {
            "category":"Professional",
            "subcategory":"Management & Consulting",
            "type":"Services"
        }
    ],
    "sg:phone":"+1 801 829 3600",
    "sg:postcode":"84050",
    "sg:province":"UT",
    "sg:tags":[
        "business"
    ],
    "wof:name":"M A Associates",
    "wof:placetype":"venue"
},
  "geometry": {"coordinates":[-111.674004,41.045131],"type":"Point"}
}