{
  "type": "Feature",
  "properties": {
    "iso:country":"US",
    "sg:address":"214 S Main St",
    "sg:city":"Springville",
    "sg:classifiers":[
        {
            "category":"Shopping",
            "subcategory":"Pharmacy",
            "type":"Retail Goods"
        }
    ],
    "sg:phone":"+1 801 489 6041",
    "sg:postcode":"84663",
    "sg:province":"UT",
    "wof:name":"SOS Drug Store",
    "wof:placetype":"venue"
},
  "geometry": {"coordinates":[-111.61071699999999,40.162664],"type":"Point"}
}