{
  "type": "Feature",
  "properties": {
    "iso:country":"US",
    "sg:address":"451 S State St",
    "sg:city":"Salt Lake City",
    "sg:classifiers":[
        {
            "category":"Government",
            "subcategory":"Office",
            "type":"Public Place"
        }
    ],
    "sg:phone":"+1 801 535 7703",
    "sg:postcode":"84111",
    "sg:province":"UT",
    "sg:tags":[
        "development"
    ],
    "wof:name":"Salt Lake City Future Comm",
    "wof:placetype":"venue"
},
  "geometry": {"coordinates":[-111.888148,40.759588],"type":"Point"}
}