{
  "type": "Feature",
  "properties": {
    "iso:country":"US",
    "sg:address":"9910 N 4600 W",
    "sg:city":"Pleasant Grove",
    "sg:classifiers":[
        {
            "category":"Wholesale",
            "subcategory":"Home Furnishings",
            "type":"Manufacturing & Wholesale Goods"
        }
    ],
    "sg:phone":"+1 801 492 0552",
    "sg:postcode":"84062",
    "sg:province":"UT",
    "wof:name":"G C Creations",
    "wof:placetype":"venue"
},
  "geometry": {"coordinates":[-111.768505,40.413168],"type":"Point"}
}