{
  "type": "Feature",
  "properties": {
    "iso:country":"US",
    "sg:address":"1435 S 1350 E",
    "sg:city":"Clearfield",
    "sg:classifiers":[
        {
            "category":"Health Services",
            "subcategory":"Doctor",
            "type":"Services"
        }
    ],
    "sg:phone":"+1 801 774 6567",
    "sg:postcode":"84015",
    "sg:province":"UT",
    "wof:name":"Scott Carlton DDS",
    "wof:placetype":"venue"
},
  "geometry": {"coordinates":[-111.999707,41.092992],"type":"Point"}
}