{
  "type": "Feature",
  "properties": {
    "iso:country":"US",
    "sg:address":"207 E Broadway",
    "sg:city":"Salt Lake City",
    "sg:classifiers":[
        {
            "category":"Shopping",
            "subcategory":"Used Merchandise",
            "type":"Retail Goods"
        }
    ],
    "sg:phone":"+1 801 364 7979",
    "sg:postcode":"84111",
    "sg:province":"UT",
    "sg:tags":[
        "antique"
    ],
    "wof:name":"Retro Rose",
    "wof:placetype":"venue"
},
  "geometry": {"coordinates":[-111.88428399999999,40.762902],"type":"Point"}
}