{
  "type": "Feature",
  "properties": {
    "iso:country":"US",
    "sg:address":"149 N 1250 W",
    "sg:city":"Clearfield",
    "sg:classifiers":[
        {
            "category":"Communications",
            "type":"Services"
        }
    ],
    "sg:phone":"+1 801 728 4952",
    "sg:postcode":"84015",
    "sg:province":"UT",
    "wof:name":"Motorola Communications & Elct",
    "wof:placetype":"venue"
},
  "geometry": {"coordinates":[-112.050192,41.116034],"type":"Point"}
}