{
  "type": "Feature",
  "properties": {
    "iso:country":"US",
    "sg:address":"750 N Main St",
    "sg:city":"Logan",
    "sg:classifiers":[
        {
            "category":"Banks & Credit Unions",
            "subcategory":"Bank",
            "type":"Services"
        }
    ],
    "sg:phone":"+1 435 750 0303",
    "sg:postcode":"84321",
    "sg:province":"UT",
    "sg:tags":[
        "federal",
        "savings"
    ],
    "sg:website":"www.wamu.com",
    "wof:name":"Washington Mutual Bank",
    "wof:placetype":"venue"
},
  "geometry": {"coordinates":[-111.834575,41.744745],"type":"Point"}
}