{
  "type": "Feature",
  "properties": {
    "iso:country":"US",
    "sg:address":"7563 Main St",
    "sg:city":"Midvale",
    "sg:classifiers":[
        {
            "category":"Shopping",
            "type":"Retail Goods"
        }
    ],
    "sg:phone":"+1 801 569 1918",
    "sg:postcode":"84047",
    "sg:province":"UT",
    "sg:tags":[
        "product",
        "wood"
    ],
    "wof:name":"Utah Wood Care",
    "wof:placetype":"venue"
},
  "geometry": {"coordinates":[-111.91020899999999,40.613876],"type":"Point"}
}