{
  "type": "Feature",
  "properties": {
    "iso:country":"US",
    "sg:address":"528 Main St",
    "sg:city":"Park City",
    "sg:classifiers":[
        {
            "category":"Organizations",
            "subcategory":"Professional Association",
            "type":"Services"
        }
    ],
    "sg:phone":"+1 435 649 6104",
    "sg:postcode":"84060",
    "sg:province":"UT",
    "sg:tags":[
        "business"
    ],
    "wof:name":"Park City Chamber of Commerce",
    "wof:placetype":"venue"
},
  "geometry": {"coordinates":[-111.496934,40.645781],"type":"Point"}
}