{
  "type": "Feature",
  "properties": {
    "iso:country":"US",
    "sg:address":"352 Quince St",
    "sg:city":"Salt Lake City",
    "sg:classifiers":[
        {
            "category":"Organizations",
            "subcategory":"Non-profit Organization",
            "type":"Services"
        }
    ],
    "sg:phone":"+1 801 363 3066",
    "sg:postcode":"84103",
    "sg:province":"UT",
    "sg:website":"www.jamesbrownshow.com",
    "wof:name":"James Brown Show",
    "wof:placetype":"venue"
},
  "geometry": {"coordinates":[-111.895319,40.77597],"type":"Point"}
}