{
  "type": "Feature",
  "properties": {
    "iso:country":"US",
    "sg:address":"1358 Indiana Ave",
    "sg:city":"Salt Lake City",
    "sg:classifiers":[
        {
            "category":"Professional",
            "subcategory":"Computer Services",
            "type":"Services"
        }
    ],
    "sg:phone":"+1 801 596 1919",
    "sg:postcode":"84104",
    "sg:province":"UT",
    "sg:tags":[
        "information",
        "technology"
    ],
    "wof:name":"Utah Clean",
    "wof:placetype":"venue"
},
  "geometry": {"coordinates":[-111.929828,40.751339],"type":"Point"}
}