{
  "type": "Feature",
  "properties": {
    "iso:country":"US",
    "sg:address":"724 Front St",
    "sg:city":"Evanston",
    "sg:classifiers":[
        {
            "category":"Professional",
            "subcategory":"Accounting & Tax Preparation",
            "type":"Services"
        }
    ],
    "sg:phone":"+1 307 789 6222",
    "sg:postcode":"82930",
    "sg:province":"UT",
    "sg:tags":[
        "accountant"
    ],
    "wof:name":"Brent Liechty",
    "wof:placetype":"venue"
},
  "geometry": {"coordinates":[-110.962833,41.266802],"type":"Point"}
}