{
  "type": "Feature",
  "properties": {
    "iso:country":"US",
    "sg:address":"3495 W 3500 S",
    "sg:city":"West Valley",
    "sg:classifiers":[
        {
            "category":"Building & Trades",
            "subcategory":"Equipment Rental",
            "type":"Services"
        }
    ],
    "sg:phone":"+1 801 955 8800",
    "sg:postcode":"84119",
    "sg:province":"UT",
    "sg:tags":[
        "leasing",
        "furniture"
    ],
    "sg:website":"www.shopaarons.com",
    "wof:name":"Aaron's Rental Purchase",
    "wof:placetype":"venue"
},
  "geometry": {"coordinates":[-111.976108,40.696545],"type":"Point"}
}