{
  "type": "Feature",
  "properties": {
    "iso:country":"US",
    "sg:address":"4576 Monroe Blvd",
    "sg:city":"Ogden",
    "sg:classifiers":[
        {
            "category":"Building & Trades",
            "subcategory":"Construction",
            "type":"Services"
        }
    ],
    "sg:phone":"+1 801 479 9487",
    "sg:postcode":"84403",
    "sg:province":"UT",
    "sg:tags":[
        "house"
    ],
    "wof:name":"Extreme Construction Inc",
    "wof:placetype":"venue"
},
  "geometry": {"coordinates":[-111.958491,41.180871],"type":"Point"}
}