{
  "type": "Feature",
  "properties": {
    "iso:country":"US",
    "sg:address":"8090 S Bryce Dr",
    "sg:city":"Sandy",
    "sg:classifiers":[
        {
            "category":"Social Services",
            "type":"Services"
        }
    ],
    "sg:phone":"+1 801 561 8196",
    "sg:postcode":"84070",
    "sg:province":"UT",
    "wof:name":"Angies Angels",
    "wof:placetype":"venue"
},
  "geometry": {"coordinates":[-111.87841899999999,40.60414],"type":"Point"}
}