{
  "type": "Feature",
  "properties": {
    "iso:country":"US",
    "sg:address":"2475 Washington Blvd",
    "sg:city":"Ogden",
    "sg:classifiers":[
        {
            "category":"Banks & Credit Unions",
            "subcategory":"Financial Services",
            "type":"Services"
        }
    ],
    "sg:phone":"+1 801 395 9551",
    "sg:postcode":"84401",
    "sg:province":"UT",
    "sg:tags":[
        "investor"
    ],
    "wof:name":"Sidon Investments LLC",
    "wof:placetype":"venue"
},
  "geometry": {"coordinates":[-111.97053,41.222243],"type":"Point"}
}