{
  "type": "Feature",
  "properties": {
    "iso:country":"US",
    "sg:address":"505 Main St",
    "sg:city":"Park City",
    "sg:classifiers":[
        {
            "category":"Personal",
            "type":"Services"
        }
    ],
    "sg:phone":"+1 435 649 1233",
    "sg:postcode":"84060",
    "sg:province":"UT",
    "sg:tags":[
        "therapist",
        "massage"
    ],
    "wof:name":"Massage Professionals",
    "wof:placetype":"venue"
},
  "geometry": {"coordinates":[-111.496872,40.645679],"type":"Point"}
}