{
  "type": "Feature",
  "properties": {
    "iso:country":"US",
    "sg:address":"8169 S State St",
    "sg:city":"Midvale",
    "sg:classifiers":[
        {
            "category":"Retail",
            "subcategory":"Auto Repair",
            "type":"Services"
        }
    ],
    "sg:phone":"+1 801 562 1300",
    "sg:postcode":"84047",
    "sg:province":"UT",
    "sg:tags":[
        "repairing",
        "automobile"
    ],
    "wof:name":"Mr Clutch",
    "wof:placetype":"venue"
},
  "geometry": {"coordinates":[-111.890676,40.602863],"type":"Point"}
}