{
  "type": "Feature",
  "properties": {
    "iso:country":"US",
    "sg:address":"100 Church St",
    "sg:city":"Logan",
    "sg:classifiers":[
        {
            "category":"Professional",
            "subcategory":"Art Services",
            "type":"Services"
        }
    ],
    "sg:phone":"+1 435 753 0593",
    "sg:postcode":"84321",
    "sg:province":"UT",
    "sg:tags":[
        "graphic",
        "designer"
    ],
    "wof:name":"One Hundred Church St",
    "wof:placetype":"venue"
},
  "geometry": {"coordinates":[-111.833634,41.734139],"type":"Point"}
}