{
  "type": "Feature",
  "properties": {
    "iso:country":"US",
    "sg:address":"720 Guardsman Way",
    "sg:city":"Salt Lake City",
    "sg:classifiers":[
        {
            "category":"Education",
            "subcategory":"School",
            "type":"Public Place"
        }
    ],
    "sg:phone":"+1 801 355 7485",
    "sg:postcode":"84108",
    "sg:province":"UT",
    "sg:tags":[
        "private"
    ],
    "sg:website":"www.rowland-hall.org",
    "wof:name":"Rowland Hall - St Marks School",
    "wof:placetype":"venue"
},
  "geometry": {"coordinates":[-111.84540200000001,40.753123],"type":"Point"}
}