{
  "type": "Feature",
  "properties": {
    "iso:country":"US",
    "sg:address":"177 S Pioneer Cir",
    "sg:city":"Veyo",
    "sg:classifiers":[
        {
            "category":"Professional",
            "subcategory":"Management & Consulting",
            "type":"Services"
        }
    ],
    "sg:phone":"+1 435 574 3747",
    "sg:postcode":"84782",
    "sg:province":"UT",
    "sg:tags":[
        "consultant",
        "educational"
    ],
    "wof:name":"Donna Dillingham-Evans",
    "wof:placetype":"venue"
},
  "geometry": {"coordinates":[-113.661946,37.36687],"type":"Point"}
}