{
  "type": "Feature",
  "properties": {
    "iso:country":"US",
    "sg:address":"2266 E 170 N",
    "sg:city":"St George",
    "sg:classifiers":[
        {
            "category":"Shopping",
            "type":"Retail Goods"
        }
    ],
    "sg:phone":"+1 435 673 9147",
    "sg:postcode":"84790",
    "sg:province":"UT",
    "sg:tags":[
        "merchandise"
    ],
    "wof:name":"Hamps Custom Paintg",
    "wof:placetype":"venue"
},
  "geometry": {"coordinates":[-113.534916,37.111296],"type":"Point"}
}