{
  "type": "Feature",
  "properties": {
    "iso:country":"US",
    "sg:address":"845 S Main St Ste A1",
    "sg:city":"Bountiful",
    "sg:classifiers":[
        {
            "category":"Real Estate",
            "subcategory":"Architect",
            "type":"Services"
        }
    ],
    "sg:phone":"+1 801 298 5777",
    "sg:postcode":"84010",
    "sg:province":"UT",
    "wof:name":"Smith Hyatt Architects",
    "wof:placetype":"venue"
},
  "geometry": {"coordinates":[-111.881075,40.880188],"type":"Point"}
}