{
  "type": "Feature",
  "properties": {
    "iso:country":"US",
    "sg:address":"4241 Quarterhorse Ln",
    "sg:city":"Cedar City",
    "sg:classifiers":[
        {
            "category":"Building & Trades",
            "subcategory":"Construction",
            "type":"Services"
        }
    ],
    "sg:phone":"+1 435 867 4285",
    "sg:postcode":"84720",
    "sg:province":"UT",
    "sg:tags":[
        "carpentry",
        "contractor"
    ],
    "wof:name":"Renaissance Woodworking Inc",
    "wof:placetype":"venue"
},
  "geometry": {"coordinates":[-113.06325,37.754344],"type":"Point"}
}