{
  "type": "Feature",
  "properties": {
    "iso:country":"US",
    "sg:address":"738 S 1300 E",
    "sg:city":"Salt Lake City",
    "sg:classifiers":[
        {
            "category":"Professional",
            "subcategory":"Management & Consulting",
            "type":"Services"
        }
    ],
    "sg:phone":"+1 801 583 3674",
    "sg:postcode":"84102",
    "sg:province":"UT",
    "sg:tags":[
        "business"
    ],
    "wof:name":"Don Gren and Assoc",
    "wof:placetype":"venue"
},
  "geometry": {"coordinates":[-111.85396299999999,40.752813],"type":"Point"}
}