{
  "type": "Feature",
  "properties": {
    "iso:country":"US",
    "sg:address":"1915 Choctaw Ridge",
    "sg:city":"Ogden",
    "sg:classifiers":[
        {
            "category":"Wholesale",
            "subcategory":"Sporting Goods",
            "type":"Manufacturing & Wholesale Goods"
        }
    ],
    "sg:phone":"+1 801 479 0995",
    "sg:postcode":"84403",
    "sg:province":"UT",
    "sg:tags":[
        "st",
        "equipment",
        "representative",
        "mail",
        "ski",
        "manufacturer"
    ],
    "wof:name":"Bonnie and Hyde Inc",
    "wof:placetype":"venue"
},
  "geometry": {"coordinates":[-111.929433,41.166473],"type":"Point"}
}