{
  "type": "Feature",
  "properties": {
    "iso:country":"US",
    "sg:address":"8733 W 2700 S",
    "sg:city":"Magna",
    "sg:classifiers":[
        {
            "category":"Bars & Pubs",
            "type":"Food & Drink"
        }
    ],
    "sg:phone":"+1 801 250 5462",
    "sg:postcode":"84044",
    "sg:province":"UT",
    "wof:name":"Blue Moon",
    "wof:placetype":"venue"
},
  "geometry": {"coordinates":[-112.099707,40.711088],"type":"Point"}
}