{
  "type": "Feature",
  "properties": {
    "iso:country":"US",
    "sg:address":"2600 S Main St",
    "sg:city":"South Salt Lake",
    "sg:classifiers":[
        {
            "category":"Government",
            "subcategory":"Fire Station",
            "type":"Public Place"
        }
    ],
    "sg:phone":"+1 801 483 6043",
    "sg:postcode":"84115",
    "sg:province":"UT",
    "sg:tags":[
        "department",
        "protection"
    ],
    "sg:website":"www.southsaltlakecity.com",
    "wof:name":"South Salt Lake Fire Dept",
    "wof:placetype":"venue"
},
  "geometry": {"coordinates":[-111.891183,40.71373],"type":"Point"}
}