{
  "type": "Feature",
  "properties": {
    "iso:country":"US",
    "sg:address":"4819 N 2800 W",
    "sg:city":"Cedar City",
    "sg:classifiers":[
        {
            "category":"Utilities",
            "subcategory":"Water",
            "type":"Services"
        }
    ],
    "sg:phone":"+1 435 586 4611",
    "sg:postcode":"84720",
    "sg:province":"UT",
    "sg:tags":[
        "supply"
    ],
    "wof:name":"Midvalley Estates Water Co",
    "wof:placetype":"venue"
},
  "geometry": {"coordinates":[-113.103722,37.765257],"type":"Point"}
}