{
  "type": "Feature",
  "properties": {
    "iso:country":"US",
    "sg:address":"275 E 6100 S",
    "sg:city":"Murray",
    "sg:classifiers":[
        {
            "category":"Real Estate",
            "subcategory":"Real Estate Agent",
            "type":"Services"
        }
    ],
    "sg:phone":"+1 801 865 7665",
    "sg:postcode":"84107",
    "sg:province":"UT",
    "sg:tags":[
        "management"
    ],
    "wof:name":"Armstrong Property Management",
    "wof:placetype":"venue"
},
  "geometry": {"coordinates":[-111.88437500000001,40.638414],"type":"Point"}
}