{
  "type": "Feature",
  "properties": {
    "iso:country":"US",
    "sg:address":"1345 E 3900 S",
    "sg:city":"Holladay",
    "sg:classifiers":[
        {
            "category":"Health Services",
            "subcategory":"Doctor",
            "type":"Services"
        }
    ],
    "sg:phone":"+1 801 272 4466",
    "sg:postcode":"84124",
    "sg:province":"UT",
    "sg:tags":[
        "dentist"
    ],
    "wof:name":"Kent A Giauque DDS",
    "wof:placetype":"venue"
},
  "geometry": {"coordinates":[-111.852947,40.687152],"type":"Point"}
}