{
  "type": "Feature",
  "properties": {
    "iso:country":"US",
    "sg:address":"200 N Main St",
    "sg:city":"Layton",
    "sg:classifiers":[
        {
            "category":"Retail",
            "subcategory":"Auto Repair",
            "type":"Services"
        }
    ],
    "sg:phone":"+1 801 593 9200",
    "sg:postcode":"84041",
    "sg:province":"UT",
    "sg:tags":[
        "collision"
    ],
    "wof:name":"Carstar Layton Collision Inc",
    "wof:placetype":"venue"
},
  "geometry": {"coordinates":[-111.96892200000001,41.063417],"type":"Point"}
}