{
  "type": "Feature",
  "properties": {
    "iso:country":"US",
    "sg:address":"9315 S 700 E",
    "sg:city":"Sandy",
    "sg:classifiers":[
        {
            "category":"Autos & Motor Vehicles",
            "subcategory":"Auto Supplies",
            "type":"Retail Goods"
        }
    ],
    "sg:phone":"+1 801 566 5114",
    "sg:postcode":"84070",
    "sg:province":"UT",
    "sg:tags":[
        "automobile",
        "parts"
    ],
    "wof:name":"Bradshaw Federated Auto Parts",
    "wof:placetype":"venue"
},
  "geometry": {"coordinates":[-111.87212,40.58495],"type":"Point"}
}