{
  "type": "Feature",
  "properties": {
    "iso:country":"US",
    "sg:address":"24 W Main St",
    "sg:city":"Lehi",
    "sg:classifiers":[
        {
            "category":"Restaurant",
            "type":"Food & Drink"
        }
    ],
    "sg:menulink":"http://www.allmenus.com/ut/lehi/36030-porters-place/menu/",
    "sg:phone":"+1 801 768 8348",
    "sg:postcode":"84043",
    "sg:province":"UT",
    "sg:tags":[
        "american",
        "steakhouse"
    ],
    "wof:name":"Porter's Place",
    "wof:placetype":"venue"
},
  "geometry": {"coordinates":[-111.849604,40.387868],"type":"Point"}
}