{
  "type": "Feature",
  "properties": {
    "iso:country":"US",
    "sg:address":"380 S Orem Blvd",
    "sg:city":"Orem",
    "sg:classifiers":[
        {
            "category":"Autos & Motor Vehicles",
            "subcategory":"Automobile Sales",
            "type":"Retail Goods"
        }
    ],
    "sg:phone":"+1 801 434 7011",
    "sg:postcode":"84058",
    "sg:province":"UT",
    "sg:tags":[
        "car",
        "dealer"
    ],
    "wof:name":"Alpine Motor Sport",
    "wof:placetype":"venue"
},
  "geometry": {"coordinates":[-111.694884,40.291342],"type":"Point"}
}