{
  "type": "Feature",
  "properties": {
    "iso:country":"US",
    "sg:address":"180 N 1100 E St",
    "sg:city":"Washington",
    "sg:classifiers":[
        {
            "category":"Building & Trades",
            "subcategory":"Construction",
            "type":"Services"
        }
    ],
    "sg:phone":"+1 435 628 8392",
    "sg:postcode":"84780",
    "sg:province":"UT",
    "sg:tags":[
        "contractor"
    ],
    "wof:name":"Evans & Sons Drywall",
    "wof:placetype":"venue"
},
  "geometry": {"coordinates":[-113.490831,37.131182],"type":"Point"}
}