{
  "type": "Feature",
  "properties": {
    "iso:country":"US",
    "sg:address":"680 E 2620 N",
    "sg:city":"Provo",
    "sg:classifiers":[
        {
            "category":"Building & Trades",
            "subcategory":"Construction",
            "type":"Services"
        }
    ],
    "sg:phone":"+1 801 377 1923",
    "sg:postcode":"84604",
    "sg:province":"UT",
    "sg:tags":[
        "residential",
        "contractor"
    ],
    "wof:name":"Mountain View Development",
    "wof:placetype":"venue"
},
  "geometry": {"coordinates":[-111.647187,40.268252],"type":"Point"}
}