{
  "type": "Feature",
  "properties": {
    "iso:country":"US",
    "sg:address":"1901 E 2990 South St",
    "sg:city":"Salt Lake City",
    "sg:classifiers":[
        {
            "category":"Farming",
            "subcategory":"Farm & Veterinary Services",
            "type":"Manufacturing & Wholesale Goods"
        }
    ],
    "sg:phone":"+1 801 484 0287",
    "sg:postcode":"84106",
    "sg:province":"UT",
    "sg:tags":[
        "livestock"
    ],
    "wof:name":"Deans Limousins",
    "wof:placetype":"venue"
},
  "geometry": {"coordinates":[-111.837596,40.706161],"type":"Point"}
}