{
  "type": "Feature",
  "properties": {
    "iso:country":"US",
    "sg:address":"165 E 2700 S",
    "sg:city":"South Salt Lake",
    "sg:classifiers":[
        {
            "category":"Wholesale",
            "subcategory":"Home Furnishings",
            "type":"Manufacturing & Wholesale Goods"
        }
    ],
    "sg:phone":"+1 801 466 3901",
    "sg:postcode":"84115",
    "sg:province":"UT",
    "sg:tags":[
        "picture",
        "frame"
    ],
    "wof:name":"CMI Moulding",
    "wof:placetype":"venue"
},
  "geometry": {"coordinates":[-111.88601,40.712721],"type":"Point"}
}