{
  "type": "Feature",
  "properties": {
    "iso:country":"US",
    "sg:address":"458 E 1150 N",
    "sg:city":"Logan",
    "sg:classifiers":[
        {
            "category":"Professional",
            "subcategory":"Management & Consulting",
            "type":"Services"
        }
    ],
    "sg:phone":"+1 435 232 6101",
    "sg:postcode":"84341",
    "sg:province":"UT",
    "sg:tags":[
        "public",
        "relations"
    ],
    "wof:name":"American Poly Profiles",
    "wof:placetype":"venue"
},
  "geometry": {"coordinates":[-111.822546,41.752385],"type":"Point"}
}