{
  "type": "Feature",
  "properties": {
    "iso:country":"US",
    "sg:address":"319 W 100 S",
    "sg:city":"Vernal",
    "sg:classifiers":[
        {
            "category":"Insurance",
            "subcategory":"Insurance Agent",
            "type":"Services"
        }
    ],
    "sg:phone":"+1 435 781 1856",
    "sg:postcode":"84078",
    "sg:province":"UT",
    "wof:name":"Western Title Insurance Agency",
    "wof:placetype":"venue"
},
  "geometry": {"coordinates":[-109.534981,40.454136],"type":"Point"}
}