{
  "type": "Feature",
  "properties": {
    "iso:country":"US",
    "sg:address":"7070 S 2300 East St",
    "sg:city":"Salt Lake City",
    "sg:classifiers":[
        {
            "category":"Professional",
            "subcategory":"Business Services",
            "type":"Services"
        }
    ],
    "sg:phone":"+1 801 809 4279",
    "sg:postcode":"84121",
    "sg:province":"UT",
    "wof:name":"Bradford McDonald Group",
    "wof:placetype":"venue"
},
  "geometry": {"coordinates":[-111.824815,40.623362],"type":"Point"}
}