{
  "type": "Feature",
  "properties": {
    "iso:country":"US",
    "sg:address":"1394 N 1100 W",
    "sg:city":"Woods Cross",
    "sg:classifiers":[
        {
            "category":"Health Services",
            "subcategory":"Doctor",
            "type":"Services"
        }
    ],
    "sg:phone":"+1 801 397 0938",
    "sg:postcode":"84087",
    "sg:province":"UT",
    "sg:tags":[
        "medical"
    ],
    "wof:name":"Arock Surgeon Inc",
    "wof:placetype":"venue"
},
  "geometry": {"coordinates":[-111.911794,40.904112],"type":"Point"}
}