{
  "type": "Feature",
  "properties": {
    "iso:country":"US",
    "sg:address":"1427 N 1900 W",
    "sg:city":"Provo",
    "sg:classifiers":[
        {
            "category":"Real Estate",
            "subcategory":"Real Estate Agent",
            "type":"Services"
        }
    ],
    "sg:phone":"+1 801 373 4000",
    "sg:postcode":"84604",
    "sg:province":"UT",
    "sg:tags":[
        "management"
    ],
    "wof:name":"Halladay Property Mgmt Inc",
    "wof:placetype":"venue"
},
  "geometry": {"coordinates":[-111.691289,40.252759],"type":"Point"}
}