{
  "type": "Feature",
  "properties": {
    "iso:country":"US",
    "sg:address":"8664 Gravel Hills Dr",
    "sg:city":"Sandy",
    "sg:classifiers":[
        {
            "category":"Retail",
            "subcategory":"Portrait Studio",
            "type":"Services"
        }
    ],
    "sg:phone":"+1 801 566 9194",
    "sg:postcode":"84094",
    "sg:province":"UT",
    "sg:tags":[
        "photo"
    ],
    "sg:website":"www.gammell.com",
    "wof:name":"Gammell Photography",
    "wof:placetype":"venue"
},
  "geometry": {"coordinates":[-111.860547,40.593938],"type":"Point"}
}