{
  "type": "Feature",
  "properties": {
    "iso:country":"US",
    "sg:address":"354 E 300 S",
    "sg:city":"Hyrum",
    "sg:classifiers":[
        {
            "category":"Manufacturing",
            "subcategory":"Apparel",
            "type":"Manufacturing & Wholesale Goods"
        }
    ],
    "sg:phone":"+1 435 245 9697",
    "sg:postcode":"84319",
    "sg:province":"UT",
    "wof:name":"Quilt N Time",
    "wof:placetype":"venue"
},
  "geometry": {"coordinates":[-111.845626,41.62747],"type":"Point"}
}