{
  "type": "Feature",
  "properties": {
    "iso:country":"US",
    "sg:address":"957 N Main St",
    "sg:city":"Layton",
    "sg:classifiers":[
        {
            "category":"Shopping",
            "subcategory":"Discount & Variety Stores",
            "type":"Retail Goods"
        }
    ],
    "sg:phone":"+1 801 547 1505",
    "sg:postcode":"84041",
    "sg:province":"UT",
    "wof:name":"Honks 1 Dollar",
    "wof:placetype":"venue"
},
  "geometry": {"coordinates":[-111.97991399999999,41.073354],"type":"Point"}
}