{
  "type": "Feature",
  "properties": {
    "iso:country":"US",
    "sg:address":"4789 E River Rd",
    "sg:city":"Duchesne",
    "sg:phone":"+1 435 738 2608",
    "sg:postcode":"84021",
    "sg:province":"UT",
    "sg:tags":[
        "gas"
    ],
    "wof:name":"Big T Propane & Construction",
    "wof:placetype":"venue"
},
  "geometry": {"coordinates":[-110.390337,40.162905],"type":"Point"}
}