{
  "type": "Feature",
  "properties": {
    "iso:country":"US",
    "sg:address":"625 W 600 S",
    "sg:city":"Brigham City",
    "sg:classifiers":[
        {
            "category":"Organizations",
            "subcategory":"Professional Association",
            "type":"Services"
        }
    ],
    "sg:phone":"+1 435 723 3853",
    "sg:postcode":"84302",
    "sg:province":"UT",
    "wof:name":"American Assn Univ Women",
    "wof:placetype":"venue"
},
  "geometry": {"coordinates":[-112.026636,41.498453],"type":"Point"}
}