{
  "type": "Feature",
  "properties": {
    "iso:country":"US",
    "sg:address":"8682 Sandy Pkwy",
    "sg:city":"Sandy",
    "sg:classifiers":[
        {
            "category":"Building & Trades",
            "subcategory":"Pest Control",
            "type":"Services"
        }
    ],
    "sg:phone":"+1 801 255 4651",
    "sg:postcode":"84070",
    "sg:province":"UT",
    "wof:name":"South Salt Lake Cnty Mosquito",
    "wof:placetype":"venue"
},
  "geometry": {"coordinates":[-111.90512099999999,40.594485],"type":"Point"}
}