{
  "type": "Feature",
  "properties": {
    "iso:country":"US",
    "sg:address":"585 S Main St",
    "sg:city":"Layton",
    "sg:classifiers":[
        {
            "category":"Insurance",
            "subcategory":"Insurance Agent",
            "type":"Services"
        }
    ],
    "sg:phone":"+1 801 546 2626",
    "sg:postcode":"84041",
    "sg:province":"UT",
    "wof:name":"Allstate",
    "wof:placetype":"venue"
},
  "geometry": {"coordinates":[-111.959129,41.05171],"type":"Point"}
}