{
  "type": "Feature",
  "properties": {
    "iso:country":"US",
    "sg:address":"1656 W 2550 S",
    "sg:city":"Ogden",
    "sg:classifiers":[
        {
            "category":"Building & Trades",
            "subcategory":"Construction",
            "type":"Services"
        }
    ],
    "sg:phone":"+1 801 394 1661",
    "sg:postcode":"84401",
    "sg:province":"UT",
    "sg:tags":[
        "glass",
        "contractor"
    ],
    "wof:name":"Western Glass Inc",
    "wof:placetype":"venue"
},
  "geometry": {"coordinates":[-112.01903900000001,41.219688],"type":"Point"}
}