{
  "type": "Feature",
  "properties": {
    "iso:country":"US",
    "sg:address":"555 N 4500 W",
    "sg:city":"Clearfield",
    "sg:classifiers":[
        {
            "category":"Building & Trades",
            "subcategory":"Cleaning & Sanitation",
            "type":"Services"
        }
    ],
    "sg:phone":"+1 801 779 0874",
    "sg:postcode":"84015",
    "sg:province":"UT",
    "sg:tags":[
        "maintenance"
    ],
    "wof:name":"Vision Window Cleaning Service",
    "wof:placetype":"venue"
},
  "geometry": {"coordinates":[-112.11263700000001,41.125163],"type":"Point"}
}