{
  "type": "Feature",
  "properties": {
    "iso:country":"US",
    "sg:address":"8637 S 1700 E",
    "sg:city":"Sandy",
    "sg:classifiers":[
        {
            "category":"Freight",
            "type":"Transportation"
        }
    ],
    "sg:phone":"+1 801 255 8564",
    "sg:postcode":"84093",
    "sg:province":"UT",
    "sg:tags":[
        "operator",
        "trucking"
    ],
    "wof:name":"Todd Roper",
    "wof:placetype":"venue"
},
  "geometry": {"coordinates":[-111.843554,40.59466],"type":"Point"}
}