{
  "type": "Feature",
  "properties": {
    "iso:country":"US",
    "sg:address":"337 S 400 E",
    "sg:city":"Salt Lake City",
    "sg:classifiers":[
        {
            "category":"Shopping",
            "subcategory":"Computers & Home Electronics",
            "type":"Retail Goods"
        }
    ],
    "sg:phone":"+1 801 521 4040",
    "sg:postcode":"84111",
    "sg:province":"UT",
    "sg:tags":[
        "equipment",
        "dealer"
    ],
    "wof:name":"CODA Technologies",
    "wof:placetype":"venue"
},
  "geometry": {"coordinates":[-111.87956200000001,40.761453],"type":"Point"}
}