{
  "type": "Feature",
  "properties": {
    "iso:country":"US",
    "sg:address":"165 N 1330 W",
    "sg:city":"Orem",
    "sg:classifiers":[
        {
            "category":"Recreation",
            "type":"Entertainment"
        }
    ],
    "sg:phone":"+1 801 765 1123",
    "sg:postcode":"84057",
    "sg:province":"UT",
    "sg:tags":[
        "amusement"
    ],
    "wof:name":"Prodigy",
    "wof:placetype":"venue"
},
  "geometry": {"coordinates":[-111.727447,40.297143],"type":"Point"}
}