{
  "type": "Feature",
  "properties": {
    "iso:country":"US",
    "sg:address":"749 E 300 N",
    "sg:city":"Morgan",
    "sg:classifiers":[
        {
            "category":"Building & Trades",
            "subcategory":"Construction",
            "type":"Services"
        }
    ],
    "sg:phone":"+1 801 829 0600",
    "sg:postcode":"84050",
    "sg:province":"UT",
    "sg:tags":[
        "house"
    ],
    "wof:name":"Imn Construction Inc",
    "wof:placetype":"venue"
},
  "geometry": {"coordinates":[-111.672971,41.048144],"type":"Point"}
}