{
  "type": "Feature",
  "properties": {
    "iso:country":"US",
    "sg:address":"5757 W 2300 S",
    "sg:city":"Salt Lake City",
    "sg:classifiers":[
        {
            "category":"Wholesale",
            "subcategory":"Auto Parts",
            "type":"Manufacturing & Wholesale Goods"
        }
    ],
    "sg:phone":"+1 801 972 8926",
    "sg:postcode":"84128",
    "sg:province":"UT",
    "sg:tags":[
        "automobile",
        "rebuilt",
        "used",
        "retail"
    ],
    "wof:name":"Penguin Auto Wrecking Inc",
    "wof:placetype":"venue"
},
  "geometry": {"coordinates":[-112.027377,40.720227],"type":"Point"}
}