{
  "type": "Feature",
  "properties": {
    "iso:country":"US",
    "sg:address":"504 W 9460 S",
    "sg:city":"Sandy",
    "sg:classifiers":[
        {
            "category":"Building & Trades",
            "subcategory":"Construction",
            "type":"Services"
        }
    ],
    "sg:phone":"+1 801 304 5957",
    "sg:postcode":"84070",
    "sg:province":"UT",
    "sg:tags":[
        "tile",
        "dealer"
    ],
    "wof:name":"Milestone Tile & Marble",
    "wof:placetype":"venue"
},
  "geometry": {"coordinates":[-111.907364,40.579621],"type":"Point"}
}