{
  "type": "Feature",
  "properties": {
    "iso:country":"US",
    "sg:address":"7138 Highland Dr",
    "sg:city":"Salt Lake City",
    "sg:classifiers":[
        {
            "category":"Professional",
            "subcategory":"Accounting & Tax Preparation",
            "type":"Services"
        }
    ],
    "sg:phone":"+1 801 944 8767",
    "sg:postcode":"84121",
    "sg:province":"UT",
    "sg:tags":[
        "auditing",
        "freight"
    ],
    "wof:name":"Precision Data Link",
    "wof:placetype":"venue"
},
  "geometry": {"coordinates":[-111.83436,40.623057],"type":"Point"}
}