{
  "type": "Feature",
  "properties": {
    "iso:country":"US",
    "sg:address":"710 Stokes Ave",
    "sg:city":"Draper",
    "sg:classifiers":[
        {
            "category":"Farming",
            "subcategory":"Farm",
            "type":"Manufacturing & Wholesale Goods"
        }
    ],
    "sg:phone":"+1 801 495 1477",
    "sg:postcode":"84020",
    "sg:province":"UT",
    "sg:tags":[
        "crop",
        "general"
    ],
    "wof:name":"New Farms LLC",
    "wof:placetype":"venue"
},
  "geometry": {"coordinates":[-111.86956000000001,40.504439],"type":"Point"}
}