{
  "type": "Feature",
  "properties": {
    "iso:country":"US",
    "sg:address":"1225 E 200 S",
    "sg:city":"Mt Pleasant",
    "sg:classifiers":[
        {
            "category":"Professional",
            "subcategory":"Engineering",
            "type":"Services"
        }
    ],
    "sg:phone":"+1 435 462 9313",
    "sg:postcode":"84647",
    "sg:province":"UT",
    "sg:tags":[
        "engineer"
    ],
    "wof:name":"Pinnacle Engineering & Land",
    "wof:placetype":"venue"
},
  "geometry": {"coordinates":[-111.430041,39.543751],"type":"Point"}
}