{
  "type": "Feature",
  "properties": {
    "iso:country":"US",
    "sg:address":"2011 Flora Tech Rd",
    "sg:city":"Hurricane",
    "sg:classifiers":[
        {
            "category":"Government",
            "subcategory":"Office",
            "type":"Public Place"
        }
    ],
    "sg:phone":"+1 435 635 3899",
    "sg:postcode":"84737",
    "sg:province":"UT",
    "sg:tags":[
        "management"
    ],
    "wof:name":"Washington Co Water Dist",
    "wof:placetype":"venue"
},
  "geometry": {"coordinates":[-113.367093,37.13995],"type":"Point"}
}