{
  "type": "Feature",
  "properties": {
    "iso:country":"US",
    "sg:address":"284 E Main St",
    "sg:city":"Grantsville",
    "sg:classifiers":[
        {
            "category":"Building & Trades",
            "subcategory":"Plumbing",
            "type":"Services"
        }
    ],
    "sg:phone":"+1 801 860 4644",
    "sg:postcode":"84029",
    "sg:province":"UT",
    "sg:tags":[
        "contractor"
    ],
    "wof:name":"Debest Heating Air",
    "wof:placetype":"venue"
},
  "geometry": {"coordinates":[-112.453754,40.599694],"type":"Point"}
}