{
  "type": "Feature",
  "properties": {
    "iso:country":"US",
    "sg:address":"159 N 400 W",
    "sg:city":"Richfield",
    "sg:classifiers":[
        {
            "category":"Organizations",
            "subcategory":"Religious Organization",
            "type":"Services"
        }
    ],
    "sg:phone":"+1 435 896 5541",
    "sg:postcode":"84701",
    "sg:province":"UT",
    "sg:tags":[
        "church"
    ],
    "wof:name":"Church Of Jesus Christ Of Lds",
    "wof:placetype":"venue"
},
  "geometry": {"coordinates":[-112.09198000000001,38.77004],"type":"Point"}
}