{
  "type": "Feature",
  "properties": {
    "iso:country":"US",
    "sg:address":"2090 S Hwy 89",
    "sg:city":"Brigham City",
    "sg:classifiers":[
        {
            "category":"Autos & Motor Vehicles",
            "subcategory":"Automobile Sales",
            "type":"Retail Goods"
        },
        {
            "category":"Wholesale",
            "subcategory":"Motor Vehicles",
            "type":"Manufacturing & Wholesale Goods"
        }
    ],
    "sg:phone":"+1 435 723 9428",
    "sg:postcode":"84302",
    "sg:province":"UT",
    "sg:tags":[
        "car",
        "dealer"
    ],
    "wof:name":"Bryce's Truck Sales",
    "wof:placetype":"venue"
},
  "geometry": {"coordinates":[-112.02792100000001,41.471847],"type":"Point"}
}