{
  "type": "Feature",
  "properties": {
    "iso:country":"US",
    "sg:address":"854 E 3750 N",
    "sg:city":"Provo",
    "sg:classifiers":[
        {
            "category":"Health Services",
            "subcategory":"Podiatrist",
            "type":"Services"
        }
    ],
    "sg:phone":"+1 801 225 3095",
    "sg:postcode":"84604",
    "sg:province":"UT",
    "wof:name":"Scott Humpherys DPM Inc",
    "wof:placetype":"venue"
},
  "geometry": {"coordinates":[-111.64415700000001,40.283324],"type":"Point"}
}