{
  "type": "Feature",
  "properties": {
    "iso:country":"US",
    "sg:address":"760 E Main St",
    "sg:city":"Lehi",
    "sg:classifiers":[
        {
            "category":"Banks & Credit Unions",
            "subcategory":"Bank",
            "type":"Services"
        }
    ],
    "sg:phone":"+1 801 342 2274",
    "sg:postcode":"84043",
    "sg:province":"UT",
    "wof:name":"Wells Fargo Bank",
    "wof:placetype":"venue"
},
  "geometry": {"coordinates":[-111.839084,40.388072],"type":"Point"}
}