{
  "type": "Feature",
  "properties": {
    "iso:country":"US",
    "sg:address":"1360 E 2100 N",
    "sg:city":"Logan",
    "sg:classifiers":[
        {
            "category":"Insurance",
            "subcategory":"Insurance Agent",
            "type":"Services"
        }
    ],
    "sg:phone":"+1 435 752 9191",
    "sg:postcode":"84341",
    "sg:province":"UT",
    "wof:name":"New York Life Insurance Co",
    "wof:placetype":"venue"
},
  "geometry": {"coordinates":[-111.800472,41.769249],"type":"Point"}
}