{
  "type": "Feature",
  "properties": {
    "iso:country":"US",
    "sg:address":"1231 E 300 S",
    "sg:city":"Salt Lake City",
    "sg:classifiers":[
        {
            "category":"Real Estate",
            "subcategory":"Real Estate Operator",
            "type":"Services"
        }
    ],
    "sg:phone":"+1 801 583 5880",
    "sg:postcode":"84102",
    "sg:province":"UT",
    "sg:tags":[
        "building",
        "apartment"
    ],
    "wof:name":"Dixie Whitaker",
    "wof:placetype":"venue"
},
  "geometry": {"coordinates":[-111.85623,40.762906],"type":"Point"}
}