{
  "type": "Feature",
  "properties": {
    "iso:country":"US",
    "sg:address":"2550 Dry Creek Dr",
    "sg:city":"Riverton",
    "sg:classifiers":[
        {
            "category":"Building & Trades",
            "subcategory":"Cleaning & Sanitation",
            "type":"Services"
        }
    ],
    "sg:phone":"+1 801 201 3894",
    "sg:postcode":"84065",
    "sg:province":"UT",
    "sg:tags":[
        "maintenance"
    ],
    "wof:name":"Fine Details",
    "wof:placetype":"venue"
},
  "geometry": {"coordinates":[-111.95452400000001,40.519127],"type":"Point"}
}