{
  "type": "Feature",
  "properties": {
    "iso:country":"US",
    "sg:address":"5084 Jedediah Dr",
    "sg:city":"Salt Lake City",
    "sg:classifiers":[
        {
            "category":"Professional",
            "type":"Services"
        }
    ],
    "sg:phone":"+1 801 967 6129",
    "sg:postcode":"84118",
    "sg:province":"UT",
    "wof:name":"John F Visser",
    "wof:placetype":"venue"
},
  "geometry": {"coordinates":[-112.015666,40.658852],"type":"Point"}
}