{
  "type": "Feature",
  "properties": {
    "iso:country":"US",
    "sg:address":"8521 S State St",
    "sg:city":"Sandy",
    "sg:classifiers":[
        {
            "category":"Retail",
            "subcategory":"Repair Shop",
            "type":"Services"
        }
    ],
    "sg:phone":"+1 801 566 0322",
    "sg:postcode":"84070",
    "sg:province":"UT",
    "sg:tags":[
        "lock",
        "locksmith"
    ],
    "wof:name":"Tod's Lock & Key",
    "wof:placetype":"venue"
},
  "geometry": {"coordinates":[-111.890733,40.597506],"type":"Point"}
}