{
  "type": "Feature",
  "properties": {
    "iso:country":"US",
    "sg:address":"1760 S 1100 E",
    "sg:city":"Salt Lake City",
    "sg:classifiers":[
        {
            "category":"Insurance",
            "subcategory":"Insurance Agent",
            "type":"Services"
        }
    ],
    "sg:phone":"+1 801 487 1788",
    "sg:postcode":"84105",
    "sg:province":"UT",
    "wof:name":"Cayias Insurance",
    "wof:placetype":"venue"
},
  "geometry": {"coordinates":[-111.85953000000001,40.732335],"type":"Point"}
}