{
  "type": "Feature",
  "properties": {
    "iso:country":"US",
    "sg:address":"2343 Paul Cir",
    "sg:city":"Salt Lake City",
    "sg:classifiers":[
        {
            "category":"Retail",
            "subcategory":"Auto Repair",
            "type":"Services"
        }
    ],
    "sg:phone":"+1 801 560 2728",
    "sg:postcode":"84118",
    "sg:province":"UT",
    "sg:tags":[
        "automotive"
    ],
    "wof:name":"Jardine Services",
    "wof:placetype":"venue"
},
  "geometry": {"coordinates":[-111.95116299999999,40.639348],"type":"Point"}
}