{
  "type": "Feature",
  "properties": {
    "iso:country":"US",
    "sg:address":"44 W 2400 N",
    "sg:city":"Clearfield",
    "sg:classifiers":[
        {
            "category":"Wholesale",
            "subcategory":"Auto Parts",
            "type":"Manufacturing & Wholesale Goods"
        }
    ],
    "sg:phone":"+1 801 773 6641",
    "sg:postcode":"84015",
    "sg:province":"UT",
    "wof:name":"Fuel Air & Spark Technology",
    "wof:placetype":"venue"
},
  "geometry": {"coordinates":[-112.02898399999999,41.148707],"type":"Point"}
}