{
  "type": "Feature",
  "properties": {
    "iso:country":"US",
    "sg:address":"106 W Main St",
    "sg:city":"Mt Pleasant",
    "sg:classifiers":[
        {
            "category":"Banks & Credit Unions",
            "subcategory":"Bank",
            "type":"Services"
        }
    ],
    "sg:phone":"+1 435 462 2473",
    "sg:postcode":"84647",
    "sg:province":"UT",
    "wof:name":"Wells Fargo Bank",
    "wof:placetype":"venue"
},
  "geometry": {"coordinates":[-111.459057,39.546869],"type":"Point"}
}