{
  "type": "Feature",
  "properties": {
    "iso:country":"US",
    "sg:address":"9769 S 700 E",
    "sg:city":"Sandy",
    "sg:classifiers":[
        {
            "category":"Food & Beverages",
            "subcategory":"Groceries & Convenience Stores",
            "type":"Retail Goods"
        }
    ],
    "sg:phone":"+1 801 571 5051",
    "sg:postcode":"84070",
    "sg:province":"UT",
    "wof:name":"7-Eleven",
    "wof:placetype":"venue"
},
  "geometry": {"coordinates":[-111.872112,40.575204],"type":"Point"}
}