{
  "type": "Feature",
  "properties": {
    "iso:country":"US",
    "sg:address":"965 Bradsley Pl",
    "sg:city":"Salt Lake City",
    "sg:classifiers":[
        {
            "category":"Wholesale",
            "subcategory":"Books, Periodicals, & Newspapers",
            "type":"Manufacturing & Wholesale Goods"
        }
    ],
    "sg:phone":"+1 801 972 5454",
    "sg:postcode":"84119",
    "sg:province":"UT",
    "sg:tags":[
        "magazine"
    ],
    "sg:website":"www.andersonnews.com",
    "wof:name":"Anderson News Co",
    "wof:placetype":"venue"
},
  "geometry": {"coordinates":[-111.918035,40.716905],"type":"Point"}
}