{
  "type": "Feature",
  "properties": {
    "iso:country":"US",
    "sg:address":"233 W 4800 S",
    "sg:city":"Murray",
    "sg:classifiers":[
        {
            "category":"Wholesale",
            "subcategory":"Auto Parts",
            "type":"Manufacturing & Wholesale Goods"
        }
    ],
    "sg:phone":"+1 801 269 0757",
    "sg:postcode":"84107",
    "sg:province":"UT",
    "sg:tags":[
        "shaft",
        "drive"
    ],
    "wof:name":"Drive Shafts Utah Inc",
    "wof:placetype":"venue"
},
  "geometry": {"coordinates":[-111.897621,40.667327],"type":"Point"}
}