{
  "type": "Feature",
  "properties": {
    "iso:country":"US",
    "sg:address":"9016 S 1300 E",
    "sg:city":"Sandy",
    "sg:classifiers":[
        {
            "category":"Banks & Credit Unions",
            "subcategory":"Bank",
            "type":"Services"
        }
    ],
    "sg:phone":"+1 801 255 5932",
    "sg:postcode":"84094",
    "sg:province":"UT",
    "sg:tags":[
        "short",
        "b",
        "institution",
        "business",
        "nonresidential"
    ],
    "wof:name":"Insurance Factoring Services",
    "wof:placetype":"venue"
},
  "geometry": {"coordinates":[-111.85326499999999,40.587232],"type":"Point"}
}