{
  "type": "Feature",
  "properties": {
    "iso:country":"US",
    "sg:address":"162 W 200 S",
    "sg:city":"Panguitch",
    "sg:classifiers":[
        {
            "category":"Wholesale",
            "subcategory":"Machinery & Supplies",
            "type":"Manufacturing & Wholesale Goods"
        }
    ],
    "sg:phone":"+1 435 676 8990",
    "sg:postcode":"84759",
    "sg:province":"UT",
    "sg:tags":[
        "equipment"
    ],
    "wof:name":"Ken Ren Construction Co",
    "wof:placetype":"venue"
},
  "geometry": {"coordinates":[-112.440027,37.819673],"type":"Point"}
}