{
  "type": "Feature",
  "properties": {
    "iso:country":"US",
    "sg:address":"2516 E Keddington Ln",
    "sg:city":"Salt Lake City",
    "sg:classifiers":[
        {
            "category":"Professional",
            "subcategory":"Art Services",
            "type":"Services"
        }
    ],
    "sg:phone":"+1 801 278 5693",
    "sg:postcode":"84117",
    "sg:province":"UT",
    "sg:tags":[
        "commercial",
        "design"
    ],
    "wof:name":"History Projects Inc",
    "wof:placetype":"venue"
},
  "geometry": {"coordinates":[-111.817825,40.671868],"type":"Point"}
}