{
  "type": "Feature",
  "properties": {
    "iso:country":"US",
    "sg:address":"1895 W 5200 S",
    "sg:city":"Stockton",
    "sg:classifiers":[
        {
            "category":"Shopping",
            "subcategory":"Clothing, Apparel, & Fashions",
            "type":"Retail Goods"
        }
    ],
    "sg:phone":"+1 435 882 5108",
    "sg:postcode":"84067",
    "sg:province":"UT",
    "sg:tags":[
        "dressmaker"
    ],
    "wof:name":"Heirloom Closet",
    "wof:placetype":"venue"
},
  "geometry": {"coordinates":[-112.024531,41.169264],"type":"Point"}
}