{
  "type": "Feature",
  "properties": {
    "iso:country":"US",
    "sg:address":"465 N 1030 W",
    "sg:city":"Lindon",
    "sg:classifiers":[
        {
            "category":"Retail",
            "subcategory":"Auto Repair",
            "type":"Services"
        }
    ],
    "sg:phone":"+1 801 785 4477",
    "sg:postcode":"84042",
    "sg:province":"UT",
    "sg:tags":[
        "body",
        "automobile",
        "painting"
    ],
    "wof:name":"Lindon Collision Repair",
    "wof:placetype":"venue"
},
  "geometry": {"coordinates":[-111.741511,40.34618],"type":"Point"}
}