{
  "type": "Feature",
  "properties": {
    "iso:country":"US",
    "sg:address":"1449 N Angel St",
    "sg:city":"Layton",
    "sg:classifiers":[
        {
            "category":"Autos & Motor Vehicles",
            "subcategory":"Automobile Sales",
            "type":"Retail Goods"
        }
    ],
    "sg:phone":"+1 801 593 8405",
    "sg:postcode":"84041",
    "sg:province":"UT",
    "sg:tags":[
        "car",
        "dealer"
    ],
    "wof:name":"Cobalt Motor Sports",
    "wof:placetype":"venue"
},
  "geometry": {"coordinates":[-111.987877,41.080772],"type":"Point"}
}