{
  "type": "Feature",
  "properties": {
    "iso:country":"US",
    "sg:address":"1096 S 920 W",
    "sg:city":"Hurricane",
    "sg:classifiers":[
        {
            "category":"Health Services",
            "subcategory":"Medical Lab",
            "type":"Services"
        }
    ],
    "sg:phone":"+1 435 635 4591",
    "sg:postcode":"84737",
    "sg:province":"UT",
    "sg:tags":[
        "laboratory",
        "dental"
    ],
    "wof:name":"Silver State Dental Lab Inc",
    "wof:placetype":"venue"
},
  "geometry": {"coordinates":[-113.305505,37.159281],"type":"Point"}
}