{
  "type": "Feature",
  "properties": {
    "iso:country":"US",
    "sg:address":"11757 S 700 E",
    "sg:city":"Draper",
    "sg:classifiers":[
        {
            "category":"Retail",
            "subcategory":"Animal Services",
            "type":"Services"
        }
    ],
    "sg:phone":"+1 801 571 3664",
    "sg:postcode":"84020",
    "sg:province":"UT",
    "sg:tags":[
        "pet",
        "boarding",
        "sitting"
    ],
    "wof:name":"Home Sweet Kennels",
    "wof:placetype":"venue"
},
  "geometry": {"coordinates":[-111.87105200000001,40.538406],"type":"Point"}
}