{
  "type": "Feature",
  "properties": {
    "iso:country":"US",
    "sg:address":"2032 Highland Springs Rd",
    "sg:city":"Ogden",
    "sg:classifiers":[
        {
            "category":"Shopping",
            "subcategory":"Used Merchandise",
            "type":"Retail Goods"
        }
    ],
    "sg:phone":"+1 801 476 6908",
    "sg:postcode":"84403",
    "sg:province":"UT",
    "wof:name":"B & R Antiques & Collectable",
    "wof:placetype":"venue"
},
  "geometry": {"coordinates":[-111.932337,41.154505],"type":"Point"}
}