{
  "type": "Feature",
  "properties": {
    "iso:country":"US",
    "sg:address":"445 S 200 W",
    "sg:city":"Heber City",
    "sg:classifiers":[
        {
            "category":"Building & Trades",
            "subcategory":"Construction",
            "type":"Services"
        }
    ],
    "sg:phone":"+1 435 654 2261",
    "sg:postcode":"84032",
    "sg:province":"UT",
    "sg:tags":[
        "residential"
    ],
    "wof:name":"G N K Construction",
    "wof:placetype":"venue"
},
  "geometry": {"coordinates":[-111.416963,40.502097],"type":"Point"}
}