{
  "type": "Feature",
  "properties": {
    "iso:country":"US",
    "sg:address":"3722 E 4100 N",
    "sg:city":"Eden",
    "sg:classifiers":[
        {
            "category":"Utilities",
            "subcategory":"Water",
            "type":"Services"
        }
    ],
    "sg:phone":"+1 801 745 3856",
    "sg:postcode":"84310",
    "sg:province":"UT",
    "sg:tags":[
        "supply"
    ],
    "wof:name":"Liberty Pipeline Co",
    "wof:placetype":"venue"
},
  "geometry": {"coordinates":[-111.863045,41.333549],"type":"Point"}
}