{
  "type": "Feature",
  "properties": {
    "iso:country":"US",
    "sg:address":"1275 W 2320 S",
    "sg:city":"Salt Lake City",
    "sg:classifiers":[
        {
            "category":"Social Services",
            "subcategory":"Adult Care",
            "type":"Services"
        }
    ],
    "sg:phone":"+1 801 977 9779",
    "sg:postcode":"84119",
    "sg:province":"UT",
    "sg:tags":[
        "residential"
    ],
    "wof:name":"Work Activity Center Inc",
    "wof:placetype":"venue"
},
  "geometry": {"coordinates":[-111.92845699999999,40.72074],"type":"Point"}
}