{
  "type": "Feature",
  "properties": {
    "iso:country":"US",
    "sg:address":"1600 S 4650 W",
    "sg:city":"Salt Lake City",
    "sg:classifiers":[
        {
            "category":"Sports & Exercise",
            "subcategory":"Race Track",
            "type":"Entertainment"
        }
    ],
    "sg:phone":"+1 801 973 4735",
    "sg:postcode":"84104",
    "sg:province":"UT",
    "sg:tags":[
        "indoor",
        "racing"
    ],
    "wof:name":"Nascart Indoor Speedway Inc",
    "wof:placetype":"venue"
},
  "geometry": {"coordinates":[-112.00238,40.733133],"type":"Point"}
}