{
  "type": "Feature",
  "properties": {
    "iso:country":"US",
    "sg:address":"277 S 1000 E",
    "sg:city":"St George",
    "sg:classifiers":[
        {
            "category":"Real Estate",
            "subcategory":"Real Estate Agent",
            "type":"Services"
        }
    ],
    "sg:phone":"+1 435 656 9013",
    "sg:postcode":"84770",
    "sg:province":"UT",
    "sg:tags":[
        "manages",
        "apartment",
        "complex"
    ],
    "wof:name":"Bridge Property Management LLC",
    "wof:placetype":"venue"
},
  "geometry": {"coordinates":[-113.562074,37.103431],"type":"Point"}
}