{
  "type": "Feature",
  "properties": {
    "iso:country":"US",
    "sg:address":"3463 Airport Rd",
    "sg:city":"Ogden",
    "sg:classifiers":[
        {
            "category":"Professional",
            "subcategory":"Business Services",
            "type":"Services"
        }
    ],
    "sg:phone":"+1 801 627 5867",
    "sg:postcode":"84405",
    "sg:province":"UT",
    "wof:name":"Skydive Ogden",
    "wof:placetype":"venue"
},
  "geometry": {"coordinates":[-111.998276,41.203874],"type":"Point"}
}