{
  "type": "Feature",
  "properties": {
    "iso:country":"US",
    "sg:address":"1867 S 900 W",
    "sg:city":"Salt Lake City",
    "sg:classifiers":[
        {
            "category":"Building & Trades",
            "subcategory":"Construction",
            "type":"Services"
        }
    ],
    "sg:phone":"+1 801 975 1900",
    "sg:postcode":"84104",
    "sg:province":"UT",
    "sg:tags":[
        "sandblasting"
    ],
    "wof:name":"Ameri Pride",
    "wof:placetype":"venue"
},
  "geometry": {"coordinates":[-111.916726,40.728994],"type":"Point"}
}