{
  "type": "Feature",
  "properties": {
    "iso:country":"US",
    "sg:address":"85 W 100 S",
    "sg:city":"Willard",
    "sg:classifiers":[
        {
            "category":"Professional",
            "subcategory":"Business Services",
            "type":"Services"
        }
    ],
    "sg:phone":"+1 435 723 8330",
    "sg:postcode":"84340",
    "sg:province":"UT",
    "wof:name":"Concepts In Interior Systems L",
    "wof:placetype":"venue"
},
  "geometry": {"coordinates":[-112.036874,41.406886],"type":"Point"}
}