{
  "type": "Feature",
  "properties": {
    "iso:country":"US",
    "sg:address":"6400 Ute Blvd",
    "sg:city":"Park City",
    "sg:classifiers":[
        {
            "category":"Restaurant",
            "type":"Food & Drink"
        }
    ],
    "sg:menulink":"http://www.allmenus.com/ut/park-city/61290-park-city-pizza-co/menu/",
    "sg:phone":"+1 435 649 1591",
    "sg:postcode":"84098",
    "sg:province":"UT",
    "sg:tags":[
        "american",
        "pizza"
    ],
    "wof:name":"Park City Pizza Co",
    "wof:placetype":"venue"
},
  "geometry": {"coordinates":[-111.539738,40.725026],"type":"Point"}
}