{
  "type": "Feature",
  "properties": {
    "iso:country":"US",
    "sg:address":"735 Industrial Rd",
    "sg:city":"St George",
    "sg:classifiers":[
        {
            "category":"Food & Beverages",
            "subcategory":"Specialty",
            "type":"Retail Goods"
        }
    ],
    "sg:phone":"+1 435 628 0534",
    "sg:postcode":"84770",
    "sg:province":"UT",
    "wof:name":"Herbal Fibr Blend-Barley Green",
    "wof:placetype":"venue"
},
  "geometry": {"coordinates":[-113.554565,37.121289],"type":"Point"}
}