{
  "type": "Feature",
  "properties": {
    "iso:country":"US",
    "sg:address":"662 N 700 E",
    "sg:city":"Payson",
    "sg:classifiers":[
        {
            "category":"Professional",
            "subcategory":"Business Services",
            "type":"Services"
        }
    ],
    "sg:phone":"+1 801 465 0840",
    "sg:postcode":"84651",
    "sg:province":"UT",
    "wof:name":"Max Prince",
    "wof:placetype":"venue"
},
  "geometry": {"coordinates":[-111.72135299999999,40.052716],"type":"Point"}
}