{
  "type": "Feature",
  "properties": {
    "iso:country":"US",
    "sg:address":"11018 S Conestoga Dr",
    "sg:city":"Spanish Fork",
    "sg:classifiers":[
        {
            "category":"Professional",
            "type":"Services"
        }
    ],
    "sg:phone":"+1 801 873 3373",
    "sg:postcode":"84660",
    "sg:province":"UT",
    "wof:name":"Metcalf Village LLC",
    "wof:placetype":"venue"
},
  "geometry": {"coordinates":[-111.56756900000001,40.024645],"type":"Point"}
}