{
  "type": "Feature",
  "properties": {
    "iso:country":"US",
    "sg:address":"4179 Riverdale Rd",
    "sg:city":"Ogden",
    "sg:classifiers":[
        {
            "category":"Restaurant",
            "type":"Food & Drink"
        }
    ],
    "sg:menulink":"http://www.allmenus.com/ut/ogden/132863-subway/menu/",
    "sg:phone":"+1 801 621 7827",
    "sg:postcode":"84405",
    "sg:province":"UT",
    "sg:tags":[
        "american",
        "sandwich"
    ],
    "wof:name":"Subway",
    "wof:placetype":"venue"
},
  "geometry": {"coordinates":[-111.984977,41.187104],"type":"Point"}
}