{
  "type": "Feature",
  "properties": {
    "iso:country":"US",
    "sg:address":"1176 N 730 E",
    "sg:city":"Pleasant Grove",
    "sg:classifiers":[
        {
            "category":"Organizations",
            "subcategory":"Religious Organization",
            "type":"Services"
        }
    ],
    "sg:phone":"+1 801 785 7570",
    "sg:postcode":"84062",
    "sg:province":"UT",
    "sg:tags":[
        "church"
    ],
    "wof:name":"Church Of Jesus Christ Of Lds",
    "wof:placetype":"venue"
},
  "geometry": {"coordinates":[-111.724211,40.375893],"type":"Point"}
}