{
  "type": "Feature",
  "properties": {
    "iso:country":"US",
    "sg:address":"1163 W 820 N",
    "sg:city":"Provo",
    "sg:classifiers":[
        {
            "category":"Building & Trades",
            "subcategory":"Construction",
            "type":"Services"
        }
    ],
    "sg:phone":"+1 801 809 1898",
    "sg:postcode":"84601",
    "sg:province":"UT",
    "sg:tags":[
        "carpentry",
        "contractor"
    ],
    "wof:name":"B & W Construction Co",
    "wof:placetype":"venue"
},
  "geometry": {"coordinates":[-111.67982499999999,40.244553],"type":"Point"}
}