{
  "type": "Feature",
  "properties": {
    "iso:country":"US",
    "sg:address":"6196 S Redwood Rd",
    "sg:city":"Salt Lake City",
    "sg:classifiers":[
        {
            "category":"Social Services",
            "type":"Services"
        }
    ],
    "sg:phone":"+1 801 963 1204",
    "sg:postcode":"84123",
    "sg:province":"UT",
    "wof:name":"Quest Mntal Hlth Cnseling Svcs",
    "wof:placetype":"venue"
},
  "geometry": {"coordinates":[-111.938844,40.639168],"type":"Point"}
}