{
  "type": "Feature",
  "properties": {
    "iso:country":"US",
    "sg:address":"25 E 1800 S",
    "sg:city":"Clearfield",
    "sg:classifiers":[
        {
            "category":"Banks & Credit Unions",
            "subcategory":"Bank",
            "type":"Services"
        }
    ],
    "sg:phone":"+1 801 825 8364",
    "sg:postcode":"84015",
    "sg:province":"UT",
    "sg:tags":[
        "loan",
        "broker"
    ],
    "wof:name":"Michael V Lujan",
    "wof:placetype":"venue"
},
  "geometry": {"coordinates":[-112.025773,41.087741],"type":"Point"}
}