{
  "type": "Feature",
  "properties": {
    "iso:country":"US",
    "sg:address":"85 S 185 E",
    "sg:city":"Farmington",
    "sg:classifiers":[
        {
            "category":"Insurance",
            "subcategory":"Insurance Agent",
            "type":"Services"
        }
    ],
    "sg:phone":"+1 801 447 8369",
    "sg:postcode":"84025",
    "sg:province":"UT",
    "wof:name":"Horace Mann Insurance Co",
    "wof:placetype":"venue"
},
  "geometry": {"coordinates":[-111.88352500000001,40.980376],"type":"Point"}
}