{
  "type": "Feature",
  "properties": {
    "iso:country":"US",
    "sg:address":"6865 S Greendale Rd",
    "sg:city":"Salt Lake City",
    "sg:classifiers":[
        {
            "category":"Professional",
            "subcategory":"Computer Services",
            "type":"Services"
        }
    ],
    "sg:phone":"+1 801 942 0212",
    "sg:postcode":"84121",
    "sg:province":"UT",
    "sg:tags":[
        "development",
        "software"
    ],
    "wof:name":"Digital Research & Development",
    "wof:placetype":"venue"
},
  "geometry": {"coordinates":[-111.83577699999999,40.62629],"type":"Point"}
}