{
  "type": "Feature",
  "properties": {
    "iso:country":"US",
    "sg:address":"2037 S 2700 W",
    "sg:city":"Ogden",
    "sg:classifiers":[
        {
            "category":"Restaurant",
            "type":"Food & Drink"
        }
    ],
    "sg:phone":"+1 801 731 5097",
    "sg:postcode":"84401",
    "sg:province":"UT",
    "sg:tags":[
        "florist",
        "eating"
    ],
    "wof:name":"Prairie House Dry Goods Co",
    "wof:placetype":"venue"
},
  "geometry": {"coordinates":[-112.044785,41.232166],"type":"Point"}
}