{
  "type": "Feature",
  "properties": {
    "iso:country":"US",
    "sg:address":"10328 S 360 E",
    "sg:city":"Sandy",
    "sg:classifiers":[
        {
            "category":"Banks & Credit Unions",
            "subcategory":"Bank",
            "type":"Services"
        }
    ],
    "sg:phone":"+1 801 904 3859",
    "sg:postcode":"84070",
    "sg:province":"UT",
    "sg:tags":[
        "mortgage"
    ],
    "wof:name":"Perfect Mortgage",
    "wof:placetype":"venue"
},
  "geometry": {"coordinates":[-111.881215,40.563262],"type":"Point"}
}