{
  "type": "Feature",
  "properties": {
    "iso:country":"US",
    "sg:address":"816 E 9400 S",
    "sg:city":"Sandy",
    "sg:classifiers":[
        {
            "category":"Restaurant",
            "type":"Food & Drink"
        }
    ],
    "sg:menulink":"http://www.allmenus.com/ut/salt-lake-city/37354-la-costa/menu/",
    "sg:phone":"+1 801 553 1505",
    "sg:postcode":"84094",
    "sg:province":"UT",
    "sg:tags":[
        "mexican"
    ],
    "wof:name":"La Costa",
    "wof:placetype":"venue"
},
  "geometry": {"coordinates":[-111.868656,40.580605],"type":"Point"}
}