{
  "type": "Feature",
  "properties": {
    "iso:country":"US",
    "sg:address":"1127 N 1600 W",
    "sg:city":"Mapleton",
    "sg:classifiers":[
        {
            "category":"Professional",
            "type":"Services"
        }
    ],
    "sg:phone":"+1 801 491 0679",
    "sg:postcode":"84664",
    "sg:province":"UT",
    "sg:tags":[
        "establishment"
    ],
    "wof:name":"Stark Inc",
    "wof:placetype":"venue"
},
  "geometry": {"coordinates":[-111.598028,40.140729],"type":"Point"}
}