{
  "type": "Feature",
  "properties": {
    "iso:country":"US",
    "sg:address":"541 W 2600 S",
    "sg:city":"Bountiful",
    "sg:classifiers":[
        {
            "category":"Shopping",
            "subcategory":"Gifts & Souvenirs",
            "type":"Retail Goods"
        }
    ],
    "sg:phone":"+1 801 292 0107",
    "sg:postcode":"84010",
    "sg:province":"UT",
    "sg:tags":[
        "shop"
    ],
    "wof:name":"Tina's Hallmark",
    "wof:placetype":"venue"
},
  "geometry": {"coordinates":[-111.892887,40.861672],"type":"Point"}
}