{
  "type": "Feature",
  "properties": {
    "iso:country":"US",
    "sg:address":"1164 W 850 N",
    "sg:city":"Centerville",
    "sg:classifiers":[
        {
            "category":"Building & Trades",
            "subcategory":"Cleaning & Sanitation",
            "type":"Services"
        },
        {
            "category":"Retail",
            "subcategory":"Laundry & Dry Cleaning",
            "type":"Services"
        }
    ],
    "sg:phone":"+1 801 335 3227",
    "sg:postcode":"84014",
    "sg:province":"UT",
    "sg:tags":[
        "home",
        "carpet"
    ],
    "sg:website":"www.biocleanofutah.com",
    "wof:name":"Bio Clean of Utah",
    "wof:placetype":"venue"
},
  "geometry": {"coordinates":[-111.895819,40.927919],"type":"Point"}
}