{
  "type": "Feature",
  "properties": {
    "iso:country":"US",
    "sg:address":"860 W Riverdale Rd",
    "sg:city":"Ogden",
    "sg:classifiers":[
        {
            "category":"Personal",
            "type":"Services"
        }
    ],
    "sg:phone":"+1 801 627 2901",
    "sg:postcode":"84405",
    "sg:province":"UT",
    "sg:tags":[
        "therapist",
        "massage"
    ],
    "wof:name":"Therapeutic Relaxation",
    "wof:placetype":"venue"
},
  "geometry": {"coordinates":[-111.998614,41.179274],"type":"Point"}
}