{
  "type": "Feature",
  "properties": {
    "iso:country":"US",
    "sg:address":"5814 W Connor Ct",
    "sg:city":"American Fork",
    "sg:classifiers":[
        {
            "category":"Professional",
            "subcategory":"Management & Consulting",
            "type":"Services"
        }
    ],
    "sg:phone":"+1 801 763 7374",
    "sg:postcode":"84003",
    "sg:province":"UT",
    "sg:tags":[
        "business"
    ],
    "wof:name":"Experius LLC",
    "wof:placetype":"venue"
},
  "geometry": {"coordinates":[-111.79825099999999,40.437263],"type":"Point"}
}