{
  "type": "Feature",
  "properties": {
    "iso:country":"US",
    "sg:address":"3177 W 8450 S",
    "sg:city":"Magna",
    "sg:classifiers":[
        {
            "category":"Retail",
            "subcategory":"Laundry & Dry Cleaning",
            "type":"Services"
        }
    ],
    "sg:phone":"+1 801 250 5452",
    "sg:postcode":"84088",
    "sg:province":"UT",
    "sg:tags":[
        "cleaners",
        "rug",
        "carpet"
    ],
    "wof:name":"Aspen Chemdry",
    "wof:placetype":"venue"
},
  "geometry": {"coordinates":[-111.966864,40.598556],"type":"Point"}
}