{
  "type": "Feature",
  "properties": {
    "iso:country":"US",
    "sg:address":"1387 N Center St",
    "sg:city":"American Fork",
    "sg:classifiers":[
        {
            "category":"Building & Trades",
            "subcategory":"Construction",
            "type":"Services"
        }
    ],
    "sg:phone":"+1 801 342 0099",
    "sg:postcode":"84003",
    "sg:province":"UT",
    "wof:name":"Automated Interiors",
    "wof:placetype":"venue"
},
  "geometry": {"coordinates":[-111.798226,40.404719],"type":"Point"}
}