{
  "type": "Feature",
  "properties": {
    "iso:country":"US",
    "sg:address":"942 W Weaver Ln",
    "sg:city":"Layton",
    "sg:classifiers":[
        {
            "category":"Banks & Credit Unions",
            "subcategory":"Bank",
            "type":"Services"
        }
    ],
    "sg:phone":"+1 801 544 8454",
    "sg:postcode":"84041",
    "sg:province":"UT",
    "sg:tags":[
        "lender",
        "mortgage"
    ],
    "wof:name":"Partners Lending",
    "wof:placetype":"venue"
},
  "geometry": {"coordinates":[-111.982904,41.048053],"type":"Point"}
}