{
  "type": "Feature",
  "properties": {
    "iso:country":"US",
    "sg:address":"55 N Main St",
    "sg:city":"Bountiful",
    "sg:classifiers":[
        {
            "category":"Retail",
            "subcategory":"Portrait Studio",
            "type":"Services"
        }
    ],
    "sg:phone":"+1 801 397 0448",
    "sg:postcode":"84010",
    "sg:province":"UT",
    "sg:tags":[
        "photographer"
    ],
    "sg:website":"www.galleryphoto.com",
    "wof:name":"Gallery Photography",
    "wof:placetype":"venue"
},
  "geometry": {"coordinates":[-111.880781,40.889852],"type":"Point"}
}