{
  "type": "Feature",
  "properties": {
    "iso:country":"US",
    "sg:address":"4922 E Meadows Dr",
    "sg:city":"Park City",
    "sg:classifiers":[
        {
            "category":"Building & Trades",
            "subcategory":"Construction",
            "type":"Services"
        }
    ],
    "sg:phone":"+1 435 640 2803",
    "sg:postcode":"84098",
    "sg:province":"UT",
    "sg:tags":[
        "product",
        "asphalt"
    ],
    "wof:name":"Park City Seal Coat LLC",
    "wof:placetype":"venue"
},
  "geometry": {"coordinates":[-111.53726399999999,40.703958],"type":"Point"}
}