{
  "type": "Feature",
  "properties": {
    "iso:country":"US",
    "sg:address":"4741 S 175 W",
    "sg:city":"Ogden",
    "sg:classifiers":[
        {
            "category":"Manufacturing",
            "subcategory":"Building Materials",
            "type":"Manufacturing & Wholesale Goods"
        }
    ],
    "sg:phone":"+1 801 334 9311",
    "sg:postcode":"84405",
    "sg:province":"UT",
    "sg:tags":[
        "mfg"
    ],
    "wof:name":"Craftmasters Inc",
    "wof:placetype":"venue"
},
  "geometry": {"coordinates":[-111.97977,41.177296],"type":"Point"}
}