{
  "type": "Feature",
  "properties": {
    "iso:country":"US",
    "sg:address":"370 N Main St",
    "sg:city":"Orangeville",
    "sg:classifiers":[
        {
            "category":"Building & Trades",
            "subcategory":"Construction",
            "type":"Services"
        }
    ],
    "sg:phone":"+1 435 748 2636",
    "sg:postcode":"84537",
    "sg:province":"UT",
    "sg:tags":[
        "general",
        "contractor"
    ],
    "wof:name":"Stilson & Sons Constr Inc",
    "wof:placetype":"venue"
},
  "geometry": {"coordinates":[-111.053287,39.232217],"type":"Point"}
}