{
  "type": "Feature",
  "properties": {
    "iso:country":"US",
    "sg:address":"155 E 400 S",
    "sg:city":"American Fork",
    "sg:classifiers":[
        {
            "category":"Banks & Credit Unions",
            "subcategory":"Financial Services",
            "type":"Services"
        }
    ],
    "sg:phone":"+1 801 756 4996",
    "sg:postcode":"84003",
    "sg:province":"UT",
    "sg:tags":[
        "trust",
        "management"
    ],
    "wof:name":"Chesnut Family Trust",
    "wof:placetype":"venue"
},
  "geometry": {"coordinates":[-111.79401900000001,40.368931],"type":"Point"}
}