{
  "type": "Feature",
  "properties": {
    "iso:country":"US",
    "sg:address":"3951 S Bountiful Blvd",
    "sg:city":"Bountiful",
    "sg:classifiers":[
        {
            "category":"Professional",
            "subcategory":"Advertising",
            "type":"Services"
        }
    ],
    "sg:phone":"+1 801 631 8484",
    "sg:postcode":"84010",
    "sg:province":"UT",
    "wof:name":"Money Mailer",
    "wof:placetype":"venue"
},
  "geometry": {"coordinates":[-111.87562699999999,40.845634],"type":"Point"}
}