{
  "type": "Feature",
  "properties": {
    "iso:country":"US",
    "sg:address":"1138 Newgate Mall",
    "sg:city":"Ogden",
    "sg:classifiers":[
        {
            "category":"Health Services",
            "subcategory":"Health Practitioner",
            "type":"Services"
        }
    ],
    "sg:phone":"+1 801 627 8200",
    "sg:postcode":"84405",
    "sg:province":"UT",
    "wof:name":"Night and Optical",
    "wof:placetype":"venue"
},
  "geometry": {"coordinates":[-111.977147,41.195431],"type":"Point"}
}