{
  "type": "Feature",
  "properties": {
    "iso:country":"US",
    "sg:address":"100 N State St",
    "sg:city":"Lindon",
    "sg:classifiers":[
        {
            "category":"Government",
            "subcategory":"Office",
            "type":"Public Place"
        }
    ],
    "sg:phone":"+1 801 785 5044",
    "sg:postcode":"84042",
    "sg:province":"UT",
    "sg:tags":[
        "city"
    ],
    "wof:name":"Lindon City Hall",
    "wof:placetype":"venue"
},
  "geometry": {"coordinates":[-111.719961,40.341611],"type":"Point"}
}