{
  "type": "Feature",
  "properties": {
    "iso:country":"US",
    "sg:address":"155 S Main St",
    "sg:city":"Salt Lake City",
    "sg:classifiers":[
        {
            "category":"Health Services",
            "subcategory":"Optometrist",
            "type":"Services"
        }
    ],
    "sg:phone":"+1 801 363 0835",
    "sg:postcode":"84111",
    "sg:province":"UT",
    "wof:name":"Bruce Brewer",
    "wof:placetype":"venue"
},
  "geometry": {"coordinates":[-111.891018,40.766197],"type":"Point"}
}