{
  "type": "Feature",
  "properties": {
    "iso:country":"US",
    "sg:address":"2389 S 1100 W",
    "sg:city":"Woods Cross",
    "sg:classifiers":[
        {
            "category":"Manufacturing",
            "subcategory":"Metals",
            "type":"Manufacturing & Wholesale Goods"
        }
    ],
    "sg:phone":"+1 801 292 4471",
    "sg:postcode":"84087",
    "sg:province":"UT",
    "sg:tags":[
        "steel"
    ],
    "wof:name":"Pipe Fabricating & Supply Co",
    "wof:placetype":"venue"
},
  "geometry": {"coordinates":[-111.911779,40.86715],"type":"Point"}
}