{
  "type": "Feature",
  "properties": {
    "iso:country":"US",
    "sg:address":"2084 S 900 E",
    "sg:city":"Bountiful",
    "sg:classifiers":[
        {
            "category":"Professional",
            "subcategory":"Management & Consulting",
            "type":"Services"
        }
    ],
    "sg:phone":"+1 801 296 2880",
    "sg:postcode":"84010",
    "sg:province":"UT",
    "sg:tags":[
        "technical",
        "sales"
    ],
    "wof:name":"Tei Corp",
    "wof:placetype":"venue"
},
  "geometry": {"coordinates":[-111.862639,40.865751],"type":"Point"}
}