{
  "type": "Feature",
  "properties": {
    "iso:country":"US",
    "sg:address":"546 River Meadows Dr",
    "sg:city":"Alpine",
    "sg:classifiers":[
        {
            "category":"Professional",
            "type":"Services"
        }
    ],
    "sg:phone":"+1 801 756 4246",
    "sg:postcode":"84004",
    "sg:province":"UT",
    "wof:name":"Dvo Lick & Stick Incorporated",
    "wof:placetype":"venue"
},
  "geometry": {"coordinates":[-111.768574,40.450796],"type":"Point"}
}