{
  "type": "Feature",
  "properties": {
    "iso:country":"US",
    "sg:address":"6 N Main St",
    "sg:city":"Payson",
    "sg:classifiers":[
        {
            "category":"Retail",
            "subcategory":"Portrait Studio",
            "type":"Services"
        }
    ],
    "sg:phone":"+1 801 465 4674",
    "sg:postcode":"84651",
    "sg:province":"UT",
    "sg:tags":[
        "photo"
    ],
    "wof:name":"Memory Lane Photography",
    "wof:placetype":"venue"
},
  "geometry": {"coordinates":[-111.73219899999999,40.044506],"type":"Point"}
}