{
  "type": "Feature",
  "properties": {
    "iso:country":"US",
    "sg:address":"39 Sumac Way",
    "sg:city":"Brigham City",
    "sg:classifiers":[
        {
            "category":"Shopping",
            "subcategory":"Bicycles & Sporting Goods",
            "type":"Retail Goods"
        }
    ],
    "sg:phone":"+1 435 723 7521",
    "sg:postcode":"84302",
    "sg:province":"UT",
    "sg:tags":[
        "archery",
        "equipment"
    ],
    "wof:name":"Roy-N-Kat Archery",
    "wof:placetype":"venue"
},
  "geometry": {"coordinates":[-112.017323,41.488524],"type":"Point"}
}