{
  "type": "Feature",
  "properties": {
    "iso:country":"US",
    "sg:address":"4047 S 2175 W",
    "sg:city":"Roy",
    "sg:classifiers":[
        {
            "category":"Personal",
            "subcategory":"Beauty Salon",
            "type":"Services"
        }
    ],
    "sg:phone":"+1 801 731 9188",
    "sg:postcode":"84067",
    "sg:province":"UT",
    "sg:tags":[
        "shop"
    ],
    "wof:name":"Nails By Robin",
    "wof:placetype":"venue"
},
  "geometry": {"coordinates":[-112.032327,41.189967],"type":"Point"}
}