{
  "type": "Feature",
  "properties": {
    "iso:country":"US",
    "sg:address":"125 E 6100 S",
    "sg:city":"Salt Lake City",
    "sg:classifiers":[
        {
            "category":"Retail",
            "subcategory":"Repair Shop",
            "type":"Services"
        }
    ],
    "sg:phone":"+1 801 268 9562",
    "sg:postcode":"84107",
    "sg:province":"UT",
    "sg:tags":[
        "picture",
        "custom",
        "art",
        "dealer",
        "framing"
    ],
    "wof:name":"Frame Station The",
    "wof:placetype":"venue"
},
  "geometry": {"coordinates":[-111.885828,40.638504],"type":"Point"}
}