{
  "type": "Feature",
  "properties": {
    "iso:country":"US",
    "sg:address":"130 W Aspen Way",
    "sg:city":"Salem",
    "sg:classifiers":[
        {
            "category":"Real Estate",
            "subcategory":"Real Estate Agent",
            "type":"Services"
        }
    ],
    "sg:phone":"+1 801 423 0236",
    "sg:postcode":"84653",
    "sg:province":"UT",
    "wof:name":"Gladys S Biggers Trustee",
    "wof:placetype":"venue"
},
  "geometry": {"coordinates":[-111.675684,40.044819],"type":"Point"}
}