{
  "type": "Feature",
  "properties": {
    "iso:country":"US",
    "sg:address":"3610 Lariat Rd",
    "sg:city":"Park City",
    "sg:classifiers":[
        {
            "category":"Real Estate",
            "subcategory":"Real Estate Agent",
            "type":"Services"
        }
    ],
    "sg:phone":"+1 435 649 9669",
    "sg:postcode":"84098",
    "sg:province":"UT",
    "wof:name":"Bryan Shadix",
    "wof:placetype":"venue"
},
  "geometry": {"coordinates":[-111.583207,40.76399],"type":"Point"}
}