{
  "type": "Feature",
  "properties": {
    "iso:country":"US",
    "sg:address":"305 S 600 E",
    "sg:city":"Centerville",
    "sg:classifiers":[
        {
            "category":"Professional",
            "subcategory":"Business Services",
            "type":"Services"
        }
    ],
    "sg:phone":"+1 801 544 6909",
    "sg:postcode":"84014",
    "sg:province":"UT",
    "wof:name":"Professional Bldg Inspector",
    "wof:placetype":"venue"
},
  "geometry": {"coordinates":[-111.86945,40.913063],"type":"Point"}
}