{
  "type": "Feature",
  "properties": {
    "iso:country":"US",
    "sg:address":"135 E 800 N",
    "sg:city":"Orem",
    "sg:classifiers":[
        {
            "category":"Insurance",
            "subcategory":"Insurance Agent",
            "type":"Services"
        }
    ],
    "sg:phone":"+1 801 225 5959",
    "sg:postcode":"84057",
    "sg:province":"UT",
    "wof:name":"Allstate Insurance",
    "wof:placetype":"venue"
},
  "geometry": {"coordinates":[-111.692132,40.311958],"type":"Point"}
}