{
  "type": "Feature",
  "properties": {
    "iso:country":"US",
    "sg:address":"531 E University Pkwy",
    "sg:city":"Orem",
    "sg:classifiers":[
        {
            "category":"Restaurant",
            "type":"Food & Drink"
        }
    ],
    "sg:phone":"+1 801 764 0743",
    "sg:postcode":"84058",
    "sg:province":"UT",
    "sg:website":"www.landrys.com",
    "wof:name":"Joe's Crab Shack",
    "wof:placetype":"venue"
},
  "geometry": {"coordinates":[-111.68349499999999,40.273501],"type":"Point"}
}