{
  "type": "Feature",
  "properties": {
    "iso:country":"US",
    "sg:address":"523 N Main St",
    "sg:city":"Panguitch",
    "sg:classifiers":[
        {
            "category":"Restaurant",
            "type":"Food & Drink"
        }
    ],
    "sg:phone":"+1 435 676 2377",
    "sg:postcode":"84759",
    "sg:province":"UT",
    "wof:name":"Grandma Tina's Spaghetti House",
    "wof:placetype":"venue"
},
  "geometry": {"coordinates":[-112.43565,37.830958],"type":"Point"}
}