{
  "type": "Feature",
  "properties": {
    "iso:country":"US",
    "sg:address":"264 E 300 N",
    "sg:city":"Washington",
    "sg:classifiers":[
        {
            "category":"Health Services",
            "subcategory":"Medical Lab",
            "type":"Services"
        }
    ],
    "sg:phone":"+1 435 674 2162",
    "sg:postcode":"84780",
    "sg:province":"UT",
    "sg:tags":[
        "laboratory",
        "dental"
    ],
    "wof:name":"Royal Image",
    "wof:placetype":"venue"
},
  "geometry": {"coordinates":[-113.505797,37.135759],"type":"Point"}
}