{
  "type": "Feature",
  "properties": {
    "iso:country":"US",
    "sg:address":"1601 N 400 E",
    "sg:city":"Logan",
    "sg:classifiers":[
        {
            "category":"Organizations",
            "subcategory":"Religious Organization",
            "type":"Services"
        }
    ],
    "sg:phone":"+1 435 752 9443",
    "sg:postcode":"84341",
    "sg:province":"UT",
    "wof:name":"Cache Valley Bible Fellowship",
    "wof:placetype":"venue"
},
  "geometry": {"coordinates":[-111.823933,41.759562],"type":"Point"}
}