{
  "type": "Feature",
  "properties": {
    "iso:country":"US",
    "sg:address":"4214 S Shanna St",
    "sg:city":"Salt Lake City",
    "sg:classifiers":[
        {
            "category":"Professional",
            "subcategory":"Engineering",
            "type":"Services"
        }
    ],
    "sg:phone":"+1 801 278 2317",
    "sg:postcode":"84124",
    "sg:province":"UT",
    "wof:name":"Jahne Charles J Pe & Assoc",
    "wof:placetype":"venue"
},
  "geometry": {"coordinates":[-111.810244,40.681024],"type":"Point"}
}