{
  "type": "Feature",
  "properties": {
    "iso:country":"US",
    "sg:address":"781 Centennial Dr",
    "sg:city":"North Salt Lake",
    "sg:classifiers":[
        {
            "category":"Building & Trades",
            "subcategory":"Electrical",
            "type":"Services"
        }
    ],
    "sg:phone":"+1 801 671 6201",
    "sg:postcode":"84054",
    "sg:province":"UT",
    "sg:tags":[
        "control",
        "energy"
    ],
    "wof:name":"Co-Lo Ems",
    "wof:placetype":"venue"
},
  "geometry": {"coordinates":[-111.89196200000001,40.835063],"type":"Point"}
}