{
  "type": "Feature",
  "properties": {
    "iso:country":"US",
    "sg:address":"212 E 900 N",
    "sg:city":"American Fork",
    "sg:classifiers":[
        {
            "category":"Organizations",
            "subcategory":"Labor Organization",
            "type":"Services"
        }
    ],
    "sg:phone":"+1 801 756 0810",
    "sg:postcode":"84003",
    "sg:province":"UT",
    "wof:name":"Experience Ceramics Lc",
    "wof:placetype":"venue"
},
  "geometry": {"coordinates":[-111.79191400000001,40.39483],"type":"Point"}
}