{
  "type": "Feature",
  "properties": {
    "iso:country":"US",
    "sg:address":"2 Cottonwood Dr",
    "sg:city":"Centerville",
    "sg:classifiers":[
        {
            "category":"Building & Trades",
            "subcategory":"Locksmith",
            "type":"Services"
        }
    ],
    "sg:phone":"+1 801 656 2268",
    "sg:postcode":"84014",
    "sg:province":"UT",
    "sg:tags":[
        "key"
    ],
    "wof:name":"0 1 Emergency A Locksmith",
    "wof:placetype":"venue"
},
  "geometry": {"coordinates":[-111.877639,40.935193],"type":"Point"}
}