{
  "type": "Feature",
  "properties": {
    "iso:country":"US",
    "sg:address":"2148 E Hill Field Rd",
    "sg:city":"Layton",
    "sg:classifiers":[
        {
            "category":"Building & Trades",
            "subcategory":"Electrical",
            "type":"Services"
        }
    ],
    "sg:phone":"+1 801 525 9100",
    "sg:postcode":"84041",
    "sg:province":"UT",
    "sg:tags":[
        "electric",
        "contractor"
    ],
    "wof:name":"Wasatch Electric",
    "wof:placetype":"venue"
},
  "geometry": {"coordinates":[-111.92479400000001,41.104475],"type":"Point"}
}