{
  "type": "Feature",
  "properties": {
    "iso:country":"US",
    "sg:address":"420 E 400 S",
    "sg:city":"Salt Lake City",
    "sg:classifiers":[
        {
            "category":"Restaurant",
            "type":"Food & Drink"
        }
    ],
    "sg:phone":"+1 801 532 4283",
    "sg:postcode":"84111",
    "sg:province":"UT",
    "wof:name":"Arbys Unit 174",
    "wof:placetype":"venue"
},
  "geometry": {"coordinates":[-111.881176,40.760654],"type":"Point"}
}