{
  "type": "Feature",
  "properties": {
    "iso:country":"US",
    "sg:address":"1480 Orchard Dr Ste 105",
    "sg:city":"Bountiful",
    "sg:classifiers":[
        {
            "category":"Health Services",
            "subcategory":"Dentist",
            "type":"Services"
        }
    ],
    "sg:phone":"+1 801 295 7171",
    "sg:postcode":"84010",
    "sg:province":"UT",
    "wof:name":"Rocky Mountain Dental Associates",
    "wof:placetype":"venue"
},
  "geometry": {"coordinates":[-111.87512099999999,40.875028],"type":"Point"}
}