{
  "type": "Feature",
  "properties": {
    "iso:country":"US",
    "sg:address":"992 W 1150 S",
    "sg:city":"Provo",
    "sg:classifiers":[
        {
            "category":"Personal",
            "subcategory":"Beauty Salon",
            "type":"Services"
        }
    ],
    "sg:phone":"+1 801 356 2730",
    "sg:postcode":"84601",
    "sg:province":"UT",
    "sg:tags":[
        "shop"
    ],
    "wof:name":"Cutters Edge Inc",
    "wof:placetype":"venue"
},
  "geometry": {"coordinates":[-111.677553,40.218537],"type":"Point"}
}