{
  "type": "Feature",
  "properties": {
    "iso:country":"US",
    "sg:address":"96 N State St",
    "sg:city":"Morgan",
    "sg:classifiers":[
        {
            "category":"Food & Beverages",
            "subcategory":"Groceries & Convenience Stores",
            "type":"Retail Goods"
        }
    ],
    "sg:phone":"+1 801 829 3676",
    "sg:postcode":"84050",
    "sg:province":"UT",
    "wof:name":"Nebco Service",
    "wof:placetype":"venue"
},
  "geometry": {"coordinates":[-111.676512,41.034373],"type":"Point"}
}