{
  "type": "Feature",
  "properties": {
    "iso:country":"US",
    "sg:address":"2061 E 9400 S",
    "sg:city":"Sandy",
    "sg:classifiers":[
        {
            "category":"Health Services",
            "subcategory":"Chiropractor",
            "type":"Services"
        }
    ],
    "sg:phone":"+1 801 943 8308",
    "sg:postcode":"84093",
    "sg:province":"UT",
    "wof:name":"Canyon Chiropractic",
    "wof:placetype":"venue"
},
  "geometry": {"coordinates":[-111.830561,40.580548],"type":"Point"}
}