{
  "type": "Feature",
  "properties": {
    "iso:country":"US",
    "sg:address":"493 W 940 N",
    "sg:city":"American Fork",
    "sg:classifiers":[
        {
            "category":"Professional",
            "subcategory":"Management & Consulting",
            "type":"Services"
        }
    ],
    "sg:phone":"+1 801 492 1238",
    "sg:postcode":"84003",
    "sg:province":"UT",
    "wof:name":"Top Athletes Marketing LLC",
    "wof:placetype":"venue"
},
  "geometry": {"coordinates":[-111.81088800000001,40.395511],"type":"Point"}
}