{
  "type": "Feature",
  "properties": {
    "iso:country":"US",
    "sg:address":"1027 Arlington Way",
    "sg:city":"Bountiful",
    "sg:classifiers":[
        {
            "category":"Building & Trades",
            "subcategory":"Pest Control",
            "type":"Services"
        }
    ],
    "sg:phone":"+1 801 309 3358",
    "sg:postcode":"84010",
    "sg:province":"UT",
    "sg:tags":[
        "mothproofing"
    ],
    "wof:name":"All Star Pest Control",
    "wof:placetype":"venue"
},
  "geometry": {"coordinates":[-111.859816,40.870691],"type":"Point"}
}