{
  "type": "Feature",
  "properties": {
    "iso:country":"US",
    "sg:address":"8722 Harrison St",
    "sg:city":"Sandy",
    "sg:classifiers":[
        {
            "category":"Professional",
            "type":"Services"
        }
    ],
    "sg:phone":"+1 801 255 4418",
    "sg:postcode":"84070",
    "sg:province":"UT",
    "sg:tags":[
        "establishment"
    ],
    "wof:name":"Primeinsurance Syndicate",
    "wof:placetype":"venue"
},
  "geometry": {"coordinates":[-111.900762,40.593055],"type":"Point"}
}