{
  "type": "Feature",
  "properties": {
    "iso:country":"US",
    "sg:address":"3902 Ogden Ave",
    "sg:city":"Ogden",
    "sg:classifiers":[
        {
            "category":"Professional",
            "subcategory":"Business Services",
            "type":"Services"
        }
    ],
    "sg:phone":"+1 801 686 0296",
    "sg:postcode":"84403",
    "sg:province":"UT",
    "wof:name":"Shred Masters",
    "wof:placetype":"venue"
},
  "geometry": {"coordinates":[-111.969593,41.190528],"type":"Point"}
}