{
  "type": "Feature",
  "properties": {
    "iso:country":"US",
    "sg:address":"5225 S Redwood Rd",
    "sg:city":"Salt Lake City",
    "sg:classifiers":[
        {
            "category":"Education",
            "subcategory":"School",
            "type":"Public Place"
        }
    ],
    "sg:phone":"+1 801 685 5455",
    "sg:postcode":"84123",
    "sg:province":"UT",
    "wof:name":"Taylorsville High School",
    "wof:placetype":"venue"
},
  "geometry": {"coordinates":[-111.938799,40.653171],"type":"Point"}
}