{
  "type": "Feature",
  "properties": {
    "iso:country":"US",
    "sg:address":"436 Crown Pointe Dr",
    "sg:city":"Murray",
    "sg:classifiers":[
        {
            "category":"Professional",
            "subcategory":"Advertising",
            "type":"Services"
        }
    ],
    "sg:phone":"+1 801 269 8957",
    "sg:postcode":"84107",
    "sg:province":"UT",
    "wof:name":"Key Advertising Specialties",
    "wof:placetype":"venue"
},
  "geometry": {"coordinates":[-111.879739,40.647398],"type":"Point"}
}