{
  "type": "Feature",
  "properties": {
    "iso:country":"US",
    "sg:address":"867 Glendale St",
    "sg:city":"Salt Lake City",
    "sg:classifiers":[
        {
            "category":"Shopping",
            "subcategory":"Tobacco",
            "type":"Retail Goods"
        }
    ],
    "sg:phone":"+1 801 363 9993",
    "sg:postcode":"84104",
    "sg:province":"UT",
    "sg:tags":[
        "cigarette",
        "cigar",
        "dealer"
    ],
    "wof:name":"Swift 1 Stop Smoke Shop",
    "wof:placetype":"venue"
},
  "geometry": {"coordinates":[-111.923298,40.75076],"type":"Point"}
}