{
  "type": "Feature",
  "properties": {
    "iso:country":"US",
    "sg:address":"5544 S Indian Rock Rd",
    "sg:city":"Salt Lake City",
    "sg:classifiers":[
        {
            "category":"Building & Trades",
            "subcategory":"Construction",
            "type":"Services"
        }
    ],
    "sg:phone":"+1 801 277 8505",
    "sg:postcode":"84117",
    "sg:province":"UT",
    "sg:tags":[
        "house"
    ],
    "wof:name":"Charis Construction LLC",
    "wof:placetype":"venue"
},
  "geometry": {"coordinates":[-111.80896199999999,40.649429],"type":"Point"}
}