{
  "type": "Feature",
  "properties": {
    "iso:country":"US",
    "sg:address":"5159 Commerce Dr",
    "sg:city":"Salt Lake City",
    "sg:classifiers":[
        {
            "category":"Banks & Credit Unions",
            "subcategory":"Investment Brokerage",
            "type":"Services"
        }
    ],
    "sg:phone":"+1 801 266 3116",
    "sg:postcode":"84107",
    "sg:province":"UT",
    "wof:name":"LCI Enterprises",
    "wof:placetype":"venue"
},
  "geometry": {"coordinates":[-111.898377,40.658862],"type":"Point"}
}