{
  "type": "Feature",
  "properties": {
    "iso:country":"US",
    "sg:address":"547 N Main St",
    "sg:city":"Layton",
    "sg:classifiers":[
        {
            "category":"Shopping",
            "subcategory":"Bicycles & Sporting Goods",
            "type":"Retail Goods"
        }
    ],
    "sg:phone":"+1 801 544 0525",
    "sg:postcode":"84041",
    "sg:province":"UT",
    "sg:tags":[
        "sport",
        "team"
    ],
    "wof:name":"Academy Sports Inc",
    "wof:placetype":"venue"
},
  "geometry": {"coordinates":[-111.97398099999999,41.067852],"type":"Point"}
}