{
  "type": "Feature",
  "properties": {
    "iso:country":"US",
    "sg:address":"415 N Main St",
    "sg:city":"Cedar City",
    "sg:classifiers":[
        {
            "category":"Professional",
            "subcategory":"Accounting & Tax Preparation",
            "type":"Services"
        }
    ],
    "sg:phone":"+1 435 586 0137",
    "sg:postcode":"84720",
    "sg:province":"UT",
    "sg:tags":[
        "accountant"
    ],
    "wof:name":"Claude Slack CPA",
    "wof:placetype":"venue"
},
  "geometry": {"coordinates":[-113.061863,37.684576],"type":"Point"}
}