{
  "type": "Feature",
  "properties": {
    "iso:country":"US",
    "sg:address":"3768 E Campus Dr",
    "sg:city":"Lehi",
    "sg:classifiers":[
        {
            "category":"Real Estate",
            "subcategory":"Real Estate Agent",
            "type":"Services"
        }
    ],
    "sg:phone":"+1 801 789 8500",
    "sg:postcode":"84043",
    "sg:province":"UT",
    "wof:name":"Era Legacy Realtors",
    "wof:placetype":"venue"
},
  "geometry": {"coordinates":[-111.973519,40.379518],"type":"Point"}
}