{
  "type": "Feature",
  "properties": {
    "iso:country":"US",
    "sg:address":"1128 E 100 S",
    "sg:city":"Payson",
    "sg:classifiers":[
        {
            "category":"Organizations",
            "subcategory":"Religious Organization",
            "type":"Services"
        }
    ],
    "sg:phone":"+1 801 465 9914",
    "sg:postcode":"84651",
    "sg:province":"UT",
    "sg:tags":[
        "church"
    ],
    "wof:name":"Church Of Jesus Christ Of Lds",
    "wof:placetype":"venue"
},
  "geometry": {"coordinates":[-111.713731,40.042722],"type":"Point"}
}