{
  "type": "Feature",
  "properties": {
    "iso:country":"US",
    "sg:address":"176 W 36th St",
    "sg:city":"Ogden",
    "sg:classifiers":[
        {
            "category":"Personal",
            "subcategory":"Shoe Repair & Shine",
            "type":"Services"
        }
    ],
    "sg:phone":"+1 801 392 8713",
    "sg:postcode":"84405",
    "sg:province":"UT",
    "sg:tags":[
        "repairing",
        "boot"
    ],
    "wof:name":"Quality Boot & Shoe Repair",
    "wof:placetype":"venue"
},
  "geometry": {"coordinates":[-111.982749,41.197949],"type":"Point"}
}