{
  "type": "Feature",
  "properties": {
    "iso:country":"US",
    "sg:address":"8485 Danish Rd",
    "sg:city":"Sandy",
    "sg:classifiers":[
        {
            "category":"Building & Trades",
            "subcategory":"Construction",
            "type":"Services"
        }
    ],
    "sg:phone":"+1 801 942 7379",
    "sg:postcode":"84093",
    "sg:province":"UT",
    "sg:tags":[
        "house"
    ],
    "wof:name":"Advance Construction",
    "wof:placetype":"venue"
},
  "geometry": {"coordinates":[-111.800758,40.597293],"type":"Point"}
}