{
  "type": "Feature",
  "properties": {
    "iso:country":"US",
    "sg:address":"727 24th St",
    "sg:city":"Ogden",
    "sg:classifiers":[
        {
            "category":"Banks & Credit Unions",
            "subcategory":"Bank",
            "type":"Services"
        }
    ],
    "sg:phone":"+1 801 612 2211",
    "sg:postcode":"84401",
    "sg:province":"UT",
    "sg:tags":[
        "mortgage"
    ],
    "wof:name":"T L C Fin-Ser",
    "wof:placetype":"venue"
},
  "geometry": {"coordinates":[-111.96136300000001,41.222565],"type":"Point"}
}