{
  "type": "Feature",
  "properties": {
    "iso:country":"US",
    "sg:address":"3154 S Washington St",
    "sg:city":"South Salt Lake",
    "sg:classifiers":[
        {
            "category":"Wholesale",
            "subcategory":"Metals & Minerals",
            "type":"Manufacturing & Wholesale Goods"
        }
    ],
    "sg:phone":"+1 801 466 7273",
    "sg:postcode":"84115",
    "sg:province":"UT",
    "sg:tags":[
        "pipe"
    ],
    "wof:name":"Combined Plastics",
    "wof:placetype":"venue"
},
  "geometry": {"coordinates":[-111.898032,40.701878],"type":"Point"}
}