{
  "type": "Feature",
  "properties": {
    "iso:country":"US",
    "sg:address":"3078 Oakwood Dr",
    "sg:city":"Bountiful",
    "sg:classifiers":[
        {
            "category":"Professional",
            "subcategory":"Accounting & Tax Preparation",
            "type":"Services"
        }
    ],
    "sg:phone":"+1 801 294 0471",
    "sg:postcode":"84010",
    "sg:province":"UT",
    "wof:name":"Bybee Accounting",
    "wof:placetype":"venue"
},
  "geometry": {"coordinates":[-111.868694,40.855695],"type":"Point"}
}