{
  "type": "Feature",
  "properties": {
    "iso:country":"US",
    "sg:address":"532 N 500 W",
    "sg:city":"Santaquin",
    "sg:classifiers":[
        {
            "category":"Education",
            "subcategory":"School",
            "type":"Public Place"
        }
    ],
    "sg:phone":"+1 801 489 9326",
    "sg:postcode":"84655",
    "sg:province":"UT",
    "wof:name":"Montessori World Of Discovery",
    "wof:placetype":"venue"
},
  "geometry": {"coordinates":[-111.73887999999999,40.050666],"type":"Point"}
}