{
  "type": "Feature",
  "properties": {
    "iso:country":"US",
    "sg:address":"748 N 350 E",
    "sg:city":"American Fork",
    "sg:classifiers":[
        {
            "category":"Manufacturing",
            "subcategory":"Apparel",
            "type":"Manufacturing & Wholesale Goods"
        }
    ],
    "sg:phone":"+1 801 756 5139",
    "sg:postcode":"84003",
    "sg:province":"UT",
    "sg:tags":[
        "textile",
        "bag",
        "mfg"
    ],
    "wof:name":"Tinas Sewing",
    "wof:placetype":"venue"
},
  "geometry": {"coordinates":[-111.789614,40.391914],"type":"Point"}
}