{
  "type": "Feature",
  "properties": {
    "iso:country":"US",
    "sg:address":"171 S Main St",
    "sg:city":"Hurricane",
    "sg:classifiers":[
        {
            "category":"Organizations",
            "subcategory":"Non-profit Organization",
            "type":"Services"
        }
    ],
    "sg:phone":"+1 435 635 7333",
    "sg:postcode":"84737",
    "sg:province":"UT",
    "sg:tags":[
        "information",
        "alcoholism",
        "treatment"
    ],
    "wof:name":"TIC",
    "wof:placetype":"venue"
},
  "geometry": {"coordinates":[-113.288037,37.174026],"type":"Point"}
}