{
  "type": "Feature",
  "properties": {
    "iso:country":"US",
    "sg:address":"1481 W 13200 S",
    "sg:city":"Riverton",
    "sg:classifiers":[
        {
            "category":"Building & Trades",
            "subcategory":"Construction",
            "type":"Services"
        }
    ],
    "sg:phone":"+1 801 446 1292",
    "sg:postcode":"84065",
    "sg:province":"UT",
    "sg:tags":[
        "contractor"
    ],
    "wof:name":"Ace Gutter",
    "wof:placetype":"venue"
},
  "geometry": {"coordinates":[-111.93111,40.511371],"type":"Point"}
}