{
  "type": "Feature",
  "properties": {
    "iso:country":"US",
    "sg:address":"5150 W 4820 S",
    "sg:city":"Salt Lake City",
    "sg:classifiers":[
        {
            "category":"Manufacturing",
            "subcategory":"Printing",
            "type":"Manufacturing & Wholesale Goods"
        }
    ],
    "sg:phone":"+1 801 963 9267",
    "sg:postcode":"84118",
    "sg:province":"UT",
    "sg:tags":[
        "telephone",
        "publishing"
    ],
    "wof:name":"Local Pages Inc",
    "wof:placetype":"venue"
},
  "geometry": {"coordinates":[-112.013712,40.665532],"type":"Point"}
}