{
  "type": "Feature",
  "properties": {
    "iso:country":"US",
    "sg:address":"330 E State Rd",
    "sg:city":"Pleasant Grove",
    "sg:classifiers":[
        {
            "category":"Restaurant",
            "type":"Food & Drink"
        }
    ],
    "sg:menulink":"http://www.allmenus.com/ut/american-fork-pleasant-grove/35412-los-compadres/menu/",
    "sg:phone":"+1 801 796 0979",
    "sg:postcode":"84062",
    "sg:province":"UT",
    "sg:tags":[
        "mexican"
    ],
    "wof:name":"Los Compadres",
    "wof:placetype":"venue"
},
  "geometry": {"coordinates":[-111.735202,40.354849],"type":"Point"}
}