{
  "type": "Feature",
  "properties": {
    "iso:country":"US",
    "sg:address":"1616 Snow Queen Pl",
    "sg:city":"Salt Lake City",
    "sg:classifiers":[
        {
            "category":"Real Estate",
            "subcategory":"Real Estate Operator",
            "type":"Services"
        }
    ],
    "sg:phone":"+1 801 973 0838",
    "sg:postcode":"84104",
    "sg:province":"UT",
    "sg:tags":[
        "apartment",
        "complex"
    ],
    "wof:name":"Heartland Apts",
    "wof:placetype":"venue"
},
  "geometry": {"coordinates":[-111.935204,40.734035],"type":"Point"}
}