{
  "type": "Feature",
  "properties": {
    "iso:country":"US",
    "sg:address":"9418 Sunset Ridge Dr",
    "sg:city":"Sandy",
    "sg:classifiers":[
        {
            "category":"Shopping",
            "type":"Retail Goods"
        }
    ],
    "sg:phone":"+1 801 942 3720",
    "sg:postcode":"84092",
    "sg:province":"UT",
    "sg:tags":[
        "merchandise"
    ],
    "wof:name":"Scents N Such",
    "wof:placetype":"venue"
},
  "geometry": {"coordinates":[-111.809459,40.579539],"type":"Point"}
}