{
  "type": "Feature",
  "properties": {
    "iso:country":"US",
    "sg:address":"2762 W 12600 S",
    "sg:city":"Riverton",
    "sg:classifiers":[
        {
            "category":"Restaurant",
            "type":"Food & Drink"
        }
    ],
    "sg:menulink":"http://www.allmenus.com/ut/salt-lake-city/214594-5-buck-pizza/menu/",
    "sg:phone":"+1 801 302 9291",
    "sg:postcode":"84065",
    "sg:province":"UT",
    "sg:tags":[
        "american",
        "pizza"
    ],
    "wof:name":"5 Buck Pizza",
    "wof:placetype":"venue"
},
  "geometry": {"coordinates":[-111.95896,40.5227],"type":"Point"}
}