{
  "type": "Feature",
  "properties": {
    "iso:country":"US",
    "sg:address":"6975 Union Park Center",
    "sg:city":"Midvale",
    "sg:classifiers":[
        {
            "category":"Real Estate",
            "subcategory":"Real Estate Agent",
            "type":"Services"
        }
    ],
    "sg:phone":"+1 801 990 9514",
    "sg:postcode":"84047",
    "sg:province":"UT",
    "sg:tags":[
        "broker"
    ],
    "wof:name":"Builders Development Group Inc",
    "wof:placetype":"venue"
},
  "geometry": {"coordinates":[-111.86049800000001,40.62518],"type":"Point"}
}