{
  "type": "Feature",
  "properties": {
    "iso:country":"US",
    "sg:address":"8455 W 2700 S",
    "sg:city":"Magna",
    "sg:classifiers":[
        {
            "category":"Shopping",
            "subcategory":"Used Merchandise",
            "type":"Retail Goods"
        }
    ],
    "sg:phone":"+1 801 250 5495",
    "sg:postcode":"84044",
    "sg:province":"UT",
    "sg:tags":[
        "shop",
        "thrift"
    ],
    "wof:name":"Penny Pinchers",
    "wof:placetype":"venue"
},
  "geometry": {"coordinates":[-112.09291,40.711121],"type":"Point"}
}