{
  "type": "Feature",
  "properties": {
    "iso:country":"US",
    "sg:address":"2221 E Wilmott Dr",
    "sg:city":"Salt Lake City",
    "sg:classifiers":[
        {
            "category":"Real Estate",
            "subcategory":"Architect",
            "type":"Services"
        }
    ],
    "sg:phone":"+1 801 277 2767",
    "sg:postcode":"84109",
    "sg:province":"UT",
    "sg:tags":[
        "architectural"
    ],
    "wof:name":"Pettit M Lester Jr Design",
    "wof:placetype":"venue"
},
  "geometry": {"coordinates":[-111.82658000000001,40.693373],"type":"Point"}
}