{
  "type": "Feature",
  "properties": {
    "iso:country":"US",
    "sg:address":"20 S 850 W",
    "sg:city":"Hurricane",
    "sg:classifiers":[
        {
            "category":"Banks & Credit Unions",
            "subcategory":"Bank",
            "type":"Services"
        }
    ],
    "sg:phone":"+1 435 635 3394",
    "sg:postcode":"84737",
    "sg:province":"UT",
    "sg:tags":[
        "loan",
        "broker"
    ],
    "wof:name":"Preferred Mortgage Brokers",
    "wof:placetype":"venue"
},
  "geometry": {"coordinates":[-113.304407,37.175628],"type":"Point"}
}