{
  "type": "Feature",
  "properties": {
    "iso:country":"US",
    "sg:address":"279 Edgehill Dr",
    "sg:city":"Kaysville",
    "sg:classifiers":[
        {
            "category":"Professional",
            "subcategory":"Management & Consulting",
            "type":"Services"
        }
    ],
    "sg:phone":"+1 801 444 3674",
    "sg:postcode":"84037",
    "sg:province":"UT",
    "wof:name":"Elink Marketing",
    "wof:placetype":"venue"
},
  "geometry": {"coordinates":[-111.91576000000001,41.030603],"type":"Point"}
}