{
  "type": "Feature",
  "properties": {
    "iso:country":"US",
    "sg:address":"5089 S 900 East St",
    "sg:city":"Salt Lake City",
    "sg:classifiers":[
        {
            "category":"Health Services",
            "subcategory":"Doctor",
            "type":"Services"
        }
    ],
    "sg:phone":"+1 801 265 0173",
    "sg:postcode":"84117",
    "sg:province":"UT",
    "sg:tags":[
        "physician",
        "medical",
        "surgeon"
    ],
    "wof:name":"Arlington Park Surgery Ctr LLC",
    "wof:placetype":"venue"
},
  "geometry": {"coordinates":[-111.865302,40.660872],"type":"Point"}
}