{
  "type": "Feature",
  "properties": {
    "iso:country":"US",
    "sg:address":"1030 Military Dr",
    "sg:city":"Salt Lake City",
    "sg:classifiers":[
        {
            "category":"Shopping",
            "subcategory":"Used Merchandise",
            "type":"Retail Goods"
        }
    ],
    "sg:phone":"+1 801 583 0705",
    "sg:postcode":"84105",
    "sg:province":"UT",
    "wof:name":"Temptations Plus Inc",
    "wof:placetype":"venue"
},
  "geometry": {"coordinates":[-111.842258,40.748248],"type":"Point"}
}