{
  "type": "Feature",
  "properties": {
    "iso:country":"US",
    "sg:address":"110 W 300 North St",
    "sg:city":"Wales",
    "sg:classifiers":[
        {
            "category":"Government",
            "subcategory":"Post Office",
            "type":"Public Place"
        }
    ],
    "sg:phone":"+1 435 436 8464",
    "sg:postcode":"84667",
    "sg:province":"UT",
    "wof:name":"US Post Office",
    "wof:placetype":"venue"
},
  "geometry": {"coordinates":[-111.637068,39.489786],"type":"Point"}
}