{
  "type": "Feature",
  "properties": {
    "iso:country":"US",
    "sg:address":"324 E Stonehedge Dr",
    "sg:city":"Salt Lake City",
    "sg:classifiers":[
        {
            "category":"Freight",
            "type":"Transportation"
        }
    ],
    "sg:phone":"+1 801 685 0640",
    "sg:postcode":"84107",
    "sg:province":"UT",
    "wof:name":"Mdj Transportation Inc",
    "wof:placetype":"venue"
},
  "geometry": {"coordinates":[-111.877561,40.681112],"type":"Point"}
}