{
  "type": "Feature",
  "properties": {
    "iso:country":"US",
    "sg:address":"157 N Commercial St",
    "sg:city":"Morgan",
    "sg:classifiers":[
        {
            "category":"Insurance",
            "subcategory":"Insurance Agent",
            "type":"Services"
        }
    ],
    "sg:phone":"+1 801 829 6303",
    "sg:postcode":"84050",
    "sg:province":"UT",
    "wof:name":"Neil O Maxwell Insurance",
    "wof:placetype":"venue"
},
  "geometry": {"coordinates":[-111.67303200000001,41.044617],"type":"Point"}
}