{
  "type": "Feature",
  "properties": {
    "iso:country":"US",
    "sg:address":"6755 W 3800 S",
    "sg:city":"West Valley",
    "sg:classifiers":[
        {
            "category":"Organizations",
            "subcategory":"Religious Organization",
            "type":"Services"
        }
    ],
    "sg:phone":"+1 801 252 2583",
    "sg:postcode":"84128",
    "sg:province":"UT",
    "sg:tags":[
        "church"
    ],
    "wof:name":"Church Of Jesus Christ Of Lds",
    "wof:placetype":"venue"
},
  "geometry": {"coordinates":[-112.051422,40.689199],"type":"Point"}
}