{
  "type": "Feature",
  "properties": {
    "iso:country":"US",
    "sg:address":"4041 Adams Cir",
    "sg:city":"Hill Afb",
    "sg:classifiers":[
        {
            "category":"Real Estate",
            "subcategory":"Real Estate Agent",
            "type":"Services"
        }
    ],
    "sg:phone":"+1 801 645 1985",
    "sg:postcode":"84056",
    "sg:province":"UT",
    "sg:tags":[
        "management",
        "business"
    ],
    "wof:name":"Young's Properties LLC",
    "wof:placetype":"venue"
},
  "geometry": {"coordinates":[-112.003068,41.108051],"type":"Point"}
}