{
  "type": "Feature",
  "properties": {
    "iso:country":"US",
    "sg:address":"28 S 400 E",
    "sg:city":"Salt Lake City",
    "sg:classifiers":[
        {
            "category":"Wholesale",
            "subcategory":"Machinery & Supplies",
            "type":"Manufacturing & Wholesale Goods"
        }
    ],
    "sg:phone":"+1 801 532 2767",
    "sg:postcode":"84111",
    "sg:province":"UT",
    "sg:tags":[
        "equipment",
        "industrial",
        "safety"
    ],
    "wof:name":"Aros Inc",
    "wof:placetype":"venue"
},
  "geometry": {"coordinates":[-111.879716,40.769176],"type":"Point"}
}