{
  "type": "Feature",
  "properties": {
    "iso:country":"US",
    "sg:address":"315 E 500 N",
    "sg:city":"American Fork",
    "sg:classifiers":[
        {
            "category":"Real Estate",
            "subcategory":"Real Estate Agent",
            "type":"Services"
        }
    ],
    "sg:phone":"+1 801 763 1001",
    "sg:postcode":"84003",
    "sg:province":"UT",
    "wof:name":"Prudential Utah Real Estate",
    "wof:placetype":"venue"
},
  "geometry": {"coordinates":[-111.78808600000001,40.386676],"type":"Point"}
}