{
  "type": "Feature",
  "properties": {
    "iso:country":"US",
    "sg:address":"1331 E 600 N",
    "sg:city":"Orem",
    "sg:classifiers":[
        {
            "category":"Organizations",
            "subcategory":"Labor Organization",
            "type":"Services"
        }
    ],
    "sg:phone":"+1 801 225 6792",
    "sg:postcode":"84097",
    "sg:province":"UT",
    "wof:name":"Mehlhoff Prpts Springville Lc",
    "wof:placetype":"venue"
},
  "geometry": {"coordinates":[-111.66398,40.30855],"type":"Point"}
}