{
  "type": "Feature",
  "properties": {
    "iso:country":"US",
    "sg:address":"132 E St",
    "sg:city":"Salt Lake City",
    "sg:classifiers":[
        {
            "category":"Manufacturing",
            "subcategory":"Furniture",
            "type":"Manufacturing & Wholesale Goods"
        }
    ],
    "sg:phone":"+1 801 534 1014",
    "sg:postcode":"84103",
    "sg:province":"UT",
    "sg:tags":[
        "interior",
        "design",
        "wood",
        "upholstering",
        "mfg"
    ],
    "wof:name":"F Weixler Co Inc",
    "wof:placetype":"venue"
},
  "geometry": {"coordinates":[-111.87763699999999,40.772079],"type":"Point"}
}