{
  "type": "Feature",
  "properties": {
    "iso:country":"US",
    "sg:address":"610 S 900 W",
    "sg:city":"Salt Lake City",
    "sg:classifiers":[
        {
            "category":"Real Estate",
            "subcategory":"Real Estate Operator",
            "type":"Services"
        }
    ],
    "sg:phone":"+1 801 532 0845",
    "sg:postcode":"84104",
    "sg:province":"UT",
    "sg:tags":[
        "apartment"
    ],
    "wof:name":"Riverside Apartments",
    "wof:placetype":"venue"
},
  "geometry": {"coordinates":[-111.91689599999999,40.755425],"type":"Point"}
}