{
  "type": "Feature",
  "properties": {
    "iso:country":"US",
    "sg:address":"1611 S 925 W",
    "sg:city":"Woods Cross",
    "sg:classifiers":[
        {
            "category":"Professional",
            "type":"Services"
        }
    ],
    "sg:phone":"+1 801 397 0044",
    "sg:postcode":"84087",
    "sg:province":"UT",
    "wof:name":"Bakers Creations LLC",
    "wof:placetype":"venue"
},
  "geometry": {"coordinates":[-111.905197,40.873651],"type":"Point"}
}