{
  "type": "Feature",
  "properties": {
    "iso:country":"US",
    "sg:address":"693 E Capitol Blvd",
    "sg:city":"Salt Lake City",
    "sg:classifiers":[
        {
            "category":"Shopping",
            "type":"Retail Goods"
        }
    ],
    "sg:phone":"+1 801 364 1862",
    "sg:postcode":"84103",
    "sg:province":"UT",
    "sg:tags":[
        "merchandise"
    ],
    "wof:name":"Business Performance Group",
    "wof:placetype":"venue"
},
  "geometry": {"coordinates":[-111.885941,40.783534],"type":"Point"}
}