{
  "type": "Feature",
  "properties": {
    "iso:country":"US",
    "sg:address":"800 N 500 E",
    "sg:city":"Payson",
    "sg:classifiers":[
        {
            "category":"Organizations",
            "subcategory":"Religious Organization",
            "type":"Services"
        }
    ],
    "sg:phone":"+1 435 896 0478",
    "sg:postcode":"84651",
    "sg:province":"UT",
    "sg:tags":[
        "church"
    ],
    "wof:name":"Jesus Christ Of Lds",
    "wof:placetype":"venue"
},
  "geometry": {"coordinates":[-111.72542300000001,40.055914],"type":"Point"}
}