{
  "type": "Feature",
  "properties": {
    "iso:country":"US",
    "sg:address":"10 W Broadway",
    "sg:city":"Salt Lake City",
    "sg:classifiers":[
        {
            "category":"Government",
            "subcategory":"Office",
            "type":"Public Place"
        }
    ],
    "sg:phone":"+1 801 524 5706",
    "sg:postcode":"84101",
    "sg:province":"UT",
    "sg:tags":[
        "federal"
    ],
    "wof:name":"US Labor Dept Wage & Hour Div",
    "wof:placetype":"venue"
},
  "geometry": {"coordinates":[-111.893771,40.762898],"type":"Point"}
}