{
  "type": "Feature",
  "properties": {
    "iso:country":"US",
    "sg:address":"2712 S 3600 W",
    "sg:city":"Salt Lake City",
    "sg:classifiers":[
        {
            "category":"Health Services",
            "subcategory":"Health Practitioner",
            "type":"Services"
        }
    ],
    "sg:phone":"+1 801 965 8162",
    "sg:postcode":"84119",
    "sg:province":"UT",
    "wof:name":"Past PC",
    "wof:placetype":"venue"
},
  "geometry": {"coordinates":[-111.977216,40.710542],"type":"Point"}
}