{
  "type": "Feature",
  "properties": {
    "iso:country":"US",
    "sg:address":"8938 S Sun Leaf Dr",
    "sg:city":"West Jordan",
    "sg:classifiers":[
        {
            "category":"Personal",
            "subcategory":"Beauty Salon",
            "type":"Services"
        }
    ],
    "sg:phone":"+1 801 282 0543",
    "sg:postcode":"84088",
    "sg:province":"UT",
    "sg:tags":[
        "shop"
    ],
    "wof:name":"Samanthas Shear Expressions",
    "wof:placetype":"venue"
},
  "geometry": {"coordinates":[-111.99415999999999,40.588925],"type":"Point"}
}