{
  "type": "Feature",
  "properties": {
    "iso:country":"US",
    "sg:address":"3401 W 3540 S",
    "sg:city":"Salt Lake City",
    "sg:classifiers":[
        {
            "category":"Wholesale",
            "subcategory":"Sporting Goods",
            "type":"Manufacturing & Wholesale Goods"
        }
    ],
    "sg:phone":"+1 801 557 6182",
    "sg:postcode":"84119",
    "sg:province":"UT",
    "wof:name":"Custom Fly",
    "wof:placetype":"venue"
},
  "geometry": {"coordinates":[-111.973204,40.69564],"type":"Point"}
}