{
  "type": "Feature",
  "properties": {
    "iso:country":"US",
    "sg:address":"3400 N 3500 W",
    "sg:city":"Vernal",
    "sg:classifiers":[
        {
            "category":"Manufacturing",
            "subcategory":"Lumber",
            "type":"Manufacturing & Wholesale Goods"
        }
    ],
    "sg:phone":"+1 435 789 3397",
    "sg:postcode":"84078",
    "sg:province":"UT",
    "sg:tags":[
        "fire",
        "fighting"
    ],
    "wof:name":"Rocky Mountain Fire Inc",
    "wof:placetype":"venue"
},
  "geometry": {"coordinates":[-109.59565499999999,40.497209],"type":"Point"}
}