{
  "type": "Feature",
  "properties": {
    "iso:country":"US",
    "sg:address":"2724 S 3600 W",
    "sg:city":"West Valley",
    "sg:classifiers":[
        {
            "category":"Building & Trades",
            "subcategory":"Construction",
            "type":"Services"
        }
    ],
    "sg:phone":"+1 801 969 9665",
    "sg:postcode":"84119",
    "sg:province":"UT",
    "sg:tags":[
        "roofing",
        "contractor"
    ],
    "wof:name":"Professional Roofing Svc",
    "wof:placetype":"venue"
},
  "geometry": {"coordinates":[-111.977217,40.710776],"type":"Point"}
}