{
  "type": "Feature",
  "properties": {
    "iso:country":"US",
    "sg:address":"26 S Main St",
    "sg:city":"Payson",
    "sg:classifiers":[
        {
            "category":"Education",
            "subcategory":"Dance Studio",
            "type":"Public Place"
        }
    ],
    "sg:phone":"+1 801 465 1499",
    "sg:postcode":"84651",
    "sg:province":"UT",
    "sg:tags":[
        "instruction",
        "dancing"
    ],
    "wof:name":"Dance Technique",
    "wof:placetype":"venue"
},
  "geometry": {"coordinates":[-111.73235699999999,40.043324],"type":"Point"}
}