{
  "type": "Feature",
  "properties": {
    "iso:country":"US",
    "sg:address":"250 N Main St",
    "sg:city":"Tooele",
    "sg:classifiers":[
        {
            "category":"Food & Beverages",
            "subcategory":"Groceries & Convenience Stores",
            "type":"Retail Goods"
        }
    ],
    "sg:phone":"+1 435 882 4616",
    "sg:postcode":"84074",
    "sg:province":"UT",
    "sg:tags":[
        "supermarket",
        "chain"
    ],
    "wof:name":"Albertsons 368",
    "wof:placetype":"venue"
},
  "geometry": {"coordinates":[-112.29840900000001,40.53746],"type":"Point"}
}