{
  "type": "Feature",
  "properties": {
    "iso:country":"US",
    "sg:address":"8134 Oak Creek Dr",
    "sg:city":"Sandy",
    "sg:classifiers":[
        {
            "category":"Manufacturing",
            "subcategory":"Apparel",
            "type":"Manufacturing & Wholesale Goods"
        }
    ],
    "sg:phone":"+1 801 944 4556",
    "sg:postcode":"84093",
    "sg:province":"UT",
    "sg:tags":[
        "textile",
        "product",
        "fabricated",
        "mfg"
    ],
    "wof:name":"Russell Bringhurst",
    "wof:placetype":"venue"
},
  "geometry": {"coordinates":[-111.819323,40.603953],"type":"Point"}
}