{
  "type": "Feature",
  "properties": {
    "iso:country":"US",
    "sg:address":"1060 E 100 S",
    "sg:city":"Salt Lake City",
    "sg:classifiers":[
        {
            "category":"Health Services",
            "subcategory":"Doctor",
            "type":"Services"
        }
    ],
    "sg:phone":"+1 801 322 5423",
    "sg:postcode":"84102",
    "sg:province":"UT",
    "sg:tags":[
        "dentist"
    ],
    "wof:name":"Crayton R Walker DDS",
    "wof:placetype":"venue"
},
  "geometry": {"coordinates":[-111.860032,40.767105],"type":"Point"}
}