{
  "type": "Feature",
  "properties": {
    "iso:country":"US",
    "sg:address":"1975 S 2300 E",
    "sg:city":"Salt Lake City",
    "sg:classifiers":[
        {
            "category":"Organizations",
            "subcategory":"Religious Organization",
            "type":"Services"
        }
    ],
    "sg:phone":"+1 801 485 5610",
    "sg:postcode":"84108",
    "sg:province":"UT",
    "sg:tags":[
        "church"
    ],
    "wof:name":"St Ambrose Catholic Church",
    "wof:placetype":"venue"
},
  "geometry": {"coordinates":[-111.82499900000001,40.726938],"type":"Point"}
}