{
  "type": "Feature",
  "properties": {
    "iso:country":"US",
    "sg:address":"3596 Atlas Way",
    "sg:city":"Salt Lake City",
    "sg:classifiers":[
        {
            "category":"Professional",
            "subcategory":"Accounting & Tax Preparation",
            "type":"Services"
        }
    ],
    "sg:phone":"+1 801 955 7356",
    "sg:postcode":"84120",
    "sg:province":"UT",
    "sg:tags":[
        "accountant"
    ],
    "wof:name":"KLB Enterprises",
    "wof:placetype":"venue"
},
  "geometry": {"coordinates":[-112.001321,40.694619],"type":"Point"}
}