{
  "type": "Feature",
  "properties": {
    "iso:country":"US",
    "sg:address":"1315 Lowell Ave",
    "sg:city":"Park City",
    "sg:classifiers":[
        {
            "category":"Recreation",
            "type":"Entertainment"
        }
    ],
    "sg:phone":"+1 435 658 5544",
    "sg:postcode":"84060",
    "sg:province":"UT",
    "sg:tags":[
        "equipment",
        "skiing"
    ],
    "sg:website":"www.parkcitymountain.com",
    "wof:name":"Legacy Sports",
    "wof:placetype":"venue"
},
  "geometry": {"coordinates":[-111.500944,40.646982],"type":"Point"}
}