{
  "type": "Feature",
  "properties": {
    "iso:country":"US",
    "sg:address":"1077 E 1750 S",
    "sg:city":"Vernal",
    "sg:classifiers":[
        {
            "category":"Building & Trades",
            "subcategory":"Construction",
            "type":"Services"
        }
    ],
    "sg:phone":"+1 435 790 8534",
    "sg:postcode":"84078",
    "sg:province":"UT",
    "sg:tags":[
        "special",
        "contractor"
    ],
    "wof:name":"Uffords Insulation Service",
    "wof:placetype":"venue"
},
  "geometry": {"coordinates":[-109.500755,40.430438],"type":"Point"}
}