{
  "type": "Feature",
  "properties": {
    "iso:country":"US",
    "sg:address":"693 E 100 S",
    "sg:city":"Spanish Fork",
    "sg:classifiers":[
        {
            "category":"Shopping",
            "subcategory":"Hobbies, Toys, & Games",
            "type":"Retail Goods"
        },
        {
            "category":"Shopping",
            "subcategory":"Jewelry",
            "type":"Retail Goods"
        }
    ],
    "sg:phone":"+1 801 798 2758",
    "sg:postcode":"84660",
    "sg:province":"UT",
    "sg:tags":[
        "shop",
        "merchandise",
        "rock"
    ],
    "wof:name":"Larry's Jewelry & Rock Shop",
    "wof:placetype":"venue"
},
  "geometry": {"coordinates":[-111.642911,40.108469],"type":"Point"}
}