{
  "type": "Feature",
  "properties": {
    "iso:country":"US",
    "sg:address":"5612 E 2200 N",
    "sg:city":"Eden",
    "sg:classifiers":[
        {
            "category":"Personal",
            "type":"Services"
        }
    ],
    "sg:phone":"+1 801 745 4009",
    "sg:postcode":"84310",
    "sg:province":"UT",
    "wof:name":"Hearthside Reception Center",
    "wof:placetype":"venue"
},
  "geometry": {"coordinates":[-111.812642,41.298872],"type":"Point"}
}