{
  "type": "Feature",
  "properties": {
    "iso:country":"US",
    "sg:address":"4350 Richard Crest Dr",
    "sg:city":"Salt Lake City",
    "sg:classifiers":[
        {
            "category":"Building & Trades",
            "subcategory":"Construction",
            "type":"Services"
        }
    ],
    "sg:phone":"+1 801 969 6515",
    "sg:postcode":"84119",
    "sg:province":"UT",
    "sg:tags":[
        "contractor"
    ],
    "wof:name":"A A A Demolition & Excavating",
    "wof:placetype":"venue"
},
  "geometry": {"coordinates":[-111.951335,40.676676],"type":"Point"}
}