{
  "type": "Feature",
  "properties": {
    "iso:country":"US",
    "sg:address":"9679 S 700 E",
    "sg:city":"Sandy",
    "sg:classifiers":[
        {
            "category":"Wholesale",
            "subcategory":"Machinery & Supplies",
            "type":"Manufacturing & Wholesale Goods"
        }
    ],
    "sg:phone":"+1 801 572 0149",
    "sg:postcode":"84070",
    "sg:province":"UT",
    "sg:tags":[
        "car"
    ],
    "wof:name":"Bonneville Car Wash Equipment",
    "wof:placetype":"venue"
},
  "geometry": {"coordinates":[-111.87209799999999,40.573558],"type":"Point"}
}