{
  "type": "Feature",
  "properties": {
    "iso:country":"US",
    "sg:address":"102 W 500 S",
    "sg:city":"Salt Lake City",
    "sg:classifiers":[
        {
            "category":"Professional",
            "subcategory":"Engineering",
            "type":"Services"
        }
    ],
    "sg:phone":"+1 801 328 8800",
    "sg:postcode":"84101",
    "sg:province":"UT",
    "sg:tags":[
        "engineer"
    ],
    "wof:name":"James D Graham & Assoc Inc",
    "wof:placetype":"venue"
},
  "geometry": {"coordinates":[-111.896766,40.758548],"type":"Point"}
}