{
  "type": "Feature",
  "properties": {
    "iso:country":"US",
    "sg:address":"3489 S 2000 E",
    "sg:city":"Salt Lake City",
    "sg:classifiers":[
        {
            "category":"Building & Trades",
            "subcategory":"Construction",
            "type":"Services"
        }
    ],
    "sg:phone":"+1 801 272 1400",
    "sg:postcode":"84109",
    "sg:province":"UT",
    "sg:tags":[
        "specializing",
        "contractor",
        "remodeling",
        "general"
    ],
    "wof:name":"Andy Monaco Construction Co",
    "wof:placetype":"venue"
},
  "geometry": {"coordinates":[-111.833386,40.695237],"type":"Point"}
}