{
  "type": "Feature",
  "properties": {
    "iso:country":"US",
    "sg:address":"1323 E Gentile St",
    "sg:city":"Layton",
    "sg:classifiers":[
        {
            "category":"Organizations",
            "subcategory":"Religious Organization",
            "type":"Services"
        }
    ],
    "sg:phone":"+1 801 544 1419",
    "sg:postcode":"84040",
    "sg:province":"UT",
    "sg:tags":[
        "church"
    ],
    "wof:name":"Jehovah's Witnesses",
    "wof:placetype":"venue"
},
  "geometry": {"coordinates":[-111.942367,41.062221],"type":"Point"}
}