{
  "type": "Feature",
  "properties": {
    "iso:country":"US",
    "sg:address":"4835 Highland Dr",
    "sg:city":"Salt Lake City",
    "sg:classifiers":[
        {
            "category":"Shopping",
            "subcategory":"Clothing, Apparel, & Fashions",
            "type":"Retail Goods"
        }
    ],
    "sg:phone":"+1 801 272 9795",
    "sg:postcode":"84117",
    "sg:province":"UT",
    "sg:website":"www.wetseal.com",
    "wof:name":"Wet Seal",
    "wof:placetype":"venue"
},
  "geometry": {"coordinates":[-111.83904699999999,40.664914],"type":"Point"}
}