{
  "type": "Feature",
  "properties": {
    "iso:country":"US",
    "sg:address":"133 E Central St",
    "sg:city":"Monticello",
    "sg:classifiers":[
        {
            "category":"Restaurant",
            "type":"Food & Drink"
        }
    ],
    "sg:phone":"+1 435 587 5048",
    "sg:postcode":"84535",
    "sg:province":"UT",
    "wof:name":"Monticello Cross Roads",
    "wof:placetype":"venue"
},
  "geometry": {"coordinates":[-109.340474,37.872697],"type":"Point"}
}