{
  "type": "Feature",
  "properties": {
    "iso:country":"US",
    "sg:address":"2888 E 3300 S",
    "sg:city":"Salt Lake City",
    "sg:classifiers":[
        {
            "category":"Retail",
            "subcategory":"Auto Repair",
            "type":"Services"
        }
    ],
    "sg:phone":"+1 801 466 0792",
    "sg:postcode":"84109",
    "sg:province":"UT",
    "sg:tags":[
        "repairing",
        "automobile"
    ],
    "wof:name":"Stewish Automotive",
    "wof:placetype":"venue"
},
  "geometry": {"coordinates":[-111.809804,40.699768],"type":"Point"}
}