{
  "type": "Feature",
  "properties": {
    "iso:country":"US",
    "sg:address":"17 S Main St",
    "sg:city":"Payson",
    "sg:classifiers":[
        {
            "category":"Professional",
            "type":"Services"
        }
    ],
    "sg:phone":"+1 801 465 0367",
    "sg:postcode":"84651",
    "sg:province":"UT",
    "sg:tags":[
        "establishment"
    ],
    "wof:name":"Gingerbread House",
    "wof:placetype":"venue"
},
  "geometry": {"coordinates":[-111.732207,40.043417],"type":"Point"}
}