{
  "type": "Feature",
  "properties": {
    "iso:country":"US",
    "sg:address":"1995 Bountiful Blvd",
    "sg:city":"Bountiful",
    "sg:classifiers":[
        {
            "category":"Professional",
            "type":"Services"
        }
    ],
    "sg:phone":"+1 801 677 0165",
    "sg:postcode":"84010",
    "sg:province":"UT",
    "sg:tags":[
        "establishment"
    ],
    "wof:name":"South Davis Metro Fire Agency",
    "wof:placetype":"venue"
},
  "geometry": {"coordinates":[-111.848292,40.867087],"type":"Point"}
}