{
  "type": "Feature",
  "properties": {
    "iso:country":"US",
    "sg:address":"1240 E 100 S",
    "sg:city":"St George",
    "sg:classifiers":[
        {
            "category":"Insurance",
            "subcategory":"Title Insurance",
            "type":"Services"
        }
    ],
    "sg:phone":"+1 435 673 5491",
    "sg:postcode":"84790",
    "sg:province":"UT",
    "wof:name":"First American Title Insur Co",
    "wof:placetype":"venue"
},
  "geometry": {"coordinates":[-113.55643000000001,37.106325],"type":"Point"}
}