{
  "type": "Feature",
  "properties": {
    "iso:country":"US",
    "sg:address":"1998 N Redwood Rd",
    "sg:city":"Salt Lake City",
    "sg:classifiers":[
        {
            "category":"Manufacturing",
            "subcategory":"Tools & Machinery",
            "type":"Manufacturing & Wholesale Goods"
        }
    ],
    "sg:phone":"+1 801 363 8010",
    "sg:postcode":"84116",
    "sg:province":"UT",
    "sg:tags":[
        "machine",
        "shop"
    ],
    "sg:website":"www.hexadyneaviation.com",
    "wof:name":"Hexatron Engineering",
    "wof:placetype":"venue"
},
  "geometry": {"coordinates":[-111.938305,40.814989],"type":"Point"}
}