{
  "type": "Feature",
  "properties": {
    "iso:country":"US",
    "sg:address":"1275 E 820 N",
    "sg:city":"Provo",
    "sg:classifiers":[
        {
            "category":"Real Estate",
            "subcategory":"Real Estate Agent",
            "type":"Services"
        }
    ],
    "sg:phone":"+1 801 375 2626",
    "sg:postcode":"84606",
    "sg:province":"UT",
    "sg:tags":[
        "bakery",
        "retail"
    ],
    "wof:name":"Real Estate Market Place",
    "wof:placetype":"venue"
},
  "geometry": {"coordinates":[-111.636156,40.244897],"type":"Point"}
}