{
  "type": "Feature",
  "properties": {
    "iso:country":"US",
    "sg:address":"10161 N 5890 West St",
    "sg:city":"Highland",
    "sg:classifiers":[
        {
            "category":"Building & Trades",
            "subcategory":"Cleaning & Sanitation",
            "type":"Services"
        }
    ],
    "sg:phone":"+1 801 376 7879",
    "sg:postcode":"84003",
    "sg:province":"UT",
    "sg:tags":[
        "janitor"
    ],
    "wof:name":"Spencer's Precision Cleaning",
    "wof:placetype":"venue"
},
  "geometry": {"coordinates":[-111.799493,40.417117],"type":"Point"}
}