{
  "type": "Feature",
  "properties": {
    "iso:country":"US",
    "sg:address":"1633 W 700 N",
    "sg:city":"Salt Lake City",
    "sg:classifiers":[
        {
            "category":"Utilities",
            "subcategory":"Mobile Phone",
            "type":"Services"
        }
    ],
    "sg:phone":"+1 801 366 9400",
    "sg:postcode":"84116",
    "sg:province":"UT",
    "sg:tags":[
        "telephone",
        "cellular"
    ],
    "wof:name":"Green Street Wireless",
    "wof:placetype":"venue"
},
  "geometry": {"coordinates":[-111.938335,40.784637],"type":"Point"}
}