{
  "type": "Feature",
  "properties": {
    "iso:country":"US",
    "sg:address":"1170 W 1000 S",
    "sg:city":"Logan",
    "sg:classifiers":[
        {
            "category":"Farming",
            "subcategory":"Livestock Farm",
            "type":"Manufacturing & Wholesale Goods"
        }
    ],
    "sg:phone":"+1 435 752 6930",
    "sg:postcode":"84321",
    "sg:province":"UT",
    "sg:tags":[
        "ranch"
    ],
    "wof:name":"Logan River Ranch",
    "wof:placetype":"venue"
},
  "geometry": {"coordinates":[-111.86017,41.713388],"type":"Point"}
}