{
  "type": "Feature",
  "properties": {
    "iso:country":"US",
    "sg:address":"2020 E 3300 S",
    "sg:city":"Salt Lake City",
    "sg:classifiers":[
        {
            "category":"Personal",
            "subcategory":"Barber",
            "type":"Services"
        }
    ],
    "sg:phone":"+1 801 486 1572",
    "sg:postcode":"84109",
    "sg:province":"UT",
    "sg:tags":[
        "shop"
    ],
    "wof:name":"2020 Barber Shop",
    "wof:placetype":"venue"
},
  "geometry": {"coordinates":[-111.83319,40.699795],"type":"Point"}
}