{
  "type": "Feature",
  "properties": {
    "iso:country":"US",
    "sg:address":"746 E 3800 N",
    "sg:city":"Provo",
    "sg:classifiers":[
        {
            "category":"Professional",
            "subcategory":"Computer Services",
            "type":"Services"
        }
    ],
    "sg:phone":"+1 801 226 0993",
    "sg:postcode":"84604",
    "sg:province":"UT",
    "sg:tags":[
        "programing",
        "custom"
    ],
    "wof:name":"Lansoft Inc",
    "wof:placetype":"venue"
},
  "geometry": {"coordinates":[-111.645167,40.28434],"type":"Point"}
}