{
  "type": "Feature",
  "properties": {
    "iso:country":"US",
    "sg:address":"2780 N 4800 W",
    "sg:city":"Corinne",
    "sg:classifiers":[
        {
            "category":"Freight",
            "type":"Transportation"
        }
    ],
    "sg:phone":"+1 435 744 5537",
    "sg:postcode":"84307",
    "sg:province":"UT",
    "sg:tags":[
        "trucking"
    ],
    "wof:name":"Archibald Petroleum Truck Inc",
    "wof:placetype":"venue"
},
  "geometry": {"coordinates":[-112.129479,41.556645],"type":"Point"}
}