{
  "type": "Feature",
  "properties": {
    "iso:country":"US",
    "sg:address":"2575 N 1500 W",
    "sg:city":"Vernal",
    "sg:classifiers":[
        {
            "category":"Organizations",
            "subcategory":"Religious Organization",
            "type":"Services"
        }
    ],
    "sg:phone":"+1 435 789 0355",
    "sg:postcode":"84078",
    "sg:province":"UT",
    "sg:tags":[
        "church"
    ],
    "wof:name":"Church Of Jesus Christ Of Lds",
    "wof:placetype":"venue"
},
  "geometry": {"coordinates":[-109.557947,40.491881],"type":"Point"}
}