{
  "type": "Feature",
  "properties": {
    "iso:country":"US",
    "sg:address":"1170 S 920 W",
    "sg:city":"Hurricane",
    "sg:classifiers":[
        {
            "category":"Building & Trades",
            "subcategory":"Construction",
            "type":"Services"
        }
    ],
    "sg:phone":"+1 435 635 2362",
    "sg:postcode":"84737",
    "sg:province":"UT",
    "sg:tags":[
        "hanging",
        "contractor"
    ],
    "wof:name":"R L Robson Painting Co Inc",
    "wof:placetype":"venue"
},
  "geometry": {"coordinates":[-113.305513,37.158024],"type":"Point"}
}