{
  "type": "Feature",
  "properties": {
    "iso:country":"US",
    "sg:address":"91 N Main St",
    "sg:city":"Cedar City",
    "sg:classifiers":[
        {
            "category":"Shopping",
            "subcategory":"Pharmacy",
            "type":"Retail Goods"
        }
    ],
    "sg:phone":"+1 435 586 9651",
    "sg:postcode":"84720",
    "sg:province":"UT",
    "wof:name":"Bullochs United Drugs",
    "wof:placetype":"venue"
},
  "geometry": {"coordinates":[-113.06177099999999,37.678989],"type":"Point"}
}