{
  "type": "Feature",
  "properties": {
    "iso:country":"US",
    "sg:address":"625 W Girard Ave",
    "sg:city":"Salt Lake City",
    "sg:classifiers":[
        {
            "category":"Organizations",
            "subcategory":"Professional Association",
            "type":"Services"
        }
    ],
    "sg:phone":"+1 801 532 3308",
    "sg:postcode":"84116",
    "sg:province":"UT",
    "sg:tags":[
        "chambers",
        "commerce"
    ],
    "wof:name":"Utah Hispanic Chamber-Cmmrc",
    "wof:placetype":"venue"
},
  "geometry": {"coordinates":[-111.90907300000001,40.781311],"type":"Point"}
}