{
  "type": "Feature",
  "properties": {
    "iso:country":"US",
    "sg:address":"2141 E Lincoln Ln",
    "sg:city":"Salt Lake City",
    "sg:classifiers":[
        {
            "category":"Home & Garden",
            "subcategory":"Building Materials",
            "type":"Retail Goods"
        }
    ],
    "sg:phone":"+1 801 557 0632",
    "sg:postcode":"84124",
    "sg:province":"UT",
    "sg:tags":[
        "door"
    ],
    "wof:name":"Will's Overhead Door",
    "wof:placetype":"venue"
},
  "geometry": {"coordinates":[-111.832149,40.680403],"type":"Point"}
}