{
  "type": "Feature",
  "properties": {
    "iso:country":"US",
    "sg:address":"930 E State St",
    "sg:city":"Lehi",
    "sg:classifiers":[
        {
            "category":"Banks & Credit Unions",
            "subcategory":"Investment Brokerage",
            "type":"Services"
        }
    ],
    "sg:phone":"+1 801 492 1820",
    "sg:postcode":"84043",
    "sg:province":"UT",
    "sg:tags":[
        "consultant",
        "planning",
        "financial"
    ],
    "sg:website":"www.th-financial.com",
    "wof:name":"AIG Royal Alliance",
    "wof:placetype":"venue"
},
  "geometry": {"coordinates":[-111.833653,40.391392],"type":"Point"}
}