{
  "type": "Feature",
  "properties": {
    "iso:country":"US",
    "sg:address":"3689 Highland Dr",
    "sg:city":"Salt Lake City",
    "sg:classifiers":[
        {
            "category":"Retail",
            "subcategory":"Portrait Studio",
            "type":"Services"
        }
    ],
    "sg:phone":"+1 801 487 4153",
    "sg:postcode":"84106",
    "sg:province":"UT",
    "sg:tags":[
        "photo"
    ],
    "wof:name":"Jaylynn Photography",
    "wof:placetype":"venue"
},
  "geometry": {"coordinates":[-111.84705,40.691108],"type":"Point"}
}