{
  "type": "Feature",
  "properties": {
    "iso:country":"US",
    "sg:address":"1772 S 375 E",
    "sg:city":"Springville",
    "sg:classifiers":[
        {
            "category":"Professional",
            "subcategory":"Management & Consulting",
            "type":"Services"
        }
    ],
    "sg:phone":"+1 801 489 7748",
    "sg:postcode":"84663",
    "sg:province":"UT",
    "sg:tags":[
        "business"
    ],
    "wof:name":"Wildland Restorations LLC",
    "wof:placetype":"venue"
},
  "geometry": {"coordinates":[-111.60350099999999,40.142849],"type":"Point"}
}