{
  "type": "Feature",
  "properties": {
    "iso:country":"US",
    "sg:address":"659 W 6960 S",
    "sg:city":"Midvale",
    "sg:classifiers":[
        {
            "category":"Building & Trades",
            "subcategory":"Construction",
            "type":"Services"
        }
    ],
    "sg:phone":"+1 801 255 1462",
    "sg:postcode":"84047",
    "sg:province":"UT",
    "sg:tags":[
        "concrete",
        "contractor"
    ],
    "wof:name":"Omega Pools Inc Aka Omega Gnte",
    "wof:placetype":"venue"
},
  "geometry": {"coordinates":[-111.90916,40.624946],"type":"Point"}
}