{
  "type": "Feature",
  "properties": {
    "iso:country":"US",
    "sg:address":"3596 Pleasant Green Dr",
    "sg:city":"Magna",
    "sg:classifiers":[
        {
            "category":"Professional",
            "subcategory":"Business Services",
            "type":"Services"
        },
        {
            "category":"Government",
            "subcategory":"Post Office",
            "type":"Public Place"
        }
    ],
    "sg:phone":"+1 801 259 9960",
    "sg:postcode":"84044",
    "sg:province":"UT",
    "sg:tags":[
        "delivery",
        "messenger",
        "courier"
    ],
    "wof:name":"Dave Serbeck Carriers",
    "wof:placetype":"venue"
},
  "geometry": {"coordinates":[-112.08466300000001,40.694341],"type":"Point"}
}