{
  "type": "Feature",
  "properties": {
    "iso:country":"US",
    "sg:address":"1762 S 900 E",
    "sg:city":"Salt Lake City",
    "sg:classifiers":[
        {
            "category":"Building & Trades",
            "subcategory":"Construction",
            "type":"Services"
        }
    ],
    "sg:phone":"+1 801 484 9777",
    "sg:postcode":"84105",
    "sg:province":"UT",
    "sg:tags":[
        "contractor"
    ],
    "sg:website":"www.realform.com",
    "wof:name":"Real Form Inc",
    "wof:placetype":"venue"
},
  "geometry": {"coordinates":[-111.865404,40.732411],"type":"Point"}
}