{
  "type": "Feature",
  "properties": {
    "iso:country":"US",
    "sg:address":"1057 Deborah Dr",
    "sg:city":"Bountiful",
    "sg:classifiers":[
        {
            "category":"Organizations",
            "subcategory":"Labor Organization",
            "type":"Services"
        }
    ],
    "sg:phone":"+1 801 298 2113",
    "sg:postcode":"84010",
    "sg:province":"UT",
    "wof:name":"Ryn Properties V Lc",
    "wof:placetype":"venue"
},
  "geometry": {"coordinates":[-111.861193,40.867806],"type":"Point"}
}