{
  "type": "Feature",
  "properties": {
    "iso:country":"US",
    "sg:address":"2645 Parleys Way",
    "sg:city":"Salt Lake City",
    "sg:classifiers":[
        {
            "category":"Sports & Exercise",
            "subcategory":"Gym",
            "type":"Entertainment"
        }
    ],
    "sg:phone":"+1 801 484 2828",
    "sg:postcode":"84109",
    "sg:province":"UT",
    "sg:tags":[
        "personal",
        "trainer",
        "fitness",
        "physical",
        "facility"
    ],
    "wof:name":"Foothill Personal Training LLC",
    "wof:placetype":"venue"
},
  "geometry": {"coordinates":[-111.817448,40.720948],"type":"Point"}
}