{
  "type": "Feature",
  "properties": {
    "iso:country":"US",
    "sg:address":"1712 N 1950 W",
    "sg:city":"Provo",
    "sg:classifiers":[
        {
            "category":"Wholesale",
            "subcategory":"Drugs",
            "type":"Manufacturing & Wholesale Goods"
        }
    ],
    "sg:phone":"+1 801 224 2616",
    "sg:postcode":"84604",
    "sg:province":"UT",
    "wof:name":"Nutri-Care International",
    "wof:placetype":"venue"
},
  "geometry": {"coordinates":[-111.691784,40.256563],"type":"Point"}
}