{
  "type": "Feature",
  "properties": {
    "iso:country":"US",
    "sg:address":"985 Sunset Ridge",
    "sg:city":"Logan",
    "sg:classifiers":[
        {
            "category":"Food & Beverages",
            "subcategory":"Dairy",
            "type":"Retail Goods"
        },
        {
            "category":"Wholesale",
            "subcategory":"Groceries",
            "type":"Manufacturing & Wholesale Goods"
        }
    ],
    "sg:phone":"+1 435 753 7766",
    "sg:postcode":"84321",
    "sg:province":"UT",
    "sg:tags":[
        "product",
        "broker"
    ],
    "wof:name":"Cache Valley Foods Inc",
    "wof:placetype":"venue"
},
  "geometry": {"coordinates":[-111.808424,41.730657],"type":"Point"}
}