{
  "type": "Feature",
  "properties": {
    "iso:country":"US",
    "sg:address":"238 Eugene St",
    "sg:city":"North Salt Lake",
    "sg:classifiers":[
        {
            "category":"Professional",
            "type":"Services"
        }
    ],
    "sg:phone":"+1 801 936 0440",
    "sg:postcode":"84054",
    "sg:province":"UT",
    "sg:tags":[
        "establishment"
    ],
    "wof:name":"Acteca Deoro",
    "wof:placetype":"venue"
},
  "geometry": {"coordinates":[-111.89968500000001,40.839211],"type":"Point"}
}