{
  "type": "Feature",
  "properties": {
    "iso:country":"US",
    "sg:address":"625 W Girard Ave",
    "sg:city":"Salt Lake City",
    "sg:classifiers":[
        {
            "category":"Professional",
            "subcategory":"Management & Consulting",
            "type":"Services"
        },
        {
            "category":"Real Estate",
            "subcategory":"Real Estate Operator",
            "type":"Services"
        }
    ],
    "sg:phone":"+1 801 521 1709",
    "sg:postcode":"84116",
    "sg:province":"UT",
    "sg:tags":[
        "building",
        "business",
        "parks"
    ],
    "wof:name":"Pete Suazo Business Center",
    "wof:placetype":"venue"
},
  "geometry": {"coordinates":[-111.90907300000001,40.781311],"type":"Point"}
}