{
  "type": "Feature",
  "properties": {
    "iso:country":"US",
    "sg:address":"960 N 1200 W",
    "sg:city":"Orem",
    "sg:classifiers":[
        {
            "category":"Freight",
            "type":"Transportation"
        }
    ],
    "sg:phone":"+1 801 221 9864",
    "sg:postcode":"84057",
    "sg:province":"UT",
    "sg:tags":[
        "trucking"
    ],
    "wof:name":"DST Express",
    "wof:placetype":"venue"
},
  "geometry": {"coordinates":[-111.72451,40.316312],"type":"Point"}
}