{
  "type": "Feature",
  "properties": {
    "iso:country":"US",
    "sg:address":"586 N Main St",
    "sg:city":"Payson",
    "sg:classifiers":[
        {
            "category":"Banks & Credit Unions",
            "subcategory":"Bank",
            "type":"Services"
        }
    ],
    "sg:phone":"+1 801 465 2600",
    "sg:postcode":"84651",
    "sg:province":"UT",
    "sg:tags":[
        "state",
        "commercial"
    ],
    "wof:name":"Far West Bank",
    "wof:placetype":"venue"
},
  "geometry": {"coordinates":[-111.73218,40.052147],"type":"Point"}
}