{
  "type": "Feature",
  "properties": {
    "iso:country":"US",
    "sg:address":"10450 S State St",
    "sg:city":"Sandy",
    "sg:classifiers":[
        {
            "category":"Restaurant",
            "type":"Food & Drink"
        }
    ],
    "sg:menulink":"http://www.allmenus.com/ut/salt-lake-city/132801-subway/menu/",
    "sg:phone":"+1 801 816 1394",
    "sg:postcode":"84070",
    "sg:province":"UT",
    "sg:tags":[
        "american",
        "sandwich"
    ],
    "wof:name":"Subway",
    "wof:placetype":"venue"
},
  "geometry": {"coordinates":[-111.890716,40.564053],"type":"Point"}
}