{
  "type": "Feature",
  "properties": {
    "iso:country":"US",
    "sg:address":"1558 E 1455 N",
    "sg:city":"Logan",
    "sg:classifiers":[
        {
            "category":"Sports & Exercise",
            "subcategory":"Gym",
            "type":"Entertainment"
        }
    ],
    "sg:phone":"+1 435 752 2619",
    "sg:postcode":"84341",
    "sg:province":"UT",
    "sg:tags":[
        "fitness",
        "physical",
        "facility"
    ],
    "wof:name":"Fitness Design & Developm",
    "wof:placetype":"venue"
},
  "geometry": {"coordinates":[-111.796053,41.757617],"type":"Point"}
}