{
  "type": "Feature",
  "properties": {
    "iso:country":"US",
    "sg:address":"10190 S 1300 W",
    "sg:city":"South Jordan",
    "sg:classifiers":[
        {
            "category":"Shopping",
            "subcategory":"Clothing, Apparel, & Fashions",
            "type":"Retail Goods"
        }
    ],
    "sg:phone":"+1 801 254 6731",
    "sg:postcode":"84095",
    "sg:province":"UT",
    "sg:tags":[
        "family"
    ],
    "wof:name":"Beehive Clothing",
    "wof:placetype":"venue"
},
  "geometry": {"coordinates":[-111.92919999999999,40.566109],"type":"Point"}
}