{
  "type": "Feature",
  "properties": {
    "iso:country":"US",
    "sg:address":"1466 W 3500 S",
    "sg:city":"Salt Lake City",
    "sg:classifiers":[
        {
            "category":"Real Estate",
            "subcategory":"Real Estate Operator",
            "type":"Services"
        }
    ],
    "sg:phone":"+1 801 975 1849",
    "sg:postcode":"84119",
    "sg:province":"UT",
    "sg:tags":[
        "building",
        "apartment"
    ],
    "wof:name":"Compass Villa Senior Housing",
    "wof:placetype":"venue"
},
  "geometry": {"coordinates":[-111.932261,40.698308],"type":"Point"}
}