{
  "type": "Feature",
  "properties": {
    "iso:country":"US",
    "sg:address":"8526 Johnson Way Dr",
    "sg:city":"Sandy",
    "sg:classifiers":[
        {
            "category":"Manufacturing",
            "subcategory":"Glass & Minerals",
            "type":"Manufacturing & Wholesale Goods"
        }
    ],
    "sg:phone":"+1 801 255 9070",
    "sg:postcode":"84094",
    "sg:province":"UT",
    "sg:tags":[
        "tile",
        "ceramic",
        "mfg"
    ],
    "wof:name":"BJ Ceramics",
    "wof:placetype":"venue"
},
  "geometry": {"coordinates":[-111.87045999999999,40.595415],"type":"Point"}
}