{
  "type": "Feature",
  "properties": {
    "iso:country":"US",
    "sg:address":"240 W Main St",
    "sg:city":"American Fork",
    "sg:classifiers":[
        {
            "category":"Professional",
            "subcategory":"Accounting & Tax Preparation",
            "type":"Services"
        }
    ],
    "sg:phone":"+1 801 756 1171",
    "sg:postcode":"84003",
    "sg:province":"UT",
    "wof:name":"Blackhurst Pharis C",
    "wof:placetype":"venue"
},
  "geometry": {"coordinates":[-111.805645,40.376908],"type":"Point"}
}