{
  "type": "Feature",
  "properties": {
    "iso:country":"US",
    "sg:address":"1163 E 3400 N",
    "sg:city":"Ogden",
    "sg:classifiers":[
        {
            "category":"Real Estate",
            "subcategory":"Real Estate Agent",
            "type":"Services"
        }
    ],
    "sg:phone":"+1 801 782 4394",
    "sg:postcode":"84414",
    "sg:province":"UT",
    "sg:tags":[
        "management"
    ],
    "wof:name":"Tealco LLC",
    "wof:placetype":"venue"
},
  "geometry": {"coordinates":[-111.944624,41.323231],"type":"Point"}
}