{
  "type": "Feature",
  "properties": {
    "iso:country":"US",
    "sg:address":"4555 S Redwood Rd",
    "sg:city":"Salt Lake City",
    "sg:classifiers":[
        {
            "category":"Shopping",
            "subcategory":"Computers & Home Electronics",
            "type":"Retail Goods"
        }
    ],
    "sg:phone":"+1 801 263 8246",
    "sg:postcode":"84123",
    "sg:province":"UT",
    "wof:name":"Numu Computers",
    "wof:placetype":"venue"
},
  "geometry": {"coordinates":[-111.93879,40.671117],"type":"Point"}
}