{
  "type": "Feature",
  "properties": {
    "iso:country":"US",
    "sg:address":"356 S Main St",
    "sg:city":"Blanding",
    "sg:classifiers":[
        {
            "category":"Health Services",
            "subcategory":"Hospital",
            "type":"Services"
        }
    ],
    "sg:phone":"+1 435 678 2992",
    "sg:postcode":"84511",
    "sg:province":"UT",
    "sg:tags":[
        "clinic",
        "mental",
        "outpatient",
        "specialty"
    ],
    "wof:name":"San Juan Counseling Center",
    "wof:placetype":"venue"
},
  "geometry": {"coordinates":[-109.478155,37.620321],"type":"Point"}
}