{
  "type": "Feature",
  "properties": {
    "iso:country":"US",
    "sg:address":"100 N 100 E",
    "sg:city":"Levan",
    "sg:classifiers":[
        {
            "category":"Restaurant",
            "type":"Food & Drink"
        }
    ],
    "sg:phone":"+1 435 623 0134",
    "sg:postcode":"84620",
    "sg:province":"UT",
    "wof:name":"Shake It Up",
    "wof:placetype":"venue"
},
  "geometry": {"coordinates":[-111.932142,38.92229],"type":"Point"}
}