{
  "type": "Feature",
  "properties": {
    "iso:country":"US",
    "sg:address":"16 S 100 E",
    "sg:city":"Moab",
    "sg:classifiers":[
        {
            "category":"Organizations",
            "subcategory":"Non-profit Organization",
            "type":"Services"
        },
        {
            "category":"Social Services",
            "type":"Services"
        }
    ],
    "sg:phone":"+1 435 259 4127",
    "sg:postcode":"84532",
    "sg:province":"UT",
    "sg:tags":[
        "for",
        "disability",
        "handicapped",
        "operator",
        "home",
        "mentally"
    ],
    "wof:name":"Rise Inc",
    "wof:placetype":"venue"
},
  "geometry": {"coordinates":[-109.54887100000001,38.573053],"type":"Point"}
}