{
  "type": "Feature",
  "properties": {
    "iso:country":"US",
    "sg:address":"590 W 500 S",
    "sg:city":"Price",
    "sg:classifiers":[
        {
            "category":"Education",
            "subcategory":"School",
            "type":"Public Place"
        }
    ],
    "sg:phone":"+1 435 637 0828",
    "sg:postcode":"84501",
    "sg:province":"UT",
    "wof:name":"Creek View Elementary School",
    "wof:placetype":"venue"
},
  "geometry": {"coordinates":[-110.818145,39.592146],"type":"Point"}
}