{
  "type": "Feature",
  "properties": {
    "iso:country":"US",
    "sg:address":"125 S 400 E",
    "sg:city":"Orem",
    "sg:classifiers":[
        {
            "category":"Organizations",
            "subcategory":"Religious Organization",
            "type":"Services"
        }
    ],
    "sg:phone":"+1 801 222 3185",
    "sg:postcode":"84097",
    "sg:province":"UT",
    "sg:tags":[
        "church"
    ],
    "wof:name":"Lds Seminary",
    "wof:placetype":"venue"
},
  "geometry": {"coordinates":[-111.685793,40.293753],"type":"Point"}
}