{
  "type": "Feature",
  "properties": {
    "iso:country":"US",
    "sg:address":"1810 S Hwy 89",
    "sg:city":"Brigham City",
    "sg:classifiers":[
        {
            "category":"Home & Garden",
            "subcategory":"Garden Supply",
            "type":"Retail Goods"
        }
    ],
    "sg:phone":"+1 435 723 7748",
    "sg:postcode":"84302",
    "sg:province":"UT",
    "sg:tags":[
        "nurseryman"
    ],
    "wof:name":"Alpine Gardens",
    "wof:placetype":"venue"
},
  "geometry": {"coordinates":[-112.023111,41.477541],"type":"Point"}
}