{
  "type": "Feature",
  "properties": {
    "iso:country":"US",
    "sg:address":"321 E 800 S",
    "sg:city":"Springville",
    "sg:classifiers":[
        {
            "category":"Professional",
            "subcategory":"Management & Consulting",
            "type":"Services"
        }
    ],
    "sg:phone":"+1 801 489 8263",
    "sg:postcode":"84663",
    "sg:province":"UT",
    "sg:tags":[
        "health",
        "care"
    ],
    "wof:name":"Traditions Health Care",
    "wof:placetype":"venue"
},
  "geometry": {"coordinates":[-111.604489,40.155373],"type":"Point"}
}