{
  "type": "Feature",
  "properties": {
    "iso:country":"US",
    "sg:address":"491 S Main St",
    "sg:city":"Cedar City",
    "sg:classifiers":[
        {
            "category":"Personal",
            "subcategory":"Barber",
            "type":"Services"
        }
    ],
    "sg:phone":"+1 435 586 9798",
    "sg:postcode":"84720",
    "sg:province":"UT",
    "wof:name":"Jacob's Hair Place",
    "wof:placetype":"venue"
},
  "geometry": {"coordinates":[-113.064232,37.665756],"type":"Point"}
}