{
  "type": "Feature",
  "properties": {
    "iso:country":"US",
    "sg:address":"420 E Center St",
    "sg:city":"Aurora",
    "sg:classifiers":[
        {
            "category":"Freight",
            "type":"Transportation"
        }
    ],
    "sg:phone":"+1 435 979 2216",
    "sg:postcode":"84620",
    "sg:province":"UT",
    "sg:tags":[
        "special"
    ],
    "wof:name":"Mountain View Storage",
    "wof:placetype":"venue"
},
  "geometry": {"coordinates":[-111.925904,38.920889],"type":"Point"}
}