{
  "type": "Feature",
  "properties": {
    "iso:country":"US",
    "sg:address":"80 N Main St",
    "sg:city":"Monticello",
    "sg:classifiers":[
        {
            "category":"Education",
            "subcategory":"Library",
            "type":"Public Place"
        }
    ],
    "sg:phone":"+1 435 587 2281",
    "sg:postcode":"84535",
    "sg:province":"UT",
    "wof:name":"San Juan County Library",
    "wof:placetype":"venue"
},
  "geometry": {"coordinates":[-109.342786,37.872881],"type":"Point"}
}