{
  "type": "Feature",
  "properties": {
    "iso:country":"US",
    "sg:address":"750 N Homestead Blvd",
    "sg:city":"Price",
    "sg:classifiers":[
        {
            "category":"Education",
            "subcategory":"School",
            "type":"Public Place"
        }
    ],
    "sg:phone":"+1 435 637 7177",
    "sg:postcode":"84501",
    "sg:province":"UT",
    "wof:name":"Castle Heights Elementary Schl",
    "wof:placetype":"venue"
},
  "geometry": {"coordinates":[-110.785281,39.612773],"type":"Point"}
}