{
  "type": "Feature",
  "properties": {
    "iso:country":"US",
    "sg:address":"183 N 555 W",
    "sg:city":"Orem",
    "sg:classifiers":[
        {
            "category":"Professional",
            "subcategory":"Credit Reporting & Collection",
            "type":"Services"
        }
    ],
    "sg:phone":"+1 801 226 7248",
    "sg:postcode":"84057",
    "sg:province":"UT",
    "wof:name":"T M Mortensen Receivables L C",
    "wof:placetype":"venue"
},
  "geometry": {"coordinates":[-111.70906100000001,40.300208],"type":"Point"}
}