{
  "type": "Feature",
  "properties": {
    "iso:country":"US",
    "sg:address":"129 N 1000 E",
    "sg:city":"Orem",
    "sg:classifiers":[
        {
            "category":"Government",
            "subcategory":"Office",
            "type":"Public Place"
        }
    ],
    "sg:phone":"+1 801 225 7085",
    "sg:postcode":"84097",
    "sg:province":"UT",
    "sg:tags":[
        "conservation"
    ],
    "wof:name":"Endangered Plant Studies Inc",
    "wof:placetype":"venue"
},
  "geometry": {"coordinates":[-111.671841,40.300462],"type":"Point"}
}