{
  "type": "Feature",
  "properties": {
    "iso:country":"US",
    "sg:address":"662 Garfield Ave",
    "sg:city":"Salt Lake City",
    "sg:classifiers":[
        {
            "category":"Professional",
            "subcategory":"Business Services",
            "type":"Services"
        }
    ],
    "sg:phone":"+1 801 474 0300",
    "sg:postcode":"84105",
    "sg:province":"UT",
    "sg:tags":[
        "plant",
        "design",
        "maintenance"
    ],
    "wof:name":"Folliage",
    "wof:placetype":"venue"
},
  "geometry": {"coordinates":[-111.87257099999999,40.729389],"type":"Point"}
}