{
  "type": "Feature",
  "properties": {
    "iso:country":"US",
    "sg:address":"2535 Valley View Ave",
    "sg:city":"Salt Lake City",
    "sg:classifiers":[
        {
            "category":"Organizations",
            "subcategory":"Labor Organization",
            "type":"Services"
        }
    ],
    "sg:phone":"+1 801 278 9860",
    "sg:postcode":"84117",
    "sg:province":"UT",
    "wof:name":"Carabine Investments Lc",
    "wof:placetype":"venue"
},
  "geometry": {"coordinates":[-111.82029900000001,40.665036],"type":"Point"}
}