{
  "type": "Feature",
  "properties": {
    "iso:country":"US",
    "sg:address":"1447 Willow Loop",
    "sg:city":"Park City",
    "sg:classifiers":[
        {
            "category":"Professional",
            "subcategory":"Management & Consulting",
            "type":"Services"
        }
    ],
    "sg:phone":"+1 435 901 0977",
    "sg:postcode":"84098",
    "sg:province":"UT",
    "sg:tags":[
        "business"
    ],
    "wof:name":"Jonathan C Ball",
    "wof:placetype":"venue"
},
  "geometry": {"coordinates":[-111.537694,40.703836],"type":"Point"}
}