{
  "type": "Feature",
  "properties": {
    "iso:country":"US",
    "sg:address":"132 S Main St",
    "sg:city":"Monticello",
    "sg:classifiers":[
        {
            "category":"Real Estate",
            "subcategory":"Real Estate Agent",
            "type":"Services"
        }
    ],
    "sg:phone":"+1 435 587 2424",
    "sg:postcode":"84535",
    "sg:province":"UT",
    "wof:name":"Lex Realty",
    "wof:placetype":"venue"
},
  "geometry": {"coordinates":[-109.343052,37.87073],"type":"Point"}
}