{
  "type": "Feature",
  "properties": {
    "iso:country":"US",
    "sg:address":"2304 Murray Holladay Rd",
    "sg:city":"Salt Lake City",
    "sg:classifiers":[
        {
            "category":"Shopping",
            "subcategory":"Used Merchandise",
            "type":"Retail Goods"
        }
    ],
    "sg:phone":"+1 801 277 7701",
    "sg:postcode":"84117",
    "sg:province":"UT",
    "sg:tags":[
        "furniture"
    ],
    "wof:name":"Rivive",
    "wof:placetype":"venue"
},
  "geometry": {"coordinates":[-111.825478,40.667814],"type":"Point"}
}