{
  "type": "Feature",
  "properties": {
    "iso:country":"US",
    "sg:address":"22 E 100 S",
    "sg:city":"Salt Lake City",
    "sg:classifiers":[
        {
            "category":"Restaurant",
            "type":"Food & Drink"
        }
    ],
    "sg:phone":"+1 801 363 9328",
    "sg:postcode":"84111",
    "sg:province":"UT",
    "wof:name":"Martine",
    "wof:placetype":"venue"
},
  "geometry": {"coordinates":[-111.890379,40.767099],"type":"Point"}
}