{
  "type": "Feature",
  "properties": {
    "iso:country":"US",
    "sg:address":"280 N 900 E",
    "sg:city":"Kaysville",
    "sg:classifiers":[
        {
            "category":"Food & Beverages",
            "subcategory":"Specialty",
            "type":"Retail Goods"
        }
    ],
    "sg:phone":"+1 801 497 9289",
    "sg:postcode":"84037",
    "sg:province":"UT",
    "sg:tags":[
        "vitamin"
    ],
    "wof:name":"L Scott Research",
    "wof:placetype":"venue"
},
  "geometry": {"coordinates":[-111.918239,41.039995],"type":"Point"}
}