{
  "type": "Feature",
  "properties": {
    "iso:country":"US",
    "sg:address":"2480 US Hwy 40",
    "sg:city":"Roosevelt",
    "sg:classifiers":[
        {
            "category":"Mining & Drilling",
            "type":"Manufacturing & Wholesale Goods"
        }
    ],
    "sg:phone":"+1 435 722 4520",
    "sg:postcode":"84066",
    "sg:province":"UT",
    "sg:tags":[
        "field",
        "oil"
    ],
    "wof:name":"Central Hydraulic Inc",
    "wof:placetype":"venue"
},
  "geometry": {"coordinates":[-110.040801,40.267983],"type":"Point"}
}