{
  "type": "Feature",
  "properties": {
    "iso:country":"US",
    "sg:address":"1546 W Gentile St",
    "sg:city":"Layton",
    "sg:classifiers":[
        {
            "category":"Building & Trades",
            "subcategory":"Construction",
            "type":"Services"
        }
    ],
    "sg:phone":"+1 801 544 8783",
    "sg:postcode":"84041",
    "sg:province":"UT",
    "sg:tags":[
        "house"
    ],
    "wof:name":"Noel D Flint Construction",
    "wof:placetype":"venue"
},
  "geometry": {"coordinates":[-111.993589,41.06023],"type":"Point"}
}