{
  "type": "Feature",
  "properties": {
    "iso:country":"US",
    "sg:address":"1433 Spring Ln",
    "sg:city":"Salt Lake City",
    "sg:classifiers":[
        {
            "category":"Professional",
            "subcategory":"Computer Services",
            "type":"Services"
        }
    ],
    "sg:phone":"+1 801 278 3434",
    "sg:postcode":"84117",
    "sg:province":"UT",
    "sg:tags":[
        "prepackaged",
        "consulting",
        "management",
        "software"
    ],
    "wof:name":"Management By Numbers",
    "wof:placetype":"venue"
},
  "geometry": {"coordinates":[-111.849395,40.65838],"type":"Point"}
}