{
  "type": "Feature",
  "properties": {
    "iso:country":"US",
    "sg:address":"214 Farrer St",
    "sg:city":"Green River",
    "sg:classifiers":[
        {
            "category":"Travel",
            "subcategory":"Hotels & Motels",
            "type":"Entertainment"
        }
    ],
    "sg:phone":"+1 435 564 3382",
    "sg:postcode":"84525",
    "sg:province":"UT",
    "sg:tags":[
        "breakfast",
        "accommodation",
        "bed"
    ],
    "wof:name":"Banker's Hatt",
    "wof:placetype":"venue"
},
  "geometry": {"coordinates":[-110.15518,38.990715],"type":"Point"}
}