{
  "type": "Feature",
  "properties": {
    "iso:country":"US",
    "sg:address":"405 S 100 W",
    "sg:city":"Bountiful",
    "sg:classifiers":[
        {
            "category":"Education",
            "subcategory":"School",
            "type":"Public Place"
        }
    ],
    "sg:phone":"+1 801 797 9870",
    "sg:postcode":"84010",
    "sg:province":"UT",
    "wof:name":"Institute of Real Estate Education",
    "wof:placetype":"venue"
},
  "geometry": {"coordinates":[-111.882768,40.885179],"type":"Point"}
}