{
  "type": "Feature",
  "properties": {
    "iso:country":"US",
    "sg:address":"90 Cutler Dr",
    "sg:city":"North Salt Lake",
    "sg:classifiers":[
        {
            "category":"Building & Trades",
            "subcategory":"Electrical",
            "type":"Services"
        }
    ],
    "sg:phone":"+1 801 292 2956",
    "sg:postcode":"84054",
    "sg:province":"UT",
    "sg:tags":[
        "electrician"
    ],
    "wof:name":"Vfc Inc",
    "wof:placetype":"venue"
},
  "geometry": {"coordinates":[-111.933998,40.8419],"type":"Point"}
}