{
  "type": "Feature",
  "properties": {
    "iso:country":"US",
    "sg:address":"9840 S Poppy Ln",
    "sg:city":"Sandy",
    "sg:classifiers":[
        {
            "category":"Education",
            "subcategory":"Library",
            "type":"Public Place"
        }
    ],
    "sg:phone":"+1 801 571 0936",
    "sg:postcode":"84094",
    "sg:province":"UT",
    "wof:name":"Moon Library Sales",
    "wof:placetype":"venue"
},
  "geometry": {"coordinates":[-111.86595800000001,40.571389],"type":"Point"}
}