{
  "type": "Feature",
  "properties": {
    "iso:country":"US",
    "sg:address":"1955 E 2700 S",
    "sg:city":"Salt Lake City",
    "sg:classifiers":[
        {
            "category":"Retail",
            "subcategory":"Auto Repair",
            "type":"Services"
        }
    ],
    "sg:phone":"+1 801 467 4922",
    "sg:postcode":"84106",
    "sg:province":"UT",
    "sg:tags":[
        "general"
    ],
    "wof:name":"Waynes Service Center Inc",
    "wof:placetype":"venue"
},
  "geometry": {"coordinates":[-111.83429,40.712786],"type":"Point"}
}