{
  "type": "Feature",
  "properties": {
    "iso:country":"US",
    "sg:address":"536 N 1000 W",
    "sg:city":"Salt Lake City",
    "sg:classifiers":[
        {
            "category":"Building & Trades",
            "subcategory":"Construction",
            "type":"Services"
        }
    ],
    "sg:phone":"+1 801 364 2132",
    "sg:postcode":"84116",
    "sg:province":"UT",
    "sg:tags":[
        "house"
    ],
    "wof:name":"A P & M Specialist",
    "wof:placetype":"venue"
},
  "geometry": {"coordinates":[-111.91962599999999,40.781582],"type":"Point"}
}