{
  "type": "Feature",
  "properties": {
    "iso:country":"US",
    "sg:address":"4589 Argonaut Dr",
    "sg:city":"Salt Lake City",
    "sg:classifiers":[
        {
            "category":"Retail",
            "subcategory":"Auto Repair",
            "type":"Services"
        }
    ],
    "sg:phone":"+1 801 963 3683",
    "sg:postcode":"84120",
    "sg:province":"UT",
    "sg:tags":[
        "automotive"
    ],
    "wof:name":"Andreasen Auto & Towing",
    "wof:placetype":"venue"
},
  "geometry": {"coordinates":[-112.00848999999999,40.669983],"type":"Point"}
}