{
  "type": "Feature",
  "properties": {
    "iso:country":"US",
    "sg:address":"48 S Main St",
    "sg:city":"Nephi",
    "sg:classifiers":[
        {
            "category":"Shopping",
            "subcategory":"Optical Goods",
            "type":"Retail Goods"
        }
    ],
    "sg:phone":"+1 435 623 2100",
    "sg:postcode":"84648",
    "sg:province":"UT",
    "wof:name":"Nebo Vision Clinic",
    "wof:placetype":"venue"
},
  "geometry": {"coordinates":[-111.83615,39.707501],"type":"Point"}
}