{
  "type": "Feature",
  "properties": {
    "iso:country":"US",
    "sg:address":"4722 S 4015 W",
    "sg:city":"Kearns",
    "sg:classifiers":[
        {
            "category":"Banks & Credit Unions",
            "subcategory":"Bank",
            "type":"Services"
        }
    ],
    "sg:phone":"+1 801 840 2274",
    "sg:postcode":"84118",
    "sg:province":"UT",
    "sg:tags":[
        "cashing",
        "check"
    ],
    "wof:name":"Access 2 Cash",
    "wof:placetype":"venue"
},
  "geometry": {"coordinates":[-111.986088,40.667575],"type":"Point"}
}