{
  "type": "Feature",
  "properties": {
    "iso:country":"US",
    "sg:address":"3776 N 300 W",
    "sg:city":"Provo",
    "sg:classifiers":[
        {
            "category":"Professional",
            "type":"Services"
        }
    ],
    "sg:phone":"+1 801 224 9667",
    "sg:postcode":"84604",
    "sg:province":"UT",
    "sg:tags":[
        "establishment"
    ],
    "wof:name":"Consensus Group",
    "wof:placetype":"venue"
},
  "geometry": {"coordinates":[-111.663049,40.283147],"type":"Point"}
}