{
  "type": "Feature",
  "properties": {
    "iso:country":"US",
    "sg:address":"98 W 200 N",
    "sg:city":"Manti",
    "sg:classifiers":[
        {
            "category":"Building & Trades",
            "subcategory":"Plumbing",
            "type":"Services"
        }
    ],
    "sg:phone":"+1 435 835 4351",
    "sg:postcode":"84642",
    "sg:province":"UT",
    "sg:tags":[
        "plumbing",
        "contractor"
    ],
    "wof:name":"Harmon's Hardware Inc",
    "wof:placetype":"venue"
},
  "geometry": {"coordinates":[-111.638271,39.268331],"type":"Point"}
}