{
  "type": "Feature",
  "properties": {
    "iso:country":"US",
    "sg:address":"510 Main St",
    "sg:city":"Henefer",
    "sg:classifiers":[
        {
            "category":"Wholesale",
            "subcategory":"Machinery & Supplies",
            "type":"Manufacturing & Wholesale Goods"
        }
    ],
    "sg:phone":"+1 435 336 5696",
    "sg:postcode":"84033",
    "sg:province":"UT",
    "sg:tags":[
        "equipment",
        "dairy"
    ],
    "wof:name":"Dairy Tank Co",
    "wof:placetype":"venue"
},
  "geometry": {"coordinates":[-111.503411,41.02371],"type":"Point"}
}