{
  "type": "Feature",
  "properties": {
    "iso:country":"US",
    "sg:address":"595 Camden Park Ln",
    "sg:city":"Draper",
    "sg:classifiers":[
        {
            "category":"Autos & Motor Vehicles",
            "subcategory":"Automobile Sales",
            "type":"Retail Goods"
        }
    ],
    "sg:phone":"+1 801 495 9202",
    "sg:postcode":"84020",
    "sg:province":"UT",
    "wof:name":"Redeye Racing",
    "wof:placetype":"venue"
},
  "geometry": {"coordinates":[-111.876991,40.543756],"type":"Point"}
}