{
  "type": "Feature",
  "properties": {
    "iso:country":"US",
    "sg:address":"3787 S 500 W",
    "sg:city":"Salt Lake City",
    "sg:classifiers":[
        {
            "category":"Autos & Motor Vehicles",
            "subcategory":"Boat Sales",
            "type":"Retail Goods"
        }
    ],
    "sg:phone":"+1 801 268 6400",
    "sg:postcode":"84115",
    "sg:province":"UT",
    "sg:tags":[
        "dealer",
        "sales"
    ],
    "wof:name":"Wasatch Marine",
    "wof:placetype":"venue"
},
  "geometry": {"coordinates":[-111.905421,40.689076],"type":"Point"}
}