{
  "type": "Feature",
  "properties": {
    "iso:country":"US",
    "sg:address":"4568 Highland Dr",
    "sg:city":"Salt Lake City",
    "sg:classifiers":[
        {
            "category":"Wholesale",
            "subcategory":"Machinery & Supplies",
            "type":"Manufacturing & Wholesale Goods"
        }
    ],
    "sg:phone":"+1 801 272 1107",
    "sg:postcode":"84117",
    "sg:province":"UT",
    "sg:tags":[
        "process",
        "equipment",
        "rep",
        "industrial",
        "mfg"
    ],
    "wof:name":"Hobbs Tank & Equipment Inc",
    "wof:placetype":"venue"
},
  "geometry": {"coordinates":[-111.84141700000001,40.673616],"type":"Point"}
}