{
  "type": "Feature",
  "properties": {
    "iso:country":"US",
    "sg:address":"96 N 500 W",
    "sg:city":"Bountiful",
    "sg:classifiers":[
        {
            "category":"Home & Garden",
            "subcategory":"Carpets & Floor Coverings",
            "type":"Retail Goods"
        }
    ],
    "sg:phone":"+1 801 295 0434",
    "sg:postcode":"84010",
    "sg:province":"UT",
    "sg:tags":[
        "carpeting"
    ],
    "wof:name":"Riley Kay & Sons Carpet Service",
    "wof:placetype":"venue"
},
  "geometry": {"coordinates":[-111.891998,40.8899],"type":"Point"}
}