{
  "type": "Feature",
  "properties": {
    "iso:country":"US",
    "sg:address":"2614 Washington Blvd",
    "sg:city":"Ogden",
    "sg:classifiers":[
        {
            "category":"Insurance",
            "subcategory":"Insurance Agent",
            "type":"Services"
        }
    ],
    "sg:phone":"+1 801 393 5351",
    "sg:postcode":"84401",
    "sg:province":"UT",
    "wof:name":"Farmers Insurance",
    "wof:placetype":"venue"
},
  "geometry": {"coordinates":[-111.97046400000001,41.217522],"type":"Point"}
}