{
  "type": "Feature",
  "properties": {
    "iso:country":"US",
    "sg:address":"3565 W 2400 S",
    "sg:city":"Heber City",
    "sg:classifiers":[
        {
            "category":"Social Services",
            "subcategory":"Child Care",
            "type":"Services"
        }
    ],
    "sg:phone":"+1 435 654 4864",
    "sg:postcode":"84032",
    "sg:province":"UT",
    "sg:tags":[
        "day"
    ],
    "wof:name":"Carolyn Taylor Day Care",
    "wof:placetype":"venue"
},
  "geometry": {"coordinates":[-111.47089699999999,40.476776],"type":"Point"}
}