{
  "type": "Feature",
  "properties": {
    "iso:country":"US",
    "sg:address":"1665 Progress Way",
    "sg:city":"Tooele",
    "sg:classifiers":[
        {
            "category":"Retail",
            "subcategory":"Repair Shop",
            "type":"Services"
        }
    ],
    "sg:phone":"+1 435 882 6359",
    "sg:postcode":"84074",
    "sg:province":"UT",
    "sg:tags":[
        "welding"
    ],
    "wof:name":"Russell Welding Corp",
    "wof:placetype":"venue"
},
  "geometry": {"coordinates":[-112.29503,40.564191],"type":"Point"}
}