{
  "type": "Feature",
  "properties": {
    "iso:country":"US",
    "sg:address":"1215 Mission Rd",
    "sg:city":"Salt Lake City",
    "sg:classifiers":[
        {
            "category":"Building & Trades",
            "subcategory":"Construction",
            "type":"Services"
        }
    ],
    "sg:phone":"+1 801 973 0291",
    "sg:postcode":"84104",
    "sg:province":"UT",
    "sg:tags":[
        "concrete",
        "contractor"
    ],
    "wof:name":"Wasatch Concrete Contractor",
    "wof:placetype":"venue"
},
  "geometry": {"coordinates":[-111.93147,40.742228],"type":"Point"}
}