{
  "type": "Feature",
  "properties": {
    "iso:country":"US",
    "sg:address":"250 E Center St",
    "sg:city":"Ephraim",
    "sg:classifiers":[
        {
            "category":"Real Estate",
            "subcategory":"Real Estate Operator",
            "type":"Services"
        }
    ],
    "sg:phone":"+1 435 283 5877",
    "sg:postcode":"84627",
    "sg:province":"UT",
    "sg:tags":[
        "apartment"
    ],
    "wof:name":"Snow Village Apartments",
    "wof:placetype":"venue"
},
  "geometry": {"coordinates":[-111.58062,39.359661],"type":"Point"}
}