{
  "type": "Feature",
  "properties": {
    "iso:country":"US",
    "sg:address":"82 W 300 N",
    "sg:city":"North Salt Lake",
    "sg:classifiers":[
        {
            "category":"Manufacturing",
            "subcategory":"Tools & Machinery",
            "type":"Manufacturing & Wholesale Goods"
        }
    ],
    "sg:phone":"+1 801 292 9732",
    "sg:postcode":"84054",
    "sg:province":"UT",
    "sg:tags":[
        "household",
        "appliance",
        "mfg"
    ],
    "wof:name":"Iund Manufacturing",
    "wof:placetype":"venue"
},
  "geometry": {"coordinates":[-111.91231999999999,40.847341],"type":"Point"}
}