{
  "type": "Feature",
  "properties": {
    "iso:country":"US",
    "sg:address":"2298 Zions Dr",
    "sg:city":"Salt Lake City",
    "sg:classifiers":[
        {
            "category":"Shopping",
            "subcategory":"Bicycles & Sporting Goods",
            "type":"Retail Goods"
        }
    ],
    "sg:phone":"+1 801 964 6846",
    "sg:postcode":"84118",
    "sg:province":"UT",
    "sg:tags":[
        "gun",
        "gunsmith"
    ],
    "wof:name":"Nightowls Gunsmithing",
    "wof:placetype":"venue"
},
  "geometry": {"coordinates":[-111.949366,40.652561],"type":"Point"}
}