{
  "type": "Feature",
  "properties": {
    "iso:country":"US",
    "sg:address":"11951 S 800 E",
    "sg:city":"Draper",
    "sg:classifiers":[
        {
            "category":"Farming",
            "subcategory":"Livestock Farm",
            "type":"Manufacturing & Wholesale Goods"
        }
    ],
    "sg:phone":"+1 801 572 5335",
    "sg:postcode":"84020",
    "sg:province":"UT",
    "sg:tags":[
        "animal",
        "general"
    ],
    "wof:name":"H & K Ranch Design",
    "wof:placetype":"venue"
},
  "geometry": {"coordinates":[-111.86925100000001,40.533344],"type":"Point"}
}