{
  "type": "Feature",
  "properties": {
    "iso:country":"US",
    "sg:address":"2468 S 1760 W",
    "sg:city":"Ogden",
    "sg:classifiers":[
        {
            "category":"Wholesale",
            "subcategory":"Hardware",
            "type":"Manufacturing & Wholesale Goods"
        }
    ],
    "sg:phone":"+1 801 337 0146",
    "sg:postcode":"84401",
    "sg:province":"UT",
    "sg:tags":[
        "air",
        "heating",
        "warm",
        "conditioning",
        "supply"
    ],
    "wof:name":"Contractors Hvac Supply Inc",
    "wof:placetype":"venue"
},
  "geometry": {"coordinates":[-112.02252900000001,41.221122],"type":"Point"}
}