{
  "type": "Feature",
  "properties": {
    "iso:country":"US",
    "sg:address":"3400 Pacific Ave",
    "sg:city":"Ogden",
    "sg:classifiers":[
        {
            "category":"Wholesale",
            "subcategory":"Construction Materials",
            "type":"Manufacturing & Wholesale Goods"
        }
    ],
    "sg:phone":"+1 801 392 5988",
    "sg:postcode":"84401",
    "sg:province":"UT",
    "sg:tags":[
        "lumber"
    ],
    "wof:name":"Anderson Lumber",
    "wof:placetype":"venue"
},
  "geometry": {"coordinates":[-111.984517,41.203461],"type":"Point"}
}