{
  "type": "Feature",
  "properties": {
    "iso:country":"US",
    "sg:address":"190 S Main St",
    "sg:city":"Bountiful",
    "sg:classifiers":[
        {
            "category":"Home & Garden",
            "subcategory":"Hardware",
            "type":"Retail Goods"
        }
    ],
    "sg:phone":"+1 801 295 2371",
    "sg:postcode":"84010",
    "sg:province":"UT",
    "wof:name":"Bountiful Lumber & Supply Co",
    "wof:placetype":"venue"
},
  "geometry": {"coordinates":[-111.880769,40.88827],"type":"Point"}
}