{
  "type": "Feature",
  "properties": {
    "iso:country":"US",
    "sg:address":"5814 Ayrshire Dr",
    "sg:city":"Salt Lake City",
    "sg:classifiers":[
        {
            "category":"Professional",
            "subcategory":"Business Services",
            "type":"Services"
        }
    ],
    "sg:phone":"+1 801 268 2676",
    "sg:postcode":"84107",
    "sg:province":"UT",
    "wof:name":"Core Essentials Sales",
    "wof:placetype":"venue"
},
  "geometry": {"coordinates":[-111.879274,40.642763],"type":"Point"}
}