{
  "type": "Feature",
  "properties": {
    "iso:country":"US",
    "sg:address":"1655 W 4100 S",
    "sg:city":"Murray",
    "sg:classifiers":[
        {
            "category":"Recreation",
            "type":"Entertainment"
        }
    ],
    "sg:phone":"+1 801 262 7548",
    "sg:postcode":"84123",
    "sg:province":"UT",
    "sg:tags":[
        "parlor",
        "billiard"
    ],
    "wof:name":"May Hong",
    "wof:placetype":"venue"
},
  "geometry": {"coordinates":[-111.937168,40.682191],"type":"Point"}
}