{
  "type": "Feature",
  "properties": {
    "iso:country":"US",
    "sg:address":"375 N 500 W",
    "sg:city":"Salt Lake City",
    "sg:classifiers":[
        {
            "category":"Building & Trades",
            "subcategory":"Construction",
            "type":"Services"
        }
    ],
    "sg:phone":"+1 801 363 0955",
    "sg:postcode":"84116",
    "sg:province":"UT",
    "sg:tags":[
        "equipment",
        "contractor"
    ],
    "wof:name":"United Scaffolding",
    "wof:placetype":"venue"
},
  "geometry": {"coordinates":[-111.905473,40.776395],"type":"Point"}
}