{
  "type": "Feature",
  "properties": {
    "iso:country":"US",
    "sg:address":"226 W 2230 North St",
    "sg:city":"Provo",
    "sg:classifiers":[
        {
            "category":"Utilities",
            "subcategory":"Telephone",
            "type":"Services"
        }
    ],
    "sg:phone":"+1 801 221 3707",
    "sg:postcode":"84604",
    "sg:province":"UT",
    "sg:tags":[
        "communications"
    ],
    "wof:name":"Quik Internet of Central Utah",
    "wof:placetype":"venue"
},
  "geometry": {"coordinates":[-111.662843,40.263541],"type":"Point"}
}