{
  "type": "Feature",
  "properties": {
    "iso:country":"US",
    "sg:address":"757 E 800 N",
    "sg:city":"Orem",
    "sg:classifiers":[
        {
            "category":"Health Services",
            "subcategory":"Chiropractor",
            "type":"Services"
        }
    ],
    "sg:phone":"+1 801 235 9944",
    "sg:postcode":"84097",
    "sg:province":"UT",
    "wof:name":"Cascade Spinal Rehabilitation",
    "wof:placetype":"venue"
},
  "geometry": {"coordinates":[-111.677896,40.311985],"type":"Point"}
}