{
  "type": "Feature",
  "properties": {
    "iso:country":"US",
    "sg:address":"1767 S State St",
    "sg:city":"Orem",
    "sg:classifiers":[
        {
            "category":"Manufacturing",
            "subcategory":"Apparel",
            "type":"Manufacturing & Wholesale Goods"
        }
    ],
    "sg:phone":"+1 801 225 1512",
    "sg:postcode":"84097",
    "sg:province":"UT",
    "sg:tags":[
        "canvas",
        "product",
        "related"
    ],
    "wof:name":"Huish's Awnings",
    "wof:placetype":"venue"
},
  "geometry": {"coordinates":[-111.680969,40.26586],"type":"Point"}
}