{
  "type": "Feature",
  "properties": {
    "iso:country":"US",
    "sg:address":"1153 Castle Dale Cir",
    "sg:city":"Sandy",
    "sg:classifiers":[
        {
            "category":"Shopping",
            "type":"Retail Goods"
        }
    ],
    "sg:phone":"+1 801 545 0899",
    "sg:postcode":"84094",
    "sg:province":"UT",
    "sg:tags":[
        "cosmetic",
        "perfume"
    ],
    "wof:name":"Linda Larson Cosmetics",
    "wof:placetype":"venue"
},
  "geometry": {"coordinates":[-111.859983,40.539569],"type":"Point"}
}