{
  "type": "Feature",
  "properties": {
    "iso:country":"US",
    "sg:address":"234 W Center St",
    "sg:city":"Provo",
    "sg:classifiers":[
        {
            "category":"Professional",
            "subcategory":"Computer Services",
            "type":"Services"
        }
    ],
    "sg:phone":"+1 801 592 3181",
    "sg:postcode":"84601",
    "sg:province":"UT",
    "sg:tags":[
        "related"
    ],
    "wof:name":"Lunar Creation",
    "wof:placetype":"venue"
},
  "geometry": {"coordinates":[-111.663436,40.233863],"type":"Point"}
}