{
  "type": "Feature",
  "properties": {
    "iso:country":"US",
    "sg:address":"236 Cottage Wood Ln",
    "sg:city":"Salt Lake City",
    "sg:classifiers":[
        {
            "category":"Wholesale",
            "subcategory":"Electrical",
            "type":"Manufacturing & Wholesale Goods"
        }
    ],
    "sg:phone":"+1 801 281 2009",
    "sg:postcode":"84107",
    "sg:province":"UT",
    "sg:tags":[
        "control",
        "security",
        "system"
    ],
    "wof:name":"King Central",
    "wof:placetype":"venue"
},
  "geometry": {"coordinates":[-111.88402600000001,40.67316],"type":"Point"}
}