{
  "type": "Feature",
  "properties": {
    "iso:country":"US",
    "sg:address":"6440 Wasatch Blvd",
    "sg:city":"Salt Lake City",
    "sg:classifiers":[
        {
            "category":"Banks & Credit Unions",
            "subcategory":"Bank",
            "type":"Services"
        }
    ],
    "sg:phone":"+1 801 415 0320",
    "sg:postcode":"84121",
    "sg:province":"UT",
    "sg:tags":[
        "loan"
    ],
    "sg:website":"www.realnetlending.com",
    "wof:name":"Realnet Lending",
    "wof:placetype":"venue"
},
  "geometry": {"coordinates":[-111.798098,40.636591],"type":"Point"}
}