{
  "type": "Feature",
  "properties": {
    "iso:country":"US",
    "sg:address":"1410 N 1900 W",
    "sg:city":"Ogden",
    "sg:classifiers":[
        {
            "category":"Home & Garden",
            "subcategory":"Garden Supply",
            "type":"Retail Goods"
        }
    ],
    "sg:phone":"+1 801 782 4149",
    "sg:postcode":"84404",
    "sg:province":"UT",
    "sg:tags":[
        "nursery"
    ],
    "wof:name":"Jerrys Nursery & Garden Center",
    "wof:placetype":"venue"
},
  "geometry": {"coordinates":[-112.02548400000001,41.28166],"type":"Point"}
}