{
  "type": "Feature",
  "properties": {
    "iso:country":"US",
    "sg:address":"251 E Main St",
    "sg:city":"Vernal",
    "sg:classifiers":[
        {
            "category":"Travel",
            "subcategory":"Hotels & Motels",
            "type":"Entertainment"
        }
    ],
    "sg:phone":"+1 435 789 2660",
    "sg:postcode":"84078",
    "sg:province":"UT",
    "sg:tags":[
        "shop",
        "gift"
    ],
    "wof:name":"Best Western",
    "wof:placetype":"venue"
},
  "geometry": {"coordinates":[-109.524764,40.455832],"type":"Point"}
}