{
  "type": "Feature",
  "properties": {
    "iso:country":"US",
    "sg:address":"927 E 70 S",
    "sg:city":"Lindon",
    "sg:classifiers":[
        {
            "category":"Utilities",
            "subcategory":"Telephone",
            "type":"Services"
        }
    ],
    "sg:phone":"+1 801 376 7272",
    "sg:postcode":"84042",
    "sg:province":"UT",
    "sg:tags":[
        "union",
        "credit",
        "for",
        "internet"
    ],
    "wof:name":"Memberclassifiedscom",
    "wof:placetype":"venue"
},
  "geometry": {"coordinates":[-111.69238199999999,40.336358],"type":"Point"}
}