{
  "type": "Feature",
  "properties": {
    "iso:country":"US",
    "sg:address":"8556 S 2940 W",
    "sg:city":"West Jordan",
    "sg:classifiers":[
        {
            "category":"Restaurant",
            "type":"Food & Drink"
        }
    ],
    "sg:phone":"+1 801 566 7131",
    "sg:postcode":"84088",
    "sg:province":"UT",
    "sg:tags":[
        "delicatessen"
    ],
    "wof:name":"Deli Express",
    "wof:placetype":"venue"
},
  "geometry": {"coordinates":[-111.962661,40.595614],"type":"Point"}
}