{
  "type": "Feature",
  "properties": {
    "iso:country":"US",
    "sg:address":"1220 2nd Ave",
    "sg:city":"Salt Lake City",
    "sg:classifiers":[
        {
            "category":"Social Services",
            "subcategory":"Job Training",
            "type":"Services"
        }
    ],
    "sg:phone":"+1 801 243 8224",
    "sg:postcode":"84103",
    "sg:province":"UT",
    "wof:name":"Cohesion",
    "wof:placetype":"venue"
},
  "geometry": {"coordinates":[-111.852728,40.771614],"type":"Point"}
}