{
  "type": "Feature",
  "properties": {
    "iso:country":"US",
    "sg:address":"1595 W 5550 N",
    "sg:city":"St George",
    "sg:classifiers":[
        {
            "category":"Wholesale",
            "subcategory":"Machinery & Supplies",
            "type":"Manufacturing & Wholesale Goods"
        }
    ],
    "sg:phone":"+1 435 656 2448",
    "sg:postcode":"84770",
    "sg:province":"UT",
    "sg:tags":[
        "fastener",
        "industrial"
    ],
    "wof:name":"Donchar Industries",
    "wof:placetype":"venue"
},
  "geometry": {"coordinates":[-113.614671,37.206459],"type":"Point"}
}