{
  "type": "Feature",
  "properties": {
    "iso:country":"US",
    "sg:address":"5106 Amelia Earhart Dr",
    "sg:city":"Salt Lake City",
    "sg:classifiers":[
        {
            "category":"Freight",
            "type":"Transportation"
        }
    ],
    "sg:phone":"+1 801 973 9747",
    "sg:postcode":"84116",
    "sg:province":"UT",
    "wof:name":"Aerologistic",
    "wof:placetype":"venue"
},
  "geometry": {"coordinates":[-112.014922,40.77647],"type":"Point"}
}