{
  "type": "Feature",
  "properties": {
    "iso:country":"US",
    "sg:address":"3971 S Redwood Rd",
    "sg:city":"Salt Lake City",
    "sg:classifiers":[
        {
            "category":"Shopping",
            "subcategory":"Gifts & Souvenirs",
            "type":"Retail Goods"
        }
    ],
    "sg:phone":"+1 801 952 0184",
    "sg:postcode":"84123",
    "sg:province":"UT",
    "sg:tags":[
        "indian"
    ],
    "wof:name":"Drurylane's Native American",
    "wof:placetype":"venue"
},
  "geometry": {"coordinates":[-111.93888800000001,40.687932],"type":"Point"}
}