{
  "type": "Feature",
  "properties": {
    "iso:country":"US",
    "sg:address":"1182 S 1680 W",
    "sg:city":"Orem",
    "sg:classifiers":[
        {
            "category":"Professional",
            "subcategory":"Advertising",
            "type":"Services"
        },
        {
            "category":"Wholesale",
            "subcategory":"Non-durable Goods",
            "type":"Manufacturing & Wholesale Goods"
        }
    ],
    "sg:phone":"+1 801 377 8695",
    "sg:postcode":"84058",
    "sg:province":"UT",
    "sg:website":"www.voxpromotions.com",
    "wof:name":"Vox Promotions Inc",
    "wof:placetype":"venue"
},
  "geometry": {"coordinates":[-111.73536900000001,40.274812],"type":"Point"}
}