{
  "type": "Feature",
  "properties": {
    "iso:country":"US",
    "sg:address":"340 E Main St",
    "sg:city":"Castle Dale",
    "sg:classifiers":[
        {
            "category":"Restaurant",
            "type":"Food & Drink"
        }
    ],
    "sg:phone":"+1 435 381 5080",
    "sg:postcode":"84513",
    "sg:province":"UT",
    "wof:name":"Big Mama's Pizza & Deli",
    "wof:placetype":"venue"
},
  "geometry": {"coordinates":[-111.012874,39.211691],"type":"Point"}
}