{
  "type": "Feature",
  "properties": {
    "iso:country":"US",
    "sg:address":"3520 N Main St",
    "sg:city":"Logan",
    "sg:classifiers":[
        {
            "category":"Education",
            "subcategory":"College",
            "type":"Public Place"
        }
    ],
    "sg:phone":"+1 435 797 2279",
    "sg:postcode":"84341",
    "sg:province":"UT",
    "sg:tags":[
        "business"
    ],
    "wof:name":"College of Business",
    "wof:placetype":"venue"
},
  "geometry": {"coordinates":[-111.83343600000001,41.798588],"type":"Point"}
}