{
  "type": "Feature",
  "properties": {
    "iso:country":"US",
    "sg:address":"303 E South Temple",
    "sg:city":"Salt Lake City",
    "sg:classifiers":[
        {
            "category":"Insurance",
            "subcategory":"Insurance Agent",
            "type":"Services"
        }
    ],
    "sg:phone":"+1 801 534 1315",
    "sg:postcode":"84111",
    "sg:province":"UT",
    "wof:name":"National Benefits Partner Insu",
    "wof:placetype":"venue"
},
  "geometry": {"coordinates":[-111.88207,40.769423],"type":"Point"}
}