{
  "type": "Feature",
  "properties": {
    "iso:country":"US",
    "sg:address":"2460 Briarcreek Cir",
    "sg:city":"Salt Lake City",
    "sg:classifiers":[
        {
            "category":"Freight",
            "type":"Transportation"
        }
    ],
    "sg:phone":"+1 801 272 2038",
    "sg:postcode":"84117",
    "sg:province":"UT",
    "wof:name":"CL Logistics Properties LLC",
    "wof:placetype":"venue"
},
  "geometry": {"coordinates":[-111.82064,40.674037],"type":"Point"}
}