{
  "type": "Feature",
  "properties": {
    "iso:country":"US",
    "sg:address":"355 N University Ave",
    "sg:city":"Provo",
    "sg:classifiers":[
        {
            "category":"Utilities",
            "subcategory":"Mobile Phone",
            "type":"Services"
        }
    ],
    "sg:phone":"+1 801 812 3733",
    "sg:postcode":"84601",
    "sg:province":"UT",
    "sg:tags":[
        "communication",
        "radiotelephone"
    ],
    "wof:name":"Free Pager Shop",
    "wof:placetype":"venue"
},
  "geometry": {"coordinates":[-111.658728,40.238332],"type":"Point"}
}