{
  "type": "Feature",
  "properties": {
    "iso:country":"US",
    "sg:address":"188 W State Rd",
    "sg:city":"American Fork",
    "sg:classifiers":[
        {
            "category":"Personal",
            "subcategory":"Beauty Salon",
            "type":"Services"
        }
    ],
    "sg:phone":"+1 801 492 1133",
    "sg:postcode":"84003",
    "sg:province":"UT",
    "sg:tags":[
        "shop"
    ],
    "wof:name":"Salon Cachet",
    "wof:placetype":"venue"
},
  "geometry": {"coordinates":[-111.81364600000001,40.38057],"type":"Point"}
}