{
  "type": "Feature",
  "properties": {
    "iso:country":"US",
    "sg:address":"4455 S 700 E",
    "sg:city":"Salt Lake City",
    "sg:classifiers":[
        {
            "category":"Professional",
            "subcategory":"Computer Services",
            "type":"Services"
        }
    ],
    "sg:phone":"+1 801 281 3434",
    "sg:postcode":"84107",
    "sg:province":"UT",
    "wof:name":"Ragula Systems",
    "wof:placetype":"venue"
},
  "geometry": {"coordinates":[-111.87134500000001,40.674988],"type":"Point"}
}