{
  "type": "Feature",
  "properties": {
    "iso:country":"US",
    "sg:address":"2965 Highland Dr",
    "sg:city":"Salt Lake City",
    "sg:classifiers":[
        {
            "category":"Restaurant",
            "type":"Food & Drink"
        }
    ],
    "sg:phone":"+1 801 466 8058",
    "sg:postcode":"84106",
    "sg:province":"UT",
    "wof:name":"Eakin's Grill",
    "wof:placetype":"venue"
},
  "geometry": {"coordinates":[-111.853009,40.706468],"type":"Point"}
}