{
  "type": "Feature",
  "properties": {
    "iso:country":"US",
    "sg:address":"4352 Imperial Way",
    "sg:city":"Provo",
    "sg:classifiers":[
        {
            "category":"Wholesale",
            "subcategory":"Farm Supplies",
            "type":"Manufacturing & Wholesale Goods"
        }
    ],
    "sg:phone":"+1 801 765 0355",
    "sg:postcode":"84604",
    "sg:province":"UT",
    "sg:tags":[
        "chemical"
    ],
    "wof:name":"Sierra Technologies",
    "wof:placetype":"venue"
},
  "geometry": {"coordinates":[-111.63618,40.292615],"type":"Point"}
}