{
  "type": "Feature",
  "properties": {
    "iso:country":"US",
    "sg:address":"6730 S 400 W",
    "sg:city":"Midvale",
    "sg:classifiers":[
        {
            "category":"Manufacturing",
            "subcategory":"Tools & Machinery",
            "type":"Manufacturing & Wholesale Goods"
        }
    ],
    "sg:phone":"+1 801 262 4889",
    "sg:postcode":"84047",
    "sg:province":"UT",
    "sg:tags":[
        "machine",
        "shop",
        "industrial",
        "mfg"
    ],
    "wof:name":"Cole Machine & Mfg Lc",
    "wof:placetype":"venue"
},
  "geometry": {"coordinates":[-111.900063,40.627286],"type":"Point"}
}