{
  "type": "Feature",
  "properties": {
    "iso:country":"US",
    "sg:address":"905 S Oak Dr",
    "sg:city":"Woodland Hills",
    "sg:classifiers":[
        {
            "category":"Retail",
            "subcategory":"Animal Services",
            "type":"Services"
        }
    ],
    "sg:phone":"+1 801 423 3701",
    "sg:postcode":"84653",
    "sg:province":"UT",
    "sg:tags":[
        "training",
        "dog"
    ],
    "wof:name":"PFP Inc",
    "wof:placetype":"venue"
},
  "geometry": {"coordinates":[-111.65570700000001,40.010093],"type":"Point"}
}