{
  "type": "Feature",
  "properties": {
    "iso:country":"US",
    "sg:address":"1458 E 300 S",
    "sg:city":"Pleasant Grove",
    "sg:classifiers":[
        {
            "category":"Professional",
            "subcategory":"Business Services",
            "type":"Services"
        }
    ],
    "sg:phone":"+1 801 785 7654",
    "sg:postcode":"84062",
    "sg:province":"UT",
    "wof:name":"Silver Willow Enterprises LLC",
    "wof:placetype":"venue"
},
  "geometry": {"coordinates":[-111.706857,40.360206],"type":"Point"}
}