{
  "type": "Feature",
  "properties": {
    "iso:country":"US",
    "sg:address":"1980 Ashridge Cir",
    "sg:city":"Sandy",
    "sg:classifiers":[
        {
            "category":"Professional",
            "subcategory":"Employment Agencies",
            "type":"Services"
        }
    ],
    "sg:phone":"+1 801 566 7860",
    "sg:postcode":"84093",
    "sg:province":"UT",
    "sg:tags":[
        "consulting"
    ],
    "wof:name":"The Rads Group",
    "wof:placetype":"venue"
},
  "geometry": {"coordinates":[-111.834881,40.590988],"type":"Point"}
}