{
  "type": "Feature",
  "properties": {
    "iso:country":"US",
    "sg:address":"711 E Vine St",
    "sg:city":"Tooele",
    "sg:classifiers":[
        {
            "category":"Education",
            "subcategory":"School",
            "type":"Public Place"
        }
    ],
    "sg:phone":"+1 435 833 1966",
    "sg:postcode":"84074",
    "sg:province":"UT",
    "wof:name":"Oquirrh Hills School",
    "wof:placetype":"venue"
},
  "geometry": {"coordinates":[-112.279265,40.531109],"type":"Point"}
}