{
  "type": "Feature",
  "properties": {
    "iso:country":"US",
    "sg:address":"2795 Cottonwood Pkwy",
    "sg:city":"Salt Lake City",
    "sg:classifiers":[
        {
            "category":"Insurance",
            "subcategory":"Title Insurance",
            "type":"Services"
        },
        {
            "category":"Real Estate",
            "subcategory":"Real Estate Services",
            "type":"Services"
        }
    ],
    "sg:phone":"+1 801 269 1131",
    "sg:postcode":"84121",
    "sg:province":"UT",
    "sg:tags":[
        "depository",
        "banking",
        "company"
    ],
    "wof:name":"First American Title Insur Co",
    "wof:placetype":"venue"
},
  "geometry": {"coordinates":[-111.81200800000001,40.632521],"type":"Point"}
}