{
  "type": "Feature",
  "properties": {
    "iso:country":"US",
    "sg:address":"240 Edison St",
    "sg:city":"Salt Lake City",
    "sg:classifiers":[
        {
            "category":"Wholesale",
            "subcategory":"Durable Goods & Equipment",
            "type":"Manufacturing & Wholesale Goods"
        }
    ],
    "sg:phone":"+1 801 364 1600",
    "sg:postcode":"84111",
    "sg:province":"UT",
    "sg:tags":[
        "exporter"
    ],
    "wof:name":"KOSMO Corp",
    "wof:placetype":"venue"
},
  "geometry": {"coordinates":[-111.886629,40.763715],"type":"Point"}
}