{
  "type": "Feature",
  "properties": {
    "iso:country":"US",
    "sg:address":"8439 Meadow Lark Ln",
    "sg:city":"West Jordan",
    "sg:classifiers":[
        {
            "category":"Building & Trades",
            "subcategory":"Construction",
            "type":"Services"
        }
    ],
    "sg:phone":"+1 801 280 0371",
    "sg:postcode":"84088",
    "sg:province":"UT",
    "sg:tags":[
        "contractor"
    ],
    "wof:name":"Custom Stucco & Plastering",
    "wof:placetype":"venue"
},
  "geometry": {"coordinates":[-111.97783099999999,40.598004],"type":"Point"}
}