{
  "type": "Feature",
  "properties": {
    "iso:country":"US",
    "sg:address":"3070 Rasmussen Rd",
    "sg:city":"Park City",
    "sg:classifiers":[
        {
            "category":"Manufacturing",
            "subcategory":"Printing",
            "type":"Manufacturing & Wholesale Goods"
        }
    ],
    "sg:phone":"+1 435 940 1701",
    "sg:postcode":"84098",
    "sg:province":"UT",
    "sg:tags":[
        "publisher"
    ],
    "sg:website":"www.mediapartnerspublishing.com",
    "wof:name":"Media Partners Publishing",
    "wof:placetype":"venue"
},
  "geometry": {"coordinates":[-111.566525,40.749561],"type":"Point"}
}