{
  "type": "Feature",
  "properties": {
    "iso:country":"US",
    "sg:address":"336 S Main St",
    "sg:city":"Pleasant Grove",
    "sg:classifiers":[
        {
            "category":"Autos & Motor Vehicles",
            "subcategory":"Auto Supplies",
            "type":"Retail Goods"
        }
    ],
    "sg:phone":"+1 801 785 5071",
    "sg:postcode":"84062",
    "sg:province":"UT",
    "sg:tags":[
        "automobile",
        "parts"
    ],
    "wof:name":"Parts Unlimited Inc",
    "wof:placetype":"venue"
},
  "geometry": {"coordinates":[-111.74081700000001,40.359965],"type":"Point"}
}