{
  "type": "Feature",
  "properties": {
    "iso:country":"US",
    "sg:address":"45 E 200 S",
    "sg:city":"Brigham City",
    "sg:classifiers":[
        {
            "category":"Professional",
            "subcategory":"Lawyer & Legal Services",
            "type":"Services"
        }
    ],
    "sg:phone":"+1 435 723 7009",
    "sg:postcode":"84302",
    "sg:province":"UT",
    "wof:name":"Express Law Legal Ctr",
    "wof:placetype":"venue"
},
  "geometry": {"coordinates":[-112.014966,41.506142],"type":"Point"}
}