{
  "type": "Feature",
  "properties": {
    "iso:country":"US",
    "sg:address":"9 S 2380 W",
    "sg:city":"Cedar City",
    "sg:classifiers":[
        {
            "category":"Professional",
            "subcategory":"Computer Services",
            "type":"Services"
        }
    ],
    "sg:phone":"+1 435 586 2127",
    "sg:postcode":"84720",
    "sg:province":"UT",
    "sg:tags":[
        "consultant",
        "designer"
    ],
    "sg:website":"www.dataprocs.com",
    "wof:name":"Datapro Inc",
    "wof:placetype":"venue"
},
  "geometry": {"coordinates":[-113.09436100000001,37.676215],"type":"Point"}
}