{
  "type": "Feature",
  "properties": {
    "iso:country":"US",
    "sg:address":"10828 S 1255 W",
    "sg:city":"South Jordan",
    "sg:classifiers":[
        {
            "category":"Professional",
            "subcategory":"Management & Consulting",
            "type":"Services"
        }
    ],
    "sg:phone":"+1 801 789 5851",
    "sg:postcode":"84095",
    "sg:province":"UT",
    "wof:name":"Rjm Ventures LLC",
    "wof:placetype":"venue"
},
  "geometry": {"coordinates":[-111.927778,40.554917],"type":"Point"}
}