{
  "type": "Feature",
  "properties": {
    "iso:country":"US",
    "sg:address":"179 E 300 N",
    "sg:city":"Castle Dale",
    "sg:classifiers":[
        {
            "category":"Home & Garden",
            "subcategory":"Garden Supply",
            "type":"Retail Goods"
        }
    ],
    "sg:phone":"+1 435 381 5074",
    "sg:postcode":"84513",
    "sg:province":"UT",
    "sg:tags":[
        "lawn"
    ],
    "wof:name":"C T Sales & Svc",
    "wof:placetype":"venue"
},
  "geometry": {"coordinates":[-111.01652900000001,39.216158],"type":"Point"}
}