{
  "type": "Feature",
  "properties": {
    "iso:country":"US",
    "sg:address":"1061 E 900 S",
    "sg:city":"Salt Lake City",
    "sg:classifiers":[
        {
            "category":"Personal",
            "subcategory":"Beauty Salon",
            "type":"Services"
        }
    ],
    "sg:phone":"+1 801 519 2900",
    "sg:postcode":"84105",
    "sg:province":"UT",
    "wof:name":"Figaro",
    "wof:placetype":"venue"
},
  "geometry": {"coordinates":[-111.859792,40.749871],"type":"Point"}
}