{
  "type": "Feature",
  "properties": {
    "iso:country":"US",
    "sg:address":"299 S Main St",
    "sg:city":"Salt Lake City",
    "sg:classifiers":[
        {
            "category":"Banks & Credit Unions",
            "subcategory":"Investment Brokerage",
            "type":"Services"
        }
    ],
    "sg:phone":"+1 801 359 8880",
    "sg:postcode":"84111",
    "sg:province":"UT",
    "sg:tags":[
        "advisory",
        "security"
    ],
    "wof:name":"Peterson Capital Inc",
    "wof:placetype":"venue"
},
  "geometry": {"coordinates":[-111.891093,40.764998],"type":"Point"}
}