{
  "type": "Feature",
  "properties": {
    "iso:country":"US",
    "sg:address":"151 Old Station Way",
    "sg:city":"North Salt Lake",
    "sg:classifiers":[
        {
            "category":"Shopping",
            "type":"Retail Goods"
        }
    ],
    "sg:phone":"+1 801 706 0280",
    "sg:postcode":"84054",
    "sg:province":"UT",
    "sg:tags":[
        "merchandise"
    ],
    "wof:name":"Doggy Ksses Posh Pet Phtgraphy",
    "wof:placetype":"venue"
},
  "geometry": {"coordinates":[-111.91108699999999,40.844227],"type":"Point"}
}