{
  "type": "Feature",
  "properties": {
    "iso:country":"US",
    "sg:address":"1269 Malvern Ave",
    "sg:city":"Salt Lake City",
    "sg:classifiers":[
        {
            "category":"Building & Trades",
            "subcategory":"Construction",
            "type":"Services"
        }
    ],
    "sg:phone":"+1 801 485 2785",
    "sg:postcode":"84106",
    "sg:province":"UT",
    "sg:tags":[
        "designer",
        "marine",
        "contractor"
    ],
    "wof:name":"C & C Marine Inc",
    "wof:placetype":"venue"
},
  "geometry": {"coordinates":[-111.854623,40.713704],"type":"Point"}
}