{
  "type": "Feature",
  "properties": {
    "iso:country":"US",
    "sg:address":"76 S 900 W",
    "sg:city":"Salt Lake City",
    "sg:classifiers":[
        {
            "category":"Bars & Pubs",
            "type":"Food & Drink"
        }
    ],
    "sg:phone":"+1 801 363 9117",
    "sg:postcode":"84104",
    "sg:province":"UT",
    "sg:tags":[
        "club",
        "night"
    ],
    "wof:name":"Art's Place",
    "wof:placetype":"venue"
},
  "geometry": {"coordinates":[-111.916906,40.767532],"type":"Point"}
}