{
  "type": "Feature",
  "properties": {
    "iso:country":"US",
    "sg:address":"777 E 3900 S",
    "sg:city":"Salt Lake City",
    "sg:classifiers":[
        {
            "category":"Social Services",
            "subcategory":"Adult Care",
            "type":"Services"
        }
    ],
    "sg:phone":"+1 801 288 0700",
    "sg:postcode":"84107",
    "sg:province":"UT",
    "wof:name":"Millcreek Retirement Residence",
    "wof:placetype":"venue"
},
  "geometry": {"coordinates":[-111.868385,40.687129],"type":"Point"}
}