{
  "type": "Feature",
  "properties": {
    "iso:country":"US",
    "sg:address":"172 S Rio Grande St",
    "sg:city":"Salt Lake City",
    "sg:classifiers":[
        {
            "category":"Restaurant",
            "type":"Food & Drink"
        }
    ],
    "sg:menulink":"http://www.allmenus.com/ut/salt-lake-city/35224-ztejas/menu/",
    "sg:phone":"+1 801 456 0450",
    "sg:postcode":"84101",
    "sg:province":"UT",
    "sg:tags":[
        "american",
        "southwestern"
    ],
    "wof:name":"Ztejas",
    "wof:placetype":"venue"
},
  "geometry": {"coordinates":[-111.90410900000001,40.765563],"type":"Point"}
}