{
  "type": "Feature",
  "properties": {
    "iso:country":"US",
    "sg:address":"160 W Kanab Creek Dr",
    "sg:city":"Kanab",
    "sg:classifiers":[
        {
            "category":"Farming",
            "subcategory":"Livestock Farm",
            "type":"Manufacturing & Wholesale Goods"
        }
    ],
    "sg:phone":"+1 435 644 3984",
    "sg:postcode":"84741",
    "sg:province":"UT",
    "sg:tags":[
        "specialty",
        "animal"
    ],
    "wof:name":"Healing Heart Sanctuary",
    "wof:placetype":"venue"
},
  "geometry": {"coordinates":[-112.53209,37.029501],"type":"Point"}
}