{
  "type": "Feature",
  "properties": {
    "iso:country":"US",
    "sg:address":"17 N Merchant St",
    "sg:city":"American Fork",
    "sg:classifiers":[
        {
            "category":"Home & Garden",
            "subcategory":"Hardware",
            "type":"Retail Goods"
        }
    ],
    "sg:phone":"+1 801 756 2685",
    "sg:postcode":"84003",
    "sg:province":"UT",
    "wof:name":"True Value",
    "wof:placetype":"venue"
},
  "geometry": {"coordinates":[-111.799278,40.378605],"type":"Point"}
}