{
  "type": "Feature",
  "properties": {
    "iso:country":"US",
    "sg:address":"5520 Harold Gatty Dr",
    "sg:city":"Salt Lake City",
    "sg:classifiers":[
        {
            "category":"Wholesale",
            "subcategory":"Groceries",
            "type":"Manufacturing & Wholesale Goods"
        }
    ],
    "sg:phone":"+1 801 531 1100",
    "sg:postcode":"84116",
    "sg:province":"UT",
    "sg:tags":[
        "food"
    ],
    "sg:website":"www.nicholasandco.com",
    "wof:name":"Nicholas & Co Food Svc Distr",
    "wof:placetype":"venue"
},
  "geometry": {"coordinates":[-112.023059,40.781405],"type":"Point"}
}