{
  "type": "Feature",
  "properties": {
    "iso:country":"US",
    "sg:address":"119 W 30th St",
    "sg:city":"Ogden",
    "sg:classifiers":[
        {
            "category":"Organizations",
            "subcategory":"Religious Organization",
            "type":"Services"
        }
    ],
    "sg:phone":"+1 801 393 1252",
    "sg:postcode":"84401",
    "sg:province":"UT",
    "wof:name":"Finley Tmpl Chrch of God Chrst",
    "wof:placetype":"venue"
},
  "geometry": {"coordinates":[-111.98037100000001,41.21032],"type":"Point"}
}