{
  "type": "Feature",
  "properties": {
    "iso:country":"US",
    "sg:address":"993 E 740 S",
    "sg:city":"Spanish Fork",
    "sg:classifiers":[
        {
            "category":"Building & Trades",
            "subcategory":"Plumbing",
            "type":"Services"
        }
    ],
    "sg:phone":"+1 801 798 6861",
    "sg:postcode":"84660",
    "sg:province":"UT",
    "sg:tags":[
        "plumbing",
        "contractor"
    ],
    "wof:name":"B & B Plumbing",
    "wof:placetype":"venue"
},
  "geometry": {"coordinates":[-111.63712099999999,40.100529],"type":"Point"}
}