{
  "type": "Feature",
  "properties": {
    "iso:country":"US",
    "sg:address":"440 S 90 W",
    "sg:city":"Richmond",
    "sg:classifiers":[
        {
            "category":"Insurance",
            "subcategory":"Insurance Agent",
            "type":"Services"
        }
    ],
    "sg:phone":"+1 435 258 5196",
    "sg:postcode":"84333",
    "sg:province":"UT",
    "wof:name":"Alan D Smith Insurance",
    "wof:placetype":"venue"
},
  "geometry": {"coordinates":[-111.811353,41.913338],"type":"Point"}
}