{
  "type": "Feature",
  "properties": {
    "iso:country":"US",
    "sg:address":"404 Canyon Rd",
    "sg:city":"Smithfield",
    "sg:classifiers":[
        {
            "category":"Building & Trades",
            "subcategory":"Construction",
            "type":"Services"
        }
    ],
    "sg:phone":"+1 435 563 9516",
    "sg:postcode":"84335",
    "sg:province":"UT",
    "sg:tags":[
        "house"
    ],
    "wof:name":"Sean Priest Construction Inc",
    "wof:placetype":"venue"
},
  "geometry": {"coordinates":[-111.820412,41.841091],"type":"Point"}
}