{
  "type": "Feature",
  "properties": {
    "iso:country":"US",
    "sg:address":"275 E 3000 S",
    "sg:city":"Price",
    "sg:classifiers":[
        {
            "category":"Health Services",
            "subcategory":"Doctor",
            "type":"Services"
        }
    ],
    "sg:phone":"+1 435 637 1805",
    "sg:postcode":"84501",
    "sg:province":"UT",
    "sg:tags":[
        "medical"
    ],
    "wof:name":"Ob Enterprises LLC",
    "wof:placetype":"venue"
},
  "geometry": {"coordinates":[-110.810447,39.557005],"type":"Point"}
}