{
  "type": "Feature",
  "properties": {
    "iso:country":"US",
    "sg:address":"968 Sugarmont Dr",
    "sg:city":"Salt Lake City",
    "sg:classifiers":[
        {
            "category":"Social Services",
            "subcategory":"Child Care",
            "type":"Services"
        }
    ],
    "sg:phone":"+1 801 466 1540",
    "sg:postcode":"84106",
    "sg:province":"UT",
    "sg:website":"www.bgcslc.org",
    "wof:name":"Sugar House Club-Child Care",
    "wof:placetype":"venue"
},
  "geometry": {"coordinates":[-111.863073,40.722551],"type":"Point"}
}