{
  "type": "Feature",
  "properties": {
    "iso:country":"US",
    "sg:address":"788 E 6775 S",
    "sg:city":"Midvale",
    "sg:classifiers":[
        {
            "category":"Professional",
            "subcategory":"Art Services",
            "type":"Services"
        }
    ],
    "sg:phone":"+1 801 566 1127",
    "sg:postcode":"84047",
    "sg:province":"UT",
    "sg:tags":[
        "commercial",
        "design",
        "artist"
    ],
    "wof:name":"Dangerfield Design",
    "wof:placetype":"venue"
},
  "geometry": {"coordinates":[-111.868584,40.628527],"type":"Point"}
}