{
  "type": "Feature",
  "properties": {
    "iso:country":"US",
    "sg:address":"410 W 800 S",
    "sg:city":"Santaquin",
    "sg:classifiers":[
        {
            "category":"Farming",
            "subcategory":"Dairy Farm",
            "type":"Manufacturing & Wholesale Goods"
        }
    ],
    "sg:phone":"+1 801 754 5352",
    "sg:postcode":"84655",
    "sg:province":"UT",
    "wof:name":"Circle C Dairy Inc",
    "wof:placetype":"venue"
},
  "geometry": {"coordinates":[-111.855467,39.982086],"type":"Point"}
}