{
  "type": "Feature",
  "properties": {
    "iso:country":"US",
    "sg:address":"470 N 200 E",
    "sg:city":"Spanish Fork",
    "sg:classifiers":[
        {
            "category":"Autos & Motor Vehicles",
            "subcategory":"Auto Supplies",
            "type":"Retail Goods"
        }
    ],
    "sg:phone":"+1 801 798 8499",
    "sg:postcode":"84660",
    "sg:province":"UT",
    "wof:name":"Ricks Tire Co Inc",
    "wof:placetype":"venue"
},
  "geometry": {"coordinates":[-111.651189,40.115371],"type":"Point"}
}