{
  "type": "Feature",
  "properties": {
    "iso:country":"US",
    "sg:address":"440 N 500 W",
    "sg:city":"Richfield",
    "sg:phone":"+1 435 896 5525",
    "sg:postcode":"84701",
    "sg:province":"UT",
    "sg:tags":[
        "beef",
        "farm",
        "crop",
        "field",
        "cattle",
        "feedlot"
    ],
    "wof:name":"Langston Verl",
    "wof:placetype":"venue"
},
  "geometry": {"coordinates":[-112.093613,38.774523],"type":"Point"}
}