{
  "type": "Feature",
  "properties": {
    "iso:country":"US",
    "sg:address":"247 24th St",
    "sg:city":"Ogden",
    "sg:classifiers":[
        {
            "category":"Travel",
            "subcategory":"Hotels & Motels",
            "type":"Entertainment"
        }
    ],
    "sg:phone":"+1 801 627 1190",
    "sg:postcode":"84401",
    "sg:province":"UT",
    "sg:tags":[
        "management"
    ],
    "wof:name":"Ogden Marriott",
    "wof:placetype":"venue"
},
  "geometry": {"coordinates":[-111.974379,41.222727],"type":"Point"}
}