{
  "type": "Feature",
  "properties": {
    "iso:country":"US",
    "sg:address":"9205 US Hwy 89",
    "sg:city":"Willard",
    "sg:classifiers":[
        {
            "category":"Building & Trades",
            "subcategory":"Construction",
            "type":"Services"
        }
    ],
    "sg:phone":"+1 801 737 0709",
    "sg:postcode":"84340",
    "sg:province":"UT",
    "sg:tags":[
        "excavating",
        "contractor"
    ],
    "wof:name":"Orton Construction",
    "wof:placetype":"venue"
},
  "geometry": {"coordinates":[-112.031672,41.34265],"type":"Point"}
}