{
  "type": "Feature",
  "properties": {
    "iso:country":"US",
    "sg:address":"564 W Porter Ln",
    "sg:city":"Centerville",
    "sg:classifiers":[
        {
            "category":"Building & Trades",
            "subcategory":"Landscaping Services",
            "type":"Services"
        }
    ],
    "sg:phone":"+1 801 296 1396",
    "sg:postcode":"84014",
    "sg:province":"UT",
    "wof:name":"Andys Handy Landscaping",
    "wof:placetype":"venue"
},
  "geometry": {"coordinates":[-111.89040300000001,40.913154],"type":"Point"}
}