{
  "type": "Feature",
  "properties": {
    "iso:country":"US",
    "sg:address":"238 N 900 E",
    "sg:city":"Hyde Park",
    "sg:classifiers":[
        {
            "category":"Shopping",
            "subcategory":"Bicycles & Sporting Goods",
            "type":"Retail Goods"
        }
    ],
    "sg:phone":"+1 435 563 5076",
    "sg:postcode":"84318",
    "sg:province":"UT",
    "wof:name":"Used Bowling Supplies",
    "wof:placetype":"venue"
},
  "geometry": {"coordinates":[-111.797113,41.803828],"type":"Point"}
}