{
  "type": "Feature",
  "properties": {
    "iso:country":"US",
    "sg:address":"1899 S Redwood Rd",
    "sg:city":"Salt Lake City",
    "sg:classifiers":[
        {
            "category":"Professional",
            "subcategory":"Business Services",
            "type":"Services"
        }
    ],
    "sg:phone":"+1 801 328 2891",
    "sg:postcode":"84104",
    "sg:province":"UT",
    "sg:tags":[
        "courier"
    ],
    "wof:name":"Trans-Box Systems Inc",
    "wof:placetype":"venue"
},
  "geometry": {"coordinates":[-111.938959,40.728743],"type":"Point"}
}