{
  "type": "Feature",
  "properties": {
    "iso:country":"US",
    "sg:address":"1780 W Deep Creek Rd",
    "sg:city":"Morgan",
    "sg:classifiers":[
        {
            "category":"Professional",
            "type":"Services"
        }
    ],
    "sg:phone":"+1 801 829 3294",
    "sg:postcode":"84050",
    "sg:province":"UT",
    "wof:name":"Deep Creek Ditch Co",
    "wof:placetype":"venue"
},
  "geometry": {"coordinates":[-111.71774000000001,41.032739],"type":"Point"}
}