{
  "type": "Feature",
  "properties": {
    "iso:country":"US",
    "sg:address":"2073 E Sahara Dr",
    "sg:city":"Salt Lake City",
    "sg:classifiers":[
        {
            "category":"Professional",
            "subcategory":"Business Services",
            "type":"Services"
        }
    ],
    "sg:phone":"+1 801 278 8135",
    "sg:postcode":"84124",
    "sg:province":"UT",
    "wof:name":"South West Associates Inc",
    "wof:placetype":"venue"
},
  "geometry": {"coordinates":[-111.83308,40.677593],"type":"Point"}
}