{
  "type": "Feature",
  "properties": {
    "iso:country":"US",
    "sg:address":"1056 E 4750 South St",
    "sg:city":"Ogden",
    "sg:classifiers":[
        {
            "category":"Banks & Credit Unions",
            "subcategory":"Financial Services",
            "type":"Services"
        }
    ],
    "sg:phone":"+1 801 479 0623",
    "sg:postcode":"84403",
    "sg:province":"UT",
    "sg:tags":[
        "management",
        "open",
        "investment"
    ],
    "wof:name":"J Roger Johnsen Investments",
    "wof:placetype":"venue"
},
  "geometry": {"coordinates":[-111.95187300000001,41.17728],"type":"Point"}
}