{
  "type": "Feature",
  "properties": {
    "iso:country":"US",
    "sg:address":"2261 S Redwood Rd",
    "sg:city":"Salt Lake City",
    "sg:classifiers":[
        {
            "category":"Organizations",
            "subcategory":"Labor Organization",
            "type":"Services"
        }
    ],
    "sg:phone":"+1 801 973 6784",
    "sg:postcode":"84119",
    "sg:province":"UT",
    "wof:name":"Local 19",
    "wof:placetype":"venue"
},
  "geometry": {"coordinates":[-111.938889,40.721782],"type":"Point"}
}