{
  "type": "Feature",
  "properties": {
    "iso:country":"US",
    "sg:address":"3717 650 W",
    "sg:city":"Ogden",
    "sg:classifiers":[
        {
            "category":"Building & Trades",
            "subcategory":"Construction",
            "type":"Services"
        }
    ],
    "sg:phone":"+1 801 627 6090",
    "sg:postcode":"84405",
    "sg:province":"UT",
    "sg:tags":[
        "downspouts",
        "gutter"
    ],
    "wof:name":"Rainbow Raingutters Inc",
    "wof:placetype":"venue"
},
  "geometry": {"coordinates":[-111.996826,41.195142],"type":"Point"}
}