{
  "type": "Feature",
  "properties": {
    "iso:country":"US",
    "sg:address":"14953 Heritagecrest Way",
    "sg:city":"Riverton",
    "sg:classifiers":[
        {
            "category":"Home & Garden",
            "subcategory":"Furniture",
            "type":"Retail Goods"
        }
    ],
    "sg:phone":"+1 801 254 2559",
    "sg:postcode":"84065",
    "sg:province":"UT",
    "sg:tags":[
        "cabinet"
    ],
    "wof:name":"Nielco Cabinets Inc",
    "wof:placetype":"venue"
},
  "geometry": {"coordinates":[-111.911444,40.481225],"type":"Point"}
}