{
  "type": "Feature",
  "properties": {
    "iso:country":"US",
    "sg:address":"13002 Mountain Crest Cir",
    "sg:city":"Draper",
    "sg:classifiers":[
        {
            "category":"Real Estate",
            "subcategory":"Real Estate Agent",
            "type":"Services"
        },
        {
            "category":"Professional",
            "subcategory":"Business Services",
            "type":"Services"
        }
    ],
    "sg:phone":"+1 801 553 0382",
    "sg:postcode":"84020",
    "sg:province":"UT",
    "sg:tags":[
        "appraiser"
    ],
    "wof:name":"Evans Appraisal Group Inc",
    "wof:placetype":"venue"
},
  "geometry": {"coordinates":[-111.84357,40.514251],"type":"Point"}
}