{
  "type": "Feature",
  "properties": {
    "iso:country":"US",
    "sg:address":"5983 Highland Dr",
    "sg:city":"Morgan",
    "sg:classifiers":[
        {
            "category":"Building & Trades",
            "subcategory":"Equipment Rental",
            "type":"Services"
        }
    ],
    "sg:phone":"+1 801 876 3269",
    "sg:postcode":"84050",
    "sg:province":"UT",
    "sg:tags":[
        "heavy",
        "crane",
        "construction"
    ],
    "wof:name":"Kukal Cranes Inc",
    "wof:placetype":"venue"
},
  "geometry": {"coordinates":[-111.81146,41.143907],"type":"Point"}
}