{
  "type": "Feature",
  "properties": {
    "iso:country":"US",
    "sg:address":"966 Cedar Knolls W",
    "sg:city":"Cedar City",
    "sg:classifiers":[
        {
            "category":"Banks & Credit Unions",
            "subcategory":"Investment Brokerage",
            "type":"Services"
        }
    ],
    "sg:phone":"+1 435 586 6226",
    "sg:postcode":"84720",
    "sg:province":"UT",
    "sg:tags":[
        "consultant",
        "financing"
    ],
    "wof:name":"September Star",
    "wof:placetype":"venue"
},
  "geometry": {"coordinates":[-113.07796999999999,37.662056],"type":"Point"}
}