{
  "type": "Feature",
  "properties": {
    "iso:country":"US",
    "sg:address":"12138 Gracie View Pl",
    "sg:city":"Draper",
    "sg:classifiers":[
        {
            "category":"Professional",
            "subcategory":"Business Services",
            "type":"Services"
        }
    ],
    "sg:phone":"+1 801 545 0202",
    "sg:postcode":"84020",
    "sg:province":"UT",
    "sg:tags":[
        "equipment",
        "electrical"
    ],
    "wof:name":"Orion Systems",
    "wof:placetype":"venue"
},
  "geometry": {"coordinates":[-111.91133600000001,40.529516],"type":"Point"}
}