{
  "type": "Feature",
  "properties": {
    "iso:country":"US",
    "sg:address":"947 Ridge Hill Ln",
    "sg:city":"Midvale",
    "sg:classifiers":[
        {
            "category":"Professional",
            "subcategory":"Computer Services",
            "type":"Services"
        }
    ],
    "sg:phone":"+1 801 255 6387",
    "sg:postcode":"84047",
    "sg:province":"UT",
    "sg:tags":[
        "related"
    ],
    "wof:name":"Prestian Computers",
    "wof:placetype":"venue"
},
  "geometry": {"coordinates":[-111.863975,40.615366],"type":"Point"}
}