{
  "type": "Feature",
  "properties": {
    "iso:country":"US",
    "sg:address":"5900 S 3100 W",
    "sg:city":"Roy",
    "sg:classifiers":[
        {
            "category":"Organizations",
            "subcategory":"Religious Organization",
            "type":"Services"
        }
    ],
    "sg:phone":"+1 801 774 2123",
    "sg:postcode":"84067",
    "sg:province":"UT",
    "sg:tags":[
        "church"
    ],
    "wof:name":"LDS Church 24th Ward",
    "wof:placetype":"venue"
},
  "geometry": {"coordinates":[-112.054754,41.155995],"type":"Point"}
}