{
  "type": "Feature",
  "properties": {
    "iso:country":"US",
    "sg:address":"113 E 1825 N",
    "sg:city":"Centerville",
    "sg:classifiers":[
        {
            "category":"Real Estate",
            "subcategory":"Real Estate Agent",
            "type":"Services"
        }
    ],
    "sg:phone":"+1 801 292 4775",
    "sg:postcode":"84014",
    "sg:province":"UT",
    "wof:name":"Continental Townhous",
    "wof:placetype":"venue"
},
  "geometry": {"coordinates":[-111.87815000000001,40.944106],"type":"Point"}
}