{
  "type": "Feature",
  "properties": {
    "iso:country":"US",
    "sg:address":"5327 S Mountain Men Dr",
    "sg:city":"Salt Lake City",
    "sg:classifiers":[
        {
            "category":"Organizations",
            "subcategory":"Community Association",
            "type":"Services"
        }
    ],
    "sg:phone":"+1 801 966 6603",
    "sg:postcode":"84118",
    "sg:province":"UT",
    "wof:name":"Bennion Family Assoc",
    "wof:placetype":"venue"
},
  "geometry": {"coordinates":[-112.018428,40.659576],"type":"Point"}
}