{
  "type": "Feature",
  "properties": {
    "iso:country":"US",
    "sg:address":"3711 E Eastcliff Dr",
    "sg:city":"Salt Lake City",
    "sg:classifiers":[
        {
            "category":"Retail",
            "subcategory":"Portrait Studio",
            "type":"Services"
        }
    ],
    "sg:phone":"+1 801 278 6585",
    "sg:postcode":"84124",
    "sg:province":"UT",
    "sg:tags":[
        "photo"
    ],
    "wof:name":"John Aldrich Photography",
    "wof:placetype":"venue"
},
  "geometry": {"coordinates":[-111.79095100000001,40.676026],"type":"Point"}
}