{
  "type": "Feature",
  "properties": {
    "iso:country":"US",
    "sg:address":"968 S 970 W",
    "sg:city":"Woods Cross",
    "sg:classifiers":[
        {
            "category":"Professional",
            "subcategory":"Research",
            "type":"Services"
        }
    ],
    "sg:phone":"+1 801 294 0454",
    "sg:postcode":"84087",
    "sg:province":"UT",
    "sg:tags":[
        "environmental",
        "ecological"
    ],
    "wof:name":"Air Quality Svc",
    "wof:placetype":"venue"
},
  "geometry": {"coordinates":[-111.907005,40.879081],"type":"Point"}
}