{
  "type": "Feature",
  "properties": {
    "iso:country":"US",
    "sg:address":"2171 Alexander St",
    "sg:city":"Salt Lake City",
    "sg:classifiers":[
        {
            "category":"Manufacturing",
            "subcategory":"Metals",
            "type":"Manufacturing & Wholesale Goods"
        }
    ],
    "sg:phone":"+1 801 972 5046",
    "sg:postcode":"84119",
    "sg:province":"UT",
    "wof:name":"Reinvented Wheel",
    "wof:placetype":"venue"
},
  "geometry": {"coordinates":[-111.94846099999999,40.717786],"type":"Point"}
}