{
  "type": "Feature",
  "properties": {
    "iso:country":"US",
    "sg:address":"1324 E Millbrook Way",
    "sg:city":"Bountiful",
    "sg:classifiers":[
        {
            "category":"Banks & Credit Unions",
            "subcategory":"Investment Brokerage",
            "type":"Services"
        }
    ],
    "sg:phone":"+1 801 292 5256",
    "sg:postcode":"84010",
    "sg:province":"UT",
    "sg:tags":[
        "advisory"
    ],
    "wof:name":"Rocky Mtn Inv Advisors LLC",
    "wof:placetype":"venue"
},
  "geometry": {"coordinates":[-111.85175,40.875511],"type":"Point"}
}