{
  "type": "Feature",
  "properties": {
    "iso:country":"US",
    "sg:address":"877 W 400 S",
    "sg:city":"Salt Lake City",
    "sg:classifiers":[
        {
            "category":"Banks & Credit Unions",
            "subcategory":"Bank",
            "type":"Services"
        }
    ],
    "sg:phone":"+1 801 359 4911",
    "sg:postcode":"84104",
    "sg:province":"UT",
    "sg:tags":[
        "money",
        "transfer"
    ],
    "wof:name":"Dolex Dollar Express",
    "wof:placetype":"venue"
},
  "geometry": {"coordinates":[-111.915789,40.760562],"type":"Point"}
}