{
  "type": "Feature",
  "properties": {
    "iso:country":"US",
    "sg:address":"6338 Dixie Dr",
    "sg:city":"West Jordan",
    "sg:classifiers":[
        {
            "category":"Building & Trades",
            "subcategory":"Cleaning & Sanitation",
            "type":"Services"
        }
    ],
    "sg:phone":"+1 801 966 1764",
    "sg:postcode":"84084",
    "sg:province":"UT",
    "wof:name":"Marys House Keeping",
    "wof:placetype":"venue"
},
  "geometry": {"coordinates":[-111.978363,40.635896],"type":"Point"}
}