{
  "type": "Feature",
  "properties": {
    "iso:country":"US",
    "sg:address":"1520 US Hwy 40",
    "sg:city":"Heber City",
    "sg:classifiers":[
        {
            "category":"Wholesale",
            "subcategory":"Machinery & Supplies",
            "type":"Manufacturing & Wholesale Goods"
        }
    ],
    "sg:phone":"+1 435 654 0211",
    "sg:postcode":"84032",
    "sg:province":"UT",
    "sg:tags":[
        "repair",
        "electrical"
    ],
    "wof:name":"Horner Inc",
    "wof:placetype":"venue"
},
  "geometry": {"coordinates":[-111.40925799999999,40.529043],"type":"Point"}
}