{
  "type": "Feature",
  "properties": {
    "iso:country":"US",
    "sg:address":"132 S Main St",
    "sg:city":"Logan",
    "sg:classifiers":[
        {
            "category":"Insurance",
            "subcategory":"Hazard Insurance",
            "type":"Services"
        }
    ],
    "sg:phone":"+1 435 753 2316",
    "sg:postcode":"84321",
    "sg:province":"UT",
    "sg:tags":[
        "bond"
    ],
    "wof:name":"A Best Rand's Bail Bonds",
    "wof:placetype":"venue"
},
  "geometry": {"coordinates":[-111.834975,41.729567],"type":"Point"}
}