{
  "type": "Feature",
  "properties": {
    "iso:country":"US",
    "sg:address":"890 Heritage Park Blvd",
    "sg:city":"Layton",
    "sg:classifiers":[
        {
            "category":"Health Services",
            "subcategory":"Doctor",
            "type":"Services"
        }
    ],
    "sg:phone":"+1 801 614 0998",
    "sg:postcode":"84041",
    "sg:province":"UT",
    "sg:tags":[
        "physician",
        "surgeon"
    ],
    "wof:name":"Davis Center For Oral",
    "wof:placetype":"venue"
},
  "geometry": {"coordinates":[-111.980073,41.083236],"type":"Point"}
}