{
  "type": "Feature",
  "properties": {
    "iso:country":"US",
    "sg:address":"102 S 100 W",
    "sg:city":"Brigham City",
    "sg:classifiers":[
        {
            "category":"Professional",
            "subcategory":"Lawyer & Legal Services",
            "type":"Services"
        }
    ],
    "sg:phone":"+1 435 723 8569",
    "sg:postcode":"84302",
    "sg:province":"UT",
    "sg:tags":[
        "attorney"
    ],
    "wof:name":"Jack Molgard",
    "wof:placetype":"venue"
},
  "geometry": {"coordinates":[-112.01754099999999,41.506165],"type":"Point"}
}