{
  "type": "Feature",
  "properties": {
    "iso:country":"US",
    "sg:address":"132 Wendover Blvd",
    "sg:city":"Wendover",
    "sg:classifiers":[
        {
            "category":"Personal",
            "subcategory":"Beauty Salon",
            "type":"Services"
        }
    ],
    "sg:phone":"+1 435 665 2147",
    "sg:postcode":"84083",
    "sg:province":"UT",
    "wof:name":"Hair Collection",
    "wof:placetype":"venue"
},
  "geometry": {"coordinates":[-114.041033,40.736207],"type":"Point"}
}