{
  "type": "Feature",
  "properties": {
    "iso:country":"US",
    "sg:address":"3175 W 5400 S",
    "sg:city":"Salt Lake City",
    "sg:classifiers":[
        {
            "category":"Insurance",
            "subcategory":"Insurance Agent",
            "type":"Services"
        }
    ],
    "sg:phone":"+1 801 964 1704",
    "sg:postcode":"84118",
    "sg:province":"UT",
    "wof:name":"Bao Insurance Agency Inc",
    "wof:placetype":"venue"
},
  "geometry": {"coordinates":[-111.966719,40.653018],"type":"Point"}
}