{
  "type": "Feature",
  "properties": {
    "iso:country":"US",
    "sg:address":"4215 W 2200 N",
    "sg:city":"Ogden",
    "sg:classifiers":[
        {
            "category":"Freight",
            "type":"Transportation"
        }
    ],
    "sg:phone":"+1 801 731 3667",
    "sg:postcode":"84404",
    "sg:province":"UT",
    "sg:tags":[
        "operator",
        "local",
        "trucking"
    ],
    "wof:name":"Brown Pearl Trucking",
    "wof:placetype":"venue"
},
  "geometry": {"coordinates":[-112.081568,41.297855],"type":"Point"}
}