{
  "type": "Feature",
  "properties": {
    "iso:country":"US",
    "sg:address":"209 E 400 S",
    "sg:city":"Provo",
    "sg:classifiers":[
        {
            "category":"Professional",
            "type":"Services"
        }
    ],
    "sg:phone":"+1 801 375 3133",
    "sg:postcode":"84606",
    "sg:province":"UT",
    "sg:tags":[
        "establishment"
    ],
    "wof:name":"This N That Samplers",
    "wof:placetype":"venue"
},
  "geometry": {"coordinates":[-111.653569,40.228427],"type":"Point"}
}