{
  "type": "Feature",
  "properties": {
    "iso:country":"US",
    "sg:address":"1908 E Rio Cir",
    "sg:city":"Sandy",
    "sg:classifiers":[
        {
            "category":"Professional",
            "subcategory":"Business Services",
            "type":"Services"
        }
    ],
    "sg:phone":"+1 801 943 8775",
    "sg:postcode":"84093",
    "sg:province":"UT",
    "wof:name":"Sonic Solutions",
    "wof:placetype":"venue"
},
  "geometry": {"coordinates":[-111.837046,40.601731],"type":"Point"}
}