{
  "type": "Feature",
  "properties": {
    "iso:country":"US",
    "sg:address":"62 N 2120 E Cir",
    "sg:city":"St George",
    "sg:classifiers":[
        {
            "category":"Building & Trades",
            "subcategory":"Plumbing",
            "type":"Services"
        }
    ],
    "sg:phone":"+1 435 680 2471",
    "sg:postcode":"84790",
    "sg:province":"UT",
    "sg:tags":[
        "contractor"
    ],
    "wof:name":"Cox Precision Air",
    "wof:placetype":"venue"
},
  "geometry": {"coordinates":[-113.538051,37.109896],"type":"Point"}
}