{
  "type": "Feature",
  "properties": {
    "iso:country":"US",
    "sg:address":"390 N Main St",
    "sg:city":"Heber City",
    "sg:classifiers":[
        {
            "category":"Real Estate",
            "subcategory":"Real Estate Agent",
            "type":"Services"
        }
    ],
    "sg:phone":"+1 435 654 5300",
    "sg:postcode":"84032",
    "sg:province":"UT",
    "wof:name":"Coldwell Banker",
    "wof:placetype":"venue"
},
  "geometry": {"coordinates":[-111.413364,40.511701],"type":"Point"}
}