{
  "type": "Feature",
  "properties": {
    "iso:country":"US",
    "sg:address":"377 E 200 S",
    "sg:city":"Salt Lake City",
    "sg:classifiers":[
        {
            "category":"Restaurant",
            "type":"Food & Drink"
        }
    ],
    "sg:phone":"+1 801 532 1155",
    "sg:postcode":"84111",
    "sg:province":"UT",
    "wof:name":"Crown Burgers Restaurant",
    "wof:placetype":"venue"
},
  "geometry": {"coordinates":[-111.880486,40.765079],"type":"Point"}
}