{
  "type": "Feature",
  "properties": {
    "iso:country":"US",
    "sg:address":"2021 S State St",
    "sg:city":"Provo",
    "sg:classifiers":[
        {
            "category":"Government",
            "subcategory":"Jail",
            "type":"Public Place"
        }
    ],
    "sg:phone":"+1 801 354 7200",
    "sg:postcode":"84606",
    "sg:province":"UT",
    "sg:tags":[
        "govt",
        "state",
        "institution"
    ],
    "wof:name":"Juvenile Court",
    "wof:placetype":"venue"
},
  "geometry": {"coordinates":[-111.627194,40.205563],"type":"Point"}
}