{
  "type": "Feature",
  "properties": {
    "iso:country":"US",
    "sg:address":"80 W Center St",
    "sg:city":"Springville",
    "sg:classifiers":[
        {
            "category":"Retail",
            "subcategory":"Photofinishing",
            "type":"Services"
        }
    ],
    "sg:phone":"+1 801 489 3218",
    "sg:postcode":"84663",
    "sg:province":"UT",
    "sg:tags":[
        "photo",
        "finishing"
    ],
    "sg:website":"www.snelsonphotolab.com",
    "wof:name":"Snelson Photo Color Lab",
    "wof:placetype":"venue"
},
  "geometry": {"coordinates":[-111.611313,40.166761],"type":"Point"}
}