{
  "type": "Feature",
  "properties": {
    "iso:country":"US",
    "sg:address":"1164 US Hwy 89",
    "sg:city":"Kaysville",
    "sg:classifiers":[
        {
            "category":"Freight",
            "type":"Transportation"
        }
    ],
    "sg:phone":"+1 801 547 0694",
    "sg:postcode":"84037",
    "sg:province":"UT",
    "sg:tags":[
        "general"
    ],
    "wof:name":"R V Layton & Boat Storage",
    "wof:placetype":"venue"
},
  "geometry": {"coordinates":[-111.910561,41.015206],"type":"Point"}
}