{
  "type": "Feature",
  "properties": {
    "iso:country":"US",
    "sg:address":"4923 Elaine Dr",
    "sg:city":"Salt Lake City",
    "sg:classifiers":[
        {
            "category":"Home & Garden",
            "subcategory":"Carpets & Floor Coverings",
            "type":"Retail Goods"
        }
    ],
    "sg:phone":"+1 801 969 5628",
    "sg:postcode":"84120",
    "sg:province":"UT",
    "wof:name":"Ventura Carpet",
    "wof:placetype":"venue"
},
  "geometry": {"coordinates":[-112.008734,40.686402],"type":"Point"}
}